Compiled from "ParallelFlowable.java"
public abstract class io.reactivex.rxjava3.parallel.ParallelFlowable<T> {
  public io.reactivex.rxjava3.parallel.ParallelFlowable();
    Code:
       0: aload_0
       1: invokespecial #1                  // Method java/lang/Object."<init>":()V
       4: return

  public abstract void subscribe(org.reactivestreams.Subscriber<? super T>[]);

  public abstract int parallelism();

  protected final boolean validate(org.reactivestreams.Subscriber<?>[]);
    Code:
       0: aload_1
       1: ldc           #2                  // String subscribers is null
       3: invokestatic  #3                  // Method java/util/Objects.requireNonNull:(Ljava/lang/Object;Ljava/lang/String;)Ljava/lang/Object;
       6: pop
       7: aload_0
       8: invokevirtual #4                  // Method parallelism:()I
      11: istore_2
      12: aload_1
      13: arraylength
      14: iload_2
      15: if_icmpeq     94
      18: new           #5                  // class java/lang/IllegalArgumentException
      21: dup
      22: new           #6                  // class java/lang/StringBuilder
      25: dup
      26: invokespecial #7                  // Method java/lang/StringBuilder."<init>":()V
      29: ldc           #8                  // String parallelism =
      31: invokevirtual #9                  // Method java/lang/StringBuilder.append:(Ljava/lang/String;)Ljava/lang/StringBuilder;
      34: iload_2
      35: invokevirtual #10                 // Method java/lang/StringBuilder.append:(I)Ljava/lang/StringBuilder;
      38: ldc           #11                 // String , subscribers =
      40: invokevirtual #9                  // Method java/lang/StringBuilder.append:(Ljava/lang/String;)Ljava/lang/StringBuilder;
      43: aload_1
      44: arraylength
      45: invokevirtual #10                 // Method java/lang/StringBuilder.append:(I)Ljava/lang/StringBuilder;
      48: invokevirtual #12                 // Method java/lang/StringBuilder.toString:()Ljava/lang/String;
      51: invokespecial #13                 // Method java/lang/IllegalArgumentException."<init>":(Ljava/lang/String;)V
      54: astore_3
      55: aload_1
      56: astore        4
      58: aload         4
      60: arraylength
      61: istore        5
      63: iconst_0
      64: istore        6
      66: iload         6
      68: iload         5
      70: if_icmpge     92
      73: aload         4
      75: iload         6
      77: aaload
      78: astore        7
      80: aload_3
      81: aload         7
      83: invokestatic  #14                 // Method io/reactivex/rxjava3/internal/subscriptions/EmptySubscription.error:(Ljava/lang/Throwable;Lorg/reactivestreams/Subscriber;)V
      86: iinc          6, 1
      89: goto          66
      92: iconst_0
      93: ireturn
      94: iconst_1
      95: ireturn

  public static <T> io.reactivex.rxjava3.parallel.ParallelFlowable<T> from(org.reactivestreams.Publisher<? extends T>);
    Code:
       0: aload_0
       1: invokestatic  #15                 // Method java/lang/Runtime.getRuntime:()Ljava/lang/Runtime;
       4: invokevirtual #16                 // Method java/lang/Runtime.availableProcessors:()I
       7: invokestatic  #17                 // Method io/reactivex/rxjava3/core/Flowable.bufferSize:()I
      10: invokestatic  #18                 // Method from:(Lorg/reactivestreams/Publisher;II)Lio/reactivex/rxjava3/parallel/ParallelFlowable;
      13: areturn

  public static <T> io.reactivex.rxjava3.parallel.ParallelFlowable<T> from(org.reactivestreams.Publisher<? extends T>, int);
    Code:
       0: aload_0
       1: iload_1
       2: invokestatic  #17                 // Method io/reactivex/rxjava3/core/Flowable.bufferSize:()I
       5: invokestatic  #19                 // Method from:(Lorg/reactivestreams/Publisher;II)Lio/reactivex/rxjava3/parallel/ParallelFlowable;
       8: areturn

  public static <T> io.reactivex.rxjava3.parallel.ParallelFlowable<T> from(org.reactivestreams.Publisher<? extends T>, int, int);
    Code:
       0: aload_0
       1: ldc           #20                 // String source is null
       3: invokestatic  #3                  // Method java/util/Objects.requireNonNull:(Ljava/lang/Object;Ljava/lang/String;)Ljava/lang/Object;
       6: pop
       7: iload_1
       8: ldc           #21                 // String parallelism
      10: invokestatic  #22                 // Method io/reactivex/rxjava3/internal/functions/ObjectHelper.verifyPositive:(ILjava/lang/String;)I
      13: pop
      14: iload_2
      15: ldc           #23                 // String prefetch
      17: invokestatic  #22                 // Method io/reactivex/rxjava3/internal/functions/ObjectHelper.verifyPositive:(ILjava/lang/String;)I
      20: pop
      21: new           #24                 // class io/reactivex/rxjava3/internal/operators/parallel/ParallelFromPublisher
      24: dup
      25: aload_0
      26: iload_1
      27: iload_2
      28: invokespecial #25                 // Method io/reactivex/rxjava3/internal/operators/parallel/ParallelFromPublisher."<init>":(Lorg/reactivestreams/Publisher;II)V
      31: invokestatic  #26                 // Method io/reactivex/rxjava3/plugins/RxJavaPlugins.onAssembly:(Lio/reactivex/rxjava3/parallel/ParallelFlowable;)Lio/reactivex/rxjava3/parallel/ParallelFlowable;
      34: areturn

  public final <R> io.reactivex.rxjava3.parallel.ParallelFlowable<R> map(io.reactivex.rxjava3.functions.Function<? super T, ? extends R>);
    Code:
       0: aload_1
       1: ldc           #27                 // String mapper is null
       3: invokestatic  #3                  // Method java/util/Objects.requireNonNull:(Ljava/lang/Object;Ljava/lang/String;)Ljava/lang/Object;
       6: pop
       7: new           #28                 // class io/reactivex/rxjava3/internal/operators/parallel/ParallelMap
      10: dup
      11: aload_0
      12: aload_1
      13: invokespecial #29                 // Method io/reactivex/rxjava3/internal/operators/parallel/ParallelMap."<init>":(Lio/reactivex/rxjava3/parallel/ParallelFlowable;Lio/reactivex/rxjava3/functions/Function;)V
      16: invokestatic  #30                 // Method io/reactivex/rxjava3/plugins/RxJavaPlugins.onAssembly:(Lio/reactivex/rxjava3/parallel/ParallelFlowable;)Lio/reactivex/rxjava3/parallel/ParallelFlowable;
      19: areturn

  public final <R> io.reactivex.rxjava3.parallel.ParallelFlowable<R> map(io.reactivex.rxjava3.functions.Function<? super T, ? extends R>, io.reactivex.rxjava3.parallel.ParallelFailureHandling);
    Code:
       0: aload_1
       1: ldc           #27                 // String mapper is null
       3: invokestatic  #3                  // Method java/util/Objects.requireNonNull:(Ljava/lang/Object;Ljava/lang/String;)Ljava/lang/Object;
       6: pop
       7: aload_2
       8: ldc           #31                 // String errorHandler is null
      10: invokestatic  #3                  // Method java/util/Objects.requireNonNull:(Ljava/lang/Object;Ljava/lang/String;)Ljava/lang/Object;
      13: pop
      14: new           #32                 // class io/reactivex/rxjava3/internal/operators/parallel/ParallelMapTry
      17: dup
      18: aload_0
      19: aload_1
      20: aload_2
      21: invokespecial #33                 // Method io/reactivex/rxjava3/internal/operators/parallel/ParallelMapTry."<init>":(Lio/reactivex/rxjava3/parallel/ParallelFlowable;Lio/reactivex/rxjava3/functions/Function;Lio/reactivex/rxjava3/functions/BiFunction;)V
      24: invokestatic  #34                 // Method io/reactivex/rxjava3/plugins/RxJavaPlugins.onAssembly:(Lio/reactivex/rxjava3/parallel/ParallelFlowable;)Lio/reactivex/rxjava3/parallel/ParallelFlowable;
      27: areturn

  public final <R> io.reactivex.rxjava3.parallel.ParallelFlowable<R> map(io.reactivex.rxjava3.functions.Function<? super T, ? extends R>, io.reactivex.rxjava3.functions.BiFunction<? super java.lang.Long, ? super java.lang.Throwable, io.reactivex.rxjava3.parallel.ParallelFailureHandling>);
    Code:
       0: aload_1
       1: ldc           #27                 // String mapper is null
       3: invokestatic  #3                  // Method java/util/Objects.requireNonNull:(Ljava/lang/Object;Ljava/lang/String;)Ljava/lang/Object;
       6: pop
       7: aload_2
       8: ldc           #31                 // String errorHandler is null
      10: invokestatic  #3                  // Method java/util/Objects.requireNonNull:(Ljava/lang/Object;Ljava/lang/String;)Ljava/lang/Object;
      13: pop
      14: new           #32                 // class io/reactivex/rxjava3/internal/operators/parallel/ParallelMapTry
      17: dup
      18: aload_0
      19: aload_1
      20: aload_2
      21: invokespecial #33                 // Method io/reactivex/rxjava3/internal/operators/parallel/ParallelMapTry."<init>":(Lio/reactivex/rxjava3/parallel/ParallelFlowable;Lio/reactivex/rxjava3/functions/Function;Lio/reactivex/rxjava3/functions/BiFunction;)V
      24: invokestatic  #35                 // Method io/reactivex/rxjava3/plugins/RxJavaPlugins.onAssembly:(Lio/reactivex/rxjava3/parallel/ParallelFlowable;)Lio/reactivex/rxjava3/parallel/ParallelFlowable;
      27: areturn

  public final io.reactivex.rxjava3.parallel.ParallelFlowable<T> filter(io.reactivex.rxjava3.functions.Predicate<? super T>);
    Code:
       0: aload_1
       1: ldc           #36                 // String predicate is null
       3: invokestatic  #3                  // Method java/util/Objects.requireNonNull:(Ljava/lang/Object;Ljava/lang/String;)Ljava/lang/Object;
       6: pop
       7: new           #37                 // class io/reactivex/rxjava3/internal/operators/parallel/ParallelFilter
      10: dup
      11: aload_0
      12: aload_1
      13: invokespecial #38                 // Method io/reactivex/rxjava3/internal/operators/parallel/ParallelFilter."<init>":(Lio/reactivex/rxjava3/parallel/ParallelFlowable;Lio/reactivex/rxjava3/functions/Predicate;)V
      16: invokestatic  #39                 // Method io/reactivex/rxjava3/plugins/RxJavaPlugins.onAssembly:(Lio/reactivex/rxjava3/parallel/ParallelFlowable;)Lio/reactivex/rxjava3/parallel/ParallelFlowable;
      19: areturn

  public final io.reactivex.rxjava3.parallel.ParallelFlowable<T> filter(io.reactivex.rxjava3.functions.Predicate<? super T>, io.reactivex.rxjava3.parallel.ParallelFailureHandling);
    Code:
       0: aload_1
       1: ldc           #36                 // String predicate is null
       3: invokestatic  #3                  // Method java/util/Objects.requireNonNull:(Ljava/lang/Object;Ljava/lang/String;)Ljava/lang/Object;
       6: pop
       7: aload_2
       8: ldc           #31                 // String errorHandler is null
      10: invokestatic  #3                  // Method java/util/Objects.requireNonNull:(Ljava/lang/Object;Ljava/lang/String;)Ljava/lang/Object;
      13: pop
      14: new           #40                 // class io/reactivex/rxjava3/internal/operators/parallel/ParallelFilterTry
      17: dup
      18: aload_0
      19: aload_1
      20: aload_2
      21: invokespecial #41                 // Method io/reactivex/rxjava3/internal/operators/parallel/ParallelFilterTry."<init>":(Lio/reactivex/rxjava3/parallel/ParallelFlowable;Lio/reactivex/rxjava3/functions/Predicate;Lio/reactivex/rxjava3/functions/BiFunction;)V
      24: invokestatic  #42                 // Method io/reactivex/rxjava3/plugins/RxJavaPlugins.onAssembly:(Lio/reactivex/rxjava3/parallel/ParallelFlowable;)Lio/reactivex/rxjava3/parallel/ParallelFlowable;
      27: areturn

  public final io.reactivex.rxjava3.parallel.ParallelFlowable<T> filter(io.reactivex.rxjava3.functions.Predicate<? super T>, io.reactivex.rxjava3.functions.BiFunction<? super java.lang.Long, ? super java.lang.Throwable, io.reactivex.rxjava3.parallel.ParallelFailureHandling>);
    Code:
       0: aload_1
       1: ldc           #36                 // String predicate is null
       3: invokestatic  #3                  // Method java/util/Objects.requireNonNull:(Ljava/lang/Object;Ljava/lang/String;)Ljava/lang/Object;
       6: pop
       7: aload_2
       8: ldc           #31                 // String errorHandler is null
      10: invokestatic  #3                  // Method java/util/Objects.requireNonNull:(Ljava/lang/Object;Ljava/lang/String;)Ljava/lang/Object;
      13: pop
      14: new           #40                 // class io/reactivex/rxjava3/internal/operators/parallel/ParallelFilterTry
      17: dup
      18: aload_0
      19: aload_1
      20: aload_2
      21: invokespecial #41                 // Method io/reactivex/rxjava3/internal/operators/parallel/ParallelFilterTry."<init>":(Lio/reactivex/rxjava3/parallel/ParallelFlowable;Lio/reactivex/rxjava3/functions/Predicate;Lio/reactivex/rxjava3/functions/BiFunction;)V
      24: invokestatic  #43                 // Method io/reactivex/rxjava3/plugins/RxJavaPlugins.onAssembly:(Lio/reactivex/rxjava3/parallel/ParallelFlowable;)Lio/reactivex/rxjava3/parallel/ParallelFlowable;
      27: areturn

  public final io.reactivex.rxjava3.parallel.ParallelFlowable<T> runOn(io.reactivex.rxjava3.core.Scheduler);
    Code:
       0: aload_0
       1: aload_1
       2: invokestatic  #17                 // Method io/reactivex/rxjava3/core/Flowable.bufferSize:()I
       5: invokevirtual #44                 // Method runOn:(Lio/reactivex/rxjava3/core/Scheduler;I)Lio/reactivex/rxjava3/parallel/ParallelFlowable;
       8: areturn

  public final io.reactivex.rxjava3.parallel.ParallelFlowable<T> runOn(io.reactivex.rxjava3.core.Scheduler, int);
    Code:
       0: aload_1
       1: ldc           #45                 // String scheduler is null
       3: invokestatic  #3                  // Method java/util/Objects.requireNonNull:(Ljava/lang/Object;Ljava/lang/String;)Ljava/lang/Object;
       6: pop
       7: iload_2
       8: ldc           #23                 // String prefetch
      10: invokestatic  #22                 // Method io/reactivex/rxjava3/internal/functions/ObjectHelper.verifyPositive:(ILjava/lang/String;)I
      13: pop
      14: new           #46                 // class io/reactivex/rxjava3/internal/operators/parallel/ParallelRunOn
      17: dup
      18: aload_0
      19: aload_1
      20: iload_2
      21: invokespecial #47                 // Method io/reactivex/rxjava3/internal/operators/parallel/ParallelRunOn."<init>":(Lio/reactivex/rxjava3/parallel/ParallelFlowable;Lio/reactivex/rxjava3/core/Scheduler;I)V
      24: invokestatic  #48                 // Method io/reactivex/rxjava3/plugins/RxJavaPlugins.onAssembly:(Lio/reactivex/rxjava3/parallel/ParallelFlowable;)Lio/reactivex/rxjava3/parallel/ParallelFlowable;
      27: areturn

  public final io.reactivex.rxjava3.core.Flowable<T> reduce(io.reactivex.rxjava3.functions.BiFunction<T, T, T>);
    Code:
       0: aload_1
       1: ldc           #49                 // String reducer is null
       3: invokestatic  #3                  // Method java/util/Objects.requireNonNull:(Ljava/lang/Object;Ljava/lang/String;)Ljava/lang/Object;
       6: pop
       7: new           #50                 // class io/reactivex/rxjava3/internal/operators/parallel/ParallelReduceFull
      10: dup
      11: aload_0
      12: aload_1
      13: invokespecial #51                 // Method io/reactivex/rxjava3/internal/operators/parallel/ParallelReduceFull."<init>":(Lio/reactivex/rxjava3/parallel/ParallelFlowable;Lio/reactivex/rxjava3/functions/BiFunction;)V
      16: invokestatic  #52                 // Method io/reactivex/rxjava3/plugins/RxJavaPlugins.onAssembly:(Lio/reactivex/rxjava3/core/Flowable;)Lio/reactivex/rxjava3/core/Flowable;
      19: areturn

  public final <R> io.reactivex.rxjava3.parallel.ParallelFlowable<R> reduce(io.reactivex.rxjava3.functions.Supplier<R>, io.reactivex.rxjava3.functions.BiFunction<R, ? super T, R>);
    Code:
       0: aload_1
       1: ldc           #53                 // String initialSupplier is null
       3: invokestatic  #3                  // Method java/util/Objects.requireNonNull:(Ljava/lang/Object;Ljava/lang/String;)Ljava/lang/Object;
       6: pop
       7: aload_2
       8: ldc           #49                 // String reducer is null
      10: invokestatic  #3                  // Method java/util/Objects.requireNonNull:(Ljava/lang/Object;Ljava/lang/String;)Ljava/lang/Object;
      13: pop
      14: new           #54                 // class io/reactivex/rxjava3/internal/operators/parallel/ParallelReduce
      17: dup
      18: aload_0
      19: aload_1
      20: aload_2
      21: invokespecial #55                 // Method io/reactivex/rxjava3/internal/operators/parallel/ParallelReduce."<init>":(Lio/reactivex/rxjava3/parallel/ParallelFlowable;Lio/reactivex/rxjava3/functions/Supplier;Lio/reactivex/rxjava3/functions/BiFunction;)V
      24: invokestatic  #56                 // Method io/reactivex/rxjava3/plugins/RxJavaPlugins.onAssembly:(Lio/reactivex/rxjava3/parallel/ParallelFlowable;)Lio/reactivex/rxjava3/parallel/ParallelFlowable;
      27: areturn

  public final io.reactivex.rxjava3.core.Flowable<T> sequential();
    Code:
       0: aload_0
       1: invokestatic  #17                 // Method io/reactivex/rxjava3/core/Flowable.bufferSize:()I
       4: invokevirtual #57                 // Method sequential:(I)Lio/reactivex/rxjava3/core/Flowable;
       7: areturn

  public final io.reactivex.rxjava3.core.Flowable<T> sequential(int);
    Code:
       0: iload_1
       1: ldc           #23                 // String prefetch
       3: invokestatic  #22                 // Method io/reactivex/rxjava3/internal/functions/ObjectHelper.verifyPositive:(ILjava/lang/String;)I
       6: pop
       7: new           #58                 // class io/reactivex/rxjava3/internal/operators/parallel/ParallelJoin
      10: dup
      11: aload_0
      12: iload_1
      13: iconst_0
      14: invokespecial #59                 // Method io/reactivex/rxjava3/internal/operators/parallel/ParallelJoin."<init>":(Lio/reactivex/rxjava3/parallel/ParallelFlowable;IZ)V
      17: invokestatic  #60                 // Method io/reactivex/rxjava3/plugins/RxJavaPlugins.onAssembly:(Lio/reactivex/rxjava3/core/Flowable;)Lio/reactivex/rxjava3/core/Flowable;
      20: areturn

  public final io.reactivex.rxjava3.core.Flowable<T> sequentialDelayError();
    Code:
       0: aload_0
       1: invokestatic  #17                 // Method io/reactivex/rxjava3/core/Flowable.bufferSize:()I
       4: invokevirtual #61                 // Method sequentialDelayError:(I)Lio/reactivex/rxjava3/core/Flowable;
       7: areturn

  public final io.reactivex.rxjava3.core.Flowable<T> sequentialDelayError(int);
    Code:
       0: iload_1
       1: ldc           #23                 // String prefetch
       3: invokestatic  #22                 // Method io/reactivex/rxjava3/internal/functions/ObjectHelper.verifyPositive:(ILjava/lang/String;)I
       6: pop
       7: new           #58                 // class io/reactivex/rxjava3/internal/operators/parallel/ParallelJoin
      10: dup
      11: aload_0
      12: iload_1
      13: iconst_1
      14: invokespecial #59                 // Method io/reactivex/rxjava3/internal/operators/parallel/ParallelJoin."<init>":(Lio/reactivex/rxjava3/parallel/ParallelFlowable;IZ)V
      17: invokestatic  #62                 // Method io/reactivex/rxjava3/plugins/RxJavaPlugins.onAssembly:(Lio/reactivex/rxjava3/core/Flowable;)Lio/reactivex/rxjava3/core/Flowable;
      20: areturn

  public final io.reactivex.rxjava3.core.Flowable<T> sorted(java.util.Comparator<? super T>);
    Code:
       0: aload_0
       1: aload_1
       2: bipush        16
       4: invokevirtual #63                 // Method sorted:(Ljava/util/Comparator;I)Lio/reactivex/rxjava3/core/Flowable;
       7: areturn

  public final io.reactivex.rxjava3.core.Flowable<T> sorted(java.util.Comparator<? super T>, int);
    Code:
       0: aload_1
       1: ldc           #64                 // String comparator is null
       3: invokestatic  #3                  // Method java/util/Objects.requireNonNull:(Ljava/lang/Object;Ljava/lang/String;)Ljava/lang/Object;
       6: pop
       7: iload_2
       8: ldc           #65                 // String capacityHint
      10: invokestatic  #22                 // Method io/reactivex/rxjava3/internal/functions/ObjectHelper.verifyPositive:(ILjava/lang/String;)I
      13: pop
      14: iload_2
      15: aload_0
      16: invokevirtual #4                  // Method parallelism:()I
      19: idiv
      20: iconst_1
      21: iadd
      22: istore_3
      23: aload_0
      24: iload_3
      25: invokestatic  #66                 // Method io/reactivex/rxjava3/internal/functions/Functions.createArrayList:(I)Lio/reactivex/rxjava3/functions/Supplier;
      28: invokestatic  #67                 // Method io/reactivex/rxjava3/internal/util/ListAddBiConsumer.instance:()Lio/reactivex/rxjava3/functions/BiFunction;
      31: invokevirtual #68                 // Method reduce:(Lio/reactivex/rxjava3/functions/Supplier;Lio/reactivex/rxjava3/functions/BiFunction;)Lio/reactivex/rxjava3/parallel/ParallelFlowable;
      34: astore        4
      36: aload         4
      38: new           #69                 // class io/reactivex/rxjava3/internal/util/SorterFunction
      41: dup
      42: aload_1
      43: invokespecial #70                 // Method io/reactivex/rxjava3/internal/util/SorterFunction."<init>":(Ljava/util/Comparator;)V
      46: invokevirtual #71                 // Method map:(Lio/reactivex/rxjava3/functions/Function;)Lio/reactivex/rxjava3/parallel/ParallelFlowable;
      49: astore        5
      51: new           #72                 // class io/reactivex/rxjava3/internal/operators/parallel/ParallelSortedJoin
      54: dup
      55: aload         5
      57: aload_1
      58: invokespecial #73                 // Method io/reactivex/rxjava3/internal/operators/parallel/ParallelSortedJoin."<init>":(Lio/reactivex/rxjava3/parallel/ParallelFlowable;Ljava/util/Comparator;)V
      61: invokestatic  #74                 // Method io/reactivex/rxjava3/plugins/RxJavaPlugins.onAssembly:(Lio/reactivex/rxjava3/core/Flowable;)Lio/reactivex/rxjava3/core/Flowable;
      64: areturn

  public final io.reactivex.rxjava3.core.Flowable<java.util.List<T>> toSortedList(java.util.Comparator<? super T>);
    Code:
       0: aload_0
       1: aload_1
       2: bipush        16
       4: invokevirtual #75                 // Method toSortedList:(Ljava/util/Comparator;I)Lio/reactivex/rxjava3/core/Flowable;
       7: areturn

  public final io.reactivex.rxjava3.core.Flowable<java.util.List<T>> toSortedList(java.util.Comparator<? super T>, int);
    Code:
       0: aload_1
       1: ldc           #64                 // String comparator is null
       3: invokestatic  #3                  // Method java/util/Objects.requireNonNull:(Ljava/lang/Object;Ljava/lang/String;)Ljava/lang/Object;
       6: pop
       7: iload_2
       8: ldc           #65                 // String capacityHint
      10: invokestatic  #22                 // Method io/reactivex/rxjava3/internal/functions/ObjectHelper.verifyPositive:(ILjava/lang/String;)I
      13: pop
      14: iload_2
      15: aload_0
      16: invokevirtual #4                  // Method parallelism:()I
      19: idiv
      20: iconst_1
      21: iadd
      22: istore_3
      23: aload_0
      24: iload_3
      25: invokestatic  #66                 // Method io/reactivex/rxjava3/internal/functions/Functions.createArrayList:(I)Lio/reactivex/rxjava3/functions/Supplier;
      28: invokestatic  #67                 // Method io/reactivex/rxjava3/internal/util/ListAddBiConsumer.instance:()Lio/reactivex/rxjava3/functions/BiFunction;
      31: invokevirtual #76                 // Method reduce:(Lio/reactivex/rxjava3/functions/Supplier;Lio/reactivex/rxjava3/functions/BiFunction;)Lio/reactivex/rxjava3/parallel/ParallelFlowable;
      34: astore        4
      36: aload         4
      38: new           #69                 // class io/reactivex/rxjava3/internal/util/SorterFunction
      41: dup
      42: aload_1
      43: invokespecial #70                 // Method io/reactivex/rxjava3/internal/util/SorterFunction."<init>":(Ljava/util/Comparator;)V
      46: invokevirtual #77                 // Method map:(Lio/reactivex/rxjava3/functions/Function;)Lio/reactivex/rxjava3/parallel/ParallelFlowable;
      49: astore        5
      51: aload         5
      53: new           #78                 // class io/reactivex/rxjava3/internal/util/MergerBiFunction
      56: dup
      57: aload_1
      58: invokespecial #79                 // Method io/reactivex/rxjava3/internal/util/MergerBiFunction."<init>":(Ljava/util/Comparator;)V
      61: invokevirtual #80                 // Method reduce:(Lio/reactivex/rxjava3/functions/BiFunction;)Lio/reactivex/rxjava3/core/Flowable;
      64: astore        6
      66: aload         6
      68: invokestatic  #81                 // Method io/reactivex/rxjava3/plugins/RxJavaPlugins.onAssembly:(Lio/reactivex/rxjava3/core/Flowable;)Lio/reactivex/rxjava3/core/Flowable;
      71: areturn

  public final io.reactivex.rxjava3.parallel.ParallelFlowable<T> doOnNext(io.reactivex.rxjava3.functions.Consumer<? super T>);
    Code:
       0: aload_1
       1: ldc           #82                 // String onNext is null
       3: invokestatic  #3                  // Method java/util/Objects.requireNonNull:(Ljava/lang/Object;Ljava/lang/String;)Ljava/lang/Object;
       6: pop
       7: new           #83                 // class io/reactivex/rxjava3/internal/operators/parallel/ParallelPeek
      10: dup
      11: aload_0
      12: aload_1
      13: invokestatic  #84                 // Method io/reactivex/rxjava3/internal/functions/Functions.emptyConsumer:()Lio/reactivex/rxjava3/functions/Consumer;
      16: invokestatic  #84                 // Method io/reactivex/rxjava3/internal/functions/Functions.emptyConsumer:()Lio/reactivex/rxjava3/functions/Consumer;
      19: getstatic     #85                 // Field io/reactivex/rxjava3/internal/functions/Functions.EMPTY_ACTION:Lio/reactivex/rxjava3/functions/Action;
      22: getstatic     #85                 // Field io/reactivex/rxjava3/internal/functions/Functions.EMPTY_ACTION:Lio/reactivex/rxjava3/functions/Action;
      25: invokestatic  #84                 // Method io/reactivex/rxjava3/internal/functions/Functions.emptyConsumer:()Lio/reactivex/rxjava3/functions/Consumer;
      28: getstatic     #86                 // Field io/reactivex/rxjava3/internal/functions/Functions.EMPTY_LONG_CONSUMER:Lio/reactivex/rxjava3/functions/LongConsumer;
      31: getstatic     #85                 // Field io/reactivex/rxjava3/internal/functions/Functions.EMPTY_ACTION:Lio/reactivex/rxjava3/functions/Action;
      34: invokespecial #87                 // Method io/reactivex/rxjava3/internal/operators/parallel/ParallelPeek."<init>":(Lio/reactivex/rxjava3/parallel/ParallelFlowable;Lio/reactivex/rxjava3/functions/Consumer;Lio/reactivex/rxjava3/functions/Consumer;Lio/reactivex/rxjava3/functions/Consumer;Lio/reactivex/rxjava3/functions/Action;Lio/reactivex/rxjava3/functions/Action;Lio/reactivex/rxjava3/functions/Consumer;Lio/reactivex/rxjava3/functions/LongConsumer;Lio/reactivex/rxjava3/functions/Action;)V
      37: invokestatic  #88                 // Method io/reactivex/rxjava3/plugins/RxJavaPlugins.onAssembly:(Lio/reactivex/rxjava3/parallel/ParallelFlowable;)Lio/reactivex/rxjava3/parallel/ParallelFlowable;
      40: areturn

  public final io.reactivex.rxjava3.parallel.ParallelFlowable<T> doOnNext(io.reactivex.rxjava3.functions.Consumer<? super T>, io.reactivex.rxjava3.parallel.ParallelFailureHandling);
    Code:
       0: aload_1
       1: ldc           #82                 // String onNext is null
       3: invokestatic  #3                  // Method java/util/Objects.requireNonNull:(Ljava/lang/Object;Ljava/lang/String;)Ljava/lang/Object;
       6: pop
       7: aload_2
       8: ldc           #31                 // String errorHandler is null
      10: invokestatic  #3                  // Method java/util/Objects.requireNonNull:(Ljava/lang/Object;Ljava/lang/String;)Ljava/lang/Object;
      13: pop
      14: new           #89                 // class io/reactivex/rxjava3/internal/operators/parallel/ParallelDoOnNextTry
      17: dup
      18: aload_0
      19: aload_1
      20: aload_2
      21: invokespecial #90                 // Method io/reactivex/rxjava3/internal/operators/parallel/ParallelDoOnNextTry."<init>":(Lio/reactivex/rxjava3/parallel/ParallelFlowable;Lio/reactivex/rxjava3/functions/Consumer;Lio/reactivex/rxjava3/functions/BiFunction;)V
      24: invokestatic  #91                 // Method io/reactivex/rxjava3/plugins/RxJavaPlugins.onAssembly:(Lio/reactivex/rxjava3/parallel/ParallelFlowable;)Lio/reactivex/rxjava3/parallel/ParallelFlowable;
      27: areturn

  public final io.reactivex.rxjava3.parallel.ParallelFlowable<T> doOnNext(io.reactivex.rxjava3.functions.Consumer<? super T>, io.reactivex.rxjava3.functions.BiFunction<? super java.lang.Long, ? super java.lang.Throwable, io.reactivex.rxjava3.parallel.ParallelFailureHandling>);
    Code:
       0: aload_1
       1: ldc           #82                 // String onNext is null
       3: invokestatic  #3                  // Method java/util/Objects.requireNonNull:(Ljava/lang/Object;Ljava/lang/String;)Ljava/lang/Object;
       6: pop
       7: aload_2
       8: ldc           #31                 // String errorHandler is null
      10: invokestatic  #3                  // Method java/util/Objects.requireNonNull:(Ljava/lang/Object;Ljava/lang/String;)Ljava/lang/Object;
      13: pop
      14: new           #89                 // class io/reactivex/rxjava3/internal/operators/parallel/ParallelDoOnNextTry
      17: dup
      18: aload_0
      19: aload_1
      20: aload_2
      21: invokespecial #90                 // Method io/reactivex/rxjava3/internal/operators/parallel/ParallelDoOnNextTry."<init>":(Lio/reactivex/rxjava3/parallel/ParallelFlowable;Lio/reactivex/rxjava3/functions/Consumer;Lio/reactivex/rxjava3/functions/BiFunction;)V
      24: invokestatic  #92                 // Method io/reactivex/rxjava3/plugins/RxJavaPlugins.onAssembly:(Lio/reactivex/rxjava3/parallel/ParallelFlowable;)Lio/reactivex/rxjava3/parallel/ParallelFlowable;
      27: areturn

  public final io.reactivex.rxjava3.parallel.ParallelFlowable<T> doAfterNext(io.reactivex.rxjava3.functions.Consumer<? super T>);
    Code:
       0: aload_1
       1: ldc           #93                 // String onAfterNext is null
       3: invokestatic  #3                  // Method java/util/Objects.requireNonNull:(Ljava/lang/Object;Ljava/lang/String;)Ljava/lang/Object;
       6: pop
       7: new           #83                 // class io/reactivex/rxjava3/internal/operators/parallel/ParallelPeek
      10: dup
      11: aload_0
      12: invokestatic  #84                 // Method io/reactivex/rxjava3/internal/functions/Functions.emptyConsumer:()Lio/reactivex/rxjava3/functions/Consumer;
      15: aload_1
      16: invokestatic  #84                 // Method io/reactivex/rxjava3/internal/functions/Functions.emptyConsumer:()Lio/reactivex/rxjava3/functions/Consumer;
      19: getstatic     #85                 // Field io/reactivex/rxjava3/internal/functions/Functions.EMPTY_ACTION:Lio/reactivex/rxjava3/functions/Action;
      22: getstatic     #85                 // Field io/reactivex/rxjava3/internal/functions/Functions.EMPTY_ACTION:Lio/reactivex/rxjava3/functions/Action;
      25: invokestatic  #84                 // Method io/reactivex/rxjava3/internal/functions/Functions.emptyConsumer:()Lio/reactivex/rxjava3/functions/Consumer;
      28: getstatic     #86                 // Field io/reactivex/rxjava3/internal/functions/Functions.EMPTY_LONG_CONSUMER:Lio/reactivex/rxjava3/functions/LongConsumer;
      31: getstatic     #85                 // Field io/reactivex/rxjava3/internal/functions/Functions.EMPTY_ACTION:Lio/reactivex/rxjava3/functions/Action;
      34: invokespecial #87                 // Method io/reactivex/rxjava3/internal/operators/parallel/ParallelPeek."<init>":(Lio/reactivex/rxjava3/parallel/ParallelFlowable;Lio/reactivex/rxjava3/functions/Consumer;Lio/reactivex/rxjava3/functions/Consumer;Lio/reactivex/rxjava3/functions/Consumer;Lio/reactivex/rxjava3/functions/Action;Lio/reactivex/rxjava3/functions/Action;Lio/reactivex/rxjava3/functions/Consumer;Lio/reactivex/rxjava3/functions/LongConsumer;Lio/reactivex/rxjava3/functions/Action;)V
      37: invokestatic  #94                 // Method io/reactivex/rxjava3/plugins/RxJavaPlugins.onAssembly:(Lio/reactivex/rxjava3/parallel/ParallelFlowable;)Lio/reactivex/rxjava3/parallel/ParallelFlowable;
      40: areturn

  public final io.reactivex.rxjava3.parallel.ParallelFlowable<T> doOnError(io.reactivex.rxjava3.functions.Consumer<? super java.lang.Throwable>);
    Code:
       0: aload_1
       1: ldc           #95                 // String onError is null
       3: invokestatic  #3                  // Method java/util/Objects.requireNonNull:(Ljava/lang/Object;Ljava/lang/String;)Ljava/lang/Object;
       6: pop
       7: new           #83                 // class io/reactivex/rxjava3/internal/operators/parallel/ParallelPeek
      10: dup
      11: aload_0
      12: invokestatic  #84                 // Method io/reactivex/rxjava3/internal/functions/Functions.emptyConsumer:()Lio/reactivex/rxjava3/functions/Consumer;
      15: invokestatic  #84                 // Method io/reactivex/rxjava3/internal/functions/Functions.emptyConsumer:()Lio/reactivex/rxjava3/functions/Consumer;
      18: aload_1
      19: getstatic     #85                 // Field io/reactivex/rxjava3/internal/functions/Functions.EMPTY_ACTION:Lio/reactivex/rxjava3/functions/Action;
      22: getstatic     #85                 // Field io/reactivex/rxjava3/internal/functions/Functions.EMPTY_ACTION:Lio/reactivex/rxjava3/functions/Action;
      25: invokestatic  #84                 // Method io/reactivex/rxjava3/internal/functions/Functions.emptyConsumer:()Lio/reactivex/rxjava3/functions/Consumer;
      28: getstatic     #86                 // Field io/reactivex/rxjava3/internal/functions/Functions.EMPTY_LONG_CONSUMER:Lio/reactivex/rxjava3/functions/LongConsumer;
      31: getstatic     #85                 // Field io/reactivex/rxjava3/internal/functions/Functions.EMPTY_ACTION:Lio/reactivex/rxjava3/functions/Action;
      34: invokespecial #87                 // Method io/reactivex/rxjava3/internal/operators/parallel/ParallelPeek."<init>":(Lio/reactivex/rxjava3/parallel/ParallelFlowable;Lio/reactivex/rxjava3/functions/Consumer;Lio/reactivex/rxjava3/functions/Consumer;Lio/reactivex/rxjava3/functions/Consumer;Lio/reactivex/rxjava3/functions/Action;Lio/reactivex/rxjava3/functions/Action;Lio/reactivex/rxjava3/functions/Consumer;Lio/reactivex/rxjava3/functions/LongConsumer;Lio/reactivex/rxjava3/functions/Action;)V
      37: invokestatic  #96                 // Method io/reactivex/rxjava3/plugins/RxJavaPlugins.onAssembly:(Lio/reactivex/rxjava3/parallel/ParallelFlowable;)Lio/reactivex/rxjava3/parallel/ParallelFlowable;
      40: areturn

  public final io.reactivex.rxjava3.parallel.ParallelFlowable<T> doOnComplete(io.reactivex.rxjava3.functions.Action);
    Code:
       0: aload_1
       1: ldc           #97                 // String onComplete is null
       3: invokestatic  #3                  // Method java/util/Objects.requireNonNull:(Ljava/lang/Object;Ljava/lang/String;)Ljava/lang/Object;
       6: pop
       7: new           #83                 // class io/reactivex/rxjava3/internal/operators/parallel/ParallelPeek
      10: dup
      11: aload_0
      12: invokestatic  #84                 // Method io/reactivex/rxjava3/internal/functions/Functions.emptyConsumer:()Lio/reactivex/rxjava3/functions/Consumer;
      15: invokestatic  #84                 // Method io/reactivex/rxjava3/internal/functions/Functions.emptyConsumer:()Lio/reactivex/rxjava3/functions/Consumer;
      18: invokestatic  #84                 // Method io/reactivex/rxjava3/internal/functions/Functions.emptyConsumer:()Lio/reactivex/rxjava3/functions/Consumer;
      21: aload_1
      22: getstatic     #85                 // Field io/reactivex/rxjava3/internal/functions/Functions.EMPTY_ACTION:Lio/reactivex/rxjava3/functions/Action;
      25: invokestatic  #84                 // Method io/reactivex/rxjava3/internal/functions/Functions.emptyConsumer:()Lio/reactivex/rxjava3/functions/Consumer;
      28: getstatic     #86                 // Field io/reactivex/rxjava3/internal/functions/Functions.EMPTY_LONG_CONSUMER:Lio/reactivex/rxjava3/functions/LongConsumer;
      31: getstatic     #85                 // Field io/reactivex/rxjava3/internal/functions/Functions.EMPTY_ACTION:Lio/reactivex/rxjava3/functions/Action;
      34: invokespecial #87                 // Method io/reactivex/rxjava3/internal/operators/parallel/ParallelPeek."<init>":(Lio/reactivex/rxjava3/parallel/ParallelFlowable;Lio/reactivex/rxjava3/functions/Consumer;Lio/reactivex/rxjava3/functions/Consumer;Lio/reactivex/rxjava3/functions/Consumer;Lio/reactivex/rxjava3/functions/Action;Lio/reactivex/rxjava3/functions/Action;Lio/reactivex/rxjava3/functions/Consumer;Lio/reactivex/rxjava3/functions/LongConsumer;Lio/reactivex/rxjava3/functions/Action;)V
      37: invokestatic  #98                 // Method io/reactivex/rxjava3/plugins/RxJavaPlugins.onAssembly:(Lio/reactivex/rxjava3/parallel/ParallelFlowable;)Lio/reactivex/rxjava3/parallel/ParallelFlowable;
      40: areturn

  public final io.reactivex.rxjava3.parallel.ParallelFlowable<T> doAfterTerminated(io.reactivex.rxjava3.functions.Action);
    Code:
       0: aload_1
       1: ldc           #99                 // String onAfterTerminate is null
       3: invokestatic  #3                  // Method java/util/Objects.requireNonNull:(Ljava/lang/Object;Ljava/lang/String;)Ljava/lang/Object;
       6: pop
       7: new           #83                 // class io/reactivex/rxjava3/internal/operators/parallel/ParallelPeek
      10: dup
      11: aload_0
      12: invokestatic  #84                 // Method io/reactivex/rxjava3/internal/functions/Functions.emptyConsumer:()Lio/reactivex/rxjava3/functions/Consumer;
      15: invokestatic  #84                 // Method io/reactivex/rxjava3/internal/functions/Functions.emptyConsumer:()Lio/reactivex/rxjava3/functions/Consumer;
      18: invokestatic  #84                 // Method io/reactivex/rxjava3/internal/functions/Functions.emptyConsumer:()Lio/reactivex/rxjava3/functions/Consumer;
      21: getstatic     #85                 // Field io/reactivex/rxjava3/internal/functions/Functions.EMPTY_ACTION:Lio/reactivex/rxjava3/functions/Action;
      24: aload_1
      25: invokestatic  #84                 // Method io/reactivex/rxjava3/internal/functions/Functions.emptyConsumer:()Lio/reactivex/rxjava3/functions/Consumer;
      28: getstatic     #86                 // Field io/reactivex/rxjava3/internal/functions/Functions.EMPTY_LONG_CONSUMER:Lio/reactivex/rxjava3/functions/LongConsumer;
      31: getstatic     #85                 // Field io/reactivex/rxjava3/internal/functions/Functions.EMPTY_ACTION:Lio/reactivex/rxjava3/functions/Action;
      34: invokespecial #87                 // Method io/reactivex/rxjava3/internal/operators/parallel/ParallelPeek."<init>":(Lio/reactivex/rxjava3/parallel/ParallelFlowable;Lio/reactivex/rxjava3/functions/Consumer;Lio/reactivex/rxjava3/functions/Consumer;Lio/reactivex/rxjava3/functions/Consumer;Lio/reactivex/rxjava3/functions/Action;Lio/reactivex/rxjava3/functions/Action;Lio/reactivex/rxjava3/functions/Consumer;Lio/reactivex/rxjava3/functions/LongConsumer;Lio/reactivex/rxjava3/functions/Action;)V
      37: invokestatic  #100                // Method io/reactivex/rxjava3/plugins/RxJavaPlugins.onAssembly:(Lio/reactivex/rxjava3/parallel/ParallelFlowable;)Lio/reactivex/rxjava3/parallel/ParallelFlowable;
      40: areturn

  public final io.reactivex.rxjava3.parallel.ParallelFlowable<T> doOnSubscribe(io.reactivex.rxjava3.functions.Consumer<? super org.reactivestreams.Subscription>);
    Code:
       0: aload_1
       1: ldc           #101                // String onSubscribe is null
       3: invokestatic  #3                  // Method java/util/Objects.requireNonNull:(Ljava/lang/Object;Ljava/lang/String;)Ljava/lang/Object;
       6: pop
       7: new           #83                 // class io/reactivex/rxjava3/internal/operators/parallel/ParallelPeek
      10: dup
      11: aload_0
      12: invokestatic  #84                 // Method io/reactivex/rxjava3/internal/functions/Functions.emptyConsumer:()Lio/reactivex/rxjava3/functions/Consumer;
      15: invokestatic  #84                 // Method io/reactivex/rxjava3/internal/functions/Functions.emptyConsumer:()Lio/reactivex/rxjava3/functions/Consumer;
      18: invokestatic  #84                 // Method io/reactivex/rxjava3/internal/functions/Functions.emptyConsumer:()Lio/reactivex/rxjava3/functions/Consumer;
      21: getstatic     #85                 // Field io/reactivex/rxjava3/internal/functions/Functions.EMPTY_ACTION:Lio/reactivex/rxjava3/functions/Action;
      24: getstatic     #85                 // Field io/reactivex/rxjava3/internal/functions/Functions.EMPTY_ACTION:Lio/reactivex/rxjava3/functions/Action;
      27: aload_1
      28: getstatic     #86                 // Field io/reactivex/rxjava3/internal/functions/Functions.EMPTY_LONG_CONSUMER:Lio/reactivex/rxjava3/functions/LongConsumer;
      31: getstatic     #85                 // Field io/reactivex/rxjava3/internal/functions/Functions.EMPTY_ACTION:Lio/reactivex/rxjava3/functions/Action;
      34: invokespecial #87                 // Method io/reactivex/rxjava3/internal/operators/parallel/ParallelPeek."<init>":(Lio/reactivex/rxjava3/parallel/ParallelFlowable;Lio/reactivex/rxjava3/functions/Consumer;Lio/reactivex/rxjava3/functions/Consumer;Lio/reactivex/rxjava3/functions/Consumer;Lio/reactivex/rxjava3/functions/Action;Lio/reactivex/rxjava3/functions/Action;Lio/reactivex/rxjava3/functions/Consumer;Lio/reactivex/rxjava3/functions/LongConsumer;Lio/reactivex/rxjava3/functions/Action;)V
      37: invokestatic  #102                // Method io/reactivex/rxjava3/plugins/RxJavaPlugins.onAssembly:(Lio/reactivex/rxjava3/parallel/ParallelFlowable;)Lio/reactivex/rxjava3/parallel/ParallelFlowable;
      40: areturn

  public final io.reactivex.rxjava3.parallel.ParallelFlowable<T> doOnRequest(io.reactivex.rxjava3.functions.LongConsumer);
    Code:
       0: aload_1
       1: ldc           #103                // String onRequest is null
       3: invokestatic  #3                  // Method java/util/Objects.requireNonNull:(Ljava/lang/Object;Ljava/lang/String;)Ljava/lang/Object;
       6: pop
       7: new           #83                 // class io/reactivex/rxjava3/internal/operators/parallel/ParallelPeek
      10: dup
      11: aload_0
      12: invokestatic  #84                 // Method io/reactivex/rxjava3/internal/functions/Functions.emptyConsumer:()Lio/reactivex/rxjava3/functions/Consumer;
      15: invokestatic  #84                 // Method io/reactivex/rxjava3/internal/functions/Functions.emptyConsumer:()Lio/reactivex/rxjava3/functions/Consumer;
      18: invokestatic  #84                 // Method io/reactivex/rxjava3/internal/functions/Functions.emptyConsumer:()Lio/reactivex/rxjava3/functions/Consumer;
      21: getstatic     #85                 // Field io/reactivex/rxjava3/internal/functions/Functions.EMPTY_ACTION:Lio/reactivex/rxjava3/functions/Action;
      24: getstatic     #85                 // Field io/reactivex/rxjava3/internal/functions/Functions.EMPTY_ACTION:Lio/reactivex/rxjava3/functions/Action;
      27: invokestatic  #84                 // Method io/reactivex/rxjava3/internal/functions/Functions.emptyConsumer:()Lio/reactivex/rxjava3/functions/Consumer;
      30: aload_1
      31: getstatic     #85                 // Field io/reactivex/rxjava3/internal/functions/Functions.EMPTY_ACTION:Lio/reactivex/rxjava3/functions/Action;
      34: invokespecial #87                 // Method io/reactivex/rxjava3/internal/operators/parallel/ParallelPeek."<init>":(Lio/reactivex/rxjava3/parallel/ParallelFlowable;Lio/reactivex/rxjava3/functions/Consumer;Lio/reactivex/rxjava3/functions/Consumer;Lio/reactivex/rxjava3/functions/Consumer;Lio/reactivex/rxjava3/functions/Action;Lio/reactivex/rxjava3/functions/Action;Lio/reactivex/rxjava3/functions/Consumer;Lio/reactivex/rxjava3/functions/LongConsumer;Lio/reactivex/rxjava3/functions/Action;)V
      37: invokestatic  #104                // Method io/reactivex/rxjava3/plugins/RxJavaPlugins.onAssembly:(Lio/reactivex/rxjava3/parallel/ParallelFlowable;)Lio/reactivex/rxjava3/parallel/ParallelFlowable;
      40: areturn

  public final io.reactivex.rxjava3.parallel.ParallelFlowable<T> doOnCancel(io.reactivex.rxjava3.functions.Action);
    Code:
       0: aload_1
       1: ldc           #105                // String onCancel is null
       3: invokestatic  #3                  // Method java/util/Objects.requireNonNull:(Ljava/lang/Object;Ljava/lang/String;)Ljava/lang/Object;
       6: pop
       7: new           #83                 // class io/reactivex/rxjava3/internal/operators/parallel/ParallelPeek
      10: dup
      11: aload_0
      12: invokestatic  #84                 // Method io/reactivex/rxjava3/internal/functions/Functions.emptyConsumer:()Lio/reactivex/rxjava3/functions/Consumer;
      15: invokestatic  #84                 // Method io/reactivex/rxjava3/internal/functions/Functions.emptyConsumer:()Lio/reactivex/rxjava3/functions/Consumer;
      18: invokestatic  #84                 // Method io/reactivex/rxjava3/internal/functions/Functions.emptyConsumer:()Lio/reactivex/rxjava3/functions/Consumer;
      21: getstatic     #85                 // Field io/reactivex/rxjava3/internal/functions/Functions.EMPTY_ACTION:Lio/reactivex/rxjava3/functions/Action;
      24: getstatic     #85                 // Field io/reactivex/rxjava3/internal/functions/Functions.EMPTY_ACTION:Lio/reactivex/rxjava3/functions/Action;
      27: invokestatic  #84                 // Method io/reactivex/rxjava3/internal/functions/Functions.emptyConsumer:()Lio/reactivex/rxjava3/functions/Consumer;
      30: getstatic     #86                 // Field io/reactivex/rxjava3/internal/functions/Functions.EMPTY_LONG_CONSUMER:Lio/reactivex/rxjava3/functions/LongConsumer;
      33: aload_1
      34: invokespecial #87                 // Method io/reactivex/rxjava3/internal/operators/parallel/ParallelPeek."<init>":(Lio/reactivex/rxjava3/parallel/ParallelFlowable;Lio/reactivex/rxjava3/functions/Consumer;Lio/reactivex/rxjava3/functions/Consumer;Lio/reactivex/rxjava3/functions/Consumer;Lio/reactivex/rxjava3/functions/Action;Lio/reactivex/rxjava3/functions/Action;Lio/reactivex/rxjava3/functions/Consumer;Lio/reactivex/rxjava3/functions/LongConsumer;Lio/reactivex/rxjava3/functions/Action;)V
      37: invokestatic  #106                // Method io/reactivex/rxjava3/plugins/RxJavaPlugins.onAssembly:(Lio/reactivex/rxjava3/parallel/ParallelFlowable;)Lio/reactivex/rxjava3/parallel/ParallelFlowable;
      40: areturn

  public final <C> io.reactivex.rxjava3.parallel.ParallelFlowable<C> collect(io.reactivex.rxjava3.functions.Supplier<? extends C>, io.reactivex.rxjava3.functions.BiConsumer<? super C, ? super T>);
    Code:
       0: aload_1
       1: ldc           #107                // String collectionSupplier is null
       3: invokestatic  #3                  // Method java/util/Objects.requireNonNull:(Ljava/lang/Object;Ljava/lang/String;)Ljava/lang/Object;
       6: pop
       7: aload_2
       8: ldc           #108                // String collector is null
      10: invokestatic  #3                  // Method java/util/Objects.requireNonNull:(Ljava/lang/Object;Ljava/lang/String;)Ljava/lang/Object;
      13: pop
      14: new           #109                // class io/reactivex/rxjava3/internal/operators/parallel/ParallelCollect
      17: dup
      18: aload_0
      19: aload_1
      20: aload_2
      21: invokespecial #110                // Method io/reactivex/rxjava3/internal/operators/parallel/ParallelCollect."<init>":(Lio/reactivex/rxjava3/parallel/ParallelFlowable;Lio/reactivex/rxjava3/functions/Supplier;Lio/reactivex/rxjava3/functions/BiConsumer;)V
      24: invokestatic  #111                // Method io/reactivex/rxjava3/plugins/RxJavaPlugins.onAssembly:(Lio/reactivex/rxjava3/parallel/ParallelFlowable;)Lio/reactivex/rxjava3/parallel/ParallelFlowable;
      27: areturn

  public static <T> io.reactivex.rxjava3.parallel.ParallelFlowable<T> fromArray(org.reactivestreams.Publisher<T>...);
    Code:
       0: aload_0
       1: ldc           #112                // String publishers is null
       3: invokestatic  #3                  // Method java/util/Objects.requireNonNull:(Ljava/lang/Object;Ljava/lang/String;)Ljava/lang/Object;
       6: pop
       7: aload_0
       8: arraylength
       9: ifne          22
      12: new           #5                  // class java/lang/IllegalArgumentException
      15: dup
      16: ldc           #113                // String Zero publishers not supported
      18: invokespecial #13                 // Method java/lang/IllegalArgumentException."<init>":(Ljava/lang/String;)V
      21: athrow
      22: new           #114                // class io/reactivex/rxjava3/internal/operators/parallel/ParallelFromArray
      25: dup
      26: aload_0
      27: invokespecial #115                // Method io/reactivex/rxjava3/internal/operators/parallel/ParallelFromArray."<init>":([Lorg/reactivestreams/Publisher;)V
      30: invokestatic  #116                // Method io/reactivex/rxjava3/plugins/RxJavaPlugins.onAssembly:(Lio/reactivex/rxjava3/parallel/ParallelFlowable;)Lio/reactivex/rxjava3/parallel/ParallelFlowable;
      33: areturn

  public final <R> R to(io.reactivex.rxjava3.parallel.ParallelFlowableConverter<T, R>);
    Code:
       0: aload_1
       1: ldc           #117                // String converter is null
       3: invokestatic  #3                  // Method java/util/Objects.requireNonNull:(Ljava/lang/Object;Ljava/lang/String;)Ljava/lang/Object;
       6: checkcast     #118                // class io/reactivex/rxjava3/parallel/ParallelFlowableConverter
       9: aload_0
      10: invokeinterface #119,  2          // InterfaceMethod io/reactivex/rxjava3/parallel/ParallelFlowableConverter.apply:(Lio/reactivex/rxjava3/parallel/ParallelFlowable;)Ljava/lang/Object;
      15: areturn

  public final <U> io.reactivex.rxjava3.parallel.ParallelFlowable<U> compose(io.reactivex.rxjava3.parallel.ParallelTransformer<T, U>);
    Code:
       0: aload_1
       1: ldc           #120                // String composer is null
       3: invokestatic  #3                  // Method java/util/Objects.requireNonNull:(Ljava/lang/Object;Ljava/lang/String;)Ljava/lang/Object;
       6: checkcast     #121                // class io/reactivex/rxjava3/parallel/ParallelTransformer
       9: aload_0
      10: invokeinterface #122,  2          // InterfaceMethod io/reactivex/rxjava3/parallel/ParallelTransformer.apply:(Lio/reactivex/rxjava3/parallel/ParallelFlowable;)Lio/reactivex/rxjava3/parallel/ParallelFlowable;
      15: invokestatic  #123                // Method io/reactivex/rxjava3/plugins/RxJavaPlugins.onAssembly:(Lio/reactivex/rxjava3/parallel/ParallelFlowable;)Lio/reactivex/rxjava3/parallel/ParallelFlowable;
      18: areturn

  public final <R> io.reactivex.rxjava3.parallel.ParallelFlowable<R> flatMap(io.reactivex.rxjava3.functions.Function<? super T, ? extends org.reactivestreams.Publisher<? extends R>>);
    Code:
       0: aload_0
       1: aload_1
       2: iconst_0
       3: invokestatic  #17                 // Method io/reactivex/rxjava3/core/Flowable.bufferSize:()I
       6: invokestatic  #17                 // Method io/reactivex/rxjava3/core/Flowable.bufferSize:()I
       9: invokevirtual #124                // Method flatMap:(Lio/reactivex/rxjava3/functions/Function;ZII)Lio/reactivex/rxjava3/parallel/ParallelFlowable;
      12: areturn

  public final <R> io.reactivex.rxjava3.parallel.ParallelFlowable<R> flatMap(io.reactivex.rxjava3.functions.Function<? super T, ? extends org.reactivestreams.Publisher<? extends R>>, boolean);
    Code:
       0: aload_0
       1: aload_1
       2: iload_2
       3: invokestatic  #17                 // Method io/reactivex/rxjava3/core/Flowable.bufferSize:()I
       6: invokestatic  #17                 // Method io/reactivex/rxjava3/core/Flowable.bufferSize:()I
       9: invokevirtual #125                // Method flatMap:(Lio/reactivex/rxjava3/functions/Function;ZII)Lio/reactivex/rxjava3/parallel/ParallelFlowable;
      12: areturn

  public final <R> io.reactivex.rxjava3.parallel.ParallelFlowable<R> flatMap(io.reactivex.rxjava3.functions.Function<? super T, ? extends org.reactivestreams.Publisher<? extends R>>, boolean, int);
    Code:
       0: aload_0
       1: aload_1
       2: iload_2
       3: iload_3
       4: invokestatic  #17                 // Method io/reactivex/rxjava3/core/Flowable.bufferSize:()I
       7: invokevirtual #126                // Method flatMap:(Lio/reactivex/rxjava3/functions/Function;ZII)Lio/reactivex/rxjava3/parallel/ParallelFlowable;
      10: areturn

  public final <R> io.reactivex.rxjava3.parallel.ParallelFlowable<R> flatMap(io.reactivex.rxjava3.functions.Function<? super T, ? extends org.reactivestreams.Publisher<? extends R>>, boolean, int, int);
    Code:
       0: aload_1
       1: ldc           #27                 // String mapper is null
       3: invokestatic  #3                  // Method java/util/Objects.requireNonNull:(Ljava/lang/Object;Ljava/lang/String;)Ljava/lang/Object;
       6: pop
       7: iload_3
       8: ldc           #127                // String maxConcurrency
      10: invokestatic  #22                 // Method io/reactivex/rxjava3/internal/functions/ObjectHelper.verifyPositive:(ILjava/lang/String;)I
      13: pop
      14: iload         4
      16: ldc           #23                 // String prefetch
      18: invokestatic  #22                 // Method io/reactivex/rxjava3/internal/functions/ObjectHelper.verifyPositive:(ILjava/lang/String;)I
      21: pop
      22: new           #128                // class io/reactivex/rxjava3/internal/operators/parallel/ParallelFlatMap
      25: dup
      26: aload_0
      27: aload_1
      28: iload_2
      29: iload_3
      30: iload         4
      32: invokespecial #129                // Method io/reactivex/rxjava3/internal/operators/parallel/ParallelFlatMap."<init>":(Lio/reactivex/rxjava3/parallel/ParallelFlowable;Lio/reactivex/rxjava3/functions/Function;ZII)V
      35: invokestatic  #130                // Method io/reactivex/rxjava3/plugins/RxJavaPlugins.onAssembly:(Lio/reactivex/rxjava3/parallel/ParallelFlowable;)Lio/reactivex/rxjava3/parallel/ParallelFlowable;
      38: areturn

  public final <R> io.reactivex.rxjava3.parallel.ParallelFlowable<R> concatMap(io.reactivex.rxjava3.functions.Function<? super T, ? extends org.reactivestreams.Publisher<? extends R>>);
    Code:
       0: aload_0
       1: aload_1
       2: iconst_2
       3: invokevirtual #131                // Method concatMap:(Lio/reactivex/rxjava3/functions/Function;I)Lio/reactivex/rxjava3/parallel/ParallelFlowable;
       6: areturn

  public final <R> io.reactivex.rxjava3.parallel.ParallelFlowable<R> concatMap(io.reactivex.rxjava3.functions.Function<? super T, ? extends org.reactivestreams.Publisher<? extends R>>, int);
    Code:
       0: aload_1
       1: ldc           #27                 // String mapper is null
       3: invokestatic  #3                  // Method java/util/Objects.requireNonNull:(Ljava/lang/Object;Ljava/lang/String;)Ljava/lang/Object;
       6: pop
       7: iload_2
       8: ldc           #23                 // String prefetch
      10: invokestatic  #22                 // Method io/reactivex/rxjava3/internal/functions/ObjectHelper.verifyPositive:(ILjava/lang/String;)I
      13: pop
      14: new           #132                // class io/reactivex/rxjava3/internal/operators/parallel/ParallelConcatMap
      17: dup
      18: aload_0
      19: aload_1
      20: iload_2
      21: getstatic     #133                // Field io/reactivex/rxjava3/internal/util/ErrorMode.IMMEDIATE:Lio/reactivex/rxjava3/internal/util/ErrorMode;
      24: invokespecial #134                // Method io/reactivex/rxjava3/internal/operators/parallel/ParallelConcatMap."<init>":(Lio/reactivex/rxjava3/parallel/ParallelFlowable;Lio/reactivex/rxjava3/functions/Function;ILio/reactivex/rxjava3/internal/util/ErrorMode;)V
      27: invokestatic  #135                // Method io/reactivex/rxjava3/plugins/RxJavaPlugins.onAssembly:(Lio/reactivex/rxjava3/parallel/ParallelFlowable;)Lio/reactivex/rxjava3/parallel/ParallelFlowable;
      30: areturn

  public final <R> io.reactivex.rxjava3.parallel.ParallelFlowable<R> concatMapDelayError(io.reactivex.rxjava3.functions.Function<? super T, ? extends org.reactivestreams.Publisher<? extends R>>, boolean);
    Code:
       0: aload_0
       1: aload_1
       2: iconst_2
       3: iload_2
       4: invokevirtual #136                // Method concatMapDelayError:(Lio/reactivex/rxjava3/functions/Function;IZ)Lio/reactivex/rxjava3/parallel/ParallelFlowable;
       7: areturn

  public final <R> io.reactivex.rxjava3.parallel.ParallelFlowable<R> concatMapDelayError(io.reactivex.rxjava3.functions.Function<? super T, ? extends org.reactivestreams.Publisher<? extends R>>, int, boolean);
    Code:
       0: aload_1
       1: ldc           #27                 // String mapper is null
       3: invokestatic  #3                  // Method java/util/Objects.requireNonNull:(Ljava/lang/Object;Ljava/lang/String;)Ljava/lang/Object;
       6: pop
       7: iload_2
       8: ldc           #23                 // String prefetch
      10: invokestatic  #22                 // Method io/reactivex/rxjava3/internal/functions/ObjectHelper.verifyPositive:(ILjava/lang/String;)I
      13: pop
      14: new           #132                // class io/reactivex/rxjava3/internal/operators/parallel/ParallelConcatMap
      17: dup
      18: aload_0
      19: aload_1
      20: iload_2
      21: iload_3
      22: ifeq          31
      25: getstatic     #137                // Field io/reactivex/rxjava3/internal/util/ErrorMode.END:Lio/reactivex/rxjava3/internal/util/ErrorMode;
      28: goto          34
      31: getstatic     #138                // Field io/reactivex/rxjava3/internal/util/ErrorMode.BOUNDARY:Lio/reactivex/rxjava3/internal/util/ErrorMode;
      34: invokespecial #134                // Method io/reactivex/rxjava3/internal/operators/parallel/ParallelConcatMap."<init>":(Lio/reactivex/rxjava3/parallel/ParallelFlowable;Lio/reactivex/rxjava3/functions/Function;ILio/reactivex/rxjava3/internal/util/ErrorMode;)V
      37: invokestatic  #139                // Method io/reactivex/rxjava3/plugins/RxJavaPlugins.onAssembly:(Lio/reactivex/rxjava3/parallel/ParallelFlowable;)Lio/reactivex/rxjava3/parallel/ParallelFlowable;
      40: areturn

  public final <U> io.reactivex.rxjava3.parallel.ParallelFlowable<U> flatMapIterable(io.reactivex.rxjava3.functions.Function<? super T, ? extends java.lang.Iterable<? extends U>>);
    Code:
       0: aload_0
       1: aload_1
       2: invokestatic  #17                 // Method io/reactivex/rxjava3/core/Flowable.bufferSize:()I
       5: invokevirtual #140                // Method flatMapIterable:(Lio/reactivex/rxjava3/functions/Function;I)Lio/reactivex/rxjava3/parallel/ParallelFlowable;
       8: areturn

  public final <U> io.reactivex.rxjava3.parallel.ParallelFlowable<U> flatMapIterable(io.reactivex.rxjava3.functions.Function<? super T, ? extends java.lang.Iterable<? extends U>>, int);
    Code:
       0: aload_1
       1: ldc           #27                 // String mapper is null
       3: invokestatic  #3                  // Method java/util/Objects.requireNonNull:(Ljava/lang/Object;Ljava/lang/String;)Ljava/lang/Object;
       6: pop
       7: iload_2
       8: ldc           #141                // String bufferSize
      10: invokestatic  #22                 // Method io/reactivex/rxjava3/internal/functions/ObjectHelper.verifyPositive:(ILjava/lang/String;)I
      13: pop
      14: new           #142                // class io/reactivex/rxjava3/internal/operators/parallel/ParallelFlatMapIterable
      17: dup
      18: aload_0
      19: aload_1
      20: iload_2
      21: invokespecial #143                // Method io/reactivex/rxjava3/internal/operators/parallel/ParallelFlatMapIterable."<init>":(Lio/reactivex/rxjava3/parallel/ParallelFlowable;Lio/reactivex/rxjava3/functions/Function;I)V
      24: invokestatic  #144                // Method io/reactivex/rxjava3/plugins/RxJavaPlugins.onAssembly:(Lio/reactivex/rxjava3/parallel/ParallelFlowable;)Lio/reactivex/rxjava3/parallel/ParallelFlowable;
      27: areturn

  public final <R> io.reactivex.rxjava3.parallel.ParallelFlowable<R> mapOptional(io.reactivex.rxjava3.functions.Function<? super T, java.util.Optional<? extends R>>);
    Code:
       0: aload_1
       1: ldc           #27                 // String mapper is null
       3: invokestatic  #3                  // Method java/util/Objects.requireNonNull:(Ljava/lang/Object;Ljava/lang/String;)Ljava/lang/Object;
       6: pop
       7: new           #145                // class io/reactivex/rxjava3/internal/jdk8/ParallelMapOptional
      10: dup
      11: aload_0
      12: aload_1
      13: invokespecial #146                // Method io/reactivex/rxjava3/internal/jdk8/ParallelMapOptional."<init>":(Lio/reactivex/rxjava3/parallel/ParallelFlowable;Lio/reactivex/rxjava3/functions/Function;)V
      16: invokestatic  #147                // Method io/reactivex/rxjava3/plugins/RxJavaPlugins.onAssembly:(Lio/reactivex/rxjava3/parallel/ParallelFlowable;)Lio/reactivex/rxjava3/parallel/ParallelFlowable;
      19: areturn

  public final <R> io.reactivex.rxjava3.parallel.ParallelFlowable<R> mapOptional(io.reactivex.rxjava3.functions.Function<? super T, java.util.Optional<? extends R>>, io.reactivex.rxjava3.parallel.ParallelFailureHandling);
    Code:
       0: aload_1
       1: ldc           #27                 // String mapper is null
       3: invokestatic  #3                  // Method java/util/Objects.requireNonNull:(Ljava/lang/Object;Ljava/lang/String;)Ljava/lang/Object;
       6: pop
       7: aload_2
       8: ldc           #31                 // String errorHandler is null
      10: invokestatic  #3                  // Method java/util/Objects.requireNonNull:(Ljava/lang/Object;Ljava/lang/String;)Ljava/lang/Object;
      13: pop
      14: new           #148                // class io/reactivex/rxjava3/internal/jdk8/ParallelMapTryOptional
      17: dup
      18: aload_0
      19: aload_1
      20: aload_2
      21: invokespecial #149                // Method io/reactivex/rxjava3/internal/jdk8/ParallelMapTryOptional."<init>":(Lio/reactivex/rxjava3/parallel/ParallelFlowable;Lio/reactivex/rxjava3/functions/Function;Lio/reactivex/rxjava3/functions/BiFunction;)V
      24: invokestatic  #150                // Method io/reactivex/rxjava3/plugins/RxJavaPlugins.onAssembly:(Lio/reactivex/rxjava3/parallel/ParallelFlowable;)Lio/reactivex/rxjava3/parallel/ParallelFlowable;
      27: areturn

  public final <R> io.reactivex.rxjava3.parallel.ParallelFlowable<R> mapOptional(io.reactivex.rxjava3.functions.Function<? super T, java.util.Optional<? extends R>>, io.reactivex.rxjava3.functions.BiFunction<? super java.lang.Long, ? super java.lang.Throwable, io.reactivex.rxjava3.parallel.ParallelFailureHandling>);
    Code:
       0: aload_1
       1: ldc           #27                 // String mapper is null
       3: invokestatic  #3                  // Method java/util/Objects.requireNonNull:(Ljava/lang/Object;Ljava/lang/String;)Ljava/lang/Object;
       6: pop
       7: aload_2
       8: ldc           #31                 // String errorHandler is null
      10: invokestatic  #3                  // Method java/util/Objects.requireNonNull:(Ljava/lang/Object;Ljava/lang/String;)Ljava/lang/Object;
      13: pop
      14: new           #148                // class io/reactivex/rxjava3/internal/jdk8/ParallelMapTryOptional
      17: dup
      18: aload_0
      19: aload_1
      20: aload_2
      21: invokespecial #149                // Method io/reactivex/rxjava3/internal/jdk8/ParallelMapTryOptional."<init>":(Lio/reactivex/rxjava3/parallel/ParallelFlowable;Lio/reactivex/rxjava3/functions/Function;Lio/reactivex/rxjava3/functions/BiFunction;)V
      24: invokestatic  #151                // Method io/reactivex/rxjava3/plugins/RxJavaPlugins.onAssembly:(Lio/reactivex/rxjava3/parallel/ParallelFlowable;)Lio/reactivex/rxjava3/parallel/ParallelFlowable;
      27: areturn

  public final <R> io.reactivex.rxjava3.parallel.ParallelFlowable<R> flatMapStream(io.reactivex.rxjava3.functions.Function<? super T, ? extends java.util.stream.Stream<? extends R>>);
    Code:
       0: aload_0
       1: aload_1
       2: invokestatic  #17                 // Method io/reactivex/rxjava3/core/Flowable.bufferSize:()I
       5: invokevirtual #152                // Method flatMapStream:(Lio/reactivex/rxjava3/functions/Function;I)Lio/reactivex/rxjava3/parallel/ParallelFlowable;
       8: areturn

  public final <R> io.reactivex.rxjava3.parallel.ParallelFlowable<R> flatMapStream(io.reactivex.rxjava3.functions.Function<? super T, ? extends java.util.stream.Stream<? extends R>>, int);
    Code:
       0: aload_1
       1: ldc           #27                 // String mapper is null
       3: invokestatic  #3                  // Method java/util/Objects.requireNonNull:(Ljava/lang/Object;Ljava/lang/String;)Ljava/lang/Object;
       6: pop
       7: iload_2
       8: ldc           #23                 // String prefetch
      10: invokestatic  #22                 // Method io/reactivex/rxjava3/internal/functions/ObjectHelper.verifyPositive:(ILjava/lang/String;)I
      13: pop
      14: new           #153                // class io/reactivex/rxjava3/internal/jdk8/ParallelFlatMapStream
      17: dup
      18: aload_0
      19: aload_1
      20: iload_2
      21: invokespecial #154                // Method io/reactivex/rxjava3/internal/jdk8/ParallelFlatMapStream."<init>":(Lio/reactivex/rxjava3/parallel/ParallelFlowable;Lio/reactivex/rxjava3/functions/Function;I)V
      24: invokestatic  #155                // Method io/reactivex/rxjava3/plugins/RxJavaPlugins.onAssembly:(Lio/reactivex/rxjava3/parallel/ParallelFlowable;)Lio/reactivex/rxjava3/parallel/ParallelFlowable;
      27: areturn

  public final <A, R> io.reactivex.rxjava3.core.Flowable<R> collect(java.util.stream.Collector<T, A, R>);
    Code:
       0: aload_1
       1: ldc           #108                // String collector is null
       3: invokestatic  #3                  // Method java/util/Objects.requireNonNull:(Ljava/lang/Object;Ljava/lang/String;)Ljava/lang/Object;
       6: pop
       7: new           #156                // class io/reactivex/rxjava3/internal/jdk8/ParallelCollector
      10: dup
      11: aload_0
      12: aload_1
      13: invokespecial #157                // Method io/reactivex/rxjava3/internal/jdk8/ParallelCollector."<init>":(Lio/reactivex/rxjava3/parallel/ParallelFlowable;Ljava/util/stream/Collector;)V
      16: invokestatic  #158                // Method io/reactivex/rxjava3/plugins/RxJavaPlugins.onAssembly:(Lio/reactivex/rxjava3/core/Flowable;)Lio/reactivex/rxjava3/core/Flowable;
      19: areturn
}
