Compiled from "DubboRoute.java"
public class org.apache.dubbo.rpc.cluster.router.mesh.rule.virtualservice.DubboRoute {
  private java.lang.String name;

  private java.util.List<org.apache.dubbo.rpc.cluster.router.mesh.rule.virtualservice.match.StringMatch> services;

  private java.util.List<org.apache.dubbo.rpc.cluster.router.mesh.rule.virtualservice.DubboRouteDetail> routedetail;

  public org.apache.dubbo.rpc.cluster.router.mesh.rule.virtualservice.DubboRoute();
    Code:
       0: aload_0
       1: invokespecial #1                  // Method java/lang/Object."<init>":()V
       4: return

  public java.lang.String getName();
    Code:
       0: aload_0
       1: getfield      #2                  // Field name:Ljava/lang/String;
       4: areturn

  public void setName(java.lang.String);
    Code:
       0: aload_0
       1: aload_1
       2: putfield      #2                  // Field name:Ljava/lang/String;
       5: return

  public java.util.List<org.apache.dubbo.rpc.cluster.router.mesh.rule.virtualservice.match.StringMatch> getServices();
    Code:
       0: aload_0
       1: getfield      #3                  // Field services:Ljava/util/List;
       4: areturn

  public void setServices(java.util.List<org.apache.dubbo.rpc.cluster.router.mesh.rule.virtualservice.match.StringMatch>);
    Code:
       0: aload_0
       1: aload_1
       2: putfield      #3                  // Field services:Ljava/util/List;
       5: return

  public java.util.List<org.apache.dubbo.rpc.cluster.router.mesh.rule.virtualservice.DubboRouteDetail> getRoutedetail();
    Code:
       0: aload_0
       1: getfield      #4                  // Field routedetail:Ljava/util/List;
       4: areturn

  public void setRoutedetail(java.util.List<org.apache.dubbo.rpc.cluster.router.mesh.rule.virtualservice.DubboRouteDetail>);
    Code:
       0: aload_0
       1: aload_1
       2: putfield      #4                  // Field routedetail:Ljava/util/List;
       5: return

  public java.lang.String toString();
    Code:
       0: new           #5                  // class java/lang/StringBuilder
       3: dup
       4: invokespecial #6                  // Method java/lang/StringBuilder."<init>":()V
       7: ldc           #7                  // String DubboRoute{name=\'
       9: invokevirtual #8                  // Method java/lang/StringBuilder.append:(Ljava/lang/String;)Ljava/lang/StringBuilder;
      12: aload_0
      13: getfield      #2                  // Field name:Ljava/lang/String;
      16: invokevirtual #8                  // Method java/lang/StringBuilder.append:(Ljava/lang/String;)Ljava/lang/StringBuilder;
      19: bipush        39
      21: invokevirtual #9                  // Method java/lang/StringBuilder.append:(C)Ljava/lang/StringBuilder;
      24: ldc           #10                 // String , services=
      26: invokevirtual #8                  // Method java/lang/StringBuilder.append:(Ljava/lang/String;)Ljava/lang/StringBuilder;
      29: aload_0
      30: getfield      #3                  // Field services:Ljava/util/List;
      33: invokevirtual #11                 // Method java/lang/StringBuilder.append:(Ljava/lang/Object;)Ljava/lang/StringBuilder;
      36: ldc           #12                 // String , routedetail=
      38: invokevirtual #8                  // Method java/lang/StringBuilder.append:(Ljava/lang/String;)Ljava/lang/StringBuilder;
      41: aload_0
      42: getfield      #4                  // Field routedetail:Ljava/util/List;
      45: invokevirtual #11                 // Method java/lang/StringBuilder.append:(Ljava/lang/Object;)Ljava/lang/StringBuilder;
      48: bipush        125
      50: invokevirtual #9                  // Method java/lang/StringBuilder.append:(C)Ljava/lang/StringBuilder;
      53: invokevirtual #13                 // Method java/lang/StringBuilder.toString:()Ljava/lang/String;
      56: areturn
}
