Compiled from "DubboMatchRequest.java"
public class org.apache.dubbo.rpc.cluster.router.mesh.rule.virtualservice.DubboMatchRequest {
  private java.lang.String name;

  private org.apache.dubbo.rpc.cluster.router.mesh.rule.virtualservice.match.DubboMethodMatch method;

  private java.util.Map<java.lang.String, java.lang.String> sourceLabels;

  private org.apache.dubbo.rpc.cluster.router.mesh.rule.virtualservice.match.DubboAttachmentMatch attachments;

  private java.util.Map<java.lang.String, org.apache.dubbo.rpc.cluster.router.mesh.rule.virtualservice.match.StringMatch> headers;

  public org.apache.dubbo.rpc.cluster.router.mesh.rule.virtualservice.DubboMatchRequest();
    Code:
       0: aload_0
       1: invokespecial #1                  // Method java/lang/Object."<init>":()V
       4: return

  public java.lang.String getName();
    Code:
       0: aload_0
       1: getfield      #2                  // Field name:Ljava/lang/String;
       4: areturn

  public void setName(java.lang.String);
    Code:
       0: aload_0
       1: aload_1
       2: putfield      #2                  // Field name:Ljava/lang/String;
       5: return

  public org.apache.dubbo.rpc.cluster.router.mesh.rule.virtualservice.match.DubboMethodMatch getMethod();
    Code:
       0: aload_0
       1: getfield      #3                  // Field method:Lorg/apache/dubbo/rpc/cluster/router/mesh/rule/virtualservice/match/DubboMethodMatch;
       4: areturn

  public void setMethod(org.apache.dubbo.rpc.cluster.router.mesh.rule.virtualservice.match.DubboMethodMatch);
    Code:
       0: aload_0
       1: aload_1
       2: putfield      #3                  // Field method:Lorg/apache/dubbo/rpc/cluster/router/mesh/rule/virtualservice/match/DubboMethodMatch;
       5: return

  public java.util.Map<java.lang.String, java.lang.String> getSourceLabels();
    Code:
       0: aload_0
       1: getfield      #4                  // Field sourceLabels:Ljava/util/Map;
       4: areturn

  public void setSourceLabels(java.util.Map<java.lang.String, java.lang.String>);
    Code:
       0: aload_0
       1: aload_1
       2: putfield      #4                  // Field sourceLabels:Ljava/util/Map;
       5: return

  public org.apache.dubbo.rpc.cluster.router.mesh.rule.virtualservice.match.DubboAttachmentMatch getAttachments();
    Code:
       0: aload_0
       1: getfield      #5                  // Field attachments:Lorg/apache/dubbo/rpc/cluster/router/mesh/rule/virtualservice/match/DubboAttachmentMatch;
       4: areturn

  public void setAttachments(org.apache.dubbo.rpc.cluster.router.mesh.rule.virtualservice.match.DubboAttachmentMatch);
    Code:
       0: aload_0
       1: aload_1
       2: putfield      #5                  // Field attachments:Lorg/apache/dubbo/rpc/cluster/router/mesh/rule/virtualservice/match/DubboAttachmentMatch;
       5: return

  public java.util.Map<java.lang.String, org.apache.dubbo.rpc.cluster.router.mesh.rule.virtualservice.match.StringMatch> getHeaders();
    Code:
       0: aload_0
       1: getfield      #6                  // Field headers:Ljava/util/Map;
       4: areturn

  public void setHeaders(java.util.Map<java.lang.String, org.apache.dubbo.rpc.cluster.router.mesh.rule.virtualservice.match.StringMatch>);
    Code:
       0: aload_0
       1: aload_1
       2: putfield      #6                  // Field headers:Ljava/util/Map;
       5: return

  public java.lang.String toString();
    Code:
       0: new           #7                  // class java/lang/StringBuilder
       3: dup
       4: invokespecial #8                  // Method java/lang/StringBuilder."<init>":()V
       7: ldc           #9                  // String DubboMatchRequest{name=\'
       9: invokevirtual #10                 // Method java/lang/StringBuilder.append:(Ljava/lang/String;)Ljava/lang/StringBuilder;
      12: aload_0
      13: getfield      #2                  // Field name:Ljava/lang/String;
      16: invokevirtual #10                 // Method java/lang/StringBuilder.append:(Ljava/lang/String;)Ljava/lang/StringBuilder;
      19: bipush        39
      21: invokevirtual #11                 // Method java/lang/StringBuilder.append:(C)Ljava/lang/StringBuilder;
      24: ldc           #12                 // String , method=
      26: invokevirtual #10                 // Method java/lang/StringBuilder.append:(Ljava/lang/String;)Ljava/lang/StringBuilder;
      29: aload_0
      30: getfield      #3                  // Field method:Lorg/apache/dubbo/rpc/cluster/router/mesh/rule/virtualservice/match/DubboMethodMatch;
      33: invokevirtual #13                 // Method java/lang/StringBuilder.append:(Ljava/lang/Object;)Ljava/lang/StringBuilder;
      36: ldc           #14                 // String , sourceLabels=
      38: invokevirtual #10                 // Method java/lang/StringBuilder.append:(Ljava/lang/String;)Ljava/lang/StringBuilder;
      41: aload_0
      42: getfield      #4                  // Field sourceLabels:Ljava/util/Map;
      45: invokevirtual #13                 // Method java/lang/StringBuilder.append:(Ljava/lang/Object;)Ljava/lang/StringBuilder;
      48: ldc           #15                 // String , attachments=
      50: invokevirtual #10                 // Method java/lang/StringBuilder.append:(Ljava/lang/String;)Ljava/lang/StringBuilder;
      53: aload_0
      54: getfield      #5                  // Field attachments:Lorg/apache/dubbo/rpc/cluster/router/mesh/rule/virtualservice/match/DubboAttachmentMatch;
      57: invokevirtual #13                 // Method java/lang/StringBuilder.append:(Ljava/lang/Object;)Ljava/lang/StringBuilder;
      60: ldc           #16                 // String , headers=
      62: invokevirtual #10                 // Method java/lang/StringBuilder.append:(Ljava/lang/String;)Ljava/lang/StringBuilder;
      65: aload_0
      66: getfield      #6                  // Field headers:Ljava/util/Map;
      69: invokevirtual #13                 // Method java/lang/StringBuilder.append:(Ljava/lang/Object;)Ljava/lang/StringBuilder;
      72: bipush        125
      74: invokevirtual #11                 // Method java/lang/StringBuilder.append:(C)Ljava/lang/StringBuilder;
      77: invokevirtual #17                 // Method java/lang/StringBuilder.toString:()Ljava/lang/String;
      80: areturn

  public boolean isMatch(org.apache.dubbo.rpc.Invocation, java.util.Map<java.lang.String, java.lang.String>, java.util.Set<org.apache.dubbo.rpc.cluster.router.mesh.util.TracingContextProvider>);
    Code:
       0: aload_0
       1: invokevirtual #18                 // Method getMethod:()Lorg/apache/dubbo/rpc/cluster/router/mesh/rule/virtualservice/match/DubboMethodMatch;
       4: ifnull        20
       7: aload_0
       8: invokevirtual #18                 // Method getMethod:()Lorg/apache/dubbo/rpc/cluster/router/mesh/rule/virtualservice/match/DubboMethodMatch;
      11: aload_1
      12: invokevirtual #19                 // Method org/apache/dubbo/rpc/cluster/router/mesh/rule/virtualservice/match/DubboMethodMatch.isMatch:(Lorg/apache/dubbo/rpc/Invocation;)Z
      15: ifne          20
      18: iconst_0
      19: ireturn
      20: aload_0
      21: invokevirtual #20                 // Method getSourceLabels:()Ljava/util/Map;
      24: ifnull        106
      27: aload_0
      28: invokevirtual #20                 // Method getSourceLabels:()Ljava/util/Map;
      31: invokeinterface #21,  1           // InterfaceMethod java/util/Map.entrySet:()Ljava/util/Set;
      36: invokeinterface #22,  1           // InterfaceMethod java/util/Set.iterator:()Ljava/util/Iterator;
      41: astore        4
      43: aload         4
      45: invokeinterface #23,  1           // InterfaceMethod java/util/Iterator.hasNext:()Z
      50: ifeq          106
      53: aload         4
      55: invokeinterface #24,  1           // InterfaceMethod java/util/Iterator.next:()Ljava/lang/Object;
      60: checkcast     #25                 // class java/util/Map$Entry
      63: astore        5
      65: aload_2
      66: aload         5
      68: invokeinterface #26,  1           // InterfaceMethod java/util/Map$Entry.getKey:()Ljava/lang/Object;
      73: invokeinterface #27,  2           // InterfaceMethod java/util/Map.get:(Ljava/lang/Object;)Ljava/lang/Object;
      78: checkcast     #28                 // class java/lang/String
      81: astore        6
      83: aload         5
      85: invokeinterface #29,  1           // InterfaceMethod java/util/Map$Entry.getValue:()Ljava/lang/Object;
      90: checkcast     #28                 // class java/lang/String
      93: aload         6
      95: invokevirtual #30                 // Method java/lang/String.equals:(Ljava/lang/Object;)Z
      98: ifne          103
     101: iconst_0
     102: ireturn
     103: goto          43
     106: aload_0
     107: invokevirtual #31                 // Method getAttachments:()Lorg/apache/dubbo/rpc/cluster/router/mesh/rule/virtualservice/match/DubboAttachmentMatch;
     110: ifnull        123
     113: aload_0
     114: invokevirtual #31                 // Method getAttachments:()Lorg/apache/dubbo/rpc/cluster/router/mesh/rule/virtualservice/match/DubboAttachmentMatch;
     117: aload_1
     118: aload_3
     119: invokevirtual #32                 // Method org/apache/dubbo/rpc/cluster/router/mesh/rule/virtualservice/match/DubboAttachmentMatch.isMatch:(Lorg/apache/dubbo/rpc/Invocation;Ljava/util/Set;)Z
     122: ireturn
     123: iconst_1
     124: ireturn
}
