Compiled from "VirtualServiceRule.java"
public class org.apache.dubbo.rpc.cluster.router.mesh.rule.virtualservice.VirtualServiceRule extends org.apache.dubbo.rpc.cluster.router.mesh.rule.BaseRule {
  private org.apache.dubbo.rpc.cluster.router.mesh.rule.virtualservice.VirtualServiceSpec spec;

  public org.apache.dubbo.rpc.cluster.router.mesh.rule.virtualservice.VirtualServiceRule();
    Code:
       0: aload_0
       1: invokespecial #1                  // Method org/apache/dubbo/rpc/cluster/router/mesh/rule/BaseRule."<init>":()V
       4: return

  public org.apache.dubbo.rpc.cluster.router.mesh.rule.virtualservice.VirtualServiceSpec getSpec();
    Code:
       0: aload_0
       1: getfield      #2                  // Field spec:Lorg/apache/dubbo/rpc/cluster/router/mesh/rule/virtualservice/VirtualServiceSpec;
       4: areturn

  public void setSpec(org.apache.dubbo.rpc.cluster.router.mesh.rule.virtualservice.VirtualServiceSpec);
    Code:
       0: aload_0
       1: aload_1
       2: putfield      #2                  // Field spec:Lorg/apache/dubbo/rpc/cluster/router/mesh/rule/virtualservice/VirtualServiceSpec;
       5: return

  public java.lang.String toString();
    Code:
       0: new           #3                  // class java/lang/StringBuilder
       3: dup
       4: invokespecial #4                  // Method java/lang/StringBuilder."<init>":()V
       7: ldc           #5                  // String VirtualServiceRule{base=
       9: invokevirtual #6                  // Method java/lang/StringBuilder.append:(Ljava/lang/String;)Ljava/lang/StringBuilder;
      12: aload_0
      13: invokespecial #7                  // Method org/apache/dubbo/rpc/cluster/router/mesh/rule/BaseRule.toString:()Ljava/lang/String;
      16: invokevirtual #6                  // Method java/lang/StringBuilder.append:(Ljava/lang/String;)Ljava/lang/StringBuilder;
      19: ldc           #8                  // String , spec=
      21: invokevirtual #6                  // Method java/lang/StringBuilder.append:(Ljava/lang/String;)Ljava/lang/StringBuilder;
      24: aload_0
      25: getfield      #2                  // Field spec:Lorg/apache/dubbo/rpc/cluster/router/mesh/rule/virtualservice/VirtualServiceSpec;
      28: invokevirtual #9                  // Method java/lang/StringBuilder.append:(Ljava/lang/Object;)Ljava/lang/StringBuilder;
      31: bipush        125
      33: invokevirtual #10                 // Method java/lang/StringBuilder.append:(C)Ljava/lang/StringBuilder;
      36: invokevirtual #11                 // Method java/lang/StringBuilder.toString:()Ljava/lang/String;
      39: areturn
}
