Compiled from "VirtualServiceSpec.java"
public class org.apache.dubbo.rpc.cluster.router.mesh.rule.virtualservice.VirtualServiceSpec {
  private java.util.List<java.lang.String> hosts;

  private java.util.List<org.apache.dubbo.rpc.cluster.router.mesh.rule.virtualservice.DubboRoute> dubbo;

  public org.apache.dubbo.rpc.cluster.router.mesh.rule.virtualservice.VirtualServiceSpec();
    Code:
       0: aload_0
       1: invokespecial #1                  // Method java/lang/Object."<init>":()V
       4: return

  public java.util.List<java.lang.String> getHosts();
    Code:
       0: aload_0
       1: getfield      #2                  // Field hosts:Ljava/util/List;
       4: areturn

  public void setHosts(java.util.List<java.lang.String>);
    Code:
       0: aload_0
       1: aload_1
       2: putfield      #2                  // Field hosts:Ljava/util/List;
       5: return

  public java.util.List<org.apache.dubbo.rpc.cluster.router.mesh.rule.virtualservice.DubboRoute> getDubbo();
    Code:
       0: aload_0
       1: getfield      #3                  // Field dubbo:Ljava/util/List;
       4: areturn

  public void setDubbo(java.util.List<org.apache.dubbo.rpc.cluster.router.mesh.rule.virtualservice.DubboRoute>);
    Code:
       0: aload_0
       1: aload_1
       2: putfield      #3                  // Field dubbo:Ljava/util/List;
       5: return

  public java.lang.String toString();
    Code:
       0: new           #4                  // class java/lang/StringBuilder
       3: dup
       4: invokespecial #5                  // Method java/lang/StringBuilder."<init>":()V
       7: ldc           #6                  // String VirtualServiceSpec{hosts=
       9: invokevirtual #7                  // Method java/lang/StringBuilder.append:(Ljava/lang/String;)Ljava/lang/StringBuilder;
      12: aload_0
      13: getfield      #2                  // Field hosts:Ljava/util/List;
      16: invokevirtual #8                  // Method java/lang/StringBuilder.append:(Ljava/lang/Object;)Ljava/lang/StringBuilder;
      19: ldc           #9                  // String , dubbo=
      21: invokevirtual #7                  // Method java/lang/StringBuilder.append:(Ljava/lang/String;)Ljava/lang/StringBuilder;
      24: aload_0
      25: getfield      #3                  // Field dubbo:Ljava/util/List;
      28: invokevirtual #8                  // Method java/lang/StringBuilder.append:(Ljava/lang/Object;)Ljava/lang/StringBuilder;
      31: bipush        125
      33: invokevirtual #10                 // Method java/lang/StringBuilder.append:(C)Ljava/lang/StringBuilder;
      36: invokevirtual #11                 // Method java/lang/StringBuilder.toString:()Ljava/lang/String;
      39: areturn
}
