Compiled from "DelegateProviderMetaDataInvoker.java"
public class org.apache.dubbo.config.invoker.DelegateProviderMetaDataInvoker<T> implements org.apache.dubbo.rpc.Invoker {
  protected final org.apache.dubbo.rpc.Invoker<T> invoker;

  private final org.apache.dubbo.config.ServiceConfig<?> metadata;

  public org.apache.dubbo.config.invoker.DelegateProviderMetaDataInvoker(org.apache.dubbo.rpc.Invoker<T>, org.apache.dubbo.config.ServiceConfig<?>);
    Code:
       0: aload_0
       1: invokespecial #1                  // Method java/lang/Object."<init>":()V
       4: aload_0
       5: aload_1
       6: putfield      #2                  // Field invoker:Lorg/apache/dubbo/rpc/Invoker;
       9: aload_0
      10: aload_2
      11: putfield      #3                  // Field metadata:Lorg/apache/dubbo/config/ServiceConfig;
      14: return

  public java.lang.Class<T> getInterface();
    Code:
       0: aload_0
       1: getfield      #2                  // Field invoker:Lorg/apache/dubbo/rpc/Invoker;
       4: invokeinterface #4,  1            // InterfaceMethod org/apache/dubbo/rpc/Invoker.getInterface:()Ljava/lang/Class;
       9: areturn

  public org.apache.dubbo.common.URL getUrl();
    Code:
       0: aload_0
       1: getfield      #2                  // Field invoker:Lorg/apache/dubbo/rpc/Invoker;
       4: invokeinterface #5,  1            // InterfaceMethod org/apache/dubbo/rpc/Invoker.getUrl:()Lorg/apache/dubbo/common/URL;
       9: areturn

  public boolean isAvailable();
    Code:
       0: aload_0
       1: getfield      #2                  // Field invoker:Lorg/apache/dubbo/rpc/Invoker;
       4: invokeinterface #6,  1            // InterfaceMethod org/apache/dubbo/rpc/Invoker.isAvailable:()Z
       9: ireturn

  public org.apache.dubbo.rpc.Result invoke(org.apache.dubbo.rpc.Invocation) throws org.apache.dubbo.rpc.RpcException;
    Code:
       0: aload_0
       1: getfield      #2                  // Field invoker:Lorg/apache/dubbo/rpc/Invoker;
       4: aload_1
       5: invokeinterface #7,  2            // InterfaceMethod org/apache/dubbo/rpc/Invoker.invoke:(Lorg/apache/dubbo/rpc/Invocation;)Lorg/apache/dubbo/rpc/Result;
      10: areturn

  public void destroy();
    Code:
       0: aload_0
       1: getfield      #2                  // Field invoker:Lorg/apache/dubbo/rpc/Invoker;
       4: invokeinterface #8,  1            // InterfaceMethod org/apache/dubbo/rpc/Invoker.destroy:()V
       9: return

  public org.apache.dubbo.config.ServiceConfig<?> getMetadata();
    Code:
       0: aload_0
       1: getfield      #3                  // Field metadata:Lorg/apache/dubbo/config/ServiceConfig;
       4: areturn
}
