Compiled from "DoubleArrayMerger.java"
public class org.apache.dubbo.rpc.cluster.merger.DoubleArrayMerger implements org.apache.dubbo.rpc.cluster.Merger<double[]> {
  public org.apache.dubbo.rpc.cluster.merger.DoubleArrayMerger();
    Code:
       0: aload_0
       1: invokespecial #1                  // Method java/lang/Object."<init>":()V
       4: return

  public double[] merge(double[]...);
    Code:
       0: aload_1
       1: invokestatic  #2                  // Method org/apache/dubbo/common/utils/ArrayUtils.isEmpty:([Ljava/lang/Object;)Z
       4: ifeq          11
       7: iconst_0
       8: newarray       double
      10: areturn
      11: aload_1
      12: invokestatic  #3                  // Method java/util/Arrays.stream:([Ljava/lang/Object;)Ljava/util/stream/Stream;
      15: invokedynamic #4,  0              // InvokeDynamic #0:test:()Ljava/util/function/Predicate;
      20: invokeinterface #5,  2            // InterfaceMethod java/util/stream/Stream.filter:(Ljava/util/function/Predicate;)Ljava/util/stream/Stream;
      25: invokedynamic #6,  0              // InvokeDynamic #1:apply:()Ljava/util/function/Function;
      30: invokeinterface #7,  2            // InterfaceMethod java/util/stream/Stream.flatMapToDouble:(Ljava/util/function/Function;)Ljava/util/stream/DoubleStream;
      35: invokeinterface #8,  1            // InterfaceMethod java/util/stream/DoubleStream.toArray:()[D
      40: areturn

  public java.lang.Object merge(java.lang.Object[]);
    Code:
       0: aload_0
       1: aload_1
       2: checkcast     #9                  // class "[[D"
       5: invokevirtual #10                 // Method merge:([[D)[D
       8: areturn
}
