Compiled from "ListMerger.java"
public class org.apache.dubbo.rpc.cluster.merger.ListMerger implements org.apache.dubbo.rpc.cluster.Merger<java.util.List<?>> {
  public org.apache.dubbo.rpc.cluster.merger.ListMerger();
    Code:
       0: aload_0
       1: invokespecial #1                  // Method java/lang/Object."<init>":()V
       4: return

  public java.util.List<java.lang.Object> merge(java.util.List<?>...);
    Code:
       0: aload_1
       1: invokestatic  #2                  // Method org/apache/dubbo/common/utils/ArrayUtils.isEmpty:([Ljava/lang/Object;)Z
       4: ifeq          11
       7: invokestatic  #3                  // Method java/util/Collections.emptyList:()Ljava/util/List;
      10: areturn
      11: aload_1
      12: invokestatic  #4                  // InterfaceMethod java/util/stream/Stream.of:([Ljava/lang/Object;)Ljava/util/stream/Stream;
      15: invokedynamic #5,  0              // InvokeDynamic #0:test:()Ljava/util/function/Predicate;
      20: invokeinterface #6,  2            // InterfaceMethod java/util/stream/Stream.filter:(Ljava/util/function/Predicate;)Ljava/util/stream/Stream;
      25: invokedynamic #7,  0              // InvokeDynamic #1:apply:()Ljava/util/function/Function;
      30: invokeinterface #8,  2            // InterfaceMethod java/util/stream/Stream.flatMap:(Ljava/util/function/Function;)Ljava/util/stream/Stream;
      35: invokestatic  #9                  // Method java/util/stream/Collectors.toList:()Ljava/util/stream/Collector;
      38: invokeinterface #10,  2           // InterfaceMethod java/util/stream/Stream.collect:(Ljava/util/stream/Collector;)Ljava/lang/Object;
      43: checkcast     #11                 // class java/util/List
      46: areturn

  public java.lang.Object merge(java.lang.Object[]);
    Code:
       0: aload_0
       1: aload_1
       2: checkcast     #12                 // class "[Ljava/util/List;"
       5: invokevirtual #13                 // Method merge:([Ljava/util/List;)Ljava/util/List;
       8: areturn
}
