Compiled from "MergerFactory.java"
public class org.apache.dubbo.rpc.cluster.merger.MergerFactory implements org.apache.dubbo.rpc.model.ScopeModelAware {
  private static final org.apache.dubbo.common.logger.ErrorTypeAwareLogger logger;

  private java.util.concurrent.ConcurrentMap<java.lang.Class<?>, org.apache.dubbo.rpc.cluster.Merger<?>> MERGER_CACHE;

  private org.apache.dubbo.rpc.model.ScopeModel scopeModel;

  public org.apache.dubbo.rpc.cluster.merger.MergerFactory();
    Code:
       0: aload_0
       1: invokespecial #2                  // Method java/lang/Object."<init>":()V
       4: aload_0
       5: new           #3                  // class java/util/concurrent/ConcurrentHashMap
       8: dup
       9: invokespecial #4                  // Method java/util/concurrent/ConcurrentHashMap."<init>":()V
      12: putfield      #5                  // Field MERGER_CACHE:Ljava/util/concurrent/ConcurrentMap;
      15: return

  public void setScopeModel(org.apache.dubbo.rpc.model.ScopeModel);
    Code:
       0: aload_0
       1: aload_1
       2: putfield      #6                  // Field scopeModel:Lorg/apache/dubbo/rpc/model/ScopeModel;
       5: return

  public <T> org.apache.dubbo.rpc.cluster.Merger<T> getMerger(java.lang.Class<T>);
    Code:
       0: aload_1
       1: ifnonnull     14
       4: new           #7                  // class java/lang/IllegalArgumentException
       7: dup
       8: ldc           #8                  // String returnType is null
      10: invokespecial #9                  // Method java/lang/IllegalArgumentException."<init>":(Ljava/lang/String;)V
      13: athrow
      14: aload_0
      15: getfield      #5                  // Field MERGER_CACHE:Ljava/util/concurrent/ConcurrentMap;
      18: invokestatic  #10                 // Method org/apache/dubbo/common/utils/CollectionUtils.isEmptyMap:(Ljava/util/Map;)Z
      21: ifeq          28
      24: aload_0
      25: invokespecial #11                 // Method loadMergers:()V
      28: aload_0
      29: getfield      #5                  // Field MERGER_CACHE:Ljava/util/concurrent/ConcurrentMap;
      32: aload_1
      33: invokeinterface #12,  2           // InterfaceMethod java/util/concurrent/ConcurrentMap.get:(Ljava/lang/Object;)Ljava/lang/Object;
      38: checkcast     #13                 // class org/apache/dubbo/rpc/cluster/Merger
      41: astore_2
      42: aload_2
      43: ifnonnull     57
      46: aload_1
      47: invokevirtual #14                 // Method java/lang/Class.isArray:()Z
      50: ifeq          57
      53: getstatic     #15                 // Field org/apache/dubbo/rpc/cluster/merger/ArrayMerger.INSTANCE:Lorg/apache/dubbo/rpc/cluster/merger/ArrayMerger;
      56: astore_2
      57: aload_2
      58: areturn

  private void loadMergers();
    Code:
       0: aload_0
       1: getfield      #6                  // Field scopeModel:Lorg/apache/dubbo/rpc/model/ScopeModel;
       4: ldc           #13                 // class org/apache/dubbo/rpc/cluster/Merger
       6: invokevirtual #16                 // Method org/apache/dubbo/rpc/model/ScopeModel.getExtensionLoader:(Ljava/lang/Class;)Lorg/apache/dubbo/common/extension/ExtensionLoader;
       9: invokevirtual #17                 // Method org/apache/dubbo/common/extension/ExtensionLoader.getSupportedExtensions:()Ljava/util/Set;
      12: astore_1
      13: aload_1
      14: invokeinterface #18,  1           // InterfaceMethod java/util/Set.iterator:()Ljava/util/Iterator;
      19: astore_2
      20: aload_2
      21: invokeinterface #19,  1           // InterfaceMethod java/util/Iterator.hasNext:()Z
      26: ifeq          133
      29: aload_2
      30: invokeinterface #20,  1           // InterfaceMethod java/util/Iterator.next:()Ljava/lang/Object;
      35: checkcast     #21                 // class java/lang/String
      38: astore_3
      39: aload_0
      40: getfield      #6                  // Field scopeModel:Lorg/apache/dubbo/rpc/model/ScopeModel;
      43: ldc           #13                 // class org/apache/dubbo/rpc/cluster/Merger
      45: invokevirtual #16                 // Method org/apache/dubbo/rpc/model/ScopeModel.getExtensionLoader:(Ljava/lang/Class;)Lorg/apache/dubbo/common/extension/ExtensionLoader;
      48: aload_3
      49: invokevirtual #22                 // Method org/apache/dubbo/common/extension/ExtensionLoader.getExtension:(Ljava/lang/String;)Ljava/lang/Object;
      52: checkcast     #13                 // class org/apache/dubbo/rpc/cluster/Merger
      55: astore        4
      57: aload_0
      58: aload         4
      60: invokevirtual #23                 // Method java/lang/Object.getClass:()Ljava/lang/Class;
      63: invokespecial #24                 // Method getActualTypeArgument:(Ljava/lang/Class;)Ljava/lang/Class;
      66: astore        5
      68: aload         5
      70: ifnonnull     116
      73: getstatic     #25                 // Field logger:Lorg/apache/dubbo/common/logger/ErrorTypeAwareLogger;
      76: ldc           #26                 // String 2-4
      78: ldc           #27                 // String load merger config failed
      80: ldc           #28                 // String
      82: new           #29                 // class java/lang/StringBuilder
      85: dup
      86: invokespecial #30                 // Method java/lang/StringBuilder."<init>":()V
      89: ldc           #31                 // String Failed to get actual type argument from merger
      91: invokevirtual #32                 // Method java/lang/StringBuilder.append:(Ljava/lang/String;)Ljava/lang/StringBuilder;
      94: aload         4
      96: invokevirtual #23                 // Method java/lang/Object.getClass:()Ljava/lang/Class;
      99: invokevirtual #33                 // Method java/lang/Class.getName:()Ljava/lang/String;
     102: invokevirtual #32                 // Method java/lang/StringBuilder.append:(Ljava/lang/String;)Ljava/lang/StringBuilder;
     105: invokevirtual #34                 // Method java/lang/StringBuilder.toString:()Ljava/lang/String;
     108: invokeinterface #35,  5           // InterfaceMethod org/apache/dubbo/common/logger/ErrorTypeAwareLogger.warn:(Ljava/lang/String;Ljava/lang/String;Ljava/lang/String;Ljava/lang/String;)V
     113: goto          20
     116: aload_0
     117: getfield      #5                  // Field MERGER_CACHE:Ljava/util/concurrent/ConcurrentMap;
     120: aload         5
     122: aload         4
     124: invokeinterface #36,  3           // InterfaceMethod java/util/concurrent/ConcurrentMap.putIfAbsent:(Ljava/lang/Object;Ljava/lang/Object;)Ljava/lang/Object;
     129: pop
     130: goto          20
     133: return

  private java.lang.Class<?> getActualTypeArgument(java.lang.Class<? extends org.apache.dubbo.rpc.cluster.Merger>);
    Code:
       0: aload_1
       1: astore_2
       2: aload_2
       3: ldc           #37                 // class java/lang/Object
       5: if_acmpeq     95
       8: aload_2
       9: invokevirtual #38                 // Method java/lang/Class.getGenericInterfaces:()[Ljava/lang/reflect/Type;
      12: astore_3
      13: aload_3
      14: astore        5
      16: aload         5
      18: arraylength
      19: istore        6
      21: iconst_0
      22: istore        7
      24: iload         7
      26: iload         6
      28: if_icmpge     87
      31: aload         5
      33: iload         7
      35: aaload
      36: astore        8
      38: aload         8
      40: instanceof    #39                 // class java/lang/reflect/ParameterizedType
      43: ifeq          81
      46: aload         8
      48: checkcast     #39                 // class java/lang/reflect/ParameterizedType
      51: dup
      52: astore        4
      54: invokeinterface #40,  1           // InterfaceMethod java/lang/reflect/ParameterizedType.getRawType:()Ljava/lang/reflect/Type;
      59: ldc           #13                 // class org/apache/dubbo/rpc/cluster/Merger
      61: if_acmpne     81
      64: aload         4
      66: invokeinterface #41,  1           // InterfaceMethod java/lang/reflect/ParameterizedType.getActualTypeArguments:()[Ljava/lang/reflect/Type;
      71: iconst_0
      72: aaload
      73: astore        9
      75: aload         9
      77: invokestatic  #42                 // InterfaceMethod org/apache/dubbo/common/utils/TypeUtils.getRawClass:(Ljava/lang/reflect/Type;)Ljava/lang/Class;
      80: areturn
      81: iinc          7, 1
      84: goto          24
      87: aload_2
      88: invokevirtual #43                 // Method java/lang/Class.getSuperclass:()Ljava/lang/Class;
      91: astore_2
      92: goto          2
      95: aconst_null
      96: areturn

  static {};
    Code:
       0: ldc           #44                 // class org/apache/dubbo/rpc/cluster/merger/MergerFactory
       2: invokestatic  #45                 // Method org/apache/dubbo/common/logger/LoggerFactory.getErrorTypeAwareLogger:(Ljava/lang/Class;)Lorg/apache/dubbo/common/logger/ErrorTypeAwareLogger;
       5: putstatic     #25                 // Field logger:Lorg/apache/dubbo/common/logger/ErrorTypeAwareLogger;
       8: return
}
