Compiled from "SetMerger.java"
public class org.apache.dubbo.rpc.cluster.merger.SetMerger implements org.apache.dubbo.rpc.cluster.Merger<java.util.Set<?>> {
  public org.apache.dubbo.rpc.cluster.merger.SetMerger();
    Code:
       0: aload_0
       1: invokespecial #1                  // Method java/lang/Object."<init>":()V
       4: return

  public java.util.Set<java.lang.Object> merge(java.util.Set<?>...);
    Code:
       0: aload_1
       1: invokestatic  #2                  // Method org/apache/dubbo/common/utils/ArrayUtils.isEmpty:([Ljava/lang/Object;)Z
       4: ifeq          11
       7: invokestatic  #3                  // Method java/util/Collections.emptySet:()Ljava/util/Set;
      10: areturn
      11: new           #4                  // class java/util/HashSet
      14: dup
      15: invokespecial #5                  // Method java/util/HashSet."<init>":()V
      18: astore_2
      19: aload_1
      20: invokestatic  #6                  // InterfaceMethod java/util/stream/Stream.of:([Ljava/lang/Object;)Ljava/util/stream/Stream;
      23: invokedynamic #7,  0              // InvokeDynamic #0:test:()Ljava/util/function/Predicate;
      28: invokeinterface #8,  2            // InterfaceMethod java/util/stream/Stream.filter:(Ljava/util/function/Predicate;)Ljava/util/stream/Stream;
      33: aload_2
      34: dup
      35: invokevirtual #9                  // Method java/lang/Object.getClass:()Ljava/lang/Class;
      38: pop
      39: invokedynamic #10,  0             // InvokeDynamic #1:accept:(Ljava/util/Set;)Ljava/util/function/Consumer;
      44: invokeinterface #11,  2           // InterfaceMethod java/util/stream/Stream.forEach:(Ljava/util/function/Consumer;)V
      49: aload_2
      50: areturn

  public java.lang.Object merge(java.lang.Object[]);
    Code:
       0: aload_0
       1: aload_1
       2: checkcast     #12                 // class "[Ljava/util/Set;"
       5: invokevirtual #13                 // Method merge:([Ljava/util/Set;)Ljava/util/Set;
       8: areturn
}
