Compiled from "ArrayCompositeSubscription.java"
public final class io.reactivex.rxjava3.internal.subscriptions.ArrayCompositeSubscription extends java.util.concurrent.atomic.AtomicReferenceArray<org.reactivestreams.Subscription> implements io.reactivex.rxjava3.disposables.Disposable {
  private static final long serialVersionUID;

  public io.reactivex.rxjava3.internal.subscriptions.ArrayCompositeSubscription(int);
    Code:
       0: aload_0
       1: iload_1
       2: invokespecial #1                  // Method java/util/concurrent/atomic/AtomicReferenceArray."<init>":(I)V
       5: return

  public boolean setResource(int, org.reactivestreams.Subscription);
    Code:
       0: aload_0
       1: iload_1
       2: invokevirtual #2                  // Method get:(I)Ljava/lang/Object;
       5: checkcast     #3                  // class org/reactivestreams/Subscription
       8: astore_3
       9: aload_3
      10: getstatic     #4                  // Field io/reactivex/rxjava3/internal/subscriptions/SubscriptionHelper.CANCELLED:Lio/reactivex/rxjava3/internal/subscriptions/SubscriptionHelper;
      13: if_acmpne     28
      16: aload_2
      17: ifnull        26
      20: aload_2
      21: invokeinterface #5,  1            // InterfaceMethod org/reactivestreams/Subscription.cancel:()V
      26: iconst_0
      27: ireturn
      28: aload_0
      29: iload_1
      30: aload_3
      31: aload_2
      32: invokevirtual #6                  // Method compareAndSet:(ILjava/lang/Object;Ljava/lang/Object;)Z
      35: ifeq          50
      38: aload_3
      39: ifnull        48
      42: aload_3
      43: invokeinterface #5,  1            // InterfaceMethod org/reactivestreams/Subscription.cancel:()V
      48: iconst_1
      49: ireturn
      50: goto          0

  public org.reactivestreams.Subscription replaceResource(int, org.reactivestreams.Subscription);
    Code:
       0: aload_0
       1: iload_1
       2: invokevirtual #2                  // Method get:(I)Ljava/lang/Object;
       5: checkcast     #3                  // class org/reactivestreams/Subscription
       8: astore_3
       9: aload_3
      10: getstatic     #4                  // Field io/reactivex/rxjava3/internal/subscriptions/SubscriptionHelper.CANCELLED:Lio/reactivex/rxjava3/internal/subscriptions/SubscriptionHelper;
      13: if_acmpne     28
      16: aload_2
      17: ifnull        26
      20: aload_2
      21: invokeinterface #5,  1            // InterfaceMethod org/reactivestreams/Subscription.cancel:()V
      26: aconst_null
      27: areturn
      28: aload_0
      29: iload_1
      30: aload_3
      31: aload_2
      32: invokevirtual #6                  // Method compareAndSet:(ILjava/lang/Object;Ljava/lang/Object;)Z
      35: ifeq          40
      38: aload_3
      39: areturn
      40: goto          0

  public void dispose();
    Code:
       0: aload_0
       1: iconst_0
       2: invokevirtual #2                  // Method get:(I)Ljava/lang/Object;
       5: getstatic     #4                  // Field io/reactivex/rxjava3/internal/subscriptions/SubscriptionHelper.CANCELLED:Lio/reactivex/rxjava3/internal/subscriptions/SubscriptionHelper;
       8: if_acmpeq     74
      11: aload_0
      12: invokevirtual #7                  // Method length:()I
      15: istore_1
      16: iconst_0
      17: istore_2
      18: iload_2
      19: iload_1
      20: if_icmpge     74
      23: aload_0
      24: iload_2
      25: invokevirtual #2                  // Method get:(I)Ljava/lang/Object;
      28: checkcast     #3                  // class org/reactivestreams/Subscription
      31: astore_3
      32: aload_3
      33: getstatic     #4                  // Field io/reactivex/rxjava3/internal/subscriptions/SubscriptionHelper.CANCELLED:Lio/reactivex/rxjava3/internal/subscriptions/SubscriptionHelper;
      36: if_acmpeq     68
      39: aload_0
      40: iload_2
      41: getstatic     #4                  // Field io/reactivex/rxjava3/internal/subscriptions/SubscriptionHelper.CANCELLED:Lio/reactivex/rxjava3/internal/subscriptions/SubscriptionHelper;
      44: invokevirtual #8                  // Method getAndSet:(ILjava/lang/Object;)Ljava/lang/Object;
      47: checkcast     #3                  // class org/reactivestreams/Subscription
      50: astore_3
      51: aload_3
      52: getstatic     #4                  // Field io/reactivex/rxjava3/internal/subscriptions/SubscriptionHelper.CANCELLED:Lio/reactivex/rxjava3/internal/subscriptions/SubscriptionHelper;
      55: if_acmpeq     68
      58: aload_3
      59: ifnull        68
      62: aload_3
      63: invokeinterface #5,  1            // InterfaceMethod org/reactivestreams/Subscription.cancel:()V
      68: iinc          2, 1
      71: goto          18
      74: return

  public boolean isDisposed();
    Code:
       0: aload_0
       1: iconst_0
       2: invokevirtual #2                  // Method get:(I)Ljava/lang/Object;
       5: getstatic     #4                  // Field io/reactivex/rxjava3/internal/subscriptions/SubscriptionHelper.CANCELLED:Lio/reactivex/rxjava3/internal/subscriptions/SubscriptionHelper;
       8: if_acmpne     15
      11: iconst_1
      12: goto          16
      15: iconst_0
      16: ireturn
}
