Compiled from "BooleanSubscription.java"
public final class io.reactivex.rxjava3.internal.subscriptions.BooleanSubscription extends java.util.concurrent.atomic.AtomicBoolean implements org.reactivestreams.Subscription {
  private static final long serialVersionUID;

  public io.reactivex.rxjava3.internal.subscriptions.BooleanSubscription();
    Code:
       0: aload_0
       1: invokespecial #1                  // Method java/util/concurrent/atomic/AtomicBoolean."<init>":()V
       4: return

  public void request(long);
    Code:
       0: lload_1
       1: invokestatic  #2                  // Method io/reactivex/rxjava3/internal/subscriptions/SubscriptionHelper.validate:(J)Z
       4: pop
       5: return

  public void cancel();
    Code:
       0: aload_0
       1: iconst_1
       2: invokevirtual #3                  // Method lazySet:(Z)V
       5: return

  public boolean isCancelled();
    Code:
       0: aload_0
       1: invokevirtual #4                  // Method get:()Z
       4: ireturn

  public java.lang.String toString();
    Code:
       0: new           #5                  // class java/lang/StringBuilder
       3: dup
       4: invokespecial #6                  // Method java/lang/StringBuilder."<init>":()V
       7: ldc           #7                  // String BooleanSubscription(cancelled=
       9: invokevirtual #8                  // Method java/lang/StringBuilder.append:(Ljava/lang/String;)Ljava/lang/StringBuilder;
      12: aload_0
      13: invokevirtual #4                  // Method get:()Z
      16: invokevirtual #9                  // Method java/lang/StringBuilder.append:(Z)Ljava/lang/StringBuilder;
      19: ldc           #10                 // String )
      21: invokevirtual #8                  // Method java/lang/StringBuilder.append:(Ljava/lang/String;)Ljava/lang/StringBuilder;
      24: invokevirtual #11                 // Method java/lang/StringBuilder.toString:()Ljava/lang/String;
      27: areturn
}
