Compiled from "DeferredScalarSubscription.java"
public class io.reactivex.rxjava3.internal.subscriptions.DeferredScalarSubscription<T> extends io.reactivex.rxjava3.internal.subscriptions.BasicIntQueueSubscription<T> {
  private static final long serialVersionUID;

  protected final org.reactivestreams.Subscriber<? super T> downstream;

  protected T value;

  static final int NO_REQUEST_NO_VALUE;

  static final int NO_REQUEST_HAS_VALUE;

  static final int HAS_REQUEST_NO_VALUE;

  static final int HAS_REQUEST_HAS_VALUE;

  static final int CANCELLED;

  static final int FUSED_EMPTY;

  static final int FUSED_READY;

  static final int FUSED_CONSUMED;

  public io.reactivex.rxjava3.internal.subscriptions.DeferredScalarSubscription(org.reactivestreams.Subscriber<? super T>);
    Code:
       0: aload_0
       1: invokespecial #1                  // Method io/reactivex/rxjava3/internal/subscriptions/BasicIntQueueSubscription."<init>":()V
       4: aload_0
       5: aload_1
       6: putfield      #2                  // Field downstream:Lorg/reactivestreams/Subscriber;
       9: return

  public final void request(long);
    Code:
       0: lload_1
       1: invokestatic  #3                  // Method io/reactivex/rxjava3/internal/subscriptions/SubscriptionHelper.validate:(J)Z
       4: ifeq          94
       7: aload_0
       8: invokevirtual #4                  // Method get:()I
      11: istore_3
      12: iload_3
      13: bipush        -2
      15: iand
      16: ifeq          20
      19: return
      20: iload_3
      21: iconst_1
      22: if_icmpne     81
      25: aload_0
      26: iconst_1
      27: iconst_3
      28: invokevirtual #6                  // Method compareAndSet:(II)Z
      31: ifeq          80
      34: aload_0
      35: getfield      #7                  // Field value:Ljava/lang/Object;
      38: astore        4
      40: aload         4
      42: ifnull        80
      45: aload_0
      46: aconst_null
      47: putfield      #7                  // Field value:Ljava/lang/Object;
      50: aload_0
      51: getfield      #2                  // Field downstream:Lorg/reactivestreams/Subscriber;
      54: astore        5
      56: aload         5
      58: aload         4
      60: invokeinterface #8,  2            // InterfaceMethod org/reactivestreams/Subscriber.onNext:(Ljava/lang/Object;)V
      65: aload_0
      66: invokevirtual #4                  // Method get:()I
      69: iconst_4
      70: if_icmpeq     80
      73: aload         5
      75: invokeinterface #9,  1            // InterfaceMethod org/reactivestreams/Subscriber.onComplete:()V
      80: return
      81: aload_0
      82: iconst_0
      83: iconst_2
      84: invokevirtual #6                  // Method compareAndSet:(II)Z
      87: ifeq          91
      90: return
      91: goto          7
      94: return

  public final void complete(T);
    Code:
       0: aload_0
       1: invokevirtual #4                  // Method get:()I
       4: istore_2
       5: iload_2
       6: bipush        8
       8: if_icmpne     49
      11: aload_0
      12: aload_1
      13: putfield      #7                  // Field value:Ljava/lang/Object;
      16: aload_0
      17: bipush        16
      19: invokevirtual #10                 // Method lazySet:(I)V
      22: aload_0
      23: getfield      #2                  // Field downstream:Lorg/reactivestreams/Subscriber;
      26: astore_3
      27: aload_3
      28: aconst_null
      29: invokeinterface #8,  2            // InterfaceMethod org/reactivestreams/Subscriber.onNext:(Ljava/lang/Object;)V
      34: aload_0
      35: invokevirtual #4                  // Method get:()I
      38: iconst_4
      39: if_icmpeq     48
      42: aload_3
      43: invokeinterface #9,  1            // InterfaceMethod org/reactivestreams/Subscriber.onComplete:()V
      48: return
      49: iload_2
      50: bipush        -3
      52: iand
      53: ifeq          57
      56: return
      57: iload_2
      58: iconst_2
      59: if_icmpne     94
      62: aload_0
      63: iconst_3
      64: invokevirtual #10                 // Method lazySet:(I)V
      67: aload_0
      68: getfield      #2                  // Field downstream:Lorg/reactivestreams/Subscriber;
      71: astore_3
      72: aload_3
      73: aload_1
      74: invokeinterface #8,  2            // InterfaceMethod org/reactivestreams/Subscriber.onNext:(Ljava/lang/Object;)V
      79: aload_0
      80: invokevirtual #4                  // Method get:()I
      83: iconst_4
      84: if_icmpeq     93
      87: aload_3
      88: invokeinterface #9,  1            // InterfaceMethod org/reactivestreams/Subscriber.onComplete:()V
      93: return
      94: aload_0
      95: aload_1
      96: putfield      #7                  // Field value:Ljava/lang/Object;
      99: aload_0
     100: iconst_0
     101: iconst_1
     102: invokevirtual #6                  // Method compareAndSet:(II)Z
     105: ifeq          109
     108: return
     109: aload_0
     110: invokevirtual #4                  // Method get:()I
     113: istore_2
     114: iload_2
     115: iconst_4
     116: if_icmpne     5
     119: aload_0
     120: aconst_null
     121: putfield      #7                  // Field value:Ljava/lang/Object;
     124: return

  public final int requestFusion(int);
    Code:
       0: iload_1
       1: iconst_2
       2: iand
       3: ifeq          14
       6: aload_0
       7: bipush        8
       9: invokevirtual #10                 // Method lazySet:(I)V
      12: iconst_2
      13: ireturn
      14: iconst_0
      15: ireturn

  public final T poll();
    Code:
       0: aload_0
       1: invokevirtual #4                  // Method get:()I
       4: bipush        16
       6: if_icmpne     27
       9: aload_0
      10: bipush        32
      12: invokevirtual #10                 // Method lazySet:(I)V
      15: aload_0
      16: getfield      #7                  // Field value:Ljava/lang/Object;
      19: astore_1
      20: aload_0
      21: aconst_null
      22: putfield      #7                  // Field value:Ljava/lang/Object;
      25: aload_1
      26: areturn
      27: aconst_null
      28: areturn

  public final boolean isEmpty();
    Code:
       0: aload_0
       1: invokevirtual #4                  // Method get:()I
       4: bipush        16
       6: if_icmpeq     13
       9: iconst_1
      10: goto          14
      13: iconst_0
      14: ireturn

  public final void clear();
    Code:
       0: aload_0
       1: bipush        32
       3: invokevirtual #10                 // Method lazySet:(I)V
       6: aload_0
       7: aconst_null
       8: putfield      #7                  // Field value:Ljava/lang/Object;
      11: return

  public void cancel();
    Code:
       0: aload_0
       1: iconst_4
       2: invokevirtual #12                 // Method set:(I)V
       5: aload_0
       6: aconst_null
       7: putfield      #7                  // Field value:Ljava/lang/Object;
      10: return

  public final boolean isCancelled();
    Code:
       0: aload_0
       1: invokevirtual #4                  // Method get:()I
       4: iconst_4
       5: if_icmpne     12
       8: iconst_1
       9: goto          13
      12: iconst_0
      13: ireturn

  public final boolean tryCancel();
    Code:
       0: aload_0
       1: iconst_4
       2: invokevirtual #13                 // Method getAndSet:(I)I
       5: iconst_4
       6: if_icmpeq     13
       9: iconst_1
      10: goto          14
      13: iconst_0
      14: ireturn
}
