Compiled from "EmptySubscription.java"
public final class io.reactivex.rxjava3.internal.subscriptions.EmptySubscription extends java.lang.Enum<io.reactivex.rxjava3.internal.subscriptions.EmptySubscription> implements io.reactivex.rxjava3.operators.QueueSubscription<java.lang.Object> {
  public static final io.reactivex.rxjava3.internal.subscriptions.EmptySubscription INSTANCE;

  private static final io.reactivex.rxjava3.internal.subscriptions.EmptySubscription[] $VALUES;

  public static io.reactivex.rxjava3.internal.subscriptions.EmptySubscription[] values();
    Code:
       0: getstatic     #1                  // Field $VALUES:[Lio/reactivex/rxjava3/internal/subscriptions/EmptySubscription;
       3: invokevirtual #2                  // Method "[Lio/reactivex/rxjava3/internal/subscriptions/EmptySubscription;".clone:()Ljava/lang/Object;
       6: checkcast     #3                  // class "[Lio/reactivex/rxjava3/internal/subscriptions/EmptySubscription;"
       9: areturn

  public static io.reactivex.rxjava3.internal.subscriptions.EmptySubscription valueOf(java.lang.String);
    Code:
       0: ldc           #4                  // class io/reactivex/rxjava3/internal/subscriptions/EmptySubscription
       2: aload_0
       3: invokestatic  #5                  // Method java/lang/Enum.valueOf:(Ljava/lang/Class;Ljava/lang/String;)Ljava/lang/Enum;
       6: checkcast     #4                  // class io/reactivex/rxjava3/internal/subscriptions/EmptySubscription
       9: areturn

  private io.reactivex.rxjava3.internal.subscriptions.EmptySubscription();
    Code:
       0: aload_0
       1: aload_1
       2: iload_2
       3: invokespecial #6                  // Method java/lang/Enum."<init>":(Ljava/lang/String;I)V
       6: return

  public void request(long);
    Code:
       0: lload_1
       1: invokestatic  #7                  // Method io/reactivex/rxjava3/internal/subscriptions/SubscriptionHelper.validate:(J)Z
       4: pop
       5: return

  public void cancel();
    Code:
       0: return

  public java.lang.String toString();
    Code:
       0: ldc           #8                  // String EmptySubscription
       2: areturn

  public static void error(java.lang.Throwable, org.reactivestreams.Subscriber<?>);
    Code:
       0: aload_1
       1: getstatic     #9                  // Field INSTANCE:Lio/reactivex/rxjava3/internal/subscriptions/EmptySubscription;
       4: invokeinterface #10,  2           // InterfaceMethod org/reactivestreams/Subscriber.onSubscribe:(Lorg/reactivestreams/Subscription;)V
       9: aload_1
      10: aload_0
      11: invokeinterface #11,  2           // InterfaceMethod org/reactivestreams/Subscriber.onError:(Ljava/lang/Throwable;)V
      16: return

  public static void complete(org.reactivestreams.Subscriber<?>);
    Code:
       0: aload_0
       1: getstatic     #9                  // Field INSTANCE:Lio/reactivex/rxjava3/internal/subscriptions/EmptySubscription;
       4: invokeinterface #10,  2           // InterfaceMethod org/reactivestreams/Subscriber.onSubscribe:(Lorg/reactivestreams/Subscription;)V
       9: aload_0
      10: invokeinterface #12,  1           // InterfaceMethod org/reactivestreams/Subscriber.onComplete:()V
      15: return

  public java.lang.Object poll();
    Code:
       0: aconst_null
       1: areturn

  public boolean isEmpty();
    Code:
       0: iconst_1
       1: ireturn

  public void clear();
    Code:
       0: return

  public int requestFusion(int);
    Code:
       0: iload_1
       1: iconst_2
       2: iand
       3: ireturn

  public boolean offer(java.lang.Object);
    Code:
       0: new           #14                 // class java/lang/UnsupportedOperationException
       3: dup
       4: ldc           #15                 // String Should not be called!
       6: invokespecial #16                 // Method java/lang/UnsupportedOperationException."<init>":(Ljava/lang/String;)V
       9: athrow

  public boolean offer(java.lang.Object, java.lang.Object);
    Code:
       0: new           #14                 // class java/lang/UnsupportedOperationException
       3: dup
       4: ldc           #15                 // String Should not be called!
       6: invokespecial #16                 // Method java/lang/UnsupportedOperationException."<init>":(Ljava/lang/String;)V
       9: athrow

  static {};
    Code:
       0: new           #4                  // class io/reactivex/rxjava3/internal/subscriptions/EmptySubscription
       3: dup
       4: ldc           #17                 // String INSTANCE
       6: iconst_0
       7: invokespecial #18                 // Method "<init>":(Ljava/lang/String;I)V
      10: putstatic     #9                  // Field INSTANCE:Lio/reactivex/rxjava3/internal/subscriptions/EmptySubscription;
      13: iconst_1
      14: anewarray     #4                  // class io/reactivex/rxjava3/internal/subscriptions/EmptySubscription
      17: dup
      18: iconst_0
      19: getstatic     #9                  // Field INSTANCE:Lio/reactivex/rxjava3/internal/subscriptions/EmptySubscription;
      22: aastore
      23: putstatic     #1                  // Field $VALUES:[Lio/reactivex/rxjava3/internal/subscriptions/EmptySubscription;
      26: return
}
