Compiled from "SubscriptionHelper.java"
public final class io.reactivex.rxjava3.internal.subscriptions.SubscriptionHelper extends java.lang.Enum<io.reactivex.rxjava3.internal.subscriptions.SubscriptionHelper> implements org.reactivestreams.Subscription {
  public static final io.reactivex.rxjava3.internal.subscriptions.SubscriptionHelper CANCELLED;

  private static final io.reactivex.rxjava3.internal.subscriptions.SubscriptionHelper[] $VALUES;

  public static io.reactivex.rxjava3.internal.subscriptions.SubscriptionHelper[] values();
    Code:
       0: getstatic     #1                  // Field $VALUES:[Lio/reactivex/rxjava3/internal/subscriptions/SubscriptionHelper;
       3: invokevirtual #2                  // Method "[Lio/reactivex/rxjava3/internal/subscriptions/SubscriptionHelper;".clone:()Ljava/lang/Object;
       6: checkcast     #3                  // class "[Lio/reactivex/rxjava3/internal/subscriptions/SubscriptionHelper;"
       9: areturn

  public static io.reactivex.rxjava3.internal.subscriptions.SubscriptionHelper valueOf(java.lang.String);
    Code:
       0: ldc           #4                  // class io/reactivex/rxjava3/internal/subscriptions/SubscriptionHelper
       2: aload_0
       3: invokestatic  #5                  // Method java/lang/Enum.valueOf:(Ljava/lang/Class;Ljava/lang/String;)Ljava/lang/Enum;
       6: checkcast     #4                  // class io/reactivex/rxjava3/internal/subscriptions/SubscriptionHelper
       9: areturn

  private io.reactivex.rxjava3.internal.subscriptions.SubscriptionHelper();
    Code:
       0: aload_0
       1: aload_1
       2: iload_2
       3: invokespecial #6                  // Method java/lang/Enum."<init>":(Ljava/lang/String;I)V
       6: return

  public void request(long);
    Code:
       0: return

  public void cancel();
    Code:
       0: return

  public static boolean validate(org.reactivestreams.Subscription, org.reactivestreams.Subscription);
    Code:
       0: aload_1
       1: ifnonnull     18
       4: new           #7                  // class java/lang/NullPointerException
       7: dup
       8: ldc           #8                  // String next is null
      10: invokespecial #9                  // Method java/lang/NullPointerException."<init>":(Ljava/lang/String;)V
      13: invokestatic  #10                 // Method io/reactivex/rxjava3/plugins/RxJavaPlugins.onError:(Ljava/lang/Throwable;)V
      16: iconst_0
      17: ireturn
      18: aload_0
      19: ifnull        33
      22: aload_1
      23: invokeinterface #11,  1           // InterfaceMethod org/reactivestreams/Subscription.cancel:()V
      28: invokestatic  #12                 // Method reportSubscriptionSet:()V
      31: iconst_0
      32: ireturn
      33: iconst_1
      34: ireturn

  public static void reportSubscriptionSet();
    Code:
       0: new           #13                 // class io/reactivex/rxjava3/exceptions/ProtocolViolationException
       3: dup
       4: ldc           #14                 // String Subscription already set!
       6: invokespecial #15                 // Method io/reactivex/rxjava3/exceptions/ProtocolViolationException."<init>":(Ljava/lang/String;)V
       9: invokestatic  #10                 // Method io/reactivex/rxjava3/plugins/RxJavaPlugins.onError:(Ljava/lang/Throwable;)V
      12: return

  public static boolean validate(long);
    Code:
       0: lload_0
       1: lconst_0
       2: lcmp
       3: ifgt          37
       6: new           #16                 // class java/lang/IllegalArgumentException
       9: dup
      10: new           #17                 // class java/lang/StringBuilder
      13: dup
      14: invokespecial #18                 // Method java/lang/StringBuilder."<init>":()V
      17: ldc           #19                 // String n > 0 required but it was
      19: invokevirtual #20                 // Method java/lang/StringBuilder.append:(Ljava/lang/String;)Ljava/lang/StringBuilder;
      22: lload_0
      23: invokevirtual #21                 // Method java/lang/StringBuilder.append:(J)Ljava/lang/StringBuilder;
      26: invokevirtual #22                 // Method java/lang/StringBuilder.toString:()Ljava/lang/String;
      29: invokespecial #23                 // Method java/lang/IllegalArgumentException."<init>":(Ljava/lang/String;)V
      32: invokestatic  #10                 // Method io/reactivex/rxjava3/plugins/RxJavaPlugins.onError:(Ljava/lang/Throwable;)V
      35: iconst_0
      36: ireturn
      37: iconst_1
      38: ireturn

  public static void reportMoreProduced(long);
    Code:
       0: new           #13                 // class io/reactivex/rxjava3/exceptions/ProtocolViolationException
       3: dup
       4: new           #17                 // class java/lang/StringBuilder
       7: dup
       8: invokespecial #18                 // Method java/lang/StringBuilder."<init>":()V
      11: ldc           #24                 // String More produced than requested:
      13: invokevirtual #20                 // Method java/lang/StringBuilder.append:(Ljava/lang/String;)Ljava/lang/StringBuilder;
      16: lload_0
      17: invokevirtual #21                 // Method java/lang/StringBuilder.append:(J)Ljava/lang/StringBuilder;
      20: invokevirtual #22                 // Method java/lang/StringBuilder.toString:()Ljava/lang/String;
      23: invokespecial #15                 // Method io/reactivex/rxjava3/exceptions/ProtocolViolationException."<init>":(Ljava/lang/String;)V
      26: invokestatic  #10                 // Method io/reactivex/rxjava3/plugins/RxJavaPlugins.onError:(Ljava/lang/Throwable;)V
      29: return

  public static boolean set(java.util.concurrent.atomic.AtomicReference<org.reactivestreams.Subscription>, org.reactivestreams.Subscription);
    Code:
       0: aload_0
       1: invokevirtual #25                 // Method java/util/concurrent/atomic/AtomicReference.get:()Ljava/lang/Object;
       4: checkcast     #26                 // class org/reactivestreams/Subscription
       7: astore_2
       8: aload_2
       9: getstatic     #27                 // Field CANCELLED:Lio/reactivex/rxjava3/internal/subscriptions/SubscriptionHelper;
      12: if_acmpne     27
      15: aload_1
      16: ifnull        25
      19: aload_1
      20: invokeinterface #11,  1           // InterfaceMethod org/reactivestreams/Subscription.cancel:()V
      25: iconst_0
      26: ireturn
      27: aload_0
      28: aload_2
      29: aload_1
      30: invokevirtual #28                 // Method java/util/concurrent/atomic/AtomicReference.compareAndSet:(Ljava/lang/Object;Ljava/lang/Object;)Z
      33: ifeq          48
      36: aload_2
      37: ifnull        46
      40: aload_2
      41: invokeinterface #11,  1           // InterfaceMethod org/reactivestreams/Subscription.cancel:()V
      46: iconst_1
      47: ireturn
      48: goto          0

  public static boolean setOnce(java.util.concurrent.atomic.AtomicReference<org.reactivestreams.Subscription>, org.reactivestreams.Subscription);
    Code:
       0: aload_1
       1: ldc           #29                 // String s is null
       3: invokestatic  #30                 // Method java/util/Objects.requireNonNull:(Ljava/lang/Object;Ljava/lang/String;)Ljava/lang/Object;
       6: pop
       7: aload_0
       8: aconst_null
       9: aload_1
      10: invokevirtual #28                 // Method java/util/concurrent/atomic/AtomicReference.compareAndSet:(Ljava/lang/Object;Ljava/lang/Object;)Z
      13: ifne          37
      16: aload_1
      17: invokeinterface #11,  1           // InterfaceMethod org/reactivestreams/Subscription.cancel:()V
      22: aload_0
      23: invokevirtual #25                 // Method java/util/concurrent/atomic/AtomicReference.get:()Ljava/lang/Object;
      26: getstatic     #27                 // Field CANCELLED:Lio/reactivex/rxjava3/internal/subscriptions/SubscriptionHelper;
      29: if_acmpeq     35
      32: invokestatic  #12                 // Method reportSubscriptionSet:()V
      35: iconst_0
      36: ireturn
      37: iconst_1
      38: ireturn

  public static boolean replace(java.util.concurrent.atomic.AtomicReference<org.reactivestreams.Subscription>, org.reactivestreams.Subscription);
    Code:
       0: aload_0
       1: invokevirtual #25                 // Method java/util/concurrent/atomic/AtomicReference.get:()Ljava/lang/Object;
       4: checkcast     #26                 // class org/reactivestreams/Subscription
       7: astore_2
       8: aload_2
       9: getstatic     #27                 // Field CANCELLED:Lio/reactivex/rxjava3/internal/subscriptions/SubscriptionHelper;
      12: if_acmpne     27
      15: aload_1
      16: ifnull        25
      19: aload_1
      20: invokeinterface #11,  1           // InterfaceMethod org/reactivestreams/Subscription.cancel:()V
      25: iconst_0
      26: ireturn
      27: aload_0
      28: aload_2
      29: aload_1
      30: invokevirtual #28                 // Method java/util/concurrent/atomic/AtomicReference.compareAndSet:(Ljava/lang/Object;Ljava/lang/Object;)Z
      33: ifeq          38
      36: iconst_1
      37: ireturn
      38: goto          0

  public static boolean cancel(java.util.concurrent.atomic.AtomicReference<org.reactivestreams.Subscription>);
    Code:
       0: aload_0
       1: invokevirtual #25                 // Method java/util/concurrent/atomic/AtomicReference.get:()Ljava/lang/Object;
       4: checkcast     #26                 // class org/reactivestreams/Subscription
       7: astore_1
       8: aload_1
       9: getstatic     #27                 // Field CANCELLED:Lio/reactivex/rxjava3/internal/subscriptions/SubscriptionHelper;
      12: if_acmpeq     45
      15: aload_0
      16: getstatic     #27                 // Field CANCELLED:Lio/reactivex/rxjava3/internal/subscriptions/SubscriptionHelper;
      19: invokevirtual #31                 // Method java/util/concurrent/atomic/AtomicReference.getAndSet:(Ljava/lang/Object;)Ljava/lang/Object;
      22: checkcast     #26                 // class org/reactivestreams/Subscription
      25: astore_1
      26: aload_1
      27: getstatic     #27                 // Field CANCELLED:Lio/reactivex/rxjava3/internal/subscriptions/SubscriptionHelper;
      30: if_acmpeq     45
      33: aload_1
      34: ifnull        43
      37: aload_1
      38: invokeinterface #11,  1           // InterfaceMethod org/reactivestreams/Subscription.cancel:()V
      43: iconst_1
      44: ireturn
      45: iconst_0
      46: ireturn

  public static boolean deferredSetOnce(java.util.concurrent.atomic.AtomicReference<org.reactivestreams.Subscription>, java.util.concurrent.atomic.AtomicLong, org.reactivestreams.Subscription);
    Code:
       0: aload_0
       1: aload_2
       2: invokestatic  #32                 // Method setOnce:(Ljava/util/concurrent/atomic/AtomicReference;Lorg/reactivestreams/Subscription;)Z
       5: ifeq          29
       8: aload_1
       9: lconst_0
      10: invokevirtual #33                 // Method java/util/concurrent/atomic/AtomicLong.getAndSet:(J)J
      13: lstore_3
      14: lload_3
      15: lconst_0
      16: lcmp
      17: ifeq          27
      20: aload_2
      21: lload_3
      22: invokeinterface #34,  3           // InterfaceMethod org/reactivestreams/Subscription.request:(J)V
      27: iconst_1
      28: ireturn
      29: iconst_0
      30: ireturn

  public static void deferredRequest(java.util.concurrent.atomic.AtomicReference<org.reactivestreams.Subscription>, java.util.concurrent.atomic.AtomicLong, long);
    Code:
       0: aload_0
       1: invokevirtual #25                 // Method java/util/concurrent/atomic/AtomicReference.get:()Ljava/lang/Object;
       4: checkcast     #26                 // class org/reactivestreams/Subscription
       7: astore        4
       9: aload         4
      11: ifnull        25
      14: aload         4
      16: lload_2
      17: invokeinterface #34,  3           // InterfaceMethod org/reactivestreams/Subscription.request:(J)V
      22: goto          75
      25: lload_2
      26: invokestatic  #35                 // Method validate:(J)Z
      29: ifeq          75
      32: aload_1
      33: lload_2
      34: invokestatic  #36                 // Method io/reactivex/rxjava3/internal/util/BackpressureHelper.add:(Ljava/util/concurrent/atomic/AtomicLong;J)J
      37: pop2
      38: aload_0
      39: invokevirtual #25                 // Method java/util/concurrent/atomic/AtomicReference.get:()Ljava/lang/Object;
      42: checkcast     #26                 // class org/reactivestreams/Subscription
      45: astore        4
      47: aload         4
      49: ifnull        75
      52: aload_1
      53: lconst_0
      54: invokevirtual #33                 // Method java/util/concurrent/atomic/AtomicLong.getAndSet:(J)J
      57: lstore        5
      59: lload         5
      61: lconst_0
      62: lcmp
      63: ifeq          75
      66: aload         4
      68: lload         5
      70: invokeinterface #34,  3           // InterfaceMethod org/reactivestreams/Subscription.request:(J)V
      75: return

  public static boolean setOnce(java.util.concurrent.atomic.AtomicReference<org.reactivestreams.Subscription>, org.reactivestreams.Subscription, long);
    Code:
       0: aload_0
       1: aload_1
       2: invokestatic  #32                 // Method setOnce:(Ljava/util/concurrent/atomic/AtomicReference;Lorg/reactivestreams/Subscription;)Z
       5: ifeq          17
       8: aload_1
       9: lload_2
      10: invokeinterface #34,  3           // InterfaceMethod org/reactivestreams/Subscription.request:(J)V
      15: iconst_1
      16: ireturn
      17: iconst_0
      18: ireturn

  static {};
    Code:
       0: new           #4                  // class io/reactivex/rxjava3/internal/subscriptions/SubscriptionHelper
       3: dup
       4: ldc           #37                 // String CANCELLED
       6: iconst_0
       7: invokespecial #38                 // Method "<init>":(Ljava/lang/String;I)V
      10: putstatic     #27                 // Field CANCELLED:Lio/reactivex/rxjava3/internal/subscriptions/SubscriptionHelper;
      13: iconst_1
      14: anewarray     #4                  // class io/reactivex/rxjava3/internal/subscriptions/SubscriptionHelper
      17: dup
      18: iconst_0
      19: getstatic     #27                 // Field CANCELLED:Lio/reactivex/rxjava3/internal/subscriptions/SubscriptionHelper;
      22: aastore
      23: putstatic     #1                  // Field $VALUES:[Lio/reactivex/rxjava3/internal/subscriptions/SubscriptionHelper;
      26: return
}
