Compiled from "MultiDetector.java"
public final class com.google.zxing.multi.qrcode.detector.MultiDetector extends com.google.zxing.qrcode.detector.Detector {
  private static final com.google.zxing.common.DetectorResult[] EMPTY_DETECTOR_RESULTS;

  public com.google.zxing.multi.qrcode.detector.MultiDetector(com.google.zxing.common.BitMatrix);
    Code:
       0: aload_0
       1: aload_1
       2: invokespecial #1                  // Method com/google/zxing/qrcode/detector/Detector."<init>":(Lcom/google/zxing/common/BitMatrix;)V
       5: return

  public com.google.zxing.common.DetectorResult[] detectMulti(java.util.Map<com.google.zxing.DecodeHintType, ?>) throws com.google.zxing.NotFoundException;
    Code:
       0: aload_0
       1: invokevirtual #2                  // Method getImage:()Lcom/google/zxing/common/BitMatrix;
       4: astore_2
       5: aload_1
       6: ifnonnull     13
       9: aconst_null
      10: goto          25
      13: aload_1
      14: getstatic     #3                  // Field com/google/zxing/DecodeHintType.NEED_RESULT_POINT_CALLBACK:Lcom/google/zxing/DecodeHintType;
      17: invokeinterface #4,  2            // InterfaceMethod java/util/Map.get:(Ljava/lang/Object;)Ljava/lang/Object;
      22: checkcast     #5                  // class com/google/zxing/ResultPointCallback
      25: astore_3
      26: new           #6                  // class com/google/zxing/multi/qrcode/detector/MultiFinderPatternFinder
      29: dup
      30: aload_2
      31: aload_3
      32: invokespecial #7                  // Method com/google/zxing/multi/qrcode/detector/MultiFinderPatternFinder."<init>":(Lcom/google/zxing/common/BitMatrix;Lcom/google/zxing/ResultPointCallback;)V
      35: astore        4
      37: aload         4
      39: aload_1
      40: invokevirtual #8                  // Method com/google/zxing/multi/qrcode/detector/MultiFinderPatternFinder.findMulti:(Ljava/util/Map;)[Lcom/google/zxing/qrcode/detector/FinderPatternInfo;
      43: astore        5
      45: aload         5
      47: arraylength
      48: ifne          55
      51: invokestatic  #9                  // Method com/google/zxing/NotFoundException.getNotFoundInstance:()Lcom/google/zxing/NotFoundException;
      54: athrow
      55: new           #10                 // class java/util/ArrayList
      58: dup
      59: invokespecial #11                 // Method java/util/ArrayList."<init>":()V
      62: astore        6
      64: aload         5
      66: astore        7
      68: aload         7
      70: arraylength
      71: istore        8
      73: iconst_0
      74: istore        9
      76: iload         9
      78: iload         8
      80: if_icmpge     115
      83: aload         7
      85: iload         9
      87: aaload
      88: astore        10
      90: aload         6
      92: aload_0
      93: aload         10
      95: invokevirtual #12                 // Method processFinderPatternInfo:(Lcom/google/zxing/qrcode/detector/FinderPatternInfo;)Lcom/google/zxing/common/DetectorResult;
      98: invokeinterface #13,  2           // InterfaceMethod java/util/List.add:(Ljava/lang/Object;)Z
     103: pop
     104: goto          109
     107: astore        11
     109: iinc          9, 1
     112: goto          76
     115: aload         6
     117: invokeinterface #15,  1           // InterfaceMethod java/util/List.isEmpty:()Z
     122: ifeq          129
     125: getstatic     #16                 // Field EMPTY_DETECTOR_RESULTS:[Lcom/google/zxing/common/DetectorResult;
     128: areturn
     129: aload         6
     131: getstatic     #16                 // Field EMPTY_DETECTOR_RESULTS:[Lcom/google/zxing/common/DetectorResult;
     134: invokeinterface #17,  2           // InterfaceMethod java/util/List.toArray:([Ljava/lang/Object;)[Ljava/lang/Object;
     139: checkcast     #18                 // class "[Lcom/google/zxing/common/DetectorResult;"
     142: areturn
    Exception table:
       from    to  target type
          90   104   107   Class com/google/zxing/ReaderException

  static {};
    Code:
       0: iconst_0
       1: anewarray     #19                 // class com/google/zxing/common/DetectorResult
       4: putstatic     #16                 // Field EMPTY_DETECTOR_RESULTS:[Lcom/google/zxing/common/DetectorResult;
       7: return
}
