Compiled from "MultiFinderPatternFinder.java"
final class com.google.zxing.multi.qrcode.detector.MultiFinderPatternFinder$ModuleSizeComparator implements java.util.Comparator<com.google.zxing.qrcode.detector.FinderPattern>, java.io.Serializable {
  private com.google.zxing.multi.qrcode.detector.MultiFinderPatternFinder$ModuleSizeComparator();
    Code:
       0: aload_0
       1: invokespecial #2                  // Method java/lang/Object."<init>":()V
       4: return

  public int compare(com.google.zxing.qrcode.detector.FinderPattern, com.google.zxing.qrcode.detector.FinderPattern);
    Code:
       0: aload_2
       1: invokevirtual #3                  // Method com/google/zxing/qrcode/detector/FinderPattern.getEstimatedModuleSize:()F
       4: aload_1
       5: invokevirtual #3                  // Method com/google/zxing/qrcode/detector/FinderPattern.getEstimatedModuleSize:()F
       8: fsub
       9: fstore_3
      10: fload_3
      11: f2d
      12: dconst_0
      13: dcmpg
      14: ifge          21
      17: iconst_m1
      18: goto          33
      21: fload_3
      22: f2d
      23: dconst_0
      24: dcmpl
      25: ifle          32
      28: iconst_1
      29: goto          33
      32: iconst_0
      33: ireturn

  public int compare(java.lang.Object, java.lang.Object);
    Code:
       0: aload_0
       1: aload_1
       2: checkcast     #4                  // class com/google/zxing/qrcode/detector/FinderPattern
       5: aload_2
       6: checkcast     #4                  // class com/google/zxing/qrcode/detector/FinderPattern
       9: invokevirtual #5                  // Method compare:(Lcom/google/zxing/qrcode/detector/FinderPattern;Lcom/google/zxing/qrcode/detector/FinderPattern;)I
      12: ireturn

  com.google.zxing.multi.qrcode.detector.MultiFinderPatternFinder$ModuleSizeComparator(com.google.zxing.multi.qrcode.detector.MultiFinderPatternFinder$1);
    Code:
       0: aload_0
       1: invokespecial #1                  // Method "<init>":()V
       4: return
}
