Compiled from "BootstrapListener.java"
public class org.apache.dubbo.remoting.http.servlet.BootstrapListener implements javax.servlet.ServletContextListener {
  public org.apache.dubbo.remoting.http.servlet.BootstrapListener();
    Code:
       0: aload_0
       1: invokespecial #1                  // Method java/lang/Object."<init>":()V
       4: return

  public void contextInitialized(javax.servlet.ServletContextEvent);
    Code:
       0: invokestatic  #2                  // Method org/apache/dubbo/remoting/http/servlet/ServletManager.getInstance:()Lorg/apache/dubbo/remoting/http/servlet/ServletManager;
       3: sipush        -1234
       6: aload_1
       7: invokevirtual #4                  // Method javax/servlet/ServletContextEvent.getServletContext:()Ljavax/servlet/ServletContext;
      10: invokevirtual #5                  // Method org/apache/dubbo/remoting/http/servlet/ServletManager.addServletContext:(ILjavax/servlet/ServletContext;)V
      13: return

  public void contextDestroyed(javax.servlet.ServletContextEvent);
    Code:
       0: invokestatic  #2                  // Method org/apache/dubbo/remoting/http/servlet/ServletManager.getInstance:()Lorg/apache/dubbo/remoting/http/servlet/ServletManager;
       3: sipush        -1234
       6: invokevirtual #6                  // Method org/apache/dubbo/remoting/http/servlet/ServletManager.removeServletContext:(I)V
       9: return
}
