Compiled from "DispatcherServlet.java"
public class org.apache.dubbo.remoting.http.servlet.DispatcherServlet extends javax.servlet.http.HttpServlet {
  private static final long serialVersionUID;

  private static final java.util.Map<java.lang.Integer, org.apache.dubbo.remoting.http.HttpHandler> HANDLERS;

  private static org.apache.dubbo.remoting.http.servlet.DispatcherServlet INSTANCE;

  public org.apache.dubbo.remoting.http.servlet.DispatcherServlet();
    Code:
       0: aload_0
       1: invokespecial #1                  // Method javax/servlet/http/HttpServlet."<init>":()V
       4: aload_0
       5: putstatic     #2                  // Field INSTANCE:Lorg/apache/dubbo/remoting/http/servlet/DispatcherServlet;
       8: return

  public static void addHttpHandler(int, org.apache.dubbo.remoting.http.HttpHandler);
    Code:
       0: getstatic     #3                  // Field HANDLERS:Ljava/util/Map;
       3: iload_0
       4: invokestatic  #4                  // Method java/lang/Integer.valueOf:(I)Ljava/lang/Integer;
       7: aload_1
       8: invokeinterface #5,  3            // InterfaceMethod java/util/Map.put:(Ljava/lang/Object;Ljava/lang/Object;)Ljava/lang/Object;
      13: pop
      14: return

  public static void removeHttpHandler(int);
    Code:
       0: getstatic     #3                  // Field HANDLERS:Ljava/util/Map;
       3: iload_0
       4: invokestatic  #4                  // Method java/lang/Integer.valueOf:(I)Ljava/lang/Integer;
       7: invokeinterface #6,  2            // InterfaceMethod java/util/Map.remove:(Ljava/lang/Object;)Ljava/lang/Object;
      12: pop
      13: return

  public static org.apache.dubbo.remoting.http.servlet.DispatcherServlet getInstance();
    Code:
       0: getstatic     #2                  // Field INSTANCE:Lorg/apache/dubbo/remoting/http/servlet/DispatcherServlet;
       3: areturn

  protected void service(javax.servlet.http.HttpServletRequest, javax.servlet.http.HttpServletResponse) throws javax.servlet.ServletException, java.io.IOException;
    Code:
       0: getstatic     #3                  // Field HANDLERS:Ljava/util/Map;
       3: aload_1
       4: invokeinterface #7,  1            // InterfaceMethod javax/servlet/http/HttpServletRequest.getLocalPort:()I
       9: invokestatic  #4                  // Method java/lang/Integer.valueOf:(I)Ljava/lang/Integer;
      12: invokeinterface #8,  2            // InterfaceMethod java/util/Map.get:(Ljava/lang/Object;)Ljava/lang/Object;
      17: checkcast     #9                  // class org/apache/dubbo/remoting/http/HttpHandler
      20: astore_3
      21: aload_3
      22: ifnonnull     39
      25: aload_2
      26: sipush        404
      29: ldc           #11                 // String Service not found.
      31: invokeinterface #12,  3           // InterfaceMethod javax/servlet/http/HttpServletResponse.sendError:(ILjava/lang/String;)V
      36: goto          47
      39: aload_3
      40: aload_1
      41: aload_2
      42: invokeinterface #13,  3           // InterfaceMethod org/apache/dubbo/remoting/http/HttpHandler.handle:(Ljava/lang/Object;Ljava/lang/Object;)V
      47: return

  static {};
    Code:
       0: new           #14                 // class java/util/concurrent/ConcurrentHashMap
       3: dup
       4: invokespecial #15                 // Method java/util/concurrent/ConcurrentHashMap."<init>":()V
       7: putstatic     #3                  // Field HANDLERS:Ljava/util/Map;
      10: return
}
