Compiled from "ServletHttpServer.java"
public class org.apache.dubbo.remoting.http.servlet.ServletHttpServer extends org.apache.dubbo.remoting.http.support.AbstractHttpServer {
  public org.apache.dubbo.remoting.http.servlet.ServletHttpServer(org.apache.dubbo.common.URL, org.apache.dubbo.remoting.http.HttpHandler);
    Code:
       0: aload_0
       1: aload_1
       2: aload_2
       3: invokespecial #1                  // Method org/apache/dubbo/remoting/http/support/AbstractHttpServer."<init>":(Lorg/apache/dubbo/common/URL;Lorg/apache/dubbo/remoting/http/HttpHandler;)V
       6: aload_1
       7: ldc           #3                  // String bind.port
       9: sipush        8080
      12: invokevirtual #4                  // Method org/apache/dubbo/common/URL.getParameter:(Ljava/lang/String;I)I
      15: aload_2
      16: invokestatic  #5                  // Method org/apache/dubbo/remoting/http/servlet/DispatcherServlet.addHttpHandler:(ILorg/apache/dubbo/remoting/http/HttpHandler;)V
      19: return
}
