Compiled from "ServletHttpBinder.java"
public class org.apache.dubbo.remoting.http.servlet.ServletHttpBinder implements org.apache.dubbo.remoting.http.HttpBinder {
  public org.apache.dubbo.remoting.http.servlet.ServletHttpBinder();
    Code:
       0: aload_0
       1: invokespecial #1                  // Method java/lang/Object."<init>":()V
       4: return

  public org.apache.dubbo.remoting.http.HttpServer bind(org.apache.dubbo.common.URL, org.apache.dubbo.remoting.http.HttpHandler);
    Code:
       0: new           #2                  // class org/apache/dubbo/remoting/http/servlet/ServletHttpServer
       3: dup
       4: aload_1
       5: aload_2
       6: invokespecial #3                  // Method org/apache/dubbo/remoting/http/servlet/ServletHttpServer."<init>":(Lorg/apache/dubbo/common/URL;Lorg/apache/dubbo/remoting/http/HttpHandler;)V
       9: areturn
}
