Compiled from "ServletManager.java"
public class org.apache.dubbo.remoting.http.servlet.ServletManager {
  public static final int EXTERNAL_SERVER_PORT;

  private static final org.apache.dubbo.remoting.http.servlet.ServletManager INSTANCE;

  private final java.util.Map<java.lang.Integer, javax.servlet.ServletContext> contextMap;

  public org.apache.dubbo.remoting.http.servlet.ServletManager();
    Code:
       0: aload_0
       1: invokespecial #1                  // Method java/lang/Object."<init>":()V
       4: aload_0
       5: new           #2                  // class java/util/concurrent/ConcurrentHashMap
       8: dup
       9: invokespecial #3                  // Method java/util/concurrent/ConcurrentHashMap."<init>":()V
      12: putfield      #4                  // Field contextMap:Ljava/util/Map;
      15: return

  public static org.apache.dubbo.remoting.http.servlet.ServletManager getInstance();
    Code:
       0: getstatic     #5                  // Field INSTANCE:Lorg/apache/dubbo/remoting/http/servlet/ServletManager;
       3: areturn

  public void addServletContext(int, javax.servlet.ServletContext);
    Code:
       0: aload_0
       1: getfield      #4                  // Field contextMap:Ljava/util/Map;
       4: iload_1
       5: invokestatic  #6                  // Method java/lang/Integer.valueOf:(I)Ljava/lang/Integer;
       8: aload_2
       9: invokeinterface #7,  3            // InterfaceMethod java/util/Map.put:(Ljava/lang/Object;Ljava/lang/Object;)Ljava/lang/Object;
      14: pop
      15: return

  public void removeServletContext(int);
    Code:
       0: aload_0
       1: getfield      #4                  // Field contextMap:Ljava/util/Map;
       4: iload_1
       5: invokestatic  #6                  // Method java/lang/Integer.valueOf:(I)Ljava/lang/Integer;
       8: invokeinterface #8,  2            // InterfaceMethod java/util/Map.remove:(Ljava/lang/Object;)Ljava/lang/Object;
      13: pop
      14: return

  public javax.servlet.ServletContext getServletContext(int);
    Code:
       0: aload_0
       1: getfield      #4                  // Field contextMap:Ljava/util/Map;
       4: iload_1
       5: invokestatic  #6                  // Method java/lang/Integer.valueOf:(I)Ljava/lang/Integer;
       8: invokeinterface #9,  2            // InterfaceMethod java/util/Map.get:(Ljava/lang/Object;)Ljava/lang/Object;
      13: checkcast     #10                 // class javax/servlet/ServletContext
      16: areturn

  static {};
    Code:
       0: new           #11                 // class org/apache/dubbo/remoting/http/servlet/ServletManager
       3: dup
       4: invokespecial #12                 // Method "<init>":()V
       7: putstatic     #5                  // Field INSTANCE:Lorg/apache/dubbo/remoting/http/servlet/ServletManager;
      10: return
}
