Compiled from "ChannelHandlers.java"
public class org.apache.dubbo.remoting.transport.dispatcher.ChannelHandlers {
  private static org.apache.dubbo.remoting.transport.dispatcher.ChannelHandlers INSTANCE;

  protected org.apache.dubbo.remoting.transport.dispatcher.ChannelHandlers();
    Code:
       0: aload_0
       1: invokespecial #1                  // Method java/lang/Object."<init>":()V
       4: return

  public static org.apache.dubbo.remoting.ChannelHandler wrap(org.apache.dubbo.remoting.ChannelHandler, org.apache.dubbo.common.URL);
    Code:
       0: invokestatic  #2                  // Method getInstance:()Lorg/apache/dubbo/remoting/transport/dispatcher/ChannelHandlers;
       3: aload_0
       4: aload_1
       5: invokevirtual #3                  // Method wrapInternal:(Lorg/apache/dubbo/remoting/ChannelHandler;Lorg/apache/dubbo/common/URL;)Lorg/apache/dubbo/remoting/ChannelHandler;
       8: areturn

  public static org.apache.dubbo.remoting.transport.dispatcher.ChannelHandlers getInstance();
    Code:
       0: getstatic     #4                  // Field INSTANCE:Lorg/apache/dubbo/remoting/transport/dispatcher/ChannelHandlers;
       3: areturn

  static void setTestingChannelHandlers(org.apache.dubbo.remoting.transport.dispatcher.ChannelHandlers);
    Code:
       0: aload_0
       1: putstatic     #4                  // Field INSTANCE:Lorg/apache/dubbo/remoting/transport/dispatcher/ChannelHandlers;
       4: return

  protected org.apache.dubbo.remoting.ChannelHandler wrapInternal(org.apache.dubbo.remoting.ChannelHandler, org.apache.dubbo.common.URL);
    Code:
       0: new           #5                  // class org/apache/dubbo/remoting/transport/MultiMessageHandler
       3: dup
       4: new           #6                  // class org/apache/dubbo/remoting/exchange/support/header/HeartbeatHandler
       7: dup
       8: aload_2
       9: invokevirtual #7                  // Method org/apache/dubbo/common/URL.getOrDefaultFrameworkModel:()Lorg/apache/dubbo/rpc/model/FrameworkModel;
      12: ldc           #8                  // class org/apache/dubbo/remoting/Dispatcher
      14: invokevirtual #9                  // Method org/apache/dubbo/rpc/model/FrameworkModel.getExtensionLoader:(Ljava/lang/Class;)Lorg/apache/dubbo/common/extension/ExtensionLoader;
      17: invokevirtual #10                 // Method org/apache/dubbo/common/extension/ExtensionLoader.getAdaptiveExtension:()Ljava/lang/Object;
      20: checkcast     #8                  // class org/apache/dubbo/remoting/Dispatcher
      23: aload_1
      24: aload_2
      25: invokeinterface #11,  3           // InterfaceMethod org/apache/dubbo/remoting/Dispatcher.dispatch:(Lorg/apache/dubbo/remoting/ChannelHandler;Lorg/apache/dubbo/common/URL;)Lorg/apache/dubbo/remoting/ChannelHandler;
      30: invokespecial #12                 // Method org/apache/dubbo/remoting/exchange/support/header/HeartbeatHandler."<init>":(Lorg/apache/dubbo/remoting/ChannelHandler;)V
      33: invokespecial #13                 // Method org/apache/dubbo/remoting/transport/MultiMessageHandler."<init>":(Lorg/apache/dubbo/remoting/ChannelHandler;)V
      36: areturn

  static {};
    Code:
       0: new           #14                 // class org/apache/dubbo/remoting/transport/dispatcher/ChannelHandlers
       3: dup
       4: invokespecial #15                 // Method "<init>":()V
       7: putstatic     #4                  // Field INSTANCE:Lorg/apache/dubbo/remoting/transport/dispatcher/ChannelHandlers;
      10: return
}
