Compiled from "ChannelEventRunnable.java"
public final class org.apache.dubbo.remoting.transport.dispatcher.ChannelEventRunnable$ChannelState extends java.lang.Enum<org.apache.dubbo.remoting.transport.dispatcher.ChannelEventRunnable$ChannelState> {
  public static final org.apache.dubbo.remoting.transport.dispatcher.ChannelEventRunnable$ChannelState CONNECTED;

  public static final org.apache.dubbo.remoting.transport.dispatcher.ChannelEventRunnable$ChannelState DISCONNECTED;

  public static final org.apache.dubbo.remoting.transport.dispatcher.ChannelEventRunnable$ChannelState SENT;

  public static final org.apache.dubbo.remoting.transport.dispatcher.ChannelEventRunnable$ChannelState RECEIVED;

  public static final org.apache.dubbo.remoting.transport.dispatcher.ChannelEventRunnable$ChannelState CAUGHT;

  private static final org.apache.dubbo.remoting.transport.dispatcher.ChannelEventRunnable$ChannelState[] $VALUES;

  public static org.apache.dubbo.remoting.transport.dispatcher.ChannelEventRunnable$ChannelState[] values();
    Code:
       0: getstatic     #1                  // Field $VALUES:[Lorg/apache/dubbo/remoting/transport/dispatcher/ChannelEventRunnable$ChannelState;
       3: invokevirtual #2                  // Method "[Lorg/apache/dubbo/remoting/transport/dispatcher/ChannelEventRunnable$ChannelState;".clone:()Ljava/lang/Object;
       6: checkcast     #3                  // class "[Lorg/apache/dubbo/remoting/transport/dispatcher/ChannelEventRunnable$ChannelState;"
       9: areturn

  public static org.apache.dubbo.remoting.transport.dispatcher.ChannelEventRunnable$ChannelState valueOf(java.lang.String);
    Code:
       0: ldc           #4                  // class org/apache/dubbo/remoting/transport/dispatcher/ChannelEventRunnable$ChannelState
       2: aload_0
       3: invokestatic  #5                  // Method java/lang/Enum.valueOf:(Ljava/lang/Class;Ljava/lang/String;)Ljava/lang/Enum;
       6: checkcast     #4                  // class org/apache/dubbo/remoting/transport/dispatcher/ChannelEventRunnable$ChannelState
       9: areturn

  private org.apache.dubbo.remoting.transport.dispatcher.ChannelEventRunnable$ChannelState();
    Code:
       0: aload_0
       1: aload_1
       2: iload_2
       3: invokespecial #6                  // Method java/lang/Enum."<init>":(Ljava/lang/String;I)V
       6: return

  static {};
    Code:
       0: new           #4                  // class org/apache/dubbo/remoting/transport/dispatcher/ChannelEventRunnable$ChannelState
       3: dup
       4: ldc           #7                  // String CONNECTED
       6: iconst_0
       7: invokespecial #8                  // Method "<init>":(Ljava/lang/String;I)V
      10: putstatic     #9                  // Field CONNECTED:Lorg/apache/dubbo/remoting/transport/dispatcher/ChannelEventRunnable$ChannelState;
      13: new           #4                  // class org/apache/dubbo/remoting/transport/dispatcher/ChannelEventRunnable$ChannelState
      16: dup
      17: ldc           #10                 // String DISCONNECTED
      19: iconst_1
      20: invokespecial #8                  // Method "<init>":(Ljava/lang/String;I)V
      23: putstatic     #11                 // Field DISCONNECTED:Lorg/apache/dubbo/remoting/transport/dispatcher/ChannelEventRunnable$ChannelState;
      26: new           #4                  // class org/apache/dubbo/remoting/transport/dispatcher/ChannelEventRunnable$ChannelState
      29: dup
      30: ldc           #12                 // String SENT
      32: iconst_2
      33: invokespecial #8                  // Method "<init>":(Ljava/lang/String;I)V
      36: putstatic     #13                 // Field SENT:Lorg/apache/dubbo/remoting/transport/dispatcher/ChannelEventRunnable$ChannelState;
      39: new           #4                  // class org/apache/dubbo/remoting/transport/dispatcher/ChannelEventRunnable$ChannelState
      42: dup
      43: ldc           #14                 // String RECEIVED
      45: iconst_3
      46: invokespecial #8                  // Method "<init>":(Ljava/lang/String;I)V
      49: putstatic     #15                 // Field RECEIVED:Lorg/apache/dubbo/remoting/transport/dispatcher/ChannelEventRunnable$ChannelState;
      52: new           #4                  // class org/apache/dubbo/remoting/transport/dispatcher/ChannelEventRunnable$ChannelState
      55: dup
      56: ldc           #16                 // String CAUGHT
      58: iconst_4
      59: invokespecial #8                  // Method "<init>":(Ljava/lang/String;I)V
      62: putstatic     #17                 // Field CAUGHT:Lorg/apache/dubbo/remoting/transport/dispatcher/ChannelEventRunnable$ChannelState;
      65: iconst_5
      66: anewarray     #4                  // class org/apache/dubbo/remoting/transport/dispatcher/ChannelEventRunnable$ChannelState
      69: dup
      70: iconst_0
      71: getstatic     #9                  // Field CONNECTED:Lorg/apache/dubbo/remoting/transport/dispatcher/ChannelEventRunnable$ChannelState;
      74: aastore
      75: dup
      76: iconst_1
      77: getstatic     #11                 // Field DISCONNECTED:Lorg/apache/dubbo/remoting/transport/dispatcher/ChannelEventRunnable$ChannelState;
      80: aastore
      81: dup
      82: iconst_2
      83: getstatic     #13                 // Field SENT:Lorg/apache/dubbo/remoting/transport/dispatcher/ChannelEventRunnable$ChannelState;
      86: aastore
      87: dup
      88: iconst_3
      89: getstatic     #15                 // Field RECEIVED:Lorg/apache/dubbo/remoting/transport/dispatcher/ChannelEventRunnable$ChannelState;
      92: aastore
      93: dup
      94: iconst_4
      95: getstatic     #17                 // Field CAUGHT:Lorg/apache/dubbo/remoting/transport/dispatcher/ChannelEventRunnable$ChannelState;
      98: aastore
      99: putstatic     #1                  // Field $VALUES:[Lorg/apache/dubbo/remoting/transport/dispatcher/ChannelEventRunnable$ChannelState;
     102: return
}
