Compiled from "ChannelEventRunnable.java"
class org.apache.dubbo.remoting.transport.dispatcher.ChannelEventRunnable$1 {
  static final int[] $SwitchMap$org$apache$dubbo$remoting$transport$dispatcher$ChannelEventRunnable$ChannelState;

  static {};
    Code:
       0: invokestatic  #1                  // Method org/apache/dubbo/remoting/transport/dispatcher/ChannelEventRunnable$ChannelState.values:()[Lorg/apache/dubbo/remoting/transport/dispatcher/ChannelEventRunnable$ChannelState;
       3: arraylength
       4: newarray       int
       6: putstatic     #2                  // Field $SwitchMap$org$apache$dubbo$remoting$transport$dispatcher$ChannelEventRunnable$ChannelState:[I
       9: getstatic     #2                  // Field $SwitchMap$org$apache$dubbo$remoting$transport$dispatcher$ChannelEventRunnable$ChannelState:[I
      12: getstatic     #3                  // Field org/apache/dubbo/remoting/transport/dispatcher/ChannelEventRunnable$ChannelState.CONNECTED:Lorg/apache/dubbo/remoting/transport/dispatcher/ChannelEventRunnable$ChannelState;
      15: invokevirtual #4                  // Method org/apache/dubbo/remoting/transport/dispatcher/ChannelEventRunnable$ChannelState.ordinal:()I
      18: iconst_1
      19: iastore
      20: goto          24
      23: astore_0
      24: getstatic     #2                  // Field $SwitchMap$org$apache$dubbo$remoting$transport$dispatcher$ChannelEventRunnable$ChannelState:[I
      27: getstatic     #6                  // Field org/apache/dubbo/remoting/transport/dispatcher/ChannelEventRunnable$ChannelState.DISCONNECTED:Lorg/apache/dubbo/remoting/transport/dispatcher/ChannelEventRunnable$ChannelState;
      30: invokevirtual #4                  // Method org/apache/dubbo/remoting/transport/dispatcher/ChannelEventRunnable$ChannelState.ordinal:()I
      33: iconst_2
      34: iastore
      35: goto          39
      38: astore_0
      39: getstatic     #2                  // Field $SwitchMap$org$apache$dubbo$remoting$transport$dispatcher$ChannelEventRunnable$ChannelState:[I
      42: getstatic     #7                  // Field org/apache/dubbo/remoting/transport/dispatcher/ChannelEventRunnable$ChannelState.SENT:Lorg/apache/dubbo/remoting/transport/dispatcher/ChannelEventRunnable$ChannelState;
      45: invokevirtual #4                  // Method org/apache/dubbo/remoting/transport/dispatcher/ChannelEventRunnable$ChannelState.ordinal:()I
      48: iconst_3
      49: iastore
      50: goto          54
      53: astore_0
      54: getstatic     #2                  // Field $SwitchMap$org$apache$dubbo$remoting$transport$dispatcher$ChannelEventRunnable$ChannelState:[I
      57: getstatic     #8                  // Field org/apache/dubbo/remoting/transport/dispatcher/ChannelEventRunnable$ChannelState.CAUGHT:Lorg/apache/dubbo/remoting/transport/dispatcher/ChannelEventRunnable$ChannelState;
      60: invokevirtual #4                  // Method org/apache/dubbo/remoting/transport/dispatcher/ChannelEventRunnable$ChannelState.ordinal:()I
      63: iconst_4
      64: iastore
      65: goto          69
      68: astore_0
      69: return
    Exception table:
       from    to  target type
           9    20    23   Class java/lang/NoSuchFieldError
          24    35    38   Class java/lang/NoSuchFieldError
          39    50    53   Class java/lang/NoSuchFieldError
          54    65    68   Class java/lang/NoSuchFieldError
}
