Compiled from "ChannelEventRunnable.java"
public class org.apache.dubbo.remoting.transport.dispatcher.ChannelEventRunnable implements java.lang.Runnable {
  private static final org.apache.dubbo.common.logger.ErrorTypeAwareLogger logger;

  private final org.apache.dubbo.remoting.ChannelHandler handler;

  private final org.apache.dubbo.remoting.Channel channel;

  private final org.apache.dubbo.remoting.transport.dispatcher.ChannelEventRunnable$ChannelState state;

  private final java.lang.Throwable exception;

  private final java.lang.Object message;

  public org.apache.dubbo.remoting.transport.dispatcher.ChannelEventRunnable(org.apache.dubbo.remoting.Channel, org.apache.dubbo.remoting.ChannelHandler, org.apache.dubbo.remoting.transport.dispatcher.ChannelEventRunnable$ChannelState);
    Code:
       0: aload_0
       1: aload_1
       2: aload_2
       3: aload_3
       4: aconst_null
       5: invokespecial #2                  // Method "<init>":(Lorg/apache/dubbo/remoting/Channel;Lorg/apache/dubbo/remoting/ChannelHandler;Lorg/apache/dubbo/remoting/transport/dispatcher/ChannelEventRunnable$ChannelState;Ljava/lang/Throwable;)V
       8: return

  public org.apache.dubbo.remoting.transport.dispatcher.ChannelEventRunnable(org.apache.dubbo.remoting.Channel, org.apache.dubbo.remoting.ChannelHandler, org.apache.dubbo.remoting.transport.dispatcher.ChannelEventRunnable$ChannelState, java.lang.Object);
    Code:
       0: aload_0
       1: aload_1
       2: aload_2
       3: aload_3
       4: aload         4
       6: aconst_null
       7: invokespecial #3                  // Method "<init>":(Lorg/apache/dubbo/remoting/Channel;Lorg/apache/dubbo/remoting/ChannelHandler;Lorg/apache/dubbo/remoting/transport/dispatcher/ChannelEventRunnable$ChannelState;Ljava/lang/Object;Ljava/lang/Throwable;)V
      10: return

  public org.apache.dubbo.remoting.transport.dispatcher.ChannelEventRunnable(org.apache.dubbo.remoting.Channel, org.apache.dubbo.remoting.ChannelHandler, org.apache.dubbo.remoting.transport.dispatcher.ChannelEventRunnable$ChannelState, java.lang.Throwable);
    Code:
       0: aload_0
       1: aload_1
       2: aload_2
       3: aload_3
       4: aconst_null
       5: aload         4
       7: invokespecial #3                  // Method "<init>":(Lorg/apache/dubbo/remoting/Channel;Lorg/apache/dubbo/remoting/ChannelHandler;Lorg/apache/dubbo/remoting/transport/dispatcher/ChannelEventRunnable$ChannelState;Ljava/lang/Object;Ljava/lang/Throwable;)V
      10: return

  public org.apache.dubbo.remoting.transport.dispatcher.ChannelEventRunnable(org.apache.dubbo.remoting.Channel, org.apache.dubbo.remoting.ChannelHandler, org.apache.dubbo.remoting.transport.dispatcher.ChannelEventRunnable$ChannelState, java.lang.Object, java.lang.Throwable);
    Code:
       0: aload_0
       1: invokespecial #4                  // Method java/lang/Object."<init>":()V
       4: aload_0
       5: aload_1
       6: putfield      #5                  // Field channel:Lorg/apache/dubbo/remoting/Channel;
       9: aload_0
      10: aload_2
      11: putfield      #6                  // Field handler:Lorg/apache/dubbo/remoting/ChannelHandler;
      14: aload_0
      15: aload_3
      16: putfield      #7                  // Field state:Lorg/apache/dubbo/remoting/transport/dispatcher/ChannelEventRunnable$ChannelState;
      19: aload_0
      20: aload         4
      22: putfield      #8                  // Field message:Ljava/lang/Object;
      25: aload_0
      26: aload         5
      28: putfield      #9                  // Field exception:Ljava/lang/Throwable;
      31: return

  public void run();
    Code:
       0: invokestatic  #10                 // Method org/apache/dubbo/common/threadlocal/InternalThreadLocalMap.getAndRemove:()Lorg/apache/dubbo/common/threadlocal/InternalThreadLocalMap;
       3: astore_1
       4: aload_0
       5: getfield      #7                  // Field state:Lorg/apache/dubbo/remoting/transport/dispatcher/ChannelEventRunnable$ChannelState;
       8: getstatic     #11                 // Field org/apache/dubbo/remoting/transport/dispatcher/ChannelEventRunnable$ChannelState.RECEIVED:Lorg/apache/dubbo/remoting/transport/dispatcher/ChannelEventRunnable$ChannelState;
      11: if_acmpne     99
      14: aload_0
      15: getfield      #6                  // Field handler:Lorg/apache/dubbo/remoting/ChannelHandler;
      18: aload_0
      19: getfield      #5                  // Field channel:Lorg/apache/dubbo/remoting/Channel;
      22: aload_0
      23: getfield      #8                  // Field message:Ljava/lang/Object;
      26: invokeinterface #12,  3           // InterfaceMethod org/apache/dubbo/remoting/ChannelHandler.received:(Lorg/apache/dubbo/remoting/Channel;Ljava/lang/Object;)V
      31: goto          508
      34: astore_2
      35: getstatic     #14                 // Field logger:Lorg/apache/dubbo/common/logger/ErrorTypeAwareLogger;
      38: ldc           #15                 // String 99-0
      40: ldc           #16                 // String unknown error in remoting module
      42: ldc           #17                 // String
      44: new           #18                 // class java/lang/StringBuilder
      47: dup
      48: invokespecial #19                 // Method java/lang/StringBuilder."<init>":()V
      51: ldc           #20                 // String ChannelEventRunnable handle
      53: invokevirtual #21                 // Method java/lang/StringBuilder.append:(Ljava/lang/String;)Ljava/lang/StringBuilder;
      56: aload_0
      57: getfield      #7                  // Field state:Lorg/apache/dubbo/remoting/transport/dispatcher/ChannelEventRunnable$ChannelState;
      60: invokevirtual #22                 // Method java/lang/StringBuilder.append:(Ljava/lang/Object;)Ljava/lang/StringBuilder;
      63: ldc           #23                 // String  operation error, channel is
      65: invokevirtual #21                 // Method java/lang/StringBuilder.append:(Ljava/lang/String;)Ljava/lang/StringBuilder;
      68: aload_0
      69: getfield      #5                  // Field channel:Lorg/apache/dubbo/remoting/Channel;
      72: invokevirtual #22                 // Method java/lang/StringBuilder.append:(Ljava/lang/Object;)Ljava/lang/StringBuilder;
      75: ldc           #24                 // String , message is
      77: invokevirtual #21                 // Method java/lang/StringBuilder.append:(Ljava/lang/String;)Ljava/lang/StringBuilder;
      80: aload_0
      81: getfield      #8                  // Field message:Ljava/lang/Object;
      84: invokevirtual #22                 // Method java/lang/StringBuilder.append:(Ljava/lang/Object;)Ljava/lang/StringBuilder;
      87: invokevirtual #25                 // Method java/lang/StringBuilder.toString:()Ljava/lang/String;
      90: aload_2
      91: invokeinterface #26,  6           // InterfaceMethod org/apache/dubbo/common/logger/ErrorTypeAwareLogger.warn:(Ljava/lang/String;Ljava/lang/String;Ljava/lang/String;Ljava/lang/String;Ljava/lang/Throwable;)V
      96: goto          508
      99: getstatic     #27                 // Field org/apache/dubbo/remoting/transport/dispatcher/ChannelEventRunnable$1.$SwitchMap$org$apache$dubbo$remoting$transport$dispatcher$ChannelEventRunnable$ChannelState:[I
     102: aload_0
     103: getfield      #7                  // Field state:Lorg/apache/dubbo/remoting/transport/dispatcher/ChannelEventRunnable$ChannelState;
     106: invokevirtual #28                 // Method org/apache/dubbo/remoting/transport/dispatcher/ChannelEventRunnable$ChannelState.ordinal:()I
     109: iaload
     110: tableswitch   { // 1 to 4
                     1: 140
                     2: 209
                     3: 278
                     4: 363
               default: 460
          }
     140: aload_0
     141: getfield      #6                  // Field handler:Lorg/apache/dubbo/remoting/ChannelHandler;
     144: aload_0
     145: getfield      #5                  // Field channel:Lorg/apache/dubbo/remoting/Channel;
     148: invokeinterface #29,  2           // InterfaceMethod org/apache/dubbo/remoting/ChannelHandler.connected:(Lorg/apache/dubbo/remoting/Channel;)V
     153: goto          508
     156: astore_2
     157: getstatic     #14                 // Field logger:Lorg/apache/dubbo/common/logger/ErrorTypeAwareLogger;
     160: ldc           #15                 // String 99-0
     162: ldc           #16                 // String unknown error in remoting module
     164: ldc           #17                 // String
     166: new           #18                 // class java/lang/StringBuilder
     169: dup
     170: invokespecial #19                 // Method java/lang/StringBuilder."<init>":()V
     173: ldc           #20                 // String ChannelEventRunnable handle
     175: invokevirtual #21                 // Method java/lang/StringBuilder.append:(Ljava/lang/String;)Ljava/lang/StringBuilder;
     178: aload_0
     179: getfield      #7                  // Field state:Lorg/apache/dubbo/remoting/transport/dispatcher/ChannelEventRunnable$ChannelState;
     182: invokevirtual #22                 // Method java/lang/StringBuilder.append:(Ljava/lang/Object;)Ljava/lang/StringBuilder;
     185: ldc           #23                 // String  operation error, channel is
     187: invokevirtual #21                 // Method java/lang/StringBuilder.append:(Ljava/lang/String;)Ljava/lang/StringBuilder;
     190: aload_0
     191: getfield      #5                  // Field channel:Lorg/apache/dubbo/remoting/Channel;
     194: invokevirtual #22                 // Method java/lang/StringBuilder.append:(Ljava/lang/Object;)Ljava/lang/StringBuilder;
     197: invokevirtual #25                 // Method java/lang/StringBuilder.toString:()Ljava/lang/String;
     200: aload_2
     201: invokeinterface #26,  6           // InterfaceMethod org/apache/dubbo/common/logger/ErrorTypeAwareLogger.warn:(Ljava/lang/String;Ljava/lang/String;Ljava/lang/String;Ljava/lang/String;Ljava/lang/Throwable;)V
     206: goto          508
     209: aload_0
     210: getfield      #6                  // Field handler:Lorg/apache/dubbo/remoting/ChannelHandler;
     213: aload_0
     214: getfield      #5                  // Field channel:Lorg/apache/dubbo/remoting/Channel;
     217: invokeinterface #30,  2           // InterfaceMethod org/apache/dubbo/remoting/ChannelHandler.disconnected:(Lorg/apache/dubbo/remoting/Channel;)V
     222: goto          508
     225: astore_2
     226: getstatic     #14                 // Field logger:Lorg/apache/dubbo/common/logger/ErrorTypeAwareLogger;
     229: ldc           #15                 // String 99-0
     231: ldc           #16                 // String unknown error in remoting module
     233: ldc           #17                 // String
     235: new           #18                 // class java/lang/StringBuilder
     238: dup
     239: invokespecial #19                 // Method java/lang/StringBuilder."<init>":()V
     242: ldc           #20                 // String ChannelEventRunnable handle
     244: invokevirtual #21                 // Method java/lang/StringBuilder.append:(Ljava/lang/String;)Ljava/lang/StringBuilder;
     247: aload_0
     248: getfield      #7                  // Field state:Lorg/apache/dubbo/remoting/transport/dispatcher/ChannelEventRunnable$ChannelState;
     251: invokevirtual #22                 // Method java/lang/StringBuilder.append:(Ljava/lang/Object;)Ljava/lang/StringBuilder;
     254: ldc           #23                 // String  operation error, channel is
     256: invokevirtual #21                 // Method java/lang/StringBuilder.append:(Ljava/lang/String;)Ljava/lang/StringBuilder;
     259: aload_0
     260: getfield      #5                  // Field channel:Lorg/apache/dubbo/remoting/Channel;
     263: invokevirtual #22                 // Method java/lang/StringBuilder.append:(Ljava/lang/Object;)Ljava/lang/StringBuilder;
     266: invokevirtual #25                 // Method java/lang/StringBuilder.toString:()Ljava/lang/String;
     269: aload_2
     270: invokeinterface #26,  6           // InterfaceMethod org/apache/dubbo/common/logger/ErrorTypeAwareLogger.warn:(Ljava/lang/String;Ljava/lang/String;Ljava/lang/String;Ljava/lang/String;Ljava/lang/Throwable;)V
     275: goto          508
     278: aload_0
     279: getfield      #6                  // Field handler:Lorg/apache/dubbo/remoting/ChannelHandler;
     282: aload_0
     283: getfield      #5                  // Field channel:Lorg/apache/dubbo/remoting/Channel;
     286: aload_0
     287: getfield      #8                  // Field message:Ljava/lang/Object;
     290: invokeinterface #31,  3           // InterfaceMethod org/apache/dubbo/remoting/ChannelHandler.sent:(Lorg/apache/dubbo/remoting/Channel;Ljava/lang/Object;)V
     295: goto          508
     298: astore_2
     299: getstatic     #14                 // Field logger:Lorg/apache/dubbo/common/logger/ErrorTypeAwareLogger;
     302: ldc           #15                 // String 99-0
     304: ldc           #16                 // String unknown error in remoting module
     306: ldc           #17                 // String
     308: new           #18                 // class java/lang/StringBuilder
     311: dup
     312: invokespecial #19                 // Method java/lang/StringBuilder."<init>":()V
     315: ldc           #20                 // String ChannelEventRunnable handle
     317: invokevirtual #21                 // Method java/lang/StringBuilder.append:(Ljava/lang/String;)Ljava/lang/StringBuilder;
     320: aload_0
     321: getfield      #7                  // Field state:Lorg/apache/dubbo/remoting/transport/dispatcher/ChannelEventRunnable$ChannelState;
     324: invokevirtual #22                 // Method java/lang/StringBuilder.append:(Ljava/lang/Object;)Ljava/lang/StringBuilder;
     327: ldc           #23                 // String  operation error, channel is
     329: invokevirtual #21                 // Method java/lang/StringBuilder.append:(Ljava/lang/String;)Ljava/lang/StringBuilder;
     332: aload_0
     333: getfield      #5                  // Field channel:Lorg/apache/dubbo/remoting/Channel;
     336: invokevirtual #22                 // Method java/lang/StringBuilder.append:(Ljava/lang/Object;)Ljava/lang/StringBuilder;
     339: ldc           #24                 // String , message is
     341: invokevirtual #21                 // Method java/lang/StringBuilder.append:(Ljava/lang/String;)Ljava/lang/StringBuilder;
     344: aload_0
     345: getfield      #8                  // Field message:Ljava/lang/Object;
     348: invokevirtual #22                 // Method java/lang/StringBuilder.append:(Ljava/lang/Object;)Ljava/lang/StringBuilder;
     351: invokevirtual #25                 // Method java/lang/StringBuilder.toString:()Ljava/lang/String;
     354: aload_2
     355: invokeinterface #26,  6           // InterfaceMethod org/apache/dubbo/common/logger/ErrorTypeAwareLogger.warn:(Ljava/lang/String;Ljava/lang/String;Ljava/lang/String;Ljava/lang/String;Ljava/lang/Throwable;)V
     360: goto          508
     363: aload_0
     364: getfield      #6                  // Field handler:Lorg/apache/dubbo/remoting/ChannelHandler;
     367: aload_0
     368: getfield      #5                  // Field channel:Lorg/apache/dubbo/remoting/Channel;
     371: aload_0
     372: getfield      #9                  // Field exception:Ljava/lang/Throwable;
     375: invokeinterface #32,  3           // InterfaceMethod org/apache/dubbo/remoting/ChannelHandler.caught:(Lorg/apache/dubbo/remoting/Channel;Ljava/lang/Throwable;)V
     380: goto          508
     383: astore_2
     384: getstatic     #14                 // Field logger:Lorg/apache/dubbo/common/logger/ErrorTypeAwareLogger;
     387: ldc           #15                 // String 99-0
     389: ldc           #16                 // String unknown error in remoting module
     391: ldc           #17                 // String
     393: new           #18                 // class java/lang/StringBuilder
     396: dup
     397: invokespecial #19                 // Method java/lang/StringBuilder."<init>":()V
     400: ldc           #20                 // String ChannelEventRunnable handle
     402: invokevirtual #21                 // Method java/lang/StringBuilder.append:(Ljava/lang/String;)Ljava/lang/StringBuilder;
     405: aload_0
     406: getfield      #7                  // Field state:Lorg/apache/dubbo/remoting/transport/dispatcher/ChannelEventRunnable$ChannelState;
     409: invokevirtual #22                 // Method java/lang/StringBuilder.append:(Ljava/lang/Object;)Ljava/lang/StringBuilder;
     412: ldc           #23                 // String  operation error, channel is
     414: invokevirtual #21                 // Method java/lang/StringBuilder.append:(Ljava/lang/String;)Ljava/lang/StringBuilder;
     417: aload_0
     418: getfield      #5                  // Field channel:Lorg/apache/dubbo/remoting/Channel;
     421: invokevirtual #22                 // Method java/lang/StringBuilder.append:(Ljava/lang/Object;)Ljava/lang/StringBuilder;
     424: ldc           #33                 // String , message is:
     426: invokevirtual #21                 // Method java/lang/StringBuilder.append:(Ljava/lang/String;)Ljava/lang/StringBuilder;
     429: aload_0
     430: getfield      #8                  // Field message:Ljava/lang/Object;
     433: invokevirtual #22                 // Method java/lang/StringBuilder.append:(Ljava/lang/Object;)Ljava/lang/StringBuilder;
     436: ldc           #34                 // String , exception is
     438: invokevirtual #21                 // Method java/lang/StringBuilder.append:(Ljava/lang/String;)Ljava/lang/StringBuilder;
     441: aload_0
     442: getfield      #9                  // Field exception:Ljava/lang/Throwable;
     445: invokevirtual #22                 // Method java/lang/StringBuilder.append:(Ljava/lang/Object;)Ljava/lang/StringBuilder;
     448: invokevirtual #25                 // Method java/lang/StringBuilder.toString:()Ljava/lang/String;
     451: aload_2
     452: invokeinterface #26,  6           // InterfaceMethod org/apache/dubbo/common/logger/ErrorTypeAwareLogger.warn:(Ljava/lang/String;Ljava/lang/String;Ljava/lang/String;Ljava/lang/String;Ljava/lang/Throwable;)V
     457: goto          508
     460: getstatic     #14                 // Field logger:Lorg/apache/dubbo/common/logger/ErrorTypeAwareLogger;
     463: ldc           #15                 // String 99-0
     465: ldc           #16                 // String unknown error in remoting module
     467: ldc           #17                 // String
     469: new           #18                 // class java/lang/StringBuilder
     472: dup
     473: invokespecial #19                 // Method java/lang/StringBuilder."<init>":()V
     476: ldc           #35                 // String unknown state:
     478: invokevirtual #21                 // Method java/lang/StringBuilder.append:(Ljava/lang/String;)Ljava/lang/StringBuilder;
     481: aload_0
     482: getfield      #7                  // Field state:Lorg/apache/dubbo/remoting/transport/dispatcher/ChannelEventRunnable$ChannelState;
     485: invokevirtual #22                 // Method java/lang/StringBuilder.append:(Ljava/lang/Object;)Ljava/lang/StringBuilder;
     488: ldc           #24                 // String , message is
     490: invokevirtual #21                 // Method java/lang/StringBuilder.append:(Ljava/lang/String;)Ljava/lang/StringBuilder;
     493: aload_0
     494: getfield      #8                  // Field message:Ljava/lang/Object;
     497: invokevirtual #22                 // Method java/lang/StringBuilder.append:(Ljava/lang/Object;)Ljava/lang/StringBuilder;
     500: invokevirtual #25                 // Method java/lang/StringBuilder.toString:()Ljava/lang/String;
     503: invokeinterface #36,  5           // InterfaceMethod org/apache/dubbo/common/logger/ErrorTypeAwareLogger.warn:(Ljava/lang/String;Ljava/lang/String;Ljava/lang/String;Ljava/lang/String;)V
     508: aload_1
     509: invokestatic  #37                 // Method org/apache/dubbo/common/threadlocal/InternalThreadLocalMap.set:(Lorg/apache/dubbo/common/threadlocal/InternalThreadLocalMap;)V
     512: goto          522
     515: astore_3
     516: aload_1
     517: invokestatic  #37                 // Method org/apache/dubbo/common/threadlocal/InternalThreadLocalMap.set:(Lorg/apache/dubbo/common/threadlocal/InternalThreadLocalMap;)V
     520: aload_3
     521: athrow
     522: return
    Exception table:
       from    to  target type
          14    31    34   Class java/lang/Exception
         140   153   156   Class java/lang/Exception
         209   222   225   Class java/lang/Exception
         278   295   298   Class java/lang/Exception
         363   380   383   Class java/lang/Exception
           4   508   515   any

  static {};
    Code:
       0: ldc           #38                 // class org/apache/dubbo/remoting/transport/dispatcher/ChannelEventRunnable
       2: invokestatic  #39                 // Method org/apache/dubbo/common/logger/LoggerFactory.getErrorTypeAwareLogger:(Ljava/lang/Class;)Lorg/apache/dubbo/common/logger/ErrorTypeAwareLogger;
       5: putstatic     #14                 // Field logger:Lorg/apache/dubbo/common/logger/ErrorTypeAwareLogger;
       8: return
}
