Compiled from "WrappedChannelHandler.java"
public class org.apache.dubbo.remoting.transport.dispatcher.WrappedChannelHandler implements org.apache.dubbo.remoting.transport.ChannelHandlerDelegate {
  protected static final org.apache.dubbo.common.logger.ErrorTypeAwareLogger logger;

  protected final org.apache.dubbo.remoting.ChannelHandler handler;

  protected final org.apache.dubbo.common.URL url;

  protected final org.apache.dubbo.rpc.executor.ExecutorSupport executorSupport;

  public org.apache.dubbo.remoting.transport.dispatcher.WrappedChannelHandler(org.apache.dubbo.remoting.ChannelHandler, org.apache.dubbo.common.URL);
    Code:
       0: aload_0
       1: invokespecial #1                  // Method java/lang/Object."<init>":()V
       4: aload_0
       5: aload_1
       6: putfield      #2                  // Field handler:Lorg/apache/dubbo/remoting/ChannelHandler;
       9: aload_0
      10: aload_2
      11: putfield      #3                  // Field url:Lorg/apache/dubbo/common/URL;
      14: aload_0
      15: aload_2
      16: invokevirtual #4                  // Method org/apache/dubbo/common/URL.getOrDefaultApplicationModel:()Lorg/apache/dubbo/rpc/model/ApplicationModel;
      19: invokestatic  #5                  // InterfaceMethod org/apache/dubbo/common/threadpool/manager/ExecutorRepository.getInstance:(Lorg/apache/dubbo/rpc/model/ApplicationModel;)Lorg/apache/dubbo/common/threadpool/manager/ExecutorRepository;
      22: aload_2
      23: invokeinterface #6,  2            // InterfaceMethod org/apache/dubbo/common/threadpool/manager/ExecutorRepository.getExecutorSupport:(Lorg/apache/dubbo/common/URL;)Lorg/apache/dubbo/rpc/executor/ExecutorSupport;
      28: putfield      #7                  // Field executorSupport:Lorg/apache/dubbo/rpc/executor/ExecutorSupport;
      31: return

  public void close();
    Code:
       0: return

  public void connected(org.apache.dubbo.remoting.Channel) throws org.apache.dubbo.remoting.RemotingException;
    Code:
       0: aload_0
       1: getfield      #2                  // Field handler:Lorg/apache/dubbo/remoting/ChannelHandler;
       4: aload_1
       5: invokeinterface #8,  2            // InterfaceMethod org/apache/dubbo/remoting/ChannelHandler.connected:(Lorg/apache/dubbo/remoting/Channel;)V
      10: return

  public void disconnected(org.apache.dubbo.remoting.Channel) throws org.apache.dubbo.remoting.RemotingException;
    Code:
       0: aload_0
       1: getfield      #2                  // Field handler:Lorg/apache/dubbo/remoting/ChannelHandler;
       4: aload_1
       5: invokeinterface #9,  2            // InterfaceMethod org/apache/dubbo/remoting/ChannelHandler.disconnected:(Lorg/apache/dubbo/remoting/Channel;)V
      10: return

  public void sent(org.apache.dubbo.remoting.Channel, java.lang.Object) throws org.apache.dubbo.remoting.RemotingException;
    Code:
       0: aload_0
       1: getfield      #2                  // Field handler:Lorg/apache/dubbo/remoting/ChannelHandler;
       4: aload_1
       5: aload_2
       6: invokeinterface #10,  3           // InterfaceMethod org/apache/dubbo/remoting/ChannelHandler.sent:(Lorg/apache/dubbo/remoting/Channel;Ljava/lang/Object;)V
      11: return

  public void received(org.apache.dubbo.remoting.Channel, java.lang.Object) throws org.apache.dubbo.remoting.RemotingException;
    Code:
       0: aload_0
       1: getfield      #2                  // Field handler:Lorg/apache/dubbo/remoting/ChannelHandler;
       4: aload_1
       5: aload_2
       6: invokeinterface #11,  3           // InterfaceMethod org/apache/dubbo/remoting/ChannelHandler.received:(Lorg/apache/dubbo/remoting/Channel;Ljava/lang/Object;)V
      11: return

  public void caught(org.apache.dubbo.remoting.Channel, java.lang.Throwable) throws org.apache.dubbo.remoting.RemotingException;
    Code:
       0: aload_0
       1: getfield      #2                  // Field handler:Lorg/apache/dubbo/remoting/ChannelHandler;
       4: aload_1
       5: aload_2
       6: invokeinterface #12,  3           // InterfaceMethod org/apache/dubbo/remoting/ChannelHandler.caught:(Lorg/apache/dubbo/remoting/Channel;Ljava/lang/Throwable;)V
      11: return

  protected void sendFeedback(org.apache.dubbo.remoting.Channel, org.apache.dubbo.remoting.exchange.Request, java.lang.Throwable) throws org.apache.dubbo.remoting.RemotingException;
    Code:
       0: aload_2
       1: invokevirtual #13                 // Method org/apache/dubbo/remoting/exchange/Request.isTwoWay:()Z
       4: ifne          8
       7: return
       8: new           #14                 // class java/lang/StringBuilder
      11: dup
      12: invokespecial #15                 // Method java/lang/StringBuilder."<init>":()V
      15: ldc           #16                 // String Server side(
      17: invokevirtual #17                 // Method java/lang/StringBuilder.append:(Ljava/lang/String;)Ljava/lang/StringBuilder;
      20: aload_0
      21: getfield      #3                  // Field url:Lorg/apache/dubbo/common/URL;
      24: invokevirtual #18                 // Method org/apache/dubbo/common/URL.getIp:()Ljava/lang/String;
      27: invokevirtual #17                 // Method java/lang/StringBuilder.append:(Ljava/lang/String;)Ljava/lang/StringBuilder;
      30: ldc           #19                 // String ,
      32: invokevirtual #17                 // Method java/lang/StringBuilder.append:(Ljava/lang/String;)Ljava/lang/StringBuilder;
      35: aload_0
      36: getfield      #3                  // Field url:Lorg/apache/dubbo/common/URL;
      39: invokevirtual #20                 // Method org/apache/dubbo/common/URL.getPort:()I
      42: invokevirtual #21                 // Method java/lang/StringBuilder.append:(I)Ljava/lang/StringBuilder;
      45: ldc           #22                 // String ) thread pool is exhausted, detail msg:
      47: invokevirtual #17                 // Method java/lang/StringBuilder.append:(Ljava/lang/String;)Ljava/lang/StringBuilder;
      50: aload_3
      51: invokevirtual #23                 // Method java/lang/Throwable.getMessage:()Ljava/lang/String;
      54: invokevirtual #17                 // Method java/lang/StringBuilder.append:(Ljava/lang/String;)Ljava/lang/StringBuilder;
      57: invokevirtual #24                 // Method java/lang/StringBuilder.toString:()Ljava/lang/String;
      60: astore        4
      62: new           #25                 // class org/apache/dubbo/remoting/exchange/Response
      65: dup
      66: aload_2
      67: invokevirtual #26                 // Method org/apache/dubbo/remoting/exchange/Request.getId:()J
      70: aload_2
      71: invokevirtual #27                 // Method org/apache/dubbo/remoting/exchange/Request.getVersion:()Ljava/lang/String;
      74: invokespecial #28                 // Method org/apache/dubbo/remoting/exchange/Response."<init>":(JLjava/lang/String;)V
      77: astore        5
      79: aload         5
      81: bipush        100
      83: invokevirtual #29                 // Method org/apache/dubbo/remoting/exchange/Response.setStatus:(B)V
      86: aload         5
      88: aload         4
      90: invokevirtual #30                 // Method org/apache/dubbo/remoting/exchange/Response.setErrorMessage:(Ljava/lang/String;)V
      93: aload_1
      94: aload         5
      96: invokeinterface #31,  2           // InterfaceMethod org/apache/dubbo/remoting/Channel.send:(Ljava/lang/Object;)V
     101: return

  public org.apache.dubbo.remoting.ChannelHandler getHandler();
    Code:
       0: aload_0
       1: getfield      #2                  // Field handler:Lorg/apache/dubbo/remoting/ChannelHandler;
       4: instanceof    #32                 // class org/apache/dubbo/remoting/transport/ChannelHandlerDelegate
       7: ifeq          23
      10: aload_0
      11: getfield      #2                  // Field handler:Lorg/apache/dubbo/remoting/ChannelHandler;
      14: checkcast     #32                 // class org/apache/dubbo/remoting/transport/ChannelHandlerDelegate
      17: invokeinterface #33,  1           // InterfaceMethod org/apache/dubbo/remoting/transport/ChannelHandlerDelegate.getHandler:()Lorg/apache/dubbo/remoting/ChannelHandler;
      22: areturn
      23: aload_0
      24: getfield      #2                  // Field handler:Lorg/apache/dubbo/remoting/ChannelHandler;
      27: areturn

  public org.apache.dubbo.common.URL getUrl();
    Code:
       0: aload_0
       1: getfield      #3                  // Field url:Lorg/apache/dubbo/common/URL;
       4: areturn

  public java.util.concurrent.ExecutorService getPreferredExecutorService(java.lang.Object);
    Code:
       0: aload_1
       1: instanceof    #25                 // class org/apache/dubbo/remoting/exchange/Response
       4: ifeq          60
       7: aload_1
       8: checkcast     #25                 // class org/apache/dubbo/remoting/exchange/Response
      11: astore_2
      12: aload_2
      13: invokevirtual #34                 // Method org/apache/dubbo/remoting/exchange/Response.getId:()J
      16: invokestatic  #35                 // Method org/apache/dubbo/remoting/exchange/support/DefaultFuture.getFuture:(J)Lorg/apache/dubbo/remoting/exchange/support/DefaultFuture;
      19: astore_3
      20: aload_3
      21: ifnonnull     29
      24: aload_0
      25: invokevirtual #36                 // Method getSharedExecutorService:()Ljava/util/concurrent/ExecutorService;
      28: areturn
      29: aload_3
      30: invokevirtual #37                 // Method org/apache/dubbo/remoting/exchange/support/DefaultFuture.getExecutor:()Ljava/util/concurrent/ExecutorService;
      33: astore        4
      35: aload         4
      37: ifnull        50
      40: aload         4
      42: invokeinterface #38,  1           // InterfaceMethod java/util/concurrent/ExecutorService.isShutdown:()Z
      47: ifeq          57
      50: aload_0
      51: aload_1
      52: invokevirtual #39                 // Method getSharedExecutorService:(Ljava/lang/Object;)Ljava/util/concurrent/ExecutorService;
      55: astore        4
      57: aload         4
      59: areturn
      60: aload_0
      61: aload_1
      62: invokevirtual #39                 // Method getSharedExecutorService:(Ljava/lang/Object;)Ljava/util/concurrent/ExecutorService;
      65: areturn

  public java.util.concurrent.ExecutorService getSharedExecutorService(java.lang.Object);
    Code:
       0: aload_0
       1: getfield      #7                  // Field executorSupport:Lorg/apache/dubbo/rpc/executor/ExecutorSupport;
       4: aload_1
       5: invokeinterface #40,  2           // InterfaceMethod org/apache/dubbo/rpc/executor/ExecutorSupport.getExecutor:(Ljava/lang/Object;)Ljava/util/concurrent/Executor;
      10: astore_2
      11: aload_2
      12: ifnull        22
      15: aload_2
      16: checkcast     #41                 // class java/util/concurrent/ExecutorService
      19: goto          26
      22: aload_0
      23: invokevirtual #36                 // Method getSharedExecutorService:()Ljava/util/concurrent/ExecutorService;
      26: areturn

  public java.util.concurrent.ExecutorService getSharedExecutorService();
    Code:
       0: aload_0
       1: getfield      #3                  // Field url:Lorg/apache/dubbo/common/URL;
       4: invokevirtual #42                 // Method org/apache/dubbo/common/URL.getApplicationModel:()Lorg/apache/dubbo/rpc/model/ApplicationModel;
       7: ifnull        23
      10: aload_0
      11: getfield      #3                  // Field url:Lorg/apache/dubbo/common/URL;
      14: invokevirtual #42                 // Method org/apache/dubbo/common/URL.getApplicationModel:()Lorg/apache/dubbo/rpc/model/ApplicationModel;
      17: invokevirtual #43                 // Method org/apache/dubbo/rpc/model/ApplicationModel.isDestroyed:()Z
      20: ifeq          27
      23: invokestatic  #44                 // Method org/apache/dubbo/common/resource/GlobalResourcesRepository.getGlobalExecutorService:()Ljava/util/concurrent/ExecutorService;
      26: areturn
      27: aload_0
      28: getfield      #3                  // Field url:Lorg/apache/dubbo/common/URL;
      31: invokevirtual #4                  // Method org/apache/dubbo/common/URL.getOrDefaultApplicationModel:()Lorg/apache/dubbo/rpc/model/ApplicationModel;
      34: astore_1
      35: aload_1
      36: invokestatic  #5                  // InterfaceMethod org/apache/dubbo/common/threadpool/manager/ExecutorRepository.getInstance:(Lorg/apache/dubbo/rpc/model/ApplicationModel;)Lorg/apache/dubbo/common/threadpool/manager/ExecutorRepository;
      39: astore_2
      40: aload_2
      41: aload_0
      42: getfield      #3                  // Field url:Lorg/apache/dubbo/common/URL;
      45: invokeinterface #45,  2           // InterfaceMethod org/apache/dubbo/common/threadpool/manager/ExecutorRepository.getExecutor:(Lorg/apache/dubbo/common/URL;)Ljava/util/concurrent/ExecutorService;
      50: astore_3
      51: aload_3
      52: ifnonnull     66
      55: aload_2
      56: aload_0
      57: getfield      #3                  // Field url:Lorg/apache/dubbo/common/URL;
      60: invokeinterface #46,  2           // InterfaceMethod org/apache/dubbo/common/threadpool/manager/ExecutorRepository.createExecutorIfAbsent:(Lorg/apache/dubbo/common/URL;)Ljava/util/concurrent/ExecutorService;
      65: astore_3
      66: aload_3
      67: areturn

  public java.util.concurrent.ExecutorService getExecutorService();
    Code:
       0: aload_0
       1: invokevirtual #36                 // Method getSharedExecutorService:()Ljava/util/concurrent/ExecutorService;
       4: areturn

  static {};
    Code:
       0: ldc           #47                 // class org/apache/dubbo/remoting/transport/dispatcher/WrappedChannelHandler
       2: invokestatic  #48                 // Method org/apache/dubbo/common/logger/LoggerFactory.getErrorTypeAwareLogger:(Ljava/lang/Class;)Lorg/apache/dubbo/common/logger/ErrorTypeAwareLogger;
       5: putstatic     #49                 // Field logger:Lorg/apache/dubbo/common/logger/ErrorTypeAwareLogger;
       8: return
}
