Compiled from "SslClientTlsHandler.java"
public class org.apache.dubbo.remoting.transport.netty4.ssl.SslClientTlsHandler extends io.netty.channel.ChannelInboundHandlerAdapter {
  private static final org.apache.dubbo.common.logger.ErrorTypeAwareLogger logger;

  private final io.netty.handler.ssl.SslContext sslContext;

  public org.apache.dubbo.remoting.transport.netty4.ssl.SslClientTlsHandler(org.apache.dubbo.common.URL);
    Code:
       0: aload_0
       1: aload_1
       2: invokestatic  #2                  // Method org/apache/dubbo/remoting/transport/netty4/ssl/SslContexts.buildClientSslContext:(Lorg/apache/dubbo/common/URL;)Lio/netty/handler/ssl/SslContext;
       5: invokespecial #3                  // Method "<init>":(Lio/netty/handler/ssl/SslContext;)V
       8: return

  public org.apache.dubbo.remoting.transport.netty4.ssl.SslClientTlsHandler(io.netty.handler.ssl.SslContext);
    Code:
       0: aload_0
       1: invokespecial #4                  // Method io/netty/channel/ChannelInboundHandlerAdapter."<init>":()V
       4: aload_0
       5: aload_1
       6: putfield      #5                  // Field sslContext:Lio/netty/handler/ssl/SslContext;
       9: return

  public void handlerAdded(io.netty.channel.ChannelHandlerContext);
    Code:
       0: aload_0
       1: getfield      #5                  // Field sslContext:Lio/netty/handler/ssl/SslContext;
       4: aload_1
       5: invokeinterface #6,  1            // InterfaceMethod io/netty/channel/ChannelHandlerContext.alloc:()Lio/netty/buffer/ByteBufAllocator;
      10: invokevirtual #7                  // Method io/netty/handler/ssl/SslContext.newEngine:(Lio/netty/buffer/ByteBufAllocator;)Ljavax/net/ssl/SSLEngine;
      13: astore_2
      14: aload_1
      15: invokeinterface #8,  1            // InterfaceMethod io/netty/channel/ChannelHandlerContext.pipeline:()Lio/netty/channel/ChannelPipeline;
      20: aload_1
      21: invokeinterface #9,  1            // InterfaceMethod io/netty/channel/ChannelHandlerContext.name:()Ljava/lang/String;
      26: aconst_null
      27: new           #10                 // class io/netty/handler/ssl/SslHandler
      30: dup
      31: aload_2
      32: iconst_0
      33: invokespecial #11                 // Method io/netty/handler/ssl/SslHandler."<init>":(Ljavax/net/ssl/SSLEngine;Z)V
      36: invokeinterface #12,  4           // InterfaceMethod io/netty/channel/ChannelPipeline.addAfter:(Ljava/lang/String;Ljava/lang/String;Lio/netty/channel/ChannelHandler;)Lio/netty/channel/ChannelPipeline;
      41: pop
      42: return

  public void userEventTriggered(io.netty.channel.ChannelHandlerContext, java.lang.Object) throws java.lang.Exception;
    Code:
       0: aload_2
       1: instanceof    #13                 // class io/netty/handler/ssl/SslHandshakeCompletionEvent
       4: ifeq          123
       7: aload_2
       8: checkcast     #13                 // class io/netty/handler/ssl/SslHandshakeCompletionEvent
      11: astore_3
      12: aload_3
      13: invokevirtual #14                 // Method io/netty/handler/ssl/SslHandshakeCompletionEvent.isSuccess:()Z
      16: ifeq          92
      19: aload_1
      20: invokeinterface #8,  1            // InterfaceMethod io/netty/channel/ChannelHandlerContext.pipeline:()Lio/netty/channel/ChannelPipeline;
      25: ldc           #10                 // class io/netty/handler/ssl/SslHandler
      27: invokeinterface #15,  2           // InterfaceMethod io/netty/channel/ChannelPipeline.get:(Ljava/lang/Class;)Lio/netty/channel/ChannelHandler;
      32: checkcast     #10                 // class io/netty/handler/ssl/SslHandler
      35: invokevirtual #16                 // Method io/netty/handler/ssl/SslHandler.engine:()Ljavax/net/ssl/SSLEngine;
      38: invokevirtual #17                 // Method javax/net/ssl/SSLEngine.getSession:()Ljavax/net/ssl/SSLSession;
      41: astore        4
      43: getstatic     #18                 // Field logger:Lorg/apache/dubbo/common/logger/ErrorTypeAwareLogger;
      46: new           #19                 // class java/lang/StringBuilder
      49: dup
      50: invokespecial #20                 // Method java/lang/StringBuilder."<init>":()V
      53: ldc           #21                 // String TLS negotiation succeed with:
      55: invokevirtual #22                 // Method java/lang/StringBuilder.append:(Ljava/lang/String;)Ljava/lang/StringBuilder;
      58: aload         4
      60: invokeinterface #23,  1           // InterfaceMethod javax/net/ssl/SSLSession.getPeerHost:()Ljava/lang/String;
      65: invokevirtual #22                 // Method java/lang/StringBuilder.append:(Ljava/lang/String;)Ljava/lang/StringBuilder;
      68: invokevirtual #24                 // Method java/lang/StringBuilder.toString:()Ljava/lang/String;
      71: invokeinterface #25,  2           // InterfaceMethod org/apache/dubbo/common/logger/ErrorTypeAwareLogger.info:(Ljava/lang/String;)V
      76: aload_1
      77: invokeinterface #8,  1            // InterfaceMethod io/netty/channel/ChannelHandlerContext.pipeline:()Lio/netty/channel/ChannelPipeline;
      82: aload_0
      83: invokeinterface #26,  2           // InterfaceMethod io/netty/channel/ChannelPipeline.remove:(Lio/netty/channel/ChannelHandler;)Lio/netty/channel/ChannelPipeline;
      88: pop
      89: goto          123
      92: getstatic     #18                 // Field logger:Lorg/apache/dubbo/common/logger/ErrorTypeAwareLogger;
      95: ldc           #27                 // String 99-0
      97: ldc           #28                 // String unknown error in remoting module
      99: ldc           #29                 // String
     101: ldc           #30                 // String TLS negotiation failed when trying to accept new connection.
     103: aload_3
     104: invokevirtual #31                 // Method io/netty/handler/ssl/SslHandshakeCompletionEvent.cause:()Ljava/lang/Throwable;
     107: invokeinterface #32,  6           // InterfaceMethod org/apache/dubbo/common/logger/ErrorTypeAwareLogger.error:(Ljava/lang/String;Ljava/lang/String;Ljava/lang/String;Ljava/lang/String;Ljava/lang/Throwable;)V
     112: aload_1
     113: aload_3
     114: invokevirtual #31                 // Method io/netty/handler/ssl/SslHandshakeCompletionEvent.cause:()Ljava/lang/Throwable;
     117: invokeinterface #33,  2           // InterfaceMethod io/netty/channel/ChannelHandlerContext.fireExceptionCaught:(Ljava/lang/Throwable;)Lio/netty/channel/ChannelHandlerContext;
     122: pop
     123: return

  static {};
    Code:
       0: ldc           #34                 // class org/apache/dubbo/remoting/transport/netty4/ssl/SslClientTlsHandler
       2: invokestatic  #35                 // Method org/apache/dubbo/common/logger/LoggerFactory.getErrorTypeAwareLogger:(Ljava/lang/Class;)Lorg/apache/dubbo/common/logger/ErrorTypeAwareLogger;
       5: putstatic     #18                 // Field logger:Lorg/apache/dubbo/common/logger/ErrorTypeAwareLogger;
       8: return
}
