Compiled from "NacosNamingServiceUtils.java"
public class org.apache.dubbo.registry.nacos.util.NacosNamingServiceUtils {
  private static final org.apache.dubbo.common.logger.ErrorTypeAwareLogger logger;

  private static final java.lang.String NACOS_GROUP_KEY;

  private static final java.lang.String NACOS_RETRY_KEY;

  private static final java.lang.String NACOS_RETRY_WAIT_KEY;

  private static final java.lang.String NACOS_CHECK_KEY;

  private org.apache.dubbo.registry.nacos.util.NacosNamingServiceUtils();
    Code:
       0: aload_0
       1: invokespecial #3                  // Method java/lang/Object."<init>":()V
       4: new           #4                  // class java/lang/IllegalStateException
       7: dup
       8: ldc           #5                  // String NacosNamingServiceUtils should not be instantiated
      10: invokespecial #6                  // Method java/lang/IllegalStateException."<init>":(Ljava/lang/String;)V
      13: athrow

  public static com.alibaba.nacos.api.naming.pojo.Instance toInstance(org.apache.dubbo.registry.client.ServiceInstance);
    Code:
       0: new           #7                  // class com/alibaba/nacos/api/naming/pojo/Instance
       3: dup
       4: invokespecial #8                  // Method com/alibaba/nacos/api/naming/pojo/Instance."<init>":()V
       7: astore_1
       8: aload_1
       9: aload_0
      10: invokeinterface #9,  1            // InterfaceMethod org/apache/dubbo/registry/client/ServiceInstance.getServiceName:()Ljava/lang/String;
      15: invokevirtual #10                 // Method com/alibaba/nacos/api/naming/pojo/Instance.setServiceName:(Ljava/lang/String;)V
      18: aload_1
      19: aload_0
      20: invokeinterface #11,  1           // InterfaceMethod org/apache/dubbo/registry/client/ServiceInstance.getHost:()Ljava/lang/String;
      25: invokevirtual #12                 // Method com/alibaba/nacos/api/naming/pojo/Instance.setIp:(Ljava/lang/String;)V
      28: aload_1
      29: aload_0
      30: invokeinterface #13,  1           // InterfaceMethod org/apache/dubbo/registry/client/ServiceInstance.getPort:()I
      35: invokevirtual #14                 // Method com/alibaba/nacos/api/naming/pojo/Instance.setPort:(I)V
      38: aload_1
      39: aload_0
      40: invokeinterface #15,  1           // InterfaceMethod org/apache/dubbo/registry/client/ServiceInstance.getSortedMetadata:()Ljava/util/SortedMap;
      45: invokevirtual #16                 // Method com/alibaba/nacos/api/naming/pojo/Instance.setMetadata:(Ljava/util/Map;)V
      48: aload_1
      49: aload_0
      50: invokeinterface #17,  1           // InterfaceMethod org/apache/dubbo/registry/client/ServiceInstance.isEnabled:()Z
      55: invokevirtual #18                 // Method com/alibaba/nacos/api/naming/pojo/Instance.setEnabled:(Z)V
      58: aload_1
      59: aload_0
      60: invokeinterface #19,  1           // InterfaceMethod org/apache/dubbo/registry/client/ServiceInstance.isHealthy:()Z
      65: invokevirtual #20                 // Method com/alibaba/nacos/api/naming/pojo/Instance.setHealthy:(Z)V
      68: aload_1
      69: areturn

  public static org.apache.dubbo.registry.client.ServiceInstance toServiceInstance(org.apache.dubbo.common.URL, com.alibaba.nacos.api.naming.pojo.Instance);
    Code:
       0: new           #21                 // class org/apache/dubbo/registry/client/DefaultServiceInstance
       3: dup
       4: aload_1
       5: invokevirtual #22                 // Method com/alibaba/nacos/api/naming/pojo/Instance.getServiceName:()Ljava/lang/String;
       8: invokestatic  #23                 // Method com/alibaba/nacos/api/naming/utils/NamingUtils.getServiceName:(Ljava/lang/String;)Ljava/lang/String;
      11: aload_1
      12: invokevirtual #24                 // Method com/alibaba/nacos/api/naming/pojo/Instance.getIp:()Ljava/lang/String;
      15: aload_1
      16: invokevirtual #25                 // Method com/alibaba/nacos/api/naming/pojo/Instance.getPort:()I
      19: invokestatic  #26                 // Method java/lang/Integer.valueOf:(I)Ljava/lang/Integer;
      22: aload_0
      23: invokevirtual #27                 // Method org/apache/dubbo/common/URL.getScopeModel:()Lorg/apache/dubbo/rpc/model/ScopeModel;
      26: invokestatic  #28                 // Method org/apache/dubbo/rpc/model/ScopeModelUtil.getApplicationModel:(Lorg/apache/dubbo/rpc/model/ScopeModel;)Lorg/apache/dubbo/rpc/model/ApplicationModel;
      29: invokespecial #29                 // Method org/apache/dubbo/registry/client/DefaultServiceInstance."<init>":(Ljava/lang/String;Ljava/lang/String;Ljava/lang/Integer;Lorg/apache/dubbo/rpc/model/ApplicationModel;)V
      32: astore_2
      33: aload_2
      34: aload_1
      35: invokevirtual #30                 // Method com/alibaba/nacos/api/naming/pojo/Instance.getMetadata:()Ljava/util/Map;
      38: invokevirtual #31                 // Method org/apache/dubbo/registry/client/DefaultServiceInstance.setMetadata:(Ljava/util/Map;)V
      41: aload_2
      42: aload_1
      43: invokevirtual #32                 // Method com/alibaba/nacos/api/naming/pojo/Instance.isEnabled:()Z
      46: invokevirtual #33                 // Method org/apache/dubbo/registry/client/DefaultServiceInstance.setEnabled:(Z)V
      49: aload_2
      50: aload_1
      51: invokevirtual #34                 // Method com/alibaba/nacos/api/naming/pojo/Instance.isHealthy:()Z
      54: invokevirtual #35                 // Method org/apache/dubbo/registry/client/DefaultServiceInstance.setHealthy:(Z)V
      57: aload_2
      58: areturn

  public static java.lang.String getGroup(org.apache.dubbo.common.URL);
    Code:
       0: aload_0
       1: ldc           #36                 // String group
       3: ldc           #37                 // String DEFAULT_GROUP
       5: invokevirtual #38                 // Method org/apache/dubbo/common/URL.getParameter:(Ljava/lang/String;Ljava/lang/String;)Ljava/lang/String;
       8: astore_1
       9: aload_0
      10: ldc           #40                 // String nacos.group
      12: aload_1
      13: invokevirtual #38                 // Method org/apache/dubbo/common/URL.getParameter:(Ljava/lang/String;Ljava/lang/String;)Ljava/lang/String;
      16: areturn

  public static org.apache.dubbo.registry.nacos.NacosNamingServiceWrapper createNamingService(org.apache.dubbo.common.URL);
    Code:
       0: aload_0
       1: ldc           #41                 // String nacos.check
       3: iconst_1
       4: invokevirtual #42                 // Method org/apache/dubbo/common/URL.getParameter:(Ljava/lang/String;Z)Z
       7: istore_1
       8: aload_0
       9: ldc           #43                 // String nacos.retry
      11: bipush        10
      13: invokevirtual #44                 // Method org/apache/dubbo/common/URL.getPositiveParameter:(Ljava/lang/String;I)I
      16: istore_2
      17: aload_0
      18: ldc           #45                 // String nacos.retry-wait
      20: bipush        10
      22: invokevirtual #44                 // Method org/apache/dubbo/common/URL.getPositiveParameter:(Ljava/lang/String;I)I
      25: istore_3
      26: new           #46                 // class org/apache/dubbo/registry/nacos/NacosConnectionManager
      29: dup
      30: aload_0
      31: iload_1
      32: iload_2
      33: iload_3
      34: invokespecial #47                 // Method org/apache/dubbo/registry/nacos/NacosConnectionManager."<init>":(Lorg/apache/dubbo/common/URL;ZII)V
      37: astore        4
      39: new           #48                 // class org/apache/dubbo/registry/nacos/NacosNamingServiceWrapper
      42: dup
      43: aload         4
      45: iload_2
      46: iload_3
      47: invokespecial #49                 // Method org/apache/dubbo/registry/nacos/NacosNamingServiceWrapper."<init>":(Lorg/apache/dubbo/registry/nacos/NacosConnectionManager;II)V
      50: areturn

  static {};
    Code:
       0: ldc           #39                 // class org/apache/dubbo/registry/nacos/util/NacosNamingServiceUtils
       2: invokestatic  #50                 // Method org/apache/dubbo/common/logger/LoggerFactory.getErrorTypeAwareLogger:(Ljava/lang/Class;)Lorg/apache/dubbo/common/logger/ErrorTypeAwareLogger;
       5: putstatic     #51                 // Field logger:Lorg/apache/dubbo/common/logger/ErrorTypeAwareLogger;
       8: return
}
