Compiled from "AbstractCacheFactory.java"
public abstract class org.apache.dubbo.cache.support.AbstractCacheFactory implements org.apache.dubbo.cache.CacheFactory {
  private final java.util.concurrent.ConcurrentMap<java.lang.String, org.apache.dubbo.cache.Cache> caches;

  private final java.lang.Object MONITOR;

  public org.apache.dubbo.cache.support.AbstractCacheFactory();
    Code:
       0: aload_0
       1: invokespecial #2                  // Method java/lang/Object."<init>":()V
       4: aload_0
       5: new           #3                  // class java/util/concurrent/ConcurrentHashMap
       8: dup
       9: invokespecial #4                  // Method java/util/concurrent/ConcurrentHashMap."<init>":()V
      12: putfield      #5                  // Field caches:Ljava/util/concurrent/ConcurrentMap;
      15: aload_0
      16: new           #6                  // class java/lang/Object
      19: dup
      20: invokespecial #2                  // Method java/lang/Object."<init>":()V
      23: putfield      #7                  // Field MONITOR:Ljava/lang/Object;
      26: return

  public org.apache.dubbo.cache.Cache getCache(org.apache.dubbo.common.URL, org.apache.dubbo.rpc.Invocation);
    Code:
       0: aload_1
       1: ldc           #8                  // String method
       3: aload_2
       4: invokeinterface #9,  1            // InterfaceMethod org/apache/dubbo/rpc/Invocation.getMethodName:()Ljava/lang/String;
       9: invokevirtual #10                 // Method org/apache/dubbo/common/URL.addParameter:(Ljava/lang/String;Ljava/lang/String;)Lorg/apache/dubbo/common/URL;
      12: astore_1
      13: new           #11                 // class java/lang/StringBuilder
      16: dup
      17: invokespecial #12                 // Method java/lang/StringBuilder."<init>":()V
      20: aload_1
      21: invokevirtual #13                 // Method org/apache/dubbo/common/URL.getServiceKey:()Ljava/lang/String;
      24: invokevirtual #14                 // Method java/lang/StringBuilder.append:(Ljava/lang/String;)Ljava/lang/StringBuilder;
      27: aload_2
      28: invokeinterface #9,  1            // InterfaceMethod org/apache/dubbo/rpc/Invocation.getMethodName:()Ljava/lang/String;
      33: invokevirtual #14                 // Method java/lang/StringBuilder.append:(Ljava/lang/String;)Ljava/lang/StringBuilder;
      36: invokevirtual #15                 // Method java/lang/StringBuilder.toString:()Ljava/lang/String;
      39: astore_3
      40: aload_0
      41: getfield      #5                  // Field caches:Ljava/util/concurrent/ConcurrentMap;
      44: aload_3
      45: invokeinterface #16,  2           // InterfaceMethod java/util/concurrent/ConcurrentMap.get:(Ljava/lang/Object;)Ljava/lang/Object;
      50: checkcast     #17                 // class org/apache/dubbo/cache/Cache
      53: astore        4
      55: aconst_null
      56: aload         4
      58: if_acmpeq     64
      61: aload         4
      63: areturn
      64: aload_0
      65: getfield      #7                  // Field MONITOR:Ljava/lang/Object;
      68: dup
      69: astore        5
      71: monitorenter
      72: aload_0
      73: getfield      #5                  // Field caches:Ljava/util/concurrent/ConcurrentMap;
      76: aload_3
      77: invokeinterface #16,  2           // InterfaceMethod java/util/concurrent/ConcurrentMap.get:(Ljava/lang/Object;)Ljava/lang/Object;
      82: checkcast     #17                 // class org/apache/dubbo/cache/Cache
      85: astore        4
      87: aconst_null
      88: aload         4
      90: if_acmpeq     99
      93: aload         4
      95: aload         5
      97: monitorexit
      98: areturn
      99: aload_0
     100: aload_1
     101: invokevirtual #18                 // Method createCache:(Lorg/apache/dubbo/common/URL;)Lorg/apache/dubbo/cache/Cache;
     104: astore        4
     106: aload_0
     107: getfield      #5                  // Field caches:Ljava/util/concurrent/ConcurrentMap;
     110: aload_3
     111: aload         4
     113: invokeinterface #19,  3           // InterfaceMethod java/util/concurrent/ConcurrentMap.put:(Ljava/lang/Object;Ljava/lang/Object;)Ljava/lang/Object;
     118: pop
     119: aload         5
     121: monitorexit
     122: goto          133
     125: astore        6
     127: aload         5
     129: monitorexit
     130: aload         6
     132: athrow
     133: aload         4
     135: areturn
    Exception table:
       from    to  target type
          72    98   125   any
          99   122   125   any
         125   130   125   any

  protected abstract org.apache.dubbo.cache.Cache createCache(org.apache.dubbo.common.URL);
}
