Compiled from "FastJson2ObjectOutput.java"
public class org.apache.dubbo.common.serialize.fastjson2.FastJson2ObjectOutput implements org.apache.dubbo.common.serialize.ObjectOutput {
  private final org.apache.dubbo.common.serialize.fastjson2.Fastjson2CreatorManager fastjson2CreatorManager;

  private final org.apache.dubbo.common.serialize.fastjson2.Fastjson2SecurityManager fastjson2SecurityManager;

  private volatile java.lang.ClassLoader classLoader;

  private final java.io.OutputStream os;

  public org.apache.dubbo.common.serialize.fastjson2.FastJson2ObjectOutput(org.apache.dubbo.common.serialize.fastjson2.Fastjson2CreatorManager, org.apache.dubbo.common.serialize.fastjson2.Fastjson2SecurityManager, java.io.OutputStream);
    Code:
       0: aload_0
       1: invokespecial #1                  // Method java/lang/Object."<init>":()V
       4: aload_0
       5: aload_1
       6: putfield      #2                  // Field fastjson2CreatorManager:Lorg/apache/dubbo/common/serialize/fastjson2/Fastjson2CreatorManager;
       9: aload_0
      10: aload_2
      11: putfield      #3                  // Field fastjson2SecurityManager:Lorg/apache/dubbo/common/serialize/fastjson2/Fastjson2SecurityManager;
      14: aload_0
      15: invokestatic  #4                  // Method java/lang/Thread.currentThread:()Ljava/lang/Thread;
      18: invokevirtual #5                  // Method java/lang/Thread.getContextClassLoader:()Ljava/lang/ClassLoader;
      21: putfield      #6                  // Field classLoader:Ljava/lang/ClassLoader;
      24: aload_0
      25: aload_3
      26: putfield      #7                  // Field os:Ljava/io/OutputStream;
      29: aload_1
      30: aload_0
      31: getfield      #6                  // Field classLoader:Ljava/lang/ClassLoader;
      34: invokevirtual #8                  // Method org/apache/dubbo/common/serialize/fastjson2/Fastjson2CreatorManager.setCreator:(Ljava/lang/ClassLoader;)V
      37: return

  public void writeBool(boolean) throws java.io.IOException;
    Code:
       0: aload_0
       1: iload_1
       2: invokestatic  #9                  // Method java/lang/Boolean.valueOf:(Z)Ljava/lang/Boolean;
       5: invokevirtual #10                 // Method writeObject:(Ljava/lang/Object;)V
       8: return

  public void writeByte(byte) throws java.io.IOException;
    Code:
       0: aload_0
       1: iload_1
       2: invokestatic  #11                 // Method java/lang/Byte.valueOf:(B)Ljava/lang/Byte;
       5: invokevirtual #10                 // Method writeObject:(Ljava/lang/Object;)V
       8: return

  public void writeShort(short) throws java.io.IOException;
    Code:
       0: aload_0
       1: iload_1
       2: invokestatic  #12                 // Method java/lang/Short.valueOf:(S)Ljava/lang/Short;
       5: invokevirtual #10                 // Method writeObject:(Ljava/lang/Object;)V
       8: return

  public void writeInt(int) throws java.io.IOException;
    Code:
       0: aload_0
       1: iload_1
       2: invokestatic  #13                 // Method java/lang/Integer.valueOf:(I)Ljava/lang/Integer;
       5: invokevirtual #10                 // Method writeObject:(Ljava/lang/Object;)V
       8: return

  public void writeLong(long) throws java.io.IOException;
    Code:
       0: aload_0
       1: lload_1
       2: invokestatic  #14                 // Method java/lang/Long.valueOf:(J)Ljava/lang/Long;
       5: invokevirtual #10                 // Method writeObject:(Ljava/lang/Object;)V
       8: return

  public void writeFloat(float) throws java.io.IOException;
    Code:
       0: aload_0
       1: fload_1
       2: invokestatic  #15                 // Method java/lang/Float.valueOf:(F)Ljava/lang/Float;
       5: invokevirtual #10                 // Method writeObject:(Ljava/lang/Object;)V
       8: return

  public void writeDouble(double) throws java.io.IOException;
    Code:
       0: aload_0
       1: dload_1
       2: invokestatic  #16                 // Method java/lang/Double.valueOf:(D)Ljava/lang/Double;
       5: invokevirtual #10                 // Method writeObject:(Ljava/lang/Object;)V
       8: return

  public void writeUTF(java.lang.String) throws java.io.IOException;
    Code:
       0: aload_0
       1: aload_1
       2: invokevirtual #10                 // Method writeObject:(Ljava/lang/Object;)V
       5: return

  public void writeBytes(byte[]) throws java.io.IOException;
    Code:
       0: aload_0
       1: getfield      #7                  // Field os:Ljava/io/OutputStream;
       4: aload_1
       5: arraylength
       6: invokevirtual #17                 // Method java/io/OutputStream.write:(I)V
       9: aload_0
      10: getfield      #7                  // Field os:Ljava/io/OutputStream;
      13: aload_1
      14: invokevirtual #18                 // Method java/io/OutputStream.write:([B)V
      17: return

  public void writeBytes(byte[], int, int) throws java.io.IOException;
    Code:
       0: aload_0
       1: getfield      #7                  // Field os:Ljava/io/OutputStream;
       4: iload_3
       5: invokevirtual #17                 // Method java/io/OutputStream.write:(I)V
       8: aload_0
       9: getfield      #7                  // Field os:Ljava/io/OutputStream;
      12: aload_1
      13: iload_2
      14: iload_3
      15: invokevirtual #19                 // Method java/io/OutputStream.write:([BII)V
      18: return

  public void writeObject(java.lang.Object) throws java.io.IOException;
    Code:
       0: aload_0
       1: invokespecial #20                 // Method updateClassLoaderIfNeed:()V
       4: aload_0
       5: getfield      #3                  // Field fastjson2SecurityManager:Lorg/apache/dubbo/common/serialize/fastjson2/Fastjson2SecurityManager;
       8: invokevirtual #21                 // Method org/apache/dubbo/common/serialize/fastjson2/Fastjson2SecurityManager.getSecurityFilter:()Lorg/apache/dubbo/common/serialize/fastjson2/Fastjson2SecurityManager$Handler;
      11: invokevirtual #22                 // Method org/apache/dubbo/common/serialize/fastjson2/Fastjson2SecurityManager$Handler.isCheckSerializable:()Z
      14: ifeq          80
      17: aload_1
      18: bipush        8
      20: anewarray     #23                 // class com/alibaba/fastjson2/JSONWriter$Feature
      23: dup
      24: iconst_0
      25: getstatic     #24                 // Field com/alibaba/fastjson2/JSONWriter$Feature.WriteClassName:Lcom/alibaba/fastjson2/JSONWriter$Feature;
      28: aastore
      29: dup
      30: iconst_1
      31: getstatic     #25                 // Field com/alibaba/fastjson2/JSONWriter$Feature.FieldBased:Lcom/alibaba/fastjson2/JSONWriter$Feature;
      34: aastore
      35: dup
      36: iconst_2
      37: getstatic     #26                 // Field com/alibaba/fastjson2/JSONWriter$Feature.ErrorOnNoneSerializable:Lcom/alibaba/fastjson2/JSONWriter$Feature;
      40: aastore
      41: dup
      42: iconst_3
      43: getstatic     #27                 // Field com/alibaba/fastjson2/JSONWriter$Feature.ReferenceDetection:Lcom/alibaba/fastjson2/JSONWriter$Feature;
      46: aastore
      47: dup
      48: iconst_4
      49: getstatic     #28                 // Field com/alibaba/fastjson2/JSONWriter$Feature.WriteNulls:Lcom/alibaba/fastjson2/JSONWriter$Feature;
      52: aastore
      53: dup
      54: iconst_5
      55: getstatic     #29                 // Field com/alibaba/fastjson2/JSONWriter$Feature.NotWriteDefaultValue:Lcom/alibaba/fastjson2/JSONWriter$Feature;
      58: aastore
      59: dup
      60: bipush        6
      62: getstatic     #30                 // Field com/alibaba/fastjson2/JSONWriter$Feature.NotWriteHashMapArrayListClassName:Lcom/alibaba/fastjson2/JSONWriter$Feature;
      65: aastore
      66: dup
      67: bipush        7
      69: getstatic     #31                 // Field com/alibaba/fastjson2/JSONWriter$Feature.WriteNameAsSymbol:Lcom/alibaba/fastjson2/JSONWriter$Feature;
      72: aastore
      73: invokestatic  #32                 // InterfaceMethod com/alibaba/fastjson2/JSONB.toBytes:(Ljava/lang/Object;[Lcom/alibaba/fastjson2/JSONWriter$Feature;)[B
      76: astore_2
      77: goto          133
      80: aload_1
      81: bipush        7
      83: anewarray     #23                 // class com/alibaba/fastjson2/JSONWriter$Feature
      86: dup
      87: iconst_0
      88: getstatic     #24                 // Field com/alibaba/fastjson2/JSONWriter$Feature.WriteClassName:Lcom/alibaba/fastjson2/JSONWriter$Feature;
      91: aastore
      92: dup
      93: iconst_1
      94: getstatic     #25                 // Field com/alibaba/fastjson2/JSONWriter$Feature.FieldBased:Lcom/alibaba/fastjson2/JSONWriter$Feature;
      97: aastore
      98: dup
      99: iconst_2
     100: getstatic     #27                 // Field com/alibaba/fastjson2/JSONWriter$Feature.ReferenceDetection:Lcom/alibaba/fastjson2/JSONWriter$Feature;
     103: aastore
     104: dup
     105: iconst_3
     106: getstatic     #28                 // Field com/alibaba/fastjson2/JSONWriter$Feature.WriteNulls:Lcom/alibaba/fastjson2/JSONWriter$Feature;
     109: aastore
     110: dup
     111: iconst_4
     112: getstatic     #29                 // Field com/alibaba/fastjson2/JSONWriter$Feature.NotWriteDefaultValue:Lcom/alibaba/fastjson2/JSONWriter$Feature;
     115: aastore
     116: dup
     117: iconst_5
     118: getstatic     #30                 // Field com/alibaba/fastjson2/JSONWriter$Feature.NotWriteHashMapArrayListClassName:Lcom/alibaba/fastjson2/JSONWriter$Feature;
     121: aastore
     122: dup
     123: bipush        6
     125: getstatic     #31                 // Field com/alibaba/fastjson2/JSONWriter$Feature.WriteNameAsSymbol:Lcom/alibaba/fastjson2/JSONWriter$Feature;
     128: aastore
     129: invokestatic  #32                 // InterfaceMethod com/alibaba/fastjson2/JSONB.toBytes:(Ljava/lang/Object;[Lcom/alibaba/fastjson2/JSONWriter$Feature;)[B
     132: astore_2
     133: aload_0
     134: aload_2
     135: arraylength
     136: invokespecial #33                 // Method writeLength:(I)V
     139: aload_0
     140: getfield      #7                  // Field os:Ljava/io/OutputStream;
     143: aload_2
     144: invokevirtual #18                 // Method java/io/OutputStream.write:([B)V
     147: aload_0
     148: getfield      #7                  // Field os:Ljava/io/OutputStream;
     151: invokevirtual #34                 // Method java/io/OutputStream.flush:()V
     154: return

  private void updateClassLoaderIfNeed();
    Code:
       0: invokestatic  #4                  // Method java/lang/Thread.currentThread:()Ljava/lang/Thread;
       3: invokevirtual #5                  // Method java/lang/Thread.getContextClassLoader:()Ljava/lang/ClassLoader;
       6: astore_1
       7: aload_1
       8: aload_0
       9: getfield      #6                  // Field classLoader:Ljava/lang/ClassLoader;
      12: if_acmpeq     28
      15: aload_0
      16: getfield      #2                  // Field fastjson2CreatorManager:Lorg/apache/dubbo/common/serialize/fastjson2/Fastjson2CreatorManager;
      19: aload_1
      20: invokevirtual #8                  // Method org/apache/dubbo/common/serialize/fastjson2/Fastjson2CreatorManager.setCreator:(Ljava/lang/ClassLoader;)V
      23: aload_0
      24: aload_1
      25: putfield      #6                  // Field classLoader:Ljava/lang/ClassLoader;
      28: return

  private void writeLength(int) throws java.io.IOException;
    Code:
       0: iconst_4
       1: newarray       byte
       3: astore_2
       4: aload_2
       5: arraylength
       6: istore_3
       7: iconst_0
       8: istore        4
      10: iload         4
      12: iload_3
      13: if_icmpge     41
      16: aload_2
      17: iload_3
      18: iload         4
      20: isub
      21: iconst_1
      22: isub
      23: iload_1
      24: sipush        255
      27: iand
      28: i2b
      29: bastore
      30: iload_1
      31: bipush        8
      33: ishr
      34: istore_1
      35: iinc          4, 1
      38: goto          10
      41: aload_0
      42: getfield      #7                  // Field os:Ljava/io/OutputStream;
      45: aload_2
      46: invokevirtual #18                 // Method java/io/OutputStream.write:([B)V
      49: return

  public void flushBuffer() throws java.io.IOException;
    Code:
       0: aload_0
       1: getfield      #7                  // Field os:Ljava/io/OutputStream;
       4: invokevirtual #34                 // Method java/io/OutputStream.flush:()V
       7: return
}
