Compiled from "FastJson2ObjectInput.java"
public class org.apache.dubbo.common.serialize.fastjson2.FastJson2ObjectInput implements org.apache.dubbo.common.serialize.ObjectInput {
  private final org.apache.dubbo.common.serialize.fastjson2.Fastjson2CreatorManager fastjson2CreatorManager;

  private final org.apache.dubbo.common.serialize.fastjson2.Fastjson2SecurityManager fastjson2SecurityManager;

  private volatile java.lang.ClassLoader classLoader;

  private final java.io.InputStream is;

  public org.apache.dubbo.common.serialize.fastjson2.FastJson2ObjectInput(org.apache.dubbo.common.serialize.fastjson2.Fastjson2CreatorManager, org.apache.dubbo.common.serialize.fastjson2.Fastjson2SecurityManager, java.io.InputStream);
    Code:
       0: aload_0
       1: invokespecial #1                  // Method java/lang/Object."<init>":()V
       4: aload_0
       5: aload_1
       6: putfield      #2                  // Field fastjson2CreatorManager:Lorg/apache/dubbo/common/serialize/fastjson2/Fastjson2CreatorManager;
       9: aload_0
      10: aload_2
      11: putfield      #3                  // Field fastjson2SecurityManager:Lorg/apache/dubbo/common/serialize/fastjson2/Fastjson2SecurityManager;
      14: aload_0
      15: invokestatic  #4                  // Method java/lang/Thread.currentThread:()Ljava/lang/Thread;
      18: invokevirtual #5                  // Method java/lang/Thread.getContextClassLoader:()Ljava/lang/ClassLoader;
      21: putfield      #6                  // Field classLoader:Ljava/lang/ClassLoader;
      24: aload_0
      25: aload_3
      26: putfield      #7                  // Field is:Ljava/io/InputStream;
      29: aload_1
      30: aload_0
      31: getfield      #6                  // Field classLoader:Ljava/lang/ClassLoader;
      34: invokevirtual #8                  // Method org/apache/dubbo/common/serialize/fastjson2/Fastjson2CreatorManager.setCreator:(Ljava/lang/ClassLoader;)V
      37: return

  public boolean readBool() throws java.io.IOException;
    Code:
       0: aload_0
       1: getstatic     #9                  // Field java/lang/Boolean.TYPE:Ljava/lang/Class;
       4: invokevirtual #10                 // Method readObject:(Ljava/lang/Class;)Ljava/lang/Object;
       7: checkcast     #11                 // class java/lang/Boolean
      10: invokevirtual #12                 // Method java/lang/Boolean.booleanValue:()Z
      13: ireturn

  public byte readByte() throws java.io.IOException;
    Code:
       0: aload_0
       1: getstatic     #13                 // Field java/lang/Byte.TYPE:Ljava/lang/Class;
       4: invokevirtual #10                 // Method readObject:(Ljava/lang/Class;)Ljava/lang/Object;
       7: checkcast     #14                 // class java/lang/Byte
      10: invokevirtual #15                 // Method java/lang/Byte.byteValue:()B
      13: ireturn

  public short readShort() throws java.io.IOException;
    Code:
       0: aload_0
       1: getstatic     #16                 // Field java/lang/Short.TYPE:Ljava/lang/Class;
       4: invokevirtual #10                 // Method readObject:(Ljava/lang/Class;)Ljava/lang/Object;
       7: checkcast     #17                 // class java/lang/Short
      10: invokevirtual #18                 // Method java/lang/Short.shortValue:()S
      13: ireturn

  public int readInt() throws java.io.IOException;
    Code:
       0: aload_0
       1: getstatic     #19                 // Field java/lang/Integer.TYPE:Ljava/lang/Class;
       4: invokevirtual #10                 // Method readObject:(Ljava/lang/Class;)Ljava/lang/Object;
       7: checkcast     #20                 // class java/lang/Integer
      10: invokevirtual #21                 // Method java/lang/Integer.intValue:()I
      13: ireturn

  public long readLong() throws java.io.IOException;
    Code:
       0: aload_0
       1: getstatic     #22                 // Field java/lang/Long.TYPE:Ljava/lang/Class;
       4: invokevirtual #10                 // Method readObject:(Ljava/lang/Class;)Ljava/lang/Object;
       7: checkcast     #23                 // class java/lang/Long
      10: invokevirtual #24                 // Method java/lang/Long.longValue:()J
      13: lreturn

  public float readFloat() throws java.io.IOException;
    Code:
       0: aload_0
       1: getstatic     #25                 // Field java/lang/Float.TYPE:Ljava/lang/Class;
       4: invokevirtual #10                 // Method readObject:(Ljava/lang/Class;)Ljava/lang/Object;
       7: checkcast     #26                 // class java/lang/Float
      10: invokevirtual #27                 // Method java/lang/Float.floatValue:()F
      13: freturn

  public double readDouble() throws java.io.IOException;
    Code:
       0: aload_0
       1: getstatic     #28                 // Field java/lang/Double.TYPE:Ljava/lang/Class;
       4: invokevirtual #10                 // Method readObject:(Ljava/lang/Class;)Ljava/lang/Object;
       7: checkcast     #29                 // class java/lang/Double
      10: invokevirtual #30                 // Method java/lang/Double.doubleValue:()D
      13: dreturn

  public java.lang.String readUTF() throws java.io.IOException;
    Code:
       0: aload_0
       1: ldc           #31                 // class java/lang/String
       3: invokevirtual #10                 // Method readObject:(Ljava/lang/Class;)Ljava/lang/Object;
       6: checkcast     #31                 // class java/lang/String
       9: areturn

  public byte[] readBytes() throws java.io.IOException;
    Code:
       0: aload_0
       1: getfield      #7                  // Field is:Ljava/io/InputStream;
       4: invokevirtual #32                 // Method java/io/InputStream.read:()I
       7: istore_1
       8: iload_1
       9: newarray       byte
      11: astore_2
      12: aload_0
      13: getfield      #7                  // Field is:Ljava/io/InputStream;
      16: aload_2
      17: iconst_0
      18: iload_1
      19: invokevirtual #33                 // Method java/io/InputStream.read:([BII)I
      22: istore_3
      23: iload_3
      24: iload_1
      25: if_icmpeq     64
      28: new           #34                 // class java/lang/IllegalArgumentException
      31: dup
      32: new           #35                 // class java/lang/StringBuilder
      35: dup
      36: invokespecial #36                 // Method java/lang/StringBuilder."<init>":()V
      39: ldc           #37                 // String deserialize failed. expected read length:
      41: invokevirtual #38                 // Method java/lang/StringBuilder.append:(Ljava/lang/String;)Ljava/lang/StringBuilder;
      44: iload_1
      45: invokevirtual #39                 // Method java/lang/StringBuilder.append:(I)Ljava/lang/StringBuilder;
      48: ldc           #40                 // String  but actual read:
      50: invokevirtual #38                 // Method java/lang/StringBuilder.append:(Ljava/lang/String;)Ljava/lang/StringBuilder;
      53: iload_3
      54: invokevirtual #39                 // Method java/lang/StringBuilder.append:(I)Ljava/lang/StringBuilder;
      57: invokevirtual #41                 // Method java/lang/StringBuilder.toString:()Ljava/lang/String;
      60: invokespecial #42                 // Method java/lang/IllegalArgumentException."<init>":(Ljava/lang/String;)V
      63: athrow
      64: aload_2
      65: areturn

  public java.lang.Object readObject() throws java.io.IOException, java.lang.ClassNotFoundException;
    Code:
       0: aload_0
       1: ldc           #43                 // class java/lang/Object
       3: invokevirtual #10                 // Method readObject:(Ljava/lang/Class;)Ljava/lang/Object;
       6: areturn

  public <T> T readObject(java.lang.Class<T>) throws java.io.IOException;
    Code:
       0: aload_0
       1: invokespecial #44                 // Method updateClassLoaderIfNeed:()V
       4: aload_0
       5: invokespecial #45                 // Method readLength:()I
       8: istore_2
       9: iload_2
      10: newarray       byte
      12: astore_3
      13: aload_0
      14: getfield      #7                  // Field is:Ljava/io/InputStream;
      17: aload_3
      18: iconst_0
      19: iload_2
      20: invokevirtual #33                 // Method java/io/InputStream.read:([BII)I
      23: istore        4
      25: iload         4
      27: iload_2
      28: if_icmpeq     68
      31: new           #34                 // class java/lang/IllegalArgumentException
      34: dup
      35: new           #35                 // class java/lang/StringBuilder
      38: dup
      39: invokespecial #36                 // Method java/lang/StringBuilder."<init>":()V
      42: ldc           #37                 // String deserialize failed. expected read length:
      44: invokevirtual #38                 // Method java/lang/StringBuilder.append:(Ljava/lang/String;)Ljava/lang/StringBuilder;
      47: iload_2
      48: invokevirtual #39                 // Method java/lang/StringBuilder.append:(I)Ljava/lang/StringBuilder;
      51: ldc           #40                 // String  but actual read:
      53: invokevirtual #38                 // Method java/lang/StringBuilder.append:(Ljava/lang/String;)Ljava/lang/StringBuilder;
      56: iload         4
      58: invokevirtual #39                 // Method java/lang/StringBuilder.append:(I)Ljava/lang/StringBuilder;
      61: invokevirtual #41                 // Method java/lang/StringBuilder.toString:()Ljava/lang/String;
      64: invokespecial #42                 // Method java/lang/IllegalArgumentException."<init>":(Ljava/lang/String;)V
      67: athrow
      68: aload_0
      69: getfield      #3                  // Field fastjson2SecurityManager:Lorg/apache/dubbo/common/serialize/fastjson2/Fastjson2SecurityManager;
      72: invokevirtual #46                 // Method org/apache/dubbo/common/serialize/fastjson2/Fastjson2SecurityManager.getSecurityFilter:()Lorg/apache/dubbo/common/serialize/fastjson2/Fastjson2SecurityManager$Handler;
      75: astore        5
      77: aload         5
      79: invokevirtual #47                 // Method org/apache/dubbo/common/serialize/fastjson2/Fastjson2SecurityManager$Handler.isCheckSerializable:()Z
      82: ifeq          131
      85: aload_3
      86: aload_1
      87: aload         5
      89: iconst_5
      90: anewarray     #48                 // class com/alibaba/fastjson2/JSONReader$Feature
      93: dup
      94: iconst_0
      95: getstatic     #49                 // Field com/alibaba/fastjson2/JSONReader$Feature.UseDefaultConstructorAsPossible:Lcom/alibaba/fastjson2/JSONReader$Feature;
      98: aastore
      99: dup
     100: iconst_1
     101: getstatic     #50                 // Field com/alibaba/fastjson2/JSONReader$Feature.ErrorOnNoneSerializable:Lcom/alibaba/fastjson2/JSONReader$Feature;
     104: aastore
     105: dup
     106: iconst_2
     107: getstatic     #51                 // Field com/alibaba/fastjson2/JSONReader$Feature.IgnoreAutoTypeNotMatch:Lcom/alibaba/fastjson2/JSONReader$Feature;
     110: aastore
     111: dup
     112: iconst_3
     113: getstatic     #52                 // Field com/alibaba/fastjson2/JSONReader$Feature.UseNativeObject:Lcom/alibaba/fastjson2/JSONReader$Feature;
     116: aastore
     117: dup
     118: iconst_4
     119: getstatic     #53                 // Field com/alibaba/fastjson2/JSONReader$Feature.FieldBased:Lcom/alibaba/fastjson2/JSONReader$Feature;
     122: aastore
     123: invokestatic  #54                 // InterfaceMethod com/alibaba/fastjson2/JSONB.parseObject:([BLjava/lang/Class;Lcom/alibaba/fastjson2/filter/Filter;[Lcom/alibaba/fastjson2/JSONReader$Feature;)Ljava/lang/Object;
     126: astore        6
     128: goto          168
     131: aload_3
     132: aload_1
     133: aload         5
     135: iconst_4
     136: anewarray     #48                 // class com/alibaba/fastjson2/JSONReader$Feature
     139: dup
     140: iconst_0
     141: getstatic     #49                 // Field com/alibaba/fastjson2/JSONReader$Feature.UseDefaultConstructorAsPossible:Lcom/alibaba/fastjson2/JSONReader$Feature;
     144: aastore
     145: dup
     146: iconst_1
     147: getstatic     #52                 // Field com/alibaba/fastjson2/JSONReader$Feature.UseNativeObject:Lcom/alibaba/fastjson2/JSONReader$Feature;
     150: aastore
     151: dup
     152: iconst_2
     153: getstatic     #51                 // Field com/alibaba/fastjson2/JSONReader$Feature.IgnoreAutoTypeNotMatch:Lcom/alibaba/fastjson2/JSONReader$Feature;
     156: aastore
     157: dup
     158: iconst_3
     159: getstatic     #53                 // Field com/alibaba/fastjson2/JSONReader$Feature.FieldBased:Lcom/alibaba/fastjson2/JSONReader$Feature;
     162: aastore
     163: invokestatic  #54                 // InterfaceMethod com/alibaba/fastjson2/JSONB.parseObject:([BLjava/lang/Class;Lcom/alibaba/fastjson2/filter/Filter;[Lcom/alibaba/fastjson2/JSONReader$Feature;)Ljava/lang/Object;
     166: astore        6
     168: aload         6
     170: ifnull        229
     173: aload_1
     174: ifnull        229
     177: aload         6
     179: invokevirtual #55                 // Method java/lang/Object.getClass:()Ljava/lang/Class;
     182: aload_1
     183: invokestatic  #56                 // Method org/apache/dubbo/common/utils/ClassUtils.isMatch:(Ljava/lang/Class;Ljava/lang/Class;)Z
     186: ifne          229
     189: new           #34                 // class java/lang/IllegalArgumentException
     192: dup
     193: new           #35                 // class java/lang/StringBuilder
     196: dup
     197: invokespecial #36                 // Method java/lang/StringBuilder."<init>":()V
     200: ldc           #57                 // String deserialize failed. expected class:
     202: invokevirtual #38                 // Method java/lang/StringBuilder.append:(Ljava/lang/String;)Ljava/lang/StringBuilder;
     205: aload_1
     206: invokevirtual #58                 // Method java/lang/StringBuilder.append:(Ljava/lang/Object;)Ljava/lang/StringBuilder;
     209: ldc           #59                 // String  but actual class:
     211: invokevirtual #38                 // Method java/lang/StringBuilder.append:(Ljava/lang/String;)Ljava/lang/StringBuilder;
     214: aload         6
     216: invokevirtual #55                 // Method java/lang/Object.getClass:()Ljava/lang/Class;
     219: invokevirtual #58                 // Method java/lang/StringBuilder.append:(Ljava/lang/Object;)Ljava/lang/StringBuilder;
     222: invokevirtual #41                 // Method java/lang/StringBuilder.toString:()Ljava/lang/String;
     225: invokespecial #42                 // Method java/lang/IllegalArgumentException."<init>":(Ljava/lang/String;)V
     228: athrow
     229: aload         6
     231: areturn

  public <T> T readObject(java.lang.Class<T>, java.lang.reflect.Type) throws java.io.IOException, java.lang.ClassNotFoundException;
    Code:
       0: aload_0
       1: invokespecial #44                 // Method updateClassLoaderIfNeed:()V
       4: aload_0
       5: invokespecial #45                 // Method readLength:()I
       8: istore_3
       9: iload_3
      10: newarray       byte
      12: astore        4
      14: aload_0
      15: getfield      #7                  // Field is:Ljava/io/InputStream;
      18: aload         4
      20: iconst_0
      21: iload_3
      22: invokevirtual #33                 // Method java/io/InputStream.read:([BII)I
      25: istore        5
      27: iload         5
      29: iload_3
      30: if_icmpeq     70
      33: new           #34                 // class java/lang/IllegalArgumentException
      36: dup
      37: new           #35                 // class java/lang/StringBuilder
      40: dup
      41: invokespecial #36                 // Method java/lang/StringBuilder."<init>":()V
      44: ldc           #37                 // String deserialize failed. expected read length:
      46: invokevirtual #38                 // Method java/lang/StringBuilder.append:(Ljava/lang/String;)Ljava/lang/StringBuilder;
      49: iload_3
      50: invokevirtual #39                 // Method java/lang/StringBuilder.append:(I)Ljava/lang/StringBuilder;
      53: ldc           #40                 // String  but actual read:
      55: invokevirtual #38                 // Method java/lang/StringBuilder.append:(Ljava/lang/String;)Ljava/lang/StringBuilder;
      58: iload         5
      60: invokevirtual #39                 // Method java/lang/StringBuilder.append:(I)Ljava/lang/StringBuilder;
      63: invokevirtual #41                 // Method java/lang/StringBuilder.toString:()Ljava/lang/String;
      66: invokespecial #42                 // Method java/lang/IllegalArgumentException."<init>":(Ljava/lang/String;)V
      69: athrow
      70: aload_0
      71: getfield      #3                  // Field fastjson2SecurityManager:Lorg/apache/dubbo/common/serialize/fastjson2/Fastjson2SecurityManager;
      74: invokevirtual #46                 // Method org/apache/dubbo/common/serialize/fastjson2/Fastjson2SecurityManager.getSecurityFilter:()Lorg/apache/dubbo/common/serialize/fastjson2/Fastjson2SecurityManager$Handler;
      77: astore        6
      79: aload         6
      81: invokevirtual #47                 // Method org/apache/dubbo/common/serialize/fastjson2/Fastjson2SecurityManager$Handler.isCheckSerializable:()Z
      84: ifeq          134
      87: aload         4
      89: aload_1
      90: aload         6
      92: iconst_5
      93: anewarray     #48                 // class com/alibaba/fastjson2/JSONReader$Feature
      96: dup
      97: iconst_0
      98: getstatic     #49                 // Field com/alibaba/fastjson2/JSONReader$Feature.UseDefaultConstructorAsPossible:Lcom/alibaba/fastjson2/JSONReader$Feature;
     101: aastore
     102: dup
     103: iconst_1
     104: getstatic     #50                 // Field com/alibaba/fastjson2/JSONReader$Feature.ErrorOnNoneSerializable:Lcom/alibaba/fastjson2/JSONReader$Feature;
     107: aastore
     108: dup
     109: iconst_2
     110: getstatic     #51                 // Field com/alibaba/fastjson2/JSONReader$Feature.IgnoreAutoTypeNotMatch:Lcom/alibaba/fastjson2/JSONReader$Feature;
     113: aastore
     114: dup
     115: iconst_3
     116: getstatic     #52                 // Field com/alibaba/fastjson2/JSONReader$Feature.UseNativeObject:Lcom/alibaba/fastjson2/JSONReader$Feature;
     119: aastore
     120: dup
     121: iconst_4
     122: getstatic     #53                 // Field com/alibaba/fastjson2/JSONReader$Feature.FieldBased:Lcom/alibaba/fastjson2/JSONReader$Feature;
     125: aastore
     126: invokestatic  #54                 // InterfaceMethod com/alibaba/fastjson2/JSONB.parseObject:([BLjava/lang/Class;Lcom/alibaba/fastjson2/filter/Filter;[Lcom/alibaba/fastjson2/JSONReader$Feature;)Ljava/lang/Object;
     129: astore        7
     131: goto          172
     134: aload         4
     136: aload_1
     137: aload         6
     139: iconst_4
     140: anewarray     #48                 // class com/alibaba/fastjson2/JSONReader$Feature
     143: dup
     144: iconst_0
     145: getstatic     #49                 // Field com/alibaba/fastjson2/JSONReader$Feature.UseDefaultConstructorAsPossible:Lcom/alibaba/fastjson2/JSONReader$Feature;
     148: aastore
     149: dup
     150: iconst_1
     151: getstatic     #52                 // Field com/alibaba/fastjson2/JSONReader$Feature.UseNativeObject:Lcom/alibaba/fastjson2/JSONReader$Feature;
     154: aastore
     155: dup
     156: iconst_2
     157: getstatic     #51                 // Field com/alibaba/fastjson2/JSONReader$Feature.IgnoreAutoTypeNotMatch:Lcom/alibaba/fastjson2/JSONReader$Feature;
     160: aastore
     161: dup
     162: iconst_3
     163: getstatic     #53                 // Field com/alibaba/fastjson2/JSONReader$Feature.FieldBased:Lcom/alibaba/fastjson2/JSONReader$Feature;
     166: aastore
     167: invokestatic  #54                 // InterfaceMethod com/alibaba/fastjson2/JSONB.parseObject:([BLjava/lang/Class;Lcom/alibaba/fastjson2/filter/Filter;[Lcom/alibaba/fastjson2/JSONReader$Feature;)Ljava/lang/Object;
     170: astore        7
     172: aload         7
     174: ifnull        233
     177: aload_1
     178: ifnull        233
     181: aload         7
     183: invokevirtual #55                 // Method java/lang/Object.getClass:()Ljava/lang/Class;
     186: aload_1
     187: invokestatic  #56                 // Method org/apache/dubbo/common/utils/ClassUtils.isMatch:(Ljava/lang/Class;Ljava/lang/Class;)Z
     190: ifne          233
     193: new           #34                 // class java/lang/IllegalArgumentException
     196: dup
     197: new           #35                 // class java/lang/StringBuilder
     200: dup
     201: invokespecial #36                 // Method java/lang/StringBuilder."<init>":()V
     204: ldc           #57                 // String deserialize failed. expected class:
     206: invokevirtual #38                 // Method java/lang/StringBuilder.append:(Ljava/lang/String;)Ljava/lang/StringBuilder;
     209: aload_1
     210: invokevirtual #58                 // Method java/lang/StringBuilder.append:(Ljava/lang/Object;)Ljava/lang/StringBuilder;
     213: ldc           #59                 // String  but actual class:
     215: invokevirtual #38                 // Method java/lang/StringBuilder.append:(Ljava/lang/String;)Ljava/lang/StringBuilder;
     218: aload         7
     220: invokevirtual #55                 // Method java/lang/Object.getClass:()Ljava/lang/Class;
     223: invokevirtual #58                 // Method java/lang/StringBuilder.append:(Ljava/lang/Object;)Ljava/lang/StringBuilder;
     226: invokevirtual #41                 // Method java/lang/StringBuilder.toString:()Ljava/lang/String;
     229: invokespecial #42                 // Method java/lang/IllegalArgumentException."<init>":(Ljava/lang/String;)V
     232: athrow
     233: aload         7
     235: areturn

  private void updateClassLoaderIfNeed();
    Code:
       0: invokestatic  #4                  // Method java/lang/Thread.currentThread:()Ljava/lang/Thread;
       3: invokevirtual #5                  // Method java/lang/Thread.getContextClassLoader:()Ljava/lang/ClassLoader;
       6: astore_1
       7: aload_1
       8: aload_0
       9: getfield      #6                  // Field classLoader:Ljava/lang/ClassLoader;
      12: if_acmpeq     28
      15: aload_0
      16: getfield      #2                  // Field fastjson2CreatorManager:Lorg/apache/dubbo/common/serialize/fastjson2/Fastjson2CreatorManager;
      19: aload_1
      20: invokevirtual #8                  // Method org/apache/dubbo/common/serialize/fastjson2/Fastjson2CreatorManager.setCreator:(Ljava/lang/ClassLoader;)V
      23: aload_0
      24: aload_1
      25: putfield      #6                  // Field classLoader:Ljava/lang/ClassLoader;
      28: return

  private int readLength() throws java.io.IOException;
    Code:
       0: iconst_4
       1: newarray       byte
       3: astore_1
       4: aload_0
       5: getfield      #7                  // Field is:Ljava/io/InputStream;
       8: aload_1
       9: iconst_0
      10: iconst_4
      11: invokevirtual #33                 // Method java/io/InputStream.read:([BII)I
      14: istore_2
      15: iload_2
      16: iconst_4
      17: if_icmpeq     47
      20: new           #34                 // class java/lang/IllegalArgumentException
      23: dup
      24: new           #35                 // class java/lang/StringBuilder
      27: dup
      28: invokespecial #36                 // Method java/lang/StringBuilder."<init>":()V
      31: ldc           #60                 // String deserialize failed. expected read length: 4 but actual read:
      33: invokevirtual #38                 // Method java/lang/StringBuilder.append:(Ljava/lang/String;)Ljava/lang/StringBuilder;
      36: iload_2
      37: invokevirtual #39                 // Method java/lang/StringBuilder.append:(I)Ljava/lang/StringBuilder;
      40: invokevirtual #41                 // Method java/lang/StringBuilder.toString:()Ljava/lang/String;
      43: invokespecial #42                 // Method java/lang/IllegalArgumentException."<init>":(Ljava/lang/String;)V
      46: athrow
      47: iconst_0
      48: istore_3
      49: aload_1
      50: astore        4
      52: aload         4
      54: arraylength
      55: istore        5
      57: iconst_0
      58: istore        6
      60: iload         6
      62: iload         5
      64: if_icmpge     92
      67: aload         4
      69: iload         6
      71: baload
      72: istore        7
      74: iload_3
      75: bipush        8
      77: ishl
      78: iload         7
      80: sipush        255
      83: iand
      84: iadd
      85: istore_3
      86: iinc          6, 1
      89: goto          60
      92: iload_3
      93: ireturn
}
