Compiled from "Fastjson2CreatorManager.java"
public class org.apache.dubbo.common.serialize.fastjson2.Fastjson2CreatorManager implements org.apache.dubbo.rpc.model.ScopeClassLoaderListener<org.apache.dubbo.rpc.model.FrameworkModel> {
  private static final java.lang.ClassLoader SYSTEM_CLASSLOADER_KEY;

  private final java.util.Map<java.lang.ClassLoader, com.alibaba.fastjson2.reader.ObjectReaderCreatorASM> readerMap;

  private final java.util.Map<java.lang.ClassLoader, com.alibaba.fastjson2.writer.ObjectWriterCreatorASM> writerMap;

  public org.apache.dubbo.common.serialize.fastjson2.Fastjson2CreatorManager(org.apache.dubbo.rpc.model.FrameworkModel);
    Code:
       0: aload_0
       1: invokespecial #1                  // Method java/lang/Object."<init>":()V
       4: aload_0
       5: new           #2                  // class java/util/concurrent/ConcurrentHashMap
       8: dup
       9: invokespecial #3                  // Method java/util/concurrent/ConcurrentHashMap."<init>":()V
      12: putfield      #4                  // Field readerMap:Ljava/util/Map;
      15: aload_0
      16: new           #2                  // class java/util/concurrent/ConcurrentHashMap
      19: dup
      20: invokespecial #3                  // Method java/util/concurrent/ConcurrentHashMap."<init>":()V
      23: putfield      #5                  // Field writerMap:Ljava/util/Map;
      26: aload_1
      27: aload_0
      28: invokevirtual #6                  // Method org/apache/dubbo/rpc/model/FrameworkModel.addClassLoaderListener:(Lorg/apache/dubbo/rpc/model/ScopeClassLoaderListener;)V
      31: return

  public void setCreator(java.lang.ClassLoader);
    Code:
       0: aload_1
       1: ifnonnull     8
       4: getstatic     #7                  // Field SYSTEM_CLASSLOADER_KEY:Ljava/lang/ClassLoader;
       7: astore_1
       8: aload_0
       9: getfield      #4                  // Field readerMap:Ljava/util/Map;
      12: aload_1
      13: invokedynamic #8,  0              // InvokeDynamic #0:apply:()Ljava/util/function/Function;
      18: invokeinterface #9,  3            // InterfaceMethod java/util/Map.computeIfAbsent:(Ljava/lang/Object;Ljava/util/function/Function;)Ljava/lang/Object;
      23: checkcast     #10                 // class com/alibaba/fastjson2/reader/ObjectReaderCreator
      26: invokestatic  #11                 // Method com/alibaba/fastjson2/JSONFactory.setContextReaderCreator:(Lcom/alibaba/fastjson2/reader/ObjectReaderCreator;)V
      29: aload_0
      30: getfield      #5                  // Field writerMap:Ljava/util/Map;
      33: aload_1
      34: invokedynamic #12,  0             // InvokeDynamic #1:apply:()Ljava/util/function/Function;
      39: invokeinterface #9,  3            // InterfaceMethod java/util/Map.computeIfAbsent:(Ljava/lang/Object;Ljava/util/function/Function;)Ljava/lang/Object;
      44: checkcast     #13                 // class com/alibaba/fastjson2/writer/ObjectWriterCreator
      47: invokestatic  #14                 // Method com/alibaba/fastjson2/JSONFactory.setContextWriterCreator:(Lcom/alibaba/fastjson2/writer/ObjectWriterCreator;)V
      50: return

  public void onAddClassLoader(org.apache.dubbo.rpc.model.FrameworkModel, java.lang.ClassLoader);
    Code:
       0: return

  public void onRemoveClassLoader(org.apache.dubbo.rpc.model.FrameworkModel, java.lang.ClassLoader);
    Code:
       0: aload_0
       1: getfield      #4                  // Field readerMap:Ljava/util/Map;
       4: aload_2
       5: invokeinterface #15,  2           // InterfaceMethod java/util/Map.remove:(Ljava/lang/Object;)Ljava/lang/Object;
      10: pop
      11: aload_0
      12: getfield      #5                  // Field writerMap:Ljava/util/Map;
      15: aload_2
      16: invokeinterface #15,  2           // InterfaceMethod java/util/Map.remove:(Ljava/lang/Object;)Ljava/lang/Object;
      21: pop
      22: return

  public void onRemoveClassLoader(org.apache.dubbo.rpc.model.ScopeModel, java.lang.ClassLoader);
    Code:
       0: aload_0
       1: aload_1
       2: checkcast     #16                 // class org/apache/dubbo/rpc/model/FrameworkModel
       5: aload_2
       6: invokevirtual #17                 // Method onRemoveClassLoader:(Lorg/apache/dubbo/rpc/model/FrameworkModel;Ljava/lang/ClassLoader;)V
       9: return

  public void onAddClassLoader(org.apache.dubbo.rpc.model.ScopeModel, java.lang.ClassLoader);
    Code:
       0: aload_0
       1: aload_1
       2: checkcast     #16                 // class org/apache/dubbo/rpc/model/FrameworkModel
       5: aload_2
       6: invokevirtual #18                 // Method onAddClassLoader:(Lorg/apache/dubbo/rpc/model/FrameworkModel;Ljava/lang/ClassLoader;)V
       9: return

  static {};
    Code:
       0: new           #19                 // class org/apache/dubbo/common/serialize/fastjson2/Fastjson2CreatorManager$1
       3: dup
       4: invokespecial #20                 // Method org/apache/dubbo/common/serialize/fastjson2/Fastjson2CreatorManager$1."<init>":()V
       7: putstatic     #7                  // Field SYSTEM_CLASSLOADER_KEY:Ljava/lang/ClassLoader;
      10: return
}
