Compiled from "Fastjson2SecurityManager.java"
public class org.apache.dubbo.common.serialize.fastjson2.Fastjson2SecurityManager$Handler extends com.alibaba.fastjson2.filter.ContextAutoTypeBeforeHandler {
  final org.apache.dubbo.common.utils.SerializeCheckStatus status;

  final org.apache.dubbo.common.utils.SerializeSecurityManager serializeSecurityManager;

  final java.util.Map<java.lang.String, java.lang.Class<?>> classCache;

  final java.util.Set<java.lang.String> disAllowedList;

  final boolean checkSerializable;

  public org.apache.dubbo.common.serialize.fastjson2.Fastjson2SecurityManager$Handler(org.apache.dubbo.common.utils.SerializeCheckStatus, org.apache.dubbo.common.utils.SerializeSecurityManager, boolean, java.lang.String[], java.util.Set<java.lang.String>);
    Code:
       0: aload_0
       1: iconst_1
       2: aload         4
       4: invokespecial #2                  // Method com/alibaba/fastjson2/filter/ContextAutoTypeBeforeHandler."<init>":(Z[Ljava/lang/String;)V
       7: aload_0
       8: new           #3                  // class java/util/concurrent/ConcurrentHashMap
      11: dup
      12: bipush        16
      14: ldc           #4                  // float 0.75f
      16: iconst_1
      17: invokespecial #5                  // Method java/util/concurrent/ConcurrentHashMap."<init>":(IFI)V
      20: putfield      #6                  // Field classCache:Ljava/util/Map;
      23: aload_0
      24: aload_1
      25: putfield      #7                  // Field status:Lorg/apache/dubbo/common/utils/SerializeCheckStatus;
      28: aload_0
      29: aload_2
      30: putfield      #8                  // Field serializeSecurityManager:Lorg/apache/dubbo/common/utils/SerializeSecurityManager;
      33: aload_0
      34: iload_3
      35: putfield      #9                  // Field checkSerializable:Z
      38: aload_0
      39: aload         5
      41: putfield      #10                 // Field disAllowedList:Ljava/util/Set;
      44: return

  public java.lang.Class<?> apply(java.lang.String, java.lang.Class<?>, long);
    Code:
       0: aload_0
       1: aload_1
       2: aload_2
       3: lload_3
       4: invokespecial #11                 // Method com/alibaba/fastjson2/filter/ContextAutoTypeBeforeHandler.apply:(Ljava/lang/String;Ljava/lang/Class;J)Ljava/lang/Class;
       7: astore        5
       9: aload         5
      11: ifnull        17
      14: aload         5
      16: areturn
      17: aload_0
      18: getfield      #7                  // Field status:Lorg/apache/dubbo/common/utils/SerializeCheckStatus;
      21: getstatic     #12                 // Field org/apache/dubbo/common/utils/SerializeCheckStatus.STRICT:Lorg/apache/dubbo/common/utils/SerializeCheckStatus;
      24: if_acmpne     87
      27: new           #13                 // class java/lang/StringBuilder
      30: dup
      31: invokespecial #14                 // Method java/lang/StringBuilder."<init>":()V
      34: ldc           #15                 // String [Serialization Security] Serialized class
      36: invokevirtual #16                 // Method java/lang/StringBuilder.append:(Ljava/lang/String;)Ljava/lang/StringBuilder;
      39: aload_1
      40: invokevirtual #16                 // Method java/lang/StringBuilder.append:(Ljava/lang/String;)Ljava/lang/StringBuilder;
      43: ldc           #17                 // String  is not in allow list. Current mode is `STRICT`, will disallow to deserialize it by default. Please add it into security/serialize.allowlist or follow FAQ to configure it.
      45: invokevirtual #16                 // Method java/lang/StringBuilder.append:(Ljava/lang/String;)Ljava/lang/StringBuilder;
      48: invokevirtual #18                 // Method java/lang/StringBuilder.toString:()Ljava/lang/String;
      51: astore        6
      53: aload_0
      54: getfield      #8                  // Field serializeSecurityManager:Lorg/apache/dubbo/common/utils/SerializeSecurityManager;
      57: invokevirtual #19                 // Method org/apache/dubbo/common/utils/SerializeSecurityManager.getWarnedClasses:()Ljava/util/Set;
      60: aload_1
      61: invokeinterface #20,  2           // InterfaceMethod java/util/Set.add:(Ljava/lang/Object;)Z
      66: ifeq          85
      69: invokestatic  #21                 // Method org/apache/dubbo/common/serialize/fastjson2/Fastjson2SecurityManager.access$000:()Lorg/apache/dubbo/common/logger/ErrorTypeAwareLogger;
      72: ldc           #22                 // String 4-21
      74: ldc           #23                 // String
      76: ldc           #23                 // String
      78: aload         6
      80: invokeinterface #24,  5           // InterfaceMethod org/apache/dubbo/common/logger/ErrorTypeAwareLogger.error:(Ljava/lang/String;Ljava/lang/String;Ljava/lang/String;Ljava/lang/String;)V
      85: aconst_null
      86: areturn
      87: aload_0
      88: aload_1
      89: invokevirtual #25                 // Method loadClassDirectly:(Ljava/lang/String;)Ljava/lang/Class;
      92: astore        6
      94: aload         6
      96: ifnull        170
      99: aload_0
     100: getfield      #7                  // Field status:Lorg/apache/dubbo/common/utils/SerializeCheckStatus;
     103: getstatic     #26                 // Field org/apache/dubbo/common/utils/SerializeCheckStatus.WARN:Lorg/apache/dubbo/common/utils/SerializeCheckStatus;
     106: if_acmpne     167
     109: aload_0
     110: getfield      #8                  // Field serializeSecurityManager:Lorg/apache/dubbo/common/utils/SerializeSecurityManager;
     113: invokevirtual #19                 // Method org/apache/dubbo/common/utils/SerializeSecurityManager.getWarnedClasses:()Ljava/util/Set;
     116: aload_1
     117: invokeinterface #20,  2           // InterfaceMethod java/util/Set.add:(Ljava/lang/Object;)Z
     122: ifeq          167
     125: invokestatic  #21                 // Method org/apache/dubbo/common/serialize/fastjson2/Fastjson2SecurityManager.access$000:()Lorg/apache/dubbo/common/logger/ErrorTypeAwareLogger;
     128: ldc           #22                 // String 4-21
     130: ldc           #23                 // String
     132: ldc           #23                 // String
     134: new           #13                 // class java/lang/StringBuilder
     137: dup
     138: invokespecial #14                 // Method java/lang/StringBuilder."<init>":()V
     141: ldc           #15                 // String [Serialization Security] Serialized class
     143: invokevirtual #16                 // Method java/lang/StringBuilder.append:(Ljava/lang/String;)Ljava/lang/StringBuilder;
     146: aload         6
     148: invokevirtual #27                 // Method java/lang/Class.getName:()Ljava/lang/String;
     151: invokevirtual #16                 // Method java/lang/StringBuilder.append:(Ljava/lang/String;)Ljava/lang/StringBuilder;
     154: ldc           #28                 // String  is not in allow list. Current mode is `WARN`, will allow to deserialize it by default. Dubbo will set to `STRICT` mode by default in the future. Please add it into security/serialize.allowlist or follow FAQ to configure it.
     156: invokevirtual #16                 // Method java/lang/StringBuilder.append:(Ljava/lang/String;)Ljava/lang/StringBuilder;
     159: invokevirtual #18                 // Method java/lang/StringBuilder.toString:()Ljava/lang/String;
     162: invokeinterface #24,  5           // InterfaceMethod org/apache/dubbo/common/logger/ErrorTypeAwareLogger.error:(Ljava/lang/String;Ljava/lang/String;Ljava/lang/String;Ljava/lang/String;)V
     167: aload         6
     169: areturn
     170: aconst_null
     171: areturn

  public boolean checkIfDisAllow(java.lang.String);
    Code:
       0: aload_0
       1: getfield      #10                 // Field disAllowedList:Ljava/util/Set;
       4: invokeinterface #29,  1           // InterfaceMethod java/util/Set.stream:()Ljava/util/stream/Stream;
       9: aload_1
      10: dup
      11: invokevirtual #30                 // Method java/lang/Object.getClass:()Ljava/lang/Class;
      14: pop
      15: invokedynamic #31,  0             // InvokeDynamic #0:test:(Ljava/lang/String;)Ljava/util/function/Predicate;
      20: invokeinterface #32,  2           // InterfaceMethod java/util/stream/Stream.anyMatch:(Ljava/util/function/Predicate;)Z
      25: ireturn

  public boolean isCheckSerializable();
    Code:
       0: aload_0
       1: getfield      #9                  // Field checkSerializable:Z
       4: ireturn

  public java.lang.Class<?> loadClassDirectly(java.lang.String);
    Code:
       0: aload_0
       1: getfield      #6                  // Field classCache:Ljava/util/Map;
       4: aload_1
       5: invokeinterface #33,  2           // InterfaceMethod java/util/Map.get:(Ljava/lang/Object;)Ljava/lang/Object;
      10: checkcast     #34                 // class java/lang/Class
      13: astore_2
      14: aload_2
      15: ifnonnull     85
      18: aload_0
      19: aload_1
      20: invokevirtual #35                 // Method checkIfDisAllow:(Ljava/lang/String;)Z
      23: ifeq          85
      26: ldc           #36                 // class org/apache/dubbo/common/serialize/fastjson2/Fastjson2SecurityManager$DenyClass
      28: astore_2
      29: new           #13                 // class java/lang/StringBuilder
      32: dup
      33: invokespecial #14                 // Method java/lang/StringBuilder."<init>":()V
      36: ldc           #15                 // String [Serialization Security] Serialized class
      38: invokevirtual #16                 // Method java/lang/StringBuilder.append:(Ljava/lang/String;)Ljava/lang/StringBuilder;
      41: aload_1
      42: invokevirtual #16                 // Method java/lang/StringBuilder.append:(Ljava/lang/String;)Ljava/lang/StringBuilder;
      45: ldc           #37                 // String  is in disAllow list. Current mode is `WARN`, will disallow to deserialize it by default. Please add it into security/serialize.allowlist or follow FAQ to configure it.
      47: invokevirtual #16                 // Method java/lang/StringBuilder.append:(Ljava/lang/String;)Ljava/lang/StringBuilder;
      50: invokevirtual #18                 // Method java/lang/StringBuilder.toString:()Ljava/lang/String;
      53: astore_3
      54: aload_0
      55: getfield      #8                  // Field serializeSecurityManager:Lorg/apache/dubbo/common/utils/SerializeSecurityManager;
      58: invokevirtual #19                 // Method org/apache/dubbo/common/utils/SerializeSecurityManager.getWarnedClasses:()Ljava/util/Set;
      61: aload_1
      62: invokeinterface #20,  2           // InterfaceMethod java/util/Set.add:(Ljava/lang/Object;)Z
      67: ifeq          85
      70: invokestatic  #21                 // Method org/apache/dubbo/common/serialize/fastjson2/Fastjson2SecurityManager.access$000:()Lorg/apache/dubbo/common/logger/ErrorTypeAwareLogger;
      73: ldc           #22                 // String 4-21
      75: ldc           #23                 // String
      77: ldc           #23                 // String
      79: aload_3
      80: invokeinterface #24,  5           // InterfaceMethod org/apache/dubbo/common/logger/ErrorTypeAwareLogger.error:(Ljava/lang/String;Ljava/lang/String;Ljava/lang/String;Ljava/lang/String;)V
      85: aload_2
      86: ifnonnull     94
      89: aload_1
      90: invokestatic  #38                 // Method com/alibaba/fastjson2/util/TypeUtils.getMapping:(Ljava/lang/String;)Ljava/lang/Class;
      93: astore_2
      94: aload_2
      95: ifnonnull     103
      98: aload_1
      99: invokestatic  #39                 // Method com/alibaba/fastjson2/util/TypeUtils.loadClass:(Ljava/lang/String;)Ljava/lang/Class;
     102: astore_2
     103: aload_2
     104: ifnull        128
     107: aload_0
     108: getfield      #6                  // Field classCache:Ljava/util/Map;
     111: aload_1
     112: aload_2
     113: invokeinterface #40,  3           // InterfaceMethod java/util/Map.putIfAbsent:(Ljava/lang/Object;Ljava/lang/Object;)Ljava/lang/Object;
     118: checkcast     #34                 // class java/lang/Class
     121: astore_3
     122: aload_3
     123: ifnull        128
     126: aload_3
     127: astore_2
     128: aload_2
     129: ldc           #36                 // class org/apache/dubbo/common/serialize/fastjson2/Fastjson2SecurityManager$DenyClass
     131: if_acmpne     136
     134: aconst_null
     135: areturn
     136: aload_2
     137: areturn
}
