Compiled from "FastJson2Serialization.java"
public class org.apache.dubbo.common.serialize.fastjson2.FastJson2Serialization implements org.apache.dubbo.common.serialize.Serialization {
  public org.apache.dubbo.common.serialize.fastjson2.FastJson2Serialization();
    Code:
       0: aload_0
       1: invokespecial #2                  // Method java/lang/Object."<init>":()V
       4: return

  public byte getContentTypeId();
    Code:
       0: bipush        23
       2: ireturn

  public java.lang.String getContentType();
    Code:
       0: ldc           #3                  // String text/jsonb
       2: areturn

  public org.apache.dubbo.common.serialize.ObjectOutput serialize(org.apache.dubbo.common.URL, java.io.OutputStream) throws java.io.IOException;
    Code:
       0: aload_1
       1: invokestatic  #4                  // Method java/util/Optional.ofNullable:(Ljava/lang/Object;)Ljava/util/Optional;
       4: invokedynamic #5,  0              // InvokeDynamic #0:apply:()Ljava/util/function/Function;
       9: invokevirtual #6                  // Method java/util/Optional.map:(Ljava/util/function/Function;)Ljava/util/Optional;
      12: invokestatic  #7                  // Method org/apache/dubbo/rpc/model/FrameworkModel.defaultModel:()Lorg/apache/dubbo/rpc/model/FrameworkModel;
      15: invokevirtual #8                  // Method java/util/Optional.orElse:(Ljava/lang/Object;)Ljava/lang/Object;
      18: checkcast     #9                  // class org/apache/dubbo/rpc/model/FrameworkModel
      21: invokevirtual #10                 // Method org/apache/dubbo/rpc/model/FrameworkModel.getBeanFactory:()Lorg/apache/dubbo/common/beans/factory/ScopeBeanFactory;
      24: ldc           #11                 // class org/apache/dubbo/common/serialize/fastjson2/Fastjson2CreatorManager
      26: invokevirtual #12                 // Method org/apache/dubbo/common/beans/factory/ScopeBeanFactory.getBean:(Ljava/lang/Class;)Ljava/lang/Object;
      29: checkcast     #11                 // class org/apache/dubbo/common/serialize/fastjson2/Fastjson2CreatorManager
      32: astore_3
      33: aload_1
      34: invokestatic  #4                  // Method java/util/Optional.ofNullable:(Ljava/lang/Object;)Ljava/util/Optional;
      37: invokedynamic #5,  0              // InvokeDynamic #0:apply:()Ljava/util/function/Function;
      42: invokevirtual #6                  // Method java/util/Optional.map:(Ljava/util/function/Function;)Ljava/util/Optional;
      45: invokestatic  #7                  // Method org/apache/dubbo/rpc/model/FrameworkModel.defaultModel:()Lorg/apache/dubbo/rpc/model/FrameworkModel;
      48: invokevirtual #8                  // Method java/util/Optional.orElse:(Ljava/lang/Object;)Ljava/lang/Object;
      51: checkcast     #9                  // class org/apache/dubbo/rpc/model/FrameworkModel
      54: invokevirtual #10                 // Method org/apache/dubbo/rpc/model/FrameworkModel.getBeanFactory:()Lorg/apache/dubbo/common/beans/factory/ScopeBeanFactory;
      57: ldc           #13                 // class org/apache/dubbo/common/serialize/fastjson2/Fastjson2SecurityManager
      59: invokevirtual #12                 // Method org/apache/dubbo/common/beans/factory/ScopeBeanFactory.getBean:(Ljava/lang/Class;)Ljava/lang/Object;
      62: checkcast     #13                 // class org/apache/dubbo/common/serialize/fastjson2/Fastjson2SecurityManager
      65: astore        4
      67: new           #14                 // class org/apache/dubbo/common/serialize/fastjson2/FastJson2ObjectOutput
      70: dup
      71: aload_3
      72: aload         4
      74: aload_2
      75: invokespecial #15                 // Method org/apache/dubbo/common/serialize/fastjson2/FastJson2ObjectOutput."<init>":(Lorg/apache/dubbo/common/serialize/fastjson2/Fastjson2CreatorManager;Lorg/apache/dubbo/common/serialize/fastjson2/Fastjson2SecurityManager;Ljava/io/OutputStream;)V
      78: areturn

  public org.apache.dubbo.common.serialize.ObjectInput deserialize(org.apache.dubbo.common.URL, java.io.InputStream) throws java.io.IOException;
    Code:
       0: aload_1
       1: invokestatic  #4                  // Method java/util/Optional.ofNullable:(Ljava/lang/Object;)Ljava/util/Optional;
       4: invokedynamic #5,  0              // InvokeDynamic #0:apply:()Ljava/util/function/Function;
       9: invokevirtual #6                  // Method java/util/Optional.map:(Ljava/util/function/Function;)Ljava/util/Optional;
      12: invokestatic  #7                  // Method org/apache/dubbo/rpc/model/FrameworkModel.defaultModel:()Lorg/apache/dubbo/rpc/model/FrameworkModel;
      15: invokevirtual #8                  // Method java/util/Optional.orElse:(Ljava/lang/Object;)Ljava/lang/Object;
      18: checkcast     #9                  // class org/apache/dubbo/rpc/model/FrameworkModel
      21: invokevirtual #10                 // Method org/apache/dubbo/rpc/model/FrameworkModel.getBeanFactory:()Lorg/apache/dubbo/common/beans/factory/ScopeBeanFactory;
      24: ldc           #11                 // class org/apache/dubbo/common/serialize/fastjson2/Fastjson2CreatorManager
      26: invokevirtual #12                 // Method org/apache/dubbo/common/beans/factory/ScopeBeanFactory.getBean:(Ljava/lang/Class;)Ljava/lang/Object;
      29: checkcast     #11                 // class org/apache/dubbo/common/serialize/fastjson2/Fastjson2CreatorManager
      32: astore_3
      33: aload_1
      34: invokestatic  #4                  // Method java/util/Optional.ofNullable:(Ljava/lang/Object;)Ljava/util/Optional;
      37: invokedynamic #5,  0              // InvokeDynamic #0:apply:()Ljava/util/function/Function;
      42: invokevirtual #6                  // Method java/util/Optional.map:(Ljava/util/function/Function;)Ljava/util/Optional;
      45: invokestatic  #7                  // Method org/apache/dubbo/rpc/model/FrameworkModel.defaultModel:()Lorg/apache/dubbo/rpc/model/FrameworkModel;
      48: invokevirtual #8                  // Method java/util/Optional.orElse:(Ljava/lang/Object;)Ljava/lang/Object;
      51: checkcast     #9                  // class org/apache/dubbo/rpc/model/FrameworkModel
      54: invokevirtual #10                 // Method org/apache/dubbo/rpc/model/FrameworkModel.getBeanFactory:()Lorg/apache/dubbo/common/beans/factory/ScopeBeanFactory;
      57: ldc           #13                 // class org/apache/dubbo/common/serialize/fastjson2/Fastjson2SecurityManager
      59: invokevirtual #12                 // Method org/apache/dubbo/common/beans/factory/ScopeBeanFactory.getBean:(Ljava/lang/Class;)Ljava/lang/Object;
      62: checkcast     #13                 // class org/apache/dubbo/common/serialize/fastjson2/Fastjson2SecurityManager
      65: astore        4
      67: new           #16                 // class org/apache/dubbo/common/serialize/fastjson2/FastJson2ObjectInput
      70: dup
      71: aload_3
      72: aload         4
      74: aload_2
      75: invokespecial #17                 // Method org/apache/dubbo/common/serialize/fastjson2/FastJson2ObjectInput."<init>":(Lorg/apache/dubbo/common/serialize/fastjson2/Fastjson2CreatorManager;Lorg/apache/dubbo/common/serialize/fastjson2/Fastjson2SecurityManager;Ljava/io/InputStream;)V
      78: areturn
}
