Compiled from "Fastjson2SecurityManager.java"
public class org.apache.dubbo.common.serialize.fastjson2.Fastjson2SecurityManager implements org.apache.dubbo.common.utils.AllowClassNotifyListener {
  private volatile org.apache.dubbo.common.serialize.fastjson2.Fastjson2SecurityManager$Handler securityFilter;

  private static final org.apache.dubbo.common.logger.ErrorTypeAwareLogger logger;

  private final org.apache.dubbo.common.utils.SerializeSecurityManager securityManager;

  private volatile org.apache.dubbo.common.utils.SerializeCheckStatus status;

  private volatile boolean checkSerializable;

  private volatile java.util.Set<java.lang.String> allowedList;

  private volatile java.util.Set<java.lang.String> disAllowedList;

  public org.apache.dubbo.common.serialize.fastjson2.Fastjson2SecurityManager(org.apache.dubbo.rpc.model.FrameworkModel);
    Code:
       0: aload_0
       1: invokespecial #2                  // Method java/lang/Object."<init>":()V
       4: aload_0
       5: getstatic     #3                  // Field org/apache/dubbo/common/utils/AllowClassNotifyListener.DEFAULT_STATUS:Lorg/apache/dubbo/common/utils/SerializeCheckStatus;
       8: putfield      #4                  // Field status:Lorg/apache/dubbo/common/utils/SerializeCheckStatus;
      11: aload_0
      12: iconst_1
      13: putfield      #5                  // Field checkSerializable:Z
      16: aload_0
      17: new           #6                  // class org/apache/dubbo/common/utils/ConcurrentHashSet
      20: dup
      21: iconst_1
      22: invokespecial #7                  // Method org/apache/dubbo/common/utils/ConcurrentHashSet."<init>":(I)V
      25: putfield      #8                  // Field allowedList:Ljava/util/Set;
      28: aload_0
      29: new           #6                  // class org/apache/dubbo/common/utils/ConcurrentHashSet
      32: dup
      33: iconst_1
      34: invokespecial #7                  // Method org/apache/dubbo/common/utils/ConcurrentHashSet."<init>":(I)V
      37: putfield      #9                  // Field disAllowedList:Ljava/util/Set;
      40: aload_0
      41: aload_1
      42: invokevirtual #10                 // Method org/apache/dubbo/rpc/model/FrameworkModel.getBeanFactory:()Lorg/apache/dubbo/common/beans/factory/ScopeBeanFactory;
      45: ldc           #11                 // class org/apache/dubbo/common/utils/SerializeSecurityManager
      47: invokevirtual #12                 // Method org/apache/dubbo/common/beans/factory/ScopeBeanFactory.getOrRegisterBean:(Ljava/lang/Class;)Ljava/lang/Object;
      50: checkcast     #11                 // class org/apache/dubbo/common/utils/SerializeSecurityManager
      53: putfield      #13                 // Field securityManager:Lorg/apache/dubbo/common/utils/SerializeSecurityManager;
      56: aload_0
      57: getfield      #13                 // Field securityManager:Lorg/apache/dubbo/common/utils/SerializeSecurityManager;
      60: aload_0
      61: invokevirtual #14                 // Method org/apache/dubbo/common/utils/SerializeSecurityManager.registerListener:(Lorg/apache/dubbo/common/utils/AllowClassNotifyListener;)V
      64: aload_0
      65: new           #15                 // class org/apache/dubbo/common/serialize/fastjson2/Fastjson2SecurityManager$Handler
      68: dup
      69: getstatic     #3                  // Field org/apache/dubbo/common/utils/AllowClassNotifyListener.DEFAULT_STATUS:Lorg/apache/dubbo/common/utils/SerializeCheckStatus;
      72: aload_0
      73: getfield      #13                 // Field securityManager:Lorg/apache/dubbo/common/utils/SerializeSecurityManager;
      76: iconst_1
      77: iconst_0
      78: anewarray     #16                 // class java/lang/String
      81: new           #6                  // class org/apache/dubbo/common/utils/ConcurrentHashSet
      84: dup
      85: invokespecial #17                 // Method org/apache/dubbo/common/utils/ConcurrentHashSet."<init>":()V
      88: invokespecial #18                 // Method org/apache/dubbo/common/serialize/fastjson2/Fastjson2SecurityManager$Handler."<init>":(Lorg/apache/dubbo/common/utils/SerializeCheckStatus;Lorg/apache/dubbo/common/utils/SerializeSecurityManager;Z[Ljava/lang/String;Ljava/util/Set;)V
      91: putfield      #19                 // Field securityFilter:Lorg/apache/dubbo/common/serialize/fastjson2/Fastjson2SecurityManager$Handler;
      94: return

  public synchronized void notifyPrefix(java.util.Set<java.lang.String>, java.util.Set<java.lang.String>);
    Code:
       0: aload_0
       1: aload_1
       2: putfield      #8                  // Field allowedList:Ljava/util/Set;
       5: aload_0
       6: aload_2
       7: putfield      #9                  // Field disAllowedList:Ljava/util/Set;
      10: aload_0
      11: new           #15                 // class org/apache/dubbo/common/serialize/fastjson2/Fastjson2SecurityManager$Handler
      14: dup
      15: aload_0
      16: getfield      #4                  // Field status:Lorg/apache/dubbo/common/utils/SerializeCheckStatus;
      19: aload_0
      20: getfield      #13                 // Field securityManager:Lorg/apache/dubbo/common/utils/SerializeSecurityManager;
      23: aload_0
      24: getfield      #5                  // Field checkSerializable:Z
      27: aload_0
      28: getfield      #8                  // Field allowedList:Ljava/util/Set;
      31: iconst_0
      32: anewarray     #16                 // class java/lang/String
      35: invokeinterface #20,  2           // InterfaceMethod java/util/Set.toArray:([Ljava/lang/Object;)[Ljava/lang/Object;
      40: checkcast     #21                 // class "[Ljava/lang/String;"
      43: aload_0
      44: getfield      #9                  // Field disAllowedList:Ljava/util/Set;
      47: invokespecial #18                 // Method org/apache/dubbo/common/serialize/fastjson2/Fastjson2SecurityManager$Handler."<init>":(Lorg/apache/dubbo/common/utils/SerializeCheckStatus;Lorg/apache/dubbo/common/utils/SerializeSecurityManager;Z[Ljava/lang/String;Ljava/util/Set;)V
      50: putfield      #19                 // Field securityFilter:Lorg/apache/dubbo/common/serialize/fastjson2/Fastjson2SecurityManager$Handler;
      53: return

  public synchronized void notifyCheckStatus(org.apache.dubbo.common.utils.SerializeCheckStatus);
    Code:
       0: aload_0
       1: aload_1
       2: putfield      #4                  // Field status:Lorg/apache/dubbo/common/utils/SerializeCheckStatus;
       5: aload_0
       6: new           #15                 // class org/apache/dubbo/common/serialize/fastjson2/Fastjson2SecurityManager$Handler
       9: dup
      10: aload_0
      11: getfield      #4                  // Field status:Lorg/apache/dubbo/common/utils/SerializeCheckStatus;
      14: aload_0
      15: getfield      #13                 // Field securityManager:Lorg/apache/dubbo/common/utils/SerializeSecurityManager;
      18: aload_0
      19: getfield      #5                  // Field checkSerializable:Z
      22: aload_0
      23: getfield      #8                  // Field allowedList:Ljava/util/Set;
      26: iconst_0
      27: anewarray     #16                 // class java/lang/String
      30: invokeinterface #20,  2           // InterfaceMethod java/util/Set.toArray:([Ljava/lang/Object;)[Ljava/lang/Object;
      35: checkcast     #21                 // class "[Ljava/lang/String;"
      38: aload_0
      39: getfield      #9                  // Field disAllowedList:Ljava/util/Set;
      42: invokespecial #18                 // Method org/apache/dubbo/common/serialize/fastjson2/Fastjson2SecurityManager$Handler."<init>":(Lorg/apache/dubbo/common/utils/SerializeCheckStatus;Lorg/apache/dubbo/common/utils/SerializeSecurityManager;Z[Ljava/lang/String;Ljava/util/Set;)V
      45: putfield      #19                 // Field securityFilter:Lorg/apache/dubbo/common/serialize/fastjson2/Fastjson2SecurityManager$Handler;
      48: return

  public synchronized void notifyCheckSerializable(boolean);
    Code:
       0: aload_0
       1: iload_1
       2: putfield      #5                  // Field checkSerializable:Z
       5: aload_0
       6: new           #15                 // class org/apache/dubbo/common/serialize/fastjson2/Fastjson2SecurityManager$Handler
       9: dup
      10: aload_0
      11: getfield      #4                  // Field status:Lorg/apache/dubbo/common/utils/SerializeCheckStatus;
      14: aload_0
      15: getfield      #13                 // Field securityManager:Lorg/apache/dubbo/common/utils/SerializeSecurityManager;
      18: aload_0
      19: getfield      #5                  // Field checkSerializable:Z
      22: aload_0
      23: getfield      #8                  // Field allowedList:Ljava/util/Set;
      26: iconst_0
      27: anewarray     #16                 // class java/lang/String
      30: invokeinterface #20,  2           // InterfaceMethod java/util/Set.toArray:([Ljava/lang/Object;)[Ljava/lang/Object;
      35: checkcast     #21                 // class "[Ljava/lang/String;"
      38: aload_0
      39: getfield      #9                  // Field disAllowedList:Ljava/util/Set;
      42: invokespecial #18                 // Method org/apache/dubbo/common/serialize/fastjson2/Fastjson2SecurityManager$Handler."<init>":(Lorg/apache/dubbo/common/utils/SerializeCheckStatus;Lorg/apache/dubbo/common/utils/SerializeSecurityManager;Z[Ljava/lang/String;Ljava/util/Set;)V
      45: putfield      #19                 // Field securityFilter:Lorg/apache/dubbo/common/serialize/fastjson2/Fastjson2SecurityManager$Handler;
      48: return

  public org.apache.dubbo.common.serialize.fastjson2.Fastjson2SecurityManager$Handler getSecurityFilter();
    Code:
       0: aload_0
       1: getfield      #19                 // Field securityFilter:Lorg/apache/dubbo/common/serialize/fastjson2/Fastjson2SecurityManager$Handler;
       4: areturn

  static org.apache.dubbo.common.logger.ErrorTypeAwareLogger access$000();
    Code:
       0: getstatic     #1                  // Field logger:Lorg/apache/dubbo/common/logger/ErrorTypeAwareLogger;
       3: areturn

  static {};
    Code:
       0: ldc           #22                 // class org/apache/dubbo/common/serialize/fastjson2/Fastjson2SecurityManager
       2: invokestatic  #23                 // Method org/apache/dubbo/common/logger/LoggerFactory.getErrorTypeAwareLogger:(Ljava/lang/Class;)Lorg/apache/dubbo/common/logger/ErrorTypeAwareLogger;
       5: putstatic     #1                  // Field logger:Lorg/apache/dubbo/common/logger/ErrorTypeAwareLogger;
       8: return
}
