Compiled from "MustacheViewResolver.java"
public class org.springframework.boot.web.reactive.result.view.MustacheViewResolver extends org.springframework.web.reactive.result.view.UrlBasedViewResolver {
  private final com.samskivert.mustache.Mustache$Compiler compiler;

  private java.lang.String charset;

  public org.springframework.boot.web.reactive.result.view.MustacheViewResolver();
    Code:
       0: aload_0
       1: invokespecial #1                  // Method org/springframework/web/reactive/result/view/UrlBasedViewResolver."<init>":()V
       4: aload_0
       5: invokestatic  #7                  // Method com/samskivert/mustache/Mustache.compiler:()Lcom/samskivert/mustache/Mustache$Compiler;
       8: putfield      #13                 // Field compiler:Lcom/samskivert/mustache/Mustache$Compiler;
      11: aload_0
      12: aload_0
      13: invokevirtual #18                 // Method requiredViewClass:()Ljava/lang/Class;
      16: invokevirtual #22                 // Method setViewClass:(Ljava/lang/Class;)V
      19: return

  public org.springframework.boot.web.reactive.result.view.MustacheViewResolver(com.samskivert.mustache.Mustache$Compiler);
    Code:
       0: aload_0
       1: invokespecial #1                  // Method org/springframework/web/reactive/result/view/UrlBasedViewResolver."<init>":()V
       4: aload_0
       5: aload_1
       6: putfield      #13                 // Field compiler:Lcom/samskivert/mustache/Mustache$Compiler;
       9: aload_0
      10: aload_0
      11: invokevirtual #18                 // Method requiredViewClass:()Ljava/lang/Class;
      14: invokevirtual #22                 // Method setViewClass:(Ljava/lang/Class;)V
      17: return

  public void setCharset(java.lang.String);
    Code:
       0: aload_0
       1: aload_1
       2: putfield      #26                 // Field charset:Ljava/lang/String;
       5: return

  protected java.lang.Class<?> requiredViewClass();
    Code:
       0: ldc           #30                 // class org/springframework/boot/web/reactive/result/view/MustacheView
       2: areturn

  protected org.springframework.web.reactive.result.view.AbstractUrlBasedView createView(java.lang.String);
    Code:
       0: aload_0
       1: aload_1
       2: invokespecial #32                 // Method org/springframework/web/reactive/result/view/UrlBasedViewResolver.createView:(Ljava/lang/String;)Lorg/springframework/web/reactive/result/view/AbstractUrlBasedView;
       5: checkcast     #30                 // class org/springframework/boot/web/reactive/result/view/MustacheView
       8: astore_2
       9: aload_2
      10: aload_0
      11: getfield      #13                 // Field compiler:Lcom/samskivert/mustache/Mustache$Compiler;
      14: invokevirtual #36                 // Method org/springframework/boot/web/reactive/result/view/MustacheView.setCompiler:(Lcom/samskivert/mustache/Mustache$Compiler;)V
      17: aload_2
      18: aload_0
      19: getfield      #26                 // Field charset:Ljava/lang/String;
      22: invokevirtual #40                 // Method org/springframework/boot/web/reactive/result/view/MustacheView.setCharset:(Ljava/lang/String;)V
      25: aload_2
      26: areturn

  protected org.springframework.web.reactive.result.view.AbstractUrlBasedView instantiateView();
    Code:
       0: aload_0
       1: invokevirtual #44                 // Method getViewClass:()Ljava/lang/Class;
       4: ldc           #30                 // class org/springframework/boot/web/reactive/result/view/MustacheView
       6: if_acmpne     19
       9: new           #30                 // class org/springframework/boot/web/reactive/result/view/MustacheView
      12: dup
      13: invokespecial #47                 // Method org/springframework/boot/web/reactive/result/view/MustacheView."<init>":()V
      16: goto          23
      19: aload_0
      20: invokespecial #48                 // Method org/springframework/web/reactive/result/view/UrlBasedViewResolver.instantiateView:()Lorg/springframework/web/reactive/result/view/AbstractUrlBasedView;
      23: areturn
}
