Compiled from "Exchangers.java"
public class org.apache.dubbo.remoting.exchange.Exchangers {
  private org.apache.dubbo.remoting.exchange.Exchangers();
    Code:
       0: aload_0
       1: invokespecial #1                  // Method java/lang/Object."<init>":()V
       4: return

  public static org.apache.dubbo.remoting.exchange.ExchangeServer bind(java.lang.String, org.apache.dubbo.remoting.exchange.support.Replier<?>) throws org.apache.dubbo.remoting.RemotingException;
    Code:
       0: aload_0
       1: invokestatic  #2                  // Method org/apache/dubbo/common/URL.valueOf:(Ljava/lang/String;)Lorg/apache/dubbo/common/URL;
       4: aload_1
       5: invokestatic  #3                  // Method bind:(Lorg/apache/dubbo/common/URL;Lorg/apache/dubbo/remoting/exchange/support/Replier;)Lorg/apache/dubbo/remoting/exchange/ExchangeServer;
       8: areturn

  public static org.apache.dubbo.remoting.exchange.ExchangeServer bind(org.apache.dubbo.common.URL, org.apache.dubbo.remoting.exchange.support.Replier<?>) throws org.apache.dubbo.remoting.RemotingException;
    Code:
       0: aload_0
       1: new           #4                  // class org/apache/dubbo/remoting/transport/ChannelHandlerAdapter
       4: dup
       5: invokespecial #5                  // Method org/apache/dubbo/remoting/transport/ChannelHandlerAdapter."<init>":()V
       8: aload_1
       9: invokestatic  #6                  // Method bind:(Lorg/apache/dubbo/common/URL;Lorg/apache/dubbo/remoting/ChannelHandler;Lorg/apache/dubbo/remoting/exchange/support/Replier;)Lorg/apache/dubbo/remoting/exchange/ExchangeServer;
      12: areturn

  public static org.apache.dubbo.remoting.exchange.ExchangeServer bind(java.lang.String, org.apache.dubbo.remoting.ChannelHandler, org.apache.dubbo.remoting.exchange.support.Replier<?>) throws org.apache.dubbo.remoting.RemotingException;
    Code:
       0: aload_0
       1: invokestatic  #2                  // Method org/apache/dubbo/common/URL.valueOf:(Ljava/lang/String;)Lorg/apache/dubbo/common/URL;
       4: aload_1
       5: aload_2
       6: invokestatic  #6                  // Method bind:(Lorg/apache/dubbo/common/URL;Lorg/apache/dubbo/remoting/ChannelHandler;Lorg/apache/dubbo/remoting/exchange/support/Replier;)Lorg/apache/dubbo/remoting/exchange/ExchangeServer;
       9: areturn

  public static org.apache.dubbo.remoting.exchange.ExchangeServer bind(org.apache.dubbo.common.URL, org.apache.dubbo.remoting.ChannelHandler, org.apache.dubbo.remoting.exchange.support.Replier<?>) throws org.apache.dubbo.remoting.RemotingException;
    Code:
       0: aload_0
       1: new           #7                  // class org/apache/dubbo/remoting/exchange/support/ExchangeHandlerDispatcher
       4: dup
       5: aload_0
       6: invokevirtual #8                  // Method org/apache/dubbo/common/URL.getOrDefaultFrameworkModel:()Lorg/apache/dubbo/rpc/model/FrameworkModel;
       9: aload_2
      10: iconst_1
      11: anewarray     #9                  // class org/apache/dubbo/remoting/ChannelHandler
      14: dup
      15: iconst_0
      16: aload_1
      17: aastore
      18: invokespecial #10                 // Method org/apache/dubbo/remoting/exchange/support/ExchangeHandlerDispatcher."<init>":(Lorg/apache/dubbo/rpc/model/FrameworkModel;Lorg/apache/dubbo/remoting/exchange/support/Replier;[Lorg/apache/dubbo/remoting/ChannelHandler;)V
      21: invokestatic  #11                 // Method bind:(Lorg/apache/dubbo/common/URL;Lorg/apache/dubbo/remoting/exchange/ExchangeHandler;)Lorg/apache/dubbo/remoting/exchange/ExchangeServer;
      24: areturn

  public static org.apache.dubbo.remoting.exchange.ExchangeServer bind(java.lang.String, org.apache.dubbo.remoting.exchange.ExchangeHandler) throws org.apache.dubbo.remoting.RemotingException;
    Code:
       0: aload_0
       1: invokestatic  #2                  // Method org/apache/dubbo/common/URL.valueOf:(Ljava/lang/String;)Lorg/apache/dubbo/common/URL;
       4: aload_1
       5: invokestatic  #11                 // Method bind:(Lorg/apache/dubbo/common/URL;Lorg/apache/dubbo/remoting/exchange/ExchangeHandler;)Lorg/apache/dubbo/remoting/exchange/ExchangeServer;
       8: areturn

  public static org.apache.dubbo.remoting.exchange.ExchangeServer bind(org.apache.dubbo.common.URL, org.apache.dubbo.remoting.exchange.ExchangeHandler) throws org.apache.dubbo.remoting.RemotingException;
    Code:
       0: aload_0
       1: ifnonnull     14
       4: new           #12                 // class java/lang/IllegalArgumentException
       7: dup
       8: ldc           #13                 // String url == null
      10: invokespecial #14                 // Method java/lang/IllegalArgumentException."<init>":(Ljava/lang/String;)V
      13: athrow
      14: aload_1
      15: ifnonnull     28
      18: new           #12                 // class java/lang/IllegalArgumentException
      21: dup
      22: ldc           #15                 // String handler == null
      24: invokespecial #14                 // Method java/lang/IllegalArgumentException."<init>":(Ljava/lang/String;)V
      27: athrow
      28: aload_0
      29: ldc           #17                 // String codec
      31: ldc           #18                 // String exchange
      33: invokevirtual #19                 // Method org/apache/dubbo/common/URL.addParameterIfAbsent:(Ljava/lang/String;Ljava/lang/String;)Lorg/apache/dubbo/common/URL;
      36: astore_0
      37: aload_0
      38: invokestatic  #20                 // Method getExchanger:(Lorg/apache/dubbo/common/URL;)Lorg/apache/dubbo/remoting/exchange/Exchanger;
      41: aload_0
      42: aload_1
      43: invokeinterface #21,  3           // InterfaceMethod org/apache/dubbo/remoting/exchange/Exchanger.bind:(Lorg/apache/dubbo/common/URL;Lorg/apache/dubbo/remoting/exchange/ExchangeHandler;)Lorg/apache/dubbo/remoting/exchange/ExchangeServer;
      48: areturn

  public static org.apache.dubbo.remoting.exchange.ExchangeClient connect(java.lang.String) throws org.apache.dubbo.remoting.RemotingException;
    Code:
       0: aload_0
       1: invokestatic  #2                  // Method org/apache/dubbo/common/URL.valueOf:(Ljava/lang/String;)Lorg/apache/dubbo/common/URL;
       4: invokestatic  #22                 // Method connect:(Lorg/apache/dubbo/common/URL;)Lorg/apache/dubbo/remoting/exchange/ExchangeClient;
       7: areturn

  public static org.apache.dubbo.remoting.exchange.ExchangeClient connect(org.apache.dubbo.common.URL) throws org.apache.dubbo.remoting.RemotingException;
    Code:
       0: aload_0
       1: new           #4                  // class org/apache/dubbo/remoting/transport/ChannelHandlerAdapter
       4: dup
       5: invokespecial #5                  // Method org/apache/dubbo/remoting/transport/ChannelHandlerAdapter."<init>":()V
       8: aconst_null
       9: invokestatic  #23                 // Method connect:(Lorg/apache/dubbo/common/URL;Lorg/apache/dubbo/remoting/ChannelHandler;Lorg/apache/dubbo/remoting/exchange/support/Replier;)Lorg/apache/dubbo/remoting/exchange/ExchangeClient;
      12: areturn

  public static org.apache.dubbo.remoting.exchange.ExchangeClient connect(java.lang.String, org.apache.dubbo.remoting.exchange.support.Replier<?>) throws org.apache.dubbo.remoting.RemotingException;
    Code:
       0: aload_0
       1: invokestatic  #2                  // Method org/apache/dubbo/common/URL.valueOf:(Ljava/lang/String;)Lorg/apache/dubbo/common/URL;
       4: new           #4                  // class org/apache/dubbo/remoting/transport/ChannelHandlerAdapter
       7: dup
       8: invokespecial #5                  // Method org/apache/dubbo/remoting/transport/ChannelHandlerAdapter."<init>":()V
      11: aload_1
      12: invokestatic  #23                 // Method connect:(Lorg/apache/dubbo/common/URL;Lorg/apache/dubbo/remoting/ChannelHandler;Lorg/apache/dubbo/remoting/exchange/support/Replier;)Lorg/apache/dubbo/remoting/exchange/ExchangeClient;
      15: areturn

  public static org.apache.dubbo.remoting.exchange.ExchangeClient connect(org.apache.dubbo.common.URL, org.apache.dubbo.remoting.exchange.support.Replier<?>) throws org.apache.dubbo.remoting.RemotingException;
    Code:
       0: aload_0
       1: new           #4                  // class org/apache/dubbo/remoting/transport/ChannelHandlerAdapter
       4: dup
       5: invokespecial #5                  // Method org/apache/dubbo/remoting/transport/ChannelHandlerAdapter."<init>":()V
       8: aload_1
       9: invokestatic  #23                 // Method connect:(Lorg/apache/dubbo/common/URL;Lorg/apache/dubbo/remoting/ChannelHandler;Lorg/apache/dubbo/remoting/exchange/support/Replier;)Lorg/apache/dubbo/remoting/exchange/ExchangeClient;
      12: areturn

  public static org.apache.dubbo.remoting.exchange.ExchangeClient connect(java.lang.String, org.apache.dubbo.remoting.ChannelHandler, org.apache.dubbo.remoting.exchange.support.Replier<?>) throws org.apache.dubbo.remoting.RemotingException;
    Code:
       0: aload_0
       1: invokestatic  #2                  // Method org/apache/dubbo/common/URL.valueOf:(Ljava/lang/String;)Lorg/apache/dubbo/common/URL;
       4: aload_1
       5: aload_2
       6: invokestatic  #23                 // Method connect:(Lorg/apache/dubbo/common/URL;Lorg/apache/dubbo/remoting/ChannelHandler;Lorg/apache/dubbo/remoting/exchange/support/Replier;)Lorg/apache/dubbo/remoting/exchange/ExchangeClient;
       9: areturn

  public static org.apache.dubbo.remoting.exchange.ExchangeClient connect(org.apache.dubbo.common.URL, org.apache.dubbo.remoting.ChannelHandler, org.apache.dubbo.remoting.exchange.support.Replier<?>) throws org.apache.dubbo.remoting.RemotingException;
    Code:
       0: aload_0
       1: new           #7                  // class org/apache/dubbo/remoting/exchange/support/ExchangeHandlerDispatcher
       4: dup
       5: aload_0
       6: invokevirtual #8                  // Method org/apache/dubbo/common/URL.getOrDefaultFrameworkModel:()Lorg/apache/dubbo/rpc/model/FrameworkModel;
       9: aload_2
      10: iconst_1
      11: anewarray     #9                  // class org/apache/dubbo/remoting/ChannelHandler
      14: dup
      15: iconst_0
      16: aload_1
      17: aastore
      18: invokespecial #10                 // Method org/apache/dubbo/remoting/exchange/support/ExchangeHandlerDispatcher."<init>":(Lorg/apache/dubbo/rpc/model/FrameworkModel;Lorg/apache/dubbo/remoting/exchange/support/Replier;[Lorg/apache/dubbo/remoting/ChannelHandler;)V
      21: invokestatic  #24                 // Method connect:(Lorg/apache/dubbo/common/URL;Lorg/apache/dubbo/remoting/exchange/ExchangeHandler;)Lorg/apache/dubbo/remoting/exchange/ExchangeClient;
      24: areturn

  public static org.apache.dubbo.remoting.exchange.ExchangeClient connect(java.lang.String, org.apache.dubbo.remoting.exchange.ExchangeHandler) throws org.apache.dubbo.remoting.RemotingException;
    Code:
       0: aload_0
       1: invokestatic  #2                  // Method org/apache/dubbo/common/URL.valueOf:(Ljava/lang/String;)Lorg/apache/dubbo/common/URL;
       4: aload_1
       5: invokestatic  #24                 // Method connect:(Lorg/apache/dubbo/common/URL;Lorg/apache/dubbo/remoting/exchange/ExchangeHandler;)Lorg/apache/dubbo/remoting/exchange/ExchangeClient;
       8: areturn

  public static org.apache.dubbo.remoting.exchange.ExchangeClient connect(org.apache.dubbo.common.URL, org.apache.dubbo.remoting.exchange.ExchangeHandler) throws org.apache.dubbo.remoting.RemotingException;
    Code:
       0: aload_0
       1: ifnonnull     14
       4: new           #12                 // class java/lang/IllegalArgumentException
       7: dup
       8: ldc           #13                 // String url == null
      10: invokespecial #14                 // Method java/lang/IllegalArgumentException."<init>":(Ljava/lang/String;)V
      13: athrow
      14: aload_1
      15: ifnonnull     28
      18: new           #12                 // class java/lang/IllegalArgumentException
      21: dup
      22: ldc           #15                 // String handler == null
      24: invokespecial #14                 // Method java/lang/IllegalArgumentException."<init>":(Ljava/lang/String;)V
      27: athrow
      28: aload_0
      29: invokestatic  #20                 // Method getExchanger:(Lorg/apache/dubbo/common/URL;)Lorg/apache/dubbo/remoting/exchange/Exchanger;
      32: aload_0
      33: aload_1
      34: invokeinterface #25,  3           // InterfaceMethod org/apache/dubbo/remoting/exchange/Exchanger.connect:(Lorg/apache/dubbo/common/URL;Lorg/apache/dubbo/remoting/exchange/ExchangeHandler;)Lorg/apache/dubbo/remoting/exchange/ExchangeClient;
      39: areturn

  public static org.apache.dubbo.remoting.exchange.Exchanger getExchanger(org.apache.dubbo.common.URL);
    Code:
       0: aload_0
       1: ldc           #26                 // String exchanger
       3: ldc           #27                 // String header
       5: invokevirtual #28                 // Method org/apache/dubbo/common/URL.getParameter:(Ljava/lang/String;Ljava/lang/String;)Ljava/lang/String;
       8: astore_1
       9: aload_0
      10: invokevirtual #8                  // Method org/apache/dubbo/common/URL.getOrDefaultFrameworkModel:()Lorg/apache/dubbo/rpc/model/FrameworkModel;
      13: ldc           #29                 // class org/apache/dubbo/remoting/exchange/Exchanger
      15: invokevirtual #30                 // Method org/apache/dubbo/rpc/model/FrameworkModel.getExtensionLoader:(Ljava/lang/Class;)Lorg/apache/dubbo/common/extension/ExtensionLoader;
      18: aload_1
      19: invokevirtual #31                 // Method org/apache/dubbo/common/extension/ExtensionLoader.getExtension:(Ljava/lang/String;)Ljava/lang/Object;
      22: checkcast     #29                 // class org/apache/dubbo/remoting/exchange/Exchanger
      25: areturn
}
