Compiled from "HeartBeatRequest.java"
public class org.apache.dubbo.remoting.exchange.HeartBeatRequest extends org.apache.dubbo.remoting.exchange.Request {
  private byte proto;

  public org.apache.dubbo.remoting.exchange.HeartBeatRequest(long);
    Code:
       0: aload_0
       1: lload_1
       2: invokespecial #1                  // Method org/apache/dubbo/remoting/exchange/Request."<init>":(J)V
       5: return

  public byte getProto();
    Code:
       0: aload_0
       1: getfield      #2                  // Field proto:B
       4: ireturn

  public void setProto(byte);
    Code:
       0: aload_0
       1: iload_1
       2: putfield      #2                  // Field proto:B
       5: return
}
