Compiled from "HeartBeatResponse.java"
public class org.apache.dubbo.remoting.exchange.HeartBeatResponse extends org.apache.dubbo.remoting.exchange.Response {
  private byte proto;

  public org.apache.dubbo.remoting.exchange.HeartBeatResponse(long, java.lang.String);
    Code:
       0: aload_0
       1: lload_1
       2: aload_3
       3: invokespecial #1                  // Method org/apache/dubbo/remoting/exchange/Response."<init>":(JLjava/lang/String;)V
       6: return

  public byte getProto();
    Code:
       0: aload_0
       1: getfield      #2                  // Field proto:B
       4: ireturn

  public void setProto(byte);
    Code:
       0: aload_0
       1: iload_1
       2: putfield      #2                  // Field proto:B
       5: return
}
