Compiled from "PortUnificationExchanger.java"
public class org.apache.dubbo.remoting.exchange.PortUnificationExchanger {
  private static final org.apache.dubbo.common.logger.ErrorTypeAwareLogger log;

  private static final java.util.concurrent.ConcurrentMap<java.lang.String, org.apache.dubbo.remoting.RemotingServer> servers;

  public org.apache.dubbo.remoting.exchange.PortUnificationExchanger();
    Code:
       0: aload_0
       1: invokespecial #2                  // Method java/lang/Object."<init>":()V
       4: return

  public static org.apache.dubbo.remoting.RemotingServer bind(org.apache.dubbo.common.URL, org.apache.dubbo.remoting.ChannelHandler);
    Code:
       0: getstatic     #3                  // Field servers:Ljava/util/concurrent/ConcurrentMap;
       3: aload_0
       4: invokevirtual #4                  // Method org/apache/dubbo/common/URL.getAddress:()Ljava/lang/String;
       7: aload_0
       8: aload_1
       9: invokedynamic #5,  0              // InvokeDynamic #0:apply:(Lorg/apache/dubbo/common/URL;Lorg/apache/dubbo/remoting/ChannelHandler;)Ljava/util/function/Function;
      14: invokestatic  #6                  // Method org/apache/dubbo/common/utils/ConcurrentHashMapUtils.computeIfAbsent:(Ljava/util/concurrent/ConcurrentMap;Ljava/lang/Object;Ljava/util/function/Function;)Ljava/lang/Object;
      17: pop
      18: getstatic     #3                  // Field servers:Ljava/util/concurrent/ConcurrentMap;
      21: aload_0
      22: invokevirtual #4                  // Method org/apache/dubbo/common/URL.getAddress:()Ljava/lang/String;
      25: aload_0
      26: aload_1
      27: invokedynamic #7,  0              // InvokeDynamic #1:apply:(Lorg/apache/dubbo/common/URL;Lorg/apache/dubbo/remoting/ChannelHandler;)Ljava/util/function/BiFunction;
      32: invokeinterface #8,  3            // InterfaceMethod java/util/concurrent/ConcurrentMap.computeIfPresent:(Ljava/lang/Object;Ljava/util/function/BiFunction;)Ljava/lang/Object;
      37: pop
      38: getstatic     #3                  // Field servers:Ljava/util/concurrent/ConcurrentMap;
      41: aload_0
      42: invokevirtual #4                  // Method org/apache/dubbo/common/URL.getAddress:()Ljava/lang/String;
      45: invokeinterface #9,  2            // InterfaceMethod java/util/concurrent/ConcurrentMap.get:(Ljava/lang/Object;)Ljava/lang/Object;
      50: checkcast     #10                 // class org/apache/dubbo/remoting/RemotingServer
      53: areturn

  public static org.apache.dubbo.remoting.api.connection.AbstractConnectionClient connect(org.apache.dubbo.common.URL, org.apache.dubbo.remoting.ChannelHandler);
    Code:
       0: aload_0
       1: invokestatic  #11                 // Method getTransporter:(Lorg/apache/dubbo/common/URL;)Lorg/apache/dubbo/remoting/api/pu/PortUnificationTransporter;
       4: aload_0
       5: aload_1
       6: invokeinterface #12,  3           // InterfaceMethod org/apache/dubbo/remoting/api/pu/PortUnificationTransporter.connect:(Lorg/apache/dubbo/common/URL;Lorg/apache/dubbo/remoting/ChannelHandler;)Lorg/apache/dubbo/remoting/api/connection/AbstractConnectionClient;
      11: astore_2
      12: goto          25
      15: astore_3
      16: new           #14                 // class java/lang/RuntimeException
      19: dup
      20: aload_3
      21: invokespecial #15                 // Method java/lang/RuntimeException."<init>":(Ljava/lang/Throwable;)V
      24: athrow
      25: aload_2
      26: areturn
    Exception table:
       from    to  target type
           0    12    15   Class org/apache/dubbo/remoting/RemotingException

  public static void close();
    Code:
       0: new           #16                 // class java/util/ArrayList
       3: dup
       4: getstatic     #3                  // Field servers:Ljava/util/concurrent/ConcurrentMap;
       7: invokeinterface #17,  1           // InterfaceMethod java/util/concurrent/ConcurrentMap.values:()Ljava/util/Collection;
      12: invokespecial #18                 // Method java/util/ArrayList."<init>":(Ljava/util/Collection;)V
      15: astore_0
      16: getstatic     #3                  // Field servers:Ljava/util/concurrent/ConcurrentMap;
      19: invokeinterface #19,  1           // InterfaceMethod java/util/concurrent/ConcurrentMap.clear:()V
      24: aload_0
      25: invokevirtual #20                 // Method java/util/ArrayList.iterator:()Ljava/util/Iterator;
      28: astore_1
      29: aload_1
      30: invokeinterface #21,  1           // InterfaceMethod java/util/Iterator.hasNext:()Z
      35: ifeq          78
      38: aload_1
      39: invokeinterface #22,  1           // InterfaceMethod java/util/Iterator.next:()Ljava/lang/Object;
      44: checkcast     #10                 // class org/apache/dubbo/remoting/RemotingServer
      47: astore_2
      48: aload_2
      49: invokeinterface #23,  1           // InterfaceMethod org/apache/dubbo/remoting/RemotingServer.close:()V
      54: goto          75
      57: astore_3
      58: getstatic     #25                 // Field log:Lorg/apache/dubbo/common/logger/ErrorTypeAwareLogger;
      61: ldc           #26                 // String 4-8
      63: ldc           #27                 // String
      65: ldc           #27                 // String
      67: ldc           #28                 // String Close all port unification server failed
      69: aload_3
      70: invokeinterface #29,  6           // InterfaceMethod org/apache/dubbo/common/logger/ErrorTypeAwareLogger.error:(Ljava/lang/String;Ljava/lang/String;Ljava/lang/String;Ljava/lang/String;Ljava/lang/Throwable;)V
      75: goto          29
      78: return
    Exception table:
       from    to  target type
          48    54    57   Class java/lang/Throwable

  public static java.util.concurrent.ConcurrentMap<java.lang.String, org.apache.dubbo.remoting.RemotingServer> getServers();
    Code:
       0: getstatic     #3                  // Field servers:Ljava/util/concurrent/ConcurrentMap;
       3: areturn

  public static org.apache.dubbo.remoting.api.pu.PortUnificationTransporter getTransporter(org.apache.dubbo.common.URL);
    Code:
       0: aload_0
       1: invokevirtual #30                 // Method org/apache/dubbo/common/URL.getOrDefaultFrameworkModel:()Lorg/apache/dubbo/rpc/model/FrameworkModel;
       4: ldc           #31                 // class org/apache/dubbo/remoting/api/pu/PortUnificationTransporter
       6: invokevirtual #32                 // Method org/apache/dubbo/rpc/model/FrameworkModel.getExtensionLoader:(Ljava/lang/Class;)Lorg/apache/dubbo/common/extension/ExtensionLoader;
       9: invokevirtual #33                 // Method org/apache/dubbo/common/extension/ExtensionLoader.getAdaptiveExtension:()Ljava/lang/Object;
      12: checkcast     #31                 // class org/apache/dubbo/remoting/api/pu/PortUnificationTransporter
      15: areturn

  private static org.apache.dubbo.remoting.RemotingServer lambda$bind$1(org.apache.dubbo.common.URL, org.apache.dubbo.remoting.ChannelHandler, java.lang.String, org.apache.dubbo.remoting.RemotingServer);
    Code:
       0: aload_3
       1: checkcast     #34                 // class org/apache/dubbo/remoting/api/pu/AbstractPortUnificationServer
       4: aload_0
       5: aload_1
       6: invokevirtual #35                 // Method org/apache/dubbo/remoting/api/pu/AbstractPortUnificationServer.addSupportedProtocol:(Lorg/apache/dubbo/common/URL;Lorg/apache/dubbo/remoting/ChannelHandler;)V
       9: aload_3
      10: areturn

  private static org.apache.dubbo.remoting.RemotingServer lambda$bind$0(org.apache.dubbo.common.URL, org.apache.dubbo.remoting.ChannelHandler, java.lang.String);
    Code:
       0: aload_0
       1: invokestatic  #11                 // Method getTransporter:(Lorg/apache/dubbo/common/URL;)Lorg/apache/dubbo/remoting/api/pu/PortUnificationTransporter;
       4: aload_0
       5: aload_1
       6: invokeinterface #36,  3           // InterfaceMethod org/apache/dubbo/remoting/api/pu/PortUnificationTransporter.bind:(Lorg/apache/dubbo/common/URL;Lorg/apache/dubbo/remoting/ChannelHandler;)Lorg/apache/dubbo/remoting/api/pu/AbstractPortUnificationServer;
      11: astore_3
      12: goto          27
      15: astore        4
      17: new           #14                 // class java/lang/RuntimeException
      20: dup
      21: aload         4
      23: invokespecial #15                 // Method java/lang/RuntimeException."<init>":(Ljava/lang/Throwable;)V
      26: athrow
      27: aload_3
      28: areturn
    Exception table:
       from    to  target type
           0    12    15   Class org/apache/dubbo/remoting/RemotingException

  static {};
    Code:
       0: ldc           #37                 // class org/apache/dubbo/remoting/exchange/PortUnificationExchanger
       2: invokestatic  #38                 // Method org/apache/dubbo/common/logger/LoggerFactory.getErrorTypeAwareLogger:(Ljava/lang/Class;)Lorg/apache/dubbo/common/logger/ErrorTypeAwareLogger;
       5: putstatic     #25                 // Field log:Lorg/apache/dubbo/common/logger/ErrorTypeAwareLogger;
       8: new           #39                 // class java/util/concurrent/ConcurrentHashMap
      11: dup
      12: invokespecial #40                 // Method java/util/concurrent/ConcurrentHashMap."<init>":()V
      15: putstatic     #3                  // Field servers:Ljava/util/concurrent/ConcurrentMap;
      18: return
}
