Compiled from "Response.java"
public class org.apache.dubbo.remoting.exchange.Response {
  public static final byte OK;

  public static final byte CLIENT_TIMEOUT;

  public static final byte SERVER_TIMEOUT;

  public static final byte CHANNEL_INACTIVE;

  public static final byte BAD_REQUEST;

  public static final byte BAD_RESPONSE;

  public static final byte SERVICE_NOT_FOUND;

  public static final byte SERVICE_ERROR;

  public static final byte SERVER_ERROR;

  public static final byte CLIENT_ERROR;

  public static final byte SERVER_THREADPOOL_EXHAUSTED_ERROR;

  private long mId;

  private java.lang.String mVersion;

  private byte mStatus;

  private boolean mEvent;

  private java.lang.String mErrorMsg;

  private java.lang.Object mResult;

  public org.apache.dubbo.remoting.exchange.Response();
    Code:
       0: aload_0
       1: invokespecial #1                  // Method java/lang/Object."<init>":()V
       4: aload_0
       5: lconst_0
       6: putfield      #2                  // Field mId:J
       9: aload_0
      10: bipush        20
      12: putfield      #4                  // Field mStatus:B
      15: aload_0
      16: iconst_0
      17: putfield      #5                  // Field mEvent:Z
      20: return

  public org.apache.dubbo.remoting.exchange.Response(long);
    Code:
       0: aload_0
       1: invokespecial #1                  // Method java/lang/Object."<init>":()V
       4: aload_0
       5: lconst_0
       6: putfield      #2                  // Field mId:J
       9: aload_0
      10: bipush        20
      12: putfield      #4                  // Field mStatus:B
      15: aload_0
      16: iconst_0
      17: putfield      #5                  // Field mEvent:Z
      20: aload_0
      21: lload_1
      22: putfield      #2                  // Field mId:J
      25: return

  public org.apache.dubbo.remoting.exchange.Response(long, java.lang.String);
    Code:
       0: aload_0
       1: invokespecial #1                  // Method java/lang/Object."<init>":()V
       4: aload_0
       5: lconst_0
       6: putfield      #2                  // Field mId:J
       9: aload_0
      10: bipush        20
      12: putfield      #4                  // Field mStatus:B
      15: aload_0
      16: iconst_0
      17: putfield      #5                  // Field mEvent:Z
      20: aload_0
      21: lload_1
      22: putfield      #2                  // Field mId:J
      25: aload_0
      26: aload_3
      27: putfield      #6                  // Field mVersion:Ljava/lang/String;
      30: return

  public long getId();
    Code:
       0: aload_0
       1: getfield      #2                  // Field mId:J
       4: lreturn

  public void setId(long);
    Code:
       0: aload_0
       1: lload_1
       2: putfield      #2                  // Field mId:J
       5: return

  public java.lang.String getVersion();
    Code:
       0: aload_0
       1: getfield      #6                  // Field mVersion:Ljava/lang/String;
       4: areturn

  public void setVersion(java.lang.String);
    Code:
       0: aload_0
       1: aload_1
       2: putfield      #6                  // Field mVersion:Ljava/lang/String;
       5: return

  public byte getStatus();
    Code:
       0: aload_0
       1: getfield      #4                  // Field mStatus:B
       4: ireturn

  public void setStatus(byte);
    Code:
       0: aload_0
       1: iload_1
       2: putfield      #4                  // Field mStatus:B
       5: return

  public boolean isEvent();
    Code:
       0: aload_0
       1: getfield      #5                  // Field mEvent:Z
       4: ireturn

  public void setEvent(java.lang.String);
    Code:
       0: aload_0
       1: iconst_1
       2: putfield      #5                  // Field mEvent:Z
       5: aload_0
       6: aload_1
       7: putfield      #7                  // Field mResult:Ljava/lang/Object;
      10: return

  public void setEvent(boolean);
    Code:
       0: aload_0
       1: iload_1
       2: putfield      #5                  // Field mEvent:Z
       5: return

  public boolean isHeartbeat();
    Code:
       0: aload_0
       1: getfield      #5                  // Field mEvent:Z
       4: ifeq          21
       7: getstatic     #8                  // Field org/apache/dubbo/common/constants/CommonConstants.HEARTBEAT_EVENT:Ljava/lang/String;
      10: aload_0
      11: getfield      #7                  // Field mResult:Ljava/lang/Object;
      14: if_acmpne     21
      17: iconst_1
      18: goto          22
      21: iconst_0
      22: ireturn

  public void setHeartbeat(boolean);
    Code:
       0: iload_1
       1: ifeq          11
       4: aload_0
       5: getstatic     #8                  // Field org/apache/dubbo/common/constants/CommonConstants.HEARTBEAT_EVENT:Ljava/lang/String;
       8: invokevirtual #9                  // Method setEvent:(Ljava/lang/String;)V
      11: return

  public java.lang.Object getResult();
    Code:
       0: aload_0
       1: getfield      #7                  // Field mResult:Ljava/lang/Object;
       4: areturn

  public void setResult(java.lang.Object);
    Code:
       0: aload_0
       1: aload_1
       2: putfield      #7                  // Field mResult:Ljava/lang/Object;
       5: return

  public java.lang.String getErrorMessage();
    Code:
       0: aload_0
       1: getfield      #10                 // Field mErrorMsg:Ljava/lang/String;
       4: areturn

  public void setErrorMessage(java.lang.String);
    Code:
       0: aload_0
       1: aload_1
       2: putfield      #10                 // Field mErrorMsg:Ljava/lang/String;
       5: return

  public java.lang.String toString();
    Code:
       0: new           #11                 // class java/lang/StringBuilder
       3: dup
       4: invokespecial #12                 // Method java/lang/StringBuilder."<init>":()V
       7: ldc           #13                 // String Response [id=
       9: invokevirtual #14                 // Method java/lang/StringBuilder.append:(Ljava/lang/String;)Ljava/lang/StringBuilder;
      12: aload_0
      13: getfield      #2                  // Field mId:J
      16: invokevirtual #15                 // Method java/lang/StringBuilder.append:(J)Ljava/lang/StringBuilder;
      19: ldc           #16                 // String , version=
      21: invokevirtual #14                 // Method java/lang/StringBuilder.append:(Ljava/lang/String;)Ljava/lang/StringBuilder;
      24: aload_0
      25: getfield      #6                  // Field mVersion:Ljava/lang/String;
      28: invokevirtual #14                 // Method java/lang/StringBuilder.append:(Ljava/lang/String;)Ljava/lang/StringBuilder;
      31: ldc           #17                 // String , status=
      33: invokevirtual #14                 // Method java/lang/StringBuilder.append:(Ljava/lang/String;)Ljava/lang/StringBuilder;
      36: aload_0
      37: getfield      #4                  // Field mStatus:B
      40: invokevirtual #18                 // Method java/lang/StringBuilder.append:(I)Ljava/lang/StringBuilder;
      43: ldc           #19                 // String , event=
      45: invokevirtual #14                 // Method java/lang/StringBuilder.append:(Ljava/lang/String;)Ljava/lang/StringBuilder;
      48: aload_0
      49: getfield      #5                  // Field mEvent:Z
      52: invokevirtual #20                 // Method java/lang/StringBuilder.append:(Z)Ljava/lang/StringBuilder;
      55: ldc           #21                 // String , error=
      57: invokevirtual #14                 // Method java/lang/StringBuilder.append:(Ljava/lang/String;)Ljava/lang/StringBuilder;
      60: aload_0
      61: getfield      #10                 // Field mErrorMsg:Ljava/lang/String;
      64: invokevirtual #14                 // Method java/lang/StringBuilder.append:(Ljava/lang/String;)Ljava/lang/StringBuilder;
      67: ldc           #22                 // String , result=
      69: invokevirtual #14                 // Method java/lang/StringBuilder.append:(Ljava/lang/String;)Ljava/lang/StringBuilder;
      72: aload_0
      73: getfield      #7                  // Field mResult:Ljava/lang/Object;
      76: aload_0
      77: if_acmpne     85
      80: ldc           #23                 // String this
      82: goto          89
      85: aload_0
      86: getfield      #7                  // Field mResult:Ljava/lang/Object;
      89: invokevirtual #24                 // Method java/lang/StringBuilder.append:(Ljava/lang/Object;)Ljava/lang/StringBuilder;
      92: ldc           #25                 // String ]
      94: invokevirtual #14                 // Method java/lang/StringBuilder.append:(Ljava/lang/String;)Ljava/lang/StringBuilder;
      97: invokevirtual #26                 // Method java/lang/StringBuilder.toString:()Ljava/lang/String;
     100: areturn
}
