Compiled from "SpringJtaPlatform.java"
public class org.springframework.boot.orm.jpa.hibernate.SpringJtaPlatform extends org.hibernate.engine.transaction.jta.platform.internal.AbstractJtaPlatform {
  private static final long serialVersionUID;

  private final org.springframework.transaction.jta.JtaTransactionManager transactionManager;

  public org.springframework.boot.orm.jpa.hibernate.SpringJtaPlatform(org.springframework.transaction.jta.JtaTransactionManager);
    Code:
       0: aload_0
       1: invokespecial #1                  // Method org/hibernate/engine/transaction/jta/platform/internal/AbstractJtaPlatform."<init>":()V
       4: aload_1
       5: ldc           #7                  // String TransactionManager must not be null
       7: invokestatic  #9                  // Method org/springframework/util/Assert.notNull:(Ljava/lang/Object;Ljava/lang/String;)V
      10: aload_0
      11: aload_1
      12: putfield      #15                 // Field transactionManager:Lorg/springframework/transaction/jta/JtaTransactionManager;
      15: return

  protected jakarta.transaction.TransactionManager locateTransactionManager();
    Code:
       0: aload_0
       1: getfield      #15                 // Field transactionManager:Lorg/springframework/transaction/jta/JtaTransactionManager;
       4: invokevirtual #21                 // Method org/springframework/transaction/jta/JtaTransactionManager.getTransactionManager:()Ljakarta/transaction/TransactionManager;
       7: areturn

  protected jakarta.transaction.UserTransaction locateUserTransaction();
    Code:
       0: aload_0
       1: getfield      #15                 // Field transactionManager:Lorg/springframework/transaction/jta/JtaTransactionManager;
       4: invokevirtual #27                 // Method org/springframework/transaction/jta/JtaTransactionManager.getUserTransaction:()Ljakarta/transaction/UserTransaction;
       7: areturn
}
