Compiled from "OriginTrackedFieldError.java"
final class org.springframework.boot.context.properties.bind.validation.OriginTrackedFieldError extends org.springframework.validation.FieldError implements org.springframework.boot.origin.OriginProvider {
  private final org.springframework.boot.origin.Origin origin;

  private org.springframework.boot.context.properties.bind.validation.OriginTrackedFieldError(org.springframework.validation.FieldError, org.springframework.boot.origin.Origin);
    Code:
       0: aload_0
       1: aload_1
       2: invokevirtual #1                  // Method org/springframework/validation/FieldError.getObjectName:()Ljava/lang/String;
       5: aload_1
       6: invokevirtual #7                  // Method org/springframework/validation/FieldError.getField:()Ljava/lang/String;
       9: aload_1
      10: invokevirtual #10                 // Method org/springframework/validation/FieldError.getRejectedValue:()Ljava/lang/Object;
      13: aload_1
      14: invokevirtual #14                 // Method org/springframework/validation/FieldError.isBindingFailure:()Z
      17: aload_1
      18: invokevirtual #18                 // Method org/springframework/validation/FieldError.getCodes:()[Ljava/lang/String;
      21: aload_1
      22: invokevirtual #22                 // Method org/springframework/validation/FieldError.getArguments:()[Ljava/lang/Object;
      25: aload_1
      26: invokevirtual #26                 // Method org/springframework/validation/FieldError.getDefaultMessage:()Ljava/lang/String;
      29: invokespecial #29                 // Method org/springframework/validation/FieldError."<init>":(Ljava/lang/String;Ljava/lang/String;Ljava/lang/Object;Z[Ljava/lang/String;[Ljava/lang/Object;Ljava/lang/String;)V
      32: aload_0
      33: aload_2
      34: putfield      #33                 // Field origin:Lorg/springframework/boot/origin/Origin;
      37: return

  public org.springframework.boot.origin.Origin getOrigin();
    Code:
       0: aload_0
       1: getfield      #33                 // Field origin:Lorg/springframework/boot/origin/Origin;
       4: areturn

  public java.lang.String toString();
    Code:
       0: aload_0
       1: getfield      #33                 // Field origin:Lorg/springframework/boot/origin/Origin;
       4: ifnonnull     12
       7: aload_0
       8: invokespecial #39                 // Method org/springframework/validation/FieldError.toString:()Ljava/lang/String;
      11: areturn
      12: aload_0
      13: invokespecial #39                 // Method org/springframework/validation/FieldError.toString:()Ljava/lang/String;
      16: aload_0
      17: getfield      #33                 // Field origin:Lorg/springframework/boot/origin/Origin;
      20: invokedynamic #42,  0             // InvokeDynamic #0:makeConcatWithConstants:(Ljava/lang/String;Lorg/springframework/boot/origin/Origin;)Ljava/lang/String;
      25: areturn

  static org.springframework.validation.FieldError of(org.springframework.validation.FieldError, org.springframework.boot.origin.Origin);
    Code:
       0: aload_0
       1: ifnull        8
       4: aload_1
       5: ifnonnull     10
       8: aload_0
       9: areturn
      10: new           #34                 // class org/springframework/boot/context/properties/bind/validation/OriginTrackedFieldError
      13: dup
      14: aload_0
      15: aload_1
      16: invokespecial #46                 // Method "<init>":(Lorg/springframework/validation/FieldError;Lorg/springframework/boot/origin/Origin;)V
      19: areturn
}
