Compiled from "ValidationErrors.java"
public class org.springframework.boot.context.properties.bind.validation.ValidationErrors implements java.lang.Iterable<org.springframework.validation.ObjectError> {
  private final org.springframework.boot.context.properties.source.ConfigurationPropertyName name;

  private final java.util.Set<org.springframework.boot.context.properties.source.ConfigurationProperty> boundProperties;

  private final java.util.List<org.springframework.validation.ObjectError> errors;

  org.springframework.boot.context.properties.bind.validation.ValidationErrors(org.springframework.boot.context.properties.source.ConfigurationPropertyName, java.util.Set<org.springframework.boot.context.properties.source.ConfigurationProperty>, java.util.List<org.springframework.validation.ObjectError>);
    Code:
       0: aload_0
       1: invokespecial #1                  // Method java/lang/Object."<init>":()V
       4: aload_1
       5: ldc           #7                  // String Name must not be null
       7: invokestatic  #9                  // Method org/springframework/util/Assert.notNull:(Ljava/lang/Object;Ljava/lang/String;)V
      10: aload_2
      11: ldc           #15                 // String BoundProperties must not be null
      13: invokestatic  #9                  // Method org/springframework/util/Assert.notNull:(Ljava/lang/Object;Ljava/lang/String;)V
      16: aload_3
      17: ldc           #17                 // String Errors must not be null
      19: invokestatic  #9                  // Method org/springframework/util/Assert.notNull:(Ljava/lang/Object;Ljava/lang/String;)V
      22: aload_0
      23: aload_1
      24: putfield      #19                 // Field name:Lorg/springframework/boot/context/properties/source/ConfigurationPropertyName;
      27: aload_0
      28: aload_2
      29: invokestatic  #25                 // Method java/util/Collections.unmodifiableSet:(Ljava/util/Set;)Ljava/util/Set;
      32: putfield      #31                 // Field boundProperties:Ljava/util/Set;
      35: aload_0
      36: aload_0
      37: aload_1
      38: aload_2
      39: aload_3
      40: invokevirtual #35                 // Method convertErrors:(Lorg/springframework/boot/context/properties/source/ConfigurationPropertyName;Ljava/util/Set;Ljava/util/List;)Ljava/util/List;
      43: putfield      #39                 // Field errors:Ljava/util/List;
      46: return

  private java.util.List<org.springframework.validation.ObjectError> convertErrors(org.springframework.boot.context.properties.source.ConfigurationPropertyName, java.util.Set<org.springframework.boot.context.properties.source.ConfigurationProperty>, java.util.List<org.springframework.validation.ObjectError>);
    Code:
       0: new           #43                 // class java/util/ArrayList
       3: dup
       4: aload_3
       5: invokeinterface #45,  1           // InterfaceMethod java/util/List.size:()I
      10: invokespecial #51                 // Method java/util/ArrayList."<init>":(I)V
      13: astore        4
      15: aload_3
      16: invokeinterface #54,  1           // InterfaceMethod java/util/List.iterator:()Ljava/util/Iterator;
      21: astore        5
      23: aload         5
      25: invokeinterface #58,  1           // InterfaceMethod java/util/Iterator.hasNext:()Z
      30: ifeq          64
      33: aload         5
      35: invokeinterface #64,  1           // InterfaceMethod java/util/Iterator.next:()Ljava/lang/Object;
      40: checkcast     #68                 // class org/springframework/validation/ObjectError
      43: astore        6
      45: aload         4
      47: aload_0
      48: aload_1
      49: aload_2
      50: aload         6
      52: invokevirtual #70                 // Method convertError:(Lorg/springframework/boot/context/properties/source/ConfigurationPropertyName;Ljava/util/Set;Lorg/springframework/validation/ObjectError;)Lorg/springframework/validation/ObjectError;
      55: invokeinterface #74,  2           // InterfaceMethod java/util/List.add:(Ljava/lang/Object;)Z
      60: pop
      61: goto          23
      64: aload         4
      66: invokestatic  #78                 // Method java/util/Collections.unmodifiableList:(Ljava/util/List;)Ljava/util/List;
      69: areturn

  private org.springframework.validation.ObjectError convertError(org.springframework.boot.context.properties.source.ConfigurationPropertyName, java.util.Set<org.springframework.boot.context.properties.source.ConfigurationProperty>, org.springframework.validation.ObjectError);
    Code:
       0: aload_3
       1: instanceof    #82                 // class org/springframework/validation/FieldError
       4: ifeq          22
       7: aload_3
       8: checkcast     #82                 // class org/springframework/validation/FieldError
      11: astore        4
      13: aload_0
      14: aload_1
      15: aload_2
      16: aload         4
      18: invokevirtual #84                 // Method convertFieldError:(Lorg/springframework/boot/context/properties/source/ConfigurationPropertyName;Ljava/util/Set;Lorg/springframework/validation/FieldError;)Lorg/springframework/validation/FieldError;
      21: areturn
      22: aload_3
      23: areturn

  private org.springframework.validation.FieldError convertFieldError(org.springframework.boot.context.properties.source.ConfigurationPropertyName, java.util.Set<org.springframework.boot.context.properties.source.ConfigurationProperty>, org.springframework.validation.FieldError);
    Code:
       0: aload_3
       1: instanceof    #88                 // class org/springframework/boot/origin/OriginProvider
       4: ifeq          9
       7: aload_3
       8: areturn
       9: aload_3
      10: aload_0
      11: aload_1
      12: aload_2
      13: aload_3
      14: invokevirtual #90                 // Method findFieldErrorOrigin:(Lorg/springframework/boot/context/properties/source/ConfigurationPropertyName;Ljava/util/Set;Lorg/springframework/validation/FieldError;)Lorg/springframework/boot/origin/Origin;
      17: invokestatic  #94                 // Method org/springframework/boot/context/properties/bind/validation/OriginTrackedFieldError.of:(Lorg/springframework/validation/FieldError;Lorg/springframework/boot/origin/Origin;)Lorg/springframework/validation/FieldError;
      20: areturn

  private org.springframework.boot.origin.Origin findFieldErrorOrigin(org.springframework.boot.context.properties.source.ConfigurationPropertyName, java.util.Set<org.springframework.boot.context.properties.source.ConfigurationProperty>, org.springframework.validation.FieldError);
    Code:
       0: aload_2
       1: invokeinterface #100,  1          // InterfaceMethod java/util/Set.iterator:()Ljava/util/Iterator;
       6: astore        4
       8: aload         4
      10: invokeinterface #58,  1           // InterfaceMethod java/util/Iterator.hasNext:()Z
      15: ifeq          53
      18: aload         4
      20: invokeinterface #64,  1           // InterfaceMethod java/util/Iterator.next:()Ljava/lang/Object;
      25: checkcast     #103                // class org/springframework/boot/context/properties/source/ConfigurationProperty
      28: astore        5
      30: aload_0
      31: aload_1
      32: aload         5
      34: invokevirtual #105                // Method org/springframework/boot/context/properties/source/ConfigurationProperty.getName:()Lorg/springframework/boot/context/properties/source/ConfigurationPropertyName;
      37: aload_3
      38: invokevirtual #109                // Method isForError:(Lorg/springframework/boot/context/properties/source/ConfigurationPropertyName;Lorg/springframework/boot/context/properties/source/ConfigurationPropertyName;Lorg/springframework/validation/FieldError;)Z
      41: ifeq          50
      44: aload         5
      46: invokestatic  #113                // InterfaceMethod org/springframework/boot/origin/Origin.from:(Ljava/lang/Object;)Lorg/springframework/boot/origin/Origin;
      49: areturn
      50: goto          8
      53: aconst_null
      54: areturn

  private boolean isForError(org.springframework.boot.context.properties.source.ConfigurationPropertyName, org.springframework.boot.context.properties.source.ConfigurationPropertyName, org.springframework.validation.FieldError);
    Code:
       0: aload_1
       1: aload_2
       2: invokevirtual #119                // Method org/springframework/boot/context/properties/source/ConfigurationPropertyName.isParentOf:(Lorg/springframework/boot/context/properties/source/ConfigurationPropertyName;)Z
       5: ifeq          29
       8: aload_2
       9: getstatic     #125                // Field org/springframework/boot/context/properties/source/ConfigurationPropertyName$Form.UNIFORM:Lorg/springframework/boot/context/properties/source/ConfigurationPropertyName$Form;
      12: invokevirtual #131                // Method org/springframework/boot/context/properties/source/ConfigurationPropertyName.getLastElement:(Lorg/springframework/boot/context/properties/source/ConfigurationPropertyName$Form;)Ljava/lang/String;
      15: aload_3
      16: invokevirtual #135                // Method org/springframework/validation/FieldError.getField:()Ljava/lang/String;
      19: invokevirtual #139                // Method java/lang/String.equalsIgnoreCase:(Ljava/lang/String;)Z
      22: ifeq          29
      25: iconst_1
      26: goto          30
      29: iconst_0
      30: ireturn

  public org.springframework.boot.context.properties.source.ConfigurationPropertyName getName();
    Code:
       0: aload_0
       1: getfield      #19                 // Field name:Lorg/springframework/boot/context/properties/source/ConfigurationPropertyName;
       4: areturn

  public java.util.Set<org.springframework.boot.context.properties.source.ConfigurationProperty> getBoundProperties();
    Code:
       0: aload_0
       1: getfield      #31                 // Field boundProperties:Ljava/util/Set;
       4: areturn

  public boolean hasErrors();
    Code:
       0: aload_0
       1: getfield      #39                 // Field errors:Ljava/util/List;
       4: invokeinterface #145,  1          // InterfaceMethod java/util/List.isEmpty:()Z
       9: ifne          16
      12: iconst_1
      13: goto          17
      16: iconst_0
      17: ireturn

  public java.util.List<org.springframework.validation.ObjectError> getAllErrors();
    Code:
       0: aload_0
       1: getfield      #39                 // Field errors:Ljava/util/List;
       4: areturn

  public java.util.Iterator<org.springframework.validation.ObjectError> iterator();
    Code:
       0: aload_0
       1: getfield      #39                 // Field errors:Ljava/util/List;
       4: invokeinterface #54,  1           // InterfaceMethod java/util/List.iterator:()Ljava/util/Iterator;
       9: areturn
}
