Compiled from "ValidationBindHandler.java"
class org.springframework.boot.context.properties.bind.validation.ValidationBindHandler$ValidationResult extends org.springframework.validation.BeanPropertyBindingResult {
  private final org.springframework.boot.context.properties.source.ConfigurationPropertyName name;

  final org.springframework.boot.context.properties.bind.validation.ValidationBindHandler this$0;

  protected org.springframework.boot.context.properties.bind.validation.ValidationBindHandler$ValidationResult(org.springframework.boot.context.properties.bind.validation.ValidationBindHandler, org.springframework.boot.context.properties.source.ConfigurationPropertyName, java.lang.Object);
    Code:
       0: aload_0
       1: aload_1
       2: putfield      #1                  // Field this$0:Lorg/springframework/boot/context/properties/bind/validation/ValidationBindHandler;
       5: aload_0
       6: aload_3
       7: aconst_null
       8: invokespecial #7                  // Method org/springframework/validation/BeanPropertyBindingResult."<init>":(Ljava/lang/Object;Ljava/lang/String;)V
      11: aload_0
      12: aload_2
      13: putfield      #13                 // Field name:Lorg/springframework/boot/context/properties/source/ConfigurationPropertyName;
      16: return

  public java.lang.String getObjectName();
    Code:
       0: aload_0
       1: getfield      #13                 // Field name:Lorg/springframework/boot/context/properties/source/ConfigurationPropertyName;
       4: invokevirtual #17                 // Method org/springframework/boot/context/properties/source/ConfigurationPropertyName.toString:()Ljava/lang/String;
       7: areturn

  public java.lang.Class<?> getFieldType(java.lang.String);
    Code:
       0: aload_0
       1: aload_0
       2: getfield      #1                  // Field this$0:Lorg/springframework/boot/context/properties/bind/validation/ValidationBindHandler;
       5: getfield      #23                 // Field org/springframework/boot/context/properties/bind/validation/ValidationBindHandler.boundTypes:Ljava/util/Map;
       8: aload_1
       9: invokevirtual #29                 // Method getBoundField:(Ljava/util/Map;Ljava/lang/String;)Ljava/lang/Object;
      12: checkcast     #33                 // class org/springframework/core/ResolvableType
      15: astore_2
      16: aload_2
      17: ifnull        27
      20: aload_2
      21: invokevirtual #35                 // Method org/springframework/core/ResolvableType.resolve:()Ljava/lang/Class;
      24: goto          28
      27: aconst_null
      28: astore_3
      29: aload_3
      30: ifnull        35
      33: aload_3
      34: areturn
      35: aload_0
      36: aload_1
      37: invokespecial #39                 // Method org/springframework/validation/BeanPropertyBindingResult.getFieldType:(Ljava/lang/String;)Ljava/lang/Class;
      40: areturn

  protected java.lang.Object getActualFieldValue(java.lang.String);
    Code:
       0: aload_0
       1: aload_0
       2: getfield      #1                  // Field this$0:Lorg/springframework/boot/context/properties/bind/validation/ValidationBindHandler;
       5: getfield      #43                 // Field org/springframework/boot/context/properties/bind/validation/ValidationBindHandler.boundResults:Ljava/util/Map;
       8: aload_1
       9: invokevirtual #29                 // Method getBoundField:(Ljava/util/Map;Ljava/lang/String;)Ljava/lang/Object;
      12: astore_2
      13: aload_2
      14: ifnull        19
      17: aload_2
      18: areturn
      19: aload_0
      20: aload_1
      21: invokespecial #46                 // Method org/springframework/validation/BeanPropertyBindingResult.getActualFieldValue:(Ljava/lang/String;)Ljava/lang/Object;
      24: areturn
      25: astore_3
      26: aload_0
      27: aload_3
      28: invokevirtual #52                 // Method isPropertyNotReadable:(Ljava/lang/Throwable;)Z
      31: ifeq          36
      34: aconst_null
      35: areturn
      36: aload_3
      37: athrow
    Exception table:
       from    to  target type
          19    24    25   Class java/lang/Exception

  private boolean isPropertyNotReadable(java.lang.Throwable);
    Code:
       0: aload_1
       1: ifnull        21
       4: aload_1
       5: instanceof    #56                 // class org/springframework/beans/NotReadablePropertyException
       8: ifeq          13
      11: iconst_1
      12: ireturn
      13: aload_1
      14: invokevirtual #58                 // Method java/lang/Throwable.getCause:()Ljava/lang/Throwable;
      17: astore_1
      18: goto          0
      21: iconst_0
      22: ireturn

  private <T> T getBoundField(java.util.Map<org.springframework.boot.context.properties.source.ConfigurationPropertyName, T>, java.lang.String);
    Code:
       0: aload_0
       1: aload_2
       2: invokevirtual #64                 // Method getName:(Ljava/lang/String;)Lorg/springframework/boot/context/properties/source/ConfigurationPropertyName;
       5: astore_3
       6: aload_1
       7: aload_3
       8: invokeinterface #68,  2           // InterfaceMethod java/util/Map.get:(Ljava/lang/Object;)Ljava/lang/Object;
      13: astore        4
      15: aload         4
      17: ifnull        23
      20: aload         4
      22: areturn
      23: aload_3
      24: invokevirtual #74                 // Method org/springframework/boot/context/properties/source/ConfigurationPropertyName.hasIndexedElement:()Z
      27: ifeq          94
      30: aload_1
      31: invokeinterface #78,  1           // InterfaceMethod java/util/Map.entrySet:()Ljava/util/Set;
      36: invokeinterface #82,  1           // InterfaceMethod java/util/Set.iterator:()Ljava/util/Iterator;
      41: astore        5
      43: aload         5
      45: invokeinterface #88,  1           // InterfaceMethod java/util/Iterator.hasNext:()Z
      50: ifeq          94
      53: aload         5
      55: invokeinterface #93,  1           // InterfaceMethod java/util/Iterator.next:()Ljava/lang/Object;
      60: checkcast     #97                 // class java/util/Map$Entry
      63: astore        6
      65: aload_0
      66: aload         6
      68: invokeinterface #99,  1           // InterfaceMethod java/util/Map$Entry.getKey:()Ljava/lang/Object;
      73: checkcast     #18                 // class org/springframework/boot/context/properties/source/ConfigurationPropertyName
      76: aload_3
      77: invokevirtual #102                // Method isFieldNameMatch:(Lorg/springframework/boot/context/properties/source/ConfigurationPropertyName;Lorg/springframework/boot/context/properties/source/ConfigurationPropertyName;)Z
      80: ifeq          91
      83: aload         6
      85: invokeinterface #106,  1          // InterfaceMethod java/util/Map$Entry.getValue:()Ljava/lang/Object;
      90: areturn
      91: goto          43
      94: goto          98
      97: astore_3
      98: aconst_null
      99: areturn
    Exception table:
       from    to  target type
           0    22    97   Class java/lang/Exception
          23    90    97   Class java/lang/Exception
          91    94    97   Class java/lang/Exception

  private boolean isFieldNameMatch(org.springframework.boot.context.properties.source.ConfigurationPropertyName, org.springframework.boot.context.properties.source.ConfigurationPropertyName);
    Code:
       0: aload_1
       1: invokevirtual #109                // Method org/springframework/boot/context/properties/source/ConfigurationPropertyName.getNumberOfElements:()I
       4: aload_2
       5: invokevirtual #109                // Method org/springframework/boot/context/properties/source/ConfigurationPropertyName.getNumberOfElements:()I
       8: if_icmpeq     13
      11: iconst_0
      12: ireturn
      13: iconst_0
      14: istore_3
      15: iload_3
      16: aload_1
      17: invokevirtual #109                // Method org/springframework/boot/context/properties/source/ConfigurationPropertyName.getNumberOfElements:()I
      20: if_icmpge     61
      23: aload_1
      24: iload_3
      25: getstatic     #113                // Field org/springframework/boot/context/properties/source/ConfigurationPropertyName$Form.ORIGINAL:Lorg/springframework/boot/context/properties/source/ConfigurationPropertyName$Form;
      28: invokevirtual #119                // Method org/springframework/boot/context/properties/source/ConfigurationPropertyName.getElement:(ILorg/springframework/boot/context/properties/source/ConfigurationPropertyName$Form;)Ljava/lang/String;
      31: astore        4
      33: aload_2
      34: iload_3
      35: getstatic     #113                // Field org/springframework/boot/context/properties/source/ConfigurationPropertyName$Form.ORIGINAL:Lorg/springframework/boot/context/properties/source/ConfigurationPropertyName$Form;
      38: invokevirtual #119                // Method org/springframework/boot/context/properties/source/ConfigurationPropertyName.getElement:(ILorg/springframework/boot/context/properties/source/ConfigurationPropertyName$Form;)Ljava/lang/String;
      41: astore        5
      43: aload         4
      45: aload         5
      47: invokestatic  #123                // Method org/springframework/util/ObjectUtils.nullSafeEquals:(Ljava/lang/Object;Ljava/lang/Object;)Z
      50: ifne          55
      53: iconst_0
      54: ireturn
      55: iinc          3, 1
      58: goto          15
      61: iconst_1
      62: ireturn

  private org.springframework.boot.context.properties.source.ConfigurationPropertyName getName(java.lang.String);
    Code:
       0: aload_0
       1: getfield      #13                 // Field name:Lorg/springframework/boot/context/properties/source/ConfigurationPropertyName;
       4: aload_1
       5: invokestatic  #129                // Method org/springframework/boot/context/properties/bind/DataObjectPropertyName.toDashedForm:(Ljava/lang/String;)Ljava/lang/String;
       8: invokevirtual #135                // Method org/springframework/boot/context/properties/source/ConfigurationPropertyName.append:(Ljava/lang/String;)Lorg/springframework/boot/context/properties/source/ConfigurationPropertyName;
      11: areturn

  org.springframework.boot.context.properties.bind.validation.ValidationErrors getValidationErrors();
    Code:
       0: aload_0
       1: getfield      #1                  // Field this$0:Lorg/springframework/boot/context/properties/bind/validation/ValidationBindHandler;
       4: getfield      #138                // Field org/springframework/boot/context/properties/bind/validation/ValidationBindHandler.boundProperties:Ljava/util/Set;
       7: invokeinterface #142,  1          // InterfaceMethod java/util/Set.stream:()Ljava/util/stream/Stream;
      12: aload_0
      13: invokedynamic #146,  0            // InvokeDynamic #0:test:(Lorg/springframework/boot/context/properties/bind/validation/ValidationBindHandler$ValidationResult;)Ljava/util/function/Predicate;
      18: invokeinterface #150,  2          // InterfaceMethod java/util/stream/Stream.filter:(Ljava/util/function/Predicate;)Ljava/util/stream/Stream;
      23: invokedynamic #156,  0            // InvokeDynamic #1:get:()Ljava/util/function/Supplier;
      28: invokestatic  #159                // Method java/util/stream/Collectors.toCollection:(Ljava/util/function/Supplier;)Ljava/util/stream/Collector;
      31: invokeinterface #165,  2          // InterfaceMethod java/util/stream/Stream.collect:(Ljava/util/stream/Collector;)Ljava/lang/Object;
      36: checkcast     #83                 // class java/util/Set
      39: astore_1
      40: new           #169                // class org/springframework/boot/context/properties/bind/validation/ValidationErrors
      43: dup
      44: aload_0
      45: getfield      #13                 // Field name:Lorg/springframework/boot/context/properties/source/ConfigurationPropertyName;
      48: aload_1
      49: aload_0
      50: invokevirtual #171                // Method getAllErrors:()Ljava/util/List;
      53: invokespecial #175                // Method org/springframework/boot/context/properties/bind/validation/ValidationErrors."<init>":(Lorg/springframework/boot/context/properties/source/ConfigurationPropertyName;Ljava/util/Set;Ljava/util/List;)V
      56: areturn

  private boolean lambda$getValidationErrors$0(org.springframework.boot.context.properties.source.ConfigurationProperty);
    Code:
       0: aload_0
       1: getfield      #13                 // Field name:Lorg/springframework/boot/context/properties/source/ConfigurationPropertyName;
       4: aload_1
       5: invokevirtual #178                // Method org/springframework/boot/context/properties/source/ConfigurationProperty.getName:()Lorg/springframework/boot/context/properties/source/ConfigurationPropertyName;
       8: invokevirtual #183                // Method org/springframework/boot/context/properties/source/ConfigurationPropertyName.isAncestorOf:(Lorg/springframework/boot/context/properties/source/ConfigurationPropertyName;)Z
      11: ireturn
}
