Compiled from "AbstractDeployer.java"
public abstract class org.apache.dubbo.common.deploy.AbstractDeployer<E extends org.apache.dubbo.rpc.model.ScopeModel> implements org.apache.dubbo.common.deploy.Deployer<E> {
  private static final org.apache.dubbo.common.logger.ErrorTypeAwareLogger logger;

  private volatile org.apache.dubbo.common.deploy.DeployState state;

  private volatile java.lang.Throwable lastError;

  protected volatile boolean initialized;

  protected java.util.List<org.apache.dubbo.common.deploy.DeployListener<E>> listeners;

  private E scopeModel;

  public org.apache.dubbo.common.deploy.AbstractDeployer(E);
    Code:
       0: aload_0
       1: invokespecial #2                  // Method java/lang/Object."<init>":()V
       4: aload_0
       5: getstatic     #3                  // Field org/apache/dubbo/common/deploy/DeployState.PENDING:Lorg/apache/dubbo/common/deploy/DeployState;
       8: putfield      #4                  // Field state:Lorg/apache/dubbo/common/deploy/DeployState;
      11: aload_0
      12: iconst_0
      13: putfield      #5                  // Field initialized:Z
      16: aload_0
      17: new           #6                  // class java/util/concurrent/CopyOnWriteArrayList
      20: dup
      21: invokespecial #7                  // Method java/util/concurrent/CopyOnWriteArrayList."<init>":()V
      24: putfield      #8                  // Field listeners:Ljava/util/List;
      27: aload_0
      28: aload_1
      29: putfield      #9                  // Field scopeModel:Lorg/apache/dubbo/rpc/model/ScopeModel;
      32: return

  public boolean isPending();
    Code:
       0: aload_0
       1: getfield      #4                  // Field state:Lorg/apache/dubbo/common/deploy/DeployState;
       4: getstatic     #3                  // Field org/apache/dubbo/common/deploy/DeployState.PENDING:Lorg/apache/dubbo/common/deploy/DeployState;
       7: if_acmpne     14
      10: iconst_1
      11: goto          15
      14: iconst_0
      15: ireturn

  public boolean isRunning();
    Code:
       0: aload_0
       1: getfield      #4                  // Field state:Lorg/apache/dubbo/common/deploy/DeployState;
       4: getstatic     #10                 // Field org/apache/dubbo/common/deploy/DeployState.STARTING:Lorg/apache/dubbo/common/deploy/DeployState;
       7: if_acmpeq     20
      10: aload_0
      11: getfield      #4                  // Field state:Lorg/apache/dubbo/common/deploy/DeployState;
      14: getstatic     #11                 // Field org/apache/dubbo/common/deploy/DeployState.STARTED:Lorg/apache/dubbo/common/deploy/DeployState;
      17: if_acmpne     24
      20: iconst_1
      21: goto          25
      24: iconst_0
      25: ireturn

  public boolean isStarted();
    Code:
       0: aload_0
       1: getfield      #4                  // Field state:Lorg/apache/dubbo/common/deploy/DeployState;
       4: getstatic     #11                 // Field org/apache/dubbo/common/deploy/DeployState.STARTED:Lorg/apache/dubbo/common/deploy/DeployState;
       7: if_acmpne     14
      10: iconst_1
      11: goto          15
      14: iconst_0
      15: ireturn

  public boolean isStarting();
    Code:
       0: aload_0
       1: getfield      #4                  // Field state:Lorg/apache/dubbo/common/deploy/DeployState;
       4: getstatic     #10                 // Field org/apache/dubbo/common/deploy/DeployState.STARTING:Lorg/apache/dubbo/common/deploy/DeployState;
       7: if_acmpne     14
      10: iconst_1
      11: goto          15
      14: iconst_0
      15: ireturn

  public boolean isStopping();
    Code:
       0: aload_0
       1: getfield      #4                  // Field state:Lorg/apache/dubbo/common/deploy/DeployState;
       4: getstatic     #12                 // Field org/apache/dubbo/common/deploy/DeployState.STOPPING:Lorg/apache/dubbo/common/deploy/DeployState;
       7: if_acmpne     14
      10: iconst_1
      11: goto          15
      14: iconst_0
      15: ireturn

  public boolean isStopped();
    Code:
       0: aload_0
       1: getfield      #4                  // Field state:Lorg/apache/dubbo/common/deploy/DeployState;
       4: getstatic     #13                 // Field org/apache/dubbo/common/deploy/DeployState.STOPPED:Lorg/apache/dubbo/common/deploy/DeployState;
       7: if_acmpne     14
      10: iconst_1
      11: goto          15
      14: iconst_0
      15: ireturn

  public boolean isFailed();
    Code:
       0: aload_0
       1: getfield      #4                  // Field state:Lorg/apache/dubbo/common/deploy/DeployState;
       4: getstatic     #14                 // Field org/apache/dubbo/common/deploy/DeployState.FAILED:Lorg/apache/dubbo/common/deploy/DeployState;
       7: if_acmpne     14
      10: iconst_1
      11: goto          15
      14: iconst_0
      15: ireturn

  public org.apache.dubbo.common.deploy.DeployState getState();
    Code:
       0: aload_0
       1: getfield      #4                  // Field state:Lorg/apache/dubbo/common/deploy/DeployState;
       4: areturn

  public void addDeployListener(org.apache.dubbo.common.deploy.DeployListener<E>);
    Code:
       0: aload_0
       1: getfield      #8                  // Field listeners:Ljava/util/List;
       4: aload_1
       5: invokeinterface #15,  2           // InterfaceMethod java/util/List.add:(Ljava/lang/Object;)Z
      10: pop
      11: return

  public void removeDeployListener(org.apache.dubbo.common.deploy.DeployListener<E>);
    Code:
       0: aload_0
       1: getfield      #8                  // Field listeners:Ljava/util/List;
       4: aload_1
       5: invokeinterface #16,  2           // InterfaceMethod java/util/List.remove:(Ljava/lang/Object;)Z
      10: pop
      11: return

  public void setPending();
    Code:
       0: aload_0
       1: getstatic     #3                  // Field org/apache/dubbo/common/deploy/DeployState.PENDING:Lorg/apache/dubbo/common/deploy/DeployState;
       4: putfield      #4                  // Field state:Lorg/apache/dubbo/common/deploy/DeployState;
       7: return

  protected void setStarting();
    Code:
       0: aload_0
       1: getstatic     #10                 // Field org/apache/dubbo/common/deploy/DeployState.STARTING:Lorg/apache/dubbo/common/deploy/DeployState;
       4: putfield      #4                  // Field state:Lorg/apache/dubbo/common/deploy/DeployState;
       7: aload_0
       8: getfield      #8                  // Field listeners:Ljava/util/List;
      11: invokeinterface #17,  1           // InterfaceMethod java/util/List.iterator:()Ljava/util/Iterator;
      16: astore_1
      17: aload_1
      18: invokeinterface #18,  1           // InterfaceMethod java/util/Iterator.hasNext:()Z
      23: ifeq          90
      26: aload_1
      27: invokeinterface #19,  1           // InterfaceMethod java/util/Iterator.next:()Ljava/lang/Object;
      32: checkcast     #20                 // class org/apache/dubbo/common/deploy/DeployListener
      35: astore_2
      36: aload_2
      37: aload_0
      38: getfield      #9                  // Field scopeModel:Lorg/apache/dubbo/rpc/model/ScopeModel;
      41: invokeinterface #21,  2           // InterfaceMethod org/apache/dubbo/common/deploy/DeployListener.onStarting:(Lorg/apache/dubbo/rpc/model/ScopeModel;)V
      46: goto          87
      49: astore_3
      50: getstatic     #23                 // Field logger:Lorg/apache/dubbo/common/logger/ErrorTypeAwareLogger;
      53: ldc           #24                 // String 0-14
      55: ldc           #25                 // String
      57: ldc           #25                 // String
      59: new           #26                 // class java/lang/StringBuilder
      62: dup
      63: invokespecial #27                 // Method java/lang/StringBuilder."<init>":()V
      66: aload_0
      67: invokevirtual #28                 // Method getIdentifier:()Ljava/lang/String;
      70: invokevirtual #29                 // Method java/lang/StringBuilder.append:(Ljava/lang/String;)Ljava/lang/StringBuilder;
      73: ldc           #30                 // String  an exception occurred when handle starting event
      75: invokevirtual #29                 // Method java/lang/StringBuilder.append:(Ljava/lang/String;)Ljava/lang/StringBuilder;
      78: invokevirtual #31                 // Method java/lang/StringBuilder.toString:()Ljava/lang/String;
      81: aload_3
      82: invokeinterface #32,  6           // InterfaceMethod org/apache/dubbo/common/logger/ErrorTypeAwareLogger.error:(Ljava/lang/String;Ljava/lang/String;Ljava/lang/String;Ljava/lang/String;Ljava/lang/Throwable;)V
      87: goto          17
      90: return
    Exception table:
       from    to  target type
          36    46    49   Class java/lang/Throwable

  protected void setStarted();
    Code:
       0: aload_0
       1: getstatic     #11                 // Field org/apache/dubbo/common/deploy/DeployState.STARTED:Lorg/apache/dubbo/common/deploy/DeployState;
       4: putfield      #4                  // Field state:Lorg/apache/dubbo/common/deploy/DeployState;
       7: aload_0
       8: getfield      #8                  // Field listeners:Ljava/util/List;
      11: invokeinterface #17,  1           // InterfaceMethod java/util/List.iterator:()Ljava/util/Iterator;
      16: astore_1
      17: aload_1
      18: invokeinterface #18,  1           // InterfaceMethod java/util/Iterator.hasNext:()Z
      23: ifeq          90
      26: aload_1
      27: invokeinterface #19,  1           // InterfaceMethod java/util/Iterator.next:()Ljava/lang/Object;
      32: checkcast     #20                 // class org/apache/dubbo/common/deploy/DeployListener
      35: astore_2
      36: aload_2
      37: aload_0
      38: getfield      #9                  // Field scopeModel:Lorg/apache/dubbo/rpc/model/ScopeModel;
      41: invokeinterface #33,  2           // InterfaceMethod org/apache/dubbo/common/deploy/DeployListener.onStarted:(Lorg/apache/dubbo/rpc/model/ScopeModel;)V
      46: goto          87
      49: astore_3
      50: getstatic     #23                 // Field logger:Lorg/apache/dubbo/common/logger/ErrorTypeAwareLogger;
      53: ldc           #24                 // String 0-14
      55: ldc           #25                 // String
      57: ldc           #25                 // String
      59: new           #26                 // class java/lang/StringBuilder
      62: dup
      63: invokespecial #27                 // Method java/lang/StringBuilder."<init>":()V
      66: aload_0
      67: invokevirtual #28                 // Method getIdentifier:()Ljava/lang/String;
      70: invokevirtual #29                 // Method java/lang/StringBuilder.append:(Ljava/lang/String;)Ljava/lang/StringBuilder;
      73: ldc           #34                 // String  an exception occurred when handle started event
      75: invokevirtual #29                 // Method java/lang/StringBuilder.append:(Ljava/lang/String;)Ljava/lang/StringBuilder;
      78: invokevirtual #31                 // Method java/lang/StringBuilder.toString:()Ljava/lang/String;
      81: aload_3
      82: invokeinterface #32,  6           // InterfaceMethod org/apache/dubbo/common/logger/ErrorTypeAwareLogger.error:(Ljava/lang/String;Ljava/lang/String;Ljava/lang/String;Ljava/lang/String;Ljava/lang/Throwable;)V
      87: goto          17
      90: return
    Exception table:
       from    to  target type
          36    46    49   Class java/lang/Throwable

  protected void setStopping();
    Code:
       0: aload_0
       1: getstatic     #12                 // Field org/apache/dubbo/common/deploy/DeployState.STOPPING:Lorg/apache/dubbo/common/deploy/DeployState;
       4: putfield      #4                  // Field state:Lorg/apache/dubbo/common/deploy/DeployState;
       7: aload_0
       8: getfield      #8                  // Field listeners:Ljava/util/List;
      11: invokeinterface #17,  1           // InterfaceMethod java/util/List.iterator:()Ljava/util/Iterator;
      16: astore_1
      17: aload_1
      18: invokeinterface #18,  1           // InterfaceMethod java/util/Iterator.hasNext:()Z
      23: ifeq          90
      26: aload_1
      27: invokeinterface #19,  1           // InterfaceMethod java/util/Iterator.next:()Ljava/lang/Object;
      32: checkcast     #20                 // class org/apache/dubbo/common/deploy/DeployListener
      35: astore_2
      36: aload_2
      37: aload_0
      38: getfield      #9                  // Field scopeModel:Lorg/apache/dubbo/rpc/model/ScopeModel;
      41: invokeinterface #35,  2           // InterfaceMethod org/apache/dubbo/common/deploy/DeployListener.onStopping:(Lorg/apache/dubbo/rpc/model/ScopeModel;)V
      46: goto          87
      49: astore_3
      50: getstatic     #23                 // Field logger:Lorg/apache/dubbo/common/logger/ErrorTypeAwareLogger;
      53: ldc           #24                 // String 0-14
      55: ldc           #25                 // String
      57: ldc           #25                 // String
      59: new           #26                 // class java/lang/StringBuilder
      62: dup
      63: invokespecial #27                 // Method java/lang/StringBuilder."<init>":()V
      66: aload_0
      67: invokevirtual #28                 // Method getIdentifier:()Ljava/lang/String;
      70: invokevirtual #29                 // Method java/lang/StringBuilder.append:(Ljava/lang/String;)Ljava/lang/StringBuilder;
      73: ldc           #36                 // String  an exception occurred when handle stopping event
      75: invokevirtual #29                 // Method java/lang/StringBuilder.append:(Ljava/lang/String;)Ljava/lang/StringBuilder;
      78: invokevirtual #31                 // Method java/lang/StringBuilder.toString:()Ljava/lang/String;
      81: aload_3
      82: invokeinterface #32,  6           // InterfaceMethod org/apache/dubbo/common/logger/ErrorTypeAwareLogger.error:(Ljava/lang/String;Ljava/lang/String;Ljava/lang/String;Ljava/lang/String;Ljava/lang/Throwable;)V
      87: goto          17
      90: return
    Exception table:
       from    to  target type
          36    46    49   Class java/lang/Throwable

  protected void setStopped();
    Code:
       0: aload_0
       1: getstatic     #13                 // Field org/apache/dubbo/common/deploy/DeployState.STOPPED:Lorg/apache/dubbo/common/deploy/DeployState;
       4: putfield      #4                  // Field state:Lorg/apache/dubbo/common/deploy/DeployState;
       7: aload_0
       8: getfield      #8                  // Field listeners:Ljava/util/List;
      11: invokeinterface #17,  1           // InterfaceMethod java/util/List.iterator:()Ljava/util/Iterator;
      16: astore_1
      17: aload_1
      18: invokeinterface #18,  1           // InterfaceMethod java/util/Iterator.hasNext:()Z
      23: ifeq          90
      26: aload_1
      27: invokeinterface #19,  1           // InterfaceMethod java/util/Iterator.next:()Ljava/lang/Object;
      32: checkcast     #20                 // class org/apache/dubbo/common/deploy/DeployListener
      35: astore_2
      36: aload_2
      37: aload_0
      38: getfield      #9                  // Field scopeModel:Lorg/apache/dubbo/rpc/model/ScopeModel;
      41: invokeinterface #37,  2           // InterfaceMethod org/apache/dubbo/common/deploy/DeployListener.onStopped:(Lorg/apache/dubbo/rpc/model/ScopeModel;)V
      46: goto          87
      49: astore_3
      50: getstatic     #23                 // Field logger:Lorg/apache/dubbo/common/logger/ErrorTypeAwareLogger;
      53: ldc           #24                 // String 0-14
      55: ldc           #25                 // String
      57: ldc           #25                 // String
      59: new           #26                 // class java/lang/StringBuilder
      62: dup
      63: invokespecial #27                 // Method java/lang/StringBuilder."<init>":()V
      66: aload_0
      67: invokevirtual #28                 // Method getIdentifier:()Ljava/lang/String;
      70: invokevirtual #29                 // Method java/lang/StringBuilder.append:(Ljava/lang/String;)Ljava/lang/StringBuilder;
      73: ldc           #38                 // String  an exception occurred when handle stopped event
      75: invokevirtual #29                 // Method java/lang/StringBuilder.append:(Ljava/lang/String;)Ljava/lang/StringBuilder;
      78: invokevirtual #31                 // Method java/lang/StringBuilder.toString:()Ljava/lang/String;
      81: aload_3
      82: invokeinterface #32,  6           // InterfaceMethod org/apache/dubbo/common/logger/ErrorTypeAwareLogger.error:(Ljava/lang/String;Ljava/lang/String;Ljava/lang/String;Ljava/lang/String;Ljava/lang/Throwable;)V
      87: goto          17
      90: return
    Exception table:
       from    to  target type
          36    46    49   Class java/lang/Throwable

  protected void setFailed(java.lang.Throwable);
    Code:
       0: aload_0
       1: getstatic     #14                 // Field org/apache/dubbo/common/deploy/DeployState.FAILED:Lorg/apache/dubbo/common/deploy/DeployState;
       4: putfield      #4                  // Field state:Lorg/apache/dubbo/common/deploy/DeployState;
       7: aload_0
       8: aload_1
       9: putfield      #39                 // Field lastError:Ljava/lang/Throwable;
      12: aload_0
      13: getfield      #8                  // Field listeners:Ljava/util/List;
      16: invokeinterface #17,  1           // InterfaceMethod java/util/List.iterator:()Ljava/util/Iterator;
      21: astore_2
      22: aload_2
      23: invokeinterface #18,  1           // InterfaceMethod java/util/Iterator.hasNext:()Z
      28: ifeq          98
      31: aload_2
      32: invokeinterface #19,  1           // InterfaceMethod java/util/Iterator.next:()Ljava/lang/Object;
      37: checkcast     #20                 // class org/apache/dubbo/common/deploy/DeployListener
      40: astore_3
      41: aload_3
      42: aload_0
      43: getfield      #9                  // Field scopeModel:Lorg/apache/dubbo/rpc/model/ScopeModel;
      46: aload_1
      47: invokeinterface #40,  3           // InterfaceMethod org/apache/dubbo/common/deploy/DeployListener.onFailure:(Lorg/apache/dubbo/rpc/model/ScopeModel;Ljava/lang/Throwable;)V
      52: goto          95
      55: astore        4
      57: getstatic     #23                 // Field logger:Lorg/apache/dubbo/common/logger/ErrorTypeAwareLogger;
      60: ldc           #24                 // String 0-14
      62: ldc           #25                 // String
      64: ldc           #25                 // String
      66: new           #26                 // class java/lang/StringBuilder
      69: dup
      70: invokespecial #27                 // Method java/lang/StringBuilder."<init>":()V
      73: aload_0
      74: invokevirtual #28                 // Method getIdentifier:()Ljava/lang/String;
      77: invokevirtual #29                 // Method java/lang/StringBuilder.append:(Ljava/lang/String;)Ljava/lang/StringBuilder;
      80: ldc           #41                 // String  an exception occurred when handle failed event
      82: invokevirtual #29                 // Method java/lang/StringBuilder.append:(Ljava/lang/String;)Ljava/lang/StringBuilder;
      85: invokevirtual #31                 // Method java/lang/StringBuilder.toString:()Ljava/lang/String;
      88: aload         4
      90: invokeinterface #32,  6           // InterfaceMethod org/apache/dubbo/common/logger/ErrorTypeAwareLogger.error:(Ljava/lang/String;Ljava/lang/String;Ljava/lang/String;Ljava/lang/String;Ljava/lang/Throwable;)V
      95: goto          22
      98: return
    Exception table:
       from    to  target type
          41    52    55   Class java/lang/Throwable

  public java.lang.Throwable getError();
    Code:
       0: aload_0
       1: getfield      #39                 // Field lastError:Ljava/lang/Throwable;
       4: areturn

  public boolean isInitialized();
    Code:
       0: aload_0
       1: getfield      #5                  // Field initialized:Z
       4: ireturn

  protected java.lang.String getIdentifier();
    Code:
       0: aload_0
       1: getfield      #9                  // Field scopeModel:Lorg/apache/dubbo/rpc/model/ScopeModel;
       4: invokevirtual #42                 // Method org/apache/dubbo/rpc/model/ScopeModel.getDesc:()Ljava/lang/String;
       7: areturn

  static {};
    Code:
       0: ldc           #43                 // class org/apache/dubbo/common/deploy/AbstractDeployer
       2: invokestatic  #44                 // Method org/apache/dubbo/common/logger/LoggerFactory.getErrorTypeAwareLogger:(Ljava/lang/Class;)Lorg/apache/dubbo/common/logger/ErrorTypeAwareLogger;
       5: putstatic     #23                 // Field logger:Lorg/apache/dubbo/common/logger/ErrorTypeAwareLogger;
       8: return
}
