Compiled from "DeployListenerAdapter.java"
public class org.apache.dubbo.common.deploy.DeployListenerAdapter<E extends org.apache.dubbo.rpc.model.ScopeModel> implements org.apache.dubbo.common.deploy.DeployListener<E> {
  public org.apache.dubbo.common.deploy.DeployListenerAdapter();
    Code:
       0: aload_0
       1: invokespecial #1                  // Method java/lang/Object."<init>":()V
       4: return

  public void onInitialize(E);
    Code:
       0: return

  public void onStarting(E);
    Code:
       0: return

  public void onStarted(E);
    Code:
       0: return

  public void onStopping(E);
    Code:
       0: return

  public void onStopped(E);
    Code:
       0: return

  public void onFailure(E, java.lang.Throwable);
    Code:
       0: return
}
