Compiled from "TaskExecutorBuilder.java"
public class org.springframework.boot.task.TaskExecutorBuilder {
  private final java.lang.Integer queueCapacity;

  private final java.lang.Integer corePoolSize;

  private final java.lang.Integer maxPoolSize;

  private final java.lang.Boolean allowCoreThreadTimeOut;

  private final java.time.Duration keepAlive;

  private final java.lang.Boolean awaitTermination;

  private final java.time.Duration awaitTerminationPeriod;

  private final java.lang.String threadNamePrefix;

  private final org.springframework.core.task.TaskDecorator taskDecorator;

  private final java.util.Set<org.springframework.boot.task.TaskExecutorCustomizer> customizers;

  public org.springframework.boot.task.TaskExecutorBuilder();
    Code:
       0: aload_0
       1: invokespecial #1                  // Method java/lang/Object."<init>":()V
       4: aload_0
       5: aconst_null
       6: putfield      #7                  // Field queueCapacity:Ljava/lang/Integer;
       9: aload_0
      10: aconst_null
      11: putfield      #13                 // Field corePoolSize:Ljava/lang/Integer;
      14: aload_0
      15: aconst_null
      16: putfield      #16                 // Field maxPoolSize:Ljava/lang/Integer;
      19: aload_0
      20: aconst_null
      21: putfield      #19                 // Field allowCoreThreadTimeOut:Ljava/lang/Boolean;
      24: aload_0
      25: aconst_null
      26: putfield      #23                 // Field keepAlive:Ljava/time/Duration;
      29: aload_0
      30: aconst_null
      31: putfield      #27                 // Field awaitTermination:Ljava/lang/Boolean;
      34: aload_0
      35: aconst_null
      36: putfield      #30                 // Field awaitTerminationPeriod:Ljava/time/Duration;
      39: aload_0
      40: aconst_null
      41: putfield      #33                 // Field threadNamePrefix:Ljava/lang/String;
      44: aload_0
      45: aconst_null
      46: putfield      #37                 // Field taskDecorator:Lorg/springframework/core/task/TaskDecorator;
      49: aload_0
      50: aconst_null
      51: putfield      #41                 // Field customizers:Ljava/util/Set;
      54: return

  private org.springframework.boot.task.TaskExecutorBuilder(java.lang.Integer, java.lang.Integer, java.lang.Integer, java.lang.Boolean, java.time.Duration, java.lang.Boolean, java.time.Duration, java.lang.String, org.springframework.core.task.TaskDecorator, java.util.Set<org.springframework.boot.task.TaskExecutorCustomizer>);
    Code:
       0: aload_0
       1: invokespecial #1                  // Method java/lang/Object."<init>":()V
       4: aload_0
       5: aload_1
       6: putfield      #7                  // Field queueCapacity:Ljava/lang/Integer;
       9: aload_0
      10: aload_2
      11: putfield      #13                 // Field corePoolSize:Ljava/lang/Integer;
      14: aload_0
      15: aload_3
      16: putfield      #16                 // Field maxPoolSize:Ljava/lang/Integer;
      19: aload_0
      20: aload         4
      22: putfield      #19                 // Field allowCoreThreadTimeOut:Ljava/lang/Boolean;
      25: aload_0
      26: aload         5
      28: putfield      #23                 // Field keepAlive:Ljava/time/Duration;
      31: aload_0
      32: aload         6
      34: putfield      #27                 // Field awaitTermination:Ljava/lang/Boolean;
      37: aload_0
      38: aload         7
      40: putfield      #30                 // Field awaitTerminationPeriod:Ljava/time/Duration;
      43: aload_0
      44: aload         8
      46: putfield      #33                 // Field threadNamePrefix:Ljava/lang/String;
      49: aload_0
      50: aload         9
      52: putfield      #37                 // Field taskDecorator:Lorg/springframework/core/task/TaskDecorator;
      55: aload_0
      56: aload         10
      58: putfield      #41                 // Field customizers:Ljava/util/Set;
      61: return

  public org.springframework.boot.task.TaskExecutorBuilder queueCapacity(int);
    Code:
       0: new           #8                  // class org/springframework/boot/task/TaskExecutorBuilder
       3: dup
       4: iload_1
       5: invokestatic  #45                 // Method java/lang/Integer.valueOf:(I)Ljava/lang/Integer;
       8: aload_0
       9: getfield      #13                 // Field corePoolSize:Ljava/lang/Integer;
      12: aload_0
      13: getfield      #16                 // Field maxPoolSize:Ljava/lang/Integer;
      16: aload_0
      17: getfield      #19                 // Field allowCoreThreadTimeOut:Ljava/lang/Boolean;
      20: aload_0
      21: getfield      #23                 // Field keepAlive:Ljava/time/Duration;
      24: aload_0
      25: getfield      #27                 // Field awaitTermination:Ljava/lang/Boolean;
      28: aload_0
      29: getfield      #30                 // Field awaitTerminationPeriod:Ljava/time/Duration;
      32: aload_0
      33: getfield      #33                 // Field threadNamePrefix:Ljava/lang/String;
      36: aload_0
      37: getfield      #37                 // Field taskDecorator:Lorg/springframework/core/task/TaskDecorator;
      40: aload_0
      41: getfield      #41                 // Field customizers:Ljava/util/Set;
      44: invokespecial #51                 // Method "<init>":(Ljava/lang/Integer;Ljava/lang/Integer;Ljava/lang/Integer;Ljava/lang/Boolean;Ljava/time/Duration;Ljava/lang/Boolean;Ljava/time/Duration;Ljava/lang/String;Lorg/springframework/core/task/TaskDecorator;Ljava/util/Set;)V
      47: areturn

  public org.springframework.boot.task.TaskExecutorBuilder corePoolSize(int);
    Code:
       0: new           #8                  // class org/springframework/boot/task/TaskExecutorBuilder
       3: dup
       4: aload_0
       5: getfield      #7                  // Field queueCapacity:Ljava/lang/Integer;
       8: iload_1
       9: invokestatic  #45                 // Method java/lang/Integer.valueOf:(I)Ljava/lang/Integer;
      12: aload_0
      13: getfield      #16                 // Field maxPoolSize:Ljava/lang/Integer;
      16: aload_0
      17: getfield      #19                 // Field allowCoreThreadTimeOut:Ljava/lang/Boolean;
      20: aload_0
      21: getfield      #23                 // Field keepAlive:Ljava/time/Duration;
      24: aload_0
      25: getfield      #27                 // Field awaitTermination:Ljava/lang/Boolean;
      28: aload_0
      29: getfield      #30                 // Field awaitTerminationPeriod:Ljava/time/Duration;
      32: aload_0
      33: getfield      #33                 // Field threadNamePrefix:Ljava/lang/String;
      36: aload_0
      37: getfield      #37                 // Field taskDecorator:Lorg/springframework/core/task/TaskDecorator;
      40: aload_0
      41: getfield      #41                 // Field customizers:Ljava/util/Set;
      44: invokespecial #51                 // Method "<init>":(Ljava/lang/Integer;Ljava/lang/Integer;Ljava/lang/Integer;Ljava/lang/Boolean;Ljava/time/Duration;Ljava/lang/Boolean;Ljava/time/Duration;Ljava/lang/String;Lorg/springframework/core/task/TaskDecorator;Ljava/util/Set;)V
      47: areturn

  public org.springframework.boot.task.TaskExecutorBuilder maxPoolSize(int);
    Code:
       0: new           #8                  // class org/springframework/boot/task/TaskExecutorBuilder
       3: dup
       4: aload_0
       5: getfield      #7                  // Field queueCapacity:Ljava/lang/Integer;
       8: aload_0
       9: getfield      #13                 // Field corePoolSize:Ljava/lang/Integer;
      12: iload_1
      13: invokestatic  #45                 // Method java/lang/Integer.valueOf:(I)Ljava/lang/Integer;
      16: aload_0
      17: getfield      #19                 // Field allowCoreThreadTimeOut:Ljava/lang/Boolean;
      20: aload_0
      21: getfield      #23                 // Field keepAlive:Ljava/time/Duration;
      24: aload_0
      25: getfield      #27                 // Field awaitTermination:Ljava/lang/Boolean;
      28: aload_0
      29: getfield      #30                 // Field awaitTerminationPeriod:Ljava/time/Duration;
      32: aload_0
      33: getfield      #33                 // Field threadNamePrefix:Ljava/lang/String;
      36: aload_0
      37: getfield      #37                 // Field taskDecorator:Lorg/springframework/core/task/TaskDecorator;
      40: aload_0
      41: getfield      #41                 // Field customizers:Ljava/util/Set;
      44: invokespecial #51                 // Method "<init>":(Ljava/lang/Integer;Ljava/lang/Integer;Ljava/lang/Integer;Ljava/lang/Boolean;Ljava/time/Duration;Ljava/lang/Boolean;Ljava/time/Duration;Ljava/lang/String;Lorg/springframework/core/task/TaskDecorator;Ljava/util/Set;)V
      47: areturn

  public org.springframework.boot.task.TaskExecutorBuilder allowCoreThreadTimeOut(boolean);
    Code:
       0: new           #8                  // class org/springframework/boot/task/TaskExecutorBuilder
       3: dup
       4: aload_0
       5: getfield      #7                  // Field queueCapacity:Ljava/lang/Integer;
       8: aload_0
       9: getfield      #13                 // Field corePoolSize:Ljava/lang/Integer;
      12: aload_0
      13: getfield      #16                 // Field maxPoolSize:Ljava/lang/Integer;
      16: iload_1
      17: invokestatic  #54                 // Method java/lang/Boolean.valueOf:(Z)Ljava/lang/Boolean;
      20: aload_0
      21: getfield      #23                 // Field keepAlive:Ljava/time/Duration;
      24: aload_0
      25: getfield      #27                 // Field awaitTermination:Ljava/lang/Boolean;
      28: aload_0
      29: getfield      #30                 // Field awaitTerminationPeriod:Ljava/time/Duration;
      32: aload_0
      33: getfield      #33                 // Field threadNamePrefix:Ljava/lang/String;
      36: aload_0
      37: getfield      #37                 // Field taskDecorator:Lorg/springframework/core/task/TaskDecorator;
      40: aload_0
      41: getfield      #41                 // Field customizers:Ljava/util/Set;
      44: invokespecial #51                 // Method "<init>":(Ljava/lang/Integer;Ljava/lang/Integer;Ljava/lang/Integer;Ljava/lang/Boolean;Ljava/time/Duration;Ljava/lang/Boolean;Ljava/time/Duration;Ljava/lang/String;Lorg/springframework/core/task/TaskDecorator;Ljava/util/Set;)V
      47: areturn

  public org.springframework.boot.task.TaskExecutorBuilder keepAlive(java.time.Duration);
    Code:
       0: new           #8                  // class org/springframework/boot/task/TaskExecutorBuilder
       3: dup
       4: aload_0
       5: getfield      #7                  // Field queueCapacity:Ljava/lang/Integer;
       8: aload_0
       9: getfield      #13                 // Field corePoolSize:Ljava/lang/Integer;
      12: aload_0
      13: getfield      #16                 // Field maxPoolSize:Ljava/lang/Integer;
      16: aload_0
      17: getfield      #19                 // Field allowCoreThreadTimeOut:Ljava/lang/Boolean;
      20: aload_1
      21: aload_0
      22: getfield      #27                 // Field awaitTermination:Ljava/lang/Boolean;
      25: aload_0
      26: getfield      #30                 // Field awaitTerminationPeriod:Ljava/time/Duration;
      29: aload_0
      30: getfield      #33                 // Field threadNamePrefix:Ljava/lang/String;
      33: aload_0
      34: getfield      #37                 // Field taskDecorator:Lorg/springframework/core/task/TaskDecorator;
      37: aload_0
      38: getfield      #41                 // Field customizers:Ljava/util/Set;
      41: invokespecial #51                 // Method "<init>":(Ljava/lang/Integer;Ljava/lang/Integer;Ljava/lang/Integer;Ljava/lang/Boolean;Ljava/time/Duration;Ljava/lang/Boolean;Ljava/time/Duration;Ljava/lang/String;Lorg/springframework/core/task/TaskDecorator;Ljava/util/Set;)V
      44: areturn

  public org.springframework.boot.task.TaskExecutorBuilder awaitTermination(boolean);
    Code:
       0: new           #8                  // class org/springframework/boot/task/TaskExecutorBuilder
       3: dup
       4: aload_0
       5: getfield      #7                  // Field queueCapacity:Ljava/lang/Integer;
       8: aload_0
       9: getfield      #13                 // Field corePoolSize:Ljava/lang/Integer;
      12: aload_0
      13: getfield      #16                 // Field maxPoolSize:Ljava/lang/Integer;
      16: aload_0
      17: getfield      #19                 // Field allowCoreThreadTimeOut:Ljava/lang/Boolean;
      20: aload_0
      21: getfield      #23                 // Field keepAlive:Ljava/time/Duration;
      24: iload_1
      25: invokestatic  #54                 // Method java/lang/Boolean.valueOf:(Z)Ljava/lang/Boolean;
      28: aload_0
      29: getfield      #30                 // Field awaitTerminationPeriod:Ljava/time/Duration;
      32: aload_0
      33: getfield      #33                 // Field threadNamePrefix:Ljava/lang/String;
      36: aload_0
      37: getfield      #37                 // Field taskDecorator:Lorg/springframework/core/task/TaskDecorator;
      40: aload_0
      41: getfield      #41                 // Field customizers:Ljava/util/Set;
      44: invokespecial #51                 // Method "<init>":(Ljava/lang/Integer;Ljava/lang/Integer;Ljava/lang/Integer;Ljava/lang/Boolean;Ljava/time/Duration;Ljava/lang/Boolean;Ljava/time/Duration;Ljava/lang/String;Lorg/springframework/core/task/TaskDecorator;Ljava/util/Set;)V
      47: areturn

  public org.springframework.boot.task.TaskExecutorBuilder awaitTerminationPeriod(java.time.Duration);
    Code:
       0: new           #8                  // class org/springframework/boot/task/TaskExecutorBuilder
       3: dup
       4: aload_0
       5: getfield      #7                  // Field queueCapacity:Ljava/lang/Integer;
       8: aload_0
       9: getfield      #13                 // Field corePoolSize:Ljava/lang/Integer;
      12: aload_0
      13: getfield      #16                 // Field maxPoolSize:Ljava/lang/Integer;
      16: aload_0
      17: getfield      #19                 // Field allowCoreThreadTimeOut:Ljava/lang/Boolean;
      20: aload_0
      21: getfield      #23                 // Field keepAlive:Ljava/time/Duration;
      24: aload_0
      25: getfield      #27                 // Field awaitTermination:Ljava/lang/Boolean;
      28: aload_1
      29: aload_0
      30: getfield      #33                 // Field threadNamePrefix:Ljava/lang/String;
      33: aload_0
      34: getfield      #37                 // Field taskDecorator:Lorg/springframework/core/task/TaskDecorator;
      37: aload_0
      38: getfield      #41                 // Field customizers:Ljava/util/Set;
      41: invokespecial #51                 // Method "<init>":(Ljava/lang/Integer;Ljava/lang/Integer;Ljava/lang/Integer;Ljava/lang/Boolean;Ljava/time/Duration;Ljava/lang/Boolean;Ljava/time/Duration;Ljava/lang/String;Lorg/springframework/core/task/TaskDecorator;Ljava/util/Set;)V
      44: areturn

  public org.springframework.boot.task.TaskExecutorBuilder threadNamePrefix(java.lang.String);
    Code:
       0: new           #8                  // class org/springframework/boot/task/TaskExecutorBuilder
       3: dup
       4: aload_0
       5: getfield      #7                  // Field queueCapacity:Ljava/lang/Integer;
       8: aload_0
       9: getfield      #13                 // Field corePoolSize:Ljava/lang/Integer;
      12: aload_0
      13: getfield      #16                 // Field maxPoolSize:Ljava/lang/Integer;
      16: aload_0
      17: getfield      #19                 // Field allowCoreThreadTimeOut:Ljava/lang/Boolean;
      20: aload_0
      21: getfield      #23                 // Field keepAlive:Ljava/time/Duration;
      24: aload_0
      25: getfield      #27                 // Field awaitTermination:Ljava/lang/Boolean;
      28: aload_0
      29: getfield      #30                 // Field awaitTerminationPeriod:Ljava/time/Duration;
      32: aload_1
      33: aload_0
      34: getfield      #37                 // Field taskDecorator:Lorg/springframework/core/task/TaskDecorator;
      37: aload_0
      38: getfield      #41                 // Field customizers:Ljava/util/Set;
      41: invokespecial #51                 // Method "<init>":(Ljava/lang/Integer;Ljava/lang/Integer;Ljava/lang/Integer;Ljava/lang/Boolean;Ljava/time/Duration;Ljava/lang/Boolean;Ljava/time/Duration;Ljava/lang/String;Lorg/springframework/core/task/TaskDecorator;Ljava/util/Set;)V
      44: areturn

  public org.springframework.boot.task.TaskExecutorBuilder taskDecorator(org.springframework.core.task.TaskDecorator);
    Code:
       0: new           #8                  // class org/springframework/boot/task/TaskExecutorBuilder
       3: dup
       4: aload_0
       5: getfield      #7                  // Field queueCapacity:Ljava/lang/Integer;
       8: aload_0
       9: getfield      #13                 // Field corePoolSize:Ljava/lang/Integer;
      12: aload_0
      13: getfield      #16                 // Field maxPoolSize:Ljava/lang/Integer;
      16: aload_0
      17: getfield      #19                 // Field allowCoreThreadTimeOut:Ljava/lang/Boolean;
      20: aload_0
      21: getfield      #23                 // Field keepAlive:Ljava/time/Duration;
      24: aload_0
      25: getfield      #27                 // Field awaitTermination:Ljava/lang/Boolean;
      28: aload_0
      29: getfield      #30                 // Field awaitTerminationPeriod:Ljava/time/Duration;
      32: aload_0
      33: getfield      #33                 // Field threadNamePrefix:Ljava/lang/String;
      36: aload_1
      37: aload_0
      38: getfield      #41                 // Field customizers:Ljava/util/Set;
      41: invokespecial #51                 // Method "<init>":(Ljava/lang/Integer;Ljava/lang/Integer;Ljava/lang/Integer;Ljava/lang/Boolean;Ljava/time/Duration;Ljava/lang/Boolean;Ljava/time/Duration;Ljava/lang/String;Lorg/springframework/core/task/TaskDecorator;Ljava/util/Set;)V
      44: areturn

  public org.springframework.boot.task.TaskExecutorBuilder customizers(org.springframework.boot.task.TaskExecutorCustomizer...);
    Code:
       0: aload_1
       1: ldc           #59                 // String Customizers must not be null
       3: invokestatic  #61                 // Method org/springframework/util/Assert.notNull:(Ljava/lang/Object;Ljava/lang/String;)V
       6: aload_0
       7: aload_1
       8: invokestatic  #67                 // Method java/util/Arrays.asList:([Ljava/lang/Object;)Ljava/util/List;
      11: invokevirtual #73                 // Method customizers:(Ljava/lang/Iterable;)Lorg/springframework/boot/task/TaskExecutorBuilder;
      14: areturn

  public org.springframework.boot.task.TaskExecutorBuilder customizers(java.lang.Iterable<org.springframework.boot.task.TaskExecutorCustomizer>);
    Code:
       0: aload_1
       1: ldc           #59                 // String Customizers must not be null
       3: invokestatic  #61                 // Method org/springframework/util/Assert.notNull:(Ljava/lang/Object;Ljava/lang/String;)V
       6: new           #8                  // class org/springframework/boot/task/TaskExecutorBuilder
       9: dup
      10: aload_0
      11: getfield      #7                  // Field queueCapacity:Ljava/lang/Integer;
      14: aload_0
      15: getfield      #13                 // Field corePoolSize:Ljava/lang/Integer;
      18: aload_0
      19: getfield      #16                 // Field maxPoolSize:Ljava/lang/Integer;
      22: aload_0
      23: getfield      #19                 // Field allowCoreThreadTimeOut:Ljava/lang/Boolean;
      26: aload_0
      27: getfield      #23                 // Field keepAlive:Ljava/time/Duration;
      30: aload_0
      31: getfield      #27                 // Field awaitTermination:Ljava/lang/Boolean;
      34: aload_0
      35: getfield      #30                 // Field awaitTerminationPeriod:Ljava/time/Duration;
      38: aload_0
      39: getfield      #33                 // Field threadNamePrefix:Ljava/lang/String;
      42: aload_0
      43: getfield      #37                 // Field taskDecorator:Lorg/springframework/core/task/TaskDecorator;
      46: aload_0
      47: aconst_null
      48: aload_1
      49: invokevirtual #76                 // Method append:(Ljava/util/Set;Ljava/lang/Iterable;)Ljava/util/Set;
      52: invokespecial #51                 // Method "<init>":(Ljava/lang/Integer;Ljava/lang/Integer;Ljava/lang/Integer;Ljava/lang/Boolean;Ljava/time/Duration;Ljava/lang/Boolean;Ljava/time/Duration;Ljava/lang/String;Lorg/springframework/core/task/TaskDecorator;Ljava/util/Set;)V
      55: areturn

  public org.springframework.boot.task.TaskExecutorBuilder additionalCustomizers(org.springframework.boot.task.TaskExecutorCustomizer...);
    Code:
       0: aload_1
       1: ldc           #59                 // String Customizers must not be null
       3: invokestatic  #61                 // Method org/springframework/util/Assert.notNull:(Ljava/lang/Object;Ljava/lang/String;)V
       6: aload_0
       7: aload_1
       8: invokestatic  #67                 // Method java/util/Arrays.asList:([Ljava/lang/Object;)Ljava/util/List;
      11: invokevirtual #80                 // Method additionalCustomizers:(Ljava/lang/Iterable;)Lorg/springframework/boot/task/TaskExecutorBuilder;
      14: areturn

  public org.springframework.boot.task.TaskExecutorBuilder additionalCustomizers(java.lang.Iterable<org.springframework.boot.task.TaskExecutorCustomizer>);
    Code:
       0: aload_1
       1: ldc           #59                 // String Customizers must not be null
       3: invokestatic  #61                 // Method org/springframework/util/Assert.notNull:(Ljava/lang/Object;Ljava/lang/String;)V
       6: new           #8                  // class org/springframework/boot/task/TaskExecutorBuilder
       9: dup
      10: aload_0
      11: getfield      #7                  // Field queueCapacity:Ljava/lang/Integer;
      14: aload_0
      15: getfield      #13                 // Field corePoolSize:Ljava/lang/Integer;
      18: aload_0
      19: getfield      #16                 // Field maxPoolSize:Ljava/lang/Integer;
      22: aload_0
      23: getfield      #19                 // Field allowCoreThreadTimeOut:Ljava/lang/Boolean;
      26: aload_0
      27: getfield      #23                 // Field keepAlive:Ljava/time/Duration;
      30: aload_0
      31: getfield      #27                 // Field awaitTermination:Ljava/lang/Boolean;
      34: aload_0
      35: getfield      #30                 // Field awaitTerminationPeriod:Ljava/time/Duration;
      38: aload_0
      39: getfield      #33                 // Field threadNamePrefix:Ljava/lang/String;
      42: aload_0
      43: getfield      #37                 // Field taskDecorator:Lorg/springframework/core/task/TaskDecorator;
      46: aload_0
      47: aload_0
      48: getfield      #41                 // Field customizers:Ljava/util/Set;
      51: aload_1
      52: invokevirtual #76                 // Method append:(Ljava/util/Set;Ljava/lang/Iterable;)Ljava/util/Set;
      55: invokespecial #51                 // Method "<init>":(Ljava/lang/Integer;Ljava/lang/Integer;Ljava/lang/Integer;Ljava/lang/Boolean;Ljava/time/Duration;Ljava/lang/Boolean;Ljava/time/Duration;Ljava/lang/String;Lorg/springframework/core/task/TaskDecorator;Ljava/util/Set;)V
      58: areturn

  public org.springframework.scheduling.concurrent.ThreadPoolTaskExecutor build();
    Code:
       0: aload_0
       1: new           #83                 // class org/springframework/scheduling/concurrent/ThreadPoolTaskExecutor
       4: dup
       5: invokespecial #85                 // Method org/springframework/scheduling/concurrent/ThreadPoolTaskExecutor."<init>":()V
       8: invokevirtual #86                 // Method configure:(Lorg/springframework/scheduling/concurrent/ThreadPoolTaskExecutor;)Lorg/springframework/scheduling/concurrent/ThreadPoolTaskExecutor;
      11: areturn

  public <T extends org.springframework.scheduling.concurrent.ThreadPoolTaskExecutor> T build(java.lang.Class<T>);
    Code:
       0: aload_0
       1: aload_1
       2: invokestatic  #90                 // Method org/springframework/beans/BeanUtils.instantiateClass:(Ljava/lang/Class;)Ljava/lang/Object;
       5: checkcast     #83                 // class org/springframework/scheduling/concurrent/ThreadPoolTaskExecutor
       8: invokevirtual #86                 // Method configure:(Lorg/springframework/scheduling/concurrent/ThreadPoolTaskExecutor;)Lorg/springframework/scheduling/concurrent/ThreadPoolTaskExecutor;
      11: areturn

  public <T extends org.springframework.scheduling.concurrent.ThreadPoolTaskExecutor> T configure(T);
    Code:
       0: invokestatic  #96                 // Method org/springframework/boot/context/properties/PropertyMapper.get:()Lorg/springframework/boot/context/properties/PropertyMapper;
       3: invokevirtual #102                // Method org/springframework/boot/context/properties/PropertyMapper.alwaysApplyingWhenNonNull:()Lorg/springframework/boot/context/properties/PropertyMapper;
       6: astore_2
       7: aload_2
       8: aload_0
       9: getfield      #7                  // Field queueCapacity:Ljava/lang/Integer;
      12: invokevirtual #105                // Method org/springframework/boot/context/properties/PropertyMapper.from:(Ljava/lang/Object;)Lorg/springframework/boot/context/properties/PropertyMapper$Source;
      15: aload_1
      16: dup
      17: invokestatic  #109                // Method java/util/Objects.requireNonNull:(Ljava/lang/Object;)Ljava/lang/Object;
      20: pop
      21: invokedynamic #115,  0            // InvokeDynamic #0:accept:(Lorg/springframework/scheduling/concurrent/ThreadPoolTaskExecutor;)Ljava/util/function/Consumer;
      26: invokevirtual #119                // Method org/springframework/boot/context/properties/PropertyMapper$Source.to:(Ljava/util/function/Consumer;)V
      29: aload_2
      30: aload_0
      31: getfield      #13                 // Field corePoolSize:Ljava/lang/Integer;
      34: invokevirtual #105                // Method org/springframework/boot/context/properties/PropertyMapper.from:(Ljava/lang/Object;)Lorg/springframework/boot/context/properties/PropertyMapper$Source;
      37: aload_1
      38: dup
      39: invokestatic  #109                // Method java/util/Objects.requireNonNull:(Ljava/lang/Object;)Ljava/lang/Object;
      42: pop
      43: invokedynamic #125,  0            // InvokeDynamic #1:accept:(Lorg/springframework/scheduling/concurrent/ThreadPoolTaskExecutor;)Ljava/util/function/Consumer;
      48: invokevirtual #119                // Method org/springframework/boot/context/properties/PropertyMapper$Source.to:(Ljava/util/function/Consumer;)V
      51: aload_2
      52: aload_0
      53: getfield      #16                 // Field maxPoolSize:Ljava/lang/Integer;
      56: invokevirtual #105                // Method org/springframework/boot/context/properties/PropertyMapper.from:(Ljava/lang/Object;)Lorg/springframework/boot/context/properties/PropertyMapper$Source;
      59: aload_1
      60: dup
      61: invokestatic  #109                // Method java/util/Objects.requireNonNull:(Ljava/lang/Object;)Ljava/lang/Object;
      64: pop
      65: invokedynamic #126,  0            // InvokeDynamic #2:accept:(Lorg/springframework/scheduling/concurrent/ThreadPoolTaskExecutor;)Ljava/util/function/Consumer;
      70: invokevirtual #119                // Method org/springframework/boot/context/properties/PropertyMapper$Source.to:(Ljava/util/function/Consumer;)V
      73: aload_2
      74: aload_0
      75: getfield      #23                 // Field keepAlive:Ljava/time/Duration;
      78: invokevirtual #105                // Method org/springframework/boot/context/properties/PropertyMapper.from:(Ljava/lang/Object;)Lorg/springframework/boot/context/properties/PropertyMapper$Source;
      81: invokedynamic #127,  0            // InvokeDynamic #3:apply:()Ljava/util/function/Function;
      86: invokevirtual #131                // Method org/springframework/boot/context/properties/PropertyMapper$Source.asInt:(Ljava/util/function/Function;)Lorg/springframework/boot/context/properties/PropertyMapper$Source;
      89: aload_1
      90: dup
      91: invokestatic  #109                // Method java/util/Objects.requireNonNull:(Ljava/lang/Object;)Ljava/lang/Object;
      94: pop
      95: invokedynamic #135,  0            // InvokeDynamic #4:accept:(Lorg/springframework/scheduling/concurrent/ThreadPoolTaskExecutor;)Ljava/util/function/Consumer;
     100: invokevirtual #119                // Method org/springframework/boot/context/properties/PropertyMapper$Source.to:(Ljava/util/function/Consumer;)V
     103: aload_2
     104: aload_0
     105: getfield      #19                 // Field allowCoreThreadTimeOut:Ljava/lang/Boolean;
     108: invokevirtual #105                // Method org/springframework/boot/context/properties/PropertyMapper.from:(Ljava/lang/Object;)Lorg/springframework/boot/context/properties/PropertyMapper$Source;
     111: aload_1
     112: dup
     113: invokestatic  #109                // Method java/util/Objects.requireNonNull:(Ljava/lang/Object;)Ljava/lang/Object;
     116: pop
     117: invokedynamic #136,  0            // InvokeDynamic #5:accept:(Lorg/springframework/scheduling/concurrent/ThreadPoolTaskExecutor;)Ljava/util/function/Consumer;
     122: invokevirtual #119                // Method org/springframework/boot/context/properties/PropertyMapper$Source.to:(Ljava/util/function/Consumer;)V
     125: aload_2
     126: aload_0
     127: getfield      #27                 // Field awaitTermination:Ljava/lang/Boolean;
     130: invokevirtual #105                // Method org/springframework/boot/context/properties/PropertyMapper.from:(Ljava/lang/Object;)Lorg/springframework/boot/context/properties/PropertyMapper$Source;
     133: aload_1
     134: dup
     135: invokestatic  #109                // Method java/util/Objects.requireNonNull:(Ljava/lang/Object;)Ljava/lang/Object;
     138: pop
     139: invokedynamic #137,  0            // InvokeDynamic #6:accept:(Lorg/springframework/scheduling/concurrent/ThreadPoolTaskExecutor;)Ljava/util/function/Consumer;
     144: invokevirtual #119                // Method org/springframework/boot/context/properties/PropertyMapper$Source.to:(Ljava/util/function/Consumer;)V
     147: aload_2
     148: aload_0
     149: getfield      #30                 // Field awaitTerminationPeriod:Ljava/time/Duration;
     152: invokevirtual #105                // Method org/springframework/boot/context/properties/PropertyMapper.from:(Ljava/lang/Object;)Lorg/springframework/boot/context/properties/PropertyMapper$Source;
     155: invokedynamic #138,  0            // InvokeDynamic #7:apply:()Ljava/util/function/Function;
     160: invokevirtual #139                // Method org/springframework/boot/context/properties/PropertyMapper$Source.as:(Ljava/util/function/Function;)Lorg/springframework/boot/context/properties/PropertyMapper$Source;
     163: aload_1
     164: dup
     165: invokestatic  #109                // Method java/util/Objects.requireNonNull:(Ljava/lang/Object;)Ljava/lang/Object;
     168: pop
     169: invokedynamic #142,  0            // InvokeDynamic #8:accept:(Lorg/springframework/scheduling/concurrent/ThreadPoolTaskExecutor;)Ljava/util/function/Consumer;
     174: invokevirtual #119                // Method org/springframework/boot/context/properties/PropertyMapper$Source.to:(Ljava/util/function/Consumer;)V
     177: aload_2
     178: aload_0
     179: getfield      #33                 // Field threadNamePrefix:Ljava/lang/String;
     182: invokevirtual #105                // Method org/springframework/boot/context/properties/PropertyMapper.from:(Ljava/lang/Object;)Lorg/springframework/boot/context/properties/PropertyMapper$Source;
     185: invokevirtual #143                // Method org/springframework/boot/context/properties/PropertyMapper$Source.whenHasText:()Lorg/springframework/boot/context/properties/PropertyMapper$Source;
     188: aload_1
     189: dup
     190: invokestatic  #109                // Method java/util/Objects.requireNonNull:(Ljava/lang/Object;)Ljava/lang/Object;
     193: pop
     194: invokedynamic #147,  0            // InvokeDynamic #9:accept:(Lorg/springframework/scheduling/concurrent/ThreadPoolTaskExecutor;)Ljava/util/function/Consumer;
     199: invokevirtual #119                // Method org/springframework/boot/context/properties/PropertyMapper$Source.to:(Ljava/util/function/Consumer;)V
     202: aload_2
     203: aload_0
     204: getfield      #37                 // Field taskDecorator:Lorg/springframework/core/task/TaskDecorator;
     207: invokevirtual #105                // Method org/springframework/boot/context/properties/PropertyMapper.from:(Ljava/lang/Object;)Lorg/springframework/boot/context/properties/PropertyMapper$Source;
     210: aload_1
     211: dup
     212: invokestatic  #109                // Method java/util/Objects.requireNonNull:(Ljava/lang/Object;)Ljava/lang/Object;
     215: pop
     216: invokedynamic #148,  0            // InvokeDynamic #10:accept:(Lorg/springframework/scheduling/concurrent/ThreadPoolTaskExecutor;)Ljava/util/function/Consumer;
     221: invokevirtual #119                // Method org/springframework/boot/context/properties/PropertyMapper$Source.to:(Ljava/util/function/Consumer;)V
     224: aload_0
     225: getfield      #41                 // Field customizers:Ljava/util/Set;
     228: invokestatic  #149                // Method org/springframework/util/CollectionUtils.isEmpty:(Ljava/util/Collection;)Z
     231: ifne          249
     234: aload_0
     235: getfield      #41                 // Field customizers:Ljava/util/Set;
     238: aload_1
     239: invokedynamic #155,  0            // InvokeDynamic #11:accept:(Lorg/springframework/scheduling/concurrent/ThreadPoolTaskExecutor;)Ljava/util/function/Consumer;
     244: invokeinterface #156,  2          // InterfaceMethod java/util/Set.forEach:(Ljava/util/function/Consumer;)V
     249: aload_1
     250: areturn

  private <T> java.util.Set<T> append(java.util.Set<T>, java.lang.Iterable<? extends T>);
    Code:
       0: new           #161                // class java/util/LinkedHashSet
       3: dup
       4: aload_1
       5: ifnull        12
       8: aload_1
       9: goto          15
      12: invokestatic  #163                // Method java/util/Collections.emptySet:()Ljava/util/Set;
      15: invokespecial #169                // Method java/util/LinkedHashSet."<init>":(Ljava/util/Collection;)V
      18: astore_3
      19: aload_2
      20: aload_3
      21: dup
      22: invokestatic  #109                // Method java/util/Objects.requireNonNull:(Ljava/lang/Object;)Ljava/lang/Object;
      25: pop
      26: invokedynamic #172,  0            // InvokeDynamic #12:accept:(Ljava/util/Set;)Ljava/util/function/Consumer;
      31: invokeinterface #175,  2          // InterfaceMethod java/lang/Iterable.forEach:(Ljava/util/function/Consumer;)V
      36: aload_3
      37: invokestatic  #178                // Method java/util/Collections.unmodifiableSet:(Ljava/util/Set;)Ljava/util/Set;
      40: areturn

  private static void lambda$configure$0(org.springframework.scheduling.concurrent.ThreadPoolTaskExecutor, org.springframework.boot.task.TaskExecutorCustomizer);
    Code:
       0: aload_1
       1: aload_0
       2: invokeinterface #182,  2          // InterfaceMethod org/springframework/boot/task/TaskExecutorCustomizer.customize:(Lorg/springframework/scheduling/concurrent/ThreadPoolTaskExecutor;)V
       7: return
}
