Compiled from "FastJsonImpl.java"
public class org.apache.dubbo.common.json.impl.FastJsonImpl extends org.apache.dubbo.common.json.impl.AbstractJSONImpl {
  public org.apache.dubbo.common.json.impl.FastJsonImpl();
    Code:
       0: aload_0
       1: invokespecial #1                  // Method org/apache/dubbo/common/json/impl/AbstractJSONImpl."<init>":()V
       4: return

  public <T> T toJavaObject(java.lang.String, java.lang.reflect.Type);
    Code:
       0: aload_1
       1: aload_2
       2: iconst_0
       3: anewarray     #2                  // class com/alibaba/fastjson/parser/Feature
       6: invokestatic  #3                  // Method com/alibaba/fastjson/JSON.parseObject:(Ljava/lang/String;Ljava/lang/reflect/Type;[Lcom/alibaba/fastjson/parser/Feature;)Ljava/lang/Object;
       9: areturn

  public <T> java.util.List<T> toJavaList(java.lang.String, java.lang.Class<T>);
    Code:
       0: aload_1
       1: aload_2
       2: invokestatic  #4                  // Method com/alibaba/fastjson/JSON.parseArray:(Ljava/lang/String;Ljava/lang/Class;)Ljava/util/List;
       5: areturn

  public java.lang.String toJson(java.lang.Object);
    Code:
       0: aload_1
       1: iconst_1
       2: anewarray     #5                  // class com/alibaba/fastjson/serializer/SerializerFeature
       5: dup
       6: iconst_0
       7: getstatic     #6                  // Field com/alibaba/fastjson/serializer/SerializerFeature.DisableCircularReferenceDetect:Lcom/alibaba/fastjson/serializer/SerializerFeature;
      10: aastore
      11: invokestatic  #7                  // Method com/alibaba/fastjson/JSON.toJSONString:(Ljava/lang/Object;[Lcom/alibaba/fastjson/serializer/SerializerFeature;)Ljava/lang/String;
      14: areturn
}
