Compiled from "GsonImpl.java"
public class org.apache.dubbo.common.json.impl.GsonImpl extends org.apache.dubbo.common.json.impl.AbstractJSONImpl {
  private volatile java.lang.Object gsonCache;

  public org.apache.dubbo.common.json.impl.GsonImpl();
    Code:
       0: aload_0
       1: invokespecial #1                  // Method org/apache/dubbo/common/json/impl/AbstractJSONImpl."<init>":()V
       4: aload_0
       5: aconst_null
       6: putfield      #2                  // Field gsonCache:Ljava/lang/Object;
       9: return

  public <T> T toJavaObject(java.lang.String, java.lang.reflect.Type);
    Code:
       0: aload_0
       1: invokespecial #3                  // Method getGson:()Lcom/google/gson/Gson;
       4: aload_1
       5: aload_2
       6: invokevirtual #4                  // Method com/google/gson/Gson.fromJson:(Ljava/lang/String;Ljava/lang/reflect/Type;)Ljava/lang/Object;
       9: areturn

  public <T> java.util.List<T> toJavaList(java.lang.String, java.lang.Class<T>);
    Code:
       0: aload_0
       1: invokespecial #3                  // Method getGson:()Lcom/google/gson/Gson;
       4: aload_1
       5: ldc           #5                  // class java/util/List
       7: iconst_1
       8: anewarray     #6                  // class java/lang/reflect/Type
      11: dup
      12: iconst_0
      13: aload_2
      14: aastore
      15: invokestatic  #7                  // Method com/google/gson/reflect/TypeToken.getParameterized:(Ljava/lang/reflect/Type;[Ljava/lang/reflect/Type;)Lcom/google/gson/reflect/TypeToken;
      18: invokevirtual #8                  // Method com/google/gson/reflect/TypeToken.getType:()Ljava/lang/reflect/Type;
      21: invokevirtual #4                  // Method com/google/gson/Gson.fromJson:(Ljava/lang/String;Ljava/lang/reflect/Type;)Ljava/lang/Object;
      24: checkcast     #5                  // class java/util/List
      27: areturn

  public java.lang.String toJson(java.lang.Object);
    Code:
       0: aload_0
       1: invokespecial #3                  // Method getGson:()Lcom/google/gson/Gson;
       4: aload_1
       5: invokevirtual #9                  // Method com/google/gson/Gson.toJson:(Ljava/lang/Object;)Ljava/lang/String;
       8: areturn

  private com.google.gson.Gson getGson();
    Code:
       0: aload_0
       1: getfield      #2                  // Field gsonCache:Ljava/lang/Object;
       4: ifnull        17
       7: aload_0
       8: getfield      #2                  // Field gsonCache:Ljava/lang/Object;
      11: instanceof    #10                 // class com/google/gson/Gson
      14: ifne          59
      17: aload_0
      18: dup
      19: astore_1
      20: monitorenter
      21: aload_0
      22: getfield      #2                  // Field gsonCache:Ljava/lang/Object;
      25: ifnull        38
      28: aload_0
      29: getfield      #2                  // Field gsonCache:Ljava/lang/Object;
      32: instanceof    #10                 // class com/google/gson/Gson
      35: ifne          49
      38: aload_0
      39: new           #10                 // class com/google/gson/Gson
      42: dup
      43: invokespecial #11                 // Method com/google/gson/Gson."<init>":()V
      46: putfield      #2                  // Field gsonCache:Ljava/lang/Object;
      49: aload_1
      50: monitorexit
      51: goto          59
      54: astore_2
      55: aload_1
      56: monitorexit
      57: aload_2
      58: athrow
      59: aload_0
      60: getfield      #2                  // Field gsonCache:Ljava/lang/Object;
      63: checkcast     #10                 // class com/google/gson/Gson
      66: areturn
    Exception table:
       from    to  target type
          21    51    54   any
          54    57    54   any
}
