Compiled from "JacksonImpl.java"
public class org.apache.dubbo.common.json.impl.JacksonImpl extends org.apache.dubbo.common.json.impl.AbstractJSONImpl {
  private final com.fasterxml.jackson.databind.ObjectMapper objectMapper;

  private volatile java.lang.Object jacksonCache;

  public org.apache.dubbo.common.json.impl.JacksonImpl();
    Code:
       0: aload_0
       1: invokespecial #1                  // Method org/apache/dubbo/common/json/impl/AbstractJSONImpl."<init>":()V
       4: aload_0
       5: new           #2                  // class com/fasterxml/jackson/databind/ObjectMapper
       8: dup
       9: invokespecial #3                  // Method com/fasterxml/jackson/databind/ObjectMapper."<init>":()V
      12: putfield      #4                  // Field objectMapper:Lcom/fasterxml/jackson/databind/ObjectMapper;
      15: aload_0
      16: aconst_null
      17: putfield      #5                  // Field jacksonCache:Ljava/lang/Object;
      20: return

  public <T> T toJavaObject(java.lang.String, java.lang.reflect.Type);
    Code:
       0: aload_0
       1: invokespecial #6                  // Method getJackson:()Lcom/fasterxml/jackson/databind/json/JsonMapper;
       4: aload_1
       5: aload_0
       6: invokespecial #6                  // Method getJackson:()Lcom/fasterxml/jackson/databind/json/JsonMapper;
       9: invokevirtual #7                  // Method com/fasterxml/jackson/databind/json/JsonMapper.getTypeFactory:()Lcom/fasterxml/jackson/databind/type/TypeFactory;
      12: aload_2
      13: invokevirtual #8                  // Method com/fasterxml/jackson/databind/type/TypeFactory.constructType:(Ljava/lang/reflect/Type;)Lcom/fasterxml/jackson/databind/JavaType;
      16: invokevirtual #9                  // Method com/fasterxml/jackson/databind/json/JsonMapper.readValue:(Ljava/lang/String;Lcom/fasterxml/jackson/databind/JavaType;)Ljava/lang/Object;
      19: areturn
      20: astore_3
      21: new           #11                 // class java/lang/IllegalArgumentException
      24: dup
      25: aload_3
      26: invokespecial #12                 // Method java/lang/IllegalArgumentException."<init>":(Ljava/lang/Throwable;)V
      29: athrow
    Exception table:
       from    to  target type
           0    19    20   Class com/fasterxml/jackson/core/JsonProcessingException

  public <T> java.util.List<T> toJavaList(java.lang.String, java.lang.Class<T>);
    Code:
       0: aload_0
       1: invokespecial #6                  // Method getJackson:()Lcom/fasterxml/jackson/databind/json/JsonMapper;
       4: aload_1
       5: aload_0
       6: invokespecial #6                  // Method getJackson:()Lcom/fasterxml/jackson/databind/json/JsonMapper;
       9: invokevirtual #7                  // Method com/fasterxml/jackson/databind/json/JsonMapper.getTypeFactory:()Lcom/fasterxml/jackson/databind/type/TypeFactory;
      12: ldc           #13                 // class java/util/List
      14: aload_2
      15: invokevirtual #14                 // Method com/fasterxml/jackson/databind/type/TypeFactory.constructCollectionType:(Ljava/lang/Class;Ljava/lang/Class;)Lcom/fasterxml/jackson/databind/type/CollectionType;
      18: invokevirtual #9                  // Method com/fasterxml/jackson/databind/json/JsonMapper.readValue:(Ljava/lang/String;Lcom/fasterxml/jackson/databind/JavaType;)Ljava/lang/Object;
      21: checkcast     #13                 // class java/util/List
      24: areturn
      25: astore_3
      26: new           #11                 // class java/lang/IllegalArgumentException
      29: dup
      30: aload_3
      31: invokespecial #12                 // Method java/lang/IllegalArgumentException."<init>":(Ljava/lang/Throwable;)V
      34: athrow
    Exception table:
       from    to  target type
           0    24    25   Class com/fasterxml/jackson/core/JsonProcessingException

  public java.lang.String toJson(java.lang.Object);
    Code:
       0: aload_0
       1: invokespecial #6                  // Method getJackson:()Lcom/fasterxml/jackson/databind/json/JsonMapper;
       4: aload_1
       5: invokevirtual #15                 // Method com/fasterxml/jackson/databind/json/JsonMapper.writeValueAsString:(Ljava/lang/Object;)Ljava/lang/String;
       8: areturn
       9: astore_2
      10: new           #11                 // class java/lang/IllegalArgumentException
      13: dup
      14: aload_2
      15: invokespecial #12                 // Method java/lang/IllegalArgumentException."<init>":(Ljava/lang/Throwable;)V
      18: athrow
    Exception table:
       from    to  target type
           0     8     9   Class com/fasterxml/jackson/core/JsonProcessingException

  private com.fasterxml.jackson.databind.json.JsonMapper getJackson();
    Code:
       0: aload_0
       1: getfield      #5                  // Field jacksonCache:Ljava/lang/Object;
       4: ifnull        17
       7: aload_0
       8: getfield      #5                  // Field jacksonCache:Ljava/lang/Object;
      11: instanceof    #16                 // class com/fasterxml/jackson/databind/json/JsonMapper
      14: ifne          90
      17: aload_0
      18: dup
      19: astore_1
      20: monitorenter
      21: aload_0
      22: getfield      #5                  // Field jacksonCache:Ljava/lang/Object;
      25: ifnull        38
      28: aload_0
      29: getfield      #5                  // Field jacksonCache:Ljava/lang/Object;
      32: instanceof    #16                 // class com/fasterxml/jackson/databind/json/JsonMapper
      35: ifne          80
      38: aload_0
      39: invokestatic  #17                 // Method com/fasterxml/jackson/databind/json/JsonMapper.builder:()Lcom/fasterxml/jackson/databind/json/JsonMapper$Builder;
      42: getstatic     #18                 // Field com/fasterxml/jackson/databind/MapperFeature.PROPAGATE_TRANSIENT_MARKER:Lcom/fasterxml/jackson/databind/MapperFeature;
      45: iconst_1
      46: invokevirtual #19                 // Method com/fasterxml/jackson/databind/json/JsonMapper$Builder.configure:(Lcom/fasterxml/jackson/databind/MapperFeature;Z)Lcom/fasterxml/jackson/databind/cfg/MapperBuilder;
      49: checkcast     #20                 // class com/fasterxml/jackson/databind/json/JsonMapper$Builder
      52: getstatic     #21                 // Field com/fasterxml/jackson/annotation/JsonInclude$Include.NON_NULL:Lcom/fasterxml/jackson/annotation/JsonInclude$Include;
      55: invokevirtual #22                 // Method com/fasterxml/jackson/databind/json/JsonMapper$Builder.serializationInclusion:(Lcom/fasterxml/jackson/annotation/JsonInclude$Include;)Lcom/fasterxml/jackson/databind/cfg/MapperBuilder;
      58: checkcast     #20                 // class com/fasterxml/jackson/databind/json/JsonMapper$Builder
      61: new           #23                 // class com/fasterxml/jackson/datatype/jsr310/JavaTimeModule
      64: dup
      65: invokespecial #24                 // Method com/fasterxml/jackson/datatype/jsr310/JavaTimeModule."<init>":()V
      68: invokevirtual #25                 // Method com/fasterxml/jackson/databind/json/JsonMapper$Builder.addModule:(Lcom/fasterxml/jackson/databind/Module;)Lcom/fasterxml/jackson/databind/cfg/MapperBuilder;
      71: checkcast     #20                 // class com/fasterxml/jackson/databind/json/JsonMapper$Builder
      74: invokevirtual #26                 // Method com/fasterxml/jackson/databind/json/JsonMapper$Builder.build:()Lcom/fasterxml/jackson/databind/ObjectMapper;
      77: putfield      #5                  // Field jacksonCache:Ljava/lang/Object;
      80: aload_1
      81: monitorexit
      82: goto          90
      85: astore_2
      86: aload_1
      87: monitorexit
      88: aload_2
      89: athrow
      90: aload_0
      91: getfield      #5                  // Field jacksonCache:Ljava/lang/Object;
      94: checkcast     #16                 // class com/fasterxml/jackson/databind/json/JsonMapper
      97: areturn
    Exception table:
       from    to  target type
          21    82    85   any
          85    88    85   any
}
