Compiled from "SecurityScopeModelInitializer.java"
public class org.apache.dubbo.spring.security.model.SecurityScopeModelInitializer implements org.apache.dubbo.rpc.model.ScopeModelInitializer {
  public org.apache.dubbo.spring.security.model.SecurityScopeModelInitializer();
    Code:
       0: aload_0
       1: invokespecial #1                  // Method java/lang/Object."<init>":()V
       4: return

  public void initializeFrameworkModel(org.apache.dubbo.rpc.model.FrameworkModel);
    Code:
       0: aload_1
       1: invokevirtual #2                  // Method org/apache/dubbo/rpc/model/FrameworkModel.getBeanFactory:()Lorg/apache/dubbo/common/beans/factory/ScopeBeanFactory;
       4: astore_2
       5: aload_2
       6: ldc           #3                  // class org/apache/dubbo/spring/security/jackson/ObjectMapperCodec
       8: invokevirtual #4                  // Method org/apache/dubbo/common/beans/factory/ScopeBeanFactory.getOrRegisterBean:(Ljava/lang/Class;)Ljava/lang/Object;
      11: checkcast     #3                  // class org/apache/dubbo/spring/security/jackson/ObjectMapperCodec
      14: astore_3
      15: aload_1
      16: ldc           #5                  // class org/apache/dubbo/spring/security/jackson/ObjectMapperCodecCustomer
      18: invokevirtual #6                  // Method org/apache/dubbo/rpc/model/FrameworkModel.getExtensionLoader:(Ljava/lang/Class;)Lorg/apache/dubbo/common/extension/ExtensionLoader;
      21: invokevirtual #7                  // Method org/apache/dubbo/common/extension/ExtensionLoader.getSupportedExtensionInstances:()Ljava/util/Set;
      24: astore        4
      26: aload         4
      28: invokeinterface #8,  1            // InterfaceMethod java/util/Set.iterator:()Ljava/util/Iterator;
      33: astore        5
      35: aload         5
      37: invokeinterface #9,  1            // InterfaceMethod java/util/Iterator.hasNext:()Z
      42: ifeq          68
      45: aload         5
      47: invokeinterface #10,  1           // InterfaceMethod java/util/Iterator.next:()Ljava/lang/Object;
      52: checkcast     #5                  // class org/apache/dubbo/spring/security/jackson/ObjectMapperCodecCustomer
      55: astore        6
      57: aload         6
      59: aload_3
      60: invokeinterface #11,  2           // InterfaceMethod org/apache/dubbo/spring/security/jackson/ObjectMapperCodecCustomer.customize:(Lorg/apache/dubbo/spring/security/jackson/ObjectMapperCodec;)V
      65: goto          35
      68: return

  public void initializeApplicationModel(org.apache.dubbo.rpc.model.ApplicationModel);
    Code:
       0: return

  public void initializeModuleModel(org.apache.dubbo.rpc.model.ModuleModel);
    Code:
       0: return
}
