Compiled from "Prioritized.java"
public interface org.apache.dubbo.common.lang.Prioritized extends java.lang.Comparable<org.apache.dubbo.common.lang.Prioritized> {
  public static final java.util.Comparator<java.lang.Object> COMPARATOR;

  public static final int MAX_PRIORITY;

  public static final int MIN_PRIORITY;

  public static final int NORMAL_PRIORITY;

  public default int getPriority();
    Code:
       0: iconst_0
       1: ireturn

  public default int compareTo(org.apache.dubbo.common.lang.Prioritized);
    Code:
       0: aload_0
       1: invokeinterface #3,  1            // InterfaceMethod getPriority:()I
       6: aload_1
       7: invokeinterface #3,  1            // InterfaceMethod getPriority:()I
      12: invokestatic  #4                  // Method java/lang/Integer.compare:(II)I
      15: ireturn

  public default int compareTo(java.lang.Object);
    Code:
       0: aload_0
       1: aload_1
       2: checkcast     #2                  // class org/apache/dubbo/common/lang/Prioritized
       5: invokeinterface #5,  2            // InterfaceMethod compareTo:(Lorg/apache/dubbo/common/lang/Prioritized;)I
      10: ireturn

  private static int lambda$static$0(java.lang.Object, java.lang.Object);
    Code:
       0: aload_0
       1: instanceof    #2                  // class org/apache/dubbo/common/lang/Prioritized
       4: istore_2
       5: aload_1
       6: instanceof    #2                  // class org/apache/dubbo/common/lang/Prioritized
       9: istore_3
      10: iload_2
      11: ifeq          20
      14: iload_3
      15: ifne          20
      18: iconst_m1
      19: ireturn
      20: iload_3
      21: ifeq          30
      24: iload_2
      25: ifne          30
      28: iconst_1
      29: ireturn
      30: iload_2
      31: ifeq          52
      34: iload_3
      35: ifeq          52
      38: aload_0
      39: checkcast     #2                  // class org/apache/dubbo/common/lang/Prioritized
      42: aload_1
      43: checkcast     #2                  // class org/apache/dubbo/common/lang/Prioritized
      46: invokeinterface #5,  2            // InterfaceMethod compareTo:(Lorg/apache/dubbo/common/lang/Prioritized;)I
      51: ireturn
      52: iconst_0
      53: ireturn

  static {};
    Code:
       0: invokedynamic #6,  0              // InvokeDynamic #0:compare:()Ljava/util/Comparator;
       5: putstatic     #7                  // Field COMPARATOR:Ljava/util/Comparator;
       8: return
}
