Compiled from "ShutdownHookCallbacks.java"
public class org.apache.dubbo.common.lang.ShutdownHookCallbacks implements org.apache.dubbo.common.resource.Disposable {
  private final java.util.List<org.apache.dubbo.common.lang.ShutdownHookCallback> callbacks;

  private final org.apache.dubbo.rpc.model.ApplicationModel applicationModel;

  public org.apache.dubbo.common.lang.ShutdownHookCallbacks(org.apache.dubbo.rpc.model.ApplicationModel);
    Code:
       0: aload_0
       1: invokespecial #1                  // Method java/lang/Object."<init>":()V
       4: aload_0
       5: new           #2                  // class java/util/LinkedList
       8: dup
       9: invokespecial #3                  // Method java/util/LinkedList."<init>":()V
      12: putfield      #4                  // Field callbacks:Ljava/util/List;
      15: aload_0
      16: aload_1
      17: putfield      #5                  // Field applicationModel:Lorg/apache/dubbo/rpc/model/ApplicationModel;
      20: aload_0
      21: invokespecial #6                  // Method loadCallbacks:()V
      24: return

  public org.apache.dubbo.common.lang.ShutdownHookCallbacks addCallback(org.apache.dubbo.common.lang.ShutdownHookCallback);
    Code:
       0: aload_0
       1: dup
       2: astore_2
       3: monitorenter
       4: aload_0
       5: getfield      #4                  // Field callbacks:Ljava/util/List;
       8: aload_1
       9: invokeinterface #7,  2            // InterfaceMethod java/util/List.contains:(Ljava/lang/Object;)Z
      14: ifne          28
      17: aload_0
      18: getfield      #4                  // Field callbacks:Ljava/util/List;
      21: aload_1
      22: invokeinterface #8,  2            // InterfaceMethod java/util/List.add:(Ljava/lang/Object;)Z
      27: pop
      28: aload_2
      29: monitorexit
      30: goto          38
      33: astore_3
      34: aload_2
      35: monitorexit
      36: aload_3
      37: athrow
      38: aload_0
      39: areturn
    Exception table:
       from    to  target type
           4    30    33   any
          33    36    33   any

  public java.util.Collection<org.apache.dubbo.common.lang.ShutdownHookCallback> getCallbacks();
    Code:
       0: aload_0
       1: dup
       2: astore_1
       3: monitorenter
       4: aload_0
       5: getfield      #4                  // Field callbacks:Ljava/util/List;
       8: invokestatic  #9                  // Method java/util/Collections.sort:(Ljava/util/List;)V
      11: aload_0
      12: getfield      #4                  // Field callbacks:Ljava/util/List;
      15: aload_1
      16: monitorexit
      17: areturn
      18: astore_2
      19: aload_1
      20: monitorexit
      21: aload_2
      22: athrow
    Exception table:
       from    to  target type
           4    17    18   any
          18    21    18   any

  public void destroy();
    Code:
       0: aload_0
       1: dup
       2: astore_1
       3: monitorenter
       4: aload_0
       5: getfield      #4                  // Field callbacks:Ljava/util/List;
       8: invokeinterface #10,  1           // InterfaceMethod java/util/List.clear:()V
      13: aload_1
      14: monitorexit
      15: goto          23
      18: astore_2
      19: aload_1
      20: monitorexit
      21: aload_2
      22: athrow
      23: return
    Exception table:
       from    to  target type
           4    15    18   any
          18    21    18   any

  private void loadCallbacks();
    Code:
       0: aload_0
       1: getfield      #5                  // Field applicationModel:Lorg/apache/dubbo/rpc/model/ApplicationModel;
       4: ldc           #11                 // class org/apache/dubbo/common/lang/ShutdownHookCallback
       6: invokevirtual #12                 // Method org/apache/dubbo/rpc/model/ApplicationModel.getExtensionLoader:(Ljava/lang/Class;)Lorg/apache/dubbo/common/extension/ExtensionLoader;
       9: astore_1
      10: aload_1
      11: invokevirtual #13                 // Method org/apache/dubbo/common/extension/ExtensionLoader.getSupportedExtensionInstances:()Ljava/util/Set;
      14: aload_0
      15: invokedynamic #14,  0             // InvokeDynamic #0:accept:(Lorg/apache/dubbo/common/lang/ShutdownHookCallbacks;)Ljava/util/function/Consumer;
      20: invokeinterface #15,  2           // InterfaceMethod java/util/Set.forEach:(Ljava/util/function/Consumer;)V
      25: return

  public void callback();
    Code:
       0: aload_0
       1: invokevirtual #16                 // Method getCallbacks:()Ljava/util/Collection;
       4: invokedynamic #17,  0             // InvokeDynamic #1:accept:()Ljava/util/function/Consumer;
       9: invokeinterface #18,  2           // InterfaceMethod java/util/Collection.forEach:(Ljava/util/function/Consumer;)V
      14: return

  private static void lambda$callback$0(org.apache.dubbo.common.lang.ShutdownHookCallback);
    Code:
       0: aload_0
       1: dup
       2: invokevirtual #19                 // Method java/lang/Object.getClass:()Ljava/lang/Class;
       5: pop
       6: invokedynamic #20,  0             // InvokeDynamic #2:execute:(Lorg/apache/dubbo/common/lang/ShutdownHookCallback;)Lorg/apache/dubbo/common/function/ThrowableAction;
      11: invokestatic  #21                 // InterfaceMethod org/apache/dubbo/common/function/ThrowableAction.execute:(Lorg/apache/dubbo/common/function/ThrowableAction;)V
      14: return
}
