Compiled from "DefaultErrorAttributes.java"
public class org.springframework.boot.web.servlet.error.DefaultErrorAttributes implements org.springframework.boot.web.servlet.error.ErrorAttributes,org.springframework.web.servlet.HandlerExceptionResolver,org.springframework.core.Ordered {
  private static final java.lang.String ERROR_INTERNAL_ATTRIBUTE;

  public org.springframework.boot.web.servlet.error.DefaultErrorAttributes();
    Code:
       0: aload_0
       1: invokespecial #1                  // Method java/lang/Object."<init>":()V
       4: return

  public int getOrder();
    Code:
       0: ldc           #9                  // int -2147483648
       2: ireturn

  public org.springframework.web.servlet.ModelAndView resolveException(jakarta.servlet.http.HttpServletRequest, jakarta.servlet.http.HttpServletResponse, java.lang.Object, java.lang.Exception);
    Code:
       0: aload_0
       1: aload_1
       2: aload         4
       4: invokevirtual #10                 // Method storeErrorAttributes:(Ljakarta/servlet/http/HttpServletRequest;Ljava/lang/Exception;)V
       7: aconst_null
       8: areturn

  private void storeErrorAttributes(jakarta.servlet.http.HttpServletRequest, java.lang.Exception);
    Code:
       0: aload_1
       1: getstatic     #16                 // Field ERROR_INTERNAL_ATTRIBUTE:Ljava/lang/String;
       4: aload_2
       5: invokeinterface #20,  3           // InterfaceMethod jakarta/servlet/http/HttpServletRequest.setAttribute:(Ljava/lang/String;Ljava/lang/Object;)V
      10: return

  public java.util.Map<java.lang.String, java.lang.Object> getErrorAttributes(org.springframework.web.context.request.WebRequest, org.springframework.boot.web.error.ErrorAttributeOptions);
    Code:
       0: aload_0
       1: aload_1
       2: aload_2
       3: getstatic     #26                 // Field org/springframework/boot/web/error/ErrorAttributeOptions$Include.STACK_TRACE:Lorg/springframework/boot/web/error/ErrorAttributeOptions$Include;
       6: invokevirtual #32                 // Method org/springframework/boot/web/error/ErrorAttributeOptions.isIncluded:(Lorg/springframework/boot/web/error/ErrorAttributeOptions$Include;)Z
       9: invokevirtual #38                 // Method getErrorAttributes:(Lorg/springframework/web/context/request/WebRequest;Z)Ljava/util/Map;
      12: astore_3
      13: aload_2
      14: getstatic     #42                 // Field org/springframework/boot/web/error/ErrorAttributeOptions$Include.EXCEPTION:Lorg/springframework/boot/web/error/ErrorAttributeOptions$Include;
      17: invokevirtual #32                 // Method org/springframework/boot/web/error/ErrorAttributeOptions.isIncluded:(Lorg/springframework/boot/web/error/ErrorAttributeOptions$Include;)Z
      20: ifne          32
      23: aload_3
      24: ldc           #45                 // String exception
      26: invokeinterface #47,  2           // InterfaceMethod java/util/Map.remove:(Ljava/lang/Object;)Ljava/lang/Object;
      31: pop
      32: aload_2
      33: getstatic     #26                 // Field org/springframework/boot/web/error/ErrorAttributeOptions$Include.STACK_TRACE:Lorg/springframework/boot/web/error/ErrorAttributeOptions$Include;
      36: invokevirtual #32                 // Method org/springframework/boot/web/error/ErrorAttributeOptions.isIncluded:(Lorg/springframework/boot/web/error/ErrorAttributeOptions$Include;)Z
      39: ifne          51
      42: aload_3
      43: ldc           #53                 // String trace
      45: invokeinterface #47,  2           // InterfaceMethod java/util/Map.remove:(Ljava/lang/Object;)Ljava/lang/Object;
      50: pop
      51: aload_2
      52: getstatic     #55                 // Field org/springframework/boot/web/error/ErrorAttributeOptions$Include.MESSAGE:Lorg/springframework/boot/web/error/ErrorAttributeOptions$Include;
      55: invokevirtual #32                 // Method org/springframework/boot/web/error/ErrorAttributeOptions.isIncluded:(Lorg/springframework/boot/web/error/ErrorAttributeOptions$Include;)Z
      58: ifne          81
      61: aload_3
      62: ldc           #58                 // String message
      64: invokeinterface #60,  2           // InterfaceMethod java/util/Map.get:(Ljava/lang/Object;)Ljava/lang/Object;
      69: ifnull        81
      72: aload_3
      73: ldc           #58                 // String message
      75: invokeinterface #47,  2           // InterfaceMethod java/util/Map.remove:(Ljava/lang/Object;)Ljava/lang/Object;
      80: pop
      81: aload_2
      82: getstatic     #63                 // Field org/springframework/boot/web/error/ErrorAttributeOptions$Include.BINDING_ERRORS:Lorg/springframework/boot/web/error/ErrorAttributeOptions$Include;
      85: invokevirtual #32                 // Method org/springframework/boot/web/error/ErrorAttributeOptions.isIncluded:(Lorg/springframework/boot/web/error/ErrorAttributeOptions$Include;)Z
      88: ifne          100
      91: aload_3
      92: ldc           #66                 // String errors
      94: invokeinterface #47,  2           // InterfaceMethod java/util/Map.remove:(Ljava/lang/Object;)Ljava/lang/Object;
      99: pop
     100: aload_3
     101: areturn

  private java.util.Map<java.lang.String, java.lang.Object> getErrorAttributes(org.springframework.web.context.request.WebRequest, boolean);
    Code:
       0: new           #68                 // class java/util/LinkedHashMap
       3: dup
       4: invokespecial #70                 // Method java/util/LinkedHashMap."<init>":()V
       7: astore_3
       8: aload_3
       9: ldc           #71                 // String timestamp
      11: new           #73                 // class java/util/Date
      14: dup
      15: invokespecial #75                 // Method java/util/Date."<init>":()V
      18: invokeinterface #76,  3           // InterfaceMethod java/util/Map.put:(Ljava/lang/Object;Ljava/lang/Object;)Ljava/lang/Object;
      23: pop
      24: aload_0
      25: aload_3
      26: aload_1
      27: invokevirtual #80                 // Method addStatus:(Ljava/util/Map;Lorg/springframework/web/context/request/RequestAttributes;)V
      30: aload_0
      31: aload_3
      32: aload_1
      33: iload_2
      34: invokevirtual #84                 // Method addErrorDetails:(Ljava/util/Map;Lorg/springframework/web/context/request/WebRequest;Z)V
      37: aload_0
      38: aload_3
      39: aload_1
      40: invokevirtual #88                 // Method addPath:(Ljava/util/Map;Lorg/springframework/web/context/request/RequestAttributes;)V
      43: aload_3
      44: areturn

  private void addStatus(java.util.Map<java.lang.String, java.lang.Object>, org.springframework.web.context.request.RequestAttributes);
    Code:
       0: aload_0
       1: aload_2
       2: ldc           #93                 // String jakarta.servlet.error.status_code
       4: invokevirtual #95                 // Method getAttribute:(Lorg/springframework/web/context/request/RequestAttributes;Ljava/lang/String;)Ljava/lang/Object;
       7: checkcast     #99                 // class java/lang/Integer
      10: astore_3
      11: aload_3
      12: ifnonnull     42
      15: aload_1
      16: ldc           #101                // String status
      18: sipush        999
      21: invokestatic  #103                // Method java/lang/Integer.valueOf:(I)Ljava/lang/Integer;
      24: invokeinterface #76,  3           // InterfaceMethod java/util/Map.put:(Ljava/lang/Object;Ljava/lang/Object;)Ljava/lang/Object;
      29: pop
      30: aload_1
      31: ldc           #107                // String error
      33: ldc           #109                // String None
      35: invokeinterface #76,  3           // InterfaceMethod java/util/Map.put:(Ljava/lang/Object;Ljava/lang/Object;)Ljava/lang/Object;
      40: pop
      41: return
      42: aload_1
      43: ldc           #101                // String status
      45: aload_3
      46: invokeinterface #76,  3           // InterfaceMethod java/util/Map.put:(Ljava/lang/Object;Ljava/lang/Object;)Ljava/lang/Object;
      51: pop
      52: aload_1
      53: ldc           #107                // String error
      55: aload_3
      56: invokevirtual #111                // Method java/lang/Integer.intValue:()I
      59: invokestatic  #115                // Method org/springframework/http/HttpStatus.valueOf:(I)Lorg/springframework/http/HttpStatus;
      62: invokevirtual #120                // Method org/springframework/http/HttpStatus.getReasonPhrase:()Ljava/lang/String;
      65: invokeinterface #76,  3           // InterfaceMethod java/util/Map.put:(Ljava/lang/Object;Ljava/lang/Object;)Ljava/lang/Object;
      70: pop
      71: goto          91
      74: astore        4
      76: aload_1
      77: ldc           #107                // String error
      79: aload_3
      80: invokedynamic #126,  0            // InvokeDynamic #0:makeConcatWithConstants:(Ljava/lang/Integer;)Ljava/lang/String;
      85: invokeinterface #76,  3           // InterfaceMethod java/util/Map.put:(Ljava/lang/Object;Ljava/lang/Object;)Ljava/lang/Object;
      90: pop
      91: return
    Exception table:
       from    to  target type
          52    71    74   Class java/lang/Exception

  private void addErrorDetails(java.util.Map<java.lang.String, java.lang.Object>, org.springframework.web.context.request.WebRequest, boolean);
    Code:
       0: aload_0
       1: aload_2
       2: invokevirtual #130                // Method getError:(Lorg/springframework/web/context/request/WebRequest;)Ljava/lang/Throwable;
       5: astore        4
       7: aload         4
       9: ifnull        66
      12: aload         4
      14: instanceof    #134                // class jakarta/servlet/ServletException
      17: ifeq          38
      20: aload         4
      22: invokevirtual #136                // Method java/lang/Throwable.getCause:()Ljava/lang/Throwable;
      25: ifnull        38
      28: aload         4
      30: invokevirtual #136                // Method java/lang/Throwable.getCause:()Ljava/lang/Throwable;
      33: astore        4
      35: goto          12
      38: aload_1
      39: ldc           #45                 // String exception
      41: aload         4
      43: invokevirtual #142                // Method java/lang/Object.getClass:()Ljava/lang/Class;
      46: invokevirtual #146                // Method java/lang/Class.getName:()Ljava/lang/String;
      49: invokeinterface #76,  3           // InterfaceMethod java/util/Map.put:(Ljava/lang/Object;Ljava/lang/Object;)Ljava/lang/Object;
      54: pop
      55: iload_3
      56: ifeq          66
      59: aload_0
      60: aload_1
      61: aload         4
      63: invokevirtual #151                // Method addStackTrace:(Ljava/util/Map;Ljava/lang/Throwable;)V
      66: aload_0
      67: aload_1
      68: aload_2
      69: aload         4
      71: invokevirtual #155                // Method addErrorMessage:(Ljava/util/Map;Lorg/springframework/web/context/request/WebRequest;Ljava/lang/Throwable;)V
      74: return

  private void addErrorMessage(java.util.Map<java.lang.String, java.lang.Object>, org.springframework.web.context.request.WebRequest, java.lang.Throwable);
    Code:
       0: aload_0
       1: aload_3
       2: invokevirtual #159                // Method extractBindingResult:(Ljava/lang/Throwable;)Lorg/springframework/validation/BindingResult;
       5: astore        4
       7: aload         4
       9: ifnonnull     22
      12: aload_0
      13: aload_1
      14: aload_2
      15: aload_3
      16: invokevirtual #163                // Method addExceptionErrorMessage:(Ljava/util/Map;Lorg/springframework/web/context/request/WebRequest;Ljava/lang/Throwable;)V
      19: goto          29
      22: aload_0
      23: aload_1
      24: aload         4
      26: invokevirtual #166                // Method addBindingResultErrorMessage:(Ljava/util/Map;Lorg/springframework/validation/BindingResult;)V
      29: return

  private void addExceptionErrorMessage(java.util.Map<java.lang.String, java.lang.Object>, org.springframework.web.context.request.WebRequest, java.lang.Throwable);
    Code:
       0: aload_1
       1: ldc           #58                 // String message
       3: aload_0
       4: aload_2
       5: aload_3
       6: invokevirtual #170                // Method getMessage:(Lorg/springframework/web/context/request/WebRequest;Ljava/lang/Throwable;)Ljava/lang/String;
       9: invokeinterface #76,  3           // InterfaceMethod java/util/Map.put:(Ljava/lang/Object;Ljava/lang/Object;)Ljava/lang/Object;
      14: pop
      15: return

  protected java.lang.String getMessage(org.springframework.web.context.request.WebRequest, java.lang.Throwable);
    Code:
       0: aload_0
       1: aload_1
       2: ldc           #174                // String jakarta.servlet.error.message
       4: invokevirtual #95                 // Method getAttribute:(Lorg/springframework/web/context/request/RequestAttributes;Ljava/lang/String;)Ljava/lang/Object;
       7: astore_3
       8: aload_3
       9: invokestatic  #176                // Method org/springframework/util/ObjectUtils.isEmpty:(Ljava/lang/Object;)Z
      12: ifne          20
      15: aload_3
      16: invokevirtual #182                // Method java/lang/Object.toString:()Ljava/lang/String;
      19: areturn
      20: aload_2
      21: ifnull        39
      24: aload_2
      25: invokevirtual #185                // Method java/lang/Throwable.getMessage:()Ljava/lang/String;
      28: invokestatic  #187                // Method org/springframework/util/StringUtils.hasLength:(Ljava/lang/String;)Z
      31: ifeq          39
      34: aload_2
      35: invokevirtual #185                // Method java/lang/Throwable.getMessage:()Ljava/lang/String;
      38: areturn
      39: ldc           #193                // String No message available
      41: areturn

  private void addBindingResultErrorMessage(java.util.Map<java.lang.String, java.lang.Object>, org.springframework.validation.BindingResult);
    Code:
       0: aload_1
       1: ldc           #58                 // String message
       3: aload_2
       4: invokeinterface #195,  1          // InterfaceMethod org/springframework/validation/BindingResult.getObjectName:()Ljava/lang/String;
       9: aload_2
      10: invokeinterface #200,  1          // InterfaceMethod org/springframework/validation/BindingResult.getErrorCount:()I
      15: invokedynamic #203,  0            // InvokeDynamic #1:makeConcatWithConstants:(Ljava/lang/String;I)Ljava/lang/String;
      20: invokeinterface #76,  3           // InterfaceMethod java/util/Map.put:(Ljava/lang/Object;Ljava/lang/Object;)Ljava/lang/Object;
      25: pop
      26: aload_1
      27: ldc           #66                 // String errors
      29: aload_2
      30: invokeinterface #206,  1          // InterfaceMethod org/springframework/validation/BindingResult.getAllErrors:()Ljava/util/List;
      35: invokeinterface #76,  3           // InterfaceMethod java/util/Map.put:(Ljava/lang/Object;Ljava/lang/Object;)Ljava/lang/Object;
      40: pop
      41: return

  private org.springframework.validation.BindingResult extractBindingResult(java.lang.Throwable);
    Code:
       0: aload_1
       1: instanceof    #196                // class org/springframework/validation/BindingResult
       4: ifeq          14
       7: aload_1
       8: checkcast     #196                // class org/springframework/validation/BindingResult
      11: astore_2
      12: aload_2
      13: areturn
      14: aconst_null
      15: areturn

  private void addStackTrace(java.util.Map<java.lang.String, java.lang.Object>, java.lang.Throwable);
    Code:
       0: new           #210                // class java/io/StringWriter
       3: dup
       4: invokespecial #212                // Method java/io/StringWriter."<init>":()V
       7: astore_3
       8: aload_2
       9: new           #213                // class java/io/PrintWriter
      12: dup
      13: aload_3
      14: invokespecial #215                // Method java/io/PrintWriter."<init>":(Ljava/io/Writer;)V
      17: invokevirtual #218                // Method java/lang/Throwable.printStackTrace:(Ljava/io/PrintWriter;)V
      20: aload_3
      21: invokevirtual #222                // Method java/io/StringWriter.flush:()V
      24: aload_1
      25: ldc           #53                 // String trace
      27: aload_3
      28: invokevirtual #225                // Method java/io/StringWriter.toString:()Ljava/lang/String;
      31: invokeinterface #76,  3           // InterfaceMethod java/util/Map.put:(Ljava/lang/Object;Ljava/lang/Object;)Ljava/lang/Object;
      36: pop
      37: return

  private void addPath(java.util.Map<java.lang.String, java.lang.Object>, org.springframework.web.context.request.RequestAttributes);
    Code:
       0: aload_0
       1: aload_2
       2: ldc           #226                // String jakarta.servlet.error.request_uri
       4: invokevirtual #95                 // Method getAttribute:(Lorg/springframework/web/context/request/RequestAttributes;Ljava/lang/String;)Ljava/lang/Object;
       7: checkcast     #228                // class java/lang/String
      10: astore_3
      11: aload_3
      12: ifnull        25
      15: aload_1
      16: ldc           #230                // String path
      18: aload_3
      19: invokeinterface #76,  3           // InterfaceMethod java/util/Map.put:(Ljava/lang/Object;Ljava/lang/Object;)Ljava/lang/Object;
      24: pop
      25: return

  public java.lang.Throwable getError(org.springframework.web.context.request.WebRequest);
    Code:
       0: aload_0
       1: aload_1
       2: getstatic     #16                 // Field ERROR_INTERNAL_ATTRIBUTE:Ljava/lang/String;
       5: invokevirtual #95                 // Method getAttribute:(Lorg/springframework/web/context/request/RequestAttributes;Ljava/lang/String;)Ljava/lang/Object;
       8: checkcast     #137                // class java/lang/Throwable
      11: astore_2
      12: aload_2
      13: ifnonnull     27
      16: aload_0
      17: aload_1
      18: ldc           #232                // String jakarta.servlet.error.exception
      20: invokevirtual #95                 // Method getAttribute:(Lorg/springframework/web/context/request/RequestAttributes;Ljava/lang/String;)Ljava/lang/Object;
      23: checkcast     #137                // class java/lang/Throwable
      26: astore_2
      27: aload_1
      28: getstatic     #234                // Field org/springframework/boot/web/servlet/error/ErrorAttributes.ERROR_ATTRIBUTE:Ljava/lang/String;
      31: aload_2
      32: iconst_0
      33: invokeinterface #241,  4          // InterfaceMethod org/springframework/web/context/request/WebRequest.setAttribute:(Ljava/lang/String;Ljava/lang/Object;I)V
      38: aload_2
      39: areturn

  private <T> T getAttribute(org.springframework.web.context.request.RequestAttributes, java.lang.String);
    Code:
       0: aload_1
       1: aload_2
       2: iconst_0
       3: invokeinterface #246,  3          // InterfaceMethod org/springframework/web/context/request/RequestAttributes.getAttribute:(Ljava/lang/String;I)Ljava/lang/Object;
       8: areturn

  static {};
    Code:
       0: ldc           #11                 // class org/springframework/boot/web/servlet/error/DefaultErrorAttributes
       2: invokevirtual #146                // Method java/lang/Class.getName:()Ljava/lang/String;
       5: invokedynamic #249,  0            // InvokeDynamic #2:makeConcatWithConstants:(Ljava/lang/String;)Ljava/lang/String;
      10: putstatic     #16                 // Field ERROR_INTERNAL_ATTRIBUTE:Ljava/lang/String;
      13: return
}
