Compiled from "BlockPair.java"
final class com.google.zxing.qrcode.encoder.BlockPair {
  private final byte[] dataBytes;

  private final byte[] errorCorrectionBytes;

  com.google.zxing.qrcode.encoder.BlockPair(byte[], byte[]);
    Code:
       0: aload_0
       1: invokespecial #1                  // Method java/lang/Object."<init>":()V
       4: aload_0
       5: aload_1
       6: putfield      #2                  // Field dataBytes:[B
       9: aload_0
      10: aload_2
      11: putfield      #3                  // Field errorCorrectionBytes:[B
      14: return

  public byte[] getDataBytes();
    Code:
       0: aload_0
       1: getfield      #2                  // Field dataBytes:[B
       4: areturn

  public byte[] getErrorCorrectionBytes();
    Code:
       0: aload_0
       1: getfield      #3                  // Field errorCorrectionBytes:[B
       4: areturn
}
