Compiled from "Encoder.java"
public final class com.google.zxing.qrcode.encoder.Encoder {
  private static final int[] ALPHANUMERIC_TABLE;

  static final java.nio.charset.Charset DEFAULT_BYTE_MODE_ENCODING;

  private com.google.zxing.qrcode.encoder.Encoder();
    Code:
       0: aload_0
       1: invokespecial #1                  // Method java/lang/Object."<init>":()V
       4: return

  private static int calculateMaskPenalty(com.google.zxing.qrcode.encoder.ByteMatrix);
    Code:
       0: aload_0
       1: invokestatic  #2                  // Method com/google/zxing/qrcode/encoder/MaskUtil.applyMaskPenaltyRule1:(Lcom/google/zxing/qrcode/encoder/ByteMatrix;)I
       4: aload_0
       5: invokestatic  #3                  // Method com/google/zxing/qrcode/encoder/MaskUtil.applyMaskPenaltyRule2:(Lcom/google/zxing/qrcode/encoder/ByteMatrix;)I
       8: iadd
       9: aload_0
      10: invokestatic  #4                  // Method com/google/zxing/qrcode/encoder/MaskUtil.applyMaskPenaltyRule3:(Lcom/google/zxing/qrcode/encoder/ByteMatrix;)I
      13: iadd
      14: aload_0
      15: invokestatic  #5                  // Method com/google/zxing/qrcode/encoder/MaskUtil.applyMaskPenaltyRule4:(Lcom/google/zxing/qrcode/encoder/ByteMatrix;)I
      18: iadd
      19: ireturn

  public static com.google.zxing.qrcode.encoder.QRCode encode(java.lang.String, com.google.zxing.qrcode.decoder.ErrorCorrectionLevel) throws com.google.zxing.WriterException;
    Code:
       0: aload_0
       1: aload_1
       2: aconst_null
       3: invokestatic  #6                  // Method encode:(Ljava/lang/String;Lcom/google/zxing/qrcode/decoder/ErrorCorrectionLevel;Ljava/util/Map;)Lcom/google/zxing/qrcode/encoder/QRCode;
       6: areturn

  public static com.google.zxing.qrcode.encoder.QRCode encode(java.lang.String, com.google.zxing.qrcode.decoder.ErrorCorrectionLevel, java.util.Map<com.google.zxing.EncodeHintType, ?>) throws com.google.zxing.WriterException;
    Code:
       0: aload_2
       1: ifnull        38
       4: aload_2
       5: getstatic     #7                  // Field com/google/zxing/EncodeHintType.GS1_FORMAT:Lcom/google/zxing/EncodeHintType;
       8: invokeinterface #8,  2            // InterfaceMethod java/util/Map.containsKey:(Ljava/lang/Object;)Z
      13: ifeq          38
      16: aload_2
      17: getstatic     #7                  // Field com/google/zxing/EncodeHintType.GS1_FORMAT:Lcom/google/zxing/EncodeHintType;
      20: invokeinterface #9,  2            // InterfaceMethod java/util/Map.get:(Ljava/lang/Object;)Ljava/lang/Object;
      25: invokevirtual #10                 // Method java/lang/Object.toString:()Ljava/lang/String;
      28: invokestatic  #11                 // Method java/lang/Boolean.parseBoolean:(Ljava/lang/String;)Z
      31: ifeq          38
      34: iconst_1
      35: goto          39
      38: iconst_0
      39: istore        6
      41: aload_2
      42: ifnull        79
      45: aload_2
      46: getstatic     #12                 // Field com/google/zxing/EncodeHintType.QR_COMPACT:Lcom/google/zxing/EncodeHintType;
      49: invokeinterface #8,  2            // InterfaceMethod java/util/Map.containsKey:(Ljava/lang/Object;)Z
      54: ifeq          79
      57: aload_2
      58: getstatic     #12                 // Field com/google/zxing/EncodeHintType.QR_COMPACT:Lcom/google/zxing/EncodeHintType;
      61: invokeinterface #9,  2            // InterfaceMethod java/util/Map.get:(Ljava/lang/Object;)Ljava/lang/Object;
      66: invokevirtual #10                 // Method java/lang/Object.toString:()Ljava/lang/String;
      69: invokestatic  #11                 // Method java/lang/Boolean.parseBoolean:(Ljava/lang/String;)Z
      72: ifeq          79
      75: iconst_1
      76: goto          80
      79: iconst_0
      80: istore        7
      82: getstatic     #13                 // Field DEFAULT_BYTE_MODE_ENCODING:Ljava/nio/charset/Charset;
      85: astore        8
      87: aload_2
      88: ifnull        107
      91: aload_2
      92: getstatic     #14                 // Field com/google/zxing/EncodeHintType.CHARACTER_SET:Lcom/google/zxing/EncodeHintType;
      95: invokeinterface #8,  2            // InterfaceMethod java/util/Map.containsKey:(Ljava/lang/Object;)Z
     100: ifeq          107
     103: iconst_1
     104: goto          108
     107: iconst_0
     108: istore        9
     110: iload         9
     112: ifeq          132
     115: aload_2
     116: getstatic     #14                 // Field com/google/zxing/EncodeHintType.CHARACTER_SET:Lcom/google/zxing/EncodeHintType;
     119: invokeinterface #9,  2            // InterfaceMethod java/util/Map.get:(Ljava/lang/Object;)Ljava/lang/Object;
     124: invokevirtual #10                 // Method java/lang/Object.toString:()Ljava/lang/String;
     127: invokestatic  #15                 // Method java/nio/charset/Charset.forName:(Ljava/lang/String;)Ljava/nio/charset/Charset;
     130: astore        8
     132: iload         7
     134: ifeq          198
     137: getstatic     #16                 // Field com/google/zxing/qrcode/decoder/Mode.BYTE:Lcom/google/zxing/qrcode/decoder/Mode;
     140: astore        5
     142: aload         8
     144: getstatic     #13                 // Field DEFAULT_BYTE_MODE_ENCODING:Ljava/nio/charset/Charset;
     147: invokevirtual #17                 // Method java/nio/charset/Charset.equals:(Ljava/lang/Object;)Z
     150: ifeq          157
     153: aconst_null
     154: goto          159
     157: aload         8
     159: astore        10
     161: aload_0
     162: aconst_null
     163: aload         10
     165: iload         6
     167: aload_1
     168: invokestatic  #18                 // Method com/google/zxing/qrcode/encoder/MinimalEncoder.encode:(Ljava/lang/String;Lcom/google/zxing/qrcode/decoder/Version;Ljava/nio/charset/Charset;ZLcom/google/zxing/qrcode/decoder/ErrorCorrectionLevel;)Lcom/google/zxing/qrcode/encoder/MinimalEncoder$ResultList;
     171: astore        11
     173: new           #19                 // class com/google/zxing/common/BitArray
     176: dup
     177: invokespecial #20                 // Method com/google/zxing/common/BitArray."<init>":()V
     180: astore        4
     182: aload         11
     184: aload         4
     186: invokevirtual #21                 // Method com/google/zxing/qrcode/encoder/MinimalEncoder$ResultList.getBits:(Lcom/google/zxing/common/BitArray;)V
     189: aload         11
     191: invokevirtual #22                 // Method com/google/zxing/qrcode/encoder/MinimalEncoder$ResultList.getVersion:()Lcom/google/zxing/qrcode/decoder/Version;
     194: astore_3
     195: goto          426
     198: aload_0
     199: aload         8
     201: invokestatic  #23                 // Method chooseMode:(Ljava/lang/String;Ljava/nio/charset/Charset;)Lcom/google/zxing/qrcode/decoder/Mode;
     204: astore        5
     206: new           #19                 // class com/google/zxing/common/BitArray
     209: dup
     210: invokespecial #20                 // Method com/google/zxing/common/BitArray."<init>":()V
     213: astore        10
     215: aload         5
     217: getstatic     #16                 // Field com/google/zxing/qrcode/decoder/Mode.BYTE:Lcom/google/zxing/qrcode/decoder/Mode;
     220: if_acmpne     247
     223: iload         9
     225: ifeq          247
     228: aload         8
     230: invokestatic  #24                 // Method com/google/zxing/common/CharacterSetECI.getCharacterSetECI:(Ljava/nio/charset/Charset;)Lcom/google/zxing/common/CharacterSetECI;
     233: astore        11
     235: aload         11
     237: ifnull        247
     240: aload         11
     242: aload         10
     244: invokestatic  #25                 // Method appendECI:(Lcom/google/zxing/common/CharacterSetECI;Lcom/google/zxing/common/BitArray;)V
     247: iload         6
     249: ifeq          260
     252: getstatic     #26                 // Field com/google/zxing/qrcode/decoder/Mode.FNC1_FIRST_POSITION:Lcom/google/zxing/qrcode/decoder/Mode;
     255: aload         10
     257: invokestatic  #27                 // Method appendModeInfo:(Lcom/google/zxing/qrcode/decoder/Mode;Lcom/google/zxing/common/BitArray;)V
     260: aload         5
     262: aload         10
     264: invokestatic  #27                 // Method appendModeInfo:(Lcom/google/zxing/qrcode/decoder/Mode;Lcom/google/zxing/common/BitArray;)V
     267: new           #19                 // class com/google/zxing/common/BitArray
     270: dup
     271: invokespecial #20                 // Method com/google/zxing/common/BitArray."<init>":()V
     274: astore        11
     276: aload_0
     277: aload         5
     279: aload         11
     281: aload         8
     283: invokestatic  #28                 // Method appendBytes:(Ljava/lang/String;Lcom/google/zxing/qrcode/decoder/Mode;Lcom/google/zxing/common/BitArray;Ljava/nio/charset/Charset;)V
     286: aload_2
     287: ifnull        360
     290: aload_2
     291: getstatic     #29                 // Field com/google/zxing/EncodeHintType.QR_VERSION:Lcom/google/zxing/EncodeHintType;
     294: invokeinterface #8,  2            // InterfaceMethod java/util/Map.containsKey:(Ljava/lang/Object;)Z
     299: ifeq          360
     302: aload_2
     303: getstatic     #29                 // Field com/google/zxing/EncodeHintType.QR_VERSION:Lcom/google/zxing/EncodeHintType;
     306: invokeinterface #9,  2            // InterfaceMethod java/util/Map.get:(Ljava/lang/Object;)Ljava/lang/Object;
     311: invokevirtual #10                 // Method java/lang/Object.toString:()Ljava/lang/String;
     314: invokestatic  #30                 // Method java/lang/Integer.parseInt:(Ljava/lang/String;)I
     317: istore        12
     319: iload         12
     321: invokestatic  #31                 // Method com/google/zxing/qrcode/decoder/Version.getVersionForNumber:(I)Lcom/google/zxing/qrcode/decoder/Version;
     324: astore_3
     325: aload         5
     327: aload         10
     329: aload         11
     331: aload_3
     332: invokestatic  #32                 // Method calculateBitsNeeded:(Lcom/google/zxing/qrcode/decoder/Mode;Lcom/google/zxing/common/BitArray;Lcom/google/zxing/common/BitArray;Lcom/google/zxing/qrcode/decoder/Version;)I
     335: istore        13
     337: iload         13
     339: aload_3
     340: aload_1
     341: invokestatic  #33                 // Method willFit:(ILcom/google/zxing/qrcode/decoder/Version;Lcom/google/zxing/qrcode/decoder/ErrorCorrectionLevel;)Z
     344: ifne          357
     347: new           #34                 // class com/google/zxing/WriterException
     350: dup
     351: ldc           #35                 // String Data too big for requested version
     353: invokespecial #36                 // Method com/google/zxing/WriterException."<init>":(Ljava/lang/String;)V
     356: athrow
     357: goto          371
     360: aload_1
     361: aload         5
     363: aload         10
     365: aload         11
     367: invokestatic  #37                 // Method recommendVersion:(Lcom/google/zxing/qrcode/decoder/ErrorCorrectionLevel;Lcom/google/zxing/qrcode/decoder/Mode;Lcom/google/zxing/common/BitArray;Lcom/google/zxing/common/BitArray;)Lcom/google/zxing/qrcode/decoder/Version;
     370: astore_3
     371: new           #19                 // class com/google/zxing/common/BitArray
     374: dup
     375: invokespecial #20                 // Method com/google/zxing/common/BitArray."<init>":()V
     378: astore        4
     380: aload         4
     382: aload         10
     384: invokevirtual #38                 // Method com/google/zxing/common/BitArray.appendBitArray:(Lcom/google/zxing/common/BitArray;)V
     387: aload         5
     389: getstatic     #16                 // Field com/google/zxing/qrcode/decoder/Mode.BYTE:Lcom/google/zxing/qrcode/decoder/Mode;
     392: if_acmpne     403
     395: aload         11
     397: invokevirtual #39                 // Method com/google/zxing/common/BitArray.getSizeInBytes:()I
     400: goto          407
     403: aload_0
     404: invokevirtual #40                 // Method java/lang/String.length:()I
     407: istore        12
     409: iload         12
     411: aload_3
     412: aload         5
     414: aload         4
     416: invokestatic  #41                 // Method appendLengthInfo:(ILcom/google/zxing/qrcode/decoder/Version;Lcom/google/zxing/qrcode/decoder/Mode;Lcom/google/zxing/common/BitArray;)V
     419: aload         4
     421: aload         11
     423: invokevirtual #38                 // Method com/google/zxing/common/BitArray.appendBitArray:(Lcom/google/zxing/common/BitArray;)V
     426: aload_3
     427: aload_1
     428: invokevirtual #42                 // Method com/google/zxing/qrcode/decoder/Version.getECBlocksForLevel:(Lcom/google/zxing/qrcode/decoder/ErrorCorrectionLevel;)Lcom/google/zxing/qrcode/decoder/Version$ECBlocks;
     431: astore        10
     433: aload_3
     434: invokevirtual #43                 // Method com/google/zxing/qrcode/decoder/Version.getTotalCodewords:()I
     437: aload         10
     439: invokevirtual #44                 // Method com/google/zxing/qrcode/decoder/Version$ECBlocks.getTotalECCodewords:()I
     442: isub
     443: istore        11
     445: iload         11
     447: aload         4
     449: invokestatic  #45                 // Method terminateBits:(ILcom/google/zxing/common/BitArray;)V
     452: aload         4
     454: aload_3
     455: invokevirtual #43                 // Method com/google/zxing/qrcode/decoder/Version.getTotalCodewords:()I
     458: iload         11
     460: aload         10
     462: invokevirtual #46                 // Method com/google/zxing/qrcode/decoder/Version$ECBlocks.getNumBlocks:()I
     465: invokestatic  #47                 // Method interleaveWithECBytes:(Lcom/google/zxing/common/BitArray;III)Lcom/google/zxing/common/BitArray;
     468: astore        12
     470: new           #48                 // class com/google/zxing/qrcode/encoder/QRCode
     473: dup
     474: invokespecial #49                 // Method com/google/zxing/qrcode/encoder/QRCode."<init>":()V
     477: astore        13
     479: aload         13
     481: aload_1
     482: invokevirtual #50                 // Method com/google/zxing/qrcode/encoder/QRCode.setECLevel:(Lcom/google/zxing/qrcode/decoder/ErrorCorrectionLevel;)V
     485: aload         13
     487: aload         5
     489: invokevirtual #51                 // Method com/google/zxing/qrcode/encoder/QRCode.setMode:(Lcom/google/zxing/qrcode/decoder/Mode;)V
     492: aload         13
     494: aload_3
     495: invokevirtual #52                 // Method com/google/zxing/qrcode/encoder/QRCode.setVersion:(Lcom/google/zxing/qrcode/decoder/Version;)V
     498: aload_3
     499: invokevirtual #53                 // Method com/google/zxing/qrcode/decoder/Version.getDimensionForVersion:()I
     502: istore        14
     504: new           #54                 // class com/google/zxing/qrcode/encoder/ByteMatrix
     507: dup
     508: iload         14
     510: iload         14
     512: invokespecial #55                 // Method com/google/zxing/qrcode/encoder/ByteMatrix."<init>":(II)V
     515: astore        15
     517: iconst_m1
     518: istore        16
     520: aload_2
     521: ifnull        569
     524: aload_2
     525: getstatic     #56                 // Field com/google/zxing/EncodeHintType.QR_MASK_PATTERN:Lcom/google/zxing/EncodeHintType;
     528: invokeinterface #8,  2            // InterfaceMethod java/util/Map.containsKey:(Ljava/lang/Object;)Z
     533: ifeq          569
     536: aload_2
     537: getstatic     #56                 // Field com/google/zxing/EncodeHintType.QR_MASK_PATTERN:Lcom/google/zxing/EncodeHintType;
     540: invokeinterface #9,  2            // InterfaceMethod java/util/Map.get:(Ljava/lang/Object;)Ljava/lang/Object;
     545: invokevirtual #10                 // Method java/lang/Object.toString:()Ljava/lang/String;
     548: invokestatic  #30                 // Method java/lang/Integer.parseInt:(Ljava/lang/String;)I
     551: istore        17
     553: iload         17
     555: invokestatic  #57                 // Method com/google/zxing/qrcode/encoder/QRCode.isValidMaskPattern:(I)Z
     558: ifeq          566
     561: iload         17
     563: goto          567
     566: iconst_m1
     567: istore        16
     569: iload         16
     571: iconst_m1
     572: if_icmpne     586
     575: aload         12
     577: aload_1
     578: aload_3
     579: aload         15
     581: invokestatic  #58                 // Method chooseMaskPattern:(Lcom/google/zxing/common/BitArray;Lcom/google/zxing/qrcode/decoder/ErrorCorrectionLevel;Lcom/google/zxing/qrcode/decoder/Version;Lcom/google/zxing/qrcode/encoder/ByteMatrix;)I
     584: istore        16
     586: aload         13
     588: iload         16
     590: invokevirtual #59                 // Method com/google/zxing/qrcode/encoder/QRCode.setMaskPattern:(I)V
     593: aload         12
     595: aload_1
     596: aload_3
     597: iload         16
     599: aload         15
     601: invokestatic  #60                 // Method com/google/zxing/qrcode/encoder/MatrixUtil.buildMatrix:(Lcom/google/zxing/common/BitArray;Lcom/google/zxing/qrcode/decoder/ErrorCorrectionLevel;Lcom/google/zxing/qrcode/decoder/Version;ILcom/google/zxing/qrcode/encoder/ByteMatrix;)V
     604: aload         13
     606: aload         15
     608: invokevirtual #61                 // Method com/google/zxing/qrcode/encoder/QRCode.setMatrix:(Lcom/google/zxing/qrcode/encoder/ByteMatrix;)V
     611: aload         13
     613: areturn

  private static com.google.zxing.qrcode.decoder.Version recommendVersion(com.google.zxing.qrcode.decoder.ErrorCorrectionLevel, com.google.zxing.qrcode.decoder.Mode, com.google.zxing.common.BitArray, com.google.zxing.common.BitArray) throws com.google.zxing.WriterException;
    Code:
       0: aload_1
       1: aload_2
       2: aload_3
       3: iconst_1
       4: invokestatic  #31                 // Method com/google/zxing/qrcode/decoder/Version.getVersionForNumber:(I)Lcom/google/zxing/qrcode/decoder/Version;
       7: invokestatic  #32                 // Method calculateBitsNeeded:(Lcom/google/zxing/qrcode/decoder/Mode;Lcom/google/zxing/common/BitArray;Lcom/google/zxing/common/BitArray;Lcom/google/zxing/qrcode/decoder/Version;)I
      10: istore        4
      12: iload         4
      14: aload_0
      15: invokestatic  #62                 // Method chooseVersion:(ILcom/google/zxing/qrcode/decoder/ErrorCorrectionLevel;)Lcom/google/zxing/qrcode/decoder/Version;
      18: astore        5
      20: aload_1
      21: aload_2
      22: aload_3
      23: aload         5
      25: invokestatic  #32                 // Method calculateBitsNeeded:(Lcom/google/zxing/qrcode/decoder/Mode;Lcom/google/zxing/common/BitArray;Lcom/google/zxing/common/BitArray;Lcom/google/zxing/qrcode/decoder/Version;)I
      28: istore        6
      30: iload         6
      32: aload_0
      33: invokestatic  #62                 // Method chooseVersion:(ILcom/google/zxing/qrcode/decoder/ErrorCorrectionLevel;)Lcom/google/zxing/qrcode/decoder/Version;
      36: areturn

  private static int calculateBitsNeeded(com.google.zxing.qrcode.decoder.Mode, com.google.zxing.common.BitArray, com.google.zxing.common.BitArray, com.google.zxing.qrcode.decoder.Version);
    Code:
       0: aload_1
       1: invokevirtual #63                 // Method com/google/zxing/common/BitArray.getSize:()I
       4: aload_0
       5: aload_3
       6: invokevirtual #64                 // Method com/google/zxing/qrcode/decoder/Mode.getCharacterCountBits:(Lcom/google/zxing/qrcode/decoder/Version;)I
       9: iadd
      10: aload_2
      11: invokevirtual #63                 // Method com/google/zxing/common/BitArray.getSize:()I
      14: iadd
      15: ireturn

  static int getAlphanumericCode(int);
    Code:
       0: iload_0
       1: getstatic     #65                 // Field ALPHANUMERIC_TABLE:[I
       4: arraylength
       5: if_icmpge     14
       8: getstatic     #65                 // Field ALPHANUMERIC_TABLE:[I
      11: iload_0
      12: iaload
      13: ireturn
      14: iconst_m1
      15: ireturn

  public static com.google.zxing.qrcode.decoder.Mode chooseMode(java.lang.String);
    Code:
       0: aload_0
       1: aconst_null
       2: invokestatic  #23                 // Method chooseMode:(Ljava/lang/String;Ljava/nio/charset/Charset;)Lcom/google/zxing/qrcode/decoder/Mode;
       5: areturn

  private static com.google.zxing.qrcode.decoder.Mode chooseMode(java.lang.String, java.nio.charset.Charset);
    Code:
       0: getstatic     #66                 // Field com/google/zxing/common/StringUtils.SHIFT_JIS_CHARSET:Ljava/nio/charset/Charset;
       3: aload_1
       4: invokevirtual #17                 // Method java/nio/charset/Charset.equals:(Ljava/lang/Object;)Z
       7: ifeq          21
      10: aload_0
      11: invokestatic  #67                 // Method isOnlyDoubleByteKanji:(Ljava/lang/String;)Z
      14: ifeq          21
      17: getstatic     #68                 // Field com/google/zxing/qrcode/decoder/Mode.KANJI:Lcom/google/zxing/qrcode/decoder/Mode;
      20: areturn
      21: iconst_0
      22: istore_2
      23: iconst_0
      24: istore_3
      25: iconst_0
      26: istore        4
      28: iload         4
      30: aload_0
      31: invokevirtual #40                 // Method java/lang/String.length:()I
      34: if_icmpge     88
      37: aload_0
      38: iload         4
      40: invokevirtual #69                 // Method java/lang/String.charAt:(I)C
      43: istore        5
      45: iload         5
      47: bipush        48
      49: if_icmplt     64
      52: iload         5
      54: bipush        57
      56: if_icmpgt     64
      59: iconst_1
      60: istore_2
      61: goto          82
      64: iload         5
      66: invokestatic  #70                 // Method getAlphanumericCode:(I)I
      69: iconst_m1
      70: if_icmpeq     78
      73: iconst_1
      74: istore_3
      75: goto          82
      78: getstatic     #16                 // Field com/google/zxing/qrcode/decoder/Mode.BYTE:Lcom/google/zxing/qrcode/decoder/Mode;
      81: areturn
      82: iinc          4, 1
      85: goto          28
      88: iload_3
      89: ifeq          96
      92: getstatic     #71                 // Field com/google/zxing/qrcode/decoder/Mode.ALPHANUMERIC:Lcom/google/zxing/qrcode/decoder/Mode;
      95: areturn
      96: iload_2
      97: ifeq          104
     100: getstatic     #72                 // Field com/google/zxing/qrcode/decoder/Mode.NUMERIC:Lcom/google/zxing/qrcode/decoder/Mode;
     103: areturn
     104: getstatic     #16                 // Field com/google/zxing/qrcode/decoder/Mode.BYTE:Lcom/google/zxing/qrcode/decoder/Mode;
     107: areturn

  static boolean isOnlyDoubleByteKanji(java.lang.String);
    Code:
       0: aload_0
       1: getstatic     #66                 // Field com/google/zxing/common/StringUtils.SHIFT_JIS_CHARSET:Ljava/nio/charset/Charset;
       4: invokevirtual #73                 // Method java/lang/String.getBytes:(Ljava/nio/charset/Charset;)[B
       7: astore_1
       8: aload_1
       9: arraylength
      10: istore_2
      11: iload_2
      12: iconst_2
      13: irem
      14: ifeq          19
      17: iconst_0
      18: ireturn
      19: iconst_0
      20: istore_3
      21: iload_3
      22: iload_2
      23: if_icmpge     75
      26: aload_1
      27: iload_3
      28: baload
      29: sipush        255
      32: iand
      33: istore        4
      35: iload         4
      37: sipush        129
      40: if_icmplt     51
      43: iload         4
      45: sipush        159
      48: if_icmple     69
      51: iload         4
      53: sipush        224
      56: if_icmplt     67
      59: iload         4
      61: sipush        235
      64: if_icmple     69
      67: iconst_0
      68: ireturn
      69: iinc          3, 2
      72: goto          21
      75: iconst_1
      76: ireturn

  private static int chooseMaskPattern(com.google.zxing.common.BitArray, com.google.zxing.qrcode.decoder.ErrorCorrectionLevel, com.google.zxing.qrcode.decoder.Version, com.google.zxing.qrcode.encoder.ByteMatrix) throws com.google.zxing.WriterException;
    Code:
       0: ldc           #75                 // int 2147483647
       2: istore        4
       4: iconst_m1
       5: istore        5
       7: iconst_0
       8: istore        6
      10: iload         6
      12: bipush        8
      14: if_icmpge     53
      17: aload_0
      18: aload_1
      19: aload_2
      20: iload         6
      22: aload_3
      23: invokestatic  #60                 // Method com/google/zxing/qrcode/encoder/MatrixUtil.buildMatrix:(Lcom/google/zxing/common/BitArray;Lcom/google/zxing/qrcode/decoder/ErrorCorrectionLevel;Lcom/google/zxing/qrcode/decoder/Version;ILcom/google/zxing/qrcode/encoder/ByteMatrix;)V
      26: aload_3
      27: invokestatic  #76                 // Method calculateMaskPenalty:(Lcom/google/zxing/qrcode/encoder/ByteMatrix;)I
      30: istore        7
      32: iload         7
      34: iload         4
      36: if_icmpge     47
      39: iload         7
      41: istore        4
      43: iload         6
      45: istore        5
      47: iinc          6, 1
      50: goto          10
      53: iload         5
      55: ireturn

  private static com.google.zxing.qrcode.decoder.Version chooseVersion(int, com.google.zxing.qrcode.decoder.ErrorCorrectionLevel) throws com.google.zxing.WriterException;
    Code:
       0: iconst_1
       1: istore_2
       2: iload_2
       3: bipush        40
       5: if_icmpgt     30
       8: iload_2
       9: invokestatic  #31                 // Method com/google/zxing/qrcode/decoder/Version.getVersionForNumber:(I)Lcom/google/zxing/qrcode/decoder/Version;
      12: astore_3
      13: iload_0
      14: aload_3
      15: aload_1
      16: invokestatic  #33                 // Method willFit:(ILcom/google/zxing/qrcode/decoder/Version;Lcom/google/zxing/qrcode/decoder/ErrorCorrectionLevel;)Z
      19: ifeq          24
      22: aload_3
      23: areturn
      24: iinc          2, 1
      27: goto          2
      30: new           #34                 // class com/google/zxing/WriterException
      33: dup
      34: ldc           #77                 // String Data too big
      36: invokespecial #36                 // Method com/google/zxing/WriterException."<init>":(Ljava/lang/String;)V
      39: athrow

  static boolean willFit(int, com.google.zxing.qrcode.decoder.Version, com.google.zxing.qrcode.decoder.ErrorCorrectionLevel);
    Code:
       0: aload_1
       1: invokevirtual #43                 // Method com/google/zxing/qrcode/decoder/Version.getTotalCodewords:()I
       4: istore_3
       5: aload_1
       6: aload_2
       7: invokevirtual #42                 // Method com/google/zxing/qrcode/decoder/Version.getECBlocksForLevel:(Lcom/google/zxing/qrcode/decoder/ErrorCorrectionLevel;)Lcom/google/zxing/qrcode/decoder/Version$ECBlocks;
      10: astore        4
      12: aload         4
      14: invokevirtual #44                 // Method com/google/zxing/qrcode/decoder/Version$ECBlocks.getTotalECCodewords:()I
      17: istore        5
      19: iload_3
      20: iload         5
      22: isub
      23: istore        6
      25: iload_0
      26: bipush        7
      28: iadd
      29: bipush        8
      31: idiv
      32: istore        7
      34: iload         6
      36: iload         7
      38: if_icmplt     45
      41: iconst_1
      42: goto          46
      45: iconst_0
      46: ireturn

  static void terminateBits(int, com.google.zxing.common.BitArray) throws com.google.zxing.WriterException;
    Code:
       0: iload_0
       1: bipush        8
       3: imul
       4: istore_2
       5: aload_1
       6: invokevirtual #63                 // Method com/google/zxing/common/BitArray.getSize:()I
       9: iload_2
      10: if_icmple     52
      13: new           #34                 // class com/google/zxing/WriterException
      16: dup
      17: new           #78                 // class java/lang/StringBuilder
      20: dup
      21: invokespecial #79                 // Method java/lang/StringBuilder."<init>":()V
      24: ldc           #80                 // String data bits cannot fit in the QR Code
      26: invokevirtual #81                 // Method java/lang/StringBuilder.append:(Ljava/lang/String;)Ljava/lang/StringBuilder;
      29: aload_1
      30: invokevirtual #63                 // Method com/google/zxing/common/BitArray.getSize:()I
      33: invokevirtual #82                 // Method java/lang/StringBuilder.append:(I)Ljava/lang/StringBuilder;
      36: ldc           #83                 // String  >
      38: invokevirtual #81                 // Method java/lang/StringBuilder.append:(Ljava/lang/String;)Ljava/lang/StringBuilder;
      41: iload_2
      42: invokevirtual #82                 // Method java/lang/StringBuilder.append:(I)Ljava/lang/StringBuilder;
      45: invokevirtual #84                 // Method java/lang/StringBuilder.toString:()Ljava/lang/String;
      48: invokespecial #36                 // Method com/google/zxing/WriterException."<init>":(Ljava/lang/String;)V
      51: athrow
      52: iconst_0
      53: istore_3
      54: iload_3
      55: iconst_4
      56: if_icmpge     78
      59: aload_1
      60: invokevirtual #63                 // Method com/google/zxing/common/BitArray.getSize:()I
      63: iload_2
      64: if_icmpge     78
      67: aload_1
      68: iconst_0
      69: invokevirtual #85                 // Method com/google/zxing/common/BitArray.appendBit:(Z)V
      72: iinc          3, 1
      75: goto          54
      78: aload_1
      79: invokevirtual #63                 // Method com/google/zxing/common/BitArray.getSize:()I
      82: bipush        7
      84: iand
      85: istore_3
      86: iload_3
      87: ifle          111
      90: iload_3
      91: istore        4
      93: iload         4
      95: bipush        8
      97: if_icmpge     111
     100: aload_1
     101: iconst_0
     102: invokevirtual #85                 // Method com/google/zxing/common/BitArray.appendBit:(Z)V
     105: iinc          4, 1
     108: goto          93
     111: iload_0
     112: aload_1
     113: invokevirtual #39                 // Method com/google/zxing/common/BitArray.getSizeInBytes:()I
     116: isub
     117: istore        4
     119: iconst_0
     120: istore        5
     122: iload         5
     124: iload         4
     126: if_icmpge     156
     129: aload_1
     130: iload         5
     132: iconst_1
     133: iand
     134: ifne          143
     137: sipush        236
     140: goto          145
     143: bipush        17
     145: bipush        8
     147: invokevirtual #86                 // Method com/google/zxing/common/BitArray.appendBits:(II)V
     150: iinc          5, 1
     153: goto          122
     156: aload_1
     157: invokevirtual #63                 // Method com/google/zxing/common/BitArray.getSize:()I
     160: iload_2
     161: if_icmpeq     174
     164: new           #34                 // class com/google/zxing/WriterException
     167: dup
     168: ldc           #87                 // String Bits size does not equal capacity
     170: invokespecial #36                 // Method com/google/zxing/WriterException."<init>":(Ljava/lang/String;)V
     173: athrow
     174: return

  static void getNumDataBytesAndNumECBytesForBlockID(int, int, int, int, int[], int[]) throws com.google.zxing.WriterException;
    Code:
       0: iload_3
       1: iload_2
       2: if_icmplt     15
       5: new           #34                 // class com/google/zxing/WriterException
       8: dup
       9: ldc           #88                 // String Block ID too large
      11: invokespecial #36                 // Method com/google/zxing/WriterException."<init>":(Ljava/lang/String;)V
      14: athrow
      15: iload_0
      16: iload_2
      17: irem
      18: istore        6
      20: iload_2
      21: iload         6
      23: isub
      24: istore        7
      26: iload_0
      27: iload_2
      28: idiv
      29: istore        8
      31: iload         8
      33: iconst_1
      34: iadd
      35: istore        9
      37: iload_1
      38: iload_2
      39: idiv
      40: istore        10
      42: iload         10
      44: iconst_1
      45: iadd
      46: istore        11
      48: iload         8
      50: iload         10
      52: isub
      53: istore        12
      55: iload         9
      57: iload         11
      59: isub
      60: istore        13
      62: iload         12
      64: iload         13
      66: if_icmpeq     79
      69: new           #34                 // class com/google/zxing/WriterException
      72: dup
      73: ldc           #89                 // String EC bytes mismatch
      75: invokespecial #36                 // Method com/google/zxing/WriterException."<init>":(Ljava/lang/String;)V
      78: athrow
      79: iload_2
      80: iload         7
      82: iload         6
      84: iadd
      85: if_icmpeq     98
      88: new           #34                 // class com/google/zxing/WriterException
      91: dup
      92: ldc           #90                 // String RS blocks mismatch
      94: invokespecial #36                 // Method com/google/zxing/WriterException."<init>":(Ljava/lang/String;)V
      97: athrow
      98: iload_0
      99: iload         10
     101: iload         12
     103: iadd
     104: iload         7
     106: imul
     107: iload         11
     109: iload         13
     111: iadd
     112: iload         6
     114: imul
     115: iadd
     116: if_icmpeq     129
     119: new           #34                 // class com/google/zxing/WriterException
     122: dup
     123: ldc           #91                 // String Total bytes mismatch
     125: invokespecial #36                 // Method com/google/zxing/WriterException."<init>":(Ljava/lang/String;)V
     128: athrow
     129: iload_3
     130: iload         7
     132: if_icmpge     150
     135: aload         4
     137: iconst_0
     138: iload         10
     140: iastore
     141: aload         5
     143: iconst_0
     144: iload         12
     146: iastore
     147: goto          162
     150: aload         4
     152: iconst_0
     153: iload         11
     155: iastore
     156: aload         5
     158: iconst_0
     159: iload         13
     161: iastore
     162: return

  static com.google.zxing.common.BitArray interleaveWithECBytes(com.google.zxing.common.BitArray, int, int, int) throws com.google.zxing.WriterException;
    Code:
       0: aload_0
       1: invokevirtual #39                 // Method com/google/zxing/common/BitArray.getSizeInBytes:()I
       4: iload_2
       5: if_icmpeq     18
       8: new           #34                 // class com/google/zxing/WriterException
      11: dup
      12: ldc           #92                 // String Number of bits and data bytes does not match
      14: invokespecial #36                 // Method com/google/zxing/WriterException."<init>":(Ljava/lang/String;)V
      17: athrow
      18: iconst_0
      19: istore        4
      21: iconst_0
      22: istore        5
      24: iconst_0
      25: istore        6
      27: new           #93                 // class java/util/ArrayList
      30: dup
      31: iload_3
      32: invokespecial #94                 // Method java/util/ArrayList."<init>":(I)V
      35: astore        7
      37: iconst_0
      38: istore        8
      40: iload         8
      42: iload_3
      43: if_icmpge     158
      46: iconst_1
      47: newarray       int
      49: astore        9
      51: iconst_1
      52: newarray       int
      54: astore        10
      56: iload_1
      57: iload_2
      58: iload_3
      59: iload         8
      61: aload         9
      63: aload         10
      65: invokestatic  #95                 // Method getNumDataBytesAndNumECBytesForBlockID:(IIII[I[I)V
      68: aload         9
      70: iconst_0
      71: iaload
      72: istore        11
      74: iload         11
      76: newarray       byte
      78: astore        12
      80: aload_0
      81: bipush        8
      83: iload         4
      85: imul
      86: aload         12
      88: iconst_0
      89: iload         11
      91: invokevirtual #96                 // Method com/google/zxing/common/BitArray.toBytes:(I[BII)V
      94: aload         12
      96: aload         10
      98: iconst_0
      99: iaload
     100: invokestatic  #97                 // Method generateECBytes:([BI)[B
     103: astore        13
     105: aload         7
     107: new           #98                 // class com/google/zxing/qrcode/encoder/BlockPair
     110: dup
     111: aload         12
     113: aload         13
     115: invokespecial #99                 // Method com/google/zxing/qrcode/encoder/BlockPair."<init>":([B[B)V
     118: invokeinterface #100,  2          // InterfaceMethod java/util/Collection.add:(Ljava/lang/Object;)Z
     123: pop
     124: iload         5
     126: iload         11
     128: invokestatic  #101                // Method java/lang/Math.max:(II)I
     131: istore        5
     133: iload         6
     135: aload         13
     137: arraylength
     138: invokestatic  #101                // Method java/lang/Math.max:(II)I
     141: istore        6
     143: iload         4
     145: aload         9
     147: iconst_0
     148: iaload
     149: iadd
     150: istore        4
     152: iinc          8, 1
     155: goto          40
     158: iload_2
     159: iload         4
     161: if_icmpeq     174
     164: new           #34                 // class com/google/zxing/WriterException
     167: dup
     168: ldc           #102                // String Data bytes does not match offset
     170: invokespecial #36                 // Method com/google/zxing/WriterException."<init>":(Ljava/lang/String;)V
     173: athrow
     174: new           #19                 // class com/google/zxing/common/BitArray
     177: dup
     178: invokespecial #20                 // Method com/google/zxing/common/BitArray."<init>":()V
     181: astore        8
     183: iconst_0
     184: istore        9
     186: iload         9
     188: iload         5
     190: if_icmpge     260
     193: aload         7
     195: invokeinterface #103,  1          // InterfaceMethod java/util/Collection.iterator:()Ljava/util/Iterator;
     200: astore        10
     202: aload         10
     204: invokeinterface #104,  1          // InterfaceMethod java/util/Iterator.hasNext:()Z
     209: ifeq          254
     212: aload         10
     214: invokeinterface #105,  1          // InterfaceMethod java/util/Iterator.next:()Ljava/lang/Object;
     219: checkcast     #98                 // class com/google/zxing/qrcode/encoder/BlockPair
     222: astore        11
     224: aload         11
     226: invokevirtual #106                // Method com/google/zxing/qrcode/encoder/BlockPair.getDataBytes:()[B
     229: astore        12
     231: iload         9
     233: aload         12
     235: arraylength
     236: if_icmpge     251
     239: aload         8
     241: aload         12
     243: iload         9
     245: baload
     246: bipush        8
     248: invokevirtual #86                 // Method com/google/zxing/common/BitArray.appendBits:(II)V
     251: goto          202
     254: iinc          9, 1
     257: goto          186
     260: iconst_0
     261: istore        9
     263: iload         9
     265: iload         6
     267: if_icmpge     337
     270: aload         7
     272: invokeinterface #103,  1          // InterfaceMethod java/util/Collection.iterator:()Ljava/util/Iterator;
     277: astore        10
     279: aload         10
     281: invokeinterface #104,  1          // InterfaceMethod java/util/Iterator.hasNext:()Z
     286: ifeq          331
     289: aload         10
     291: invokeinterface #105,  1          // InterfaceMethod java/util/Iterator.next:()Ljava/lang/Object;
     296: checkcast     #98                 // class com/google/zxing/qrcode/encoder/BlockPair
     299: astore        11
     301: aload         11
     303: invokevirtual #107                // Method com/google/zxing/qrcode/encoder/BlockPair.getErrorCorrectionBytes:()[B
     306: astore        12
     308: iload         9
     310: aload         12
     312: arraylength
     313: if_icmpge     328
     316: aload         8
     318: aload         12
     320: iload         9
     322: baload
     323: bipush        8
     325: invokevirtual #86                 // Method com/google/zxing/common/BitArray.appendBits:(II)V
     328: goto          279
     331: iinc          9, 1
     334: goto          263
     337: iload_1
     338: aload         8
     340: invokevirtual #39                 // Method com/google/zxing/common/BitArray.getSizeInBytes:()I
     343: if_icmpeq     391
     346: new           #34                 // class com/google/zxing/WriterException
     349: dup
     350: new           #78                 // class java/lang/StringBuilder
     353: dup
     354: invokespecial #79                 // Method java/lang/StringBuilder."<init>":()V
     357: ldc           #108                // String Interleaving error:
     359: invokevirtual #81                 // Method java/lang/StringBuilder.append:(Ljava/lang/String;)Ljava/lang/StringBuilder;
     362: iload_1
     363: invokevirtual #82                 // Method java/lang/StringBuilder.append:(I)Ljava/lang/StringBuilder;
     366: ldc           #109                // String  and
     368: invokevirtual #81                 // Method java/lang/StringBuilder.append:(Ljava/lang/String;)Ljava/lang/StringBuilder;
     371: aload         8
     373: invokevirtual #39                 // Method com/google/zxing/common/BitArray.getSizeInBytes:()I
     376: invokevirtual #82                 // Method java/lang/StringBuilder.append:(I)Ljava/lang/StringBuilder;
     379: ldc           #110                // String  differ.
     381: invokevirtual #81                 // Method java/lang/StringBuilder.append:(Ljava/lang/String;)Ljava/lang/StringBuilder;
     384: invokevirtual #84                 // Method java/lang/StringBuilder.toString:()Ljava/lang/String;
     387: invokespecial #36                 // Method com/google/zxing/WriterException."<init>":(Ljava/lang/String;)V
     390: athrow
     391: aload         8
     393: areturn

  static byte[] generateECBytes(byte[], int);
    Code:
       0: aload_0
       1: arraylength
       2: istore_2
       3: iload_2
       4: iload_1
       5: iadd
       6: newarray       int
       8: astore_3
       9: iconst_0
      10: istore        4
      12: iload         4
      14: iload_2
      15: if_icmpge     36
      18: aload_3
      19: iload         4
      21: aload_0
      22: iload         4
      24: baload
      25: sipush        255
      28: iand
      29: iastore
      30: iinc          4, 1
      33: goto          12
      36: new           #111                // class com/google/zxing/common/reedsolomon/ReedSolomonEncoder
      39: dup
      40: getstatic     #112                // Field com/google/zxing/common/reedsolomon/GenericGF.QR_CODE_FIELD_256:Lcom/google/zxing/common/reedsolomon/GenericGF;
      43: invokespecial #113                // Method com/google/zxing/common/reedsolomon/ReedSolomonEncoder."<init>":(Lcom/google/zxing/common/reedsolomon/GenericGF;)V
      46: aload_3
      47: iload_1
      48: invokevirtual #114                // Method com/google/zxing/common/reedsolomon/ReedSolomonEncoder.encode:([II)V
      51: iload_1
      52: newarray       byte
      54: astore        4
      56: iconst_0
      57: istore        5
      59: iload         5
      61: iload_1
      62: if_icmpge     83
      65: aload         4
      67: iload         5
      69: aload_3
      70: iload_2
      71: iload         5
      73: iadd
      74: iaload
      75: i2b
      76: bastore
      77: iinc          5, 1
      80: goto          59
      83: aload         4
      85: areturn

  static void appendModeInfo(com.google.zxing.qrcode.decoder.Mode, com.google.zxing.common.BitArray);
    Code:
       0: aload_1
       1: aload_0
       2: invokevirtual #115                // Method com/google/zxing/qrcode/decoder/Mode.getBits:()I
       5: iconst_4
       6: invokevirtual #86                 // Method com/google/zxing/common/BitArray.appendBits:(II)V
       9: return

  static void appendLengthInfo(int, com.google.zxing.qrcode.decoder.Version, com.google.zxing.qrcode.decoder.Mode, com.google.zxing.common.BitArray) throws com.google.zxing.WriterException;
    Code:
       0: aload_2
       1: aload_1
       2: invokevirtual #64                 // Method com/google/zxing/qrcode/decoder/Mode.getCharacterCountBits:(Lcom/google/zxing/qrcode/decoder/Version;)I
       5: istore        4
       7: iload_0
       8: iconst_1
       9: iload         4
      11: ishl
      12: if_icmplt     51
      15: new           #34                 // class com/google/zxing/WriterException
      18: dup
      19: new           #78                 // class java/lang/StringBuilder
      22: dup
      23: invokespecial #79                 // Method java/lang/StringBuilder."<init>":()V
      26: iload_0
      27: invokevirtual #82                 // Method java/lang/StringBuilder.append:(I)Ljava/lang/StringBuilder;
      30: ldc           #116                // String  is bigger than
      32: invokevirtual #81                 // Method java/lang/StringBuilder.append:(Ljava/lang/String;)Ljava/lang/StringBuilder;
      35: iconst_1
      36: iload         4
      38: ishl
      39: iconst_1
      40: isub
      41: invokevirtual #82                 // Method java/lang/StringBuilder.append:(I)Ljava/lang/StringBuilder;
      44: invokevirtual #84                 // Method java/lang/StringBuilder.toString:()Ljava/lang/String;
      47: invokespecial #36                 // Method com/google/zxing/WriterException."<init>":(Ljava/lang/String;)V
      50: athrow
      51: aload_3
      52: iload_0
      53: iload         4
      55: invokevirtual #86                 // Method com/google/zxing/common/BitArray.appendBits:(II)V
      58: return

  static void appendBytes(java.lang.String, com.google.zxing.qrcode.decoder.Mode, com.google.zxing.common.BitArray, java.nio.charset.Charset) throws com.google.zxing.WriterException;
    Code:
       0: getstatic     #117                // Field com/google/zxing/qrcode/encoder/Encoder$1.$SwitchMap$com$google$zxing$qrcode$decoder$Mode:[I
       3: aload_1
       4: invokevirtual #118                // Method com/google/zxing/qrcode/decoder/Mode.ordinal:()I
       7: iaload
       8: tableswitch   { // 1 to 4
                     1: 40
                     2: 48
                     3: 56
                     4: 65
               default: 73
          }
      40: aload_0
      41: aload_2
      42: invokestatic  #119                // Method appendNumericBytes:(Ljava/lang/CharSequence;Lcom/google/zxing/common/BitArray;)V
      45: goto          100
      48: aload_0
      49: aload_2
      50: invokestatic  #120                // Method appendAlphanumericBytes:(Ljava/lang/CharSequence;Lcom/google/zxing/common/BitArray;)V
      53: goto          100
      56: aload_0
      57: aload_2
      58: aload_3
      59: invokestatic  #121                // Method append8BitBytes:(Ljava/lang/String;Lcom/google/zxing/common/BitArray;Ljava/nio/charset/Charset;)V
      62: goto          100
      65: aload_0
      66: aload_2
      67: invokestatic  #122                // Method appendKanjiBytes:(Ljava/lang/String;Lcom/google/zxing/common/BitArray;)V
      70: goto          100
      73: new           #34                 // class com/google/zxing/WriterException
      76: dup
      77: new           #78                 // class java/lang/StringBuilder
      80: dup
      81: invokespecial #79                 // Method java/lang/StringBuilder."<init>":()V
      84: ldc           #123                // String Invalid mode:
      86: invokevirtual #81                 // Method java/lang/StringBuilder.append:(Ljava/lang/String;)Ljava/lang/StringBuilder;
      89: aload_1
      90: invokevirtual #124                // Method java/lang/StringBuilder.append:(Ljava/lang/Object;)Ljava/lang/StringBuilder;
      93: invokevirtual #84                 // Method java/lang/StringBuilder.toString:()Ljava/lang/String;
      96: invokespecial #36                 // Method com/google/zxing/WriterException."<init>":(Ljava/lang/String;)V
      99: athrow
     100: return

  static void appendNumericBytes(java.lang.CharSequence, com.google.zxing.common.BitArray);
    Code:
       0: aload_0
       1: invokeinterface #125,  1          // InterfaceMethod java/lang/CharSequence.length:()I
       6: istore_2
       7: iconst_0
       8: istore_3
       9: iload_3
      10: iload_2
      11: if_icmpge     141
      14: aload_0
      15: iload_3
      16: invokeinterface #126,  2          // InterfaceMethod java/lang/CharSequence.charAt:(I)C
      21: bipush        48
      23: isub
      24: istore        4
      26: iload_3
      27: iconst_2
      28: iadd
      29: iload_2
      30: if_icmpge     87
      33: aload_0
      34: iload_3
      35: iconst_1
      36: iadd
      37: invokeinterface #126,  2          // InterfaceMethod java/lang/CharSequence.charAt:(I)C
      42: bipush        48
      44: isub
      45: istore        5
      47: aload_0
      48: iload_3
      49: iconst_2
      50: iadd
      51: invokeinterface #126,  2          // InterfaceMethod java/lang/CharSequence.charAt:(I)C
      56: bipush        48
      58: isub
      59: istore        6
      61: aload_1
      62: iload         4
      64: bipush        100
      66: imul
      67: iload         5
      69: bipush        10
      71: imul
      72: iadd
      73: iload         6
      75: iadd
      76: bipush        10
      78: invokevirtual #86                 // Method com/google/zxing/common/BitArray.appendBits:(II)V
      81: iinc          3, 3
      84: goto          138
      87: iload_3
      88: iconst_1
      89: iadd
      90: iload_2
      91: if_icmpge     128
      94: aload_0
      95: iload_3
      96: iconst_1
      97: iadd
      98: invokeinterface #126,  2          // InterfaceMethod java/lang/CharSequence.charAt:(I)C
     103: bipush        48
     105: isub
     106: istore        5
     108: aload_1
     109: iload         4
     111: bipush        10
     113: imul
     114: iload         5
     116: iadd
     117: bipush        7
     119: invokevirtual #86                 // Method com/google/zxing/common/BitArray.appendBits:(II)V
     122: iinc          3, 2
     125: goto          138
     128: aload_1
     129: iload         4
     131: iconst_4
     132: invokevirtual #86                 // Method com/google/zxing/common/BitArray.appendBits:(II)V
     135: iinc          3, 1
     138: goto          9
     141: return

  static void appendAlphanumericBytes(java.lang.CharSequence, com.google.zxing.common.BitArray) throws com.google.zxing.WriterException;
    Code:
       0: aload_0
       1: invokeinterface #125,  1          // InterfaceMethod java/lang/CharSequence.length:()I
       6: istore_2
       7: iconst_0
       8: istore_3
       9: iload_3
      10: iload_2
      11: if_icmpge     109
      14: aload_0
      15: iload_3
      16: invokeinterface #126,  2          // InterfaceMethod java/lang/CharSequence.charAt:(I)C
      21: invokestatic  #70                 // Method getAlphanumericCode:(I)I
      24: istore        4
      26: iload         4
      28: iconst_m1
      29: if_icmpne     40
      32: new           #34                 // class com/google/zxing/WriterException
      35: dup
      36: invokespecial #127                // Method com/google/zxing/WriterException."<init>":()V
      39: athrow
      40: iload_3
      41: iconst_1
      42: iadd
      43: iload_2
      44: if_icmpge     95
      47: aload_0
      48: iload_3
      49: iconst_1
      50: iadd
      51: invokeinterface #126,  2          // InterfaceMethod java/lang/CharSequence.charAt:(I)C
      56: invokestatic  #70                 // Method getAlphanumericCode:(I)I
      59: istore        5
      61: iload         5
      63: iconst_m1
      64: if_icmpne     75
      67: new           #34                 // class com/google/zxing/WriterException
      70: dup
      71: invokespecial #127                // Method com/google/zxing/WriterException."<init>":()V
      74: athrow
      75: aload_1
      76: iload         4
      78: bipush        45
      80: imul
      81: iload         5
      83: iadd
      84: bipush        11
      86: invokevirtual #86                 // Method com/google/zxing/common/BitArray.appendBits:(II)V
      89: iinc          3, 2
      92: goto          106
      95: aload_1
      96: iload         4
      98: bipush        6
     100: invokevirtual #86                 // Method com/google/zxing/common/BitArray.appendBits:(II)V
     103: iinc          3, 1
     106: goto          9
     109: return

  static void append8BitBytes(java.lang.String, com.google.zxing.common.BitArray, java.nio.charset.Charset);
    Code:
       0: aload_0
       1: aload_2
       2: invokevirtual #73                 // Method java/lang/String.getBytes:(Ljava/nio/charset/Charset;)[B
       5: astore_3
       6: aload_3
       7: astore        4
       9: aload         4
      11: arraylength
      12: istore        5
      14: iconst_0
      15: istore        6
      17: iload         6
      19: iload         5
      21: if_icmpge     45
      24: aload         4
      26: iload         6
      28: baload
      29: istore        7
      31: aload_1
      32: iload         7
      34: bipush        8
      36: invokevirtual #86                 // Method com/google/zxing/common/BitArray.appendBits:(II)V
      39: iinc          6, 1
      42: goto          17
      45: return

  static void appendKanjiBytes(java.lang.String, com.google.zxing.common.BitArray) throws com.google.zxing.WriterException;
    Code:
       0: aload_0
       1: getstatic     #66                 // Field com/google/zxing/common/StringUtils.SHIFT_JIS_CHARSET:Ljava/nio/charset/Charset;
       4: invokevirtual #73                 // Method java/lang/String.getBytes:(Ljava/nio/charset/Charset;)[B
       7: astore_2
       8: aload_2
       9: arraylength
      10: iconst_2
      11: irem
      12: ifeq          25
      15: new           #34                 // class com/google/zxing/WriterException
      18: dup
      19: ldc           #128                // String Kanji byte size not even
      21: invokespecial #36                 // Method com/google/zxing/WriterException."<init>":(Ljava/lang/String;)V
      24: athrow
      25: aload_2
      26: arraylength
      27: iconst_1
      28: isub
      29: istore_3
      30: iconst_0
      31: istore        4
      33: iload         4
      35: iload_3
      36: if_icmpge     167
      39: aload_2
      40: iload         4
      42: baload
      43: sipush        255
      46: iand
      47: istore        5
      49: aload_2
      50: iload         4
      52: iconst_1
      53: iadd
      54: baload
      55: sipush        255
      58: iand
      59: istore        6
      61: iload         5
      63: bipush        8
      65: ishl
      66: iload         6
      68: ior
      69: istore        7
      71: iconst_m1
      72: istore        8
      74: iload         7
      76: ldc           #129                // int 33088
      78: if_icmplt     98
      81: iload         7
      83: ldc           #130                // int 40956
      85: if_icmpgt     98
      88: iload         7
      90: ldc           #129                // int 33088
      92: isub
      93: istore        8
      95: goto          119
      98: iload         7
     100: ldc           #131                // int 57408
     102: if_icmplt     119
     105: iload         7
     107: ldc           #132                // int 60351
     109: if_icmpgt     119
     112: iload         7
     114: ldc           #133                // int 49472
     116: isub
     117: istore        8
     119: iload         8
     121: iconst_m1
     122: if_icmpne     135
     125: new           #34                 // class com/google/zxing/WriterException
     128: dup
     129: ldc           #134                // String Invalid byte sequence
     131: invokespecial #36                 // Method com/google/zxing/WriterException."<init>":(Ljava/lang/String;)V
     134: athrow
     135: iload         8
     137: bipush        8
     139: ishr
     140: sipush        192
     143: imul
     144: iload         8
     146: sipush        255
     149: iand
     150: iadd
     151: istore        9
     153: aload_1
     154: iload         9
     156: bipush        13
     158: invokevirtual #86                 // Method com/google/zxing/common/BitArray.appendBits:(II)V
     161: iinc          4, 2
     164: goto          33
     167: return

  private static void appendECI(com.google.zxing.common.CharacterSetECI, com.google.zxing.common.BitArray);
    Code:
       0: aload_1
       1: getstatic     #135                // Field com/google/zxing/qrcode/decoder/Mode.ECI:Lcom/google/zxing/qrcode/decoder/Mode;
       4: invokevirtual #115                // Method com/google/zxing/qrcode/decoder/Mode.getBits:()I
       7: iconst_4
       8: invokevirtual #86                 // Method com/google/zxing/common/BitArray.appendBits:(II)V
      11: aload_1
      12: aload_0
      13: invokevirtual #136                // Method com/google/zxing/common/CharacterSetECI.getValue:()I
      16: bipush        8
      18: invokevirtual #86                 // Method com/google/zxing/common/BitArray.appendBits:(II)V
      21: return

  static {};
    Code:
       0: bipush        96
       2: newarray       int
       4: dup
       5: iconst_0
       6: iconst_m1
       7: iastore
       8: dup
       9: iconst_1
      10: iconst_m1
      11: iastore
      12: dup
      13: iconst_2
      14: iconst_m1
      15: iastore
      16: dup
      17: iconst_3
      18: iconst_m1
      19: iastore
      20: dup
      21: iconst_4
      22: iconst_m1
      23: iastore
      24: dup
      25: iconst_5
      26: iconst_m1
      27: iastore
      28: dup
      29: bipush        6
      31: iconst_m1
      32: iastore
      33: dup
      34: bipush        7
      36: iconst_m1
      37: iastore
      38: dup
      39: bipush        8
      41: iconst_m1
      42: iastore
      43: dup
      44: bipush        9
      46: iconst_m1
      47: iastore
      48: dup
      49: bipush        10
      51: iconst_m1
      52: iastore
      53: dup
      54: bipush        11
      56: iconst_m1
      57: iastore
      58: dup
      59: bipush        12
      61: iconst_m1
      62: iastore
      63: dup
      64: bipush        13
      66: iconst_m1
      67: iastore
      68: dup
      69: bipush        14
      71: iconst_m1
      72: iastore
      73: dup
      74: bipush        15
      76: iconst_m1
      77: iastore
      78: dup
      79: bipush        16
      81: iconst_m1
      82: iastore
      83: dup
      84: bipush        17
      86: iconst_m1
      87: iastore
      88: dup
      89: bipush        18
      91: iconst_m1
      92: iastore
      93: dup
      94: bipush        19
      96: iconst_m1
      97: iastore
      98: dup
      99: bipush        20
     101: iconst_m1
     102: iastore
     103: dup
     104: bipush        21
     106: iconst_m1
     107: iastore
     108: dup
     109: bipush        22
     111: iconst_m1
     112: iastore
     113: dup
     114: bipush        23
     116: iconst_m1
     117: iastore
     118: dup
     119: bipush        24
     121: iconst_m1
     122: iastore
     123: dup
     124: bipush        25
     126: iconst_m1
     127: iastore
     128: dup
     129: bipush        26
     131: iconst_m1
     132: iastore
     133: dup
     134: bipush        27
     136: iconst_m1
     137: iastore
     138: dup
     139: bipush        28
     141: iconst_m1
     142: iastore
     143: dup
     144: bipush        29
     146: iconst_m1
     147: iastore
     148: dup
     149: bipush        30
     151: iconst_m1
     152: iastore
     153: dup
     154: bipush        31
     156: iconst_m1
     157: iastore
     158: dup
     159: bipush        32
     161: bipush        36
     163: iastore
     164: dup
     165: bipush        33
     167: iconst_m1
     168: iastore
     169: dup
     170: bipush        34
     172: iconst_m1
     173: iastore
     174: dup
     175: bipush        35
     177: iconst_m1
     178: iastore
     179: dup
     180: bipush        36
     182: bipush        37
     184: iastore
     185: dup
     186: bipush        37
     188: bipush        38
     190: iastore
     191: dup
     192: bipush        38
     194: iconst_m1
     195: iastore
     196: dup
     197: bipush        39
     199: iconst_m1
     200: iastore
     201: dup
     202: bipush        40
     204: iconst_m1
     205: iastore
     206: dup
     207: bipush        41
     209: iconst_m1
     210: iastore
     211: dup
     212: bipush        42
     214: bipush        39
     216: iastore
     217: dup
     218: bipush        43
     220: bipush        40
     222: iastore
     223: dup
     224: bipush        44
     226: iconst_m1
     227: iastore
     228: dup
     229: bipush        45
     231: bipush        41
     233: iastore
     234: dup
     235: bipush        46
     237: bipush        42
     239: iastore
     240: dup
     241: bipush        47
     243: bipush        43
     245: iastore
     246: dup
     247: bipush        48
     249: iconst_0
     250: iastore
     251: dup
     252: bipush        49
     254: iconst_1
     255: iastore
     256: dup
     257: bipush        50
     259: iconst_2
     260: iastore
     261: dup
     262: bipush        51
     264: iconst_3
     265: iastore
     266: dup
     267: bipush        52
     269: iconst_4
     270: iastore
     271: dup
     272: bipush        53
     274: iconst_5
     275: iastore
     276: dup
     277: bipush        54
     279: bipush        6
     281: iastore
     282: dup
     283: bipush        55
     285: bipush        7
     287: iastore
     288: dup
     289: bipush        56
     291: bipush        8
     293: iastore
     294: dup
     295: bipush        57
     297: bipush        9
     299: iastore
     300: dup
     301: bipush        58
     303: bipush        44
     305: iastore
     306: dup
     307: bipush        59
     309: iconst_m1
     310: iastore
     311: dup
     312: bipush        60
     314: iconst_m1
     315: iastore
     316: dup
     317: bipush        61
     319: iconst_m1
     320: iastore
     321: dup
     322: bipush        62
     324: iconst_m1
     325: iastore
     326: dup
     327: bipush        63
     329: iconst_m1
     330: iastore
     331: dup
     332: bipush        64
     334: iconst_m1
     335: iastore
     336: dup
     337: bipush        65
     339: bipush        10
     341: iastore
     342: dup
     343: bipush        66
     345: bipush        11
     347: iastore
     348: dup
     349: bipush        67
     351: bipush        12
     353: iastore
     354: dup
     355: bipush        68
     357: bipush        13
     359: iastore
     360: dup
     361: bipush        69
     363: bipush        14
     365: iastore
     366: dup
     367: bipush        70
     369: bipush        15
     371: iastore
     372: dup
     373: bipush        71
     375: bipush        16
     377: iastore
     378: dup
     379: bipush        72
     381: bipush        17
     383: iastore
     384: dup
     385: bipush        73
     387: bipush        18
     389: iastore
     390: dup
     391: bipush        74
     393: bipush        19
     395: iastore
     396: dup
     397: bipush        75
     399: bipush        20
     401: iastore
     402: dup
     403: bipush        76
     405: bipush        21
     407: iastore
     408: dup
     409: bipush        77
     411: bipush        22
     413: iastore
     414: dup
     415: bipush        78
     417: bipush        23
     419: iastore
     420: dup
     421: bipush        79
     423: bipush        24
     425: iastore
     426: dup
     427: bipush        80
     429: bipush        25
     431: iastore
     432: dup
     433: bipush        81
     435: bipush        26
     437: iastore
     438: dup
     439: bipush        82
     441: bipush        27
     443: iastore
     444: dup
     445: bipush        83
     447: bipush        28
     449: iastore
     450: dup
     451: bipush        84
     453: bipush        29
     455: iastore
     456: dup
     457: bipush        85
     459: bipush        30
     461: iastore
     462: dup
     463: bipush        86
     465: bipush        31
     467: iastore
     468: dup
     469: bipush        87
     471: bipush        32
     473: iastore
     474: dup
     475: bipush        88
     477: bipush        33
     479: iastore
     480: dup
     481: bipush        89
     483: bipush        34
     485: iastore
     486: dup
     487: bipush        90
     489: bipush        35
     491: iastore
     492: dup
     493: bipush        91
     495: iconst_m1
     496: iastore
     497: dup
     498: bipush        92
     500: iconst_m1
     501: iastore
     502: dup
     503: bipush        93
     505: iconst_m1
     506: iastore
     507: dup
     508: bipush        94
     510: iconst_m1
     511: iastore
     512: dup
     513: bipush        95
     515: iconst_m1
     516: iastore
     517: putstatic     #65                 // Field ALPHANUMERIC_TABLE:[I
     520: getstatic     #137                // Field java/nio/charset/StandardCharsets.ISO_8859_1:Ljava/nio/charset/Charset;
     523: putstatic     #13                 // Field DEFAULT_BYTE_MODE_ENCODING:Ljava/nio/charset/Charset;
     526: return
}
