Compiled from "MatrixUtil.java"
final class com.google.zxing.qrcode.encoder.MatrixUtil {
  private static final int[][] POSITION_DETECTION_PATTERN;

  private static final int[][] POSITION_ADJUSTMENT_PATTERN;

  private static final int[][] POSITION_ADJUSTMENT_PATTERN_COORDINATE_TABLE;

  private static final int[][] TYPE_INFO_COORDINATES;

  private static final int VERSION_INFO_POLY;

  private static final int TYPE_INFO_POLY;

  private static final int TYPE_INFO_MASK_PATTERN;

  private com.google.zxing.qrcode.encoder.MatrixUtil();
    Code:
       0: aload_0
       1: invokespecial #1                  // Method java/lang/Object."<init>":()V
       4: return

  static void clearMatrix(com.google.zxing.qrcode.encoder.ByteMatrix);
    Code:
       0: aload_0
       1: iconst_m1
       2: invokevirtual #2                  // Method com/google/zxing/qrcode/encoder/ByteMatrix.clear:(B)V
       5: return

  static void buildMatrix(com.google.zxing.common.BitArray, com.google.zxing.qrcode.decoder.ErrorCorrectionLevel, com.google.zxing.qrcode.decoder.Version, int, com.google.zxing.qrcode.encoder.ByteMatrix) throws com.google.zxing.WriterException;
    Code:
       0: aload         4
       2: invokestatic  #3                  // Method clearMatrix:(Lcom/google/zxing/qrcode/encoder/ByteMatrix;)V
       5: aload_2
       6: aload         4
       8: invokestatic  #4                  // Method embedBasicPatterns:(Lcom/google/zxing/qrcode/decoder/Version;Lcom/google/zxing/qrcode/encoder/ByteMatrix;)V
      11: aload_1
      12: iload_3
      13: aload         4
      15: invokestatic  #5                  // Method embedTypeInfo:(Lcom/google/zxing/qrcode/decoder/ErrorCorrectionLevel;ILcom/google/zxing/qrcode/encoder/ByteMatrix;)V
      18: aload_2
      19: aload         4
      21: invokestatic  #6                  // Method maybeEmbedVersionInfo:(Lcom/google/zxing/qrcode/decoder/Version;Lcom/google/zxing/qrcode/encoder/ByteMatrix;)V
      24: aload_0
      25: iload_3
      26: aload         4
      28: invokestatic  #7                  // Method embedDataBits:(Lcom/google/zxing/common/BitArray;ILcom/google/zxing/qrcode/encoder/ByteMatrix;)V
      31: return

  static void embedBasicPatterns(com.google.zxing.qrcode.decoder.Version, com.google.zxing.qrcode.encoder.ByteMatrix) throws com.google.zxing.WriterException;
    Code:
       0: aload_1
       1: invokestatic  #8                  // Method embedPositionDetectionPatternsAndSeparators:(Lcom/google/zxing/qrcode/encoder/ByteMatrix;)V
       4: aload_1
       5: invokestatic  #9                  // Method embedDarkDotAtLeftBottomCorner:(Lcom/google/zxing/qrcode/encoder/ByteMatrix;)V
       8: aload_0
       9: aload_1
      10: invokestatic  #10                 // Method maybeEmbedPositionAdjustmentPatterns:(Lcom/google/zxing/qrcode/decoder/Version;Lcom/google/zxing/qrcode/encoder/ByteMatrix;)V
      13: aload_1
      14: invokestatic  #11                 // Method embedTimingPatterns:(Lcom/google/zxing/qrcode/encoder/ByteMatrix;)V
      17: return

  static void embedTypeInfo(com.google.zxing.qrcode.decoder.ErrorCorrectionLevel, int, com.google.zxing.qrcode.encoder.ByteMatrix) throws com.google.zxing.WriterException;
    Code:
       0: new           #12                 // class com/google/zxing/common/BitArray
       3: dup
       4: invokespecial #13                 // Method com/google/zxing/common/BitArray."<init>":()V
       7: astore_3
       8: aload_0
       9: iload_1
      10: aload_3
      11: invokestatic  #14                 // Method makeTypeInfoBits:(Lcom/google/zxing/qrcode/decoder/ErrorCorrectionLevel;ILcom/google/zxing/common/BitArray;)V
      14: iconst_0
      15: istore        4
      17: iload         4
      19: aload_3
      20: invokevirtual #15                 // Method com/google/zxing/common/BitArray.getSize:()I
      23: if_icmpge     131
      26: aload_3
      27: aload_3
      28: invokevirtual #15                 // Method com/google/zxing/common/BitArray.getSize:()I
      31: iconst_1
      32: isub
      33: iload         4
      35: isub
      36: invokevirtual #16                 // Method com/google/zxing/common/BitArray.get:(I)Z
      39: istore        5
      41: getstatic     #17                 // Field TYPE_INFO_COORDINATES:[[I
      44: iload         4
      46: aaload
      47: astore        6
      49: aload         6
      51: iconst_0
      52: iaload
      53: istore        7
      55: aload         6
      57: iconst_1
      58: iaload
      59: istore        8
      61: aload_2
      62: iload         7
      64: iload         8
      66: iload         5
      68: invokevirtual #18                 // Method com/google/zxing/qrcode/encoder/ByteMatrix.set:(IIZ)V
      71: iload         4
      73: bipush        8
      75: if_icmpge     96
      78: aload_2
      79: invokevirtual #19                 // Method com/google/zxing/qrcode/encoder/ByteMatrix.getWidth:()I
      82: iload         4
      84: isub
      85: iconst_1
      86: isub
      87: istore        9
      89: bipush        8
      91: istore        10
      93: goto          115
      96: bipush        8
      98: istore        9
     100: aload_2
     101: invokevirtual #20                 // Method com/google/zxing/qrcode/encoder/ByteMatrix.getHeight:()I
     104: bipush        7
     106: isub
     107: iload         4
     109: bipush        8
     111: isub
     112: iadd
     113: istore        10
     115: aload_2
     116: iload         9
     118: iload         10
     120: iload         5
     122: invokevirtual #18                 // Method com/google/zxing/qrcode/encoder/ByteMatrix.set:(IIZ)V
     125: iinc          4, 1
     128: goto          17
     131: return

  static void maybeEmbedVersionInfo(com.google.zxing.qrcode.decoder.Version, com.google.zxing.qrcode.encoder.ByteMatrix) throws com.google.zxing.WriterException;
    Code:
       0: aload_0
       1: invokevirtual #21                 // Method com/google/zxing/qrcode/decoder/Version.getVersionNumber:()I
       4: bipush        7
       6: if_icmpge     10
       9: return
      10: new           #12                 // class com/google/zxing/common/BitArray
      13: dup
      14: invokespecial #13                 // Method com/google/zxing/common/BitArray."<init>":()V
      17: astore_2
      18: aload_0
      19: aload_2
      20: invokestatic  #22                 // Method makeVersionInfoBits:(Lcom/google/zxing/qrcode/decoder/Version;Lcom/google/zxing/common/BitArray;)V
      23: bipush        17
      25: istore_3
      26: iconst_0
      27: istore        4
      29: iload         4
      31: bipush        6
      33: if_icmpge     103
      36: iconst_0
      37: istore        5
      39: iload         5
      41: iconst_3
      42: if_icmpge     97
      45: aload_2
      46: iload_3
      47: invokevirtual #16                 // Method com/google/zxing/common/BitArray.get:(I)Z
      50: istore        6
      52: iinc          3, -1
      55: aload_1
      56: iload         4
      58: aload_1
      59: invokevirtual #20                 // Method com/google/zxing/qrcode/encoder/ByteMatrix.getHeight:()I
      62: bipush        11
      64: isub
      65: iload         5
      67: iadd
      68: iload         6
      70: invokevirtual #18                 // Method com/google/zxing/qrcode/encoder/ByteMatrix.set:(IIZ)V
      73: aload_1
      74: aload_1
      75: invokevirtual #20                 // Method com/google/zxing/qrcode/encoder/ByteMatrix.getHeight:()I
      78: bipush        11
      80: isub
      81: iload         5
      83: iadd
      84: iload         4
      86: iload         6
      88: invokevirtual #18                 // Method com/google/zxing/qrcode/encoder/ByteMatrix.set:(IIZ)V
      91: iinc          5, 1
      94: goto          39
      97: iinc          4, 1
     100: goto          29
     103: return

  static void embedDataBits(com.google.zxing.common.BitArray, int, com.google.zxing.qrcode.encoder.ByteMatrix) throws com.google.zxing.WriterException;
    Code:
       0: iconst_0
       1: istore_3
       2: iconst_m1
       3: istore        4
       5: aload_2
       6: invokevirtual #19                 // Method com/google/zxing/qrcode/encoder/ByteMatrix.getWidth:()I
       9: iconst_1
      10: isub
      11: istore        5
      13: aload_2
      14: invokevirtual #20                 // Method com/google/zxing/qrcode/encoder/ByteMatrix.getHeight:()I
      17: iconst_1
      18: isub
      19: istore        6
      21: iload         5
      23: ifle          179
      26: iload         5
      28: bipush        6
      30: if_icmpne     36
      33: iinc          5, -1
      36: iload         6
      38: iflt          161
      41: iload         6
      43: aload_2
      44: invokevirtual #20                 // Method com/google/zxing/qrcode/encoder/ByteMatrix.getHeight:()I
      47: if_icmpge     161
      50: iconst_0
      51: istore        7
      53: iload         7
      55: iconst_2
      56: if_icmpge     151
      59: iload         5
      61: iload         7
      63: isub
      64: istore        8
      66: aload_2
      67: iload         8
      69: iload         6
      71: invokevirtual #23                 // Method com/google/zxing/qrcode/encoder/ByteMatrix.get:(II)B
      74: invokestatic  #24                 // Method isEmpty:(I)Z
      77: ifne          83
      80: goto          145
      83: iload_3
      84: aload_0
      85: invokevirtual #15                 // Method com/google/zxing/common/BitArray.getSize:()I
      88: if_icmpge     104
      91: aload_0
      92: iload_3
      93: invokevirtual #16                 // Method com/google/zxing/common/BitArray.get:(I)Z
      96: istore        9
      98: iinc          3, 1
     101: goto          107
     104: iconst_0
     105: istore        9
     107: iload_1
     108: iconst_m1
     109: if_icmpeq     135
     112: iload_1
     113: iload         8
     115: iload         6
     117: invokestatic  #25                 // Method com/google/zxing/qrcode/encoder/MaskUtil.getDataMaskBit:(III)Z
     120: ifeq          135
     123: iload         9
     125: ifne          132
     128: iconst_1
     129: goto          133
     132: iconst_0
     133: istore        9
     135: aload_2
     136: iload         8
     138: iload         6
     140: iload         9
     142: invokevirtual #18                 // Method com/google/zxing/qrcode/encoder/ByteMatrix.set:(IIZ)V
     145: iinc          7, 1
     148: goto          53
     151: iload         6
     153: iload         4
     155: iadd
     156: istore        6
     158: goto          36
     161: iload         4
     163: ineg
     164: istore        4
     166: iload         6
     168: iload         4
     170: iadd
     171: istore        6
     173: iinc          5, -2
     176: goto          21
     179: iload_3
     180: aload_0
     181: invokevirtual #15                 // Method com/google/zxing/common/BitArray.getSize:()I
     184: if_icmpeq     226
     187: new           #26                 // class com/google/zxing/WriterException
     190: dup
     191: new           #27                 // class java/lang/StringBuilder
     194: dup
     195: invokespecial #28                 // Method java/lang/StringBuilder."<init>":()V
     198: ldc           #29                 // String Not all bits consumed:
     200: invokevirtual #30                 // Method java/lang/StringBuilder.append:(Ljava/lang/String;)Ljava/lang/StringBuilder;
     203: iload_3
     204: invokevirtual #31                 // Method java/lang/StringBuilder.append:(I)Ljava/lang/StringBuilder;
     207: bipush        47
     209: invokevirtual #32                 // Method java/lang/StringBuilder.append:(C)Ljava/lang/StringBuilder;
     212: aload_0
     213: invokevirtual #15                 // Method com/google/zxing/common/BitArray.getSize:()I
     216: invokevirtual #31                 // Method java/lang/StringBuilder.append:(I)Ljava/lang/StringBuilder;
     219: invokevirtual #33                 // Method java/lang/StringBuilder.toString:()Ljava/lang/String;
     222: invokespecial #34                 // Method com/google/zxing/WriterException."<init>":(Ljava/lang/String;)V
     225: athrow
     226: return

  static int findMSBSet(int);
    Code:
       0: bipush        32
       2: iload_0
       3: invokestatic  #35                 // Method java/lang/Integer.numberOfLeadingZeros:(I)I
       6: isub
       7: ireturn

  static int calculateBCHCode(int, int);
    Code:
       0: iload_1
       1: ifne          14
       4: new           #36                 // class java/lang/IllegalArgumentException
       7: dup
       8: ldc           #37                 // String 0 polynomial
      10: invokespecial #38                 // Method java/lang/IllegalArgumentException."<init>":(Ljava/lang/String;)V
      13: athrow
      14: iload_1
      15: invokestatic  #39                 // Method findMSBSet:(I)I
      18: istore_2
      19: iload_0
      20: iload_2
      21: iconst_1
      22: isub
      23: ishl
      24: istore_0
      25: iload_0
      26: invokestatic  #39                 // Method findMSBSet:(I)I
      29: iload_2
      30: if_icmplt     47
      33: iload_0
      34: iload_1
      35: iload_0
      36: invokestatic  #39                 // Method findMSBSet:(I)I
      39: iload_2
      40: isub
      41: ishl
      42: ixor
      43: istore_0
      44: goto          25
      47: iload_0
      48: ireturn

  static void makeTypeInfoBits(com.google.zxing.qrcode.decoder.ErrorCorrectionLevel, int, com.google.zxing.common.BitArray) throws com.google.zxing.WriterException;
    Code:
       0: iload_1
       1: invokestatic  #40                 // Method com/google/zxing/qrcode/encoder/QRCode.isValidMaskPattern:(I)Z
       4: ifne          17
       7: new           #26                 // class com/google/zxing/WriterException
      10: dup
      11: ldc           #41                 // String Invalid mask pattern
      13: invokespecial #34                 // Method com/google/zxing/WriterException."<init>":(Ljava/lang/String;)V
      16: athrow
      17: aload_0
      18: invokevirtual #42                 // Method com/google/zxing/qrcode/decoder/ErrorCorrectionLevel.getBits:()I
      21: iconst_3
      22: ishl
      23: iload_1
      24: ior
      25: istore_3
      26: aload_2
      27: iload_3
      28: iconst_5
      29: invokevirtual #43                 // Method com/google/zxing/common/BitArray.appendBits:(II)V
      32: iload_3
      33: sipush        1335
      36: invokestatic  #45                 // Method calculateBCHCode:(II)I
      39: istore        4
      41: aload_2
      42: iload         4
      44: bipush        10
      46: invokevirtual #43                 // Method com/google/zxing/common/BitArray.appendBits:(II)V
      49: new           #12                 // class com/google/zxing/common/BitArray
      52: dup
      53: invokespecial #13                 // Method com/google/zxing/common/BitArray."<init>":()V
      56: astore        5
      58: aload         5
      60: sipush        21522
      63: bipush        15
      65: invokevirtual #43                 // Method com/google/zxing/common/BitArray.appendBits:(II)V
      68: aload_2
      69: aload         5
      71: invokevirtual #46                 // Method com/google/zxing/common/BitArray.xor:(Lcom/google/zxing/common/BitArray;)V
      74: aload_2
      75: invokevirtual #15                 // Method com/google/zxing/common/BitArray.getSize:()I
      78: bipush        15
      80: if_icmpeq     113
      83: new           #26                 // class com/google/zxing/WriterException
      86: dup
      87: new           #27                 // class java/lang/StringBuilder
      90: dup
      91: invokespecial #28                 // Method java/lang/StringBuilder."<init>":()V
      94: ldc           #47                 // String should not happen but we got:
      96: invokevirtual #30                 // Method java/lang/StringBuilder.append:(Ljava/lang/String;)Ljava/lang/StringBuilder;
      99: aload_2
     100: invokevirtual #15                 // Method com/google/zxing/common/BitArray.getSize:()I
     103: invokevirtual #31                 // Method java/lang/StringBuilder.append:(I)Ljava/lang/StringBuilder;
     106: invokevirtual #33                 // Method java/lang/StringBuilder.toString:()Ljava/lang/String;
     109: invokespecial #34                 // Method com/google/zxing/WriterException."<init>":(Ljava/lang/String;)V
     112: athrow
     113: return

  static void makeVersionInfoBits(com.google.zxing.qrcode.decoder.Version, com.google.zxing.common.BitArray) throws com.google.zxing.WriterException;
    Code:
       0: aload_1
       1: aload_0
       2: invokevirtual #21                 // Method com/google/zxing/qrcode/decoder/Version.getVersionNumber:()I
       5: bipush        6
       7: invokevirtual #43                 // Method com/google/zxing/common/BitArray.appendBits:(II)V
      10: aload_0
      11: invokevirtual #21                 // Method com/google/zxing/qrcode/decoder/Version.getVersionNumber:()I
      14: sipush        7973
      17: invokestatic  #45                 // Method calculateBCHCode:(II)I
      20: istore_2
      21: aload_1
      22: iload_2
      23: bipush        12
      25: invokevirtual #43                 // Method com/google/zxing/common/BitArray.appendBits:(II)V
      28: aload_1
      29: invokevirtual #15                 // Method com/google/zxing/common/BitArray.getSize:()I
      32: bipush        18
      34: if_icmpeq     67
      37: new           #26                 // class com/google/zxing/WriterException
      40: dup
      41: new           #27                 // class java/lang/StringBuilder
      44: dup
      45: invokespecial #28                 // Method java/lang/StringBuilder."<init>":()V
      48: ldc           #47                 // String should not happen but we got:
      50: invokevirtual #30                 // Method java/lang/StringBuilder.append:(Ljava/lang/String;)Ljava/lang/StringBuilder;
      53: aload_1
      54: invokevirtual #15                 // Method com/google/zxing/common/BitArray.getSize:()I
      57: invokevirtual #31                 // Method java/lang/StringBuilder.append:(I)Ljava/lang/StringBuilder;
      60: invokevirtual #33                 // Method java/lang/StringBuilder.toString:()Ljava/lang/String;
      63: invokespecial #34                 // Method com/google/zxing/WriterException."<init>":(Ljava/lang/String;)V
      66: athrow
      67: return

  private static boolean isEmpty(int);
    Code:
       0: iload_0
       1: iconst_m1
       2: if_icmpne     9
       5: iconst_1
       6: goto          10
       9: iconst_0
      10: ireturn

  private static void embedTimingPatterns(com.google.zxing.qrcode.encoder.ByteMatrix);
    Code:
       0: bipush        8
       2: istore_1
       3: iload_1
       4: aload_0
       5: invokevirtual #19                 // Method com/google/zxing/qrcode/encoder/ByteMatrix.getWidth:()I
       8: bipush        8
      10: isub
      11: if_icmpge     68
      14: iload_1
      15: iconst_1
      16: iadd
      17: iconst_2
      18: irem
      19: istore_2
      20: aload_0
      21: iload_1
      22: bipush        6
      24: invokevirtual #23                 // Method com/google/zxing/qrcode/encoder/ByteMatrix.get:(II)B
      27: invokestatic  #24                 // Method isEmpty:(I)Z
      30: ifeq          41
      33: aload_0
      34: iload_1
      35: bipush        6
      37: iload_2
      38: invokevirtual #48                 // Method com/google/zxing/qrcode/encoder/ByteMatrix.set:(III)V
      41: aload_0
      42: bipush        6
      44: iload_1
      45: invokevirtual #23                 // Method com/google/zxing/qrcode/encoder/ByteMatrix.get:(II)B
      48: invokestatic  #24                 // Method isEmpty:(I)Z
      51: ifeq          62
      54: aload_0
      55: bipush        6
      57: iload_1
      58: iload_2
      59: invokevirtual #48                 // Method com/google/zxing/qrcode/encoder/ByteMatrix.set:(III)V
      62: iinc          1, 1
      65: goto          3
      68: return

  private static void embedDarkDotAtLeftBottomCorner(com.google.zxing.qrcode.encoder.ByteMatrix) throws com.google.zxing.WriterException;
    Code:
       0: aload_0
       1: bipush        8
       3: aload_0
       4: invokevirtual #20                 // Method com/google/zxing/qrcode/encoder/ByteMatrix.getHeight:()I
       7: bipush        8
       9: isub
      10: invokevirtual #23                 // Method com/google/zxing/qrcode/encoder/ByteMatrix.get:(II)B
      13: ifne          24
      16: new           #26                 // class com/google/zxing/WriterException
      19: dup
      20: invokespecial #49                 // Method com/google/zxing/WriterException."<init>":()V
      23: athrow
      24: aload_0
      25: bipush        8
      27: aload_0
      28: invokevirtual #20                 // Method com/google/zxing/qrcode/encoder/ByteMatrix.getHeight:()I
      31: bipush        8
      33: isub
      34: iconst_1
      35: invokevirtual #48                 // Method com/google/zxing/qrcode/encoder/ByteMatrix.set:(III)V
      38: return

  private static void embedHorizontalSeparationPattern(int, int, com.google.zxing.qrcode.encoder.ByteMatrix) throws com.google.zxing.WriterException;
    Code:
       0: iconst_0
       1: istore_3
       2: iload_3
       3: bipush        8
       5: if_icmpge     45
       8: aload_2
       9: iload_0
      10: iload_3
      11: iadd
      12: iload_1
      13: invokevirtual #23                 // Method com/google/zxing/qrcode/encoder/ByteMatrix.get:(II)B
      16: invokestatic  #24                 // Method isEmpty:(I)Z
      19: ifne          30
      22: new           #26                 // class com/google/zxing/WriterException
      25: dup
      26: invokespecial #49                 // Method com/google/zxing/WriterException."<init>":()V
      29: athrow
      30: aload_2
      31: iload_0
      32: iload_3
      33: iadd
      34: iload_1
      35: iconst_0
      36: invokevirtual #48                 // Method com/google/zxing/qrcode/encoder/ByteMatrix.set:(III)V
      39: iinc          3, 1
      42: goto          2
      45: return

  private static void embedVerticalSeparationPattern(int, int, com.google.zxing.qrcode.encoder.ByteMatrix) throws com.google.zxing.WriterException;
    Code:
       0: iconst_0
       1: istore_3
       2: iload_3
       3: bipush        7
       5: if_icmpge     45
       8: aload_2
       9: iload_0
      10: iload_1
      11: iload_3
      12: iadd
      13: invokevirtual #23                 // Method com/google/zxing/qrcode/encoder/ByteMatrix.get:(II)B
      16: invokestatic  #24                 // Method isEmpty:(I)Z
      19: ifne          30
      22: new           #26                 // class com/google/zxing/WriterException
      25: dup
      26: invokespecial #49                 // Method com/google/zxing/WriterException."<init>":()V
      29: athrow
      30: aload_2
      31: iload_0
      32: iload_1
      33: iload_3
      34: iadd
      35: iconst_0
      36: invokevirtual #48                 // Method com/google/zxing/qrcode/encoder/ByteMatrix.set:(III)V
      39: iinc          3, 1
      42: goto          2
      45: return

  private static void embedPositionAdjustmentPattern(int, int, com.google.zxing.qrcode.encoder.ByteMatrix);
    Code:
       0: iconst_0
       1: istore_3
       2: iload_3
       3: iconst_5
       4: if_icmpge     51
       7: getstatic     #50                 // Field POSITION_ADJUSTMENT_PATTERN:[[I
      10: iload_3
      11: aaload
      12: astore        4
      14: iconst_0
      15: istore        5
      17: iload         5
      19: iconst_5
      20: if_icmpge     45
      23: aload_2
      24: iload_0
      25: iload         5
      27: iadd
      28: iload_1
      29: iload_3
      30: iadd
      31: aload         4
      33: iload         5
      35: iaload
      36: invokevirtual #48                 // Method com/google/zxing/qrcode/encoder/ByteMatrix.set:(III)V
      39: iinc          5, 1
      42: goto          17
      45: iinc          3, 1
      48: goto          2
      51: return

  private static void embedPositionDetectionPattern(int, int, com.google.zxing.qrcode.encoder.ByteMatrix);
    Code:
       0: iconst_0
       1: istore_3
       2: iload_3
       3: bipush        7
       5: if_icmpge     53
       8: getstatic     #51                 // Field POSITION_DETECTION_PATTERN:[[I
      11: iload_3
      12: aaload
      13: astore        4
      15: iconst_0
      16: istore        5
      18: iload         5
      20: bipush        7
      22: if_icmpge     47
      25: aload_2
      26: iload_0
      27: iload         5
      29: iadd
      30: iload_1
      31: iload_3
      32: iadd
      33: aload         4
      35: iload         5
      37: iaload
      38: invokevirtual #48                 // Method com/google/zxing/qrcode/encoder/ByteMatrix.set:(III)V
      41: iinc          5, 1
      44: goto          18
      47: iinc          3, 1
      50: goto          2
      53: return

  private static void embedPositionDetectionPatternsAndSeparators(com.google.zxing.qrcode.encoder.ByteMatrix) throws com.google.zxing.WriterException;
    Code:
       0: getstatic     #51                 // Field POSITION_DETECTION_PATTERN:[[I
       3: iconst_0
       4: aaload
       5: arraylength
       6: istore_1
       7: iconst_0
       8: iconst_0
       9: aload_0
      10: invokestatic  #52                 // Method embedPositionDetectionPattern:(IILcom/google/zxing/qrcode/encoder/ByteMatrix;)V
      13: aload_0
      14: invokevirtual #19                 // Method com/google/zxing/qrcode/encoder/ByteMatrix.getWidth:()I
      17: iload_1
      18: isub
      19: iconst_0
      20: aload_0
      21: invokestatic  #52                 // Method embedPositionDetectionPattern:(IILcom/google/zxing/qrcode/encoder/ByteMatrix;)V
      24: iconst_0
      25: aload_0
      26: invokevirtual #19                 // Method com/google/zxing/qrcode/encoder/ByteMatrix.getWidth:()I
      29: iload_1
      30: isub
      31: aload_0
      32: invokestatic  #52                 // Method embedPositionDetectionPattern:(IILcom/google/zxing/qrcode/encoder/ByteMatrix;)V
      35: bipush        8
      37: istore_2
      38: iconst_0
      39: iload_2
      40: iconst_1
      41: isub
      42: aload_0
      43: invokestatic  #53                 // Method embedHorizontalSeparationPattern:(IILcom/google/zxing/qrcode/encoder/ByteMatrix;)V
      46: aload_0
      47: invokevirtual #19                 // Method com/google/zxing/qrcode/encoder/ByteMatrix.getWidth:()I
      50: iload_2
      51: isub
      52: iload_2
      53: iconst_1
      54: isub
      55: aload_0
      56: invokestatic  #53                 // Method embedHorizontalSeparationPattern:(IILcom/google/zxing/qrcode/encoder/ByteMatrix;)V
      59: iconst_0
      60: aload_0
      61: invokevirtual #19                 // Method com/google/zxing/qrcode/encoder/ByteMatrix.getWidth:()I
      64: iload_2
      65: isub
      66: aload_0
      67: invokestatic  #53                 // Method embedHorizontalSeparationPattern:(IILcom/google/zxing/qrcode/encoder/ByteMatrix;)V
      70: bipush        7
      72: istore_3
      73: iload_3
      74: iconst_0
      75: aload_0
      76: invokestatic  #54                 // Method embedVerticalSeparationPattern:(IILcom/google/zxing/qrcode/encoder/ByteMatrix;)V
      79: aload_0
      80: invokevirtual #20                 // Method com/google/zxing/qrcode/encoder/ByteMatrix.getHeight:()I
      83: iload_3
      84: isub
      85: iconst_1
      86: isub
      87: iconst_0
      88: aload_0
      89: invokestatic  #54                 // Method embedVerticalSeparationPattern:(IILcom/google/zxing/qrcode/encoder/ByteMatrix;)V
      92: iload_3
      93: aload_0
      94: invokevirtual #20                 // Method com/google/zxing/qrcode/encoder/ByteMatrix.getHeight:()I
      97: iload_3
      98: isub
      99: aload_0
     100: invokestatic  #54                 // Method embedVerticalSeparationPattern:(IILcom/google/zxing/qrcode/encoder/ByteMatrix;)V
     103: return

  private static void maybeEmbedPositionAdjustmentPatterns(com.google.zxing.qrcode.decoder.Version, com.google.zxing.qrcode.encoder.ByteMatrix);
    Code:
       0: aload_0
       1: invokevirtual #21                 // Method com/google/zxing/qrcode/decoder/Version.getVersionNumber:()I
       4: iconst_2
       5: if_icmpge     9
       8: return
       9: aload_0
      10: invokevirtual #21                 // Method com/google/zxing/qrcode/decoder/Version.getVersionNumber:()I
      13: iconst_1
      14: isub
      15: istore_2
      16: getstatic     #55                 // Field POSITION_ADJUSTMENT_PATTERN_COORDINATE_TABLE:[[I
      19: iload_2
      20: aaload
      21: astore_3
      22: aload_3
      23: astore        4
      25: aload         4
      27: arraylength
      28: istore        5
      30: iconst_0
      31: istore        6
      33: iload         6
      35: iload         5
      37: if_icmpge     120
      40: aload         4
      42: iload         6
      44: iaload
      45: istore        7
      47: iload         7
      49: iflt          114
      52: aload_3
      53: astore        8
      55: aload         8
      57: arraylength
      58: istore        9
      60: iconst_0
      61: istore        10
      63: iload         10
      65: iload         9
      67: if_icmpge     114
      70: aload         8
      72: iload         10
      74: iaload
      75: istore        11
      77: iload         11
      79: iflt          108
      82: aload_1
      83: iload         11
      85: iload         7
      87: invokevirtual #23                 // Method com/google/zxing/qrcode/encoder/ByteMatrix.get:(II)B
      90: invokestatic  #24                 // Method isEmpty:(I)Z
      93: ifeq          108
      96: iload         11
      98: iconst_2
      99: isub
     100: iload         7
     102: iconst_2
     103: isub
     104: aload_1
     105: invokestatic  #56                 // Method embedPositionAdjustmentPattern:(IILcom/google/zxing/qrcode/encoder/ByteMatrix;)V
     108: iinc          10, 1
     111: goto          63
     114: iinc          6, 1
     117: goto          33
     120: return

  static {};
    Code:
       0: bipush        7
       2: anewarray     #57                 // class "[I"
       5: dup
       6: iconst_0
       7: bipush        7
       9: newarray       int
      11: dup
      12: iconst_0
      13: iconst_1
      14: iastore
      15: dup
      16: iconst_1
      17: iconst_1
      18: iastore
      19: dup
      20: iconst_2
      21: iconst_1
      22: iastore
      23: dup
      24: iconst_3
      25: iconst_1
      26: iastore
      27: dup
      28: iconst_4
      29: iconst_1
      30: iastore
      31: dup
      32: iconst_5
      33: iconst_1
      34: iastore
      35: dup
      36: bipush        6
      38: iconst_1
      39: iastore
      40: aastore
      41: dup
      42: iconst_1
      43: bipush        7
      45: newarray       int
      47: dup
      48: iconst_0
      49: iconst_1
      50: iastore
      51: dup
      52: iconst_1
      53: iconst_0
      54: iastore
      55: dup
      56: iconst_2
      57: iconst_0
      58: iastore
      59: dup
      60: iconst_3
      61: iconst_0
      62: iastore
      63: dup
      64: iconst_4
      65: iconst_0
      66: iastore
      67: dup
      68: iconst_5
      69: iconst_0
      70: iastore
      71: dup
      72: bipush        6
      74: iconst_1
      75: iastore
      76: aastore
      77: dup
      78: iconst_2
      79: bipush        7
      81: newarray       int
      83: dup
      84: iconst_0
      85: iconst_1
      86: iastore
      87: dup
      88: iconst_1
      89: iconst_0
      90: iastore
      91: dup
      92: iconst_2
      93: iconst_1
      94: iastore
      95: dup
      96: iconst_3
      97: iconst_1
      98: iastore
      99: dup
     100: iconst_4
     101: iconst_1
     102: iastore
     103: dup
     104: iconst_5
     105: iconst_0
     106: iastore
     107: dup
     108: bipush        6
     110: iconst_1
     111: iastore
     112: aastore
     113: dup
     114: iconst_3
     115: bipush        7
     117: newarray       int
     119: dup
     120: iconst_0
     121: iconst_1
     122: iastore
     123: dup
     124: iconst_1
     125: iconst_0
     126: iastore
     127: dup
     128: iconst_2
     129: iconst_1
     130: iastore
     131: dup
     132: iconst_3
     133: iconst_1
     134: iastore
     135: dup
     136: iconst_4
     137: iconst_1
     138: iastore
     139: dup
     140: iconst_5
     141: iconst_0
     142: iastore
     143: dup
     144: bipush        6
     146: iconst_1
     147: iastore
     148: aastore
     149: dup
     150: iconst_4
     151: bipush        7
     153: newarray       int
     155: dup
     156: iconst_0
     157: iconst_1
     158: iastore
     159: dup
     160: iconst_1
     161: iconst_0
     162: iastore
     163: dup
     164: iconst_2
     165: iconst_1
     166: iastore
     167: dup
     168: iconst_3
     169: iconst_1
     170: iastore
     171: dup
     172: iconst_4
     173: iconst_1
     174: iastore
     175: dup
     176: iconst_5
     177: iconst_0
     178: iastore
     179: dup
     180: bipush        6
     182: iconst_1
     183: iastore
     184: aastore
     185: dup
     186: iconst_5
     187: bipush        7
     189: newarray       int
     191: dup
     192: iconst_0
     193: iconst_1
     194: iastore
     195: dup
     196: iconst_1
     197: iconst_0
     198: iastore
     199: dup
     200: iconst_2
     201: iconst_0
     202: iastore
     203: dup
     204: iconst_3
     205: iconst_0
     206: iastore
     207: dup
     208: iconst_4
     209: iconst_0
     210: iastore
     211: dup
     212: iconst_5
     213: iconst_0
     214: iastore
     215: dup
     216: bipush        6
     218: iconst_1
     219: iastore
     220: aastore
     221: dup
     222: bipush        6
     224: bipush        7
     226: newarray       int
     228: dup
     229: iconst_0
     230: iconst_1
     231: iastore
     232: dup
     233: iconst_1
     234: iconst_1
     235: iastore
     236: dup
     237: iconst_2
     238: iconst_1
     239: iastore
     240: dup
     241: iconst_3
     242: iconst_1
     243: iastore
     244: dup
     245: iconst_4
     246: iconst_1
     247: iastore
     248: dup
     249: iconst_5
     250: iconst_1
     251: iastore
     252: dup
     253: bipush        6
     255: iconst_1
     256: iastore
     257: aastore
     258: putstatic     #51                 // Field POSITION_DETECTION_PATTERN:[[I
     261: iconst_5
     262: anewarray     #57                 // class "[I"
     265: dup
     266: iconst_0
     267: iconst_5
     268: newarray       int
     270: dup
     271: iconst_0
     272: iconst_1
     273: iastore
     274: dup
     275: iconst_1
     276: iconst_1
     277: iastore
     278: dup
     279: iconst_2
     280: iconst_1
     281: iastore
     282: dup
     283: iconst_3
     284: iconst_1
     285: iastore
     286: dup
     287: iconst_4
     288: iconst_1
     289: iastore
     290: aastore
     291: dup
     292: iconst_1
     293: iconst_5
     294: newarray       int
     296: dup
     297: iconst_0
     298: iconst_1
     299: iastore
     300: dup
     301: iconst_1
     302: iconst_0
     303: iastore
     304: dup
     305: iconst_2
     306: iconst_0
     307: iastore
     308: dup
     309: iconst_3
     310: iconst_0
     311: iastore
     312: dup
     313: iconst_4
     314: iconst_1
     315: iastore
     316: aastore
     317: dup
     318: iconst_2
     319: iconst_5
     320: newarray       int
     322: dup
     323: iconst_0
     324: iconst_1
     325: iastore
     326: dup
     327: iconst_1
     328: iconst_0
     329: iastore
     330: dup
     331: iconst_2
     332: iconst_1
     333: iastore
     334: dup
     335: iconst_3
     336: iconst_0
     337: iastore
     338: dup
     339: iconst_4
     340: iconst_1
     341: iastore
     342: aastore
     343: dup
     344: iconst_3
     345: iconst_5
     346: newarray       int
     348: dup
     349: iconst_0
     350: iconst_1
     351: iastore
     352: dup
     353: iconst_1
     354: iconst_0
     355: iastore
     356: dup
     357: iconst_2
     358: iconst_0
     359: iastore
     360: dup
     361: iconst_3
     362: iconst_0
     363: iastore
     364: dup
     365: iconst_4
     366: iconst_1
     367: iastore
     368: aastore
     369: dup
     370: iconst_4
     371: iconst_5
     372: newarray       int
     374: dup
     375: iconst_0
     376: iconst_1
     377: iastore
     378: dup
     379: iconst_1
     380: iconst_1
     381: iastore
     382: dup
     383: iconst_2
     384: iconst_1
     385: iastore
     386: dup
     387: iconst_3
     388: iconst_1
     389: iastore
     390: dup
     391: iconst_4
     392: iconst_1
     393: iastore
     394: aastore
     395: putstatic     #50                 // Field POSITION_ADJUSTMENT_PATTERN:[[I
     398: bipush        40
     400: anewarray     #57                 // class "[I"
     403: dup
     404: iconst_0
     405: bipush        7
     407: newarray       int
     409: dup
     410: iconst_0
     411: iconst_m1
     412: iastore
     413: dup
     414: iconst_1
     415: iconst_m1
     416: iastore
     417: dup
     418: iconst_2
     419: iconst_m1
     420: iastore
     421: dup
     422: iconst_3
     423: iconst_m1
     424: iastore
     425: dup
     426: iconst_4
     427: iconst_m1
     428: iastore
     429: dup
     430: iconst_5
     431: iconst_m1
     432: iastore
     433: dup
     434: bipush        6
     436: iconst_m1
     437: iastore
     438: aastore
     439: dup
     440: iconst_1
     441: bipush        7
     443: newarray       int
     445: dup
     446: iconst_0
     447: bipush        6
     449: iastore
     450: dup
     451: iconst_1
     452: bipush        18
     454: iastore
     455: dup
     456: iconst_2
     457: iconst_m1
     458: iastore
     459: dup
     460: iconst_3
     461: iconst_m1
     462: iastore
     463: dup
     464: iconst_4
     465: iconst_m1
     466: iastore
     467: dup
     468: iconst_5
     469: iconst_m1
     470: iastore
     471: dup
     472: bipush        6
     474: iconst_m1
     475: iastore
     476: aastore
     477: dup
     478: iconst_2
     479: bipush        7
     481: newarray       int
     483: dup
     484: iconst_0
     485: bipush        6
     487: iastore
     488: dup
     489: iconst_1
     490: bipush        22
     492: iastore
     493: dup
     494: iconst_2
     495: iconst_m1
     496: iastore
     497: dup
     498: iconst_3
     499: iconst_m1
     500: iastore
     501: dup
     502: iconst_4
     503: iconst_m1
     504: iastore
     505: dup
     506: iconst_5
     507: iconst_m1
     508: iastore
     509: dup
     510: bipush        6
     512: iconst_m1
     513: iastore
     514: aastore
     515: dup
     516: iconst_3
     517: bipush        7
     519: newarray       int
     521: dup
     522: iconst_0
     523: bipush        6
     525: iastore
     526: dup
     527: iconst_1
     528: bipush        26
     530: iastore
     531: dup
     532: iconst_2
     533: iconst_m1
     534: iastore
     535: dup
     536: iconst_3
     537: iconst_m1
     538: iastore
     539: dup
     540: iconst_4
     541: iconst_m1
     542: iastore
     543: dup
     544: iconst_5
     545: iconst_m1
     546: iastore
     547: dup
     548: bipush        6
     550: iconst_m1
     551: iastore
     552: aastore
     553: dup
     554: iconst_4
     555: bipush        7
     557: newarray       int
     559: dup
     560: iconst_0
     561: bipush        6
     563: iastore
     564: dup
     565: iconst_1
     566: bipush        30
     568: iastore
     569: dup
     570: iconst_2
     571: iconst_m1
     572: iastore
     573: dup
     574: iconst_3
     575: iconst_m1
     576: iastore
     577: dup
     578: iconst_4
     579: iconst_m1
     580: iastore
     581: dup
     582: iconst_5
     583: iconst_m1
     584: iastore
     585: dup
     586: bipush        6
     588: iconst_m1
     589: iastore
     590: aastore
     591: dup
     592: iconst_5
     593: bipush        7
     595: newarray       int
     597: dup
     598: iconst_0
     599: bipush        6
     601: iastore
     602: dup
     603: iconst_1
     604: bipush        34
     606: iastore
     607: dup
     608: iconst_2
     609: iconst_m1
     610: iastore
     611: dup
     612: iconst_3
     613: iconst_m1
     614: iastore
     615: dup
     616: iconst_4
     617: iconst_m1
     618: iastore
     619: dup
     620: iconst_5
     621: iconst_m1
     622: iastore
     623: dup
     624: bipush        6
     626: iconst_m1
     627: iastore
     628: aastore
     629: dup
     630: bipush        6
     632: bipush        7
     634: newarray       int
     636: dup
     637: iconst_0
     638: bipush        6
     640: iastore
     641: dup
     642: iconst_1
     643: bipush        22
     645: iastore
     646: dup
     647: iconst_2
     648: bipush        38
     650: iastore
     651: dup
     652: iconst_3
     653: iconst_m1
     654: iastore
     655: dup
     656: iconst_4
     657: iconst_m1
     658: iastore
     659: dup
     660: iconst_5
     661: iconst_m1
     662: iastore
     663: dup
     664: bipush        6
     666: iconst_m1
     667: iastore
     668: aastore
     669: dup
     670: bipush        7
     672: bipush        7
     674: newarray       int
     676: dup
     677: iconst_0
     678: bipush        6
     680: iastore
     681: dup
     682: iconst_1
     683: bipush        24
     685: iastore
     686: dup
     687: iconst_2
     688: bipush        42
     690: iastore
     691: dup
     692: iconst_3
     693: iconst_m1
     694: iastore
     695: dup
     696: iconst_4
     697: iconst_m1
     698: iastore
     699: dup
     700: iconst_5
     701: iconst_m1
     702: iastore
     703: dup
     704: bipush        6
     706: iconst_m1
     707: iastore
     708: aastore
     709: dup
     710: bipush        8
     712: bipush        7
     714: newarray       int
     716: dup
     717: iconst_0
     718: bipush        6
     720: iastore
     721: dup
     722: iconst_1
     723: bipush        26
     725: iastore
     726: dup
     727: iconst_2
     728: bipush        46
     730: iastore
     731: dup
     732: iconst_3
     733: iconst_m1
     734: iastore
     735: dup
     736: iconst_4
     737: iconst_m1
     738: iastore
     739: dup
     740: iconst_5
     741: iconst_m1
     742: iastore
     743: dup
     744: bipush        6
     746: iconst_m1
     747: iastore
     748: aastore
     749: dup
     750: bipush        9
     752: bipush        7
     754: newarray       int
     756: dup
     757: iconst_0
     758: bipush        6
     760: iastore
     761: dup
     762: iconst_1
     763: bipush        28
     765: iastore
     766: dup
     767: iconst_2
     768: bipush        50
     770: iastore
     771: dup
     772: iconst_3
     773: iconst_m1
     774: iastore
     775: dup
     776: iconst_4
     777: iconst_m1
     778: iastore
     779: dup
     780: iconst_5
     781: iconst_m1
     782: iastore
     783: dup
     784: bipush        6
     786: iconst_m1
     787: iastore
     788: aastore
     789: dup
     790: bipush        10
     792: bipush        7
     794: newarray       int
     796: dup
     797: iconst_0
     798: bipush        6
     800: iastore
     801: dup
     802: iconst_1
     803: bipush        30
     805: iastore
     806: dup
     807: iconst_2
     808: bipush        54
     810: iastore
     811: dup
     812: iconst_3
     813: iconst_m1
     814: iastore
     815: dup
     816: iconst_4
     817: iconst_m1
     818: iastore
     819: dup
     820: iconst_5
     821: iconst_m1
     822: iastore
     823: dup
     824: bipush        6
     826: iconst_m1
     827: iastore
     828: aastore
     829: dup
     830: bipush        11
     832: bipush        7
     834: newarray       int
     836: dup
     837: iconst_0
     838: bipush        6
     840: iastore
     841: dup
     842: iconst_1
     843: bipush        32
     845: iastore
     846: dup
     847: iconst_2
     848: bipush        58
     850: iastore
     851: dup
     852: iconst_3
     853: iconst_m1
     854: iastore
     855: dup
     856: iconst_4
     857: iconst_m1
     858: iastore
     859: dup
     860: iconst_5
     861: iconst_m1
     862: iastore
     863: dup
     864: bipush        6
     866: iconst_m1
     867: iastore
     868: aastore
     869: dup
     870: bipush        12
     872: bipush        7
     874: newarray       int
     876: dup
     877: iconst_0
     878: bipush        6
     880: iastore
     881: dup
     882: iconst_1
     883: bipush        34
     885: iastore
     886: dup
     887: iconst_2
     888: bipush        62
     890: iastore
     891: dup
     892: iconst_3
     893: iconst_m1
     894: iastore
     895: dup
     896: iconst_4
     897: iconst_m1
     898: iastore
     899: dup
     900: iconst_5
     901: iconst_m1
     902: iastore
     903: dup
     904: bipush        6
     906: iconst_m1
     907: iastore
     908: aastore
     909: dup
     910: bipush        13
     912: bipush        7
     914: newarray       int
     916: dup
     917: iconst_0
     918: bipush        6
     920: iastore
     921: dup
     922: iconst_1
     923: bipush        26
     925: iastore
     926: dup
     927: iconst_2
     928: bipush        46
     930: iastore
     931: dup
     932: iconst_3
     933: bipush        66
     935: iastore
     936: dup
     937: iconst_4
     938: iconst_m1
     939: iastore
     940: dup
     941: iconst_5
     942: iconst_m1
     943: iastore
     944: dup
     945: bipush        6
     947: iconst_m1
     948: iastore
     949: aastore
     950: dup
     951: bipush        14
     953: bipush        7
     955: newarray       int
     957: dup
     958: iconst_0
     959: bipush        6
     961: iastore
     962: dup
     963: iconst_1
     964: bipush        26
     966: iastore
     967: dup
     968: iconst_2
     969: bipush        48
     971: iastore
     972: dup
     973: iconst_3
     974: bipush        70
     976: iastore
     977: dup
     978: iconst_4
     979: iconst_m1
     980: iastore
     981: dup
     982: iconst_5
     983: iconst_m1
     984: iastore
     985: dup
     986: bipush        6
     988: iconst_m1
     989: iastore
     990: aastore
     991: dup
     992: bipush        15
     994: bipush        7
     996: newarray       int
     998: dup
     999: iconst_0
    1000: bipush        6
    1002: iastore
    1003: dup
    1004: iconst_1
    1005: bipush        26
    1007: iastore
    1008: dup
    1009: iconst_2
    1010: bipush        50
    1012: iastore
    1013: dup
    1014: iconst_3
    1015: bipush        74
    1017: iastore
    1018: dup
    1019: iconst_4
    1020: iconst_m1
    1021: iastore
    1022: dup
    1023: iconst_5
    1024: iconst_m1
    1025: iastore
    1026: dup
    1027: bipush        6
    1029: iconst_m1
    1030: iastore
    1031: aastore
    1032: dup
    1033: bipush        16
    1035: bipush        7
    1037: newarray       int
    1039: dup
    1040: iconst_0
    1041: bipush        6
    1043: iastore
    1044: dup
    1045: iconst_1
    1046: bipush        30
    1048: iastore
    1049: dup
    1050: iconst_2
    1051: bipush        54
    1053: iastore
    1054: dup
    1055: iconst_3
    1056: bipush        78
    1058: iastore
    1059: dup
    1060: iconst_4
    1061: iconst_m1
    1062: iastore
    1063: dup
    1064: iconst_5
    1065: iconst_m1
    1066: iastore
    1067: dup
    1068: bipush        6
    1070: iconst_m1
    1071: iastore
    1072: aastore
    1073: dup
    1074: bipush        17
    1076: bipush        7
    1078: newarray       int
    1080: dup
    1081: iconst_0
    1082: bipush        6
    1084: iastore
    1085: dup
    1086: iconst_1
    1087: bipush        30
    1089: iastore
    1090: dup
    1091: iconst_2
    1092: bipush        56
    1094: iastore
    1095: dup
    1096: iconst_3
    1097: bipush        82
    1099: iastore
    1100: dup
    1101: iconst_4
    1102: iconst_m1
    1103: iastore
    1104: dup
    1105: iconst_5
    1106: iconst_m1
    1107: iastore
    1108: dup
    1109: bipush        6
    1111: iconst_m1
    1112: iastore
    1113: aastore
    1114: dup
    1115: bipush        18
    1117: bipush        7
    1119: newarray       int
    1121: dup
    1122: iconst_0
    1123: bipush        6
    1125: iastore
    1126: dup
    1127: iconst_1
    1128: bipush        30
    1130: iastore
    1131: dup
    1132: iconst_2
    1133: bipush        58
    1135: iastore
    1136: dup
    1137: iconst_3
    1138: bipush        86
    1140: iastore
    1141: dup
    1142: iconst_4
    1143: iconst_m1
    1144: iastore
    1145: dup
    1146: iconst_5
    1147: iconst_m1
    1148: iastore
    1149: dup
    1150: bipush        6
    1152: iconst_m1
    1153: iastore
    1154: aastore
    1155: dup
    1156: bipush        19
    1158: bipush        7
    1160: newarray       int
    1162: dup
    1163: iconst_0
    1164: bipush        6
    1166: iastore
    1167: dup
    1168: iconst_1
    1169: bipush        34
    1171: iastore
    1172: dup
    1173: iconst_2
    1174: bipush        62
    1176: iastore
    1177: dup
    1178: iconst_3
    1179: bipush        90
    1181: iastore
    1182: dup
    1183: iconst_4
    1184: iconst_m1
    1185: iastore
    1186: dup
    1187: iconst_5
    1188: iconst_m1
    1189: iastore
    1190: dup
    1191: bipush        6
    1193: iconst_m1
    1194: iastore
    1195: aastore
    1196: dup
    1197: bipush        20
    1199: bipush        7
    1201: newarray       int
    1203: dup
    1204: iconst_0
    1205: bipush        6
    1207: iastore
    1208: dup
    1209: iconst_1
    1210: bipush        28
    1212: iastore
    1213: dup
    1214: iconst_2
    1215: bipush        50
    1217: iastore
    1218: dup
    1219: iconst_3
    1220: bipush        72
    1222: iastore
    1223: dup
    1224: iconst_4
    1225: bipush        94
    1227: iastore
    1228: dup
    1229: iconst_5
    1230: iconst_m1
    1231: iastore
    1232: dup
    1233: bipush        6
    1235: iconst_m1
    1236: iastore
    1237: aastore
    1238: dup
    1239: bipush        21
    1241: bipush        7
    1243: newarray       int
    1245: dup
    1246: iconst_0
    1247: bipush        6
    1249: iastore
    1250: dup
    1251: iconst_1
    1252: bipush        26
    1254: iastore
    1255: dup
    1256: iconst_2
    1257: bipush        50
    1259: iastore
    1260: dup
    1261: iconst_3
    1262: bipush        74
    1264: iastore
    1265: dup
    1266: iconst_4
    1267: bipush        98
    1269: iastore
    1270: dup
    1271: iconst_5
    1272: iconst_m1
    1273: iastore
    1274: dup
    1275: bipush        6
    1277: iconst_m1
    1278: iastore
    1279: aastore
    1280: dup
    1281: bipush        22
    1283: bipush        7
    1285: newarray       int
    1287: dup
    1288: iconst_0
    1289: bipush        6
    1291: iastore
    1292: dup
    1293: iconst_1
    1294: bipush        30
    1296: iastore
    1297: dup
    1298: iconst_2
    1299: bipush        54
    1301: iastore
    1302: dup
    1303: iconst_3
    1304: bipush        78
    1306: iastore
    1307: dup
    1308: iconst_4
    1309: bipush        102
    1311: iastore
    1312: dup
    1313: iconst_5
    1314: iconst_m1
    1315: iastore
    1316: dup
    1317: bipush        6
    1319: iconst_m1
    1320: iastore
    1321: aastore
    1322: dup
    1323: bipush        23
    1325: bipush        7
    1327: newarray       int
    1329: dup
    1330: iconst_0
    1331: bipush        6
    1333: iastore
    1334: dup
    1335: iconst_1
    1336: bipush        28
    1338: iastore
    1339: dup
    1340: iconst_2
    1341: bipush        54
    1343: iastore
    1344: dup
    1345: iconst_3
    1346: bipush        80
    1348: iastore
    1349: dup
    1350: iconst_4
    1351: bipush        106
    1353: iastore
    1354: dup
    1355: iconst_5
    1356: iconst_m1
    1357: iastore
    1358: dup
    1359: bipush        6
    1361: iconst_m1
    1362: iastore
    1363: aastore
    1364: dup
    1365: bipush        24
    1367: bipush        7
    1369: newarray       int
    1371: dup
    1372: iconst_0
    1373: bipush        6
    1375: iastore
    1376: dup
    1377: iconst_1
    1378: bipush        32
    1380: iastore
    1381: dup
    1382: iconst_2
    1383: bipush        58
    1385: iastore
    1386: dup
    1387: iconst_3
    1388: bipush        84
    1390: iastore
    1391: dup
    1392: iconst_4
    1393: bipush        110
    1395: iastore
    1396: dup
    1397: iconst_5
    1398: iconst_m1
    1399: iastore
    1400: dup
    1401: bipush        6
    1403: iconst_m1
    1404: iastore
    1405: aastore
    1406: dup
    1407: bipush        25
    1409: bipush        7
    1411: newarray       int
    1413: dup
    1414: iconst_0
    1415: bipush        6
    1417: iastore
    1418: dup
    1419: iconst_1
    1420: bipush        30
    1422: iastore
    1423: dup
    1424: iconst_2
    1425: bipush        58
    1427: iastore
    1428: dup
    1429: iconst_3
    1430: bipush        86
    1432: iastore
    1433: dup
    1434: iconst_4
    1435: bipush        114
    1437: iastore
    1438: dup
    1439: iconst_5
    1440: iconst_m1
    1441: iastore
    1442: dup
    1443: bipush        6
    1445: iconst_m1
    1446: iastore
    1447: aastore
    1448: dup
    1449: bipush        26
    1451: bipush        7
    1453: newarray       int
    1455: dup
    1456: iconst_0
    1457: bipush        6
    1459: iastore
    1460: dup
    1461: iconst_1
    1462: bipush        34
    1464: iastore
    1465: dup
    1466: iconst_2
    1467: bipush        62
    1469: iastore
    1470: dup
    1471: iconst_3
    1472: bipush        90
    1474: iastore
    1475: dup
    1476: iconst_4
    1477: bipush        118
    1479: iastore
    1480: dup
    1481: iconst_5
    1482: iconst_m1
    1483: iastore
    1484: dup
    1485: bipush        6
    1487: iconst_m1
    1488: iastore
    1489: aastore
    1490: dup
    1491: bipush        27
    1493: bipush        7
    1495: newarray       int
    1497: dup
    1498: iconst_0
    1499: bipush        6
    1501: iastore
    1502: dup
    1503: iconst_1
    1504: bipush        26
    1506: iastore
    1507: dup
    1508: iconst_2
    1509: bipush        50
    1511: iastore
    1512: dup
    1513: iconst_3
    1514: bipush        74
    1516: iastore
    1517: dup
    1518: iconst_4
    1519: bipush        98
    1521: iastore
    1522: dup
    1523: iconst_5
    1524: bipush        122
    1526: iastore
    1527: dup
    1528: bipush        6
    1530: iconst_m1
    1531: iastore
    1532: aastore
    1533: dup
    1534: bipush        28
    1536: bipush        7
    1538: newarray       int
    1540: dup
    1541: iconst_0
    1542: bipush        6
    1544: iastore
    1545: dup
    1546: iconst_1
    1547: bipush        30
    1549: iastore
    1550: dup
    1551: iconst_2
    1552: bipush        54
    1554: iastore
    1555: dup
    1556: iconst_3
    1557: bipush        78
    1559: iastore
    1560: dup
    1561: iconst_4
    1562: bipush        102
    1564: iastore
    1565: dup
    1566: iconst_5
    1567: bipush        126
    1569: iastore
    1570: dup
    1571: bipush        6
    1573: iconst_m1
    1574: iastore
    1575: aastore
    1576: dup
    1577: bipush        29
    1579: bipush        7
    1581: newarray       int
    1583: dup
    1584: iconst_0
    1585: bipush        6
    1587: iastore
    1588: dup
    1589: iconst_1
    1590: bipush        26
    1592: iastore
    1593: dup
    1594: iconst_2
    1595: bipush        52
    1597: iastore
    1598: dup
    1599: iconst_3
    1600: bipush        78
    1602: iastore
    1603: dup
    1604: iconst_4
    1605: bipush        104
    1607: iastore
    1608: dup
    1609: iconst_5
    1610: sipush        130
    1613: iastore
    1614: dup
    1615: bipush        6
    1617: iconst_m1
    1618: iastore
    1619: aastore
    1620: dup
    1621: bipush        30
    1623: bipush        7
    1625: newarray       int
    1627: dup
    1628: iconst_0
    1629: bipush        6
    1631: iastore
    1632: dup
    1633: iconst_1
    1634: bipush        30
    1636: iastore
    1637: dup
    1638: iconst_2
    1639: bipush        56
    1641: iastore
    1642: dup
    1643: iconst_3
    1644: bipush        82
    1646: iastore
    1647: dup
    1648: iconst_4
    1649: bipush        108
    1651: iastore
    1652: dup
    1653: iconst_5
    1654: sipush        134
    1657: iastore
    1658: dup
    1659: bipush        6
    1661: iconst_m1
    1662: iastore
    1663: aastore
    1664: dup
    1665: bipush        31
    1667: bipush        7
    1669: newarray       int
    1671: dup
    1672: iconst_0
    1673: bipush        6
    1675: iastore
    1676: dup
    1677: iconst_1
    1678: bipush        34
    1680: iastore
    1681: dup
    1682: iconst_2
    1683: bipush        60
    1685: iastore
    1686: dup
    1687: iconst_3
    1688: bipush        86
    1690: iastore
    1691: dup
    1692: iconst_4
    1693: bipush        112
    1695: iastore
    1696: dup
    1697: iconst_5
    1698: sipush        138
    1701: iastore
    1702: dup
    1703: bipush        6
    1705: iconst_m1
    1706: iastore
    1707: aastore
    1708: dup
    1709: bipush        32
    1711: bipush        7
    1713: newarray       int
    1715: dup
    1716: iconst_0
    1717: bipush        6
    1719: iastore
    1720: dup
    1721: iconst_1
    1722: bipush        30
    1724: iastore
    1725: dup
    1726: iconst_2
    1727: bipush        58
    1729: iastore
    1730: dup
    1731: iconst_3
    1732: bipush        86
    1734: iastore
    1735: dup
    1736: iconst_4
    1737: bipush        114
    1739: iastore
    1740: dup
    1741: iconst_5
    1742: sipush        142
    1745: iastore
    1746: dup
    1747: bipush        6
    1749: iconst_m1
    1750: iastore
    1751: aastore
    1752: dup
    1753: bipush        33
    1755: bipush        7
    1757: newarray       int
    1759: dup
    1760: iconst_0
    1761: bipush        6
    1763: iastore
    1764: dup
    1765: iconst_1
    1766: bipush        34
    1768: iastore
    1769: dup
    1770: iconst_2
    1771: bipush        62
    1773: iastore
    1774: dup
    1775: iconst_3
    1776: bipush        90
    1778: iastore
    1779: dup
    1780: iconst_4
    1781: bipush        118
    1783: iastore
    1784: dup
    1785: iconst_5
    1786: sipush        146
    1789: iastore
    1790: dup
    1791: bipush        6
    1793: iconst_m1
    1794: iastore
    1795: aastore
    1796: dup
    1797: bipush        34
    1799: bipush        7
    1801: newarray       int
    1803: dup
    1804: iconst_0
    1805: bipush        6
    1807: iastore
    1808: dup
    1809: iconst_1
    1810: bipush        30
    1812: iastore
    1813: dup
    1814: iconst_2
    1815: bipush        54
    1817: iastore
    1818: dup
    1819: iconst_3
    1820: bipush        78
    1822: iastore
    1823: dup
    1824: iconst_4
    1825: bipush        102
    1827: iastore
    1828: dup
    1829: iconst_5
    1830: bipush        126
    1832: iastore
    1833: dup
    1834: bipush        6
    1836: sipush        150
    1839: iastore
    1840: aastore
    1841: dup
    1842: bipush        35
    1844: bipush        7
    1846: newarray       int
    1848: dup
    1849: iconst_0
    1850: bipush        6
    1852: iastore
    1853: dup
    1854: iconst_1
    1855: bipush        24
    1857: iastore
    1858: dup
    1859: iconst_2
    1860: bipush        50
    1862: iastore
    1863: dup
    1864: iconst_3
    1865: bipush        76
    1867: iastore
    1868: dup
    1869: iconst_4
    1870: bipush        102
    1872: iastore
    1873: dup
    1874: iconst_5
    1875: sipush        128
    1878: iastore
    1879: dup
    1880: bipush        6
    1882: sipush        154
    1885: iastore
    1886: aastore
    1887: dup
    1888: bipush        36
    1890: bipush        7
    1892: newarray       int
    1894: dup
    1895: iconst_0
    1896: bipush        6
    1898: iastore
    1899: dup
    1900: iconst_1
    1901: bipush        28
    1903: iastore
    1904: dup
    1905: iconst_2
    1906: bipush        54
    1908: iastore
    1909: dup
    1910: iconst_3
    1911: bipush        80
    1913: iastore
    1914: dup
    1915: iconst_4
    1916: bipush        106
    1918: iastore
    1919: dup
    1920: iconst_5
    1921: sipush        132
    1924: iastore
    1925: dup
    1926: bipush        6
    1928: sipush        158
    1931: iastore
    1932: aastore
    1933: dup
    1934: bipush        37
    1936: bipush        7
    1938: newarray       int
    1940: dup
    1941: iconst_0
    1942: bipush        6
    1944: iastore
    1945: dup
    1946: iconst_1
    1947: bipush        32
    1949: iastore
    1950: dup
    1951: iconst_2
    1952: bipush        58
    1954: iastore
    1955: dup
    1956: iconst_3
    1957: bipush        84
    1959: iastore
    1960: dup
    1961: iconst_4
    1962: bipush        110
    1964: iastore
    1965: dup
    1966: iconst_5
    1967: sipush        136
    1970: iastore
    1971: dup
    1972: bipush        6
    1974: sipush        162
    1977: iastore
    1978: aastore
    1979: dup
    1980: bipush        38
    1982: bipush        7
    1984: newarray       int
    1986: dup
    1987: iconst_0
    1988: bipush        6
    1990: iastore
    1991: dup
    1992: iconst_1
    1993: bipush        26
    1995: iastore
    1996: dup
    1997: iconst_2
    1998: bipush        54
    2000: iastore
    2001: dup
    2002: iconst_3
    2003: bipush        82
    2005: iastore
    2006: dup
    2007: iconst_4
    2008: bipush        110
    2010: iastore
    2011: dup
    2012: iconst_5
    2013: sipush        138
    2016: iastore
    2017: dup
    2018: bipush        6
    2020: sipush        166
    2023: iastore
    2024: aastore
    2025: dup
    2026: bipush        39
    2028: bipush        7
    2030: newarray       int
    2032: dup
    2033: iconst_0
    2034: bipush        6
    2036: iastore
    2037: dup
    2038: iconst_1
    2039: bipush        30
    2041: iastore
    2042: dup
    2043: iconst_2
    2044: bipush        58
    2046: iastore
    2047: dup
    2048: iconst_3
    2049: bipush        86
    2051: iastore
    2052: dup
    2053: iconst_4
    2054: bipush        114
    2056: iastore
    2057: dup
    2058: iconst_5
    2059: sipush        142
    2062: iastore
    2063: dup
    2064: bipush        6
    2066: sipush        170
    2069: iastore
    2070: aastore
    2071: putstatic     #55                 // Field POSITION_ADJUSTMENT_PATTERN_COORDINATE_TABLE:[[I
    2074: bipush        15
    2076: anewarray     #57                 // class "[I"
    2079: dup
    2080: iconst_0
    2081: iconst_2
    2082: newarray       int
    2084: dup
    2085: iconst_0
    2086: bipush        8
    2088: iastore
    2089: dup
    2090: iconst_1
    2091: iconst_0
    2092: iastore
    2093: aastore
    2094: dup
    2095: iconst_1
    2096: iconst_2
    2097: newarray       int
    2099: dup
    2100: iconst_0
    2101: bipush        8
    2103: iastore
    2104: dup
    2105: iconst_1
    2106: iconst_1
    2107: iastore
    2108: aastore
    2109: dup
    2110: iconst_2
    2111: iconst_2
    2112: newarray       int
    2114: dup
    2115: iconst_0
    2116: bipush        8
    2118: iastore
    2119: dup
    2120: iconst_1
    2121: iconst_2
    2122: iastore
    2123: aastore
    2124: dup
    2125: iconst_3
    2126: iconst_2
    2127: newarray       int
    2129: dup
    2130: iconst_0
    2131: bipush        8
    2133: iastore
    2134: dup
    2135: iconst_1
    2136: iconst_3
    2137: iastore
    2138: aastore
    2139: dup
    2140: iconst_4
    2141: iconst_2
    2142: newarray       int
    2144: dup
    2145: iconst_0
    2146: bipush        8
    2148: iastore
    2149: dup
    2150: iconst_1
    2151: iconst_4
    2152: iastore
    2153: aastore
    2154: dup
    2155: iconst_5
    2156: iconst_2
    2157: newarray       int
    2159: dup
    2160: iconst_0
    2161: bipush        8
    2163: iastore
    2164: dup
    2165: iconst_1
    2166: iconst_5
    2167: iastore
    2168: aastore
    2169: dup
    2170: bipush        6
    2172: iconst_2
    2173: newarray       int
    2175: dup
    2176: iconst_0
    2177: bipush        8
    2179: iastore
    2180: dup
    2181: iconst_1
    2182: bipush        7
    2184: iastore
    2185: aastore
    2186: dup
    2187: bipush        7
    2189: iconst_2
    2190: newarray       int
    2192: dup
    2193: iconst_0
    2194: bipush        8
    2196: iastore
    2197: dup
    2198: iconst_1
    2199: bipush        8
    2201: iastore
    2202: aastore
    2203: dup
    2204: bipush        8
    2206: iconst_2
    2207: newarray       int
    2209: dup
    2210: iconst_0
    2211: bipush        7
    2213: iastore
    2214: dup
    2215: iconst_1
    2216: bipush        8
    2218: iastore
    2219: aastore
    2220: dup
    2221: bipush        9
    2223: iconst_2
    2224: newarray       int
    2226: dup
    2227: iconst_0
    2228: iconst_5
    2229: iastore
    2230: dup
    2231: iconst_1
    2232: bipush        8
    2234: iastore
    2235: aastore
    2236: dup
    2237: bipush        10
    2239: iconst_2
    2240: newarray       int
    2242: dup
    2243: iconst_0
    2244: iconst_4
    2245: iastore
    2246: dup
    2247: iconst_1
    2248: bipush        8
    2250: iastore
    2251: aastore
    2252: dup
    2253: bipush        11
    2255: iconst_2
    2256: newarray       int
    2258: dup
    2259: iconst_0
    2260: iconst_3
    2261: iastore
    2262: dup
    2263: iconst_1
    2264: bipush        8
    2266: iastore
    2267: aastore
    2268: dup
    2269: bipush        12
    2271: iconst_2
    2272: newarray       int
    2274: dup
    2275: iconst_0
    2276: iconst_2
    2277: iastore
    2278: dup
    2279: iconst_1
    2280: bipush        8
    2282: iastore
    2283: aastore
    2284: dup
    2285: bipush        13
    2287: iconst_2
    2288: newarray       int
    2290: dup
    2291: iconst_0
    2292: iconst_1
    2293: iastore
    2294: dup
    2295: iconst_1
    2296: bipush        8
    2298: iastore
    2299: aastore
    2300: dup
    2301: bipush        14
    2303: iconst_2
    2304: newarray       int
    2306: dup
    2307: iconst_0
    2308: iconst_0
    2309: iastore
    2310: dup
    2311: iconst_1
    2312: bipush        8
    2314: iastore
    2315: aastore
    2316: putstatic     #17                 // Field TYPE_INFO_COORDINATES:[[I
    2319: return
}
