Compiled from "MinimalEncoder.java"
final class com.google.zxing.qrcode.encoder.MinimalEncoder$ResultList {
  private final java.util.List<com.google.zxing.qrcode.encoder.MinimalEncoder$ResultList$ResultNode> list;

  private final com.google.zxing.qrcode.decoder.Version version;

  final com.google.zxing.qrcode.encoder.MinimalEncoder this$0;

  com.google.zxing.qrcode.encoder.MinimalEncoder$ResultList(com.google.zxing.qrcode.encoder.MinimalEncoder, com.google.zxing.qrcode.decoder.Version, com.google.zxing.qrcode.encoder.MinimalEncoder$Edge);
    Code:
       0: aload_0
       1: aload_1
       2: putfield      #2                  // Field this$0:Lcom/google/zxing/qrcode/encoder/MinimalEncoder;
       5: aload_0
       6: invokespecial #3                  // Method java/lang/Object."<init>":()V
       9: aload_0
      10: new           #4                  // class java/util/ArrayList
      13: dup
      14: invokespecial #5                  // Method java/util/ArrayList."<init>":()V
      17: putfield      #6                  // Field list:Ljava/util/List;
      20: iconst_0
      21: istore        4
      23: aload_3
      24: astore        5
      26: iconst_0
      27: istore        6
      29: aload         5
      31: ifnull        213
      34: iload         4
      36: aload         5
      38: invokestatic  #7                  // Method com/google/zxing/qrcode/encoder/MinimalEncoder$Edge.access$000:(Lcom/google/zxing/qrcode/encoder/MinimalEncoder$Edge;)I
      41: iadd
      42: istore        4
      44: aload         5
      46: invokestatic  #8                  // Method com/google/zxing/qrcode/encoder/MinimalEncoder$Edge.access$700:(Lcom/google/zxing/qrcode/encoder/MinimalEncoder$Edge;)Lcom/google/zxing/qrcode/encoder/MinimalEncoder$Edge;
      49: astore        7
      51: aload         5
      53: invokestatic  #9                  // Method com/google/zxing/qrcode/encoder/MinimalEncoder$Edge.access$200:(Lcom/google/zxing/qrcode/encoder/MinimalEncoder$Edge;)Lcom/google/zxing/qrcode/decoder/Mode;
      56: getstatic     #10                 // Field com/google/zxing/qrcode/decoder/Mode.BYTE:Lcom/google/zxing/qrcode/decoder/Mode;
      59: if_acmpne     75
      62: aload         7
      64: ifnonnull     75
      67: aload         5
      69: invokestatic  #11                 // Method com/google/zxing/qrcode/encoder/MinimalEncoder$Edge.access$100:(Lcom/google/zxing/qrcode/encoder/MinimalEncoder$Edge;)I
      72: ifne          93
      75: aload         7
      77: ifnull        97
      80: aload         5
      82: invokestatic  #11                 // Method com/google/zxing/qrcode/encoder/MinimalEncoder$Edge.access$100:(Lcom/google/zxing/qrcode/encoder/MinimalEncoder$Edge;)I
      85: aload         7
      87: invokestatic  #11                 // Method com/google/zxing/qrcode/encoder/MinimalEncoder$Edge.access$100:(Lcom/google/zxing/qrcode/encoder/MinimalEncoder$Edge;)I
      90: if_icmpeq     97
      93: iconst_1
      94: goto          98
      97: iconst_0
      98: istore        8
     100: iload         8
     102: ifeq          108
     105: iconst_1
     106: istore        6
     108: aload         7
     110: ifnull        131
     113: aload         7
     115: invokestatic  #9                  // Method com/google/zxing/qrcode/encoder/MinimalEncoder$Edge.access$200:(Lcom/google/zxing/qrcode/encoder/MinimalEncoder$Edge;)Lcom/google/zxing/qrcode/decoder/Mode;
     118: aload         5
     120: invokestatic  #9                  // Method com/google/zxing/qrcode/encoder/MinimalEncoder$Edge.access$200:(Lcom/google/zxing/qrcode/encoder/MinimalEncoder$Edge;)Lcom/google/zxing/qrcode/decoder/Mode;
     123: if_acmpne     131
     126: iload         8
     128: ifeq          169
     131: aload_0
     132: getfield      #6                  // Field list:Ljava/util/List;
     135: iconst_0
     136: new           #12                 // class com/google/zxing/qrcode/encoder/MinimalEncoder$ResultList$ResultNode
     139: dup
     140: aload_0
     141: aload         5
     143: invokestatic  #9                  // Method com/google/zxing/qrcode/encoder/MinimalEncoder$Edge.access$200:(Lcom/google/zxing/qrcode/encoder/MinimalEncoder$Edge;)Lcom/google/zxing/qrcode/decoder/Mode;
     146: aload         5
     148: invokestatic  #13                 // Method com/google/zxing/qrcode/encoder/MinimalEncoder$Edge.access$800:(Lcom/google/zxing/qrcode/encoder/MinimalEncoder$Edge;)I
     151: aload         5
     153: invokestatic  #11                 // Method com/google/zxing/qrcode/encoder/MinimalEncoder$Edge.access$100:(Lcom/google/zxing/qrcode/encoder/MinimalEncoder$Edge;)I
     156: iload         4
     158: invokespecial #14                 // Method com/google/zxing/qrcode/encoder/MinimalEncoder$ResultList$ResultNode."<init>":(Lcom/google/zxing/qrcode/encoder/MinimalEncoder$ResultList;Lcom/google/zxing/qrcode/decoder/Mode;III)V
     161: invokeinterface #15,  3           // InterfaceMethod java/util/List.add:(ILjava/lang/Object;)V
     166: iconst_0
     167: istore        4
     169: iload         8
     171: ifeq          206
     174: aload_0
     175: getfield      #6                  // Field list:Ljava/util/List;
     178: iconst_0
     179: new           #12                 // class com/google/zxing/qrcode/encoder/MinimalEncoder$ResultList$ResultNode
     182: dup
     183: aload_0
     184: getstatic     #16                 // Field com/google/zxing/qrcode/decoder/Mode.ECI:Lcom/google/zxing/qrcode/decoder/Mode;
     187: aload         5
     189: invokestatic  #13                 // Method com/google/zxing/qrcode/encoder/MinimalEncoder$Edge.access$800:(Lcom/google/zxing/qrcode/encoder/MinimalEncoder$Edge;)I
     192: aload         5
     194: invokestatic  #11                 // Method com/google/zxing/qrcode/encoder/MinimalEncoder$Edge.access$100:(Lcom/google/zxing/qrcode/encoder/MinimalEncoder$Edge;)I
     197: iconst_0
     198: invokespecial #14                 // Method com/google/zxing/qrcode/encoder/MinimalEncoder$ResultList$ResultNode."<init>":(Lcom/google/zxing/qrcode/encoder/MinimalEncoder$ResultList;Lcom/google/zxing/qrcode/decoder/Mode;III)V
     201: invokeinterface #15,  3           // InterfaceMethod java/util/List.add:(ILjava/lang/Object;)V
     206: aload         7
     208: astore        5
     210: goto          29
     213: aload_1
     214: invokestatic  #17                 // Method com/google/zxing/qrcode/encoder/MinimalEncoder.access$900:(Lcom/google/zxing/qrcode/encoder/MinimalEncoder;)Z
     217: ifeq          334
     220: aload_0
     221: getfield      #6                  // Field list:Ljava/util/List;
     224: iconst_0
     225: invokeinterface #18,  2           // InterfaceMethod java/util/List.get:(I)Ljava/lang/Object;
     230: checkcast     #12                 // class com/google/zxing/qrcode/encoder/MinimalEncoder$ResultList$ResultNode
     233: astore        7
     235: aload         7
     237: ifnull        280
     240: aload         7
     242: invokestatic  #19                 // Method com/google/zxing/qrcode/encoder/MinimalEncoder$ResultList$ResultNode.access$1000:(Lcom/google/zxing/qrcode/encoder/MinimalEncoder$ResultList$ResultNode;)Lcom/google/zxing/qrcode/decoder/Mode;
     245: getstatic     #16                 // Field com/google/zxing/qrcode/decoder/Mode.ECI:Lcom/google/zxing/qrcode/decoder/Mode;
     248: if_acmpeq     280
     251: iload         6
     253: ifeq          280
     256: aload_0
     257: getfield      #6                  // Field list:Ljava/util/List;
     260: iconst_0
     261: new           #12                 // class com/google/zxing/qrcode/encoder/MinimalEncoder$ResultList$ResultNode
     264: dup
     265: aload_0
     266: getstatic     #16                 // Field com/google/zxing/qrcode/decoder/Mode.ECI:Lcom/google/zxing/qrcode/decoder/Mode;
     269: iconst_0
     270: iconst_0
     271: iconst_0
     272: invokespecial #14                 // Method com/google/zxing/qrcode/encoder/MinimalEncoder$ResultList$ResultNode."<init>":(Lcom/google/zxing/qrcode/encoder/MinimalEncoder$ResultList;Lcom/google/zxing/qrcode/decoder/Mode;III)V
     275: invokeinterface #15,  3           // InterfaceMethod java/util/List.add:(ILjava/lang/Object;)V
     280: aload_0
     281: getfield      #6                  // Field list:Ljava/util/List;
     284: iconst_0
     285: invokeinterface #18,  2           // InterfaceMethod java/util/List.get:(I)Ljava/lang/Object;
     290: checkcast     #12                 // class com/google/zxing/qrcode/encoder/MinimalEncoder$ResultList$ResultNode
     293: astore        7
     295: aload_0
     296: getfield      #6                  // Field list:Ljava/util/List;
     299: aload         7
     301: invokestatic  #19                 // Method com/google/zxing/qrcode/encoder/MinimalEncoder$ResultList$ResultNode.access$1000:(Lcom/google/zxing/qrcode/encoder/MinimalEncoder$ResultList$ResultNode;)Lcom/google/zxing/qrcode/decoder/Mode;
     304: getstatic     #16                 // Field com/google/zxing/qrcode/decoder/Mode.ECI:Lcom/google/zxing/qrcode/decoder/Mode;
     307: if_acmpeq     314
     310: iconst_0
     311: goto          315
     314: iconst_1
     315: new           #12                 // class com/google/zxing/qrcode/encoder/MinimalEncoder$ResultList$ResultNode
     318: dup
     319: aload_0
     320: getstatic     #20                 // Field com/google/zxing/qrcode/decoder/Mode.FNC1_FIRST_POSITION:Lcom/google/zxing/qrcode/decoder/Mode;
     323: iconst_0
     324: iconst_0
     325: iconst_0
     326: invokespecial #14                 // Method com/google/zxing/qrcode/encoder/MinimalEncoder$ResultList$ResultNode."<init>":(Lcom/google/zxing/qrcode/encoder/MinimalEncoder$ResultList;Lcom/google/zxing/qrcode/decoder/Mode;III)V
     329: invokeinterface #15,  3           // InterfaceMethod java/util/List.add:(ILjava/lang/Object;)V
     334: aload_2
     335: invokevirtual #21                 // Method com/google/zxing/qrcode/decoder/Version.getVersionNumber:()I
     338: istore        7
     340: getstatic     #22                 // Field com/google/zxing/qrcode/encoder/MinimalEncoder$1.$SwitchMap$com$google$zxing$qrcode$encoder$MinimalEncoder$VersionSize:[I
     343: aload_2
     344: invokestatic  #23                 // Method com/google/zxing/qrcode/encoder/MinimalEncoder.getVersionSize:(Lcom/google/zxing/qrcode/decoder/Version;)Lcom/google/zxing/qrcode/encoder/MinimalEncoder$VersionSize;
     347: invokevirtual #24                 // Method com/google/zxing/qrcode/encoder/MinimalEncoder$VersionSize.ordinal:()I
     350: iaload
     351: tableswitch   { // 1 to 3
                     1: 376
                     2: 386
                     3: 397
               default: 397
          }
     376: iconst_1
     377: istore        8
     379: bipush        9
     381: istore        9
     383: goto          405
     386: bipush        10
     388: istore        8
     390: bipush        26
     392: istore        9
     394: goto          405
     397: bipush        27
     399: istore        8
     401: bipush        40
     403: istore        9
     405: aload_0
     406: aload_2
     407: invokespecial #25                 // Method getSize:(Lcom/google/zxing/qrcode/decoder/Version;)I
     410: istore        10
     412: iload         7
     414: iload         9
     416: if_icmpge     442
     419: iload         10
     421: iload         7
     423: invokestatic  #26                 // Method com/google/zxing/qrcode/decoder/Version.getVersionForNumber:(I)Lcom/google/zxing/qrcode/decoder/Version;
     426: aload_1
     427: invokestatic  #27                 // Method com/google/zxing/qrcode/encoder/MinimalEncoder.access$1100:(Lcom/google/zxing/qrcode/encoder/MinimalEncoder;)Lcom/google/zxing/qrcode/decoder/ErrorCorrectionLevel;
     430: invokestatic  #28                 // Method com/google/zxing/qrcode/encoder/Encoder.willFit:(ILcom/google/zxing/qrcode/decoder/Version;Lcom/google/zxing/qrcode/decoder/ErrorCorrectionLevel;)Z
     433: ifne          442
     436: iinc          7, 1
     439: goto          412
     442: iload         7
     444: iload         8
     446: if_icmple     474
     449: iload         10
     451: iload         7
     453: iconst_1
     454: isub
     455: invokestatic  #26                 // Method com/google/zxing/qrcode/decoder/Version.getVersionForNumber:(I)Lcom/google/zxing/qrcode/decoder/Version;
     458: aload_1
     459: invokestatic  #27                 // Method com/google/zxing/qrcode/encoder/MinimalEncoder.access$1100:(Lcom/google/zxing/qrcode/encoder/MinimalEncoder;)Lcom/google/zxing/qrcode/decoder/ErrorCorrectionLevel;
     462: invokestatic  #28                 // Method com/google/zxing/qrcode/encoder/Encoder.willFit:(ILcom/google/zxing/qrcode/decoder/Version;Lcom/google/zxing/qrcode/decoder/ErrorCorrectionLevel;)Z
     465: ifeq          474
     468: iinc          7, -1
     471: goto          442
     474: aload_0
     475: iload         7
     477: invokestatic  #26                 // Method com/google/zxing/qrcode/decoder/Version.getVersionForNumber:(I)Lcom/google/zxing/qrcode/decoder/Version;
     480: putfield      #1                  // Field version:Lcom/google/zxing/qrcode/decoder/Version;
     483: return

  int getSize();
    Code:
       0: aload_0
       1: aload_0
       2: getfield      #1                  // Field version:Lcom/google/zxing/qrcode/decoder/Version;
       5: invokespecial #25                 // Method getSize:(Lcom/google/zxing/qrcode/decoder/Version;)I
       8: ireturn

  private int getSize(com.google.zxing.qrcode.decoder.Version);
    Code:
       0: iconst_0
       1: istore_2
       2: aload_0
       3: getfield      #6                  // Field list:Ljava/util/List;
       6: invokeinterface #29,  1           // InterfaceMethod java/util/List.iterator:()Ljava/util/Iterator;
      11: astore_3
      12: aload_3
      13: invokeinterface #30,  1           // InterfaceMethod java/util/Iterator.hasNext:()Z
      18: ifeq          44
      21: aload_3
      22: invokeinterface #31,  1           // InterfaceMethod java/util/Iterator.next:()Ljava/lang/Object;
      27: checkcast     #12                 // class com/google/zxing/qrcode/encoder/MinimalEncoder$ResultList$ResultNode
      30: astore        4
      32: iload_2
      33: aload         4
      35: aload_1
      36: invokestatic  #32                 // Method com/google/zxing/qrcode/encoder/MinimalEncoder$ResultList$ResultNode.access$1200:(Lcom/google/zxing/qrcode/encoder/MinimalEncoder$ResultList$ResultNode;Lcom/google/zxing/qrcode/decoder/Version;)I
      39: iadd
      40: istore_2
      41: goto          12
      44: iload_2
      45: ireturn

  void getBits(com.google.zxing.common.BitArray) throws com.google.zxing.WriterException;
    Code:
       0: aload_0
       1: getfield      #6                  // Field list:Ljava/util/List;
       4: invokeinterface #29,  1           // InterfaceMethod java/util/List.iterator:()Ljava/util/Iterator;
       9: astore_2
      10: aload_2
      11: invokeinterface #30,  1           // InterfaceMethod java/util/Iterator.hasNext:()Z
      16: ifeq          37
      19: aload_2
      20: invokeinterface #31,  1           // InterfaceMethod java/util/Iterator.next:()Ljava/lang/Object;
      25: checkcast     #12                 // class com/google/zxing/qrcode/encoder/MinimalEncoder$ResultList$ResultNode
      28: astore_3
      29: aload_3
      30: aload_1
      31: invokestatic  #33                 // Method com/google/zxing/qrcode/encoder/MinimalEncoder$ResultList$ResultNode.access$1300:(Lcom/google/zxing/qrcode/encoder/MinimalEncoder$ResultList$ResultNode;Lcom/google/zxing/common/BitArray;)V
      34: goto          10
      37: return

  com.google.zxing.qrcode.decoder.Version getVersion();
    Code:
       0: aload_0
       1: getfield      #1                  // Field version:Lcom/google/zxing/qrcode/decoder/Version;
       4: areturn

  public java.lang.String toString();
    Code:
       0: new           #34                 // class java/lang/StringBuilder
       3: dup
       4: invokespecial #35                 // Method java/lang/StringBuilder."<init>":()V
       7: astore_1
       8: aconst_null
       9: astore_2
      10: aload_0
      11: getfield      #6                  // Field list:Ljava/util/List;
      14: invokeinterface #29,  1           // InterfaceMethod java/util/List.iterator:()Ljava/util/Iterator;
      19: astore_3
      20: aload_3
      21: invokeinterface #30,  1           // InterfaceMethod java/util/Iterator.hasNext:()Z
      26: ifeq          67
      29: aload_3
      30: invokeinterface #31,  1           // InterfaceMethod java/util/Iterator.next:()Ljava/lang/Object;
      35: checkcast     #12                 // class com/google/zxing/qrcode/encoder/MinimalEncoder$ResultList$ResultNode
      38: astore        4
      40: aload_2
      41: ifnull        51
      44: aload_1
      45: ldc           #36                 // String ,
      47: invokevirtual #37                 // Method java/lang/StringBuilder.append:(Ljava/lang/String;)Ljava/lang/StringBuilder;
      50: pop
      51: aload_1
      52: aload         4
      54: invokevirtual #38                 // Method com/google/zxing/qrcode/encoder/MinimalEncoder$ResultList$ResultNode.toString:()Ljava/lang/String;
      57: invokevirtual #37                 // Method java/lang/StringBuilder.append:(Ljava/lang/String;)Ljava/lang/StringBuilder;
      60: pop
      61: aload         4
      63: astore_2
      64: goto          20
      67: aload_1
      68: invokevirtual #39                 // Method java/lang/StringBuilder.toString:()Ljava/lang/String;
      71: areturn

  static com.google.zxing.qrcode.decoder.Version access$1400(com.google.zxing.qrcode.encoder.MinimalEncoder$ResultList);
    Code:
       0: aload_0
       1: getfield      #1                  // Field version:Lcom/google/zxing/qrcode/decoder/Version;
       4: areturn
}
