Compiled from "MinimalEncoder.java"
final class com.google.zxing.qrcode.encoder.MinimalEncoder {
  private final java.lang.String stringToEncode;

  private final boolean isGS1;

  private final com.google.zxing.common.ECIEncoderSet encoders;

  private final com.google.zxing.qrcode.decoder.ErrorCorrectionLevel ecLevel;

  com.google.zxing.qrcode.encoder.MinimalEncoder(java.lang.String, java.nio.charset.Charset, boolean, com.google.zxing.qrcode.decoder.ErrorCorrectionLevel);
    Code:
       0: aload_0
       1: invokespecial #5                  // Method java/lang/Object."<init>":()V
       4: aload_0
       5: aload_1
       6: putfield      #4                  // Field stringToEncode:Ljava/lang/String;
       9: aload_0
      10: iload_3
      11: putfield      #2                  // Field isGS1:Z
      14: aload_0
      15: new           #6                  // class com/google/zxing/common/ECIEncoderSet
      18: dup
      19: aload_1
      20: aload_2
      21: iconst_m1
      22: invokespecial #7                  // Method com/google/zxing/common/ECIEncoderSet."<init>":(Ljava/lang/String;Ljava/nio/charset/Charset;I)V
      25: putfield      #3                  // Field encoders:Lcom/google/zxing/common/ECIEncoderSet;
      28: aload_0
      29: aload         4
      31: putfield      #1                  // Field ecLevel:Lcom/google/zxing/qrcode/decoder/ErrorCorrectionLevel;
      34: return

  static com.google.zxing.qrcode.encoder.MinimalEncoder$ResultList encode(java.lang.String, com.google.zxing.qrcode.decoder.Version, java.nio.charset.Charset, boolean, com.google.zxing.qrcode.decoder.ErrorCorrectionLevel) throws com.google.zxing.WriterException;
    Code:
       0: new           #8                  // class com/google/zxing/qrcode/encoder/MinimalEncoder
       3: dup
       4: aload_0
       5: aload_2
       6: iload_3
       7: aload         4
       9: invokespecial #9                  // Method "<init>":(Ljava/lang/String;Ljava/nio/charset/Charset;ZLcom/google/zxing/qrcode/decoder/ErrorCorrectionLevel;)V
      12: aload_1
      13: invokevirtual #10                 // Method encode:(Lcom/google/zxing/qrcode/decoder/Version;)Lcom/google/zxing/qrcode/encoder/MinimalEncoder$ResultList;
      16: areturn

  com.google.zxing.qrcode.encoder.MinimalEncoder$ResultList encode(com.google.zxing.qrcode.decoder.Version) throws com.google.zxing.WriterException;
    Code:
       0: aload_1
       1: ifnonnull     153
       4: iconst_3
       5: anewarray     #11                 // class com/google/zxing/qrcode/decoder/Version
       8: dup
       9: iconst_0
      10: getstatic     #12                 // Field com/google/zxing/qrcode/encoder/MinimalEncoder$VersionSize.SMALL:Lcom/google/zxing/qrcode/encoder/MinimalEncoder$VersionSize;
      13: invokestatic  #13                 // Method getVersion:(Lcom/google/zxing/qrcode/encoder/MinimalEncoder$VersionSize;)Lcom/google/zxing/qrcode/decoder/Version;
      16: aastore
      17: dup
      18: iconst_1
      19: getstatic     #14                 // Field com/google/zxing/qrcode/encoder/MinimalEncoder$VersionSize.MEDIUM:Lcom/google/zxing/qrcode/encoder/MinimalEncoder$VersionSize;
      22: invokestatic  #13                 // Method getVersion:(Lcom/google/zxing/qrcode/encoder/MinimalEncoder$VersionSize;)Lcom/google/zxing/qrcode/decoder/Version;
      25: aastore
      26: dup
      27: iconst_2
      28: getstatic     #15                 // Field com/google/zxing/qrcode/encoder/MinimalEncoder$VersionSize.LARGE:Lcom/google/zxing/qrcode/encoder/MinimalEncoder$VersionSize;
      31: invokestatic  #13                 // Method getVersion:(Lcom/google/zxing/qrcode/encoder/MinimalEncoder$VersionSize;)Lcom/google/zxing/qrcode/decoder/Version;
      34: aastore
      35: astore_2
      36: iconst_3
      37: anewarray     #16                 // class com/google/zxing/qrcode/encoder/MinimalEncoder$ResultList
      40: dup
      41: iconst_0
      42: aload_0
      43: aload_2
      44: iconst_0
      45: aaload
      46: invokevirtual #17                 // Method encodeSpecificVersion:(Lcom/google/zxing/qrcode/decoder/Version;)Lcom/google/zxing/qrcode/encoder/MinimalEncoder$ResultList;
      49: aastore
      50: dup
      51: iconst_1
      52: aload_0
      53: aload_2
      54: iconst_1
      55: aaload
      56: invokevirtual #17                 // Method encodeSpecificVersion:(Lcom/google/zxing/qrcode/decoder/Version;)Lcom/google/zxing/qrcode/encoder/MinimalEncoder$ResultList;
      59: aastore
      60: dup
      61: iconst_2
      62: aload_0
      63: aload_2
      64: iconst_2
      65: aaload
      66: invokevirtual #17                 // Method encodeSpecificVersion:(Lcom/google/zxing/qrcode/decoder/Version;)Lcom/google/zxing/qrcode/encoder/MinimalEncoder$ResultList;
      69: aastore
      70: astore_3
      71: ldc           #19                 // int 2147483647
      73: istore        4
      75: iconst_m1
      76: istore        5
      78: iconst_0
      79: istore        6
      81: iload         6
      83: iconst_3
      84: if_icmpge     133
      87: aload_3
      88: iload         6
      90: aaload
      91: invokevirtual #20                 // Method com/google/zxing/qrcode/encoder/MinimalEncoder$ResultList.getSize:()I
      94: istore        7
      96: iload         7
      98: aload_2
      99: iload         6
     101: aaload
     102: aload_0
     103: getfield      #1                  // Field ecLevel:Lcom/google/zxing/qrcode/decoder/ErrorCorrectionLevel;
     106: invokestatic  #21                 // Method com/google/zxing/qrcode/encoder/Encoder.willFit:(ILcom/google/zxing/qrcode/decoder/Version;Lcom/google/zxing/qrcode/decoder/ErrorCorrectionLevel;)Z
     109: ifeq          127
     112: iload         7
     114: iload         4
     116: if_icmpge     127
     119: iload         7
     121: istore        4
     123: iload         6
     125: istore        5
     127: iinc          6, 1
     130: goto          81
     133: iload         5
     135: ifge          148
     138: new           #22                 // class com/google/zxing/WriterException
     141: dup
     142: ldc           #23                 // String Data too big for any version
     144: invokespecial #24                 // Method com/google/zxing/WriterException."<init>":(Ljava/lang/String;)V
     147: athrow
     148: aload_3
     149: iload         5
     151: aaload
     152: areturn
     153: aload_0
     154: aload_1
     155: invokevirtual #17                 // Method encodeSpecificVersion:(Lcom/google/zxing/qrcode/decoder/Version;)Lcom/google/zxing/qrcode/encoder/MinimalEncoder$ResultList;
     158: astore_2
     159: aload_2
     160: invokevirtual #20                 // Method com/google/zxing/qrcode/encoder/MinimalEncoder$ResultList.getSize:()I
     163: aload_2
     164: invokevirtual #25                 // Method com/google/zxing/qrcode/encoder/MinimalEncoder$ResultList.getVersion:()Lcom/google/zxing/qrcode/decoder/Version;
     167: invokestatic  #26                 // Method getVersionSize:(Lcom/google/zxing/qrcode/decoder/Version;)Lcom/google/zxing/qrcode/encoder/MinimalEncoder$VersionSize;
     170: invokestatic  #13                 // Method getVersion:(Lcom/google/zxing/qrcode/encoder/MinimalEncoder$VersionSize;)Lcom/google/zxing/qrcode/decoder/Version;
     173: aload_0
     174: getfield      #1                  // Field ecLevel:Lcom/google/zxing/qrcode/decoder/ErrorCorrectionLevel;
     177: invokestatic  #21                 // Method com/google/zxing/qrcode/encoder/Encoder.willFit:(ILcom/google/zxing/qrcode/decoder/Version;Lcom/google/zxing/qrcode/decoder/ErrorCorrectionLevel;)Z
     180: ifne          210
     183: new           #22                 // class com/google/zxing/WriterException
     186: dup
     187: new           #27                 // class java/lang/StringBuilder
     190: dup
     191: invokespecial #28                 // Method java/lang/StringBuilder."<init>":()V
     194: ldc           #29                 // String Data too big for version
     196: invokevirtual #30                 // Method java/lang/StringBuilder.append:(Ljava/lang/String;)Ljava/lang/StringBuilder;
     199: aload_1
     200: invokevirtual #31                 // Method java/lang/StringBuilder.append:(Ljava/lang/Object;)Ljava/lang/StringBuilder;
     203: invokevirtual #32                 // Method java/lang/StringBuilder.toString:()Ljava/lang/String;
     206: invokespecial #24                 // Method com/google/zxing/WriterException."<init>":(Ljava/lang/String;)V
     209: athrow
     210: aload_2
     211: areturn

  static com.google.zxing.qrcode.encoder.MinimalEncoder$VersionSize getVersionSize(com.google.zxing.qrcode.decoder.Version);
    Code:
       0: aload_0
       1: invokevirtual #33                 // Method com/google/zxing/qrcode/decoder/Version.getVersionNumber:()I
       4: bipush        9
       6: if_icmpgt     15
       9: getstatic     #12                 // Field com/google/zxing/qrcode/encoder/MinimalEncoder$VersionSize.SMALL:Lcom/google/zxing/qrcode/encoder/MinimalEncoder$VersionSize;
      12: goto          33
      15: aload_0
      16: invokevirtual #33                 // Method com/google/zxing/qrcode/decoder/Version.getVersionNumber:()I
      19: bipush        26
      21: if_icmpgt     30
      24: getstatic     #14                 // Field com/google/zxing/qrcode/encoder/MinimalEncoder$VersionSize.MEDIUM:Lcom/google/zxing/qrcode/encoder/MinimalEncoder$VersionSize;
      27: goto          33
      30: getstatic     #15                 // Field com/google/zxing/qrcode/encoder/MinimalEncoder$VersionSize.LARGE:Lcom/google/zxing/qrcode/encoder/MinimalEncoder$VersionSize;
      33: areturn

  static com.google.zxing.qrcode.decoder.Version getVersion(com.google.zxing.qrcode.encoder.MinimalEncoder$VersionSize);
    Code:
       0: getstatic     #34                 // Field com/google/zxing/qrcode/encoder/MinimalEncoder$1.$SwitchMap$com$google$zxing$qrcode$encoder$MinimalEncoder$VersionSize:[I
       3: aload_0
       4: invokevirtual #35                 // Method com/google/zxing/qrcode/encoder/MinimalEncoder$VersionSize.ordinal:()I
       7: iaload
       8: tableswitch   { // 1 to 3
                     1: 36
                     2: 42
                     3: 48
               default: 48
          }
      36: bipush        9
      38: invokestatic  #36                 // Method com/google/zxing/qrcode/decoder/Version.getVersionForNumber:(I)Lcom/google/zxing/qrcode/decoder/Version;
      41: areturn
      42: bipush        26
      44: invokestatic  #36                 // Method com/google/zxing/qrcode/decoder/Version.getVersionForNumber:(I)Lcom/google/zxing/qrcode/decoder/Version;
      47: areturn
      48: bipush        40
      50: invokestatic  #36                 // Method com/google/zxing/qrcode/decoder/Version.getVersionForNumber:(I)Lcom/google/zxing/qrcode/decoder/Version;
      53: areturn

  static boolean isNumeric(char);
    Code:
       0: iload_0
       1: bipush        48
       3: if_icmplt     16
       6: iload_0
       7: bipush        57
       9: if_icmpgt     16
      12: iconst_1
      13: goto          17
      16: iconst_0
      17: ireturn

  static boolean isDoubleByteKanji(char);
    Code:
       0: iload_0
       1: invokestatic  #37                 // Method java/lang/String.valueOf:(C)Ljava/lang/String;
       4: invokestatic  #38                 // Method com/google/zxing/qrcode/encoder/Encoder.isOnlyDoubleByteKanji:(Ljava/lang/String;)Z
       7: ireturn

  static boolean isAlphanumeric(char);
    Code:
       0: iload_0
       1: invokestatic  #39                 // Method com/google/zxing/qrcode/encoder/Encoder.getAlphanumericCode:(I)I
       4: iconst_m1
       5: if_icmpeq     12
       8: iconst_1
       9: goto          13
      12: iconst_0
      13: ireturn

  boolean canEncode(com.google.zxing.qrcode.decoder.Mode, char);
    Code:
       0: getstatic     #40                 // Field com/google/zxing/qrcode/encoder/MinimalEncoder$1.$SwitchMap$com$google$zxing$qrcode$decoder$Mode:[I
       3: aload_1
       4: invokevirtual #41                 // Method com/google/zxing/qrcode/decoder/Mode.ordinal:()I
       7: iaload
       8: tableswitch   { // 1 to 4
                     1: 40
                     2: 45
                     3: 50
                     4: 55
               default: 57
          }
      40: iload_2
      41: invokestatic  #42                 // Method isDoubleByteKanji:(C)Z
      44: ireturn
      45: iload_2
      46: invokestatic  #43                 // Method isAlphanumeric:(C)Z
      49: ireturn
      50: iload_2
      51: invokestatic  #44                 // Method isNumeric:(C)Z
      54: ireturn
      55: iconst_1
      56: ireturn
      57: iconst_0
      58: ireturn

  static int getCompactedOrdinal(com.google.zxing.qrcode.decoder.Mode);
    Code:
       0: aload_0
       1: ifnonnull     6
       4: iconst_0
       5: ireturn
       6: getstatic     #40                 // Field com/google/zxing/qrcode/encoder/MinimalEncoder$1.$SwitchMap$com$google$zxing$qrcode$decoder$Mode:[I
       9: aload_0
      10: invokevirtual #41                 // Method com/google/zxing/qrcode/decoder/Mode.ordinal:()I
      13: iaload
      14: tableswitch   { // 1 to 4
                     1: 44
                     2: 46
                     3: 48
                     4: 50
               default: 52
          }
      44: iconst_0
      45: ireturn
      46: iconst_1
      47: ireturn
      48: iconst_2
      49: ireturn
      50: iconst_3
      51: ireturn
      52: new           #45                 // class java/lang/IllegalStateException
      55: dup
      56: new           #27                 // class java/lang/StringBuilder
      59: dup
      60: invokespecial #28                 // Method java/lang/StringBuilder."<init>":()V
      63: ldc           #46                 // String Illegal mode
      65: invokevirtual #30                 // Method java/lang/StringBuilder.append:(Ljava/lang/String;)Ljava/lang/StringBuilder;
      68: aload_0
      69: invokevirtual #31                 // Method java/lang/StringBuilder.append:(Ljava/lang/Object;)Ljava/lang/StringBuilder;
      72: invokevirtual #32                 // Method java/lang/StringBuilder.toString:()Ljava/lang/String;
      75: invokespecial #47                 // Method java/lang/IllegalStateException."<init>":(Ljava/lang/String;)V
      78: athrow

  void addEdge(com.google.zxing.qrcode.encoder.MinimalEncoder$Edge[][][], int, com.google.zxing.qrcode.encoder.MinimalEncoder$Edge);
    Code:
       0: iload_2
       1: aload_3
       2: invokestatic  #48                 // Method com/google/zxing/qrcode/encoder/MinimalEncoder$Edge.access$000:(Lcom/google/zxing/qrcode/encoder/MinimalEncoder$Edge;)I
       5: iadd
       6: istore        4
       8: aload_1
       9: iload         4
      11: aaload
      12: aload_3
      13: invokestatic  #49                 // Method com/google/zxing/qrcode/encoder/MinimalEncoder$Edge.access$100:(Lcom/google/zxing/qrcode/encoder/MinimalEncoder$Edge;)I
      16: aaload
      17: astore        5
      19: aload_3
      20: invokestatic  #50                 // Method com/google/zxing/qrcode/encoder/MinimalEncoder$Edge.access$200:(Lcom/google/zxing/qrcode/encoder/MinimalEncoder$Edge;)Lcom/google/zxing/qrcode/decoder/Mode;
      23: invokestatic  #51                 // Method getCompactedOrdinal:(Lcom/google/zxing/qrcode/decoder/Mode;)I
      26: istore        6
      28: aload         5
      30: iload         6
      32: aaload
      33: ifnull        51
      36: aload         5
      38: iload         6
      40: aaload
      41: invokestatic  #52                 // Method com/google/zxing/qrcode/encoder/MinimalEncoder$Edge.access$300:(Lcom/google/zxing/qrcode/encoder/MinimalEncoder$Edge;)I
      44: aload_3
      45: invokestatic  #52                 // Method com/google/zxing/qrcode/encoder/MinimalEncoder$Edge.access$300:(Lcom/google/zxing/qrcode/encoder/MinimalEncoder$Edge;)I
      48: if_icmple     57
      51: aload         5
      53: iload         6
      55: aload_3
      56: aastore
      57: return

  void addEdges(com.google.zxing.qrcode.decoder.Version, com.google.zxing.qrcode.encoder.MinimalEncoder$Edge[][][], int, com.google.zxing.qrcode.encoder.MinimalEncoder$Edge);
    Code:
       0: iconst_0
       1: istore        5
       3: aload_0
       4: getfield      #3                  // Field encoders:Lcom/google/zxing/common/ECIEncoderSet;
       7: invokevirtual #53                 // Method com/google/zxing/common/ECIEncoderSet.length:()I
      10: istore        6
      12: aload_0
      13: getfield      #3                  // Field encoders:Lcom/google/zxing/common/ECIEncoderSet;
      16: invokevirtual #54                 // Method com/google/zxing/common/ECIEncoderSet.getPriorityEncoderIndex:()I
      19: istore        7
      21: iload         7
      23: iflt          56
      26: aload_0
      27: getfield      #3                  // Field encoders:Lcom/google/zxing/common/ECIEncoderSet;
      30: aload_0
      31: getfield      #4                  // Field stringToEncode:Ljava/lang/String;
      34: iload_3
      35: invokevirtual #55                 // Method java/lang/String.charAt:(I)C
      38: iload         7
      40: invokevirtual #56                 // Method com/google/zxing/common/ECIEncoderSet.canEncode:(CI)Z
      43: ifeq          56
      46: iload         7
      48: istore        5
      50: iload         7
      52: iconst_1
      53: iadd
      54: istore        6
      56: iload         5
      58: istore        8
      60: iload         8
      62: iload         6
      64: if_icmpge     118
      67: aload_0
      68: getfield      #3                  // Field encoders:Lcom/google/zxing/common/ECIEncoderSet;
      71: aload_0
      72: getfield      #4                  // Field stringToEncode:Ljava/lang/String;
      75: iload_3
      76: invokevirtual #55                 // Method java/lang/String.charAt:(I)C
      79: iload         8
      81: invokevirtual #56                 // Method com/google/zxing/common/ECIEncoderSet.canEncode:(CI)Z
      84: ifeq          112
      87: aload_0
      88: aload_2
      89: iload_3
      90: new           #57                 // class com/google/zxing/qrcode/encoder/MinimalEncoder$Edge
      93: dup
      94: aload_0
      95: getstatic     #58                 // Field com/google/zxing/qrcode/decoder/Mode.BYTE:Lcom/google/zxing/qrcode/decoder/Mode;
      98: iload_3
      99: iload         8
     101: iconst_1
     102: aload         4
     104: aload_1
     105: aconst_null
     106: invokespecial #59                 // Method com/google/zxing/qrcode/encoder/MinimalEncoder$Edge."<init>":(Lcom/google/zxing/qrcode/encoder/MinimalEncoder;Lcom/google/zxing/qrcode/decoder/Mode;IIILcom/google/zxing/qrcode/encoder/MinimalEncoder$Edge;Lcom/google/zxing/qrcode/decoder/Version;Lcom/google/zxing/qrcode/encoder/MinimalEncoder$1;)V
     109: invokevirtual #60                 // Method addEdge:([[[Lcom/google/zxing/qrcode/encoder/MinimalEncoder$Edge;ILcom/google/zxing/qrcode/encoder/MinimalEncoder$Edge;)V
     112: iinc          8, 1
     115: goto          60
     118: aload_0
     119: getstatic     #61                 // Field com/google/zxing/qrcode/decoder/Mode.KANJI:Lcom/google/zxing/qrcode/decoder/Mode;
     122: aload_0
     123: getfield      #4                  // Field stringToEncode:Ljava/lang/String;
     126: iload_3
     127: invokevirtual #55                 // Method java/lang/String.charAt:(I)C
     130: invokevirtual #62                 // Method canEncode:(Lcom/google/zxing/qrcode/decoder/Mode;C)Z
     133: ifeq          160
     136: aload_0
     137: aload_2
     138: iload_3
     139: new           #57                 // class com/google/zxing/qrcode/encoder/MinimalEncoder$Edge
     142: dup
     143: aload_0
     144: getstatic     #61                 // Field com/google/zxing/qrcode/decoder/Mode.KANJI:Lcom/google/zxing/qrcode/decoder/Mode;
     147: iload_3
     148: iconst_0
     149: iconst_1
     150: aload         4
     152: aload_1
     153: aconst_null
     154: invokespecial #59                 // Method com/google/zxing/qrcode/encoder/MinimalEncoder$Edge."<init>":(Lcom/google/zxing/qrcode/encoder/MinimalEncoder;Lcom/google/zxing/qrcode/decoder/Mode;IIILcom/google/zxing/qrcode/encoder/MinimalEncoder$Edge;Lcom/google/zxing/qrcode/decoder/Version;Lcom/google/zxing/qrcode/encoder/MinimalEncoder$1;)V
     157: invokevirtual #60                 // Method addEdge:([[[Lcom/google/zxing/qrcode/encoder/MinimalEncoder$Edge;ILcom/google/zxing/qrcode/encoder/MinimalEncoder$Edge;)V
     160: aload_0
     161: getfield      #4                  // Field stringToEncode:Ljava/lang/String;
     164: invokevirtual #63                 // Method java/lang/String.length:()I
     167: istore        8
     169: aload_0
     170: getstatic     #64                 // Field com/google/zxing/qrcode/decoder/Mode.ALPHANUMERIC:Lcom/google/zxing/qrcode/decoder/Mode;
     173: aload_0
     174: getfield      #4                  // Field stringToEncode:Ljava/lang/String;
     177: iload_3
     178: invokevirtual #55                 // Method java/lang/String.charAt:(I)C
     181: invokevirtual #62                 // Method canEncode:(Lcom/google/zxing/qrcode/decoder/Mode;C)Z
     184: ifeq          243
     187: aload_0
     188: aload_2
     189: iload_3
     190: new           #57                 // class com/google/zxing/qrcode/encoder/MinimalEncoder$Edge
     193: dup
     194: aload_0
     195: getstatic     #64                 // Field com/google/zxing/qrcode/decoder/Mode.ALPHANUMERIC:Lcom/google/zxing/qrcode/decoder/Mode;
     198: iload_3
     199: iconst_0
     200: iload_3
     201: iconst_1
     202: iadd
     203: iload         8
     205: if_icmpge     228
     208: aload_0
     209: getstatic     #64                 // Field com/google/zxing/qrcode/decoder/Mode.ALPHANUMERIC:Lcom/google/zxing/qrcode/decoder/Mode;
     212: aload_0
     213: getfield      #4                  // Field stringToEncode:Ljava/lang/String;
     216: iload_3
     217: iconst_1
     218: iadd
     219: invokevirtual #55                 // Method java/lang/String.charAt:(I)C
     222: invokevirtual #62                 // Method canEncode:(Lcom/google/zxing/qrcode/decoder/Mode;C)Z
     225: ifne          232
     228: iconst_1
     229: goto          233
     232: iconst_2
     233: aload         4
     235: aload_1
     236: aconst_null
     237: invokespecial #59                 // Method com/google/zxing/qrcode/encoder/MinimalEncoder$Edge."<init>":(Lcom/google/zxing/qrcode/encoder/MinimalEncoder;Lcom/google/zxing/qrcode/decoder/Mode;IIILcom/google/zxing/qrcode/encoder/MinimalEncoder$Edge;Lcom/google/zxing/qrcode/decoder/Version;Lcom/google/zxing/qrcode/encoder/MinimalEncoder$1;)V
     240: invokevirtual #60                 // Method addEdge:([[[Lcom/google/zxing/qrcode/encoder/MinimalEncoder$Edge;ILcom/google/zxing/qrcode/encoder/MinimalEncoder$Edge;)V
     243: aload_0
     244: getstatic     #65                 // Field com/google/zxing/qrcode/decoder/Mode.NUMERIC:Lcom/google/zxing/qrcode/decoder/Mode;
     247: aload_0
     248: getfield      #4                  // Field stringToEncode:Ljava/lang/String;
     251: iload_3
     252: invokevirtual #55                 // Method java/lang/String.charAt:(I)C
     255: invokevirtual #62                 // Method canEncode:(Lcom/google/zxing/qrcode/decoder/Mode;C)Z
     258: ifeq          349
     261: aload_0
     262: aload_2
     263: iload_3
     264: new           #57                 // class com/google/zxing/qrcode/encoder/MinimalEncoder$Edge
     267: dup
     268: aload_0
     269: getstatic     #65                 // Field com/google/zxing/qrcode/decoder/Mode.NUMERIC:Lcom/google/zxing/qrcode/decoder/Mode;
     272: iload_3
     273: iconst_0
     274: iload_3
     275: iconst_1
     276: iadd
     277: iload         8
     279: if_icmpge     302
     282: aload_0
     283: getstatic     #65                 // Field com/google/zxing/qrcode/decoder/Mode.NUMERIC:Lcom/google/zxing/qrcode/decoder/Mode;
     286: aload_0
     287: getfield      #4                  // Field stringToEncode:Ljava/lang/String;
     290: iload_3
     291: iconst_1
     292: iadd
     293: invokevirtual #55                 // Method java/lang/String.charAt:(I)C
     296: invokevirtual #62                 // Method canEncode:(Lcom/google/zxing/qrcode/decoder/Mode;C)Z
     299: ifne          306
     302: iconst_1
     303: goto          339
     306: iload_3
     307: iconst_2
     308: iadd
     309: iload         8
     311: if_icmpge     334
     314: aload_0
     315: getstatic     #65                 // Field com/google/zxing/qrcode/decoder/Mode.NUMERIC:Lcom/google/zxing/qrcode/decoder/Mode;
     318: aload_0
     319: getfield      #4                  // Field stringToEncode:Ljava/lang/String;
     322: iload_3
     323: iconst_2
     324: iadd
     325: invokevirtual #55                 // Method java/lang/String.charAt:(I)C
     328: invokevirtual #62                 // Method canEncode:(Lcom/google/zxing/qrcode/decoder/Mode;C)Z
     331: ifne          338
     334: iconst_2
     335: goto          339
     338: iconst_3
     339: aload         4
     341: aload_1
     342: aconst_null
     343: invokespecial #59                 // Method com/google/zxing/qrcode/encoder/MinimalEncoder$Edge."<init>":(Lcom/google/zxing/qrcode/encoder/MinimalEncoder;Lcom/google/zxing/qrcode/decoder/Mode;IIILcom/google/zxing/qrcode/encoder/MinimalEncoder$Edge;Lcom/google/zxing/qrcode/decoder/Version;Lcom/google/zxing/qrcode/encoder/MinimalEncoder$1;)V
     346: invokevirtual #60                 // Method addEdge:([[[Lcom/google/zxing/qrcode/encoder/MinimalEncoder$Edge;ILcom/google/zxing/qrcode/encoder/MinimalEncoder$Edge;)V
     349: return

  com.google.zxing.qrcode.encoder.MinimalEncoder$ResultList encodeSpecificVersion(com.google.zxing.qrcode.decoder.Version) throws com.google.zxing.WriterException;
    Code:
       0: aload_0
       1: getfield      #4                  // Field stringToEncode:Ljava/lang/String;
       4: invokevirtual #63                 // Method java/lang/String.length:()I
       7: istore_2
       8: iload_2
       9: iconst_1
      10: iadd
      11: aload_0
      12: getfield      #3                  // Field encoders:Lcom/google/zxing/common/ECIEncoderSet;
      15: invokevirtual #53                 // Method com/google/zxing/common/ECIEncoderSet.length:()I
      18: iconst_4
      19: multianewarray #66,  3            // class "[[[Lcom/google/zxing/qrcode/encoder/MinimalEncoder$Edge;"
      23: astore_3
      24: aload_0
      25: aload_1
      26: aload_3
      27: iconst_0
      28: aconst_null
      29: invokevirtual #67                 // Method addEdges:(Lcom/google/zxing/qrcode/decoder/Version;[[[Lcom/google/zxing/qrcode/encoder/MinimalEncoder$Edge;ILcom/google/zxing/qrcode/encoder/MinimalEncoder$Edge;)V
      32: iconst_1
      33: istore        4
      35: iload         4
      37: iload_2
      38: if_icmpgt     120
      41: iconst_0
      42: istore        5
      44: iload         5
      46: aload_0
      47: getfield      #3                  // Field encoders:Lcom/google/zxing/common/ECIEncoderSet;
      50: invokevirtual #53                 // Method com/google/zxing/common/ECIEncoderSet.length:()I
      53: if_icmpge     114
      56: iconst_0
      57: istore        6
      59: iload         6
      61: iconst_4
      62: if_icmpge     108
      65: aload_3
      66: iload         4
      68: aaload
      69: iload         5
      71: aaload
      72: iload         6
      74: aaload
      75: ifnull        102
      78: iload         4
      80: iload_2
      81: if_icmpge     102
      84: aload_0
      85: aload_1
      86: aload_3
      87: iload         4
      89: aload_3
      90: iload         4
      92: aaload
      93: iload         5
      95: aaload
      96: iload         6
      98: aaload
      99: invokevirtual #67                 // Method addEdges:(Lcom/google/zxing/qrcode/decoder/Version;[[[Lcom/google/zxing/qrcode/encoder/MinimalEncoder$Edge;ILcom/google/zxing/qrcode/encoder/MinimalEncoder$Edge;)V
     102: iinc          6, 1
     105: goto          59
     108: iinc          5, 1
     111: goto          44
     114: iinc          4, 1
     117: goto          35
     120: iconst_m1
     121: istore        4
     123: iconst_m1
     124: istore        5
     126: ldc           #19                 // int 2147483647
     128: istore        6
     130: iconst_0
     131: istore        7
     133: iload         7
     135: aload_0
     136: getfield      #3                  // Field encoders:Lcom/google/zxing/common/ECIEncoderSet;
     139: invokevirtual #53                 // Method com/google/zxing/common/ECIEncoderSet.length:()I
     142: if_icmpge     214
     145: iconst_0
     146: istore        8
     148: iload         8
     150: iconst_4
     151: if_icmpge     208
     154: aload_3
     155: iload_2
     156: aaload
     157: iload         7
     159: aaload
     160: iload         8
     162: aaload
     163: ifnull        202
     166: aload_3
     167: iload_2
     168: aaload
     169: iload         7
     171: aaload
     172: iload         8
     174: aaload
     175: astore        9
     177: aload         9
     179: invokestatic  #52                 // Method com/google/zxing/qrcode/encoder/MinimalEncoder$Edge.access$300:(Lcom/google/zxing/qrcode/encoder/MinimalEncoder$Edge;)I
     182: iload         6
     184: if_icmpge     202
     187: aload         9
     189: invokestatic  #52                 // Method com/google/zxing/qrcode/encoder/MinimalEncoder$Edge.access$300:(Lcom/google/zxing/qrcode/encoder/MinimalEncoder$Edge;)I
     192: istore        6
     194: iload         7
     196: istore        4
     198: iload         8
     200: istore        5
     202: iinc          8, 1
     205: goto          148
     208: iinc          7, 1
     211: goto          133
     214: iload         4
     216: ifge          254
     219: new           #22                 // class com/google/zxing/WriterException
     222: dup
     223: new           #27                 // class java/lang/StringBuilder
     226: dup
     227: invokespecial #28                 // Method java/lang/StringBuilder."<init>":()V
     230: ldc           #68                 // String Internal error: failed to encode \"
     232: invokevirtual #30                 // Method java/lang/StringBuilder.append:(Ljava/lang/String;)Ljava/lang/StringBuilder;
     235: aload_0
     236: getfield      #4                  // Field stringToEncode:Ljava/lang/String;
     239: invokevirtual #30                 // Method java/lang/StringBuilder.append:(Ljava/lang/String;)Ljava/lang/StringBuilder;
     242: ldc           #69                 // String \"
     244: invokevirtual #30                 // Method java/lang/StringBuilder.append:(Ljava/lang/String;)Ljava/lang/StringBuilder;
     247: invokevirtual #32                 // Method java/lang/StringBuilder.toString:()Ljava/lang/String;
     250: invokespecial #24                 // Method com/google/zxing/WriterException."<init>":(Ljava/lang/String;)V
     253: athrow
     254: new           #16                 // class com/google/zxing/qrcode/encoder/MinimalEncoder$ResultList
     257: dup
     258: aload_0
     259: aload_1
     260: aload_3
     261: iload_2
     262: aaload
     263: iload         4
     265: aaload
     266: iload         5
     268: aaload
     269: invokespecial #70                 // Method com/google/zxing/qrcode/encoder/MinimalEncoder$ResultList."<init>":(Lcom/google/zxing/qrcode/encoder/MinimalEncoder;Lcom/google/zxing/qrcode/decoder/Version;Lcom/google/zxing/qrcode/encoder/MinimalEncoder$Edge;)V
     272: areturn

  static java.lang.String access$500(com.google.zxing.qrcode.encoder.MinimalEncoder);
    Code:
       0: aload_0
       1: getfield      #4                  // Field stringToEncode:Ljava/lang/String;
       4: areturn

  static com.google.zxing.common.ECIEncoderSet access$600(com.google.zxing.qrcode.encoder.MinimalEncoder);
    Code:
       0: aload_0
       1: getfield      #3                  // Field encoders:Lcom/google/zxing/common/ECIEncoderSet;
       4: areturn

  static boolean access$900(com.google.zxing.qrcode.encoder.MinimalEncoder);
    Code:
       0: aload_0
       1: getfield      #2                  // Field isGS1:Z
       4: ireturn

  static com.google.zxing.qrcode.decoder.ErrorCorrectionLevel access$1100(com.google.zxing.qrcode.encoder.MinimalEncoder);
    Code:
       0: aload_0
       1: getfield      #1                  // Field ecLevel:Lcom/google/zxing/qrcode/decoder/ErrorCorrectionLevel;
       4: areturn
}
