Compiled from "MinimalEncoder.java"
final class com.google.zxing.qrcode.encoder.MinimalEncoder$VersionSize extends java.lang.Enum<com.google.zxing.qrcode.encoder.MinimalEncoder$VersionSize> {
  public static final com.google.zxing.qrcode.encoder.MinimalEncoder$VersionSize SMALL;

  public static final com.google.zxing.qrcode.encoder.MinimalEncoder$VersionSize MEDIUM;

  public static final com.google.zxing.qrcode.encoder.MinimalEncoder$VersionSize LARGE;

  private final java.lang.String description;

  private static final com.google.zxing.qrcode.encoder.MinimalEncoder$VersionSize[] $VALUES;

  public static com.google.zxing.qrcode.encoder.MinimalEncoder$VersionSize[] values();
    Code:
       0: getstatic     #1                  // Field $VALUES:[Lcom/google/zxing/qrcode/encoder/MinimalEncoder$VersionSize;
       3: invokevirtual #2                  // Method "[Lcom/google/zxing/qrcode/encoder/MinimalEncoder$VersionSize;".clone:()Ljava/lang/Object;
       6: checkcast     #3                  // class "[Lcom/google/zxing/qrcode/encoder/MinimalEncoder$VersionSize;"
       9: areturn

  public static com.google.zxing.qrcode.encoder.MinimalEncoder$VersionSize valueOf(java.lang.String);
    Code:
       0: ldc           #4                  // class com/google/zxing/qrcode/encoder/MinimalEncoder$VersionSize
       2: aload_0
       3: invokestatic  #5                  // Method java/lang/Enum.valueOf:(Ljava/lang/Class;Ljava/lang/String;)Ljava/lang/Enum;
       6: checkcast     #4                  // class com/google/zxing/qrcode/encoder/MinimalEncoder$VersionSize
       9: areturn

  private com.google.zxing.qrcode.encoder.MinimalEncoder$VersionSize(java.lang.String);
    Code:
       0: aload_0
       1: aload_1
       2: iload_2
       3: invokespecial #6                  // Method java/lang/Enum."<init>":(Ljava/lang/String;I)V
       6: aload_0
       7: aload_3
       8: putfield      #7                  // Field description:Ljava/lang/String;
      11: return

  public java.lang.String toString();
    Code:
       0: aload_0
       1: getfield      #7                  // Field description:Ljava/lang/String;
       4: areturn

  static {};
    Code:
       0: new           #4                  // class com/google/zxing/qrcode/encoder/MinimalEncoder$VersionSize
       3: dup
       4: ldc           #8                  // String SMALL
       6: iconst_0
       7: ldc           #9                  // String version 1-9
       9: invokespecial #10                 // Method "<init>":(Ljava/lang/String;ILjava/lang/String;)V
      12: putstatic     #11                 // Field SMALL:Lcom/google/zxing/qrcode/encoder/MinimalEncoder$VersionSize;
      15: new           #4                  // class com/google/zxing/qrcode/encoder/MinimalEncoder$VersionSize
      18: dup
      19: ldc           #12                 // String MEDIUM
      21: iconst_1
      22: ldc           #13                 // String version 10-26
      24: invokespecial #10                 // Method "<init>":(Ljava/lang/String;ILjava/lang/String;)V
      27: putstatic     #14                 // Field MEDIUM:Lcom/google/zxing/qrcode/encoder/MinimalEncoder$VersionSize;
      30: new           #4                  // class com/google/zxing/qrcode/encoder/MinimalEncoder$VersionSize
      33: dup
      34: ldc           #15                 // String LARGE
      36: iconst_2
      37: ldc           #16                 // String version 27-40
      39: invokespecial #10                 // Method "<init>":(Ljava/lang/String;ILjava/lang/String;)V
      42: putstatic     #17                 // Field LARGE:Lcom/google/zxing/qrcode/encoder/MinimalEncoder$VersionSize;
      45: iconst_3
      46: anewarray     #4                  // class com/google/zxing/qrcode/encoder/MinimalEncoder$VersionSize
      49: dup
      50: iconst_0
      51: getstatic     #11                 // Field SMALL:Lcom/google/zxing/qrcode/encoder/MinimalEncoder$VersionSize;
      54: aastore
      55: dup
      56: iconst_1
      57: getstatic     #14                 // Field MEDIUM:Lcom/google/zxing/qrcode/encoder/MinimalEncoder$VersionSize;
      60: aastore
      61: dup
      62: iconst_2
      63: getstatic     #17                 // Field LARGE:Lcom/google/zxing/qrcode/encoder/MinimalEncoder$VersionSize;
      66: aastore
      67: putstatic     #1                  // Field $VALUES:[Lcom/google/zxing/qrcode/encoder/MinimalEncoder$VersionSize;
      70: return
}
