Compiled from "MinimalEncoder.java"
class com.google.zxing.qrcode.encoder.MinimalEncoder$1 {
  static final int[] $SwitchMap$com$google$zxing$qrcode$encoder$MinimalEncoder$VersionSize;

  static final int[] $SwitchMap$com$google$zxing$qrcode$decoder$Mode;

  static {};
    Code:
       0: invokestatic  #1                  // Method com/google/zxing/qrcode/decoder/Mode.values:()[Lcom/google/zxing/qrcode/decoder/Mode;
       3: arraylength
       4: newarray       int
       6: putstatic     #2                  // Field $SwitchMap$com$google$zxing$qrcode$decoder$Mode:[I
       9: getstatic     #2                  // Field $SwitchMap$com$google$zxing$qrcode$decoder$Mode:[I
      12: getstatic     #3                  // Field com/google/zxing/qrcode/decoder/Mode.KANJI:Lcom/google/zxing/qrcode/decoder/Mode;
      15: invokevirtual #4                  // Method com/google/zxing/qrcode/decoder/Mode.ordinal:()I
      18: iconst_1
      19: iastore
      20: goto          24
      23: astore_0
      24: getstatic     #2                  // Field $SwitchMap$com$google$zxing$qrcode$decoder$Mode:[I
      27: getstatic     #6                  // Field com/google/zxing/qrcode/decoder/Mode.ALPHANUMERIC:Lcom/google/zxing/qrcode/decoder/Mode;
      30: invokevirtual #4                  // Method com/google/zxing/qrcode/decoder/Mode.ordinal:()I
      33: iconst_2
      34: iastore
      35: goto          39
      38: astore_0
      39: getstatic     #2                  // Field $SwitchMap$com$google$zxing$qrcode$decoder$Mode:[I
      42: getstatic     #7                  // Field com/google/zxing/qrcode/decoder/Mode.NUMERIC:Lcom/google/zxing/qrcode/decoder/Mode;
      45: invokevirtual #4                  // Method com/google/zxing/qrcode/decoder/Mode.ordinal:()I
      48: iconst_3
      49: iastore
      50: goto          54
      53: astore_0
      54: getstatic     #2                  // Field $SwitchMap$com$google$zxing$qrcode$decoder$Mode:[I
      57: getstatic     #8                  // Field com/google/zxing/qrcode/decoder/Mode.BYTE:Lcom/google/zxing/qrcode/decoder/Mode;
      60: invokevirtual #4                  // Method com/google/zxing/qrcode/decoder/Mode.ordinal:()I
      63: iconst_4
      64: iastore
      65: goto          69
      68: astore_0
      69: getstatic     #2                  // Field $SwitchMap$com$google$zxing$qrcode$decoder$Mode:[I
      72: getstatic     #9                  // Field com/google/zxing/qrcode/decoder/Mode.ECI:Lcom/google/zxing/qrcode/decoder/Mode;
      75: invokevirtual #4                  // Method com/google/zxing/qrcode/decoder/Mode.ordinal:()I
      78: iconst_5
      79: iastore
      80: goto          84
      83: astore_0
      84: invokestatic  #10                 // Method com/google/zxing/qrcode/encoder/MinimalEncoder$VersionSize.values:()[Lcom/google/zxing/qrcode/encoder/MinimalEncoder$VersionSize;
      87: arraylength
      88: newarray       int
      90: putstatic     #11                 // Field $SwitchMap$com$google$zxing$qrcode$encoder$MinimalEncoder$VersionSize:[I
      93: getstatic     #11                 // Field $SwitchMap$com$google$zxing$qrcode$encoder$MinimalEncoder$VersionSize:[I
      96: getstatic     #12                 // Field com/google/zxing/qrcode/encoder/MinimalEncoder$VersionSize.SMALL:Lcom/google/zxing/qrcode/encoder/MinimalEncoder$VersionSize;
      99: invokevirtual #13                 // Method com/google/zxing/qrcode/encoder/MinimalEncoder$VersionSize.ordinal:()I
     102: iconst_1
     103: iastore
     104: goto          108
     107: astore_0
     108: getstatic     #11                 // Field $SwitchMap$com$google$zxing$qrcode$encoder$MinimalEncoder$VersionSize:[I
     111: getstatic     #14                 // Field com/google/zxing/qrcode/encoder/MinimalEncoder$VersionSize.MEDIUM:Lcom/google/zxing/qrcode/encoder/MinimalEncoder$VersionSize;
     114: invokevirtual #13                 // Method com/google/zxing/qrcode/encoder/MinimalEncoder$VersionSize.ordinal:()I
     117: iconst_2
     118: iastore
     119: goto          123
     122: astore_0
     123: getstatic     #11                 // Field $SwitchMap$com$google$zxing$qrcode$encoder$MinimalEncoder$VersionSize:[I
     126: getstatic     #15                 // Field com/google/zxing/qrcode/encoder/MinimalEncoder$VersionSize.LARGE:Lcom/google/zxing/qrcode/encoder/MinimalEncoder$VersionSize;
     129: invokevirtual #13                 // Method com/google/zxing/qrcode/encoder/MinimalEncoder$VersionSize.ordinal:()I
     132: iconst_3
     133: iastore
     134: goto          138
     137: astore_0
     138: return
    Exception table:
       from    to  target type
           9    20    23   Class java/lang/NoSuchFieldError
          24    35    38   Class java/lang/NoSuchFieldError
          39    50    53   Class java/lang/NoSuchFieldError
          54    65    68   Class java/lang/NoSuchFieldError
          69    80    83   Class java/lang/NoSuchFieldError
          93   104   107   Class java/lang/NoSuchFieldError
         108   119   122   Class java/lang/NoSuchFieldError
         123   134   137   Class java/lang/NoSuchFieldError
}
