Compiled from "QRCode.java"
public final class com.google.zxing.qrcode.encoder.QRCode {
  public static final int NUM_MASK_PATTERNS;

  private com.google.zxing.qrcode.decoder.Mode mode;

  private com.google.zxing.qrcode.decoder.ErrorCorrectionLevel ecLevel;

  private com.google.zxing.qrcode.decoder.Version version;

  private int maskPattern;

  private com.google.zxing.qrcode.encoder.ByteMatrix matrix;

  public com.google.zxing.qrcode.encoder.QRCode();
    Code: 
       0: aload_0
       1: invokespecial #1                  // Method java/lang/Object."<init>":()V
       4: aload_0
       5: iconst_m1
       6: putfield      #2                  // Field maskPattern:I
       9: return

  public com.google.zxing.qrcode.decoder.Mode getMode();
    Code:
       0: aload_0
       1: getfield      #3                  // Field mode:Lcom/google/zxing/qrcode/decoder/Mode;
       4: areturn

  public com.google.zxing.qrcode.decoder.ErrorCorrectionLevel getECLevel();
    Code:
       0: aload_0
       1: getfield      #4                  // Field ecLevel:Lcom/google/zxing/qrcode/decoder/ErrorCorrectionLevel;
       4: areturn

  public com.google.zxing.qrcode.decoder.Version getVersion();
    Code:
       0: aload_0
       1: getfield      #5                  // Field version:Lcom/google/zxing/qrcode/decoder/Version;
       4: areturn

  public int getMaskPattern();
    Code:
       0: aload_0
       1: getfield      #2                  // Field maskPattern:I
       4: ireturn

  public com.google.zxing.qrcode.encoder.ByteMatrix getMatrix();
    Code:
       0: aload_0
       1: getfield      #6                  // Field matrix:Lcom/google/zxing/qrcode/encoder/ByteMatrix;
       4: areturn

  public java.lang.String toString();
    Code:
       0: new           #7                  // class java/lang/StringBuilder
       3: dup
       4: sipush        200
       7: invokespecial #8                  // Method java/lang/StringBuilder."<init>":(I)V
      10: astore_1
      11: aload_1
      12: ldc           #9                  // String <<\n
      14: invokevirtual #10                 // Method java/lang/StringBuilder.append:(Ljava/lang/String;)Ljava/lang/StringBuilder;
      17: pop
      18: aload_1
      19: ldc           #11                 // String  mode:
      21: invokevirtual #10                 // Method java/lang/StringBuilder.append:(Ljava/lang/String;)Ljava/lang/StringBuilder;
      24: pop
      25: aload_1
      26: aload_0
      27: getfield      #3                  // Field mode:Lcom/google/zxing/qrcode/decoder/Mode;
      30: invokevirtual #12                 // Method java/lang/StringBuilder.append:(Ljava/lang/Object;)Ljava/lang/StringBuilder;
      33: pop
      34: aload_1
      35: ldc           #13                 // String \n ecLevel:
      37: invokevirtual #10                 // Method java/lang/StringBuilder.append:(Ljava/lang/String;)Ljava/lang/StringBuilder;
      40: pop
      41: aload_1
      42: aload_0
      43: getfield      #4                  // Field ecLevel:Lcom/google/zxing/qrcode/decoder/ErrorCorrectionLevel;
      46: invokevirtual #12                 // Method java/lang/StringBuilder.append:(Ljava/lang/Object;)Ljava/lang/StringBuilder;
      49: pop
      50: aload_1
      51: ldc           #14                 // String \n version:
      53: invokevirtual #10                 // Method java/lang/StringBuilder.append:(Ljava/lang/String;)Ljava/lang/StringBuilder;
      56: pop
      57: aload_1
      58: aload_0
      59: getfield      #5                  // Field version:Lcom/google/zxing/qrcode/decoder/Version;
      62: invokevirtual #12                 // Method java/lang/StringBuilder.append:(Ljava/lang/Object;)Ljava/lang/StringBuilder;
      65: pop
      66: aload_1
      67: ldc           #15                 // String \n maskPattern:
      69: invokevirtual #10                 // Method java/lang/StringBuilder.append:(Ljava/lang/String;)Ljava/lang/StringBuilder;
      72: pop
      73: aload_1
      74: aload_0
      75: getfield      #2                  // Field maskPattern:I
      78: invokevirtual #16                 // Method java/lang/StringBuilder.append:(I)Ljava/lang/StringBuilder;
      81: pop
      82: aload_0
      83: getfield      #6                  // Field matrix:Lcom/google/zxing/qrcode/encoder/ByteMatrix;
      86: ifnonnull     99
      89: aload_1
      90: ldc           #17                 // String \n matrix: null\n
      92: invokevirtual #10                 // Method java/lang/StringBuilder.append:(Ljava/lang/String;)Ljava/lang/StringBuilder;
      95: pop
      96: goto          115
      99: aload_1
     100: ldc           #18                 // String \n matrix:\n
     102: invokevirtual #10                 // Method java/lang/StringBuilder.append:(Ljava/lang/String;)Ljava/lang/StringBuilder;
     105: pop
     106: aload_1
     107: aload_0
     108: getfield      #6                  // Field matrix:Lcom/google/zxing/qrcode/encoder/ByteMatrix;
     111: invokevirtual #12                 // Method java/lang/StringBuilder.append:(Ljava/lang/Object;)Ljava/lang/StringBuilder;
     114: pop
     115: aload_1
     116: ldc           #19                 // String >>\n
     118: invokevirtual #10                 // Method java/lang/StringBuilder.append:(Ljava/lang/String;)Ljava/lang/StringBuilder;
     121: pop
     122: aload_1
     123: invokevirtual #20                 // Method java/lang/StringBuilder.toString:()Ljava/lang/String;
     126: areturn

  public void setMode(com.google.zxing.qrcode.decoder.Mode);
    Code:
       0: aload_0
       1: aload_1
       2: putfield      #3                  // Field mode:Lcom/google/zxing/qrcode/decoder/Mode;
       5: return

  public void setECLevel(com.google.zxing.qrcode.decoder.ErrorCorrectionLevel);
    Code:
       0: aload_0
       1: aload_1
       2: putfield      #4                  // Field ecLevel:Lcom/google/zxing/qrcode/decoder/ErrorCorrectionLevel;
       5: return

  public void setVersion(com.google.zxing.qrcode.decoder.Version);
    Code:
       0: aload_0
       1: aload_1
       2: putfield      #5                  // Field version:Lcom/google/zxing/qrcode/decoder/Version;
       5: return

  public void setMaskPattern(int);
    Code:
       0: aload_0
       1: iload_1
       2: putfield      #2                  // Field maskPattern:I
       5: return

  public void setMatrix(com.google.zxing.qrcode.encoder.ByteMatrix);
    Code:
       0: aload_0
       1: aload_1
       2: putfield      #6                  // Field matrix:Lcom/google/zxing/qrcode/encoder/ByteMatrix;
       5: return

  public static boolean isValidMaskPattern(int);
    Code:
       0: iload_0
       1: iflt          14
       4: iload_0
       5: bipush        8
       7: if_icmpge     14
      10: iconst_1
      11: goto          15
      14: iconst_0
      15: ireturn
}
