Compiled from "ConfigParser.java"
public class org.apache.dubbo.rpc.cluster.configurator.parser.ConfigParser {
  public org.apache.dubbo.rpc.cluster.configurator.parser.ConfigParser();
    Code:
       0: aload_0
       1: invokespecial #5                  // Method java/lang/Object."<init>":()V
       4: return

  public static java.util.List<org.apache.dubbo.common.URL> parseConfigurators(java.lang.String);
    Code:
       0: aload_0
       1: invokestatic  #6                  // Method parseJsonArray:(Ljava/lang/String;)Ljava/util/List;
       4: astore_1
       5: aload_1
       6: invokestatic  #7                  // Method org/apache/dubbo/common/utils/CollectionUtils.isNotEmpty:(Ljava/util/Collection;)Z
       9: ifeq          14
      12: aload_1
      13: areturn
      14: new           #8                  // class java/util/ArrayList
      17: dup
      18: invokespecial #9                  // Method java/util/ArrayList."<init>":()V
      21: astore_2
      22: aload_0
      23: invokestatic  #10                 // Method parseObject:(Ljava/lang/String;)Lorg/apache/dubbo/rpc/cluster/configurator/parser/model/ConfiguratorConfig;
      26: astore_3
      27: aload_3
      28: invokevirtual #11                 // Method org/apache/dubbo/rpc/cluster/configurator/parser/model/ConfiguratorConfig.getScope:()Ljava/lang/String;
      31: astore        4
      33: aload_3
      34: invokevirtual #12                 // Method org/apache/dubbo/rpc/cluster/configurator/parser/model/ConfiguratorConfig.getConfigs:()Ljava/util/List;
      37: astore        5
      39: ldc           #13                 // String application
      41: aload         4
      43: invokevirtual #14                 // Method java/lang/String.equals:(Ljava/lang/Object;)Z
      46: ifeq          66
      49: aload         5
      51: aload_2
      52: aload_3
      53: invokedynamic #15,  0             // InvokeDynamic #0:accept:(Ljava/util/List;Lorg/apache/dubbo/rpc/cluster/configurator/parser/model/ConfiguratorConfig;)Ljava/util/function/Consumer;
      58: invokeinterface #16,  2           // InterfaceMethod java/util/List.forEach:(Ljava/util/function/Consumer;)V
      63: goto          80
      66: aload         5
      68: aload_2
      69: aload_3
      70: invokedynamic #17,  0             // InvokeDynamic #1:accept:(Ljava/util/List;Lorg/apache/dubbo/rpc/cluster/configurator/parser/model/ConfiguratorConfig;)Ljava/util/function/Consumer;
      75: invokeinterface #16,  2           // InterfaceMethod java/util/List.forEach:(Ljava/util/function/Consumer;)V
      80: aload_2
      81: areturn

  private static java.util.List<org.apache.dubbo.common.URL> parseJsonArray(java.lang.String);
    Code:
       0: new           #8                  // class java/util/ArrayList
       3: dup
       4: invokespecial #9                  // Method java/util/ArrayList."<init>":()V
       7: astore_1
       8: aload_0
       9: ldc           #18                 // class java/lang/String
      11: invokestatic  #19                 // Method org/apache/dubbo/common/utils/JsonUtils.toJavaList:(Ljava/lang/String;Ljava/lang/Class;)Ljava/util/List;
      14: astore_2
      15: aload_2
      16: invokestatic  #20                 // Method org/apache/dubbo/common/utils/CollectionUtils.isEmpty:(Ljava/util/Collection;)Z
      19: ifne          34
      22: aload_2
      23: aload_1
      24: invokedynamic #21,  0             // InvokeDynamic #2:accept:(Ljava/util/List;)Ljava/util/function/Consumer;
      29: invokeinterface #16,  2           // InterfaceMethod java/util/List.forEach:(Ljava/util/function/Consumer;)V
      34: goto          40
      37: astore_2
      38: aconst_null
      39: areturn
      40: aload_1
      41: areturn
    Exception table:
       from    to  target type
           8    34    37   Class java/lang/Throwable

  private static org.apache.dubbo.rpc.cluster.configurator.parser.model.ConfiguratorConfig parseObject(java.lang.String);
    Code:
       0: new           #23                 // class org/yaml/snakeyaml/Yaml
       3: dup
       4: new           #24                 // class org/yaml/snakeyaml/constructor/SafeConstructor
       7: dup
       8: new           #25                 // class org/yaml/snakeyaml/LoaderOptions
      11: dup
      12: invokespecial #26                 // Method org/yaml/snakeyaml/LoaderOptions."<init>":()V
      15: invokespecial #27                 // Method org/yaml/snakeyaml/constructor/SafeConstructor."<init>":(Lorg/yaml/snakeyaml/LoaderOptions;)V
      18: invokespecial #28                 // Method org/yaml/snakeyaml/Yaml."<init>":(Lorg/yaml/snakeyaml/constructor/BaseConstructor;)V
      21: astore_1
      22: aload_1
      23: aload_0
      24: invokevirtual #29                 // Method org/yaml/snakeyaml/Yaml.load:(Ljava/lang/String;)Ljava/lang/Object;
      27: checkcast     #30                 // class java/util/Map
      30: astore_2
      31: aload_2
      32: invokestatic  #31                 // Method org/apache/dubbo/rpc/cluster/configurator/parser/model/ConfiguratorConfig.parseFromMap:(Ljava/util/Map;)Lorg/apache/dubbo/rpc/cluster/configurator/parser/model/ConfiguratorConfig;
      35: areturn

  private static java.util.List<org.apache.dubbo.common.URL> serviceItemToUrls(org.apache.dubbo.rpc.cluster.configurator.parser.model.ConfigItem, org.apache.dubbo.rpc.cluster.configurator.parser.model.ConfiguratorConfig);
    Code:
       0: new           #8                  // class java/util/ArrayList
       3: dup
       4: invokespecial #9                  // Method java/util/ArrayList."<init>":()V
       7: astore_2
       8: aload_0
       9: invokestatic  #32                 // Method parseAddresses:(Lorg/apache/dubbo/rpc/cluster/configurator/parser/model/ConfigItem;)Ljava/util/List;
      12: astore_3
      13: aload_3
      14: aload_1
      15: aload_0
      16: aload_2
      17: invokedynamic #33,  0             // InvokeDynamic #3:accept:(Lorg/apache/dubbo/rpc/cluster/configurator/parser/model/ConfiguratorConfig;Lorg/apache/dubbo/rpc/cluster/configurator/parser/model/ConfigItem;Ljava/util/List;)Ljava/util/function/Consumer;
      22: invokeinterface #16,  2           // InterfaceMethod java/util/List.forEach:(Ljava/util/function/Consumer;)V
      27: aload_2
      28: areturn

  private static java.util.List<org.apache.dubbo.common.URL> appItemToUrls(org.apache.dubbo.rpc.cluster.configurator.parser.model.ConfigItem, org.apache.dubbo.rpc.cluster.configurator.parser.model.ConfiguratorConfig);
    Code:
       0: new           #8                  // class java/util/ArrayList
       3: dup
       4: invokespecial #9                  // Method java/util/ArrayList."<init>":()V
       7: astore_2
       8: aload_0
       9: invokestatic  #32                 // Method parseAddresses:(Lorg/apache/dubbo/rpc/cluster/configurator/parser/model/ConfigItem;)Ljava/util/List;
      12: astore_3
      13: aload_3
      14: invokeinterface #34,  1           // InterfaceMethod java/util/List.iterator:()Ljava/util/Iterator;
      19: astore        4
      21: aload         4
      23: invokeinterface #35,  1           // InterfaceMethod java/util/Iterator.hasNext:()Z
      28: ifeq          248
      31: aload         4
      33: invokeinterface #36,  1           // InterfaceMethod java/util/Iterator.next:()Ljava/lang/Object;
      38: checkcast     #18                 // class java/lang/String
      41: astore        5
      43: new           #37                 // class java/lang/StringBuilder
      46: dup
      47: invokespecial #38                 // Method java/lang/StringBuilder."<init>":()V
      50: astore        6
      52: aload         6
      54: ldc           #39                 // String override://
      56: invokevirtual #40                 // Method java/lang/StringBuilder.append:(Ljava/lang/String;)Ljava/lang/StringBuilder;
      59: aload         5
      61: invokevirtual #40                 // Method java/lang/StringBuilder.append:(Ljava/lang/String;)Ljava/lang/StringBuilder;
      64: bipush        47
      66: invokevirtual #41                 // Method java/lang/StringBuilder.append:(C)Ljava/lang/StringBuilder;
      69: pop
      70: aload_0
      71: invokevirtual #42                 // Method org/apache/dubbo/rpc/cluster/configurator/parser/model/ConfigItem.getServices:()Ljava/util/List;
      74: astore        7
      76: aload         7
      78: ifnonnull     90
      81: new           #8                  // class java/util/ArrayList
      84: dup
      85: invokespecial #9                  // Method java/util/ArrayList."<init>":()V
      88: astore        7
      90: aload         7
      92: invokeinterface #43,  1           // InterfaceMethod java/util/List.isEmpty:()Z
      97: ifeq          110
     100: aload         7
     102: ldc           #44                 // String *
     104: invokeinterface #45,  2           // InterfaceMethod java/util/List.add:(Ljava/lang/Object;)Z
     109: pop
     110: aload         7
     112: invokeinterface #34,  1           // InterfaceMethod java/util/List.iterator:()Ljava/util/Iterator;
     117: astore        8
     119: aload         8
     121: invokeinterface #35,  1           // InterfaceMethod java/util/Iterator.hasNext:()Z
     126: ifeq          245
     129: aload         8
     131: invokeinterface #36,  1           // InterfaceMethod java/util/Iterator.next:()Ljava/lang/Object;
     136: checkcast     #18                 // class java/lang/String
     139: astore        9
     141: new           #37                 // class java/lang/StringBuilder
     144: dup
     145: aload         6
     147: invokespecial #46                 // Method java/lang/StringBuilder."<init>":(Ljava/lang/CharSequence;)V
     150: astore        10
     152: aload         10
     154: aload         9
     156: invokestatic  #47                 // Method appendService:(Ljava/lang/String;)Ljava/lang/String;
     159: invokevirtual #40                 // Method java/lang/StringBuilder.append:(Ljava/lang/String;)Ljava/lang/StringBuilder;
     162: pop
     163: aload         10
     165: aload_0
     166: invokestatic  #48                 // Method toParameterString:(Lorg/apache/dubbo/rpc/cluster/configurator/parser/model/ConfigItem;)Ljava/lang/String;
     169: invokevirtual #40                 // Method java/lang/StringBuilder.append:(Ljava/lang/String;)Ljava/lang/StringBuilder;
     172: pop
     173: aload         10
     175: ldc           #49                 // String &application=
     177: invokevirtual #40                 // Method java/lang/StringBuilder.append:(Ljava/lang/String;)Ljava/lang/StringBuilder;
     180: aload_1
     181: invokevirtual #50                 // Method org/apache/dubbo/rpc/cluster/configurator/parser/model/ConfiguratorConfig.getKey:()Ljava/lang/String;
     184: invokevirtual #40                 // Method java/lang/StringBuilder.append:(Ljava/lang/String;)Ljava/lang/StringBuilder;
     187: pop
     188: aload_0
     189: aload_1
     190: aload         10
     192: invokestatic  #51                 // Method parseEnabled:(Lorg/apache/dubbo/rpc/cluster/configurator/parser/model/ConfigItem;Lorg/apache/dubbo/rpc/cluster/configurator/parser/model/ConfiguratorConfig;Ljava/lang/StringBuilder;)V
     195: aload         10
     197: ldc           #52                 // String &category=
     199: invokevirtual #40                 // Method java/lang/StringBuilder.append:(Ljava/lang/String;)Ljava/lang/StringBuilder;
     202: ldc           #53                 // String appdynamicconfigurators
     204: invokevirtual #40                 // Method java/lang/StringBuilder.append:(Ljava/lang/String;)Ljava/lang/StringBuilder;
     207: pop
     208: aload         10
     210: ldc           #54                 // String &configVersion=
     212: invokevirtual #40                 // Method java/lang/StringBuilder.append:(Ljava/lang/String;)Ljava/lang/StringBuilder;
     215: aload_1
     216: invokevirtual #55                 // Method org/apache/dubbo/rpc/cluster/configurator/parser/model/ConfiguratorConfig.getConfigVersion:()Ljava/lang/String;
     219: invokevirtual #40                 // Method java/lang/StringBuilder.append:(Ljava/lang/String;)Ljava/lang/StringBuilder;
     222: pop
     223: aload_2
     224: aload         10
     226: invokevirtual #56                 // Method java/lang/StringBuilder.toString:()Ljava/lang/String;
     229: invokestatic  #57                 // Method org/apache/dubbo/common/URL.valueOf:(Ljava/lang/String;)Lorg/apache/dubbo/common/URL;
     232: aload_0
     233: invokestatic  #58                 // Method appendMatchCondition:(Lorg/apache/dubbo/common/URL;Lorg/apache/dubbo/rpc/cluster/configurator/parser/model/ConfigItem;)Lorg/apache/dubbo/common/URL;
     236: invokeinterface #45,  2           // InterfaceMethod java/util/List.add:(Ljava/lang/Object;)Z
     241: pop
     242: goto          119
     245: goto          21
     248: aload_2
     249: areturn

  private static java.lang.String toParameterString(org.apache.dubbo.rpc.cluster.configurator.parser.model.ConfigItem);
    Code:
       0: new           #37                 // class java/lang/StringBuilder
       3: dup
       4: invokespecial #38                 // Method java/lang/StringBuilder."<init>":()V
       7: astore_1
       8: aload_1
       9: ldc           #59                 // String category=
      11: invokevirtual #40                 // Method java/lang/StringBuilder.append:(Ljava/lang/String;)Ljava/lang/StringBuilder;
      14: pop
      15: aload_1
      16: ldc           #60                 // String dynamicconfigurators
      18: invokevirtual #40                 // Method java/lang/StringBuilder.append:(Ljava/lang/String;)Ljava/lang/StringBuilder;
      21: pop
      22: aload_0
      23: invokevirtual #61                 // Method org/apache/dubbo/rpc/cluster/configurator/parser/model/ConfigItem.getSide:()Ljava/lang/String;
      26: ifnull        45
      29: aload_1
      30: ldc           #62                 // String &side=
      32: invokevirtual #40                 // Method java/lang/StringBuilder.append:(Ljava/lang/String;)Ljava/lang/StringBuilder;
      35: pop
      36: aload_1
      37: aload_0
      38: invokevirtual #61                 // Method org/apache/dubbo/rpc/cluster/configurator/parser/model/ConfigItem.getSide:()Ljava/lang/String;
      41: invokevirtual #40                 // Method java/lang/StringBuilder.append:(Ljava/lang/String;)Ljava/lang/StringBuilder;
      44: pop
      45: aload_0
      46: invokevirtual #63                 // Method org/apache/dubbo/rpc/cluster/configurator/parser/model/ConfigItem.getParameters:()Ljava/util/Map;
      49: astore_2
      50: aload_2
      51: invokestatic  #64                 // Method org/apache/dubbo/common/utils/CollectionUtils.isEmptyMap:(Ljava/util/Map;)Z
      54: ifeq          67
      57: new           #65                 // class java/lang/IllegalStateException
      60: dup
      61: ldc           #66                 // String Invalid configurator rule, please specify at least one parameter you want to change in the rule.
      63: invokespecial #67                 // Method java/lang/IllegalStateException."<init>":(Ljava/lang/String;)V
      66: athrow
      67: aload_2
      68: aload_1
      69: invokedynamic #68,  0             // InvokeDynamic #4:accept:(Ljava/lang/StringBuilder;)Ljava/util/function/BiConsumer;
      74: invokeinterface #69,  2           // InterfaceMethod java/util/Map.forEach:(Ljava/util/function/BiConsumer;)V
      79: aload_0
      80: invokevirtual #70                 // Method org/apache/dubbo/rpc/cluster/configurator/parser/model/ConfigItem.getProviderAddresses:()Ljava/util/List;
      83: invokestatic  #7                  // Method org/apache/dubbo/common/utils/CollectionUtils.isNotEmpty:(Ljava/util/Collection;)Z
      86: ifeq          127
      89: aload_1
      90: bipush        38
      92: invokevirtual #41                 // Method java/lang/StringBuilder.append:(C)Ljava/lang/StringBuilder;
      95: pop
      96: aload_1
      97: ldc           #71                 // String providerAddresses
      99: invokevirtual #40                 // Method java/lang/StringBuilder.append:(Ljava/lang/String;)Ljava/lang/StringBuilder;
     102: pop
     103: aload_1
     104: bipush        61
     106: invokevirtual #41                 // Method java/lang/StringBuilder.append:(C)Ljava/lang/StringBuilder;
     109: pop
     110: aload_1
     111: aload_0
     112: invokevirtual #70                 // Method org/apache/dubbo/rpc/cluster/configurator/parser/model/ConfigItem.getProviderAddresses:()Ljava/util/List;
     115: ldc           #72                 // String ,
     117: invokestatic  #73                 // Method org/apache/dubbo/common/utils/CollectionUtils.join:(Ljava/util/List;Ljava/lang/String;)Ljava/lang/String;
     120: invokevirtual #40                 // Method java/lang/StringBuilder.append:(Ljava/lang/String;)Ljava/lang/StringBuilder;
     123: pop
     124: goto          174
     127: ldc           #74                 // String provider
     129: aload_0
     130: invokevirtual #61                 // Method org/apache/dubbo/rpc/cluster/configurator/parser/model/ConfigItem.getSide:()Ljava/lang/String;
     133: invokevirtual #14                 // Method java/lang/String.equals:(Ljava/lang/Object;)Z
     136: ifeq          174
     139: aload_1
     140: bipush        38
     142: invokevirtual #41                 // Method java/lang/StringBuilder.append:(C)Ljava/lang/StringBuilder;
     145: pop
     146: aload_1
     147: ldc           #71                 // String providerAddresses
     149: invokevirtual #40                 // Method java/lang/StringBuilder.append:(Ljava/lang/String;)Ljava/lang/StringBuilder;
     152: pop
     153: aload_1
     154: bipush        61
     156: invokevirtual #41                 // Method java/lang/StringBuilder.append:(C)Ljava/lang/StringBuilder;
     159: pop
     160: aload_1
     161: aload_0
     162: invokestatic  #32                 // Method parseAddresses:(Lorg/apache/dubbo/rpc/cluster/configurator/parser/model/ConfigItem;)Ljava/util/List;
     165: ldc           #72                 // String ,
     167: invokestatic  #73                 // Method org/apache/dubbo/common/utils/CollectionUtils.join:(Ljava/util/List;Ljava/lang/String;)Ljava/lang/String;
     170: invokevirtual #40                 // Method java/lang/StringBuilder.append:(Ljava/lang/String;)Ljava/lang/StringBuilder;
     173: pop
     174: aload_1
     175: invokevirtual #56                 // Method java/lang/StringBuilder.toString:()Ljava/lang/String;
     178: areturn

  private static java.lang.String appendService(java.lang.String);
    Code:
       0: new           #37                 // class java/lang/StringBuilder
       3: dup
       4: invokespecial #38                 // Method java/lang/StringBuilder."<init>":()V
       7: astore_1
       8: aload_0
       9: invokestatic  #75                 // Method org/apache/dubbo/common/utils/StringUtils.isEmpty:(Ljava/lang/String;)Z
      12: ifeq          25
      15: new           #65                 // class java/lang/IllegalStateException
      18: dup
      19: ldc           #76                 // String service field in configuration is null.
      21: invokespecial #67                 // Method java/lang/IllegalStateException."<init>":(Ljava/lang/String;)V
      24: athrow
      25: aload_0
      26: astore_2
      27: aload_2
      28: bipush        47
      30: invokevirtual #77                 // Method java/lang/String.indexOf:(I)I
      33: istore_3
      34: iload_3
      35: ifle          68
      38: aload_1
      39: ldc           #78                 // String group=
      41: invokevirtual #40                 // Method java/lang/StringBuilder.append:(Ljava/lang/String;)Ljava/lang/StringBuilder;
      44: pop
      45: aload_1
      46: aload_2
      47: iconst_0
      48: iload_3
      49: invokevirtual #79                 // Method java/lang/StringBuilder.append:(Ljava/lang/CharSequence;II)Ljava/lang/StringBuilder;
      52: pop
      53: aload_1
      54: bipush        38
      56: invokevirtual #41                 // Method java/lang/StringBuilder.append:(C)Ljava/lang/StringBuilder;
      59: pop
      60: aload_2
      61: iload_3
      62: iconst_1
      63: iadd
      64: invokevirtual #80                 // Method java/lang/String.substring:(I)Ljava/lang/String;
      67: astore_2
      68: aload_2
      69: bipush        58
      71: invokevirtual #77                 // Method java/lang/String.indexOf:(I)I
      74: istore        4
      76: iload         4
      78: ifle          116
      81: aload_1
      82: ldc           #81                 // String version=
      84: invokevirtual #40                 // Method java/lang/StringBuilder.append:(Ljava/lang/String;)Ljava/lang/StringBuilder;
      87: pop
      88: aload_1
      89: aload_2
      90: iload         4
      92: iconst_1
      93: iadd
      94: invokevirtual #80                 // Method java/lang/String.substring:(I)Ljava/lang/String;
      97: invokevirtual #40                 // Method java/lang/StringBuilder.append:(Ljava/lang/String;)Ljava/lang/StringBuilder;
     100: pop
     101: aload_1
     102: bipush        38
     104: invokevirtual #41                 // Method java/lang/StringBuilder.append:(C)Ljava/lang/StringBuilder;
     107: pop
     108: aload_2
     109: iconst_0
     110: iload         4
     112: invokevirtual #82                 // Method java/lang/String.substring:(II)Ljava/lang/String;
     115: astore_2
     116: aload_1
     117: iconst_0
     118: new           #37                 // class java/lang/StringBuilder
     121: dup
     122: invokespecial #38                 // Method java/lang/StringBuilder."<init>":()V
     125: aload_2
     126: invokevirtual #40                 // Method java/lang/StringBuilder.append:(Ljava/lang/String;)Ljava/lang/StringBuilder;
     129: ldc           #83                 // String ?
     131: invokevirtual #40                 // Method java/lang/StringBuilder.append:(Ljava/lang/String;)Ljava/lang/StringBuilder;
     134: invokevirtual #56                 // Method java/lang/StringBuilder.toString:()Ljava/lang/String;
     137: invokevirtual #84                 // Method java/lang/StringBuilder.insert:(ILjava/lang/String;)Ljava/lang/StringBuilder;
     140: pop
     141: aload_1
     142: invokevirtual #56                 // Method java/lang/StringBuilder.toString:()Ljava/lang/String;
     145: areturn

  private static void parseEnabled(org.apache.dubbo.rpc.cluster.configurator.parser.model.ConfigItem, org.apache.dubbo.rpc.cluster.configurator.parser.model.ConfiguratorConfig, java.lang.StringBuilder);
    Code:
       0: aload_2
       1: ldc           #85                 // String &enabled=
       3: invokevirtual #40                 // Method java/lang/StringBuilder.append:(Ljava/lang/String;)Ljava/lang/StringBuilder;
       6: pop
       7: aload_0
       8: invokevirtual #86                 // Method org/apache/dubbo/rpc/cluster/configurator/parser/model/ConfigItem.getType:()Ljava/lang/String;
      11: ifnull        26
      14: ldc           #88                 // String general
      16: aload_0
      17: invokevirtual #86                 // Method org/apache/dubbo/rpc/cluster/configurator/parser/model/ConfigItem.getType:()Ljava/lang/String;
      20: invokevirtual #14                 // Method java/lang/String.equals:(Ljava/lang/Object;)Z
      23: ifeq          38
      26: aload_2
      27: aload_1
      28: invokevirtual #89                 // Method org/apache/dubbo/rpc/cluster/configurator/parser/model/ConfiguratorConfig.getEnabled:()Ljava/lang/Boolean;
      31: invokevirtual #90                 // Method java/lang/StringBuilder.append:(Ljava/lang/Object;)Ljava/lang/StringBuilder;
      34: pop
      35: goto          47
      38: aload_2
      39: aload_0
      40: invokevirtual #91                 // Method org/apache/dubbo/rpc/cluster/configurator/parser/model/ConfigItem.getEnabled:()Ljava/lang/Boolean;
      43: invokevirtual #90                 // Method java/lang/StringBuilder.append:(Ljava/lang/Object;)Ljava/lang/StringBuilder;
      46: pop
      47: return

  private static java.util.List<java.lang.String> parseAddresses(org.apache.dubbo.rpc.cluster.configurator.parser.model.ConfigItem);
    Code:
       0: aload_0
       1: invokevirtual #92                 // Method org/apache/dubbo/rpc/cluster/configurator/parser/model/ConfigItem.getAddresses:()Ljava/util/List;
       4: astore_1
       5: aload_1
       6: ifnonnull     17
       9: new           #8                  // class java/util/ArrayList
      12: dup
      13: invokespecial #9                  // Method java/util/ArrayList."<init>":()V
      16: astore_1
      17: aload_1
      18: invokeinterface #43,  1           // InterfaceMethod java/util/List.isEmpty:()Z
      23: ifeq          35
      26: aload_1
      27: ldc           #93                 // String 0.0.0.0
      29: invokeinterface #45,  2           // InterfaceMethod java/util/List.add:(Ljava/lang/Object;)Z
      34: pop
      35: aload_1
      36: areturn

  private static org.apache.dubbo.common.URL appendMatchCondition(org.apache.dubbo.common.URL, org.apache.dubbo.rpc.cluster.configurator.parser.model.ConfigItem);
    Code:
       0: aload_1
       1: invokevirtual #94                 // Method org/apache/dubbo/rpc/cluster/configurator/parser/model/ConfigItem.getMatch:()Lorg/apache/dubbo/rpc/cluster/configurator/parser/model/ConditionMatch;
       4: ifnull        18
       7: aload_0
       8: ldc           #95                 // String MATCH_CONDITION
      10: aload_1
      11: invokevirtual #94                 // Method org/apache/dubbo/rpc/cluster/configurator/parser/model/ConfigItem.getMatch:()Lorg/apache/dubbo/rpc/cluster/configurator/parser/model/ConditionMatch;
      14: invokevirtual #96                 // Method org/apache/dubbo/common/URL.putAttribute:(Ljava/lang/String;Ljava/lang/Object;)Lorg/apache/dubbo/common/URL;
      17: astore_0
      18: aload_0
      19: areturn

  private static void lambda$toParameterString$5(java.lang.StringBuilder, java.lang.String, java.lang.String);
    Code:
       0: aload_0
       1: bipush        38
       3: invokevirtual #41                 // Method java/lang/StringBuilder.append:(C)Ljava/lang/StringBuilder;
       6: pop
       7: aload_0
       8: aload_1
       9: invokevirtual #40                 // Method java/lang/StringBuilder.append:(Ljava/lang/String;)Ljava/lang/StringBuilder;
      12: pop
      13: aload_0
      14: bipush        61
      16: invokevirtual #41                 // Method java/lang/StringBuilder.append:(C)Ljava/lang/StringBuilder;
      19: pop
      20: aload_0
      21: aload_2
      22: invokevirtual #40                 // Method java/lang/StringBuilder.append:(Ljava/lang/String;)Ljava/lang/StringBuilder;
      25: pop
      26: return

  private static void lambda$serviceItemToUrls$4(org.apache.dubbo.rpc.cluster.configurator.parser.model.ConfiguratorConfig, org.apache.dubbo.rpc.cluster.configurator.parser.model.ConfigItem, java.util.List, java.lang.String);
    Code:
       0: new           #37                 // class java/lang/StringBuilder
       3: dup
       4: invokespecial #38                 // Method java/lang/StringBuilder."<init>":()V
       7: astore        4
       9: aload         4
      11: ldc           #39                 // String override://
      13: invokevirtual #40                 // Method java/lang/StringBuilder.append:(Ljava/lang/String;)Ljava/lang/StringBuilder;
      16: aload_3
      17: invokevirtual #40                 // Method java/lang/StringBuilder.append:(Ljava/lang/String;)Ljava/lang/StringBuilder;
      20: bipush        47
      22: invokevirtual #41                 // Method java/lang/StringBuilder.append:(C)Ljava/lang/StringBuilder;
      25: pop
      26: aload         4
      28: aload_0
      29: invokevirtual #50                 // Method org/apache/dubbo/rpc/cluster/configurator/parser/model/ConfiguratorConfig.getKey:()Ljava/lang/String;
      32: invokestatic  #47                 // Method appendService:(Ljava/lang/String;)Ljava/lang/String;
      35: invokevirtual #40                 // Method java/lang/StringBuilder.append:(Ljava/lang/String;)Ljava/lang/StringBuilder;
      38: pop
      39: aload         4
      41: aload_1
      42: invokestatic  #48                 // Method toParameterString:(Lorg/apache/dubbo/rpc/cluster/configurator/parser/model/ConfigItem;)Ljava/lang/String;
      45: invokevirtual #40                 // Method java/lang/StringBuilder.append:(Ljava/lang/String;)Ljava/lang/StringBuilder;
      48: pop
      49: aload_1
      50: aload_0
      51: aload         4
      53: invokestatic  #51                 // Method parseEnabled:(Lorg/apache/dubbo/rpc/cluster/configurator/parser/model/ConfigItem;Lorg/apache/dubbo/rpc/cluster/configurator/parser/model/ConfiguratorConfig;Ljava/lang/StringBuilder;)V
      56: aload         4
      58: ldc           #54                 // String &configVersion=
      60: invokevirtual #40                 // Method java/lang/StringBuilder.append:(Ljava/lang/String;)Ljava/lang/StringBuilder;
      63: aload_0
      64: invokevirtual #55                 // Method org/apache/dubbo/rpc/cluster/configurator/parser/model/ConfiguratorConfig.getConfigVersion:()Ljava/lang/String;
      67: invokevirtual #40                 // Method java/lang/StringBuilder.append:(Ljava/lang/String;)Ljava/lang/StringBuilder;
      70: pop
      71: aload_1
      72: invokevirtual #97                 // Method org/apache/dubbo/rpc/cluster/configurator/parser/model/ConfigItem.getApplications:()Ljava/util/List;
      75: astore        5
      77: aload         5
      79: invokestatic  #7                  // Method org/apache/dubbo/common/utils/CollectionUtils.isNotEmpty:(Ljava/util/Collection;)Z
      82: ifeq          104
      85: aload         5
      87: aload         4
      89: aload_2
      90: aload_1
      91: invokedynamic #98,  0             // InvokeDynamic #5:accept:(Ljava/lang/StringBuilder;Ljava/util/List;Lorg/apache/dubbo/rpc/cluster/configurator/parser/model/ConfigItem;)Ljava/util/function/Consumer;
      96: invokeinterface #16,  2           // InterfaceMethod java/util/List.forEach:(Ljava/util/function/Consumer;)V
     101: goto          123
     104: aload_2
     105: aload         4
     107: invokevirtual #56                 // Method java/lang/StringBuilder.toString:()Ljava/lang/String;
     110: invokestatic  #57                 // Method org/apache/dubbo/common/URL.valueOf:(Ljava/lang/String;)Lorg/apache/dubbo/common/URL;
     113: aload_1
     114: invokestatic  #58                 // Method appendMatchCondition:(Lorg/apache/dubbo/common/URL;Lorg/apache/dubbo/rpc/cluster/configurator/parser/model/ConfigItem;)Lorg/apache/dubbo/common/URL;
     117: invokeinterface #45,  2           // InterfaceMethod java/util/List.add:(Ljava/lang/Object;)Z
     122: pop
     123: return

  private static void lambda$null$3(java.lang.StringBuilder, java.util.List, org.apache.dubbo.rpc.cluster.configurator.parser.model.ConfigItem, java.lang.String);
    Code:
       0: new           #37                 // class java/lang/StringBuilder
       3: dup
       4: aload_0
       5: invokespecial #46                 // Method java/lang/StringBuilder."<init>":(Ljava/lang/CharSequence;)V
       8: astore        4
      10: aload_1
      11: aload         4
      13: ldc           #49                 // String &application=
      15: invokevirtual #40                 // Method java/lang/StringBuilder.append:(Ljava/lang/String;)Ljava/lang/StringBuilder;
      18: aload_3
      19: invokevirtual #40                 // Method java/lang/StringBuilder.append:(Ljava/lang/String;)Ljava/lang/StringBuilder;
      22: invokevirtual #56                 // Method java/lang/StringBuilder.toString:()Ljava/lang/String;
      25: invokestatic  #57                 // Method org/apache/dubbo/common/URL.valueOf:(Ljava/lang/String;)Lorg/apache/dubbo/common/URL;
      28: aload_2
      29: invokestatic  #58                 // Method appendMatchCondition:(Lorg/apache/dubbo/common/URL;Lorg/apache/dubbo/rpc/cluster/configurator/parser/model/ConfigItem;)Lorg/apache/dubbo/common/URL;
      32: invokeinterface #45,  2           // InterfaceMethod java/util/List.add:(Ljava/lang/Object;)Z
      37: pop
      38: return

  private static void lambda$parseJsonArray$2(java.util.List, java.lang.String);
    Code:
       0: aload_0
       1: aload_1
       2: invokestatic  #57                 // Method org/apache/dubbo/common/URL.valueOf:(Ljava/lang/String;)Lorg/apache/dubbo/common/URL;
       5: invokeinterface #45,  2           // InterfaceMethod java/util/List.add:(Ljava/lang/Object;)Z
      10: pop
      11: return

  private static void lambda$parseConfigurators$1(java.util.List, org.apache.dubbo.rpc.cluster.configurator.parser.model.ConfiguratorConfig, org.apache.dubbo.rpc.cluster.configurator.parser.model.ConfigItem);
    Code:
       0: aload_0
       1: aload_2
       2: aload_1
       3: invokestatic  #99                 // Method serviceItemToUrls:(Lorg/apache/dubbo/rpc/cluster/configurator/parser/model/ConfigItem;Lorg/apache/dubbo/rpc/cluster/configurator/parser/model/ConfiguratorConfig;)Ljava/util/List;
       6: invokeinterface #100,  2          // InterfaceMethod java/util/List.addAll:(Ljava/util/Collection;)Z
      11: pop
      12: return

  private static void lambda$parseConfigurators$0(java.util.List, org.apache.dubbo.rpc.cluster.configurator.parser.model.ConfiguratorConfig, org.apache.dubbo.rpc.cluster.configurator.parser.model.ConfigItem);
    Code:
       0: aload_0
       1: aload_2
       2: aload_1
       3: invokestatic  #101                // Method appItemToUrls:(Lorg/apache/dubbo/rpc/cluster/configurator/parser/model/ConfigItem;Lorg/apache/dubbo/rpc/cluster/configurator/parser/model/ConfiguratorConfig;)Ljava/util/List;
       6: invokeinterface #100,  2          // InterfaceMethod java/util/List.addAll:(Ljava/util/Collection;)Z
      11: pop
      12: return
}
