Compiled from "StringToOptionalConverter.java"
public class org.apache.dubbo.common.convert.StringToOptionalConverter implements org.apache.dubbo.common.convert.StringConverter<java.util.Optional> {
  public org.apache.dubbo.common.convert.StringToOptionalConverter();
    Code:
       0: aload_0
       1: invokespecial #1                  // Method java/lang/Object."<init>":()V
       4: return

  public java.util.Optional convert(java.lang.String);
    Code:
       0: aload_1
       1: invokestatic  #2                  // Method java/util/Optional.ofNullable:(Ljava/lang/Object;)Ljava/util/Optional;
       4: areturn

  public int getPriority();
    Code:
       0: ldc           #4                  // int 2147483647
       2: ireturn

  public java.lang.Object convert(java.lang.Object);
    Code:
       0: aload_0
       1: aload_1
       2: checkcast     #5                  // class java/lang/String
       5: invokevirtual #6                  // Method convert:(Ljava/lang/String;)Ljava/util/Optional;
       8: areturn
}
