Compiled from "StringToIntegerConverter.java"
public class org.apache.dubbo.common.convert.StringToIntegerConverter implements org.apache.dubbo.common.convert.StringConverter<java.lang.Integer> {
  public org.apache.dubbo.common.convert.StringToIntegerConverter();
    Code:
       0: aload_0
       1: invokespecial #1                  // Method java/lang/Object."<init>":()V
       4: return

  public java.lang.Integer convert(java.lang.String);
    Code:
       0: aload_1
       1: invokestatic  #2                  // Method org/apache/dubbo/common/utils/StringUtils.isNotEmpty:(Ljava/lang/String;)Z
       4: ifeq          14
       7: aload_1
       8: invokestatic  #3                  // Method java/lang/Integer.valueOf:(Ljava/lang/String;)Ljava/lang/Integer;
      11: goto          15
      14: aconst_null
      15: areturn

  public int getPriority();
    Code:
       0: iconst_0
       1: ireturn

  public java.lang.Object convert(java.lang.Object);
    Code:
       0: aload_0
       1: aload_1
       2: checkcast     #5                  // class java/lang/String
       5: invokevirtual #6                  // Method convert:(Ljava/lang/String;)Ljava/lang/Integer;
       8: areturn
}
