Compiled from "StringToCharacterConverter.java"
public class org.apache.dubbo.common.convert.StringToCharacterConverter implements org.apache.dubbo.common.convert.StringConverter<java.lang.Character> {
  public org.apache.dubbo.common.convert.StringToCharacterConverter();
    Code:
       0: aload_0
       1: invokespecial #1                  // Method java/lang/Object."<init>":()V
       4: return

  public java.lang.Character convert(java.lang.String);
    Code:
       0: aload_1
       1: invokestatic  #2                  // Method org/apache/dubbo/common/utils/StringUtils.length:(Ljava/lang/CharSequence;)I
       4: istore_2
       5: iload_2
       6: ifne          11
       9: aconst_null
      10: areturn
      11: iload_2
      12: iconst_1
      13: if_icmple     26
      16: new           #3                  // class java/lang/IllegalArgumentException
      19: dup
      20: ldc           #4                  // String The source String is more than one character!
      22: invokespecial #5                  // Method java/lang/IllegalArgumentException."<init>":(Ljava/lang/String;)V
      25: athrow
      26: aload_1
      27: iconst_0
      28: invokevirtual #6                  // Method java/lang/String.charAt:(I)C
      31: invokestatic  #7                  // Method java/lang/Character.valueOf:(C)Ljava/lang/Character;
      34: areturn

  public int getPriority();
    Code:
       0: bipush        8
       2: ireturn

  public java.lang.Object convert(java.lang.Object);
    Code:
       0: aload_0
       1: aload_1
       2: checkcast     #9                  // class java/lang/String
       5: invokevirtual #10                 // Method convert:(Ljava/lang/String;)Ljava/lang/Character;
       8: areturn
}
