Compiled from "StringToStringConverter.java"
public class org.apache.dubbo.common.convert.StringToStringConverter implements org.apache.dubbo.common.convert.StringConverter<java.lang.String> {
  public org.apache.dubbo.common.convert.StringToStringConverter();
    Code:
       0: aload_0
       1: invokespecial #1                  // Method java/lang/Object."<init>":()V
       4: return

  public java.lang.String convert(java.lang.String);
    Code:
       0: aload_1
       1: areturn

  public java.lang.Object convert(java.lang.Object);
    Code:
       0: aload_0
       1: aload_1
       2: checkcast     #2                  // class java/lang/String
       5: invokevirtual #3                  // Method convert:(Ljava/lang/String;)Ljava/lang/String;
       8: areturn
}
