Compiled from "BaseRestClient.java"
public abstract class org.apache.dubbo.remoting.http.BaseRestClient<CLIENT> implements org.apache.dubbo.remoting.http.RestClient {
  protected CLIENT client;

  protected org.apache.dubbo.remoting.http.config.HttpClientConfig clientConfig;

  public org.apache.dubbo.remoting.http.BaseRestClient(org.apache.dubbo.remoting.http.config.HttpClientConfig);
    Code:
       0: aload_0
       1: invokespecial #1                  // Method java/lang/Object."<init>":()V
       4: aload_0
       5: aload_1
       6: putfield      #2                  // Field clientConfig:Lorg/apache/dubbo/remoting/http/config/HttpClientConfig;
       9: aload_0
      10: aload_0
      11: aload_1
      12: invokevirtual #3                  // Method createHttpClient:(Lorg/apache/dubbo/remoting/http/config/HttpClientConfig;)Ljava/lang/Object;
      15: putfield      #4                  // Field client:Ljava/lang/Object;
      18: return

  protected abstract CLIENT createHttpClient(org.apache.dubbo.remoting.http.config.HttpClientConfig);

  public org.apache.dubbo.remoting.http.config.HttpClientConfig getClientConfig();
    Code:
       0: aload_0
       1: getfield      #2                  // Field clientConfig:Lorg/apache/dubbo/remoting/http/config/HttpClientConfig;
       4: areturn

  public CLIENT getClient();
    Code:
       0: aload_0
       1: getfield      #4                  // Field client:Ljava/lang/Object;
       4: areturn
}
