Compiled from "RestResult.java"
public interface org.apache.dubbo.remoting.http.RestResult {
  public abstract java.lang.String getContentType();

  public abstract byte[] getBody() throws java.io.IOException;

  public abstract java.util.Map<java.lang.String, java.util.List<java.lang.String>> headers();

  public abstract byte[] getErrorResponse() throws java.io.IOException;

  public abstract int getResponseCode() throws java.io.IOException;

  public abstract java.lang.String getMessage() throws java.io.IOException;

  public default java.lang.String appendErrorMessage(java.lang.String, java.lang.String);
    Code:
       0: new           #1                  // class java/lang/StringBuilder
       3: dup
       4: invokespecial #2                  // Method java/lang/StringBuilder."<init>":()V
       7: aload_1
       8: invokevirtual #3                  // Method java/lang/StringBuilder.append:(Ljava/lang/String;)Ljava/lang/StringBuilder;
      11: ldc           #4                  // String \n error info is:
      13: invokevirtual #3                  // Method java/lang/StringBuilder.append:(Ljava/lang/String;)Ljava/lang/StringBuilder;
      16: aload_2
      17: invokevirtual #3                  // Method java/lang/StringBuilder.append:(Ljava/lang/String;)Ljava/lang/StringBuilder;
      20: invokevirtual #5                  // Method java/lang/StringBuilder.toString:()Ljava/lang/String;
      23: areturn
}
