Compiled from "DatabaseDriver.java"
public class org.springframework.boot.jdbc.DatabaseDriver extends java.lang.Enum<org.springframework.boot.jdbc.DatabaseDriver> {
  public static final org.springframework.boot.jdbc.DatabaseDriver UNKNOWN;

  public static final org.springframework.boot.jdbc.DatabaseDriver DERBY;

  public static final org.springframework.boot.jdbc.DatabaseDriver H2;

  public static final org.springframework.boot.jdbc.DatabaseDriver HSQLDB;

  public static final org.springframework.boot.jdbc.DatabaseDriver SQLITE;

  public static final org.springframework.boot.jdbc.DatabaseDriver MYSQL;

  public static final org.springframework.boot.jdbc.DatabaseDriver MARIADB;

  public static final org.springframework.boot.jdbc.DatabaseDriver ORACLE;

  public static final org.springframework.boot.jdbc.DatabaseDriver POSTGRESQL;

  public static final org.springframework.boot.jdbc.DatabaseDriver REDSHIFT;

  public static final org.springframework.boot.jdbc.DatabaseDriver HANA;

  public static final org.springframework.boot.jdbc.DatabaseDriver JTDS;

  public static final org.springframework.boot.jdbc.DatabaseDriver SQLSERVER;

  public static final org.springframework.boot.jdbc.DatabaseDriver FIREBIRD;

  public static final org.springframework.boot.jdbc.DatabaseDriver DB2;

  public static final org.springframework.boot.jdbc.DatabaseDriver DB2_AS400;

  public static final org.springframework.boot.jdbc.DatabaseDriver TERADATA;

  public static final org.springframework.boot.jdbc.DatabaseDriver INFORMIX;

  public static final org.springframework.boot.jdbc.DatabaseDriver PHOENIX;

  public static final org.springframework.boot.jdbc.DatabaseDriver TESTCONTAINERS;

  private final java.lang.String productName;

  private final java.lang.String driverClassName;

  private final java.lang.String xaDataSourceClassName;

  private final java.lang.String validationQuery;

  private static final org.springframework.boot.jdbc.DatabaseDriver[] $VALUES;

  public static org.springframework.boot.jdbc.DatabaseDriver[] values();
    Code:
       0: getstatic     #64                 // Field $VALUES:[Lorg/springframework/boot/jdbc/DatabaseDriver;
       3: invokevirtual #68                 // Method "[Lorg/springframework/boot/jdbc/DatabaseDriver;".clone:()Ljava/lang/Object;
       6: checkcast     #69                 // class "[Lorg/springframework/boot/jdbc/DatabaseDriver;"
       9: areturn

  public static org.springframework.boot.jdbc.DatabaseDriver valueOf(java.lang.String);
    Code:
       0: ldc           #1                  // class org/springframework/boot/jdbc/DatabaseDriver
       2: aload_0
       3: invokestatic  #73                 // Method java/lang/Enum.valueOf:(Ljava/lang/Class;Ljava/lang/String;)Ljava/lang/Enum;
       6: checkcast     #1                  // class org/springframework/boot/jdbc/DatabaseDriver
       9: areturn

  private org.springframework.boot.jdbc.DatabaseDriver(java.lang.String, java.lang.String);
    Code:
       0: aload_0
       1: aload_1
       2: iload_2
       3: aload_3
       4: aload         4
       6: aconst_null
       7: invokespecial #79                 // Method "<init>":(Ljava/lang/String;ILjava/lang/String;Ljava/lang/String;Ljava/lang/String;)V
      10: return

  private org.springframework.boot.jdbc.DatabaseDriver(java.lang.String, java.lang.String, java.lang.String);
    Code:
       0: aload_0
       1: aload_1
       2: iload_2
       3: aload_3
       4: aload         4
       6: aload         5
       8: aconst_null
       9: invokespecial #83                 // Method "<init>":(Ljava/lang/String;ILjava/lang/String;Ljava/lang/String;Ljava/lang/String;Ljava/lang/String;)V
      12: return

  private org.springframework.boot.jdbc.DatabaseDriver(java.lang.String, java.lang.String, java.lang.String, java.lang.String);
    Code:
       0: aload_0
       1: aload_1
       2: iload_2
       3: invokespecial #86                 // Method java/lang/Enum."<init>":(Ljava/lang/String;I)V
       6: aload_0
       7: aload_3
       8: putfield      #89                 // Field productName:Ljava/lang/String;
      11: aload_0
      12: aload         4
      14: putfield      #93                 // Field driverClassName:Ljava/lang/String;
      17: aload_0
      18: aload         5
      20: putfield      #96                 // Field xaDataSourceClassName:Ljava/lang/String;
      23: aload_0
      24: aload         6
      26: putfield      #99                 // Field validationQuery:Ljava/lang/String;
      29: return

  public java.lang.String getId();
    Code:
       0: aload_0
       1: invokevirtual #102                // Method name:()Ljava/lang/String;
       4: getstatic     #106                // Field java/util/Locale.ENGLISH:Ljava/util/Locale;
       7: invokevirtual #112                // Method java/lang/String.toLowerCase:(Ljava/util/Locale;)Ljava/lang/String;
      10: areturn

  protected java.util.Collection<java.lang.String> getUrlPrefixes();
    Code:
       0: aload_0
       1: invokevirtual #102                // Method name:()Ljava/lang/String;
       4: getstatic     #106                // Field java/util/Locale.ENGLISH:Ljava/util/Locale;
       7: invokevirtual #112                // Method java/lang/String.toLowerCase:(Ljava/util/Locale;)Ljava/lang/String;
      10: invokestatic  #118                // Method java/util/Collections.singleton:(Ljava/lang/Object;)Ljava/util/Set;
      13: areturn

  protected boolean matchProductName(java.lang.String);
    Code:
       0: aload_0
       1: getfield      #89                 // Field productName:Ljava/lang/String;
       4: ifnull        22
       7: aload_0
       8: getfield      #89                 // Field productName:Ljava/lang/String;
      11: aload_1
      12: invokevirtual #124                // Method java/lang/String.equalsIgnoreCase:(Ljava/lang/String;)Z
      15: ifeq          22
      18: iconst_1
      19: goto          23
      22: iconst_0
      23: ireturn

  public java.lang.String getDriverClassName();
    Code:
       0: aload_0
       1: getfield      #93                 // Field driverClassName:Ljava/lang/String;
       4: areturn

  public java.lang.String getXaDataSourceClassName();
    Code:
       0: aload_0
       1: getfield      #96                 // Field xaDataSourceClassName:Ljava/lang/String;
       4: areturn

  public java.lang.String getValidationQuery();
    Code:
       0: aload_0
       1: getfield      #99                 // Field validationQuery:Ljava/lang/String;
       4: areturn

  public static org.springframework.boot.jdbc.DatabaseDriver fromJdbcUrl(java.lang.String);
    Code:
       0: aload_0
       1: invokestatic  #128                // Method org/springframework/util/StringUtils.hasLength:(Ljava/lang/String;)Z
       4: ifeq          128
       7: aload_0
       8: ldc           #133                // String jdbc
      10: invokevirtual #135                // Method java/lang/String.startsWith:(Ljava/lang/String;)Z
      13: ldc           #138                // String URL must start with \'jdbc\'
      15: invokestatic  #140                // Method org/springframework/util/Assert.isTrue:(ZLjava/lang/String;)V
      18: aload_0
      19: ldc           #133                // String jdbc
      21: invokevirtual #146                // Method java/lang/String.length:()I
      24: invokevirtual #150                // Method java/lang/String.substring:(I)Ljava/lang/String;
      27: getstatic     #106                // Field java/util/Locale.ENGLISH:Ljava/util/Locale;
      30: invokevirtual #112                // Method java/lang/String.toLowerCase:(Ljava/util/Locale;)Ljava/lang/String;
      33: astore_1
      34: invokestatic  #154                // Method values:()[Lorg/springframework/boot/jdbc/DatabaseDriver;
      37: astore_2
      38: aload_2
      39: arraylength
      40: istore_3
      41: iconst_0
      42: istore        4
      44: iload         4
      46: iload_3
      47: if_icmpge     128
      50: aload_2
      51: iload         4
      53: aaload
      54: astore        5
      56: aload         5
      58: invokevirtual #158                // Method getUrlPrefixes:()Ljava/util/Collection;
      61: invokeinterface #162,  1          // InterfaceMethod java/util/Collection.iterator:()Ljava/util/Iterator;
      66: astore        6
      68: aload         6
      70: invokeinterface #168,  1          // InterfaceMethod java/util/Iterator.hasNext:()Z
      75: ifeq          122
      78: aload         6
      80: invokeinterface #174,  1          // InterfaceMethod java/util/Iterator.next:()Ljava/lang/Object;
      85: checkcast     #113                // class java/lang/String
      88: astore        7
      90: aload         7
      92: invokedynamic #177,  0            // InvokeDynamic #0:makeConcatWithConstants:(Ljava/lang/String;)Ljava/lang/String;
      97: astore        8
      99: aload         5
     101: getstatic     #3                  // Field UNKNOWN:Lorg/springframework/boot/jdbc/DatabaseDriver;
     104: if_acmpeq     119
     107: aload_1
     108: aload         8
     110: invokevirtual #135                // Method java/lang/String.startsWith:(Ljava/lang/String;)Z
     113: ifeq          119
     116: aload         5
     118: areturn
     119: goto          68
     122: iinc          4, 1
     125: goto          44
     128: getstatic     #3                  // Field UNKNOWN:Lorg/springframework/boot/jdbc/DatabaseDriver;
     131: areturn

  public static org.springframework.boot.jdbc.DatabaseDriver fromProductName(java.lang.String);
    Code:
       0: aload_0
       1: invokestatic  #128                // Method org/springframework/util/StringUtils.hasLength:(Ljava/lang/String;)Z
       4: ifeq          44
       7: invokestatic  #154                // Method values:()[Lorg/springframework/boot/jdbc/DatabaseDriver;
      10: astore_1
      11: aload_1
      12: arraylength
      13: istore_2
      14: iconst_0
      15: istore_3
      16: iload_3
      17: iload_2
      18: if_icmpge     44
      21: aload_1
      22: iload_3
      23: aaload
      24: astore        4
      26: aload         4
      28: aload_0
      29: invokevirtual #181                // Method matchProductName:(Ljava/lang/String;)Z
      32: ifeq          38
      35: aload         4
      37: areturn
      38: iinc          3, 1
      41: goto          16
      44: getstatic     #3                  // Field UNKNOWN:Lorg/springframework/boot/jdbc/DatabaseDriver;
      47: areturn

  public static org.springframework.boot.jdbc.DatabaseDriver fromDataSource(javax.sql.DataSource);
    Code:
       0: aload_0
       1: invokedynamic #184,  0            // InvokeDynamic #1:processMetaData:()Lorg/springframework/jdbc/support/DatabaseMetaDataCallback;
       6: invokestatic  #188                // Method org/springframework/jdbc/support/JdbcUtils.extractDatabaseMetaData:(Ljavax/sql/DataSource;Lorg/springframework/jdbc/support/DatabaseMetaDataCallback;)Ljava/lang/Object;
       9: checkcast     #113                // class java/lang/String
      12: invokestatic  #194                // Method org/springframework/jdbc/support/JdbcUtils.commonDatabaseName:(Ljava/lang/String;)Ljava/lang/String;
      15: astore_1
      16: aload_1
      17: invokestatic  #197                // Method fromProductName:(Ljava/lang/String;)Lorg/springframework/boot/jdbc/DatabaseDriver;
      20: areturn
      21: astore_1
      22: getstatic     #3                  // Field UNKNOWN:Lorg/springframework/boot/jdbc/DatabaseDriver;
      25: areturn
    Exception table:
       from    to  target type
           0    20    21   Class java/lang/Exception

  private static org.springframework.boot.jdbc.DatabaseDriver[] $values();
    Code:
       0: bipush        20
       2: anewarray     #1                  // class org/springframework/boot/jdbc/DatabaseDriver
       5: dup
       6: iconst_0
       7: getstatic     #3                  // Field UNKNOWN:Lorg/springframework/boot/jdbc/DatabaseDriver;
      10: aastore
      11: dup
      12: iconst_1
      13: getstatic     #7                  // Field DERBY:Lorg/springframework/boot/jdbc/DatabaseDriver;
      16: aastore
      17: dup
      18: iconst_2
      19: getstatic     #10                 // Field H2:Lorg/springframework/boot/jdbc/DatabaseDriver;
      22: aastore
      23: dup
      24: iconst_3
      25: getstatic     #13                 // Field HSQLDB:Lorg/springframework/boot/jdbc/DatabaseDriver;
      28: aastore
      29: dup
      30: iconst_4
      31: getstatic     #16                 // Field SQLITE:Lorg/springframework/boot/jdbc/DatabaseDriver;
      34: aastore
      35: dup
      36: iconst_5
      37: getstatic     #19                 // Field MYSQL:Lorg/springframework/boot/jdbc/DatabaseDriver;
      40: aastore
      41: dup
      42: bipush        6
      44: getstatic     #22                 // Field MARIADB:Lorg/springframework/boot/jdbc/DatabaseDriver;
      47: aastore
      48: dup
      49: bipush        7
      51: getstatic     #25                 // Field ORACLE:Lorg/springframework/boot/jdbc/DatabaseDriver;
      54: aastore
      55: dup
      56: bipush        8
      58: getstatic     #28                 // Field POSTGRESQL:Lorg/springframework/boot/jdbc/DatabaseDriver;
      61: aastore
      62: dup
      63: bipush        9
      65: getstatic     #31                 // Field REDSHIFT:Lorg/springframework/boot/jdbc/DatabaseDriver;
      68: aastore
      69: dup
      70: bipush        10
      72: getstatic     #34                 // Field HANA:Lorg/springframework/boot/jdbc/DatabaseDriver;
      75: aastore
      76: dup
      77: bipush        11
      79: getstatic     #37                 // Field JTDS:Lorg/springframework/boot/jdbc/DatabaseDriver;
      82: aastore
      83: dup
      84: bipush        12
      86: getstatic     #40                 // Field SQLSERVER:Lorg/springframework/boot/jdbc/DatabaseDriver;
      89: aastore
      90: dup
      91: bipush        13
      93: getstatic     #43                 // Field FIREBIRD:Lorg/springframework/boot/jdbc/DatabaseDriver;
      96: aastore
      97: dup
      98: bipush        14
     100: getstatic     #46                 // Field DB2:Lorg/springframework/boot/jdbc/DatabaseDriver;
     103: aastore
     104: dup
     105: bipush        15
     107: getstatic     #49                 // Field DB2_AS400:Lorg/springframework/boot/jdbc/DatabaseDriver;
     110: aastore
     111: dup
     112: bipush        16
     114: getstatic     #52                 // Field TERADATA:Lorg/springframework/boot/jdbc/DatabaseDriver;
     117: aastore
     118: dup
     119: bipush        17
     121: getstatic     #55                 // Field INFORMIX:Lorg/springframework/boot/jdbc/DatabaseDriver;
     124: aastore
     125: dup
     126: bipush        18
     128: getstatic     #58                 // Field PHOENIX:Lorg/springframework/boot/jdbc/DatabaseDriver;
     131: aastore
     132: dup
     133: bipush        19
     135: getstatic     #61                 // Field TESTCONTAINERS:Lorg/springframework/boot/jdbc/DatabaseDriver;
     138: aastore
     139: areturn

  static {};
    Code:
       0: new           #1                  // class org/springframework/boot/jdbc/DatabaseDriver
       3: dup
       4: ldc           #203                // String UNKNOWN
       6: iconst_0
       7: aconst_null
       8: aconst_null
       9: invokespecial #204                // Method "<init>":(Ljava/lang/String;ILjava/lang/String;Ljava/lang/String;)V
      12: putstatic     #3                  // Field UNKNOWN:Lorg/springframework/boot/jdbc/DatabaseDriver;
      15: new           #1                  // class org/springframework/boot/jdbc/DatabaseDriver
      18: dup
      19: ldc           #207                // String DERBY
      21: iconst_1
      22: ldc           #208                // String Apache Derby
      24: ldc           #210                // String org.apache.derby.jdbc.EmbeddedDriver
      26: ldc           #212                // String org.apache.derby.jdbc.EmbeddedXADataSource
      28: ldc           #214                // String SELECT 1 FROM SYSIBM.SYSDUMMY1
      30: invokespecial #83                 // Method "<init>":(Ljava/lang/String;ILjava/lang/String;Ljava/lang/String;Ljava/lang/String;Ljava/lang/String;)V
      33: putstatic     #7                  // Field DERBY:Lorg/springframework/boot/jdbc/DatabaseDriver;
      36: new           #1                  // class org/springframework/boot/jdbc/DatabaseDriver
      39: dup
      40: ldc           #216                // String H2
      42: iconst_2
      43: ldc           #216                // String H2
      45: ldc           #217                // String org.h2.Driver
      47: ldc           #219                // String org.h2.jdbcx.JdbcDataSource
      49: ldc           #221                // String SELECT 1
      51: invokespecial #83                 // Method "<init>":(Ljava/lang/String;ILjava/lang/String;Ljava/lang/String;Ljava/lang/String;Ljava/lang/String;)V
      54: putstatic     #10                 // Field H2:Lorg/springframework/boot/jdbc/DatabaseDriver;
      57: new           #1                  // class org/springframework/boot/jdbc/DatabaseDriver
      60: dup
      61: ldc           #223                // String HSQLDB
      63: iconst_3
      64: ldc           #224                // String HSQL Database Engine
      66: ldc           #226                // String org.hsqldb.jdbc.JDBCDriver
      68: ldc           #228                // String org.hsqldb.jdbc.pool.JDBCXADataSource
      70: ldc           #230                // String SELECT COUNT(*) FROM INFORMATION_SCHEMA.SYSTEM_USERS
      72: invokespecial #83                 // Method "<init>":(Ljava/lang/String;ILjava/lang/String;Ljava/lang/String;Ljava/lang/String;Ljava/lang/String;)V
      75: putstatic     #13                 // Field HSQLDB:Lorg/springframework/boot/jdbc/DatabaseDriver;
      78: new           #1                  // class org/springframework/boot/jdbc/DatabaseDriver
      81: dup
      82: ldc           #232                // String SQLITE
      84: iconst_4
      85: ldc           #233                // String SQLite
      87: ldc           #235                // String org.sqlite.JDBC
      89: invokespecial #204                // Method "<init>":(Ljava/lang/String;ILjava/lang/String;Ljava/lang/String;)V
      92: putstatic     #16                 // Field SQLITE:Lorg/springframework/boot/jdbc/DatabaseDriver;
      95: new           #1                  // class org/springframework/boot/jdbc/DatabaseDriver
      98: dup
      99: ldc           #237                // String MYSQL
     101: iconst_5
     102: ldc           #238                // String MySQL
     104: ldc           #240                // String com.mysql.cj.jdbc.Driver
     106: ldc           #242                // String com.mysql.cj.jdbc.MysqlXADataSource
     108: ldc           #244                // String /* ping */ SELECT 1
     110: invokespecial #83                 // Method "<init>":(Ljava/lang/String;ILjava/lang/String;Ljava/lang/String;Ljava/lang/String;Ljava/lang/String;)V
     113: putstatic     #19                 // Field MYSQL:Lorg/springframework/boot/jdbc/DatabaseDriver;
     116: new           #1                  // class org/springframework/boot/jdbc/DatabaseDriver
     119: dup
     120: ldc           #246                // String MARIADB
     122: bipush        6
     124: ldc           #247                // String MariaDB
     126: ldc           #249                // String org.mariadb.jdbc.Driver
     128: ldc           #251                // String org.mariadb.jdbc.MariaDbDataSource
     130: ldc           #221                // String SELECT 1
     132: invokespecial #83                 // Method "<init>":(Ljava/lang/String;ILjava/lang/String;Ljava/lang/String;Ljava/lang/String;Ljava/lang/String;)V
     135: putstatic     #22                 // Field MARIADB:Lorg/springframework/boot/jdbc/DatabaseDriver;
     138: new           #1                  // class org/springframework/boot/jdbc/DatabaseDriver
     141: dup
     142: ldc           #253                // String ORACLE
     144: bipush        7
     146: ldc           #254                // String Oracle
     148: ldc_w         #256                // String oracle.jdbc.OracleDriver
     151: ldc_w         #258                // String oracle.jdbc.xa.client.OracleXADataSource
     154: ldc_w         #260                // String SELECT \'Hello\' from DUAL
     157: invokespecial #83                 // Method "<init>":(Ljava/lang/String;ILjava/lang/String;Ljava/lang/String;Ljava/lang/String;Ljava/lang/String;)V
     160: putstatic     #25                 // Field ORACLE:Lorg/springframework/boot/jdbc/DatabaseDriver;
     163: new           #1                  // class org/springframework/boot/jdbc/DatabaseDriver
     166: dup
     167: ldc_w         #262                // String POSTGRESQL
     170: bipush        8
     172: ldc_w         #263                // String PostgreSQL
     175: ldc_w         #265                // String org.postgresql.Driver
     178: ldc_w         #267                // String org.postgresql.xa.PGXADataSource
     181: ldc           #221                // String SELECT 1
     183: invokespecial #83                 // Method "<init>":(Ljava/lang/String;ILjava/lang/String;Ljava/lang/String;Ljava/lang/String;Ljava/lang/String;)V
     186: putstatic     #28                 // Field POSTGRESQL:Lorg/springframework/boot/jdbc/DatabaseDriver;
     189: new           #1                  // class org/springframework/boot/jdbc/DatabaseDriver
     192: dup
     193: ldc_w         #269                // String REDSHIFT
     196: bipush        9
     198: ldc_w         #270                // String Redshift
     201: ldc_w         #272                // String com.amazon.redshift.jdbc.Driver
     204: aconst_null
     205: ldc           #221                // String SELECT 1
     207: invokespecial #83                 // Method "<init>":(Ljava/lang/String;ILjava/lang/String;Ljava/lang/String;Ljava/lang/String;Ljava/lang/String;)V
     210: putstatic     #31                 // Field REDSHIFT:Lorg/springframework/boot/jdbc/DatabaseDriver;
     213: new           #274                // class org/springframework/boot/jdbc/DatabaseDriver$1
     216: dup
     217: ldc_w         #276                // String HANA
     220: bipush        10
     222: ldc_w         #277                // String HDB
     225: ldc_w         #279                // String com.sap.db.jdbc.Driver
     228: ldc_w         #281                // String com.sap.db.jdbcext.XADataSourceSAP
     231: ldc_w         #283                // String SELECT 1 FROM SYS.DUMMY
     234: invokespecial #285                // Method org/springframework/boot/jdbc/DatabaseDriver$1."<init>":(Ljava/lang/String;ILjava/lang/String;Ljava/lang/String;Ljava/lang/String;Ljava/lang/String;)V
     237: putstatic     #34                 // Field HANA:Lorg/springframework/boot/jdbc/DatabaseDriver;
     240: new           #1                  // class org/springframework/boot/jdbc/DatabaseDriver
     243: dup
     244: ldc_w         #286                // String JTDS
     247: bipush        11
     249: aconst_null
     250: ldc_w         #287                // String net.sourceforge.jtds.jdbc.Driver
     253: invokespecial #204                // Method "<init>":(Ljava/lang/String;ILjava/lang/String;Ljava/lang/String;)V
     256: putstatic     #37                 // Field JTDS:Lorg/springframework/boot/jdbc/DatabaseDriver;
     259: new           #289                // class org/springframework/boot/jdbc/DatabaseDriver$2
     262: dup
     263: ldc_w         #291                // String SQLSERVER
     266: bipush        12
     268: ldc_w         #292                // String Microsoft SQL Server
     271: ldc_w         #294                // String com.microsoft.sqlserver.jdbc.SQLServerDriver
     274: ldc_w         #296                // String com.microsoft.sqlserver.jdbc.SQLServerXADataSource
     277: ldc           #221                // String SELECT 1
     279: invokespecial #298                // Method org/springframework/boot/jdbc/DatabaseDriver$2."<init>":(Ljava/lang/String;ILjava/lang/String;Ljava/lang/String;Ljava/lang/String;Ljava/lang/String;)V
     282: putstatic     #40                 // Field SQLSERVER:Lorg/springframework/boot/jdbc/DatabaseDriver;
     285: new           #299                // class org/springframework/boot/jdbc/DatabaseDriver$3
     288: dup
     289: ldc_w         #301                // String FIREBIRD
     292: bipush        13
     294: ldc_w         #302                // String Firebird
     297: ldc_w         #304                // String org.firebirdsql.jdbc.FBDriver
     300: ldc_w         #306                // String org.firebirdsql.ds.FBXADataSource
     303: ldc_w         #308                // String SELECT 1 FROM RDB$DATABASE
     306: invokespecial #310                // Method org/springframework/boot/jdbc/DatabaseDriver$3."<init>":(Ljava/lang/String;ILjava/lang/String;Ljava/lang/String;Ljava/lang/String;Ljava/lang/String;)V
     309: putstatic     #43                 // Field FIREBIRD:Lorg/springframework/boot/jdbc/DatabaseDriver;
     312: new           #311                // class org/springframework/boot/jdbc/DatabaseDriver$4
     315: dup
     316: ldc_w         #313                // String DB2
     319: bipush        14
     321: ldc_w         #313                // String DB2
     324: ldc_w         #314                // String com.ibm.db2.jcc.DB2Driver
     327: ldc_w         #316                // String com.ibm.db2.jcc.DB2XADataSource
     330: ldc           #214                // String SELECT 1 FROM SYSIBM.SYSDUMMY1
     332: invokespecial #318                // Method org/springframework/boot/jdbc/DatabaseDriver$4."<init>":(Ljava/lang/String;ILjava/lang/String;Ljava/lang/String;Ljava/lang/String;Ljava/lang/String;)V
     335: putstatic     #46                 // Field DB2:Lorg/springframework/boot/jdbc/DatabaseDriver;
     338: new           #319                // class org/springframework/boot/jdbc/DatabaseDriver$5
     341: dup
     342: ldc_w         #321                // String DB2_AS400
     345: bipush        15
     347: ldc_w         #322                // String DB2 UDB for AS/400
     350: ldc_w         #324                // String com.ibm.as400.access.AS400JDBCDriver
     353: ldc_w         #326                // String com.ibm.as400.access.AS400JDBCXADataSource
     356: ldc           #214                // String SELECT 1 FROM SYSIBM.SYSDUMMY1
     358: invokespecial #328                // Method org/springframework/boot/jdbc/DatabaseDriver$5."<init>":(Ljava/lang/String;ILjava/lang/String;Ljava/lang/String;Ljava/lang/String;Ljava/lang/String;)V
     361: putstatic     #49                 // Field DB2_AS400:Lorg/springframework/boot/jdbc/DatabaseDriver;
     364: new           #1                  // class org/springframework/boot/jdbc/DatabaseDriver
     367: dup
     368: ldc_w         #329                // String TERADATA
     371: bipush        16
     373: ldc_w         #330                // String Teradata
     376: ldc_w         #332                // String com.teradata.jdbc.TeraDriver
     379: invokespecial #204                // Method "<init>":(Ljava/lang/String;ILjava/lang/String;Ljava/lang/String;)V
     382: putstatic     #52                 // Field TERADATA:Lorg/springframework/boot/jdbc/DatabaseDriver;
     385: new           #334                // class org/springframework/boot/jdbc/DatabaseDriver$6
     388: dup
     389: ldc_w         #336                // String INFORMIX
     392: bipush        17
     394: ldc_w         #337                // String Informix Dynamic Server
     397: ldc_w         #339                // String com.informix.jdbc.IfxDriver
     400: aconst_null
     401: ldc_w         #341                // String select count(*) from systables
     404: invokespecial #343                // Method org/springframework/boot/jdbc/DatabaseDriver$6."<init>":(Ljava/lang/String;ILjava/lang/String;Ljava/lang/String;Ljava/lang/String;Ljava/lang/String;)V
     407: putstatic     #55                 // Field INFORMIX:Lorg/springframework/boot/jdbc/DatabaseDriver;
     410: new           #1                  // class org/springframework/boot/jdbc/DatabaseDriver
     413: dup
     414: ldc_w         #344                // String PHOENIX
     417: bipush        18
     419: ldc_w         #345                // String Apache Phoenix
     422: ldc_w         #347                // String org.apache.phoenix.jdbc.PhoenixDriver
     425: aconst_null
     426: ldc_w         #349                // String SELECT 1 FROM SYSTEM.CATALOG LIMIT 1
     429: invokespecial #83                 // Method "<init>":(Ljava/lang/String;ILjava/lang/String;Ljava/lang/String;Ljava/lang/String;Ljava/lang/String;)V
     432: putstatic     #58                 // Field PHOENIX:Lorg/springframework/boot/jdbc/DatabaseDriver;
     435: new           #351                // class org/springframework/boot/jdbc/DatabaseDriver$7
     438: dup
     439: ldc_w         #353                // String TESTCONTAINERS
     442: bipush        19
     444: aconst_null
     445: ldc_w         #354                // String org.testcontainers.jdbc.ContainerDatabaseDriver
     448: invokespecial #356                // Method org/springframework/boot/jdbc/DatabaseDriver$7."<init>":(Ljava/lang/String;ILjava/lang/String;Ljava/lang/String;)V
     451: putstatic     #61                 // Field TESTCONTAINERS:Lorg/springframework/boot/jdbc/DatabaseDriver;
     454: invokestatic  #357                // Method $values:()[Lorg/springframework/boot/jdbc/DatabaseDriver;
     457: putstatic     #64                 // Field $VALUES:[Lorg/springframework/boot/jdbc/DatabaseDriver;
     460: return
}
