Compiled from "DataSourceUnwrapper.java"
public final class org.springframework.boot.jdbc.DataSourceUnwrapper {
  private static final boolean DELEGATING_DATA_SOURCE_PRESENT;

  private org.springframework.boot.jdbc.DataSourceUnwrapper();
    Code:
       0: aload_0
       1: invokespecial #1                  // Method java/lang/Object."<init>":()V
       4: return

  public static <I, T extends I> T unwrap(javax.sql.DataSource, java.lang.Class<I>, java.lang.Class<T>);
    Code:
       0: aload_2
       1: aload_0
       2: invokevirtual #7                  // Method java/lang/Class.isInstance:(Ljava/lang/Object;)Z
       5: ifeq          14
       8: aload_2
       9: aload_0
      10: invokevirtual #13                 // Method java/lang/Class.cast:(Ljava/lang/Object;)Ljava/lang/Object;
      13: areturn
      14: aload_0
      15: aload_1
      16: invokestatic  #17                 // Method safeUnwrap:(Ljava/sql/Wrapper;Ljava/lang/Class;)Ljava/lang/Object;
      19: astore_3
      20: aload_3
      21: ifnull        38
      24: aload_1
      25: aload_2
      26: invokevirtual #23                 // Method java/lang/Class.isAssignableFrom:(Ljava/lang/Class;)Z
      29: ifeq          38
      32: aload_2
      33: aload_3
      34: invokevirtual #13                 // Method java/lang/Class.cast:(Ljava/lang/Object;)Ljava/lang/Object;
      37: areturn
      38: getstatic     #27                 // Field DELEGATING_DATA_SOURCE_PRESENT:Z
      41: ifeq          63
      44: aload_0
      45: invokestatic  #31                 // Method org/springframework/boot/jdbc/DataSourceUnwrapper$DelegatingDataSourceUnwrapper.getTargetDataSource:(Ljavax/sql/DataSource;)Ljavax/sql/DataSource;
      48: astore        4
      50: aload         4
      52: ifnull        63
      55: aload         4
      57: aload_1
      58: aload_2
      59: invokestatic  #37                 // Method unwrap:(Ljavax/sql/DataSource;Ljava/lang/Class;Ljava/lang/Class;)Ljava/lang/Object;
      62: areturn
      63: aload_0
      64: invokestatic  #41                 // Method org/springframework/aop/support/AopUtils.isAopProxy:(Ljava/lang/Object;)Z
      67: ifeq          99
      70: aload_0
      71: invokestatic  #46                 // Method org/springframework/aop/framework/AopProxyUtils.getSingletonTarget:(Ljava/lang/Object;)Ljava/lang/Object;
      74: astore        4
      76: aload         4
      78: instanceof    #51                 // class javax/sql/DataSource
      81: ifeq          99
      84: aload         4
      86: checkcast     #51                 // class javax/sql/DataSource
      89: astore        5
      91: aload         5
      93: aload_1
      94: aload_2
      95: invokestatic  #37                 // Method unwrap:(Ljavax/sql/DataSource;Ljava/lang/Class;Ljava/lang/Class;)Ljava/lang/Object;
      98: areturn
      99: aconst_null
     100: areturn

  public static <T> T unwrap(javax.sql.DataSource, java.lang.Class<T>);
    Code:
       0: aload_0
       1: aload_1
       2: aload_1
       3: invokestatic  #37                 // Method unwrap:(Ljavax/sql/DataSource;Ljava/lang/Class;Ljava/lang/Class;)Ljava/lang/Object;
       6: areturn

  private static <S> S safeUnwrap(java.sql.Wrapper, java.lang.Class<S>);
    Code:
       0: aload_1
       1: invokevirtual #53                 // Method java/lang/Class.isInterface:()Z
       4: ifeq          25
       7: aload_0
       8: aload_1
       9: invokeinterface #57,  2           // InterfaceMethod java/sql/Wrapper.isWrapperFor:(Ljava/lang/Class;)Z
      14: ifeq          25
      17: aload_0
      18: aload_1
      19: invokeinterface #62,  2           // InterfaceMethod java/sql/Wrapper.unwrap:(Ljava/lang/Class;)Ljava/lang/Object;
      24: areturn
      25: goto          29
      28: astore_2
      29: aconst_null
      30: areturn
    Exception table:
       from    to  target type
           0    24    28   Class java/lang/Exception

  static {};
    Code:
       0: ldc           #67                 // String org.springframework.jdbc.datasource.DelegatingDataSource
       2: ldc           #18                 // class org/springframework/boot/jdbc/DataSourceUnwrapper
       4: invokevirtual #69                 // Method java/lang/Class.getClassLoader:()Ljava/lang/ClassLoader;
       7: invokestatic  #73                 // Method org/springframework/util/ClassUtils.isPresent:(Ljava/lang/String;Ljava/lang/ClassLoader;)Z
      10: putstatic     #27                 // Field DELEGATING_DATA_SOURCE_PRESENT:Z
      13: return
}
