Compiled from "DataSourceBuilder.java"
class org.springframework.boot.jdbc.DataSourceBuilder$OraclePoolDataSourceProperties extends org.springframework.boot.jdbc.DataSourceBuilder$MappedDataSourceProperties<oracle.ucp.jdbc.PoolDataSource> {
  public java.lang.Class<? extends oracle.ucp.jdbc.PoolDataSource> getDataSourceInstanceType();
    Code:
       0: ldc           #1                  // class oracle/ucp/jdbc/PoolDataSourceImpl
       2: areturn

  org.springframework.boot.jdbc.DataSourceBuilder$OraclePoolDataSourceProperties();
    Code:
       0: aload_0
       1: invokespecial #3                  // Method org/springframework/boot/jdbc/DataSourceBuilder$MappedDataSourceProperties."<init>":()V
       4: aload_0
       5: getstatic     #9                  // Field org/springframework/boot/jdbc/DataSourceBuilder$DataSourceProperty.URL:Lorg/springframework/boot/jdbc/DataSourceBuilder$DataSourceProperty;
       8: invokedynamic #15,  0             // InvokeDynamic #0:get:()Lorg/springframework/boot/jdbc/DataSourceBuilder$Getter;
      13: invokedynamic #19,  0             // InvokeDynamic #1:set:()Lorg/springframework/boot/jdbc/DataSourceBuilder$Setter;
      18: invokevirtual #23                 // Method add:(Lorg/springframework/boot/jdbc/DataSourceBuilder$DataSourceProperty;Lorg/springframework/boot/jdbc/DataSourceBuilder$Getter;Lorg/springframework/boot/jdbc/DataSourceBuilder$Setter;)V
      21: aload_0
      22: getstatic     #29                 // Field org/springframework/boot/jdbc/DataSourceBuilder$DataSourceProperty.DRIVER_CLASS_NAME:Lorg/springframework/boot/jdbc/DataSourceBuilder$DataSourceProperty;
      25: invokedynamic #32,  0             // InvokeDynamic #2:get:()Lorg/springframework/boot/jdbc/DataSourceBuilder$Getter;
      30: invokedynamic #33,  0             // InvokeDynamic #3:set:()Lorg/springframework/boot/jdbc/DataSourceBuilder$Setter;
      35: invokevirtual #23                 // Method add:(Lorg/springframework/boot/jdbc/DataSourceBuilder$DataSourceProperty;Lorg/springframework/boot/jdbc/DataSourceBuilder$Getter;Lorg/springframework/boot/jdbc/DataSourceBuilder$Setter;)V
      38: aload_0
      39: getstatic     #34                 // Field org/springframework/boot/jdbc/DataSourceBuilder$DataSourceProperty.USERNAME:Lorg/springframework/boot/jdbc/DataSourceBuilder$DataSourceProperty;
      42: invokedynamic #37,  0             // InvokeDynamic #4:get:()Lorg/springframework/boot/jdbc/DataSourceBuilder$Getter;
      47: invokedynamic #38,  0             // InvokeDynamic #5:set:()Lorg/springframework/boot/jdbc/DataSourceBuilder$Setter;
      52: invokevirtual #23                 // Method add:(Lorg/springframework/boot/jdbc/DataSourceBuilder$DataSourceProperty;Lorg/springframework/boot/jdbc/DataSourceBuilder$Getter;Lorg/springframework/boot/jdbc/DataSourceBuilder$Setter;)V
      55: aload_0
      56: getstatic     #39                 // Field org/springframework/boot/jdbc/DataSourceBuilder$DataSourceProperty.PASSWORD:Lorg/springframework/boot/jdbc/DataSourceBuilder$DataSourceProperty;
      59: aconst_null
      60: invokedynamic #42,  0             // InvokeDynamic #6:set:()Lorg/springframework/boot/jdbc/DataSourceBuilder$Setter;
      65: invokevirtual #23                 // Method add:(Lorg/springframework/boot/jdbc/DataSourceBuilder$DataSourceProperty;Lorg/springframework/boot/jdbc/DataSourceBuilder$Getter;Lorg/springframework/boot/jdbc/DataSourceBuilder$Setter;)V
      68: return
}
