Compiled from "DatabaseDriver.java"
final class org.springframework.boot.jdbc.DatabaseDriver$7 extends org.springframework.boot.jdbc.DatabaseDriver {
  private org.springframework.boot.jdbc.DatabaseDriver$7(java.lang.String, int, java.lang.String, java.lang.String);
    Code:
       0: aload_0
       1: aload_1
       2: iload_2
       3: aload_3
       4: aload         4
       6: invokespecial #1                  // Method org/springframework/boot/jdbc/DatabaseDriver."<init>":(Ljava/lang/String;ILjava/lang/String;Ljava/lang/String;)V
       9: return

  protected java.util.Collection<java.lang.String> getUrlPrefixes();
    Code:
       0: ldc           #7                  // String tc
       2: invokestatic  #9                  // Method java/util/Collections.singleton:(Ljava/lang/Object;)Ljava/util/Set;
       5: areturn
}
