Compiled from "DataSourceBuilder.java"
class org.springframework.boot.jdbc.DataSourceBuilder$ComboPooledDataSourceProperties extends org.springframework.boot.jdbc.DataSourceBuilder$MappedDataSourceProperties<com.mchange.v2.c3p0.ComboPooledDataSource> {
  org.springframework.boot.jdbc.DataSourceBuilder$ComboPooledDataSourceProperties();
    Code:
       0: aload_0
       1: invokespecial #1                  // Method org/springframework/boot/jdbc/DataSourceBuilder$MappedDataSourceProperties."<init>":()V
       4: aload_0
       5: getstatic     #7                  // Field org/springframework/boot/jdbc/DataSourceBuilder$DataSourceProperty.URL:Lorg/springframework/boot/jdbc/DataSourceBuilder$DataSourceProperty;
       8: invokedynamic #13,  0             // InvokeDynamic #0:get:()Lorg/springframework/boot/jdbc/DataSourceBuilder$Getter;
      13: invokedynamic #17,  0             // InvokeDynamic #1:set:()Lorg/springframework/boot/jdbc/DataSourceBuilder$Setter;
      18: invokevirtual #21                 // Method add:(Lorg/springframework/boot/jdbc/DataSourceBuilder$DataSourceProperty;Lorg/springframework/boot/jdbc/DataSourceBuilder$Getter;Lorg/springframework/boot/jdbc/DataSourceBuilder$Setter;)V
      21: aload_0
      22: getstatic     #27                 // Field org/springframework/boot/jdbc/DataSourceBuilder$DataSourceProperty.DRIVER_CLASS_NAME:Lorg/springframework/boot/jdbc/DataSourceBuilder$DataSourceProperty;
      25: invokedynamic #30,  0             // InvokeDynamic #2:get:()Lorg/springframework/boot/jdbc/DataSourceBuilder$Getter;
      30: aload_0
      31: invokedynamic #31,  0             // InvokeDynamic #3:set:(Lorg/springframework/boot/jdbc/DataSourceBuilder$ComboPooledDataSourceProperties;)Lorg/springframework/boot/jdbc/DataSourceBuilder$Setter;
      36: invokevirtual #21                 // Method add:(Lorg/springframework/boot/jdbc/DataSourceBuilder$DataSourceProperty;Lorg/springframework/boot/jdbc/DataSourceBuilder$Getter;Lorg/springframework/boot/jdbc/DataSourceBuilder$Setter;)V
      39: aload_0
      40: getstatic     #34                 // Field org/springframework/boot/jdbc/DataSourceBuilder$DataSourceProperty.USERNAME:Lorg/springframework/boot/jdbc/DataSourceBuilder$DataSourceProperty;
      43: invokedynamic #37,  0             // InvokeDynamic #4:get:()Lorg/springframework/boot/jdbc/DataSourceBuilder$Getter;
      48: invokedynamic #38,  0             // InvokeDynamic #5:set:()Lorg/springframework/boot/jdbc/DataSourceBuilder$Setter;
      53: invokevirtual #21                 // Method add:(Lorg/springframework/boot/jdbc/DataSourceBuilder$DataSourceProperty;Lorg/springframework/boot/jdbc/DataSourceBuilder$Getter;Lorg/springframework/boot/jdbc/DataSourceBuilder$Setter;)V
      56: aload_0
      57: getstatic     #39                 // Field org/springframework/boot/jdbc/DataSourceBuilder$DataSourceProperty.PASSWORD:Lorg/springframework/boot/jdbc/DataSourceBuilder$DataSourceProperty;
      60: invokedynamic #42,  0             // InvokeDynamic #6:get:()Lorg/springframework/boot/jdbc/DataSourceBuilder$Getter;
      65: invokedynamic #43,  0             // InvokeDynamic #7:set:()Lorg/springframework/boot/jdbc/DataSourceBuilder$Setter;
      70: invokevirtual #21                 // Method add:(Lorg/springframework/boot/jdbc/DataSourceBuilder$DataSourceProperty;Lorg/springframework/boot/jdbc/DataSourceBuilder$Getter;Lorg/springframework/boot/jdbc/DataSourceBuilder$Setter;)V
      73: return

  private void setDriverClass(com.mchange.v2.c3p0.ComboPooledDataSource, java.lang.String);
    Code:
       0: aload_1
       1: aload_2
       2: invokevirtual #44                 // Method com/mchange/v2/c3p0/ComboPooledDataSource.setDriverClass:(Ljava/lang/String;)V
       5: goto          18
       8: astore_3
       9: new           #52                 // class java/lang/IllegalArgumentException
      12: dup
      13: aload_3
      14: invokespecial #54                 // Method java/lang/IllegalArgumentException."<init>":(Ljava/lang/Throwable;)V
      17: athrow
      18: return
    Exception table:
       from    to  target type
           0     5     8   Class java/beans/PropertyVetoException
}
