Compiled from "DataSourceBuilder.java"
final class org.springframework.boot.jdbc.DataSourceBuilder$DataSourceProperty extends java.lang.Enum<org.springframework.boot.jdbc.DataSourceBuilder$DataSourceProperty> {
  public static final org.springframework.boot.jdbc.DataSourceBuilder$DataSourceProperty URL;

  public static final org.springframework.boot.jdbc.DataSourceBuilder$DataSourceProperty DRIVER_CLASS_NAME;

  public static final org.springframework.boot.jdbc.DataSourceBuilder$DataSourceProperty USERNAME;

  public static final org.springframework.boot.jdbc.DataSourceBuilder$DataSourceProperty PASSWORD;

  private final boolean optional;

  private final java.lang.String[] names;

  private static final org.springframework.boot.jdbc.DataSourceBuilder$DataSourceProperty[] $VALUES;

  public static org.springframework.boot.jdbc.DataSourceBuilder$DataSourceProperty[] values();
    Code:
       0: getstatic     #16                 // Field $VALUES:[Lorg/springframework/boot/jdbc/DataSourceBuilder$DataSourceProperty;
       3: invokevirtual #20                 // Method "[Lorg/springframework/boot/jdbc/DataSourceBuilder$DataSourceProperty;".clone:()Ljava/lang/Object;
       6: checkcast     #21                 // class "[Lorg/springframework/boot/jdbc/DataSourceBuilder$DataSourceProperty;"
       9: areturn

  public static org.springframework.boot.jdbc.DataSourceBuilder$DataSourceProperty valueOf(java.lang.String);
    Code:
       0: ldc           #1                  // class org/springframework/boot/jdbc/DataSourceBuilder$DataSourceProperty
       2: aload_0
       3: invokestatic  #25                 // Method java/lang/Enum.valueOf:(Ljava/lang/Class;Ljava/lang/String;)Ljava/lang/Enum;
       6: checkcast     #1                  // class org/springframework/boot/jdbc/DataSourceBuilder$DataSourceProperty
       9: areturn

  private org.springframework.boot.jdbc.DataSourceBuilder$DataSourceProperty(boolean, java.lang.String...);
    Code:
       0: aload_0
       1: aload_1
       2: iload_2
       3: invokespecial #31                 // Method java/lang/Enum."<init>":(Ljava/lang/String;I)V
       6: aload_0
       7: iload_3
       8: putfield      #35                 // Field optional:Z
      11: aload_0
      12: aload         4
      14: putfield      #39                 // Field names:[Ljava/lang/String;
      17: return

  boolean isOptional();
    Code:
       0: aload_0
       1: getfield      #35                 // Field optional:Z
       4: ireturn

  public java.lang.String toString();
    Code:
       0: aload_0
       1: getfield      #39                 // Field names:[Ljava/lang/String;
       4: iconst_0
       5: aaload
       6: areturn

  java.lang.reflect.Method findSetter(java.lang.Class<?>);
    Code:
       0: aload_0
       1: ldc           #43                 // String set
       3: aload_1
       4: iconst_1
       5: anewarray     #45                 // class java/lang/Class
       8: dup
       9: iconst_0
      10: ldc           #47                 // class java/lang/String
      12: aastore
      13: invokevirtual #49                 // Method findMethod:(Ljava/lang/String;Ljava/lang/Class;[Ljava/lang/Class;)Ljava/lang/reflect/Method;
      16: areturn

  java.lang.reflect.Method findGetter(java.lang.Class<?>);
    Code:
       0: aload_0
       1: ldc           #53                 // String get
       3: aload_1
       4: iconst_0
       5: anewarray     #45                 // class java/lang/Class
       8: invokevirtual #49                 // Method findMethod:(Ljava/lang/String;Ljava/lang/Class;[Ljava/lang/Class;)Ljava/lang/reflect/Method;
      11: areturn

  private java.lang.reflect.Method findMethod(java.lang.String, java.lang.Class<?>, java.lang.Class<?>...);
    Code:
       0: aload_0
       1: getfield      #39                 // Field names:[Ljava/lang/String;
       4: astore        4
       6: aload         4
       8: arraylength
       9: istore        5
      11: iconst_0
      12: istore        6
      14: iload         6
      16: iload         5
      18: if_icmpge     64
      21: aload         4
      23: iload         6
      25: aaload
      26: astore        7
      28: aload_1
      29: aload         7
      31: invokestatic  #55                 // Method org/springframework/util/StringUtils.capitalize:(Ljava/lang/String;)Ljava/lang/String;
      34: invokedynamic #61,  0             // InvokeDynamic #0:makeConcatWithConstants:(Ljava/lang/String;Ljava/lang/String;)Ljava/lang/String;
      39: astore        8
      41: aload_2
      42: aload         8
      44: aload_3
      45: invokestatic  #65                 // Method org/springframework/util/ReflectionUtils.findMethod:(Ljava/lang/Class;Ljava/lang/String;[Ljava/lang/Class;)Ljava/lang/reflect/Method;
      48: astore        9
      50: aload         9
      52: ifnull        58
      55: aload         9
      57: areturn
      58: iinc          6, 1
      61: goto          14
      64: aconst_null
      65: areturn

  private static org.springframework.boot.jdbc.DataSourceBuilder$DataSourceProperty[] $values();
    Code:
       0: iconst_4
       1: anewarray     #1                  // class org/springframework/boot/jdbc/DataSourceBuilder$DataSourceProperty
       4: dup
       5: iconst_0
       6: getstatic     #3                  // Field URL:Lorg/springframework/boot/jdbc/DataSourceBuilder$DataSourceProperty;
       9: aastore
      10: dup
      11: iconst_1
      12: getstatic     #7                  // Field DRIVER_CLASS_NAME:Lorg/springframework/boot/jdbc/DataSourceBuilder$DataSourceProperty;
      15: aastore
      16: dup
      17: iconst_2
      18: getstatic     #10                 // Field USERNAME:Lorg/springframework/boot/jdbc/DataSourceBuilder$DataSourceProperty;
      21: aastore
      22: dup
      23: iconst_3
      24: getstatic     #13                 // Field PASSWORD:Lorg/springframework/boot/jdbc/DataSourceBuilder$DataSourceProperty;
      27: aastore
      28: areturn

  static {};
    Code:
       0: new           #1                  // class org/springframework/boot/jdbc/DataSourceBuilder$DataSourceProperty
       3: dup
       4: ldc           #70                 // String URL
       6: iconst_0
       7: iconst_0
       8: iconst_2
       9: anewarray     #47                 // class java/lang/String
      12: dup
      13: iconst_0
      14: ldc           #71                 // String url
      16: aastore
      17: dup
      18: iconst_1
      19: ldc           #70                 // String URL
      21: aastore
      22: invokespecial #73                 // Method "<init>":(Ljava/lang/String;IZ[Ljava/lang/String;)V
      25: putstatic     #3                  // Field URL:Lorg/springframework/boot/jdbc/DataSourceBuilder$DataSourceProperty;
      28: new           #1                  // class org/springframework/boot/jdbc/DataSourceBuilder$DataSourceProperty
      31: dup
      32: ldc           #76                 // String DRIVER_CLASS_NAME
      34: iconst_1
      35: iconst_1
      36: iconst_1
      37: anewarray     #47                 // class java/lang/String
      40: dup
      41: iconst_0
      42: ldc           #77                 // String driverClassName
      44: aastore
      45: invokespecial #73                 // Method "<init>":(Ljava/lang/String;IZ[Ljava/lang/String;)V
      48: putstatic     #7                  // Field DRIVER_CLASS_NAME:Lorg/springframework/boot/jdbc/DataSourceBuilder$DataSourceProperty;
      51: new           #1                  // class org/springframework/boot/jdbc/DataSourceBuilder$DataSourceProperty
      54: dup
      55: ldc           #79                 // String USERNAME
      57: iconst_2
      58: iconst_0
      59: iconst_2
      60: anewarray     #47                 // class java/lang/String
      63: dup
      64: iconst_0
      65: ldc           #80                 // String username
      67: aastore
      68: dup
      69: iconst_1
      70: ldc           #82                 // String user
      72: aastore
      73: invokespecial #73                 // Method "<init>":(Ljava/lang/String;IZ[Ljava/lang/String;)V
      76: putstatic     #10                 // Field USERNAME:Lorg/springframework/boot/jdbc/DataSourceBuilder$DataSourceProperty;
      79: new           #1                  // class org/springframework/boot/jdbc/DataSourceBuilder$DataSourceProperty
      82: dup
      83: ldc           #84                 // String PASSWORD
      85: iconst_3
      86: iconst_0
      87: iconst_1
      88: anewarray     #47                 // class java/lang/String
      91: dup
      92: iconst_0
      93: ldc           #85                 // String password
      95: aastore
      96: invokespecial #73                 // Method "<init>":(Ljava/lang/String;IZ[Ljava/lang/String;)V
      99: putstatic     #13                 // Field PASSWORD:Lorg/springframework/boot/jdbc/DataSourceBuilder$DataSourceProperty;
     102: invokestatic  #87                 // Method $values:()[Lorg/springframework/boot/jdbc/DataSourceBuilder$DataSourceProperty;
     105: putstatic     #16                 // Field $VALUES:[Lorg/springframework/boot/jdbc/DataSourceBuilder$DataSourceProperty;
     108: return
}
