Compiled from "DataSourceBuilder.java"
class org.springframework.boot.jdbc.DataSourceBuilder$SimpleDataSourceProperties extends org.springframework.boot.jdbc.DataSourceBuilder$MappedDataSourceProperties<org.springframework.jdbc.datasource.SimpleDriverDataSource> {
  org.springframework.boot.jdbc.DataSourceBuilder$SimpleDataSourceProperties();
    Code:
       0: aload_0
       1: invokespecial #1                  // Method org/springframework/boot/jdbc/DataSourceBuilder$MappedDataSourceProperties."<init>":()V
       4: aload_0
       5: getstatic     #7                  // Field org/springframework/boot/jdbc/DataSourceBuilder$DataSourceProperty.URL:Lorg/springframework/boot/jdbc/DataSourceBuilder$DataSourceProperty;
       8: invokedynamic #13,  0             // InvokeDynamic #0:get:()Lorg/springframework/boot/jdbc/DataSourceBuilder$Getter;
      13: invokedynamic #17,  0             // InvokeDynamic #1:set:()Lorg/springframework/boot/jdbc/DataSourceBuilder$Setter;
      18: invokevirtual #21                 // Method add:(Lorg/springframework/boot/jdbc/DataSourceBuilder$DataSourceProperty;Lorg/springframework/boot/jdbc/DataSourceBuilder$Getter;Lorg/springframework/boot/jdbc/DataSourceBuilder$Setter;)V
      21: aload_0
      22: getstatic     #27                 // Field org/springframework/boot/jdbc/DataSourceBuilder$DataSourceProperty.DRIVER_CLASS_NAME:Lorg/springframework/boot/jdbc/DataSourceBuilder$DataSourceProperty;
      25: ldc           #30                 // class java/lang/Class
      27: invokedynamic #32,  0             // InvokeDynamic #2:get:()Lorg/springframework/boot/jdbc/DataSourceBuilder$Getter;
      32: invokedynamic #33,  0             // InvokeDynamic #3:set:()Lorg/springframework/boot/jdbc/DataSourceBuilder$Setter;
      37: invokevirtual #34                 // Method add:(Lorg/springframework/boot/jdbc/DataSourceBuilder$DataSourceProperty;Ljava/lang/Class;Lorg/springframework/boot/jdbc/DataSourceBuilder$Getter;Lorg/springframework/boot/jdbc/DataSourceBuilder$Setter;)V
      40: aload_0
      41: getstatic     #37                 // Field org/springframework/boot/jdbc/DataSourceBuilder$DataSourceProperty.USERNAME:Lorg/springframework/boot/jdbc/DataSourceBuilder$DataSourceProperty;
      44: invokedynamic #40,  0             // InvokeDynamic #4:get:()Lorg/springframework/boot/jdbc/DataSourceBuilder$Getter;
      49: invokedynamic #41,  0             // InvokeDynamic #5:set:()Lorg/springframework/boot/jdbc/DataSourceBuilder$Setter;
      54: invokevirtual #21                 // Method add:(Lorg/springframework/boot/jdbc/DataSourceBuilder$DataSourceProperty;Lorg/springframework/boot/jdbc/DataSourceBuilder$Getter;Lorg/springframework/boot/jdbc/DataSourceBuilder$Setter;)V
      57: aload_0
      58: getstatic     #42                 // Field org/springframework/boot/jdbc/DataSourceBuilder$DataSourceProperty.PASSWORD:Lorg/springframework/boot/jdbc/DataSourceBuilder$DataSourceProperty;
      61: invokedynamic #45,  0             // InvokeDynamic #6:get:()Lorg/springframework/boot/jdbc/DataSourceBuilder$Getter;
      66: invokedynamic #46,  0             // InvokeDynamic #7:set:()Lorg/springframework/boot/jdbc/DataSourceBuilder$Setter;
      71: invokevirtual #21                 // Method add:(Lorg/springframework/boot/jdbc/DataSourceBuilder$DataSourceProperty;Lorg/springframework/boot/jdbc/DataSourceBuilder$Getter;Lorg/springframework/boot/jdbc/DataSourceBuilder$Setter;)V
      74: return

  private static java.lang.Class lambda$new$0(org.springframework.jdbc.datasource.SimpleDriverDataSource) throws java.sql.SQLException;
    Code:
       0: aload_0
       1: invokevirtual #47                 // Method org/springframework/jdbc/datasource/SimpleDriverDataSource.getDriver:()Ljava/sql/Driver;
       4: invokevirtual #53                 // Method java/lang/Object.getClass:()Ljava/lang/Class;
       7: areturn
}
