Compiled from "DataSourceBuilderRuntimeHints.java"
class org.springframework.boot.jdbc.DataSourceBuilderRuntimeHints implements org.springframework.aot.hint.RuntimeHintsRegistrar {
  private static final java.util.List<java.lang.String> TYPE_NAMES;

  org.springframework.boot.jdbc.DataSourceBuilderRuntimeHints();
    Code:
       0: aload_0
       1: invokespecial #1                  // Method java/lang/Object."<init>":()V
       4: return

  public void registerHints(org.springframework.aot.hint.RuntimeHints, java.lang.ClassLoader);
    Code:
       0: getstatic     #7                  // Field TYPE_NAMES:Ljava/util/List;
       3: invokeinterface #13,  1           // InterfaceMethod java/util/List.iterator:()Ljava/util/Iterator;
       8: astore_3
       9: aload_3
      10: invokeinterface #19,  1           // InterfaceMethod java/util/Iterator.hasNext:()Z
      15: ifeq          48
      18: aload_3
      19: invokeinterface #25,  1           // InterfaceMethod java/util/Iterator.next:()Ljava/lang/Object;
      24: checkcast     #29                 // class java/lang/String
      27: astore        4
      29: aload_1
      30: invokevirtual #31                 // Method org/springframework/aot/hint/RuntimeHints.reflection:()Lorg/springframework/aot/hint/ReflectionHints;
      33: aload_2
      34: aload         4
      36: invokedynamic #37,  0             // InvokeDynamic #0:accept:()Ljava/util/function/Consumer;
      41: invokevirtual #41                 // Method org/springframework/aot/hint/ReflectionHints.registerTypeIfPresent:(Ljava/lang/ClassLoader;Ljava/lang/String;Ljava/util/function/Consumer;)Lorg/springframework/aot/hint/ReflectionHints;
      44: pop
      45: goto          9
      48: return

  private static void lambda$registerHints$0(org.springframework.aot.hint.TypeHint$Builder);
    Code:
       0: aload_0
       1: iconst_1
       2: anewarray     #47                 // class org/springframework/aot/hint/MemberCategory
       5: dup
       6: iconst_0
       7: getstatic     #49                 // Field org/springframework/aot/hint/MemberCategory.INVOKE_PUBLIC_CONSTRUCTORS:Lorg/springframework/aot/hint/MemberCategory;
      10: aastore
      11: invokevirtual #53                 // Method org/springframework/aot/hint/TypeHint$Builder.withMembers:([Lorg/springframework/aot/hint/MemberCategory;)Lorg/springframework/aot/hint/TypeHint$Builder;
      14: pop
      15: return

  static {};
    Code:
       0: new           #59                 // class java/util/ArrayList
       3: dup
       4: invokespecial #61                 // Method java/util/ArrayList."<init>":()V
       7: astore_0
       8: aload_0
       9: ldc           #62                 // String com.mchange.v2.c3p0.ComboPooledDataSource
      11: invokeinterface #64,  2           // InterfaceMethod java/util/List.add:(Ljava/lang/Object;)Z
      16: pop
      17: aload_0
      18: ldc           #68                 // String org.h2.jdbcx.JdbcDataSource
      20: invokeinterface #64,  2           // InterfaceMethod java/util/List.add:(Ljava/lang/Object;)Z
      25: pop
      26: aload_0
      27: ldc           #70                 // String com.zaxxer.hikari.HikariDataSource
      29: invokeinterface #64,  2           // InterfaceMethod java/util/List.add:(Ljava/lang/Object;)Z
      34: pop
      35: aload_0
      36: ldc           #72                 // String org.apache.commons.dbcp2.BasicDataSource
      38: invokeinterface #64,  2           // InterfaceMethod java/util/List.add:(Ljava/lang/Object;)Z
      43: pop
      44: aload_0
      45: ldc           #74                 // String oracle.jdbc.datasource.OracleDataSource
      47: invokeinterface #64,  2           // InterfaceMethod java/util/List.add:(Ljava/lang/Object;)Z
      52: pop
      53: aload_0
      54: ldc           #76                 // String oracle.ucp.jdbc.PoolDataSource
      56: invokeinterface #64,  2           // InterfaceMethod java/util/List.add:(Ljava/lang/Object;)Z
      61: pop
      62: aload_0
      63: ldc           #78                 // String org.postgresql.ds.PGSimpleDataSource
      65: invokeinterface #64,  2           // InterfaceMethod java/util/List.add:(Ljava/lang/Object;)Z
      70: pop
      71: aload_0
      72: ldc           #80                 // String org.springframework.jdbc.datasource.SimpleDriverDataSource
      74: invokeinterface #64,  2           // InterfaceMethod java/util/List.add:(Ljava/lang/Object;)Z
      79: pop
      80: aload_0
      81: ldc           #82                 // String org.apache.tomcat.jdbc.pool.DataSource
      83: invokeinterface #64,  2           // InterfaceMethod java/util/List.add:(Ljava/lang/Object;)Z
      88: pop
      89: aload_0
      90: invokestatic  #84                 // Method java/util/Collections.unmodifiableList:(Ljava/util/List;)Ljava/util/List;
      93: putstatic     #7                  // Field TYPE_NAMES:Ljava/util/List;
      96: return
}
