Compiled from "DataSourceBuilder.java"
class org.springframework.boot.jdbc.DataSourceBuilder$MappedDataSourceProperties<T extends javax.sql.DataSource> implements org.springframework.boot.jdbc.DataSourceBuilder$DataSourceProperties<T> {
  private final java.util.Map<org.springframework.boot.jdbc.DataSourceBuilder$DataSourceProperty, org.springframework.boot.jdbc.DataSourceBuilder$MappedDataSourceProperty<T, ?>> mappedProperties;

  private final java.lang.Class<T> dataSourceType;

  org.springframework.boot.jdbc.DataSourceBuilder$MappedDataSourceProperties();
    Code:
       0: aload_0
       1: invokespecial #1                  // Method java/lang/Object."<init>":()V
       4: aload_0
       5: new           #7                  // class java/util/HashMap
       8: dup
       9: invokespecial #9                  // Method java/util/HashMap."<init>":()V
      12: putfield      #10                 // Field mappedProperties:Ljava/util/Map;
      15: aload_0
      16: ldc           #11                 // class org/springframework/boot/jdbc/DataSourceBuilder$MappedDataSourceProperties
      18: aload_0
      19: invokevirtual #16                 // Method java/lang/Object.getClass:()Ljava/lang/Class;
      22: invokestatic  #20                 // Method org/springframework/core/ResolvableType.forClass:(Ljava/lang/Class;Ljava/lang/Class;)Lorg/springframework/core/ResolvableType;
      25: iconst_0
      26: newarray       int
      28: invokevirtual #26                 // Method org/springframework/core/ResolvableType.resolveGeneric:([I)Ljava/lang/Class;
      31: putfield      #30                 // Field dataSourceType:Ljava/lang/Class;
      34: return

  public java.lang.Class<? extends T> getDataSourceInstanceType();
    Code:
       0: aload_0
       1: getfield      #30                 // Field dataSourceType:Ljava/lang/Class;
       4: areturn

  protected void add(org.springframework.boot.jdbc.DataSourceBuilder$DataSourceProperty, org.springframework.boot.jdbc.DataSourceBuilder$Getter<T, java.lang.String>, org.springframework.boot.jdbc.DataSourceBuilder$Setter<T, java.lang.String>);
    Code:
       0: aload_0
       1: aload_1
       2: ldc           #34                 // class java/lang/String
       4: aload_2
       5: aload_3
       6: invokevirtual #36                 // Method add:(Lorg/springframework/boot/jdbc/DataSourceBuilder$DataSourceProperty;Ljava/lang/Class;Lorg/springframework/boot/jdbc/DataSourceBuilder$Getter;Lorg/springframework/boot/jdbc/DataSourceBuilder$Setter;)V
       9: return

  protected <V> void add(org.springframework.boot.jdbc.DataSourceBuilder$DataSourceProperty, java.lang.Class<V>, org.springframework.boot.jdbc.DataSourceBuilder$Getter<T, V>, org.springframework.boot.jdbc.DataSourceBuilder$Setter<T, V>);
    Code:
       0: aload_0
       1: getfield      #10                 // Field mappedProperties:Ljava/util/Map;
       4: aload_1
       5: new           #40                 // class org/springframework/boot/jdbc/DataSourceBuilder$MappedDataSourceProperty
       8: dup
       9: aload_1
      10: aload_2
      11: aload_3
      12: aload         4
      14: invokespecial #42                 // Method org/springframework/boot/jdbc/DataSourceBuilder$MappedDataSourceProperty."<init>":(Lorg/springframework/boot/jdbc/DataSourceBuilder$DataSourceProperty;Ljava/lang/Class;Lorg/springframework/boot/jdbc/DataSourceBuilder$Getter;Lorg/springframework/boot/jdbc/DataSourceBuilder$Setter;)V
      17: invokeinterface #44,  3           // InterfaceMethod java/util/Map.put:(Ljava/lang/Object;Ljava/lang/Object;)Ljava/lang/Object;
      22: pop
      23: return

  public boolean canSet(org.springframework.boot.jdbc.DataSourceBuilder$DataSourceProperty);
    Code:
       0: aload_0
       1: getfield      #10                 // Field mappedProperties:Ljava/util/Map;
       4: aload_1
       5: invokeinterface #50,  2           // InterfaceMethod java/util/Map.containsKey:(Ljava/lang/Object;)Z
      10: ireturn

  public void set(T, org.springframework.boot.jdbc.DataSourceBuilder$DataSourceProperty, java.lang.String);
    Code:
       0: aload_0
       1: aload_2
       2: invokevirtual #54                 // Method getMapping:(Lorg/springframework/boot/jdbc/DataSourceBuilder$DataSourceProperty;)Lorg/springframework/boot/jdbc/DataSourceBuilder$MappedDataSourceProperty;
       5: astore        4
       7: aload         4
       9: ifnull        19
      12: aload         4
      14: aload_1
      15: aload_3
      16: invokevirtual #58                 // Method org/springframework/boot/jdbc/DataSourceBuilder$MappedDataSourceProperty.set:(Ljavax/sql/DataSource;Ljava/lang/String;)V
      19: return

  public java.lang.String get(T, org.springframework.boot.jdbc.DataSourceBuilder$DataSourceProperty);
    Code:
       0: aload_0
       1: aload_2
       2: invokevirtual #54                 // Method getMapping:(Lorg/springframework/boot/jdbc/DataSourceBuilder$DataSourceProperty;)Lorg/springframework/boot/jdbc/DataSourceBuilder$MappedDataSourceProperty;
       5: astore_3
       6: aload_3
       7: ifnull        16
      10: aload_3
      11: aload_1
      12: invokevirtual #62                 // Method org/springframework/boot/jdbc/DataSourceBuilder$MappedDataSourceProperty.get:(Ljavax/sql/DataSource;)Ljava/lang/String;
      15: areturn
      16: aconst_null
      17: areturn

  private org.springframework.boot.jdbc.DataSourceBuilder$MappedDataSourceProperty<T, ?> getMapping(org.springframework.boot.jdbc.DataSourceBuilder$DataSourceProperty);
    Code:
       0: aload_0
       1: getfield      #10                 // Field mappedProperties:Ljava/util/Map;
       4: aload_1
       5: invokeinterface #66,  2           // InterfaceMethod java/util/Map.get:(Ljava/lang/Object;)Ljava/lang/Object;
      10: checkcast     #40                 // class org/springframework/boot/jdbc/DataSourceBuilder$MappedDataSourceProperty
      13: astore_2
      14: aload_1
      15: invokevirtual #69                 // Method org/springframework/boot/jdbc/DataSourceBuilder$DataSourceProperty.isOptional:()Z
      18: ifne          29
      21: aload_2
      22: ifnonnull     29
      25: iconst_1
      26: goto          30
      29: iconst_0
      30: aload_1
      31: invokedynamic #75,  0             // InvokeDynamic #0:get:(Lorg/springframework/boot/jdbc/DataSourceBuilder$DataSourceProperty;)Ljava/util/function/Supplier;
      36: invokestatic  #78                 // Method org/springframework/boot/jdbc/UnsupportedDataSourcePropertyException.throwIf:(ZLjava/util/function/Supplier;)V
      39: aload_2
      40: areturn

  static <T extends javax.sql.DataSource> org.springframework.boot.jdbc.DataSourceBuilder$MappedDataSourceProperties<T> forType(java.lang.ClassLoader, java.lang.Class<T>);
    Code:
       0: aload_0
       1: aload_1
       2: invokestatic  #84                 // Method lookupPooled:(Ljava/lang/ClassLoader;Ljava/lang/Class;)Lorg/springframework/boot/jdbc/DataSourceBuilder$MappedDataSourceProperties;
       5: astore_2
       6: aload_1
       7: ifnull        14
      10: aload_2
      11: ifnull        16
      14: aload_2
      15: areturn
      16: aload_0
      17: aload_1
      18: invokestatic  #88                 // Method lookupBasic:(Ljava/lang/ClassLoader;Ljava/lang/Class;)Lorg/springframework/boot/jdbc/DataSourceBuilder$MappedDataSourceProperties;
      21: areturn

  private static <T extends javax.sql.DataSource> org.springframework.boot.jdbc.DataSourceBuilder$MappedDataSourceProperties<T> lookupPooled(java.lang.ClassLoader, java.lang.Class<T>);
    Code:
       0: aconst_null
       1: astore_2
       2: aload_0
       3: aload_1
       4: aload_2
       5: ldc           #91                 // String com.zaxxer.hikari.HikariDataSource
       7: invokedynamic #93,  0             // InvokeDynamic #1:get:()Ljava/util/function/Supplier;
      12: iconst_0
      13: anewarray     #34                 // class java/lang/String
      16: invokestatic  #96                 // Method lookup:(Ljava/lang/ClassLoader;Ljava/lang/Class;Lorg/springframework/boot/jdbc/DataSourceBuilder$MappedDataSourceProperties;Ljava/lang/String;Ljava/util/function/Supplier;[Ljava/lang/String;)Lorg/springframework/boot/jdbc/DataSourceBuilder$MappedDataSourceProperties;
      19: astore_2
      20: aload_0
      21: aload_1
      22: aload_2
      23: ldc           #100                // String org.apache.tomcat.jdbc.pool.DataSource
      25: invokedynamic #102,  0            // InvokeDynamic #2:get:()Ljava/util/function/Supplier;
      30: iconst_0
      31: anewarray     #34                 // class java/lang/String
      34: invokestatic  #96                 // Method lookup:(Ljava/lang/ClassLoader;Ljava/lang/Class;Lorg/springframework/boot/jdbc/DataSourceBuilder$MappedDataSourceProperties;Ljava/lang/String;Ljava/util/function/Supplier;[Ljava/lang/String;)Lorg/springframework/boot/jdbc/DataSourceBuilder$MappedDataSourceProperties;
      37: astore_2
      38: aload_0
      39: aload_1
      40: aload_2
      41: ldc           #103                // String org.apache.commons.dbcp2.BasicDataSource
      43: invokedynamic #105,  0            // InvokeDynamic #3:get:()Ljava/util/function/Supplier;
      48: iconst_0
      49: anewarray     #34                 // class java/lang/String
      52: invokestatic  #96                 // Method lookup:(Ljava/lang/ClassLoader;Ljava/lang/Class;Lorg/springframework/boot/jdbc/DataSourceBuilder$MappedDataSourceProperties;Ljava/lang/String;Ljava/util/function/Supplier;[Ljava/lang/String;)Lorg/springframework/boot/jdbc/DataSourceBuilder$MappedDataSourceProperties;
      55: astore_2
      56: aload_0
      57: aload_1
      58: aload_2
      59: ldc           #106                // String oracle.ucp.jdbc.PoolDataSourceImpl
      61: invokedynamic #108,  0            // InvokeDynamic #4:get:()Ljava/util/function/Supplier;
      66: iconst_1
      67: anewarray     #34                 // class java/lang/String
      70: dup
      71: iconst_0
      72: ldc           #109                // String oracle.jdbc.OracleConnection
      74: aastore
      75: invokestatic  #96                 // Method lookup:(Ljava/lang/ClassLoader;Ljava/lang/Class;Lorg/springframework/boot/jdbc/DataSourceBuilder$MappedDataSourceProperties;Ljava/lang/String;Ljava/util/function/Supplier;[Ljava/lang/String;)Lorg/springframework/boot/jdbc/DataSourceBuilder$MappedDataSourceProperties;
      78: astore_2
      79: aload_0
      80: aload_1
      81: aload_2
      82: ldc           #111                // String com.mchange.v2.c3p0.ComboPooledDataSource
      84: invokedynamic #113,  0            // InvokeDynamic #5:get:()Ljava/util/function/Supplier;
      89: iconst_0
      90: anewarray     #34                 // class java/lang/String
      93: invokestatic  #96                 // Method lookup:(Ljava/lang/ClassLoader;Ljava/lang/Class;Lorg/springframework/boot/jdbc/DataSourceBuilder$MappedDataSourceProperties;Ljava/lang/String;Ljava/util/function/Supplier;[Ljava/lang/String;)Lorg/springframework/boot/jdbc/DataSourceBuilder$MappedDataSourceProperties;
      96: astore_2
      97: aload_2
      98: areturn

  private static <T extends javax.sql.DataSource> org.springframework.boot.jdbc.DataSourceBuilder$MappedDataSourceProperties<T> lookupBasic(java.lang.ClassLoader, java.lang.Class<T>);
    Code:
       0: aconst_null
       1: astore_2
       2: aload_0
       3: aload_1
       4: aload_2
       5: ldc           #114                // String org.springframework.jdbc.datasource.SimpleDriverDataSource
       7: invokedynamic #116,  0            // InvokeDynamic #6:get:()Ljava/util/function/Supplier;
      12: iconst_0
      13: anewarray     #34                 // class java/lang/String
      16: invokestatic  #96                 // Method lookup:(Ljava/lang/ClassLoader;Ljava/lang/Class;Lorg/springframework/boot/jdbc/DataSourceBuilder$MappedDataSourceProperties;Ljava/lang/String;Ljava/util/function/Supplier;[Ljava/lang/String;)Lorg/springframework/boot/jdbc/DataSourceBuilder$MappedDataSourceProperties;
      19: astore_2
      20: aload_0
      21: aload_1
      22: aload_2
      23: ldc           #117                // String oracle.jdbc.datasource.OracleDataSource
      25: invokedynamic #119,  0            // InvokeDynamic #7:get:()Ljava/util/function/Supplier;
      30: iconst_0
      31: anewarray     #34                 // class java/lang/String
      34: invokestatic  #96                 // Method lookup:(Ljava/lang/ClassLoader;Ljava/lang/Class;Lorg/springframework/boot/jdbc/DataSourceBuilder$MappedDataSourceProperties;Ljava/lang/String;Ljava/util/function/Supplier;[Ljava/lang/String;)Lorg/springframework/boot/jdbc/DataSourceBuilder$MappedDataSourceProperties;
      37: astore_2
      38: aload_0
      39: aload_1
      40: aload_2
      41: ldc           #120                // String org.h2.jdbcx.JdbcDataSource
      43: invokedynamic #122,  0            // InvokeDynamic #8:get:()Ljava/util/function/Supplier;
      48: iconst_0
      49: anewarray     #34                 // class java/lang/String
      52: invokestatic  #96                 // Method lookup:(Ljava/lang/ClassLoader;Ljava/lang/Class;Lorg/springframework/boot/jdbc/DataSourceBuilder$MappedDataSourceProperties;Ljava/lang/String;Ljava/util/function/Supplier;[Ljava/lang/String;)Lorg/springframework/boot/jdbc/DataSourceBuilder$MappedDataSourceProperties;
      55: astore_2
      56: aload_0
      57: aload_1
      58: aload_2
      59: ldc           #123                // String org.postgresql.ds.PGSimpleDataSource
      61: invokedynamic #125,  0            // InvokeDynamic #9:get:()Ljava/util/function/Supplier;
      66: iconst_0
      67: anewarray     #34                 // class java/lang/String
      70: invokestatic  #96                 // Method lookup:(Ljava/lang/ClassLoader;Ljava/lang/Class;Lorg/springframework/boot/jdbc/DataSourceBuilder$MappedDataSourceProperties;Ljava/lang/String;Ljava/util/function/Supplier;[Ljava/lang/String;)Lorg/springframework/boot/jdbc/DataSourceBuilder$MappedDataSourceProperties;
      73: astore_2
      74: aload_2
      75: areturn

  private static <T extends javax.sql.DataSource> org.springframework.boot.jdbc.DataSourceBuilder$MappedDataSourceProperties<T> lookup(java.lang.ClassLoader, java.lang.Class<T>, org.springframework.boot.jdbc.DataSourceBuilder$MappedDataSourceProperties<T>, java.lang.String, java.util.function.Supplier<org.springframework.boot.jdbc.DataSourceBuilder$MappedDataSourceProperties<?>>, java.lang.String...);
    Code:
       0: aload_2
       1: ifnonnull     14
       4: aload_0
       5: aload_3
       6: aload         5
       8: invokestatic  #126                // Method allPresent:(Ljava/lang/ClassLoader;Ljava/lang/String;[Ljava/lang/String;)Z
      11: ifne          16
      14: aload_2
      15: areturn
      16: aload         4
      18: invokeinterface #130,  1          // InterfaceMethod java/util/function/Supplier.get:()Ljava/lang/Object;
      23: checkcast     #11                 // class org/springframework/boot/jdbc/DataSourceBuilder$MappedDataSourceProperties
      26: astore        6
      28: aload_1
      29: ifnull        44
      32: aload         6
      34: invokevirtual #135                // Method getDataSourceInstanceType:()Ljava/lang/Class;
      37: aload_1
      38: invokevirtual #138                // Method java/lang/Class.isAssignableFrom:(Ljava/lang/Class;)Z
      41: ifeq          49
      44: aload         6
      46: goto          50
      49: aconst_null
      50: areturn

  private static boolean allPresent(java.lang.ClassLoader, java.lang.String, java.lang.String[]);
    Code:
       0: aload_1
       1: aload_0
       2: invokestatic  #144                // Method org/springframework/util/ClassUtils.isPresent:(Ljava/lang/String;Ljava/lang/ClassLoader;)Z
       5: istore_3
       6: aload_2
       7: astore        4
       9: aload         4
      11: arraylength
      12: istore        5
      14: iconst_0
      15: istore        6
      17: iload         6
      19: iload         5
      21: if_icmpge     56
      24: aload         4
      26: iload         6
      28: aaload
      29: astore        7
      31: iload_3
      32: ifeq          48
      35: aload         7
      37: aload_0
      38: invokestatic  #144                // Method org/springframework/util/ClassUtils.isPresent:(Ljava/lang/String;Ljava/lang/ClassLoader;)Z
      41: ifeq          48
      44: iconst_1
      45: goto          49
      48: iconst_0
      49: istore_3
      50: iinc          6, 1
      53: goto          17
      56: iload_3
      57: ireturn

  private static java.lang.String lambda$getMapping$0(org.springframework.boot.jdbc.DataSourceBuilder$DataSourceProperty);
    Code:
       0: aload_0
       1: invokedynamic #150,  0            // InvokeDynamic #10:makeConcatWithConstants:(Lorg/springframework/boot/jdbc/DataSourceBuilder$DataSourceProperty;)Ljava/lang/String;
       6: areturn
}
