Compiled from "DataSourceUnwrapper.java"
class org.springframework.boot.jdbc.DataSourceUnwrapper$DelegatingDataSourceUnwrapper {
  private org.springframework.boot.jdbc.DataSourceUnwrapper$DelegatingDataSourceUnwrapper();
    Code:
       0: aload_0
       1: invokespecial #1                  // Method java/lang/Object."<init>":()V
       4: return

  private static javax.sql.DataSource getTargetDataSource(javax.sql.DataSource);
    Code:
       0: aload_0
       1: instanceof    #7                  // class org/springframework/jdbc/datasource/DelegatingDataSource
       4: ifeq          17
       7: aload_0
       8: checkcast     #7                  // class org/springframework/jdbc/datasource/DelegatingDataSource
      11: astore_1
      12: aload_1
      13: invokevirtual #9                  // Method org/springframework/jdbc/datasource/DelegatingDataSource.getTargetDataSource:()Ljavax/sql/DataSource;
      16: areturn
      17: aconst_null
      18: areturn
}
