Compiled from "EmbeddedDatabaseConnection.java"
public final class org.springframework.boot.jdbc.EmbeddedDatabaseConnection extends java.lang.Enum<org.springframework.boot.jdbc.EmbeddedDatabaseConnection> {
  public static final org.springframework.boot.jdbc.EmbeddedDatabaseConnection NONE;

  public static final org.springframework.boot.jdbc.EmbeddedDatabaseConnection H2;

  public static final org.springframework.boot.jdbc.EmbeddedDatabaseConnection DERBY;

  public static final org.springframework.boot.jdbc.EmbeddedDatabaseConnection HSQLDB;

  private final java.lang.String alternativeDriverClass;

  private final java.lang.String url;

  private static final org.springframework.boot.jdbc.EmbeddedDatabaseConnection[] $VALUES;

  public static org.springframework.boot.jdbc.EmbeddedDatabaseConnection[] values();
    Code:
       0: getstatic     #16                 // Field $VALUES:[Lorg/springframework/boot/jdbc/EmbeddedDatabaseConnection;
       3: invokevirtual #20                 // Method "[Lorg/springframework/boot/jdbc/EmbeddedDatabaseConnection;".clone:()Ljava/lang/Object;
       6: checkcast     #21                 // class "[Lorg/springframework/boot/jdbc/EmbeddedDatabaseConnection;"
       9: areturn

  public static org.springframework.boot.jdbc.EmbeddedDatabaseConnection valueOf(java.lang.String);
    Code:
       0: ldc           #1                  // class org/springframework/boot/jdbc/EmbeddedDatabaseConnection
       2: aload_0
       3: invokestatic  #25                 // Method java/lang/Enum.valueOf:(Ljava/lang/Class;Ljava/lang/String;)Ljava/lang/Enum;
       6: checkcast     #1                  // class org/springframework/boot/jdbc/EmbeddedDatabaseConnection
       9: areturn

  private org.springframework.boot.jdbc.EmbeddedDatabaseConnection(java.lang.String);
    Code:
       0: aload_0
       1: aload_1
       2: iload_2
       3: aconst_null
       4: aload_3
       5: invokespecial #31                 // Method "<init>":(Ljava/lang/String;ILjava/lang/String;Ljava/lang/String;)V
       8: return

  private org.springframework.boot.jdbc.EmbeddedDatabaseConnection(java.lang.String, java.lang.String);
    Code:
       0: aload_0
       1: aload_1
       2: iload_2
       3: invokespecial #35                 // Method java/lang/Enum."<init>":(Ljava/lang/String;I)V
       6: aload_0
       7: aload_3
       8: putfield      #38                 // Field alternativeDriverClass:Ljava/lang/String;
      11: aload_0
      12: aload         4
      14: putfield      #42                 // Field url:Ljava/lang/String;
      17: return

  public java.lang.String getDriverClassName();
    Code:
       0: getstatic     #45                 // Field org/springframework/boot/jdbc/EmbeddedDatabaseConnection$1.$SwitchMap$org$springframework$boot$jdbc$EmbeddedDatabaseConnection:[I
       3: aload_0
       4: invokevirtual #51                 // Method ordinal:()I
       7: iaload
       8: tableswitch   { // 1 to 4
                     1: 48
                     2: 52
                     3: 61
                     4: 70
               default: 40
          }
      40: new           #55                 // class java/lang/IncompatibleClassChangeError
      43: dup
      44: invokespecial #57                 // Method java/lang/IncompatibleClassChangeError."<init>":()V
      47: athrow
      48: aconst_null
      49: goto          76
      52: getstatic     #60                 // Field org/springframework/boot/jdbc/DatabaseDriver.H2:Lorg/springframework/boot/jdbc/DatabaseDriver;
      55: invokevirtual #65                 // Method org/springframework/boot/jdbc/DatabaseDriver.getDriverClassName:()Ljava/lang/String;
      58: goto          76
      61: getstatic     #69                 // Field org/springframework/boot/jdbc/DatabaseDriver.DERBY:Lorg/springframework/boot/jdbc/DatabaseDriver;
      64: invokevirtual #65                 // Method org/springframework/boot/jdbc/DatabaseDriver.getDriverClassName:()Ljava/lang/String;
      67: goto          76
      70: getstatic     #71                 // Field org/springframework/boot/jdbc/DatabaseDriver.HSQLDB:Lorg/springframework/boot/jdbc/DatabaseDriver;
      73: invokevirtual #65                 // Method org/springframework/boot/jdbc/DatabaseDriver.getDriverClassName:()Ljava/lang/String;
      76: areturn

  public org.springframework.jdbc.datasource.embedded.EmbeddedDatabaseType getType();
    Code:
       0: getstatic     #45                 // Field org/springframework/boot/jdbc/EmbeddedDatabaseConnection$1.$SwitchMap$org$springframework$boot$jdbc$EmbeddedDatabaseConnection:[I
       3: aload_0
       4: invokevirtual #51                 // Method ordinal:()I
       7: iaload
       8: tableswitch   { // 1 to 4
                     1: 48
                     2: 52
                     3: 58
                     4: 64
               default: 40
          }
      40: new           #55                 // class java/lang/IncompatibleClassChangeError
      43: dup
      44: invokespecial #57                 // Method java/lang/IncompatibleClassChangeError."<init>":()V
      47: athrow
      48: aconst_null
      49: goto          67
      52: getstatic     #73                 // Field org/springframework/jdbc/datasource/embedded/EmbeddedDatabaseType.H2:Lorg/springframework/jdbc/datasource/embedded/EmbeddedDatabaseType;
      55: goto          67
      58: getstatic     #78                 // Field org/springframework/jdbc/datasource/embedded/EmbeddedDatabaseType.DERBY:Lorg/springframework/jdbc/datasource/embedded/EmbeddedDatabaseType;
      61: goto          67
      64: getstatic     #80                 // Field org/springframework/jdbc/datasource/embedded/EmbeddedDatabaseType.HSQL:Lorg/springframework/jdbc/datasource/embedded/EmbeddedDatabaseType;
      67: areturn

  public java.lang.String getUrl(java.lang.String);
    Code:
       0: aload_1
       1: ldc           #83                 // String DatabaseName must not be empty
       3: invokestatic  #85                 // Method org/springframework/util/Assert.hasText:(Ljava/lang/String;Ljava/lang/String;)V
       6: aload_0
       7: getfield      #42                 // Field url:Ljava/lang/String;
      10: ifnull        31
      13: aload_0
      14: getfield      #42                 // Field url:Ljava/lang/String;
      17: iconst_1
      18: anewarray     #91                 // class java/lang/Object
      21: dup
      22: iconst_0
      23: aload_1
      24: aastore
      25: invokestatic  #93                 // Method java/lang/String.format:(Ljava/lang/String;[Ljava/lang/Object;)Ljava/lang/String;
      28: goto          32
      31: aconst_null
      32: areturn

  boolean isEmbeddedUrl(java.lang.String);
    Code:
       0: getstatic     #45                 // Field org/springframework/boot/jdbc/EmbeddedDatabaseConnection$1.$SwitchMap$org$springframework$boot$jdbc$EmbeddedDatabaseConnection:[I
       3: aload_0
       4: invokevirtual #51                 // Method ordinal:()I
       7: iaload
       8: tableswitch   { // 1 to 4
                     1: 48
                     2: 52
                     3: 61
                     4: 65
               default: 40
          }
      40: new           #55                 // class java/lang/IncompatibleClassChangeError
      43: dup
      44: invokespecial #57                 // Method java/lang/IncompatibleClassChangeError."<init>":()V
      47: athrow
      48: iconst_0
      49: goto          71
      52: aload_1
      53: ldc           #99                 // String :h2:mem
      55: invokevirtual #101                // Method java/lang/String.contains:(Ljava/lang/CharSequence;)Z
      58: goto          71
      61: iconst_1
      62: goto          71
      65: aload_1
      66: ldc           #105                // String :hsqldb:mem:
      68: invokevirtual #101                // Method java/lang/String.contains:(Ljava/lang/CharSequence;)Z
      71: ireturn

  boolean isDriverCompatible(java.lang.String);
    Code:
       0: aload_1
       1: ifnull        30
       4: aload_1
       5: aload_0
       6: invokevirtual #107                // Method getDriverClassName:()Ljava/lang/String;
       9: invokevirtual #108                // Method java/lang/String.equals:(Ljava/lang/Object;)Z
      12: ifne          26
      15: aload_1
      16: aload_0
      17: getfield      #38                 // Field alternativeDriverClass:Ljava/lang/String;
      20: invokevirtual #108                // Method java/lang/String.equals:(Ljava/lang/Object;)Z
      23: ifeq          30
      26: iconst_1
      27: goto          31
      30: iconst_0
      31: ireturn

  public static boolean isEmbedded(java.lang.String, java.lang.String);
    Code:
       0: aload_0
       1: ifnonnull     6
       4: iconst_0
       5: ireturn
       6: aload_0
       7: invokestatic  #112                // Method getEmbeddedDatabaseConnection:(Ljava/lang/String;)Lorg/springframework/boot/jdbc/EmbeddedDatabaseConnection;
      10: astore_2
      11: aload_2
      12: getstatic     #3                  // Field NONE:Lorg/springframework/boot/jdbc/EmbeddedDatabaseConnection;
      15: if_acmpne     20
      18: iconst_0
      19: ireturn
      20: aload_1
      21: ifnull        32
      24: aload_2
      25: aload_1
      26: invokevirtual #116                // Method isEmbeddedUrl:(Ljava/lang/String;)Z
      29: ifeq          36
      32: iconst_1
      33: goto          37
      36: iconst_0
      37: ireturn

  private static org.springframework.boot.jdbc.EmbeddedDatabaseConnection getEmbeddedDatabaseConnection(java.lang.String);
    Code:
       0: iconst_3
       1: anewarray     #1                  // class org/springframework/boot/jdbc/EmbeddedDatabaseConnection
       4: dup
       5: iconst_0
       6: getstatic     #7                  // Field H2:Lorg/springframework/boot/jdbc/EmbeddedDatabaseConnection;
       9: aastore
      10: dup
      11: iconst_1
      12: getstatic     #13                 // Field HSQLDB:Lorg/springframework/boot/jdbc/EmbeddedDatabaseConnection;
      15: aastore
      16: dup
      17: iconst_2
      18: getstatic     #10                 // Field DERBY:Lorg/springframework/boot/jdbc/EmbeddedDatabaseConnection;
      21: aastore
      22: invokestatic  #120                // InterfaceMethod java/util/stream/Stream.of:([Ljava/lang/Object;)Ljava/util/stream/Stream;
      25: aload_0
      26: invokedynamic #126,  0            // InvokeDynamic #0:test:(Ljava/lang/String;)Ljava/util/function/Predicate;
      31: invokeinterface #130,  2          // InterfaceMethod java/util/stream/Stream.filter:(Ljava/util/function/Predicate;)Ljava/util/stream/Stream;
      36: invokeinterface #134,  1          // InterfaceMethod java/util/stream/Stream.findFirst:()Ljava/util/Optional;
      41: getstatic     #3                  // Field NONE:Lorg/springframework/boot/jdbc/EmbeddedDatabaseConnection;
      44: invokevirtual #138                // Method java/util/Optional.orElse:(Ljava/lang/Object;)Ljava/lang/Object;
      47: checkcast     #1                  // class org/springframework/boot/jdbc/EmbeddedDatabaseConnection
      50: areturn

  public static boolean isEmbedded(javax.sql.DataSource);
    Code:
       0: new           #144                // class org/springframework/jdbc/core/JdbcTemplate
       3: dup
       4: aload_0
       5: invokespecial #146                // Method org/springframework/jdbc/core/JdbcTemplate."<init>":(Ljavax/sql/DataSource;)V
       8: new           #149                // class org/springframework/boot/jdbc/EmbeddedDatabaseConnection$IsEmbedded
      11: dup
      12: invokespecial #151                // Method org/springframework/boot/jdbc/EmbeddedDatabaseConnection$IsEmbedded."<init>":()V
      15: invokevirtual #152                // Method org/springframework/jdbc/core/JdbcTemplate.execute:(Lorg/springframework/jdbc/core/ConnectionCallback;)Ljava/lang/Object;
      18: checkcast     #156                // class java/lang/Boolean
      21: invokevirtual #158                // Method java/lang/Boolean.booleanValue:()Z
      24: ireturn
      25: astore_1
      26: iconst_0
      27: ireturn
    Exception table:
       from    to  target type
           0    24    25   Class org/springframework/dao/DataAccessException

  public static org.springframework.boot.jdbc.EmbeddedDatabaseConnection get(java.lang.ClassLoader);
    Code:
       0: invokestatic  #164                // Method values:()[Lorg/springframework/boot/jdbc/EmbeddedDatabaseConnection;
       3: astore_1
       4: aload_1
       5: arraylength
       6: istore_2
       7: iconst_0
       8: istore_3
       9: iload_3
      10: iload_2
      11: if_icmpge     48
      14: aload_1
      15: iload_3
      16: aaload
      17: astore        4
      19: aload         4
      21: getstatic     #3                  // Field NONE:Lorg/springframework/boot/jdbc/EmbeddedDatabaseConnection;
      24: if_acmpeq     42
      27: aload         4
      29: invokevirtual #107                // Method getDriverClassName:()Ljava/lang/String;
      32: aload_0
      33: invokestatic  #168                // Method org/springframework/util/ClassUtils.isPresent:(Ljava/lang/String;Ljava/lang/ClassLoader;)Z
      36: ifeq          42
      39: aload         4
      41: areturn
      42: iinc          3, 1
      45: goto          9
      48: getstatic     #3                  // Field NONE:Lorg/springframework/boot/jdbc/EmbeddedDatabaseConnection;
      51: areturn

  private static boolean lambda$getEmbeddedDatabaseConnection$0(java.lang.String, org.springframework.boot.jdbc.EmbeddedDatabaseConnection);
    Code:
       0: aload_1
       1: aload_0
       2: invokevirtual #174                // Method isDriverCompatible:(Ljava/lang/String;)Z
       5: ireturn

  private static org.springframework.boot.jdbc.EmbeddedDatabaseConnection[] $values();
    Code:
       0: iconst_4
       1: anewarray     #1                  // class org/springframework/boot/jdbc/EmbeddedDatabaseConnection
       4: dup
       5: iconst_0
       6: getstatic     #3                  // Field NONE:Lorg/springframework/boot/jdbc/EmbeddedDatabaseConnection;
       9: aastore
      10: dup
      11: iconst_1
      12: getstatic     #7                  // Field H2:Lorg/springframework/boot/jdbc/EmbeddedDatabaseConnection;
      15: aastore
      16: dup
      17: iconst_2
      18: getstatic     #10                 // Field DERBY:Lorg/springframework/boot/jdbc/EmbeddedDatabaseConnection;
      21: aastore
      22: dup
      23: iconst_3
      24: getstatic     #13                 // Field HSQLDB:Lorg/springframework/boot/jdbc/EmbeddedDatabaseConnection;
      27: aastore
      28: areturn

  static {};
    Code:
       0: new           #1                  // class org/springframework/boot/jdbc/EmbeddedDatabaseConnection
       3: dup
       4: ldc           #177                // String NONE
       6: iconst_0
       7: aconst_null
       8: invokespecial #178                // Method "<init>":(Ljava/lang/String;ILjava/lang/String;)V
      11: putstatic     #3                  // Field NONE:Lorg/springframework/boot/jdbc/EmbeddedDatabaseConnection;
      14: new           #1                  // class org/springframework/boot/jdbc/EmbeddedDatabaseConnection
      17: dup
      18: ldc           #181                // String H2
      20: iconst_1
      21: ldc           #182                // String jdbc:h2:mem:%s;DB_CLOSE_DELAY=-1;DB_CLOSE_ON_EXIT=FALSE
      23: invokespecial #178                // Method "<init>":(Ljava/lang/String;ILjava/lang/String;)V
      26: putstatic     #7                  // Field H2:Lorg/springframework/boot/jdbc/EmbeddedDatabaseConnection;
      29: new           #1                  // class org/springframework/boot/jdbc/EmbeddedDatabaseConnection
      32: dup
      33: ldc           #184                // String DERBY
      35: iconst_2
      36: ldc           #185                // String jdbc:derby:memory:%s;create=true
      38: invokespecial #178                // Method "<init>":(Ljava/lang/String;ILjava/lang/String;)V
      41: putstatic     #10                 // Field DERBY:Lorg/springframework/boot/jdbc/EmbeddedDatabaseConnection;
      44: new           #1                  // class org/springframework/boot/jdbc/EmbeddedDatabaseConnection
      47: dup
      48: ldc           #187                // String HSQLDB
      50: iconst_3
      51: ldc           #188                // String org.hsqldb.jdbcDriver
      53: ldc           #190                // String jdbc:hsqldb:mem:%s
      55: invokespecial #31                 // Method "<init>":(Ljava/lang/String;ILjava/lang/String;Ljava/lang/String;)V
      58: putstatic     #13                 // Field HSQLDB:Lorg/springframework/boot/jdbc/EmbeddedDatabaseConnection;
      61: invokestatic  #192                // Method $values:()[Lorg/springframework/boot/jdbc/EmbeddedDatabaseConnection;
      64: putstatic     #16                 // Field $VALUES:[Lorg/springframework/boot/jdbc/EmbeddedDatabaseConnection;
      67: return
}
