Compiled from "EmbeddedDatabaseConnection.java"
class org.springframework.boot.jdbc.EmbeddedDatabaseConnection$IsEmbedded implements org.springframework.jdbc.core.ConnectionCallback<java.lang.Boolean> {
  private org.springframework.boot.jdbc.EmbeddedDatabaseConnection$IsEmbedded();
    Code:
       0: aload_0
       1: invokespecial #1                  // Method java/lang/Object."<init>":()V
       4: return

  public java.lang.Boolean doInConnection(java.sql.Connection) throws java.sql.SQLException, org.springframework.dao.DataAccessException;
    Code:
       0: aload_1
       1: invokeinterface #7,  1            // InterfaceMethod java/sql/Connection.getMetaData:()Ljava/sql/DatabaseMetaData;
       6: astore_2
       7: aload_2
       8: invokeinterface #13,  1           // InterfaceMethod java/sql/DatabaseMetaData.getDatabaseProductName:()Ljava/lang/String;
      13: astore_3
      14: aload_3
      15: ifnonnull     23
      18: iconst_0
      19: invokestatic  #19                 // Method java/lang/Boolean.valueOf:(Z)Ljava/lang/Boolean;
      22: areturn
      23: aload_3
      24: getstatic     #25                 // Field java/util/Locale.ENGLISH:Ljava/util/Locale;
      27: invokevirtual #31                 // Method java/lang/String.toUpperCase:(Ljava/util/Locale;)Ljava/lang/String;
      30: astore_3
      31: invokestatic  #37                 // Method org/springframework/boot/jdbc/EmbeddedDatabaseConnection.values:()[Lorg/springframework/boot/jdbc/EmbeddedDatabaseConnection;
      34: astore        4
      36: aload         4
      38: astore        5
      40: aload         5
      42: arraylength
      43: istore        6
      45: iconst_0
      46: istore        7
      48: iload         7
      50: iload         6
      52: if_icmpge     123
      55: aload         5
      57: iload         7
      59: aaload
      60: astore        8
      62: aload         8
      64: getstatic     #43                 // Field org/springframework/boot/jdbc/EmbeddedDatabaseConnection.NONE:Lorg/springframework/boot/jdbc/EmbeddedDatabaseConnection;
      67: if_acmpeq     117
      70: aload_3
      71: aload         8
      73: invokevirtual #47                 // Method org/springframework/boot/jdbc/EmbeddedDatabaseConnection.getType:()Lorg/springframework/jdbc/datasource/embedded/EmbeddedDatabaseType;
      76: invokevirtual #51                 // Method org/springframework/jdbc/datasource/embedded/EmbeddedDatabaseType.name:()Ljava/lang/String;
      79: invokevirtual #56                 // Method java/lang/String.contains:(Ljava/lang/CharSequence;)Z
      82: ifeq          117
      85: aload_2
      86: invokeinterface #60,  1           // InterfaceMethod java/sql/DatabaseMetaData.getURL:()Ljava/lang/String;
      91: astore        9
      93: aload         9
      95: ifnull        108
      98: aload         8
     100: aload         9
     102: invokevirtual #63                 // Method org/springframework/boot/jdbc/EmbeddedDatabaseConnection.isEmbeddedUrl:(Ljava/lang/String;)Z
     105: ifeq          112
     108: iconst_1
     109: goto          113
     112: iconst_0
     113: invokestatic  #19                 // Method java/lang/Boolean.valueOf:(Z)Ljava/lang/Boolean;
     116: areturn
     117: iinc          7, 1
     120: goto          48
     123: iconst_0
     124: invokestatic  #19                 // Method java/lang/Boolean.valueOf:(Z)Ljava/lang/Boolean;
     127: areturn

  public java.lang.Object doInConnection(java.sql.Connection) throws java.sql.SQLException, org.springframework.dao.DataAccessException;
    Code:
       0: aload_0
       1: aload_1
       2: invokevirtual #67                 // Method doInConnection:(Ljava/sql/Connection;)Ljava/lang/Boolean;
       5: areturn
}
