Compiled from "SchemaManagement.java"
public final class org.springframework.boot.jdbc.SchemaManagement extends java.lang.Enum<org.springframework.boot.jdbc.SchemaManagement> {
  public static final org.springframework.boot.jdbc.SchemaManagement MANAGED;

  public static final org.springframework.boot.jdbc.SchemaManagement UNMANAGED;

  private static final org.springframework.boot.jdbc.SchemaManagement[] $VALUES;

  public static org.springframework.boot.jdbc.SchemaManagement[] values();
    Code:
       0: getstatic     #10                 // Field $VALUES:[Lorg/springframework/boot/jdbc/SchemaManagement;
       3: invokevirtual #14                 // Method "[Lorg/springframework/boot/jdbc/SchemaManagement;".clone:()Ljava/lang/Object;
       6: checkcast     #15                 // class "[Lorg/springframework/boot/jdbc/SchemaManagement;"
       9: areturn

  public static org.springframework.boot.jdbc.SchemaManagement valueOf(java.lang.String);
    Code:
       0: ldc           #1                  // class org/springframework/boot/jdbc/SchemaManagement
       2: aload_0
       3: invokestatic  #19                 // Method java/lang/Enum.valueOf:(Ljava/lang/Class;Ljava/lang/String;)Ljava/lang/Enum;
       6: checkcast     #1                  // class org/springframework/boot/jdbc/SchemaManagement
       9: areturn

  private org.springframework.boot.jdbc.SchemaManagement();
    Code:
       0: aload_0
       1: aload_1
       2: iload_2
       3: invokespecial #25                 // Method java/lang/Enum."<init>":(Ljava/lang/String;I)V
       6: return

  private static org.springframework.boot.jdbc.SchemaManagement[] $values();
    Code:
       0: iconst_2
       1: anewarray     #1                  // class org/springframework/boot/jdbc/SchemaManagement
       4: dup
       5: iconst_0
       6: getstatic     #3                  // Field MANAGED:Lorg/springframework/boot/jdbc/SchemaManagement;
       9: aastore
      10: dup
      11: iconst_1
      12: getstatic     #7                  // Field UNMANAGED:Lorg/springframework/boot/jdbc/SchemaManagement;
      15: aastore
      16: areturn

  static {};
    Code:
       0: new           #1                  // class org/springframework/boot/jdbc/SchemaManagement
       3: dup
       4: ldc           #29                 // String MANAGED
       6: iconst_0
       7: invokespecial #30                 // Method "<init>":(Ljava/lang/String;I)V
      10: putstatic     #3                  // Field MANAGED:Lorg/springframework/boot/jdbc/SchemaManagement;
      13: new           #1                  // class org/springframework/boot/jdbc/SchemaManagement
      16: dup
      17: ldc           #31                 // String UNMANAGED
      19: iconst_1
      20: invokespecial #30                 // Method "<init>":(Ljava/lang/String;I)V
      23: putstatic     #7                  // Field UNMANAGED:Lorg/springframework/boot/jdbc/SchemaManagement;
      26: invokestatic  #32                 // Method $values:()[Lorg/springframework/boot/jdbc/SchemaManagement;
      29: putstatic     #10                 // Field $VALUES:[Lorg/springframework/boot/jdbc/SchemaManagement;
      32: return
}
