Compiled from "SpringJdbcDependsOnDatabaseInitializationDetector.java"
class org.springframework.boot.jdbc.SpringJdbcDependsOnDatabaseInitializationDetector extends org.springframework.boot.sql.init.dependency.AbstractBeansOfTypeDependsOnDatabaseInitializationDetector {
  org.springframework.boot.jdbc.SpringJdbcDependsOnDatabaseInitializationDetector();
    Code:
       0: aload_0
       1: invokespecial #1                  // Method org/springframework/boot/sql/init/dependency/AbstractBeansOfTypeDependsOnDatabaseInitializationDetector."<init>":()V
       4: return

  protected java.util.Set<java.lang.Class<?>> getDependsOnDatabaseInitializationBeanTypes();
    Code:
       0: new           #7                  // class java/util/HashSet
       3: dup
       4: iconst_2
       5: anewarray     #9                  // class java/lang/Class
       8: dup
       9: iconst_0
      10: ldc           #11                 // class org/springframework/jdbc/core/JdbcOperations
      12: aastore
      13: dup
      14: iconst_1
      15: ldc           #13                 // class org/springframework/jdbc/core/namedparam/NamedParameterJdbcOperations
      17: aastore
      18: invokestatic  #15                 // Method java/util/Arrays.asList:([Ljava/lang/Object;)Ljava/util/List;
      21: invokespecial #21                 // Method java/util/HashSet."<init>":(Ljava/util/Collection;)V
      24: areturn
}
