Compiled from "UnsupportedDataSourcePropertyException.java"
public class org.springframework.boot.jdbc.UnsupportedDataSourcePropertyException extends java.lang.RuntimeException {
  org.springframework.boot.jdbc.UnsupportedDataSourcePropertyException(java.lang.String);
    Code:
       0: aload_0
       1: aload_1
       2: invokespecial #1                  // Method java/lang/RuntimeException."<init>":(Ljava/lang/String;)V
       5: return

  static void throwIf(boolean, java.util.function.Supplier<java.lang.String>);
    Code:
       0: iload_0
       1: ifeq          21
       4: new           #7                  // class org/springframework/boot/jdbc/UnsupportedDataSourcePropertyException
       7: dup
       8: aload_1
       9: invokeinterface #9,  1            // InterfaceMethod java/util/function/Supplier.get:()Ljava/lang/Object;
      14: checkcast     #15                 // class java/lang/String
      17: invokespecial #17                 // Method "<init>":(Ljava/lang/String;)V
      20: athrow
      21: return
}
