Compiled from "ScriptRule.java"
public class org.apache.dubbo.rpc.cluster.router.script.config.model.ScriptRule extends org.apache.dubbo.rpc.cluster.router.AbstractRouterRule {
  private static final java.lang.String TYPE_KEY;

  private static final java.lang.String SCRIPT_KEY;

  private java.lang.String type;

  private java.lang.String script;

  public org.apache.dubbo.rpc.cluster.router.script.config.model.ScriptRule();
    Code:
       0: aload_0
       1: invokespecial #1                  // Method org/apache/dubbo/rpc/cluster/router/AbstractRouterRule."<init>":()V
       4: return

  public static org.apache.dubbo.rpc.cluster.router.script.config.model.ScriptRule parse(java.lang.String);
    Code:
       0: new           #2                  // class org/yaml/snakeyaml/Yaml
       3: dup
       4: new           #3                  // class org/yaml/snakeyaml/constructor/SafeConstructor
       7: dup
       8: new           #4                  // class org/yaml/snakeyaml/LoaderOptions
      11: dup
      12: invokespecial #5                  // Method org/yaml/snakeyaml/LoaderOptions."<init>":()V
      15: invokespecial #6                  // Method org/yaml/snakeyaml/constructor/SafeConstructor."<init>":(Lorg/yaml/snakeyaml/LoaderOptions;)V
      18: invokespecial #7                  // Method org/yaml/snakeyaml/Yaml."<init>":(Lorg/yaml/snakeyaml/constructor/BaseConstructor;)V
      21: astore_1
      22: aload_1
      23: aload_0
      24: invokevirtual #8                  // Method org/yaml/snakeyaml/Yaml.load:(Ljava/lang/String;)Ljava/lang/Object;
      27: checkcast     #9                  // class java/util/Map
      30: astore_2
      31: new           #10                 // class org/apache/dubbo/rpc/cluster/router/script/config/model/ScriptRule
      34: dup
      35: invokespecial #11                 // Method "<init>":()V
      38: astore_3
      39: aload_3
      40: aload_2
      41: invokevirtual #12                 // Method parseFromMap0:(Ljava/util/Map;)V
      44: aload_3
      45: aload_0
      46: invokevirtual #13                 // Method setRawRule:(Ljava/lang/String;)V
      49: aload_2
      50: ldc           #14                 // String type
      52: invokeinterface #15,  2           // InterfaceMethod java/util/Map.get:(Ljava/lang/Object;)Ljava/lang/Object;
      57: astore        4
      59: aload         4
      61: ifnull        73
      64: aload_3
      65: aload         4
      67: checkcast     #16                 // class java/lang/String
      70: invokevirtual #17                 // Method setType:(Ljava/lang/String;)V
      73: aload_2
      74: ldc           #18                 // String script
      76: invokeinterface #15,  2           // InterfaceMethod java/util/Map.get:(Ljava/lang/Object;)Ljava/lang/Object;
      81: astore        5
      83: aload         5
      85: ifnull        100
      88: aload_3
      89: aload         5
      91: checkcast     #16                 // class java/lang/String
      94: invokevirtual #19                 // Method setScript:(Ljava/lang/String;)V
      97: goto          105
     100: aload_3
     101: iconst_0
     102: invokevirtual #20                 // Method setValid:(Z)V
     105: aload_3
     106: areturn

  public java.lang.String getType();
    Code:
       0: aload_0
       1: getfield      #21                 // Field type:Ljava/lang/String;
       4: areturn

  public void setType(java.lang.String);
    Code:
       0: aload_0
       1: aload_1
       2: putfield      #21                 // Field type:Ljava/lang/String;
       5: return

  public java.lang.String getScript();
    Code:
       0: aload_0
       1: getfield      #22                 // Field script:Ljava/lang/String;
       4: areturn

  public void setScript(java.lang.String);
    Code:
       0: aload_0
       1: aload_1
       2: putfield      #22                 // Field script:Ljava/lang/String;
       5: return
}
