Compiled from "TripleWrapper.java"
public final class org.apache.dubbo.triple.TripleWrapper {
  private static final com.google.protobuf.Descriptors$Descriptor internal_static_org_apache_dubbo_triple_TripleRequestWrapper_descriptor;

  private static final com.google.protobuf.GeneratedMessageV3$FieldAccessorTable internal_static_org_apache_dubbo_triple_TripleRequestWrapper_fieldAccessorTable;

  private static final com.google.protobuf.Descriptors$Descriptor internal_static_org_apache_dubbo_triple_TripleResponseWrapper_descriptor;

  private static final com.google.protobuf.GeneratedMessageV3$FieldAccessorTable internal_static_org_apache_dubbo_triple_TripleResponseWrapper_fieldAccessorTable;

  private static final com.google.protobuf.Descriptors$Descriptor internal_static_org_apache_dubbo_triple_TripleExceptionWrapper_descriptor;

  private static final com.google.protobuf.GeneratedMessageV3$FieldAccessorTable internal_static_org_apache_dubbo_triple_TripleExceptionWrapper_fieldAccessorTable;

  private static com.google.protobuf.Descriptors$FileDescriptor descriptor;

  private org.apache.dubbo.triple.TripleWrapper();
    Code:
       0: aload_0
       1: invokespecial #7                  // Method java/lang/Object."<init>":()V
       4: return

  public static void registerAllExtensions(com.google.protobuf.ExtensionRegistryLite);
    Code:
       0: return

  public static void registerAllExtensions(com.google.protobuf.ExtensionRegistry);
    Code:
       0: aload_0
       1: invokestatic  #8                  // Method registerAllExtensions:(Lcom/google/protobuf/ExtensionRegistryLite;)V
       4: return

  public static com.google.protobuf.Descriptors$FileDescriptor getDescriptor();
    Code:
       0: getstatic     #9                  // Field descriptor:Lcom/google/protobuf/Descriptors$FileDescriptor;
       3: areturn

  static com.google.protobuf.Descriptors$Descriptor access$000();
    Code:
       0: getstatic     #6                  // Field internal_static_org_apache_dubbo_triple_TripleRequestWrapper_descriptor:Lcom/google/protobuf/Descriptors$Descriptor;
       3: areturn

  static com.google.protobuf.GeneratedMessageV3$FieldAccessorTable access$100();
    Code:
       0: getstatic     #5                  // Field internal_static_org_apache_dubbo_triple_TripleRequestWrapper_fieldAccessorTable:Lcom/google/protobuf/GeneratedMessageV3$FieldAccessorTable;
       3: areturn

  static com.google.protobuf.Descriptors$Descriptor access$1000();
    Code:
       0: getstatic     #4                  // Field internal_static_org_apache_dubbo_triple_TripleResponseWrapper_descriptor:Lcom/google/protobuf/Descriptors$Descriptor;
       3: areturn

  static com.google.protobuf.GeneratedMessageV3$FieldAccessorTable access$1100();
    Code:
       0: getstatic     #3                  // Field internal_static_org_apache_dubbo_triple_TripleResponseWrapper_fieldAccessorTable:Lcom/google/protobuf/GeneratedMessageV3$FieldAccessorTable;
       3: areturn

  static com.google.protobuf.Descriptors$Descriptor access$2000();
    Code:
       0: getstatic     #2                  // Field internal_static_org_apache_dubbo_triple_TripleExceptionWrapper_descriptor:Lcom/google/protobuf/Descriptors$Descriptor;
       3: areturn

  static com.google.protobuf.GeneratedMessageV3$FieldAccessorTable access$2100();
    Code:
       0: getstatic     #1                  // Field internal_static_org_apache_dubbo_triple_TripleExceptionWrapper_fieldAccessorTable:Lcom/google/protobuf/GeneratedMessageV3$FieldAccessorTable;
       3: areturn

  static {};
    Code:
       0: iconst_1
       1: anewarray     #10                 // class java/lang/String
       4: dup
       5: iconst_0
       6: ldc           #11                 // String \n\u0014triple_wrapper.proto\u0012\u0017org.apache.dubbo.triple\"M\n\u0014TripleRequestWrapper\u0012\u0015\n\rserializeType\u0018\u0001 \u0001(\t\u0012\f\n\u0004args\u0018\u0002 \u0003(\f\u0012\u0010\n\bargTypes\u0018\u0003 \u0003(\t\"J\n\u0015TripleResponseWrapper\u0012\u0015\n\rserializeType\u0018\u0001 \u0001(\t\u0012\f\n\u0004data\u0018\u0002 \u0001(\f\u0012\f\n\u0004type\u0018\u0003 \u0001(\t\"b\n\u0016TripleExceptionWrapper\u0012\u0010\n\blanguage\u0018\u0001 \u0001(\t\u0012\u0015\n\rserialization\u0018\u0002 \u0001(\t\u0012\u0011\n\tclassName\u0018\u0003 \u0001(\t\u0012\f\n\u0004data\u0018\u0004 \u0001(\fb\u0006proto3
       8: aastore
       9: astore_0
      10: aload_0
      11: iconst_0
      12: anewarray     #12                 // class com/google/protobuf/Descriptors$FileDescriptor
      15: invokestatic  #13                 // Method com/google/protobuf/Descriptors$FileDescriptor.internalBuildGeneratedFileFrom:([Ljava/lang/String;[Lcom/google/protobuf/Descriptors$FileDescriptor;)Lcom/google/protobuf/Descriptors$FileDescriptor;
      18: putstatic     #9                  // Field descriptor:Lcom/google/protobuf/Descriptors$FileDescriptor;
      21: invokestatic  #14                 // Method getDescriptor:()Lcom/google/protobuf/Descriptors$FileDescriptor;
      24: invokevirtual #15                 // Method com/google/protobuf/Descriptors$FileDescriptor.getMessageTypes:()Ljava/util/List;
      27: iconst_0
      28: invokeinterface #16,  2           // InterfaceMethod java/util/List.get:(I)Ljava/lang/Object;
      33: checkcast     #17                 // class com/google/protobuf/Descriptors$Descriptor
      36: putstatic     #6                  // Field internal_static_org_apache_dubbo_triple_TripleRequestWrapper_descriptor:Lcom/google/protobuf/Descriptors$Descriptor;
      39: new           #18                 // class com/google/protobuf/GeneratedMessageV3$FieldAccessorTable
      42: dup
      43: getstatic     #6                  // Field internal_static_org_apache_dubbo_triple_TripleRequestWrapper_descriptor:Lcom/google/protobuf/Descriptors$Descriptor;
      46: iconst_3
      47: anewarray     #10                 // class java/lang/String
      50: dup
      51: iconst_0
      52: ldc           #19                 // String SerializeType
      54: aastore
      55: dup
      56: iconst_1
      57: ldc           #20                 // String Args
      59: aastore
      60: dup
      61: iconst_2
      62: ldc           #21                 // String ArgTypes
      64: aastore
      65: invokespecial #22                 // Method com/google/protobuf/GeneratedMessageV3$FieldAccessorTable."<init>":(Lcom/google/protobuf/Descriptors$Descriptor;[Ljava/lang/String;)V
      68: putstatic     #5                  // Field internal_static_org_apache_dubbo_triple_TripleRequestWrapper_fieldAccessorTable:Lcom/google/protobuf/GeneratedMessageV3$FieldAccessorTable;
      71: invokestatic  #14                 // Method getDescriptor:()Lcom/google/protobuf/Descriptors$FileDescriptor;
      74: invokevirtual #15                 // Method com/google/protobuf/Descriptors$FileDescriptor.getMessageTypes:()Ljava/util/List;
      77: iconst_1
      78: invokeinterface #16,  2           // InterfaceMethod java/util/List.get:(I)Ljava/lang/Object;
      83: checkcast     #17                 // class com/google/protobuf/Descriptors$Descriptor
      86: putstatic     #4                  // Field internal_static_org_apache_dubbo_triple_TripleResponseWrapper_descriptor:Lcom/google/protobuf/Descriptors$Descriptor;
      89: new           #18                 // class com/google/protobuf/GeneratedMessageV3$FieldAccessorTable
      92: dup
      93: getstatic     #4                  // Field internal_static_org_apache_dubbo_triple_TripleResponseWrapper_descriptor:Lcom/google/protobuf/Descriptors$Descriptor;
      96: iconst_3
      97: anewarray     #10                 // class java/lang/String
     100: dup
     101: iconst_0
     102: ldc           #19                 // String SerializeType
     104: aastore
     105: dup
     106: iconst_1
     107: ldc           #23                 // String Data
     109: aastore
     110: dup
     111: iconst_2
     112: ldc           #24                 // String Type
     114: aastore
     115: invokespecial #22                 // Method com/google/protobuf/GeneratedMessageV3$FieldAccessorTable."<init>":(Lcom/google/protobuf/Descriptors$Descriptor;[Ljava/lang/String;)V
     118: putstatic     #3                  // Field internal_static_org_apache_dubbo_triple_TripleResponseWrapper_fieldAccessorTable:Lcom/google/protobuf/GeneratedMessageV3$FieldAccessorTable;
     121: invokestatic  #14                 // Method getDescriptor:()Lcom/google/protobuf/Descriptors$FileDescriptor;
     124: invokevirtual #15                 // Method com/google/protobuf/Descriptors$FileDescriptor.getMessageTypes:()Ljava/util/List;
     127: iconst_2
     128: invokeinterface #16,  2           // InterfaceMethod java/util/List.get:(I)Ljava/lang/Object;
     133: checkcast     #17                 // class com/google/protobuf/Descriptors$Descriptor
     136: putstatic     #2                  // Field internal_static_org_apache_dubbo_triple_TripleExceptionWrapper_descriptor:Lcom/google/protobuf/Descriptors$Descriptor;
     139: new           #18                 // class com/google/protobuf/GeneratedMessageV3$FieldAccessorTable
     142: dup
     143: getstatic     #2                  // Field internal_static_org_apache_dubbo_triple_TripleExceptionWrapper_descriptor:Lcom/google/protobuf/Descriptors$Descriptor;
     146: iconst_4
     147: anewarray     #10                 // class java/lang/String
     150: dup
     151: iconst_0
     152: ldc           #25                 // String Language
     154: aastore
     155: dup
     156: iconst_1
     157: ldc           #26                 // String Serialization
     159: aastore
     160: dup
     161: iconst_2
     162: ldc           #27                 // String ClassName
     164: aastore
     165: dup
     166: iconst_3
     167: ldc           #23                 // String Data
     169: aastore
     170: invokespecial #22                 // Method com/google/protobuf/GeneratedMessageV3$FieldAccessorTable."<init>":(Lcom/google/protobuf/Descriptors$Descriptor;[Ljava/lang/String;)V
     173: putstatic     #1                  // Field internal_static_org_apache_dubbo_triple_TripleExceptionWrapper_fieldAccessorTable:Lcom/google/protobuf/GeneratedMessageV3$FieldAccessorTable;
     176: return
}
