Compiled from "TripleWrapper.java"
public final class org.apache.dubbo.triple.TripleWrapper$TripleRequestWrapper extends com.google.protobuf.GeneratedMessageV3 implements org.apache.dubbo.triple.TripleWrapper$TripleRequestWrapperOrBuilder {
  private static final long serialVersionUID;

  public static final int SERIALIZETYPE_FIELD_NUMBER;

  private volatile java.lang.Object serializeType_;

  public static final int ARGS_FIELD_NUMBER;

  private java.util.List<com.google.protobuf.ByteString> args_;

  public static final int ARGTYPES_FIELD_NUMBER;

  private com.google.protobuf.LazyStringArrayList argTypes_;

  private byte memoizedIsInitialized;

  private static final org.apache.dubbo.triple.TripleWrapper$TripleRequestWrapper DEFAULT_INSTANCE;

  private static final com.google.protobuf.Parser<org.apache.dubbo.triple.TripleWrapper$TripleRequestWrapper> PARSER;

  private org.apache.dubbo.triple.TripleWrapper$TripleRequestWrapper(com.google.protobuf.GeneratedMessageV3$Builder<?>);
    Code:
       0: aload_0
       1: aload_1
       2: invokespecial #6                  // Method com/google/protobuf/GeneratedMessageV3."<init>":(Lcom/google/protobuf/GeneratedMessageV3$Builder;)V
       5: aload_0
       6: ldc           #7                  // String
       8: putfield      #3                  // Field serializeType_:Ljava/lang/Object;
      11: aload_0
      12: invokestatic  #8                  // Method com/google/protobuf/LazyStringArrayList.emptyList:()Lcom/google/protobuf/LazyStringArrayList;
      15: putfield      #2                  // Field argTypes_:Lcom/google/protobuf/LazyStringArrayList;
      18: aload_0
      19: iconst_m1
      20: putfield      #9                  // Field memoizedIsInitialized:B
      23: return

  private org.apache.dubbo.triple.TripleWrapper$TripleRequestWrapper();
    Code:
       0: aload_0
       1: invokespecial #10                 // Method com/google/protobuf/GeneratedMessageV3."<init>":()V
       4: aload_0
       5: ldc           #7                  // String
       7: putfield      #3                  // Field serializeType_:Ljava/lang/Object;
      10: aload_0
      11: invokestatic  #8                  // Method com/google/protobuf/LazyStringArrayList.emptyList:()Lcom/google/protobuf/LazyStringArrayList;
      14: putfield      #2                  // Field argTypes_:Lcom/google/protobuf/LazyStringArrayList;
      17: aload_0
      18: iconst_m1
      19: putfield      #9                  // Field memoizedIsInitialized:B
      22: aload_0
      23: ldc           #7                  // String
      25: putfield      #3                  // Field serializeType_:Ljava/lang/Object;
      28: aload_0
      29: invokestatic  #11                 // Method java/util/Collections.emptyList:()Ljava/util/List;
      32: putfield      #4                  // Field args_:Ljava/util/List;
      35: aload_0
      36: invokestatic  #8                  // Method com/google/protobuf/LazyStringArrayList.emptyList:()Lcom/google/protobuf/LazyStringArrayList;
      39: putfield      #2                  // Field argTypes_:Lcom/google/protobuf/LazyStringArrayList;
      42: return

  protected java.lang.Object newInstance(com.google.protobuf.GeneratedMessageV3$UnusedPrivateParameter);
    Code:
       0: new           #12                 // class org/apache/dubbo/triple/TripleWrapper$TripleRequestWrapper
       3: dup
       4: invokespecial #13                 // Method "<init>":()V
       7: areturn

  public static final com.google.protobuf.Descriptors$Descriptor getDescriptor();
    Code:
       0: invokestatic  #14                 // Method org/apache/dubbo/triple/TripleWrapper.access$000:()Lcom/google/protobuf/Descriptors$Descriptor;
       3: areturn

  protected com.google.protobuf.GeneratedMessageV3$FieldAccessorTable internalGetFieldAccessorTable();
    Code:
       0: invokestatic  #15                 // Method org/apache/dubbo/triple/TripleWrapper.access$100:()Lcom/google/protobuf/GeneratedMessageV3$FieldAccessorTable;
       3: ldc           #12                 // class org/apache/dubbo/triple/TripleWrapper$TripleRequestWrapper
       5: ldc           #16                 // class org/apache/dubbo/triple/TripleWrapper$TripleRequestWrapper$Builder
       7: invokevirtual #17                 // Method com/google/protobuf/GeneratedMessageV3$FieldAccessorTable.ensureFieldAccessorsInitialized:(Ljava/lang/Class;Ljava/lang/Class;)Lcom/google/protobuf/GeneratedMessageV3$FieldAccessorTable;
      10: areturn

  public java.lang.String getSerializeType();
    Code:
       0: aload_0
       1: getfield      #3                  // Field serializeType_:Ljava/lang/Object;
       4: astore_1
       5: aload_1
       6: instanceof    #18                 // class java/lang/String
       9: ifeq          17
      12: aload_1
      13: checkcast     #18                 // class java/lang/String
      16: areturn
      17: aload_1
      18: checkcast     #19                 // class com/google/protobuf/ByteString
      21: astore_2
      22: aload_2
      23: invokevirtual #20                 // Method com/google/protobuf/ByteString.toStringUtf8:()Ljava/lang/String;
      26: astore_3
      27: aload_0
      28: aload_3
      29: putfield      #3                  // Field serializeType_:Ljava/lang/Object;
      32: aload_3
      33: areturn

  public com.google.protobuf.ByteString getSerializeTypeBytes();
    Code:
       0: aload_0
       1: getfield      #3                  // Field serializeType_:Ljava/lang/Object;
       4: astore_1
       5: aload_1
       6: instanceof    #18                 // class java/lang/String
       9: ifeq          27
      12: aload_1
      13: checkcast     #18                 // class java/lang/String
      16: invokestatic  #21                 // Method com/google/protobuf/ByteString.copyFromUtf8:(Ljava/lang/String;)Lcom/google/protobuf/ByteString;
      19: astore_2
      20: aload_0
      21: aload_2
      22: putfield      #3                  // Field serializeType_:Ljava/lang/Object;
      25: aload_2
      26: areturn
      27: aload_1
      28: checkcast     #19                 // class com/google/protobuf/ByteString
      31: areturn

  public java.util.List<com.google.protobuf.ByteString> getArgsList();
    Code:
       0: aload_0
       1: getfield      #4                  // Field args_:Ljava/util/List;
       4: areturn

  public int getArgsCount();
    Code:
       0: aload_0
       1: getfield      #4                  // Field args_:Ljava/util/List;
       4: invokeinterface #22,  1           // InterfaceMethod java/util/List.size:()I
       9: ireturn

  public com.google.protobuf.ByteString getArgs(int);
    Code:
       0: aload_0
       1: getfield      #4                  // Field args_:Ljava/util/List;
       4: iload_1
       5: invokeinterface #23,  2           // InterfaceMethod java/util/List.get:(I)Ljava/lang/Object;
      10: checkcast     #19                 // class com/google/protobuf/ByteString
      13: areturn

  public com.google.protobuf.ProtocolStringList getArgTypesList();
    Code:
       0: aload_0
       1: getfield      #2                  // Field argTypes_:Lcom/google/protobuf/LazyStringArrayList;
       4: areturn

  public int getArgTypesCount();
    Code:
       0: aload_0
       1: getfield      #2                  // Field argTypes_:Lcom/google/protobuf/LazyStringArrayList;
       4: invokevirtual #24                 // Method com/google/protobuf/LazyStringArrayList.size:()I
       7: ireturn

  public java.lang.String getArgTypes(int);
    Code:
       0: aload_0
       1: getfield      #2                  // Field argTypes_:Lcom/google/protobuf/LazyStringArrayList;
       4: iload_1
       5: invokevirtual #25                 // Method com/google/protobuf/LazyStringArrayList.get:(I)Ljava/lang/String;
       8: areturn

  public com.google.protobuf.ByteString getArgTypesBytes(int);
    Code:
       0: aload_0
       1: getfield      #2                  // Field argTypes_:Lcom/google/protobuf/LazyStringArrayList;
       4: iload_1
       5: invokevirtual #26                 // Method com/google/protobuf/LazyStringArrayList.getByteString:(I)Lcom/google/protobuf/ByteString;
       8: areturn

  public final boolean isInitialized();
    Code:
       0: aload_0
       1: getfield      #9                  // Field memoizedIsInitialized:B
       4: istore_1
       5: iload_1
       6: iconst_1
       7: if_icmpne     12
      10: iconst_1
      11: ireturn
      12: iload_1
      13: ifne          18
      16: iconst_0
      17: ireturn
      18: aload_0
      19: iconst_1
      20: putfield      #9                  // Field memoizedIsInitialized:B
      23: iconst_1
      24: ireturn

  public void writeTo(com.google.protobuf.CodedOutputStream) throws java.io.IOException;
    Code:
       0: aload_0
       1: getfield      #3                  // Field serializeType_:Ljava/lang/Object;
       4: invokestatic  #27                 // Method com/google/protobuf/GeneratedMessageV3.isStringEmpty:(Ljava/lang/Object;)Z
       7: ifne          19
      10: aload_1
      11: iconst_1
      12: aload_0
      13: getfield      #3                  // Field serializeType_:Ljava/lang/Object;
      16: invokestatic  #28                 // Method com/google/protobuf/GeneratedMessageV3.writeString:(Lcom/google/protobuf/CodedOutputStream;ILjava/lang/Object;)V
      19: iconst_0
      20: istore_2
      21: iload_2
      22: aload_0
      23: getfield      #4                  // Field args_:Ljava/util/List;
      26: invokeinterface #22,  1           // InterfaceMethod java/util/List.size:()I
      31: if_icmpge     58
      34: aload_1
      35: iconst_2
      36: aload_0
      37: getfield      #4                  // Field args_:Ljava/util/List;
      40: iload_2
      41: invokeinterface #23,  2           // InterfaceMethod java/util/List.get:(I)Ljava/lang/Object;
      46: checkcast     #19                 // class com/google/protobuf/ByteString
      49: invokevirtual #29                 // Method com/google/protobuf/CodedOutputStream.writeBytes:(ILcom/google/protobuf/ByteString;)V
      52: iinc          2, 1
      55: goto          21
      58: iconst_0
      59: istore_2
      60: iload_2
      61: aload_0
      62: getfield      #2                  // Field argTypes_:Lcom/google/protobuf/LazyStringArrayList;
      65: invokevirtual #24                 // Method com/google/protobuf/LazyStringArrayList.size:()I
      68: if_icmpge     90
      71: aload_1
      72: iconst_3
      73: aload_0
      74: getfield      #2                  // Field argTypes_:Lcom/google/protobuf/LazyStringArrayList;
      77: iload_2
      78: invokevirtual #30                 // Method com/google/protobuf/LazyStringArrayList.getRaw:(I)Ljava/lang/Object;
      81: invokestatic  #28                 // Method com/google/protobuf/GeneratedMessageV3.writeString:(Lcom/google/protobuf/CodedOutputStream;ILjava/lang/Object;)V
      84: iinc          2, 1
      87: goto          60
      90: aload_0
      91: invokevirtual #31                 // Method getUnknownFields:()Lcom/google/protobuf/UnknownFieldSet;
      94: aload_1
      95: invokevirtual #32                 // Method com/google/protobuf/UnknownFieldSet.writeTo:(Lcom/google/protobuf/CodedOutputStream;)V
      98: return

  public int getSerializedSize();
    Code:
       0: aload_0
       1: getfield      #33                 // Field memoizedSize:I
       4: istore_1
       5: iload_1
       6: iconst_m1
       7: if_icmpeq     12
      10: iload_1
      11: ireturn
      12: iconst_0
      13: istore_1
      14: aload_0
      15: getfield      #3                  // Field serializeType_:Ljava/lang/Object;
      18: invokestatic  #27                 // Method com/google/protobuf/GeneratedMessageV3.isStringEmpty:(Ljava/lang/Object;)Z
      21: ifne          35
      24: iload_1
      25: iconst_1
      26: aload_0
      27: getfield      #3                  // Field serializeType_:Ljava/lang/Object;
      30: invokestatic  #34                 // Method com/google/protobuf/GeneratedMessageV3.computeStringSize:(ILjava/lang/Object;)I
      33: iadd
      34: istore_1
      35: iconst_0
      36: istore_2
      37: iconst_0
      38: istore_3
      39: iload_3
      40: aload_0
      41: getfield      #4                  // Field args_:Ljava/util/List;
      44: invokeinterface #22,  1           // InterfaceMethod java/util/List.size:()I
      49: if_icmpge     77
      52: iload_2
      53: aload_0
      54: getfield      #4                  // Field args_:Ljava/util/List;
      57: iload_3
      58: invokeinterface #23,  2           // InterfaceMethod java/util/List.get:(I)Ljava/lang/Object;
      63: checkcast     #19                 // class com/google/protobuf/ByteString
      66: invokestatic  #35                 // Method com/google/protobuf/CodedOutputStream.computeBytesSizeNoTag:(Lcom/google/protobuf/ByteString;)I
      69: iadd
      70: istore_2
      71: iinc          3, 1
      74: goto          39
      77: iload_1
      78: iload_2
      79: iadd
      80: istore_1
      81: iload_1
      82: iconst_1
      83: aload_0
      84: invokevirtual #36                 // Method getArgsList:()Ljava/util/List;
      87: invokeinterface #22,  1           // InterfaceMethod java/util/List.size:()I
      92: imul
      93: iadd
      94: istore_1
      95: iconst_0
      96: istore_2
      97: iconst_0
      98: istore_3
      99: iload_3
     100: aload_0
     101: getfield      #2                  // Field argTypes_:Lcom/google/protobuf/LazyStringArrayList;
     104: invokevirtual #24                 // Method com/google/protobuf/LazyStringArrayList.size:()I
     107: if_icmpge     130
     110: iload_2
     111: aload_0
     112: getfield      #2                  // Field argTypes_:Lcom/google/protobuf/LazyStringArrayList;
     115: iload_3
     116: invokevirtual #30                 // Method com/google/protobuf/LazyStringArrayList.getRaw:(I)Ljava/lang/Object;
     119: invokestatic  #37                 // Method computeStringSizeNoTag:(Ljava/lang/Object;)I
     122: iadd
     123: istore_2
     124: iinc          3, 1
     127: goto          99
     130: iload_1
     131: iload_2
     132: iadd
     133: istore_1
     134: iload_1
     135: iconst_1
     136: aload_0
     137: invokevirtual #38                 // Method getArgTypesList:()Lcom/google/protobuf/ProtocolStringList;
     140: invokeinterface #39,  1           // InterfaceMethod com/google/protobuf/ProtocolStringList.size:()I
     145: imul
     146: iadd
     147: istore_1
     148: iload_1
     149: aload_0
     150: invokevirtual #31                 // Method getUnknownFields:()Lcom/google/protobuf/UnknownFieldSet;
     153: invokevirtual #40                 // Method com/google/protobuf/UnknownFieldSet.getSerializedSize:()I
     156: iadd
     157: istore_1
     158: aload_0
     159: iload_1
     160: putfield      #33                 // Field memoizedSize:I
     163: iload_1
     164: ireturn

  public boolean equals(java.lang.Object);
    Code:
       0: aload_1
       1: aload_0
       2: if_acmpne     7
       5: iconst_1
       6: ireturn
       7: aload_1
       8: instanceof    #12                 // class org/apache/dubbo/triple/TripleWrapper$TripleRequestWrapper
      11: ifne          20
      14: aload_0
      15: aload_1
      16: invokespecial #41                 // Method com/google/protobuf/GeneratedMessageV3.equals:(Ljava/lang/Object;)Z
      19: ireturn
      20: aload_1
      21: checkcast     #12                 // class org/apache/dubbo/triple/TripleWrapper$TripleRequestWrapper
      24: astore_2
      25: aload_0
      26: invokevirtual #42                 // Method getSerializeType:()Ljava/lang/String;
      29: aload_2
      30: invokevirtual #42                 // Method getSerializeType:()Ljava/lang/String;
      33: invokevirtual #43                 // Method java/lang/String.equals:(Ljava/lang/Object;)Z
      36: ifne          41
      39: iconst_0
      40: ireturn
      41: aload_0
      42: invokevirtual #36                 // Method getArgsList:()Ljava/util/List;
      45: aload_2
      46: invokevirtual #36                 // Method getArgsList:()Ljava/util/List;
      49: invokeinterface #44,  2           // InterfaceMethod java/util/List.equals:(Ljava/lang/Object;)Z
      54: ifne          59
      57: iconst_0
      58: ireturn
      59: aload_0
      60: invokevirtual #38                 // Method getArgTypesList:()Lcom/google/protobuf/ProtocolStringList;
      63: aload_2
      64: invokevirtual #38                 // Method getArgTypesList:()Lcom/google/protobuf/ProtocolStringList;
      67: invokevirtual #45                 // Method java/lang/Object.equals:(Ljava/lang/Object;)Z
      70: ifne          75
      73: iconst_0
      74: ireturn
      75: aload_0
      76: invokevirtual #31                 // Method getUnknownFields:()Lcom/google/protobuf/UnknownFieldSet;
      79: aload_2
      80: invokevirtual #31                 // Method getUnknownFields:()Lcom/google/protobuf/UnknownFieldSet;
      83: invokevirtual #46                 // Method com/google/protobuf/UnknownFieldSet.equals:(Ljava/lang/Object;)Z
      86: ifne          91
      89: iconst_0
      90: ireturn
      91: iconst_1
      92: ireturn

  public int hashCode();
    Code:
       0: aload_0
       1: getfield      #47                 // Field memoizedHashCode:I
       4: ifeq          12
       7: aload_0
       8: getfield      #47                 // Field memoizedHashCode:I
      11: ireturn
      12: bipush        41
      14: istore_1
      15: bipush        19
      17: iload_1
      18: imul
      19: invokestatic  #48                 // Method getDescriptor:()Lcom/google/protobuf/Descriptors$Descriptor;
      22: invokevirtual #49                 // Method java/lang/Object.hashCode:()I
      25: iadd
      26: istore_1
      27: bipush        37
      29: iload_1
      30: imul
      31: iconst_1
      32: iadd
      33: istore_1
      34: bipush        53
      36: iload_1
      37: imul
      38: aload_0
      39: invokevirtual #42                 // Method getSerializeType:()Ljava/lang/String;
      42: invokevirtual #50                 // Method java/lang/String.hashCode:()I
      45: iadd
      46: istore_1
      47: aload_0
      48: invokevirtual #51                 // Method getArgsCount:()I
      51: ifle          76
      54: bipush        37
      56: iload_1
      57: imul
      58: iconst_2
      59: iadd
      60: istore_1
      61: bipush        53
      63: iload_1
      64: imul
      65: aload_0
      66: invokevirtual #36                 // Method getArgsList:()Ljava/util/List;
      69: invokeinterface #52,  1           // InterfaceMethod java/util/List.hashCode:()I
      74: iadd
      75: istore_1
      76: aload_0
      77: invokevirtual #53                 // Method getArgTypesCount:()I
      80: ifle          103
      83: bipush        37
      85: iload_1
      86: imul
      87: iconst_3
      88: iadd
      89: istore_1
      90: bipush        53
      92: iload_1
      93: imul
      94: aload_0
      95: invokevirtual #38                 // Method getArgTypesList:()Lcom/google/protobuf/ProtocolStringList;
      98: invokevirtual #49                 // Method java/lang/Object.hashCode:()I
     101: iadd
     102: istore_1
     103: bipush        29
     105: iload_1
     106: imul
     107: aload_0
     108: invokevirtual #31                 // Method getUnknownFields:()Lcom/google/protobuf/UnknownFieldSet;
     111: invokevirtual #54                 // Method com/google/protobuf/UnknownFieldSet.hashCode:()I
     114: iadd
     115: istore_1
     116: aload_0
     117: iload_1
     118: putfield      #47                 // Field memoizedHashCode:I
     121: iload_1
     122: ireturn

  public static org.apache.dubbo.triple.TripleWrapper$TripleRequestWrapper parseFrom(java.nio.ByteBuffer) throws com.google.protobuf.InvalidProtocolBufferException;
    Code:
       0: getstatic     #55                 // Field PARSER:Lcom/google/protobuf/Parser;
       3: aload_0
       4: invokeinterface #56,  2           // InterfaceMethod com/google/protobuf/Parser.parseFrom:(Ljava/nio/ByteBuffer;)Ljava/lang/Object;
       9: checkcast     #12                 // class org/apache/dubbo/triple/TripleWrapper$TripleRequestWrapper
      12: areturn

  public static org.apache.dubbo.triple.TripleWrapper$TripleRequestWrapper parseFrom(java.nio.ByteBuffer, com.google.protobuf.ExtensionRegistryLite) throws com.google.protobuf.InvalidProtocolBufferException;
    Code:
       0: getstatic     #55                 // Field PARSER:Lcom/google/protobuf/Parser;
       3: aload_0
       4: aload_1
       5: invokeinterface #57,  3           // InterfaceMethod com/google/protobuf/Parser.parseFrom:(Ljava/nio/ByteBuffer;Lcom/google/protobuf/ExtensionRegistryLite;)Ljava/lang/Object;
      10: checkcast     #12                 // class org/apache/dubbo/triple/TripleWrapper$TripleRequestWrapper
      13: areturn

  public static org.apache.dubbo.triple.TripleWrapper$TripleRequestWrapper parseFrom(com.google.protobuf.ByteString) throws com.google.protobuf.InvalidProtocolBufferException;
    Code:
       0: getstatic     #55                 // Field PARSER:Lcom/google/protobuf/Parser;
       3: aload_0
       4: invokeinterface #58,  2           // InterfaceMethod com/google/protobuf/Parser.parseFrom:(Lcom/google/protobuf/ByteString;)Ljava/lang/Object;
       9: checkcast     #12                 // class org/apache/dubbo/triple/TripleWrapper$TripleRequestWrapper
      12: areturn

  public static org.apache.dubbo.triple.TripleWrapper$TripleRequestWrapper parseFrom(com.google.protobuf.ByteString, com.google.protobuf.ExtensionRegistryLite) throws com.google.protobuf.InvalidProtocolBufferException;
    Code:
       0: getstatic     #55                 // Field PARSER:Lcom/google/protobuf/Parser;
       3: aload_0
       4: aload_1
       5: invokeinterface #59,  3           // InterfaceMethod com/google/protobuf/Parser.parseFrom:(Lcom/google/protobuf/ByteString;Lcom/google/protobuf/ExtensionRegistryLite;)Ljava/lang/Object;
      10: checkcast     #12                 // class org/apache/dubbo/triple/TripleWrapper$TripleRequestWrapper
      13: areturn

  public static org.apache.dubbo.triple.TripleWrapper$TripleRequestWrapper parseFrom(byte[]) throws com.google.protobuf.InvalidProtocolBufferException;
    Code:
       0: getstatic     #55                 // Field PARSER:Lcom/google/protobuf/Parser;
       3: aload_0
       4: invokeinterface #60,  2           // InterfaceMethod com/google/protobuf/Parser.parseFrom:([B)Ljava/lang/Object;
       9: checkcast     #12                 // class org/apache/dubbo/triple/TripleWrapper$TripleRequestWrapper
      12: areturn

  public static org.apache.dubbo.triple.TripleWrapper$TripleRequestWrapper parseFrom(byte[], com.google.protobuf.ExtensionRegistryLite) throws com.google.protobuf.InvalidProtocolBufferException;
    Code:
       0: getstatic     #55                 // Field PARSER:Lcom/google/protobuf/Parser;
       3: aload_0
       4: aload_1
       5: invokeinterface #61,  3           // InterfaceMethod com/google/protobuf/Parser.parseFrom:([BLcom/google/protobuf/ExtensionRegistryLite;)Ljava/lang/Object;
      10: checkcast     #12                 // class org/apache/dubbo/triple/TripleWrapper$TripleRequestWrapper
      13: areturn

  public static org.apache.dubbo.triple.TripleWrapper$TripleRequestWrapper parseFrom(java.io.InputStream) throws java.io.IOException;
    Code:
       0: getstatic     #55                 // Field PARSER:Lcom/google/protobuf/Parser;
       3: aload_0
       4: invokestatic  #62                 // Method com/google/protobuf/GeneratedMessageV3.parseWithIOException:(Lcom/google/protobuf/Parser;Ljava/io/InputStream;)Lcom/google/protobuf/Message;
       7: checkcast     #12                 // class org/apache/dubbo/triple/TripleWrapper$TripleRequestWrapper
      10: areturn

  public static org.apache.dubbo.triple.TripleWrapper$TripleRequestWrapper parseFrom(java.io.InputStream, com.google.protobuf.ExtensionRegistryLite) throws java.io.IOException;
    Code:
       0: getstatic     #55                 // Field PARSER:Lcom/google/protobuf/Parser;
       3: aload_0
       4: aload_1
       5: invokestatic  #63                 // Method com/google/protobuf/GeneratedMessageV3.parseWithIOException:(Lcom/google/protobuf/Parser;Ljava/io/InputStream;Lcom/google/protobuf/ExtensionRegistryLite;)Lcom/google/protobuf/Message;
       8: checkcast     #12                 // class org/apache/dubbo/triple/TripleWrapper$TripleRequestWrapper
      11: areturn

  public static org.apache.dubbo.triple.TripleWrapper$TripleRequestWrapper parseDelimitedFrom(java.io.InputStream) throws java.io.IOException;
    Code:
       0: getstatic     #55                 // Field PARSER:Lcom/google/protobuf/Parser;
       3: aload_0
       4: invokestatic  #64                 // Method com/google/protobuf/GeneratedMessageV3.parseDelimitedWithIOException:(Lcom/google/protobuf/Parser;Ljava/io/InputStream;)Lcom/google/protobuf/Message;
       7: checkcast     #12                 // class org/apache/dubbo/triple/TripleWrapper$TripleRequestWrapper
      10: areturn

  public static org.apache.dubbo.triple.TripleWrapper$TripleRequestWrapper parseDelimitedFrom(java.io.InputStream, com.google.protobuf.ExtensionRegistryLite) throws java.io.IOException;
    Code:
       0: getstatic     #55                 // Field PARSER:Lcom/google/protobuf/Parser;
       3: aload_0
       4: aload_1
       5: invokestatic  #65                 // Method com/google/protobuf/GeneratedMessageV3.parseDelimitedWithIOException:(Lcom/google/protobuf/Parser;Ljava/io/InputStream;Lcom/google/protobuf/ExtensionRegistryLite;)Lcom/google/protobuf/Message;
       8: checkcast     #12                 // class org/apache/dubbo/triple/TripleWrapper$TripleRequestWrapper
      11: areturn

  public static org.apache.dubbo.triple.TripleWrapper$TripleRequestWrapper parseFrom(com.google.protobuf.CodedInputStream) throws java.io.IOException;
    Code:
       0: getstatic     #55                 // Field PARSER:Lcom/google/protobuf/Parser;
       3: aload_0
       4: invokestatic  #66                 // Method com/google/protobuf/GeneratedMessageV3.parseWithIOException:(Lcom/google/protobuf/Parser;Lcom/google/protobuf/CodedInputStream;)Lcom/google/protobuf/Message;
       7: checkcast     #12                 // class org/apache/dubbo/triple/TripleWrapper$TripleRequestWrapper
      10: areturn

  public static org.apache.dubbo.triple.TripleWrapper$TripleRequestWrapper parseFrom(com.google.protobuf.CodedInputStream, com.google.protobuf.ExtensionRegistryLite) throws java.io.IOException;
    Code:
       0: getstatic     #55                 // Field PARSER:Lcom/google/protobuf/Parser;
       3: aload_0
       4: aload_1
       5: invokestatic  #67                 // Method com/google/protobuf/GeneratedMessageV3.parseWithIOException:(Lcom/google/protobuf/Parser;Lcom/google/protobuf/CodedInputStream;Lcom/google/protobuf/ExtensionRegistryLite;)Lcom/google/protobuf/Message;
       8: checkcast     #12                 // class org/apache/dubbo/triple/TripleWrapper$TripleRequestWrapper
      11: areturn

  public org.apache.dubbo.triple.TripleWrapper$TripleRequestWrapper$Builder newBuilderForType();
    Code:
       0: invokestatic  #68                 // Method newBuilder:()Lorg/apache/dubbo/triple/TripleWrapper$TripleRequestWrapper$Builder;
       3: areturn

  public static org.apache.dubbo.triple.TripleWrapper$TripleRequestWrapper$Builder newBuilder();
    Code:
       0: getstatic     #69                 // Field DEFAULT_INSTANCE:Lorg/apache/dubbo/triple/TripleWrapper$TripleRequestWrapper;
       3: invokevirtual #70                 // Method toBuilder:()Lorg/apache/dubbo/triple/TripleWrapper$TripleRequestWrapper$Builder;
       6: areturn

  public static org.apache.dubbo.triple.TripleWrapper$TripleRequestWrapper$Builder newBuilder(org.apache.dubbo.triple.TripleWrapper$TripleRequestWrapper);
    Code:
       0: getstatic     #69                 // Field DEFAULT_INSTANCE:Lorg/apache/dubbo/triple/TripleWrapper$TripleRequestWrapper;
       3: invokevirtual #70                 // Method toBuilder:()Lorg/apache/dubbo/triple/TripleWrapper$TripleRequestWrapper$Builder;
       6: aload_0
       7: invokevirtual #71                 // Method org/apache/dubbo/triple/TripleWrapper$TripleRequestWrapper$Builder.mergeFrom:(Lorg/apache/dubbo/triple/TripleWrapper$TripleRequestWrapper;)Lorg/apache/dubbo/triple/TripleWrapper$TripleRequestWrapper$Builder;
      10: areturn

  public org.apache.dubbo.triple.TripleWrapper$TripleRequestWrapper$Builder toBuilder();
    Code:
       0: aload_0
       1: getstatic     #69                 // Field DEFAULT_INSTANCE:Lorg/apache/dubbo/triple/TripleWrapper$TripleRequestWrapper;
       4: if_acmpne     18
       7: new           #16                 // class org/apache/dubbo/triple/TripleWrapper$TripleRequestWrapper$Builder
      10: dup
      11: aconst_null
      12: invokespecial #72                 // Method org/apache/dubbo/triple/TripleWrapper$TripleRequestWrapper$Builder."<init>":(Lorg/apache/dubbo/triple/TripleWrapper$1;)V
      15: goto          30
      18: new           #16                 // class org/apache/dubbo/triple/TripleWrapper$TripleRequestWrapper$Builder
      21: dup
      22: aconst_null
      23: invokespecial #72                 // Method org/apache/dubbo/triple/TripleWrapper$TripleRequestWrapper$Builder."<init>":(Lorg/apache/dubbo/triple/TripleWrapper$1;)V
      26: aload_0
      27: invokevirtual #71                 // Method org/apache/dubbo/triple/TripleWrapper$TripleRequestWrapper$Builder.mergeFrom:(Lorg/apache/dubbo/triple/TripleWrapper$TripleRequestWrapper;)Lorg/apache/dubbo/triple/TripleWrapper$TripleRequestWrapper$Builder;
      30: areturn

  protected org.apache.dubbo.triple.TripleWrapper$TripleRequestWrapper$Builder newBuilderForType(com.google.protobuf.GeneratedMessageV3$BuilderParent);
    Code:
       0: new           #16                 // class org/apache/dubbo/triple/TripleWrapper$TripleRequestWrapper$Builder
       3: dup
       4: aload_1
       5: aconst_null
       6: invokespecial #73                 // Method org/apache/dubbo/triple/TripleWrapper$TripleRequestWrapper$Builder."<init>":(Lcom/google/protobuf/GeneratedMessageV3$BuilderParent;Lorg/apache/dubbo/triple/TripleWrapper$1;)V
       9: astore_2
      10: aload_2
      11: areturn

  public static org.apache.dubbo.triple.TripleWrapper$TripleRequestWrapper getDefaultInstance();
    Code:
       0: getstatic     #69                 // Field DEFAULT_INSTANCE:Lorg/apache/dubbo/triple/TripleWrapper$TripleRequestWrapper;
       3: areturn

  public static com.google.protobuf.Parser<org.apache.dubbo.triple.TripleWrapper$TripleRequestWrapper> parser();
    Code:
       0: getstatic     #55                 // Field PARSER:Lcom/google/protobuf/Parser;
       3: areturn

  public com.google.protobuf.Parser<org.apache.dubbo.triple.TripleWrapper$TripleRequestWrapper> getParserForType();
    Code:
       0: getstatic     #55                 // Field PARSER:Lcom/google/protobuf/Parser;
       3: areturn

  public org.apache.dubbo.triple.TripleWrapper$TripleRequestWrapper getDefaultInstanceForType();
    Code:
       0: getstatic     #69                 // Field DEFAULT_INSTANCE:Lorg/apache/dubbo/triple/TripleWrapper$TripleRequestWrapper;
       3: areturn

  protected com.google.protobuf.Message$Builder newBuilderForType(com.google.protobuf.GeneratedMessageV3$BuilderParent);
    Code:
       0: aload_0
       1: aload_1
       2: invokevirtual #74                 // Method newBuilderForType:(Lcom/google/protobuf/GeneratedMessageV3$BuilderParent;)Lorg/apache/dubbo/triple/TripleWrapper$TripleRequestWrapper$Builder;
       5: areturn

  public com.google.protobuf.Message$Builder toBuilder();
    Code:
       0: aload_0
       1: invokevirtual #70                 // Method toBuilder:()Lorg/apache/dubbo/triple/TripleWrapper$TripleRequestWrapper$Builder;
       4: areturn

  public com.google.protobuf.Message$Builder newBuilderForType();
    Code:
       0: aload_0
       1: invokevirtual #75                 // Method newBuilderForType:()Lorg/apache/dubbo/triple/TripleWrapper$TripleRequestWrapper$Builder;
       4: areturn

  public com.google.protobuf.MessageLite$Builder toBuilder();
    Code:
       0: aload_0
       1: invokevirtual #70                 // Method toBuilder:()Lorg/apache/dubbo/triple/TripleWrapper$TripleRequestWrapper$Builder;
       4: areturn

  public com.google.protobuf.MessageLite$Builder newBuilderForType();
    Code:
       0: aload_0
       1: invokevirtual #75                 // Method newBuilderForType:()Lorg/apache/dubbo/triple/TripleWrapper$TripleRequestWrapper$Builder;
       4: areturn

  public com.google.protobuf.MessageLite getDefaultInstanceForType();
    Code:
       0: aload_0
       1: invokevirtual #76                 // Method getDefaultInstanceForType:()Lorg/apache/dubbo/triple/TripleWrapper$TripleRequestWrapper;
       4: areturn

  public com.google.protobuf.Message getDefaultInstanceForType();
    Code:
       0: aload_0
       1: invokevirtual #76                 // Method getDefaultInstanceForType:()Lorg/apache/dubbo/triple/TripleWrapper$TripleRequestWrapper;
       4: areturn

  public java.util.List getArgTypesList();
    Code:
       0: aload_0
       1: invokevirtual #38                 // Method getArgTypesList:()Lcom/google/protobuf/ProtocolStringList;
       4: areturn

  org.apache.dubbo.triple.TripleWrapper$TripleRequestWrapper(com.google.protobuf.GeneratedMessageV3$Builder, org.apache.dubbo.triple.TripleWrapper$1);
    Code:
       0: aload_0
       1: aload_1
       2: invokespecial #5                  // Method "<init>":(Lcom/google/protobuf/GeneratedMessageV3$Builder;)V
       5: return

  static java.util.List access$502(org.apache.dubbo.triple.TripleWrapper$TripleRequestWrapper, java.util.List);
    Code:
       0: aload_0
       1: aload_1
       2: dup_x1
       3: putfield      #4                  // Field args_:Ljava/util/List;
       6: areturn

  static java.lang.Object access$602(org.apache.dubbo.triple.TripleWrapper$TripleRequestWrapper, java.lang.Object);
    Code:
       0: aload_0
       1: aload_1
       2: dup_x1
       3: putfield      #3                  // Field serializeType_:Ljava/lang/Object;
       6: areturn

  static com.google.protobuf.LazyStringArrayList access$702(org.apache.dubbo.triple.TripleWrapper$TripleRequestWrapper, com.google.protobuf.LazyStringArrayList);
    Code:
       0: aload_0
       1: aload_1
       2: dup_x1
       3: putfield      #2                  // Field argTypes_:Lcom/google/protobuf/LazyStringArrayList;
       6: areturn

  static java.lang.Object access$600(org.apache.dubbo.triple.TripleWrapper$TripleRequestWrapper);
    Code:
       0: aload_0
       1: getfield      #3                  // Field serializeType_:Ljava/lang/Object;
       4: areturn

  static java.util.List access$500(org.apache.dubbo.triple.TripleWrapper$TripleRequestWrapper);
    Code:
       0: aload_0
       1: getfield      #4                  // Field args_:Ljava/util/List;
       4: areturn

  static com.google.protobuf.LazyStringArrayList access$700(org.apache.dubbo.triple.TripleWrapper$TripleRequestWrapper);
    Code:
       0: aload_0
       1: getfield      #2                  // Field argTypes_:Lcom/google/protobuf/LazyStringArrayList;
       4: areturn

  static void access$800(com.google.protobuf.ByteString) throws java.lang.IllegalArgumentException;
    Code:
       0: aload_0
       1: invokestatic  #1                  // Method checkByteStringIsUtf8:(Lcom/google/protobuf/ByteString;)V
       4: return

  static void access$900(com.google.protobuf.ByteString) throws java.lang.IllegalArgumentException;
    Code:
       0: aload_0
       1: invokestatic  #1                  // Method checkByteStringIsUtf8:(Lcom/google/protobuf/ByteString;)V
       4: return

  static {};
    Code:
       0: new           #12                 // class org/apache/dubbo/triple/TripleWrapper$TripleRequestWrapper
       3: dup
       4: invokespecial #13                 // Method "<init>":()V
       7: putstatic     #69                 // Field DEFAULT_INSTANCE:Lorg/apache/dubbo/triple/TripleWrapper$TripleRequestWrapper;
      10: new           #77                 // class org/apache/dubbo/triple/TripleWrapper$TripleRequestWrapper$1
      13: dup
      14: invokespecial #78                 // Method org/apache/dubbo/triple/TripleWrapper$TripleRequestWrapper$1."<init>":()V
      17: putstatic     #55                 // Field PARSER:Lcom/google/protobuf/Parser;
      20: return
}
