Compiled from "TripleWrapper.java"
public final class org.apache.dubbo.triple.TripleWrapper$TripleRequestWrapper$Builder extends com.google.protobuf.GeneratedMessageV3$Builder<org.apache.dubbo.triple.TripleWrapper$TripleRequestWrapper$Builder> implements org.apache.dubbo.triple.TripleWrapper$TripleRequestWrapperOrBuilder {
  private int bitField0_;

  private java.lang.Object serializeType_;

  private java.util.List<com.google.protobuf.ByteString> args_;

  private com.google.protobuf.LazyStringArrayList argTypes_;

  public static final com.google.protobuf.Descriptors$Descriptor getDescriptor();
    Code:
       0: invokestatic  #3                  // Method org/apache/dubbo/triple/TripleWrapper.access$000:()Lcom/google/protobuf/Descriptors$Descriptor;
       3: areturn

  protected com.google.protobuf.GeneratedMessageV3$FieldAccessorTable internalGetFieldAccessorTable();
    Code:
       0: invokestatic  #4                  // Method org/apache/dubbo/triple/TripleWrapper.access$100:()Lcom/google/protobuf/GeneratedMessageV3$FieldAccessorTable;
       3: ldc           #5                  // class org/apache/dubbo/triple/TripleWrapper$TripleRequestWrapper
       5: ldc           #6                  // class org/apache/dubbo/triple/TripleWrapper$TripleRequestWrapper$Builder
       7: invokevirtual #7                  // Method com/google/protobuf/GeneratedMessageV3$FieldAccessorTable.ensureFieldAccessorsInitialized:(Ljava/lang/Class;Ljava/lang/Class;)Lcom/google/protobuf/GeneratedMessageV3$FieldAccessorTable;
      10: areturn

  private org.apache.dubbo.triple.TripleWrapper$TripleRequestWrapper$Builder();
    Code:
       0: aload_0
       1: invokespecial #8                  // Method com/google/protobuf/GeneratedMessageV3$Builder."<init>":()V
       4: aload_0
       5: ldc           #9                  // String
       7: putfield      #10                 // Field serializeType_:Ljava/lang/Object;
      10: aload_0
      11: invokestatic  #11                 // Method java/util/Collections.emptyList:()Ljava/util/List;
      14: putfield      #12                 // Field args_:Ljava/util/List;
      17: aload_0
      18: invokestatic  #13                 // Method com/google/protobuf/LazyStringArrayList.emptyList:()Lcom/google/protobuf/LazyStringArrayList;
      21: putfield      #14                 // Field argTypes_:Lcom/google/protobuf/LazyStringArrayList;
      24: return

  private org.apache.dubbo.triple.TripleWrapper$TripleRequestWrapper$Builder(com.google.protobuf.GeneratedMessageV3$BuilderParent);
    Code:
       0: aload_0
       1: aload_1
       2: invokespecial #15                 // Method com/google/protobuf/GeneratedMessageV3$Builder."<init>":(Lcom/google/protobuf/GeneratedMessageV3$BuilderParent;)V
       5: aload_0
       6: ldc           #9                  // String
       8: putfield      #10                 // Field serializeType_:Ljava/lang/Object;
      11: aload_0
      12: invokestatic  #11                 // Method java/util/Collections.emptyList:()Ljava/util/List;
      15: putfield      #12                 // Field args_:Ljava/util/List;
      18: aload_0
      19: invokestatic  #13                 // Method com/google/protobuf/LazyStringArrayList.emptyList:()Lcom/google/protobuf/LazyStringArrayList;
      22: putfield      #14                 // Field argTypes_:Lcom/google/protobuf/LazyStringArrayList;
      25: return

  public org.apache.dubbo.triple.TripleWrapper$TripleRequestWrapper$Builder clear();
    Code:
       0: aload_0
       1: invokespecial #16                 // Method com/google/protobuf/GeneratedMessageV3$Builder.clear:()Lcom/google/protobuf/GeneratedMessageV3$Builder;
       4: pop
       5: aload_0
       6: iconst_0
       7: putfield      #17                 // Field bitField0_:I
      10: aload_0
      11: ldc           #9                  // String
      13: putfield      #10                 // Field serializeType_:Ljava/lang/Object;
      16: aload_0
      17: invokestatic  #11                 // Method java/util/Collections.emptyList:()Ljava/util/List;
      20: putfield      #12                 // Field args_:Ljava/util/List;
      23: aload_0
      24: invokestatic  #13                 // Method com/google/protobuf/LazyStringArrayList.emptyList:()Lcom/google/protobuf/LazyStringArrayList;
      27: putfield      #14                 // Field argTypes_:Lcom/google/protobuf/LazyStringArrayList;
      30: aload_0
      31: areturn

  public com.google.protobuf.Descriptors$Descriptor getDescriptorForType();
    Code:
       0: invokestatic  #3                  // Method org/apache/dubbo/triple/TripleWrapper.access$000:()Lcom/google/protobuf/Descriptors$Descriptor;
       3: areturn

  public org.apache.dubbo.triple.TripleWrapper$TripleRequestWrapper getDefaultInstanceForType();
    Code:
       0: invokestatic  #18                 // Method org/apache/dubbo/triple/TripleWrapper$TripleRequestWrapper.getDefaultInstance:()Lorg/apache/dubbo/triple/TripleWrapper$TripleRequestWrapper;
       3: areturn

  public org.apache.dubbo.triple.TripleWrapper$TripleRequestWrapper build();
    Code:
       0: aload_0
       1: invokevirtual #19                 // Method buildPartial:()Lorg/apache/dubbo/triple/TripleWrapper$TripleRequestWrapper;
       4: astore_1
       5: aload_1
       6: invokevirtual #20                 // Method org/apache/dubbo/triple/TripleWrapper$TripleRequestWrapper.isInitialized:()Z
       9: ifne          17
      12: aload_1
      13: invokestatic  #21                 // Method newUninitializedMessageException:(Lcom/google/protobuf/Message;)Lcom/google/protobuf/UninitializedMessageException;
      16: athrow
      17: aload_1
      18: areturn

  public org.apache.dubbo.triple.TripleWrapper$TripleRequestWrapper buildPartial();
    Code:
       0: new           #5                  // class org/apache/dubbo/triple/TripleWrapper$TripleRequestWrapper
       3: dup
       4: aload_0
       5: aconst_null
       6: invokespecial #22                 // Method org/apache/dubbo/triple/TripleWrapper$TripleRequestWrapper."<init>":(Lcom/google/protobuf/GeneratedMessageV3$Builder;Lorg/apache/dubbo/triple/TripleWrapper$1;)V
       9: astore_1
      10: aload_0
      11: aload_1
      12: invokespecial #23                 // Method buildPartialRepeatedFields:(Lorg/apache/dubbo/triple/TripleWrapper$TripleRequestWrapper;)V
      15: aload_0
      16: getfield      #17                 // Field bitField0_:I
      19: ifeq          27
      22: aload_0
      23: aload_1
      24: invokespecial #24                 // Method buildPartial0:(Lorg/apache/dubbo/triple/TripleWrapper$TripleRequestWrapper;)V
      27: aload_0
      28: invokevirtual #25                 // Method onBuilt:()V
      31: aload_1
      32: areturn

  private void buildPartialRepeatedFields(org.apache.dubbo.triple.TripleWrapper$TripleRequestWrapper);
    Code:
       0: aload_0
       1: getfield      #17                 // Field bitField0_:I
       4: iconst_2
       5: iand
       6: ifeq          31
       9: aload_0
      10: aload_0
      11: getfield      #12                 // Field args_:Ljava/util/List;
      14: invokestatic  #26                 // Method java/util/Collections.unmodifiableList:(Ljava/util/List;)Ljava/util/List;
      17: putfield      #12                 // Field args_:Ljava/util/List;
      20: aload_0
      21: aload_0
      22: getfield      #17                 // Field bitField0_:I
      25: bipush        -3
      27: iand
      28: putfield      #17                 // Field bitField0_:I
      31: aload_1
      32: aload_0
      33: getfield      #12                 // Field args_:Ljava/util/List;
      36: invokestatic  #27                 // Method org/apache/dubbo/triple/TripleWrapper$TripleRequestWrapper.access$502:(Lorg/apache/dubbo/triple/TripleWrapper$TripleRequestWrapper;Ljava/util/List;)Ljava/util/List;
      39: pop
      40: return

  private void buildPartial0(org.apache.dubbo.triple.TripleWrapper$TripleRequestWrapper);
    Code:
       0: aload_0
       1: getfield      #17                 // Field bitField0_:I
       4: istore_2
       5: iload_2
       6: iconst_1
       7: iand
       8: ifeq          20
      11: aload_1
      12: aload_0
      13: getfield      #10                 // Field serializeType_:Ljava/lang/Object;
      16: invokestatic  #28                 // Method org/apache/dubbo/triple/TripleWrapper$TripleRequestWrapper.access$602:(Lorg/apache/dubbo/triple/TripleWrapper$TripleRequestWrapper;Ljava/lang/Object;)Ljava/lang/Object;
      19: pop
      20: iload_2
      21: iconst_4
      22: iand
      23: ifeq          42
      26: aload_0
      27: getfield      #14                 // Field argTypes_:Lcom/google/protobuf/LazyStringArrayList;
      30: invokevirtual #29                 // Method com/google/protobuf/LazyStringArrayList.makeImmutable:()V
      33: aload_1
      34: aload_0
      35: getfield      #14                 // Field argTypes_:Lcom/google/protobuf/LazyStringArrayList;
      38: invokestatic  #30                 // Method org/apache/dubbo/triple/TripleWrapper$TripleRequestWrapper.access$702:(Lorg/apache/dubbo/triple/TripleWrapper$TripleRequestWrapper;Lcom/google/protobuf/LazyStringArrayList;)Lcom/google/protobuf/LazyStringArrayList;
      41: pop
      42: return

  public org.apache.dubbo.triple.TripleWrapper$TripleRequestWrapper$Builder mergeFrom(com.google.protobuf.Message);
    Code:
       0: aload_1
       1: instanceof    #5                  // class org/apache/dubbo/triple/TripleWrapper$TripleRequestWrapper
       4: ifeq          16
       7: aload_0
       8: aload_1
       9: checkcast     #5                  // class org/apache/dubbo/triple/TripleWrapper$TripleRequestWrapper
      12: invokevirtual #31                 // Method mergeFrom:(Lorg/apache/dubbo/triple/TripleWrapper$TripleRequestWrapper;)Lorg/apache/dubbo/triple/TripleWrapper$TripleRequestWrapper$Builder;
      15: areturn
      16: aload_0
      17: aload_1
      18: invokespecial #32                 // Method com/google/protobuf/GeneratedMessageV3$Builder.mergeFrom:(Lcom/google/protobuf/Message;)Lcom/google/protobuf/AbstractMessage$Builder;
      21: pop
      22: aload_0
      23: areturn

  public org.apache.dubbo.triple.TripleWrapper$TripleRequestWrapper$Builder mergeFrom(org.apache.dubbo.triple.TripleWrapper$TripleRequestWrapper);
    Code:
       0: aload_1
       1: invokestatic  #18                 // Method org/apache/dubbo/triple/TripleWrapper$TripleRequestWrapper.getDefaultInstance:()Lorg/apache/dubbo/triple/TripleWrapper$TripleRequestWrapper;
       4: if_acmpne     9
       7: aload_0
       8: areturn
       9: aload_1
      10: invokevirtual #33                 // Method org/apache/dubbo/triple/TripleWrapper$TripleRequestWrapper.getSerializeType:()Ljava/lang/String;
      13: invokevirtual #34                 // Method java/lang/String.isEmpty:()Z
      16: ifne          41
      19: aload_0
      20: aload_1
      21: invokestatic  #35                 // Method org/apache/dubbo/triple/TripleWrapper$TripleRequestWrapper.access$600:(Lorg/apache/dubbo/triple/TripleWrapper$TripleRequestWrapper;)Ljava/lang/Object;
      24: putfield      #10                 // Field serializeType_:Ljava/lang/Object;
      27: aload_0
      28: dup
      29: getfield      #17                 // Field bitField0_:I
      32: iconst_1
      33: ior
      34: putfield      #17                 // Field bitField0_:I
      37: aload_0
      38: invokevirtual #36                 // Method onChanged:()V
      41: aload_1
      42: invokestatic  #37                 // Method org/apache/dubbo/triple/TripleWrapper$TripleRequestWrapper.access$500:(Lorg/apache/dubbo/triple/TripleWrapper$TripleRequestWrapper;)Ljava/util/List;
      45: invokeinterface #38,  1           // InterfaceMethod java/util/List.isEmpty:()Z
      50: ifne          109
      53: aload_0
      54: getfield      #12                 // Field args_:Ljava/util/List;
      57: invokeinterface #38,  1           // InterfaceMethod java/util/List.isEmpty:()Z
      62: ifeq          87
      65: aload_0
      66: aload_1
      67: invokestatic  #37                 // Method org/apache/dubbo/triple/TripleWrapper$TripleRequestWrapper.access$500:(Lorg/apache/dubbo/triple/TripleWrapper$TripleRequestWrapper;)Ljava/util/List;
      70: putfield      #12                 // Field args_:Ljava/util/List;
      73: aload_0
      74: aload_0
      75: getfield      #17                 // Field bitField0_:I
      78: bipush        -3
      80: iand
      81: putfield      #17                 // Field bitField0_:I
      84: goto          105
      87: aload_0
      88: invokespecial #39                 // Method ensureArgsIsMutable:()V
      91: aload_0
      92: getfield      #12                 // Field args_:Ljava/util/List;
      95: aload_1
      96: invokestatic  #37                 // Method org/apache/dubbo/triple/TripleWrapper$TripleRequestWrapper.access$500:(Lorg/apache/dubbo/triple/TripleWrapper$TripleRequestWrapper;)Ljava/util/List;
      99: invokeinterface #40,  2           // InterfaceMethod java/util/List.addAll:(Ljava/util/Collection;)Z
     104: pop
     105: aload_0
     106: invokevirtual #36                 // Method onChanged:()V
     109: aload_1
     110: invokestatic  #41                 // Method org/apache/dubbo/triple/TripleWrapper$TripleRequestWrapper.access$700:(Lorg/apache/dubbo/triple/TripleWrapper$TripleRequestWrapper;)Lcom/google/protobuf/LazyStringArrayList;
     113: invokevirtual #42                 // Method com/google/protobuf/LazyStringArrayList.isEmpty:()Z
     116: ifne          170
     119: aload_0
     120: getfield      #14                 // Field argTypes_:Lcom/google/protobuf/LazyStringArrayList;
     123: invokevirtual #42                 // Method com/google/protobuf/LazyStringArrayList.isEmpty:()Z
     126: ifeq          150
     129: aload_0
     130: aload_1
     131: invokestatic  #41                 // Method org/apache/dubbo/triple/TripleWrapper$TripleRequestWrapper.access$700:(Lorg/apache/dubbo/triple/TripleWrapper$TripleRequestWrapper;)Lcom/google/protobuf/LazyStringArrayList;
     134: putfield      #14                 // Field argTypes_:Lcom/google/protobuf/LazyStringArrayList;
     137: aload_0
     138: dup
     139: getfield      #17                 // Field bitField0_:I
     142: iconst_4
     143: ior
     144: putfield      #17                 // Field bitField0_:I
     147: goto          166
     150: aload_0
     151: invokespecial #43                 // Method ensureArgTypesIsMutable:()V
     154: aload_0
     155: getfield      #14                 // Field argTypes_:Lcom/google/protobuf/LazyStringArrayList;
     158: aload_1
     159: invokestatic  #41                 // Method org/apache/dubbo/triple/TripleWrapper$TripleRequestWrapper.access$700:(Lorg/apache/dubbo/triple/TripleWrapper$TripleRequestWrapper;)Lcom/google/protobuf/LazyStringArrayList;
     162: invokevirtual #44                 // Method com/google/protobuf/LazyStringArrayList.addAll:(Ljava/util/Collection;)Z
     165: pop
     166: aload_0
     167: invokevirtual #36                 // Method onChanged:()V
     170: aload_0
     171: aload_1
     172: invokevirtual #45                 // Method org/apache/dubbo/triple/TripleWrapper$TripleRequestWrapper.getUnknownFields:()Lcom/google/protobuf/UnknownFieldSet;
     175: invokevirtual #46                 // Method mergeUnknownFields:(Lcom/google/protobuf/UnknownFieldSet;)Lorg/apache/dubbo/triple/TripleWrapper$TripleRequestWrapper$Builder;
     178: pop
     179: aload_0
     180: invokevirtual #36                 // Method onChanged:()V
     183: aload_0
     184: areturn

  public final boolean isInitialized();
    Code:
       0: iconst_1
       1: ireturn

  public org.apache.dubbo.triple.TripleWrapper$TripleRequestWrapper$Builder mergeFrom(com.google.protobuf.CodedInputStream, com.google.protobuf.ExtensionRegistryLite) throws java.io.IOException;
    Code:
       0: aload_2
       1: ifnonnull     12
       4: new           #47                 // class java/lang/NullPointerException
       7: dup
       8: invokespecial #48                 // Method java/lang/NullPointerException."<init>":()V
      11: athrow
      12: iconst_0
      13: istore_3
      14: iload_3
      15: ifne          158
      18: aload_1
      19: invokevirtual #49                 // Method com/google/protobuf/CodedInputStream.readTag:()I
      22: istore        4
      24: iload         4
      26: lookupswitch  { // 4
                     0: 68
                    10: 73
                    18: 94
                    26: 119
               default: 142
          }
      68: iconst_1
      69: istore_3
      70: goto          155
      73: aload_0
      74: aload_1
      75: invokevirtual #50                 // Method com/google/protobuf/CodedInputStream.readStringRequireUtf8:()Ljava/lang/String;
      78: putfield      #10                 // Field serializeType_:Ljava/lang/Object;
      81: aload_0
      82: dup
      83: getfield      #17                 // Field bitField0_:I
      86: iconst_1
      87: ior
      88: putfield      #17                 // Field bitField0_:I
      91: goto          155
      94: aload_1
      95: invokevirtual #51                 // Method com/google/protobuf/CodedInputStream.readBytes:()Lcom/google/protobuf/ByteString;
      98: astore        5
     100: aload_0
     101: invokespecial #39                 // Method ensureArgsIsMutable:()V
     104: aload_0
     105: getfield      #12                 // Field args_:Ljava/util/List;
     108: aload         5
     110: invokeinterface #52,  2           // InterfaceMethod java/util/List.add:(Ljava/lang/Object;)Z
     115: pop
     116: goto          155
     119: aload_1
     120: invokevirtual #50                 // Method com/google/protobuf/CodedInputStream.readStringRequireUtf8:()Ljava/lang/String;
     123: astore        5
     125: aload_0
     126: invokespecial #43                 // Method ensureArgTypesIsMutable:()V
     129: aload_0
     130: getfield      #14                 // Field argTypes_:Lcom/google/protobuf/LazyStringArrayList;
     133: aload         5
     135: invokevirtual #53                 // Method com/google/protobuf/LazyStringArrayList.add:(Ljava/lang/Object;)Z
     138: pop
     139: goto          155
     142: aload_0
     143: aload_1
     144: aload_2
     145: iload         4
     147: invokespecial #54                 // Method com/google/protobuf/GeneratedMessageV3$Builder.parseUnknownField:(Lcom/google/protobuf/CodedInputStream;Lcom/google/protobuf/ExtensionRegistryLite;I)Z
     150: ifne          155
     153: iconst_1
     154: istore_3
     155: goto          14
     158: aload_0
     159: invokevirtual #36                 // Method onChanged:()V
     162: goto          180
     165: astore_3
     166: aload_3
     167: invokevirtual #56                 // Method com/google/protobuf/InvalidProtocolBufferException.unwrapIOException:()Ljava/io/IOException;
     170: athrow
     171: astore        6
     173: aload_0
     174: invokevirtual #36                 // Method onChanged:()V
     177: aload         6
     179: athrow
     180: aload_0
     181: areturn
    Exception table:
       from    to  target type
          12   158   165   Class com/google/protobuf/InvalidProtocolBufferException
          12   158   171   any
         165   173   171   any

  public java.lang.String getSerializeType();
    Code:
       0: aload_0
       1: getfield      #10                 // Field serializeType_:Ljava/lang/Object;
       4: astore_1
       5: aload_1
       6: instanceof    #57                 // class java/lang/String
       9: ifne          29
      12: aload_1
      13: checkcast     #58                 // class com/google/protobuf/ByteString
      16: astore_2
      17: aload_2
      18: invokevirtual #59                 // Method com/google/protobuf/ByteString.toStringUtf8:()Ljava/lang/String;
      21: astore_3
      22: aload_0
      23: aload_3
      24: putfield      #10                 // Field serializeType_:Ljava/lang/Object;
      27: aload_3
      28: areturn
      29: aload_1
      30: checkcast     #57                 // class java/lang/String
      33: areturn

  public com.google.protobuf.ByteString getSerializeTypeBytes();
    Code:
       0: aload_0
       1: getfield      #10                 // Field serializeType_:Ljava/lang/Object;
       4: astore_1
       5: aload_1
       6: instanceof    #57                 // class java/lang/String
       9: ifeq          27
      12: aload_1
      13: checkcast     #57                 // class java/lang/String
      16: invokestatic  #60                 // Method com/google/protobuf/ByteString.copyFromUtf8:(Ljava/lang/String;)Lcom/google/protobuf/ByteString;
      19: astore_2
      20: aload_0
      21: aload_2
      22: putfield      #10                 // Field serializeType_:Ljava/lang/Object;
      25: aload_2
      26: areturn
      27: aload_1
      28: checkcast     #58                 // class com/google/protobuf/ByteString
      31: areturn

  public org.apache.dubbo.triple.TripleWrapper$TripleRequestWrapper$Builder setSerializeType(java.lang.String);
    Code:
       0: aload_1
       1: ifnonnull     12
       4: new           #47                 // class java/lang/NullPointerException
       7: dup
       8: invokespecial #48                 // Method java/lang/NullPointerException."<init>":()V
      11: athrow
      12: aload_0
      13: aload_1
      14: putfield      #10                 // Field serializeType_:Ljava/lang/Object;
      17: aload_0
      18: dup
      19: getfield      #17                 // Field bitField0_:I
      22: iconst_1
      23: ior
      24: putfield      #17                 // Field bitField0_:I
      27: aload_0
      28: invokevirtual #36                 // Method onChanged:()V
      31: aload_0
      32: areturn

  public org.apache.dubbo.triple.TripleWrapper$TripleRequestWrapper$Builder clearSerializeType();
    Code:
       0: aload_0
       1: invokestatic  #18                 // Method org/apache/dubbo/triple/TripleWrapper$TripleRequestWrapper.getDefaultInstance:()Lorg/apache/dubbo/triple/TripleWrapper$TripleRequestWrapper;
       4: invokevirtual #33                 // Method org/apache/dubbo/triple/TripleWrapper$TripleRequestWrapper.getSerializeType:()Ljava/lang/String;
       7: putfield      #10                 // Field serializeType_:Ljava/lang/Object;
      10: aload_0
      11: aload_0
      12: getfield      #17                 // Field bitField0_:I
      15: bipush        -2
      17: iand
      18: putfield      #17                 // Field bitField0_:I
      21: aload_0
      22: invokevirtual #36                 // Method onChanged:()V
      25: aload_0
      26: areturn

  public org.apache.dubbo.triple.TripleWrapper$TripleRequestWrapper$Builder setSerializeTypeBytes(com.google.protobuf.ByteString);
    Code:
       0: aload_1
       1: ifnonnull     12
       4: new           #47                 // class java/lang/NullPointerException
       7: dup
       8: invokespecial #48                 // Method java/lang/NullPointerException."<init>":()V
      11: athrow
      12: aload_1
      13: invokestatic  #61                 // Method org/apache/dubbo/triple/TripleWrapper$TripleRequestWrapper.access$800:(Lcom/google/protobuf/ByteString;)V
      16: aload_0
      17: aload_1
      18: putfield      #10                 // Field serializeType_:Ljava/lang/Object;
      21: aload_0
      22: dup
      23: getfield      #17                 // Field bitField0_:I
      26: iconst_1
      27: ior
      28: putfield      #17                 // Field bitField0_:I
      31: aload_0
      32: invokevirtual #36                 // Method onChanged:()V
      35: aload_0
      36: areturn

  private void ensureArgsIsMutable();
    Code:
       0: aload_0
       1: getfield      #17                 // Field bitField0_:I
       4: iconst_2
       5: iand
       6: ifne          34
       9: aload_0
      10: new           #62                 // class java/util/ArrayList
      13: dup
      14: aload_0
      15: getfield      #12                 // Field args_:Ljava/util/List;
      18: invokespecial #63                 // Method java/util/ArrayList."<init>":(Ljava/util/Collection;)V
      21: putfield      #12                 // Field args_:Ljava/util/List;
      24: aload_0
      25: dup
      26: getfield      #17                 // Field bitField0_:I
      29: iconst_2
      30: ior
      31: putfield      #17                 // Field bitField0_:I
      34: return

  public java.util.List<com.google.protobuf.ByteString> getArgsList();
    Code:
       0: aload_0
       1: getfield      #17                 // Field bitField0_:I
       4: iconst_2
       5: iand
       6: ifeq          19
       9: aload_0
      10: getfield      #12                 // Field args_:Ljava/util/List;
      13: invokestatic  #26                 // Method java/util/Collections.unmodifiableList:(Ljava/util/List;)Ljava/util/List;
      16: goto          23
      19: aload_0
      20: getfield      #12                 // Field args_:Ljava/util/List;
      23: areturn

  public int getArgsCount();
    Code:
       0: aload_0
       1: getfield      #12                 // Field args_:Ljava/util/List;
       4: invokeinterface #64,  1           // InterfaceMethod java/util/List.size:()I
       9: ireturn

  public com.google.protobuf.ByteString getArgs(int);
    Code:
       0: aload_0
       1: getfield      #12                 // Field args_:Ljava/util/List;
       4: iload_1
       5: invokeinterface #65,  2           // InterfaceMethod java/util/List.get:(I)Ljava/lang/Object;
      10: checkcast     #58                 // class com/google/protobuf/ByteString
      13: areturn

  public org.apache.dubbo.triple.TripleWrapper$TripleRequestWrapper$Builder setArgs(int, com.google.protobuf.ByteString);
    Code:
       0: aload_2
       1: ifnonnull     12
       4: new           #47                 // class java/lang/NullPointerException
       7: dup
       8: invokespecial #48                 // Method java/lang/NullPointerException."<init>":()V
      11: athrow
      12: aload_0
      13: invokespecial #39                 // Method ensureArgsIsMutable:()V
      16: aload_0
      17: getfield      #12                 // Field args_:Ljava/util/List;
      20: iload_1
      21: aload_2
      22: invokeinterface #66,  3           // InterfaceMethod java/util/List.set:(ILjava/lang/Object;)Ljava/lang/Object;
      27: pop
      28: aload_0
      29: invokevirtual #36                 // Method onChanged:()V
      32: aload_0
      33: areturn

  public org.apache.dubbo.triple.TripleWrapper$TripleRequestWrapper$Builder addArgs(com.google.protobuf.ByteString);
    Code:
       0: aload_1
       1: ifnonnull     12
       4: new           #47                 // class java/lang/NullPointerException
       7: dup
       8: invokespecial #48                 // Method java/lang/NullPointerException."<init>":()V
      11: athrow
      12: aload_0
      13: invokespecial #39                 // Method ensureArgsIsMutable:()V
      16: aload_0
      17: getfield      #12                 // Field args_:Ljava/util/List;
      20: aload_1
      21: invokeinterface #52,  2           // InterfaceMethod java/util/List.add:(Ljava/lang/Object;)Z
      26: pop
      27: aload_0
      28: invokevirtual #36                 // Method onChanged:()V
      31: aload_0
      32: areturn

  public org.apache.dubbo.triple.TripleWrapper$TripleRequestWrapper$Builder addAllArgs(java.lang.Iterable<? extends com.google.protobuf.ByteString>);
    Code:
       0: aload_0
       1: invokespecial #39                 // Method ensureArgsIsMutable:()V
       4: aload_1
       5: aload_0
       6: getfield      #12                 // Field args_:Ljava/util/List;
       9: invokestatic  #67                 // Method com/google/protobuf/AbstractMessageLite$Builder.addAll:(Ljava/lang/Iterable;Ljava/util/List;)V
      12: aload_0
      13: invokevirtual #36                 // Method onChanged:()V
      16: aload_0
      17: areturn

  public org.apache.dubbo.triple.TripleWrapper$TripleRequestWrapper$Builder clearArgs();
    Code:
       0: aload_0
       1: invokestatic  #11                 // Method java/util/Collections.emptyList:()Ljava/util/List;
       4: putfield      #12                 // Field args_:Ljava/util/List;
       7: aload_0
       8: aload_0
       9: getfield      #17                 // Field bitField0_:I
      12: bipush        -3
      14: iand
      15: putfield      #17                 // Field bitField0_:I
      18: aload_0
      19: invokevirtual #36                 // Method onChanged:()V
      22: aload_0
      23: areturn

  private void ensureArgTypesIsMutable();
    Code:
       0: aload_0
       1: getfield      #14                 // Field argTypes_:Lcom/google/protobuf/LazyStringArrayList;
       4: invokevirtual #68                 // Method com/google/protobuf/LazyStringArrayList.isModifiable:()Z
       7: ifne          25
      10: aload_0
      11: new           #69                 // class com/google/protobuf/LazyStringArrayList
      14: dup
      15: aload_0
      16: getfield      #14                 // Field argTypes_:Lcom/google/protobuf/LazyStringArrayList;
      19: invokespecial #70                 // Method com/google/protobuf/LazyStringArrayList."<init>":(Lcom/google/protobuf/LazyStringList;)V
      22: putfield      #14                 // Field argTypes_:Lcom/google/protobuf/LazyStringArrayList;
      25: aload_0
      26: dup
      27: getfield      #17                 // Field bitField0_:I
      30: iconst_4
      31: ior
      32: putfield      #17                 // Field bitField0_:I
      35: return

  public com.google.protobuf.ProtocolStringList getArgTypesList();
    Code:
       0: aload_0
       1: getfield      #14                 // Field argTypes_:Lcom/google/protobuf/LazyStringArrayList;
       4: invokevirtual #29                 // Method com/google/protobuf/LazyStringArrayList.makeImmutable:()V
       7: aload_0
       8: getfield      #14                 // Field argTypes_:Lcom/google/protobuf/LazyStringArrayList;
      11: areturn

  public int getArgTypesCount();
    Code:
       0: aload_0
       1: getfield      #14                 // Field argTypes_:Lcom/google/protobuf/LazyStringArrayList;
       4: invokevirtual #71                 // Method com/google/protobuf/LazyStringArrayList.size:()I
       7: ireturn

  public java.lang.String getArgTypes(int);
    Code:
       0: aload_0
       1: getfield      #14                 // Field argTypes_:Lcom/google/protobuf/LazyStringArrayList;
       4: iload_1
       5: invokevirtual #72                 // Method com/google/protobuf/LazyStringArrayList.get:(I)Ljava/lang/String;
       8: areturn

  public com.google.protobuf.ByteString getArgTypesBytes(int);
    Code:
       0: aload_0
       1: getfield      #14                 // Field argTypes_:Lcom/google/protobuf/LazyStringArrayList;
       4: iload_1
       5: invokevirtual #73                 // Method com/google/protobuf/LazyStringArrayList.getByteString:(I)Lcom/google/protobuf/ByteString;
       8: areturn

  public org.apache.dubbo.triple.TripleWrapper$TripleRequestWrapper$Builder setArgTypes(int, java.lang.String);
    Code:
       0: aload_2
       1: ifnonnull     12
       4: new           #47                 // class java/lang/NullPointerException
       7: dup
       8: invokespecial #48                 // Method java/lang/NullPointerException."<init>":()V
      11: athrow
      12: aload_0
      13: invokespecial #43                 // Method ensureArgTypesIsMutable:()V
      16: aload_0
      17: getfield      #14                 // Field argTypes_:Lcom/google/protobuf/LazyStringArrayList;
      20: iload_1
      21: aload_2
      22: invokevirtual #74                 // Method com/google/protobuf/LazyStringArrayList.set:(ILjava/lang/String;)Ljava/lang/String;
      25: pop
      26: aload_0
      27: dup
      28: getfield      #17                 // Field bitField0_:I
      31: iconst_4
      32: ior
      33: putfield      #17                 // Field bitField0_:I
      36: aload_0
      37: invokevirtual #36                 // Method onChanged:()V
      40: aload_0
      41: areturn

  public org.apache.dubbo.triple.TripleWrapper$TripleRequestWrapper$Builder addArgTypes(java.lang.String);
    Code:
       0: aload_1
       1: ifnonnull     12
       4: new           #47                 // class java/lang/NullPointerException
       7: dup
       8: invokespecial #48                 // Method java/lang/NullPointerException."<init>":()V
      11: athrow
      12: aload_0
      13: invokespecial #43                 // Method ensureArgTypesIsMutable:()V
      16: aload_0
      17: getfield      #14                 // Field argTypes_:Lcom/google/protobuf/LazyStringArrayList;
      20: aload_1
      21: invokevirtual #53                 // Method com/google/protobuf/LazyStringArrayList.add:(Ljava/lang/Object;)Z
      24: pop
      25: aload_0
      26: dup
      27: getfield      #17                 // Field bitField0_:I
      30: iconst_4
      31: ior
      32: putfield      #17                 // Field bitField0_:I
      35: aload_0
      36: invokevirtual #36                 // Method onChanged:()V
      39: aload_0
      40: areturn

  public org.apache.dubbo.triple.TripleWrapper$TripleRequestWrapper$Builder addAllArgTypes(java.lang.Iterable<java.lang.String>);
    Code:
       0: aload_0
       1: invokespecial #43                 // Method ensureArgTypesIsMutable:()V
       4: aload_1
       5: aload_0
       6: getfield      #14                 // Field argTypes_:Lcom/google/protobuf/LazyStringArrayList;
       9: invokestatic  #67                 // Method com/google/protobuf/AbstractMessageLite$Builder.addAll:(Ljava/lang/Iterable;Ljava/util/List;)V
      12: aload_0
      13: dup
      14: getfield      #17                 // Field bitField0_:I
      17: iconst_4
      18: ior
      19: putfield      #17                 // Field bitField0_:I
      22: aload_0
      23: invokevirtual #36                 // Method onChanged:()V
      26: aload_0
      27: areturn

  public org.apache.dubbo.triple.TripleWrapper$TripleRequestWrapper$Builder clearArgTypes();
    Code:
       0: aload_0
       1: invokestatic  #13                 // Method com/google/protobuf/LazyStringArrayList.emptyList:()Lcom/google/protobuf/LazyStringArrayList;
       4: putfield      #14                 // Field argTypes_:Lcom/google/protobuf/LazyStringArrayList;
       7: aload_0
       8: aload_0
       9: getfield      #17                 // Field bitField0_:I
      12: bipush        -5
      14: iand
      15: putfield      #17                 // Field bitField0_:I
      18: aload_0
      19: invokevirtual #36                 // Method onChanged:()V
      22: aload_0
      23: areturn

  public org.apache.dubbo.triple.TripleWrapper$TripleRequestWrapper$Builder addArgTypesBytes(com.google.protobuf.ByteString);
    Code:
       0: aload_1
       1: ifnonnull     12
       4: new           #47                 // class java/lang/NullPointerException
       7: dup
       8: invokespecial #48                 // Method java/lang/NullPointerException."<init>":()V
      11: athrow
      12: aload_1
      13: invokestatic  #75                 // Method org/apache/dubbo/triple/TripleWrapper$TripleRequestWrapper.access$900:(Lcom/google/protobuf/ByteString;)V
      16: aload_0
      17: invokespecial #43                 // Method ensureArgTypesIsMutable:()V
      20: aload_0
      21: getfield      #14                 // Field argTypes_:Lcom/google/protobuf/LazyStringArrayList;
      24: aload_1
      25: invokevirtual #76                 // Method com/google/protobuf/LazyStringArrayList.add:(Lcom/google/protobuf/ByteString;)V
      28: aload_0
      29: dup
      30: getfield      #17                 // Field bitField0_:I
      33: iconst_4
      34: ior
      35: putfield      #17                 // Field bitField0_:I
      38: aload_0
      39: invokevirtual #36                 // Method onChanged:()V
      42: aload_0
      43: areturn

  public final org.apache.dubbo.triple.TripleWrapper$TripleRequestWrapper$Builder setUnknownFields(com.google.protobuf.UnknownFieldSet);
    Code:
       0: aload_0
       1: aload_1
       2: invokespecial #77                 // Method com/google/protobuf/GeneratedMessageV3$Builder.setUnknownFields:(Lcom/google/protobuf/UnknownFieldSet;)Lcom/google/protobuf/GeneratedMessageV3$Builder;
       5: checkcast     #6                  // class org/apache/dubbo/triple/TripleWrapper$TripleRequestWrapper$Builder
       8: areturn

  public final org.apache.dubbo.triple.TripleWrapper$TripleRequestWrapper$Builder mergeUnknownFields(com.google.protobuf.UnknownFieldSet);
    Code:
       0: aload_0
       1: aload_1
       2: invokespecial #78                 // Method com/google/protobuf/GeneratedMessageV3$Builder.mergeUnknownFields:(Lcom/google/protobuf/UnknownFieldSet;)Lcom/google/protobuf/GeneratedMessageV3$Builder;
       5: checkcast     #6                  // class org/apache/dubbo/triple/TripleWrapper$TripleRequestWrapper$Builder
       8: areturn

  public com.google.protobuf.GeneratedMessageV3$Builder mergeUnknownFields(com.google.protobuf.UnknownFieldSet);
    Code:
       0: aload_0
       1: aload_1
       2: invokevirtual #46                 // Method mergeUnknownFields:(Lcom/google/protobuf/UnknownFieldSet;)Lorg/apache/dubbo/triple/TripleWrapper$TripleRequestWrapper$Builder;
       5: areturn

  public com.google.protobuf.GeneratedMessageV3$Builder setUnknownFields(com.google.protobuf.UnknownFieldSet);
    Code:
       0: aload_0
       1: aload_1
       2: invokevirtual #79                 // Method setUnknownFields:(Lcom/google/protobuf/UnknownFieldSet;)Lorg/apache/dubbo/triple/TripleWrapper$TripleRequestWrapper$Builder;
       5: areturn

  public com.google.protobuf.GeneratedMessageV3$Builder clear();
    Code:
       0: aload_0
       1: invokevirtual #80                 // Method clear:()Lorg/apache/dubbo/triple/TripleWrapper$TripleRequestWrapper$Builder;
       4: areturn

  public com.google.protobuf.AbstractMessage$Builder mergeUnknownFields(com.google.protobuf.UnknownFieldSet);
    Code:
       0: aload_0
       1: aload_1
       2: invokevirtual #46                 // Method mergeUnknownFields:(Lcom/google/protobuf/UnknownFieldSet;)Lorg/apache/dubbo/triple/TripleWrapper$TripleRequestWrapper$Builder;
       5: areturn

  public com.google.protobuf.AbstractMessage$Builder mergeFrom(com.google.protobuf.CodedInputStream, com.google.protobuf.ExtensionRegistryLite) throws java.io.IOException;
    Code:
       0: aload_0
       1: aload_1
       2: aload_2
       3: invokevirtual #81                 // Method mergeFrom:(Lcom/google/protobuf/CodedInputStream;Lcom/google/protobuf/ExtensionRegistryLite;)Lorg/apache/dubbo/triple/TripleWrapper$TripleRequestWrapper$Builder;
       6: areturn

  public com.google.protobuf.AbstractMessage$Builder mergeFrom(com.google.protobuf.Message);
    Code:
       0: aload_0
       1: aload_1
       2: invokevirtual #82                 // Method mergeFrom:(Lcom/google/protobuf/Message;)Lorg/apache/dubbo/triple/TripleWrapper$TripleRequestWrapper$Builder;
       5: areturn

  public com.google.protobuf.AbstractMessage$Builder clear();
    Code:
       0: aload_0
       1: invokevirtual #80                 // Method clear:()Lorg/apache/dubbo/triple/TripleWrapper$TripleRequestWrapper$Builder;
       4: areturn

  public com.google.protobuf.Message$Builder mergeUnknownFields(com.google.protobuf.UnknownFieldSet);
    Code:
       0: aload_0
       1: aload_1
       2: invokevirtual #46                 // Method mergeUnknownFields:(Lcom/google/protobuf/UnknownFieldSet;)Lorg/apache/dubbo/triple/TripleWrapper$TripleRequestWrapper$Builder;
       5: areturn

  public com.google.protobuf.Message$Builder setUnknownFields(com.google.protobuf.UnknownFieldSet);
    Code:
       0: aload_0
       1: aload_1
       2: invokevirtual #79                 // Method setUnknownFields:(Lcom/google/protobuf/UnknownFieldSet;)Lorg/apache/dubbo/triple/TripleWrapper$TripleRequestWrapper$Builder;
       5: areturn

  public com.google.protobuf.Message$Builder mergeFrom(com.google.protobuf.CodedInputStream, com.google.protobuf.ExtensionRegistryLite) throws java.io.IOException;
    Code:
       0: aload_0
       1: aload_1
       2: aload_2
       3: invokevirtual #81                 // Method mergeFrom:(Lcom/google/protobuf/CodedInputStream;Lcom/google/protobuf/ExtensionRegistryLite;)Lorg/apache/dubbo/triple/TripleWrapper$TripleRequestWrapper$Builder;
       6: areturn

  public com.google.protobuf.Message buildPartial();
    Code:
       0: aload_0
       1: invokevirtual #19                 // Method buildPartial:()Lorg/apache/dubbo/triple/TripleWrapper$TripleRequestWrapper;
       4: areturn

  public com.google.protobuf.Message build();
    Code:
       0: aload_0
       1: invokevirtual #83                 // Method build:()Lorg/apache/dubbo/triple/TripleWrapper$TripleRequestWrapper;
       4: areturn

  public com.google.protobuf.Message$Builder mergeFrom(com.google.protobuf.Message);
    Code:
       0: aload_0
       1: aload_1
       2: invokevirtual #82                 // Method mergeFrom:(Lcom/google/protobuf/Message;)Lorg/apache/dubbo/triple/TripleWrapper$TripleRequestWrapper$Builder;
       5: areturn

  public com.google.protobuf.Message$Builder clear();
    Code:
       0: aload_0
       1: invokevirtual #80                 // Method clear:()Lorg/apache/dubbo/triple/TripleWrapper$TripleRequestWrapper$Builder;
       4: areturn

  public com.google.protobuf.MessageLite$Builder mergeFrom(com.google.protobuf.CodedInputStream, com.google.protobuf.ExtensionRegistryLite) throws java.io.IOException;
    Code:
       0: aload_0
       1: aload_1
       2: aload_2
       3: invokevirtual #81                 // Method mergeFrom:(Lcom/google/protobuf/CodedInputStream;Lcom/google/protobuf/ExtensionRegistryLite;)Lorg/apache/dubbo/triple/TripleWrapper$TripleRequestWrapper$Builder;
       6: areturn

  public com.google.protobuf.MessageLite buildPartial();
    Code:
       0: aload_0
       1: invokevirtual #19                 // Method buildPartial:()Lorg/apache/dubbo/triple/TripleWrapper$TripleRequestWrapper;
       4: areturn

  public com.google.protobuf.MessageLite build();
    Code:
       0: aload_0
       1: invokevirtual #83                 // Method build:()Lorg/apache/dubbo/triple/TripleWrapper$TripleRequestWrapper;
       4: areturn

  public com.google.protobuf.MessageLite$Builder clear();
    Code:
       0: aload_0
       1: invokevirtual #80                 // Method clear:()Lorg/apache/dubbo/triple/TripleWrapper$TripleRequestWrapper$Builder;
       4: areturn

  public com.google.protobuf.MessageLite getDefaultInstanceForType();
    Code:
       0: aload_0
       1: invokevirtual #84                 // Method getDefaultInstanceForType:()Lorg/apache/dubbo/triple/TripleWrapper$TripleRequestWrapper;
       4: areturn

  public com.google.protobuf.Message getDefaultInstanceForType();
    Code:
       0: aload_0
       1: invokevirtual #84                 // Method getDefaultInstanceForType:()Lorg/apache/dubbo/triple/TripleWrapper$TripleRequestWrapper;
       4: areturn

  public com.google.protobuf.AbstractMessageLite$Builder mergeFrom(com.google.protobuf.CodedInputStream, com.google.protobuf.ExtensionRegistryLite) throws java.io.IOException;
    Code:
       0: aload_0
       1: aload_1
       2: aload_2
       3: invokevirtual #81                 // Method mergeFrom:(Lcom/google/protobuf/CodedInputStream;Lcom/google/protobuf/ExtensionRegistryLite;)Lorg/apache/dubbo/triple/TripleWrapper$TripleRequestWrapper$Builder;
       6: areturn

  public java.util.List getArgTypesList();
    Code:
       0: aload_0
       1: invokevirtual #85                 // Method getArgTypesList:()Lcom/google/protobuf/ProtocolStringList;
       4: areturn

  org.apache.dubbo.triple.TripleWrapper$TripleRequestWrapper$Builder(org.apache.dubbo.triple.TripleWrapper$1);
    Code:
       0: aload_0
       1: invokespecial #2                  // Method "<init>":()V
       4: return

  org.apache.dubbo.triple.TripleWrapper$TripleRequestWrapper$Builder(com.google.protobuf.GeneratedMessageV3$BuilderParent, org.apache.dubbo.triple.TripleWrapper$1);
    Code:
       0: aload_0
       1: aload_1
       2: invokespecial #1                  // Method "<init>":(Lcom/google/protobuf/GeneratedMessageV3$BuilderParent;)V
       5: return
}
