Compiled from "PDF417Writer.java"
public final class com.google.zxing.pdf417.PDF417Writer implements com.google.zxing.Writer {
  private static final int WHITE_SPACE;

  private static final int DEFAULT_ERROR_CORRECTION_LEVEL;

  public com.google.zxing.pdf417.PDF417Writer();
    Code:
       0: aload_0
       1: invokespecial #1                  // Method java/lang/Object."<init>":()V
       4: return

  public com.google.zxing.common.BitMatrix encode(java.lang.String, com.google.zxing.BarcodeFormat, int, int, java.util.Map<com.google.zxing.EncodeHintType, ?>) throws com.google.zxing.WriterException;
    Code:
       0: aload_2
       1: getstatic     #2                  // Field com/google/zxing/BarcodeFormat.PDF_417:Lcom/google/zxing/BarcodeFormat;
       4: if_acmpeq     34
       7: new           #3                  // class java/lang/IllegalArgumentException
      10: dup
      11: new           #4                  // class java/lang/StringBuilder
      14: dup
      15: invokespecial #5                  // Method java/lang/StringBuilder."<init>":()V
      18: ldc           #6                  // String Can only encode PDF_417, but got
      20: invokevirtual #7                  // Method java/lang/StringBuilder.append:(Ljava/lang/String;)Ljava/lang/StringBuilder;
      23: aload_2
      24: invokevirtual #8                  // Method java/lang/StringBuilder.append:(Ljava/lang/Object;)Ljava/lang/StringBuilder;
      27: invokevirtual #9                  // Method java/lang/StringBuilder.toString:()Ljava/lang/String;
      30: invokespecial #10                 // Method java/lang/IllegalArgumentException."<init>":(Ljava/lang/String;)V
      33: athrow
      34: new           #11                 // class com/google/zxing/pdf417/encoder/PDF417
      37: dup
      38: invokespecial #12                 // Method com/google/zxing/pdf417/encoder/PDF417."<init>":()V
      41: astore        6
      43: bipush        30
      45: istore        7
      47: iconst_2
      48: istore        8
      50: iconst_0
      51: istore        9
      53: aload         5
      55: ifnull        318
      58: aload         5
      60: getstatic     #14                 // Field com/google/zxing/EncodeHintType.PDF417_COMPACT:Lcom/google/zxing/EncodeHintType;
      63: invokeinterface #15,  2           // InterfaceMethod java/util/Map.containsKey:(Ljava/lang/Object;)Z
      68: ifeq          92
      71: aload         6
      73: aload         5
      75: getstatic     #14                 // Field com/google/zxing/EncodeHintType.PDF417_COMPACT:Lcom/google/zxing/EncodeHintType;
      78: invokeinterface #16,  2           // InterfaceMethod java/util/Map.get:(Ljava/lang/Object;)Ljava/lang/Object;
      83: invokevirtual #17                 // Method java/lang/Object.toString:()Ljava/lang/String;
      86: invokestatic  #18                 // Method java/lang/Boolean.parseBoolean:(Ljava/lang/String;)Z
      89: invokevirtual #19                 // Method com/google/zxing/pdf417/encoder/PDF417.setCompact:(Z)V
      92: aload         5
      94: getstatic     #20                 // Field com/google/zxing/EncodeHintType.PDF417_COMPACTION:Lcom/google/zxing/EncodeHintType;
      97: invokeinterface #15,  2           // InterfaceMethod java/util/Map.containsKey:(Ljava/lang/Object;)Z
     102: ifeq          126
     105: aload         6
     107: aload         5
     109: getstatic     #20                 // Field com/google/zxing/EncodeHintType.PDF417_COMPACTION:Lcom/google/zxing/EncodeHintType;
     112: invokeinterface #16,  2           // InterfaceMethod java/util/Map.get:(Ljava/lang/Object;)Ljava/lang/Object;
     117: invokevirtual #17                 // Method java/lang/Object.toString:()Ljava/lang/String;
     120: invokestatic  #21                 // Method com/google/zxing/pdf417/encoder/Compaction.valueOf:(Ljava/lang/String;)Lcom/google/zxing/pdf417/encoder/Compaction;
     123: invokevirtual #22                 // Method com/google/zxing/pdf417/encoder/PDF417.setCompaction:(Lcom/google/zxing/pdf417/encoder/Compaction;)V
     126: aload         5
     128: getstatic     #23                 // Field com/google/zxing/EncodeHintType.PDF417_DIMENSIONS:Lcom/google/zxing/EncodeHintType;
     131: invokeinterface #15,  2           // InterfaceMethod java/util/Map.containsKey:(Ljava/lang/Object;)Z
     136: ifeq          179
     139: aload         5
     141: getstatic     #23                 // Field com/google/zxing/EncodeHintType.PDF417_DIMENSIONS:Lcom/google/zxing/EncodeHintType;
     144: invokeinterface #16,  2           // InterfaceMethod java/util/Map.get:(Ljava/lang/Object;)Ljava/lang/Object;
     149: checkcast     #24                 // class com/google/zxing/pdf417/encoder/Dimensions
     152: astore        10
     154: aload         6
     156: aload         10
     158: invokevirtual #25                 // Method com/google/zxing/pdf417/encoder/Dimensions.getMaxCols:()I
     161: aload         10
     163: invokevirtual #26                 // Method com/google/zxing/pdf417/encoder/Dimensions.getMinCols:()I
     166: aload         10
     168: invokevirtual #27                 // Method com/google/zxing/pdf417/encoder/Dimensions.getMaxRows:()I
     171: aload         10
     173: invokevirtual #28                 // Method com/google/zxing/pdf417/encoder/Dimensions.getMinRows:()I
     176: invokevirtual #29                 // Method com/google/zxing/pdf417/encoder/PDF417.setDimensions:(IIII)V
     179: aload         5
     181: getstatic     #30                 // Field com/google/zxing/EncodeHintType.MARGIN:Lcom/google/zxing/EncodeHintType;
     184: invokeinterface #15,  2           // InterfaceMethod java/util/Map.containsKey:(Ljava/lang/Object;)Z
     189: ifeq          210
     192: aload         5
     194: getstatic     #30                 // Field com/google/zxing/EncodeHintType.MARGIN:Lcom/google/zxing/EncodeHintType;
     197: invokeinterface #16,  2           // InterfaceMethod java/util/Map.get:(Ljava/lang/Object;)Ljava/lang/Object;
     202: invokevirtual #17                 // Method java/lang/Object.toString:()Ljava/lang/String;
     205: invokestatic  #31                 // Method java/lang/Integer.parseInt:(Ljava/lang/String;)I
     208: istore        7
     210: aload         5
     212: getstatic     #32                 // Field com/google/zxing/EncodeHintType.ERROR_CORRECTION:Lcom/google/zxing/EncodeHintType;
     215: invokeinterface #15,  2           // InterfaceMethod java/util/Map.containsKey:(Ljava/lang/Object;)Z
     220: ifeq          241
     223: aload         5
     225: getstatic     #32                 // Field com/google/zxing/EncodeHintType.ERROR_CORRECTION:Lcom/google/zxing/EncodeHintType;
     228: invokeinterface #16,  2           // InterfaceMethod java/util/Map.get:(Ljava/lang/Object;)Ljava/lang/Object;
     233: invokevirtual #17                 // Method java/lang/Object.toString:()Ljava/lang/String;
     236: invokestatic  #31                 // Method java/lang/Integer.parseInt:(Ljava/lang/String;)I
     239: istore        8
     241: aload         5
     243: getstatic     #33                 // Field com/google/zxing/EncodeHintType.CHARACTER_SET:Lcom/google/zxing/EncodeHintType;
     246: invokeinterface #15,  2           // InterfaceMethod java/util/Map.containsKey:(Ljava/lang/Object;)Z
     251: ifeq          279
     254: aload         5
     256: getstatic     #33                 // Field com/google/zxing/EncodeHintType.CHARACTER_SET:Lcom/google/zxing/EncodeHintType;
     259: invokeinterface #16,  2           // InterfaceMethod java/util/Map.get:(Ljava/lang/Object;)Ljava/lang/Object;
     264: invokevirtual #17                 // Method java/lang/Object.toString:()Ljava/lang/String;
     267: invokestatic  #34                 // Method java/nio/charset/Charset.forName:(Ljava/lang/String;)Ljava/nio/charset/Charset;
     270: astore        10
     272: aload         6
     274: aload         10
     276: invokevirtual #35                 // Method com/google/zxing/pdf417/encoder/PDF417.setEncoding:(Ljava/nio/charset/Charset;)V
     279: aload         5
     281: getstatic     #36                 // Field com/google/zxing/EncodeHintType.PDF417_AUTO_ECI:Lcom/google/zxing/EncodeHintType;
     284: invokeinterface #15,  2           // InterfaceMethod java/util/Map.containsKey:(Ljava/lang/Object;)Z
     289: ifeq          315
     292: aload         5
     294: getstatic     #36                 // Field com/google/zxing/EncodeHintType.PDF417_AUTO_ECI:Lcom/google/zxing/EncodeHintType;
     297: invokeinterface #16,  2           // InterfaceMethod java/util/Map.get:(Ljava/lang/Object;)Ljava/lang/Object;
     302: invokevirtual #17                 // Method java/lang/Object.toString:()Ljava/lang/String;
     305: invokestatic  #18                 // Method java/lang/Boolean.parseBoolean:(Ljava/lang/String;)Z
     308: ifeq          315
     311: iconst_1
     312: goto          316
     315: iconst_0
     316: istore        9
     318: aload         6
     320: aload_1
     321: iload         8
     323: iload_3
     324: iload         4
     326: iload         7
     328: iload         9
     330: invokestatic  #37                 // Method bitMatrixFromEncoder:(Lcom/google/zxing/pdf417/encoder/PDF417;Ljava/lang/String;IIIIZ)Lcom/google/zxing/common/BitMatrix;
     333: areturn

  public com.google.zxing.common.BitMatrix encode(java.lang.String, com.google.zxing.BarcodeFormat, int, int) throws com.google.zxing.WriterException;
    Code:
       0: aload_0
       1: aload_1
       2: aload_2
       3: iload_3
       4: iload         4
       6: aconst_null
       7: invokevirtual #38                 // Method encode:(Ljava/lang/String;Lcom/google/zxing/BarcodeFormat;IILjava/util/Map;)Lcom/google/zxing/common/BitMatrix;
      10: areturn

  private static com.google.zxing.common.BitMatrix bitMatrixFromEncoder(com.google.zxing.pdf417.encoder.PDF417, java.lang.String, int, int, int, int, boolean) throws com.google.zxing.WriterException;
    Code:
       0: aload_0
       1: aload_1
       2: iload_2
       3: iload         6
       5: invokevirtual #39                 // Method com/google/zxing/pdf417/encoder/PDF417.generateBarcodeLogic:(Ljava/lang/String;IZ)V
       8: iconst_4
       9: istore        7
      11: aload_0
      12: invokevirtual #40                 // Method com/google/zxing/pdf417/encoder/PDF417.getBarcodeMatrix:()Lcom/google/zxing/pdf417/encoder/BarcodeMatrix;
      15: iconst_1
      16: iload         7
      18: invokevirtual #41                 // Method com/google/zxing/pdf417/encoder/BarcodeMatrix.getScaledMatrix:(II)[[B
      21: astore        8
      23: iconst_0
      24: istore        9
      26: iload         4
      28: iload_3
      29: if_icmple     36
      32: iconst_1
      33: goto          37
      36: iconst_0
      37: aload         8
      39: iconst_0
      40: aaload
      41: arraylength
      42: aload         8
      44: arraylength
      45: if_icmpge     52
      48: iconst_1
      49: goto          53
      52: iconst_0
      53: if_icmpeq     66
      56: aload         8
      58: invokestatic  #42                 // Method rotateArray:([[B)[[B
      61: astore        8
      63: iconst_1
      64: istore        9
      66: iload_3
      67: aload         8
      69: iconst_0
      70: aaload
      71: arraylength
      72: idiv
      73: istore        10
      75: iload         4
      77: aload         8
      79: arraylength
      80: idiv
      81: istore        11
      83: iload         10
      85: iload         11
      87: invokestatic  #43                 // Method java/lang/Math.min:(II)I
      90: istore        12
      92: iload         12
      94: iconst_1
      95: if_icmple     134
      98: aload_0
      99: invokevirtual #40                 // Method com/google/zxing/pdf417/encoder/PDF417.getBarcodeMatrix:()Lcom/google/zxing/pdf417/encoder/BarcodeMatrix;
     102: iload         12
     104: iload         12
     106: iload         7
     108: imul
     109: invokevirtual #41                 // Method com/google/zxing/pdf417/encoder/BarcodeMatrix.getScaledMatrix:(II)[[B
     112: astore        13
     114: iload         9
     116: ifeq          126
     119: aload         13
     121: invokestatic  #42                 // Method rotateArray:([[B)[[B
     124: astore        13
     126: aload         13
     128: iload         5
     130: invokestatic  #44                 // Method bitMatrixFromBitArray:([[BI)Lcom/google/zxing/common/BitMatrix;
     133: areturn
     134: aload         8
     136: iload         5
     138: invokestatic  #44                 // Method bitMatrixFromBitArray:([[BI)Lcom/google/zxing/common/BitMatrix;
     141: areturn

  private static com.google.zxing.common.BitMatrix bitMatrixFromBitArray(byte[][], int);
    Code:
       0: new           #45                 // class com/google/zxing/common/BitMatrix
       3: dup
       4: aload_0
       5: iconst_0
       6: aaload
       7: arraylength
       8: iconst_2
       9: iload_1
      10: imul
      11: iadd
      12: aload_0
      13: arraylength
      14: iconst_2
      15: iload_1
      16: imul
      17: iadd
      18: invokespecial #46                 // Method com/google/zxing/common/BitMatrix."<init>":(II)V
      21: astore_2
      22: aload_2
      23: invokevirtual #47                 // Method com/google/zxing/common/BitMatrix.clear:()V
      26: iconst_0
      27: istore_3
      28: aload_2
      29: invokevirtual #48                 // Method com/google/zxing/common/BitMatrix.getHeight:()I
      32: iload_1
      33: isub
      34: iconst_1
      35: isub
      36: istore        4
      38: iload_3
      39: aload_0
      40: arraylength
      41: if_icmpge     95
      44: aload_0
      45: iload_3
      46: aaload
      47: astore        5
      49: iconst_0
      50: istore        6
      52: iload         6
      54: aload_0
      55: iconst_0
      56: aaload
      57: arraylength
      58: if_icmpge     86
      61: aload         5
      63: iload         6
      65: baload
      66: iconst_1
      67: if_icmpne     80
      70: aload_2
      71: iload         6
      73: iload_1
      74: iadd
      75: iload         4
      77: invokevirtual #49                 // Method com/google/zxing/common/BitMatrix.set:(II)V
      80: iinc          6, 1
      83: goto          52
      86: iinc          3, 1
      89: iinc          4, -1
      92: goto          38
      95: aload_2
      96: areturn

  private static byte[][] rotateArray(byte[][]);
    Code:
       0: aload_0
       1: iconst_0
       2: aaload
       3: arraylength
       4: aload_0
       5: arraylength
       6: multianewarray #50,  2            // class "[[B"
      10: astore_1
      11: iconst_0
      12: istore_2
      13: iload_2
      14: aload_0
      15: arraylength
      16: if_icmpge     62
      19: aload_0
      20: arraylength
      21: iload_2
      22: isub
      23: iconst_1
      24: isub
      25: istore_3
      26: iconst_0
      27: istore        4
      29: iload         4
      31: aload_0
      32: iconst_0
      33: aaload
      34: arraylength
      35: if_icmpge     56
      38: aload_1
      39: iload         4
      41: aaload
      42: iload_3
      43: aload_0
      44: iload_2
      45: aaload
      46: iload         4
      48: baload
      49: bastore
      50: iinc          4, 1
      53: goto          29
      56: iinc          2, 1
      59: goto          13
      62: aload_1
      63: areturn
}
