Compiled from "PDF417ResultMetadata.java"
public final class com.google.zxing.pdf417.PDF417ResultMetadata {
  private int segmentIndex;

  private java.lang.String fileId;

  private boolean lastSegment;

  private int segmentCount;

  private java.lang.String sender;

  private java.lang.String addressee;

  private java.lang.String fileName;

  private long fileSize;

  private long timestamp;

  private int checksum;

  private int[] optionalData;

  public com.google.zxing.pdf417.PDF417ResultMetadata();
    Code:
       0: aload_0
       1: invokespecial #1                  // Method java/lang/Object."<init>":()V
       4: aload_0
       5: iconst_m1
       6: putfield      #2                  // Field segmentCount:I
       9: aload_0
      10: ldc2_w        #3                  // long -1l
      13: putfield      #5                  // Field fileSize:J
      16: aload_0
      17: ldc2_w        #3                  // long -1l
      20: putfield      #6                  // Field timestamp:J
      23: aload_0
      24: iconst_m1
      25: putfield      #7                  // Field checksum:I
      28: return

  public int getSegmentIndex();
    Code:
       0: aload_0
       1: getfield      #8                  // Field segmentIndex:I
       4: ireturn

  public void setSegmentIndex(int);
    Code:
       0: aload_0
       1: iload_1
       2: putfield      #8                  // Field segmentIndex:I
       5: return

  public java.lang.String getFileId();
    Code:
       0: aload_0
       1: getfield      #9                  // Field fileId:Ljava/lang/String;
       4: areturn

  public void setFileId(java.lang.String);
    Code:
       0: aload_0
       1: aload_1
       2: putfield      #9                  // Field fileId:Ljava/lang/String;
       5: return

  public int[] getOptionalData();
    Code:
       0: aload_0
       1: getfield      #10                 // Field optionalData:[I
       4: areturn

  public void setOptionalData(int[]);
    Code:
       0: aload_0
       1: aload_1
       2: putfield      #10                 // Field optionalData:[I
       5: return

  public boolean isLastSegment();
    Code:
       0: aload_0
       1: getfield      #11                 // Field lastSegment:Z
       4: ireturn

  public void setLastSegment(boolean);
    Code:
       0: aload_0
       1: iload_1
       2: putfield      #11                 // Field lastSegment:Z
       5: return

  public int getSegmentCount();
    Code:
       0: aload_0
       1: getfield      #2                  // Field segmentCount:I
       4: ireturn

  public void setSegmentCount(int);
    Code:
       0: aload_0
       1: iload_1
       2: putfield      #2                  // Field segmentCount:I
       5: return

  public java.lang.String getSender();
    Code:
       0: aload_0
       1: getfield      #12                 // Field sender:Ljava/lang/String;
       4: areturn

  public void setSender(java.lang.String);
    Code:
       0: aload_0
       1: aload_1
       2: putfield      #12                 // Field sender:Ljava/lang/String;
       5: return

  public java.lang.String getAddressee();
    Code:
       0: aload_0
       1: getfield      #13                 // Field addressee:Ljava/lang/String;
       4: areturn

  public void setAddressee(java.lang.String);
    Code:
       0: aload_0
       1: aload_1
       2: putfield      #13                 // Field addressee:Ljava/lang/String;
       5: return

  public java.lang.String getFileName();
    Code:
       0: aload_0
       1: getfield      #14                 // Field fileName:Ljava/lang/String;
       4: areturn

  public void setFileName(java.lang.String);
    Code:
       0: aload_0
       1: aload_1
       2: putfield      #14                 // Field fileName:Ljava/lang/String;
       5: return

  public long getFileSize();
    Code:
       0: aload_0
       1: getfield      #5                  // Field fileSize:J
       4: lreturn

  public void setFileSize(long);
    Code:
       0: aload_0
       1: lload_1
       2: putfield      #5                  // Field fileSize:J
       5: return

  public int getChecksum();
    Code:
       0: aload_0
       1: getfield      #7                  // Field checksum:I
       4: ireturn

  public void setChecksum(int);
    Code:
       0: aload_0
       1: iload_1
       2: putfield      #7                  // Field checksum:I
       5: return

  public long getTimestamp();
    Code:
       0: aload_0
       1: getfield      #6                  // Field timestamp:J
       4: lreturn

  public void setTimestamp(long);
    Code:
       0: aload_0
       1: lload_1
       2: putfield      #6                  // Field timestamp:J
       5: return
}
