Compiled from "PDF417Reader.java"
public final class com.google.zxing.pdf417.PDF417Reader implements com.google.zxing.Reader,com.google.zxing.multi.MultipleBarcodeReader {
  private static final com.google.zxing.Result[] EMPTY_RESULT_ARRAY;

  public com.google.zxing.pdf417.PDF417Reader();
    Code:
       0: aload_0
       1: invokespecial #1                  // Method java/lang/Object."<init>":()V
       4: return

  public com.google.zxing.Result decode(com.google.zxing.BinaryBitmap) throws com.google.zxing.NotFoundException, com.google.zxing.FormatException, com.google.zxing.ChecksumException;
    Code:
       0: aload_0
       1: aload_1
       2: aconst_null
       3: invokevirtual #2                  // Method decode:(Lcom/google/zxing/BinaryBitmap;Ljava/util/Map;)Lcom/google/zxing/Result;
       6: areturn

  public com.google.zxing.Result decode(com.google.zxing.BinaryBitmap, java.util.Map<com.google.zxing.DecodeHintType, ?>) throws com.google.zxing.NotFoundException, com.google.zxing.FormatException, com.google.zxing.ChecksumException;
    Code:
       0: aload_1
       1: aload_2
       2: iconst_0
       3: invokestatic  #3                  // Method decode:(Lcom/google/zxing/BinaryBitmap;Ljava/util/Map;Z)[Lcom/google/zxing/Result;
       6: astore_3
       7: aload_3
       8: arraylength
       9: ifeq          18
      12: aload_3
      13: iconst_0
      14: aaload
      15: ifnonnull     22
      18: invokestatic  #4                  // Method com/google/zxing/NotFoundException.getNotFoundInstance:()Lcom/google/zxing/NotFoundException;
      21: athrow
      22: aload_3
      23: iconst_0
      24: aaload
      25: areturn

  public com.google.zxing.Result[] decodeMultiple(com.google.zxing.BinaryBitmap) throws com.google.zxing.NotFoundException;
    Code:
       0: aload_0
       1: aload_1
       2: aconst_null
       3: invokevirtual #5                  // Method decodeMultiple:(Lcom/google/zxing/BinaryBitmap;Ljava/util/Map;)[Lcom/google/zxing/Result;
       6: areturn

  public com.google.zxing.Result[] decodeMultiple(com.google.zxing.BinaryBitmap, java.util.Map<com.google.zxing.DecodeHintType, ?>) throws com.google.zxing.NotFoundException;
    Code:
       0: aload_1
       1: aload_2
       2: iconst_1
       3: invokestatic  #3                  // Method decode:(Lcom/google/zxing/BinaryBitmap;Ljava/util/Map;Z)[Lcom/google/zxing/Result;
       6: areturn
       7: astore_3
       8: invokestatic  #4                  // Method com/google/zxing/NotFoundException.getNotFoundInstance:()Lcom/google/zxing/NotFoundException;
      11: athrow
    Exception table:
       from    to  target type
           0     6     7   Class com/google/zxing/FormatException
           0     6     7   Class com/google/zxing/ChecksumException

  private static com.google.zxing.Result[] decode(com.google.zxing.BinaryBitmap, java.util.Map<com.google.zxing.DecodeHintType, ?>, boolean) throws com.google.zxing.NotFoundException, com.google.zxing.FormatException, com.google.zxing.ChecksumException;
    Code:
       0: new           #8                  // class java/util/ArrayList
       3: dup
       4: invokespecial #9                  // Method java/util/ArrayList."<init>":()V
       7: astore_3
       8: aload_0
       9: aload_1
      10: iload_2
      11: invokestatic  #10                 // Method com/google/zxing/pdf417/detector/Detector.detect:(Lcom/google/zxing/BinaryBitmap;Ljava/util/Map;Z)Lcom/google/zxing/pdf417/detector/PDF417DetectorResult;
      14: astore        4
      16: aload         4
      18: invokevirtual #11                 // Method com/google/zxing/pdf417/detector/PDF417DetectorResult.getPoints:()Ljava/util/List;
      21: invokeinterface #12,  1           // InterfaceMethod java/util/List.iterator:()Ljava/util/Iterator;
      26: astore        5
      28: aload         5
      30: invokeinterface #13,  1           // InterfaceMethod java/util/Iterator.hasNext:()Z
      35: ifeq          209
      38: aload         5
      40: invokeinterface #14,  1           // InterfaceMethod java/util/Iterator.next:()Ljava/lang/Object;
      45: checkcast     #15                 // class "[Lcom/google/zxing/ResultPoint;"
      48: astore        6
      50: aload         4
      52: invokevirtual #16                 // Method com/google/zxing/pdf417/detector/PDF417DetectorResult.getBits:()Lcom/google/zxing/common/BitMatrix;
      55: aload         6
      57: iconst_4
      58: aaload
      59: aload         6
      61: iconst_5
      62: aaload
      63: aload         6
      65: bipush        6
      67: aaload
      68: aload         6
      70: bipush        7
      72: aaload
      73: aload         6
      75: invokestatic  #17                 // Method getMinCodewordWidth:([Lcom/google/zxing/ResultPoint;)I
      78: aload         6
      80: invokestatic  #18                 // Method getMaxCodewordWidth:([Lcom/google/zxing/ResultPoint;)I
      83: invokestatic  #19                 // Method com/google/zxing/pdf417/decoder/PDF417ScanningDecoder.decode:(Lcom/google/zxing/common/BitMatrix;Lcom/google/zxing/ResultPoint;Lcom/google/zxing/ResultPoint;Lcom/google/zxing/ResultPoint;Lcom/google/zxing/ResultPoint;II)Lcom/google/zxing/common/DecoderResult;
      86: astore        7
      88: new           #20                 // class com/google/zxing/Result
      91: dup
      92: aload         7
      94: invokevirtual #21                 // Method com/google/zxing/common/DecoderResult.getText:()Ljava/lang/String;
      97: aload         7
      99: invokevirtual #22                 // Method com/google/zxing/common/DecoderResult.getRawBytes:()[B
     102: aload         6
     104: getstatic     #23                 // Field com/google/zxing/BarcodeFormat.PDF_417:Lcom/google/zxing/BarcodeFormat;
     107: invokespecial #24                 // Method com/google/zxing/Result."<init>":(Ljava/lang/String;[B[Lcom/google/zxing/ResultPoint;Lcom/google/zxing/BarcodeFormat;)V
     110: astore        8
     112: aload         8
     114: getstatic     #25                 // Field com/google/zxing/ResultMetadataType.ERROR_CORRECTION_LEVEL:Lcom/google/zxing/ResultMetadataType;
     117: aload         7
     119: invokevirtual #26                 // Method com/google/zxing/common/DecoderResult.getECLevel:()Ljava/lang/String;
     122: invokevirtual #27                 // Method com/google/zxing/Result.putMetadata:(Lcom/google/zxing/ResultMetadataType;Ljava/lang/Object;)V
     125: aload         7
     127: invokevirtual #28                 // Method com/google/zxing/common/DecoderResult.getOther:()Ljava/lang/Object;
     130: checkcast     #29                 // class com/google/zxing/pdf417/PDF417ResultMetadata
     133: astore        9
     135: aload         9
     137: ifnull        150
     140: aload         8
     142: getstatic     #30                 // Field com/google/zxing/ResultMetadataType.PDF417_EXTRA_METADATA:Lcom/google/zxing/ResultMetadataType;
     145: aload         9
     147: invokevirtual #27                 // Method com/google/zxing/Result.putMetadata:(Lcom/google/zxing/ResultMetadataType;Ljava/lang/Object;)V
     150: aload         8
     152: getstatic     #31                 // Field com/google/zxing/ResultMetadataType.ORIENTATION:Lcom/google/zxing/ResultMetadataType;
     155: aload         4
     157: invokevirtual #32                 // Method com/google/zxing/pdf417/detector/PDF417DetectorResult.getRotation:()I
     160: invokestatic  #33                 // Method java/lang/Integer.valueOf:(I)Ljava/lang/Integer;
     163: invokevirtual #27                 // Method com/google/zxing/Result.putMetadata:(Lcom/google/zxing/ResultMetadataType;Ljava/lang/Object;)V
     166: aload         8
     168: getstatic     #34                 // Field com/google/zxing/ResultMetadataType.SYMBOLOGY_IDENTIFIER:Lcom/google/zxing/ResultMetadataType;
     171: new           #35                 // class java/lang/StringBuilder
     174: dup
     175: invokespecial #36                 // Method java/lang/StringBuilder."<init>":()V
     178: ldc           #37                 // String ]L
     180: invokevirtual #38                 // Method java/lang/StringBuilder.append:(Ljava/lang/String;)Ljava/lang/StringBuilder;
     183: aload         7
     185: invokevirtual #39                 // Method com/google/zxing/common/DecoderResult.getSymbologyModifier:()I
     188: invokevirtual #40                 // Method java/lang/StringBuilder.append:(I)Ljava/lang/StringBuilder;
     191: invokevirtual #41                 // Method java/lang/StringBuilder.toString:()Ljava/lang/String;
     194: invokevirtual #27                 // Method com/google/zxing/Result.putMetadata:(Lcom/google/zxing/ResultMetadataType;Ljava/lang/Object;)V
     197: aload_3
     198: aload         8
     200: invokeinterface #42,  2           // InterfaceMethod java/util/List.add:(Ljava/lang/Object;)Z
     205: pop
     206: goto          28
     209: aload_3
     210: getstatic     #43                 // Field EMPTY_RESULT_ARRAY:[Lcom/google/zxing/Result;
     213: invokeinterface #44,  2           // InterfaceMethod java/util/List.toArray:([Ljava/lang/Object;)[Ljava/lang/Object;
     218: checkcast     #45                 // class "[Lcom/google/zxing/Result;"
     221: areturn

  private static int getMaxWidth(com.google.zxing.ResultPoint, com.google.zxing.ResultPoint);
    Code:
       0: aload_0
       1: ifnull        8
       4: aload_1
       5: ifnonnull     10
       8: iconst_0
       9: ireturn
      10: aload_0
      11: invokevirtual #46                 // Method com/google/zxing/ResultPoint.getX:()F
      14: aload_1
      15: invokevirtual #46                 // Method com/google/zxing/ResultPoint.getX:()F
      18: fsub
      19: invokestatic  #47                 // Method java/lang/Math.abs:(F)F
      22: f2i
      23: ireturn

  private static int getMinWidth(com.google.zxing.ResultPoint, com.google.zxing.ResultPoint);
    Code:
       0: aload_0
       1: ifnull        8
       4: aload_1
       5: ifnonnull     11
       8: ldc           #49                 // int 2147483647
      10: ireturn
      11: aload_0
      12: invokevirtual #46                 // Method com/google/zxing/ResultPoint.getX:()F
      15: aload_1
      16: invokevirtual #46                 // Method com/google/zxing/ResultPoint.getX:()F
      19: fsub
      20: invokestatic  #47                 // Method java/lang/Math.abs:(F)F
      23: f2i
      24: ireturn

  private static int getMaxCodewordWidth(com.google.zxing.ResultPoint[]);
    Code:
       0: aload_0
       1: iconst_0
       2: aaload
       3: aload_0
       4: iconst_4
       5: aaload
       6: invokestatic  #50                 // Method getMaxWidth:(Lcom/google/zxing/ResultPoint;Lcom/google/zxing/ResultPoint;)I
       9: aload_0
      10: bipush        6
      12: aaload
      13: aload_0
      14: iconst_2
      15: aaload
      16: invokestatic  #50                 // Method getMaxWidth:(Lcom/google/zxing/ResultPoint;Lcom/google/zxing/ResultPoint;)I
      19: bipush        17
      21: imul
      22: bipush        18
      24: idiv
      25: invokestatic  #52                 // Method java/lang/Math.max:(II)I
      28: aload_0
      29: iconst_1
      30: aaload
      31: aload_0
      32: iconst_5
      33: aaload
      34: invokestatic  #50                 // Method getMaxWidth:(Lcom/google/zxing/ResultPoint;Lcom/google/zxing/ResultPoint;)I
      37: aload_0
      38: bipush        7
      40: aaload
      41: aload_0
      42: iconst_3
      43: aaload
      44: invokestatic  #50                 // Method getMaxWidth:(Lcom/google/zxing/ResultPoint;Lcom/google/zxing/ResultPoint;)I
      47: bipush        17
      49: imul
      50: bipush        18
      52: idiv
      53: invokestatic  #52                 // Method java/lang/Math.max:(II)I
      56: invokestatic  #52                 // Method java/lang/Math.max:(II)I
      59: ireturn

  private static int getMinCodewordWidth(com.google.zxing.ResultPoint[]);
    Code:
       0: aload_0
       1: iconst_0
       2: aaload
       3: aload_0
       4: iconst_4
       5: aaload
       6: invokestatic  #53                 // Method getMinWidth:(Lcom/google/zxing/ResultPoint;Lcom/google/zxing/ResultPoint;)I
       9: aload_0
      10: bipush        6
      12: aaload
      13: aload_0
      14: iconst_2
      15: aaload
      16: invokestatic  #53                 // Method getMinWidth:(Lcom/google/zxing/ResultPoint;Lcom/google/zxing/ResultPoint;)I
      19: bipush        17
      21: imul
      22: bipush        18
      24: idiv
      25: invokestatic  #54                 // Method java/lang/Math.min:(II)I
      28: aload_0
      29: iconst_1
      30: aaload
      31: aload_0
      32: iconst_5
      33: aaload
      34: invokestatic  #53                 // Method getMinWidth:(Lcom/google/zxing/ResultPoint;Lcom/google/zxing/ResultPoint;)I
      37: aload_0
      38: bipush        7
      40: aaload
      41: aload_0
      42: iconst_3
      43: aaload
      44: invokestatic  #53                 // Method getMinWidth:(Lcom/google/zxing/ResultPoint;Lcom/google/zxing/ResultPoint;)I
      47: bipush        17
      49: imul
      50: bipush        18
      52: idiv
      53: invokestatic  #54                 // Method java/lang/Math.min:(II)I
      56: invokestatic  #54                 // Method java/lang/Math.min:(II)I
      59: ireturn

  public void reset();
    Code:
       0: return

  static {};
    Code:
       0: iconst_0
       1: anewarray     #20                 // class com/google/zxing/Result
       4: putstatic     #43                 // Field EMPTY_RESULT_ARRAY:[Lcom/google/zxing/Result;
       7: return
}
