Compiled from "JsonMixinModuleEntriesBeanRegistrationAotProcessor.java"
class org.springframework.boot.jackson.JsonMixinModuleEntriesBeanRegistrationAotProcessor implements org.springframework.beans.factory.aot.BeanRegistrationAotProcessor {
  org.springframework.boot.jackson.JsonMixinModuleEntriesBeanRegistrationAotProcessor();
    Code:
       0: aload_0
       1: invokespecial #1                  // Method java/lang/Object."<init>":()V
       4: return

  public org.springframework.beans.factory.aot.BeanRegistrationAotContribution processAheadOfTime(org.springframework.beans.factory.support.RegisteredBean);
    Code:
       0: aload_1
       1: invokevirtual #7                  // Method org/springframework/beans/factory/support/RegisteredBean.getBeanClass:()Ljava/lang/Class;
       4: ldc           #13                 // class org/springframework/boot/jackson/JsonMixinModuleEntries
       6: invokevirtual #15                 // Method java/lang/Object.equals:(Ljava/lang/Object;)Z
       9: ifeq          22
      12: aload_1
      13: invokedynamic #19,  0             // InvokeDynamic #0:apply:(Lorg/springframework/beans/factory/support/RegisteredBean;)Ljava/util/function/UnaryOperator;
      18: invokestatic  #23                 // InterfaceMethod org/springframework/beans/factory/aot/BeanRegistrationAotContribution.withCustomCodeFragments:(Ljava/util/function/UnaryOperator;)Lorg/springframework/beans/factory/aot/BeanRegistrationAotContribution;
      21: areturn
      22: aconst_null
      23: areturn

  private static org.springframework.beans.factory.aot.BeanRegistrationCodeFragments lambda$processAheadOfTime$0(org.springframework.beans.factory.support.RegisteredBean, org.springframework.beans.factory.aot.BeanRegistrationCodeFragments);
    Code:
       0: new           #29                 // class org/springframework/boot/jackson/JsonMixinModuleEntriesBeanRegistrationAotProcessor$AotContribution
       3: dup
       4: aload_1
       5: aload_0
       6: invokespecial #31                 // Method org/springframework/boot/jackson/JsonMixinModuleEntriesBeanRegistrationAotProcessor$AotContribution."<init>":(Lorg/springframework/beans/factory/aot/BeanRegistrationCodeFragments;Lorg/springframework/beans/factory/support/RegisteredBean;)V
       9: areturn
}
