Compiled from "JsonMixinModuleEntriesBeanRegistrationAotProcessor.java"
class org.springframework.boot.jackson.JsonMixinModuleEntriesBeanRegistrationAotProcessor$AotContribution extends org.springframework.beans.factory.aot.BeanRegistrationCodeFragmentsDecorator {
  private final org.springframework.beans.factory.support.RegisteredBean registeredBean;

  private final java.lang.ClassLoader classLoader;

  org.springframework.boot.jackson.JsonMixinModuleEntriesBeanRegistrationAotProcessor$AotContribution(org.springframework.beans.factory.aot.BeanRegistrationCodeFragments, org.springframework.beans.factory.support.RegisteredBean);
    Code:
       0: aload_0
       1: aload_1
       2: invokespecial #1                  // Method org/springframework/beans/factory/aot/BeanRegistrationCodeFragmentsDecorator."<init>":(Lorg/springframework/beans/factory/aot/BeanRegistrationCodeFragments;)V
       5: aload_0
       6: aload_2
       7: putfield      #7                  // Field registeredBean:Lorg/springframework/beans/factory/support/RegisteredBean;
      10: aload_0
      11: aload_2
      12: invokevirtual #13                 // Method org/springframework/beans/factory/support/RegisteredBean.getBeanFactory:()Lorg/springframework/beans/factory/config/ConfigurableListableBeanFactory;
      15: invokeinterface #19,  1           // InterfaceMethod org/springframework/beans/factory/config/ConfigurableListableBeanFactory.getBeanClassLoader:()Ljava/lang/ClassLoader;
      20: putfield      #25                 // Field classLoader:Ljava/lang/ClassLoader;
      23: return

  public org.springframework.javapoet.CodeBlock generateInstanceSupplierCode(org.springframework.aot.generate.GenerationContext, org.springframework.beans.factory.aot.BeanRegistrationCode, java.lang.reflect.Executable, boolean);
    Code:
       0: aload_0
       1: getfield      #7                  // Field registeredBean:Lorg/springframework/beans/factory/support/RegisteredBean;
       4: invokevirtual #13                 // Method org/springframework/beans/factory/support/RegisteredBean.getBeanFactory:()Lorg/springframework/beans/factory/config/ConfigurableListableBeanFactory;
       7: aload_0
       8: getfield      #7                  // Field registeredBean:Lorg/springframework/beans/factory/support/RegisteredBean;
      11: invokevirtual #29                 // Method org/springframework/beans/factory/support/RegisteredBean.getBeanName:()Ljava/lang/String;
      14: ldc           #33                 // class org/springframework/boot/jackson/JsonMixinModuleEntries
      16: invokeinterface #35,  3           // InterfaceMethod org/springframework/beans/factory/config/ConfigurableListableBeanFactory.getBean:(Ljava/lang/String;Ljava/lang/Class;)Ljava/lang/Object;
      21: checkcast     #33                 // class org/springframework/boot/jackson/JsonMixinModuleEntries
      24: astore        5
      26: aload_0
      27: aload_1
      28: invokeinterface #39,  1           // InterfaceMethod org/springframework/aot/generate/GenerationContext.getRuntimeHints:()Lorg/springframework/aot/hint/RuntimeHints;
      33: aload         5
      35: invokevirtual #45                 // Method contributeHints:(Lorg/springframework/aot/hint/RuntimeHints;Lorg/springframework/boot/jackson/JsonMixinModuleEntries;)V
      38: aload_2
      39: invokeinterface #49,  1           // InterfaceMethod org/springframework/beans/factory/aot/BeanRegistrationCode.getMethods:()Lorg/springframework/aot/generate/GeneratedMethods;
      44: ldc           #55                 // String getInstance
      46: aload_0
      47: aload         5
      49: invokedynamic #57,  0             // InvokeDynamic #0:accept:(Lorg/springframework/boot/jackson/JsonMixinModuleEntriesBeanRegistrationAotProcessor$AotContribution;Lorg/springframework/boot/jackson/JsonMixinModuleEntries;)Ljava/util/function/Consumer;
      54: invokevirtual #61                 // Method org/springframework/aot/generate/GeneratedMethods.add:(Ljava/lang/String;Ljava/util/function/Consumer;)Lorg/springframework/aot/generate/GeneratedMethod;
      57: astore        6
      59: aload         6
      61: invokevirtual #67                 // Method org/springframework/aot/generate/GeneratedMethod.toMethodReference:()Lorg/springframework/aot/generate/MethodReference;
      64: invokeinterface #73,  1           // InterfaceMethod org/springframework/aot/generate/MethodReference.toCodeBlock:()Lorg/springframework/javapoet/CodeBlock;
      69: areturn

  private void addEntryCode(org.springframework.javapoet.CodeBlock$Builder, java.lang.Class<?>, java.lang.Class<?>);
    Code:
       0: iconst_2
       1: anewarray     #79                 // class org/springframework/aot/generate/AccessControl
       4: dup
       5: iconst_0
       6: aload_2
       7: invokestatic  #81                 // Method org/springframework/aot/generate/AccessControl.forClass:(Ljava/lang/Class;)Lorg/springframework/aot/generate/AccessControl;
      10: aastore
      11: dup
      12: iconst_1
      13: aload_3
      14: invokestatic  #81                 // Method org/springframework/aot/generate/AccessControl.forClass:(Ljava/lang/Class;)Lorg/springframework/aot/generate/AccessControl;
      17: aastore
      18: invokestatic  #85                 // Method org/springframework/aot/generate/AccessControl.lowest:([Lorg/springframework/aot/generate/AccessControl;)Lorg/springframework/aot/generate/AccessControl;
      21: astore        4
      23: aload         4
      25: invokevirtual #89                 // Method org/springframework/aot/generate/AccessControl.isPublic:()Z
      28: ifeq          58
      31: aload_1
      32: ldc           #93                 // String $L.and($T.class, $T.class)
      34: iconst_3
      35: anewarray     #95                 // class java/lang/Object
      38: dup
      39: iconst_0
      40: ldc           #97                 // String mixins
      42: aastore
      43: dup
      44: iconst_1
      45: aload_2
      46: aastore
      47: dup
      48: iconst_2
      49: aload_3
      50: aastore
      51: invokevirtual #99                 // Method org/springframework/javapoet/CodeBlock$Builder.addStatement:(Ljava/lang/String;[Ljava/lang/Object;)Lorg/springframework/javapoet/CodeBlock$Builder;
      54: pop
      55: goto          88
      58: aload_1
      59: ldc           #105                // String $L.and($S, $S)
      61: iconst_3
      62: anewarray     #95                 // class java/lang/Object
      65: dup
      66: iconst_0
      67: ldc           #97                 // String mixins
      69: aastore
      70: dup
      71: iconst_1
      72: aload_2
      73: invokevirtual #107                // Method java/lang/Class.getName:()Ljava/lang/String;
      76: aastore
      77: dup
      78: iconst_2
      79: aload_3
      80: invokevirtual #107                // Method java/lang/Class.getName:()Ljava/lang/String;
      83: aastore
      84: invokevirtual #99                 // Method org/springframework/javapoet/CodeBlock$Builder.addStatement:(Ljava/lang/String;[Ljava/lang/Object;)Lorg/springframework/javapoet/CodeBlock$Builder;
      87: pop
      88: return

  private void contributeHints(org.springframework.aot.hint.RuntimeHints, org.springframework.boot.jackson.JsonMixinModuleEntries);
    Code:
       0: new           #112                // class java/util/LinkedHashSet
       3: dup
       4: invokespecial #114                // Method java/util/LinkedHashSet."<init>":()V
       7: astore_3
       8: aload_2
       9: aload_0
      10: getfield      #25                 // Field classLoader:Ljava/lang/ClassLoader;
      13: aload_3
      14: invokedynamic #117,  0            // InvokeDynamic #1:accept:(Ljava/util/Set;)Ljava/util/function/BiConsumer;
      19: invokevirtual #120                // Method org/springframework/boot/jackson/JsonMixinModuleEntries.doWithEntry:(Ljava/lang/ClassLoader;Ljava/util/function/BiConsumer;)V
      22: new           #124                // class org/springframework/aot/hint/BindingReflectionHintsRegistrar
      25: dup
      26: invokespecial #126                // Method org/springframework/aot/hint/BindingReflectionHintsRegistrar."<init>":()V
      29: aload_1
      30: invokevirtual #127                // Method org/springframework/aot/hint/RuntimeHints.reflection:()Lorg/springframework/aot/hint/ReflectionHints;
      33: aload_3
      34: invokedynamic #133,  0            // InvokeDynamic #2:apply:()Ljava/util/function/IntFunction;
      39: invokeinterface #137,  2          // InterfaceMethod java/util/Set.toArray:(Ljava/util/function/IntFunction;)[Ljava/lang/Object;
      44: checkcast     #143                // class "[Ljava/lang/reflect/Type;"
      47: invokevirtual #145                // Method org/springframework/aot/hint/BindingReflectionHintsRegistrar.registerReflectionHints:(Lorg/springframework/aot/hint/ReflectionHints;[Ljava/lang/reflect/Type;)V
      50: return

  private static java.lang.Class[] lambda$contributeHints$3(int);
    Code:
       0: iload_0
       1: anewarray     #108                // class java/lang/Class
       4: areturn

  private static void lambda$contributeHints$2(java.util.Set, java.lang.Class, java.lang.Class);
    Code:
       0: aload_0
       1: aload_2
       2: invokeinterface #149,  2          // InterfaceMethod java/util/Set.add:(Ljava/lang/Object;)Z
       7: pop
       8: return

  private void lambda$generateInstanceSupplierCode$1(org.springframework.boot.jackson.JsonMixinModuleEntries, org.springframework.javapoet.MethodSpec$Builder);
    Code:
       0: ldc           #33                 // class org/springframework/boot/jackson/JsonMixinModuleEntries
       2: astore_3
       3: aload_2
       4: ldc           #152                // String Get the bean instance for \'$L\'.
       6: iconst_1
       7: anewarray     #95                 // class java/lang/Object
      10: dup
      11: iconst_0
      12: aload_0
      13: getfield      #7                  // Field registeredBean:Lorg/springframework/beans/factory/support/RegisteredBean;
      16: invokevirtual #29                 // Method org/springframework/beans/factory/support/RegisteredBean.getBeanName:()Ljava/lang/String;
      19: aastore
      20: invokevirtual #154                // Method org/springframework/javapoet/MethodSpec$Builder.addJavadoc:(Ljava/lang/String;[Ljava/lang/Object;)Lorg/springframework/javapoet/MethodSpec$Builder;
      23: pop
      24: aload_2
      25: iconst_2
      26: anewarray     #160                // class javax/lang/model/element/Modifier
      29: dup
      30: iconst_0
      31: getstatic     #162                // Field javax/lang/model/element/Modifier.PRIVATE:Ljavax/lang/model/element/Modifier;
      34: aastore
      35: dup
      36: iconst_1
      37: getstatic     #166                // Field javax/lang/model/element/Modifier.STATIC:Ljavax/lang/model/element/Modifier;
      40: aastore
      41: invokevirtual #169                // Method org/springframework/javapoet/MethodSpec$Builder.addModifiers:([Ljavax/lang/model/element/Modifier;)Lorg/springframework/javapoet/MethodSpec$Builder;
      44: pop
      45: aload_2
      46: aload_3
      47: invokevirtual #173                // Method org/springframework/javapoet/MethodSpec$Builder.returns:(Ljava/lang/reflect/Type;)Lorg/springframework/javapoet/MethodSpec$Builder;
      50: pop
      51: invokestatic  #177                // Method org/springframework/javapoet/CodeBlock.builder:()Lorg/springframework/javapoet/CodeBlock$Builder;
      54: astore        4
      56: aload         4
      58: ldc           #183                // String return $T.create(
      60: iconst_1
      61: anewarray     #95                 // class java/lang/Object
      64: dup
      65: iconst_0
      66: ldc           #33                 // class org/springframework/boot/jackson/JsonMixinModuleEntries
      68: aastore
      69: invokevirtual #185                // Method org/springframework/javapoet/CodeBlock$Builder.add:(Ljava/lang/String;[Ljava/lang/Object;)Lorg/springframework/javapoet/CodeBlock$Builder;
      72: ldc           #187                // String (mixins) ->
      74: iconst_0
      75: anewarray     #95                 // class java/lang/Object
      78: invokevirtual #189                // Method org/springframework/javapoet/CodeBlock$Builder.beginControlFlow:(Ljava/lang/String;[Ljava/lang/Object;)Lorg/springframework/javapoet/CodeBlock$Builder;
      81: pop
      82: aload_1
      83: aload_0
      84: getfield      #25                 // Field classLoader:Ljava/lang/ClassLoader;
      87: aload_0
      88: aload         4
      90: invokedynamic #192,  0            // InvokeDynamic #3:accept:(Lorg/springframework/boot/jackson/JsonMixinModuleEntriesBeanRegistrationAotProcessor$AotContribution;Lorg/springframework/javapoet/CodeBlock$Builder;)Ljava/util/function/BiConsumer;
      95: invokevirtual #120                // Method org/springframework/boot/jackson/JsonMixinModuleEntries.doWithEntry:(Ljava/lang/ClassLoader;Ljava/util/function/BiConsumer;)V
      98: aload         4
     100: ldc           #195                // String )
     102: iconst_0
     103: anewarray     #95                 // class java/lang/Object
     106: invokevirtual #197                // Method org/springframework/javapoet/CodeBlock$Builder.endControlFlow:(Ljava/lang/String;[Ljava/lang/Object;)Lorg/springframework/javapoet/CodeBlock$Builder;
     109: pop
     110: aload_2
     111: aload         4
     113: invokevirtual #200                // Method org/springframework/javapoet/CodeBlock$Builder.build:()Lorg/springframework/javapoet/CodeBlock;
     116: invokevirtual #203                // Method org/springframework/javapoet/MethodSpec$Builder.addCode:(Lorg/springframework/javapoet/CodeBlock;)Lorg/springframework/javapoet/MethodSpec$Builder;
     119: pop
     120: return

  private void lambda$generateInstanceSupplierCode$0(org.springframework.javapoet.CodeBlock$Builder, java.lang.Class, java.lang.Class);
    Code:
       0: aload_0
       1: aload_1
       2: aload_2
       3: aload_3
       4: invokevirtual #207                // Method addEntryCode:(Lorg/springframework/javapoet/CodeBlock$Builder;Ljava/lang/Class;Ljava/lang/Class;)V
       7: return
}
