Compiled from "JsonMixinModuleEntries.java"
class org.springframework.boot.jackson.JsonMixinModuleEntries$JsonMixinComponentScanner extends org.springframework.context.annotation.ClassPathScanningCandidateComponentProvider {
  org.springframework.boot.jackson.JsonMixinModuleEntries$JsonMixinComponentScanner();
    Code:
       0: aload_0
       1: invokespecial #1                  // Method org/springframework/context/annotation/ClassPathScanningCandidateComponentProvider."<init>":()V
       4: aload_0
       5: new           #7                  // class org/springframework/core/type/filter/AnnotationTypeFilter
       8: dup
       9: ldc           #9                  // class org/springframework/boot/jackson/JsonMixin
      11: invokespecial #11                 // Method org/springframework/core/type/filter/AnnotationTypeFilter."<init>":(Ljava/lang/Class;)V
      14: invokevirtual #14                 // Method addIncludeFilter:(Lorg/springframework/core/type/filter/TypeFilter;)V
      17: return

  protected boolean isCandidateComponent(org.springframework.beans.factory.annotation.AnnotatedBeanDefinition);
    Code:
       0: iconst_1
       1: ireturn
}
