Compiled from "JsonMixinModuleEntries.java"
public class org.springframework.boot.jackson.JsonMixinModuleEntries$Builder {
  private final java.util.Map<java.lang.Object, java.lang.Object> entries;

  org.springframework.boot.jackson.JsonMixinModuleEntries$Builder();
    Code:
       0: aload_0
       1: invokespecial #1                  // Method java/lang/Object."<init>":()V
       4: aload_0
       5: new           #7                  // class java/util/LinkedHashMap
       8: dup
       9: invokespecial #9                  // Method java/util/LinkedHashMap."<init>":()V
      12: putfield      #10                 // Field entries:Ljava/util/Map;
      15: return

  public org.springframework.boot.jackson.JsonMixinModuleEntries$Builder and(java.lang.String, java.lang.String);
    Code:
       0: aload_0
       1: getfield      #10                 // Field entries:Ljava/util/Map;
       4: aload_1
       5: aload_2
       6: invokeinterface #16,  3           // InterfaceMethod java/util/Map.put:(Ljava/lang/Object;Ljava/lang/Object;)Ljava/lang/Object;
      11: pop
      12: aload_0
      13: areturn

  public org.springframework.boot.jackson.JsonMixinModuleEntries$Builder and(java.lang.Class<?>, java.lang.Class<?>);
    Code:
       0: aload_0
       1: getfield      #10                 // Field entries:Ljava/util/Map;
       4: aload_1
       5: aload_2
       6: invokeinterface #16,  3           // InterfaceMethod java/util/Map.put:(Ljava/lang/Object;Ljava/lang/Object;)Ljava/lang/Object;
      11: pop
      12: aload_0
      13: areturn

  org.springframework.boot.jackson.JsonMixinModuleEntries build();
    Code:
       0: new           #22                 // class org/springframework/boot/jackson/JsonMixinModuleEntries
       3: dup
       4: aload_0
       5: invokespecial #24                 // Method org/springframework/boot/jackson/JsonMixinModuleEntries."<init>":(Lorg/springframework/boot/jackson/JsonMixinModuleEntries$Builder;)V
       8: areturn
}
