Compiled from "JsonMixinModule.java"
public class org.springframework.boot.jackson.JsonMixinModule extends com.fasterxml.jackson.databind.module.SimpleModule {
  public org.springframework.boot.jackson.JsonMixinModule();
    Code:
       0: aload_0
       1: invokespecial #1                  // Method com/fasterxml/jackson/databind/module/SimpleModule."<init>":()V
       4: return

  public org.springframework.boot.jackson.JsonMixinModule(org.springframework.context.ApplicationContext, java.util.Collection<java.lang.String>);
    Code:
       0: aload_0
       1: invokespecial #1                  // Method com/fasterxml/jackson/databind/module/SimpleModule."<init>":()V
       4: aload_1
       5: ldc           #7                  // String Context must not be null
       7: invokestatic  #9                  // Method org/springframework/util/Assert.notNull:(Ljava/lang/Object;Ljava/lang/String;)V
      10: aload_0
      11: aload_1
      12: aload_2
      13: invokestatic  #15                 // Method org/springframework/boot/jackson/JsonMixinModuleEntries.scan:(Lorg/springframework/context/ApplicationContext;Ljava/util/Collection;)Lorg/springframework/boot/jackson/JsonMixinModuleEntries;
      16: aload_1
      17: invokeinterface #21,  1           // InterfaceMethod org/springframework/context/ApplicationContext.getClassLoader:()Ljava/lang/ClassLoader;
      22: invokevirtual #27                 // Method registerEntries:(Lorg/springframework/boot/jackson/JsonMixinModuleEntries;Ljava/lang/ClassLoader;)V
      25: return

  public void registerEntries(org.springframework.boot.jackson.JsonMixinModuleEntries, java.lang.ClassLoader);
    Code:
       0: aload_1
       1: aload_2
       2: aload_0
       3: invokedynamic #33,  0             // InvokeDynamic #0:accept:(Lorg/springframework/boot/jackson/JsonMixinModule;)Ljava/util/function/BiConsumer;
       8: invokevirtual #37                 // Method org/springframework/boot/jackson/JsonMixinModuleEntries.doWithEntry:(Ljava/lang/ClassLoader;Ljava/util/function/BiConsumer;)V
      11: return
}
