Compiled from "JsonComponentModule.java"
public class org.springframework.boot.jackson.JsonComponentModule extends com.fasterxml.jackson.databind.module.SimpleModule implements org.springframework.beans.factory.BeanFactoryAware,org.springframework.beans.factory.InitializingBean {
  private org.springframework.beans.factory.BeanFactory beanFactory;

  public org.springframework.boot.jackson.JsonComponentModule();
    Code:
       0: aload_0
       1: invokespecial #1                  // Method com/fasterxml/jackson/databind/module/SimpleModule."<init>":()V
       4: return

  public void setBeanFactory(org.springframework.beans.factory.BeanFactory) throws org.springframework.beans.BeansException;
    Code:
       0: aload_0
       1: aload_1
       2: putfield      #7                  // Field beanFactory:Lorg/springframework/beans/factory/BeanFactory;
       5: return

  public void afterPropertiesSet();
    Code:
       0: aload_0
       1: invokevirtual #13                 // Method registerJsonComponents:()V
       4: return

  public void registerJsonComponents();
    Code:
       0: aload_0
       1: getfield      #7                  // Field beanFactory:Lorg/springframework/beans/factory/BeanFactory;
       4: astore_1
       5: aload_1
       6: ifnull        52
       9: aload_1
      10: instanceof    #16                 // class org/springframework/beans/factory/ListableBeanFactory
      13: ifeq          26
      16: aload_1
      17: checkcast     #16                 // class org/springframework/beans/factory/ListableBeanFactory
      20: astore_2
      21: aload_0
      22: aload_2
      23: invokevirtual #18                 // Method addJsonBeans:(Lorg/springframework/beans/factory/ListableBeanFactory;)V
      26: aload_1
      27: instanceof    #22                 // class org/springframework/beans/factory/HierarchicalBeanFactory
      30: ifeq          47
      33: aload_1
      34: checkcast     #22                 // class org/springframework/beans/factory/HierarchicalBeanFactory
      37: astore_2
      38: aload_2
      39: invokeinterface #24,  1           // InterfaceMethod org/springframework/beans/factory/HierarchicalBeanFactory.getParentBeanFactory:()Lorg/springframework/beans/factory/BeanFactory;
      44: goto          48
      47: aconst_null
      48: astore_1
      49: goto          5
      52: return

  private void addJsonBeans(org.springframework.beans.factory.ListableBeanFactory);
    Code:
       0: aload_1
       1: ldc           #28                 // class org/springframework/boot/jackson/JsonComponent
       3: invokeinterface #30,  2           // InterfaceMethod org/springframework/beans/factory/ListableBeanFactory.getBeansWithAnnotation:(Ljava/lang/Class;)Ljava/util/Map;
       8: astore_2
       9: aload_2
      10: invokeinterface #34,  1           // InterfaceMethod java/util/Map.values:()Ljava/util/Collection;
      15: invokeinterface #40,  1           // InterfaceMethod java/util/Collection.iterator:()Ljava/util/Iterator;
      20: astore_3
      21: aload_3
      22: invokeinterface #46,  1           // InterfaceMethod java/util/Iterator.hasNext:()Z
      27: ifeq          47
      30: aload_3
      31: invokeinterface #52,  1           // InterfaceMethod java/util/Iterator.next:()Ljava/lang/Object;
      36: astore        4
      38: aload_0
      39: aload         4
      41: invokevirtual #56                 // Method addJsonBean:(Ljava/lang/Object;)V
      44: goto          21
      47: return

  private void addJsonBean(java.lang.Object);
    Code:
       0: aload_1
       1: invokevirtual #60                 // Method java/lang/Object.getClass:()Ljava/lang/Class;
       4: getstatic     #66                 // Field org/springframework/core/annotation/MergedAnnotations$SearchStrategy.TYPE_HIERARCHY:Lorg/springframework/core/annotation/MergedAnnotations$SearchStrategy;
       7: invokestatic  #72                 // InterfaceMethod org/springframework/core/annotation/MergedAnnotations.from:(Ljava/lang/reflect/AnnotatedElement;Lorg/springframework/core/annotation/MergedAnnotations$SearchStrategy;)Lorg/springframework/core/annotation/MergedAnnotations;
      10: ldc           #28                 // class org/springframework/boot/jackson/JsonComponent
      12: invokeinterface #78,  2           // InterfaceMethod org/springframework/core/annotation/MergedAnnotations.get:(Ljava/lang/Class;)Lorg/springframework/core/annotation/MergedAnnotation;
      17: astore_2
      18: aload_2
      19: ldc           #82                 // String type
      21: invokeinterface #84,  2           // InterfaceMethod org/springframework/core/annotation/MergedAnnotation.getClassArray:(Ljava/lang/String;)[Ljava/lang/Class;
      26: astore_3
      27: aload_2
      28: ldc           #90                 // String scope
      30: ldc           #92                 // class org/springframework/boot/jackson/JsonComponent$Scope
      32: invokeinterface #94,  3           // InterfaceMethod org/springframework/core/annotation/MergedAnnotation.getEnum:(Ljava/lang/String;Ljava/lang/Class;)Ljava/lang/Enum;
      37: checkcast     #92                 // class org/springframework/boot/jackson/JsonComponent$Scope
      40: astore        4
      42: aload_0
      43: aload_1
      44: aload_3
      45: aload         4
      47: invokevirtual #98                 // Method addJsonBean:(Ljava/lang/Object;[Ljava/lang/Class;Lorg/springframework/boot/jackson/JsonComponent$Scope;)V
      50: return

  private void addJsonBean(java.lang.Object, java.lang.Class<?>[], org.springframework.boot.jackson.JsonComponent$Scope);
    Code:
       0: aload_1
       1: instanceof    #101                // class com/fasterxml/jackson/databind/JsonSerializer
       4: ifeq          20
       7: aload_0
       8: aload_1
       9: checkcast     #101                // class com/fasterxml/jackson/databind/JsonSerializer
      12: aload_3
      13: aload_2
      14: invokevirtual #103                // Method addJsonSerializerBean:(Lcom/fasterxml/jackson/databind/JsonSerializer;Lorg/springframework/boot/jackson/JsonComponent$Scope;[Ljava/lang/Class;)V
      17: goto          55
      20: aload_1
      21: instanceof    #107                // class com/fasterxml/jackson/databind/JsonDeserializer
      24: ifeq          39
      27: aload_0
      28: aload_1
      29: checkcast     #107                // class com/fasterxml/jackson/databind/JsonDeserializer
      32: aload_2
      33: invokevirtual #109                // Method addJsonDeserializerBean:(Lcom/fasterxml/jackson/databind/JsonDeserializer;[Ljava/lang/Class;)V
      36: goto          55
      39: aload_1
      40: instanceof    #113                // class com/fasterxml/jackson/databind/KeyDeserializer
      43: ifeq          55
      46: aload_0
      47: aload_1
      48: checkcast     #113                // class com/fasterxml/jackson/databind/KeyDeserializer
      51: aload_2
      52: invokevirtual #115                // Method addKeyDeserializerBean:(Lcom/fasterxml/jackson/databind/KeyDeserializer;[Ljava/lang/Class;)V
      55: aload_1
      56: invokevirtual #60                 // Method java/lang/Object.getClass:()Ljava/lang/Class;
      59: invokevirtual #119                // Method java/lang/Class.getDeclaredClasses:()[Ljava/lang/Class;
      62: astore        4
      64: aload         4
      66: arraylength
      67: istore        5
      69: iconst_0
      70: istore        6
      72: iload         6
      74: iload         5
      76: if_icmpge     115
      79: aload         4
      81: iload         6
      83: aaload
      84: astore        7
      86: aload         7
      88: invokestatic  #125                // Method isSuitableInnerClass:(Ljava/lang/Class;)Z
      91: ifeq          109
      94: aload         7
      96: invokestatic  #129                // Method org/springframework/beans/BeanUtils.instantiateClass:(Ljava/lang/Class;)Ljava/lang/Object;
      99: astore        8
     101: aload_0
     102: aload         8
     104: aload_2
     105: aload_3
     106: invokevirtual #98                 // Method addJsonBean:(Ljava/lang/Object;[Ljava/lang/Class;Lorg/springframework/boot/jackson/JsonComponent$Scope;)V
     109: iinc          6, 1
     112: goto          72
     115: return

  private static boolean isSuitableInnerClass(java.lang.Class<?>);
    Code:
       0: aload_0
       1: invokevirtual #135                // Method java/lang/Class.getModifiers:()I
       4: invokestatic  #139                // Method java/lang/reflect/Modifier.isAbstract:(I)Z
       7: ifne          41
      10: ldc           #101                // class com/fasterxml/jackson/databind/JsonSerializer
      12: aload_0
      13: invokevirtual #145                // Method java/lang/Class.isAssignableFrom:(Ljava/lang/Class;)Z
      16: ifne          37
      19: ldc           #107                // class com/fasterxml/jackson/databind/JsonDeserializer
      21: aload_0
      22: invokevirtual #145                // Method java/lang/Class.isAssignableFrom:(Ljava/lang/Class;)Z
      25: ifne          37
      28: ldc           #113                // class com/fasterxml/jackson/databind/KeyDeserializer
      30: aload_0
      31: invokevirtual #145                // Method java/lang/Class.isAssignableFrom:(Ljava/lang/Class;)Z
      34: ifeq          41
      37: iconst_1
      38: goto          42
      41: iconst_0
      42: ireturn

  private <T> void addJsonSerializerBean(com.fasterxml.jackson.databind.JsonSerializer<T>, org.springframework.boot.jackson.JsonComponent$Scope, java.lang.Class<?>[]);
    Code:
       0: ldc           #101                // class com/fasterxml/jackson/databind/JsonSerializer
       2: aload_1
       3: invokevirtual #60                 // Method java/lang/Object.getClass:()Ljava/lang/Class;
       6: invokestatic  #148                // Method org/springframework/core/ResolvableType.forClass:(Ljava/lang/Class;Ljava/lang/Class;)Lorg/springframework/core/ResolvableType;
       9: iconst_0
      10: newarray       int
      12: invokevirtual #154                // Method org/springframework/core/ResolvableType.resolveGeneric:([I)Ljava/lang/Class;
      15: astore        4
      17: aload_0
      18: aload_1
      19: aload         4
      21: aload_3
      22: aload_2
      23: getstatic     #158                // Field org/springframework/boot/jackson/JsonComponent$Scope.VALUES:Lorg/springframework/boot/jackson/JsonComponent$Scope;
      26: if_acmpne     38
      29: aload_0
      30: invokedynamic #162,  0            // InvokeDynamic #0:accept:(Lorg/springframework/boot/jackson/JsonComponentModule;)Ljava/util/function/BiConsumer;
      35: goto          44
      38: aload_0
      39: invokedynamic #166,  0            // InvokeDynamic #1:accept:(Lorg/springframework/boot/jackson/JsonComponentModule;)Ljava/util/function/BiConsumer;
      44: invokevirtual #167                // Method addBeanToModule:(Ljava/lang/Object;Ljava/lang/Class;[Ljava/lang/Class;Ljava/util/function/BiConsumer;)V
      47: return

  private <T> void addJsonDeserializerBean(com.fasterxml.jackson.databind.JsonDeserializer<T>, java.lang.Class<?>[]);
    Code:
       0: ldc           #107                // class com/fasterxml/jackson/databind/JsonDeserializer
       2: aload_1
       3: invokevirtual #60                 // Method java/lang/Object.getClass:()Ljava/lang/Class;
       6: invokestatic  #148                // Method org/springframework/core/ResolvableType.forClass:(Ljava/lang/Class;Ljava/lang/Class;)Lorg/springframework/core/ResolvableType;
       9: iconst_0
      10: newarray       int
      12: invokevirtual #154                // Method org/springframework/core/ResolvableType.resolveGeneric:([I)Ljava/lang/Class;
      15: astore_3
      16: aload_0
      17: aload_1
      18: aload_3
      19: aload_2
      20: aload_0
      21: invokedynamic #171,  0            // InvokeDynamic #2:accept:(Lorg/springframework/boot/jackson/JsonComponentModule;)Ljava/util/function/BiConsumer;
      26: invokevirtual #167                // Method addBeanToModule:(Ljava/lang/Object;Ljava/lang/Class;[Ljava/lang/Class;Ljava/util/function/BiConsumer;)V
      29: return

  private void addKeyDeserializerBean(com.fasterxml.jackson.databind.KeyDeserializer, java.lang.Class<?>[]);
    Code:
       0: aload_2
       1: ldc           #172                // String Type must be specified for KeyDeserializer
       3: invokestatic  #174                // Method org/springframework/util/Assert.notEmpty:([Ljava/lang/Object;Ljava/lang/String;)V
       6: aload_0
       7: aload_1
       8: ldc           #61                 // class java/lang/Object
      10: aload_2
      11: aload_0
      12: invokedynamic #180,  0            // InvokeDynamic #3:accept:(Lorg/springframework/boot/jackson/JsonComponentModule;)Ljava/util/function/BiConsumer;
      17: invokevirtual #167                // Method addBeanToModule:(Ljava/lang/Object;Ljava/lang/Class;[Ljava/lang/Class;Ljava/util/function/BiConsumer;)V
      20: return

  private <E, T> void addBeanToModule(E, java.lang.Class<T>, java.lang.Class<?>[], java.util.function.BiConsumer<java.lang.Class<T>, E>);
    Code:
       0: aload_3
       1: invokestatic  #181                // Method org/springframework/util/ObjectUtils.isEmpty:([Ljava/lang/Object;)Z
       4: ifeq          17
       7: aload         4
       9: aload_2
      10: aload_1
      11: invokeinterface #187,  3          // InterfaceMethod java/util/function/BiConsumer.accept:(Ljava/lang/Object;Ljava/lang/Object;)V
      16: return
      17: aload_3
      18: astore        5
      20: aload         5
      22: arraylength
      23: istore        6
      25: iconst_0
      26: istore        7
      28: iload         7
      30: iload         6
      32: if_icmpge     64
      35: aload         5
      37: iload         7
      39: aaload
      40: astore        8
      42: aload_2
      43: aload         8
      45: invokestatic  #192                // Method org/springframework/util/Assert.isAssignable:(Ljava/lang/Class;Ljava/lang/Class;)V
      48: aload         4
      50: aload         8
      52: aload_1
      53: invokeinterface #187,  3          // InterfaceMethod java/util/function/BiConsumer.accept:(Ljava/lang/Object;Ljava/lang/Object;)V
      58: iinc          7, 1
      61: goto          28
      64: return
}
