Compiled from "JsonComponent.java"
public final class org.springframework.boot.jackson.JsonComponent$Scope extends java.lang.Enum<org.springframework.boot.jackson.JsonComponent$Scope> {
  public static final org.springframework.boot.jackson.JsonComponent$Scope VALUES;

  public static final org.springframework.boot.jackson.JsonComponent$Scope KEYS;

  private static final org.springframework.boot.jackson.JsonComponent$Scope[] $VALUES;

  public static org.springframework.boot.jackson.JsonComponent$Scope[] values();
    Code:
       0: getstatic     #10                 // Field $VALUES:[Lorg/springframework/boot/jackson/JsonComponent$Scope;
       3: invokevirtual #14                 // Method "[Lorg/springframework/boot/jackson/JsonComponent$Scope;".clone:()Ljava/lang/Object;
       6: checkcast     #15                 // class "[Lorg/springframework/boot/jackson/JsonComponent$Scope;"
       9: areturn

  public static org.springframework.boot.jackson.JsonComponent$Scope valueOf(java.lang.String);
    Code:
       0: ldc           #1                  // class org/springframework/boot/jackson/JsonComponent$Scope
       2: aload_0
       3: invokestatic  #19                 // Method java/lang/Enum.valueOf:(Ljava/lang/Class;Ljava/lang/String;)Ljava/lang/Enum;
       6: checkcast     #1                  // class org/springframework/boot/jackson/JsonComponent$Scope
       9: areturn

  private org.springframework.boot.jackson.JsonComponent$Scope();
    Code:
       0: aload_0
       1: aload_1
       2: iload_2
       3: invokespecial #25                 // Method java/lang/Enum."<init>":(Ljava/lang/String;I)V
       6: return

  private static org.springframework.boot.jackson.JsonComponent$Scope[] $values();
    Code:
       0: iconst_2
       1: anewarray     #1                  // class org/springframework/boot/jackson/JsonComponent$Scope
       4: dup
       5: iconst_0
       6: getstatic     #3                  // Field VALUES:Lorg/springframework/boot/jackson/JsonComponent$Scope;
       9: aastore
      10: dup
      11: iconst_1
      12: getstatic     #7                  // Field KEYS:Lorg/springframework/boot/jackson/JsonComponent$Scope;
      15: aastore
      16: areturn

  static {};
    Code:
       0: new           #1                  // class org/springframework/boot/jackson/JsonComponent$Scope
       3: dup
       4: ldc           #29                 // String VALUES
       6: iconst_0
       7: invokespecial #30                 // Method "<init>":(Ljava/lang/String;I)V
      10: putstatic     #3                  // Field VALUES:Lorg/springframework/boot/jackson/JsonComponent$Scope;
      13: new           #1                  // class org/springframework/boot/jackson/JsonComponent$Scope
      16: dup
      17: ldc           #31                 // String KEYS
      19: iconst_1
      20: invokespecial #30                 // Method "<init>":(Ljava/lang/String;I)V
      23: putstatic     #7                  // Field KEYS:Lorg/springframework/boot/jackson/JsonComponent$Scope;
      26: invokestatic  #32                 // Method $values:()[Lorg/springframework/boot/jackson/JsonComponent$Scope;
      29: putstatic     #10                 // Field $VALUES:[Lorg/springframework/boot/jackson/JsonComponent$Scope;
      32: return
}
