Compiled from "JsonObjectSerializer.java"
public abstract class org.springframework.boot.jackson.JsonObjectSerializer<T> extends com.fasterxml.jackson.databind.JsonSerializer<T> {
  public org.springframework.boot.jackson.JsonObjectSerializer();
    Code:
       0: aload_0
       1: invokespecial #1                  // Method com/fasterxml/jackson/databind/JsonSerializer."<init>":()V
       4: return

  public final void serialize(T, com.fasterxml.jackson.core.JsonGenerator, com.fasterxml.jackson.databind.SerializerProvider) throws java.io.IOException;
    Code:
       0: aload_2
       1: invokevirtual #7                  // Method com/fasterxml/jackson/core/JsonGenerator.writeStartObject:()V
       4: aload_0
       5: aload_1
       6: aload_2
       7: aload_3
       8: invokevirtual #12                 // Method serializeObject:(Ljava/lang/Object;Lcom/fasterxml/jackson/core/JsonGenerator;Lcom/fasterxml/jackson/databind/SerializerProvider;)V
      11: aload_2
      12: invokevirtual #18                 // Method com/fasterxml/jackson/core/JsonGenerator.writeEndObject:()V
      15: goto          51
      18: astore        4
      20: aload         4
      22: instanceof    #23                 // class java/io/IOException
      25: ifeq          38
      28: aload         4
      30: checkcast     #23                 // class java/io/IOException
      33: astore        5
      35: aload         5
      37: athrow
      38: new           #25                 // class com/fasterxml/jackson/databind/JsonMappingException
      41: dup
      42: aload_2
      43: ldc           #27                 // String Object serialize error
      45: aload         4
      47: invokespecial #29                 // Method com/fasterxml/jackson/databind/JsonMappingException."<init>":(Ljava/io/Closeable;Ljava/lang/String;Ljava/lang/Throwable;)V
      50: athrow
      51: return
    Exception table:
       from    to  target type
           0    15    18   Class java/lang/Exception

  protected abstract void serializeObject(T, com.fasterxml.jackson.core.JsonGenerator, com.fasterxml.jackson.databind.SerializerProvider) throws java.io.IOException;
}
