Compiled from "JsonComponentModule.java"
class org.springframework.boot.jackson.JsonComponentModule$JsonComponentBeanFactoryInitializationAotProcessor implements org.springframework.beans.factory.aot.BeanFactoryInitializationAotProcessor {
  org.springframework.boot.jackson.JsonComponentModule$JsonComponentBeanFactoryInitializationAotProcessor();
    Code:
       0: aload_0
       1: invokespecial #1                  // Method java/lang/Object."<init>":()V
       4: return

  public org.springframework.beans.factory.aot.BeanFactoryInitializationAotContribution processAheadOfTime(org.springframework.beans.factory.config.ConfigurableListableBeanFactory);
    Code:
       0: aload_1
       1: ldc           #7                  // class org/springframework/boot/jackson/JsonComponent
       3: invokeinterface #9,  2            // InterfaceMethod org/springframework/beans/factory/config/ConfigurableListableBeanFactory.getBeanNamesForAnnotation:(Ljava/lang/Class;)[Ljava/lang/String;
       8: astore_2
       9: new           #15                 // class java/util/HashMap
      12: dup
      13: invokespecial #17                 // Method java/util/HashMap."<init>":()V
      16: astore_3
      17: aload_2
      18: astore        4
      20: aload         4
      22: arraylength
      23: istore        5
      25: iconst_0
      26: istore        6
      28: iload         6
      30: iload         5
      32: if_icmpge     126
      35: aload         4
      37: iload         6
      39: aaload
      40: astore        7
      42: aload_1
      43: aload         7
      45: iconst_1
      46: invokeinterface #18,  3           // InterfaceMethod org/springframework/beans/factory/config/ConfigurableListableBeanFactory.getType:(Ljava/lang/String;Z)Ljava/lang/Class;
      51: astore        8
      53: aload         8
      55: invokevirtual #22                 // Method java/lang/Class.getDeclaredClasses:()[Ljava/lang/Class;
      58: astore        9
      60: aload         9
      62: arraylength
      63: istore        10
      65: iconst_0
      66: istore        11
      68: iload         11
      70: iload         10
      72: if_icmpge     120
      75: aload         9
      77: iload         11
      79: aaload
      80: astore        12
      82: aload         12
      84: invokestatic  #28                 // Method org/springframework/boot/jackson/JsonComponentModule.isSuitableInnerClass:(Ljava/lang/Class;)Z
      87: ifeq          114
      90: aload_3
      91: aload         8
      93: invokedynamic #34,  0             // InvokeDynamic #0:apply:()Ljava/util/function/Function;
      98: invokeinterface #38,  3           // InterfaceMethod java/util/Map.computeIfAbsent:(Ljava/lang/Object;Ljava/util/function/Function;)Ljava/lang/Object;
     103: checkcast     #44                 // class java/util/List
     106: aload         12
     108: invokeinterface #46,  2           // InterfaceMethod java/util/List.add:(Ljava/lang/Object;)Z
     113: pop
     114: iinc          11, 1
     117: goto          68
     120: iinc          6, 1
     123: goto          28
     126: aload_3
     127: invokeinterface #50,  1           // InterfaceMethod java/util/Map.isEmpty:()Z
     132: ifeq          139
     135: aconst_null
     136: goto          147
     139: new           #54                 // class org/springframework/boot/jackson/JsonComponentModule$JsonComponentAotContribution
     142: dup
     143: aload_3
     144: invokespecial #56                 // Method org/springframework/boot/jackson/JsonComponentModule$JsonComponentAotContribution."<init>":(Ljava/util/Map;)V
     147: areturn

  private static java.util.List lambda$processAheadOfTime$0(java.lang.Class);
    Code:
       0: new           #59                 // class java/util/ArrayList
       3: dup
       4: invokespecial #61                 // Method java/util/ArrayList."<init>":()V
       7: areturn
}
