Compiled from "JsonComponentModule.java"
final class org.springframework.boot.jackson.JsonComponentModule$JsonComponentAotContribution implements org.springframework.beans.factory.aot.BeanFactoryInitializationAotContribution {
  private final java.util.Map<java.lang.Class<?>, java.util.List<java.lang.Class<?>>> innerComponents;

  private org.springframework.boot.jackson.JsonComponentModule$JsonComponentAotContribution(java.util.Map<java.lang.Class<?>, java.util.List<java.lang.Class<?>>>);
    Code:
       0: aload_0
       1: invokespecial #1                  // Method java/lang/Object."<init>":()V
       4: aload_0
       5: aload_1
       6: putfield      #7                  // Field innerComponents:Ljava/util/Map;
       9: return

  public void applyTo(org.springframework.aot.generate.GenerationContext, org.springframework.beans.factory.aot.BeanFactoryInitializationCode);
    Code:
       0: aload_1
       1: invokeinterface #13,  1           // InterfaceMethod org/springframework/aot/generate/GenerationContext.getRuntimeHints:()Lorg/springframework/aot/hint/RuntimeHints;
       6: invokevirtual #19                 // Method org/springframework/aot/hint/RuntimeHints.reflection:()Lorg/springframework/aot/hint/ReflectionHints;
       9: astore_3
      10: aload_0
      11: getfield      #7                  // Field innerComponents:Ljava/util/Map;
      14: aload_3
      15: invokedynamic #25,  0             // InvokeDynamic #0:accept:(Lorg/springframework/aot/hint/ReflectionHints;)Ljava/util/function/BiConsumer;
      20: invokeinterface #29,  2           // InterfaceMethod java/util/Map.forEach:(Ljava/util/function/BiConsumer;)V
      25: return

  private static void lambda$applyTo$1(org.springframework.aot.hint.ReflectionHints, java.lang.Class, java.util.List);
    Code:
       0: aload_0
       1: aload_1
       2: iconst_1
       3: anewarray     #35                 // class org/springframework/aot/hint/MemberCategory
       6: dup
       7: iconst_0
       8: getstatic     #37                 // Field org/springframework/aot/hint/MemberCategory.DECLARED_CLASSES:Lorg/springframework/aot/hint/MemberCategory;
      11: aastore
      12: invokevirtual #41                 // Method org/springframework/aot/hint/ReflectionHints.registerType:(Ljava/lang/Class;[Lorg/springframework/aot/hint/MemberCategory;)Lorg/springframework/aot/hint/ReflectionHints;
      15: pop
      16: aload_2
      17: aload_0
      18: invokedynamic #47,  0             // InvokeDynamic #1:accept:(Lorg/springframework/aot/hint/ReflectionHints;)Ljava/util/function/Consumer;
      23: invokeinterface #50,  2           // InterfaceMethod java/util/List.forEach:(Ljava/util/function/Consumer;)V
      28: return

  private static void lambda$applyTo$0(org.springframework.aot.hint.ReflectionHints, java.lang.Class);
    Code:
       0: aload_0
       1: aload_1
       2: iconst_1
       3: anewarray     #35                 // class org/springframework/aot/hint/MemberCategory
       6: dup
       7: iconst_0
       8: getstatic     #55                 // Field org/springframework/aot/hint/MemberCategory.INVOKE_DECLARED_CONSTRUCTORS:Lorg/springframework/aot/hint/MemberCategory;
      11: aastore
      12: invokevirtual #41                 // Method org/springframework/aot/hint/ReflectionHints.registerType:(Ljava/lang/Class;[Lorg/springframework/aot/hint/MemberCategory;)Lorg/springframework/aot/hint/ReflectionHints;
      15: pop
      16: return
}
