Compiled from "JsonMixinModuleEntries.java"
public final class org.springframework.boot.jackson.JsonMixinModuleEntries {
  private final java.util.Map<java.lang.Object, java.lang.Object> entries;

  private org.springframework.boot.jackson.JsonMixinModuleEntries(org.springframework.boot.jackson.JsonMixinModuleEntries$Builder);
    Code:
       0: aload_0
       1: invokespecial #1                  // Method java/lang/Object."<init>":()V
       4: aload_0
       5: new           #7                  // class java/util/LinkedHashMap
       8: dup
       9: aload_1
      10: getfield      #9                  // Field org/springframework/boot/jackson/JsonMixinModuleEntries$Builder.entries:Ljava/util/Map;
      13: invokespecial #15                 // Method java/util/LinkedHashMap."<init>":(Ljava/util/Map;)V
      16: putfield      #18                 // Field entries:Ljava/util/Map;
      19: return

  public static org.springframework.boot.jackson.JsonMixinModuleEntries create(java.util.function.Consumer<org.springframework.boot.jackson.JsonMixinModuleEntries$Builder>);
    Code:
       0: new           #10                 // class org/springframework/boot/jackson/JsonMixinModuleEntries$Builder
       3: dup
       4: invokespecial #21                 // Method org/springframework/boot/jackson/JsonMixinModuleEntries$Builder."<init>":()V
       7: astore_1
       8: aload_0
       9: aload_1
      10: invokeinterface #22,  2           // InterfaceMethod java/util/function/Consumer.accept:(Ljava/lang/Object;)V
      15: aload_1
      16: invokevirtual #28                 // Method org/springframework/boot/jackson/JsonMixinModuleEntries$Builder.build:()Lorg/springframework/boot/jackson/JsonMixinModuleEntries;
      19: areturn

  public static org.springframework.boot.jackson.JsonMixinModuleEntries scan(org.springframework.context.ApplicationContext, java.util.Collection<java.lang.String>);
    Code:
       0: aload_1
       1: aload_0
       2: invokedynamic #32,  0             // InvokeDynamic #0:accept:(Ljava/util/Collection;Lorg/springframework/context/ApplicationContext;)Ljava/util/function/Consumer;
       7: invokestatic  #35                 // Method create:(Ljava/util/function/Consumer;)Lorg/springframework/boot/jackson/JsonMixinModuleEntries;
      10: areturn

  private static void registerMixinClass(org.springframework.boot.jackson.JsonMixinModuleEntries$Builder, java.lang.Class<?>);
    Code:
       0: aload_1
       1: getstatic     #39                 // Field org/springframework/core/annotation/MergedAnnotations$SearchStrategy.TYPE_HIERARCHY:Lorg/springframework/core/annotation/MergedAnnotations$SearchStrategy;
       4: invokestatic  #45                 // InterfaceMethod org/springframework/core/annotation/MergedAnnotations.from:(Ljava/lang/reflect/AnnotatedElement;Lorg/springframework/core/annotation/MergedAnnotations$SearchStrategy;)Lorg/springframework/core/annotation/MergedAnnotations;
       7: ldc           #51                 // class org/springframework/boot/jackson/JsonMixin
       9: invokeinterface #53,  2           // InterfaceMethod org/springframework/core/annotation/MergedAnnotations.get:(Ljava/lang/Class;)Lorg/springframework/core/annotation/MergedAnnotation;
      14: astore_2
      15: aload_2
      16: ldc           #57                 // String type
      18: invokeinterface #59,  2           // InterfaceMethod org/springframework/core/annotation/MergedAnnotation.getClassArray:(Ljava/lang/String;)[Ljava/lang/Class;
      23: astore_3
      24: aload_3
      25: arraylength
      26: istore        4
      28: iconst_0
      29: istore        5
      31: iload         5
      33: iload         4
      35: if_icmpge     58
      38: aload_3
      39: iload         5
      41: aaload
      42: astore        6
      44: aload_0
      45: aload         6
      47: aload_1
      48: invokevirtual #65                 // Method org/springframework/boot/jackson/JsonMixinModuleEntries$Builder.and:(Ljava/lang/Class;Ljava/lang/Class;)Lorg/springframework/boot/jackson/JsonMixinModuleEntries$Builder;
      51: pop
      52: iinc          5, 1
      55: goto          31
      58: return

  public void doWithEntry(java.lang.ClassLoader, java.util.function.BiConsumer<java.lang.Class<?>, java.lang.Class<?>>);
    Code:
       0: aload_0
       1: getfield      #18                 // Field entries:Ljava/util/Map;
       4: aload_0
       5: aload_2
       6: aload_1
       7: invokedynamic #69,  0             // InvokeDynamic #1:accept:(Lorg/springframework/boot/jackson/JsonMixinModuleEntries;Ljava/util/function/BiConsumer;Ljava/lang/ClassLoader;)Ljava/util/function/BiConsumer;
      12: invokeinterface #72,  2           // InterfaceMethod java/util/Map.forEach:(Ljava/util/function/BiConsumer;)V
      17: return

  private java.lang.Class<?> resolveClassNameIfNecessary(java.lang.Object, java.lang.ClassLoader);
    Code:
       0: aload_1
       1: instanceof    #78                 // class java/lang/Class
       4: ifeq          16
       7: aload_1
       8: checkcast     #78                 // class java/lang/Class
      11: astore_3
      12: aload_3
      13: goto          24
      16: aload_1
      17: checkcast     #80                 // class java/lang/String
      20: aload_2
      21: invokestatic  #82                 // Method org/springframework/util/ClassUtils.resolveClassName:(Ljava/lang/String;Ljava/lang/ClassLoader;)Ljava/lang/Class;
      24: areturn

  private void lambda$doWithEntry$1(java.util.function.BiConsumer, java.lang.ClassLoader, java.lang.Object, java.lang.Object);
    Code:
       0: aload_1
       1: aload_0
       2: aload_3
       3: aload_2
       4: invokevirtual #88                 // Method resolveClassNameIfNecessary:(Ljava/lang/Object;Ljava/lang/ClassLoader;)Ljava/lang/Class;
       7: aload_0
       8: aload         4
      10: aload_2
      11: invokevirtual #88                 // Method resolveClassNameIfNecessary:(Ljava/lang/Object;Ljava/lang/ClassLoader;)Ljava/lang/Class;
      14: invokeinterface #92,  3           // InterfaceMethod java/util/function/BiConsumer.accept:(Ljava/lang/Object;Ljava/lang/Object;)V
      19: return

  private static void lambda$scan$0(java.util.Collection, org.springframework.context.ApplicationContext, org.springframework.boot.jackson.JsonMixinModuleEntries$Builder);
    Code:
       0: aload_0
       1: invokestatic  #97                 // Method org/springframework/util/ObjectUtils.isEmpty:(Ljava/lang/Object;)Z
       4: ifeq          8
       7: return
       8: new           #103                // class org/springframework/boot/jackson/JsonMixinModuleEntries$JsonMixinComponentScanner
      11: dup
      12: invokespecial #105                // Method org/springframework/boot/jackson/JsonMixinModuleEntries$JsonMixinComponentScanner."<init>":()V
      15: astore_3
      16: aload_3
      17: aload_1
      18: invokeinterface #106,  1          // InterfaceMethod org/springframework/context/ApplicationContext.getEnvironment:()Lorg/springframework/core/env/Environment;
      23: invokevirtual #112                // Method org/springframework/boot/jackson/JsonMixinModuleEntries$JsonMixinComponentScanner.setEnvironment:(Lorg/springframework/core/env/Environment;)V
      26: aload_3
      27: aload_1
      28: invokevirtual #116                // Method org/springframework/boot/jackson/JsonMixinModuleEntries$JsonMixinComponentScanner.setResourceLoader:(Lorg/springframework/core/io/ResourceLoader;)V
      31: aload_0
      32: invokeinterface #120,  1          // InterfaceMethod java/util/Collection.iterator:()Ljava/util/Iterator;
      37: astore        4
      39: aload         4
      41: invokeinterface #126,  1          // InterfaceMethod java/util/Iterator.hasNext:()Z
      46: ifeq          134
      49: aload         4
      51: invokeinterface #132,  1          // InterfaceMethod java/util/Iterator.next:()Ljava/lang/Object;
      56: checkcast     #80                 // class java/lang/String
      59: astore        5
      61: aload         5
      63: invokestatic  #136                // Method org/springframework/util/StringUtils.hasText:(Ljava/lang/String;)Z
      66: ifeq          131
      69: aload_3
      70: aload         5
      72: invokevirtual #142                // Method org/springframework/boot/jackson/JsonMixinModuleEntries$JsonMixinComponentScanner.findCandidateComponents:(Ljava/lang/String;)Ljava/util/Set;
      75: invokeinterface #146,  1          // InterfaceMethod java/util/Set.iterator:()Ljava/util/Iterator;
      80: astore        6
      82: aload         6
      84: invokeinterface #126,  1          // InterfaceMethod java/util/Iterator.hasNext:()Z
      89: ifeq          131
      92: aload         6
      94: invokeinterface #132,  1          // InterfaceMethod java/util/Iterator.next:()Ljava/lang/Object;
      99: checkcast     #149                // class org/springframework/beans/factory/config/BeanDefinition
     102: astore        7
     104: aload         7
     106: invokeinterface #151,  1          // InterfaceMethod org/springframework/beans/factory/config/BeanDefinition.getBeanClassName:()Ljava/lang/String;
     111: aload_1
     112: invokeinterface #155,  1          // InterfaceMethod org/springframework/context/ApplicationContext.getClassLoader:()Ljava/lang/ClassLoader;
     117: invokestatic  #82                 // Method org/springframework/util/ClassUtils.resolveClassName:(Ljava/lang/String;Ljava/lang/ClassLoader;)Ljava/lang/Class;
     120: astore        8
     122: aload_2
     123: aload         8
     125: invokestatic  #159                // Method registerMixinClass:(Lorg/springframework/boot/jackson/JsonMixinModuleEntries$Builder;Ljava/lang/Class;)V
     128: goto          82
     131: goto          39
     134: return
}
