Compiled from "JsonObjectDeserializer.java"
public abstract class org.springframework.boot.jackson.JsonObjectDeserializer<T> extends com.fasterxml.jackson.databind.JsonDeserializer<T> {
  public org.springframework.boot.jackson.JsonObjectDeserializer();
    Code:
       0: aload_0
       1: invokespecial #1                  // Method com/fasterxml/jackson/databind/JsonDeserializer."<init>":()V
       4: return

  public final T deserialize(com.fasterxml.jackson.core.JsonParser, com.fasterxml.jackson.databind.DeserializationContext) throws java.io.IOException;
    Code:
       0: aload_1
       1: invokevirtual #7                  // Method com/fasterxml/jackson/core/JsonParser.getCodec:()Lcom/fasterxml/jackson/core/ObjectCodec;
       4: astore_3
       5: aload_3
       6: aload_1
       7: invokevirtual #13                 // Method com/fasterxml/jackson/core/ObjectCodec.readTree:(Lcom/fasterxml/jackson/core/JsonParser;)Lcom/fasterxml/jackson/core/TreeNode;
      10: checkcast     #19                 // class com/fasterxml/jackson/databind/JsonNode
      13: astore        4
      15: aload_0
      16: aload_1
      17: aload_2
      18: aload_3
      19: aload         4
      21: invokevirtual #21                 // Method deserializeObject:(Lcom/fasterxml/jackson/core/JsonParser;Lcom/fasterxml/jackson/databind/DeserializationContext;Lcom/fasterxml/jackson/core/ObjectCodec;Lcom/fasterxml/jackson/databind/JsonNode;)Ljava/lang/Object;
      24: areturn
      25: astore_3
      26: aload_3
      27: instanceof    #29                 // class java/io/IOException
      30: ifeq          42
      33: aload_3
      34: checkcast     #29                 // class java/io/IOException
      37: astore        4
      39: aload         4
      41: athrow
      42: new           #31                 // class com/fasterxml/jackson/databind/JsonMappingException
      45: dup
      46: aload_1
      47: ldc           #33                 // String Object deserialize error
      49: aload_3
      50: invokespecial #35                 // Method com/fasterxml/jackson/databind/JsonMappingException."<init>":(Ljava/io/Closeable;Ljava/lang/String;Ljava/lang/Throwable;)V
      53: athrow
    Exception table:
       from    to  target type
           0    24    25   Class java/lang/Exception

  protected abstract T deserializeObject(com.fasterxml.jackson.core.JsonParser, com.fasterxml.jackson.databind.DeserializationContext, com.fasterxml.jackson.core.ObjectCodec, com.fasterxml.jackson.databind.JsonNode) throws java.io.IOException;

  protected final <D> D nullSafeValue(com.fasterxml.jackson.databind.JsonNode, java.lang.Class<D>);
    Code:
       0: aload_2
       1: ldc           #38                 // String Type must not be null
       3: invokestatic  #40                 // Method org/springframework/util/Assert.notNull:(Ljava/lang/Object;Ljava/lang/String;)V
       6: aload_1
       7: ifnonnull     12
      10: aconst_null
      11: areturn
      12: aload_2
      13: ldc           #46                 // class java/lang/String
      15: if_acmpne     23
      18: aload_1
      19: invokevirtual #48                 // Method com/fasterxml/jackson/databind/JsonNode.textValue:()Ljava/lang/String;
      22: areturn
      23: aload_2
      24: ldc           #52                 // class java/lang/Boolean
      26: if_acmpne     37
      29: aload_1
      30: invokevirtual #54                 // Method com/fasterxml/jackson/databind/JsonNode.booleanValue:()Z
      33: invokestatic  #58                 // Method java/lang/Boolean.valueOf:(Z)Ljava/lang/Boolean;
      36: areturn
      37: aload_2
      38: ldc           #62                 // class java/lang/Long
      40: if_acmpne     51
      43: aload_1
      44: invokevirtual #64                 // Method com/fasterxml/jackson/databind/JsonNode.longValue:()J
      47: invokestatic  #68                 // Method java/lang/Long.valueOf:(J)Ljava/lang/Long;
      50: areturn
      51: aload_2
      52: ldc           #71                 // class java/lang/Integer
      54: if_acmpne     65
      57: aload_1
      58: invokevirtual #73                 // Method com/fasterxml/jackson/databind/JsonNode.intValue:()I
      61: invokestatic  #77                 // Method java/lang/Integer.valueOf:(I)Ljava/lang/Integer;
      64: areturn
      65: aload_2
      66: ldc           #80                 // class java/lang/Short
      68: if_acmpne     79
      71: aload_1
      72: invokevirtual #82                 // Method com/fasterxml/jackson/databind/JsonNode.shortValue:()S
      75: invokestatic  #86                 // Method java/lang/Short.valueOf:(S)Ljava/lang/Short;
      78: areturn
      79: aload_2
      80: ldc           #89                 // class java/lang/Double
      82: if_acmpne     93
      85: aload_1
      86: invokevirtual #91                 // Method com/fasterxml/jackson/databind/JsonNode.doubleValue:()D
      89: invokestatic  #95                 // Method java/lang/Double.valueOf:(D)Ljava/lang/Double;
      92: areturn
      93: aload_2
      94: ldc           #98                 // class java/lang/Float
      96: if_acmpne     107
      99: aload_1
     100: invokevirtual #100                // Method com/fasterxml/jackson/databind/JsonNode.floatValue:()F
     103: invokestatic  #104                // Method java/lang/Float.valueOf:(F)Ljava/lang/Float;
     106: areturn
     107: aload_2
     108: ldc           #107                // class java/math/BigDecimal
     110: if_acmpne     118
     113: aload_1
     114: invokevirtual #109                // Method com/fasterxml/jackson/databind/JsonNode.decimalValue:()Ljava/math/BigDecimal;
     117: areturn
     118: aload_2
     119: ldc           #113                // class java/math/BigInteger
     121: if_acmpne     129
     124: aload_1
     125: invokevirtual #115                // Method com/fasterxml/jackson/databind/JsonNode.bigIntegerValue:()Ljava/math/BigInteger;
     128: areturn
     129: new           #119                // class java/lang/IllegalArgumentException
     132: dup
     133: aload_2
     134: invokevirtual #121                // Method java/lang/Class.getName:()Ljava/lang/String;
     137: invokedynamic #126,  0            // InvokeDynamic #0:makeConcatWithConstants:(Ljava/lang/String;)Ljava/lang/String;
     142: invokespecial #130                // Method java/lang/IllegalArgumentException."<init>":(Ljava/lang/String;)V
     145: athrow

  protected final com.fasterxml.jackson.databind.JsonNode getRequiredNode(com.fasterxml.jackson.databind.JsonNode, java.lang.String);
    Code:
       0: aload_1
       1: ldc           #133                // String Tree must not be null
       3: invokestatic  #40                 // Method org/springframework/util/Assert.notNull:(Ljava/lang/Object;Ljava/lang/String;)V
       6: aload_1
       7: aload_2
       8: invokevirtual #135                // Method com/fasterxml/jackson/databind/JsonNode.get:(Ljava/lang/String;)Lcom/fasterxml/jackson/databind/JsonNode;
      11: astore_3
      12: aload_3
      13: ifnull        27
      16: aload_3
      17: instanceof    #139                // class com/fasterxml/jackson/databind/node/NullNode
      20: ifne          27
      23: iconst_1
      24: goto          28
      27: iconst_0
      28: aload_2
      29: invokedynamic #141,  0            // InvokeDynamic #1:get:(Ljava/lang/String;)Ljava/util/function/Supplier;
      34: invokestatic  #144                // Method org/springframework/util/Assert.state:(ZLjava/util/function/Supplier;)V
      37: aload_3
      38: areturn

  private static java.lang.String lambda$getRequiredNode$0(java.lang.String);
    Code:
       0: aload_0
       1: invokedynamic #148,  0            // InvokeDynamic #2:makeConcatWithConstants:(Ljava/lang/String;)Ljava/lang/String;
       6: areturn
}
