Compiled from "BaseParseContext.java"
public class org.apache.dubbo.rpc.protocol.rest.annotation.BaseParseContext {
  protected java.util.List<java.lang.Object> args;

  protected java.util.List<org.apache.dubbo.metadata.rest.ArgInfo> argInfos;

  public org.apache.dubbo.rpc.protocol.rest.annotation.BaseParseContext();
    Code:
       0: aload_0
       1: invokespecial #1                  // Method java/lang/Object."<init>":()V
       4: return

  public java.util.List<java.lang.Object> getArgs();
    Code:
       0: aload_0
       1: getfield      #2                  // Field args:Ljava/util/List;
       4: areturn

  public void setArgs(java.util.List<java.lang.Object>);
    Code:
       0: aload_0
       1: aload_1
       2: putfield      #2                  // Field args:Ljava/util/List;
       5: return

  public java.util.List<org.apache.dubbo.metadata.rest.ArgInfo> getArgInfos();
    Code:
       0: aload_0
       1: getfield      #3                  // Field argInfos:Ljava/util/List;
       4: areturn

  public void setArgInfos(java.util.List<org.apache.dubbo.metadata.rest.ArgInfo>);
    Code:
       0: aload_0
       1: aload_1
       2: putfield      #3                  // Field argInfos:Ljava/util/List;
       5: return

  public org.apache.dubbo.metadata.rest.ArgInfo getArgInfoByIndex(int);
    Code:
       0: aload_0
       1: invokevirtual #4                  // Method getArgInfos:()Ljava/util/List;
       4: iload_1
       5: invokeinterface #5,  2            // InterfaceMethod java/util/List.get:(I)Ljava/lang/Object;
      10: checkcast     #6                  // class org/apache/dubbo/metadata/rest/ArgInfo
      13: areturn
}
