Compiled from "ParamParserManager.java"
public class org.apache.dubbo.rpc.protocol.rest.annotation.ParamParserManager {
  private static final java.util.Set<org.apache.dubbo.rpc.protocol.rest.annotation.param.parse.consumer.BaseConsumerParamParser> consumerParamParsers;

  private static final java.util.Set<org.apache.dubbo.rpc.protocol.rest.annotation.param.parse.provider.BaseProviderParamParser> providerParamParsers;

  public org.apache.dubbo.rpc.protocol.rest.annotation.ParamParserManager();
    Code:
       0: aload_0
       1: invokespecial #1                  // Method java/lang/Object."<init>":()V
       4: return

  public static java.lang.Object[] providerParamParse(org.apache.dubbo.rpc.protocol.rest.annotation.param.parse.provider.ProviderParseContext);
    Code:
       0: aload_0
       1: invokevirtual #2                  // Method org/apache/dubbo/rpc/protocol/rest/annotation/param/parse/provider/ProviderParseContext.getArgInfos:()Ljava/util/List;
       4: astore_1
       5: iconst_0
       6: istore_2
       7: iload_2
       8: aload_1
       9: invokeinterface #3,  1            // InterfaceMethod java/util/List.size:()I
      14: if_icmpge     73
      17: getstatic     #4                  // Field providerParamParsers:Ljava/util/Set;
      20: invokeinterface #5,  1            // InterfaceMethod java/util/Set.iterator:()Ljava/util/Iterator;
      25: astore_3
      26: aload_3
      27: invokeinterface #6,  1            // InterfaceMethod java/util/Iterator.hasNext:()Z
      32: ifeq          67
      35: aload_3
      36: invokeinterface #7,  1            // InterfaceMethod java/util/Iterator.next:()Ljava/lang/Object;
      41: checkcast     #8                  // class org/apache/dubbo/rpc/protocol/rest/annotation/ParamParser
      44: astore        4
      46: aload         4
      48: aload_0
      49: aload_1
      50: iload_2
      51: invokeinterface #9,  2            // InterfaceMethod java/util/List.get:(I)Ljava/lang/Object;
      56: checkcast     #10                 // class org/apache/dubbo/metadata/rest/ArgInfo
      59: invokeinterface #11,  3           // InterfaceMethod org/apache/dubbo/rpc/protocol/rest/annotation/ParamParser.parse:(Ljava/lang/Object;Lorg/apache/dubbo/metadata/rest/ArgInfo;)V
      64: goto          26
      67: iinc          2, 1
      70: goto          7
      73: aload_0
      74: invokevirtual #12                 // Method org/apache/dubbo/rpc/protocol/rest/annotation/param/parse/provider/ProviderParseContext.getArgs:()Ljava/util/List;
      77: iconst_0
      78: anewarray     #13                 // class java/lang/Object
      81: invokeinterface #14,  2           // InterfaceMethod java/util/List.toArray:([Ljava/lang/Object;)[Ljava/lang/Object;
      86: areturn

  public static void consumerParamParse(org.apache.dubbo.rpc.protocol.rest.annotation.param.parse.consumer.ConsumerParseContext);
    Code:
       0: aload_0
       1: invokevirtual #15                 // Method org/apache/dubbo/rpc/protocol/rest/annotation/param/parse/consumer/ConsumerParseContext.getArgInfos:()Ljava/util/List;
       4: astore_1
       5: iconst_0
       6: istore_2
       7: iload_2
       8: aload_1
       9: invokeinterface #3,  1            // InterfaceMethod java/util/List.size:()I
      14: if_icmpge     87
      17: getstatic     #16                 // Field consumerParamParsers:Ljava/util/Set;
      20: invokeinterface #5,  1            // InterfaceMethod java/util/Set.iterator:()Ljava/util/Iterator;
      25: astore_3
      26: aload_3
      27: invokeinterface #6,  1            // InterfaceMethod java/util/Iterator.hasNext:()Z
      32: ifeq          81
      35: aload_3
      36: invokeinterface #7,  1            // InterfaceMethod java/util/Iterator.next:()Ljava/lang/Object;
      41: checkcast     #17                 // class org/apache/dubbo/rpc/protocol/rest/annotation/param/parse/consumer/BaseConsumerParamParser
      44: astore        4
      46: aload_0
      47: iload_2
      48: invokevirtual #18                 // Method org/apache/dubbo/rpc/protocol/rest/annotation/param/parse/consumer/ConsumerParseContext.getArgInfoByIndex:(I)Lorg/apache/dubbo/metadata/rest/ArgInfo;
      51: astore        5
      53: aload         4
      55: aload         5
      57: invokeinterface #19,  2           // InterfaceMethod org/apache/dubbo/rpc/protocol/rest/annotation/param/parse/consumer/BaseConsumerParamParser.paramTypeMatch:(Lorg/apache/dubbo/metadata/rest/ArgInfo;)Z
      62: ifne          68
      65: goto          26
      68: aload         4
      70: aload_0
      71: aload         5
      73: invokeinterface #20,  3           // InterfaceMethod org/apache/dubbo/rpc/protocol/rest/annotation/param/parse/consumer/BaseConsumerParamParser.parse:(Ljava/lang/Object;Lorg/apache/dubbo/metadata/rest/ArgInfo;)V
      78: goto          26
      81: iinc          2, 1
      84: goto          7
      87: return

  static {};
    Code:
       0: invokestatic  #21                 // Method org/apache/dubbo/rpc/model/FrameworkModel.defaultModel:()Lorg/apache/dubbo/rpc/model/FrameworkModel;
       3: ldc           #17                 // class org/apache/dubbo/rpc/protocol/rest/annotation/param/parse/consumer/BaseConsumerParamParser
       5: invokevirtual #22                 // Method org/apache/dubbo/rpc/model/FrameworkModel.getExtensionLoader:(Ljava/lang/Class;)Lorg/apache/dubbo/common/extension/ExtensionLoader;
       8: invokevirtual #23                 // Method org/apache/dubbo/common/extension/ExtensionLoader.getSupportedExtensionInstances:()Ljava/util/Set;
      11: putstatic     #16                 // Field consumerParamParsers:Ljava/util/Set;
      14: invokestatic  #21                 // Method org/apache/dubbo/rpc/model/FrameworkModel.defaultModel:()Lorg/apache/dubbo/rpc/model/FrameworkModel;
      17: ldc           #24                 // class org/apache/dubbo/rpc/protocol/rest/annotation/param/parse/provider/BaseProviderParamParser
      19: invokevirtual #22                 // Method org/apache/dubbo/rpc/model/FrameworkModel.getExtensionLoader:(Ljava/lang/Class;)Lorg/apache/dubbo/common/extension/ExtensionLoader;
      22: invokevirtual #23                 // Method org/apache/dubbo/common/extension/ExtensionLoader.getSupportedExtensionInstances:()Ljava/util/Set;
      25: putstatic     #4                  // Field providerParamParsers:Ljava/util/Set;
      28: return
}
