Compiled from "CuratorFrameworkUtils.java"
public abstract class org.apache.dubbo.registry.zookeeper.util.CuratorFrameworkUtils {
  public org.apache.dubbo.registry.zookeeper.util.CuratorFrameworkUtils();
    Code:
       0: aload_0
       1: invokespecial #3                  // Method java/lang/Object."<init>":()V
       4: return

  public static org.apache.curator.x.discovery.ServiceDiscovery<org.apache.dubbo.registry.zookeeper.ZookeeperInstance> buildServiceDiscovery(org.apache.curator.framework.CuratorFramework, java.lang.String);
    Code:
       0: ldc           #4                  // class org/apache/dubbo/registry/zookeeper/ZookeeperInstance
       2: invokestatic  #5                  // Method org/apache/curator/x/discovery/ServiceDiscoveryBuilder.builder:(Ljava/lang/Class;)Lorg/apache/curator/x/discovery/ServiceDiscoveryBuilder;
       5: aload_0
       6: invokevirtual #6                  // Method org/apache/curator/x/discovery/ServiceDiscoveryBuilder.client:(Lorg/apache/curator/framework/CuratorFramework;)Lorg/apache/curator/x/discovery/ServiceDiscoveryBuilder;
       9: aload_1
      10: invokevirtual #7                  // Method org/apache/curator/x/discovery/ServiceDiscoveryBuilder.basePath:(Ljava/lang/String;)Lorg/apache/curator/x/discovery/ServiceDiscoveryBuilder;
      13: invokevirtual #8                  // Method org/apache/curator/x/discovery/ServiceDiscoveryBuilder.build:()Lorg/apache/curator/x/discovery/ServiceDiscovery;
      16: areturn

  public static org.apache.curator.framework.CuratorFramework buildCuratorFramework(org.apache.dubbo.common.URL, org.apache.dubbo.registry.zookeeper.ZookeeperServiceDiscovery) throws java.lang.Exception;
    Code:
       0: invokestatic  #9                  // Method org/apache/curator/framework/CuratorFrameworkFactory.builder:()Lorg/apache/curator/framework/CuratorFrameworkFactory$Builder;
       3: aload_0
       4: invokevirtual #10                 // Method org/apache/dubbo/common/URL.getBackupAddress:()Ljava/lang/String;
       7: invokevirtual #11                 // Method org/apache/curator/framework/CuratorFrameworkFactory$Builder.connectString:(Ljava/lang/String;)Lorg/apache/curator/framework/CuratorFrameworkFactory$Builder;
      10: aload_0
      11: invokestatic  #12                 // Method buildRetryPolicy:(Lorg/apache/dubbo/common/URL;)Lorg/apache/curator/RetryPolicy;
      14: invokevirtual #13                 // Method org/apache/curator/framework/CuratorFrameworkFactory$Builder.retryPolicy:(Lorg/apache/curator/RetryPolicy;)Lorg/apache/curator/framework/CuratorFrameworkFactory$Builder;
      17: astore_2
      18: aload_0
      19: invokevirtual #14                 // Method org/apache/dubbo/common/URL.getUserInformation:()Ljava/lang/String;
      22: astore_3
      23: aload_3
      24: invokestatic  #15                 // Method org/apache/dubbo/common/utils/StringUtils.isNotEmpty:(Ljava/lang/String;)Z
      27: ifeq          53
      30: aload_2
      31: ldc           #16                 // String digest
      33: aload_3
      34: invokevirtual #17                 // Method java/lang/String.getBytes:()[B
      37: invokevirtual #18                 // Method org/apache/curator/framework/CuratorFrameworkFactory$Builder.authorization:(Ljava/lang/String;[B)Lorg/apache/curator/framework/CuratorFrameworkFactory$Builder;
      40: astore_2
      41: aload_2
      42: new           #19                 // class org/apache/dubbo/registry/zookeeper/util/CuratorFrameworkUtils$1
      45: dup
      46: invokespecial #20                 // Method org/apache/dubbo/registry/zookeeper/util/CuratorFrameworkUtils$1."<init>":()V
      49: invokevirtual #21                 // Method org/apache/curator/framework/CuratorFrameworkFactory$Builder.aclProvider:(Lorg/apache/curator/framework/api/ACLProvider;)Lorg/apache/curator/framework/CuratorFrameworkFactory$Builder;
      52: pop
      53: aload_2
      54: invokevirtual #22                 // Method org/apache/curator/framework/CuratorFrameworkFactory$Builder.build:()Lorg/apache/curator/framework/CuratorFramework;
      57: astore        4
      59: aload         4
      61: invokeinterface #23,  1           // InterfaceMethod org/apache/curator/framework/CuratorFramework.start:()V
      66: aload         4
      68: getstatic     #24                 // Field org/apache/dubbo/registry/zookeeper/util/CuratorFrameworkParams.BLOCK_UNTIL_CONNECTED_WAIT:Lorg/apache/dubbo/registry/zookeeper/util/CuratorFrameworkParams;
      71: aload_0
      72: invokevirtual #25                 // Method org/apache/dubbo/registry/zookeeper/util/CuratorFrameworkParams.getParameterValue:(Lorg/apache/dubbo/common/URL;)Ljava/lang/Object;
      75: checkcast     #26                 // class java/lang/Integer
      78: invokevirtual #27                 // Method java/lang/Integer.intValue:()I
      81: getstatic     #28                 // Field org/apache/dubbo/registry/zookeeper/util/CuratorFrameworkParams.BLOCK_UNTIL_CONNECTED_UNIT:Lorg/apache/dubbo/registry/zookeeper/util/CuratorFrameworkParams;
      84: aload_0
      85: invokevirtual #25                 // Method org/apache/dubbo/registry/zookeeper/util/CuratorFrameworkParams.getParameterValue:(Lorg/apache/dubbo/common/URL;)Ljava/lang/Object;
      88: checkcast     #29                 // class java/util/concurrent/TimeUnit
      91: invokeinterface #30,  3           // InterfaceMethod org/apache/curator/framework/CuratorFramework.blockUntilConnected:(ILjava/util/concurrent/TimeUnit;)Z
      96: pop
      97: aload         4
      99: invokeinterface #31,  1           // InterfaceMethod org/apache/curator/framework/CuratorFramework.getState:()Lorg/apache/curator/framework/imps/CuratorFrameworkState;
     104: getstatic     #32                 // Field org/apache/curator/framework/imps/CuratorFrameworkState.STARTED:Lorg/apache/curator/framework/imps/CuratorFrameworkState;
     107: invokevirtual #33                 // Method org/apache/curator/framework/imps/CuratorFrameworkState.equals:(Ljava/lang/Object;)Z
     110: ifne          123
     113: new           #34                 // class java/lang/IllegalStateException
     116: dup
     117: ldc           #35                 // String zookeeper client initialization failed
     119: invokespecial #36                 // Method java/lang/IllegalStateException."<init>":(Ljava/lang/String;)V
     122: athrow
     123: aload         4
     125: invokeinterface #37,  1           // InterfaceMethod org/apache/curator/framework/CuratorFramework.getZookeeperClient:()Lorg/apache/curator/CuratorZookeeperClient;
     130: invokevirtual #38                 // Method org/apache/curator/CuratorZookeeperClient.isConnected:()Z
     133: ifne          146
     136: new           #34                 // class java/lang/IllegalStateException
     139: dup
     140: ldc           #39                 // String failed to connect to zookeeper server
     142: invokespecial #36                 // Method java/lang/IllegalStateException."<init>":(Ljava/lang/String;)V
     145: athrow
     146: aload         4
     148: areturn

  public static org.apache.curator.RetryPolicy buildRetryPolicy(org.apache.dubbo.common.URL);
    Code:
       0: getstatic     #40                 // Field org/apache/dubbo/registry/zookeeper/util/CuratorFrameworkParams.BASE_SLEEP_TIME:Lorg/apache/dubbo/registry/zookeeper/util/CuratorFrameworkParams;
       3: aload_0
       4: invokevirtual #25                 // Method org/apache/dubbo/registry/zookeeper/util/CuratorFrameworkParams.getParameterValue:(Lorg/apache/dubbo/common/URL;)Ljava/lang/Object;
       7: checkcast     #26                 // class java/lang/Integer
      10: invokevirtual #27                 // Method java/lang/Integer.intValue:()I
      13: istore_1
      14: getstatic     #41                 // Field org/apache/dubbo/registry/zookeeper/util/CuratorFrameworkParams.MAX_RETRIES:Lorg/apache/dubbo/registry/zookeeper/util/CuratorFrameworkParams;
      17: aload_0
      18: invokevirtual #25                 // Method org/apache/dubbo/registry/zookeeper/util/CuratorFrameworkParams.getParameterValue:(Lorg/apache/dubbo/common/URL;)Ljava/lang/Object;
      21: checkcast     #26                 // class java/lang/Integer
      24: invokevirtual #27                 // Method java/lang/Integer.intValue:()I
      27: istore_2
      28: getstatic     #42                 // Field org/apache/dubbo/registry/zookeeper/util/CuratorFrameworkParams.MAX_SLEEP:Lorg/apache/dubbo/registry/zookeeper/util/CuratorFrameworkParams;
      31: aload_0
      32: invokevirtual #25                 // Method org/apache/dubbo/registry/zookeeper/util/CuratorFrameworkParams.getParameterValue:(Lorg/apache/dubbo/common/URL;)Ljava/lang/Object;
      35: checkcast     #26                 // class java/lang/Integer
      38: invokevirtual #27                 // Method java/lang/Integer.intValue:()I
      41: istore_3
      42: new           #43                 // class org/apache/curator/retry/ExponentialBackoffRetry
      45: dup
      46: iload_1
      47: iload_2
      48: iload_3
      49: invokespecial #44                 // Method org/apache/curator/retry/ExponentialBackoffRetry."<init>":(III)V
      52: areturn

  public static java.util.List<org.apache.dubbo.registry.client.ServiceInstance> build(org.apache.dubbo.common.URL, java.util.Collection<org.apache.curator.x.discovery.ServiceInstance<org.apache.dubbo.registry.zookeeper.ZookeeperInstance>>);
    Code:
       0: aload_1
       1: invokeinterface #45,  1           // InterfaceMethod java/util/Collection.stream:()Ljava/util/stream/Stream;
       6: aload_0
       7: invokedynamic #46,  0             // InvokeDynamic #0:apply:(Lorg/apache/dubbo/common/URL;)Ljava/util/function/Function;
      12: invokeinterface #47,  2           // InterfaceMethod java/util/stream/Stream.map:(Ljava/util/function/Function;)Ljava/util/stream/Stream;
      17: invokestatic  #48                 // Method java/util/stream/Collectors.toList:()Ljava/util/stream/Collector;
      20: invokeinterface #49,  2           // InterfaceMethod java/util/stream/Stream.collect:(Ljava/util/stream/Collector;)Ljava/lang/Object;
      25: checkcast     #50                 // class java/util/List
      28: areturn

  public static org.apache.dubbo.registry.client.ServiceInstance build(org.apache.dubbo.common.URL, org.apache.curator.x.discovery.ServiceInstance<org.apache.dubbo.registry.zookeeper.ZookeeperInstance>);
    Code:
       0: aload_1
       1: invokevirtual #51                 // Method org/apache/curator/x/discovery/ServiceInstance.getName:()Ljava/lang/String;
       4: astore_2
       5: aload_1
       6: invokevirtual #52                 // Method org/apache/curator/x/discovery/ServiceInstance.getAddress:()Ljava/lang/String;
       9: astore_3
      10: aload_1
      11: invokevirtual #53                 // Method org/apache/curator/x/discovery/ServiceInstance.getPort:()Ljava/lang/Integer;
      14: invokevirtual #27                 // Method java/lang/Integer.intValue:()I
      17: istore        4
      19: aload_1
      20: invokevirtual #54                 // Method org/apache/curator/x/discovery/ServiceInstance.getPayload:()Ljava/lang/Object;
      23: checkcast     #4                  // class org/apache/dubbo/registry/zookeeper/ZookeeperInstance
      26: astore        5
      28: new           #55                 // class org/apache/dubbo/registry/client/DefaultServiceInstance
      31: dup
      32: aload_2
      33: aload_3
      34: iload         4
      36: invokestatic  #56                 // Method java/lang/Integer.valueOf:(I)Ljava/lang/Integer;
      39: aload_0
      40: invokevirtual #57                 // Method org/apache/dubbo/common/URL.getScopeModel:()Lorg/apache/dubbo/rpc/model/ScopeModel;
      43: invokestatic  #58                 // Method org/apache/dubbo/rpc/model/ScopeModelUtil.getApplicationModel:(Lorg/apache/dubbo/rpc/model/ScopeModel;)Lorg/apache/dubbo/rpc/model/ApplicationModel;
      46: invokespecial #59                 // Method org/apache/dubbo/registry/client/DefaultServiceInstance."<init>":(Ljava/lang/String;Ljava/lang/String;Ljava/lang/Integer;Lorg/apache/dubbo/rpc/model/ApplicationModel;)V
      49: astore        6
      51: aload         6
      53: aload         5
      55: invokevirtual #60                 // Method org/apache/dubbo/registry/zookeeper/ZookeeperInstance.getMetadata:()Ljava/util/Map;
      58: invokevirtual #61                 // Method org/apache/dubbo/registry/client/DefaultServiceInstance.setMetadata:(Ljava/util/Map;)V
      61: aload         6
      63: areturn

  public static org.apache.curator.x.discovery.ServiceInstance<org.apache.dubbo.registry.zookeeper.ZookeeperInstance> build(org.apache.dubbo.registry.client.ServiceInstance);
    Code:
       0: aload_0
       1: invokeinterface #62,  1           // InterfaceMethod org/apache/dubbo/registry/client/ServiceInstance.getServiceName:()Ljava/lang/String;
       6: astore_2
       7: aload_0
       8: invokeinterface #63,  1           // InterfaceMethod org/apache/dubbo/registry/client/ServiceInstance.getHost:()Ljava/lang/String;
      13: astore_3
      14: aload_0
      15: invokeinterface #64,  1           // InterfaceMethod org/apache/dubbo/registry/client/ServiceInstance.getPort:()I
      20: istore        4
      22: aload_0
      23: invokeinterface #65,  1           // InterfaceMethod org/apache/dubbo/registry/client/ServiceInstance.getSortedMetadata:()Ljava/util/SortedMap;
      28: astore        5
      30: aload_3
      31: iload         4
      33: invokestatic  #66                 // Method generateId:(Ljava/lang/String;I)Ljava/lang/String;
      36: astore        6
      38: new           #4                  // class org/apache/dubbo/registry/zookeeper/ZookeeperInstance
      41: dup
      42: aload         6
      44: aload_2
      45: aload         5
      47: invokespecial #67                 // Method org/apache/dubbo/registry/zookeeper/ZookeeperInstance."<init>":(Ljava/lang/String;Ljava/lang/String;Ljava/util/Map;)V
      50: astore        7
      52: invokestatic  #68                 // Method org/apache/curator/x/discovery/ServiceInstance.builder:()Lorg/apache/curator/x/discovery/ServiceInstanceBuilder;
      55: aload         6
      57: invokevirtual #69                 // Method org/apache/curator/x/discovery/ServiceInstanceBuilder.id:(Ljava/lang/String;)Lorg/apache/curator/x/discovery/ServiceInstanceBuilder;
      60: aload_2
      61: invokevirtual #70                 // Method org/apache/curator/x/discovery/ServiceInstanceBuilder.name:(Ljava/lang/String;)Lorg/apache/curator/x/discovery/ServiceInstanceBuilder;
      64: aload_3
      65: invokevirtual #71                 // Method org/apache/curator/x/discovery/ServiceInstanceBuilder.address:(Ljava/lang/String;)Lorg/apache/curator/x/discovery/ServiceInstanceBuilder;
      68: iload         4
      70: invokevirtual #72                 // Method org/apache/curator/x/discovery/ServiceInstanceBuilder.port:(I)Lorg/apache/curator/x/discovery/ServiceInstanceBuilder;
      73: aload         7
      75: invokevirtual #73                 // Method org/apache/curator/x/discovery/ServiceInstanceBuilder.payload:(Ljava/lang/Object;)Lorg/apache/curator/x/discovery/ServiceInstanceBuilder;
      78: astore_1
      79: goto          94
      82: astore        8
      84: new           #75                 // class java/lang/RuntimeException
      87: dup
      88: aload         8
      90: invokespecial #76                 // Method java/lang/RuntimeException."<init>":(Ljava/lang/Throwable;)V
      93: athrow
      94: aload_1
      95: invokevirtual #77                 // Method org/apache/curator/x/discovery/ServiceInstanceBuilder.build:()Lorg/apache/curator/x/discovery/ServiceInstance;
      98: areturn
    Exception table:
       from    to  target type
          52    79    82   Class java/lang/Exception

  public static java.lang.String generateId(java.lang.String, int);
    Code:
       0: new           #78                 // class java/lang/StringBuilder
       3: dup
       4: invokespecial #79                 // Method java/lang/StringBuilder."<init>":()V
       7: aload_0
       8: invokevirtual #80                 // Method java/lang/StringBuilder.append:(Ljava/lang/String;)Ljava/lang/StringBuilder;
      11: ldc           #81                 // String :
      13: invokevirtual #80                 // Method java/lang/StringBuilder.append:(Ljava/lang/String;)Ljava/lang/StringBuilder;
      16: iload_1
      17: invokevirtual #82                 // Method java/lang/StringBuilder.append:(I)Ljava/lang/StringBuilder;
      20: invokevirtual #83                 // Method java/lang/StringBuilder.toString:()Ljava/lang/String;
      23: areturn

  public static java.lang.String getRootPath(org.apache.dubbo.common.URL);
    Code:
       0: getstatic     #84                 // Field org/apache/dubbo/registry/zookeeper/util/CuratorFrameworkParams.ROOT_PATH:Lorg/apache/dubbo/registry/zookeeper/util/CuratorFrameworkParams;
       3: aload_0
       4: invokevirtual #25                 // Method org/apache/dubbo/registry/zookeeper/util/CuratorFrameworkParams.getParameterValue:(Lorg/apache/dubbo/common/URL;)Ljava/lang/Object;
       7: checkcast     #85                 // class java/lang/String
      10: astore_1
      11: aload_1
      12: ldc           #86                 // String /services
      14: invokevirtual #87                 // Method java/lang/String.equalsIgnoreCase:(Ljava/lang/String;)Z
      17: ifeq          60
      20: getstatic     #88                 // Field org/apache/dubbo/registry/zookeeper/util/CuratorFrameworkParams.GROUP_PATH:Lorg/apache/dubbo/registry/zookeeper/util/CuratorFrameworkParams;
      23: aload_0
      24: invokevirtual #25                 // Method org/apache/dubbo/registry/zookeeper/util/CuratorFrameworkParams.getParameterValue:(Lorg/apache/dubbo/common/URL;)Ljava/lang/Object;
      27: checkcast     #85                 // class java/lang/String
      30: astore_1
      31: aload_1
      32: ldc           #89                 // String /
      34: invokevirtual #90                 // Method java/lang/String.startsWith:(Ljava/lang/String;)Z
      37: ifne          60
      40: new           #78                 // class java/lang/StringBuilder
      43: dup
      44: invokespecial #79                 // Method java/lang/StringBuilder."<init>":()V
      47: ldc           #89                 // String /
      49: invokevirtual #80                 // Method java/lang/StringBuilder.append:(Ljava/lang/String;)Ljava/lang/StringBuilder;
      52: aload_1
      53: invokevirtual #80                 // Method java/lang/StringBuilder.append:(Ljava/lang/String;)Ljava/lang/StringBuilder;
      56: invokevirtual #83                 // Method java/lang/StringBuilder.toString:()Ljava/lang/String;
      59: astore_1
      60: aload_1
      61: areturn

  private static org.apache.dubbo.registry.client.ServiceInstance lambda$build$0(org.apache.dubbo.common.URL, org.apache.curator.x.discovery.ServiceInstance);
    Code:
       0: aload_0
       1: aload_1
       2: invokestatic  #91                 // Method build:(Lorg/apache/dubbo/common/URL;Lorg/apache/curator/x/discovery/ServiceInstance;)Lorg/apache/dubbo/registry/client/ServiceInstance;
       5: areturn
}
