Compiled from "CuratorFrameworkParams.java"
public final class org.apache.dubbo.registry.zookeeper.util.CuratorFrameworkParams extends java.lang.Enum<org.apache.dubbo.registry.zookeeper.util.CuratorFrameworkParams> {
  public static final org.apache.dubbo.registry.zookeeper.util.CuratorFrameworkParams ROOT_PATH;

  public static final org.apache.dubbo.registry.zookeeper.util.CuratorFrameworkParams GROUP_PATH;

  public static final org.apache.dubbo.registry.zookeeper.util.CuratorFrameworkParams INSTANCE_HOST;

  public static final org.apache.dubbo.registry.zookeeper.util.CuratorFrameworkParams INSTANCE_PORT;

  public static final org.apache.dubbo.registry.zookeeper.util.CuratorFrameworkParams BASE_SLEEP_TIME;

  public static final org.apache.dubbo.registry.zookeeper.util.CuratorFrameworkParams MAX_RETRIES;

  public static final org.apache.dubbo.registry.zookeeper.util.CuratorFrameworkParams MAX_SLEEP;

  public static final org.apache.dubbo.registry.zookeeper.util.CuratorFrameworkParams BLOCK_UNTIL_CONNECTED_WAIT;

  public static final org.apache.dubbo.registry.zookeeper.util.CuratorFrameworkParams BLOCK_UNTIL_CONNECTED_UNIT;

  private final java.lang.String name;

  private final java.lang.Object defaultValue;

  private final java.util.function.Function<java.lang.String, java.lang.Object> converter;

  private static final org.apache.dubbo.registry.zookeeper.util.CuratorFrameworkParams[] $VALUES;

  public static org.apache.dubbo.registry.zookeeper.util.CuratorFrameworkParams[] values();
    Code:
       0: getstatic     #2                  // Field $VALUES:[Lorg/apache/dubbo/registry/zookeeper/util/CuratorFrameworkParams;
       3: invokevirtual #3                  // Method "[Lorg/apache/dubbo/registry/zookeeper/util/CuratorFrameworkParams;".clone:()Ljava/lang/Object;
       6: checkcast     #4                  // class "[Lorg/apache/dubbo/registry/zookeeper/util/CuratorFrameworkParams;"
       9: areturn

  public static org.apache.dubbo.registry.zookeeper.util.CuratorFrameworkParams valueOf(java.lang.String);
    Code:
       0: ldc           #5                  // class org/apache/dubbo/registry/zookeeper/util/CuratorFrameworkParams
       2: aload_0
       3: invokestatic  #6                  // Method java/lang/Enum.valueOf:(Ljava/lang/Class;Ljava/lang/String;)Ljava/lang/Enum;
       6: checkcast     #5                  // class org/apache/dubbo/registry/zookeeper/util/CuratorFrameworkParams
       9: areturn

  private <T> org.apache.dubbo.registry.zookeeper.util.CuratorFrameworkParams(java.lang.String, T, java.util.function.Function<java.lang.String, T>);
    Code:
       0: aload_0
       1: aload_1
       2: iload_2
       3: invokespecial #7                  // Method java/lang/Enum."<init>":(Ljava/lang/String;I)V
       6: aload_0
       7: aload_3
       8: putfield      #8                  // Field name:Ljava/lang/String;
      11: aload_0
      12: aload         4
      14: putfield      #9                  // Field defaultValue:Ljava/lang/Object;
      17: aload_0
      18: aload         5
      20: putfield      #10                 // Field converter:Ljava/util/function/Function;
      23: return

  public <T> T getParameterValue(org.apache.dubbo.common.URL);
    Code:
       0: aload_1
       1: aload_0
       2: getfield      #8                  // Field name:Ljava/lang/String;
       5: invokevirtual #11                 // Method org/apache/dubbo/common/URL.getParameter:(Ljava/lang/String;)Ljava/lang/String;
       8: astore_2
       9: aload_2
      10: ifnull        26
      13: aload_0
      14: getfield      #10                 // Field converter:Ljava/util/function/Function;
      17: aload_2
      18: invokeinterface #12,  2           // InterfaceMethod java/util/function/Function.apply:(Ljava/lang/Object;)Ljava/lang/Object;
      23: goto          30
      26: aload_0
      27: getfield      #9                  // Field defaultValue:Ljava/lang/Object;
      30: astore_3
      31: aload_3
      32: areturn

  private static java.lang.String lambda$static$3(java.lang.String);
    Code:
       0: aload_0
       1: areturn

  private static java.lang.String lambda$static$2(java.lang.String);
    Code:
       0: aload_0
       1: areturn

  private static java.lang.String lambda$static$1(java.lang.String);
    Code:
       0: aload_0
       1: areturn

  private static java.lang.String lambda$static$0(java.lang.String);
    Code:
       0: aload_0
       1: areturn

  static {};
    Code:
       0: new           #5                  // class org/apache/dubbo/registry/zookeeper/util/CuratorFrameworkParams
       3: dup
       4: ldc           #13                 // String ROOT_PATH
       6: iconst_0
       7: ldc           #14                 // String rootPath
       9: ldc           #15                 // String /services
      11: invokedynamic #16,  0             // InvokeDynamic #0:apply:()Ljava/util/function/Function;
      16: invokespecial #17                 // Method "<init>":(Ljava/lang/String;ILjava/lang/String;Ljava/lang/Object;Ljava/util/function/Function;)V
      19: putstatic     #18                 // Field ROOT_PATH:Lorg/apache/dubbo/registry/zookeeper/util/CuratorFrameworkParams;
      22: new           #5                  // class org/apache/dubbo/registry/zookeeper/util/CuratorFrameworkParams
      25: dup
      26: ldc           #19                 // String GROUP_PATH
      28: iconst_1
      29: ldc           #20                 // String group
      31: ldc           #15                 // String /services
      33: invokedynamic #21,  0             // InvokeDynamic #1:apply:()Ljava/util/function/Function;
      38: invokespecial #17                 // Method "<init>":(Ljava/lang/String;ILjava/lang/String;Ljava/lang/Object;Ljava/util/function/Function;)V
      41: putstatic     #22                 // Field GROUP_PATH:Lorg/apache/dubbo/registry/zookeeper/util/CuratorFrameworkParams;
      44: new           #5                  // class org/apache/dubbo/registry/zookeeper/util/CuratorFrameworkParams
      47: dup
      48: ldc           #23                 // String INSTANCE_HOST
      50: iconst_2
      51: ldc           #24                 // String instanceHost
      53: aconst_null
      54: invokedynamic #25,  0             // InvokeDynamic #2:apply:()Ljava/util/function/Function;
      59: invokespecial #17                 // Method "<init>":(Ljava/lang/String;ILjava/lang/String;Ljava/lang/Object;Ljava/util/function/Function;)V
      62: putstatic     #26                 // Field INSTANCE_HOST:Lorg/apache/dubbo/registry/zookeeper/util/CuratorFrameworkParams;
      65: new           #5                  // class org/apache/dubbo/registry/zookeeper/util/CuratorFrameworkParams
      68: dup
      69: ldc           #27                 // String INSTANCE_PORT
      71: iconst_3
      72: ldc           #28                 // String instancePort
      74: aconst_null
      75: invokedynamic #29,  0             // InvokeDynamic #3:apply:()Ljava/util/function/Function;
      80: invokespecial #17                 // Method "<init>":(Ljava/lang/String;ILjava/lang/String;Ljava/lang/Object;Ljava/util/function/Function;)V
      83: putstatic     #30                 // Field INSTANCE_PORT:Lorg/apache/dubbo/registry/zookeeper/util/CuratorFrameworkParams;
      86: new           #5                  // class org/apache/dubbo/registry/zookeeper/util/CuratorFrameworkParams
      89: dup
      90: ldc           #31                 // String BASE_SLEEP_TIME
      92: iconst_4
      93: ldc           #32                 // String baseSleepTimeMs
      95: bipush        50
      97: invokestatic  #33                 // Method java/lang/Integer.valueOf:(I)Ljava/lang/Integer;
     100: invokedynamic #34,  0             // InvokeDynamic #4:apply:()Ljava/util/function/Function;
     105: invokespecial #17                 // Method "<init>":(Ljava/lang/String;ILjava/lang/String;Ljava/lang/Object;Ljava/util/function/Function;)V
     108: putstatic     #35                 // Field BASE_SLEEP_TIME:Lorg/apache/dubbo/registry/zookeeper/util/CuratorFrameworkParams;
     111: new           #5                  // class org/apache/dubbo/registry/zookeeper/util/CuratorFrameworkParams
     114: dup
     115: ldc           #36                 // String MAX_RETRIES
     117: iconst_5
     118: ldc           #37                 // String maxRetries
     120: bipush        10
     122: invokestatic  #33                 // Method java/lang/Integer.valueOf:(I)Ljava/lang/Integer;
     125: invokedynamic #34,  0             // InvokeDynamic #4:apply:()Ljava/util/function/Function;
     130: invokespecial #17                 // Method "<init>":(Ljava/lang/String;ILjava/lang/String;Ljava/lang/Object;Ljava/util/function/Function;)V
     133: putstatic     #38                 // Field MAX_RETRIES:Lorg/apache/dubbo/registry/zookeeper/util/CuratorFrameworkParams;
     136: new           #5                  // class org/apache/dubbo/registry/zookeeper/util/CuratorFrameworkParams
     139: dup
     140: ldc           #39                 // String MAX_SLEEP
     142: bipush        6
     144: ldc           #40                 // String maxSleepMs
     146: sipush        500
     149: invokestatic  #33                 // Method java/lang/Integer.valueOf:(I)Ljava/lang/Integer;
     152: invokedynamic #34,  0             // InvokeDynamic #4:apply:()Ljava/util/function/Function;
     157: invokespecial #17                 // Method "<init>":(Ljava/lang/String;ILjava/lang/String;Ljava/lang/Object;Ljava/util/function/Function;)V
     160: putstatic     #41                 // Field MAX_SLEEP:Lorg/apache/dubbo/registry/zookeeper/util/CuratorFrameworkParams;
     163: new           #5                  // class org/apache/dubbo/registry/zookeeper/util/CuratorFrameworkParams
     166: dup
     167: ldc           #42                 // String BLOCK_UNTIL_CONNECTED_WAIT
     169: bipush        7
     171: ldc           #43                 // String blockUntilConnectedWait
     173: bipush        10
     175: invokestatic  #33                 // Method java/lang/Integer.valueOf:(I)Ljava/lang/Integer;
     178: invokedynamic #34,  0             // InvokeDynamic #4:apply:()Ljava/util/function/Function;
     183: invokespecial #17                 // Method "<init>":(Ljava/lang/String;ILjava/lang/String;Ljava/lang/Object;Ljava/util/function/Function;)V
     186: putstatic     #44                 // Field BLOCK_UNTIL_CONNECTED_WAIT:Lorg/apache/dubbo/registry/zookeeper/util/CuratorFrameworkParams;
     189: new           #5                  // class org/apache/dubbo/registry/zookeeper/util/CuratorFrameworkParams
     192: dup
     193: ldc           #45                 // String BLOCK_UNTIL_CONNECTED_UNIT
     195: bipush        8
     197: ldc           #46                 // String blockUntilConnectedUnit
     199: getstatic     #47                 // Field java/util/concurrent/TimeUnit.SECONDS:Ljava/util/concurrent/TimeUnit;
     202: invokedynamic #48,  0             // InvokeDynamic #5:apply:()Ljava/util/function/Function;
     207: invokespecial #17                 // Method "<init>":(Ljava/lang/String;ILjava/lang/String;Ljava/lang/Object;Ljava/util/function/Function;)V
     210: putstatic     #49                 // Field BLOCK_UNTIL_CONNECTED_UNIT:Lorg/apache/dubbo/registry/zookeeper/util/CuratorFrameworkParams;
     213: bipush        9
     215: anewarray     #5                  // class org/apache/dubbo/registry/zookeeper/util/CuratorFrameworkParams
     218: dup
     219: iconst_0
     220: getstatic     #18                 // Field ROOT_PATH:Lorg/apache/dubbo/registry/zookeeper/util/CuratorFrameworkParams;
     223: aastore
     224: dup
     225: iconst_1
     226: getstatic     #22                 // Field GROUP_PATH:Lorg/apache/dubbo/registry/zookeeper/util/CuratorFrameworkParams;
     229: aastore
     230: dup
     231: iconst_2
     232: getstatic     #26                 // Field INSTANCE_HOST:Lorg/apache/dubbo/registry/zookeeper/util/CuratorFrameworkParams;
     235: aastore
     236: dup
     237: iconst_3
     238: getstatic     #30                 // Field INSTANCE_PORT:Lorg/apache/dubbo/registry/zookeeper/util/CuratorFrameworkParams;
     241: aastore
     242: dup
     243: iconst_4
     244: getstatic     #35                 // Field BASE_SLEEP_TIME:Lorg/apache/dubbo/registry/zookeeper/util/CuratorFrameworkParams;
     247: aastore
     248: dup
     249: iconst_5
     250: getstatic     #38                 // Field MAX_RETRIES:Lorg/apache/dubbo/registry/zookeeper/util/CuratorFrameworkParams;
     253: aastore
     254: dup
     255: bipush        6
     257: getstatic     #41                 // Field MAX_SLEEP:Lorg/apache/dubbo/registry/zookeeper/util/CuratorFrameworkParams;
     260: aastore
     261: dup
     262: bipush        7
     264: getstatic     #44                 // Field BLOCK_UNTIL_CONNECTED_WAIT:Lorg/apache/dubbo/registry/zookeeper/util/CuratorFrameworkParams;
     267: aastore
     268: dup
     269: bipush        8
     271: getstatic     #49                 // Field BLOCK_UNTIL_CONNECTED_UNIT:Lorg/apache/dubbo/registry/zookeeper/util/CuratorFrameworkParams;
     274: aastore
     275: putstatic     #2                  // Field $VALUES:[Lorg/apache/dubbo/registry/zookeeper/util/CuratorFrameworkParams;
     278: return
}
