Compiled from "CompactedJavaSerialization.java"
public class org.apache.dubbo.common.serialize.java.CompactedJavaSerialization implements org.apache.dubbo.common.serialize.Serialization {
  public org.apache.dubbo.common.serialize.java.CompactedJavaSerialization();
    Code:
       0: aload_0
       1: invokespecial #2                  // Method java/lang/Object."<init>":()V
       4: return

  public byte getContentTypeId();
    Code:
       0: iconst_4
       1: ireturn

  public java.lang.String getContentType();
    Code:
       0: ldc           #3                  // String x-application/compactedjava
       2: areturn

  public org.apache.dubbo.common.serialize.ObjectOutput serialize(org.apache.dubbo.common.URL, java.io.OutputStream) throws java.io.IOException;
    Code:
       0: new           #4                  // class org/apache/dubbo/common/serialize/java/JavaObjectOutput
       3: dup
       4: aload_2
       5: iconst_1
       6: invokespecial #5                  // Method org/apache/dubbo/common/serialize/java/JavaObjectOutput."<init>":(Ljava/io/OutputStream;Z)V
       9: areturn

  public org.apache.dubbo.common.serialize.ObjectInput deserialize(org.apache.dubbo.common.URL, java.io.InputStream) throws java.io.IOException;
    Code:
       0: new           #6                  // class org/apache/dubbo/common/serialize/java/JavaObjectInput
       3: dup
       4: aload_2
       5: iconst_1
       6: invokespecial #7                  // Method org/apache/dubbo/common/serialize/java/JavaObjectInput."<init>":(Ljava/io/InputStream;Z)V
       9: areturn
}
