Compiled from "JavaObjectInput.java"
public class org.apache.dubbo.common.serialize.java.JavaObjectInput extends org.apache.dubbo.common.serialize.nativejava.NativeJavaObjectInput {
  public static final int MAX_BYTE_ARRAY_LENGTH;

  public org.apache.dubbo.common.serialize.java.JavaObjectInput(java.io.InputStream) throws java.io.IOException;
    Code:
       0: aload_0
       1: new           #1                  // class java/io/ObjectInputStream
       4: dup
       5: aload_1
       6: invokespecial #2                  // Method java/io/ObjectInputStream."<init>":(Ljava/io/InputStream;)V
       9: invokespecial #3                  // Method org/apache/dubbo/common/serialize/nativejava/NativeJavaObjectInput."<init>":(Ljava/io/ObjectInputStream;)V
      12: return

  public org.apache.dubbo.common.serialize.java.JavaObjectInput(java.io.InputStream, boolean) throws java.io.IOException;
    Code:
       0: aload_0
       1: iload_2
       2: ifeq          16
       5: new           #4                  // class org/apache/dubbo/common/serialize/java/CompactedObjectInputStream
       8: dup
       9: aload_1
      10: invokespecial #5                  // Method org/apache/dubbo/common/serialize/java/CompactedObjectInputStream."<init>":(Ljava/io/InputStream;)V
      13: goto          24
      16: new           #1                  // class java/io/ObjectInputStream
      19: dup
      20: aload_1
      21: invokespecial #2                  // Method java/io/ObjectInputStream."<init>":(Ljava/io/InputStream;)V
      24: invokespecial #3                  // Method org/apache/dubbo/common/serialize/nativejava/NativeJavaObjectInput."<init>":(Ljava/io/ObjectInputStream;)V
      27: return

  public byte[] readBytes() throws java.io.IOException;
    Code:
       0: aload_0
       1: invokevirtual #6                  // Method getObjectInputStream:()Ljava/io/ObjectInputStream;
       4: invokevirtual #7                  // Method java/io/ObjectInputStream.readInt:()I
       7: istore_1
       8: iload_1
       9: ifge          14
      12: aconst_null
      13: areturn
      14: iload_1
      15: ifne          22
      18: iconst_0
      19: newarray       byte
      21: areturn
      22: iload_1
      23: ldc           #9                  // int 8388608
      25: if_icmple     55
      28: new           #10                 // class java/io/IOException
      31: dup
      32: new           #11                 // class java/lang/StringBuilder
      35: dup
      36: invokespecial #12                 // Method java/lang/StringBuilder."<init>":()V
      39: ldc           #13                 // String Byte array length too large.
      41: invokevirtual #14                 // Method java/lang/StringBuilder.append:(Ljava/lang/String;)Ljava/lang/StringBuilder;
      44: iload_1
      45: invokevirtual #15                 // Method java/lang/StringBuilder.append:(I)Ljava/lang/StringBuilder;
      48: invokevirtual #16                 // Method java/lang/StringBuilder.toString:()Ljava/lang/String;
      51: invokespecial #17                 // Method java/io/IOException."<init>":(Ljava/lang/String;)V
      54: athrow
      55: iload_1
      56: newarray       byte
      58: astore_2
      59: aload_0
      60: invokevirtual #6                  // Method getObjectInputStream:()Ljava/io/ObjectInputStream;
      63: aload_2
      64: invokevirtual #18                 // Method java/io/ObjectInputStream.readFully:([B)V
      67: aload_2
      68: areturn

  public java.lang.String readUTF() throws java.io.IOException;
    Code:
       0: aload_0
       1: invokevirtual #6                  // Method getObjectInputStream:()Ljava/io/ObjectInputStream;
       4: invokevirtual #7                  // Method java/io/ObjectInputStream.readInt:()I
       7: istore_1
       8: iload_1
       9: ifge          14
      12: aconst_null
      13: areturn
      14: aload_0
      15: invokevirtual #6                  // Method getObjectInputStream:()Ljava/io/ObjectInputStream;
      18: invokevirtual #19                 // Method java/io/ObjectInputStream.readUTF:()Ljava/lang/String;
      21: areturn

  public java.lang.Object readObject() throws java.io.IOException, java.lang.ClassNotFoundException;
    Code:
       0: aload_0
       1: invokevirtual #6                  // Method getObjectInputStream:()Ljava/io/ObjectInputStream;
       4: invokevirtual #20                 // Method java/io/ObjectInputStream.readByte:()B
       7: istore_1
       8: iload_1
       9: ifne          14
      12: aconst_null
      13: areturn
      14: aload_0
      15: invokevirtual #6                  // Method getObjectInputStream:()Ljava/io/ObjectInputStream;
      18: invokevirtual #21                 // Method java/io/ObjectInputStream.readObject:()Ljava/lang/Object;
      21: areturn

  public <T> T readObject(java.lang.Class<T>) throws java.io.IOException, java.lang.ClassNotFoundException;
    Code:
       0: aload_0
       1: invokevirtual #22                 // Method readObject:()Ljava/lang/Object;
       4: areturn

  public <T> T readObject(java.lang.Class<T>, java.lang.reflect.Type) throws java.io.IOException, java.lang.ClassNotFoundException;
    Code:
       0: aload_0
       1: invokevirtual #22                 // Method readObject:()Ljava/lang/Object;
       4: areturn
}
