Compiled from "JavaObjectOutput.java"
public class org.apache.dubbo.common.serialize.java.JavaObjectOutput extends org.apache.dubbo.common.serialize.nativejava.NativeJavaObjectOutput {
  public org.apache.dubbo.common.serialize.java.JavaObjectOutput(java.io.OutputStream) throws java.io.IOException;
    Code:
       0: aload_0
       1: new           #1                  // class java/io/ObjectOutputStream
       4: dup
       5: aload_1
       6: invokespecial #2                  // Method java/io/ObjectOutputStream."<init>":(Ljava/io/OutputStream;)V
       9: invokespecial #3                  // Method org/apache/dubbo/common/serialize/nativejava/NativeJavaObjectOutput."<init>":(Ljava/io/ObjectOutputStream;)V
      12: return

  public org.apache.dubbo.common.serialize.java.JavaObjectOutput(java.io.OutputStream, boolean) throws java.io.IOException;
    Code:
       0: aload_0
       1: iload_2
       2: ifeq          16
       5: new           #4                  // class org/apache/dubbo/common/serialize/java/CompactedObjectOutputStream
       8: dup
       9: aload_1
      10: invokespecial #5                  // Method org/apache/dubbo/common/serialize/java/CompactedObjectOutputStream."<init>":(Ljava/io/OutputStream;)V
      13: goto          24
      16: new           #1                  // class java/io/ObjectOutputStream
      19: dup
      20: aload_1
      21: invokespecial #2                  // Method java/io/ObjectOutputStream."<init>":(Ljava/io/OutputStream;)V
      24: invokespecial #3                  // Method org/apache/dubbo/common/serialize/nativejava/NativeJavaObjectOutput."<init>":(Ljava/io/ObjectOutputStream;)V
      27: return

  public void writeUTF(java.lang.String) throws java.io.IOException;
    Code:
       0: aload_1
       1: ifnonnull     15
       4: aload_0
       5: invokevirtual #6                  // Method getObjectOutputStream:()Ljava/io/ObjectOutputStream;
       8: iconst_m1
       9: invokevirtual #7                  // Method java/io/ObjectOutputStream.writeInt:(I)V
      12: goto          34
      15: aload_0
      16: invokevirtual #6                  // Method getObjectOutputStream:()Ljava/io/ObjectOutputStream;
      19: aload_1
      20: invokevirtual #8                  // Method java/lang/String.length:()I
      23: invokevirtual #7                  // Method java/io/ObjectOutputStream.writeInt:(I)V
      26: aload_0
      27: invokevirtual #6                  // Method getObjectOutputStream:()Ljava/io/ObjectOutputStream;
      30: aload_1
      31: invokevirtual #9                  // Method java/io/ObjectOutputStream.writeUTF:(Ljava/lang/String;)V
      34: return

  public void writeObject(java.lang.Object) throws java.io.IOException;
    Code:
       0: aload_1
       1: ifnonnull     15
       4: aload_0
       5: invokevirtual #6                  // Method getObjectOutputStream:()Ljava/io/ObjectOutputStream;
       8: iconst_0
       9: invokevirtual #10                 // Method java/io/ObjectOutputStream.writeByte:(I)V
      12: goto          31
      15: aload_0
      16: invokevirtual #6                  // Method getObjectOutputStream:()Ljava/io/ObjectOutputStream;
      19: iconst_1
      20: invokevirtual #10                 // Method java/io/ObjectOutputStream.writeByte:(I)V
      23: aload_0
      24: invokevirtual #6                  // Method getObjectOutputStream:()Ljava/io/ObjectOutputStream;
      27: aload_1
      28: invokevirtual #11                 // Method java/io/ObjectOutputStream.writeObject:(Ljava/lang/Object;)V
      31: return

  public void flushBuffer() throws java.io.IOException;
    Code:
       0: aload_0
       1: invokevirtual #6                  // Method getObjectOutputStream:()Ljava/io/ObjectOutputStream;
       4: invokevirtual #12                 // Method java/io/ObjectOutputStream.flush:()V
       7: return
}
