Compiled from "AnnotationBeanDefinitionParser.java"
public class org.apache.dubbo.config.spring.schema.AnnotationBeanDefinitionParser extends org.springframework.beans.factory.xml.AbstractSingleBeanDefinitionParser {
  public org.apache.dubbo.config.spring.schema.AnnotationBeanDefinitionParser();
    Code:
       0: aload_0
       1: invokespecial #1                  // Method org/springframework/beans/factory/xml/AbstractSingleBeanDefinitionParser."<init>":()V
       4: return

  protected void doParse(org.w3c.dom.Element, org.springframework.beans.factory.xml.ParserContext, org.springframework.beans.factory.support.BeanDefinitionBuilder);
    Code:
       0: aload_1
       1: ldc           #2                  // String package
       3: invokeinterface #3,  2            // InterfaceMethod org/w3c/dom/Element.getAttribute:(Ljava/lang/String;)Ljava/lang/String;
       8: astore        4
      10: aload         4
      12: invokestatic  #4                  // Method org/springframework/util/StringUtils.commaDelimitedListToStringArray:(Ljava/lang/String;)[Ljava/lang/String;
      15: invokestatic  #5                  // Method org/springframework/util/StringUtils.trimArrayElements:([Ljava/lang/String;)[Ljava/lang/String;
      18: astore        5
      20: aload_3
      21: aload         5
      23: invokevirtual #6                  // Method org/springframework/beans/factory/support/BeanDefinitionBuilder.addConstructorArgValue:(Ljava/lang/Object;)Lorg/springframework/beans/factory/support/BeanDefinitionBuilder;
      26: pop
      27: aload_3
      28: iconst_2
      29: invokevirtual #8                  // Method org/springframework/beans/factory/support/BeanDefinitionBuilder.setRole:(I)Lorg/springframework/beans/factory/support/BeanDefinitionBuilder;
      32: pop
      33: return

  protected boolean shouldGenerateIdAsFallback();
    Code:
       0: iconst_1
       1: ireturn

  protected java.lang.Class<?> getBeanClass(org.w3c.dom.Element);
    Code:
       0: ldc           #9                  // class org/apache/dubbo/config/spring/beans/factory/annotation/ServiceAnnotationPostProcessor
       2: areturn
}
