Compiled from "DubboBeanDefinitionParser.java"
public class org.apache.dubbo.config.spring.schema.DubboBeanDefinitionParser implements org.springframework.beans.factory.xml.BeanDefinitionParser {
  private static final org.apache.dubbo.common.logger.Logger logger;

  private static final java.util.regex.Pattern GROUP_AND_VERSION;

  private static final java.lang.String ONRETURN;

  private static final java.lang.String ONTHROW;

  private static final java.lang.String ONINVOKE;

  private static final java.lang.String EXECUTOR;

  private static final java.lang.String METHOD;

  private static final java.lang.String BEAN_NAME;

  private static boolean resolvePlaceholdersEnabled;

  private final java.lang.Class<?> beanClass;

  private static java.util.Map<java.lang.String, java.util.Map<java.lang.String, java.lang.Class>> beanPropsCache;

  public org.apache.dubbo.config.spring.schema.DubboBeanDefinitionParser(java.lang.Class<?>);
    Code:
       0: aload_0
       1: invokespecial #2                  // Method java/lang/Object."<init>":()V
       4: aload_0
       5: aload_1
       6: putfield      #3                  // Field beanClass:Ljava/lang/Class;
       9: return

  private static org.springframework.beans.factory.support.RootBeanDefinition parse(org.w3c.dom.Element, org.springframework.beans.factory.xml.ParserContext, java.lang.Class<?>, boolean);
    Code:
       0: new           #4                  // class org/springframework/beans/factory/support/RootBeanDefinition
       3: dup
       4: invokespecial #5                  // Method org/springframework/beans/factory/support/RootBeanDefinition."<init>":()V
       7: astore        4
       9: aload         4
      11: aload_2
      12: invokevirtual #6                  // Method org/springframework/beans/factory/support/RootBeanDefinition.setBeanClass:(Ljava/lang/Class;)V
      15: aload         4
      17: iconst_0
      18: invokevirtual #7                  // Method org/springframework/beans/factory/support/RootBeanDefinition.setLazyInit:(Z)V
      21: aload_0
      22: ldc           #8                  // String id
      24: aload_1
      25: invokestatic  #9                  // Method resolveAttribute:(Lorg/w3c/dom/Element;Ljava/lang/String;Lorg/springframework/beans/factory/xml/ParserContext;)Ljava/lang/String;
      28: astore        5
      30: aload         5
      32: invokestatic  #10                 // Method org/apache/dubbo/common/utils/StringUtils.isNotEmpty:(Ljava/lang/String;)Z
      35: ifeq          50
      38: aload         4
      40: invokevirtual #11                 // Method org/springframework/beans/factory/support/RootBeanDefinition.getPropertyValues:()Lorg/springframework/beans/MutablePropertyValues;
      43: ldc           #8                  // String id
      45: aload         5
      47: invokevirtual #12                 // Method org/springframework/beans/MutablePropertyValues.addPropertyValue:(Ljava/lang/String;Ljava/lang/Object;)V
      50: aload         5
      52: invokestatic  #13                 // Method org/apache/dubbo/common/utils/StringUtils.isEmpty:(Ljava/lang/String;)Z
      55: ifeq          67
      58: aload_0
      59: ldc           #14                 // String name
      61: aload_1
      62: invokestatic  #9                  // Method resolveAttribute:(Lorg/w3c/dom/Element;Ljava/lang/String;Lorg/springframework/beans/factory/xml/ParserContext;)Ljava/lang/String;
      65: astore        5
      67: aload         5
      69: astore        6
      71: aload         6
      73: invokestatic  #13                 // Method org/apache/dubbo/common/utils/StringUtils.isEmpty:(Ljava/lang/String;)Z
      76: ifeq          162
      79: aload_2
      80: invokevirtual #15                 // Method java/lang/Class.getName:()Ljava/lang/String;
      83: astore        7
      85: iconst_0
      86: istore        8
      88: new           #16                 // class java/lang/StringBuilder
      91: dup
      92: invokespecial #17                 // Method java/lang/StringBuilder."<init>":()V
      95: aload         7
      97: invokevirtual #18                 // Method java/lang/StringBuilder.append:(Ljava/lang/String;)Ljava/lang/StringBuilder;
     100: ldc           #19                 // String #
     102: invokevirtual #18                 // Method java/lang/StringBuilder.append:(Ljava/lang/String;)Ljava/lang/StringBuilder;
     105: iload         8
     107: invokevirtual #20                 // Method java/lang/StringBuilder.append:(I)Ljava/lang/StringBuilder;
     110: invokevirtual #21                 // Method java/lang/StringBuilder.toString:()Ljava/lang/String;
     113: astore        6
     115: aload_1
     116: invokevirtual #22                 // Method org/springframework/beans/factory/xml/ParserContext.getRegistry:()Lorg/springframework/beans/factory/support/BeanDefinitionRegistry;
     119: aload         6
     121: invokeinterface #23,  2           // InterfaceMethod org/springframework/beans/factory/support/BeanDefinitionRegistry.containsBeanDefinition:(Ljava/lang/String;)Z
     126: ifeq          162
     129: new           #16                 // class java/lang/StringBuilder
     132: dup
     133: invokespecial #17                 // Method java/lang/StringBuilder."<init>":()V
     136: aload         7
     138: invokevirtual #18                 // Method java/lang/StringBuilder.append:(Ljava/lang/String;)Ljava/lang/StringBuilder;
     141: ldc           #19                 // String #
     143: invokevirtual #18                 // Method java/lang/StringBuilder.append:(Ljava/lang/String;)Ljava/lang/StringBuilder;
     146: iload         8
     148: iinc          8, 1
     151: invokevirtual #20                 // Method java/lang/StringBuilder.append:(I)Ljava/lang/StringBuilder;
     154: invokevirtual #21                 // Method java/lang/StringBuilder.toString:()Ljava/lang/String;
     157: astore        6
     159: goto          115
     162: aload         4
     164: ldc           #25                 // String BEAN_NAME
     166: aload         6
     168: invokevirtual #26                 // Method org/springframework/beans/factory/support/RootBeanDefinition.setAttribute:(Ljava/lang/String;Ljava/lang/Object;)V
     171: ldc           #27                 // class org/apache/dubbo/config/ProtocolConfig
     173: aload_2
     174: invokevirtual #28                 // Method java/lang/Object.equals:(Ljava/lang/Object;)Z
     177: ifeq          183
     180: goto          285
     183: ldc           #29                 // class org/apache/dubbo/config/spring/ServiceBean
     185: aload_2
     186: invokevirtual #28                 // Method java/lang/Object.equals:(Ljava/lang/Object;)Z
     189: ifeq          285
     192: aload_0
     193: ldc           #30                 // String class
     195: aload_1
     196: invokestatic  #9                  // Method resolveAttribute:(Lorg/w3c/dom/Element;Ljava/lang/String;Lorg/springframework/beans/factory/xml/ParserContext;)Ljava/lang/String;
     199: astore        7
     201: aload         7
     203: invokestatic  #10                 // Method org/apache/dubbo/common/utils/StringUtils.isNotEmpty:(Ljava/lang/String;)Z
     206: ifeq          285
     209: new           #4                  // class org/springframework/beans/factory/support/RootBeanDefinition
     212: dup
     213: invokespecial #5                  // Method org/springframework/beans/factory/support/RootBeanDefinition."<init>":()V
     216: astore        8
     218: aload         8
     220: aload         7
     222: invokestatic  #31                 // Method org/apache/dubbo/common/utils/ReflectUtils.forName:(Ljava/lang/String;)Ljava/lang/Class;
     225: invokevirtual #6                  // Method org/springframework/beans/factory/support/RootBeanDefinition.setBeanClass:(Ljava/lang/Class;)V
     228: aload         8
     230: iconst_0
     231: invokevirtual #7                  // Method org/springframework/beans/factory/support/RootBeanDefinition.setLazyInit:(Z)V
     234: aload_0
     235: invokeinterface #32,  1           // InterfaceMethod org/w3c/dom/Element.getChildNodes:()Lorg/w3c/dom/NodeList;
     240: aload         8
     242: aload_1
     243: invokestatic  #33                 // Method parseProperties:(Lorg/w3c/dom/NodeList;Lorg/springframework/beans/factory/support/RootBeanDefinition;Lorg/springframework/beans/factory/xml/ParserContext;)V
     246: aload         4
     248: invokevirtual #11                 // Method org/springframework/beans/factory/support/RootBeanDefinition.getPropertyValues:()Lorg/springframework/beans/MutablePropertyValues;
     251: ldc           #34                 // String ref
     253: new           #35                 // class org/springframework/beans/factory/config/BeanDefinitionHolder
     256: dup
     257: aload         8
     259: new           #16                 // class java/lang/StringBuilder
     262: dup
     263: invokespecial #17                 // Method java/lang/StringBuilder."<init>":()V
     266: aload         6
     268: invokevirtual #18                 // Method java/lang/StringBuilder.append:(Ljava/lang/String;)Ljava/lang/StringBuilder;
     271: ldc           #36                 // String Impl
     273: invokevirtual #18                 // Method java/lang/StringBuilder.append:(Ljava/lang/String;)Ljava/lang/StringBuilder;
     276: invokevirtual #21                 // Method java/lang/StringBuilder.toString:()Ljava/lang/String;
     279: invokespecial #37                 // Method org/springframework/beans/factory/config/BeanDefinitionHolder."<init>":(Lorg/springframework/beans/factory/config/BeanDefinition;Ljava/lang/String;)V
     282: invokevirtual #12                 // Method org/springframework/beans/MutablePropertyValues.addPropertyValue:(Ljava/lang/String;Ljava/lang/Object;)V
     285: getstatic     #38                 // Field beanPropsCache:Ljava/util/Map;
     288: aload_2
     289: invokevirtual #15                 // Method java/lang/Class.getName:()Ljava/lang/String;
     292: invokeinterface #39,  2           // InterfaceMethod java/util/Map.get:(Ljava/lang/Object;)Ljava/lang/Object;
     297: checkcast     #40                 // class java/util/Map
     300: astore        7
     302: aload         7
     304: ifnonnull     356
     307: new           #41                 // class java/util/HashMap
     310: dup
     311: invokespecial #42                 // Method java/util/HashMap."<init>":()V
     314: astore        7
     316: getstatic     #38                 // Field beanPropsCache:Ljava/util/Map;
     319: aload_2
     320: invokevirtual #15                 // Method java/lang/Class.getName:()Ljava/lang/String;
     323: aload         7
     325: invokeinterface #43,  3           // InterfaceMethod java/util/Map.put:(Ljava/lang/Object;Ljava/lang/Object;)Ljava/lang/Object;
     330: pop
     331: ldc           #44                 // class org/apache/dubbo/config/spring/ReferenceBean
     333: aload_2
     334: invokevirtual #28                 // Method java/lang/Object.equals:(Ljava/lang/Object;)Z
     337: ifeq          350
     340: ldc           #45                 // class org/apache/dubbo/config/ReferenceConfig
     342: aload         7
     344: invokestatic  #46                 // Method getPropertyMap:(Ljava/lang/Class;Ljava/util/Map;)V
     347: goto          356
     350: aload_2
     351: aload         7
     353: invokestatic  #46                 // Method getPropertyMap:(Ljava/lang/Class;Ljava/util/Map;)V
     356: aconst_null
     357: astore        8
     359: new           #47                 // class java/util/HashSet
     362: dup
     363: invokespecial #48                 // Method java/util/HashSet."<init>":()V
     366: astore        9
     368: aload         7
     370: invokeinterface #49,  1           // InterfaceMethod java/util/Map.entrySet:()Ljava/util/Set;
     375: invokeinterface #50,  1           // InterfaceMethod java/util/Set.iterator:()Ljava/util/Iterator;
     380: astore        10
     382: aload         10
     384: invokeinterface #51,  1           // InterfaceMethod java/util/Iterator.hasNext:()Z
     389: ifeq          964
     392: aload         10
     394: invokeinterface #52,  1           // InterfaceMethod java/util/Iterator.next:()Ljava/lang/Object;
     399: checkcast     #53                 // class java/util/Map$Entry
     402: astore        11
     404: aload         11
     406: invokeinterface #54,  1           // InterfaceMethod java/util/Map$Entry.getKey:()Ljava/lang/Object;
     411: checkcast     #55                 // class java/lang/String
     414: astore        12
     416: aload         11
     418: invokeinterface #56,  1           // InterfaceMethod java/util/Map$Entry.getValue:()Ljava/lang/Object;
     423: checkcast     #57                 // class java/lang/Class
     426: astore        13
     428: aload         12
     430: ldc           #58                 // String -
     432: invokestatic  #59                 // Method org/apache/dubbo/common/utils/StringUtils.camelToSplitName:(Ljava/lang/String;Ljava/lang/String;)Ljava/lang/String;
     435: astore        14
     437: aload         9
     439: aload         14
     441: invokeinterface #60,  2           // InterfaceMethod java/util/Set.add:(Ljava/lang/Object;)Z
     446: pop
     447: ldc           #61                 // String parameters
     449: aload         14
     451: invokevirtual #62                 // Method java/lang/String.equals:(Ljava/lang/Object;)Z
     454: ifeq          474
     457: aload_0
     458: invokeinterface #32,  1           // InterfaceMethod org/w3c/dom/Element.getChildNodes:()Lorg/w3c/dom/NodeList;
     463: aload         4
     465: aload_1
     466: invokestatic  #63                 // Method parseParameters:(Lorg/w3c/dom/NodeList;Lorg/springframework/beans/factory/support/RootBeanDefinition;Lorg/springframework/beans/factory/xml/ParserContext;)Lorg/springframework/beans/factory/support/ManagedMap;
     469: astore        8
     471: goto          961
     474: ldc           #64                 // String methods
     476: aload         14
     478: invokevirtual #62                 // Method java/lang/String.equals:(Ljava/lang/Object;)Z
     481: ifeq          501
     484: aload         6
     486: aload_0
     487: invokeinterface #32,  1           // InterfaceMethod org/w3c/dom/Element.getChildNodes:()Lorg/w3c/dom/NodeList;
     492: aload         4
     494: aload_1
     495: invokestatic  #65                 // Method parseMethods:(Ljava/lang/String;Lorg/w3c/dom/NodeList;Lorg/springframework/beans/factory/support/RootBeanDefinition;Lorg/springframework/beans/factory/xml/ParserContext;)V
     498: goto          961
     501: ldc           #66                 // String arguments
     503: aload         14
     505: invokevirtual #62                 // Method java/lang/String.equals:(Ljava/lang/Object;)Z
     508: ifeq          528
     511: aload         6
     513: aload_0
     514: invokeinterface #32,  1           // InterfaceMethod org/w3c/dom/Element.getChildNodes:()Lorg/w3c/dom/NodeList;
     519: aload         4
     521: aload_1
     522: invokestatic  #67                 // Method parseArguments:(Ljava/lang/String;Lorg/w3c/dom/NodeList;Lorg/springframework/beans/factory/support/RootBeanDefinition;Lorg/springframework/beans/factory/xml/ParserContext;)V
     525: goto          961
     528: aload_0
     529: aload         14
     531: aload_1
     532: invokestatic  #9                  // Method resolveAttribute:(Lorg/w3c/dom/Element;Ljava/lang/String;Lorg/springframework/beans/factory/xml/ParserContext;)Ljava/lang/String;
     535: astore        15
     537: aload         15
     539: invokestatic  #68                 // Method org/apache/dubbo/common/utils/StringUtils.isNotBlank:(Ljava/lang/CharSequence;)Z
     542: ifeq          961
     545: aload         15
     547: invokevirtual #69                 // Method java/lang/String.trim:()Ljava/lang/String;
     550: astore        15
     552: ldc           #70                 // String registry
     554: aload         14
     556: invokevirtual #62                 // Method java/lang/String.equals:(Ljava/lang/Object;)Z
     559: ifeq          609
     562: ldc           #72                 // String N/A
     564: aload         15
     566: invokevirtual #73                 // Method java/lang/String.equalsIgnoreCase:(Ljava/lang/String;)Z
     569: ifeq          609
     572: new           #71                 // class org/apache/dubbo/config/RegistryConfig
     575: dup
     576: invokespecial #74                 // Method org/apache/dubbo/config/RegistryConfig."<init>":()V
     579: astore        16
     581: aload         16
     583: ldc           #72                 // String N/A
     585: invokevirtual #75                 // Method org/apache/dubbo/config/RegistryConfig.setAddress:(Ljava/lang/String;)V
     588: aload         4
     590: invokevirtual #11                 // Method org/springframework/beans/factory/support/RootBeanDefinition.getPropertyValues:()Lorg/springframework/beans/MutablePropertyValues;
     593: ldc           #76                 // String registries
     595: aload         16
     597: invokevirtual #12                 // Method org/springframework/beans/MutablePropertyValues.addPropertyValue:(Ljava/lang/String;Ljava/lang/Object;)V
     600: aload         4
     602: iconst_1
     603: invokevirtual #7                  // Method org/springframework/beans/factory/support/RootBeanDefinition.setLazyInit:(Z)V
     606: goto          961
     609: ldc           #77                 // String provider
     611: aload         14
     613: invokevirtual #62                 // Method java/lang/String.equals:(Ljava/lang/Object;)Z
     616: ifne          648
     619: ldc           #70                 // String registry
     621: aload         14
     623: invokevirtual #62                 // Method java/lang/String.equals:(Ljava/lang/Object;)Z
     626: ifne          648
     629: ldc           #78                 // String protocol
     631: aload         14
     633: invokevirtual #62                 // Method java/lang/String.equals:(Ljava/lang/Object;)Z
     636: ifeq          681
     639: ldc           #79                 // class org/apache/dubbo/config/AbstractServiceConfig
     641: aload_2
     642: invokevirtual #80                 // Method java/lang/Class.isAssignableFrom:(Ljava/lang/Class;)Z
     645: ifeq          681
     648: aload         4
     650: invokevirtual #11                 // Method org/springframework/beans/factory/support/RootBeanDefinition.getPropertyValues:()Lorg/springframework/beans/MutablePropertyValues;
     653: new           #16                 // class java/lang/StringBuilder
     656: dup
     657: invokespecial #17                 // Method java/lang/StringBuilder."<init>":()V
     660: aload         12
     662: invokevirtual #18                 // Method java/lang/StringBuilder.append:(Ljava/lang/String;)Ljava/lang/StringBuilder;
     665: ldc           #81                 // String Ids
     667: invokevirtual #18                 // Method java/lang/StringBuilder.append:(Ljava/lang/String;)Ljava/lang/StringBuilder;
     670: invokevirtual #21                 // Method java/lang/StringBuilder.toString:()Ljava/lang/String;
     673: aload         15
     675: invokevirtual #12                 // Method org/springframework/beans/MutablePropertyValues.addPropertyValue:(Ljava/lang/String;Ljava/lang/Object;)V
     678: goto          961
     681: aload         13
     683: invokestatic  #82                 // Method isPrimitive:(Ljava/lang/Class;)Z
     686: ifeq          705
     689: aload         14
     691: aload         15
     693: invokestatic  #83                 // Method getCompatibleDefaultValue:(Ljava/lang/String;Ljava/lang/String;)Ljava/lang/String;
     696: astore        15
     698: aload         15
     700: astore        16
     702: goto          944
     705: ldc           #84                 // String onreturn
     707: aload         14
     709: invokevirtual #62                 // Method java/lang/String.equals:(Ljava/lang/Object;)Z
     712: ifne          735
     715: ldc           #85                 // String onthrow
     717: aload         14
     719: invokevirtual #62                 // Method java/lang/String.equals:(Ljava/lang/Object;)Z
     722: ifne          735
     725: ldc           #86                 // String oninvoke
     727: aload         14
     729: invokevirtual #62                 // Method java/lang/String.equals:(Ljava/lang/Object;)Z
     732: ifeq          809
     735: aload         15
     737: ldc           #87                 // String .
     739: invokevirtual #88                 // Method java/lang/String.lastIndexOf:(Ljava/lang/String;)I
     742: istore        17
     744: aload         15
     746: iconst_0
     747: iload         17
     749: invokevirtual #89                 // Method java/lang/String.substring:(II)Ljava/lang/String;
     752: astore        18
     754: aload         15
     756: iload         17
     758: iconst_1
     759: iadd
     760: invokevirtual #90                 // Method java/lang/String.substring:(I)Ljava/lang/String;
     763: astore        19
     765: new           #91                 // class org/springframework/beans/factory/config/RuntimeBeanReference
     768: dup
     769: aload         18
     771: invokespecial #92                 // Method org/springframework/beans/factory/config/RuntimeBeanReference."<init>":(Ljava/lang/String;)V
     774: astore        16
     776: aload         4
     778: invokevirtual #11                 // Method org/springframework/beans/factory/support/RootBeanDefinition.getPropertyValues:()Lorg/springframework/beans/MutablePropertyValues;
     781: new           #16                 // class java/lang/StringBuilder
     784: dup
     785: invokespecial #17                 // Method java/lang/StringBuilder."<init>":()V
     788: aload         14
     790: invokevirtual #18                 // Method java/lang/StringBuilder.append:(Ljava/lang/String;)Ljava/lang/StringBuilder;
     793: ldc           #93                 // String Method
     795: invokevirtual #18                 // Method java/lang/StringBuilder.append:(Ljava/lang/String;)Ljava/lang/StringBuilder;
     798: invokevirtual #21                 // Method java/lang/StringBuilder.toString:()Ljava/lang/String;
     801: aload         19
     803: invokevirtual #12                 // Method org/springframework/beans/MutablePropertyValues.addPropertyValue:(Ljava/lang/String;Ljava/lang/Object;)V
     806: goto          944
     809: ldc           #94                 // String executor
     811: aload         14
     813: invokevirtual #62                 // Method java/lang/String.equals:(Ljava/lang/Object;)Z
     816: ifeq          833
     819: new           #91                 // class org/springframework/beans/factory/config/RuntimeBeanReference
     822: dup
     823: aload         15
     825: invokespecial #92                 // Method org/springframework/beans/factory/config/RuntimeBeanReference."<init>":(Ljava/lang/String;)V
     828: astore        16
     830: goto          944
     833: ldc           #34                 // String ref
     835: aload         14
     837: invokevirtual #62                 // Method java/lang/String.equals:(Ljava/lang/Object;)Z
     840: ifeq          933
     843: aload_1
     844: invokevirtual #22                 // Method org/springframework/beans/factory/xml/ParserContext.getRegistry:()Lorg/springframework/beans/factory/support/BeanDefinitionRegistry;
     847: aload         15
     849: invokeinterface #23,  2           // InterfaceMethod org/springframework/beans/factory/support/BeanDefinitionRegistry.containsBeanDefinition:(Ljava/lang/String;)Z
     854: ifeq          933
     857: aload_1
     858: invokevirtual #22                 // Method org/springframework/beans/factory/xml/ParserContext.getRegistry:()Lorg/springframework/beans/factory/support/BeanDefinitionRegistry;
     861: aload         15
     863: invokeinterface #95,  2           // InterfaceMethod org/springframework/beans/factory/support/BeanDefinitionRegistry.getBeanDefinition:(Ljava/lang/String;)Lorg/springframework/beans/factory/config/BeanDefinition;
     868: astore        17
     870: aload         17
     872: invokeinterface #96,  1           // InterfaceMethod org/springframework/beans/factory/config/BeanDefinition.isSingleton:()Z
     877: ifne          933
     880: new           #97                 // class java/lang/IllegalStateException
     883: dup
     884: new           #16                 // class java/lang/StringBuilder
     887: dup
     888: invokespecial #17                 // Method java/lang/StringBuilder."<init>":()V
     891: ldc           #98                 // String The exported service ref
     893: invokevirtual #18                 // Method java/lang/StringBuilder.append:(Ljava/lang/String;)Ljava/lang/StringBuilder;
     896: aload         15
     898: invokevirtual #18                 // Method java/lang/StringBuilder.append:(Ljava/lang/String;)Ljava/lang/StringBuilder;
     901: ldc           #99                 // String  must be singleton! Please set the
     903: invokevirtual #18                 // Method java/lang/StringBuilder.append:(Ljava/lang/String;)Ljava/lang/StringBuilder;
     906: aload         15
     908: invokevirtual #18                 // Method java/lang/StringBuilder.append:(Ljava/lang/String;)Ljava/lang/StringBuilder;
     911: ldc           #100                // String  bean scope to singleton, eg: <bean id=\"
     913: invokevirtual #18                 // Method java/lang/StringBuilder.append:(Ljava/lang/String;)Ljava/lang/StringBuilder;
     916: aload         15
     918: invokevirtual #18                 // Method java/lang/StringBuilder.append:(Ljava/lang/String;)Ljava/lang/StringBuilder;
     921: ldc           #101                // String \" scope=\"singleton\" ...>
     923: invokevirtual #18                 // Method java/lang/StringBuilder.append:(Ljava/lang/String;)Ljava/lang/StringBuilder;
     926: invokevirtual #21                 // Method java/lang/StringBuilder.toString:()Ljava/lang/String;
     929: invokespecial #102                // Method java/lang/IllegalStateException."<init>":(Ljava/lang/String;)V
     932: athrow
     933: new           #91                 // class org/springframework/beans/factory/config/RuntimeBeanReference
     936: dup
     937: aload         15
     939: invokespecial #92                 // Method org/springframework/beans/factory/config/RuntimeBeanReference."<init>":(Ljava/lang/String;)V
     942: astore        16
     944: aload         16
     946: ifnull        961
     949: aload         4
     951: invokevirtual #11                 // Method org/springframework/beans/factory/support/RootBeanDefinition.getPropertyValues:()Lorg/springframework/beans/MutablePropertyValues;
     954: aload         12
     956: aload         16
     958: invokevirtual #12                 // Method org/springframework/beans/MutablePropertyValues.addPropertyValue:(Ljava/lang/String;Ljava/lang/Object;)V
     961: goto          382
     964: aload_0
     965: invokeinterface #103,  1          // InterfaceMethod org/w3c/dom/Element.getAttributes:()Lorg/w3c/dom/NamedNodeMap;
     970: astore        10
     972: aload         10
     974: invokeinterface #104,  1          // InterfaceMethod org/w3c/dom/NamedNodeMap.getLength:()I
     979: istore        11
     981: iconst_0
     982: istore        12
     984: iload         12
     986: iload         11
     988: if_icmpge     1071
     991: aload         10
     993: iload         12
     995: invokeinterface #105,  2          // InterfaceMethod org/w3c/dom/NamedNodeMap.item:(I)Lorg/w3c/dom/Node;
    1000: astore        13
    1002: aload         13
    1004: invokeinterface #106,  1          // InterfaceMethod org/w3c/dom/Node.getLocalName:()Ljava/lang/String;
    1009: astore        14
    1011: aload         9
    1013: aload         14
    1015: invokeinterface #107,  2          // InterfaceMethod java/util/Set.contains:(Ljava/lang/Object;)Z
    1020: ifne          1065
    1023: aload         8
    1025: ifnonnull     1037
    1028: new           #108                // class org/springframework/beans/factory/support/ManagedMap
    1031: dup
    1032: invokespecial #109                // Method org/springframework/beans/factory/support/ManagedMap."<init>":()V
    1035: astore        8
    1037: aload         13
    1039: invokeinterface #110,  1          // InterfaceMethod org/w3c/dom/Node.getNodeValue:()Ljava/lang/String;
    1044: astore        15
    1046: aload         8
    1048: aload         14
    1050: new           #111                // class org/springframework/beans/factory/config/TypedStringValue
    1053: dup
    1054: aload         15
    1056: ldc           #55                 // class java/lang/String
    1058: invokespecial #112                // Method org/springframework/beans/factory/config/TypedStringValue."<init>":(Ljava/lang/String;Ljava/lang/Class;)V
    1061: invokevirtual #113                // Method org/springframework/beans/factory/support/ManagedMap.put:(Ljava/lang/Object;Ljava/lang/Object;)Ljava/lang/Object;
    1064: pop
    1065: iinc          12, 1
    1068: goto          984
    1071: aload         8
    1073: ifnull        1088
    1076: aload         4
    1078: invokevirtual #11                 // Method org/springframework/beans/factory/support/RootBeanDefinition.getPropertyValues:()Lorg/springframework/beans/MutablePropertyValues;
    1081: ldc           #61                 // String parameters
    1083: aload         8
    1085: invokevirtual #12                 // Method org/springframework/beans/MutablePropertyValues.addPropertyValue:(Ljava/lang/String;Ljava/lang/Object;)V
    1088: ldc           #114                // class org/apache/dubbo/config/ProviderConfig
    1090: aload_2
    1091: invokevirtual #28                 // Method java/lang/Object.equals:(Ljava/lang/Object;)Z
    1094: ifeq          1116
    1097: aload_0
    1098: aload_1
    1099: ldc           #29                 // class org/apache/dubbo/config/spring/ServiceBean
    1101: iconst_1
    1102: ldc           #115                // String service
    1104: ldc           #77                 // String provider
    1106: aload         6
    1108: aload         4
    1110: invokestatic  #116                // Method parseNested:(Lorg/w3c/dom/Element;Lorg/springframework/beans/factory/xml/ParserContext;Ljava/lang/Class;ZLjava/lang/String;Ljava/lang/String;Ljava/lang/String;Lorg/springframework/beans/factory/config/BeanDefinition;)V
    1113: goto          1180
    1116: ldc           #117                // class org/apache/dubbo/config/ConsumerConfig
    1118: aload_2
    1119: invokevirtual #28                 // Method java/lang/Object.equals:(Ljava/lang/Object;)Z
    1122: ifeq          1144
    1125: aload_0
    1126: aload_1
    1127: ldc           #44                 // class org/apache/dubbo/config/spring/ReferenceBean
    1129: iconst_1
    1130: ldc           #118                // String reference
    1132: ldc           #119                // String consumer
    1134: aload         6
    1136: aload         4
    1138: invokestatic  #116                // Method parseNested:(Lorg/w3c/dom/Element;Lorg/springframework/beans/factory/xml/ParserContext;Ljava/lang/Class;ZLjava/lang/String;Ljava/lang/String;Ljava/lang/String;Lorg/springframework/beans/factory/config/BeanDefinition;)V
    1141: goto          1180
    1144: ldc           #44                 // class org/apache/dubbo/config/spring/ReferenceBean
    1146: aload_2
    1147: invokevirtual #28                 // Method java/lang/Object.equals:(Ljava/lang/Object;)Z
    1150: ifeq          1164
    1153: aload_0
    1154: aload_1
    1155: aload         4
    1157: aconst_null
    1158: invokestatic  #120                // Method configReferenceBean:(Lorg/w3c/dom/Element;Lorg/springframework/beans/factory/xml/ParserContext;Lorg/springframework/beans/factory/support/RootBeanDefinition;Lorg/springframework/beans/factory/config/BeanDefinition;)V
    1161: goto          1180
    1164: ldc           #121                // class org/apache/dubbo/config/MetricsConfig
    1166: aload_2
    1167: invokevirtual #28                 // Method java/lang/Object.equals:(Ljava/lang/Object;)Z
    1170: ifeq          1180
    1173: aload_0
    1174: aload_1
    1175: aload         4
    1177: invokestatic  #122                // Method parseMetrics:(Lorg/w3c/dom/Element;Lorg/springframework/beans/factory/xml/ParserContext;Lorg/springframework/beans/factory/support/RootBeanDefinition;)V
    1180: aload_1
    1181: invokevirtual #22                 // Method org/springframework/beans/factory/xml/ParserContext.getRegistry:()Lorg/springframework/beans/factory/support/BeanDefinitionRegistry;
    1184: aload         6
    1186: invokeinterface #23,  2           // InterfaceMethod org/springframework/beans/factory/support/BeanDefinitionRegistry.containsBeanDefinition:(Ljava/lang/String;)Z
    1191: ifeq          1222
    1194: new           #97                 // class java/lang/IllegalStateException
    1197: dup
    1198: new           #16                 // class java/lang/StringBuilder
    1201: dup
    1202: invokespecial #17                 // Method java/lang/StringBuilder."<init>":()V
    1205: ldc           #123                // String Duplicate spring bean name:
    1207: invokevirtual #18                 // Method java/lang/StringBuilder.append:(Ljava/lang/String;)Ljava/lang/StringBuilder;
    1210: aload         6
    1212: invokevirtual #18                 // Method java/lang/StringBuilder.append:(Ljava/lang/String;)Ljava/lang/StringBuilder;
    1215: invokevirtual #21                 // Method java/lang/StringBuilder.toString:()Ljava/lang/String;
    1218: invokespecial #102                // Method java/lang/IllegalStateException."<init>":(Ljava/lang/String;)V
    1221: athrow
    1222: iload_3
    1223: ifeq          1239
    1226: aload_1
    1227: invokevirtual #22                 // Method org/springframework/beans/factory/xml/ParserContext.getRegistry:()Lorg/springframework/beans/factory/support/BeanDefinitionRegistry;
    1230: aload         6
    1232: aload         4
    1234: invokeinterface #124,  3          // InterfaceMethod org/springframework/beans/factory/support/BeanDefinitionRegistry.registerBeanDefinition:(Ljava/lang/String;Lorg/springframework/beans/factory/config/BeanDefinition;)V
    1239: aload         4
    1241: areturn

  private static void parseMetrics(org.w3c.dom.Element, org.springframework.beans.factory.xml.ParserContext, org.springframework.beans.factory.support.RootBeanDefinition);
    Code:
       0: aload_0
       1: invokeinterface #32,  1           // InterfaceMethod org/w3c/dom/Element.getChildNodes:()Lorg/w3c/dom/NodeList;
       6: astore_3
       7: aconst_null
       8: astore        4
      10: iconst_0
      11: istore        5
      13: iload         5
      15: aload_3
      16: invokeinterface #125,  1          // InterfaceMethod org/w3c/dom/NodeList.getLength:()I
      21: if_icmpge     321
      24: aload_3
      25: iload         5
      27: invokeinterface #126,  2          // InterfaceMethod org/w3c/dom/NodeList.item:(I)Lorg/w3c/dom/Node;
      32: instanceof    #127                // class org/w3c/dom/Element
      35: ifne          41
      38: goto          315
      41: aload_3
      42: iload         5
      44: invokeinterface #126,  2          // InterfaceMethod org/w3c/dom/NodeList.item:(I)Lorg/w3c/dom/Node;
      49: checkcast     #127                // class org/w3c/dom/Element
      52: astore        6
      54: ldc           #128                // String aggregation
      56: aload         6
      58: invokeinterface #129,  1          // InterfaceMethod org/w3c/dom/Element.getNodeName:()Ljava/lang/String;
      63: invokevirtual #62                 // Method java/lang/String.equals:(Ljava/lang/Object;)Z
      66: ifne          84
      69: ldc           #128                // String aggregation
      71: aload         6
      73: invokeinterface #130,  1          // InterfaceMethod org/w3c/dom/Element.getLocalName:()Ljava/lang/String;
      78: invokevirtual #62                 // Method java/lang/String.equals:(Ljava/lang/Object;)Z
      81: ifeq          115
      84: new           #131                // class org/apache/dubbo/config/nested/AggregationConfig
      87: dup
      88: invokespecial #132                // Method org/apache/dubbo/config/nested/AggregationConfig."<init>":()V
      91: astore        7
      93: aload         7
      95: aload         6
      97: aload_1
      98: invokestatic  #133                // Method assignProperties:(Ljava/lang/Object;Lorg/w3c/dom/Element;Lorg/springframework/beans/factory/xml/ParserContext;)V
     101: aload_2
     102: invokevirtual #11                 // Method org/springframework/beans/factory/support/RootBeanDefinition.getPropertyValues:()Lorg/springframework/beans/MutablePropertyValues;
     105: ldc           #128                // String aggregation
     107: aload         7
     109: invokevirtual #12                 // Method org/springframework/beans/MutablePropertyValues.addPropertyValue:(Ljava/lang/String;Ljava/lang/Object;)V
     112: goto          315
     115: ldc           #134                // String histogram
     117: aload         6
     119: invokeinterface #129,  1          // InterfaceMethod org/w3c/dom/Element.getNodeName:()Ljava/lang/String;
     124: invokevirtual #62                 // Method java/lang/String.equals:(Ljava/lang/Object;)Z
     127: ifne          145
     130: ldc           #134                // String histogram
     132: aload         6
     134: invokeinterface #130,  1          // InterfaceMethod org/w3c/dom/Element.getLocalName:()Ljava/lang/String;
     139: invokevirtual #62                 // Method java/lang/String.equals:(Ljava/lang/Object;)Z
     142: ifeq          176
     145: new           #135                // class org/apache/dubbo/config/nested/HistogramConfig
     148: dup
     149: invokespecial #136                // Method org/apache/dubbo/config/nested/HistogramConfig."<init>":()V
     152: astore        7
     154: aload         7
     156: aload         6
     158: aload_1
     159: invokestatic  #133                // Method assignProperties:(Ljava/lang/Object;Lorg/w3c/dom/Element;Lorg/springframework/beans/factory/xml/ParserContext;)V
     162: aload_2
     163: invokevirtual #11                 // Method org/springframework/beans/factory/support/RootBeanDefinition.getPropertyValues:()Lorg/springframework/beans/MutablePropertyValues;
     166: ldc           #134                // String histogram
     168: aload         7
     170: invokevirtual #12                 // Method org/springframework/beans/MutablePropertyValues.addPropertyValue:(Ljava/lang/String;Ljava/lang/Object;)V
     173: goto          315
     176: ldc           #137                // String prometheus-exporter
     178: aload         6
     180: invokeinterface #129,  1          // InterfaceMethod org/w3c/dom/Element.getNodeName:()Ljava/lang/String;
     185: invokevirtual #62                 // Method java/lang/String.equals:(Ljava/lang/Object;)Z
     188: ifne          206
     191: ldc           #137                // String prometheus-exporter
     193: aload         6
     195: invokeinterface #130,  1          // InterfaceMethod org/w3c/dom/Element.getLocalName:()Ljava/lang/String;
     200: invokevirtual #62                 // Method java/lang/String.equals:(Ljava/lang/Object;)Z
     203: ifeq          247
     206: aload         4
     208: ifnonnull     220
     211: new           #138                // class org/apache/dubbo/config/nested/PrometheusConfig
     214: dup
     215: invokespecial #139                // Method org/apache/dubbo/config/nested/PrometheusConfig."<init>":()V
     218: astore        4
     220: new           #140                // class org/apache/dubbo/config/nested/PrometheusConfig$Exporter
     223: dup
     224: invokespecial #141                // Method org/apache/dubbo/config/nested/PrometheusConfig$Exporter."<init>":()V
     227: astore        7
     229: aload         7
     231: aload         6
     233: aload_1
     234: invokestatic  #133                // Method assignProperties:(Ljava/lang/Object;Lorg/w3c/dom/Element;Lorg/springframework/beans/factory/xml/ParserContext;)V
     237: aload         4
     239: aload         7
     241: invokevirtual #142                // Method org/apache/dubbo/config/nested/PrometheusConfig.setExporter:(Lorg/apache/dubbo/config/nested/PrometheusConfig$Exporter;)V
     244: goto          315
     247: ldc           #143                // String prometheus-pushgateway
     249: aload         6
     251: invokeinterface #129,  1          // InterfaceMethod org/w3c/dom/Element.getNodeName:()Ljava/lang/String;
     256: invokevirtual #62                 // Method java/lang/String.equals:(Ljava/lang/Object;)Z
     259: ifne          277
     262: ldc           #143                // String prometheus-pushgateway
     264: aload         6
     266: invokeinterface #130,  1          // InterfaceMethod org/w3c/dom/Element.getLocalName:()Ljava/lang/String;
     271: invokevirtual #62                 // Method java/lang/String.equals:(Ljava/lang/Object;)Z
     274: ifeq          315
     277: aload         4
     279: ifnonnull     291
     282: new           #138                // class org/apache/dubbo/config/nested/PrometheusConfig
     285: dup
     286: invokespecial #139                // Method org/apache/dubbo/config/nested/PrometheusConfig."<init>":()V
     289: astore        4
     291: new           #144                // class org/apache/dubbo/config/nested/PrometheusConfig$Pushgateway
     294: dup
     295: invokespecial #145                // Method org/apache/dubbo/config/nested/PrometheusConfig$Pushgateway."<init>":()V
     298: astore        7
     300: aload         7
     302: aload         6
     304: aload_1
     305: invokestatic  #133                // Method assignProperties:(Ljava/lang/Object;Lorg/w3c/dom/Element;Lorg/springframework/beans/factory/xml/ParserContext;)V
     308: aload         4
     310: aload         7
     312: invokevirtual #146                // Method org/apache/dubbo/config/nested/PrometheusConfig.setPushgateway:(Lorg/apache/dubbo/config/nested/PrometheusConfig$Pushgateway;)V
     315: iinc          5, 1
     318: goto          13
     321: aload         4
     323: ifnull        337
     326: aload_2
     327: invokevirtual #11                 // Method org/springframework/beans/factory/support/RootBeanDefinition.getPropertyValues:()Lorg/springframework/beans/MutablePropertyValues;
     330: ldc           #147                // String prometheus
     332: aload         4
     334: invokevirtual #12                 // Method org/springframework/beans/MutablePropertyValues.addPropertyValue:(Ljava/lang/String;Ljava/lang/Object;)V
     337: return

  private static void assignProperties(java.lang.Object, org.w3c.dom.Element, org.springframework.beans.factory.xml.ParserContext);
    Code:
       0: aload_0
       1: invokevirtual #148                // Method java/lang/Object.getClass:()Ljava/lang/Class;
       4: invokevirtual #149                // Method java/lang/Class.getMethods:()[Ljava/lang/reflect/Method;
       7: astore_3
       8: aload_3
       9: astore        4
      11: aload         4
      13: arraylength
      14: istore        5
      16: iconst_0
      17: istore        6
      19: iload         6
      21: iload         5
      23: if_icmpge     158
      26: aload         4
      28: iload         6
      30: aaload
      31: astore        7
      33: aload         7
      35: invokestatic  #150                // InterfaceMethod org/apache/dubbo/common/utils/MethodUtils.isSetter:(Ljava/lang/reflect/Method;)Z
      38: ifeq          152
      41: new           #16                 // class java/lang/StringBuilder
      44: dup
      45: invokespecial #17                 // Method java/lang/StringBuilder."<init>":()V
      48: aload         7
      50: invokevirtual #151                // Method java/lang/reflect/Method.getName:()Ljava/lang/String;
      53: iconst_3
      54: iconst_4
      55: invokevirtual #89                 // Method java/lang/String.substring:(II)Ljava/lang/String;
      58: invokevirtual #152                // Method java/lang/String.toLowerCase:()Ljava/lang/String;
      61: invokevirtual #18                 // Method java/lang/StringBuilder.append:(Ljava/lang/String;)Ljava/lang/StringBuilder;
      64: aload         7
      66: invokevirtual #151                // Method java/lang/reflect/Method.getName:()Ljava/lang/String;
      69: iconst_4
      70: invokevirtual #90                 // Method java/lang/String.substring:(I)Ljava/lang/String;
      73: invokevirtual #18                 // Method java/lang/StringBuilder.append:(Ljava/lang/String;)Ljava/lang/StringBuilder;
      76: invokevirtual #21                 // Method java/lang/StringBuilder.toString:()Ljava/lang/String;
      79: astore        8
      81: aload         8
      83: ldc           #58                 // String -
      85: invokestatic  #59                 // Method org/apache/dubbo/common/utils/StringUtils.camelToSplitName:(Ljava/lang/String;Ljava/lang/String;)Ljava/lang/String;
      88: astore        9
      90: aload_1
      91: aload         9
      93: aload_2
      94: invokestatic  #9                  // Method resolveAttribute:(Lorg/w3c/dom/Element;Ljava/lang/String;Lorg/springframework/beans/factory/xml/ParserContext;)Ljava/lang/String;
      97: astore        10
      99: aload         10
     101: invokestatic  #10                 // Method org/apache/dubbo/common/utils/StringUtils.isNotEmpty:(Ljava/lang/String;)Z
     104: ifeq          152
     107: aload         7
     109: invokevirtual #153                // Method java/lang/reflect/Method.getParameterTypes:()[Ljava/lang/Class;
     112: iconst_0
     113: aaload
     114: aload         10
     116: invokestatic  #154                // Method org/apache/dubbo/common/utils/ClassUtils.convertPrimitive:(Ljava/lang/Class;Ljava/lang/String;)Ljava/lang/Object;
     119: astore        11
     121: aload         7
     123: aload_0
     124: iconst_1
     125: anewarray     #155                // class java/lang/Object
     128: dup
     129: iconst_0
     130: aload         11
     132: aastore
     133: invokevirtual #156                // Method java/lang/reflect/Method.invoke:(Ljava/lang/Object;[Ljava/lang/Object;)Ljava/lang/Object;
     136: pop
     137: goto          152
     140: astore        11
     142: new           #97                 // class java/lang/IllegalStateException
     145: dup
     146: aload         11
     148: invokespecial #159                // Method java/lang/IllegalStateException."<init>":(Ljava/lang/Throwable;)V
     151: athrow
     152: iinc          6, 1
     155: goto          19
     158: return
    Exception table:
       from    to  target type
         107   137   140   Class java/lang/IllegalAccessException
         107   137   140   Class java/lang/reflect/InvocationTargetException

  private static void configReferenceBean(org.w3c.dom.Element, org.springframework.beans.factory.xml.ParserContext, org.springframework.beans.factory.support.RootBeanDefinition, org.springframework.beans.factory.config.BeanDefinition);
    Code:
       0: aload_0
       1: ldc           #161                // String interface
       3: aload_1
       4: invokestatic  #9                  // Method resolveAttribute:(Lorg/w3c/dom/Element;Ljava/lang/String;Lorg/springframework/beans/factory/xml/ParserContext;)Ljava/lang/String;
       7: astore        4
       9: aload_0
      10: ldc           #162                // String generic
      12: aload_1
      13: invokestatic  #9                  // Method resolveAttribute:(Lorg/w3c/dom/Element;Ljava/lang/String;Lorg/springframework/beans/factory/xml/ParserContext;)Ljava/lang/String;
      16: astore        5
      18: aload         5
      20: invokestatic  #163                // Method org/apache/dubbo/common/utils/StringUtils.isBlank:(Ljava/lang/CharSequence;)Z
      23: ifeq          46
      26: aload_3
      27: ifnull        46
      30: aload_3
      31: invokeinterface #164,  1          // InterfaceMethod org/springframework/beans/factory/config/BeanDefinition.getPropertyValues:()Lorg/springframework/beans/MutablePropertyValues;
      36: ldc           #162                // String generic
      38: invokestatic  #165                // Method org/apache/dubbo/config/spring/util/SpringCompatUtils.getPropertyValue:(Lorg/springframework/beans/PropertyValues;Ljava/lang/String;)Ljava/lang/Object;
      41: checkcast     #55                 // class java/lang/String
      44: astore        5
      46: aload         5
      48: ifnull        71
      51: aload         5
      53: aload_1
      54: invokestatic  #166                // Method resolvePlaceholders:(Ljava/lang/String;Lorg/springframework/beans/factory/xml/ParserContext;)Ljava/lang/String;
      57: astore        5
      59: aload_2
      60: invokevirtual #11                 // Method org/springframework/beans/factory/support/RootBeanDefinition.getPropertyValues:()Lorg/springframework/beans/MutablePropertyValues;
      63: ldc           #162                // String generic
      65: aload         5
      67: invokevirtual #167                // Method org/springframework/beans/MutablePropertyValues.add:(Ljava/lang/String;Ljava/lang/Object;)Lorg/springframework/beans/MutablePropertyValues;
      70: pop
      71: aload_2
      72: ldc           #168                // String interfaceName
      74: aload         4
      76: invokevirtual #26                 // Method org/springframework/beans/factory/support/RootBeanDefinition.setAttribute:(Ljava/lang/String;Ljava/lang/Object;)V
      79: aload         5
      81: aload         4
      83: invokestatic  #169                // Method org/apache/dubbo/config/ReferenceConfig.determineInterfaceClass:(Ljava/lang/String;Ljava/lang/String;)Ljava/lang/Class;
      86: astore        6
      88: aload_2
      89: ldc           #170                // String interfaceClass
      91: aload         6
      93: invokevirtual #26                 // Method org/springframework/beans/factory/support/RootBeanDefinition.setAttribute:(Ljava/lang/String;Ljava/lang/Object;)V
      96: new           #171                // class org/springframework/beans/factory/support/GenericBeanDefinition
      99: dup
     100: invokespecial #172                // Method org/springframework/beans/factory/support/GenericBeanDefinition."<init>":()V
     103: astore        7
     105: aload         7
     107: aload         6
     109: invokevirtual #173                // Method org/springframework/beans/factory/support/GenericBeanDefinition.setBeanClass:(Ljava/lang/Class;)V
     112: aload_2
     113: ldc           #25                 // String BEAN_NAME
     115: invokevirtual #174                // Method org/springframework/beans/factory/support/RootBeanDefinition.getAttribute:(Ljava/lang/String;)Ljava/lang/Object;
     118: checkcast     #55                 // class java/lang/String
     121: astore        8
     123: aload_2
     124: new           #35                 // class org/springframework/beans/factory/config/BeanDefinitionHolder
     127: dup
     128: aload         7
     130: new           #16                 // class java/lang/StringBuilder
     133: dup
     134: invokespecial #17                 // Method java/lang/StringBuilder."<init>":()V
     137: aload         8
     139: invokevirtual #18                 // Method java/lang/StringBuilder.append:(Ljava/lang/String;)Ljava/lang/StringBuilder;
     142: ldc           #175                // String _decorated
     144: invokevirtual #18                 // Method java/lang/StringBuilder.append:(Ljava/lang/String;)Ljava/lang/StringBuilder;
     147: invokevirtual #21                 // Method java/lang/StringBuilder.toString:()Ljava/lang/String;
     150: invokespecial #37                 // Method org/springframework/beans/factory/config/BeanDefinitionHolder."<init>":(Lorg/springframework/beans/factory/config/BeanDefinition;Ljava/lang/String;)V
     153: invokevirtual #176                // Method org/springframework/beans/factory/support/RootBeanDefinition.setDecoratedDefinition:(Lorg/springframework/beans/factory/config/BeanDefinitionHolder;)V
     156: aload_2
     157: ldc           #178                // String factoryBeanObjectType
     159: aload         6
     161: invokevirtual #26                 // Method org/springframework/beans/factory/support/RootBeanDefinition.setAttribute:(Ljava/lang/String;Ljava/lang/Object;)V
     164: aload_2
     165: invokevirtual #11                 // Method org/springframework/beans/factory/support/RootBeanDefinition.getPropertyValues:()Lorg/springframework/beans/MutablePropertyValues;
     168: invokevirtual #179                // Method org/springframework/beans/MutablePropertyValues.getPropertyValueList:()Ljava/util/List;
     171: astore        9
     173: aload         9
     175: invokeinterface #180,  1          // InterfaceMethod java/util/List.iterator:()Ljava/util/Iterator;
     180: astore        10
     182: aload         10
     184: invokeinterface #51,  1           // InterfaceMethod java/util/Iterator.hasNext:()Z
     189: ifeq          213
     192: aload         10
     194: invokeinterface #52,  1           // InterfaceMethod java/util/Iterator.next:()Ljava/lang/Object;
     199: checkcast     #181                // class org/springframework/beans/PropertyValue
     202: astore        11
     204: aload         11
     206: iconst_1
     207: invokevirtual #182                // Method org/springframework/beans/PropertyValue.setOptional:(Z)V
     210: goto          182
     213: return

  private static void getPropertyMap(java.lang.Class<?>, java.util.Map<java.lang.String, java.lang.Class>);
    Code:
       0: aload_0
       1: invokevirtual #149                // Method java/lang/Class.getMethods:()[Ljava/lang/reflect/Method;
       4: astore_2
       5: aload_2
       6: arraylength
       7: istore_3
       8: iconst_0
       9: istore        4
      11: iload         4
      13: iload_3
      14: if_icmpge     243
      17: aload_2
      18: iload         4
      20: aaload
      21: astore        5
      23: aload         5
      25: invokevirtual #151                // Method java/lang/reflect/Method.getName:()Ljava/lang/String;
      28: astore        6
      30: aload         6
      32: invokevirtual #183                // Method java/lang/String.length:()I
      35: iconst_3
      36: if_icmple     237
      39: aload         6
      41: ldc           #184                // String set
      43: invokevirtual #185                // Method java/lang/String.startsWith:(Ljava/lang/String;)Z
      46: ifeq          237
      49: aload         5
      51: invokevirtual #186                // Method java/lang/reflect/Method.getModifiers:()I
      54: invokestatic  #187                // Method java/lang/reflect/Modifier.isPublic:(I)Z
      57: ifeq          237
      60: aload         5
      62: invokevirtual #153                // Method java/lang/reflect/Method.getParameterTypes:()[Ljava/lang/Class;
      65: arraylength
      66: iconst_1
      67: if_icmpne     237
      70: aload         5
      72: invokevirtual #153                // Method java/lang/reflect/Method.getParameterTypes:()[Ljava/lang/Class;
      75: iconst_0
      76: aaload
      77: astore        7
      79: new           #16                 // class java/lang/StringBuilder
      82: dup
      83: invokespecial #17                 // Method java/lang/StringBuilder."<init>":()V
      86: aload         6
      88: iconst_3
      89: iconst_4
      90: invokevirtual #89                 // Method java/lang/String.substring:(II)Ljava/lang/String;
      93: invokevirtual #152                // Method java/lang/String.toLowerCase:()Ljava/lang/String;
      96: invokevirtual #18                 // Method java/lang/StringBuilder.append:(Ljava/lang/String;)Ljava/lang/StringBuilder;
      99: aload         6
     101: iconst_4
     102: invokevirtual #90                 // Method java/lang/String.substring:(I)Ljava/lang/String;
     105: invokevirtual #18                 // Method java/lang/StringBuilder.append:(Ljava/lang/String;)Ljava/lang/StringBuilder;
     108: invokevirtual #21                 // Method java/lang/StringBuilder.toString:()Ljava/lang/String;
     111: astore        8
     113: aconst_null
     114: astore        9
     116: aload_0
     117: new           #16                 // class java/lang/StringBuilder
     120: dup
     121: invokespecial #17                 // Method java/lang/StringBuilder."<init>":()V
     124: ldc           #188                // String get
     126: invokevirtual #18                 // Method java/lang/StringBuilder.append:(Ljava/lang/String;)Ljava/lang/StringBuilder;
     129: aload         6
     131: iconst_3
     132: invokevirtual #90                 // Method java/lang/String.substring:(I)Ljava/lang/String;
     135: invokevirtual #18                 // Method java/lang/StringBuilder.append:(Ljava/lang/String;)Ljava/lang/StringBuilder;
     138: invokevirtual #21                 // Method java/lang/StringBuilder.toString:()Ljava/lang/String;
     141: iconst_0
     142: anewarray     #57                 // class java/lang/Class
     145: invokevirtual #189                // Method java/lang/Class.getMethod:(Ljava/lang/String;[Ljava/lang/Class;)Ljava/lang/reflect/Method;
     148: astore        9
     150: goto          194
     153: astore        10
     155: aload_0
     156: new           #16                 // class java/lang/StringBuilder
     159: dup
     160: invokespecial #17                 // Method java/lang/StringBuilder."<init>":()V
     163: ldc           #191                // String is
     165: invokevirtual #18                 // Method java/lang/StringBuilder.append:(Ljava/lang/String;)Ljava/lang/StringBuilder;
     168: aload         6
     170: iconst_3
     171: invokevirtual #90                 // Method java/lang/String.substring:(I)Ljava/lang/String;
     174: invokevirtual #18                 // Method java/lang/StringBuilder.append:(Ljava/lang/String;)Ljava/lang/StringBuilder;
     177: invokevirtual #21                 // Method java/lang/StringBuilder.toString:()Ljava/lang/String;
     180: iconst_0
     181: anewarray     #57                 // class java/lang/Class
     184: invokevirtual #189                // Method java/lang/Class.getMethod:(Ljava/lang/String;[Ljava/lang/Class;)Ljava/lang/reflect/Method;
     187: astore        9
     189: goto          194
     192: astore        11
     194: aload         9
     196: ifnull        237
     199: aload         9
     201: invokevirtual #186                // Method java/lang/reflect/Method.getModifiers:()I
     204: invokestatic  #187                // Method java/lang/reflect/Modifier.isPublic:(I)Z
     207: ifeq          237
     210: aload         7
     212: aload         9
     214: invokevirtual #192                // Method java/lang/reflect/Method.getReturnType:()Ljava/lang/Class;
     217: invokevirtual #28                 // Method java/lang/Object.equals:(Ljava/lang/Object;)Z
     220: ifne          226
     223: goto          237
     226: aload_1
     227: aload         8
     229: aload         7
     231: invokeinterface #43,  3           // InterfaceMethod java/util/Map.put:(Ljava/lang/Object;Ljava/lang/Object;)Ljava/lang/Object;
     236: pop
     237: iinc          4, 1
     240: goto          11
     243: return
    Exception table:
       from    to  target type
         116   150   153   Class java/lang/NoSuchMethodException
         155   189   192   Class java/lang/NoSuchMethodException

  private static java.lang.String getCompatibleDefaultValue(java.lang.String, java.lang.String);
    Code:
       0: ldc           #193                // String async
       2: aload_0
       3: invokevirtual #62                 // Method java/lang/String.equals:(Ljava/lang/Object;)Z
       6: ifeq          18
       9: ldc           #194                // String false
      11: aload_1
      12: invokevirtual #62                 // Method java/lang/String.equals:(Ljava/lang/Object;)Z
      15: ifne          108
      18: ldc           #195                // String timeout
      20: aload_0
      21: invokevirtual #62                 // Method java/lang/String.equals:(Ljava/lang/Object;)Z
      24: ifeq          36
      27: ldc           #196                // String 0
      29: aload_1
      30: invokevirtual #62                 // Method java/lang/String.equals:(Ljava/lang/Object;)Z
      33: ifne          108
      36: ldc           #197                // String delay
      38: aload_0
      39: invokevirtual #62                 // Method java/lang/String.equals:(Ljava/lang/Object;)Z
      42: ifeq          54
      45: ldc           #196                // String 0
      47: aload_1
      48: invokevirtual #62                 // Method java/lang/String.equals:(Ljava/lang/Object;)Z
      51: ifne          108
      54: ldc           #198                // String version
      56: aload_0
      57: invokevirtual #62                 // Method java/lang/String.equals:(Ljava/lang/Object;)Z
      60: ifeq          72
      63: ldc           #199                // String 0.0.0
      65: aload_1
      66: invokevirtual #62                 // Method java/lang/String.equals:(Ljava/lang/Object;)Z
      69: ifne          108
      72: ldc           #200                // String stat
      74: aload_0
      75: invokevirtual #62                 // Method java/lang/String.equals:(Ljava/lang/Object;)Z
      78: ifeq          90
      81: ldc           #201                // String -1
      83: aload_1
      84: invokevirtual #62                 // Method java/lang/String.equals:(Ljava/lang/Object;)Z
      87: ifne          108
      90: ldc           #202                // String reliable
      92: aload_0
      93: invokevirtual #62                 // Method java/lang/String.equals:(Ljava/lang/Object;)Z
      96: ifeq          110
      99: ldc           #194                // String false
     101: aload_1
     102: invokevirtual #62                 // Method java/lang/String.equals:(Ljava/lang/Object;)Z
     105: ifeq          110
     108: aconst_null
     109: astore_1
     110: aload_1
     111: areturn

  private static boolean isPrimitive(java.lang.Class<?>);
    Code:
       0: aload_0
       1: invokevirtual #203                // Method java/lang/Class.isPrimitive:()Z
       4: ifne          73
       7: aload_0
       8: ldc           #204                // class java/lang/Boolean
      10: if_acmpeq     73
      13: aload_0
      14: ldc           #205                // class java/lang/Byte
      16: if_acmpeq     73
      19: aload_0
      20: ldc           #206                // class java/lang/Character
      22: if_acmpeq     73
      25: aload_0
      26: ldc           #207                // class java/lang/Short
      28: if_acmpeq     73
      31: aload_0
      32: ldc           #208                // class java/lang/Integer
      34: if_acmpeq     73
      37: aload_0
      38: ldc           #209                // class java/lang/Long
      40: if_acmpeq     73
      43: aload_0
      44: ldc           #210                // class java/lang/Float
      46: if_acmpeq     73
      49: aload_0
      50: ldc           #211                // class java/lang/Double
      52: if_acmpeq     73
      55: aload_0
      56: ldc           #55                 // class java/lang/String
      58: if_acmpeq     73
      61: aload_0
      62: ldc           #212                // class java/util/Date
      64: if_acmpeq     73
      67: aload_0
      68: ldc           #57                 // class java/lang/Class
      70: if_acmpne     77
      73: iconst_1
      74: goto          78
      77: iconst_0
      78: ireturn

  private static void parseNested(org.w3c.dom.Element, org.springframework.beans.factory.xml.ParserContext, java.lang.Class<?>, boolean, java.lang.String, java.lang.String, java.lang.String, org.springframework.beans.factory.config.BeanDefinition);
    Code:
       0: aload_0
       1: invokeinterface #32,  1           // InterfaceMethod org/w3c/dom/Element.getChildNodes:()Lorg/w3c/dom/NodeList;
       6: astore        8
       8: aload         8
      10: ifnonnull     14
      13: return
      14: iconst_1
      15: istore        9
      17: iconst_0
      18: istore        10
      20: iload         10
      22: aload         8
      24: invokeinterface #125,  1          // InterfaceMethod org/w3c/dom/NodeList.getLength:()I
      29: if_icmpge     196
      32: aload         8
      34: iload         10
      36: invokeinterface #126,  2          // InterfaceMethod org/w3c/dom/NodeList.item:(I)Lorg/w3c/dom/Node;
      41: astore        11
      43: aload         11
      45: instanceof    #127                // class org/w3c/dom/Element
      48: ifne          54
      51: goto          190
      54: aload         4
      56: aload         11
      58: invokeinterface #213,  1          // InterfaceMethod org/w3c/dom/Node.getNodeName:()Ljava/lang/String;
      63: invokevirtual #62                 // Method java/lang/String.equals:(Ljava/lang/Object;)Z
      66: ifne          84
      69: aload         4
      71: aload         11
      73: invokeinterface #106,  1          // InterfaceMethod org/w3c/dom/Node.getLocalName:()Ljava/lang/String;
      78: invokevirtual #62                 // Method java/lang/String.equals:(Ljava/lang/Object;)Z
      81: ifeq          190
      84: iload         9
      86: ifeq          123
      89: iconst_0
      90: istore        9
      92: aload_0
      93: ldc           #214                // String default
      95: aload_1
      96: invokestatic  #9                  // Method resolveAttribute:(Lorg/w3c/dom/Element;Ljava/lang/String;Lorg/springframework/beans/factory/xml/ParserContext;)Ljava/lang/String;
      99: astore        12
     101: aload         12
     103: invokestatic  #13                 // Method org/apache/dubbo/common/utils/StringUtils.isEmpty:(Ljava/lang/String;)Z
     106: ifeq          123
     109: aload         7
     111: invokeinterface #164,  1          // InterfaceMethod org/springframework/beans/factory/config/BeanDefinition.getPropertyValues:()Lorg/springframework/beans/MutablePropertyValues;
     116: ldc           #214                // String default
     118: ldc           #194                // String false
     120: invokevirtual #12                 // Method org/springframework/beans/MutablePropertyValues.addPropertyValue:(Ljava/lang/String;Ljava/lang/Object;)V
     123: aload         11
     125: checkcast     #127                // class org/w3c/dom/Element
     128: aload_1
     129: aload_2
     130: iload_3
     131: invokestatic  #215                // Method parse:(Lorg/w3c/dom/Element;Lorg/springframework/beans/factory/xml/ParserContext;Ljava/lang/Class;Z)Lorg/springframework/beans/factory/support/RootBeanDefinition;
     134: astore        12
     136: aload         12
     138: ifnull        190
     141: aload         6
     143: invokestatic  #10                 // Method org/apache/dubbo/common/utils/StringUtils.isNotEmpty:(Ljava/lang/String;)Z
     146: ifeq          168
     149: aload         12
     151: invokevirtual #11                 // Method org/springframework/beans/factory/support/RootBeanDefinition.getPropertyValues:()Lorg/springframework/beans/MutablePropertyValues;
     154: aload         5
     156: new           #91                 // class org/springframework/beans/factory/config/RuntimeBeanReference
     159: dup
     160: aload         6
     162: invokespecial #92                 // Method org/springframework/beans/factory/config/RuntimeBeanReference."<init>":(Ljava/lang/String;)V
     165: invokevirtual #12                 // Method org/springframework/beans/MutablePropertyValues.addPropertyValue:(Ljava/lang/String;Ljava/lang/Object;)V
     168: ldc           #44                 // class org/apache/dubbo/config/spring/ReferenceBean
     170: aload_2
     171: invokevirtual #28                 // Method java/lang/Object.equals:(Ljava/lang/Object;)Z
     174: ifeq          190
     177: aload         11
     179: checkcast     #127                // class org/w3c/dom/Element
     182: aload_1
     183: aload         12
     185: aload         7
     187: invokestatic  #120                // Method configReferenceBean:(Lorg/w3c/dom/Element;Lorg/springframework/beans/factory/xml/ParserContext;Lorg/springframework/beans/factory/support/RootBeanDefinition;Lorg/springframework/beans/factory/config/BeanDefinition;)V
     190: iinc          10, 1
     193: goto          20
     196: return

  private static void parseProperties(org.w3c.dom.NodeList, org.springframework.beans.factory.support.RootBeanDefinition, org.springframework.beans.factory.xml.ParserContext);
    Code:
       0: aload_0
       1: ifnonnull     5
       4: return
       5: iconst_0
       6: istore_3
       7: iload_3
       8: aload_0
       9: invokeinterface #125,  1          // InterfaceMethod org/w3c/dom/NodeList.getLength:()I
      14: if_icmpge     223
      17: aload_0
      18: iload_3
      19: invokeinterface #126,  2          // InterfaceMethod org/w3c/dom/NodeList.item:(I)Lorg/w3c/dom/Node;
      24: instanceof    #127                // class org/w3c/dom/Element
      27: ifne          33
      30: goto          217
      33: aload_0
      34: iload_3
      35: invokeinterface #126,  2          // InterfaceMethod org/w3c/dom/NodeList.item:(I)Lorg/w3c/dom/Node;
      40: checkcast     #127                // class org/w3c/dom/Element
      43: astore        4
      45: ldc           #216                // String property
      47: aload         4
      49: invokeinterface #129,  1          // InterfaceMethod org/w3c/dom/Element.getNodeName:()Ljava/lang/String;
      54: invokevirtual #62                 // Method java/lang/String.equals:(Ljava/lang/Object;)Z
      57: ifne          75
      60: ldc           #216                // String property
      62: aload         4
      64: invokeinterface #130,  1          // InterfaceMethod org/w3c/dom/Element.getLocalName:()Ljava/lang/String;
      69: invokevirtual #62                 // Method java/lang/String.equals:(Ljava/lang/Object;)Z
      72: ifeq          217
      75: aload         4
      77: ldc           #14                 // String name
      79: aload_2
      80: invokestatic  #9                  // Method resolveAttribute:(Lorg/w3c/dom/Element;Ljava/lang/String;Lorg/springframework/beans/factory/xml/ParserContext;)Ljava/lang/String;
      83: astore        5
      85: aload         5
      87: invokestatic  #10                 // Method org/apache/dubbo/common/utils/StringUtils.isNotEmpty:(Ljava/lang/String;)Z
      90: ifeq          217
      93: aload         4
      95: ldc           #217                // String value
      97: aload_2
      98: invokestatic  #9                  // Method resolveAttribute:(Lorg/w3c/dom/Element;Ljava/lang/String;Lorg/springframework/beans/factory/xml/ParserContext;)Ljava/lang/String;
     101: astore        6
     103: aload         4
     105: ldc           #34                 // String ref
     107: aload_2
     108: invokestatic  #9                  // Method resolveAttribute:(Lorg/w3c/dom/Element;Ljava/lang/String;Lorg/springframework/beans/factory/xml/ParserContext;)Ljava/lang/String;
     111: astore        7
     113: aload         6
     115: invokestatic  #10                 // Method org/apache/dubbo/common/utils/StringUtils.isNotEmpty:(Ljava/lang/String;)Z
     118: ifeq          135
     121: aload_1
     122: invokevirtual #11                 // Method org/springframework/beans/factory/support/RootBeanDefinition.getPropertyValues:()Lorg/springframework/beans/MutablePropertyValues;
     125: aload         5
     127: aload         6
     129: invokevirtual #12                 // Method org/springframework/beans/MutablePropertyValues.addPropertyValue:(Ljava/lang/String;Ljava/lang/Object;)V
     132: goto          217
     135: aload         7
     137: invokestatic  #10                 // Method org/apache/dubbo/common/utils/StringUtils.isNotEmpty:(Ljava/lang/String;)Z
     140: ifeq          164
     143: aload_1
     144: invokevirtual #11                 // Method org/springframework/beans/factory/support/RootBeanDefinition.getPropertyValues:()Lorg/springframework/beans/MutablePropertyValues;
     147: aload         5
     149: new           #91                 // class org/springframework/beans/factory/config/RuntimeBeanReference
     152: dup
     153: aload         7
     155: invokespecial #92                 // Method org/springframework/beans/factory/config/RuntimeBeanReference."<init>":(Ljava/lang/String;)V
     158: invokevirtual #12                 // Method org/springframework/beans/MutablePropertyValues.addPropertyValue:(Ljava/lang/String;Ljava/lang/Object;)V
     161: goto          217
     164: new           #218                // class java/lang/UnsupportedOperationException
     167: dup
     168: new           #16                 // class java/lang/StringBuilder
     171: dup
     172: invokespecial #17                 // Method java/lang/StringBuilder."<init>":()V
     175: ldc           #219                // String Unsupported <property name=\"
     177: invokevirtual #18                 // Method java/lang/StringBuilder.append:(Ljava/lang/String;)Ljava/lang/StringBuilder;
     180: aload         5
     182: invokevirtual #18                 // Method java/lang/StringBuilder.append:(Ljava/lang/String;)Ljava/lang/StringBuilder;
     185: ldc           #220                // String \"> sub tag, Only supported <property name=\"
     187: invokevirtual #18                 // Method java/lang/StringBuilder.append:(Ljava/lang/String;)Ljava/lang/StringBuilder;
     190: aload         5
     192: invokevirtual #18                 // Method java/lang/StringBuilder.append:(Ljava/lang/String;)Ljava/lang/StringBuilder;
     195: ldc           #221                // String \" ref=\"...\" /> or <property name=\"
     197: invokevirtual #18                 // Method java/lang/StringBuilder.append:(Ljava/lang/String;)Ljava/lang/StringBuilder;
     200: aload         5
     202: invokevirtual #18                 // Method java/lang/StringBuilder.append:(Ljava/lang/String;)Ljava/lang/StringBuilder;
     205: ldc           #222                // String \" value=\"...\" />
     207: invokevirtual #18                 // Method java/lang/StringBuilder.append:(Ljava/lang/String;)Ljava/lang/StringBuilder;
     210: invokevirtual #21                 // Method java/lang/StringBuilder.toString:()Ljava/lang/String;
     213: invokespecial #223                // Method java/lang/UnsupportedOperationException."<init>":(Ljava/lang/String;)V
     216: athrow
     217: iinc          3, 1
     220: goto          7
     223: return

  private static org.springframework.beans.factory.support.ManagedMap parseParameters(org.w3c.dom.NodeList, org.springframework.beans.factory.support.RootBeanDefinition, org.springframework.beans.factory.xml.ParserContext);
    Code:
       0: aload_0
       1: ifnonnull     6
       4: aconst_null
       5: areturn
       6: aconst_null
       7: astore_3
       8: iconst_0
       9: istore        4
      11: iload         4
      13: aload_0
      14: invokeinterface #125,  1          // InterfaceMethod org/w3c/dom/NodeList.getLength:()I
      19: if_icmpge     180
      22: aload_0
      23: iload         4
      25: invokeinterface #126,  2          // InterfaceMethod org/w3c/dom/NodeList.item:(I)Lorg/w3c/dom/Node;
      30: instanceof    #127                // class org/w3c/dom/Element
      33: ifne          39
      36: goto          174
      39: aload_0
      40: iload         4
      42: invokeinterface #126,  2          // InterfaceMethod org/w3c/dom/NodeList.item:(I)Lorg/w3c/dom/Node;
      47: checkcast     #127                // class org/w3c/dom/Element
      50: astore        5
      52: ldc           #224                // String parameter
      54: aload         5
      56: invokeinterface #129,  1          // InterfaceMethod org/w3c/dom/Element.getNodeName:()Ljava/lang/String;
      61: invokevirtual #62                 // Method java/lang/String.equals:(Ljava/lang/Object;)Z
      64: ifne          82
      67: ldc           #224                // String parameter
      69: aload         5
      71: invokeinterface #130,  1          // InterfaceMethod org/w3c/dom/Element.getLocalName:()Ljava/lang/String;
      76: invokevirtual #62                 // Method java/lang/String.equals:(Ljava/lang/Object;)Z
      79: ifeq          174
      82: aload_3
      83: ifnonnull     94
      86: new           #108                // class org/springframework/beans/factory/support/ManagedMap
      89: dup
      90: invokespecial #109                // Method org/springframework/beans/factory/support/ManagedMap."<init>":()V
      93: astore_3
      94: aload         5
      96: ldc           #225                // String key
      98: aload_2
      99: invokestatic  #9                  // Method resolveAttribute:(Lorg/w3c/dom/Element;Ljava/lang/String;Lorg/springframework/beans/factory/xml/ParserContext;)Ljava/lang/String;
     102: astore        6
     104: aload         5
     106: ldc           #217                // String value
     108: aload_2
     109: invokestatic  #9                  // Method resolveAttribute:(Lorg/w3c/dom/Element;Ljava/lang/String;Lorg/springframework/beans/factory/xml/ParserContext;)Ljava/lang/String;
     112: astore        7
     114: ldc           #226                // String true
     116: aload         5
     118: ldc           #227                // String hide
     120: aload_2
     121: invokestatic  #9                  // Method resolveAttribute:(Lorg/w3c/dom/Element;Ljava/lang/String;Lorg/springframework/beans/factory/xml/ParserContext;)Ljava/lang/String;
     124: invokevirtual #62                 // Method java/lang/String.equals:(Ljava/lang/Object;)Z
     127: istore        8
     129: iload         8
     131: ifeq          156
     134: new           #16                 // class java/lang/StringBuilder
     137: dup
     138: invokespecial #17                 // Method java/lang/StringBuilder."<init>":()V
     141: ldc           #87                 // String .
     143: invokevirtual #18                 // Method java/lang/StringBuilder.append:(Ljava/lang/String;)Ljava/lang/StringBuilder;
     146: aload         6
     148: invokevirtual #18                 // Method java/lang/StringBuilder.append:(Ljava/lang/String;)Ljava/lang/StringBuilder;
     151: invokevirtual #21                 // Method java/lang/StringBuilder.toString:()Ljava/lang/String;
     154: astore        6
     156: aload_3
     157: aload         6
     159: new           #111                // class org/springframework/beans/factory/config/TypedStringValue
     162: dup
     163: aload         7
     165: ldc           #55                 // class java/lang/String
     167: invokespecial #112                // Method org/springframework/beans/factory/config/TypedStringValue."<init>":(Ljava/lang/String;Ljava/lang/Class;)V
     170: invokevirtual #113                // Method org/springframework/beans/factory/support/ManagedMap.put:(Ljava/lang/Object;Ljava/lang/Object;)Ljava/lang/Object;
     173: pop
     174: iinc          4, 1
     177: goto          11
     180: aload_3
     181: areturn

  private static void parseMethods(java.lang.String, org.w3c.dom.NodeList, org.springframework.beans.factory.support.RootBeanDefinition, org.springframework.beans.factory.xml.ParserContext);
    Code:
       0: aload_1
       1: ifnonnull     5
       4: return
       5: aconst_null
       6: astore        4
       8: iconst_0
       9: istore        5
      11: iload         5
      13: aload_1
      14: invokeinterface #125,  1          // InterfaceMethod org/w3c/dom/NodeList.getLength:()I
      19: if_icmpge     207
      22: aload_1
      23: iload         5
      25: invokeinterface #126,  2          // InterfaceMethod org/w3c/dom/NodeList.item:(I)Lorg/w3c/dom/Node;
      30: instanceof    #127                // class org/w3c/dom/Element
      33: ifne          39
      36: goto          201
      39: aload_1
      40: iload         5
      42: invokeinterface #126,  2          // InterfaceMethod org/w3c/dom/NodeList.item:(I)Lorg/w3c/dom/Node;
      47: checkcast     #127                // class org/w3c/dom/Element
      50: astore        6
      52: ldc           #228                // String method
      54: aload         6
      56: invokeinterface #129,  1          // InterfaceMethod org/w3c/dom/Element.getNodeName:()Ljava/lang/String;
      61: invokevirtual #62                 // Method java/lang/String.equals:(Ljava/lang/Object;)Z
      64: ifne          82
      67: ldc           #228                // String method
      69: aload         6
      71: invokeinterface #130,  1          // InterfaceMethod org/w3c/dom/Element.getLocalName:()Ljava/lang/String;
      76: invokevirtual #62                 // Method java/lang/String.equals:(Ljava/lang/Object;)Z
      79: ifeq          201
      82: aload         6
      84: ldc           #14                 // String name
      86: aload_3
      87: invokestatic  #9                  // Method resolveAttribute:(Lorg/w3c/dom/Element;Ljava/lang/String;Lorg/springframework/beans/factory/xml/ParserContext;)Ljava/lang/String;
      90: astore        7
      92: aload         7
      94: invokestatic  #13                 // Method org/apache/dubbo/common/utils/StringUtils.isEmpty:(Ljava/lang/String;)Z
      97: ifeq          110
     100: new           #97                 // class java/lang/IllegalStateException
     103: dup
     104: ldc           #229                // String <dubbo:method> name attribute == null
     106: invokespecial #102                // Method java/lang/IllegalStateException."<init>":(Ljava/lang/String;)V
     109: athrow
     110: aload         4
     112: ifnonnull     124
     115: new           #230                // class org/springframework/beans/factory/support/ManagedList
     118: dup
     119: invokespecial #231                // Method org/springframework/beans/factory/support/ManagedList."<init>":()V
     122: astore        4
     124: aload         6
     126: aload_3
     127: ldc           #232                // class org/apache/dubbo/config/MethodConfig
     129: iconst_0
     130: invokestatic  #215                // Method parse:(Lorg/w3c/dom/Element;Lorg/springframework/beans/factory/xml/ParserContext;Ljava/lang/Class;Z)Lorg/springframework/beans/factory/support/RootBeanDefinition;
     133: astore        8
     135: new           #16                 // class java/lang/StringBuilder
     138: dup
     139: invokespecial #17                 // Method java/lang/StringBuilder."<init>":()V
     142: aload_0
     143: invokevirtual #18                 // Method java/lang/StringBuilder.append:(Ljava/lang/String;)Ljava/lang/StringBuilder;
     146: ldc           #87                 // String .
     148: invokevirtual #18                 // Method java/lang/StringBuilder.append:(Ljava/lang/String;)Ljava/lang/StringBuilder;
     151: aload         7
     153: invokevirtual #18                 // Method java/lang/StringBuilder.append:(Ljava/lang/String;)Ljava/lang/StringBuilder;
     156: invokevirtual #21                 // Method java/lang/StringBuilder.toString:()Ljava/lang/String;
     159: astore        9
     161: aload         8
     163: ldc           #8                  // String id
     165: invokestatic  #233                // Method hasPropertyValue:(Lorg/springframework/beans/factory/support/AbstractBeanDefinition;Ljava/lang/String;)Z
     168: ifne          180
     171: aload         8
     173: ldc           #8                  // String id
     175: aload         9
     177: invokestatic  #234                // Method addPropertyValue:(Lorg/springframework/beans/factory/support/AbstractBeanDefinition;Ljava/lang/String;Ljava/lang/String;)V
     180: new           #35                 // class org/springframework/beans/factory/config/BeanDefinitionHolder
     183: dup
     184: aload         8
     186: aload         9
     188: invokespecial #37                 // Method org/springframework/beans/factory/config/BeanDefinitionHolder."<init>":(Lorg/springframework/beans/factory/config/BeanDefinition;Ljava/lang/String;)V
     191: astore        10
     193: aload         4
     195: aload         10
     197: invokevirtual #235                // Method org/springframework/beans/factory/support/ManagedList.add:(Ljava/lang/Object;)Z
     200: pop
     201: iinc          5, 1
     204: goto          11
     207: aload         4
     209: ifnull        223
     212: aload_2
     213: invokevirtual #11                 // Method org/springframework/beans/factory/support/RootBeanDefinition.getPropertyValues:()Lorg/springframework/beans/MutablePropertyValues;
     216: ldc           #64                 // String methods
     218: aload         4
     220: invokevirtual #12                 // Method org/springframework/beans/MutablePropertyValues.addPropertyValue:(Ljava/lang/String;Ljava/lang/Object;)V
     223: return

  private static boolean hasPropertyValue(org.springframework.beans.factory.support.AbstractBeanDefinition, java.lang.String);
    Code:
       0: aload_0
       1: invokevirtual #236                // Method org/springframework/beans/factory/support/AbstractBeanDefinition.getPropertyValues:()Lorg/springframework/beans/MutablePropertyValues;
       4: aload_1
       5: invokevirtual #237                // Method org/springframework/beans/MutablePropertyValues.contains:(Ljava/lang/String;)Z
       8: ireturn

  private static void addPropertyValue(org.springframework.beans.factory.support.AbstractBeanDefinition, java.lang.String, java.lang.String);
    Code:
       0: aload_1
       1: invokestatic  #163                // Method org/apache/dubbo/common/utils/StringUtils.isBlank:(Ljava/lang/CharSequence;)Z
       4: ifne          14
       7: aload_2
       8: invokestatic  #163                // Method org/apache/dubbo/common/utils/StringUtils.isBlank:(Ljava/lang/CharSequence;)Z
      11: ifeq          15
      14: return
      15: aload_0
      16: invokevirtual #236                // Method org/springframework/beans/factory/support/AbstractBeanDefinition.getPropertyValues:()Lorg/springframework/beans/MutablePropertyValues;
      19: aload_1
      20: aload_2
      21: invokevirtual #12                 // Method org/springframework/beans/MutablePropertyValues.addPropertyValue:(Ljava/lang/String;Ljava/lang/Object;)V
      24: return

  private static void parseArguments(java.lang.String, org.w3c.dom.NodeList, org.springframework.beans.factory.support.RootBeanDefinition, org.springframework.beans.factory.xml.ParserContext);
    Code:
       0: aload_1
       1: ifnonnull     5
       4: return
       5: aconst_null
       6: astore        4
       8: iconst_0
       9: istore        5
      11: iload         5
      13: aload_1
      14: invokeinterface #125,  1          // InterfaceMethod org/w3c/dom/NodeList.getLength:()I
      19: if_icmpge     170
      22: aload_1
      23: iload         5
      25: invokeinterface #126,  2          // InterfaceMethod org/w3c/dom/NodeList.item:(I)Lorg/w3c/dom/Node;
      30: instanceof    #127                // class org/w3c/dom/Element
      33: ifne          39
      36: goto          164
      39: aload_1
      40: iload         5
      42: invokeinterface #126,  2          // InterfaceMethod org/w3c/dom/NodeList.item:(I)Lorg/w3c/dom/Node;
      47: checkcast     #127                // class org/w3c/dom/Element
      50: astore        6
      52: ldc           #238                // String argument
      54: aload         6
      56: invokeinterface #129,  1          // InterfaceMethod org/w3c/dom/Element.getNodeName:()Ljava/lang/String;
      61: invokevirtual #62                 // Method java/lang/String.equals:(Ljava/lang/Object;)Z
      64: ifne          82
      67: ldc           #238                // String argument
      69: aload         6
      71: invokeinterface #130,  1          // InterfaceMethod org/w3c/dom/Element.getLocalName:()Ljava/lang/String;
      76: invokevirtual #62                 // Method java/lang/String.equals:(Ljava/lang/Object;)Z
      79: ifeq          164
      82: aload         6
      84: ldc           #239                // String index
      86: aload_3
      87: invokestatic  #9                  // Method resolveAttribute:(Lorg/w3c/dom/Element;Ljava/lang/String;Lorg/springframework/beans/factory/xml/ParserContext;)Ljava/lang/String;
      90: astore        7
      92: aload         4
      94: ifnonnull     106
      97: new           #230                // class org/springframework/beans/factory/support/ManagedList
     100: dup
     101: invokespecial #231                // Method org/springframework/beans/factory/support/ManagedList."<init>":()V
     104: astore        4
     106: aload         6
     108: aload_3
     109: ldc           #240                // class org/apache/dubbo/config/ArgumentConfig
     111: iconst_0
     112: invokestatic  #215                // Method parse:(Lorg/w3c/dom/Element;Lorg/springframework/beans/factory/xml/ParserContext;Ljava/lang/Class;Z)Lorg/springframework/beans/factory/support/RootBeanDefinition;
     115: astore        8
     117: new           #16                 // class java/lang/StringBuilder
     120: dup
     121: invokespecial #17                 // Method java/lang/StringBuilder."<init>":()V
     124: aload_0
     125: invokevirtual #18                 // Method java/lang/StringBuilder.append:(Ljava/lang/String;)Ljava/lang/StringBuilder;
     128: ldc           #87                 // String .
     130: invokevirtual #18                 // Method java/lang/StringBuilder.append:(Ljava/lang/String;)Ljava/lang/StringBuilder;
     133: aload         7
     135: invokevirtual #18                 // Method java/lang/StringBuilder.append:(Ljava/lang/String;)Ljava/lang/StringBuilder;
     138: invokevirtual #21                 // Method java/lang/StringBuilder.toString:()Ljava/lang/String;
     141: astore        9
     143: new           #35                 // class org/springframework/beans/factory/config/BeanDefinitionHolder
     146: dup
     147: aload         8
     149: aload         9
     151: invokespecial #37                 // Method org/springframework/beans/factory/config/BeanDefinitionHolder."<init>":(Lorg/springframework/beans/factory/config/BeanDefinition;Ljava/lang/String;)V
     154: astore        10
     156: aload         4
     158: aload         10
     160: invokevirtual #235                // Method org/springframework/beans/factory/support/ManagedList.add:(Ljava/lang/Object;)Z
     163: pop
     164: iinc          5, 1
     167: goto          11
     170: aload         4
     172: ifnull        186
     175: aload_2
     176: invokevirtual #11                 // Method org/springframework/beans/factory/support/RootBeanDefinition.getPropertyValues:()Lorg/springframework/beans/MutablePropertyValues;
     179: ldc           #66                 // String arguments
     181: aload         4
     183: invokevirtual #12                 // Method org/springframework/beans/MutablePropertyValues.addPropertyValue:(Ljava/lang/String;Ljava/lang/Object;)V
     186: return

  public org.springframework.beans.factory.config.BeanDefinition parse(org.w3c.dom.Element, org.springframework.beans.factory.xml.ParserContext);
    Code:
       0: aload_1
       1: aload_2
       2: aload_0
       3: getfield      #3                  // Field beanClass:Ljava/lang/Class;
       6: iconst_1
       7: invokestatic  #215                // Method parse:(Lorg/w3c/dom/Element;Lorg/springframework/beans/factory/xml/ParserContext;Ljava/lang/Class;Z)Lorg/springframework/beans/factory/support/RootBeanDefinition;
      10: areturn

  private static java.lang.String resolveAttribute(org.w3c.dom.Element, java.lang.String, org.springframework.beans.factory.xml.ParserContext);
    Code:
       0: aload_0
       1: aload_1
       2: invokeinterface #241,  2          // InterfaceMethod org/w3c/dom/Element.getAttribute:(Ljava/lang/String;)Ljava/lang/String;
       7: astore_3
       8: aload_3
       9: areturn

  private static java.lang.String resolvePlaceholders(java.lang.String, org.springframework.beans.factory.xml.ParserContext);
    Code:
       0: getstatic     #242                // Field resolvePlaceholdersEnabled:Z
       3: ifeq          25
       6: aload_1
       7: invokevirtual #243                // Method org/springframework/beans/factory/xml/ParserContext.getReaderContext:()Lorg/springframework/beans/factory/xml/XmlReaderContext;
      10: invokevirtual #244                // Method org/springframework/beans/factory/xml/XmlReaderContext.getEnvironment:()Lorg/springframework/core/env/Environment;
      13: aload_0
      14: invokeinterface #245,  2          // InterfaceMethod org/springframework/core/env/Environment.resolveRequiredPlaceholders:(Ljava/lang/String;)Ljava/lang/String;
      19: areturn
      20: astore_2
      21: iconst_0
      22: putstatic     #242                // Field resolvePlaceholdersEnabled:Z
      25: aload_0
      26: areturn
    Exception table:
       from    to  target type
           6    19    20   Class java/lang/NoSuchMethodError

  static {};
    Code:
       0: ldc           #24                 // class org/apache/dubbo/config/spring/schema/DubboBeanDefinitionParser
       2: invokestatic  #247                // Method org/apache/dubbo/common/logger/LoggerFactory.getLogger:(Ljava/lang/Class;)Lorg/apache/dubbo/common/logger/Logger;
       5: putstatic     #248                // Field logger:Lorg/apache/dubbo/common/logger/Logger;
       8: ldc           #249                // String ^[\\-.0-9_a-zA-Z]+(\\:[\\-.0-9_a-zA-Z]+)?$
      10: invokestatic  #250                // Method java/util/regex/Pattern.compile:(Ljava/lang/String;)Ljava/util/regex/Pattern;
      13: putstatic     #251                // Field GROUP_AND_VERSION:Ljava/util/regex/Pattern;
      16: iconst_1
      17: putstatic     #242                // Field resolvePlaceholdersEnabled:Z
      20: new           #41                 // class java/util/HashMap
      23: dup
      24: invokespecial #42                 // Method java/util/HashMap."<init>":()V
      27: putstatic     #38                 // Field beanPropsCache:Ljava/util/Map;
      30: return
}
