Compiled from "DubboNamespaceHandler.java"
public class org.apache.dubbo.config.spring.schema.DubboNamespaceHandler extends org.springframework.beans.factory.xml.NamespaceHandlerSupport implements org.apache.dubbo.config.spring.beans.factory.config.ConfigurableSourceBeanMetadataElement {
  public org.apache.dubbo.config.spring.schema.DubboNamespaceHandler();
    Code:
       0: aload_0
       1: invokespecial #1                  // Method org/springframework/beans/factory/xml/NamespaceHandlerSupport."<init>":()V
       4: return

  public void init();
    Code:
       0: aload_0
       1: ldc           #2                  // String application
       3: new           #3                  // class org/apache/dubbo/config/spring/schema/DubboBeanDefinitionParser
       6: dup
       7: ldc           #4                  // class org/apache/dubbo/config/ApplicationConfig
       9: invokespecial #5                  // Method org/apache/dubbo/config/spring/schema/DubboBeanDefinitionParser."<init>":(Ljava/lang/Class;)V
      12: invokevirtual #6                  // Method registerBeanDefinitionParser:(Ljava/lang/String;Lorg/springframework/beans/factory/xml/BeanDefinitionParser;)V
      15: aload_0
      16: ldc           #7                  // String module
      18: new           #3                  // class org/apache/dubbo/config/spring/schema/DubboBeanDefinitionParser
      21: dup
      22: ldc           #8                  // class org/apache/dubbo/config/ModuleConfig
      24: invokespecial #5                  // Method org/apache/dubbo/config/spring/schema/DubboBeanDefinitionParser."<init>":(Ljava/lang/Class;)V
      27: invokevirtual #6                  // Method registerBeanDefinitionParser:(Ljava/lang/String;Lorg/springframework/beans/factory/xml/BeanDefinitionParser;)V
      30: aload_0
      31: ldc           #9                  // String registry
      33: new           #3                  // class org/apache/dubbo/config/spring/schema/DubboBeanDefinitionParser
      36: dup
      37: ldc           #10                 // class org/apache/dubbo/config/RegistryConfig
      39: invokespecial #5                  // Method org/apache/dubbo/config/spring/schema/DubboBeanDefinitionParser."<init>":(Ljava/lang/Class;)V
      42: invokevirtual #6                  // Method registerBeanDefinitionParser:(Ljava/lang/String;Lorg/springframework/beans/factory/xml/BeanDefinitionParser;)V
      45: aload_0
      46: ldc           #11                 // String config-center
      48: new           #3                  // class org/apache/dubbo/config/spring/schema/DubboBeanDefinitionParser
      51: dup
      52: ldc           #12                 // class org/apache/dubbo/config/spring/ConfigCenterBean
      54: invokespecial #5                  // Method org/apache/dubbo/config/spring/schema/DubboBeanDefinitionParser."<init>":(Ljava/lang/Class;)V
      57: invokevirtual #6                  // Method registerBeanDefinitionParser:(Ljava/lang/String;Lorg/springframework/beans/factory/xml/BeanDefinitionParser;)V
      60: aload_0
      61: ldc           #13                 // String metadata-report
      63: new           #3                  // class org/apache/dubbo/config/spring/schema/DubboBeanDefinitionParser
      66: dup
      67: ldc           #14                 // class org/apache/dubbo/config/MetadataReportConfig
      69: invokespecial #5                  // Method org/apache/dubbo/config/spring/schema/DubboBeanDefinitionParser."<init>":(Ljava/lang/Class;)V
      72: invokevirtual #6                  // Method registerBeanDefinitionParser:(Ljava/lang/String;Lorg/springframework/beans/factory/xml/BeanDefinitionParser;)V
      75: aload_0
      76: ldc           #15                 // String monitor
      78: new           #3                  // class org/apache/dubbo/config/spring/schema/DubboBeanDefinitionParser
      81: dup
      82: ldc           #16                 // class org/apache/dubbo/config/MonitorConfig
      84: invokespecial #5                  // Method org/apache/dubbo/config/spring/schema/DubboBeanDefinitionParser."<init>":(Ljava/lang/Class;)V
      87: invokevirtual #6                  // Method registerBeanDefinitionParser:(Ljava/lang/String;Lorg/springframework/beans/factory/xml/BeanDefinitionParser;)V
      90: aload_0
      91: ldc           #17                 // String metrics
      93: new           #3                  // class org/apache/dubbo/config/spring/schema/DubboBeanDefinitionParser
      96: dup
      97: ldc           #18                 // class org/apache/dubbo/config/MetricsConfig
      99: invokespecial #5                  // Method org/apache/dubbo/config/spring/schema/DubboBeanDefinitionParser."<init>":(Ljava/lang/Class;)V
     102: invokevirtual #6                  // Method registerBeanDefinitionParser:(Ljava/lang/String;Lorg/springframework/beans/factory/xml/BeanDefinitionParser;)V
     105: aload_0
     106: ldc           #19                 // String tracing
     108: new           #3                  // class org/apache/dubbo/config/spring/schema/DubboBeanDefinitionParser
     111: dup
     112: ldc           #20                 // class org/apache/dubbo/config/TracingConfig
     114: invokespecial #5                  // Method org/apache/dubbo/config/spring/schema/DubboBeanDefinitionParser."<init>":(Ljava/lang/Class;)V
     117: invokevirtual #6                  // Method registerBeanDefinitionParser:(Ljava/lang/String;Lorg/springframework/beans/factory/xml/BeanDefinitionParser;)V
     120: aload_0
     121: ldc           #21                 // String ssl
     123: new           #3                  // class org/apache/dubbo/config/spring/schema/DubboBeanDefinitionParser
     126: dup
     127: ldc           #22                 // class org/apache/dubbo/config/SslConfig
     129: invokespecial #5                  // Method org/apache/dubbo/config/spring/schema/DubboBeanDefinitionParser."<init>":(Ljava/lang/Class;)V
     132: invokevirtual #6                  // Method registerBeanDefinitionParser:(Ljava/lang/String;Lorg/springframework/beans/factory/xml/BeanDefinitionParser;)V
     135: aload_0
     136: ldc           #23                 // String provider
     138: new           #3                  // class org/apache/dubbo/config/spring/schema/DubboBeanDefinitionParser
     141: dup
     142: ldc           #24                 // class org/apache/dubbo/config/ProviderConfig
     144: invokespecial #5                  // Method org/apache/dubbo/config/spring/schema/DubboBeanDefinitionParser."<init>":(Ljava/lang/Class;)V
     147: invokevirtual #6                  // Method registerBeanDefinitionParser:(Ljava/lang/String;Lorg/springframework/beans/factory/xml/BeanDefinitionParser;)V
     150: aload_0
     151: ldc           #25                 // String consumer
     153: new           #3                  // class org/apache/dubbo/config/spring/schema/DubboBeanDefinitionParser
     156: dup
     157: ldc           #26                 // class org/apache/dubbo/config/ConsumerConfig
     159: invokespecial #5                  // Method org/apache/dubbo/config/spring/schema/DubboBeanDefinitionParser."<init>":(Ljava/lang/Class;)V
     162: invokevirtual #6                  // Method registerBeanDefinitionParser:(Ljava/lang/String;Lorg/springframework/beans/factory/xml/BeanDefinitionParser;)V
     165: aload_0
     166: ldc           #27                 // String protocol
     168: new           #3                  // class org/apache/dubbo/config/spring/schema/DubboBeanDefinitionParser
     171: dup
     172: ldc           #28                 // class org/apache/dubbo/config/ProtocolConfig
     174: invokespecial #5                  // Method org/apache/dubbo/config/spring/schema/DubboBeanDefinitionParser."<init>":(Ljava/lang/Class;)V
     177: invokevirtual #6                  // Method registerBeanDefinitionParser:(Ljava/lang/String;Lorg/springframework/beans/factory/xml/BeanDefinitionParser;)V
     180: aload_0
     181: ldc           #29                 // String service
     183: new           #3                  // class org/apache/dubbo/config/spring/schema/DubboBeanDefinitionParser
     186: dup
     187: ldc           #30                 // class org/apache/dubbo/config/spring/ServiceBean
     189: invokespecial #5                  // Method org/apache/dubbo/config/spring/schema/DubboBeanDefinitionParser."<init>":(Ljava/lang/Class;)V
     192: invokevirtual #6                  // Method registerBeanDefinitionParser:(Ljava/lang/String;Lorg/springframework/beans/factory/xml/BeanDefinitionParser;)V
     195: aload_0
     196: ldc           #31                 // String reference
     198: new           #3                  // class org/apache/dubbo/config/spring/schema/DubboBeanDefinitionParser
     201: dup
     202: ldc           #32                 // class org/apache/dubbo/config/spring/ReferenceBean
     204: invokespecial #5                  // Method org/apache/dubbo/config/spring/schema/DubboBeanDefinitionParser."<init>":(Ljava/lang/Class;)V
     207: invokevirtual #6                  // Method registerBeanDefinitionParser:(Ljava/lang/String;Lorg/springframework/beans/factory/xml/BeanDefinitionParser;)V
     210: aload_0
     211: ldc           #33                 // String annotation
     213: new           #34                 // class org/apache/dubbo/config/spring/schema/AnnotationBeanDefinitionParser
     216: dup
     217: invokespecial #35                 // Method org/apache/dubbo/config/spring/schema/AnnotationBeanDefinitionParser."<init>":()V
     220: invokevirtual #6                  // Method registerBeanDefinitionParser:(Ljava/lang/String;Lorg/springframework/beans/factory/xml/BeanDefinitionParser;)V
     223: return

  public org.springframework.beans.factory.config.BeanDefinition parse(org.w3c.dom.Element, org.springframework.beans.factory.xml.ParserContext);
    Code:
       0: aload_2
       1: invokevirtual #36                 // Method org/springframework/beans/factory/xml/ParserContext.getRegistry:()Lorg/springframework/beans/factory/support/BeanDefinitionRegistry;
       4: astore_3
       5: aload_0
       6: aload_3
       7: invokespecial #37                 // Method registerAnnotationConfigProcessors:(Lorg/springframework/beans/factory/support/BeanDefinitionRegistry;)V
      10: aload_2
      11: invokevirtual #36                 // Method org/springframework/beans/factory/xml/ParserContext.getRegistry:()Lorg/springframework/beans/factory/support/BeanDefinitionRegistry;
      14: invokestatic  #38                 // Method org/apache/dubbo/config/spring/context/DubboSpringInitializer.initialize:(Lorg/springframework/beans/factory/support/BeanDefinitionRegistry;)V
      17: aload_0
      18: aload_1
      19: aload_2
      20: invokespecial #39                 // Method org/springframework/beans/factory/xml/NamespaceHandlerSupport.parse:(Lorg/w3c/dom/Element;Lorg/springframework/beans/factory/xml/ParserContext;)Lorg/springframework/beans/factory/config/BeanDefinition;
      23: astore        4
      25: aload_0
      26: aload         4
      28: invokevirtual #40                 // Method setSource:(Lorg/springframework/beans/BeanMetadataElement;)V
      31: aload         4
      33: areturn

  private void registerAnnotationConfigProcessors(org.springframework.beans.factory.support.BeanDefinitionRegistry);
    Code:
       0: aload_1
       1: invokestatic  #41                 // Method org/springframework/context/annotation/AnnotationConfigUtils.registerAnnotationConfigProcessors:(Lorg/springframework/beans/factory/support/BeanDefinitionRegistry;)V
       4: return
}
