Compiled from "DeprecatedInvokerListener.java"
public class org.apache.dubbo.rpc.listener.DeprecatedInvokerListener extends org.apache.dubbo.rpc.listener.InvokerListenerAdapter {
  private static final org.apache.dubbo.common.logger.ErrorTypeAwareLogger LOGGER;

  public org.apache.dubbo.rpc.listener.DeprecatedInvokerListener();
    Code:
       0: aload_0
       1: invokespecial #3                  // Method org/apache/dubbo/rpc/listener/InvokerListenerAdapter."<init>":()V
       4: return

  public void referred(org.apache.dubbo.rpc.Invoker<?>) throws org.apache.dubbo.rpc.RpcException;
    Code:
       0: aload_1
       1: invokeinterface #4,  1            // InterfaceMethod org/apache/dubbo/rpc/Invoker.getUrl:()Lorg/apache/dubbo/common/URL;
       6: ldc           #5                  // String deprecated
       8: iconst_0
       9: invokevirtual #6                  // Method org/apache/dubbo/common/URL.getParameter:(Ljava/lang/String;Z)Z
      12: ifeq          70
      15: getstatic     #7                  // Field LOGGER:Lorg/apache/dubbo/common/logger/ErrorTypeAwareLogger;
      18: ldc           #8                  // String 3-6
      20: ldc           #9                  // String
      22: ldc           #9                  // String
      24: new           #10                 // class java/lang/StringBuilder
      27: dup
      28: invokespecial #11                 // Method java/lang/StringBuilder."<init>":()V
      31: ldc           #12                 // String The service
      33: invokevirtual #13                 // Method java/lang/StringBuilder.append:(Ljava/lang/String;)Ljava/lang/StringBuilder;
      36: aload_1
      37: invokeinterface #14,  1           // InterfaceMethod org/apache/dubbo/rpc/Invoker.getInterface:()Ljava/lang/Class;
      42: invokevirtual #15                 // Method java/lang/Class.getName:()Ljava/lang/String;
      45: invokevirtual #13                 // Method java/lang/StringBuilder.append:(Ljava/lang/String;)Ljava/lang/StringBuilder;
      48: ldc           #16                 // String  is DEPRECATED! Declare from
      50: invokevirtual #13                 // Method java/lang/StringBuilder.append:(Ljava/lang/String;)Ljava/lang/StringBuilder;
      53: aload_1
      54: invokeinterface #4,  1            // InterfaceMethod org/apache/dubbo/rpc/Invoker.getUrl:()Lorg/apache/dubbo/common/URL;
      59: invokevirtual #17                 // Method java/lang/StringBuilder.append:(Ljava/lang/Object;)Ljava/lang/StringBuilder;
      62: invokevirtual #18                 // Method java/lang/StringBuilder.toString:()Ljava/lang/String;
      65: invokeinterface #19,  5           // InterfaceMethod org/apache/dubbo/common/logger/ErrorTypeAwareLogger.error:(Ljava/lang/String;Ljava/lang/String;Ljava/lang/String;Ljava/lang/String;)V
      70: return

  static {};
    Code:
       0: ldc           #20                 // class org/apache/dubbo/rpc/listener/DeprecatedInvokerListener
       2: invokestatic  #21                 // Method org/apache/dubbo/common/logger/LoggerFactory.getErrorTypeAwareLogger:(Ljava/lang/Class;)Lorg/apache/dubbo/common/logger/ErrorTypeAwareLogger;
       5: putstatic     #7                  // Field LOGGER:Lorg/apache/dubbo/common/logger/ErrorTypeAwareLogger;
       8: return
}
