Compiled from "InjvmExporterListener.java"
public class org.apache.dubbo.rpc.listener.InjvmExporterListener extends org.apache.dubbo.rpc.listener.ExporterListenerAdapter {
  private final java.util.Map<java.lang.String, java.util.Set<org.apache.dubbo.rpc.listener.ExporterChangeListener>> exporterChangeListeners;

  private final java.util.Map<java.lang.String, org.apache.dubbo.rpc.Exporter<?>> exporters;

  public org.apache.dubbo.rpc.listener.InjvmExporterListener();
    Code:
       0: aload_0
       1: invokespecial #1                  // Method org/apache/dubbo/rpc/listener/ExporterListenerAdapter."<init>":()V
       4: aload_0
       5: new           #2                  // class java/util/concurrent/ConcurrentHashMap
       8: dup
       9: invokespecial #3                  // Method java/util/concurrent/ConcurrentHashMap."<init>":()V
      12: putfield      #4                  // Field exporterChangeListeners:Ljava/util/Map;
      15: aload_0
      16: new           #2                  // class java/util/concurrent/ConcurrentHashMap
      19: dup
      20: invokespecial #3                  // Method java/util/concurrent/ConcurrentHashMap."<init>":()V
      23: putfield      #5                  // Field exporters:Ljava/util/Map;
      26: return

  public void exported(org.apache.dubbo.rpc.Exporter<?>) throws org.apache.dubbo.rpc.RpcException;
    Code:
       0: aload_1
       1: invokeinterface #6,  1            // InterfaceMethod org/apache/dubbo/rpc/Exporter.getInvoker:()Lorg/apache/dubbo/rpc/Invoker;
       6: invokeinterface #7,  1            // InterfaceMethod org/apache/dubbo/rpc/Invoker.getUrl:()Lorg/apache/dubbo/common/URL;
      11: invokevirtual #8                  // Method org/apache/dubbo/common/URL.getServiceKey:()Ljava/lang/String;
      14: astore_2
      15: aload_0
      16: getfield      #5                  // Field exporters:Ljava/util/Map;
      19: aload_2
      20: aload_1
      21: invokeinterface #9,  3            // InterfaceMethod java/util/Map.putIfAbsent:(Ljava/lang/Object;Ljava/lang/Object;)Ljava/lang/Object;
      26: pop
      27: aload_0
      28: getfield      #4                  // Field exporterChangeListeners:Ljava/util/Map;
      31: aload_2
      32: invokeinterface #10,  2           // InterfaceMethod java/util/Map.get:(Ljava/lang/Object;)Ljava/lang/Object;
      37: checkcast     #11                 // class java/util/Set
      40: astore_3
      41: aload_3
      42: invokestatic  #12                 // Method org/apache/dubbo/common/utils/CollectionUtils.isEmpty:(Ljava/util/Collection;)Z
      45: ifne          89
      48: aload_3
      49: invokeinterface #13,  1           // InterfaceMethod java/util/Set.iterator:()Ljava/util/Iterator;
      54: astore        4
      56: aload         4
      58: invokeinterface #14,  1           // InterfaceMethod java/util/Iterator.hasNext:()Z
      63: ifeq          89
      66: aload         4
      68: invokeinterface #15,  1           // InterfaceMethod java/util/Iterator.next:()Ljava/lang/Object;
      73: checkcast     #16                 // class org/apache/dubbo/rpc/listener/ExporterChangeListener
      76: astore        5
      78: aload         5
      80: aload_1
      81: invokeinterface #17,  2           // InterfaceMethod org/apache/dubbo/rpc/listener/ExporterChangeListener.onExporterChangeExport:(Lorg/apache/dubbo/rpc/Exporter;)V
      86: goto          56
      89: aload_0
      90: aload_1
      91: invokespecial #18                 // Method org/apache/dubbo/rpc/listener/ExporterListenerAdapter.exported:(Lorg/apache/dubbo/rpc/Exporter;)V
      94: return

  public void unexported(org.apache.dubbo.rpc.Exporter<?>) throws org.apache.dubbo.rpc.RpcException;
    Code:
       0: aload_1
       1: invokeinterface #6,  1            // InterfaceMethod org/apache/dubbo/rpc/Exporter.getInvoker:()Lorg/apache/dubbo/rpc/Invoker;
       6: invokeinterface #7,  1            // InterfaceMethod org/apache/dubbo/rpc/Invoker.getUrl:()Lorg/apache/dubbo/common/URL;
      11: invokevirtual #8                  // Method org/apache/dubbo/common/URL.getServiceKey:()Ljava/lang/String;
      14: astore_2
      15: aload_0
      16: getfield      #5                  // Field exporters:Ljava/util/Map;
      19: aload_2
      20: aload_1
      21: invokeinterface #19,  3           // InterfaceMethod java/util/Map.remove:(Ljava/lang/Object;Ljava/lang/Object;)Z
      26: pop
      27: aload_0
      28: getfield      #4                  // Field exporterChangeListeners:Ljava/util/Map;
      31: aload_2
      32: invokeinterface #10,  2           // InterfaceMethod java/util/Map.get:(Ljava/lang/Object;)Ljava/lang/Object;
      37: checkcast     #11                 // class java/util/Set
      40: astore_3
      41: aload_3
      42: invokestatic  #12                 // Method org/apache/dubbo/common/utils/CollectionUtils.isEmpty:(Ljava/util/Collection;)Z
      45: ifne          89
      48: aload_3
      49: invokeinterface #13,  1           // InterfaceMethod java/util/Set.iterator:()Ljava/util/Iterator;
      54: astore        4
      56: aload         4
      58: invokeinterface #14,  1           // InterfaceMethod java/util/Iterator.hasNext:()Z
      63: ifeq          89
      66: aload         4
      68: invokeinterface #15,  1           // InterfaceMethod java/util/Iterator.next:()Ljava/lang/Object;
      73: checkcast     #16                 // class org/apache/dubbo/rpc/listener/ExporterChangeListener
      76: astore        5
      78: aload         5
      80: aload_1
      81: invokeinterface #20,  2           // InterfaceMethod org/apache/dubbo/rpc/listener/ExporterChangeListener.onExporterChangeUnExport:(Lorg/apache/dubbo/rpc/Exporter;)V
      86: goto          56
      89: aload_0
      90: aload_1
      91: invokespecial #21                 // Method org/apache/dubbo/rpc/listener/ExporterListenerAdapter.unexported:(Lorg/apache/dubbo/rpc/Exporter;)V
      94: return

  public synchronized void addExporterChangeListener(org.apache.dubbo.rpc.listener.ExporterChangeListener, java.lang.String);
    Code:
       0: aload_0
       1: getfield      #4                  // Field exporterChangeListeners:Ljava/util/Map;
       4: aload_2
       5: new           #22                 // class org/apache/dubbo/common/utils/ConcurrentHashSet
       8: dup
       9: invokespecial #23                 // Method org/apache/dubbo/common/utils/ConcurrentHashSet."<init>":()V
      12: invokeinterface #9,  3            // InterfaceMethod java/util/Map.putIfAbsent:(Ljava/lang/Object;Ljava/lang/Object;)Ljava/lang/Object;
      17: pop
      18: aload_0
      19: getfield      #4                  // Field exporterChangeListeners:Ljava/util/Map;
      22: aload_2
      23: invokeinterface #10,  2           // InterfaceMethod java/util/Map.get:(Ljava/lang/Object;)Ljava/lang/Object;
      28: checkcast     #11                 // class java/util/Set
      31: aload_1
      32: invokeinterface #24,  2           // InterfaceMethod java/util/Set.add:(Ljava/lang/Object;)Z
      37: pop
      38: aload_0
      39: getfield      #5                  // Field exporters:Ljava/util/Map;
      42: aload_2
      43: invokeinterface #10,  2           // InterfaceMethod java/util/Map.get:(Ljava/lang/Object;)Ljava/lang/Object;
      48: ifnull        72
      51: aload_0
      52: getfield      #5                  // Field exporters:Ljava/util/Map;
      55: aload_2
      56: invokeinterface #10,  2           // InterfaceMethod java/util/Map.get:(Ljava/lang/Object;)Ljava/lang/Object;
      61: checkcast     #25                 // class org/apache/dubbo/rpc/Exporter
      64: astore_3
      65: aload_1
      66: aload_3
      67: invokeinterface #17,  2           // InterfaceMethod org/apache/dubbo/rpc/listener/ExporterChangeListener.onExporterChangeExport:(Lorg/apache/dubbo/rpc/Exporter;)V
      72: return

  public synchronized void removeExporterChangeListener(org.apache.dubbo.rpc.listener.ExporterChangeListener, java.lang.String);
    Code:
       0: aload_0
       1: getfield      #4                  // Field exporterChangeListeners:Ljava/util/Map;
       4: aload_2
       5: invokeinterface #10,  2           // InterfaceMethod java/util/Map.get:(Ljava/lang/Object;)Ljava/lang/Object;
      10: checkcast     #11                 // class java/util/Set
      13: astore_3
      14: aload_3
      15: invokestatic  #12                 // Method org/apache/dubbo/common/utils/CollectionUtils.isEmpty:(Ljava/util/Collection;)Z
      18: ifeq          22
      21: return
      22: aload_3
      23: aload_1
      24: invokeinterface #26,  2           // InterfaceMethod java/util/Set.remove:(Ljava/lang/Object;)Z
      29: pop
      30: aload_3
      31: invokestatic  #12                 // Method org/apache/dubbo/common/utils/CollectionUtils.isEmpty:(Ljava/util/Collection;)Z
      34: ifeq          48
      37: aload_0
      38: getfield      #4                  // Field exporterChangeListeners:Ljava/util/Map;
      41: aload_2
      42: invokeinterface #27,  2           // InterfaceMethod java/util/Map.remove:(Ljava/lang/Object;)Ljava/lang/Object;
      47: pop
      48: return
}
