Compiled from "ListenerInvokerWrapper.java"
public class org.apache.dubbo.rpc.listener.ListenerInvokerWrapper<T> implements org.apache.dubbo.rpc.Invoker<T> {
  private static final org.apache.dubbo.common.logger.ErrorTypeAwareLogger logger;

  private final org.apache.dubbo.rpc.Invoker<T> invoker;

  private final java.util.List<org.apache.dubbo.rpc.InvokerListener> listeners;

  public org.apache.dubbo.rpc.listener.ListenerInvokerWrapper(org.apache.dubbo.rpc.Invoker<T>, java.util.List<org.apache.dubbo.rpc.InvokerListener>);
    Code:
       0: aload_0
       1: invokespecial #1                  // Method java/lang/Object."<init>":()V
       4: aload_1
       5: ifnonnull     18
       8: new           #2                  // class java/lang/IllegalArgumentException
      11: dup
      12: ldc           #3                  // String invoker == null
      14: invokespecial #4                  // Method java/lang/IllegalArgumentException."<init>":(Ljava/lang/String;)V
      17: athrow
      18: aload_0
      19: aload_1
      20: putfield      #5                  // Field invoker:Lorg/apache/dubbo/rpc/Invoker;
      23: aload_0
      24: aload_2
      25: putfield      #6                  // Field listeners:Ljava/util/List;
      28: aload_0
      29: aload_1
      30: invokedynamic #7,  0              // InvokeDynamic #0:accept:(Lorg/apache/dubbo/rpc/Invoker;)Ljava/util/function/Consumer;
      35: invokespecial #8                  // Method listenerEvent:(Ljava/util/function/Consumer;)V
      38: return

  public java.lang.Class<T> getInterface();
    Code:
       0: aload_0
       1: getfield      #5                  // Field invoker:Lorg/apache/dubbo/rpc/Invoker;
       4: invokeinterface #9,  1            // InterfaceMethod org/apache/dubbo/rpc/Invoker.getInterface:()Ljava/lang/Class;
       9: areturn

  public org.apache.dubbo.common.URL getUrl();
    Code:
       0: aload_0
       1: getfield      #5                  // Field invoker:Lorg/apache/dubbo/rpc/Invoker;
       4: invokeinterface #10,  1           // InterfaceMethod org/apache/dubbo/rpc/Invoker.getUrl:()Lorg/apache/dubbo/common/URL;
       9: areturn

  public boolean isAvailable();
    Code:
       0: aload_0
       1: getfield      #5                  // Field invoker:Lorg/apache/dubbo/rpc/Invoker;
       4: invokeinterface #11,  1           // InterfaceMethod org/apache/dubbo/rpc/Invoker.isAvailable:()Z
       9: ireturn

  public org.apache.dubbo.rpc.Result invoke(org.apache.dubbo.rpc.Invocation) throws org.apache.dubbo.rpc.RpcException;
    Code:
       0: aload_0
       1: getfield      #5                  // Field invoker:Lorg/apache/dubbo/rpc/Invoker;
       4: aload_1
       5: invokeinterface #12,  2           // InterfaceMethod org/apache/dubbo/rpc/Invoker.invoke:(Lorg/apache/dubbo/rpc/Invocation;)Lorg/apache/dubbo/rpc/Result;
      10: areturn

  public java.lang.String toString();
    Code:
       0: new           #13                 // class java/lang/StringBuilder
       3: dup
       4: invokespecial #14                 // Method java/lang/StringBuilder."<init>":()V
       7: aload_0
       8: invokevirtual #15                 // Method getInterface:()Ljava/lang/Class;
      11: invokevirtual #16                 // Method java/lang/StringBuilder.append:(Ljava/lang/Object;)Ljava/lang/StringBuilder;
      14: ldc           #17                 // String  ->
      16: invokevirtual #18                 // Method java/lang/StringBuilder.append:(Ljava/lang/String;)Ljava/lang/StringBuilder;
      19: aload_0
      20: invokevirtual #19                 // Method getUrl:()Lorg/apache/dubbo/common/URL;
      23: ifnonnull     31
      26: ldc           #20                 // String
      28: goto          38
      31: aload_0
      32: invokevirtual #19                 // Method getUrl:()Lorg/apache/dubbo/common/URL;
      35: invokevirtual #21                 // Method org/apache/dubbo/common/URL.toString:()Ljava/lang/String;
      38: invokevirtual #18                 // Method java/lang/StringBuilder.append:(Ljava/lang/String;)Ljava/lang/StringBuilder;
      41: invokevirtual #22                 // Method java/lang/StringBuilder.toString:()Ljava/lang/String;
      44: areturn

  public void destroy();
    Code:
       0: aload_0
       1: getfield      #5                  // Field invoker:Lorg/apache/dubbo/rpc/Invoker;
       4: invokeinterface #23,  1           // InterfaceMethod org/apache/dubbo/rpc/Invoker.destroy:()V
       9: aload_0
      10: aload_0
      11: invokedynamic #24,  0             // InvokeDynamic #1:accept:(Lorg/apache/dubbo/rpc/listener/ListenerInvokerWrapper;)Ljava/util/function/Consumer;
      16: invokespecial #8                  // Method listenerEvent:(Ljava/util/function/Consumer;)V
      19: goto          35
      22: astore_1
      23: aload_0
      24: aload_0
      25: invokedynamic #24,  0             // InvokeDynamic #1:accept:(Lorg/apache/dubbo/rpc/listener/ListenerInvokerWrapper;)Ljava/util/function/Consumer;
      30: invokespecial #8                  // Method listenerEvent:(Ljava/util/function/Consumer;)V
      33: aload_1
      34: athrow
      35: return
    Exception table:
       from    to  target type
           0     9    22   any

  public org.apache.dubbo.rpc.Invoker<T> getInvoker();
    Code:
       0: aload_0
       1: getfield      #5                  // Field invoker:Lorg/apache/dubbo/rpc/Invoker;
       4: areturn

  public java.util.List<org.apache.dubbo.rpc.InvokerListener> getListeners();
    Code:
       0: aload_0
       1: getfield      #6                  // Field listeners:Ljava/util/List;
       4: areturn

  private void listenerEvent(java.util.function.Consumer<org.apache.dubbo.rpc.InvokerListener>);
    Code:
       0: aload_0
       1: getfield      #6                  // Field listeners:Ljava/util/List;
       4: invokestatic  #25                 // Method org/apache/dubbo/common/utils/CollectionUtils.isNotEmpty:(Ljava/util/Collection;)Z
       7: ifeq          93
      10: aconst_null
      11: astore_2
      12: aload_0
      13: getfield      #6                  // Field listeners:Ljava/util/List;
      16: invokeinterface #26,  1           // InterfaceMethod java/util/List.iterator:()Ljava/util/Iterator;
      21: astore_3
      22: aload_3
      23: invokeinterface #27,  1           // InterfaceMethod java/util/Iterator.hasNext:()Z
      28: ifeq          87
      31: aload_3
      32: invokeinterface #28,  1           // InterfaceMethod java/util/Iterator.next:()Ljava/lang/Object;
      37: checkcast     #29                 // class org/apache/dubbo/rpc/InvokerListener
      40: astore        4
      42: aload         4
      44: ifnull        84
      47: aload_1
      48: aload         4
      50: invokeinterface #30,  2           // InterfaceMethod java/util/function/Consumer.accept:(Ljava/lang/Object;)V
      55: goto          84
      58: astore        5
      60: getstatic     #32                 // Field logger:Lorg/apache/dubbo/common/logger/ErrorTypeAwareLogger;
      63: ldc           #34                 // String 99-0
      65: ldc           #35                 // String wrapped listener internal error
      67: ldc           #36                 // String
      69: aload         5
      71: invokevirtual #37                 // Method java/lang/RuntimeException.getMessage:()Ljava/lang/String;
      74: aload         5
      76: invokeinterface #38,  6           // InterfaceMethod org/apache/dubbo/common/logger/ErrorTypeAwareLogger.error:(Ljava/lang/String;Ljava/lang/String;Ljava/lang/String;Ljava/lang/String;Ljava/lang/Throwable;)V
      81: aload         5
      83: astore_2
      84: goto          22
      87: aload_2
      88: ifnull        93
      91: aload_2
      92: athrow
      93: return
    Exception table:
       from    to  target type
          47    55    58   Class java/lang/RuntimeException

  private void lambda$destroy$1(org.apache.dubbo.rpc.InvokerListener);
    Code:
       0: aload_1
       1: aload_0
       2: getfield      #5                  // Field invoker:Lorg/apache/dubbo/rpc/Invoker;
       5: invokeinterface #39,  2           // InterfaceMethod org/apache/dubbo/rpc/InvokerListener.destroyed:(Lorg/apache/dubbo/rpc/Invoker;)V
      10: return

  private static void lambda$new$0(org.apache.dubbo.rpc.Invoker, org.apache.dubbo.rpc.InvokerListener);
    Code:
       0: aload_1
       1: aload_0
       2: invokeinterface #40,  2           // InterfaceMethod org/apache/dubbo/rpc/InvokerListener.referred:(Lorg/apache/dubbo/rpc/Invoker;)V
       7: return

  static {};
    Code:
       0: ldc           #41                 // class org/apache/dubbo/rpc/listener/ListenerInvokerWrapper
       2: invokestatic  #42                 // Method org/apache/dubbo/common/logger/LoggerFactory.getErrorTypeAwareLogger:(Ljava/lang/Class;)Lorg/apache/dubbo/common/logger/ErrorTypeAwareLogger;
       5: putstatic     #32                 // Field logger:Lorg/apache/dubbo/common/logger/ErrorTypeAwareLogger;
       8: return
}
