Compiled from "ColorConverter.java"
public final class org.springframework.boot.logging.log4j2.ColorConverter extends org.apache.logging.log4j.core.pattern.LogEventPatternConverter {
  private static final java.util.Map<java.lang.String, org.springframework.boot.ansi.AnsiElement> ELEMENTS;

  private static final java.util.Map<java.lang.Integer, org.springframework.boot.ansi.AnsiElement> LEVELS;

  private final java.util.List<org.apache.logging.log4j.core.pattern.PatternFormatter> formatters;

  private final org.springframework.boot.ansi.AnsiElement styling;

  private org.springframework.boot.logging.log4j2.ColorConverter(java.util.List<org.apache.logging.log4j.core.pattern.PatternFormatter>, org.springframework.boot.ansi.AnsiElement);
    Code:
       0: aload_0
       1: ldc           #1                  // String style
       3: ldc           #1                  // String style
       5: invokespecial #3                  // Method org/apache/logging/log4j/core/pattern/LogEventPatternConverter."<init>":(Ljava/lang/String;Ljava/lang/String;)V
       8: aload_0
       9: aload_1
      10: putfield      #9                  // Field formatters:Ljava/util/List;
      13: aload_0
      14: aload_2
      15: putfield      #15                 // Field styling:Lorg/springframework/boot/ansi/AnsiElement;
      18: return

  public static org.springframework.boot.logging.log4j2.ColorConverter newInstance(org.apache.logging.log4j.core.config.Configuration, java.lang.String[]);
    Code:
       0: aload_1
       1: arraylength
       2: iconst_1
       3: if_icmpge     23
       6: getstatic     #19                 // Field LOGGER:Lorg/apache/logging/log4j/Logger;
       9: ldc           #23                 // String Incorrect number of options on style. Expected at least 1, received {}
      11: aload_1
      12: arraylength
      13: invokestatic  #25                 // Method java/lang/Integer.valueOf:(I)Ljava/lang/Integer;
      16: invokeinterface #31,  3           // InterfaceMethod org/apache/logging/log4j/Logger.error:(Ljava/lang/String;Ljava/lang/Object;)V
      21: aconst_null
      22: areturn
      23: aload_1
      24: iconst_0
      25: aaload
      26: ifnonnull     41
      29: getstatic     #19                 // Field LOGGER:Lorg/apache/logging/log4j/Logger;
      32: ldc           #37                 // String No pattern supplied on style
      34: invokeinterface #39,  2           // InterfaceMethod org/apache/logging/log4j/Logger.error:(Ljava/lang/String;)V
      39: aconst_null
      40: areturn
      41: aload_0
      42: invokestatic  #42                 // Method org/apache/logging/log4j/core/layout/PatternLayout.createPatternParser:(Lorg/apache/logging/log4j/core/config/Configuration;)Lorg/apache/logging/log4j/core/pattern/PatternParser;
      45: astore_2
      46: aload_2
      47: aload_1
      48: iconst_0
      49: aaload
      50: invokevirtual #48                 // Method org/apache/logging/log4j/core/pattern/PatternParser.parse:(Ljava/lang/String;)Ljava/util/List;
      53: astore_3
      54: aload_1
      55: arraylength
      56: iconst_1
      57: if_icmpeq     77
      60: getstatic     #54                 // Field ELEMENTS:Ljava/util/Map;
      63: aload_1
      64: iconst_1
      65: aaload
      66: invokeinterface #58,  2           // InterfaceMethod java/util/Map.get:(Ljava/lang/Object;)Ljava/lang/Object;
      71: checkcast     #64                 // class org/springframework/boot/ansi/AnsiElement
      74: goto          78
      77: aconst_null
      78: astore        4
      80: new           #10                 // class org/springframework/boot/logging/log4j2/ColorConverter
      83: dup
      84: aload_3
      85: aload         4
      87: invokespecial #66                 // Method "<init>":(Ljava/util/List;Lorg/springframework/boot/ansi/AnsiElement;)V
      90: areturn

  public boolean handlesThrowable();
    Code:
       0: aload_0
       1: getfield      #9                  // Field formatters:Ljava/util/List;
       4: invokeinterface #69,  1           // InterfaceMethod java/util/List.iterator:()Ljava/util/Iterator;
       9: astore_1
      10: aload_1
      11: invokeinterface #75,  1           // InterfaceMethod java/util/Iterator.hasNext:()Z
      16: ifeq          41
      19: aload_1
      20: invokeinterface #81,  1           // InterfaceMethod java/util/Iterator.next:()Ljava/lang/Object;
      25: checkcast     #85                 // class org/apache/logging/log4j/core/pattern/PatternFormatter
      28: astore_2
      29: aload_2
      30: invokevirtual #87                 // Method org/apache/logging/log4j/core/pattern/PatternFormatter.handlesThrowable:()Z
      33: ifeq          38
      36: iconst_1
      37: ireturn
      38: goto          10
      41: aload_0
      42: invokespecial #90                 // Method org/apache/logging/log4j/core/pattern/LogEventPatternConverter.handlesThrowable:()Z
      45: ireturn

  public void format(org.apache.logging.log4j.core.LogEvent, java.lang.StringBuilder);
    Code:
       0: new           #91                 // class java/lang/StringBuilder
       3: dup
       4: invokespecial #93                 // Method java/lang/StringBuilder."<init>":()V
       7: astore_3
       8: aload_0
       9: getfield      #9                  // Field formatters:Ljava/util/List;
      12: invokeinterface #69,  1           // InterfaceMethod java/util/List.iterator:()Ljava/util/Iterator;
      17: astore        4
      19: aload         4
      21: invokeinterface #75,  1           // InterfaceMethod java/util/Iterator.hasNext:()Z
      26: ifeq          51
      29: aload         4
      31: invokeinterface #81,  1           // InterfaceMethod java/util/Iterator.next:()Ljava/lang/Object;
      36: checkcast     #85                 // class org/apache/logging/log4j/core/pattern/PatternFormatter
      39: astore        5
      41: aload         5
      43: aload_1
      44: aload_3
      45: invokevirtual #96                 // Method org/apache/logging/log4j/core/pattern/PatternFormatter.format:(Lorg/apache/logging/log4j/core/LogEvent;Ljava/lang/StringBuilder;)V
      48: goto          19
      51: aload_3
      52: invokevirtual #100                // Method java/lang/StringBuilder.length:()I
      55: ifle          120
      58: aload_0
      59: getfield      #15                 // Field styling:Lorg/springframework/boot/ansi/AnsiElement;
      62: astore        4
      64: aload         4
      66: ifnonnull     109
      69: getstatic     #104                // Field LEVELS:Ljava/util/Map;
      72: aload_1
      73: invokeinterface #107,  1          // InterfaceMethod org/apache/logging/log4j/core/LogEvent.getLevel:()Lorg/apache/logging/log4j/Level;
      78: invokevirtual #113                // Method org/apache/logging/log4j/Level.intLevel:()I
      81: invokestatic  #25                 // Method java/lang/Integer.valueOf:(I)Ljava/lang/Integer;
      84: invokeinterface #58,  2           // InterfaceMethod java/util/Map.get:(Ljava/lang/Object;)Ljava/lang/Object;
      89: checkcast     #64                 // class org/springframework/boot/ansi/AnsiElement
      92: astore        4
      94: aload         4
      96: ifnull        104
      99: aload         4
     101: goto          107
     104: getstatic     #118                // Field org/springframework/boot/ansi/AnsiColor.GREEN:Lorg/springframework/boot/ansi/AnsiColor;
     107: astore        4
     109: aload_0
     110: aload_2
     111: aload_3
     112: invokevirtual #124                // Method java/lang/StringBuilder.toString:()Ljava/lang/String;
     115: aload         4
     117: invokevirtual #128                // Method appendAnsiString:(Ljava/lang/StringBuilder;Ljava/lang/String;Lorg/springframework/boot/ansi/AnsiElement;)V
     120: return

  protected void appendAnsiString(java.lang.StringBuilder, java.lang.String, org.springframework.boot.ansi.AnsiElement);
    Code:
       0: aload_1
       1: iconst_2
       2: anewarray     #132                // class java/lang/Object
       5: dup
       6: iconst_0
       7: aload_3
       8: aastore
       9: dup
      10: iconst_1
      11: aload_2
      12: aastore
      13: invokestatic  #134                // Method org/springframework/boot/ansi/AnsiOutput.toString:([Ljava/lang/Object;)Ljava/lang/String;
      16: invokevirtual #139                // Method java/lang/StringBuilder.append:(Ljava/lang/String;)Ljava/lang/StringBuilder;
      19: pop
      20: return

  static {};
    Code:
       0: new           #143                // class java/util/HashMap
       3: dup
       4: invokespecial #145                // Method java/util/HashMap."<init>":()V
       7: astore_0
       8: aload_0
       9: ldc           #146                // String black
      11: getstatic     #148                // Field org/springframework/boot/ansi/AnsiColor.BLACK:Lorg/springframework/boot/ansi/AnsiColor;
      14: invokeinterface #151,  3          // InterfaceMethod java/util/Map.put:(Ljava/lang/Object;Ljava/lang/Object;)Ljava/lang/Object;
      19: pop
      20: aload_0
      21: ldc           #155                // String white
      23: getstatic     #157                // Field org/springframework/boot/ansi/AnsiColor.WHITE:Lorg/springframework/boot/ansi/AnsiColor;
      26: invokeinterface #151,  3          // InterfaceMethod java/util/Map.put:(Ljava/lang/Object;Ljava/lang/Object;)Ljava/lang/Object;
      31: pop
      32: aload_0
      33: ldc           #160                // String faint
      35: getstatic     #162                // Field org/springframework/boot/ansi/AnsiStyle.FAINT:Lorg/springframework/boot/ansi/AnsiStyle;
      38: invokeinterface #151,  3          // InterfaceMethod java/util/Map.put:(Ljava/lang/Object;Ljava/lang/Object;)Ljava/lang/Object;
      43: pop
      44: aload_0
      45: ldc           #168                // String red
      47: getstatic     #170                // Field org/springframework/boot/ansi/AnsiColor.RED:Lorg/springframework/boot/ansi/AnsiColor;
      50: invokeinterface #151,  3          // InterfaceMethod java/util/Map.put:(Ljava/lang/Object;Ljava/lang/Object;)Ljava/lang/Object;
      55: pop
      56: aload_0
      57: ldc           #173                // String green
      59: getstatic     #118                // Field org/springframework/boot/ansi/AnsiColor.GREEN:Lorg/springframework/boot/ansi/AnsiColor;
      62: invokeinterface #151,  3          // InterfaceMethod java/util/Map.put:(Ljava/lang/Object;Ljava/lang/Object;)Ljava/lang/Object;
      67: pop
      68: aload_0
      69: ldc           #175                // String yellow
      71: getstatic     #177                // Field org/springframework/boot/ansi/AnsiColor.YELLOW:Lorg/springframework/boot/ansi/AnsiColor;
      74: invokeinterface #151,  3          // InterfaceMethod java/util/Map.put:(Ljava/lang/Object;Ljava/lang/Object;)Ljava/lang/Object;
      79: pop
      80: aload_0
      81: ldc           #180                // String blue
      83: getstatic     #182                // Field org/springframework/boot/ansi/AnsiColor.BLUE:Lorg/springframework/boot/ansi/AnsiColor;
      86: invokeinterface #151,  3          // InterfaceMethod java/util/Map.put:(Ljava/lang/Object;Ljava/lang/Object;)Ljava/lang/Object;
      91: pop
      92: aload_0
      93: ldc           #185                // String magenta
      95: getstatic     #187                // Field org/springframework/boot/ansi/AnsiColor.MAGENTA:Lorg/springframework/boot/ansi/AnsiColor;
      98: invokeinterface #151,  3          // InterfaceMethod java/util/Map.put:(Ljava/lang/Object;Ljava/lang/Object;)Ljava/lang/Object;
     103: pop
     104: aload_0
     105: ldc           #190                // String cyan
     107: getstatic     #192                // Field org/springframework/boot/ansi/AnsiColor.CYAN:Lorg/springframework/boot/ansi/AnsiColor;
     110: invokeinterface #151,  3          // InterfaceMethod java/util/Map.put:(Ljava/lang/Object;Ljava/lang/Object;)Ljava/lang/Object;
     115: pop
     116: aload_0
     117: ldc           #195                // String bright_black
     119: getstatic     #197                // Field org/springframework/boot/ansi/AnsiColor.BRIGHT_BLACK:Lorg/springframework/boot/ansi/AnsiColor;
     122: invokeinterface #151,  3          // InterfaceMethod java/util/Map.put:(Ljava/lang/Object;Ljava/lang/Object;)Ljava/lang/Object;
     127: pop
     128: aload_0
     129: ldc           #200                // String bright_white
     131: getstatic     #202                // Field org/springframework/boot/ansi/AnsiColor.BRIGHT_WHITE:Lorg/springframework/boot/ansi/AnsiColor;
     134: invokeinterface #151,  3          // InterfaceMethod java/util/Map.put:(Ljava/lang/Object;Ljava/lang/Object;)Ljava/lang/Object;
     139: pop
     140: aload_0
     141: ldc           #205                // String bright_red
     143: getstatic     #207                // Field org/springframework/boot/ansi/AnsiColor.BRIGHT_RED:Lorg/springframework/boot/ansi/AnsiColor;
     146: invokeinterface #151,  3          // InterfaceMethod java/util/Map.put:(Ljava/lang/Object;Ljava/lang/Object;)Ljava/lang/Object;
     151: pop
     152: aload_0
     153: ldc           #210                // String bright_green
     155: getstatic     #212                // Field org/springframework/boot/ansi/AnsiColor.BRIGHT_GREEN:Lorg/springframework/boot/ansi/AnsiColor;
     158: invokeinterface #151,  3          // InterfaceMethod java/util/Map.put:(Ljava/lang/Object;Ljava/lang/Object;)Ljava/lang/Object;
     163: pop
     164: aload_0
     165: ldc           #215                // String bright_yellow
     167: getstatic     #217                // Field org/springframework/boot/ansi/AnsiColor.BRIGHT_YELLOW:Lorg/springframework/boot/ansi/AnsiColor;
     170: invokeinterface #151,  3          // InterfaceMethod java/util/Map.put:(Ljava/lang/Object;Ljava/lang/Object;)Ljava/lang/Object;
     175: pop
     176: aload_0
     177: ldc           #220                // String bright_blue
     179: getstatic     #222                // Field org/springframework/boot/ansi/AnsiColor.BRIGHT_BLUE:Lorg/springframework/boot/ansi/AnsiColor;
     182: invokeinterface #151,  3          // InterfaceMethod java/util/Map.put:(Ljava/lang/Object;Ljava/lang/Object;)Ljava/lang/Object;
     187: pop
     188: aload_0
     189: ldc           #225                // String bright_magenta
     191: getstatic     #227                // Field org/springframework/boot/ansi/AnsiColor.BRIGHT_MAGENTA:Lorg/springframework/boot/ansi/AnsiColor;
     194: invokeinterface #151,  3          // InterfaceMethod java/util/Map.put:(Ljava/lang/Object;Ljava/lang/Object;)Ljava/lang/Object;
     199: pop
     200: aload_0
     201: ldc           #230                // String bright_cyan
     203: getstatic     #232                // Field org/springframework/boot/ansi/AnsiColor.BRIGHT_CYAN:Lorg/springframework/boot/ansi/AnsiColor;
     206: invokeinterface #151,  3          // InterfaceMethod java/util/Map.put:(Ljava/lang/Object;Ljava/lang/Object;)Ljava/lang/Object;
     211: pop
     212: aload_0
     213: invokestatic  #235                // Method java/util/Collections.unmodifiableMap:(Ljava/util/Map;)Ljava/util/Map;
     216: putstatic     #54                 // Field ELEMENTS:Ljava/util/Map;
     219: new           #143                // class java/util/HashMap
     222: dup
     223: invokespecial #145                // Method java/util/HashMap."<init>":()V
     226: astore_0
     227: aload_0
     228: getstatic     #241                // Field org/apache/logging/log4j/Level.FATAL:Lorg/apache/logging/log4j/Level;
     231: invokevirtual #113                // Method org/apache/logging/log4j/Level.intLevel:()I
     234: invokestatic  #25                 // Method java/lang/Integer.valueOf:(I)Ljava/lang/Integer;
     237: getstatic     #170                // Field org/springframework/boot/ansi/AnsiColor.RED:Lorg/springframework/boot/ansi/AnsiColor;
     240: invokeinterface #151,  3          // InterfaceMethod java/util/Map.put:(Ljava/lang/Object;Ljava/lang/Object;)Ljava/lang/Object;
     245: pop
     246: aload_0
     247: getstatic     #245                // Field org/apache/logging/log4j/Level.ERROR:Lorg/apache/logging/log4j/Level;
     250: invokevirtual #113                // Method org/apache/logging/log4j/Level.intLevel:()I
     253: invokestatic  #25                 // Method java/lang/Integer.valueOf:(I)Ljava/lang/Integer;
     256: getstatic     #170                // Field org/springframework/boot/ansi/AnsiColor.RED:Lorg/springframework/boot/ansi/AnsiColor;
     259: invokeinterface #151,  3          // InterfaceMethod java/util/Map.put:(Ljava/lang/Object;Ljava/lang/Object;)Ljava/lang/Object;
     264: pop
     265: aload_0
     266: getstatic     #248                // Field org/apache/logging/log4j/Level.WARN:Lorg/apache/logging/log4j/Level;
     269: invokevirtual #113                // Method org/apache/logging/log4j/Level.intLevel:()I
     272: invokestatic  #25                 // Method java/lang/Integer.valueOf:(I)Ljava/lang/Integer;
     275: getstatic     #177                // Field org/springframework/boot/ansi/AnsiColor.YELLOW:Lorg/springframework/boot/ansi/AnsiColor;
     278: invokeinterface #151,  3          // InterfaceMethod java/util/Map.put:(Ljava/lang/Object;Ljava/lang/Object;)Ljava/lang/Object;
     283: pop
     284: aload_0
     285: invokestatic  #235                // Method java/util/Collections.unmodifiableMap:(Ljava/util/Map;)Ljava/util/Map;
     288: putstatic     #104                // Field LEVELS:Ljava/util/Map;
     291: return
}
