Compiled from "Log4J2LoggingSystem.java"
public class org.springframework.boot.logging.log4j2.Log4J2LoggingSystem$Factory implements org.springframework.boot.logging.LoggingSystemFactory {
  private static final boolean PRESENT;

  public org.springframework.boot.logging.log4j2.Log4J2LoggingSystem$Factory();
    Code:
       0: aload_0
       1: invokespecial #1                  // Method java/lang/Object."<init>":()V
       4: return

  public org.springframework.boot.logging.LoggingSystem getLoggingSystem(java.lang.ClassLoader);
    Code:
       0: getstatic     #7                  // Field PRESENT:Z
       3: ifeq          15
       6: new           #13                 // class org/springframework/boot/logging/log4j2/Log4J2LoggingSystem
       9: dup
      10: aload_1
      11: invokespecial #15                 // Method org/springframework/boot/logging/log4j2/Log4J2LoggingSystem."<init>":(Ljava/lang/ClassLoader;)V
      14: areturn
      15: aconst_null
      16: areturn

  static {};
    Code:
       0: ldc           #18                 // String org.apache.logging.log4j.core.impl.Log4jContextFactory
       2: ldc           #8                  // class org/springframework/boot/logging/log4j2/Log4J2LoggingSystem$Factory
       4: invokevirtual #20                 // Method java/lang/Class.getClassLoader:()Ljava/lang/ClassLoader;
       7: invokestatic  #26                 // Method org/springframework/util/ClassUtils.isPresent:(Ljava/lang/String;Ljava/lang/ClassLoader;)Z
      10: putstatic     #7                  // Field PRESENT:Z
      13: return
}
