Compiled from "SpringEnvironmentLookup.java"
class org.springframework.boot.logging.log4j2.SpringEnvironmentLookup implements org.apache.logging.log4j.core.config.LoggerContextAware,org.apache.logging.log4j.core.lookup.StrLookup {
  private volatile org.springframework.core.env.Environment environment;

  org.springframework.boot.logging.log4j2.SpringEnvironmentLookup();
    Code:
       0: aload_0
       1: invokespecial #1                  // Method java/lang/Object."<init>":()V
       4: return

  public java.lang.String lookup(org.apache.logging.log4j.core.LogEvent, java.lang.String);
    Code:
       0: aload_0
       1: aload_2
       2: invokevirtual #7                  // Method lookup:(Ljava/lang/String;)Ljava/lang/String;
       5: areturn

  public java.lang.String lookup(java.lang.String);
    Code:
       0: aload_0
       1: getfield      #13                 // Field environment:Lorg/springframework/core/env/Environment;
       4: ifnull        11
       7: iconst_1
       8: goto          12
      11: iconst_0
      12: ldc           #17                 // String Unable to obtain Spring Environment from LoggerContext
      14: invokestatic  #19                 // Method org/springframework/util/Assert.state:(ZLjava/lang/String;)V
      17: aload_0
      18: getfield      #13                 // Field environment:Lorg/springframework/core/env/Environment;
      21: aload_1
      22: invokeinterface #25,  2           // InterfaceMethod org/springframework/core/env/Environment.getProperty:(Ljava/lang/String;)Ljava/lang/String;
      27: areturn

  public void setLoggerContext(org.apache.logging.log4j.core.LoggerContext);
    Code:
       0: aload_0
       1: aload_1
       2: invokestatic  #30                 // Method org/springframework/boot/logging/log4j2/Log4J2LoggingSystem.getEnvironment:(Lorg/apache/logging/log4j/core/LoggerContext;)Lorg/springframework/core/env/Environment;
       5: putfield      #13                 // Field environment:Lorg/springframework/core/env/Environment;
       8: return
}
