Compiled from "SpringProfileArbiter.java"
final class org.springframework.boot.logging.log4j2.SpringProfileArbiter implements org.apache.logging.log4j.core.config.arbiters.Arbiter {
  private final org.springframework.core.env.Environment environment;

  private final org.springframework.core.env.Profiles profiles;

  private org.springframework.boot.logging.log4j2.SpringProfileArbiter(org.springframework.core.env.Environment, java.lang.String[]);
    Code:
       0: aload_0
       1: invokespecial #1                  // Method java/lang/Object."<init>":()V
       4: aload_0
       5: aload_1
       6: putfield      #7                  // Field environment:Lorg/springframework/core/env/Environment;
       9: aload_0
      10: aload_2
      11: invokestatic  #13                 // InterfaceMethod org/springframework/core/env/Profiles.of:([Ljava/lang/String;)Lorg/springframework/core/env/Profiles;
      14: putfield      #19                 // Field profiles:Lorg/springframework/core/env/Profiles;
      17: return

  public boolean isCondition();
    Code:
       0: aload_0
       1: getfield      #7                  // Field environment:Lorg/springframework/core/env/Environment;
       4: ifnull        23
       7: aload_0
       8: getfield      #7                  // Field environment:Lorg/springframework/core/env/Environment;
      11: aload_0
      12: getfield      #19                 // Field profiles:Lorg/springframework/core/env/Profiles;
      15: invokeinterface #23,  2           // InterfaceMethod org/springframework/core/env/Environment.acceptsProfiles:(Lorg/springframework/core/env/Profiles;)Z
      20: goto          24
      23: iconst_0
      24: ireturn

  static org.springframework.boot.logging.log4j2.SpringProfileArbiter$Builder newBuilder();
    Code:
       0: new           #29                 // class org/springframework/boot/logging/log4j2/SpringProfileArbiter$Builder
       3: dup
       4: invokespecial #31                 // Method org/springframework/boot/logging/log4j2/SpringProfileArbiter$Builder."<init>":()V
       7: areturn
}
