Compiled from "SpringEnvironmentPropertySource.java"
class org.springframework.boot.logging.log4j2.SpringEnvironmentPropertySource implements org.apache.logging.log4j.util.PropertySource {
  private static final int PRIORITY;

  private final org.springframework.core.env.Environment environment;

  org.springframework.boot.logging.log4j2.SpringEnvironmentPropertySource(org.springframework.core.env.Environment);
    Code:
       0: aload_0
       1: invokespecial #1                  // Method java/lang/Object."<init>":()V
       4: aload_1
       5: ldc           #7                  // String Environment must not be null
       7: invokestatic  #9                  // Method org/springframework/util/Assert.notNull:(Ljava/lang/Object;Ljava/lang/String;)V
      10: aload_0
      11: aload_1
      12: putfield      #15                 // Field environment:Lorg/springframework/core/env/Environment;
      15: return

  public int getPriority();
    Code:
       0: bipush        -100
       2: ireturn

  public java.lang.String getProperty(java.lang.String);
    Code:
       0: aload_0
       1: getfield      #15                 // Field environment:Lorg/springframework/core/env/Environment;
       4: aload_1
       5: invokeinterface #21,  2           // InterfaceMethod org/springframework/core/env/Environment.getProperty:(Ljava/lang/String;)Ljava/lang/String;
      10: areturn

  public boolean containsProperty(java.lang.String);
    Code:
       0: aload_0
       1: getfield      #15                 // Field environment:Lorg/springframework/core/env/Environment;
       4: aload_1
       5: invokeinterface #27,  2           // InterfaceMethod org/springframework/core/env/Environment.containsProperty:(Ljava/lang/String;)Z
      10: ireturn
}
