Compiled from "SpringProfileArbiter.java"
final class org.springframework.boot.logging.log4j2.SpringProfileArbiter$Builder implements org.apache.logging.log4j.core.util.Builder<org.springframework.boot.logging.log4j2.SpringProfileArbiter> {
  private static final org.apache.logging.log4j.Logger statusLogger;

  private java.lang.String name;

  private org.apache.logging.log4j.core.config.Configuration configuration;

  private org.apache.logging.log4j.core.LoggerContext loggerContext;

  private org.springframework.boot.logging.log4j2.SpringProfileArbiter$Builder();
    Code:
       0: aload_0
       1: invokespecial #1                  // Method java/lang/Object."<init>":()V
       4: return

  org.springframework.boot.logging.log4j2.SpringProfileArbiter$Builder setName(java.lang.String);
    Code:
       0: aload_0
       1: aload_1
       2: putfield      #7                  // Field name:Ljava/lang/String;
       5: aload_0
       6: areturn

  public org.springframework.boot.logging.log4j2.SpringProfileArbiter build();
    Code:
       0: aload_0
       1: getfield      #13                 // Field loggerContext:Lorg/apache/logging/log4j/core/LoggerContext;
       4: invokestatic  #17                 // Method org/springframework/boot/logging/log4j2/Log4J2LoggingSystem.getEnvironment:(Lorg/apache/logging/log4j/core/LoggerContext;)Lorg/springframework/core/env/Environment;
       7: astore_1
       8: aload_1
       9: ifnonnull     24
      12: getstatic     #23                 // Field statusLogger:Lorg/apache/logging/log4j/Logger;
      15: ldc           #27                 // String Cannot create Arbiter, no Spring Environment available
      17: invokeinterface #29,  2           // InterfaceMethod org/apache/logging/log4j/Logger.warn:(Ljava/lang/String;)V
      22: aconst_null
      23: areturn
      24: aload_0
      25: getfield      #35                 // Field configuration:Lorg/apache/logging/log4j/core/config/Configuration;
      28: invokeinterface #39,  1           // InterfaceMethod org/apache/logging/log4j/core/config/Configuration.getStrSubstitutor:()Lorg/apache/logging/log4j/core/lookup/StrSubstitutor;
      33: aload_0
      34: getfield      #7                  // Field name:Ljava/lang/String;
      37: invokevirtual #45                 // Method org/apache/logging/log4j/core/lookup/StrSubstitutor.replace:(Ljava/lang/String;)Ljava/lang/String;
      40: astore_2
      41: aload_2
      42: invokestatic  #51                 // Method org/springframework/util/StringUtils.commaDelimitedListToStringArray:(Ljava/lang/String;)[Ljava/lang/String;
      45: invokestatic  #57                 // Method org/springframework/util/StringUtils.trimArrayElements:([Ljava/lang/String;)[Ljava/lang/String;
      48: astore_3
      49: new           #61                 // class org/springframework/boot/logging/log4j2/SpringProfileArbiter
      52: dup
      53: aload_1
      54: aload_3
      55: invokespecial #63                 // Method org/springframework/boot/logging/log4j2/SpringProfileArbiter."<init>":(Lorg/springframework/core/env/Environment;[Ljava/lang/String;)V
      58: areturn

  public java.lang.Object build();
    Code:
       0: aload_0
       1: invokevirtual #66                 // Method build:()Lorg/springframework/boot/logging/log4j2/SpringProfileArbiter;
       4: areturn

  static {};
    Code:
       0: invokestatic  #70                 // Method org/apache/logging/log4j/status/StatusLogger.getLogger:()Lorg/apache/logging/log4j/status/StatusLogger;
       3: putstatic     #23                 // Field statusLogger:Lorg/apache/logging/log4j/Logger;
       6: return
}
