Compiled from "AsyncRpcResult.java"
public class org.apache.dubbo.rpc.AsyncRpcResult implements org.apache.dubbo.rpc.Result {
  private static final org.apache.dubbo.common.logger.ErrorTypeAwareLogger logger;

  private org.apache.dubbo.rpc.RpcContext$RestoreContext storedContext;

  private java.util.concurrent.Executor executor;

  private final org.apache.dubbo.rpc.Invocation invocation;

  private final boolean async;

  private java.util.concurrent.CompletableFuture<org.apache.dubbo.rpc.AppResponse> responseFuture;

  private static final boolean setFutureWhenSync;

  public org.apache.dubbo.rpc.AsyncRpcResult(java.util.concurrent.CompletableFuture<org.apache.dubbo.rpc.AppResponse>, org.apache.dubbo.rpc.Invocation);
    Code:
       0: aload_0
       1: invokespecial #3                  // Method java/lang/Object."<init>":()V
       4: aload_0
       5: aload_1
       6: putfield      #4                  // Field responseFuture:Ljava/util/concurrent/CompletableFuture;
       9: aload_0
      10: aload_2
      11: putfield      #5                  // Field invocation:Lorg/apache/dubbo/rpc/Invocation;
      14: aload_2
      15: checkcast     #6                  // class org/apache/dubbo/rpc/RpcInvocation
      18: astore_3
      19: aload_3
      20: ldc           #7                  // String PROVIDER_ASYNC
      22: invokevirtual #8                  // Method org/apache/dubbo/rpc/RpcInvocation.get:(Ljava/lang/Object;)Ljava/lang/Object;
      25: ifnonnull     38
      28: getstatic     #9                  // Field org/apache/dubbo/rpc/InvokeMode.SYNC:Lorg/apache/dubbo/rpc/InvokeMode;
      31: aload_3
      32: invokevirtual #10                 // Method org/apache/dubbo/rpc/RpcInvocation.getInvokeMode:()Lorg/apache/dubbo/rpc/InvokeMode;
      35: if_acmpeq     60
      38: aload_1
      39: invokevirtual #11                 // Method java/util/concurrent/CompletableFuture.isDone:()Z
      42: ifne          60
      45: aload_0
      46: iconst_1
      47: putfield      #12                 // Field async:Z
      50: aload_0
      51: invokestatic  #13                 // Method org/apache/dubbo/rpc/RpcContext.clearAndStoreContext:()Lorg/apache/dubbo/rpc/RpcContext$RestoreContext;
      54: putfield      #14                 // Field storedContext:Lorg/apache/dubbo/rpc/RpcContext$RestoreContext;
      57: goto          65
      60: aload_0
      61: iconst_0
      62: putfield      #12                 // Field async:Z
      65: return

  public java.lang.Object getValue();
    Code:
       0: aload_0
       1: invokevirtual #15                 // Method getAppResponse:()Lorg/apache/dubbo/rpc/Result;
       4: invokeinterface #16,  1           // InterfaceMethod org/apache/dubbo/rpc/Result.getValue:()Ljava/lang/Object;
       9: areturn

  public void setValue(java.lang.Object);
    Code:
       0: aload_0
       1: getfield      #4                  // Field responseFuture:Ljava/util/concurrent/CompletableFuture;
       4: invokevirtual #11                 // Method java/util/concurrent/CompletableFuture.isDone:()Z
       7: ifeq          27
      10: aload_0
      11: getfield      #4                  // Field responseFuture:Ljava/util/concurrent/CompletableFuture;
      14: invokevirtual #17                 // Method java/util/concurrent/CompletableFuture.get:()Ljava/lang/Object;
      17: checkcast     #18                 // class org/apache/dubbo/rpc/AppResponse
      20: aload_1
      21: invokevirtual #19                 // Method org/apache/dubbo/rpc/AppResponse.setValue:(Ljava/lang/Object;)V
      24: goto          53
      27: new           #18                 // class org/apache/dubbo/rpc/AppResponse
      30: dup
      31: aload_0
      32: getfield      #5                  // Field invocation:Lorg/apache/dubbo/rpc/Invocation;
      35: invokespecial #20                 // Method org/apache/dubbo/rpc/AppResponse."<init>":(Lorg/apache/dubbo/rpc/Invocation;)V
      38: astore_2
      39: aload_2
      40: aload_1
      41: invokevirtual #19                 // Method org/apache/dubbo/rpc/AppResponse.setValue:(Ljava/lang/Object;)V
      44: aload_0
      45: getfield      #4                  // Field responseFuture:Ljava/util/concurrent/CompletableFuture;
      48: aload_2
      49: invokevirtual #21                 // Method java/util/concurrent/CompletableFuture.complete:(Ljava/lang/Object;)Z
      52: pop
      53: goto          82
      56: astore_2
      57: getstatic     #23                 // Field logger:Lorg/apache/dubbo/common/logger/ErrorTypeAwareLogger;
      60: ldc           #24                 // String 3-5
      62: ldc           #25                 // String
      64: ldc           #25                 // String
      66: ldc           #26                 // String Got exception when trying to fetch the underlying result from AsyncRpcResult.
      68: invokeinterface #27,  5           // InterfaceMethod org/apache/dubbo/common/logger/ErrorTypeAwareLogger.error:(Ljava/lang/String;Ljava/lang/String;Ljava/lang/String;Ljava/lang/String;)V
      73: new           #28                 // class org/apache/dubbo/rpc/RpcException
      76: dup
      77: aload_2
      78: invokespecial #29                 // Method org/apache/dubbo/rpc/RpcException."<init>":(Ljava/lang/Throwable;)V
      81: athrow
      82: return
    Exception table:
       from    to  target type
           0    53    56   Class java/lang/Exception

  public java.lang.Throwable getException();
    Code:
       0: aload_0
       1: invokevirtual #15                 // Method getAppResponse:()Lorg/apache/dubbo/rpc/Result;
       4: invokeinterface #30,  1           // InterfaceMethod org/apache/dubbo/rpc/Result.getException:()Ljava/lang/Throwable;
       9: areturn

  public void setException(java.lang.Throwable);
    Code:
       0: aload_0
       1: getfield      #4                  // Field responseFuture:Ljava/util/concurrent/CompletableFuture;
       4: invokevirtual #11                 // Method java/util/concurrent/CompletableFuture.isDone:()Z
       7: ifeq          27
      10: aload_0
      11: getfield      #4                  // Field responseFuture:Ljava/util/concurrent/CompletableFuture;
      14: invokevirtual #17                 // Method java/util/concurrent/CompletableFuture.get:()Ljava/lang/Object;
      17: checkcast     #18                 // class org/apache/dubbo/rpc/AppResponse
      20: aload_1
      21: invokevirtual #31                 // Method org/apache/dubbo/rpc/AppResponse.setException:(Ljava/lang/Throwable;)V
      24: goto          53
      27: new           #18                 // class org/apache/dubbo/rpc/AppResponse
      30: dup
      31: aload_0
      32: getfield      #5                  // Field invocation:Lorg/apache/dubbo/rpc/Invocation;
      35: invokespecial #20                 // Method org/apache/dubbo/rpc/AppResponse."<init>":(Lorg/apache/dubbo/rpc/Invocation;)V
      38: astore_2
      39: aload_2
      40: aload_1
      41: invokevirtual #31                 // Method org/apache/dubbo/rpc/AppResponse.setException:(Ljava/lang/Throwable;)V
      44: aload_0
      45: getfield      #4                  // Field responseFuture:Ljava/util/concurrent/CompletableFuture;
      48: aload_2
      49: invokevirtual #21                 // Method java/util/concurrent/CompletableFuture.complete:(Ljava/lang/Object;)Z
      52: pop
      53: goto          82
      56: astore_2
      57: getstatic     #23                 // Field logger:Lorg/apache/dubbo/common/logger/ErrorTypeAwareLogger;
      60: ldc           #24                 // String 3-5
      62: ldc           #25                 // String
      64: ldc           #25                 // String
      66: ldc           #26                 // String Got exception when trying to fetch the underlying result from AsyncRpcResult.
      68: invokeinterface #27,  5           // InterfaceMethod org/apache/dubbo/common/logger/ErrorTypeAwareLogger.error:(Ljava/lang/String;Ljava/lang/String;Ljava/lang/String;Ljava/lang/String;)V
      73: new           #28                 // class org/apache/dubbo/rpc/RpcException
      76: dup
      77: aload_2
      78: invokespecial #29                 // Method org/apache/dubbo/rpc/RpcException."<init>":(Ljava/lang/Throwable;)V
      81: athrow
      82: return
    Exception table:
       from    to  target type
           0    53    56   Class java/lang/Exception

  public boolean hasException();
    Code:
       0: aload_0
       1: invokevirtual #15                 // Method getAppResponse:()Lorg/apache/dubbo/rpc/Result;
       4: invokeinterface #32,  1           // InterfaceMethod org/apache/dubbo/rpc/Result.hasException:()Z
       9: ireturn

  public java.util.concurrent.CompletableFuture<org.apache.dubbo.rpc.AppResponse> getResponseFuture();
    Code:
       0: aload_0
       1: getfield      #4                  // Field responseFuture:Ljava/util/concurrent/CompletableFuture;
       4: areturn

  public void setResponseFuture(java.util.concurrent.CompletableFuture<org.apache.dubbo.rpc.AppResponse>);
    Code:
       0: aload_0
       1: aload_1
       2: putfield      #4                  // Field responseFuture:Ljava/util/concurrent/CompletableFuture;
       5: return

  public org.apache.dubbo.rpc.Result getAppResponse();
    Code:
       0: aload_0
       1: getfield      #4                  // Field responseFuture:Ljava/util/concurrent/CompletableFuture;
       4: invokevirtual #11                 // Method java/util/concurrent/CompletableFuture.isDone:()Z
       7: ifeq          21
      10: aload_0
      11: getfield      #4                  // Field responseFuture:Ljava/util/concurrent/CompletableFuture;
      14: invokevirtual #17                 // Method java/util/concurrent/CompletableFuture.get:()Ljava/lang/Object;
      17: checkcast     #33                 // class org/apache/dubbo/rpc/Result
      20: areturn
      21: goto          50
      24: astore_1
      25: getstatic     #23                 // Field logger:Lorg/apache/dubbo/common/logger/ErrorTypeAwareLogger;
      28: ldc           #24                 // String 3-5
      30: ldc           #25                 // String
      32: ldc           #25                 // String
      34: ldc           #26                 // String Got exception when trying to fetch the underlying result from AsyncRpcResult.
      36: invokeinterface #27,  5           // InterfaceMethod org/apache/dubbo/common/logger/ErrorTypeAwareLogger.error:(Ljava/lang/String;Ljava/lang/String;Ljava/lang/String;Ljava/lang/String;)V
      41: new           #28                 // class org/apache/dubbo/rpc/RpcException
      44: dup
      45: aload_1
      46: invokespecial #29                 // Method org/apache/dubbo/rpc/RpcException."<init>":(Ljava/lang/Throwable;)V
      49: athrow
      50: aload_0
      51: getfield      #5                  // Field invocation:Lorg/apache/dubbo/rpc/Invocation;
      54: invokestatic  #34                 // Method createDefaultValue:(Lorg/apache/dubbo/rpc/Invocation;)Lorg/apache/dubbo/rpc/Result;
      57: areturn
    Exception table:
       from    to  target type
           0    20    24   Class java/lang/Exception

  public org.apache.dubbo.rpc.Result get() throws java.lang.InterruptedException, java.util.concurrent.ExecutionException;
    Code:
       0: aload_0
       1: getfield      #35                 // Field executor:Ljava/util/concurrent/Executor;
       4: ifnull        56
       7: aload_0
       8: getfield      #35                 // Field executor:Ljava/util/concurrent/Executor;
      11: instanceof    #36                 // class org/apache/dubbo/common/threadpool/ThreadlessExecutor
      14: ifeq          56
      17: aload_0
      18: getfield      #35                 // Field executor:Ljava/util/concurrent/Executor;
      21: checkcast     #36                 // class org/apache/dubbo/common/threadpool/ThreadlessExecutor
      24: astore_1
      25: aload_0
      26: getfield      #4                  // Field responseFuture:Ljava/util/concurrent/CompletableFuture;
      29: invokevirtual #11                 // Method java/util/concurrent/CompletableFuture.isDone:()Z
      32: ifne          42
      35: aload_1
      36: invokevirtual #37                 // Method org/apache/dubbo/common/threadpool/ThreadlessExecutor.waitAndDrain:()V
      39: goto          25
      42: aload_1
      43: invokevirtual #38                 // Method org/apache/dubbo/common/threadpool/ThreadlessExecutor.shutdown:()V
      46: goto          56
      49: astore_2
      50: aload_1
      51: invokevirtual #38                 // Method org/apache/dubbo/common/threadpool/ThreadlessExecutor.shutdown:()V
      54: aload_2
      55: athrow
      56: aload_0
      57: getfield      #4                  // Field responseFuture:Ljava/util/concurrent/CompletableFuture;
      60: invokevirtual #17                 // Method java/util/concurrent/CompletableFuture.get:()Ljava/lang/Object;
      63: checkcast     #33                 // class org/apache/dubbo/rpc/Result
      66: areturn
    Exception table:
       from    to  target type
          25    42    49   any

  public org.apache.dubbo.rpc.Result get(long, java.util.concurrent.TimeUnit) throws java.lang.InterruptedException, java.util.concurrent.ExecutionException, java.util.concurrent.TimeoutException;
    Code:
       0: aload_0
       1: getfield      #35                 // Field executor:Ljava/util/concurrent/Executor;
       4: ifnull        62
       7: aload_0
       8: getfield      #35                 // Field executor:Ljava/util/concurrent/Executor;
      11: instanceof    #36                 // class org/apache/dubbo/common/threadpool/ThreadlessExecutor
      14: ifeq          62
      17: aload_0
      18: getfield      #35                 // Field executor:Ljava/util/concurrent/Executor;
      21: checkcast     #36                 // class org/apache/dubbo/common/threadpool/ThreadlessExecutor
      24: astore        4
      26: aload_0
      27: getfield      #4                  // Field responseFuture:Ljava/util/concurrent/CompletableFuture;
      30: invokevirtual #11                 // Method java/util/concurrent/CompletableFuture.isDone:()Z
      33: ifne          44
      36: aload         4
      38: invokevirtual #37                 // Method org/apache/dubbo/common/threadpool/ThreadlessExecutor.waitAndDrain:()V
      41: goto          26
      44: aload         4
      46: invokevirtual #38                 // Method org/apache/dubbo/common/threadpool/ThreadlessExecutor.shutdown:()V
      49: goto          62
      52: astore        5
      54: aload         4
      56: invokevirtual #38                 // Method org/apache/dubbo/common/threadpool/ThreadlessExecutor.shutdown:()V
      59: aload         5
      61: athrow
      62: aload_0
      63: getfield      #4                  // Field responseFuture:Ljava/util/concurrent/CompletableFuture;
      66: lload_1
      67: aload_3
      68: invokevirtual #39                 // Method java/util/concurrent/CompletableFuture.get:(JLjava/util/concurrent/TimeUnit;)Ljava/lang/Object;
      71: checkcast     #33                 // class org/apache/dubbo/rpc/Result
      74: areturn
    Exception table:
       from    to  target type
          26    44    52   any
          52    54    52   any

  public java.lang.Object recreate() throws java.lang.Throwable;
    Code:
       0: aload_0
       1: getfield      #5                  // Field invocation:Lorg/apache/dubbo/rpc/Invocation;
       4: checkcast     #6                  // class org/apache/dubbo/rpc/RpcInvocation
       7: astore_1
       8: getstatic     #40                 // Field org/apache/dubbo/rpc/InvokeMode.FUTURE:Lorg/apache/dubbo/rpc/InvokeMode;
      11: aload_1
      12: invokevirtual #10                 // Method org/apache/dubbo/rpc/RpcInvocation.getInvokeMode:()Lorg/apache/dubbo/rpc/InvokeMode;
      15: if_acmpne     25
      18: invokestatic  #41                 // Method org/apache/dubbo/rpc/RpcContext.getClientAttachment:()Lorg/apache/dubbo/rpc/RpcContextAttachment;
      21: invokevirtual #42                 // Method org/apache/dubbo/rpc/RpcContextAttachment.getFuture:()Ljava/util/concurrent/Future;
      24: areturn
      25: getstatic     #43                 // Field org/apache/dubbo/rpc/InvokeMode.ASYNC:Lorg/apache/dubbo/rpc/InvokeMode;
      28: aload_1
      29: invokevirtual #10                 // Method org/apache/dubbo/rpc/RpcInvocation.getInvokeMode:()Lorg/apache/dubbo/rpc/InvokeMode;
      32: if_acmpne     48
      35: aload_0
      36: getfield      #5                  // Field invocation:Lorg/apache/dubbo/rpc/Invocation;
      39: invokestatic  #34                 // Method createDefaultValue:(Lorg/apache/dubbo/rpc/Invocation;)Lorg/apache/dubbo/rpc/Result;
      42: invokeinterface #44,  1           // InterfaceMethod org/apache/dubbo/rpc/Result.recreate:()Ljava/lang/Object;
      47: areturn
      48: aload_0
      49: invokevirtual #15                 // Method getAppResponse:()Lorg/apache/dubbo/rpc/Result;
      52: invokeinterface #44,  1           // InterfaceMethod org/apache/dubbo/rpc/Result.recreate:()Ljava/lang/Object;
      57: areturn

  public org.apache.dubbo.rpc.Result whenCompleteWithContext(java.util.function.BiConsumer<org.apache.dubbo.rpc.Result, java.lang.Throwable>);
    Code:
       0: aload_0
       1: aload_0
       2: getfield      #4                  // Field responseFuture:Ljava/util/concurrent/CompletableFuture;
       5: aload_0
       6: aload_1
       7: invokedynamic #45,  0             // InvokeDynamic #0:accept:(Lorg/apache/dubbo/rpc/AsyncRpcResult;Ljava/util/function/BiConsumer;)Ljava/util/function/BiConsumer;
      12: invokevirtual #46                 // Method java/util/concurrent/CompletableFuture.whenComplete:(Ljava/util/function/BiConsumer;)Ljava/util/concurrent/CompletableFuture;
      15: putfield      #4                  // Field responseFuture:Ljava/util/concurrent/CompletableFuture;
      18: getstatic     #47                 // Field setFutureWhenSync:Z
      21: ifne          40
      24: aload_0
      25: getfield      #5                  // Field invocation:Lorg/apache/dubbo/rpc/Invocation;
      28: checkcast     #6                  // class org/apache/dubbo/rpc/RpcInvocation
      31: invokevirtual #10                 // Method org/apache/dubbo/rpc/RpcInvocation.getInvokeMode:()Lorg/apache/dubbo/rpc/InvokeMode;
      34: getstatic     #9                  // Field org/apache/dubbo/rpc/InvokeMode.SYNC:Lorg/apache/dubbo/rpc/InvokeMode;
      37: if_acmpeq     57
      40: invokestatic  #48                 // Method org/apache/dubbo/rpc/RpcContext.getServiceContext:()Lorg/apache/dubbo/rpc/RpcServiceContext;
      43: new           #49                 // class org/apache/dubbo/rpc/protocol/dubbo/FutureAdapter
      46: dup
      47: aload_0
      48: getfield      #4                  // Field responseFuture:Ljava/util/concurrent/CompletableFuture;
      51: invokespecial #50                 // Method org/apache/dubbo/rpc/protocol/dubbo/FutureAdapter."<init>":(Ljava/util/concurrent/CompletableFuture;)V
      54: invokevirtual #51                 // Method org/apache/dubbo/rpc/RpcServiceContext.setFuture:(Ljava/util/concurrent/CompletableFuture;)V
      57: aload_0
      58: areturn

  public <U> java.util.concurrent.CompletableFuture<U> thenApply(java.util.function.Function<org.apache.dubbo.rpc.Result, ? extends U>);
    Code:
       0: aload_0
       1: getfield      #4                  // Field responseFuture:Ljava/util/concurrent/CompletableFuture;
       4: aload_1
       5: invokevirtual #52                 // Method java/util/concurrent/CompletableFuture.thenApply:(Ljava/util/function/Function;)Ljava/util/concurrent/CompletableFuture;
       8: areturn

  public java.util.Map<java.lang.String, java.lang.String> getAttachments();
    Code:
       0: aload_0
       1: invokevirtual #15                 // Method getAppResponse:()Lorg/apache/dubbo/rpc/Result;
       4: invokeinterface #53,  1           // InterfaceMethod org/apache/dubbo/rpc/Result.getAttachments:()Ljava/util/Map;
       9: areturn

  public java.util.Map<java.lang.String, java.lang.Object> getObjectAttachments();
    Code:
       0: aload_0
       1: invokevirtual #15                 // Method getAppResponse:()Lorg/apache/dubbo/rpc/Result;
       4: invokeinterface #54,  1           // InterfaceMethod org/apache/dubbo/rpc/Result.getObjectAttachments:()Ljava/util/Map;
       9: areturn

  public void setAttachments(java.util.Map<java.lang.String, java.lang.String>);
    Code:
       0: aload_0
       1: invokevirtual #15                 // Method getAppResponse:()Lorg/apache/dubbo/rpc/Result;
       4: aload_1
       5: invokeinterface #55,  2           // InterfaceMethod org/apache/dubbo/rpc/Result.setAttachments:(Ljava/util/Map;)V
      10: return

  public void setObjectAttachments(java.util.Map<java.lang.String, java.lang.Object>);
    Code:
       0: aload_0
       1: invokevirtual #15                 // Method getAppResponse:()Lorg/apache/dubbo/rpc/Result;
       4: aload_1
       5: invokeinterface #56,  2           // InterfaceMethod org/apache/dubbo/rpc/Result.setObjectAttachments:(Ljava/util/Map;)V
      10: return

  public void addAttachments(java.util.Map<java.lang.String, java.lang.String>);
    Code:
       0: aload_0
       1: invokevirtual #15                 // Method getAppResponse:()Lorg/apache/dubbo/rpc/Result;
       4: aload_1
       5: invokeinterface #57,  2           // InterfaceMethod org/apache/dubbo/rpc/Result.addAttachments:(Ljava/util/Map;)V
      10: return

  public void addObjectAttachments(java.util.Map<java.lang.String, java.lang.Object>);
    Code:
       0: aload_0
       1: invokevirtual #15                 // Method getAppResponse:()Lorg/apache/dubbo/rpc/Result;
       4: aload_1
       5: invokeinterface #58,  2           // InterfaceMethod org/apache/dubbo/rpc/Result.addObjectAttachments:(Ljava/util/Map;)V
      10: return

  public java.lang.String getAttachment(java.lang.String);
    Code:
       0: aload_0
       1: invokevirtual #15                 // Method getAppResponse:()Lorg/apache/dubbo/rpc/Result;
       4: aload_1
       5: invokeinterface #59,  2           // InterfaceMethod org/apache/dubbo/rpc/Result.getAttachment:(Ljava/lang/String;)Ljava/lang/String;
      10: areturn

  public java.lang.Object getObjectAttachment(java.lang.String);
    Code:
       0: aload_0
       1: invokevirtual #15                 // Method getAppResponse:()Lorg/apache/dubbo/rpc/Result;
       4: aload_1
       5: invokeinterface #60,  2           // InterfaceMethod org/apache/dubbo/rpc/Result.getObjectAttachment:(Ljava/lang/String;)Ljava/lang/Object;
      10: areturn

  public java.lang.String getAttachment(java.lang.String, java.lang.String);
    Code:
       0: aload_0
       1: invokevirtual #15                 // Method getAppResponse:()Lorg/apache/dubbo/rpc/Result;
       4: aload_1
       5: aload_2
       6: invokeinterface #61,  3           // InterfaceMethod org/apache/dubbo/rpc/Result.getAttachment:(Ljava/lang/String;Ljava/lang/String;)Ljava/lang/String;
      11: areturn

  public java.lang.Object getObjectAttachment(java.lang.String, java.lang.Object);
    Code:
       0: aload_0
       1: invokevirtual #15                 // Method getAppResponse:()Lorg/apache/dubbo/rpc/Result;
       4: aload_1
       5: aload_2
       6: invokeinterface #62,  3           // InterfaceMethod org/apache/dubbo/rpc/Result.getObjectAttachment:(Ljava/lang/String;Ljava/lang/Object;)Ljava/lang/Object;
      11: areturn

  public void setAttachment(java.lang.String, java.lang.String);
    Code:
       0: aload_0
       1: aload_1
       2: aload_2
       3: invokevirtual #63                 // Method setObjectAttachment:(Ljava/lang/String;Ljava/lang/Object;)V
       6: return

  public void setAttachment(java.lang.String, java.lang.Object);
    Code:
       0: aload_0
       1: aload_1
       2: aload_2
       3: invokevirtual #63                 // Method setObjectAttachment:(Ljava/lang/String;Ljava/lang/Object;)V
       6: return

  public void setObjectAttachment(java.lang.String, java.lang.Object);
    Code:
       0: aload_0
       1: invokevirtual #15                 // Method getAppResponse:()Lorg/apache/dubbo/rpc/Result;
       4: aload_1
       5: aload_2
       6: invokeinterface #64,  3           // InterfaceMethod org/apache/dubbo/rpc/Result.setAttachment:(Ljava/lang/String;Ljava/lang/Object;)V
      11: return

  public java.util.concurrent.Executor getExecutor();
    Code:
       0: aload_0
       1: getfield      #35                 // Field executor:Ljava/util/concurrent/Executor;
       4: areturn

  public void setExecutor(java.util.concurrent.Executor);
    Code:
       0: aload_0
       1: aload_1
       2: putfield      #35                 // Field executor:Ljava/util/concurrent/Executor;
       5: return

  public static org.apache.dubbo.rpc.AsyncRpcResult newDefaultAsyncResult(org.apache.dubbo.rpc.AppResponse, org.apache.dubbo.rpc.Invocation);
    Code:
       0: new           #65                 // class org/apache/dubbo/rpc/AsyncRpcResult
       3: dup
       4: aload_0
       5: invokestatic  #66                 // Method java/util/concurrent/CompletableFuture.completedFuture:(Ljava/lang/Object;)Ljava/util/concurrent/CompletableFuture;
       8: aload_1
       9: invokespecial #67                 // Method "<init>":(Ljava/util/concurrent/CompletableFuture;Lorg/apache/dubbo/rpc/Invocation;)V
      12: areturn

  public static org.apache.dubbo.rpc.AsyncRpcResult newDefaultAsyncResult(org.apache.dubbo.rpc.Invocation);
    Code:
       0: aconst_null
       1: aconst_null
       2: aload_0
       3: invokestatic  #68                 // Method newDefaultAsyncResult:(Ljava/lang/Object;Ljava/lang/Throwable;Lorg/apache/dubbo/rpc/Invocation;)Lorg/apache/dubbo/rpc/AsyncRpcResult;
       6: areturn

  public static org.apache.dubbo.rpc.AsyncRpcResult newDefaultAsyncResult(java.lang.Object, org.apache.dubbo.rpc.Invocation);
    Code:
       0: aload_0
       1: aconst_null
       2: aload_1
       3: invokestatic  #68                 // Method newDefaultAsyncResult:(Ljava/lang/Object;Ljava/lang/Throwable;Lorg/apache/dubbo/rpc/Invocation;)Lorg/apache/dubbo/rpc/AsyncRpcResult;
       6: areturn

  public static org.apache.dubbo.rpc.AsyncRpcResult newDefaultAsyncResult(java.lang.Throwable, org.apache.dubbo.rpc.Invocation);
    Code:
       0: aconst_null
       1: aload_0
       2: aload_1
       3: invokestatic  #68                 // Method newDefaultAsyncResult:(Ljava/lang/Object;Ljava/lang/Throwable;Lorg/apache/dubbo/rpc/Invocation;)Lorg/apache/dubbo/rpc/AsyncRpcResult;
       6: areturn

  public static org.apache.dubbo.rpc.AsyncRpcResult newDefaultAsyncResult(java.lang.Object, java.lang.Throwable, org.apache.dubbo.rpc.Invocation);
    Code:
       0: new           #69                 // class java/util/concurrent/CompletableFuture
       3: dup
       4: invokespecial #70                 // Method java/util/concurrent/CompletableFuture."<init>":()V
       7: astore_3
       8: new           #18                 // class org/apache/dubbo/rpc/AppResponse
      11: dup
      12: aload_2
      13: invokespecial #20                 // Method org/apache/dubbo/rpc/AppResponse."<init>":(Lorg/apache/dubbo/rpc/Invocation;)V
      16: astore        4
      18: aload_1
      19: ifnull        31
      22: aload         4
      24: aload_1
      25: invokevirtual #31                 // Method org/apache/dubbo/rpc/AppResponse.setException:(Ljava/lang/Throwable;)V
      28: goto          37
      31: aload         4
      33: aload_0
      34: invokevirtual #19                 // Method org/apache/dubbo/rpc/AppResponse.setValue:(Ljava/lang/Object;)V
      37: aload_3
      38: aload         4
      40: invokevirtual #21                 // Method java/util/concurrent/CompletableFuture.complete:(Ljava/lang/Object;)Z
      43: pop
      44: new           #65                 // class org/apache/dubbo/rpc/AsyncRpcResult
      47: dup
      48: aload_3
      49: aload_2
      50: invokespecial #67                 // Method "<init>":(Ljava/util/concurrent/CompletableFuture;Lorg/apache/dubbo/rpc/Invocation;)V
      53: areturn

  private static org.apache.dubbo.rpc.Result createDefaultValue(org.apache.dubbo.rpc.Invocation);
    Code:
       0: aload_0
       1: ldc           #72                 // String methodModel
       3: invokeinterface #73,  2           // InterfaceMethod org/apache/dubbo/rpc/Invocation.get:(Ljava/lang/Object;)Ljava/lang/Object;
       8: checkcast     #74                 // class org/apache/dubbo/rpc/model/ConsumerMethodModel
      11: astore_1
      12: aload_1
      13: ifnull        33
      16: new           #18                 // class org/apache/dubbo/rpc/AppResponse
      19: dup
      20: aload_1
      21: invokevirtual #75                 // Method org/apache/dubbo/rpc/model/ConsumerMethodModel.getReturnClass:()Ljava/lang/Class;
      24: invokestatic  #76                 // Method org/apache/dubbo/common/utils/ReflectUtils.defaultReturn:(Ljava/lang/Class;)Ljava/lang/Object;
      27: invokespecial #77                 // Method org/apache/dubbo/rpc/AppResponse."<init>":(Ljava/lang/Object;)V
      30: goto          40
      33: new           #18                 // class org/apache/dubbo/rpc/AppResponse
      36: dup
      37: invokespecial #78                 // Method org/apache/dubbo/rpc/AppResponse."<init>":()V
      40: areturn

  private void lambda$whenCompleteWithContext$0(java.util.function.BiConsumer, org.apache.dubbo.rpc.AppResponse, java.lang.Throwable);
    Code:
       0: aload_0
       1: getfield      #12                 // Field async:Z
       4: ifeq          14
       7: aload_0
       8: getfield      #14                 // Field storedContext:Lorg/apache/dubbo/rpc/RpcContext$RestoreContext;
      11: invokestatic  #79                 // Method org/apache/dubbo/rpc/RpcContext.restoreContext:(Lorg/apache/dubbo/rpc/RpcContext$RestoreContext;)V
      14: aload_1
      15: aload_2
      16: aload_3
      17: invokeinterface #80,  3           // InterfaceMethod java/util/function/BiConsumer.accept:(Ljava/lang/Object;Ljava/lang/Object;)V
      22: return

  static {};
    Code:
       0: ldc           #65                 // class org/apache/dubbo/rpc/AsyncRpcResult
       2: invokestatic  #81                 // Method org/apache/dubbo/common/logger/LoggerFactory.getErrorTypeAwareLogger:(Ljava/lang/Class;)Lorg/apache/dubbo/common/logger/ErrorTypeAwareLogger;
       5: putstatic     #23                 // Field logger:Lorg/apache/dubbo/common/logger/ErrorTypeAwareLogger;
       8: ldc           #82                 // String future.sync.set
      10: ldc           #83                 // String true
      12: invokestatic  #84                 // Method java/lang/System.getProperty:(Ljava/lang/String;Ljava/lang/String;)Ljava/lang/String;
      15: invokestatic  #85                 // Method java/lang/Boolean.parseBoolean:(Ljava/lang/String;)Z
      18: putstatic     #47                 // Field setFutureWhenSync:Z
      21: return
}
