Compiled from "AttachmentsAdapter.java"
public class org.apache.dubbo.rpc.AttachmentsAdapter$ObjectToStringMap extends java.util.HashMap<java.lang.String, java.lang.String> {
  private final java.util.Map<java.lang.String, java.lang.Object> attachments;

  public org.apache.dubbo.rpc.AttachmentsAdapter$ObjectToStringMap(java.util.Map<java.lang.String, java.lang.Object>);
    Code:
       0: aload_0
       1: invokespecial #1                  // Method java/util/HashMap."<init>":()V
       4: aload_1
       5: invokeinterface #2,  1            // InterfaceMethod java/util/Map.entrySet:()Ljava/util/Set;
      10: invokeinterface #3,  1            // InterfaceMethod java/util/Set.iterator:()Ljava/util/Iterator;
      15: astore_2
      16: aload_2
      17: invokeinterface #4,  1            // InterfaceMethod java/util/Iterator.hasNext:()Z
      22: ifeq          68
      25: aload_2
      26: invokeinterface #5,  1            // InterfaceMethod java/util/Iterator.next:()Ljava/lang/Object;
      31: checkcast     #6                  // class java/util/Map$Entry
      34: astore_3
      35: aload_0
      36: aload_3
      37: invokeinterface #7,  1            // InterfaceMethod java/util/Map$Entry.getValue:()Ljava/lang/Object;
      42: invokespecial #8                  // Method convert:(Ljava/lang/Object;)Ljava/lang/String;
      45: astore        4
      47: aload         4
      49: ifnull        65
      52: aload_0
      53: aload_3
      54: invokeinterface #9,  1            // InterfaceMethod java/util/Map$Entry.getKey:()Ljava/lang/Object;
      59: aload         4
      61: invokespecial #10                 // Method java/util/HashMap.put:(Ljava/lang/Object;Ljava/lang/Object;)Ljava/lang/Object;
      64: pop
      65: goto          16
      68: aload_0
      69: aload_1
      70: putfield      #11                 // Field attachments:Ljava/util/Map;
      73: return

  public java.lang.String put(java.lang.String, java.lang.String);
    Code:
       0: aload_0
       1: getfield      #11                 // Field attachments:Ljava/util/Map;
       4: aload_1
       5: aload_2
       6: invokeinterface #12,  3           // InterfaceMethod java/util/Map.put:(Ljava/lang/Object;Ljava/lang/Object;)Ljava/lang/Object;
      11: pop
      12: aload_0
      13: aload_1
      14: aload_2
      15: invokespecial #10                 // Method java/util/HashMap.put:(Ljava/lang/Object;Ljava/lang/Object;)Ljava/lang/Object;
      18: checkcast     #13                 // class java/lang/String
      21: areturn

  public java.lang.String remove(java.lang.Object);
    Code:
       0: aload_0
       1: getfield      #11                 // Field attachments:Ljava/util/Map;
       4: aload_1
       5: invokeinterface #14,  2           // InterfaceMethod java/util/Map.remove:(Ljava/lang/Object;)Ljava/lang/Object;
      10: pop
      11: aload_0
      12: aload_1
      13: invokespecial #15                 // Method java/util/HashMap.remove:(Ljava/lang/Object;)Ljava/lang/Object;
      16: checkcast     #13                 // class java/lang/String
      19: areturn

  private java.lang.String convert(java.lang.Object);
    Code:
       0: aload_1
       1: instanceof    #13                 // class java/lang/String
       4: ifeq          12
       7: aload_1
       8: checkcast     #13                 // class java/lang/String
      11: areturn
      12: aconst_null
      13: areturn

  public void clear();
    Code:
       0: aload_0
       1: getfield      #11                 // Field attachments:Ljava/util/Map;
       4: invokeinterface #16,  1           // InterfaceMethod java/util/Map.clear:()V
       9: aload_0
      10: invokespecial #17                 // Method java/util/HashMap.clear:()V
      13: return

  public void putAll(java.util.Map<? extends java.lang.String, ? extends java.lang.String>);
    Code:
       0: aload_0
       1: getfield      #11                 // Field attachments:Ljava/util/Map;
       4: aload_1
       5: invokeinterface #18,  2           // InterfaceMethod java/util/Map.putAll:(Ljava/util/Map;)V
      10: aload_0
      11: aload_1
      12: invokespecial #19                 // Method java/util/HashMap.putAll:(Ljava/util/Map;)V
      15: return

  public java.lang.Object remove(java.lang.Object);
    Code:
       0: aload_0
       1: aload_1
       2: invokevirtual #20                 // Method remove:(Ljava/lang/Object;)Ljava/lang/String;
       5: areturn

  public java.lang.Object put(java.lang.Object, java.lang.Object);
    Code:
       0: aload_0
       1: aload_1
       2: checkcast     #13                 // class java/lang/String
       5: aload_2
       6: checkcast     #13                 // class java/lang/String
       9: invokevirtual #21                 // Method put:(Ljava/lang/String;Ljava/lang/String;)Ljava/lang/String;
      12: areturn
}
