Compiled from "CancellationContext.java"
public class org.apache.dubbo.rpc.CancellationContext implements java.io.Closeable {
  private volatile java.util.ArrayList<org.apache.dubbo.rpc.ExecutableListener> listeners;

  private java.lang.Throwable cancellationCause;

  private boolean cancelled;

  public org.apache.dubbo.rpc.CancellationContext();
    Code:
       0: aload_0
       1: invokespecial #1                  // Method java/lang/Object."<init>":()V
       4: return

  public void addListener(org.apache.dubbo.rpc.CancellationListener, java.util.concurrent.Executor);
    Code:
       0: aload_0
       1: aload_1
       2: aload_2
       3: aconst_null
       4: invokevirtual #2                  // Method addListener:(Lorg/apache/dubbo/rpc/CancellationListener;Ljava/util/concurrent/Executor;Lorg/apache/dubbo/rpc/RpcServiceContext;)V
       7: return

  public void addListener(org.apache.dubbo.rpc.CancellationListener);
    Code:
       0: aload_0
       1: aload_1
       2: invokedynamic #3,  0              // InvokeDynamic #0:execute:()Ljava/util/concurrent/Executor;
       7: aconst_null
       8: invokevirtual #2                  // Method addListener:(Lorg/apache/dubbo/rpc/CancellationListener;Ljava/util/concurrent/Executor;Lorg/apache/dubbo/rpc/RpcServiceContext;)V
      11: return

  public void addListener(org.apache.dubbo.rpc.CancellationListener, org.apache.dubbo.rpc.RpcServiceContext);
    Code:
       0: aload_0
       1: aload_1
       2: invokedynamic #3,  0              // InvokeDynamic #0:execute:()Ljava/util/concurrent/Executor;
       7: aload_2
       8: invokevirtual #2                  // Method addListener:(Lorg/apache/dubbo/rpc/CancellationListener;Ljava/util/concurrent/Executor;Lorg/apache/dubbo/rpc/RpcServiceContext;)V
      11: return

  public void addListener(org.apache.dubbo.rpc.CancellationListener, java.util.concurrent.Executor, org.apache.dubbo.rpc.RpcServiceContext);
    Code:
       0: aload_0
       1: new           #4                  // class org/apache/dubbo/rpc/ExecutableListener
       4: dup
       5: aload_2
       6: aload_1
       7: aload_3
       8: invokespecial #5                  // Method org/apache/dubbo/rpc/ExecutableListener."<init>":(Ljava/util/concurrent/Executor;Lorg/apache/dubbo/rpc/CancellationListener;Lorg/apache/dubbo/rpc/RpcServiceContext;)V
      11: invokevirtual #6                  // Method addListenerInternal:(Lorg/apache/dubbo/rpc/ExecutableListener;)V
      14: return

  public synchronized void addListenerInternal(org.apache.dubbo.rpc.ExecutableListener);
    Code:
       0: aload_0
       1: invokevirtual #7                  // Method isCancelled:()Z
       4: ifeq          14
       7: aload_1
       8: invokevirtual #8                  // Method org/apache/dubbo/rpc/ExecutableListener.deliver:()V
      11: goto          41
      14: aload_0
      15: getfield      #9                  // Field listeners:Ljava/util/ArrayList;
      18: ifnonnull     32
      21: aload_0
      22: new           #10                 // class java/util/ArrayList
      25: dup
      26: invokespecial #11                 // Method java/util/ArrayList."<init>":()V
      29: putfield      #9                  // Field listeners:Ljava/util/ArrayList;
      32: aload_0
      33: getfield      #9                  // Field listeners:Ljava/util/ArrayList;
      36: aload_1
      37: invokevirtual #12                 // Method java/util/ArrayList.add:(Ljava/lang/Object;)Z
      40: pop
      41: return

  public boolean cancel(java.lang.Throwable);
    Code:
       0: iconst_0
       1: istore_2
       2: aload_0
       3: dup
       4: astore_3
       5: monitorenter
       6: aload_0
       7: getfield      #13                 // Field cancelled:Z
      10: ifne          25
      13: aload_0
      14: iconst_1
      15: putfield      #13                 // Field cancelled:Z
      18: aload_0
      19: aload_1
      20: putfield      #14                 // Field cancellationCause:Ljava/lang/Throwable;
      23: iconst_1
      24: istore_2
      25: aload_3
      26: monitorexit
      27: goto          37
      30: astore        4
      32: aload_3
      33: monitorexit
      34: aload         4
      36: athrow
      37: iload_2
      38: ifeq          45
      41: aload_0
      42: invokespecial #15                 // Method notifyAndClearListeners:()V
      45: iload_2
      46: ireturn
    Exception table:
       from    to  target type
           6    27    30   any
          30    34    30   any

  private void notifyAndClearListeners();
    Code:
       0: aload_0
       1: dup
       2: astore_2
       3: monitorenter
       4: aload_0
       5: getfield      #9                  // Field listeners:Ljava/util/ArrayList;
       8: ifnonnull     14
      11: aload_2
      12: monitorexit
      13: return
      14: aload_0
      15: getfield      #9                  // Field listeners:Ljava/util/ArrayList;
      18: astore_1
      19: aload_0
      20: aconst_null
      21: putfield      #9                  // Field listeners:Ljava/util/ArrayList;
      24: aload_2
      25: monitorexit
      26: goto          34
      29: astore_3
      30: aload_2
      31: monitorexit
      32: aload_3
      33: athrow
      34: aload_1
      35: invokevirtual #16                 // Method java/util/ArrayList.iterator:()Ljava/util/Iterator;
      38: astore_2
      39: aload_2
      40: invokeinterface #17,  1           // InterfaceMethod java/util/Iterator.hasNext:()Z
      45: ifeq          65
      48: aload_2
      49: invokeinterface #18,  1           // InterfaceMethod java/util/Iterator.next:()Ljava/lang/Object;
      54: checkcast     #4                  // class org/apache/dubbo/rpc/ExecutableListener
      57: astore_3
      58: aload_3
      59: invokevirtual #8                  // Method org/apache/dubbo/rpc/ExecutableListener.deliver:()V
      62: goto          39
      65: return
    Exception table:
       from    to  target type
           4    13    29   any
          14    26    29   any
          29    32    29   any

  public synchronized boolean isCancelled();
    Code:
       0: aload_0
       1: getfield      #13                 // Field cancelled:Z
       4: ireturn

  public java.util.List<org.apache.dubbo.rpc.ExecutableListener> getListeners();
    Code:
       0: aload_0
       1: getfield      #9                  // Field listeners:Ljava/util/ArrayList;
       4: areturn

  public java.lang.Throwable getCancellationCause();
    Code:
       0: aload_0
       1: getfield      #14                 // Field cancellationCause:Ljava/lang/Throwable;
       4: areturn

  public void close() throws java.io.IOException;
    Code:
       0: aload_0
       1: aconst_null
       2: invokevirtual #19                 // Method cancel:(Ljava/lang/Throwable;)Z
       5: pop
       6: return
}
