Compiled from "ExecutableListener.java"
public class org.apache.dubbo.rpc.ExecutableListener implements java.lang.Runnable {
  private static final org.apache.dubbo.common.logger.ErrorTypeAwareLogger log;

  private final java.util.concurrent.Executor executor;

  private final org.apache.dubbo.rpc.CancellationListener listener;

  private final org.apache.dubbo.rpc.RpcServiceContext context;

  public org.apache.dubbo.rpc.ExecutableListener(java.util.concurrent.Executor, org.apache.dubbo.rpc.CancellationListener, org.apache.dubbo.rpc.RpcServiceContext);
    Code:
       0: aload_0
       1: invokespecial #2                  // Method java/lang/Object."<init>":()V
       4: aload_0
       5: aload_1
       6: putfield      #3                  // Field executor:Ljava/util/concurrent/Executor;
       9: aload_0
      10: aload_2
      11: putfield      #4                  // Field listener:Lorg/apache/dubbo/rpc/CancellationListener;
      14: aload_0
      15: aload_3
      16: putfield      #5                  // Field context:Lorg/apache/dubbo/rpc/RpcServiceContext;
      19: return

  public org.apache.dubbo.rpc.ExecutableListener(java.util.concurrent.Executor, org.apache.dubbo.rpc.CancellationListener);
    Code:
       0: aload_0
       1: aload_1
       2: aload_2
       3: aconst_null
       4: invokespecial #6                  // Method "<init>":(Ljava/util/concurrent/Executor;Lorg/apache/dubbo/rpc/CancellationListener;Lorg/apache/dubbo/rpc/RpcServiceContext;)V
       7: return

  public void deliver();
    Code:
       0: aload_0
       1: getfield      #3                  // Field executor:Ljava/util/concurrent/Executor;
       4: aload_0
       5: invokeinterface #7,  2            // InterfaceMethod java/util/concurrent/Executor.execute:(Ljava/lang/Runnable;)V
      10: goto          31
      13: astore_1
      14: getstatic     #9                  // Field log:Lorg/apache/dubbo/common/logger/ErrorTypeAwareLogger;
      17: ldc           #10                 // String 0-9
      19: ldc           #11                 // String
      21: ldc           #11                 // String
      23: ldc           #12                 // String Exception notifying context listener
      25: aload_1
      26: invokeinterface #13,  6           // InterfaceMethod org/apache/dubbo/common/logger/ErrorTypeAwareLogger.warn:(Ljava/lang/String;Ljava/lang/String;Ljava/lang/String;Ljava/lang/String;Ljava/lang/Throwable;)V
      31: return
    Exception table:
       from    to  target type
           0    10    13   Class java/lang/Throwable

  public java.util.concurrent.Executor getExecutor();
    Code:
       0: aload_0
       1: getfield      #3                  // Field executor:Ljava/util/concurrent/Executor;
       4: areturn

  public org.apache.dubbo.rpc.CancellationListener getListener();
    Code:
       0: aload_0
       1: getfield      #4                  // Field listener:Lorg/apache/dubbo/rpc/CancellationListener;
       4: areturn

  public org.apache.dubbo.rpc.RpcServiceContext getContext();
    Code:
       0: aload_0
       1: getfield      #5                  // Field context:Lorg/apache/dubbo/rpc/RpcServiceContext;
       4: areturn

  public void run();
    Code:
       0: aload_0
       1: getfield      #4                  // Field listener:Lorg/apache/dubbo/rpc/CancellationListener;
       4: aload_0
       5: getfield      #5                  // Field context:Lorg/apache/dubbo/rpc/RpcServiceContext;
       8: invokeinterface #14,  2           // InterfaceMethod org/apache/dubbo/rpc/CancellationListener.cancelled:(Lorg/apache/dubbo/rpc/RpcServiceContext;)V
      13: return

  static {};
    Code:
       0: ldc           #15                 // class org/apache/dubbo/rpc/ExecutableListener
       2: invokestatic  #16                 // Method org/apache/dubbo/common/logger/LoggerFactory.getErrorTypeAwareLogger:(Ljava/lang/Class;)Lorg/apache/dubbo/common/logger/ErrorTypeAwareLogger;
       5: putstatic     #9                  // Field log:Lorg/apache/dubbo/common/logger/ErrorTypeAwareLogger;
       8: return
}
