Compiled from "FutureContext.java"
public class org.apache.dubbo.rpc.FutureContext {
  private static final org.apache.dubbo.common.threadlocal.InternalThreadLocal<org.apache.dubbo.rpc.FutureContext> futureTL;

  private java.util.concurrent.CompletableFuture<?> future;

  private java.util.concurrent.CompletableFuture<?> compatibleFuture;

  private static final boolean clearFutureAfterGet;

  public org.apache.dubbo.rpc.FutureContext();
    Code:
       0: aload_0
       1: invokespecial #1                  // Method java/lang/Object."<init>":()V
       4: return

  public static org.apache.dubbo.rpc.FutureContext getContext();
    Code:
       0: getstatic     #2                  // Field futureTL:Lorg/apache/dubbo/common/threadlocal/InternalThreadLocal;
       3: invokevirtual #3                  // Method org/apache/dubbo/common/threadlocal/InternalThreadLocal.get:()Ljava/lang/Object;
       6: checkcast     #4                  // class org/apache/dubbo/rpc/FutureContext
       9: areturn

  public <T> java.util.concurrent.CompletableFuture<T> getCompletableFuture();
    Code:
       0: aload_0
       1: getfield      #5                  // Field future:Ljava/util/concurrent/CompletableFuture;
       4: astore_1
       5: getstatic     #6                  // Field clearFutureAfterGet:Z
       8: ifeq          16
      11: aload_0
      12: aconst_null
      13: putfield      #5                  // Field future:Ljava/util/concurrent/CompletableFuture;
      16: aload_1
      17: areturn
      18: astore_2
      19: getstatic     #6                  // Field clearFutureAfterGet:Z
      22: ifeq          30
      25: aload_0
      26: aconst_null
      27: putfield      #5                  // Field future:Ljava/util/concurrent/CompletableFuture;
      30: aload_2
      31: athrow
    Exception table:
       from    to  target type
           0     5    18   any

  public void setFuture(java.util.concurrent.CompletableFuture<?>);
    Code:
       0: aload_0
       1: aload_1
       2: putfield      #5                  // Field future:Ljava/util/concurrent/CompletableFuture;
       5: return

  public <T> java.util.concurrent.CompletableFuture<T> getCompatibleCompletableFuture();
    Code:
       0: aload_0
       1: getfield      #7                  // Field compatibleFuture:Ljava/util/concurrent/CompletableFuture;
       4: astore_1
       5: getstatic     #6                  // Field clearFutureAfterGet:Z
       8: ifeq          16
      11: aload_0
      12: aconst_null
      13: putfield      #7                  // Field compatibleFuture:Ljava/util/concurrent/CompletableFuture;
      16: aload_1
      17: areturn
      18: astore_2
      19: getstatic     #6                  // Field clearFutureAfterGet:Z
      22: ifeq          30
      25: aload_0
      26: aconst_null
      27: putfield      #7                  // Field compatibleFuture:Ljava/util/concurrent/CompletableFuture;
      30: aload_2
      31: athrow
    Exception table:
       from    to  target type
           0     5    18   any

  public void setCompatibleFuture(java.util.concurrent.CompletableFuture<?>);
    Code:
       0: aload_0
       1: aload_1
       2: putfield      #7                  // Field compatibleFuture:Ljava/util/concurrent/CompletableFuture;
       5: aload_1
       6: ifnull        21
       9: aload_0
      10: new           #8                  // class org/apache/dubbo/rpc/protocol/dubbo/FutureAdapter
      13: dup
      14: aload_1
      15: invokespecial #9                  // Method org/apache/dubbo/rpc/protocol/dubbo/FutureAdapter."<init>":(Ljava/util/concurrent/CompletableFuture;)V
      18: invokevirtual #10                 // Method setFuture:(Ljava/util/concurrent/CompletableFuture;)V
      21: return

  static {};
    Code:
       0: new           #11                 // class org/apache/dubbo/rpc/FutureContext$1
       3: dup
       4: invokespecial #12                 // Method org/apache/dubbo/rpc/FutureContext$1."<init>":()V
       7: putstatic     #2                  // Field futureTL:Lorg/apache/dubbo/common/threadlocal/InternalThreadLocal;
      10: ldc           #14                 // String future.clear.once
      12: ldc           #15                 // String false
      14: invokestatic  #16                 // Method java/lang/System.getProperty:(Ljava/lang/String;Ljava/lang/String;)Ljava/lang/String;
      17: invokestatic  #17                 // Method java/lang/Boolean.parseBoolean:(Ljava/lang/String;)Z
      20: putstatic     #6                  // Field clearFutureAfterGet:Z
      23: return
}
