Compiled from "InvokeMode.java"
public final class org.apache.dubbo.rpc.InvokeMode extends java.lang.Enum<org.apache.dubbo.rpc.InvokeMode> {
  public static final org.apache.dubbo.rpc.InvokeMode SYNC;

  public static final org.apache.dubbo.rpc.InvokeMode ASYNC;

  public static final org.apache.dubbo.rpc.InvokeMode FUTURE;

  private static final org.apache.dubbo.rpc.InvokeMode[] $VALUES;

  public static org.apache.dubbo.rpc.InvokeMode[] values();
    Code:
       0: getstatic     #1                  // Field $VALUES:[Lorg/apache/dubbo/rpc/InvokeMode;
       3: invokevirtual #2                  // Method "[Lorg/apache/dubbo/rpc/InvokeMode;".clone:()Ljava/lang/Object;
       6: checkcast     #3                  // class "[Lorg/apache/dubbo/rpc/InvokeMode;"
       9: areturn

  public static org.apache.dubbo.rpc.InvokeMode valueOf(java.lang.String);
    Code:
       0: ldc           #4                  // class org/apache/dubbo/rpc/InvokeMode
       2: aload_0
       3: invokestatic  #5                  // Method java/lang/Enum.valueOf:(Ljava/lang/Class;Ljava/lang/String;)Ljava/lang/Enum;
       6: checkcast     #4                  // class org/apache/dubbo/rpc/InvokeMode
       9: areturn

  private org.apache.dubbo.rpc.InvokeMode();
    Code:
       0: aload_0
       1: aload_1
       2: iload_2
       3: invokespecial #6                  // Method java/lang/Enum."<init>":(Ljava/lang/String;I)V
       6: return

  static {};
    Code:
       0: new           #4                  // class org/apache/dubbo/rpc/InvokeMode
       3: dup
       4: ldc           #7                  // String SYNC
       6: iconst_0
       7: invokespecial #8                  // Method "<init>":(Ljava/lang/String;I)V
      10: putstatic     #9                  // Field SYNC:Lorg/apache/dubbo/rpc/InvokeMode;
      13: new           #4                  // class org/apache/dubbo/rpc/InvokeMode
      16: dup
      17: ldc           #10                 // String ASYNC
      19: iconst_1
      20: invokespecial #8                  // Method "<init>":(Ljava/lang/String;I)V
      23: putstatic     #11                 // Field ASYNC:Lorg/apache/dubbo/rpc/InvokeMode;
      26: new           #4                  // class org/apache/dubbo/rpc/InvokeMode
      29: dup
      30: ldc           #12                 // String FUTURE
      32: iconst_2
      33: invokespecial #8                  // Method "<init>":(Ljava/lang/String;I)V
      36: putstatic     #13                 // Field FUTURE:Lorg/apache/dubbo/rpc/InvokeMode;
      39: iconst_3
      40: anewarray     #4                  // class org/apache/dubbo/rpc/InvokeMode
      43: dup
      44: iconst_0
      45: getstatic     #9                  // Field SYNC:Lorg/apache/dubbo/rpc/InvokeMode;
      48: aastore
      49: dup
      50: iconst_1
      51: getstatic     #11                 // Field ASYNC:Lorg/apache/dubbo/rpc/InvokeMode;
      54: aastore
      55: dup
      56: iconst_2
      57: getstatic     #13                 // Field FUTURE:Lorg/apache/dubbo/rpc/InvokeMode;
      60: aastore
      61: putstatic     #1                  // Field $VALUES:[Lorg/apache/dubbo/rpc/InvokeMode;
      64: return
}
