Compiled from "InvocationProfilerUtils.java"
public class org.apache.dubbo.rpc.InvocationProfilerUtils {
  public org.apache.dubbo.rpc.InvocationProfilerUtils();
    Code:
       0: aload_0
       1: invokespecial #1                  // Method java/lang/Object."<init>":()V
       4: return

  public static void enterSimpleProfiler(org.apache.dubbo.rpc.Invocation, java.util.concurrent.Callable<java.lang.String>);
    Code:
       0: invokestatic  #2                  // Method org/apache/dubbo/common/profiler/ProfilerSwitch.isEnableSimpleProfiler:()Z
       3: ifeq          11
       6: aload_0
       7: aload_1
       8: invokestatic  #3                  // Method enterProfiler:(Lorg/apache/dubbo/rpc/Invocation;Ljava/util/concurrent/Callable;)V
      11: return

  public static void releaseSimpleProfiler(org.apache.dubbo.rpc.Invocation);
    Code:
       0: invokestatic  #2                  // Method org/apache/dubbo/common/profiler/ProfilerSwitch.isEnableSimpleProfiler:()Z
       3: ifeq          10
       6: aload_0
       7: invokestatic  #4                  // Method releaseProfiler:(Lorg/apache/dubbo/rpc/Invocation;)V
      10: return

  public static void enterDetailProfiler(org.apache.dubbo.rpc.Invocation, java.util.concurrent.Callable<java.lang.String>);
    Code:
       0: invokestatic  #5                  // Method org/apache/dubbo/common/profiler/ProfilerSwitch.isEnableDetailProfiler:()Z
       3: ifeq          11
       6: aload_0
       7: aload_1
       8: invokestatic  #3                  // Method enterProfiler:(Lorg/apache/dubbo/rpc/Invocation;Ljava/util/concurrent/Callable;)V
      11: return

  public static void releaseDetailProfiler(org.apache.dubbo.rpc.Invocation);
    Code:
       0: invokestatic  #5                  // Method org/apache/dubbo/common/profiler/ProfilerSwitch.isEnableDetailProfiler:()Z
       3: ifeq          10
       6: aload_0
       7: invokestatic  #4                  // Method releaseProfiler:(Lorg/apache/dubbo/rpc/Invocation;)V
      10: return

  public static void enterProfiler(org.apache.dubbo.rpc.Invocation, java.lang.String);
    Code:
       0: aload_0
       1: ldc           #7                  // String DUBBO_INVOKE_PROFILER
       3: invokeinterface #8,  2            // InterfaceMethod org/apache/dubbo/rpc/Invocation.get:(Ljava/lang/Object;)Ljava/lang/Object;
       8: astore_2
       9: aload_2
      10: instanceof    #9                  // class org/apache/dubbo/common/profiler/ProfilerEntry
      13: ifeq          33
      16: aload_0
      17: ldc           #7                  // String DUBBO_INVOKE_PROFILER
      19: aload_2
      20: checkcast     #9                  // class org/apache/dubbo/common/profiler/ProfilerEntry
      23: aload_1
      24: invokestatic  #10                 // Method org/apache/dubbo/common/profiler/Profiler.enter:(Lorg/apache/dubbo/common/profiler/ProfilerEntry;Ljava/lang/String;)Lorg/apache/dubbo/common/profiler/ProfilerEntry;
      27: invokeinterface #11,  3           // InterfaceMethod org/apache/dubbo/rpc/Invocation.put:(Ljava/lang/Object;Ljava/lang/Object;)Ljava/lang/Object;
      32: pop
      33: return

  public static void enterProfiler(org.apache.dubbo.rpc.Invocation, java.util.concurrent.Callable<java.lang.String>);
    Code:
       0: aload_0
       1: ldc           #7                  // String DUBBO_INVOKE_PROFILER
       3: invokeinterface #8,  2            // InterfaceMethod org/apache/dubbo/rpc/Invocation.get:(Ljava/lang/Object;)Ljava/lang/Object;
       8: astore_2
       9: aload_2
      10: instanceof    #9                  // class org/apache/dubbo/common/profiler/ProfilerEntry
      13: ifeq          51
      16: ldc           #12                 // String
      18: astore_3
      19: aload_1
      20: invokeinterface #13,  1           // InterfaceMethod java/util/concurrent/Callable.call:()Ljava/lang/Object;
      25: checkcast     #14                 // class java/lang/String
      28: astore_3
      29: goto          34
      32: astore        4
      34: aload_0
      35: ldc           #7                  // String DUBBO_INVOKE_PROFILER
      37: aload_2
      38: checkcast     #9                  // class org/apache/dubbo/common/profiler/ProfilerEntry
      41: aload_3
      42: invokestatic  #10                 // Method org/apache/dubbo/common/profiler/Profiler.enter:(Lorg/apache/dubbo/common/profiler/ProfilerEntry;Ljava/lang/String;)Lorg/apache/dubbo/common/profiler/ProfilerEntry;
      45: invokeinterface #11,  3           // InterfaceMethod org/apache/dubbo/rpc/Invocation.put:(Ljava/lang/Object;Ljava/lang/Object;)Ljava/lang/Object;
      50: pop
      51: return
    Exception table:
       from    to  target type
          19    29    32   Class java/lang/Exception

  public static void releaseProfiler(org.apache.dubbo.rpc.Invocation);
    Code:
       0: aload_0
       1: ldc           #7                  // String DUBBO_INVOKE_PROFILER
       3: invokeinterface #8,  2            // InterfaceMethod org/apache/dubbo/rpc/Invocation.get:(Ljava/lang/Object;)Ljava/lang/Object;
       8: astore_1
       9: aload_1
      10: instanceof    #9                  // class org/apache/dubbo/common/profiler/ProfilerEntry
      13: ifeq          32
      16: aload_0
      17: ldc           #7                  // String DUBBO_INVOKE_PROFILER
      19: aload_1
      20: checkcast     #9                  // class org/apache/dubbo/common/profiler/ProfilerEntry
      23: invokestatic  #16                 // Method org/apache/dubbo/common/profiler/Profiler.release:(Lorg/apache/dubbo/common/profiler/ProfilerEntry;)Lorg/apache/dubbo/common/profiler/ProfilerEntry;
      26: invokeinterface #11,  3           // InterfaceMethod org/apache/dubbo/rpc/Invocation.put:(Ljava/lang/Object;Ljava/lang/Object;)Ljava/lang/Object;
      31: pop
      32: return
}
