Compiled from "ListenableFilter.java"
public abstract class org.apache.dubbo.rpc.ListenableFilter implements org.apache.dubbo.rpc.Filter {
  protected org.apache.dubbo.rpc.BaseFilter$Listener listener;

  protected final java.util.concurrent.ConcurrentMap<org.apache.dubbo.rpc.Invocation, org.apache.dubbo.rpc.BaseFilter$Listener> listeners;

  public org.apache.dubbo.rpc.ListenableFilter();
    Code:
       0: aload_0
       1: invokespecial #1                  // Method java/lang/Object."<init>":()V
       4: aload_0
       5: aconst_null
       6: putfield      #2                  // Field listener:Lorg/apache/dubbo/rpc/BaseFilter$Listener;
       9: aload_0
      10: new           #3                  // class java/util/concurrent/ConcurrentHashMap
      13: dup
      14: invokespecial #4                  // Method java/util/concurrent/ConcurrentHashMap."<init>":()V
      17: putfield      #5                  // Field listeners:Ljava/util/concurrent/ConcurrentMap;
      20: return

  public org.apache.dubbo.rpc.BaseFilter$Listener listener();
    Code:
       0: aload_0
       1: getfield      #2                  // Field listener:Lorg/apache/dubbo/rpc/BaseFilter$Listener;
       4: areturn

  public org.apache.dubbo.rpc.BaseFilter$Listener listener(org.apache.dubbo.rpc.Invocation);
    Code:
       0: aload_0
       1: getfield      #5                  // Field listeners:Ljava/util/concurrent/ConcurrentMap;
       4: aload_1
       5: invokeinterface #6,  2            // InterfaceMethod java/util/concurrent/ConcurrentMap.get:(Ljava/lang/Object;)Ljava/lang/Object;
      10: checkcast     #7                  // class org/apache/dubbo/rpc/BaseFilter$Listener
      13: astore_2
      14: aload_2
      15: ifnonnull     23
      18: aload_0
      19: getfield      #2                  // Field listener:Lorg/apache/dubbo/rpc/BaseFilter$Listener;
      22: astore_2
      23: aload_2
      24: areturn

  public void addListener(org.apache.dubbo.rpc.Invocation, org.apache.dubbo.rpc.BaseFilter$Listener);
    Code:
       0: aload_0
       1: getfield      #5                  // Field listeners:Ljava/util/concurrent/ConcurrentMap;
       4: aload_1
       5: aload_2
       6: invokeinterface #8,  3            // InterfaceMethod java/util/concurrent/ConcurrentMap.putIfAbsent:(Ljava/lang/Object;Ljava/lang/Object;)Ljava/lang/Object;
      11: pop
      12: return

  public void removeListener(org.apache.dubbo.rpc.Invocation);
    Code:
       0: aload_0
       1: getfield      #5                  // Field listeners:Ljava/util/concurrent/ConcurrentMap;
       4: aload_1
       5: invokeinterface #9,  2            // InterfaceMethod java/util/concurrent/ConcurrentMap.remove:(Ljava/lang/Object;)Ljava/lang/Object;
      10: pop
      11: return
}
