Compiled from "RpcContext.java"
public class org.apache.dubbo.rpc.RpcContext$RestoreContext {
  private final org.apache.dubbo.rpc.RpcServiceContext serviceContext;

  private final org.apache.dubbo.rpc.RpcContextAttachment clientAttachment;

  private final org.apache.dubbo.rpc.RpcContextAttachment serverAttachment;

  private final org.apache.dubbo.rpc.RpcContextAttachment clientResponseLocal;

  private final org.apache.dubbo.rpc.RpcContextAttachment serverResponseLocal;

  public org.apache.dubbo.rpc.RpcContext$RestoreContext();
    Code:
       0: aload_0
       1: invokespecial #1                  // Method java/lang/Object."<init>":()V
       4: aload_0
       5: invokestatic  #2                  // Method org/apache/dubbo/rpc/RpcContext.getServiceContext:()Lorg/apache/dubbo/rpc/RpcServiceContext;
       8: iconst_0
       9: invokevirtual #3                  // Method org/apache/dubbo/rpc/RpcServiceContext.copyOf:(Z)Lorg/apache/dubbo/rpc/RpcServiceContext;
      12: putfield      #4                  // Field serviceContext:Lorg/apache/dubbo/rpc/RpcServiceContext;
      15: aload_0
      16: invokestatic  #5                  // Method org/apache/dubbo/rpc/RpcContext.getClientAttachment:()Lorg/apache/dubbo/rpc/RpcContextAttachment;
      19: iconst_0
      20: invokevirtual #6                  // Method org/apache/dubbo/rpc/RpcContextAttachment.copyOf:(Z)Lorg/apache/dubbo/rpc/RpcContextAttachment;
      23: putfield      #7                  // Field clientAttachment:Lorg/apache/dubbo/rpc/RpcContextAttachment;
      26: aload_0
      27: invokestatic  #8                  // Method org/apache/dubbo/rpc/RpcContext.getServerAttachment:()Lorg/apache/dubbo/rpc/RpcContextAttachment;
      30: iconst_0
      31: invokevirtual #6                  // Method org/apache/dubbo/rpc/RpcContextAttachment.copyOf:(Z)Lorg/apache/dubbo/rpc/RpcContextAttachment;
      34: putfield      #9                  // Field serverAttachment:Lorg/apache/dubbo/rpc/RpcContextAttachment;
      37: aload_0
      38: invokestatic  #10                 // Method org/apache/dubbo/rpc/RpcContext.getClientResponseContext:()Lorg/apache/dubbo/rpc/RpcContextAttachment;
      41: iconst_0
      42: invokevirtual #6                  // Method org/apache/dubbo/rpc/RpcContextAttachment.copyOf:(Z)Lorg/apache/dubbo/rpc/RpcContextAttachment;
      45: putfield      #11                 // Field clientResponseLocal:Lorg/apache/dubbo/rpc/RpcContextAttachment;
      48: aload_0
      49: invokestatic  #12                 // Method org/apache/dubbo/rpc/RpcContext.getServerResponseContext:()Lorg/apache/dubbo/rpc/RpcContextAttachment;
      52: iconst_0
      53: invokevirtual #6                  // Method org/apache/dubbo/rpc/RpcContextAttachment.copyOf:(Z)Lorg/apache/dubbo/rpc/RpcContextAttachment;
      56: putfield      #13                 // Field serverResponseLocal:Lorg/apache/dubbo/rpc/RpcContextAttachment;
      59: return

  public void restore();
    Code:
       0: aload_0
       1: getfield      #4                  // Field serviceContext:Lorg/apache/dubbo/rpc/RpcServiceContext;
       4: ifnull        20
       7: invokestatic  #14                 // Method org/apache/dubbo/rpc/RpcContext.access$000:()Lorg/apache/dubbo/common/threadlocal/InternalThreadLocal;
      10: aload_0
      11: getfield      #4                  // Field serviceContext:Lorg/apache/dubbo/rpc/RpcServiceContext;
      14: invokevirtual #15                 // Method org/apache/dubbo/common/threadlocal/InternalThreadLocal.set:(Ljava/lang/Object;)V
      17: goto          23
      20: invokestatic  #16                 // Method org/apache/dubbo/rpc/RpcContext.removeServiceContext:()V
      23: aload_0
      24: getfield      #7                  // Field clientAttachment:Lorg/apache/dubbo/rpc/RpcContextAttachment;
      27: ifnull        43
      30: invokestatic  #17                 // Method org/apache/dubbo/rpc/RpcContext.access$100:()Lorg/apache/dubbo/common/threadlocal/InternalThreadLocal;
      33: aload_0
      34: getfield      #7                  // Field clientAttachment:Lorg/apache/dubbo/rpc/RpcContextAttachment;
      37: invokevirtual #15                 // Method org/apache/dubbo/common/threadlocal/InternalThreadLocal.set:(Ljava/lang/Object;)V
      40: goto          46
      43: invokestatic  #18                 // Method org/apache/dubbo/rpc/RpcContext.removeClientAttachment:()V
      46: aload_0
      47: getfield      #9                  // Field serverAttachment:Lorg/apache/dubbo/rpc/RpcContextAttachment;
      50: ifnull        66
      53: invokestatic  #19                 // Method org/apache/dubbo/rpc/RpcContext.access$200:()Lorg/apache/dubbo/common/threadlocal/InternalThreadLocal;
      56: aload_0
      57: getfield      #9                  // Field serverAttachment:Lorg/apache/dubbo/rpc/RpcContextAttachment;
      60: invokevirtual #15                 // Method org/apache/dubbo/common/threadlocal/InternalThreadLocal.set:(Ljava/lang/Object;)V
      63: goto          69
      66: invokestatic  #20                 // Method org/apache/dubbo/rpc/RpcContext.removeServerAttachment:()V
      69: aload_0
      70: getfield      #11                 // Field clientResponseLocal:Lorg/apache/dubbo/rpc/RpcContextAttachment;
      73: ifnull        89
      76: invokestatic  #21                 // Method org/apache/dubbo/rpc/RpcContext.access$300:()Lorg/apache/dubbo/common/threadlocal/InternalThreadLocal;
      79: aload_0
      80: getfield      #11                 // Field clientResponseLocal:Lorg/apache/dubbo/rpc/RpcContextAttachment;
      83: invokevirtual #15                 // Method org/apache/dubbo/common/threadlocal/InternalThreadLocal.set:(Ljava/lang/Object;)V
      86: goto          92
      89: invokestatic  #22                 // Method org/apache/dubbo/rpc/RpcContext.removeClientResponseContext:()V
      92: aload_0
      93: getfield      #13                 // Field serverResponseLocal:Lorg/apache/dubbo/rpc/RpcContextAttachment;
      96: ifnull        112
      99: invokestatic  #23                 // Method org/apache/dubbo/rpc/RpcContext.access$400:()Lorg/apache/dubbo/common/threadlocal/InternalThreadLocal;
     102: aload_0
     103: getfield      #13                 // Field serverResponseLocal:Lorg/apache/dubbo/rpc/RpcContextAttachment;
     106: invokevirtual #15                 // Method org/apache/dubbo/common/threadlocal/InternalThreadLocal.set:(Ljava/lang/Object;)V
     109: goto          115
     112: invokestatic  #24                 // Method org/apache/dubbo/rpc/RpcContext.removeServerResponseContext:()V
     115: return
}
