Compiled from "RpcContextAttachment.java"
public class org.apache.dubbo.rpc.RpcContextAttachment extends org.apache.dubbo.rpc.RpcContext {
  protected volatile java.util.Map<java.lang.String, java.lang.Object> attachments;

  protected org.apache.dubbo.rpc.AsyncContext asyncContext;

  protected org.apache.dubbo.rpc.RpcContextAttachment();
    Code:
       0: aload_0
       1: invokespecial #1                  // Method org/apache/dubbo/rpc/RpcContext."<init>":()V
       4: aload_0
       5: new           #2                  // class java/util/HashMap
       8: dup
       9: invokespecial #3                  // Method java/util/HashMap."<init>":()V
      12: putfield      #4                  // Field attachments:Ljava/util/Map;
      15: return

  public static org.apache.dubbo.rpc.AsyncContext startAsync() throws java.lang.IllegalStateException;
    Code:
       0: invokestatic  #5                  // Method getServerAttachment:()Lorg/apache/dubbo/rpc/RpcContextAttachment;
       3: astore_0
       4: aload_0
       5: getfield      #6                  // Field asyncContext:Lorg/apache/dubbo/rpc/AsyncContext;
       8: ifnonnull     22
      11: aload_0
      12: new           #7                  // class org/apache/dubbo/rpc/AsyncContextImpl
      15: dup
      16: invokespecial #8                  // Method org/apache/dubbo/rpc/AsyncContextImpl."<init>":()V
      19: putfield      #6                  // Field asyncContext:Lorg/apache/dubbo/rpc/AsyncContext;
      22: aload_0
      23: getfield      #6                  // Field asyncContext:Lorg/apache/dubbo/rpc/AsyncContext;
      26: invokeinterface #9,  1            // InterfaceMethod org/apache/dubbo/rpc/AsyncContext.start:()V
      31: aload_0
      32: getfield      #6                  // Field asyncContext:Lorg/apache/dubbo/rpc/AsyncContext;
      35: areturn

  protected void setAsyncContext(org.apache.dubbo.rpc.AsyncContext);
    Code:
       0: aload_0
       1: aload_1
       2: putfield      #6                  // Field asyncContext:Lorg/apache/dubbo/rpc/AsyncContext;
       5: return

  public boolean isAsyncStarted();
    Code:
       0: aload_0
       1: getfield      #6                  // Field asyncContext:Lorg/apache/dubbo/rpc/AsyncContext;
       4: ifnonnull     9
       7: iconst_0
       8: ireturn
       9: aload_0
      10: getfield      #6                  // Field asyncContext:Lorg/apache/dubbo/rpc/AsyncContext;
      13: invokeinterface #10,  1           // InterfaceMethod org/apache/dubbo/rpc/AsyncContext.isAsyncStarted:()Z
      18: ireturn

  public boolean stopAsync();
    Code:
       0: aload_0
       1: getfield      #6                  // Field asyncContext:Lorg/apache/dubbo/rpc/AsyncContext;
       4: invokeinterface #11,  1           // InterfaceMethod org/apache/dubbo/rpc/AsyncContext.stop:()Z
       9: ireturn

  public org.apache.dubbo.rpc.AsyncContext getAsyncContext();
    Code:
       0: aload_0
       1: getfield      #6                  // Field asyncContext:Lorg/apache/dubbo/rpc/AsyncContext;
       4: areturn

  public java.lang.String getAttachment(java.lang.String);
    Code:
       0: aload_0
       1: getfield      #4                  // Field attachments:Ljava/util/Map;
       4: aload_1
       5: invokeinterface #12,  2           // InterfaceMethod java/util/Map.get:(Ljava/lang/Object;)Ljava/lang/Object;
      10: astore_2
      11: aload_2
      12: instanceof    #13                 // class java/lang/String
      15: ifeq          23
      18: aload_2
      19: checkcast     #13                 // class java/lang/String
      22: areturn
      23: aconst_null
      24: areturn

  public java.lang.Object getObjectAttachment(java.lang.String);
    Code:
       0: aload_0
       1: getfield      #4                  // Field attachments:Ljava/util/Map;
       4: aload_1
       5: invokeinterface #12,  2           // InterfaceMethod java/util/Map.get:(Ljava/lang/Object;)Ljava/lang/Object;
      10: areturn

  public org.apache.dubbo.rpc.RpcContextAttachment setAttachment(java.lang.String, java.lang.String);
    Code:
       0: aload_0
       1: aload_1
       2: aload_2
       3: invokevirtual #14                 // Method setObjectAttachment:(Ljava/lang/String;Ljava/lang/Object;)Lorg/apache/dubbo/rpc/RpcContextAttachment;
       6: areturn

  public org.apache.dubbo.rpc.RpcContextAttachment setAttachment(java.lang.String, java.lang.Object);
    Code:
       0: aload_0
       1: aload_1
       2: aload_2
       3: invokevirtual #14                 // Method setObjectAttachment:(Ljava/lang/String;Ljava/lang/Object;)Lorg/apache/dubbo/rpc/RpcContextAttachment;
       6: areturn

  public org.apache.dubbo.rpc.RpcContextAttachment setObjectAttachment(java.lang.String, java.lang.Object);
    Code:
       0: aload_2
       1: ifnonnull     18
       4: aload_0
       5: getfield      #4                  // Field attachments:Ljava/util/Map;
       8: aload_1
       9: invokeinterface #15,  2           // InterfaceMethod java/util/Map.remove:(Ljava/lang/Object;)Ljava/lang/Object;
      14: pop
      15: goto          30
      18: aload_0
      19: getfield      #4                  // Field attachments:Ljava/util/Map;
      22: aload_1
      23: aload_2
      24: invokeinterface #16,  3           // InterfaceMethod java/util/Map.put:(Ljava/lang/Object;Ljava/lang/Object;)Ljava/lang/Object;
      29: pop
      30: aload_0
      31: areturn

  public org.apache.dubbo.rpc.RpcContextAttachment removeAttachment(java.lang.String);
    Code:
       0: aload_0
       1: getfield      #4                  // Field attachments:Ljava/util/Map;
       4: aload_1
       5: invokeinterface #15,  2           // InterfaceMethod java/util/Map.remove:(Ljava/lang/Object;)Ljava/lang/Object;
      10: pop
      11: aload_0
      12: areturn

  public java.util.Map<java.lang.String, java.lang.String> getAttachments();
    Code:
       0: new           #17                 // class org/apache/dubbo/rpc/AttachmentsAdapter$ObjectToStringMap
       3: dup
       4: aload_0
       5: invokevirtual #18                 // Method getObjectAttachments:()Ljava/util/Map;
       8: invokespecial #19                 // Method org/apache/dubbo/rpc/AttachmentsAdapter$ObjectToStringMap."<init>":(Ljava/util/Map;)V
      11: areturn

  public java.util.Map<java.lang.String, java.lang.Object> getObjectAttachments();
    Code:
       0: aload_0
       1: getfield      #4                  // Field attachments:Ljava/util/Map;
       4: areturn

  public org.apache.dubbo.rpc.RpcContextAttachment setAttachments(java.util.Map<java.lang.String, java.lang.String>);
    Code:
       0: aload_0
       1: getfield      #4                  // Field attachments:Ljava/util/Map;
       4: invokeinterface #20,  1           // InterfaceMethod java/util/Map.clear:()V
       9: aload_1
      10: ifnull        32
      13: aload_1
      14: invokeinterface #21,  1           // InterfaceMethod java/util/Map.size:()I
      19: ifle          32
      22: aload_0
      23: getfield      #4                  // Field attachments:Ljava/util/Map;
      26: aload_1
      27: invokeinterface #22,  2           // InterfaceMethod java/util/Map.putAll:(Ljava/util/Map;)V
      32: aload_0
      33: areturn

  public org.apache.dubbo.rpc.RpcContextAttachment setObjectAttachments(java.util.Map<java.lang.String, java.lang.Object>);
    Code:
       0: aload_0
       1: getfield      #4                  // Field attachments:Ljava/util/Map;
       4: invokeinterface #20,  1           // InterfaceMethod java/util/Map.clear:()V
       9: aload_1
      10: invokestatic  #23                 // Method org/apache/dubbo/common/utils/CollectionUtils.isNotEmptyMap:(Ljava/util/Map;)Z
      13: ifeq          21
      16: aload_0
      17: aload_1
      18: putfield      #4                  // Field attachments:Ljava/util/Map;
      21: aload_0
      22: areturn

  public void clearAttachments();
    Code:
       0: aload_0
       1: getfield      #4                  // Field attachments:Ljava/util/Map;
       4: invokeinterface #20,  1           // InterfaceMethod java/util/Map.clear:()V
       9: return

  public java.util.Map<java.lang.String, java.lang.Object> get();
    Code:
       0: aload_0
       1: invokevirtual #18                 // Method getObjectAttachments:()Ljava/util/Map;
       4: areturn

  public org.apache.dubbo.rpc.RpcContextAttachment set(java.lang.String, java.lang.Object);
    Code:
       0: aload_0
       1: aload_1
       2: aload_2
       3: invokevirtual #24                 // Method setAttachment:(Ljava/lang/String;Ljava/lang/Object;)Lorg/apache/dubbo/rpc/RpcContextAttachment;
       6: areturn

  public org.apache.dubbo.rpc.RpcContextAttachment remove(java.lang.String);
    Code:
       0: aload_0
       1: aload_1
       2: invokevirtual #25                 // Method removeAttachment:(Ljava/lang/String;)Lorg/apache/dubbo/rpc/RpcContextAttachment;
       5: areturn

  public java.lang.Object get(java.lang.String);
    Code:
       0: aload_0
       1: aload_1
       2: invokevirtual #26                 // Method getAttachment:(Ljava/lang/String;)Ljava/lang/String;
       5: areturn

  public org.apache.dubbo.rpc.RpcContextAttachment copyOf(boolean);
    Code:
       0: aload_0
       1: invokevirtual #27                 // Method isValid:()Z
       4: ifne          9
       7: aconst_null
       8: areturn
       9: iload_1
      10: ifeq          61
      13: new           #28                 // class org/apache/dubbo/rpc/RpcContextAttachment
      16: dup
      17: invokespecial #29                 // Method "<init>":()V
      20: astore_2
      21: aload_0
      22: getfield      #4                  // Field attachments:Ljava/util/Map;
      25: invokestatic  #23                 // Method org/apache/dubbo/common/utils/CollectionUtils.isNotEmptyMap:(Ljava/util/Map;)Z
      28: ifeq          44
      31: aload_2
      32: getfield      #4                  // Field attachments:Ljava/util/Map;
      35: aload_0
      36: getfield      #4                  // Field attachments:Ljava/util/Map;
      39: invokeinterface #22,  2           // InterfaceMethod java/util/Map.putAll:(Ljava/util/Map;)V
      44: aload_0
      45: getfield      #6                  // Field asyncContext:Lorg/apache/dubbo/rpc/AsyncContext;
      48: ifnull        59
      51: aload_2
      52: aload_0
      53: getfield      #6                  // Field asyncContext:Lorg/apache/dubbo/rpc/AsyncContext;
      56: putfield      #6                  // Field asyncContext:Lorg/apache/dubbo/rpc/AsyncContext;
      59: aload_2
      60: areturn
      61: aload_0
      62: areturn

  protected boolean isValid();
    Code:
       0: aload_0
       1: getfield      #4                  // Field attachments:Ljava/util/Map;
       4: invokestatic  #23                 // Method org/apache/dubbo/common/utils/CollectionUtils.isNotEmptyMap:(Ljava/util/Map;)Z
       7: ireturn

  public org.apache.dubbo.rpc.RpcContext remove(java.lang.String);
    Code:
       0: aload_0
       1: aload_1
       2: invokevirtual #30                 // Method remove:(Ljava/lang/String;)Lorg/apache/dubbo/rpc/RpcContextAttachment;
       5: areturn

  public org.apache.dubbo.rpc.RpcContext set(java.lang.String, java.lang.Object);
    Code:
       0: aload_0
       1: aload_1
       2: aload_2
       3: invokevirtual #31                 // Method set:(Ljava/lang/String;Ljava/lang/Object;)Lorg/apache/dubbo/rpc/RpcContextAttachment;
       6: areturn

  public org.apache.dubbo.rpc.RpcContext setObjectAttachments(java.util.Map);
    Code:
       0: aload_0
       1: aload_1
       2: invokevirtual #32                 // Method setObjectAttachments:(Ljava/util/Map;)Lorg/apache/dubbo/rpc/RpcContextAttachment;
       5: areturn

  public org.apache.dubbo.rpc.RpcContext setAttachments(java.util.Map);
    Code:
       0: aload_0
       1: aload_1
       2: invokevirtual #33                 // Method setAttachments:(Ljava/util/Map;)Lorg/apache/dubbo/rpc/RpcContextAttachment;
       5: areturn

  public org.apache.dubbo.rpc.RpcContext removeAttachment(java.lang.String);
    Code:
       0: aload_0
       1: aload_1
       2: invokevirtual #25                 // Method removeAttachment:(Ljava/lang/String;)Lorg/apache/dubbo/rpc/RpcContextAttachment;
       5: areturn

  public org.apache.dubbo.rpc.RpcContext setObjectAttachment(java.lang.String, java.lang.Object);
    Code:
       0: aload_0
       1: aload_1
       2: aload_2
       3: invokevirtual #14                 // Method setObjectAttachment:(Ljava/lang/String;Ljava/lang/Object;)Lorg/apache/dubbo/rpc/RpcContextAttachment;
       6: areturn

  public org.apache.dubbo.rpc.RpcContext setAttachment(java.lang.String, java.lang.Object);
    Code:
       0: aload_0
       1: aload_1
       2: aload_2
       3: invokevirtual #24                 // Method setAttachment:(Ljava/lang/String;Ljava/lang/Object;)Lorg/apache/dubbo/rpc/RpcContextAttachment;
       6: areturn

  public org.apache.dubbo.rpc.RpcContext setAttachment(java.lang.String, java.lang.String);
    Code:
       0: aload_0
       1: aload_1
       2: aload_2
       3: invokevirtual #34                 // Method setAttachment:(Ljava/lang/String;Ljava/lang/String;)Lorg/apache/dubbo/rpc/RpcContextAttachment;
       6: areturn
}
