Compiled from "RpcContext.java"
public class org.apache.dubbo.rpc.RpcContext$RestoreServiceContext {
  private final org.apache.dubbo.rpc.RpcServiceContext serviceContext;

  public org.apache.dubbo.rpc.RpcContext$RestoreServiceContext();
    Code:
       0: aload_0
       1: invokespecial #1                  // Method java/lang/Object."<init>":()V
       4: invokestatic  #2                  // Method org/apache/dubbo/rpc/RpcContext.getCurrentServiceContext:()Lorg/apache/dubbo/rpc/RpcServiceContext;
       7: astore_1
       8: aload_1
       9: ifnonnull     20
      12: aload_0
      13: aconst_null
      14: putfield      #3                  // Field serviceContext:Lorg/apache/dubbo/rpc/RpcServiceContext;
      17: goto          29
      20: aload_0
      21: aload_1
      22: iconst_1
      23: invokevirtual #4                  // Method org/apache/dubbo/rpc/RpcServiceContext.copyOf:(Z)Lorg/apache/dubbo/rpc/RpcServiceContext;
      26: putfield      #3                  // Field serviceContext:Lorg/apache/dubbo/rpc/RpcServiceContext;
      29: return

  protected void restore();
    Code:
       0: aload_0
       1: getfield      #3                  // Field serviceContext:Lorg/apache/dubbo/rpc/RpcServiceContext;
       4: ifnull        20
       7: invokestatic  #5                  // Method org/apache/dubbo/rpc/RpcContext.access$000:()Lorg/apache/dubbo/common/threadlocal/InternalThreadLocal;
      10: aload_0
      11: getfield      #3                  // Field serviceContext:Lorg/apache/dubbo/rpc/RpcServiceContext;
      14: invokevirtual #6                  // Method org/apache/dubbo/common/threadlocal/InternalThreadLocal.set:(Ljava/lang/Object;)V
      17: goto          23
      20: invokestatic  #7                  // Method org/apache/dubbo/rpc/RpcContext.removeServiceContext:()V
      23: return
}
