Compiled from "RpcContext.java"
final class org.apache.dubbo.rpc.RpcContext$4 extends org.apache.dubbo.common.threadlocal.InternalThreadLocal<org.apache.dubbo.rpc.RpcContextAttachment> {
  org.apache.dubbo.rpc.RpcContext$4();
    Code:
       0: aload_0
       1: invokespecial #1                  // Method org/apache/dubbo/common/threadlocal/InternalThreadLocal."<init>":()V
       4: return

  protected org.apache.dubbo.rpc.RpcContextAttachment initialValue();
    Code:
       0: new           #2                  // class org/apache/dubbo/rpc/RpcContextAttachment
       3: dup
       4: invokespecial #3                  // Method org/apache/dubbo/rpc/RpcContextAttachment."<init>":()V
       7: areturn

  protected java.lang.Object initialValue();
    Code:
       0: aload_0
       1: invokevirtual #4                  // Method initialValue:()Lorg/apache/dubbo/rpc/RpcContextAttachment;
       4: areturn
}
