Compiled from "RpcException.java"
public class org.apache.dubbo.rpc.RpcException extends java.lang.RuntimeException {
  public static final int UNKNOWN_EXCEPTION;

  public static final int NETWORK_EXCEPTION;

  public static final int TIMEOUT_EXCEPTION;

  public static final int BIZ_EXCEPTION;

  public static final int FORBIDDEN_EXCEPTION;

  public static final int SERIALIZATION_EXCEPTION;

  public static final int NO_INVOKER_AVAILABLE_AFTER_FILTER;

  public static final int LIMIT_EXCEEDED_EXCEPTION;

  public static final int TIMEOUT_TERMINATE;

  public static final int REGISTRY_EXCEPTION;

  public static final int ROUTER_CACHE_NOT_BUILD;

  public static final int METHOD_NOT_FOUND;

  public static final int VALIDATION_EXCEPTION;

  public static final int AUTHORIZATION_EXCEPTION;

  private static final long serialVersionUID;

  private int code;

  public org.apache.dubbo.rpc.RpcException();
    Code:
       0: aload_0
       1: invokespecial #1                  // Method java/lang/RuntimeException."<init>":()V
       4: return

  public org.apache.dubbo.rpc.RpcException(java.lang.String, java.lang.Throwable);
    Code:
       0: aload_0
       1: aload_1
       2: aload_2
       3: invokespecial #2                  // Method java/lang/RuntimeException."<init>":(Ljava/lang/String;Ljava/lang/Throwable;)V
       6: return

  public org.apache.dubbo.rpc.RpcException(java.lang.String);
    Code:
       0: aload_0
       1: aload_1
       2: invokespecial #3                  // Method java/lang/RuntimeException."<init>":(Ljava/lang/String;)V
       5: return

  public org.apache.dubbo.rpc.RpcException(java.lang.Throwable);
    Code:
       0: aload_0
       1: aload_1
       2: invokespecial #4                  // Method java/lang/RuntimeException."<init>":(Ljava/lang/Throwable;)V
       5: return

  public org.apache.dubbo.rpc.RpcException(int);
    Code:
       0: aload_0
       1: invokespecial #1                  // Method java/lang/RuntimeException."<init>":()V
       4: aload_0
       5: iload_1
       6: putfield      #5                  // Field code:I
       9: return

  public org.apache.dubbo.rpc.RpcException(int, java.lang.String, java.lang.Throwable);
    Code:
       0: aload_0
       1: aload_2
       2: aload_3
       3: invokespecial #2                  // Method java/lang/RuntimeException."<init>":(Ljava/lang/String;Ljava/lang/Throwable;)V
       6: aload_0
       7: iload_1
       8: putfield      #5                  // Field code:I
      11: return

  public org.apache.dubbo.rpc.RpcException(int, java.lang.String);
    Code:
       0: aload_0
       1: aload_2
       2: invokespecial #3                  // Method java/lang/RuntimeException."<init>":(Ljava/lang/String;)V
       5: aload_0
       6: iload_1
       7: putfield      #5                  // Field code:I
      10: return

  public org.apache.dubbo.rpc.RpcException(int, java.lang.Throwable);
    Code:
       0: aload_0
       1: aload_2
       2: invokespecial #4                  // Method java/lang/RuntimeException."<init>":(Ljava/lang/Throwable;)V
       5: aload_0
       6: iload_1
       7: putfield      #5                  // Field code:I
      10: return

  public int getCode();
    Code:
       0: aload_0
       1: getfield      #5                  // Field code:I
       4: ireturn

  public void setCode(int);
    Code:
       0: aload_0
       1: iload_1
       2: putfield      #5                  // Field code:I
       5: return

  public boolean isBiz();
    Code:
       0: aload_0
       1: getfield      #5                  // Field code:I
       4: iconst_3
       5: if_icmpne     12
       8: iconst_1
       9: goto          13
      12: iconst_0
      13: ireturn

  public boolean isForbidden();
    Code:
       0: aload_0
       1: getfield      #5                  // Field code:I
       4: iconst_4
       5: if_icmpne     12
       8: iconst_1
       9: goto          13
      12: iconst_0
      13: ireturn

  public boolean isTimeout();
    Code:
       0: aload_0
       1: getfield      #5                  // Field code:I
       4: iconst_2
       5: if_icmpne     12
       8: iconst_1
       9: goto          13
      12: iconst_0
      13: ireturn

  public boolean isNetwork();
    Code:
       0: aload_0
       1: getfield      #5                  // Field code:I
       4: iconst_1
       5: if_icmpne     12
       8: iconst_1
       9: goto          13
      12: iconst_0
      13: ireturn

  public boolean isSerialization();
    Code:
       0: aload_0
       1: getfield      #5                  // Field code:I
       4: iconst_5
       5: if_icmpne     12
       8: iconst_1
       9: goto          13
      12: iconst_0
      13: ireturn

  public boolean isAuthorization();
    Code:
       0: aload_0
       1: getfield      #5                  // Field code:I
       4: bipush        13
       6: if_icmpne     13
       9: iconst_1
      10: goto          14
      13: iconst_0
      14: ireturn

  public boolean isNoInvokerAvailableAfterFilter();
    Code:
       0: aload_0
       1: getfield      #5                  // Field code:I
       4: bipush        6
       6: if_icmpne     13
       9: iconst_1
      10: goto          14
      13: iconst_0
      14: ireturn

  public boolean isLimitExceed();
    Code:
       0: aload_0
       1: getfield      #5                  // Field code:I
       4: bipush        7
       6: if_icmpeq     19
       9: aload_0
      10: invokevirtual #7                  // Method getCause:()Ljava/lang/Throwable;
      13: instanceof    #8                  // class javax/naming/LimitExceededException
      16: ifeq          23
      19: iconst_1
      20: goto          24
      23: iconst_0
      24: ireturn

  public boolean isValidation();
    Code:
       0: aload_0
       1: getfield      #5                  // Field code:I
       4: bipush        12
       6: if_icmpne     13
       9: iconst_1
      10: goto          14
      13: iconst_0
      14: ireturn
}
