Compiled from "RpcServiceContext.java"
public class org.apache.dubbo.rpc.RpcServiceContext extends org.apache.dubbo.rpc.RpcContext {
  private org.apache.dubbo.common.URL consumerUrl;

  private java.util.List<org.apache.dubbo.common.URL> urls;

  private org.apache.dubbo.common.URL url;

  private java.lang.String methodName;

  private java.lang.Class<?>[] parameterTypes;

  private java.lang.Object[] arguments;

  private java.net.InetSocketAddress localAddress;

  private java.net.InetSocketAddress remoteAddress;

  private java.lang.String remoteApplicationName;

  private java.lang.Boolean localInvoke;

  private java.util.List<org.apache.dubbo.rpc.Invoker<?>> invokers;

  private org.apache.dubbo.rpc.Invoker<?> invoker;

  private org.apache.dubbo.rpc.Invocation invocation;

  private java.lang.Object request;

  private java.lang.Object response;

  private boolean needPrintRouterSnapshot;

  protected org.apache.dubbo.rpc.RpcServiceContext();
    Code:
       0: aload_0
       1: invokespecial #3                  // Method org/apache/dubbo/rpc/RpcContext."<init>":()V
       4: return

  public java.lang.Object getRequest();
    Code:
       0: aload_0
       1: getfield      #4                  // Field request:Ljava/lang/Object;
       4: areturn

  public void setRequest(java.lang.Object);
    Code:
       0: aload_0
       1: aload_1
       2: putfield      #4                  // Field request:Ljava/lang/Object;
       5: return

  public <T> T getRequest(java.lang.Class<T>);
    Code:
       0: aload_0
       1: getfield      #4                  // Field request:Ljava/lang/Object;
       4: ifnull        28
       7: aload_1
       8: aload_0
       9: getfield      #4                  // Field request:Ljava/lang/Object;
      12: invokevirtual #5                  // Method java/lang/Object.getClass:()Ljava/lang/Class;
      15: invokevirtual #6                  // Method java/lang/Class.isAssignableFrom:(Ljava/lang/Class;)Z
      18: ifeq          28
      21: aload_0
      22: getfield      #4                  // Field request:Ljava/lang/Object;
      25: goto          29
      28: aconst_null
      29: areturn

  public java.lang.Object getResponse();
    Code:
       0: aload_0
       1: getfield      #7                  // Field response:Ljava/lang/Object;
       4: areturn

  public void setResponse(java.lang.Object);
    Code:
       0: aload_0
       1: aload_1
       2: putfield      #7                  // Field response:Ljava/lang/Object;
       5: return

  public <T> T getResponse(java.lang.Class<T>);
    Code:
       0: aload_0
       1: getfield      #7                  // Field response:Ljava/lang/Object;
       4: ifnull        28
       7: aload_1
       8: aload_0
       9: getfield      #7                  // Field response:Ljava/lang/Object;
      12: invokevirtual #5                  // Method java/lang/Object.getClass:()Ljava/lang/Class;
      15: invokevirtual #6                  // Method java/lang/Class.isAssignableFrom:(Ljava/lang/Class;)Z
      18: ifeq          28
      21: aload_0
      22: getfield      #7                  // Field response:Ljava/lang/Object;
      25: goto          29
      28: aconst_null
      29: areturn

  public boolean isProviderSide();
    Code:
       0: aload_0
       1: invokevirtual #8                  // Method isConsumerSide:()Z
       4: ifne          11
       7: iconst_1
       8: goto          12
      11: iconst_0
      12: ireturn

  public boolean isConsumerSide();
    Code:
       0: aload_0
       1: invokevirtual #9                  // Method getUrl:()Lorg/apache/dubbo/common/URL;
       4: ldc           #10                 // String provider
       6: invokevirtual #11                 // Method org/apache/dubbo/common/URL.getSide:(Ljava/lang/String;)Ljava/lang/String;
       9: ldc           #12                 // String consumer
      11: invokevirtual #13                 // Method java/lang/String.equals:(Ljava/lang/Object;)Z
      14: ireturn

  public <T> java.util.concurrent.CompletableFuture<T> getCompletableFuture();
    Code:
       0: invokestatic  #14                 // Method org/apache/dubbo/rpc/FutureContext.getContext:()Lorg/apache/dubbo/rpc/FutureContext;
       3: invokevirtual #15                 // Method org/apache/dubbo/rpc/FutureContext.getCompletableFuture:()Ljava/util/concurrent/CompletableFuture;
       6: areturn

  public <T> java.util.concurrent.Future<T> getFuture();
    Code:
       0: invokestatic  #14                 // Method org/apache/dubbo/rpc/FutureContext.getContext:()Lorg/apache/dubbo/rpc/FutureContext;
       3: invokevirtual #15                 // Method org/apache/dubbo/rpc/FutureContext.getCompletableFuture:()Ljava/util/concurrent/CompletableFuture;
       6: areturn

  public void setFuture(java.util.concurrent.CompletableFuture<?>);
    Code:
       0: invokestatic  #14                 // Method org/apache/dubbo/rpc/FutureContext.getContext:()Lorg/apache/dubbo/rpc/FutureContext;
       3: aload_1
       4: invokevirtual #16                 // Method org/apache/dubbo/rpc/FutureContext.setFuture:(Ljava/util/concurrent/CompletableFuture;)V
       7: return

  public java.util.List<org.apache.dubbo.common.URL> getUrls();
    Code:
       0: aload_0
       1: getfield      #17                 // Field urls:Ljava/util/List;
       4: ifnonnull     31
       7: aload_0
       8: getfield      #18                 // Field url:Lorg/apache/dubbo/common/URL;
      11: ifnull        31
      14: iconst_1
      15: anewarray     #19                 // class org/apache/dubbo/common/URL
      18: dup
      19: iconst_0
      20: aload_0
      21: getfield      #18                 // Field url:Lorg/apache/dubbo/common/URL;
      24: aastore
      25: invokestatic  #20                 // Method java/util/Arrays.asList:([Ljava/lang/Object;)Ljava/util/List;
      28: goto          35
      31: aload_0
      32: getfield      #17                 // Field urls:Ljava/util/List;
      35: areturn

  public void setUrls(java.util.List<org.apache.dubbo.common.URL>);
    Code:
       0: aload_0
       1: aload_1
       2: putfield      #17                 // Field urls:Ljava/util/List;
       5: aload_1
       6: invokeinterface #21,  1           // InterfaceMethod java/util/List.isEmpty:()Z
      11: ifne          28
      14: aload_0
      15: aload_1
      16: iconst_0
      17: invokeinterface #22,  2           // InterfaceMethod java/util/List.get:(I)Ljava/lang/Object;
      22: checkcast     #19                 // class org/apache/dubbo/common/URL
      25: putfield      #18                 // Field url:Lorg/apache/dubbo/common/URL;
      28: return

  public org.apache.dubbo.common.URL getUrl();
    Code:
       0: aload_0
       1: getfield      #18                 // Field url:Lorg/apache/dubbo/common/URL;
       4: areturn

  public void setUrl(org.apache.dubbo.common.URL);
    Code:
       0: aload_0
       1: aload_1
       2: putfield      #18                 // Field url:Lorg/apache/dubbo/common/URL;
       5: return

  public java.lang.String getMethodName();
    Code:
       0: aload_0
       1: getfield      #23                 // Field methodName:Ljava/lang/String;
       4: areturn

  public void setMethodName(java.lang.String);
    Code:
       0: aload_0
       1: aload_1
       2: putfield      #23                 // Field methodName:Ljava/lang/String;
       5: return

  public java.lang.Class<?>[] getParameterTypes();
    Code:
       0: aload_0
       1: getfield      #24                 // Field parameterTypes:[Ljava/lang/Class;
       4: areturn

  public void setParameterTypes(java.lang.Class<?>[]);
    Code:
       0: aload_0
       1: aload_1
       2: putfield      #24                 // Field parameterTypes:[Ljava/lang/Class;
       5: return

  public java.lang.Object[] getArguments();
    Code:
       0: aload_0
       1: getfield      #25                 // Field arguments:[Ljava/lang/Object;
       4: areturn

  public void setArguments(java.lang.Object[]);
    Code:
       0: aload_0
       1: aload_1
       2: putfield      #25                 // Field arguments:[Ljava/lang/Object;
       5: return

  public org.apache.dubbo.rpc.RpcServiceContext setLocalAddress(java.lang.String, int);
    Code:
       0: iload_2
       1: ifge          6
       4: iconst_0
       5: istore_2
       6: aload_0
       7: aload_1
       8: iload_2
       9: invokestatic  #26                 // Method java/net/InetSocketAddress.createUnresolved:(Ljava/lang/String;I)Ljava/net/InetSocketAddress;
      12: putfield      #27                 // Field localAddress:Ljava/net/InetSocketAddress;
      15: aload_0
      16: areturn

  public java.net.InetSocketAddress getLocalAddress();
    Code:
       0: aload_0
       1: getfield      #27                 // Field localAddress:Ljava/net/InetSocketAddress;
       4: areturn

  public org.apache.dubbo.rpc.RpcServiceContext setLocalAddress(java.net.InetSocketAddress);
    Code:
       0: aload_0
       1: aload_1
       2: putfield      #27                 // Field localAddress:Ljava/net/InetSocketAddress;
       5: aload_0
       6: areturn

  public java.lang.String getLocalAddressString();
    Code:
       0: new           #28                 // class java/lang/StringBuilder
       3: dup
       4: invokespecial #29                 // Method java/lang/StringBuilder."<init>":()V
       7: aload_0
       8: invokevirtual #30                 // Method getLocalHost:()Ljava/lang/String;
      11: invokevirtual #31                 // Method java/lang/StringBuilder.append:(Ljava/lang/String;)Ljava/lang/StringBuilder;
      14: ldc           #32                 // String :
      16: invokevirtual #31                 // Method java/lang/StringBuilder.append:(Ljava/lang/String;)Ljava/lang/StringBuilder;
      19: aload_0
      20: invokevirtual #33                 // Method getLocalPort:()I
      23: invokevirtual #34                 // Method java/lang/StringBuilder.append:(I)Ljava/lang/StringBuilder;
      26: invokevirtual #35                 // Method java/lang/StringBuilder.toString:()Ljava/lang/String;
      29: areturn

  public java.lang.String getLocalHostName();
    Code:
       0: aload_0
       1: getfield      #27                 // Field localAddress:Ljava/net/InetSocketAddress;
       4: ifnonnull     11
       7: aconst_null
       8: goto          18
      11: aload_0
      12: getfield      #27                 // Field localAddress:Ljava/net/InetSocketAddress;
      15: invokevirtual #36                 // Method java/net/InetSocketAddress.getHostName:()Ljava/lang/String;
      18: astore_1
      19: aload_1
      20: invokestatic  #37                 // Method org/apache/dubbo/common/utils/StringUtils.isEmpty:(Ljava/lang/String;)Z
      23: ifeq          31
      26: aload_0
      27: invokevirtual #30                 // Method getLocalHost:()Ljava/lang/String;
      30: areturn
      31: aload_1
      32: areturn

  public org.apache.dubbo.rpc.RpcServiceContext setRemoteAddress(java.lang.String, int);
    Code:
       0: iload_2
       1: ifge          6
       4: iconst_0
       5: istore_2
       6: aload_0
       7: aload_1
       8: iload_2
       9: invokestatic  #26                 // Method java/net/InetSocketAddress.createUnresolved:(Ljava/lang/String;I)Ljava/net/InetSocketAddress;
      12: putfield      #38                 // Field remoteAddress:Ljava/net/InetSocketAddress;
      15: aload_0
      16: areturn

  public java.net.InetSocketAddress getRemoteAddress();
    Code:
       0: aload_0
       1: getfield      #38                 // Field remoteAddress:Ljava/net/InetSocketAddress;
       4: areturn

  public org.apache.dubbo.rpc.RpcServiceContext setRemoteAddress(java.net.InetSocketAddress);
    Code:
       0: aload_0
       1: aload_1
       2: putfield      #38                 // Field remoteAddress:Ljava/net/InetSocketAddress;
       5: aload_0
       6: areturn

  public java.lang.String getRemoteApplicationName();
    Code:
       0: aload_0
       1: getfield      #39                 // Field remoteApplicationName:Ljava/lang/String;
       4: areturn

  public org.apache.dubbo.rpc.RpcServiceContext setRemoteApplicationName(java.lang.String);
    Code:
       0: aload_0
       1: aload_1
       2: putfield      #39                 // Field remoteApplicationName:Ljava/lang/String;
       5: aload_0
       6: areturn

  public java.lang.String getRemoteAddressString();
    Code:
       0: new           #28                 // class java/lang/StringBuilder
       3: dup
       4: invokespecial #29                 // Method java/lang/StringBuilder."<init>":()V
       7: aload_0
       8: invokevirtual #40                 // Method getRemoteHost:()Ljava/lang/String;
      11: invokevirtual #31                 // Method java/lang/StringBuilder.append:(Ljava/lang/String;)Ljava/lang/StringBuilder;
      14: ldc           #32                 // String :
      16: invokevirtual #31                 // Method java/lang/StringBuilder.append:(Ljava/lang/String;)Ljava/lang/StringBuilder;
      19: aload_0
      20: invokevirtual #41                 // Method getRemotePort:()I
      23: invokevirtual #34                 // Method java/lang/StringBuilder.append:(I)Ljava/lang/StringBuilder;
      26: invokevirtual #35                 // Method java/lang/StringBuilder.toString:()Ljava/lang/String;
      29: areturn

  public java.lang.String getRemoteHostName();
    Code:
       0: aload_0
       1: getfield      #38                 // Field remoteAddress:Ljava/net/InetSocketAddress;
       4: ifnonnull     11
       7: aconst_null
       8: goto          18
      11: aload_0
      12: getfield      #38                 // Field remoteAddress:Ljava/net/InetSocketAddress;
      15: invokevirtual #36                 // Method java/net/InetSocketAddress.getHostName:()Ljava/lang/String;
      18: areturn

  public java.lang.String getLocalHost();
    Code:
       0: aload_0
       1: getfield      #27                 // Field localAddress:Ljava/net/InetSocketAddress;
       4: ifnonnull     11
       7: aconst_null
       8: goto          44
      11: aload_0
      12: getfield      #27                 // Field localAddress:Ljava/net/InetSocketAddress;
      15: invokevirtual #42                 // Method java/net/InetSocketAddress.getAddress:()Ljava/net/InetAddress;
      18: ifnonnull     31
      21: aload_0
      22: getfield      #27                 // Field localAddress:Ljava/net/InetSocketAddress;
      25: invokevirtual #36                 // Method java/net/InetSocketAddress.getHostName:()Ljava/lang/String;
      28: goto          44
      31: aload_0
      32: getfield      #27                 // Field localAddress:Ljava/net/InetSocketAddress;
      35: invokevirtual #42                 // Method java/net/InetSocketAddress.getAddress:()Ljava/net/InetAddress;
      38: invokevirtual #43                 // Method java/net/InetAddress.getHostAddress:()Ljava/lang/String;
      41: invokestatic  #44                 // Method org/apache/dubbo/common/utils/NetUtils.filterLocalHost:(Ljava/lang/String;)Ljava/lang/String;
      44: astore_1
      45: aload_1
      46: ifnull        56
      49: aload_1
      50: invokevirtual #45                 // Method java/lang/String.length:()I
      53: ifne          60
      56: invokestatic  #46                 // Method org/apache/dubbo/common/utils/NetUtils.getLocalHost:()Ljava/lang/String;
      59: areturn
      60: aload_1
      61: areturn

  public int getLocalPort();
    Code:
       0: aload_0
       1: getfield      #27                 // Field localAddress:Ljava/net/InetSocketAddress;
       4: ifnonnull     11
       7: iconst_0
       8: goto          18
      11: aload_0
      12: getfield      #27                 // Field localAddress:Ljava/net/InetSocketAddress;
      15: invokevirtual #47                 // Method java/net/InetSocketAddress.getPort:()I
      18: ireturn

  public java.lang.String getRemoteHost();
    Code:
       0: aload_0
       1: getfield      #38                 // Field remoteAddress:Ljava/net/InetSocketAddress;
       4: ifnonnull     11
       7: aconst_null
       8: goto          44
      11: aload_0
      12: getfield      #38                 // Field remoteAddress:Ljava/net/InetSocketAddress;
      15: invokevirtual #42                 // Method java/net/InetSocketAddress.getAddress:()Ljava/net/InetAddress;
      18: ifnonnull     31
      21: aload_0
      22: getfield      #38                 // Field remoteAddress:Ljava/net/InetSocketAddress;
      25: invokevirtual #36                 // Method java/net/InetSocketAddress.getHostName:()Ljava/lang/String;
      28: goto          44
      31: aload_0
      32: getfield      #38                 // Field remoteAddress:Ljava/net/InetSocketAddress;
      35: invokevirtual #42                 // Method java/net/InetSocketAddress.getAddress:()Ljava/net/InetAddress;
      38: invokevirtual #43                 // Method java/net/InetAddress.getHostAddress:()Ljava/lang/String;
      41: invokestatic  #44                 // Method org/apache/dubbo/common/utils/NetUtils.filterLocalHost:(Ljava/lang/String;)Ljava/lang/String;
      44: areturn

  public int getRemotePort();
    Code:
       0: aload_0
       1: getfield      #38                 // Field remoteAddress:Ljava/net/InetSocketAddress;
       4: ifnonnull     11
       7: iconst_0
       8: goto          18
      11: aload_0
      12: getfield      #38                 // Field remoteAddress:Ljava/net/InetSocketAddress;
      15: invokevirtual #47                 // Method java/net/InetSocketAddress.getPort:()I
      18: ireturn

  public boolean isServerSide();
    Code:
       0: aload_0
       1: invokevirtual #48                 // Method isProviderSide:()Z
       4: ireturn

  public boolean isClientSide();
    Code:
       0: aload_0
       1: invokevirtual #8                  // Method isConsumerSide:()Z
       4: ireturn

  public java.util.List<org.apache.dubbo.rpc.Invoker<?>> getInvokers();
    Code:
       0: aload_0
       1: getfield      #49                 // Field invokers:Ljava/util/List;
       4: ifnonnull     31
       7: aload_0
       8: getfield      #50                 // Field invoker:Lorg/apache/dubbo/rpc/Invoker;
      11: ifnull        31
      14: iconst_1
      15: anewarray     #51                 // class org/apache/dubbo/rpc/Invoker
      18: dup
      19: iconst_0
      20: aload_0
      21: getfield      #50                 // Field invoker:Lorg/apache/dubbo/rpc/Invoker;
      24: aastore
      25: invokestatic  #20                 // Method java/util/Arrays.asList:([Ljava/lang/Object;)Ljava/util/List;
      28: goto          35
      31: aload_0
      32: getfield      #49                 // Field invokers:Ljava/util/List;
      35: areturn

  public org.apache.dubbo.rpc.RpcServiceContext setInvokers(java.util.List<org.apache.dubbo.rpc.Invoker<?>>);
    Code:
       0: aload_0
       1: aload_1
       2: putfield      #49                 // Field invokers:Ljava/util/List;
       5: aload_1
       6: invokestatic  #52                 // Method org/apache/dubbo/common/utils/CollectionUtils.isNotEmpty:(Ljava/util/Collection;)Z
       9: ifeq          75
      12: new           #53                 // class java/util/ArrayList
      15: dup
      16: aload_1
      17: invokeinterface #54,  1           // InterfaceMethod java/util/List.size:()I
      22: invokespecial #55                 // Method java/util/ArrayList."<init>":(I)V
      25: astore_2
      26: aload_1
      27: invokeinterface #56,  1           // InterfaceMethod java/util/List.iterator:()Ljava/util/Iterator;
      32: astore_3
      33: aload_3
      34: invokeinterface #57,  1           // InterfaceMethod java/util/Iterator.hasNext:()Z
      39: ifeq          70
      42: aload_3
      43: invokeinterface #58,  1           // InterfaceMethod java/util/Iterator.next:()Ljava/lang/Object;
      48: checkcast     #51                 // class org/apache/dubbo/rpc/Invoker
      51: astore        4
      53: aload_2
      54: aload         4
      56: invokeinterface #59,  1           // InterfaceMethod org/apache/dubbo/rpc/Invoker.getUrl:()Lorg/apache/dubbo/common/URL;
      61: invokeinterface #60,  2           // InterfaceMethod java/util/List.add:(Ljava/lang/Object;)Z
      66: pop
      67: goto          33
      70: aload_0
      71: aload_2
      72: invokevirtual #61                 // Method setUrls:(Ljava/util/List;)V
      75: aload_0
      76: areturn

  public org.apache.dubbo.rpc.Invoker<?> getInvoker();
    Code:
       0: aload_0
       1: getfield      #50                 // Field invoker:Lorg/apache/dubbo/rpc/Invoker;
       4: areturn

  public org.apache.dubbo.rpc.RpcServiceContext setInvoker(org.apache.dubbo.rpc.Invoker<?>);
    Code:
       0: aload_0
       1: aload_1
       2: putfield      #50                 // Field invoker:Lorg/apache/dubbo/rpc/Invoker;
       5: aload_1
       6: ifnull        19
       9: aload_0
      10: aload_1
      11: invokeinterface #59,  1           // InterfaceMethod org/apache/dubbo/rpc/Invoker.getUrl:()Lorg/apache/dubbo/common/URL;
      16: invokevirtual #62                 // Method setUrl:(Lorg/apache/dubbo/common/URL;)V
      19: aload_0
      20: areturn

  public org.apache.dubbo.rpc.Invocation getInvocation();
    Code:
       0: aload_0
       1: getfield      #63                 // Field invocation:Lorg/apache/dubbo/rpc/Invocation;
       4: areturn

  public org.apache.dubbo.rpc.RpcServiceContext setInvocation(org.apache.dubbo.rpc.Invocation);
    Code:
       0: aload_0
       1: aload_1
       2: putfield      #63                 // Field invocation:Lorg/apache/dubbo/rpc/Invocation;
       5: aload_1
       6: ifnull        39
       9: aload_0
      10: aload_1
      11: invokeinterface #64,  1           // InterfaceMethod org/apache/dubbo/rpc/Invocation.getMethodName:()Ljava/lang/String;
      16: invokevirtual #65                 // Method setMethodName:(Ljava/lang/String;)V
      19: aload_0
      20: aload_1
      21: invokeinterface #66,  1           // InterfaceMethod org/apache/dubbo/rpc/Invocation.getParameterTypes:()[Ljava/lang/Class;
      26: invokevirtual #67                 // Method setParameterTypes:([Ljava/lang/Class;)V
      29: aload_0
      30: aload_1
      31: invokeinterface #68,  1           // InterfaceMethod org/apache/dubbo/rpc/Invocation.getArguments:()[Ljava/lang/Object;
      36: invokevirtual #69                 // Method setArguments:([Ljava/lang/Object;)V
      39: aload_0
      40: areturn

  public <T> java.util.concurrent.CompletableFuture<T> asyncCall(java.util.concurrent.Callable<T>);
    Code:
       0: aload_0
       1: ldc           #70                 // String async
       3: getstatic     #71                 // Field java/lang/Boolean.TRUE:Ljava/lang/Boolean;
       6: invokevirtual #72                 // Method java/lang/Boolean.toString:()Ljava/lang/String;
       9: invokevirtual #73                 // Method setAttachment:(Ljava/lang/String;Ljava/lang/String;)Lorg/apache/dubbo/rpc/RpcContext;
      12: pop
      13: aload_1
      14: invokeinterface #74,  1           // InterfaceMethod java/util/concurrent/Callable.call:()Ljava/lang/Object;
      19: astore_2
      20: aload_2
      21: ifnull        59
      24: aload_2
      25: instanceof    #75                 // class java/util/concurrent/CompletableFuture
      28: ifeq          45
      31: aload_2
      32: checkcast     #75                 // class java/util/concurrent/CompletableFuture
      35: astore_3
      36: aload_0
      37: ldc           #70                 // String async
      39: invokevirtual #76                 // Method removeAttachment:(Ljava/lang/String;)Lorg/apache/dubbo/rpc/RpcContext;
      42: pop
      43: aload_3
      44: areturn
      45: aload_2
      46: invokestatic  #77                 // Method java/util/concurrent/CompletableFuture.completedFuture:(Ljava/lang/Object;)Ljava/util/concurrent/CompletableFuture;
      49: astore_3
      50: aload_0
      51: ldc           #70                 // String async
      53: invokevirtual #76                 // Method removeAttachment:(Ljava/lang/String;)Lorg/apache/dubbo/rpc/RpcContext;
      56: pop
      57: aload_3
      58: areturn
      59: aload_0
      60: ldc           #70                 // String async
      62: invokevirtual #76                 // Method removeAttachment:(Ljava/lang/String;)Lorg/apache/dubbo/rpc/RpcContext;
      65: pop
      66: goto          91
      69: astore_2
      70: new           #79                 // class org/apache/dubbo/rpc/RpcException
      73: dup
      74: aload_2
      75: invokespecial #80                 // Method org/apache/dubbo/rpc/RpcException."<init>":(Ljava/lang/Throwable;)V
      78: athrow
      79: astore        4
      81: aload_0
      82: ldc           #70                 // String async
      84: invokevirtual #76                 // Method removeAttachment:(Ljava/lang/String;)Lorg/apache/dubbo/rpc/RpcContext;
      87: pop
      88: aload         4
      90: athrow
      91: goto          111
      94: astore_2
      95: new           #75                 // class java/util/concurrent/CompletableFuture
      98: dup
      99: invokespecial #81                 // Method java/util/concurrent/CompletableFuture."<init>":()V
     102: astore_3
     103: aload_3
     104: aload_2
     105: invokevirtual #82                 // Method java/util/concurrent/CompletableFuture.completeExceptionally:(Ljava/lang/Throwable;)Z
     108: pop
     109: aload_3
     110: areturn
     111: invokestatic  #83                 // Method getServiceContext:()Lorg/apache/dubbo/rpc/RpcServiceContext;
     114: invokevirtual #84                 // Method getFuture:()Ljava/util/concurrent/Future;
     117: checkcast     #75                 // class java/util/concurrent/CompletableFuture
     120: areturn
    Exception table:
       from    to  target type
           0    36    69   Class java/lang/Exception
          45    50    69   Class java/lang/Exception
           0    36    79   any
          45    50    79   any
          69    81    79   any
           0    43    94   Class org/apache/dubbo/rpc/RpcException
          45    57    94   Class org/apache/dubbo/rpc/RpcException
          59    91    94   Class org/apache/dubbo/rpc/RpcException

  public void asyncCall(java.lang.Runnable);
    Code:
       0: aload_0
       1: ldc           #85                 // String return
       3: getstatic     #86                 // Field java/lang/Boolean.FALSE:Ljava/lang/Boolean;
       6: invokevirtual #72                 // Method java/lang/Boolean.toString:()Ljava/lang/String;
       9: invokevirtual #73                 // Method setAttachment:(Ljava/lang/String;Ljava/lang/String;)Lorg/apache/dubbo/rpc/RpcContext;
      12: pop
      13: aload_1
      14: invokeinterface #87,  1           // InterfaceMethod java/lang/Runnable.run:()V
      19: aload_0
      20: ldc           #85                 // String return
      22: invokevirtual #76                 // Method removeAttachment:(Ljava/lang/String;)Lorg/apache/dubbo/rpc/RpcContext;
      25: pop
      26: goto          71
      29: astore_2
      30: new           #79                 // class org/apache/dubbo/rpc/RpcException
      33: dup
      34: new           #28                 // class java/lang/StringBuilder
      37: dup
      38: invokespecial #29                 // Method java/lang/StringBuilder."<init>":()V
      41: ldc           #89                 // String oneway call error .
      43: invokevirtual #31                 // Method java/lang/StringBuilder.append:(Ljava/lang/String;)Ljava/lang/StringBuilder;
      46: aload_2
      47: invokevirtual #90                 // Method java/lang/Throwable.getMessage:()Ljava/lang/String;
      50: invokevirtual #31                 // Method java/lang/StringBuilder.append:(Ljava/lang/String;)Ljava/lang/StringBuilder;
      53: invokevirtual #35                 // Method java/lang/StringBuilder.toString:()Ljava/lang/String;
      56: aload_2
      57: invokespecial #91                 // Method org/apache/dubbo/rpc/RpcException."<init>":(Ljava/lang/String;Ljava/lang/Throwable;)V
      60: athrow
      61: astore_3
      62: aload_0
      63: ldc           #85                 // String return
      65: invokevirtual #76                 // Method removeAttachment:(Ljava/lang/String;)Lorg/apache/dubbo/rpc/RpcContext;
      68: pop
      69: aload_3
      70: athrow
      71: return
    Exception table:
       from    to  target type
           0    19    29   Class java/lang/Throwable
           0    19    61   any
          29    62    61   any

  public java.lang.String getGroup();
    Code:
       0: aload_0
       1: getfield      #92                 // Field consumerUrl:Lorg/apache/dubbo/common/URL;
       4: ifnonnull     9
       7: aconst_null
       8: areturn
       9: aload_0
      10: getfield      #92                 // Field consumerUrl:Lorg/apache/dubbo/common/URL;
      13: invokevirtual #93                 // Method org/apache/dubbo/common/URL.getGroup:()Ljava/lang/String;
      16: areturn

  public java.lang.String getVersion();
    Code:
       0: aload_0
       1: getfield      #92                 // Field consumerUrl:Lorg/apache/dubbo/common/URL;
       4: ifnonnull     9
       7: aconst_null
       8: areturn
       9: aload_0
      10: getfield      #92                 // Field consumerUrl:Lorg/apache/dubbo/common/URL;
      13: invokevirtual #94                 // Method org/apache/dubbo/common/URL.getVersion:()Ljava/lang/String;
      16: areturn

  public java.lang.String getInterfaceName();
    Code:
       0: aload_0
       1: getfield      #92                 // Field consumerUrl:Lorg/apache/dubbo/common/URL;
       4: ifnonnull     9
       7: aconst_null
       8: areturn
       9: aload_0
      10: getfield      #92                 // Field consumerUrl:Lorg/apache/dubbo/common/URL;
      13: invokevirtual #95                 // Method org/apache/dubbo/common/URL.getServiceInterface:()Ljava/lang/String;
      16: areturn

  public java.lang.String getProtocol();
    Code:
       0: aload_0
       1: getfield      #92                 // Field consumerUrl:Lorg/apache/dubbo/common/URL;
       4: ifnonnull     9
       7: aconst_null
       8: areturn
       9: aload_0
      10: getfield      #92                 // Field consumerUrl:Lorg/apache/dubbo/common/URL;
      13: invokevirtual #96                 // Method org/apache/dubbo/common/URL.getProtocol:()Ljava/lang/String;
      16: areturn

  public java.lang.String getServiceKey();
    Code:
       0: aload_0
       1: getfield      #92                 // Field consumerUrl:Lorg/apache/dubbo/common/URL;
       4: ifnonnull     9
       7: aconst_null
       8: areturn
       9: aload_0
      10: getfield      #92                 // Field consumerUrl:Lorg/apache/dubbo/common/URL;
      13: invokevirtual #97                 // Method org/apache/dubbo/common/URL.getServiceKey:()Ljava/lang/String;
      16: areturn

  public java.lang.String getProtocolServiceKey();
    Code:
       0: aload_0
       1: getfield      #92                 // Field consumerUrl:Lorg/apache/dubbo/common/URL;
       4: ifnonnull     9
       7: aconst_null
       8: areturn
       9: aload_0
      10: getfield      #92                 // Field consumerUrl:Lorg/apache/dubbo/common/URL;
      13: invokevirtual #98                 // Method org/apache/dubbo/common/URL.getProtocolServiceKey:()Ljava/lang/String;
      16: areturn

  public org.apache.dubbo.common.URL getConsumerUrl();
    Code:
       0: aload_0
       1: getfield      #92                 // Field consumerUrl:Lorg/apache/dubbo/common/URL;
       4: areturn

  public void setConsumerUrl(org.apache.dubbo.common.URL);
    Code:
       0: aload_0
       1: aload_1
       2: putfield      #92                 // Field consumerUrl:Lorg/apache/dubbo/common/URL;
       5: return

  public boolean isNeedPrintRouterSnapshot();
    Code:
       0: aload_0
       1: getfield      #99                 // Field needPrintRouterSnapshot:Z
       4: ireturn

  public void setNeedPrintRouterSnapshot(boolean);
    Code:
       0: aload_0
       1: iload_1
       2: putfield      #99                 // Field needPrintRouterSnapshot:Z
       5: return

  public org.apache.dubbo.rpc.RpcServiceContext setLocalInvoke(boolean);
    Code:
       0: aload_0
       1: iload_1
       2: invokestatic  #100                // Method java/lang/Boolean.valueOf:(Z)Ljava/lang/Boolean;
       5: putfield      #101                // Field localInvoke:Ljava/lang/Boolean;
       8: aload_0
       9: areturn

  public java.lang.Boolean getLocalInvoke();
    Code:
       0: aload_0
       1: getfield      #101                // Field localInvoke:Ljava/lang/Boolean;
       4: areturn

  public org.apache.dubbo.rpc.RpcServiceContext copyOf(boolean);
    Code:
       0: iload_1
       1: ifeq          134
       4: new           #102                // class org/apache/dubbo/rpc/RpcServiceContext
       7: dup
       8: invokespecial #103                // Method "<init>":()V
      11: astore_2
      12: aload_2
      13: aload_0
      14: getfield      #25                 // Field arguments:[Ljava/lang/Object;
      17: putfield      #25                 // Field arguments:[Ljava/lang/Object;
      20: aload_2
      21: aload_0
      22: getfield      #92                 // Field consumerUrl:Lorg/apache/dubbo/common/URL;
      25: putfield      #92                 // Field consumerUrl:Lorg/apache/dubbo/common/URL;
      28: aload_2
      29: aload_0
      30: getfield      #63                 // Field invocation:Lorg/apache/dubbo/rpc/Invocation;
      33: putfield      #63                 // Field invocation:Lorg/apache/dubbo/rpc/Invocation;
      36: aload_2
      37: aload_0
      38: getfield      #49                 // Field invokers:Ljava/util/List;
      41: putfield      #49                 // Field invokers:Ljava/util/List;
      44: aload_2
      45: aload_0
      46: getfield      #50                 // Field invoker:Lorg/apache/dubbo/rpc/Invoker;
      49: putfield      #50                 // Field invoker:Lorg/apache/dubbo/rpc/Invoker;
      52: aload_2
      53: aload_0
      54: getfield      #27                 // Field localAddress:Ljava/net/InetSocketAddress;
      57: putfield      #27                 // Field localAddress:Ljava/net/InetSocketAddress;
      60: aload_2
      61: aload_0
      62: getfield      #23                 // Field methodName:Ljava/lang/String;
      65: putfield      #23                 // Field methodName:Ljava/lang/String;
      68: aload_2
      69: aload_0
      70: getfield      #99                 // Field needPrintRouterSnapshot:Z
      73: putfield      #99                 // Field needPrintRouterSnapshot:Z
      76: aload_2
      77: aload_0
      78: getfield      #24                 // Field parameterTypes:[Ljava/lang/Class;
      81: putfield      #24                 // Field parameterTypes:[Ljava/lang/Class;
      84: aload_2
      85: aload_0
      86: getfield      #38                 // Field remoteAddress:Ljava/net/InetSocketAddress;
      89: putfield      #38                 // Field remoteAddress:Ljava/net/InetSocketAddress;
      92: aload_2
      93: aload_0
      94: getfield      #39                 // Field remoteApplicationName:Ljava/lang/String;
      97: putfield      #39                 // Field remoteApplicationName:Ljava/lang/String;
     100: aload_2
     101: aload_0
     102: getfield      #4                  // Field request:Ljava/lang/Object;
     105: putfield      #4                  // Field request:Ljava/lang/Object;
     108: aload_2
     109: aload_0
     110: getfield      #7                  // Field response:Ljava/lang/Object;
     113: putfield      #7                  // Field response:Ljava/lang/Object;
     116: aload_2
     117: aload_0
     118: getfield      #18                 // Field url:Lorg/apache/dubbo/common/URL;
     121: putfield      #18                 // Field url:Lorg/apache/dubbo/common/URL;
     124: aload_2
     125: aload_0
     126: getfield      #17                 // Field urls:Ljava/util/List;
     129: putfield      #17                 // Field urls:Ljava/util/List;
     132: aload_2
     133: areturn
     134: aload_0
     135: areturn

  public org.apache.dubbo.rpc.RpcContext setInvocation(org.apache.dubbo.rpc.Invocation);
    Code:
       0: aload_0
       1: aload_1
       2: invokevirtual #104                // Method setInvocation:(Lorg/apache/dubbo/rpc/Invocation;)Lorg/apache/dubbo/rpc/RpcServiceContext;
       5: areturn

  public org.apache.dubbo.rpc.RpcContext setInvoker(org.apache.dubbo.rpc.Invoker);
    Code:
       0: aload_0
       1: aload_1
       2: invokevirtual #105                // Method setInvoker:(Lorg/apache/dubbo/rpc/Invoker;)Lorg/apache/dubbo/rpc/RpcServiceContext;
       5: areturn

  public org.apache.dubbo.rpc.RpcContext setInvokers(java.util.List);
    Code:
       0: aload_0
       1: aload_1
       2: invokevirtual #106                // Method setInvokers:(Ljava/util/List;)Lorg/apache/dubbo/rpc/RpcServiceContext;
       5: areturn

  public org.apache.dubbo.rpc.RpcContext setRemoteApplicationName(java.lang.String);
    Code:
       0: aload_0
       1: aload_1
       2: invokevirtual #107                // Method setRemoteApplicationName:(Ljava/lang/String;)Lorg/apache/dubbo/rpc/RpcServiceContext;
       5: areturn

  public org.apache.dubbo.rpc.RpcContext setRemoteAddress(java.net.InetSocketAddress);
    Code:
       0: aload_0
       1: aload_1
       2: invokevirtual #108                // Method setRemoteAddress:(Ljava/net/InetSocketAddress;)Lorg/apache/dubbo/rpc/RpcServiceContext;
       5: areturn

  public org.apache.dubbo.rpc.RpcContext setRemoteAddress(java.lang.String, int);
    Code:
       0: aload_0
       1: aload_1
       2: iload_2
       3: invokevirtual #109                // Method setRemoteAddress:(Ljava/lang/String;I)Lorg/apache/dubbo/rpc/RpcServiceContext;
       6: areturn

  public org.apache.dubbo.rpc.RpcContext setLocalAddress(java.net.InetSocketAddress);
    Code:
       0: aload_0
       1: aload_1
       2: invokevirtual #110                // Method setLocalAddress:(Ljava/net/InetSocketAddress;)Lorg/apache/dubbo/rpc/RpcServiceContext;
       5: areturn

  public org.apache.dubbo.rpc.RpcContext setLocalAddress(java.lang.String, int);
    Code:
       0: aload_0
       1: aload_1
       2: iload_2
       3: invokevirtual #111                // Method setLocalAddress:(Ljava/lang/String;I)Lorg/apache/dubbo/rpc/RpcServiceContext;
       6: areturn
}
