Compiled from "RpcServerContextAttachment.java"
class org.apache.dubbo.rpc.RpcServerContextAttachment$ObjectAttachmentMap implements java.util.Map<java.lang.String, java.lang.Object> {
  private final org.apache.dubbo.rpc.RpcServerContextAttachment adapter;

  public org.apache.dubbo.rpc.RpcServerContextAttachment$ObjectAttachmentMap(org.apache.dubbo.rpc.RpcServerContextAttachment);
    Code:
       0: aload_0
       1: invokespecial #1                  // Method java/lang/Object."<init>":()V
       4: aload_0
       5: aload_1
       6: putfield      #2                  // Field adapter:Lorg/apache/dubbo/rpc/RpcServerContextAttachment;
       9: return

  private java.util.Map<java.lang.String, java.lang.Object> getAttachments();
    Code:
       0: invokestatic  #3                  // Method org/apache/dubbo/rpc/RpcContext.getClientResponseContext:()Lorg/apache/dubbo/rpc/RpcContextAttachment;
       3: invokevirtual #4                  // Method org/apache/dubbo/rpc/RpcContextAttachment.getObjectAttachments:()Ljava/util/Map;
       6: astore_1
       7: invokestatic  #5                  // Method org/apache/dubbo/rpc/RpcContext.getServerResponseContext:()Lorg/apache/dubbo/rpc/RpcContextAttachment;
      10: invokevirtual #4                  // Method org/apache/dubbo/rpc/RpcContextAttachment.getObjectAttachments:()Ljava/util/Map;
      13: astore_2
      14: new           #6                  // class java/util/HashMap
      17: dup
      18: aload_1
      19: invokeinterface #7,  1            // InterfaceMethod java/util/Map.size:()I
      24: i2d
      25: aload_2
      26: invokeinterface #7,  1            // InterfaceMethod java/util/Map.size:()I
      31: i2d
      32: ldc2_w        #8                  // double 0.75d
      35: ddiv
      36: dadd
      37: d2i
      38: iconst_1
      39: iadd
      40: invokespecial #10                 // Method java/util/HashMap."<init>":(I)V
      43: astore_3
      44: aload_3
      45: aload_1
      46: invokeinterface #11,  2           // InterfaceMethod java/util/Map.putAll:(Ljava/util/Map;)V
      51: aload_3
      52: aload_2
      53: invokeinterface #11,  2           // InterfaceMethod java/util/Map.putAll:(Ljava/util/Map;)V
      58: aload_3
      59: areturn

  public int size();
    Code:
       0: aload_0
       1: invokespecial #12                 // Method getAttachments:()Ljava/util/Map;
       4: invokeinterface #7,  1            // InterfaceMethod java/util/Map.size:()I
       9: ireturn

  public boolean isEmpty();
    Code:
       0: invokestatic  #3                  // Method org/apache/dubbo/rpc/RpcContext.getClientResponseContext:()Lorg/apache/dubbo/rpc/RpcContextAttachment;
       3: invokevirtual #4                  // Method org/apache/dubbo/rpc/RpcContextAttachment.getObjectAttachments:()Ljava/util/Map;
       6: invokeinterface #13,  1           // InterfaceMethod java/util/Map.isEmpty:()Z
      11: ifeq          32
      14: invokestatic  #5                  // Method org/apache/dubbo/rpc/RpcContext.getServerResponseContext:()Lorg/apache/dubbo/rpc/RpcContextAttachment;
      17: invokevirtual #4                  // Method org/apache/dubbo/rpc/RpcContextAttachment.getObjectAttachments:()Ljava/util/Map;
      20: invokeinterface #13,  1           // InterfaceMethod java/util/Map.isEmpty:()Z
      25: ifeq          32
      28: iconst_1
      29: goto          33
      32: iconst_0
      33: ireturn

  public boolean containsKey(java.lang.Object);
    Code:
       0: invokestatic  #3                  // Method org/apache/dubbo/rpc/RpcContext.getClientResponseContext:()Lorg/apache/dubbo/rpc/RpcContextAttachment;
       3: invokevirtual #4                  // Method org/apache/dubbo/rpc/RpcContextAttachment.getObjectAttachments:()Ljava/util/Map;
       6: aload_1
       7: invokeinterface #14,  2           // InterfaceMethod java/util/Map.containsKey:(Ljava/lang/Object;)Z
      12: ifne          30
      15: invokestatic  #5                  // Method org/apache/dubbo/rpc/RpcContext.getServerResponseContext:()Lorg/apache/dubbo/rpc/RpcContextAttachment;
      18: invokevirtual #4                  // Method org/apache/dubbo/rpc/RpcContextAttachment.getObjectAttachments:()Ljava/util/Map;
      21: aload_1
      22: invokeinterface #14,  2           // InterfaceMethod java/util/Map.containsKey:(Ljava/lang/Object;)Z
      27: ifeq          34
      30: iconst_1
      31: goto          35
      34: iconst_0
      35: ireturn

  public boolean containsValue(java.lang.Object);
    Code:
       0: invokestatic  #3                  // Method org/apache/dubbo/rpc/RpcContext.getClientResponseContext:()Lorg/apache/dubbo/rpc/RpcContextAttachment;
       3: invokevirtual #4                  // Method org/apache/dubbo/rpc/RpcContextAttachment.getObjectAttachments:()Ljava/util/Map;
       6: aload_1
       7: invokeinterface #15,  2           // InterfaceMethod java/util/Map.containsValue:(Ljava/lang/Object;)Z
      12: ifne          30
      15: invokestatic  #5                  // Method org/apache/dubbo/rpc/RpcContext.getServerResponseContext:()Lorg/apache/dubbo/rpc/RpcContextAttachment;
      18: invokevirtual #4                  // Method org/apache/dubbo/rpc/RpcContextAttachment.getObjectAttachments:()Ljava/util/Map;
      21: aload_1
      22: invokeinterface #15,  2           // InterfaceMethod java/util/Map.containsValue:(Ljava/lang/Object;)Z
      27: ifeq          34
      30: iconst_1
      31: goto          35
      34: iconst_0
      35: ireturn

  public java.lang.Object get(java.lang.Object);
    Code:
       0: aload_1
       1: instanceof    #16                 // class java/lang/String
       4: ifeq          19
       7: aload_0
       8: getfield      #2                  // Field adapter:Lorg/apache/dubbo/rpc/RpcServerContextAttachment;
      11: aload_1
      12: checkcast     #16                 // class java/lang/String
      15: invokevirtual #17                 // Method org/apache/dubbo/rpc/RpcServerContextAttachment.getObjectAttachment:(Ljava/lang/String;)Ljava/lang/Object;
      18: areturn
      19: aconst_null
      20: areturn

  public java.lang.Object put(java.lang.String, java.lang.Object);
    Code:
       0: aload_0
       1: getfield      #2                  // Field adapter:Lorg/apache/dubbo/rpc/RpcServerContextAttachment;
       4: aload_1
       5: aload_2
       6: invokevirtual #18                 // Method org/apache/dubbo/rpc/RpcServerContextAttachment.setObjectAttachment:(Ljava/lang/String;Ljava/lang/Object;)Lorg/apache/dubbo/rpc/RpcContextAttachment;
       9: areturn

  public java.lang.Object remove(java.lang.Object);
    Code:
       0: aload_1
       1: instanceof    #16                 // class java/lang/String
       4: ifeq          19
       7: aload_0
       8: getfield      #2                  // Field adapter:Lorg/apache/dubbo/rpc/RpcServerContextAttachment;
      11: aload_1
      12: checkcast     #16                 // class java/lang/String
      15: invokevirtual #19                 // Method org/apache/dubbo/rpc/RpcServerContextAttachment.removeAttachment:(Ljava/lang/String;)Lorg/apache/dubbo/rpc/RpcContextAttachment;
      18: areturn
      19: aconst_null
      20: areturn

  public void putAll(java.util.Map<? extends java.lang.String, ?>);
    Code:
       0: aload_1
       1: invokeinterface #20,  1           // InterfaceMethod java/util/Map.entrySet:()Ljava/util/Set;
       6: invokeinterface #21,  1           // InterfaceMethod java/util/Set.iterator:()Ljava/util/Iterator;
      11: astore_2
      12: aload_2
      13: invokeinterface #22,  1           // InterfaceMethod java/util/Iterator.hasNext:()Z
      18: ifeq          57
      21: aload_2
      22: invokeinterface #23,  1           // InterfaceMethod java/util/Iterator.next:()Ljava/lang/Object;
      27: checkcast     #24                 // class java/util/Map$Entry
      30: astore_3
      31: aload_0
      32: getfield      #2                  // Field adapter:Lorg/apache/dubbo/rpc/RpcServerContextAttachment;
      35: aload_3
      36: invokeinterface #25,  1           // InterfaceMethod java/util/Map$Entry.getKey:()Ljava/lang/Object;
      41: checkcast     #16                 // class java/lang/String
      44: aload_3
      45: invokeinterface #26,  1           // InterfaceMethod java/util/Map$Entry.getValue:()Ljava/lang/Object;
      50: invokevirtual #18                 // Method org/apache/dubbo/rpc/RpcServerContextAttachment.setObjectAttachment:(Ljava/lang/String;Ljava/lang/Object;)Lorg/apache/dubbo/rpc/RpcContextAttachment;
      53: pop
      54: goto          12
      57: return

  public void clear();
    Code:
       0: aload_0
       1: getfield      #2                  // Field adapter:Lorg/apache/dubbo/rpc/RpcServerContextAttachment;
       4: invokevirtual #27                 // Method org/apache/dubbo/rpc/RpcServerContextAttachment.clearAttachments:()V
       7: return

  public java.util.Set<java.lang.String> keySet();
    Code:
       0: aload_0
       1: invokespecial #12                 // Method getAttachments:()Ljava/util/Map;
       4: invokeinterface #28,  1           // InterfaceMethod java/util/Map.keySet:()Ljava/util/Set;
       9: areturn

  public java.util.Collection<java.lang.Object> values();
    Code:
       0: aload_0
       1: invokespecial #12                 // Method getAttachments:()Ljava/util/Map;
       4: invokeinterface #29,  1           // InterfaceMethod java/util/Map.values:()Ljava/util/Collection;
       9: areturn

  public java.util.Set<java.util.Map$Entry<java.lang.String, java.lang.Object>> entrySet();
    Code:
       0: aload_0
       1: invokespecial #12                 // Method getAttachments:()Ljava/util/Map;
       4: invokeinterface #20,  1           // InterfaceMethod java/util/Map.entrySet:()Ljava/util/Set;
       9: areturn

  public java.lang.Object put(java.lang.Object, java.lang.Object);
    Code:
       0: aload_0
       1: aload_1
       2: checkcast     #16                 // class java/lang/String
       5: aload_2
       6: invokevirtual #30                 // Method put:(Ljava/lang/String;Ljava/lang/Object;)Ljava/lang/Object;
       9: areturn
}
