Compiled from "RpcServerContextAttachment.java"
public class org.apache.dubbo.rpc.RpcServerContextAttachment extends org.apache.dubbo.rpc.RpcContextAttachment {
  public org.apache.dubbo.rpc.RpcServerContextAttachment();
    Code:
       0: aload_0
       1: invokespecial #1                  // Method org/apache/dubbo/rpc/RpcContextAttachment."<init>":()V
       4: return

  public org.apache.dubbo.rpc.RpcContextAttachment copyOf(boolean);
    Code:
       0: new           #2                  // class java/lang/RuntimeException
       3: dup
       4: ldc           #3                  // String copyOf internal method, should not be invoke
       6: invokespecial #4                  // Method java/lang/RuntimeException."<init>":(Ljava/lang/String;)V
       9: athrow

  protected boolean isValid();
    Code:
       0: new           #2                  // class java/lang/RuntimeException
       3: dup
       4: ldc           #5                  // String isValid of is internal method, should not be invoke
       6: invokespecial #4                  // Method java/lang/RuntimeException."<init>":(Ljava/lang/String;)V
       9: athrow

  public org.apache.dubbo.rpc.RpcContextAttachment setObjectAttachment(java.lang.String, java.lang.Object);
    Code:
       0: invokestatic  #6                  // Method org/apache/dubbo/rpc/RpcContext.getServerResponseContext:()Lorg/apache/dubbo/rpc/RpcContextAttachment;
       3: aload_1
       4: aload_2
       5: invokevirtual #7                  // Method org/apache/dubbo/rpc/RpcContextAttachment.setObjectAttachment:(Ljava/lang/String;Ljava/lang/Object;)Lorg/apache/dubbo/rpc/RpcContextAttachment;
       8: pop
       9: aload_0
      10: areturn

  protected void setAsyncContext(org.apache.dubbo.rpc.AsyncContext);
    Code:
       0: invokestatic  #6                  // Method org/apache/dubbo/rpc/RpcContext.getServerResponseContext:()Lorg/apache/dubbo/rpc/RpcContextAttachment;
       3: aload_1
       4: invokevirtual #8                  // Method org/apache/dubbo/rpc/RpcContextAttachment.setAsyncContext:(Lorg/apache/dubbo/rpc/AsyncContext;)V
       7: return

  public boolean isAsyncStarted();
    Code:
       0: invokestatic  #6                  // Method org/apache/dubbo/rpc/RpcContext.getServerResponseContext:()Lorg/apache/dubbo/rpc/RpcContextAttachment;
       3: invokevirtual #9                  // Method org/apache/dubbo/rpc/RpcContextAttachment.isAsyncStarted:()Z
       6: ireturn

  public boolean stopAsync();
    Code:
       0: invokestatic  #6                  // Method org/apache/dubbo/rpc/RpcContext.getServerResponseContext:()Lorg/apache/dubbo/rpc/RpcContextAttachment;
       3: invokevirtual #10                 // Method org/apache/dubbo/rpc/RpcContextAttachment.stopAsync:()Z
       6: ireturn

  public org.apache.dubbo.rpc.AsyncContext getAsyncContext();
    Code:
       0: invokestatic  #6                  // Method org/apache/dubbo/rpc/RpcContext.getServerResponseContext:()Lorg/apache/dubbo/rpc/RpcContextAttachment;
       3: invokevirtual #11                 // Method org/apache/dubbo/rpc/RpcContextAttachment.getAsyncContext:()Lorg/apache/dubbo/rpc/AsyncContext;
       6: areturn

  public java.lang.String getAttachment(java.lang.String);
    Code:
       0: aload_0
       1: aload_1
       2: invokevirtual #12                 // Method getObjectAttachment:(Ljava/lang/String;)Ljava/lang/Object;
       5: astore_2
       6: aload_2
       7: instanceof    #13                 // class java/lang/String
      10: ifeq          18
      13: aload_2
      14: checkcast     #13                 // class java/lang/String
      17: areturn
      18: aconst_null
      19: areturn

  public java.lang.Object getObjectAttachment(java.lang.String);
    Code:
       0: invokestatic  #6                  // Method org/apache/dubbo/rpc/RpcContext.getServerResponseContext:()Lorg/apache/dubbo/rpc/RpcContextAttachment;
       3: aload_1
       4: invokevirtual #14                 // Method org/apache/dubbo/rpc/RpcContextAttachment.getObjectAttachment:(Ljava/lang/String;)Ljava/lang/Object;
       7: astore_2
       8: aload_2
       9: ifnonnull     20
      12: invokestatic  #15                 // Method org/apache/dubbo/rpc/RpcContext.getClientResponseContext:()Lorg/apache/dubbo/rpc/RpcContextAttachment;
      15: aload_1
      16: invokevirtual #14                 // Method org/apache/dubbo/rpc/RpcContextAttachment.getObjectAttachment:(Ljava/lang/String;)Ljava/lang/Object;
      19: astore_2
      20: aload_2
      21: areturn

  public org.apache.dubbo.rpc.RpcContextAttachment setAttachment(java.lang.String, java.lang.String);
    Code:
       0: invokestatic  #6                  // Method org/apache/dubbo/rpc/RpcContext.getServerResponseContext:()Lorg/apache/dubbo/rpc/RpcContextAttachment;
       3: aload_1
       4: aload_2
       5: invokevirtual #16                 // Method org/apache/dubbo/rpc/RpcContextAttachment.setAttachment:(Ljava/lang/String;Ljava/lang/String;)Lorg/apache/dubbo/rpc/RpcContextAttachment;
       8: areturn

  public org.apache.dubbo.rpc.RpcContextAttachment setAttachment(java.lang.String, java.lang.Object);
    Code:
       0: invokestatic  #6                  // Method org/apache/dubbo/rpc/RpcContext.getServerResponseContext:()Lorg/apache/dubbo/rpc/RpcContextAttachment;
       3: aload_1
       4: aload_2
       5: invokevirtual #17                 // Method org/apache/dubbo/rpc/RpcContextAttachment.setAttachment:(Ljava/lang/String;Ljava/lang/Object;)Lorg/apache/dubbo/rpc/RpcContextAttachment;
       8: areturn

  public org.apache.dubbo.rpc.RpcContextAttachment removeAttachment(java.lang.String);
    Code:
       0: invokestatic  #6                  // Method org/apache/dubbo/rpc/RpcContext.getServerResponseContext:()Lorg/apache/dubbo/rpc/RpcContextAttachment;
       3: aload_1
       4: invokevirtual #18                 // Method org/apache/dubbo/rpc/RpcContextAttachment.removeAttachment:(Ljava/lang/String;)Lorg/apache/dubbo/rpc/RpcContextAttachment;
       7: pop
       8: invokestatic  #15                 // Method org/apache/dubbo/rpc/RpcContext.getClientResponseContext:()Lorg/apache/dubbo/rpc/RpcContextAttachment;
      11: aload_1
      12: invokevirtual #18                 // Method org/apache/dubbo/rpc/RpcContextAttachment.removeAttachment:(Ljava/lang/String;)Lorg/apache/dubbo/rpc/RpcContextAttachment;
      15: pop
      16: aload_0
      17: areturn

  public java.util.Map<java.lang.String, java.lang.String> getAttachments();
    Code:
       0: new           #19                 // class org/apache/dubbo/rpc/AttachmentsAdapter$ObjectToStringMap
       3: dup
       4: new           #20                 // class org/apache/dubbo/rpc/RpcServerContextAttachment$ObjectAttachmentMap
       7: dup
       8: aload_0
       9: invokespecial #21                 // Method org/apache/dubbo/rpc/RpcServerContextAttachment$ObjectAttachmentMap."<init>":(Lorg/apache/dubbo/rpc/RpcServerContextAttachment;)V
      12: invokespecial #22                 // Method org/apache/dubbo/rpc/AttachmentsAdapter$ObjectToStringMap."<init>":(Ljava/util/Map;)V
      15: areturn

  public java.util.Map<java.lang.String, java.lang.Object> getObjectAttachments();
    Code:
       0: new           #20                 // class org/apache/dubbo/rpc/RpcServerContextAttachment$ObjectAttachmentMap
       3: dup
       4: aload_0
       5: invokespecial #21                 // Method org/apache/dubbo/rpc/RpcServerContextAttachment$ObjectAttachmentMap."<init>":(Lorg/apache/dubbo/rpc/RpcServerContextAttachment;)V
       8: areturn

  public org.apache.dubbo.rpc.RpcContextAttachment setAttachments(java.util.Map<java.lang.String, java.lang.String>);
    Code:
       0: invokestatic  #6                  // Method org/apache/dubbo/rpc/RpcContext.getServerResponseContext:()Lorg/apache/dubbo/rpc/RpcContextAttachment;
       3: aload_1
       4: invokevirtual #23                 // Method org/apache/dubbo/rpc/RpcContextAttachment.setAttachments:(Ljava/util/Map;)Lorg/apache/dubbo/rpc/RpcContextAttachment;
       7: pop
       8: invokestatic  #15                 // Method org/apache/dubbo/rpc/RpcContext.getClientResponseContext:()Lorg/apache/dubbo/rpc/RpcContextAttachment;
      11: invokevirtual #24                 // Method org/apache/dubbo/rpc/RpcContextAttachment.clearAttachments:()V
      14: aload_0
      15: areturn

  public org.apache.dubbo.rpc.RpcContextAttachment setObjectAttachments(java.util.Map<java.lang.String, java.lang.Object>);
    Code:
       0: invokestatic  #6                  // Method org/apache/dubbo/rpc/RpcContext.getServerResponseContext:()Lorg/apache/dubbo/rpc/RpcContextAttachment;
       3: aload_1
       4: invokevirtual #25                 // Method org/apache/dubbo/rpc/RpcContextAttachment.setObjectAttachments:(Ljava/util/Map;)Lorg/apache/dubbo/rpc/RpcContextAttachment;
       7: pop
       8: invokestatic  #15                 // Method org/apache/dubbo/rpc/RpcContext.getClientResponseContext:()Lorg/apache/dubbo/rpc/RpcContextAttachment;
      11: invokevirtual #24                 // Method org/apache/dubbo/rpc/RpcContextAttachment.clearAttachments:()V
      14: aload_0
      15: areturn

  public void clearAttachments();
    Code:
       0: invokestatic  #6                  // Method org/apache/dubbo/rpc/RpcContext.getServerResponseContext:()Lorg/apache/dubbo/rpc/RpcContextAttachment;
       3: invokevirtual #24                 // Method org/apache/dubbo/rpc/RpcContextAttachment.clearAttachments:()V
       6: invokestatic  #15                 // Method org/apache/dubbo/rpc/RpcContext.getClientResponseContext:()Lorg/apache/dubbo/rpc/RpcContextAttachment;
       9: invokevirtual #24                 // Method org/apache/dubbo/rpc/RpcContextAttachment.clearAttachments:()V
      12: return

  public java.util.Map<java.lang.String, java.lang.Object> get();
    Code:
       0: aload_0
       1: invokevirtual #26                 // Method getObjectAttachments:()Ljava/util/Map;
       4: areturn

  public org.apache.dubbo.rpc.RpcContextAttachment set(java.lang.String, java.lang.Object);
    Code:
       0: aload_0
       1: aload_1
       2: aload_2
       3: invokevirtual #27                 // Method setAttachment:(Ljava/lang/String;Ljava/lang/Object;)Lorg/apache/dubbo/rpc/RpcContextAttachment;
       6: areturn

  public org.apache.dubbo.rpc.RpcContextAttachment remove(java.lang.String);
    Code:
       0: aload_0
       1: aload_1
       2: invokevirtual #28                 // Method removeAttachment:(Ljava/lang/String;)Lorg/apache/dubbo/rpc/RpcContextAttachment;
       5: areturn

  public java.lang.Object get(java.lang.String);
    Code:
       0: aload_0
       1: aload_1
       2: invokevirtual #29                 // Method getAttachment:(Ljava/lang/String;)Ljava/lang/String;
       5: areturn

  public org.apache.dubbo.rpc.RpcContext remove(java.lang.String);
    Code:
       0: aload_0
       1: aload_1
       2: invokevirtual #30                 // Method remove:(Ljava/lang/String;)Lorg/apache/dubbo/rpc/RpcContextAttachment;
       5: areturn

  public org.apache.dubbo.rpc.RpcContext set(java.lang.String, java.lang.Object);
    Code:
       0: aload_0
       1: aload_1
       2: aload_2
       3: invokevirtual #31                 // Method set:(Ljava/lang/String;Ljava/lang/Object;)Lorg/apache/dubbo/rpc/RpcContextAttachment;
       6: areturn

  public org.apache.dubbo.rpc.RpcContext setObjectAttachments(java.util.Map);
    Code:
       0: aload_0
       1: aload_1
       2: invokevirtual #32                 // Method setObjectAttachments:(Ljava/util/Map;)Lorg/apache/dubbo/rpc/RpcContextAttachment;
       5: areturn

  public org.apache.dubbo.rpc.RpcContext setAttachments(java.util.Map);
    Code:
       0: aload_0
       1: aload_1
       2: invokevirtual #33                 // Method setAttachments:(Ljava/util/Map;)Lorg/apache/dubbo/rpc/RpcContextAttachment;
       5: areturn

  public org.apache.dubbo.rpc.RpcContext removeAttachment(java.lang.String);
    Code:
       0: aload_0
       1: aload_1
       2: invokevirtual #28                 // Method removeAttachment:(Ljava/lang/String;)Lorg/apache/dubbo/rpc/RpcContextAttachment;
       5: areturn

  public org.apache.dubbo.rpc.RpcContext setObjectAttachment(java.lang.String, java.lang.Object);
    Code:
       0: aload_0
       1: aload_1
       2: aload_2
       3: invokevirtual #34                 // Method setObjectAttachment:(Ljava/lang/String;Ljava/lang/Object;)Lorg/apache/dubbo/rpc/RpcContextAttachment;
       6: areturn

  public org.apache.dubbo.rpc.RpcContext setAttachment(java.lang.String, java.lang.Object);
    Code:
       0: aload_0
       1: aload_1
       2: aload_2
       3: invokevirtual #27                 // Method setAttachment:(Ljava/lang/String;Ljava/lang/Object;)Lorg/apache/dubbo/rpc/RpcContextAttachment;
       6: areturn

  public org.apache.dubbo.rpc.RpcContext setAttachment(java.lang.String, java.lang.String);
    Code:
       0: aload_0
       1: aload_1
       2: aload_2
       3: invokevirtual #35                 // Method setAttachment:(Ljava/lang/String;Ljava/lang/String;)Lorg/apache/dubbo/rpc/RpcContextAttachment;
       6: areturn
}
