Compiled from "StatusRpcException.java"
public class org.apache.dubbo.rpc.StatusRpcException extends org.apache.dubbo.rpc.RpcException {
  private final org.apache.dubbo.rpc.TriRpcStatus status;

  public org.apache.dubbo.rpc.TriRpcStatus getStatus();
    Code:
       0: aload_0
       1: getfield      #1                  // Field status:Lorg/apache/dubbo/rpc/TriRpcStatus;
       4: areturn

  public org.apache.dubbo.rpc.StatusRpcException(org.apache.dubbo.rpc.TriRpcStatus);
    Code:
       0: aload_0
       1: aload_1
       2: getfield      #2                  // Field org/apache/dubbo/rpc/TriRpcStatus.code:Lorg/apache/dubbo/rpc/TriRpcStatus$Code;
       5: invokestatic  #3                  // Method org/apache/dubbo/rpc/TriRpcStatus.triCodeToDubboCode:(Lorg/apache/dubbo/rpc/TriRpcStatus$Code;)I
       8: aload_1
       9: invokevirtual #4                  // Method org/apache/dubbo/rpc/TriRpcStatus.toMessageWithoutCause:()Ljava/lang/String;
      12: aload_1
      13: getfield      #5                  // Field org/apache/dubbo/rpc/TriRpcStatus.cause:Ljava/lang/Throwable;
      16: invokespecial #6                  // Method org/apache/dubbo/rpc/RpcException."<init>":(ILjava/lang/String;Ljava/lang/Throwable;)V
      19: aload_0
      20: aload_1
      21: putfield      #1                  // Field status:Lorg/apache/dubbo/rpc/TriRpcStatus;
      24: return
}
