Compiled from "TimeoutCountDown.java"
public final class org.apache.dubbo.rpc.TimeoutCountDown implements java.lang.Comparable<org.apache.dubbo.rpc.TimeoutCountDown> {
  private final long timeoutInMillis;

  private final long deadlineInNanos;

  private volatile boolean expired;

  public static org.apache.dubbo.rpc.TimeoutCountDown newCountDown(long, java.util.concurrent.TimeUnit);
    Code:
       0: new           #1                  // class org/apache/dubbo/rpc/TimeoutCountDown
       3: dup
       4: lload_0
       5: aload_2
       6: invokespecial #2                  // Method "<init>":(JLjava/util/concurrent/TimeUnit;)V
       9: areturn

  private org.apache.dubbo.rpc.TimeoutCountDown(long, java.util.concurrent.TimeUnit);
    Code:
       0: aload_0
       1: invokespecial #3                  // Method java/lang/Object."<init>":()V
       4: aload_0
       5: getstatic     #4                  // Field java/util/concurrent/TimeUnit.MILLISECONDS:Ljava/util/concurrent/TimeUnit;
       8: lload_1
       9: aload_3
      10: invokevirtual #5                  // Method java/util/concurrent/TimeUnit.convert:(JLjava/util/concurrent/TimeUnit;)J
      13: putfield      #6                  // Field timeoutInMillis:J
      16: aload_0
      17: invokestatic  #7                  // Method java/lang/System.nanoTime:()J
      20: getstatic     #8                  // Field java/util/concurrent/TimeUnit.NANOSECONDS:Ljava/util/concurrent/TimeUnit;
      23: lload_1
      24: aload_3
      25: invokevirtual #5                  // Method java/util/concurrent/TimeUnit.convert:(JLjava/util/concurrent/TimeUnit;)J
      28: ladd
      29: putfield      #9                  // Field deadlineInNanos:J
      32: return

  public long getTimeoutInMilli();
    Code:
       0: aload_0
       1: getfield      #6                  // Field timeoutInMillis:J
       4: lreturn

  public boolean isExpired();
    Code:
       0: aload_0
       1: getfield      #10                 // Field expired:Z
       4: ifne          30
       7: aload_0
       8: getfield      #9                  // Field deadlineInNanos:J
      11: invokestatic  #7                  // Method java/lang/System.nanoTime:()J
      14: lsub
      15: lconst_0
      16: lcmp
      17: ifgt          28
      20: aload_0
      21: iconst_1
      22: putfield      #10                 // Field expired:Z
      25: goto          30
      28: iconst_0
      29: ireturn
      30: iconst_1
      31: ireturn

  public long timeRemaining(java.util.concurrent.TimeUnit);
    Code:
       0: invokestatic  #7                  // Method java/lang/System.nanoTime:()J
       3: lstore_2
       4: aload_0
       5: getfield      #10                 // Field expired:Z
       8: ifne          27
      11: aload_0
      12: getfield      #9                  // Field deadlineInNanos:J
      15: lload_2
      16: lsub
      17: lconst_0
      18: lcmp
      19: ifgt          27
      22: aload_0
      23: iconst_1
      24: putfield      #10                 // Field expired:Z
      27: aload_1
      28: aload_0
      29: getfield      #9                  // Field deadlineInNanos:J
      32: lload_2
      33: lsub
      34: getstatic     #8                  // Field java/util/concurrent/TimeUnit.NANOSECONDS:Ljava/util/concurrent/TimeUnit;
      37: invokevirtual #5                  // Method java/util/concurrent/TimeUnit.convert:(JLjava/util/concurrent/TimeUnit;)J
      40: lreturn

  public long elapsedMillis();
    Code:
       0: aload_0
       1: invokevirtual #11                 // Method isExpired:()Z
       4: ifeq          30
       7: aload_0
       8: getfield      #6                  // Field timeoutInMillis:J
      11: getstatic     #4                  // Field java/util/concurrent/TimeUnit.MILLISECONDS:Ljava/util/concurrent/TimeUnit;
      14: invokestatic  #7                  // Method java/lang/System.nanoTime:()J
      17: aload_0
      18: getfield      #9                  // Field deadlineInNanos:J
      21: lsub
      22: getstatic     #8                  // Field java/util/concurrent/TimeUnit.NANOSECONDS:Ljava/util/concurrent/TimeUnit;
      25: invokevirtual #5                  // Method java/util/concurrent/TimeUnit.convert:(JLjava/util/concurrent/TimeUnit;)J
      28: ladd
      29: lreturn
      30: aload_0
      31: getfield      #6                  // Field timeoutInMillis:J
      34: getstatic     #4                  // Field java/util/concurrent/TimeUnit.MILLISECONDS:Ljava/util/concurrent/TimeUnit;
      37: aload_0
      38: getfield      #9                  // Field deadlineInNanos:J
      41: invokestatic  #7                  // Method java/lang/System.nanoTime:()J
      44: lsub
      45: getstatic     #8                  // Field java/util/concurrent/TimeUnit.NANOSECONDS:Ljava/util/concurrent/TimeUnit;
      48: invokevirtual #5                  // Method java/util/concurrent/TimeUnit.convert:(JLjava/util/concurrent/TimeUnit;)J
      51: lsub
      52: lreturn

  public java.lang.String toString();
    Code:
       0: getstatic     #4                  // Field java/util/concurrent/TimeUnit.MILLISECONDS:Ljava/util/concurrent/TimeUnit;
       3: aload_0
       4: getfield      #9                  // Field deadlineInNanos:J
       7: getstatic     #8                  // Field java/util/concurrent/TimeUnit.NANOSECONDS:Ljava/util/concurrent/TimeUnit;
      10: invokevirtual #5                  // Method java/util/concurrent/TimeUnit.convert:(JLjava/util/concurrent/TimeUnit;)J
      13: lstore_1
      14: aload_0
      15: getstatic     #4                  // Field java/util/concurrent/TimeUnit.MILLISECONDS:Ljava/util/concurrent/TimeUnit;
      18: invokevirtual #12                 // Method timeRemaining:(Ljava/util/concurrent/TimeUnit;)J
      21: lstore_3
      22: new           #13                 // class java/lang/StringBuilder
      25: dup
      26: invokespecial #14                 // Method java/lang/StringBuilder."<init>":()V
      29: astore        5
      31: aload         5
      33: ldc           #15                 // String Total timeout value -
      35: invokevirtual #16                 // Method java/lang/StringBuilder.append:(Ljava/lang/String;)Ljava/lang/StringBuilder;
      38: pop
      39: aload         5
      41: lload_1
      42: invokevirtual #17                 // Method java/lang/StringBuilder.append:(J)Ljava/lang/StringBuilder;
      45: pop
      46: aload         5
      48: ldc           #18                 // String , times remaining -
      50: invokevirtual #16                 // Method java/lang/StringBuilder.append:(Ljava/lang/String;)Ljava/lang/StringBuilder;
      53: pop
      54: aload         5
      56: lload_3
      57: invokevirtual #17                 // Method java/lang/StringBuilder.append:(J)Ljava/lang/StringBuilder;
      60: pop
      61: aload         5
      63: invokevirtual #19                 // Method java/lang/StringBuilder.toString:()Ljava/lang/String;
      66: areturn

  public int compareTo(org.apache.dubbo.rpc.TimeoutCountDown);
    Code:
       0: aload_0
       1: getfield      #9                  // Field deadlineInNanos:J
       4: aload_1
       5: getfield      #9                  // Field deadlineInNanos:J
       8: lsub
       9: lstore_2
      10: lload_2
      11: lconst_0
      12: lcmp
      13: ifge          18
      16: iconst_m1
      17: ireturn
      18: lload_2
      19: lconst_0
      20: lcmp
      21: ifle          26
      24: iconst_1
      25: ireturn
      26: iconst_0
      27: ireturn

  public int compareTo(java.lang.Object);
    Code:
       0: aload_0
       1: aload_1
       2: checkcast     #1                  // class org/apache/dubbo/rpc/TimeoutCountDown
       5: invokevirtual #20                 // Method compareTo:(Lorg/apache/dubbo/rpc/TimeoutCountDown;)I
       8: ireturn
}
