Compiled from "TriRpcStatus.java"
public final class org.apache.dubbo.rpc.TriRpcStatus$Code extends java.lang.Enum<org.apache.dubbo.rpc.TriRpcStatus$Code> {
  public static final org.apache.dubbo.rpc.TriRpcStatus$Code OK;

  public static final org.apache.dubbo.rpc.TriRpcStatus$Code CANCELLED;

  public static final org.apache.dubbo.rpc.TriRpcStatus$Code UNKNOWN;

  public static final org.apache.dubbo.rpc.TriRpcStatus$Code INVALID_ARGUMENT;

  public static final org.apache.dubbo.rpc.TriRpcStatus$Code DEADLINE_EXCEEDED;

  public static final org.apache.dubbo.rpc.TriRpcStatus$Code NOT_FOUND;

  public static final org.apache.dubbo.rpc.TriRpcStatus$Code ALREADY_EXISTS;

  public static final org.apache.dubbo.rpc.TriRpcStatus$Code PERMISSION_DENIED;

  public static final org.apache.dubbo.rpc.TriRpcStatus$Code RESOURCE_EXHAUSTED;

  public static final org.apache.dubbo.rpc.TriRpcStatus$Code FAILED_PRECONDITION;

  public static final org.apache.dubbo.rpc.TriRpcStatus$Code ABORTED;

  public static final org.apache.dubbo.rpc.TriRpcStatus$Code OUT_OF_RANGE;

  public static final org.apache.dubbo.rpc.TriRpcStatus$Code UNIMPLEMENTED;

  public static final org.apache.dubbo.rpc.TriRpcStatus$Code INTERNAL;

  public static final org.apache.dubbo.rpc.TriRpcStatus$Code UNAVAILABLE;

  public static final org.apache.dubbo.rpc.TriRpcStatus$Code DATA_LOSS;

  public static final org.apache.dubbo.rpc.TriRpcStatus$Code UNAUTHENTICATED;

  public final int code;

  private static final org.apache.dubbo.rpc.TriRpcStatus$Code[] $VALUES;

  public static org.apache.dubbo.rpc.TriRpcStatus$Code[] values();
    Code:
       0: getstatic     #1                  // Field $VALUES:[Lorg/apache/dubbo/rpc/TriRpcStatus$Code;
       3: invokevirtual #2                  // Method "[Lorg/apache/dubbo/rpc/TriRpcStatus$Code;".clone:()Ljava/lang/Object;
       6: checkcast     #3                  // class "[Lorg/apache/dubbo/rpc/TriRpcStatus$Code;"
       9: areturn

  public static org.apache.dubbo.rpc.TriRpcStatus$Code valueOf(java.lang.String);
    Code:
       0: ldc           #4                  // class org/apache/dubbo/rpc/TriRpcStatus$Code
       2: aload_0
       3: invokestatic  #5                  // Method java/lang/Enum.valueOf:(Ljava/lang/Class;Ljava/lang/String;)Ljava/lang/Enum;
       6: checkcast     #4                  // class org/apache/dubbo/rpc/TriRpcStatus$Code
       9: areturn

  private org.apache.dubbo.rpc.TriRpcStatus$Code(int);
    Code:
       0: aload_0
       1: aload_1
       2: iload_2
       3: invokespecial #6                  // Method java/lang/Enum."<init>":(Ljava/lang/String;I)V
       6: aload_0
       7: iload_3
       8: putfield      #7                  // Field code:I
      11: return

  public static boolean isOk(java.lang.Integer);
    Code:
       0: aload_0
       1: invokevirtual #8                  // Method java/lang/Integer.intValue:()I
       4: getstatic     #9                  // Field OK:Lorg/apache/dubbo/rpc/TriRpcStatus$Code;
       7: getfield      #7                  // Field code:I
      10: if_icmpne     17
      13: iconst_1
      14: goto          18
      17: iconst_0
      18: ireturn

  public static org.apache.dubbo.rpc.TriRpcStatus$Code fromCode(int);
    Code:
       0: invokestatic  #10                 // Method values:()[Lorg/apache/dubbo/rpc/TriRpcStatus$Code;
       3: astore_1
       4: aload_1
       5: arraylength
       6: istore_2
       7: iconst_0
       8: istore_3
       9: iload_3
      10: iload_2
      11: if_icmpge     37
      14: aload_1
      15: iload_3
      16: aaload
      17: astore        4
      19: aload         4
      21: getfield      #7                  // Field code:I
      24: iload_0
      25: if_icmpne     31
      28: aload         4
      30: areturn
      31: iinc          3, 1
      34: goto          9
      37: new           #11                 // class java/lang/IllegalStateException
      40: dup
      41: new           #12                 // class java/lang/StringBuilder
      44: dup
      45: invokespecial #13                 // Method java/lang/StringBuilder."<init>":()V
      48: ldc           #14                 // String Can not find status for code:
      50: invokevirtual #15                 // Method java/lang/StringBuilder.append:(Ljava/lang/String;)Ljava/lang/StringBuilder;
      53: iload_0
      54: invokevirtual #16                 // Method java/lang/StringBuilder.append:(I)Ljava/lang/StringBuilder;
      57: invokevirtual #17                 // Method java/lang/StringBuilder.toString:()Ljava/lang/String;
      60: invokespecial #18                 // Method java/lang/IllegalStateException."<init>":(Ljava/lang/String;)V
      63: athrow

  static {};
    Code:
       0: new           #4                  // class org/apache/dubbo/rpc/TriRpcStatus$Code
       3: dup
       4: ldc           #19                 // String OK
       6: iconst_0
       7: iconst_0
       8: invokespecial #20                 // Method "<init>":(Ljava/lang/String;II)V
      11: putstatic     #9                  // Field OK:Lorg/apache/dubbo/rpc/TriRpcStatus$Code;
      14: new           #4                  // class org/apache/dubbo/rpc/TriRpcStatus$Code
      17: dup
      18: ldc           #21                 // String CANCELLED
      20: iconst_1
      21: iconst_1
      22: invokespecial #20                 // Method "<init>":(Ljava/lang/String;II)V
      25: putstatic     #22                 // Field CANCELLED:Lorg/apache/dubbo/rpc/TriRpcStatus$Code;
      28: new           #4                  // class org/apache/dubbo/rpc/TriRpcStatus$Code
      31: dup
      32: ldc           #23                 // String UNKNOWN
      34: iconst_2
      35: iconst_2
      36: invokespecial #20                 // Method "<init>":(Ljava/lang/String;II)V
      39: putstatic     #24                 // Field UNKNOWN:Lorg/apache/dubbo/rpc/TriRpcStatus$Code;
      42: new           #4                  // class org/apache/dubbo/rpc/TriRpcStatus$Code
      45: dup
      46: ldc           #25                 // String INVALID_ARGUMENT
      48: iconst_3
      49: iconst_3
      50: invokespecial #20                 // Method "<init>":(Ljava/lang/String;II)V
      53: putstatic     #26                 // Field INVALID_ARGUMENT:Lorg/apache/dubbo/rpc/TriRpcStatus$Code;
      56: new           #4                  // class org/apache/dubbo/rpc/TriRpcStatus$Code
      59: dup
      60: ldc           #27                 // String DEADLINE_EXCEEDED
      62: iconst_4
      63: iconst_4
      64: invokespecial #20                 // Method "<init>":(Ljava/lang/String;II)V
      67: putstatic     #28                 // Field DEADLINE_EXCEEDED:Lorg/apache/dubbo/rpc/TriRpcStatus$Code;
      70: new           #4                  // class org/apache/dubbo/rpc/TriRpcStatus$Code
      73: dup
      74: ldc           #29                 // String NOT_FOUND
      76: iconst_5
      77: iconst_5
      78: invokespecial #20                 // Method "<init>":(Ljava/lang/String;II)V
      81: putstatic     #30                 // Field NOT_FOUND:Lorg/apache/dubbo/rpc/TriRpcStatus$Code;
      84: new           #4                  // class org/apache/dubbo/rpc/TriRpcStatus$Code
      87: dup
      88: ldc           #31                 // String ALREADY_EXISTS
      90: bipush        6
      92: bipush        6
      94: invokespecial #20                 // Method "<init>":(Ljava/lang/String;II)V
      97: putstatic     #32                 // Field ALREADY_EXISTS:Lorg/apache/dubbo/rpc/TriRpcStatus$Code;
     100: new           #4                  // class org/apache/dubbo/rpc/TriRpcStatus$Code
     103: dup
     104: ldc           #33                 // String PERMISSION_DENIED
     106: bipush        7
     108: bipush        7
     110: invokespecial #20                 // Method "<init>":(Ljava/lang/String;II)V
     113: putstatic     #34                 // Field PERMISSION_DENIED:Lorg/apache/dubbo/rpc/TriRpcStatus$Code;
     116: new           #4                  // class org/apache/dubbo/rpc/TriRpcStatus$Code
     119: dup
     120: ldc           #35                 // String RESOURCE_EXHAUSTED
     122: bipush        8
     124: bipush        8
     126: invokespecial #20                 // Method "<init>":(Ljava/lang/String;II)V
     129: putstatic     #36                 // Field RESOURCE_EXHAUSTED:Lorg/apache/dubbo/rpc/TriRpcStatus$Code;
     132: new           #4                  // class org/apache/dubbo/rpc/TriRpcStatus$Code
     135: dup
     136: ldc           #37                 // String FAILED_PRECONDITION
     138: bipush        9
     140: bipush        9
     142: invokespecial #20                 // Method "<init>":(Ljava/lang/String;II)V
     145: putstatic     #38                 // Field FAILED_PRECONDITION:Lorg/apache/dubbo/rpc/TriRpcStatus$Code;
     148: new           #4                  // class org/apache/dubbo/rpc/TriRpcStatus$Code
     151: dup
     152: ldc           #39                 // String ABORTED
     154: bipush        10
     156: bipush        10
     158: invokespecial #20                 // Method "<init>":(Ljava/lang/String;II)V
     161: putstatic     #40                 // Field ABORTED:Lorg/apache/dubbo/rpc/TriRpcStatus$Code;
     164: new           #4                  // class org/apache/dubbo/rpc/TriRpcStatus$Code
     167: dup
     168: ldc           #41                 // String OUT_OF_RANGE
     170: bipush        11
     172: bipush        11
     174: invokespecial #20                 // Method "<init>":(Ljava/lang/String;II)V
     177: putstatic     #42                 // Field OUT_OF_RANGE:Lorg/apache/dubbo/rpc/TriRpcStatus$Code;
     180: new           #4                  // class org/apache/dubbo/rpc/TriRpcStatus$Code
     183: dup
     184: ldc           #43                 // String UNIMPLEMENTED
     186: bipush        12
     188: bipush        12
     190: invokespecial #20                 // Method "<init>":(Ljava/lang/String;II)V
     193: putstatic     #44                 // Field UNIMPLEMENTED:Lorg/apache/dubbo/rpc/TriRpcStatus$Code;
     196: new           #4                  // class org/apache/dubbo/rpc/TriRpcStatus$Code
     199: dup
     200: ldc           #45                 // String INTERNAL
     202: bipush        13
     204: bipush        13
     206: invokespecial #20                 // Method "<init>":(Ljava/lang/String;II)V
     209: putstatic     #46                 // Field INTERNAL:Lorg/apache/dubbo/rpc/TriRpcStatus$Code;
     212: new           #4                  // class org/apache/dubbo/rpc/TriRpcStatus$Code
     215: dup
     216: ldc           #47                 // String UNAVAILABLE
     218: bipush        14
     220: bipush        14
     222: invokespecial #20                 // Method "<init>":(Ljava/lang/String;II)V
     225: putstatic     #48                 // Field UNAVAILABLE:Lorg/apache/dubbo/rpc/TriRpcStatus$Code;
     228: new           #4                  // class org/apache/dubbo/rpc/TriRpcStatus$Code
     231: dup
     232: ldc           #49                 // String DATA_LOSS
     234: bipush        15
     236: bipush        15
     238: invokespecial #20                 // Method "<init>":(Ljava/lang/String;II)V
     241: putstatic     #50                 // Field DATA_LOSS:Lorg/apache/dubbo/rpc/TriRpcStatus$Code;
     244: new           #4                  // class org/apache/dubbo/rpc/TriRpcStatus$Code
     247: dup
     248: ldc           #51                 // String UNAUTHENTICATED
     250: bipush        16
     252: bipush        16
     254: invokespecial #20                 // Method "<init>":(Ljava/lang/String;II)V
     257: putstatic     #52                 // Field UNAUTHENTICATED:Lorg/apache/dubbo/rpc/TriRpcStatus$Code;
     260: bipush        17
     262: anewarray     #4                  // class org/apache/dubbo/rpc/TriRpcStatus$Code
     265: dup
     266: iconst_0
     267: getstatic     #9                  // Field OK:Lorg/apache/dubbo/rpc/TriRpcStatus$Code;
     270: aastore
     271: dup
     272: iconst_1
     273: getstatic     #22                 // Field CANCELLED:Lorg/apache/dubbo/rpc/TriRpcStatus$Code;
     276: aastore
     277: dup
     278: iconst_2
     279: getstatic     #24                 // Field UNKNOWN:Lorg/apache/dubbo/rpc/TriRpcStatus$Code;
     282: aastore
     283: dup
     284: iconst_3
     285: getstatic     #26                 // Field INVALID_ARGUMENT:Lorg/apache/dubbo/rpc/TriRpcStatus$Code;
     288: aastore
     289: dup
     290: iconst_4
     291: getstatic     #28                 // Field DEADLINE_EXCEEDED:Lorg/apache/dubbo/rpc/TriRpcStatus$Code;
     294: aastore
     295: dup
     296: iconst_5
     297: getstatic     #30                 // Field NOT_FOUND:Lorg/apache/dubbo/rpc/TriRpcStatus$Code;
     300: aastore
     301: dup
     302: bipush        6
     304: getstatic     #32                 // Field ALREADY_EXISTS:Lorg/apache/dubbo/rpc/TriRpcStatus$Code;
     307: aastore
     308: dup
     309: bipush        7
     311: getstatic     #34                 // Field PERMISSION_DENIED:Lorg/apache/dubbo/rpc/TriRpcStatus$Code;
     314: aastore
     315: dup
     316: bipush        8
     318: getstatic     #36                 // Field RESOURCE_EXHAUSTED:Lorg/apache/dubbo/rpc/TriRpcStatus$Code;
     321: aastore
     322: dup
     323: bipush        9
     325: getstatic     #38                 // Field FAILED_PRECONDITION:Lorg/apache/dubbo/rpc/TriRpcStatus$Code;
     328: aastore
     329: dup
     330: bipush        10
     332: getstatic     #40                 // Field ABORTED:Lorg/apache/dubbo/rpc/TriRpcStatus$Code;
     335: aastore
     336: dup
     337: bipush        11
     339: getstatic     #42                 // Field OUT_OF_RANGE:Lorg/apache/dubbo/rpc/TriRpcStatus$Code;
     342: aastore
     343: dup
     344: bipush        12
     346: getstatic     #44                 // Field UNIMPLEMENTED:Lorg/apache/dubbo/rpc/TriRpcStatus$Code;
     349: aastore
     350: dup
     351: bipush        13
     353: getstatic     #46                 // Field INTERNAL:Lorg/apache/dubbo/rpc/TriRpcStatus$Code;
     356: aastore
     357: dup
     358: bipush        14
     360: getstatic     #48                 // Field UNAVAILABLE:Lorg/apache/dubbo/rpc/TriRpcStatus$Code;
     363: aastore
     364: dup
     365: bipush        15
     367: getstatic     #50                 // Field DATA_LOSS:Lorg/apache/dubbo/rpc/TriRpcStatus$Code;
     370: aastore
     371: dup
     372: bipush        16
     374: getstatic     #52                 // Field UNAUTHENTICATED:Lorg/apache/dubbo/rpc/TriRpcStatus$Code;
     377: aastore
     378: putstatic     #1                  // Field $VALUES:[Lorg/apache/dubbo/rpc/TriRpcStatus$Code;
     381: return
}
