Compiled from "TriRpcStatus.java"
public class org.apache.dubbo.rpc.TriRpcStatus {
  public static final org.apache.dubbo.rpc.TriRpcStatus OK;

  public static final org.apache.dubbo.rpc.TriRpcStatus UNKNOWN;

  public static final org.apache.dubbo.rpc.TriRpcStatus INTERNAL;

  public static final org.apache.dubbo.rpc.TriRpcStatus NOT_FOUND;

  public static final org.apache.dubbo.rpc.TriRpcStatus CANCELLED;

  public static final org.apache.dubbo.rpc.TriRpcStatus UNAVAILABLE;

  public static final org.apache.dubbo.rpc.TriRpcStatus UNIMPLEMENTED;

  public static final org.apache.dubbo.rpc.TriRpcStatus DEADLINE_EXCEEDED;

  public final org.apache.dubbo.rpc.TriRpcStatus$Code code;

  public final java.lang.Throwable cause;

  public final java.lang.String description;

  public org.apache.dubbo.rpc.TriRpcStatus(org.apache.dubbo.rpc.TriRpcStatus$Code, java.lang.Throwable, java.lang.String);
    Code:
       0: aload_0
       1: invokespecial #2                  // Method java/lang/Object."<init>":()V
       4: aload_0
       5: aload_1
       6: putfield      #3                  // Field code:Lorg/apache/dubbo/rpc/TriRpcStatus$Code;
       9: aload_0
      10: aload_2
      11: putfield      #4                  // Field cause:Ljava/lang/Throwable;
      14: aload_0
      15: aload_3
      16: putfield      #5                  // Field description:Ljava/lang/String;
      19: return

  public static org.apache.dubbo.rpc.TriRpcStatus fromCode(int);
    Code:
       0: iload_0
       1: invokestatic  #6                  // Method org/apache/dubbo/rpc/TriRpcStatus$Code.fromCode:(I)Lorg/apache/dubbo/rpc/TriRpcStatus$Code;
       4: invokestatic  #7                  // Method fromCode:(Lorg/apache/dubbo/rpc/TriRpcStatus$Code;)Lorg/apache/dubbo/rpc/TriRpcStatus;
       7: areturn

  public static org.apache.dubbo.rpc.TriRpcStatus fromCode(org.apache.dubbo.rpc.TriRpcStatus$Code);
    Code:
       0: new           #8                  // class org/apache/dubbo/rpc/TriRpcStatus
       3: dup
       4: aload_0
       5: aconst_null
       6: aconst_null
       7: invokespecial #9                  // Method "<init>":(Lorg/apache/dubbo/rpc/TriRpcStatus$Code;Ljava/lang/Throwable;Ljava/lang/String;)V
      10: areturn

  public static org.apache.dubbo.rpc.TriRpcStatus getStatus(java.lang.Throwable);
    Code:
       0: aload_0
       1: aconst_null
       2: invokestatic  #10                 // Method getStatus:(Ljava/lang/Throwable;Ljava/lang/String;)Lorg/apache/dubbo/rpc/TriRpcStatus;
       5: areturn

  public static org.apache.dubbo.rpc.TriRpcStatus getStatus(java.lang.Throwable, java.lang.String);
    Code:
       0: aload_0
       1: instanceof    #11                 // class org/apache/dubbo/rpc/StatusRpcException
       4: ifeq          15
       7: aload_0
       8: checkcast     #11                 // class org/apache/dubbo/rpc/StatusRpcException
      11: invokevirtual #12                 // Method org/apache/dubbo/rpc/StatusRpcException.getStatus:()Lorg/apache/dubbo/rpc/TriRpcStatus;
      14: areturn
      15: aload_0
      16: instanceof    #1                  // class org/apache/dubbo/rpc/RpcException
      19: ifeq          46
      22: aload_0
      23: checkcast     #1                  // class org/apache/dubbo/rpc/RpcException
      26: astore_2
      27: aload_2
      28: invokevirtual #13                 // Method org/apache/dubbo/rpc/RpcException.getCode:()I
      31: invokestatic  #14                 // Method dubboCodeToTriCode:(I)Lorg/apache/dubbo/rpc/TriRpcStatus$Code;
      34: astore_3
      35: new           #8                  // class org/apache/dubbo/rpc/TriRpcStatus
      38: dup
      39: aload_3
      40: aload_0
      41: aload_1
      42: invokespecial #9                  // Method "<init>":(Lorg/apache/dubbo/rpc/TriRpcStatus$Code;Ljava/lang/Throwable;Ljava/lang/String;)V
      45: areturn
      46: aload_0
      47: instanceof    #15                 // class org/apache/dubbo/remoting/TimeoutException
      50: ifeq          66
      53: new           #8                  // class org/apache/dubbo/rpc/TriRpcStatus
      56: dup
      57: getstatic     #16                 // Field org/apache/dubbo/rpc/TriRpcStatus$Code.DEADLINE_EXCEEDED:Lorg/apache/dubbo/rpc/TriRpcStatus$Code;
      60: aload_0
      61: aload_1
      62: invokespecial #9                  // Method "<init>":(Lorg/apache/dubbo/rpc/TriRpcStatus$Code;Ljava/lang/Throwable;Ljava/lang/String;)V
      65: areturn
      66: new           #8                  // class org/apache/dubbo/rpc/TriRpcStatus
      69: dup
      70: getstatic     #17                 // Field org/apache/dubbo/rpc/TriRpcStatus$Code.UNKNOWN:Lorg/apache/dubbo/rpc/TriRpcStatus$Code;
      73: aload_0
      74: aload_1
      75: invokespecial #9                  // Method "<init>":(Lorg/apache/dubbo/rpc/TriRpcStatus$Code;Ljava/lang/Throwable;Ljava/lang/String;)V
      78: areturn

  public static int triCodeToDubboCode(org.apache.dubbo.rpc.TriRpcStatus$Code);
    Code:
       0: getstatic     #18                 // Field org/apache/dubbo/rpc/TriRpcStatus$1.$SwitchMap$org$apache$dubbo$rpc$TriRpcStatus$Code:[I
       3: aload_0
       4: invokevirtual #19                 // Method org/apache/dubbo/rpc/TriRpcStatus$Code.ordinal:()I
       7: iaload
       8: tableswitch   { // 1 to 4
                     1: 40
                     2: 45
                     3: 50
                     4: 55
               default: 61
          }
      40: iconst_2
      41: istore_1
      42: goto          63
      45: iconst_4
      46: istore_1
      47: goto          63
      50: iconst_1
      51: istore_1
      52: goto          63
      55: bipush        11
      57: istore_1
      58: goto          63
      61: iconst_0
      62: istore_1
      63: iload_1
      64: ireturn

  public static org.apache.dubbo.rpc.TriRpcStatus$Code dubboCodeToTriCode(int);
    Code:
       0: iload_0
       1: tableswitch   { // 1 to 11
                     1: 74
                     2: 60
                     3: 95
                     4: 67
                     5: 88
                     6: 95
                     7: 74
                     8: 60
                     9: 95
                    10: 95
                    11: 81
               default: 95
          }
      60: getstatic     #16                 // Field org/apache/dubbo/rpc/TriRpcStatus$Code.DEADLINE_EXCEEDED:Lorg/apache/dubbo/rpc/TriRpcStatus$Code;
      63: astore_1
      64: goto          99
      67: getstatic     #20                 // Field org/apache/dubbo/rpc/TriRpcStatus$Code.PERMISSION_DENIED:Lorg/apache/dubbo/rpc/TriRpcStatus$Code;
      70: astore_1
      71: goto          99
      74: getstatic     #21                 // Field org/apache/dubbo/rpc/TriRpcStatus$Code.UNAVAILABLE:Lorg/apache/dubbo/rpc/TriRpcStatus$Code;
      77: astore_1
      78: goto          99
      81: getstatic     #22                 // Field org/apache/dubbo/rpc/TriRpcStatus$Code.NOT_FOUND:Lorg/apache/dubbo/rpc/TriRpcStatus$Code;
      84: astore_1
      85: goto          99
      88: getstatic     #23                 // Field org/apache/dubbo/rpc/TriRpcStatus$Code.INTERNAL:Lorg/apache/dubbo/rpc/TriRpcStatus$Code;
      91: astore_1
      92: goto          99
      95: getstatic     #17                 // Field org/apache/dubbo/rpc/TriRpcStatus$Code.UNKNOWN:Lorg/apache/dubbo/rpc/TriRpcStatus$Code;
      98: astore_1
      99: aload_1
     100: areturn

  public static java.lang.String limitSizeTo1KB(java.lang.String);
    Code:
       0: aload_0
       1: invokevirtual #24                 // Method java/lang/String.length:()I
       4: sipush        1024
       7: if_icmpge     12
      10: aload_0
      11: areturn
      12: aload_0
      13: iconst_0
      14: sipush        1024
      17: invokevirtual #25                 // Method java/lang/String.substring:(II)Ljava/lang/String;
      20: areturn

  public static java.lang.String decodeMessage(java.lang.String);
    Code:
       0: aload_0
       1: invokestatic  #26                 // Method org/apache/dubbo/common/utils/StringUtils.isEmpty:(Ljava/lang/String;)Z
       4: ifeq          10
       7: ldc           #27                 // String
       9: areturn
      10: aload_0
      11: invokestatic  #28                 // Method io/netty/handler/codec/http/QueryStringDecoder.decodeComponent:(Ljava/lang/String;)Ljava/lang/String;
      14: areturn

  public static java.lang.String encodeMessage(java.lang.String);
    Code:
       0: aload_0
       1: invokestatic  #26                 // Method org/apache/dubbo/common/utils/StringUtils.isEmpty:(Ljava/lang/String;)Z
       4: ifeq          10
       7: ldc           #27                 // String
       9: areturn
      10: aload_0
      11: invokestatic  #29                 // Method encodeComponent:(Ljava/lang/String;)Ljava/lang/String;
      14: areturn

  private static java.lang.String encodeComponent(java.lang.String);
    Code:
       0: new           #30                 // class io/netty/handler/codec/http/QueryStringEncoder
       3: dup
       4: ldc           #27                 // String
       6: invokespecial #31                 // Method io/netty/handler/codec/http/QueryStringEncoder."<init>":(Ljava/lang/String;)V
       9: astore_1
      10: aload_1
      11: ldc           #27                 // String
      13: aload_0
      14: invokevirtual #32                 // Method io/netty/handler/codec/http/QueryStringEncoder.addParam:(Ljava/lang/String;Ljava/lang/String;)V
      17: aload_1
      18: invokevirtual #33                 // Method io/netty/handler/codec/http/QueryStringEncoder.toString:()Ljava/lang/String;
      21: iconst_2
      22: invokevirtual #34                 // Method java/lang/String.substring:(I)Ljava/lang/String;
      25: areturn

  public static org.apache.dubbo.rpc.TriRpcStatus$Code httpStatusToGrpcCode(int);
    Code:
       0: iload_0
       1: bipush        100
       3: if_icmplt     17
       6: iload_0
       7: sipush        200
      10: if_icmpge     17
      13: getstatic     #23                 // Field org/apache/dubbo/rpc/TriRpcStatus$Code.INTERNAL:Lorg/apache/dubbo/rpc/TriRpcStatus$Code;
      16: areturn
      17: iload_0
      18: getstatic     #35                 // Field io/netty/handler/codec/http/HttpResponseStatus.BAD_REQUEST:Lio/netty/handler/codec/http/HttpResponseStatus;
      21: invokevirtual #36                 // Method io/netty/handler/codec/http/HttpResponseStatus.code:()I
      24: if_icmpeq     37
      27: iload_0
      28: getstatic     #37                 // Field io/netty/handler/codec/http/HttpResponseStatus.REQUEST_HEADER_FIELDS_TOO_LARGE:Lio/netty/handler/codec/http/HttpResponseStatus;
      31: invokevirtual #36                 // Method io/netty/handler/codec/http/HttpResponseStatus.code:()I
      34: if_icmpne     41
      37: getstatic     #23                 // Field org/apache/dubbo/rpc/TriRpcStatus$Code.INTERNAL:Lorg/apache/dubbo/rpc/TriRpcStatus$Code;
      40: areturn
      41: iload_0
      42: getstatic     #38                 // Field io/netty/handler/codec/http/HttpResponseStatus.UNAUTHORIZED:Lio/netty/handler/codec/http/HttpResponseStatus;
      45: invokevirtual #36                 // Method io/netty/handler/codec/http/HttpResponseStatus.code:()I
      48: if_icmpne     55
      51: getstatic     #39                 // Field org/apache/dubbo/rpc/TriRpcStatus$Code.UNAUTHENTICATED:Lorg/apache/dubbo/rpc/TriRpcStatus$Code;
      54: areturn
      55: iload_0
      56: getstatic     #40                 // Field io/netty/handler/codec/http/HttpResponseStatus.FORBIDDEN:Lio/netty/handler/codec/http/HttpResponseStatus;
      59: invokevirtual #36                 // Method io/netty/handler/codec/http/HttpResponseStatus.code:()I
      62: if_icmpne     69
      65: getstatic     #20                 // Field org/apache/dubbo/rpc/TriRpcStatus$Code.PERMISSION_DENIED:Lorg/apache/dubbo/rpc/TriRpcStatus$Code;
      68: areturn
      69: iload_0
      70: getstatic     #41                 // Field io/netty/handler/codec/http/HttpResponseStatus.NOT_FOUND:Lio/netty/handler/codec/http/HttpResponseStatus;
      73: invokevirtual #36                 // Method io/netty/handler/codec/http/HttpResponseStatus.code:()I
      76: if_icmpne     83
      79: getstatic     #42                 // Field org/apache/dubbo/rpc/TriRpcStatus$Code.UNIMPLEMENTED:Lorg/apache/dubbo/rpc/TriRpcStatus$Code;
      82: areturn
      83: iload_0
      84: getstatic     #43                 // Field io/netty/handler/codec/http/HttpResponseStatus.BAD_GATEWAY:Lio/netty/handler/codec/http/HttpResponseStatus;
      87: invokevirtual #36                 // Method io/netty/handler/codec/http/HttpResponseStatus.code:()I
      90: if_icmpeq     123
      93: iload_0
      94: getstatic     #44                 // Field io/netty/handler/codec/http/HttpResponseStatus.TOO_MANY_REQUESTS:Lio/netty/handler/codec/http/HttpResponseStatus;
      97: invokevirtual #36                 // Method io/netty/handler/codec/http/HttpResponseStatus.code:()I
     100: if_icmpeq     123
     103: iload_0
     104: getstatic     #45                 // Field io/netty/handler/codec/http/HttpResponseStatus.SERVICE_UNAVAILABLE:Lio/netty/handler/codec/http/HttpResponseStatus;
     107: invokevirtual #36                 // Method io/netty/handler/codec/http/HttpResponseStatus.code:()I
     110: if_icmpeq     123
     113: iload_0
     114: getstatic     #46                 // Field io/netty/handler/codec/http/HttpResponseStatus.GATEWAY_TIMEOUT:Lio/netty/handler/codec/http/HttpResponseStatus;
     117: invokevirtual #36                 // Method io/netty/handler/codec/http/HttpResponseStatus.code:()I
     120: if_icmpne     127
     123: getstatic     #21                 // Field org/apache/dubbo/rpc/TriRpcStatus$Code.UNAVAILABLE:Lorg/apache/dubbo/rpc/TriRpcStatus$Code;
     126: areturn
     127: getstatic     #17                 // Field org/apache/dubbo/rpc/TriRpcStatus$Code.UNKNOWN:Lorg/apache/dubbo/rpc/TriRpcStatus$Code;
     130: areturn

  public boolean isOk();
    Code:
       0: aload_0
       1: getfield      #3                  // Field code:Lorg/apache/dubbo/rpc/TriRpcStatus$Code;
       4: getfield      #47                 // Field org/apache/dubbo/rpc/TriRpcStatus$Code.code:I
       7: invokestatic  #48                 // Method java/lang/Integer.valueOf:(I)Ljava/lang/Integer;
      10: invokestatic  #49                 // Method org/apache/dubbo/rpc/TriRpcStatus$Code.isOk:(Ljava/lang/Integer;)Z
      13: ireturn

  public org.apache.dubbo.rpc.TriRpcStatus withCause(java.lang.Throwable);
    Code:
       0: new           #8                  // class org/apache/dubbo/rpc/TriRpcStatus
       3: dup
       4: aload_0
       5: getfield      #3                  // Field code:Lorg/apache/dubbo/rpc/TriRpcStatus$Code;
       8: aload_1
       9: aload_0
      10: getfield      #5                  // Field description:Ljava/lang/String;
      13: invokespecial #9                  // Method "<init>":(Lorg/apache/dubbo/rpc/TriRpcStatus$Code;Ljava/lang/Throwable;Ljava/lang/String;)V
      16: areturn

  public org.apache.dubbo.rpc.TriRpcStatus withDescription(java.lang.String);
    Code:
       0: new           #8                  // class org/apache/dubbo/rpc/TriRpcStatus
       3: dup
       4: aload_0
       5: getfield      #3                  // Field code:Lorg/apache/dubbo/rpc/TriRpcStatus$Code;
       8: aload_0
       9: getfield      #4                  // Field cause:Ljava/lang/Throwable;
      12: aload_1
      13: invokespecial #9                  // Method "<init>":(Lorg/apache/dubbo/rpc/TriRpcStatus$Code;Ljava/lang/Throwable;Ljava/lang/String;)V
      16: areturn

  public org.apache.dubbo.rpc.TriRpcStatus appendDescription(java.lang.String);
    Code:
       0: aload_0
       1: getfield      #5                  // Field description:Ljava/lang/String;
       4: ifnonnull     13
       7: aload_0
       8: aload_1
       9: invokevirtual #50                 // Method withDescription:(Ljava/lang/String;)Lorg/apache/dubbo/rpc/TriRpcStatus;
      12: areturn
      13: new           #51                 // class java/lang/StringBuilder
      16: dup
      17: invokespecial #52                 // Method java/lang/StringBuilder."<init>":()V
      20: aload_0
      21: getfield      #5                  // Field description:Ljava/lang/String;
      24: invokevirtual #53                 // Method java/lang/StringBuilder.append:(Ljava/lang/String;)Ljava/lang/StringBuilder;
      27: ldc           #54                 // String \n
      29: invokevirtual #53                 // Method java/lang/StringBuilder.append:(Ljava/lang/String;)Ljava/lang/StringBuilder;
      32: aload_1
      33: invokevirtual #53                 // Method java/lang/StringBuilder.append:(Ljava/lang/String;)Ljava/lang/StringBuilder;
      36: invokevirtual #55                 // Method java/lang/StringBuilder.toString:()Ljava/lang/String;
      39: astore_2
      40: aload_0
      41: aload_2
      42: invokevirtual #50                 // Method withDescription:(Ljava/lang/String;)Lorg/apache/dubbo/rpc/TriRpcStatus;
      45: areturn

  public org.apache.dubbo.rpc.StatusRpcException asException();
    Code:
       0: new           #11                 // class org/apache/dubbo/rpc/StatusRpcException
       3: dup
       4: aload_0
       5: invokespecial #56                 // Method org/apache/dubbo/rpc/StatusRpcException."<init>":(Lorg/apache/dubbo/rpc/TriRpcStatus;)V
       8: areturn

  public java.lang.String toEncodedMessage();
    Code:
       0: aload_0
       1: invokevirtual #57                 // Method toMessage:()Ljava/lang/String;
       4: invokestatic  #58                 // Method limitSizeTo1KB:(Ljava/lang/String;)Ljava/lang/String;
       7: astore_1
       8: aload_1
       9: invokestatic  #29                 // Method encodeComponent:(Ljava/lang/String;)Ljava/lang/String;
      12: areturn

  public java.lang.String toMessageWithoutCause();
    Code:
       0: aload_0
       1: getfield      #5                  // Field description:Ljava/lang/String;
       4: ifnull        31
       7: ldc           #59                 // String %s : %s
       9: iconst_2
      10: anewarray     #60                 // class java/lang/Object
      13: dup
      14: iconst_0
      15: aload_0
      16: getfield      #3                  // Field code:Lorg/apache/dubbo/rpc/TriRpcStatus$Code;
      19: aastore
      20: dup
      21: iconst_1
      22: aload_0
      23: getfield      #5                  // Field description:Ljava/lang/String;
      26: aastore
      27: invokestatic  #61                 // Method java/lang/String.format:(Ljava/lang/String;[Ljava/lang/Object;)Ljava/lang/String;
      30: areturn
      31: aload_0
      32: getfield      #3                  // Field code:Lorg/apache/dubbo/rpc/TriRpcStatus$Code;
      35: invokevirtual #62                 // Method org/apache/dubbo/rpc/TriRpcStatus$Code.toString:()Ljava/lang/String;
      38: areturn

  public java.lang.String toMessage();
    Code:
       0: ldc           #27                 // String
       2: astore_1
       3: aload_0
       4: getfield      #4                  // Field cause:Ljava/lang/Throwable;
       7: ifnonnull     35
      10: new           #51                 // class java/lang/StringBuilder
      13: dup
      14: invokespecial #52                 // Method java/lang/StringBuilder."<init>":()V
      17: aload_1
      18: invokevirtual #53                 // Method java/lang/StringBuilder.append:(Ljava/lang/String;)Ljava/lang/StringBuilder;
      21: aload_0
      22: getfield      #5                  // Field description:Ljava/lang/String;
      25: invokevirtual #53                 // Method java/lang/StringBuilder.append:(Ljava/lang/String;)Ljava/lang/StringBuilder;
      28: invokevirtual #55                 // Method java/lang/StringBuilder.toString:()Ljava/lang/String;
      31: astore_1
      32: goto          78
      35: aload_0
      36: getfield      #5                  // Field description:Ljava/lang/String;
      39: ifnonnull     47
      42: ldc           #27                 // String
      44: goto          51
      47: aload_0
      48: getfield      #5                  // Field description:Ljava/lang/String;
      51: astore_2
      52: new           #51                 // class java/lang/StringBuilder
      55: dup
      56: invokespecial #52                 // Method java/lang/StringBuilder."<init>":()V
      59: aload_1
      60: invokevirtual #53                 // Method java/lang/StringBuilder.append:(Ljava/lang/String;)Ljava/lang/StringBuilder;
      63: aload_2
      64: aload_0
      65: getfield      #4                  // Field cause:Ljava/lang/Throwable;
      68: invokestatic  #63                 // Method org/apache/dubbo/common/utils/StringUtils.toString:(Ljava/lang/String;Ljava/lang/Throwable;)Ljava/lang/String;
      71: invokevirtual #53                 // Method java/lang/StringBuilder.append:(Ljava/lang/String;)Ljava/lang/StringBuilder;
      74: invokevirtual #55                 // Method java/lang/StringBuilder.toString:()Ljava/lang/String;
      77: astore_1
      78: aload_1
      79: areturn

  static {};
    Code:
       0: getstatic     #64                 // Field org/apache/dubbo/rpc/TriRpcStatus$Code.OK:Lorg/apache/dubbo/rpc/TriRpcStatus$Code;
       3: invokestatic  #7                  // Method fromCode:(Lorg/apache/dubbo/rpc/TriRpcStatus$Code;)Lorg/apache/dubbo/rpc/TriRpcStatus;
       6: putstatic     #65                 // Field OK:Lorg/apache/dubbo/rpc/TriRpcStatus;
       9: getstatic     #17                 // Field org/apache/dubbo/rpc/TriRpcStatus$Code.UNKNOWN:Lorg/apache/dubbo/rpc/TriRpcStatus$Code;
      12: invokestatic  #7                  // Method fromCode:(Lorg/apache/dubbo/rpc/TriRpcStatus$Code;)Lorg/apache/dubbo/rpc/TriRpcStatus;
      15: putstatic     #66                 // Field UNKNOWN:Lorg/apache/dubbo/rpc/TriRpcStatus;
      18: getstatic     #23                 // Field org/apache/dubbo/rpc/TriRpcStatus$Code.INTERNAL:Lorg/apache/dubbo/rpc/TriRpcStatus$Code;
      21: invokestatic  #7                  // Method fromCode:(Lorg/apache/dubbo/rpc/TriRpcStatus$Code;)Lorg/apache/dubbo/rpc/TriRpcStatus;
      24: putstatic     #67                 // Field INTERNAL:Lorg/apache/dubbo/rpc/TriRpcStatus;
      27: getstatic     #22                 // Field org/apache/dubbo/rpc/TriRpcStatus$Code.NOT_FOUND:Lorg/apache/dubbo/rpc/TriRpcStatus$Code;
      30: invokestatic  #7                  // Method fromCode:(Lorg/apache/dubbo/rpc/TriRpcStatus$Code;)Lorg/apache/dubbo/rpc/TriRpcStatus;
      33: putstatic     #68                 // Field NOT_FOUND:Lorg/apache/dubbo/rpc/TriRpcStatus;
      36: getstatic     #69                 // Field org/apache/dubbo/rpc/TriRpcStatus$Code.CANCELLED:Lorg/apache/dubbo/rpc/TriRpcStatus$Code;
      39: invokestatic  #7                  // Method fromCode:(Lorg/apache/dubbo/rpc/TriRpcStatus$Code;)Lorg/apache/dubbo/rpc/TriRpcStatus;
      42: putstatic     #70                 // Field CANCELLED:Lorg/apache/dubbo/rpc/TriRpcStatus;
      45: getstatic     #21                 // Field org/apache/dubbo/rpc/TriRpcStatus$Code.UNAVAILABLE:Lorg/apache/dubbo/rpc/TriRpcStatus$Code;
      48: invokestatic  #7                  // Method fromCode:(Lorg/apache/dubbo/rpc/TriRpcStatus$Code;)Lorg/apache/dubbo/rpc/TriRpcStatus;
      51: putstatic     #71                 // Field UNAVAILABLE:Lorg/apache/dubbo/rpc/TriRpcStatus;
      54: getstatic     #42                 // Field org/apache/dubbo/rpc/TriRpcStatus$Code.UNIMPLEMENTED:Lorg/apache/dubbo/rpc/TriRpcStatus$Code;
      57: invokestatic  #7                  // Method fromCode:(Lorg/apache/dubbo/rpc/TriRpcStatus$Code;)Lorg/apache/dubbo/rpc/TriRpcStatus;
      60: putstatic     #72                 // Field UNIMPLEMENTED:Lorg/apache/dubbo/rpc/TriRpcStatus;
      63: getstatic     #16                 // Field org/apache/dubbo/rpc/TriRpcStatus$Code.DEADLINE_EXCEEDED:Lorg/apache/dubbo/rpc/TriRpcStatus$Code;
      66: invokestatic  #7                  // Method fromCode:(Lorg/apache/dubbo/rpc/TriRpcStatus$Code;)Lorg/apache/dubbo/rpc/TriRpcStatus;
      69: putstatic     #73                 // Field DEADLINE_EXCEEDED:Lorg/apache/dubbo/rpc/TriRpcStatus;
      72: return
}
