Compiled from "KubernetesConfigUtils.java"
public class org.apache.dubbo.registry.kubernetes.util.KubernetesConfigUtils {
  public org.apache.dubbo.registry.kubernetes.util.KubernetesConfigUtils();
    Code:
       0: aload_0
       1: invokespecial #2                  // Method java/lang/Object."<init>":()V
       4: return

  public static io.fabric8.kubernetes.client.Config createKubernetesConfig(org.apache.dubbo.common.URL);
    Code:
       0: aconst_null
       1: invokestatic  #3                  // Method io/fabric8/kubernetes/client/Config.autoConfigure:(Ljava/lang/String;)Lio/fabric8/kubernetes/client/Config;
       4: astore_1
       5: new           #4                  // class io/fabric8/kubernetes/client/ConfigBuilder
       8: dup
       9: aload_1
      10: invokespecial #5                  // Method io/fabric8/kubernetes/client/ConfigBuilder."<init>":(Lio/fabric8/kubernetes/client/Config;)V
      13: aload_0
      14: invokestatic  #6                  // Method buildMasterUrl:(Lorg/apache/dubbo/common/URL;)Ljava/lang/String;
      17: invokevirtual #7                  // Method io/fabric8/kubernetes/client/ConfigBuilder.withMasterUrl:(Ljava/lang/String;)Lio/fabric8/kubernetes/client/ConfigFluent;
      20: checkcast     #4                  // class io/fabric8/kubernetes/client/ConfigBuilder
      23: aload_0
      24: ldc           #8                  // String apiVersion
      26: aload_1
      27: invokevirtual #9                  // Method io/fabric8/kubernetes/client/Config.getApiVersion:()Ljava/lang/String;
      30: invokevirtual #10                 // Method org/apache/dubbo/common/URL.getParameter:(Ljava/lang/String;Ljava/lang/String;)Ljava/lang/String;
      33: invokevirtual #11                 // Method io/fabric8/kubernetes/client/ConfigBuilder.withApiVersion:(Ljava/lang/String;)Lio/fabric8/kubernetes/client/ConfigFluent;
      36: checkcast     #4                  // class io/fabric8/kubernetes/client/ConfigBuilder
      39: aload_0
      40: ldc           #12                 // String namespace
      42: aload_1
      43: invokevirtual #13                 // Method io/fabric8/kubernetes/client/Config.getNamespace:()Ljava/lang/String;
      46: invokevirtual #10                 // Method org/apache/dubbo/common/URL.getParameter:(Ljava/lang/String;Ljava/lang/String;)Ljava/lang/String;
      49: invokevirtual #14                 // Method io/fabric8/kubernetes/client/ConfigBuilder.withNamespace:(Ljava/lang/String;)Lio/fabric8/kubernetes/client/ConfigFluent;
      52: checkcast     #4                  // class io/fabric8/kubernetes/client/ConfigBuilder
      55: aload_0
      56: ldc           #15                 // String username
      58: aload_1
      59: invokevirtual #16                 // Method io/fabric8/kubernetes/client/Config.getUsername:()Ljava/lang/String;
      62: invokevirtual #10                 // Method org/apache/dubbo/common/URL.getParameter:(Ljava/lang/String;Ljava/lang/String;)Ljava/lang/String;
      65: invokevirtual #17                 // Method io/fabric8/kubernetes/client/ConfigBuilder.withUsername:(Ljava/lang/String;)Lio/fabric8/kubernetes/client/ConfigFluent;
      68: checkcast     #4                  // class io/fabric8/kubernetes/client/ConfigBuilder
      71: aload_0
      72: ldc           #18                 // String password
      74: aload_1
      75: invokevirtual #19                 // Method io/fabric8/kubernetes/client/Config.getPassword:()Ljava/lang/String;
      78: invokevirtual #10                 // Method org/apache/dubbo/common/URL.getParameter:(Ljava/lang/String;Ljava/lang/String;)Ljava/lang/String;
      81: invokevirtual #20                 // Method io/fabric8/kubernetes/client/ConfigBuilder.withPassword:(Ljava/lang/String;)Lio/fabric8/kubernetes/client/ConfigFluent;
      84: checkcast     #4                  // class io/fabric8/kubernetes/client/ConfigBuilder
      87: aload_0
      88: ldc           #21                 // String oauthToken
      90: aload_1
      91: invokevirtual #22                 // Method io/fabric8/kubernetes/client/Config.getOauthToken:()Ljava/lang/String;
      94: invokevirtual #10                 // Method org/apache/dubbo/common/URL.getParameter:(Ljava/lang/String;Ljava/lang/String;)Ljava/lang/String;
      97: invokevirtual #23                 // Method io/fabric8/kubernetes/client/ConfigBuilder.withOauthToken:(Ljava/lang/String;)Lio/fabric8/kubernetes/client/ConfigFluent;
     100: checkcast     #4                  // class io/fabric8/kubernetes/client/ConfigBuilder
     103: aload_0
     104: ldc           #24                 // String caCertFile
     106: aload_1
     107: invokevirtual #25                 // Method io/fabric8/kubernetes/client/Config.getCaCertFile:()Ljava/lang/String;
     110: invokevirtual #10                 // Method org/apache/dubbo/common/URL.getParameter:(Ljava/lang/String;Ljava/lang/String;)Ljava/lang/String;
     113: invokevirtual #26                 // Method io/fabric8/kubernetes/client/ConfigBuilder.withCaCertFile:(Ljava/lang/String;)Lio/fabric8/kubernetes/client/ConfigFluent;
     116: checkcast     #4                  // class io/fabric8/kubernetes/client/ConfigBuilder
     119: aload_0
     120: ldc           #27                 // String caCertData
     122: aload_1
     123: invokevirtual #28                 // Method io/fabric8/kubernetes/client/Config.getCaCertData:()Ljava/lang/String;
     126: invokestatic  #29                 // Method decodeBase64:(Ljava/lang/String;)Ljava/lang/String;
     129: invokevirtual #10                 // Method org/apache/dubbo/common/URL.getParameter:(Ljava/lang/String;Ljava/lang/String;)Ljava/lang/String;
     132: invokevirtual #30                 // Method io/fabric8/kubernetes/client/ConfigBuilder.withCaCertData:(Ljava/lang/String;)Lio/fabric8/kubernetes/client/ConfigFluent;
     135: checkcast     #4                  // class io/fabric8/kubernetes/client/ConfigBuilder
     138: aload_0
     139: ldc           #31                 // String clientKeyFile
     141: aload_1
     142: invokevirtual #32                 // Method io/fabric8/kubernetes/client/Config.getClientKeyFile:()Ljava/lang/String;
     145: invokevirtual #10                 // Method org/apache/dubbo/common/URL.getParameter:(Ljava/lang/String;Ljava/lang/String;)Ljava/lang/String;
     148: invokevirtual #33                 // Method io/fabric8/kubernetes/client/ConfigBuilder.withClientKeyFile:(Ljava/lang/String;)Lio/fabric8/kubernetes/client/ConfigFluent;
     151: checkcast     #4                  // class io/fabric8/kubernetes/client/ConfigBuilder
     154: aload_0
     155: ldc           #34                 // String clientKeyData
     157: aload_1
     158: invokevirtual #35                 // Method io/fabric8/kubernetes/client/Config.getClientKeyData:()Ljava/lang/String;
     161: invokestatic  #29                 // Method decodeBase64:(Ljava/lang/String;)Ljava/lang/String;
     164: invokevirtual #10                 // Method org/apache/dubbo/common/URL.getParameter:(Ljava/lang/String;Ljava/lang/String;)Ljava/lang/String;
     167: invokevirtual #36                 // Method io/fabric8/kubernetes/client/ConfigBuilder.withClientKeyData:(Ljava/lang/String;)Lio/fabric8/kubernetes/client/ConfigFluent;
     170: checkcast     #4                  // class io/fabric8/kubernetes/client/ConfigBuilder
     173: aload_0
     174: ldc           #37                 // String clientCertFile
     176: aload_1
     177: invokevirtual #38                 // Method io/fabric8/kubernetes/client/Config.getClientCertFile:()Ljava/lang/String;
     180: invokevirtual #10                 // Method org/apache/dubbo/common/URL.getParameter:(Ljava/lang/String;Ljava/lang/String;)Ljava/lang/String;
     183: invokevirtual #39                 // Method io/fabric8/kubernetes/client/ConfigBuilder.withClientCertFile:(Ljava/lang/String;)Lio/fabric8/kubernetes/client/ConfigFluent;
     186: checkcast     #4                  // class io/fabric8/kubernetes/client/ConfigBuilder
     189: aload_0
     190: ldc           #40                 // String clientCertData
     192: aload_1
     193: invokevirtual #41                 // Method io/fabric8/kubernetes/client/Config.getClientCertData:()Ljava/lang/String;
     196: invokestatic  #29                 // Method decodeBase64:(Ljava/lang/String;)Ljava/lang/String;
     199: invokevirtual #10                 // Method org/apache/dubbo/common/URL.getParameter:(Ljava/lang/String;Ljava/lang/String;)Ljava/lang/String;
     202: invokevirtual #42                 // Method io/fabric8/kubernetes/client/ConfigBuilder.withClientCertData:(Ljava/lang/String;)Lio/fabric8/kubernetes/client/ConfigFluent;
     205: checkcast     #4                  // class io/fabric8/kubernetes/client/ConfigBuilder
     208: aload_0
     209: ldc           #43                 // String clientKeyAlgo
     211: aload_1
     212: invokevirtual #44                 // Method io/fabric8/kubernetes/client/Config.getClientKeyAlgo:()Ljava/lang/String;
     215: invokevirtual #10                 // Method org/apache/dubbo/common/URL.getParameter:(Ljava/lang/String;Ljava/lang/String;)Ljava/lang/String;
     218: invokevirtual #45                 // Method io/fabric8/kubernetes/client/ConfigBuilder.withClientKeyAlgo:(Ljava/lang/String;)Lio/fabric8/kubernetes/client/ConfigFluent;
     221: checkcast     #4                  // class io/fabric8/kubernetes/client/ConfigBuilder
     224: aload_0
     225: ldc           #46                 // String clientKeyPassphrase
     227: aload_1
     228: invokevirtual #47                 // Method io/fabric8/kubernetes/client/Config.getClientKeyPassphrase:()Ljava/lang/String;
     231: invokevirtual #10                 // Method org/apache/dubbo/common/URL.getParameter:(Ljava/lang/String;Ljava/lang/String;)Ljava/lang/String;
     234: invokevirtual #48                 // Method io/fabric8/kubernetes/client/ConfigBuilder.withClientKeyPassphrase:(Ljava/lang/String;)Lio/fabric8/kubernetes/client/ConfigFluent;
     237: checkcast     #4                  // class io/fabric8/kubernetes/client/ConfigBuilder
     240: aload_0
     241: ldc           #49                 // String connectionTimeout
     243: aload_1
     244: invokevirtual #50                 // Method io/fabric8/kubernetes/client/Config.getConnectionTimeout:()I
     247: invokevirtual #51                 // Method org/apache/dubbo/common/URL.getParameter:(Ljava/lang/String;I)I
     250: invokevirtual #52                 // Method io/fabric8/kubernetes/client/ConfigBuilder.withConnectionTimeout:(I)Lio/fabric8/kubernetes/client/ConfigFluent;
     253: checkcast     #4                  // class io/fabric8/kubernetes/client/ConfigBuilder
     256: aload_0
     257: ldc           #53                 // String requestTimeout
     259: aload_1
     260: invokevirtual #54                 // Method io/fabric8/kubernetes/client/Config.getRequestTimeout:()I
     263: invokevirtual #51                 // Method org/apache/dubbo/common/URL.getParameter:(Ljava/lang/String;I)I
     266: invokevirtual #55                 // Method io/fabric8/kubernetes/client/ConfigBuilder.withRequestTimeout:(I)Lio/fabric8/kubernetes/client/ConfigFluent;
     269: checkcast     #4                  // class io/fabric8/kubernetes/client/ConfigBuilder
     272: aload_0
     273: ldc           #56                 // String watchReconnectInterval
     275: aload_1
     276: invokevirtual #57                 // Method io/fabric8/kubernetes/client/Config.getWatchReconnectInterval:()I
     279: invokevirtual #51                 // Method org/apache/dubbo/common/URL.getParameter:(Ljava/lang/String;I)I
     282: invokevirtual #58                 // Method io/fabric8/kubernetes/client/ConfigBuilder.withWatchReconnectInterval:(I)Lio/fabric8/kubernetes/client/ConfigFluent;
     285: checkcast     #4                  // class io/fabric8/kubernetes/client/ConfigBuilder
     288: aload_0
     289: ldc           #59                 // String watchReconnectLimit
     291: aload_1
     292: invokevirtual #60                 // Method io/fabric8/kubernetes/client/Config.getWatchReconnectLimit:()I
     295: invokevirtual #51                 // Method org/apache/dubbo/common/URL.getParameter:(Ljava/lang/String;I)I
     298: invokevirtual #61                 // Method io/fabric8/kubernetes/client/ConfigBuilder.withWatchReconnectLimit:(I)Lio/fabric8/kubernetes/client/ConfigFluent;
     301: checkcast     #4                  // class io/fabric8/kubernetes/client/ConfigBuilder
     304: aload_0
     305: ldc           #62                 // String loggingInterval
     307: aload_1
     308: invokevirtual #63                 // Method io/fabric8/kubernetes/client/Config.getLoggingInterval:()I
     311: invokevirtual #51                 // Method org/apache/dubbo/common/URL.getParameter:(Ljava/lang/String;I)I
     314: invokevirtual #64                 // Method io/fabric8/kubernetes/client/ConfigBuilder.withLoggingInterval:(I)Lio/fabric8/kubernetes/client/ConfigFluent;
     317: checkcast     #4                  // class io/fabric8/kubernetes/client/ConfigBuilder
     320: aload_0
     321: ldc           #65                 // String trustCerts
     323: aload_1
     324: invokevirtual #66                 // Method io/fabric8/kubernetes/client/Config.isTrustCerts:()Z
     327: invokevirtual #67                 // Method org/apache/dubbo/common/URL.getParameter:(Ljava/lang/String;Z)Z
     330: invokevirtual #68                 // Method io/fabric8/kubernetes/client/ConfigBuilder.withTrustCerts:(Z)Lio/fabric8/kubernetes/client/ConfigFluent;
     333: checkcast     #4                  // class io/fabric8/kubernetes/client/ConfigBuilder
     336: aload_0
     337: ldc           #69                 // String http2Disable
     339: aload_1
     340: invokevirtual #70                 // Method io/fabric8/kubernetes/client/Config.isHttp2Disable:()Z
     343: invokevirtual #67                 // Method org/apache/dubbo/common/URL.getParameter:(Ljava/lang/String;Z)Z
     346: invokevirtual #71                 // Method io/fabric8/kubernetes/client/ConfigBuilder.withHttp2Disable:(Z)Lio/fabric8/kubernetes/client/ConfigFluent;
     349: checkcast     #4                  // class io/fabric8/kubernetes/client/ConfigBuilder
     352: aload_0
     353: ldc           #72                 // String httpProxy
     355: aload_1
     356: invokevirtual #73                 // Method io/fabric8/kubernetes/client/Config.getHttpProxy:()Ljava/lang/String;
     359: invokevirtual #10                 // Method org/apache/dubbo/common/URL.getParameter:(Ljava/lang/String;Ljava/lang/String;)Ljava/lang/String;
     362: invokevirtual #74                 // Method io/fabric8/kubernetes/client/ConfigBuilder.withHttpProxy:(Ljava/lang/String;)Lio/fabric8/kubernetes/client/ConfigFluent;
     365: checkcast     #4                  // class io/fabric8/kubernetes/client/ConfigBuilder
     368: aload_0
     369: ldc           #75                 // String httpsProxy
     371: aload_1
     372: invokevirtual #76                 // Method io/fabric8/kubernetes/client/Config.getHttpsProxy:()Ljava/lang/String;
     375: invokevirtual #10                 // Method org/apache/dubbo/common/URL.getParameter:(Ljava/lang/String;Ljava/lang/String;)Ljava/lang/String;
     378: invokevirtual #77                 // Method io/fabric8/kubernetes/client/ConfigBuilder.withHttpsProxy:(Ljava/lang/String;)Lio/fabric8/kubernetes/client/ConfigFluent;
     381: checkcast     #4                  // class io/fabric8/kubernetes/client/ConfigBuilder
     384: aload_0
     385: ldc           #78                 // String proxyUsername
     387: aload_1
     388: invokevirtual #79                 // Method io/fabric8/kubernetes/client/Config.getProxyUsername:()Ljava/lang/String;
     391: invokevirtual #10                 // Method org/apache/dubbo/common/URL.getParameter:(Ljava/lang/String;Ljava/lang/String;)Ljava/lang/String;
     394: invokevirtual #80                 // Method io/fabric8/kubernetes/client/ConfigBuilder.withProxyUsername:(Ljava/lang/String;)Lio/fabric8/kubernetes/client/ConfigFluent;
     397: checkcast     #4                  // class io/fabric8/kubernetes/client/ConfigBuilder
     400: aload_0
     401: ldc           #81                 // String proxyPassword
     403: aload_1
     404: invokevirtual #82                 // Method io/fabric8/kubernetes/client/Config.getProxyPassword:()Ljava/lang/String;
     407: invokevirtual #10                 // Method org/apache/dubbo/common/URL.getParameter:(Ljava/lang/String;Ljava/lang/String;)Ljava/lang/String;
     410: invokevirtual #83                 // Method io/fabric8/kubernetes/client/ConfigBuilder.withProxyPassword:(Ljava/lang/String;)Lio/fabric8/kubernetes/client/ConfigFluent;
     413: checkcast     #4                  // class io/fabric8/kubernetes/client/ConfigBuilder
     416: aload_0
     417: ldc           #84                 // String noProxy
     419: aload_1
     420: invokevirtual #85                 // Method io/fabric8/kubernetes/client/Config.getNoProxy:()[Ljava/lang/String;
     423: invokevirtual #86                 // Method org/apache/dubbo/common/URL.getParameter:(Ljava/lang/String;[Ljava/lang/String;)[Ljava/lang/String;
     426: invokevirtual #87                 // Method io/fabric8/kubernetes/client/ConfigBuilder.withNoProxy:([Ljava/lang/String;)Lio/fabric8/kubernetes/client/ConfigFluent;
     429: checkcast     #4                  // class io/fabric8/kubernetes/client/ConfigBuilder
     432: invokevirtual #88                 // Method io/fabric8/kubernetes/client/ConfigBuilder.build:()Lio/fabric8/kubernetes/client/Config;
     435: areturn

  private static java.lang.String buildMasterUrl(org.apache.dubbo.common.URL);
    Code:
       0: ldc           #89                 // String DEFAULT_MASTER_HOST
       2: aload_0
       3: invokevirtual #90                 // Method org/apache/dubbo/common/URL.getHost:()Ljava/lang/String;
       6: invokevirtual #91                 // Method java/lang/String.equalsIgnoreCase:(Ljava/lang/String;)Z
       9: ifeq          15
      12: ldc           #92                 // String https://kubernetes.default.svc
      14: areturn
      15: new           #93                 // class java/lang/StringBuilder
      18: dup
      19: invokespecial #94                 // Method java/lang/StringBuilder."<init>":()V
      22: aload_0
      23: ldc           #95                 // String useHttps
      25: iconst_1
      26: invokevirtual #67                 // Method org/apache/dubbo/common/URL.getParameter:(Ljava/lang/String;Z)Z
      29: ifeq          37
      32: ldc           #96                 // String https://
      34: goto          39
      37: ldc           #97                 // String http://
      39: invokevirtual #98                 // Method java/lang/StringBuilder.append:(Ljava/lang/String;)Ljava/lang/StringBuilder;
      42: aload_0
      43: invokevirtual #90                 // Method org/apache/dubbo/common/URL.getHost:()Ljava/lang/String;
      46: invokevirtual #98                 // Method java/lang/StringBuilder.append:(Ljava/lang/String;)Ljava/lang/StringBuilder;
      49: ldc           #99                 // String :
      51: invokevirtual #98                 // Method java/lang/StringBuilder.append:(Ljava/lang/String;)Ljava/lang/StringBuilder;
      54: aload_0
      55: invokevirtual #100                // Method org/apache/dubbo/common/URL.getPort:()I
      58: invokevirtual #101                // Method java/lang/StringBuilder.append:(I)Ljava/lang/StringBuilder;
      61: invokevirtual #102                // Method java/lang/StringBuilder.toString:()Ljava/lang/String;
      64: areturn

  private static java.lang.String decodeBase64(java.lang.String);
    Code:
       0: aload_0
       1: invokestatic  #103                // Method org/apache/dubbo/common/utils/StringUtils.isNotEmpty:(Ljava/lang/String;)Z
       4: ifeq          24
       7: new           #104                // class java/lang/String
      10: dup
      11: invokestatic  #105                // Method java/util/Base64.getDecoder:()Ljava/util/Base64$Decoder;
      14: aload_0
      15: invokevirtual #106                // Method java/util/Base64$Decoder.decode:(Ljava/lang/String;)[B
      18: invokespecial #107                // Method java/lang/String."<init>":([B)V
      21: goto          25
      24: aconst_null
      25: areturn
}
