Compiled from "NacosRegistryFactory.java"
public class org.apache.dubbo.registry.nacos.NacosRegistryFactory extends org.apache.dubbo.registry.support.AbstractRegistryFactory {
  public org.apache.dubbo.registry.nacos.NacosRegistryFactory();
    Code:
       0: aload_0
       1: invokespecial #2                  // Method org/apache/dubbo/registry/support/AbstractRegistryFactory."<init>":()V
       4: return

  protected java.lang.String createRegistryCacheKey(org.apache.dubbo.common.URL);
    Code:
       0: aload_1
       1: ldc           #3                  // String namespace
       3: invokevirtual #4                  // Method org/apache/dubbo/common/URL.getParameter:(Ljava/lang/String;)Ljava/lang/String;
       6: astore_2
       7: aload_1
       8: invokevirtual #5                  // Method org/apache/dubbo/common/URL.toServiceStringWithoutResolving:()Ljava/lang/String;
      11: invokestatic  #6                  // Method org/apache/dubbo/common/URL.valueOf:(Ljava/lang/String;)Lorg/apache/dubbo/common/URL;
      14: astore_1
      15: aload_2
      16: invokestatic  #7                  // Method org/apache/dubbo/common/utils/StringUtils.isNotEmpty:(Ljava/lang/String;)Z
      19: ifeq          30
      22: aload_1
      23: ldc           #3                  // String namespace
      25: aload_2
      26: invokevirtual #8                  // Method org/apache/dubbo/common/URL.addParameter:(Ljava/lang/String;Ljava/lang/String;)Lorg/apache/dubbo/common/URL;
      29: astore_1
      30: aload_1
      31: invokevirtual #9                  // Method org/apache/dubbo/common/URL.toFullString:()Ljava/lang/String;
      34: areturn

  protected org.apache.dubbo.registry.Registry createRegistry(org.apache.dubbo.common.URL);
    Code:
       0: new           #10                 // class org/apache/dubbo/registry/nacos/NacosRegistry
       3: dup
       4: aload_1
       5: aload_1
       6: invokestatic  #11                 // Method org/apache/dubbo/registry/nacos/util/NacosNamingServiceUtils.createNamingService:(Lorg/apache/dubbo/common/URL;)Lorg/apache/dubbo/registry/nacos/NacosNamingServiceWrapper;
       9: invokespecial #12                 // Method org/apache/dubbo/registry/nacos/NacosRegistry."<init>":(Lorg/apache/dubbo/common/URL;Lorg/apache/dubbo/registry/nacos/NacosNamingServiceWrapper;)V
      12: areturn
}
