Compiled from "NacosConnectionManager.java"
public class org.apache.dubbo.registry.nacos.NacosConnectionManager {
  private static final org.apache.dubbo.common.logger.ErrorTypeAwareLogger logger;

  private final org.apache.dubbo.common.URL connectionURL;

  private final java.util.List<com.alibaba.nacos.api.naming.NamingService> namingServiceList;

  private final int retryTimes;

  private final int sleepMsBetweenRetries;

  private final boolean check;

  public org.apache.dubbo.registry.nacos.NacosConnectionManager(org.apache.dubbo.common.URL, boolean, int, int);
    Code:
       0: aload_0
       1: invokespecial #6                  // Method java/lang/Object."<init>":()V
       4: aload_0
       5: new           #7                  // class java/util/LinkedList
       8: dup
       9: invokespecial #8                  // Method java/util/LinkedList."<init>":()V
      12: putfield      #9                  // Field namingServiceList:Ljava/util/List;
      15: aload_0
      16: aload_1
      17: putfield      #10                 // Field connectionURL:Lorg/apache/dubbo/common/URL;
      20: aload_0
      21: iload_2
      22: putfield      #11                 // Field check:Z
      25: aload_0
      26: iload_3
      27: putfield      #12                 // Field retryTimes:I
      30: aload_0
      31: iload         4
      33: putfield      #13                 // Field sleepMsBetweenRetries:I
      36: aload_0
      37: getfield      #9                  // Field namingServiceList:Ljava/util/List;
      40: aload_0
      41: invokevirtual #14                 // Method createNamingService:()Lcom/alibaba/nacos/api/naming/NamingService;
      44: invokeinterface #15,  2           // InterfaceMethod java/util/List.add:(Ljava/lang/Object;)Z
      49: pop
      50: return

  protected org.apache.dubbo.registry.nacos.NacosConnectionManager(com.alibaba.nacos.api.naming.NamingService);
    Code:
       0: aload_0
       1: invokespecial #6                  // Method java/lang/Object."<init>":()V
       4: aload_0
       5: new           #7                  // class java/util/LinkedList
       8: dup
       9: invokespecial #8                  // Method java/util/LinkedList."<init>":()V
      12: putfield      #9                  // Field namingServiceList:Ljava/util/List;
      15: aload_0
      16: aconst_null
      17: putfield      #10                 // Field connectionURL:Lorg/apache/dubbo/common/URL;
      20: aload_0
      21: iconst_0
      22: putfield      #12                 // Field retryTimes:I
      25: aload_0
      26: iconst_0
      27: putfield      #13                 // Field sleepMsBetweenRetries:I
      30: aload_0
      31: iconst_0
      32: putfield      #11                 // Field check:Z
      35: aload_0
      36: getfield      #9                  // Field namingServiceList:Ljava/util/List;
      39: aload_1
      40: invokeinterface #15,  2           // InterfaceMethod java/util/List.add:(Ljava/lang/Object;)Z
      45: pop
      46: return

  public synchronized com.alibaba.nacos.api.naming.NamingService getNamingService();
    Code:
       0: aload_0
       1: getfield      #9                  // Field namingServiceList:Ljava/util/List;
       4: invokeinterface #16,  1           // InterfaceMethod java/util/List.isEmpty:()Z
       9: ifeq          26
      12: aload_0
      13: getfield      #9                  // Field namingServiceList:Ljava/util/List;
      16: aload_0
      17: invokevirtual #14                 // Method createNamingService:()Lcom/alibaba/nacos/api/naming/NamingService;
      20: invokeinterface #15,  2           // InterfaceMethod java/util/List.add:(Ljava/lang/Object;)Z
      25: pop
      26: aload_0
      27: getfield      #9                  // Field namingServiceList:Ljava/util/List;
      30: invokestatic  #17                 // Method java/util/concurrent/ThreadLocalRandom.current:()Ljava/util/concurrent/ThreadLocalRandom;
      33: aload_0
      34: getfield      #9                  // Field namingServiceList:Ljava/util/List;
      37: invokeinterface #18,  1           // InterfaceMethod java/util/List.size:()I
      42: invokevirtual #19                 // Method java/util/concurrent/ThreadLocalRandom.nextInt:(I)I
      45: invokeinterface #20,  2           // InterfaceMethod java/util/List.get:(I)Ljava/lang/Object;
      50: checkcast     #21                 // class com/alibaba/nacos/api/naming/NamingService
      53: areturn

  public synchronized com.alibaba.nacos.api.naming.NamingService getNamingService(java.util.Set<com.alibaba.nacos.api.naming.NamingService>);
    Code:
       0: new           #7                  // class java/util/LinkedList
       3: dup
       4: aload_0
       5: getfield      #9                  // Field namingServiceList:Ljava/util/List;
       8: invokespecial #22                 // Method java/util/LinkedList."<init>":(Ljava/util/Collection;)V
      11: astore_2
      12: aload_2
      13: aload_1
      14: invokeinterface #23,  2           // InterfaceMethod java/util/List.removeAll:(Ljava/util/Collection;)Z
      19: pop
      20: aload_2
      21: invokeinterface #16,  1           // InterfaceMethod java/util/List.isEmpty:()Z
      26: ifeq          49
      29: aload_0
      30: getfield      #9                  // Field namingServiceList:Ljava/util/List;
      33: aload_0
      34: invokevirtual #14                 // Method createNamingService:()Lcom/alibaba/nacos/api/naming/NamingService;
      37: invokeinterface #15,  2           // InterfaceMethod java/util/List.add:(Ljava/lang/Object;)Z
      42: pop
      43: aload_0
      44: aload_1
      45: invokevirtual #24                 // Method getNamingService:(Ljava/util/Set;)Lcom/alibaba/nacos/api/naming/NamingService;
      48: areturn
      49: aload_2
      50: invokestatic  #17                 // Method java/util/concurrent/ThreadLocalRandom.current:()Ljava/util/concurrent/ThreadLocalRandom;
      53: aload_2
      54: invokeinterface #18,  1           // InterfaceMethod java/util/List.size:()I
      59: invokevirtual #19                 // Method java/util/concurrent/ThreadLocalRandom.nextInt:(I)I
      62: invokeinterface #20,  2           // InterfaceMethod java/util/List.get:(I)Ljava/lang/Object;
      67: checkcast     #21                 // class com/alibaba/nacos/api/naming/NamingService
      70: areturn

  public synchronized void shutdownAll();
    Code:
       0: aload_0
       1: getfield      #9                  // Field namingServiceList:Ljava/util/List;
       4: invokeinterface #25,  1           // InterfaceMethod java/util/List.iterator:()Ljava/util/Iterator;
       9: astore_1
      10: aload_1
      11: invokeinterface #26,  1           // InterfaceMethod java/util/Iterator.hasNext:()Z
      16: ifeq          59
      19: aload_1
      20: invokeinterface #27,  1           // InterfaceMethod java/util/Iterator.next:()Ljava/lang/Object;
      25: checkcast     #21                 // class com/alibaba/nacos/api/naming/NamingService
      28: astore_2
      29: aload_2
      30: invokeinterface #28,  1           // InterfaceMethod com/alibaba/nacos/api/naming/NamingService.shutDown:()V
      35: goto          56
      38: astore_3
      39: getstatic     #30                 // Field logger:Lorg/apache/dubbo/common/logger/ErrorTypeAwareLogger;
      42: ldc           #31                 // String 1-37
      44: ldc           #32                 // String
      46: ldc           #32                 // String
      48: ldc           #33                 // String Unable to shutdown nacos naming service
      50: aload_3
      51: invokeinterface #34,  6           // InterfaceMethod org/apache/dubbo/common/logger/ErrorTypeAwareLogger.warn:(Ljava/lang/String;Ljava/lang/String;Ljava/lang/String;Ljava/lang/String;Ljava/lang/Throwable;)V
      56: goto          10
      59: aload_0
      60: getfield      #9                  // Field namingServiceList:Ljava/util/List;
      63: invokeinterface #35,  1           // InterfaceMethod java/util/List.clear:()V
      68: return
    Exception table:
       from    to  target type
          29    35    38   Class java/lang/Exception

  protected com.alibaba.nacos.api.naming.NamingService createNamingService();
    Code:
       0: aload_0
       1: aload_0
       2: getfield      #10                 // Field connectionURL:Lorg/apache/dubbo/common/URL;
       5: invokespecial #36                 // Method buildNacosProperties:(Lorg/apache/dubbo/common/URL;)Ljava/util/Properties;
       8: astore_1
       9: aconst_null
      10: astore_2
      11: iconst_0
      12: istore_3
      13: iload_3
      14: aload_0
      15: getfield      #12                 // Field retryTimes:I
      18: iconst_1
      19: iadd
      20: if_icmpge     165
      23: aload_1
      24: invokestatic  #37                 // Method com/alibaba/nacos/api/NacosFactory.createNamingService:(Ljava/util/Properties;)Lcom/alibaba/nacos/api/naming/NamingService;
      27: astore_2
      28: aload_0
      29: getfield      #11                 // Field check:Z
      32: ifeq          165
      35: ldc           #38                 // String UP
      37: aload_2
      38: invokeinterface #39,  1           // InterfaceMethod com/alibaba/nacos/api/naming/NamingService.getServerStatus:()Ljava/lang/String;
      43: invokevirtual #40                 // Method java/lang/String.equals:(Ljava/lang/Object;)Z
      46: ifeq          60
      49: aload_0
      50: aload_2
      51: invokespecial #41                 // Method testNamingService:(Lcom/alibaba/nacos/api/naming/NamingService;)Z
      54: ifeq          60
      57: goto          165
      60: getstatic     #30                 // Field logger:Lorg/apache/dubbo/common/logger/ErrorTypeAwareLogger;
      63: ldc           #31                 // String 1-37
      65: ldc           #32                 // String
      67: ldc           #32                 // String
      69: new           #42                 // class java/lang/StringBuilder
      72: dup
      73: invokespecial #43                 // Method java/lang/StringBuilder."<init>":()V
      76: ldc           #44                 // String Failed to connect to nacos naming server.
      78: invokevirtual #45                 // Method java/lang/StringBuilder.append:(Ljava/lang/String;)Ljava/lang/StringBuilder;
      81: iload_3
      82: aload_0
      83: getfield      #12                 // Field retryTimes:I
      86: if_icmpge     119
      89: new           #42                 // class java/lang/StringBuilder
      92: dup
      93: invokespecial #43                 // Method java/lang/StringBuilder."<init>":()V
      96: ldc           #46                 // String Dubbo will try to retry in
      98: invokevirtual #45                 // Method java/lang/StringBuilder.append:(Ljava/lang/String;)Ljava/lang/StringBuilder;
     101: aload_0
     102: getfield      #13                 // Field sleepMsBetweenRetries:I
     105: invokevirtual #47                 // Method java/lang/StringBuilder.append:(I)Ljava/lang/StringBuilder;
     108: ldc           #48                 // String .
     110: invokevirtual #45                 // Method java/lang/StringBuilder.append:(Ljava/lang/String;)Ljava/lang/StringBuilder;
     113: invokevirtual #49                 // Method java/lang/StringBuilder.toString:()Ljava/lang/String;
     116: goto          121
     119: ldc           #50                 // String Exceed retry max times.
     121: invokevirtual #45                 // Method java/lang/StringBuilder.append:(Ljava/lang/String;)Ljava/lang/StringBuilder;
     124: ldc           #51                 // String Try times:
     126: invokevirtual #45                 // Method java/lang/StringBuilder.append:(Ljava/lang/String;)Ljava/lang/StringBuilder;
     129: iload_3
     130: iconst_1
     131: iadd
     132: invokevirtual #47                 // Method java/lang/StringBuilder.append:(I)Ljava/lang/StringBuilder;
     135: invokevirtual #49                 // Method java/lang/StringBuilder.toString:()Ljava/lang/String;
     138: invokeinterface #52,  5           // InterfaceMethod org/apache/dubbo/common/logger/ErrorTypeAwareLogger.warn:(Ljava/lang/String;Ljava/lang/String;Ljava/lang/String;Ljava/lang/String;)V
     143: aload_2
     144: invokeinterface #28,  1           // InterfaceMethod com/alibaba/nacos/api/naming/NamingService.shutDown:()V
     149: aconst_null
     150: astore_2
     151: aload_0
     152: getfield      #13                 // Field sleepMsBetweenRetries:I
     155: i2l
     156: invokestatic  #53                 // Method java/lang/Thread.sleep:(J)V
     159: iinc          3, 1
     162: goto          13
     165: goto          235
     168: astore_3
     169: getstatic     #30                 // Field logger:Lorg/apache/dubbo/common/logger/ErrorTypeAwareLogger;
     172: invokeinterface #55,  1           // InterfaceMethod org/apache/dubbo/common/logger/ErrorTypeAwareLogger.isErrorEnabled:()Z
     177: ifeq          199
     180: getstatic     #30                 // Field logger:Lorg/apache/dubbo/common/logger/ErrorTypeAwareLogger;
     183: ldc           #31                 // String 1-37
     185: ldc           #32                 // String
     187: ldc           #32                 // String
     189: aload_3
     190: invokevirtual #56                 // Method com/alibaba/nacos/api/exception/NacosException.getErrMsg:()Ljava/lang/String;
     193: aload_3
     194: invokeinterface #57,  6           // InterfaceMethod org/apache/dubbo/common/logger/ErrorTypeAwareLogger.error:(Ljava/lang/String;Ljava/lang/String;Ljava/lang/String;Ljava/lang/String;Ljava/lang/Throwable;)V
     199: goto          235
     202: astore_3
     203: getstatic     #30                 // Field logger:Lorg/apache/dubbo/common/logger/ErrorTypeAwareLogger;
     206: ldc           #59                 // String 99-1
     208: ldc           #32                 // String
     210: ldc           #32                 // String
     212: ldc           #60                 // String Interrupted when creating nacos naming service client.
     214: aload_3
     215: invokeinterface #57,  6           // InterfaceMethod org/apache/dubbo/common/logger/ErrorTypeAwareLogger.error:(Ljava/lang/String;Ljava/lang/String;Ljava/lang/String;Ljava/lang/String;Ljava/lang/Throwable;)V
     220: invokestatic  #61                 // Method java/lang/Thread.currentThread:()Ljava/lang/Thread;
     223: invokevirtual #62                 // Method java/lang/Thread.interrupt:()V
     226: new           #63                 // class java/lang/IllegalStateException
     229: dup
     230: aload_3
     231: invokespecial #64                 // Method java/lang/IllegalStateException."<init>":(Ljava/lang/Throwable;)V
     234: athrow
     235: aload_2
     236: ifnonnull     265
     239: getstatic     #30                 // Field logger:Lorg/apache/dubbo/common/logger/ErrorTypeAwareLogger;
     242: ldc           #31                 // String 1-37
     244: ldc           #32                 // String
     246: ldc           #32                 // String
     248: ldc           #65                 // String Failed to create nacos naming service client. Reason: server status check failed.
     250: invokeinterface #66,  5           // InterfaceMethod org/apache/dubbo/common/logger/ErrorTypeAwareLogger.error:(Ljava/lang/String;Ljava/lang/String;Ljava/lang/String;Ljava/lang/String;)V
     255: new           #63                 // class java/lang/IllegalStateException
     258: dup
     259: ldc           #65                 // String Failed to create nacos naming service client. Reason: server status check failed.
     261: invokespecial #67                 // Method java/lang/IllegalStateException."<init>":(Ljava/lang/String;)V
     264: athrow
     265: aload_2
     266: areturn
    Exception table:
       from    to  target type
          11   165   168   Class com/alibaba/nacos/api/exception/NacosException
          11   165   202   Class java/lang/InterruptedException

  private boolean testNamingService(com.alibaba.nacos.api.naming.NamingService);
    Code:
       0: aload_1
       1: ldc           #68                 // String Dubbo-Nacos-Test
       3: iconst_0
       4: invokeinterface #69,  3           // InterfaceMethod com/alibaba/nacos/api/naming/NamingService.getAllInstances:(Ljava/lang/String;Z)Ljava/util/List;
       9: pop
      10: iconst_1
      11: ireturn
      12: astore_2
      13: iconst_0
      14: ireturn
    Exception table:
       from    to  target type
           0    11    12   Class com/alibaba/nacos/api/exception/NacosException

  private java.util.Properties buildNacosProperties(org.apache.dubbo.common.URL);
    Code:
       0: new           #70                 // class java/util/Properties
       3: dup
       4: invokespecial #71                 // Method java/util/Properties."<init>":()V
       7: astore_2
       8: aload_0
       9: aload_1
      10: aload_2
      11: invokespecial #72                 // Method setServerAddr:(Lorg/apache/dubbo/common/URL;Ljava/util/Properties;)V
      14: aload_0
      15: aload_1
      16: aload_2
      17: invokespecial #73                 // Method setProperties:(Lorg/apache/dubbo/common/URL;Ljava/util/Properties;)V
      20: aload_2
      21: areturn

  private void setServerAddr(org.apache.dubbo.common.URL, java.util.Properties);
    Code:
       0: new           #42                 // class java/lang/StringBuilder
       3: dup
       4: aload_1
       5: invokevirtual #74                 // Method org/apache/dubbo/common/URL.getHost:()Ljava/lang/String;
       8: invokespecial #75                 // Method java/lang/StringBuilder."<init>":(Ljava/lang/String;)V
      11: bipush        58
      13: invokevirtual #76                 // Method java/lang/StringBuilder.append:(C)Ljava/lang/StringBuilder;
      16: aload_1
      17: invokevirtual #77                 // Method org/apache/dubbo/common/URL.getPort:()I
      20: invokevirtual #47                 // Method java/lang/StringBuilder.append:(I)Ljava/lang/StringBuilder;
      23: astore_3
      24: aload_1
      25: ldc           #78                 // String backup
      27: invokevirtual #79                 // Method org/apache/dubbo/common/URL.getParameter:(Ljava/lang/String;)Ljava/lang/String;
      30: astore        4
      32: aload         4
      34: invokestatic  #80                 // Method org/apache/dubbo/common/utils/StringUtils.isNotEmpty:(Ljava/lang/String;)Z
      37: ifeq          52
      40: aload_3
      41: bipush        44
      43: invokevirtual #76                 // Method java/lang/StringBuilder.append:(C)Ljava/lang/StringBuilder;
      46: aload         4
      48: invokevirtual #45                 // Method java/lang/StringBuilder.append:(Ljava/lang/String;)Ljava/lang/StringBuilder;
      51: pop
      52: aload_3
      53: invokevirtual #49                 // Method java/lang/StringBuilder.toString:()Ljava/lang/String;
      56: astore        5
      58: aload_2
      59: ldc           #81                 // String serverAddr
      61: aload         5
      63: invokevirtual #82                 // Method java/util/Properties.put:(Ljava/lang/Object;Ljava/lang/Object;)Ljava/lang/Object;
      66: pop
      67: return

  private void setProperties(org.apache.dubbo.common.URL, java.util.Properties);
    Code:
       0: aload_0
       1: aload_1
       2: aload_2
       3: ldc           #83                 // String com.alibaba.nacos.naming.log.filename
       5: aconst_null
       6: invokespecial #84                 // Method putPropertyIfAbsent:(Lorg/apache/dubbo/common/URL;Ljava/util/Properties;Ljava/lang/String;Ljava/lang/String;)V
       9: aload_1
      10: ldc           #1                  // class com/alibaba/nacos/api/PropertyKeyConst
      12: invokestatic  #85                 // Method org/apache/dubbo/common/utils/StringConstantFieldValuePredicate.of:(Ljava/lang/Class;)Ljava/util/function/Predicate;
      15: invokevirtual #86                 // Method org/apache/dubbo/common/URL.getParameters:(Ljava/util/function/Predicate;)Ljava/util/Map;
      18: astore_3
      19: aload_2
      20: aload_3
      21: invokevirtual #87                 // Method java/util/Properties.putAll:(Ljava/util/Map;)V
      24: aload_1
      25: invokevirtual #88                 // Method org/apache/dubbo/common/URL.getUsername:()Ljava/lang/String;
      28: invokestatic  #80                 // Method org/apache/dubbo/common/utils/StringUtils.isNotEmpty:(Ljava/lang/String;)Z
      31: ifeq          45
      34: aload_2
      35: ldc           #89                 // String username
      37: aload_1
      38: invokevirtual #88                 // Method org/apache/dubbo/common/URL.getUsername:()Ljava/lang/String;
      41: invokevirtual #82                 // Method java/util/Properties.put:(Ljava/lang/Object;Ljava/lang/Object;)Ljava/lang/Object;
      44: pop
      45: aload_1
      46: invokevirtual #90                 // Method org/apache/dubbo/common/URL.getPassword:()Ljava/lang/String;
      49: invokestatic  #80                 // Method org/apache/dubbo/common/utils/StringUtils.isNotEmpty:(Ljava/lang/String;)Z
      52: ifeq          66
      55: aload_2
      56: ldc           #91                 // String password
      58: aload_1
      59: invokevirtual #90                 // Method org/apache/dubbo/common/URL.getPassword:()Ljava/lang/String;
      62: invokevirtual #82                 // Method java/util/Properties.put:(Ljava/lang/Object;Ljava/lang/Object;)Ljava/lang/Object;
      65: pop
      66: return

  private void putPropertyIfAbsent(org.apache.dubbo.common.URL, java.util.Properties, java.lang.String, java.lang.String);
    Code:
       0: aload_1
       1: aload_3
       2: invokevirtual #79                 // Method org/apache/dubbo/common/URL.getParameter:(Ljava/lang/String;)Ljava/lang/String;
       5: astore        5
       7: aload         5
       9: invokestatic  #80                 // Method org/apache/dubbo/common/utils/StringUtils.isNotEmpty:(Ljava/lang/String;)Z
      12: ifeq          26
      15: aload_2
      16: aload_3
      17: aload         5
      19: invokevirtual #92                 // Method java/util/Properties.setProperty:(Ljava/lang/String;Ljava/lang/String;)Ljava/lang/Object;
      22: pop
      23: goto          42
      26: aload         4
      28: invokestatic  #80                 // Method org/apache/dubbo/common/utils/StringUtils.isNotEmpty:(Ljava/lang/String;)Z
      31: ifeq          42
      34: aload_2
      35: aload_3
      36: aload         4
      38: invokevirtual #92                 // Method java/util/Properties.setProperty:(Ljava/lang/String;Ljava/lang/String;)Ljava/lang/Object;
      41: pop
      42: return

  static {};
    Code:
       0: ldc           #93                 // class org/apache/dubbo/registry/nacos/util/NacosNamingServiceUtils
       2: invokestatic  #94                 // Method org/apache/dubbo/common/logger/LoggerFactory.getErrorTypeAwareLogger:(Ljava/lang/Class;)Lorg/apache/dubbo/common/logger/ErrorTypeAwareLogger;
       5: putstatic     #30                 // Field logger:Lorg/apache/dubbo/common/logger/ErrorTypeAwareLogger;
       8: return
}
