Compiled from "NacosServiceDiscovery.java"
public class org.apache.dubbo.registry.nacos.NacosServiceDiscovery extends org.apache.dubbo.registry.client.AbstractServiceDiscovery {
  private final org.apache.dubbo.common.logger.ErrorTypeAwareLogger logger;

  private final java.lang.String group;

  private final org.apache.dubbo.registry.nacos.NacosNamingServiceWrapper namingService;

  private static final java.lang.String NACOS_SD_USE_DEFAULT_GROUP_KEY;

  private final java.util.concurrent.ConcurrentHashMap<java.lang.String, org.apache.dubbo.registry.nacos.NacosServiceDiscovery$NacosEventListener> eventListeners;

  public org.apache.dubbo.registry.nacos.NacosServiceDiscovery(org.apache.dubbo.rpc.model.ApplicationModel, org.apache.dubbo.common.URL);
    Code:
       0: aload_0
       1: aload_1
       2: aload_2
       3: invokespecial #7                  // Method org/apache/dubbo/registry/client/AbstractServiceDiscovery."<init>":(Lorg/apache/dubbo/rpc/model/ApplicationModel;Lorg/apache/dubbo/common/URL;)V
       6: aload_0
       7: aload_0
       8: invokevirtual #8                  // Method java/lang/Object.getClass:()Ljava/lang/Class;
      11: invokestatic  #9                  // Method org/apache/dubbo/common/logger/LoggerFactory.getErrorTypeAwareLogger:(Ljava/lang/Class;)Lorg/apache/dubbo/common/logger/ErrorTypeAwareLogger;
      14: putfield      #10                 // Field logger:Lorg/apache/dubbo/common/logger/ErrorTypeAwareLogger;
      17: aload_0
      18: new           #11                 // class java/util/concurrent/ConcurrentHashMap
      21: dup
      22: invokespecial #12                 // Method java/util/concurrent/ConcurrentHashMap."<init>":()V
      25: putfield      #13                 // Field eventListeners:Ljava/util/concurrent/ConcurrentHashMap;
      28: aload_0
      29: aload_2
      30: invokestatic  #14                 // Method org/apache/dubbo/registry/nacos/util/NacosNamingServiceUtils.createNamingService:(Lorg/apache/dubbo/common/URL;)Lorg/apache/dubbo/registry/nacos/NacosNamingServiceWrapper;
      33: putfield      #15                 // Field namingService:Lorg/apache/dubbo/registry/nacos/NacosNamingServiceWrapper;
      36: aload_0
      37: aload_1
      38: ldc           #17                 // String dubbo.nacos-service-discovery.use-default-group
      40: ldc           #18                 // String false
      42: invokestatic  #19                 // Method org/apache/dubbo/common/config/ConfigurationUtils.getProperty:(Lorg/apache/dubbo/rpc/model/ScopeModel;Ljava/lang/String;Ljava/lang/String;)Ljava/lang/String;
      45: invokestatic  #20                 // Method java/lang/Boolean.parseBoolean:(Ljava/lang/String;)Z
      48: ifeq          56
      51: ldc           #21                 // String DEFAULT_GROUP
      53: goto          60
      56: aload_2
      57: invokestatic  #22                 // Method org/apache/dubbo/registry/nacos/util/NacosNamingServiceUtils.getGroup:(Lorg/apache/dubbo/common/URL;)Ljava/lang/String;
      60: putfield      #23                 // Field group:Ljava/lang/String;
      63: return

  public void doDestroy() throws java.lang.Exception;
    Code:
       0: aload_0
       1: getfield      #15                 // Field namingService:Lorg/apache/dubbo/registry/nacos/NacosNamingServiceWrapper;
       4: invokevirtual #24                 // Method org/apache/dubbo/registry/nacos/NacosNamingServiceWrapper.shutdown:()V
       7: aload_0
       8: getfield      #13                 // Field eventListeners:Ljava/util/concurrent/ConcurrentHashMap;
      11: invokevirtual #25                 // Method java/util/concurrent/ConcurrentHashMap.clear:()V
      14: return

  public void doRegister(org.apache.dubbo.registry.client.ServiceInstance);
    Code:
       0: aload_0
       1: getfield      #15                 // Field namingService:Lorg/apache/dubbo/registry/nacos/NacosNamingServiceWrapper;
       4: aload_0
       5: aload_1
       6: invokedynamic #26,  0             // InvokeDynamic #0:accept:(Lorg/apache/dubbo/registry/nacos/NacosServiceDiscovery;Lorg/apache/dubbo/registry/client/ServiceInstance;)Lorg/apache/dubbo/common/function/ThrowableConsumer;
      11: invokestatic  #27                 // InterfaceMethod org/apache/dubbo/common/function/ThrowableConsumer.execute:(Ljava/lang/Object;Lorg/apache/dubbo/common/function/ThrowableConsumer;)V
      14: return

  public void doUnregister(org.apache.dubbo.registry.client.ServiceInstance) throws java.lang.RuntimeException;
    Code:
       0: aload_0
       1: getfield      #15                 // Field namingService:Lorg/apache/dubbo/registry/nacos/NacosNamingServiceWrapper;
       4: aload_0
       5: aload_1
       6: invokedynamic #28,  0             // InvokeDynamic #1:accept:(Lorg/apache/dubbo/registry/nacos/NacosServiceDiscovery;Lorg/apache/dubbo/registry/client/ServiceInstance;)Lorg/apache/dubbo/common/function/ThrowableConsumer;
      11: invokestatic  #27                 // InterfaceMethod org/apache/dubbo/common/function/ThrowableConsumer.execute:(Ljava/lang/Object;Lorg/apache/dubbo/common/function/ThrowableConsumer;)V
      14: return

  protected void doUpdate(org.apache.dubbo.registry.client.ServiceInstance, org.apache.dubbo.registry.client.ServiceInstance) throws java.lang.RuntimeException;
    Code:
       0: ldc           #29                 // String 0
       2: aload_2
       3: invokestatic  #30                 // Method org/apache/dubbo/registry/client/metadata/ServiceInstanceMetadataUtils.getExportedServicesRevision:(Lorg/apache/dubbo/registry/client/ServiceInstance;)Ljava/lang/String;
       6: invokevirtual #31                 // Method java/lang/String.equals:(Ljava/lang/Object;)Z
       9: ifne          33
      12: ldc           #29                 // String 0
      14: aload_1
      15: invokeinterface #32,  1           // InterfaceMethod org/apache/dubbo/registry/client/ServiceInstance.getMetadata:()Ljava/util/Map;
      20: ldc           #33                 // String dubbo.metadata.revision
      22: invokeinterface #34,  2           // InterfaceMethod java/util/Map.get:(Ljava/lang/Object;)Ljava/lang/Object;
      27: invokevirtual #31                 // Method java/lang/String.equals:(Ljava/lang/Object;)Z
      30: ifeq          40
      33: aload_0
      34: aload_1
      35: aload_2
      36: invokespecial #35                 // Method org/apache/dubbo/registry/client/AbstractServiceDiscovery.doUpdate:(Lorg/apache/dubbo/registry/client/ServiceInstance;Lorg/apache/dubbo/registry/client/ServiceInstance;)V
      39: return
      40: aload_2
      41: invokeinterface #36,  1           // InterfaceMethod org/apache/dubbo/registry/client/ServiceInstance.getHost:()Ljava/lang/String;
      46: aload_1
      47: invokeinterface #36,  1           // InterfaceMethod org/apache/dubbo/registry/client/ServiceInstance.getHost:()Ljava/lang/String;
      52: invokestatic  #37                 // Method java/util/Objects.equals:(Ljava/lang/Object;Ljava/lang/Object;)Z
      55: ifeq          82
      58: aload_2
      59: invokeinterface #38,  1           // InterfaceMethod org/apache/dubbo/registry/client/ServiceInstance.getPort:()I
      64: invokestatic  #39                 // Method java/lang/Integer.valueOf:(I)Ljava/lang/Integer;
      67: aload_1
      68: invokeinterface #38,  1           // InterfaceMethod org/apache/dubbo/registry/client/ServiceInstance.getPort:()I
      73: invokestatic  #39                 // Method java/lang/Integer.valueOf:(I)Ljava/lang/Integer;
      76: invokestatic  #37                 // Method java/util/Objects.equals:(Ljava/lang/Object;Ljava/lang/Object;)Z
      79: ifne          89
      82: aload_0
      83: aload_1
      84: aload_2
      85: invokespecial #35                 // Method org/apache/dubbo/registry/client/AbstractServiceDiscovery.doUpdate:(Lorg/apache/dubbo/registry/client/ServiceInstance;Lorg/apache/dubbo/registry/client/ServiceInstance;)V
      88: return
      89: aload_1
      90: invokestatic  #40                 // Method org/apache/dubbo/registry/nacos/util/NacosNamingServiceUtils.toInstance:(Lorg/apache/dubbo/registry/client/ServiceInstance;)Lcom/alibaba/nacos/api/naming/pojo/Instance;
      93: astore_3
      94: aload_2
      95: invokestatic  #40                 // Method org/apache/dubbo/registry/nacos/util/NacosNamingServiceUtils.toInstance:(Lorg/apache/dubbo/registry/client/ServiceInstance;)Lcom/alibaba/nacos/api/naming/pojo/Instance;
      98: astore        4
     100: aload_0
     101: aload_2
     102: putfield      #41                 // Field serviceInstance:Lorg/apache/dubbo/registry/client/ServiceInstance;
     105: aload_0
     106: aload_2
     107: invokeinterface #42,  1           // InterfaceMethod org/apache/dubbo/registry/client/ServiceInstance.getServiceMetadata:()Lorg/apache/dubbo/metadata/MetadataInfo;
     112: invokevirtual #43                 // Method reportMetadata:(Lorg/apache/dubbo/metadata/MetadataInfo;)V
     115: aload_0
     116: getfield      #15                 // Field namingService:Lorg/apache/dubbo/registry/nacos/NacosNamingServiceWrapper;
     119: aload_0
     120: aload_3
     121: aload         4
     123: invokedynamic #44,  0             // InvokeDynamic #2:accept:(Lorg/apache/dubbo/registry/nacos/NacosServiceDiscovery;Lcom/alibaba/nacos/api/naming/pojo/Instance;Lcom/alibaba/nacos/api/naming/pojo/Instance;)Lorg/apache/dubbo/common/function/ThrowableConsumer;
     128: invokestatic  #27                 // InterfaceMethod org/apache/dubbo/common/function/ThrowableConsumer.execute:(Ljava/lang/Object;Lorg/apache/dubbo/common/function/ThrowableConsumer;)V
     131: goto          170
     134: astore        5
     136: new           #2                  // class org/apache/dubbo/rpc/RpcException
     139: dup
     140: bipush        9
     142: new           #46                 // class java/lang/StringBuilder
     145: dup
     146: invokespecial #47                 // Method java/lang/StringBuilder."<init>":()V
     149: ldc           #48                 // String Failed register instance
     151: invokevirtual #49                 // Method java/lang/StringBuilder.append:(Ljava/lang/String;)Ljava/lang/StringBuilder;
     154: aload_2
     155: invokevirtual #50                 // Method java/lang/Object.toString:()Ljava/lang/String;
     158: invokevirtual #49                 // Method java/lang/StringBuilder.append:(Ljava/lang/String;)Ljava/lang/StringBuilder;
     161: invokevirtual #51                 // Method java/lang/StringBuilder.toString:()Ljava/lang/String;
     164: aload         5
     166: invokespecial #52                 // Method org/apache/dubbo/rpc/RpcException."<init>":(ILjava/lang/String;Ljava/lang/Throwable;)V
     169: athrow
     170: return
    Exception table:
       from    to  target type
         100   131   134   Class java/lang/Exception

  public java.util.Set<java.lang.String> getServices();
    Code:
       0: aload_0
       1: getfield      #15                 // Field namingService:Lorg/apache/dubbo/registry/nacos/NacosNamingServiceWrapper;
       4: aload_0
       5: invokedynamic #53,  0             // InvokeDynamic #3:apply:(Lorg/apache/dubbo/registry/nacos/NacosServiceDiscovery;)Lorg/apache/dubbo/common/function/ThrowableFunction;
      10: invokestatic  #54                 // InterfaceMethod org/apache/dubbo/common/function/ThrowableFunction.execute:(Ljava/lang/Object;Lorg/apache/dubbo/common/function/ThrowableFunction;)Ljava/lang/Object;
      13: checkcast     #55                 // class java/util/Set
      16: areturn

  public java.util.List<org.apache.dubbo.registry.client.ServiceInstance> getInstances(java.lang.String) throws java.lang.NullPointerException;
    Code:
       0: aload_0
       1: getfield      #15                 // Field namingService:Lorg/apache/dubbo/registry/nacos/NacosNamingServiceWrapper;
       4: aload_0
       5: aload_1
       6: invokedynamic #56,  0             // InvokeDynamic #4:apply:(Lorg/apache/dubbo/registry/nacos/NacosServiceDiscovery;Ljava/lang/String;)Lorg/apache/dubbo/common/function/ThrowableFunction;
      11: invokestatic  #54                 // InterfaceMethod org/apache/dubbo/common/function/ThrowableFunction.execute:(Ljava/lang/Object;Lorg/apache/dubbo/common/function/ThrowableFunction;)Ljava/lang/Object;
      14: checkcast     #57                 // class java/util/List
      17: areturn

  public void addServiceInstancesChangedListener(org.apache.dubbo.registry.client.event.listener.ServiceInstancesChangedListener) throws java.lang.NullPointerException, java.lang.IllegalArgumentException;
    Code:
       0: aload_0
       1: getfield      #58                 // Field instanceListeners:Ljava/util/Set;
       4: aload_1
       5: invokeinterface #59,  2           // InterfaceMethod java/util/Set.add:(Ljava/lang/Object;)Z
      10: ifne          14
      13: return
      14: aload_1
      15: invokevirtual #60                 // Method org/apache/dubbo/registry/client/event/listener/ServiceInstancesChangedListener.getServiceNames:()Ljava/util/Set;
      18: invokeinterface #61,  1           // InterfaceMethod java/util/Set.iterator:()Ljava/util/Iterator;
      23: astore_2
      24: aload_2
      25: invokeinterface #62,  1           // InterfaceMethod java/util/Iterator.hasNext:()Z
      30: ifeq          138
      33: aload_2
      34: invokeinterface #63,  1           // InterfaceMethod java/util/Iterator.next:()Ljava/lang/Object;
      39: checkcast     #64                 // class java/lang/String
      42: astore_3
      43: aload_0
      44: getfield      #13                 // Field eventListeners:Ljava/util/concurrent/ConcurrentHashMap;
      47: aload_3
      48: invokevirtual #65                 // Method java/util/concurrent/ConcurrentHashMap.get:(Ljava/lang/Object;)Ljava/lang/Object;
      51: checkcast     #66                 // class org/apache/dubbo/registry/nacos/NacosServiceDiscovery$NacosEventListener
      54: astore        4
      56: aload         4
      58: ifnull        70
      61: aload         4
      63: aload_1
      64: invokevirtual #67                 // Method org/apache/dubbo/registry/nacos/NacosServiceDiscovery$NacosEventListener.addListener:(Lorg/apache/dubbo/registry/client/event/listener/ServiceInstancesChangedListener;)V
      67: goto          135
      70: new           #66                 // class org/apache/dubbo/registry/nacos/NacosServiceDiscovery$NacosEventListener
      73: dup
      74: aload_0
      75: invokespecial #68                 // Method org/apache/dubbo/registry/nacos/NacosServiceDiscovery$NacosEventListener."<init>":(Lorg/apache/dubbo/registry/nacos/NacosServiceDiscovery;)V
      78: astore        4
      80: aload         4
      82: aload_1
      83: invokevirtual #67                 // Method org/apache/dubbo/registry/nacos/NacosServiceDiscovery$NacosEventListener.addListener:(Lorg/apache/dubbo/registry/client/event/listener/ServiceInstancesChangedListener;)V
      86: aload_0
      87: getfield      #15                 // Field namingService:Lorg/apache/dubbo/registry/nacos/NacosNamingServiceWrapper;
      90: aload_3
      91: aload_0
      92: getfield      #23                 // Field group:Ljava/lang/String;
      95: aload         4
      97: invokevirtual #69                 // Method org/apache/dubbo/registry/nacos/NacosNamingServiceWrapper.subscribe:(Ljava/lang/String;Ljava/lang/String;Lcom/alibaba/nacos/api/naming/listener/EventListener;)V
     100: aload_0
     101: getfield      #13                 // Field eventListeners:Ljava/util/concurrent/ConcurrentHashMap;
     104: aload_3
     105: aload         4
     107: invokevirtual #70                 // Method java/util/concurrent/ConcurrentHashMap.put:(Ljava/lang/Object;Ljava/lang/Object;)Ljava/lang/Object;
     110: pop
     111: goto          135
     114: astore        5
     116: aload_0
     117: getfield      #10                 // Field logger:Lorg/apache/dubbo/common/logger/ErrorTypeAwareLogger;
     120: ldc           #72                 // String 1-37
     122: ldc           #73                 // String
     124: ldc           #73                 // String
     126: ldc           #74                 // String add nacos service instances changed listener fail
     128: aload         5
     130: invokeinterface #75,  6           // InterfaceMethod org/apache/dubbo/common/logger/ErrorTypeAwareLogger.error:(Ljava/lang/String;Ljava/lang/String;Ljava/lang/String;Ljava/lang/String;Ljava/lang/Throwable;)V
     135: goto          24
     138: return
    Exception table:
       from    to  target type
          70   111   114   Class com/alibaba/nacos/api/exception/NacosException

  public void removeServiceInstancesChangedListener(org.apache.dubbo.registry.client.event.listener.ServiceInstancesChangedListener) throws java.lang.IllegalArgumentException;
    Code:
       0: aload_0
       1: getfield      #58                 // Field instanceListeners:Ljava/util/Set;
       4: aload_1
       5: invokeinterface #76,  2           // InterfaceMethod java/util/Set.remove:(Ljava/lang/Object;)Z
      10: ifne          14
      13: return
      14: aload_1
      15: invokevirtual #60                 // Method org/apache/dubbo/registry/client/event/listener/ServiceInstancesChangedListener.getServiceNames:()Ljava/util/Set;
      18: invokeinterface #61,  1           // InterfaceMethod java/util/Set.iterator:()Ljava/util/Iterator;
      23: astore_2
      24: aload_2
      25: invokeinterface #62,  1           // InterfaceMethod java/util/Iterator.hasNext:()Z
      30: ifeq          125
      33: aload_2
      34: invokeinterface #63,  1           // InterfaceMethod java/util/Iterator.next:()Ljava/lang/Object;
      39: checkcast     #64                 // class java/lang/String
      42: astore_3
      43: aload_0
      44: getfield      #13                 // Field eventListeners:Ljava/util/concurrent/ConcurrentHashMap;
      47: aload_3
      48: invokevirtual #65                 // Method java/util/concurrent/ConcurrentHashMap.get:(Ljava/lang/Object;)Ljava/lang/Object;
      51: checkcast     #66                 // class org/apache/dubbo/registry/nacos/NacosServiceDiscovery$NacosEventListener
      54: astore        4
      56: aload         4
      58: ifnull        122
      61: aload         4
      63: aload_1
      64: invokevirtual #77                 // Method org/apache/dubbo/registry/nacos/NacosServiceDiscovery$NacosEventListener.removeListener:(Lorg/apache/dubbo/registry/client/event/listener/ServiceInstancesChangedListener;)V
      67: aload         4
      69: invokevirtual #78                 // Method org/apache/dubbo/registry/nacos/NacosServiceDiscovery$NacosEventListener.isEmpty:()Z
      72: ifeq          122
      75: aload_0
      76: getfield      #13                 // Field eventListeners:Ljava/util/concurrent/ConcurrentHashMap;
      79: aload_3
      80: invokevirtual #79                 // Method java/util/concurrent/ConcurrentHashMap.remove:(Ljava/lang/Object;)Ljava/lang/Object;
      83: pop
      84: aload_0
      85: getfield      #15                 // Field namingService:Lorg/apache/dubbo/registry/nacos/NacosNamingServiceWrapper;
      88: aload_3
      89: aload_0
      90: getfield      #23                 // Field group:Ljava/lang/String;
      93: aload         4
      95: invokevirtual #80                 // Method org/apache/dubbo/registry/nacos/NacosNamingServiceWrapper.unsubscribe:(Ljava/lang/String;Ljava/lang/String;Lcom/alibaba/nacos/api/naming/listener/EventListener;)V
      98: goto          122
     101: astore        5
     103: aload_0
     104: getfield      #10                 // Field logger:Lorg/apache/dubbo/common/logger/ErrorTypeAwareLogger;
     107: ldc           #72                 // String 1-37
     109: ldc           #73                 // String
     111: ldc           #73                 // String
     113: ldc           #81                 // String remove nacos service instances changed listener fail
     115: aload         5
     117: invokeinterface #75,  6           // InterfaceMethod org/apache/dubbo/common/logger/ErrorTypeAwareLogger.error:(Ljava/lang/String;Ljava/lang/String;Ljava/lang/String;Ljava/lang/String;Ljava/lang/Throwable;)V
     122: goto          24
     125: return
    Exception table:
       from    to  target type
          84    98   101   Class com/alibaba/nacos/api/exception/NacosException

  public org.apache.dubbo.common.URL getUrl();
    Code:
       0: aload_0
       1: getfield      #82                 // Field registryURL:Lorg/apache/dubbo/common/URL;
       4: areturn

  private void handleEvent(com.alibaba.nacos.api.naming.listener.NamingEvent, org.apache.dubbo.registry.client.event.listener.ServiceInstancesChangedListener);
    Code:
       0: aload_1
       1: invokevirtual #83                 // Method com/alibaba/nacos/api/naming/listener/NamingEvent.getServiceName:()Ljava/lang/String;
       4: astore_3
       5: aload_1
       6: invokevirtual #84                 // Method com/alibaba/nacos/api/naming/listener/NamingEvent.getInstances:()Ljava/util/List;
       9: invokeinterface #85,  1           // InterfaceMethod java/util/List.stream:()Ljava/util/stream/Stream;
      14: aload_0
      15: invokedynamic #86,  0             // InvokeDynamic #5:apply:(Lorg/apache/dubbo/registry/nacos/NacosServiceDiscovery;)Ljava/util/function/Function;
      20: invokeinterface #87,  2           // InterfaceMethod java/util/stream/Stream.map:(Ljava/util/function/Function;)Ljava/util/stream/Stream;
      25: invokestatic  #88                 // Method java/util/stream/Collectors.toList:()Ljava/util/stream/Collector;
      28: invokeinterface #89,  2           // InterfaceMethod java/util/stream/Stream.collect:(Ljava/util/stream/Collector;)Ljava/lang/Object;
      33: checkcast     #57                 // class java/util/List
      36: astore        4
      38: aload_2
      39: new           #90                 // class org/apache/dubbo/registry/client/event/ServiceInstancesChangedEvent
      42: dup
      43: aload_3
      44: aload         4
      46: invokespecial #91                 // Method org/apache/dubbo/registry/client/event/ServiceInstancesChangedEvent."<init>":(Ljava/lang/String;Ljava/util/List;)V
      49: invokevirtual #92                 // Method org/apache/dubbo/registry/client/event/listener/ServiceInstancesChangedListener.onEvent:(Lorg/apache/dubbo/registry/client/event/ServiceInstancesChangedEvent;)V
      52: return

  private org.apache.dubbo.registry.client.ServiceInstance lambda$handleEvent$6(com.alibaba.nacos.api.naming.pojo.Instance);
    Code:
       0: aload_0
       1: getfield      #82                 // Field registryURL:Lorg/apache/dubbo/common/URL;
       4: aload_1
       5: invokestatic  #93                 // Method org/apache/dubbo/registry/nacos/util/NacosNamingServiceUtils.toServiceInstance:(Lorg/apache/dubbo/common/URL;Lcom/alibaba/nacos/api/naming/pojo/Instance;)Lorg/apache/dubbo/registry/client/ServiceInstance;
       8: areturn

  private java.util.List lambda$getInstances$5(java.lang.String, org.apache.dubbo.registry.nacos.NacosNamingServiceWrapper) throws java.lang.Throwable;
    Code:
       0: aload_2
       1: aload_1
       2: aload_0
       3: getfield      #23                 // Field group:Ljava/lang/String;
       6: iconst_1
       7: invokevirtual #94                 // Method org/apache/dubbo/registry/nacos/NacosNamingServiceWrapper.selectInstances:(Ljava/lang/String;Ljava/lang/String;Z)Ljava/util/List;
      10: invokeinterface #85,  1           // InterfaceMethod java/util/List.stream:()Ljava/util/stream/Stream;
      15: aload_0
      16: invokedynamic #95,  0             // InvokeDynamic #6:apply:(Lorg/apache/dubbo/registry/nacos/NacosServiceDiscovery;)Ljava/util/function/Function;
      21: invokeinterface #87,  2           // InterfaceMethod java/util/stream/Stream.map:(Ljava/util/function/Function;)Ljava/util/stream/Stream;
      26: invokestatic  #88                 // Method java/util/stream/Collectors.toList:()Ljava/util/stream/Collector;
      29: invokeinterface #89,  2           // InterfaceMethod java/util/stream/Stream.collect:(Ljava/util/stream/Collector;)Ljava/lang/Object;
      34: checkcast     #57                 // class java/util/List
      37: areturn

  private org.apache.dubbo.registry.client.ServiceInstance lambda$null$4(com.alibaba.nacos.api.naming.pojo.Instance);
    Code:
       0: aload_0
       1: getfield      #82                 // Field registryURL:Lorg/apache/dubbo/common/URL;
       4: aload_1
       5: invokestatic  #93                 // Method org/apache/dubbo/registry/nacos/util/NacosNamingServiceUtils.toServiceInstance:(Lorg/apache/dubbo/common/URL;Lcom/alibaba/nacos/api/naming/pojo/Instance;)Lorg/apache/dubbo/registry/client/ServiceInstance;
       8: areturn

  private java.util.LinkedHashSet lambda$getServices$3(org.apache.dubbo.registry.nacos.NacosNamingServiceWrapper) throws java.lang.Throwable;
    Code:
       0: aload_1
       1: iconst_0
       2: ldc           #97                 // int 2147483647
       4: aload_0
       5: getfield      #23                 // Field group:Ljava/lang/String;
       8: invokevirtual #98                 // Method org/apache/dubbo/registry/nacos/NacosNamingServiceWrapper.getServicesOfServer:(IILjava/lang/String;)Lcom/alibaba/nacos/api/naming/pojo/ListView;
      11: astore_2
      12: new           #99                 // class java/util/LinkedHashSet
      15: dup
      16: aload_2
      17: invokevirtual #100                // Method com/alibaba/nacos/api/naming/pojo/ListView.getData:()Ljava/util/List;
      20: invokespecial #101                // Method java/util/LinkedHashSet."<init>":(Ljava/util/Collection;)V
      23: areturn

  private void lambda$doUpdate$2(com.alibaba.nacos.api.naming.pojo.Instance, com.alibaba.nacos.api.naming.pojo.Instance, org.apache.dubbo.registry.nacos.NacosNamingServiceWrapper) throws java.lang.Throwable;
    Code:
       0: aload_0
       1: getfield      #41                 // Field serviceInstance:Lorg/apache/dubbo/registry/client/ServiceInstance;
       4: invokestatic  #40                 // Method org/apache/dubbo/registry/nacos/util/NacosNamingServiceUtils.toInstance:(Lorg/apache/dubbo/registry/client/ServiceInstance;)Lcom/alibaba/nacos/api/naming/pojo/Instance;
       7: astore        4
       9: aload_3
      10: aload         4
      12: invokevirtual #102                // Method com/alibaba/nacos/api/naming/pojo/Instance.getServiceName:()Ljava/lang/String;
      15: aload_0
      16: getfield      #23                 // Field group:Ljava/lang/String;
      19: aload_1
      20: aload_2
      21: invokevirtual #103                // Method org/apache/dubbo/registry/nacos/NacosNamingServiceWrapper.updateInstance:(Ljava/lang/String;Ljava/lang/String;Lcom/alibaba/nacos/api/naming/pojo/Instance;Lcom/alibaba/nacos/api/naming/pojo/Instance;)V
      24: return

  private void lambda$doUnregister$1(org.apache.dubbo.registry.client.ServiceInstance, org.apache.dubbo.registry.nacos.NacosNamingServiceWrapper) throws java.lang.Throwable;
    Code:
       0: aload_1
       1: invokestatic  #40                 // Method org/apache/dubbo/registry/nacos/util/NacosNamingServiceUtils.toInstance:(Lorg/apache/dubbo/registry/client/ServiceInstance;)Lcom/alibaba/nacos/api/naming/pojo/Instance;
       4: astore_3
       5: aload_2
       6: aload_3
       7: invokevirtual #102                // Method com/alibaba/nacos/api/naming/pojo/Instance.getServiceName:()Ljava/lang/String;
      10: aload_0
      11: getfield      #23                 // Field group:Ljava/lang/String;
      14: aload_3
      15: invokevirtual #104                // Method org/apache/dubbo/registry/nacos/NacosNamingServiceWrapper.deregisterInstance:(Ljava/lang/String;Ljava/lang/String;Lcom/alibaba/nacos/api/naming/pojo/Instance;)V
      18: return

  private void lambda$doRegister$0(org.apache.dubbo.registry.client.ServiceInstance, org.apache.dubbo.registry.nacos.NacosNamingServiceWrapper) throws java.lang.Throwable;
    Code:
       0: aload_1
       1: invokestatic  #40                 // Method org/apache/dubbo/registry/nacos/util/NacosNamingServiceUtils.toInstance:(Lorg/apache/dubbo/registry/client/ServiceInstance;)Lcom/alibaba/nacos/api/naming/pojo/Instance;
       4: astore_3
       5: aload_2
       6: aload_3
       7: invokevirtual #102                // Method com/alibaba/nacos/api/naming/pojo/Instance.getServiceName:()Ljava/lang/String;
      10: aload_0
      11: getfield      #23                 // Field group:Ljava/lang/String;
      14: aload_3
      15: invokevirtual #105                // Method org/apache/dubbo/registry/nacos/NacosNamingServiceWrapper.registerInstance:(Ljava/lang/String;Ljava/lang/String;Lcom/alibaba/nacos/api/naming/pojo/Instance;)V
      18: return

  static void access$000(org.apache.dubbo.registry.nacos.NacosServiceDiscovery, com.alibaba.nacos.api.naming.listener.NamingEvent, org.apache.dubbo.registry.client.event.listener.ServiceInstancesChangedListener);
    Code:
       0: aload_0
       1: aload_1
       2: aload_2
       3: invokespecial #6                  // Method handleEvent:(Lcom/alibaba/nacos/api/naming/listener/NamingEvent;Lorg/apache/dubbo/registry/client/event/listener/ServiceInstancesChangedListener;)V
       6: return
}
