Compiled from "NacosServiceName.java"
public class org.apache.dubbo.registry.nacos.NacosServiceName {
  public static final java.lang.String NAME_SEPARATOR;

  public static final java.lang.String VALUE_SEPARATOR;

  public static final java.lang.String WILDCARD;

  public static final java.lang.String DEFAULT_PARAM_VALUE;

  private static final int CATEGORY_INDEX;

  private static final int SERVICE_INTERFACE_INDEX;

  private static final int SERVICE_VERSION_INDEX;

  private static final int SERVICE_GROUP_INDEX;

  private java.lang.String category;

  private java.lang.String serviceInterface;

  private java.lang.String version;

  private java.lang.String group;

  private java.lang.String value;

  public org.apache.dubbo.registry.nacos.NacosServiceName();
    Code:
       0: aload_0
       1: invokespecial #3                  // Method java/lang/Object."<init>":()V
       4: return

  public org.apache.dubbo.registry.nacos.NacosServiceName(org.apache.dubbo.common.URL);
    Code:
       0: aload_0
       1: invokespecial #3                  // Method java/lang/Object."<init>":()V
       4: aload_0
       5: aload_1
       6: ldc           #4                  // String interface
       8: invokevirtual #5                  // Method org/apache/dubbo/common/URL.getParameter:(Ljava/lang/String;)Ljava/lang/String;
      11: putfield      #6                  // Field serviceInterface:Ljava/lang/String;
      14: aload_0
      15: aload_0
      16: aload_0
      17: getfield      #6                  // Field serviceInterface:Ljava/lang/String;
      20: invokespecial #7                  // Method isConcrete:(Ljava/lang/String;)Z
      23: ifeq          31
      26: ldc           #8                  // String providers
      28: goto          35
      31: aload_1
      32: invokevirtual #9                  // Method org/apache/dubbo/common/URL.getCategory:()Ljava/lang/String;
      35: putfield      #10                 // Field category:Ljava/lang/String;
      38: aload_0
      39: aload_1
      40: ldc           #12                 // String
      42: invokevirtual #13                 // Method org/apache/dubbo/common/URL.getVersion:(Ljava/lang/String;)Ljava/lang/String;
      45: putfield      #14                 // Field version:Ljava/lang/String;
      48: aload_0
      49: aload_1
      50: ldc           #12                 // String
      52: invokevirtual #15                 // Method org/apache/dubbo/common/URL.getGroup:(Ljava/lang/String;)Ljava/lang/String;
      55: putfield      #16                 // Field group:Ljava/lang/String;
      58: aload_0
      59: aload_0
      60: invokespecial #17                 // Method toValue:()Ljava/lang/String;
      63: putfield      #18                 // Field value:Ljava/lang/String;
      66: return

  public org.apache.dubbo.registry.nacos.NacosServiceName(java.lang.String);
    Code:
       0: aload_0
       1: invokespecial #3                  // Method java/lang/Object."<init>":()V
       4: aload_0
       5: aload_1
       6: putfield      #18                 // Field value:Ljava/lang/String;
       9: aload_1
      10: ldc           #19                 // String :
      12: iconst_m1
      13: invokevirtual #20                 // Method java/lang/String.split:(Ljava/lang/String;I)[Ljava/lang/String;
      16: astore_2
      17: aload_0
      18: aload_2
      19: iconst_0
      20: aaload
      21: putfield      #10                 // Field category:Ljava/lang/String;
      24: aload_0
      25: aload_2
      26: iconst_1
      27: aaload
      28: putfield      #6                  // Field serviceInterface:Ljava/lang/String;
      31: aload_0
      32: aload_2
      33: iconst_2
      34: aaload
      35: putfield      #14                 // Field version:Ljava/lang/String;
      38: aload_0
      39: aload_2
      40: iconst_3
      41: aaload
      42: putfield      #16                 // Field group:Ljava/lang/String;
      45: return

  public static org.apache.dubbo.registry.nacos.NacosServiceName valueOf(org.apache.dubbo.common.URL);
    Code:
       0: new           #11                 // class org/apache/dubbo/registry/nacos/NacosServiceName
       3: dup
       4: aload_0
       5: invokespecial #21                 // Method "<init>":(Lorg/apache/dubbo/common/URL;)V
       8: areturn

  public boolean isConcrete();
    Code:
       0: aload_0
       1: aload_0
       2: getfield      #6                  // Field serviceInterface:Ljava/lang/String;
       5: invokespecial #7                  // Method isConcrete:(Ljava/lang/String;)Z
       8: ifeq          37
      11: aload_0
      12: aload_0
      13: getfield      #14                 // Field version:Ljava/lang/String;
      16: invokespecial #7                  // Method isConcrete:(Ljava/lang/String;)Z
      19: ifeq          37
      22: aload_0
      23: aload_0
      24: getfield      #16                 // Field group:Ljava/lang/String;
      27: invokespecial #7                  // Method isConcrete:(Ljava/lang/String;)Z
      30: ifeq          37
      33: iconst_1
      34: goto          38
      37: iconst_0
      38: ireturn

  public boolean isCompatible(org.apache.dubbo.registry.nacos.NacosServiceName);
    Code:
       0: aload_1
       1: invokevirtual #22                 // Method isConcrete:()Z
       4: ifne          9
       7: iconst_0
       8: ireturn
       9: aload_0
      10: getfield      #10                 // Field category:Ljava/lang/String;
      13: aload_1
      14: getfield      #10                 // Field category:Ljava/lang/String;
      17: invokestatic  #23                 // Method org/apache/dubbo/common/utils/StringUtils.isEquals:(Ljava/lang/String;Ljava/lang/String;)Z
      20: ifne          40
      23: aload_0
      24: aload_0
      25: getfield      #10                 // Field category:Ljava/lang/String;
      28: aload_1
      29: getfield      #10                 // Field category:Ljava/lang/String;
      32: invokespecial #24                 // Method matchRange:(Ljava/lang/String;Ljava/lang/String;)Z
      35: ifne          40
      38: iconst_0
      39: ireturn
      40: aload_0
      41: getfield      #6                  // Field serviceInterface:Ljava/lang/String;
      44: aload_1
      45: getfield      #6                  // Field serviceInterface:Ljava/lang/String;
      48: invokestatic  #23                 // Method org/apache/dubbo/common/utils/StringUtils.isEquals:(Ljava/lang/String;Ljava/lang/String;)Z
      51: ifne          56
      54: iconst_0
      55: ireturn
      56: aload_0
      57: aload_0
      58: getfield      #14                 // Field version:Ljava/lang/String;
      61: invokespecial #25                 // Method isWildcard:(Ljava/lang/String;)Z
      64: ifeq          69
      67: iconst_1
      68: ireturn
      69: aload_0
      70: aload_0
      71: getfield      #16                 // Field group:Ljava/lang/String;
      74: invokespecial #25                 // Method isWildcard:(Ljava/lang/String;)Z
      77: ifeq          82
      80: iconst_1
      81: ireturn
      82: aload_0
      83: getfield      #14                 // Field version:Ljava/lang/String;
      86: aload_1
      87: getfield      #14                 // Field version:Ljava/lang/String;
      90: invokestatic  #23                 // Method org/apache/dubbo/common/utils/StringUtils.isEquals:(Ljava/lang/String;Ljava/lang/String;)Z
      93: ifne          113
      96: aload_0
      97: aload_0
      98: getfield      #14                 // Field version:Ljava/lang/String;
     101: aload_1
     102: getfield      #14                 // Field version:Ljava/lang/String;
     105: invokespecial #24                 // Method matchRange:(Ljava/lang/String;Ljava/lang/String;)Z
     108: ifne          113
     111: iconst_0
     112: ireturn
     113: aload_0
     114: getfield      #16                 // Field group:Ljava/lang/String;
     117: aload_1
     118: getfield      #16                 // Field group:Ljava/lang/String;
     121: invokestatic  #23                 // Method org/apache/dubbo/common/utils/StringUtils.isEquals:(Ljava/lang/String;Ljava/lang/String;)Z
     124: ifne          144
     127: aload_0
     128: aload_0
     129: getfield      #16                 // Field group:Ljava/lang/String;
     132: aload_1
     133: getfield      #16                 // Field group:Ljava/lang/String;
     136: invokespecial #24                 // Method matchRange:(Ljava/lang/String;Ljava/lang/String;)Z
     139: ifne          144
     142: iconst_0
     143: ireturn
     144: iconst_1
     145: ireturn

  private boolean matchRange(java.lang.String, java.lang.String);
    Code:
       0: aload_1
       1: invokestatic  #26                 // Method org/apache/dubbo/common/utils/StringUtils.isBlank:(Ljava/lang/CharSequence;)Z
       4: ifeq          9
       7: iconst_1
       8: ireturn
       9: aload_0
      10: aload_1
      11: invokespecial #27                 // Method isRange:(Ljava/lang/String;)Z
      14: ifne          19
      17: iconst_0
      18: ireturn
      19: aload_1
      20: ldc           #28                 // String ,
      22: invokevirtual #29                 // Method java/lang/String.split:(Ljava/lang/String;)[Ljava/lang/String;
      25: astore_3
      26: aload_3
      27: invokestatic  #30                 // Method java/util/Arrays.asList:([Ljava/lang/Object;)Ljava/util/List;
      30: aload_2
      31: invokeinterface #31,  2           // InterfaceMethod java/util/List.contains:(Ljava/lang/Object;)Z
      36: ireturn

  private boolean isConcrete(java.lang.String);
    Code:
       0: aload_0
       1: aload_1
       2: invokespecial #25                 // Method isWildcard:(Ljava/lang/String;)Z
       5: ifne          20
       8: aload_0
       9: aload_1
      10: invokespecial #27                 // Method isRange:(Ljava/lang/String;)Z
      13: ifne          20
      16: iconst_1
      17: goto          21
      20: iconst_0
      21: ireturn

  private boolean isWildcard(java.lang.String);
    Code:
       0: ldc           #32                 // String *
       2: aload_1
       3: invokevirtual #33                 // Method java/lang/String.equals:(Ljava/lang/Object;)Z
       6: ireturn

  private boolean isRange(java.lang.String);
    Code:
       0: aload_1
       1: ifnull        29
       4: aload_1
       5: ldc           #28                 // String ,
       7: invokevirtual #34                 // Method java/lang/String.indexOf:(Ljava/lang/String;)I
      10: iconst_m1
      11: if_icmple     29
      14: aload_1
      15: ldc           #28                 // String ,
      17: invokevirtual #29                 // Method java/lang/String.split:(Ljava/lang/String;)[Ljava/lang/String;
      20: arraylength
      21: iconst_1
      22: if_icmple     29
      25: iconst_1
      26: goto          30
      29: iconst_0
      30: ireturn

  public java.lang.String getCategory();
    Code:
       0: aload_0
       1: getfield      #10                 // Field category:Ljava/lang/String;
       4: areturn

  public void setCategory(java.lang.String);
    Code:
       0: aload_0
       1: aload_1
       2: putfield      #10                 // Field category:Ljava/lang/String;
       5: return

  public java.lang.String getServiceInterface();
    Code:
       0: aload_0
       1: getfield      #6                  // Field serviceInterface:Ljava/lang/String;
       4: areturn

  public void setServiceInterface(java.lang.String);
    Code:
       0: aload_0
       1: aload_1
       2: putfield      #6                  // Field serviceInterface:Ljava/lang/String;
       5: return

  public java.lang.String getVersion();
    Code:
       0: aload_0
       1: getfield      #14                 // Field version:Ljava/lang/String;
       4: areturn

  public void setVersion(java.lang.String);
    Code:
       0: aload_0
       1: aload_1
       2: putfield      #14                 // Field version:Ljava/lang/String;
       5: return

  public java.lang.String getGroup();
    Code:
       0: aload_0
       1: getfield      #16                 // Field group:Ljava/lang/String;
       4: areturn

  public void setGroup(java.lang.String);
    Code:
       0: aload_0
       1: aload_1
       2: putfield      #16                 // Field group:Ljava/lang/String;
       5: return

  public java.lang.String getValue();
    Code:
       0: aload_0
       1: getfield      #18                 // Field value:Ljava/lang/String;
       4: ifnonnull     15
       7: aload_0
       8: aload_0
       9: invokespecial #17                 // Method toValue:()Ljava/lang/String;
      12: putfield      #18                 // Field value:Ljava/lang/String;
      15: aload_0
      16: getfield      #18                 // Field value:Ljava/lang/String;
      19: areturn

  private java.lang.String toValue();
    Code:
       0: new           #35                 // class java/lang/StringBuilder
       3: dup
       4: aload_0
       5: getfield      #10                 // Field category:Ljava/lang/String;
       8: invokespecial #36                 // Method java/lang/StringBuilder."<init>":(Ljava/lang/String;)V
      11: ldc           #19                 // String :
      13: invokevirtual #37                 // Method java/lang/StringBuilder.append:(Ljava/lang/String;)Ljava/lang/StringBuilder;
      16: aload_0
      17: getfield      #6                  // Field serviceInterface:Ljava/lang/String;
      20: invokevirtual #37                 // Method java/lang/StringBuilder.append:(Ljava/lang/String;)Ljava/lang/StringBuilder;
      23: ldc           #19                 // String :
      25: invokevirtual #37                 // Method java/lang/StringBuilder.append:(Ljava/lang/String;)Ljava/lang/StringBuilder;
      28: aload_0
      29: getfield      #14                 // Field version:Ljava/lang/String;
      32: invokevirtual #37                 // Method java/lang/StringBuilder.append:(Ljava/lang/String;)Ljava/lang/StringBuilder;
      35: ldc           #19                 // String :
      37: invokevirtual #37                 // Method java/lang/StringBuilder.append:(Ljava/lang/String;)Ljava/lang/StringBuilder;
      40: aload_0
      41: getfield      #16                 // Field group:Ljava/lang/String;
      44: invokevirtual #37                 // Method java/lang/StringBuilder.append:(Ljava/lang/String;)Ljava/lang/StringBuilder;
      47: invokevirtual #38                 // Method java/lang/StringBuilder.toString:()Ljava/lang/String;
      50: areturn

  public boolean equals(java.lang.Object);
    Code:
       0: aload_0
       1: aload_1
       2: if_acmpne     7
       5: iconst_1
       6: ireturn
       7: aload_1
       8: instanceof    #11                 // class org/apache/dubbo/registry/nacos/NacosServiceName
      11: ifne          16
      14: iconst_0
      15: ireturn
      16: aload_1
      17: checkcast     #11                 // class org/apache/dubbo/registry/nacos/NacosServiceName
      20: astore_2
      21: aload_0
      22: invokevirtual #39                 // Method getValue:()Ljava/lang/String;
      25: aload_2
      26: invokevirtual #39                 // Method getValue:()Ljava/lang/String;
      29: invokestatic  #40                 // Method java/util/Objects.equals:(Ljava/lang/Object;Ljava/lang/Object;)Z
      32: ireturn

  public int hashCode();
    Code:
       0: iconst_1
       1: anewarray     #41                 // class java/lang/Object
       4: dup
       5: iconst_0
       6: aload_0
       7: invokevirtual #39                 // Method getValue:()Ljava/lang/String;
      10: aastore
      11: invokestatic  #42                 // Method java/util/Objects.hash:([Ljava/lang/Object;)I
      14: ireturn

  public java.lang.String toString();
    Code:
       0: aload_0
       1: invokevirtual #39                 // Method getValue:()Ljava/lang/String;
       4: areturn
}
