Compiled from "NacosRegistry.java"
public class org.apache.dubbo.registry.nacos.NacosRegistry extends org.apache.dubbo.registry.support.FailbackRegistry {
  private static final java.util.List<java.lang.String> ALL_SUPPORTED_CATEGORIES;

  private static final int CATEGORY_INDEX;

  private static final int SERVICE_INTERFACE_INDEX;

  private static final int SERVICE_VERSION_INDEX;

  private static final int SERVICE_GROUP_INDEX;

  private static final java.lang.String WILDCARD;

  private static final java.lang.String UP;

  private static final java.lang.String SERVICE_NAME_SEPARATOR;

  private static final int PAGINATION_SIZE;

  private static final long LOOKUP_INTERVAL;

  private static final org.apache.dubbo.common.logger.ErrorTypeAwareLogger logger;

  private final org.apache.dubbo.registry.nacos.NacosNamingServiceWrapper namingService;

  private volatile java.util.concurrent.ScheduledExecutorService scheduledExecutorService;

  private final java.util.Map<org.apache.dubbo.common.URL, java.util.Map<org.apache.dubbo.registry.NotifyListener, org.apache.dubbo.registry.nacos.NacosAggregateListener>> originToAggregateListener;

  private final java.util.Map<org.apache.dubbo.common.URL, java.util.Map<org.apache.dubbo.registry.nacos.NacosAggregateListener, java.util.Map<java.lang.String, com.alibaba.nacos.api.naming.listener.EventListener>>> nacosListeners;

  private final boolean supportLegacyServiceName;

  public org.apache.dubbo.registry.nacos.NacosRegistry(org.apache.dubbo.common.URL, org.apache.dubbo.registry.nacos.NacosNamingServiceWrapper);
    Code:
       0: aload_0
       1: aload_1
       2: invokespecial #7                  // Method org/apache/dubbo/registry/support/FailbackRegistry."<init>":(Lorg/apache/dubbo/common/URL;)V
       5: aload_0
       6: new           #8                  // class java/util/concurrent/ConcurrentHashMap
       9: dup
      10: invokespecial #9                  // Method java/util/concurrent/ConcurrentHashMap."<init>":()V
      13: putfield      #10                 // Field originToAggregateListener:Ljava/util/Map;
      16: aload_0
      17: new           #8                  // class java/util/concurrent/ConcurrentHashMap
      20: dup
      21: invokespecial #9                  // Method java/util/concurrent/ConcurrentHashMap."<init>":()V
      24: putfield      #11                 // Field nacosListeners:Ljava/util/Map;
      27: aload_0
      28: aload_2
      29: putfield      #12                 // Field namingService:Lorg/apache/dubbo/registry/nacos/NacosNamingServiceWrapper;
      32: aload_0
      33: aload_1
      34: ldc           #13                 // String nacos.subscribe.legacy-name
      36: iconst_1
      37: invokevirtual #14                 // Method org/apache/dubbo/common/URL.getParameter:(Ljava/lang/String;Z)Z
      40: putfield      #15                 // Field supportLegacyServiceName:Z
      43: return

  public boolean isAvailable();
    Code:
       0: ldc           #17                 // String UP
       2: aload_0
       3: getfield      #12                 // Field namingService:Lorg/apache/dubbo/registry/nacos/NacosNamingServiceWrapper;
       6: invokevirtual #18                 // Method org/apache/dubbo/registry/nacos/NacosNamingServiceWrapper.getServerStatus:()Ljava/lang/String;
       9: invokevirtual #19                 // Method java/lang/String.equals:(Ljava/lang/Object;)Z
      12: ireturn

  public java.util.List<org.apache.dubbo.common.URL> lookup(org.apache.dubbo.common.URL);
    Code:
       0: aload_1
       1: ifnonnull     14
       4: new           #20                 // class java/lang/IllegalArgumentException
       7: dup
       8: ldc           #21                 // String lookup url == null
      10: invokespecial #22                 // Method java/lang/IllegalArgumentException."<init>":(Ljava/lang/String;)V
      13: athrow
      14: new           #23                 // class java/util/LinkedList
      17: dup
      18: invokespecial #24                 // Method java/util/LinkedList."<init>":()V
      21: astore_2
      22: aload_0
      23: aload_1
      24: aconst_null
      25: invokespecial #25                 // Method getServiceNames:(Lorg/apache/dubbo/common/URL;Lorg/apache/dubbo/registry/nacos/NacosAggregateListener;)Ljava/util/Set;
      28: astore_3
      29: aload_3
      30: invokeinterface #26,  1           // InterfaceMethod java/util/Set.iterator:()Ljava/util/Iterator;
      35: astore        4
      37: aload         4
      39: invokeinterface #27,  1           // InterfaceMethod java/util/Iterator.hasNext:()Z
      44: ifeq          96
      47: aload         4
      49: invokeinterface #28,  1           // InterfaceMethod java/util/Iterator.next:()Ljava/lang/Object;
      54: checkcast     #29                 // class java/lang/String
      57: astore        5
      59: aload_0
      60: getfield      #12                 // Field namingService:Lorg/apache/dubbo/registry/nacos/NacosNamingServiceWrapper;
      63: aload         5
      65: aload_0
      66: invokevirtual #30                 // Method getUrl:()Lorg/apache/dubbo/common/URL;
      69: ldc           #32                 // String DEFAULT_GROUP
      71: invokevirtual #33                 // Method org/apache/dubbo/common/URL.getGroup:(Ljava/lang/String;)Ljava/lang/String;
      74: invokevirtual #34                 // Method org/apache/dubbo/registry/nacos/NacosNamingServiceWrapper.getAllInstances:(Ljava/lang/String;Ljava/lang/String;)Ljava/util/List;
      77: astore        6
      79: aload_2
      80: aload_0
      81: aload_1
      82: aload         6
      84: invokespecial #35                 // Method buildURLs:(Lorg/apache/dubbo/common/URL;Ljava/util/Collection;)Ljava/util/List;
      87: invokeinterface #36,  2           // InterfaceMethod java/util/List.addAll:(Ljava/util/Collection;)Z
      92: pop
      93: goto          37
      96: aload_2
      97: areturn
      98: astore_2
      99: new           #38                 // class org/apache/dubbo/rpc/RpcException
     102: dup
     103: new           #39                 // class java/lang/StringBuilder
     106: dup
     107: invokespecial #40                 // Method java/lang/StringBuilder."<init>":()V
     110: ldc           #41                 // String Failed to lookup
     112: invokevirtual #42                 // Method java/lang/StringBuilder.append:(Ljava/lang/String;)Ljava/lang/StringBuilder;
     115: aload_1
     116: invokevirtual #43                 // Method java/lang/StringBuilder.append:(Ljava/lang/Object;)Ljava/lang/StringBuilder;
     119: ldc           #44                 // String  from nacos
     121: invokevirtual #42                 // Method java/lang/StringBuilder.append:(Ljava/lang/String;)Ljava/lang/StringBuilder;
     124: aload_0
     125: invokevirtual #30                 // Method getUrl:()Lorg/apache/dubbo/common/URL;
     128: invokevirtual #43                 // Method java/lang/StringBuilder.append:(Ljava/lang/Object;)Ljava/lang/StringBuilder;
     131: ldc           #45                 // String , cause:
     133: invokevirtual #42                 // Method java/lang/StringBuilder.append:(Ljava/lang/String;)Ljava/lang/StringBuilder;
     136: aload_2
     137: invokevirtual #46                 // Method java/lang/Exception.getMessage:()Ljava/lang/String;
     140: invokevirtual #42                 // Method java/lang/StringBuilder.append:(Ljava/lang/String;)Ljava/lang/StringBuilder;
     143: invokevirtual #47                 // Method java/lang/StringBuilder.toString:()Ljava/lang/String;
     146: aload_2
     147: invokespecial #48                 // Method org/apache/dubbo/rpc/RpcException."<init>":(Ljava/lang/String;Ljava/lang/Throwable;)V
     150: athrow
    Exception table:
       from    to  target type
          14    97    98   Class java/lang/Exception

  public void doRegister(org.apache.dubbo.common.URL);
    Code:
       0: ldc           #49                 // String provider
       2: aload_1
       3: invokevirtual #50                 // Method org/apache/dubbo/common/URL.getSide:()Ljava/lang/String;
       6: invokevirtual #19                 // Method java/lang/String.equals:(Ljava/lang/Object;)Z
       9: ifne          25
      12: aload_0
      13: invokevirtual #30                 // Method getUrl:()Lorg/apache/dubbo/common/URL;
      16: ldc           #51                 // String register-consumer-url
      18: iconst_0
      19: invokevirtual #14                 // Method org/apache/dubbo/common/URL.getParameter:(Ljava/lang/String;Z)Z
      22: ifeq          58
      25: aload_0
      26: aload_1
      27: invokespecial #52                 // Method getServiceName:(Lorg/apache/dubbo/common/URL;)Ljava/lang/String;
      30: astore_2
      31: aload_0
      32: aload_1
      33: invokespecial #53                 // Method createInstance:(Lorg/apache/dubbo/common/URL;)Lcom/alibaba/nacos/api/naming/pojo/Instance;
      36: astore_3
      37: aload_0
      38: getfield      #12                 // Field namingService:Lorg/apache/dubbo/registry/nacos/NacosNamingServiceWrapper;
      41: aload_2
      42: aload_0
      43: invokevirtual #30                 // Method getUrl:()Lorg/apache/dubbo/common/URL;
      46: ldc           #32                 // String DEFAULT_GROUP
      48: invokevirtual #33                 // Method org/apache/dubbo/common/URL.getGroup:(Ljava/lang/String;)Ljava/lang/String;
      51: aload_3
      52: invokevirtual #54                 // Method org/apache/dubbo/registry/nacos/NacosNamingServiceWrapper.registerInstance:(Ljava/lang/String;Ljava/lang/String;Lcom/alibaba/nacos/api/naming/pojo/Instance;)V
      55: goto          68
      58: getstatic     #55                 // Field logger:Lorg/apache/dubbo/common/logger/ErrorTypeAwareLogger;
      61: ldc           #56                 // String Please set \'dubbo.registry.parameters.register-consumer-url=true\' to turn on consumer url registration.
      63: invokeinterface #57,  2           // InterfaceMethod org/apache/dubbo/common/logger/ErrorTypeAwareLogger.info:(Ljava/lang/String;)V
      68: goto          124
      71: astore_2
      72: new           #38                 // class org/apache/dubbo/rpc/RpcException
      75: dup
      76: new           #39                 // class java/lang/StringBuilder
      79: dup
      80: invokespecial #40                 // Method java/lang/StringBuilder."<init>":()V
      83: ldc           #58                 // String Failed to register
      85: invokevirtual #42                 // Method java/lang/StringBuilder.append:(Ljava/lang/String;)Ljava/lang/StringBuilder;
      88: aload_1
      89: invokevirtual #43                 // Method java/lang/StringBuilder.append:(Ljava/lang/Object;)Ljava/lang/StringBuilder;
      92: ldc           #59                 // String  to nacos
      94: invokevirtual #42                 // Method java/lang/StringBuilder.append:(Ljava/lang/String;)Ljava/lang/StringBuilder;
      97: aload_0
      98: invokevirtual #30                 // Method getUrl:()Lorg/apache/dubbo/common/URL;
     101: invokevirtual #43                 // Method java/lang/StringBuilder.append:(Ljava/lang/Object;)Ljava/lang/StringBuilder;
     104: ldc           #45                 // String , cause:
     106: invokevirtual #42                 // Method java/lang/StringBuilder.append:(Ljava/lang/String;)Ljava/lang/StringBuilder;
     109: aload_2
     110: invokevirtual #46                 // Method java/lang/Exception.getMessage:()Ljava/lang/String;
     113: invokevirtual #42                 // Method java/lang/StringBuilder.append:(Ljava/lang/String;)Ljava/lang/StringBuilder;
     116: invokevirtual #47                 // Method java/lang/StringBuilder.toString:()Ljava/lang/String;
     119: aload_2
     120: invokespecial #48                 // Method org/apache/dubbo/rpc/RpcException."<init>":(Ljava/lang/String;Ljava/lang/Throwable;)V
     123: athrow
     124: return
    Exception table:
       from    to  target type
           0    68    71   Class java/lang/Exception

  public void doUnregister(org.apache.dubbo.common.URL);
    Code:
       0: aload_0
       1: aload_1
       2: invokespecial #52                 // Method getServiceName:(Lorg/apache/dubbo/common/URL;)Ljava/lang/String;
       5: astore_2
       6: aload_0
       7: aload_1
       8: invokespecial #53                 // Method createInstance:(Lorg/apache/dubbo/common/URL;)Lcom/alibaba/nacos/api/naming/pojo/Instance;
      11: astore_3
      12: aload_0
      13: getfield      #12                 // Field namingService:Lorg/apache/dubbo/registry/nacos/NacosNamingServiceWrapper;
      16: aload_2
      17: aload_0
      18: invokevirtual #30                 // Method getUrl:()Lorg/apache/dubbo/common/URL;
      21: ldc           #32                 // String DEFAULT_GROUP
      23: invokevirtual #33                 // Method org/apache/dubbo/common/URL.getGroup:(Ljava/lang/String;)Ljava/lang/String;
      26: aload_3
      27: invokevirtual #60                 // Method com/alibaba/nacos/api/naming/pojo/Instance.getIp:()Ljava/lang/String;
      30: aload_3
      31: invokevirtual #61                 // Method com/alibaba/nacos/api/naming/pojo/Instance.getPort:()I
      34: invokevirtual #62                 // Method org/apache/dubbo/registry/nacos/NacosNamingServiceWrapper.deregisterInstance:(Ljava/lang/String;Ljava/lang/String;Ljava/lang/String;I)V
      37: goto          93
      40: astore_2
      41: new           #38                 // class org/apache/dubbo/rpc/RpcException
      44: dup
      45: new           #39                 // class java/lang/StringBuilder
      48: dup
      49: invokespecial #40                 // Method java/lang/StringBuilder."<init>":()V
      52: ldc           #63                 // String Failed to unregister
      54: invokevirtual #42                 // Method java/lang/StringBuilder.append:(Ljava/lang/String;)Ljava/lang/StringBuilder;
      57: aload_1
      58: invokevirtual #43                 // Method java/lang/StringBuilder.append:(Ljava/lang/Object;)Ljava/lang/StringBuilder;
      61: ldc           #59                 // String  to nacos
      63: invokevirtual #42                 // Method java/lang/StringBuilder.append:(Ljava/lang/String;)Ljava/lang/StringBuilder;
      66: aload_0
      67: invokevirtual #30                 // Method getUrl:()Lorg/apache/dubbo/common/URL;
      70: invokevirtual #43                 // Method java/lang/StringBuilder.append:(Ljava/lang/Object;)Ljava/lang/StringBuilder;
      73: ldc           #45                 // String , cause:
      75: invokevirtual #42                 // Method java/lang/StringBuilder.append:(Ljava/lang/String;)Ljava/lang/StringBuilder;
      78: aload_2
      79: invokevirtual #46                 // Method java/lang/Exception.getMessage:()Ljava/lang/String;
      82: invokevirtual #42                 // Method java/lang/StringBuilder.append:(Ljava/lang/String;)Ljava/lang/StringBuilder;
      85: invokevirtual #47                 // Method java/lang/StringBuilder.toString:()Ljava/lang/String;
      88: aload_2
      89: invokespecial #48                 // Method org/apache/dubbo/rpc/RpcException."<init>":(Ljava/lang/String;Ljava/lang/Throwable;)V
      92: athrow
      93: return
    Exception table:
       from    to  target type
           0    37    40   Class java/lang/Exception

  public void doSubscribe(org.apache.dubbo.common.URL, org.apache.dubbo.registry.NotifyListener);
    Code:
       0: new           #64                 // class org/apache/dubbo/registry/nacos/NacosAggregateListener
       3: dup
       4: aload_2
       5: invokespecial #65                 // Method org/apache/dubbo/registry/nacos/NacosAggregateListener."<init>":(Lorg/apache/dubbo/registry/NotifyListener;)V
       8: astore_3
       9: aload_0
      10: getfield      #10                 // Field originToAggregateListener:Ljava/util/Map;
      13: aload_1
      14: invokedynamic #66,  0             // InvokeDynamic #0:apply:()Ljava/util/function/Function;
      19: invokeinterface #67,  3           // InterfaceMethod java/util/Map.computeIfAbsent:(Ljava/lang/Object;Ljava/util/function/Function;)Ljava/lang/Object;
      24: checkcast     #68                 // class java/util/Map
      27: aload_2
      28: aload_3
      29: invokeinterface #69,  3           // InterfaceMethod java/util/Map.put:(Ljava/lang/Object;Ljava/lang/Object;)Ljava/lang/Object;
      34: pop
      35: aload_0
      36: aload_1
      37: aload_3
      38: invokespecial #25                 // Method getServiceNames:(Lorg/apache/dubbo/common/URL;Lorg/apache/dubbo/registry/nacos/NacosAggregateListener;)Ljava/util/Set;
      41: astore        4
      43: aload_0
      44: aload_1
      45: aload_3
      46: aload         4
      48: invokespecial #70                 // Method doSubscribe:(Lorg/apache/dubbo/common/URL;Lorg/apache/dubbo/registry/nacos/NacosAggregateListener;Ljava/util/Set;)V
      51: return

  private void doSubscribe(org.apache.dubbo.common.URL, org.apache.dubbo.registry.nacos.NacosAggregateListener, java.util.Set<java.lang.String>);
    Code:
       0: aload_0
       1: aload_1
       2: invokespecial #71                 // Method isServiceNamesWithCompatibleMode:(Lorg/apache/dubbo/common/URL;)Z
       5: ifeq          115
       8: aload_3
       9: invokeinterface #26,  1           // InterfaceMethod java/util/Set.iterator:()Ljava/util/Iterator;
      14: astore        4
      16: aload         4
      18: invokeinterface #27,  1           // InterfaceMethod java/util/Iterator.hasNext:()Z
      23: ifeq          71
      26: aload         4
      28: invokeinterface #28,  1           // InterfaceMethod java/util/Iterator.next:()Ljava/lang/Object;
      33: checkcast     #29                 // class java/lang/String
      36: astore        5
      38: aload_0
      39: getfield      #12                 // Field namingService:Lorg/apache/dubbo/registry/nacos/NacosNamingServiceWrapper;
      42: aload         5
      44: aload_0
      45: invokevirtual #30                 // Method getUrl:()Lorg/apache/dubbo/common/URL;
      48: ldc           #32                 // String DEFAULT_GROUP
      50: invokevirtual #33                 // Method org/apache/dubbo/common/URL.getGroup:(Ljava/lang/String;)Ljava/lang/String;
      53: invokevirtual #34                 // Method org/apache/dubbo/registry/nacos/NacosNamingServiceWrapper.getAllInstances:(Ljava/lang/String;Ljava/lang/String;)Ljava/util/List;
      56: astore        6
      58: aload_0
      59: aload_1
      60: aload         5
      62: aload_2
      63: aload         6
      65: invokespecial #6                  // Method notifySubscriber:(Lorg/apache/dubbo/common/URL;Ljava/lang/String;Lorg/apache/dubbo/registry/nacos/NacosAggregateListener;Ljava/util/Collection;)V
      68: goto          16
      71: aload_3
      72: invokeinterface #26,  1           // InterfaceMethod java/util/Set.iterator:()Ljava/util/Iterator;
      77: astore        4
      79: aload         4
      81: invokeinterface #27,  1           // InterfaceMethod java/util/Iterator.hasNext:()Z
      86: ifeq          112
      89: aload         4
      91: invokeinterface #28,  1           // InterfaceMethod java/util/Iterator.next:()Ljava/lang/Object;
      96: checkcast     #29                 // class java/lang/String
      99: astore        5
     101: aload_0
     102: aload         5
     104: aload_1
     105: aload_2
     106: invokespecial #72                 // Method subscribeEventListener:(Ljava/lang/String;Lorg/apache/dubbo/common/URL;Lorg/apache/dubbo/registry/nacos/NacosAggregateListener;)V
     109: goto          79
     112: goto          268
     115: aload_3
     116: invokeinterface #26,  1           // InterfaceMethod java/util/Set.iterator:()Ljava/util/Iterator;
     121: astore        4
     123: aload         4
     125: invokeinterface #27,  1           // InterfaceMethod java/util/Iterator.hasNext:()Z
     130: ifeq          268
     133: aload         4
     135: invokeinterface #28,  1           // InterfaceMethod java/util/Iterator.next:()Ljava/lang/Object;
     140: checkcast     #29                 // class java/lang/String
     143: astore        5
     145: new           #23                 // class java/util/LinkedList
     148: dup
     149: invokespecial #24                 // Method java/util/LinkedList."<init>":()V
     152: astore        6
     154: aload         6
     156: aload_0
     157: getfield      #12                 // Field namingService:Lorg/apache/dubbo/registry/nacos/NacosNamingServiceWrapper;
     160: aload         5
     162: aload_0
     163: invokevirtual #30                 // Method getUrl:()Lorg/apache/dubbo/common/URL;
     166: ldc           #32                 // String DEFAULT_GROUP
     168: invokevirtual #33                 // Method org/apache/dubbo/common/URL.getGroup:(Ljava/lang/String;)Ljava/lang/String;
     171: invokevirtual #34                 // Method org/apache/dubbo/registry/nacos/NacosNamingServiceWrapper.getAllInstances:(Ljava/lang/String;Ljava/lang/String;)Ljava/util/List;
     174: invokeinterface #36,  2           // InterfaceMethod java/util/List.addAll:(Ljava/util/Collection;)Z
     179: pop
     180: aload         5
     182: astore        7
     184: aload         5
     186: getstatic     #73                 // Field SERVICE_NAME_SEPARATOR:Ljava/lang/String;
     189: iconst_m1
     190: invokevirtual #74                 // Method java/lang/String.split:(Ljava/lang/String;I)[Ljava/lang/String;
     193: astore        8
     195: aload         8
     197: arraylength
     198: iconst_4
     199: if_icmpne     208
     202: aload         8
     204: iconst_1
     205: aaload
     206: astore        7
     208: aload_1
     209: aload         7
     211: invokevirtual #75                 // Method org/apache/dubbo/common/URL.setPath:(Ljava/lang/String;)Lorg/apache/dubbo/common/URL;
     214: iconst_4
     215: anewarray     #29                 // class java/lang/String
     218: dup
     219: iconst_0
     220: ldc           #76                 // String interface
     222: aastore
     223: dup
     224: iconst_1
     225: aload         7
     227: aastore
     228: dup
     229: iconst_2
     230: ldc           #77                 // String check
     232: aastore
     233: dup
     234: iconst_3
     235: iconst_0
     236: invokestatic  #78                 // Method java/lang/String.valueOf:(Z)Ljava/lang/String;
     239: aastore
     240: invokevirtual #79                 // Method org/apache/dubbo/common/URL.addParameters:([Ljava/lang/String;)Lorg/apache/dubbo/common/URL;
     243: astore        9
     245: aload_0
     246: aload         9
     248: aload         5
     250: aload_2
     251: aload         6
     253: invokespecial #6                  // Method notifySubscriber:(Lorg/apache/dubbo/common/URL;Ljava/lang/String;Lorg/apache/dubbo/registry/nacos/NacosAggregateListener;Ljava/util/Collection;)V
     256: aload_0
     257: aload         5
     259: aload         9
     261: aload_2
     262: invokespecial #72                 // Method subscribeEventListener:(Ljava/lang/String;Lorg/apache/dubbo/common/URL;Lorg/apache/dubbo/registry/nacos/NacosAggregateListener;)V
     265: goto          123
     268: goto          327
     271: astore        4
     273: new           #38                 // class org/apache/dubbo/rpc/RpcException
     276: dup
     277: new           #39                 // class java/lang/StringBuilder
     280: dup
     281: invokespecial #40                 // Method java/lang/StringBuilder."<init>":()V
     284: ldc           #81                 // String Failed to subscribe
     286: invokevirtual #42                 // Method java/lang/StringBuilder.append:(Ljava/lang/String;)Ljava/lang/StringBuilder;
     289: aload_1
     290: invokevirtual #43                 // Method java/lang/StringBuilder.append:(Ljava/lang/Object;)Ljava/lang/StringBuilder;
     293: ldc           #59                 // String  to nacos
     295: invokevirtual #42                 // Method java/lang/StringBuilder.append:(Ljava/lang/String;)Ljava/lang/StringBuilder;
     298: aload_0
     299: invokevirtual #30                 // Method getUrl:()Lorg/apache/dubbo/common/URL;
     302: invokevirtual #43                 // Method java/lang/StringBuilder.append:(Ljava/lang/Object;)Ljava/lang/StringBuilder;
     305: ldc           #45                 // String , cause:
     307: invokevirtual #42                 // Method java/lang/StringBuilder.append:(Ljava/lang/String;)Ljava/lang/StringBuilder;
     310: aload         4
     312: invokevirtual #82                 // Method java/lang/Throwable.getMessage:()Ljava/lang/String;
     315: invokevirtual #42                 // Method java/lang/StringBuilder.append:(Ljava/lang/String;)Ljava/lang/StringBuilder;
     318: invokevirtual #47                 // Method java/lang/StringBuilder.toString:()Ljava/lang/String;
     321: aload         4
     323: invokespecial #48                 // Method org/apache/dubbo/rpc/RpcException."<init>":(Ljava/lang/String;Ljava/lang/Throwable;)V
     326: athrow
     327: return
    Exception table:
       from    to  target type
           0   268   271   Class java/lang/Throwable

  private boolean isServiceNamesWithCompatibleMode(org.apache.dubbo.common.URL);
    Code:
       0: aload_0
       1: aload_1
       2: invokespecial #83                 // Method isAdminProtocol:(Lorg/apache/dubbo/common/URL;)Z
       5: ifne          23
       8: aload_0
       9: aload_1
      10: invokespecial #84                 // Method createServiceName:(Lorg/apache/dubbo/common/URL;)Lorg/apache/dubbo/registry/nacos/NacosServiceName;
      13: invokevirtual #85                 // Method org/apache/dubbo/registry/nacos/NacosServiceName.isConcrete:()Z
      16: ifeq          23
      19: iconst_1
      20: goto          24
      23: iconst_0
      24: ireturn

  public void doUnsubscribe(org.apache.dubbo.common.URL, org.apache.dubbo.registry.NotifyListener);
    Code:
       0: aload_0
       1: aload_1
       2: invokespecial #83                 // Method isAdminProtocol:(Lorg/apache/dubbo/common/URL;)Z
       5: ifeq          15
       8: aload_0
       9: invokespecial #86                 // Method shutdownServiceNamesLookup:()V
      12: goto          179
      15: aload_0
      16: getfield      #10                 // Field originToAggregateListener:Ljava/util/Map;
      19: aload_1
      20: invokeinterface #87,  2           // InterfaceMethod java/util/Map.get:(Ljava/lang/Object;)Ljava/lang/Object;
      25: checkcast     #68                 // class java/util/Map
      28: astore_3
      29: aload_3
      30: ifnonnull     61
      33: getstatic     #55                 // Field logger:Lorg/apache/dubbo/common/logger/ErrorTypeAwareLogger;
      36: ldc           #88                 // String 1-37
      38: ldc           #89                 // String
      40: ldc           #89                 // String
      42: ldc           #90                 // String No aggregate listener found for url %s, this service might have already been unsubscribed.
      44: iconst_1
      45: anewarray     #91                 // class java/lang/Object
      48: dup
      49: iconst_0
      50: aload_1
      51: aastore
      52: invokestatic  #92                 // Method java/lang/String.format:(Ljava/lang/String;[Ljava/lang/Object;)Ljava/lang/String;
      55: invokeinterface #93,  5           // InterfaceMethod org/apache/dubbo/common/logger/ErrorTypeAwareLogger.warn:(Ljava/lang/String;Ljava/lang/String;Ljava/lang/String;Ljava/lang/String;)V
      60: return
      61: aload_3
      62: aload_2
      63: invokeinterface #94,  2           // InterfaceMethod java/util/Map.remove:(Ljava/lang/Object;)Ljava/lang/Object;
      68: checkcast     #64                 // class org/apache/dubbo/registry/nacos/NacosAggregateListener
      71: astore        4
      73: aload         4
      75: ifnull        159
      78: aload         4
      80: invokevirtual #95                 // Method org/apache/dubbo/registry/nacos/NacosAggregateListener.getServiceNames:()Ljava/util/Set;
      83: astore        5
      85: aload_0
      86: aload_1
      87: aload         4
      89: aload         5
      91: invokespecial #96                 // Method doUnsubscribe:(Lorg/apache/dubbo/common/URL;Lorg/apache/dubbo/registry/nacos/NacosAggregateListener;Ljava/util/Set;)V
      94: goto          159
      97: astore        6
      99: getstatic     #55                 // Field logger:Lorg/apache/dubbo/common/logger/ErrorTypeAwareLogger;
     102: ldc           #88                 // String 1-37
     104: ldc           #89                 // String
     106: ldc           #89                 // String
     108: new           #39                 // class java/lang/StringBuilder
     111: dup
     112: invokespecial #40                 // Method java/lang/StringBuilder."<init>":()V
     115: ldc           #98                 // String Failed to unsubscribe
     117: invokevirtual #42                 // Method java/lang/StringBuilder.append:(Ljava/lang/String;)Ljava/lang/StringBuilder;
     120: aload_1
     121: invokevirtual #43                 // Method java/lang/StringBuilder.append:(Ljava/lang/Object;)Ljava/lang/StringBuilder;
     124: ldc           #59                 // String  to nacos
     126: invokevirtual #42                 // Method java/lang/StringBuilder.append:(Ljava/lang/String;)Ljava/lang/StringBuilder;
     129: aload_0
     130: invokevirtual #30                 // Method getUrl:()Lorg/apache/dubbo/common/URL;
     133: invokevirtual #43                 // Method java/lang/StringBuilder.append:(Ljava/lang/Object;)Ljava/lang/StringBuilder;
     136: ldc           #45                 // String , cause:
     138: invokevirtual #42                 // Method java/lang/StringBuilder.append:(Ljava/lang/String;)Ljava/lang/StringBuilder;
     141: aload         6
     143: invokevirtual #99                 // Method com/alibaba/nacos/api/exception/NacosException.getMessage:()Ljava/lang/String;
     146: invokevirtual #42                 // Method java/lang/StringBuilder.append:(Ljava/lang/String;)Ljava/lang/StringBuilder;
     149: invokevirtual #47                 // Method java/lang/StringBuilder.toString:()Ljava/lang/String;
     152: aload         6
     154: invokeinterface #100,  6          // InterfaceMethod org/apache/dubbo/common/logger/ErrorTypeAwareLogger.error:(Ljava/lang/String;Ljava/lang/String;Ljava/lang/String;Ljava/lang/String;Ljava/lang/Throwable;)V
     159: aload_3
     160: invokeinterface #101,  1          // InterfaceMethod java/util/Map.isEmpty:()Z
     165: ifeq          179
     168: aload_0
     169: getfield      #10                 // Field originToAggregateListener:Ljava/util/Map;
     172: aload_1
     173: invokeinterface #94,  2           // InterfaceMethod java/util/Map.remove:(Ljava/lang/Object;)Ljava/lang/Object;
     178: pop
     179: return
    Exception table:
       from    to  target type
          85    94    97   Class com/alibaba/nacos/api/exception/NacosException

  private void doUnsubscribe(org.apache.dubbo.common.URL, org.apache.dubbo.registry.nacos.NacosAggregateListener, java.util.Set<java.lang.String>) throws com.alibaba.nacos.api.exception.NacosException;
    Code:
       0: aload_3
       1: invokeinterface #26,  1           // InterfaceMethod java/util/Set.iterator:()Ljava/util/Iterator;
       6: astore        4
       8: aload         4
      10: invokeinterface #27,  1           // InterfaceMethod java/util/Iterator.hasNext:()Z
      15: ifeq          41
      18: aload         4
      20: invokeinterface #28,  1           // InterfaceMethod java/util/Iterator.next:()Ljava/lang/Object;
      25: checkcast     #29                 // class java/lang/String
      28: astore        5
      30: aload_0
      31: aload         5
      33: aload_1
      34: aload_2
      35: invokespecial #102                // Method unsubscribeEventListener:(Ljava/lang/String;Lorg/apache/dubbo/common/URL;Lorg/apache/dubbo/registry/nacos/NacosAggregateListener;)V
      38: goto          8
      41: return

  private void shutdownServiceNamesLookup();
    Code:
       0: aload_0
       1: getfield      #103                // Field scheduledExecutorService:Ljava/util/concurrent/ScheduledExecutorService;
       4: ifnull        16
       7: aload_0
       8: getfield      #103                // Field scheduledExecutorService:Ljava/util/concurrent/ScheduledExecutorService;
      11: invokeinterface #104,  1          // InterfaceMethod java/util/concurrent/ScheduledExecutorService.shutdown:()V
      16: return

  private java.util.Set<java.lang.String> getServiceNames(org.apache.dubbo.common.URL, org.apache.dubbo.registry.nacos.NacosAggregateListener);
    Code:
       0: aload_0
       1: aload_1
       2: invokespecial #83                 // Method isAdminProtocol:(Lorg/apache/dubbo/common/URL;)Z
       5: ifeq          20
       8: aload_0
       9: aload_1
      10: aload_2
      11: invokespecial #105                // Method scheduleServiceNamesLookup:(Lorg/apache/dubbo/common/URL;Lorg/apache/dubbo/registry/nacos/NacosAggregateListener;)V
      14: aload_0
      15: aload_1
      16: invokespecial #106                // Method getServiceNamesForOps:(Lorg/apache/dubbo/common/URL;)Ljava/util/Set;
      19: areturn
      20: aload_0
      21: aload_1
      22: invokespecial #107                // Method getServiceNames0:(Lorg/apache/dubbo/common/URL;)Ljava/util/Set;
      25: areturn

  private java.util.Set<java.lang.String> getServiceNames0(org.apache.dubbo.common.URL);
    Code:
       0: aload_0
       1: aload_1
       2: invokespecial #84                 // Method createServiceName:(Lorg/apache/dubbo/common/URL;)Lorg/apache/dubbo/registry/nacos/NacosServiceName;
       5: astore_2
       6: aload_2
       7: invokevirtual #85                 // Method org/apache/dubbo/registry/nacos/NacosServiceName.isConcrete:()Z
      10: ifeq          70
      13: new           #108                // class java/util/LinkedHashSet
      16: dup
      17: invokespecial #109                // Method java/util/LinkedHashSet."<init>":()V
      20: astore_3
      21: aload_3
      22: aload_2
      23: invokevirtual #110                // Method org/apache/dubbo/registry/nacos/NacosServiceName.toString:()Ljava/lang/String;
      26: invokeinterface #111,  2          // InterfaceMethod java/util/Set.add:(Ljava/lang/Object;)Z
      31: pop
      32: aload_0
      33: getfield      #15                 // Field supportLegacyServiceName:Z
      36: ifeq          76
      39: aload_0
      40: aload_1
      41: invokespecial #112                // Method getLegacySubscribedServiceName:(Lorg/apache/dubbo/common/URL;)Ljava/lang/String;
      44: astore        4
      46: aload_2
      47: invokevirtual #110                // Method org/apache/dubbo/registry/nacos/NacosServiceName.toString:()Ljava/lang/String;
      50: aload         4
      52: invokevirtual #19                 // Method java/lang/String.equals:(Ljava/lang/Object;)Z
      55: ifne          67
      58: aload_3
      59: aload         4
      61: invokeinterface #111,  2          // InterfaceMethod java/util/Set.add:(Ljava/lang/Object;)Z
      66: pop
      67: goto          76
      70: aload_0
      71: aload_2
      72: invokespecial #113                // Method filterServiceNames:(Lorg/apache/dubbo/registry/nacos/NacosServiceName;)Ljava/util/Set;
      75: astore_3
      76: aload_3
      77: areturn

  private java.util.Set<java.lang.String> filterServiceNames(org.apache.dubbo.registry.nacos.NacosServiceName);
    Code:
       0: new           #108                // class java/util/LinkedHashSet
       3: dup
       4: invokespecial #109                // Method java/util/LinkedHashSet."<init>":()V
       7: astore_2
       8: aload_2
       9: aload_0
      10: getfield      #12                 // Field namingService:Lorg/apache/dubbo/registry/nacos/NacosNamingServiceWrapper;
      13: iconst_1
      14: ldc           #115                // int 2147483647
      16: aload_0
      17: invokevirtual #30                 // Method getUrl:()Lorg/apache/dubbo/common/URL;
      20: ldc           #32                 // String DEFAULT_GROUP
      22: invokevirtual #33                 // Method org/apache/dubbo/common/URL.getGroup:(Ljava/lang/String;)Ljava/lang/String;
      25: invokevirtual #116                // Method org/apache/dubbo/registry/nacos/NacosNamingServiceWrapper.getServicesOfServer:(IILjava/lang/String;)Lcom/alibaba/nacos/api/naming/pojo/ListView;
      28: invokevirtual #117                // Method com/alibaba/nacos/api/naming/pojo/ListView.getData:()Ljava/util/List;
      31: invokeinterface #118,  1          // InterfaceMethod java/util/List.stream:()Ljava/util/stream/Stream;
      36: aload_0
      37: invokedynamic #119,  0            // InvokeDynamic #1:test:(Lorg/apache/dubbo/registry/nacos/NacosRegistry;)Ljava/util/function/Predicate;
      42: invokeinterface #120,  2          // InterfaceMethod java/util/stream/Stream.filter:(Ljava/util/function/Predicate;)Ljava/util/stream/Stream;
      47: invokedynamic #121,  0            // InvokeDynamic #2:apply:()Ljava/util/function/Function;
      52: invokeinterface #122,  2          // InterfaceMethod java/util/stream/Stream.map:(Ljava/util/function/Function;)Ljava/util/stream/Stream;
      57: aload_1
      58: dup
      59: invokevirtual #123                // Method java/lang/Object.getClass:()Ljava/lang/Class;
      62: pop
      63: invokedynamic #124,  0            // InvokeDynamic #3:test:(Lorg/apache/dubbo/registry/nacos/NacosServiceName;)Ljava/util/function/Predicate;
      68: invokeinterface #120,  2          // InterfaceMethod java/util/stream/Stream.filter:(Ljava/util/function/Predicate;)Ljava/util/stream/Stream;
      73: invokedynamic #125,  0            // InvokeDynamic #4:apply:()Ljava/util/function/Function;
      78: invokeinterface #122,  2          // InterfaceMethod java/util/stream/Stream.map:(Ljava/util/function/Function;)Ljava/util/stream/Stream;
      83: invokestatic  #126                // Method java/util/stream/Collectors.toList:()Ljava/util/stream/Collector;
      86: invokeinterface #127,  2          // InterfaceMethod java/util/stream/Stream.collect:(Ljava/util/stream/Collector;)Ljava/lang/Object;
      91: checkcast     #128                // class java/util/Collection
      94: invokeinterface #129,  2          // InterfaceMethod java/util/Set.addAll:(Ljava/util/Collection;)Z
      99: pop
     100: aload_2
     101: areturn
     102: astore_2
     103: new           #38                 // class org/apache/dubbo/rpc/RpcException
     106: dup
     107: new           #39                 // class java/lang/StringBuilder
     110: dup
     111: invokespecial #40                 // Method java/lang/StringBuilder."<init>":()V
     114: ldc           #130                // String Failed to filter serviceName from nacos, url:
     116: invokevirtual #42                 // Method java/lang/StringBuilder.append:(Ljava/lang/String;)Ljava/lang/StringBuilder;
     119: aload_0
     120: invokevirtual #30                 // Method getUrl:()Lorg/apache/dubbo/common/URL;
     123: invokevirtual #43                 // Method java/lang/StringBuilder.append:(Ljava/lang/Object;)Ljava/lang/StringBuilder;
     126: ldc           #131                // String , serviceName:
     128: invokevirtual #42                 // Method java/lang/StringBuilder.append:(Ljava/lang/String;)Ljava/lang/StringBuilder;
     131: aload_1
     132: invokevirtual #43                 // Method java/lang/StringBuilder.append:(Ljava/lang/Object;)Ljava/lang/StringBuilder;
     135: ldc           #45                 // String , cause:
     137: invokevirtual #42                 // Method java/lang/StringBuilder.append:(Ljava/lang/String;)Ljava/lang/StringBuilder;
     140: aload_2
     141: invokevirtual #82                 // Method java/lang/Throwable.getMessage:()Ljava/lang/String;
     144: invokevirtual #42                 // Method java/lang/StringBuilder.append:(Ljava/lang/String;)Ljava/lang/StringBuilder;
     147: invokevirtual #47                 // Method java/lang/StringBuilder.toString:()Ljava/lang/String;
     150: aload_2
     151: invokespecial #48                 // Method org/apache/dubbo/rpc/RpcException."<init>":(Ljava/lang/String;Ljava/lang/Throwable;)V
     154: athrow
    Exception table:
       from    to  target type
           0   101   102   Class java/lang/Throwable

  private boolean isConformRules(java.lang.String);
    Code:
       0: aload_1
       1: ldc           #132                // String :
       3: iconst_m1
       4: invokevirtual #74                 // Method java/lang/String.split:(Ljava/lang/String;I)[Ljava/lang/String;
       7: arraylength
       8: iconst_4
       9: if_icmpne     16
      12: iconst_1
      13: goto          17
      16: iconst_0
      17: ireturn

  private java.lang.String getLegacySubscribedServiceName(org.apache.dubbo.common.URL);
    Code:
       0: new           #39                 // class java/lang/StringBuilder
       3: dup
       4: ldc           #133                // String providers
       6: invokespecial #134                // Method java/lang/StringBuilder."<init>":(Ljava/lang/String;)V
       9: astore_2
      10: aload_0
      11: aload_2
      12: aload_1
      13: ldc           #76                 // String interface
      15: invokespecial #135                // Method appendIfPresent:(Ljava/lang/StringBuilder;Lorg/apache/dubbo/common/URL;Ljava/lang/String;)V
      18: aload_0
      19: aload_2
      20: aload_1
      21: ldc           #136                // String version
      23: invokespecial #135                // Method appendIfPresent:(Ljava/lang/StringBuilder;Lorg/apache/dubbo/common/URL;Ljava/lang/String;)V
      26: aload_0
      27: aload_2
      28: aload_1
      29: ldc           #137                // String group
      31: invokespecial #135                // Method appendIfPresent:(Ljava/lang/StringBuilder;Lorg/apache/dubbo/common/URL;Ljava/lang/String;)V
      34: aload_2
      35: invokevirtual #47                 // Method java/lang/StringBuilder.toString:()Ljava/lang/String;
      38: areturn

  private void appendIfPresent(java.lang.StringBuilder, org.apache.dubbo.common.URL, java.lang.String);
    Code:
       0: aload_2
       1: aload_3
       2: invokevirtual #138                // Method org/apache/dubbo/common/URL.getParameter:(Ljava/lang/String;)Ljava/lang/String;
       5: astore        4
       7: aload         4
       9: invokestatic  #139                // Method org/apache/dubbo/common/utils/StringUtils.isBlank:(Ljava/lang/CharSequence;)Z
      12: ifne          28
      15: aload_1
      16: getstatic     #73                 // Field SERVICE_NAME_SEPARATOR:Ljava/lang/String;
      19: invokevirtual #42                 // Method java/lang/StringBuilder.append:(Ljava/lang/String;)Ljava/lang/StringBuilder;
      22: aload         4
      24: invokevirtual #42                 // Method java/lang/StringBuilder.append:(Ljava/lang/String;)Ljava/lang/StringBuilder;
      27: pop
      28: return

  private boolean isAdminProtocol(org.apache.dubbo.common.URL);
    Code:
       0: ldc           #140                // String admin
       2: aload_1
       3: invokevirtual #141                // Method org/apache/dubbo/common/URL.getProtocol:()Ljava/lang/String;
       6: invokevirtual #19                 // Method java/lang/String.equals:(Ljava/lang/Object;)Z
       9: ireturn

  private void scheduleServiceNamesLookup(org.apache.dubbo.common.URL, org.apache.dubbo.registry.nacos.NacosAggregateListener);
    Code:
       0: aload_0
       1: getfield      #103                // Field scheduledExecutorService:Ljava/util/concurrent/ScheduledExecutorService;
       4: ifnonnull     41
       7: aload_0
       8: invokestatic  #142                // Method java/util/concurrent/Executors.newSingleThreadScheduledExecutor:()Ljava/util/concurrent/ScheduledExecutorService;
      11: putfield      #103                // Field scheduledExecutorService:Ljava/util/concurrent/ScheduledExecutorService;
      14: aload_0
      15: getfield      #103                // Field scheduledExecutorService:Ljava/util/concurrent/ScheduledExecutorService;
      18: aload_0
      19: aload_1
      20: aload_2
      21: invokedynamic #143,  0            // InvokeDynamic #5:run:(Lorg/apache/dubbo/registry/nacos/NacosRegistry;Lorg/apache/dubbo/common/URL;Lorg/apache/dubbo/registry/nacos/NacosAggregateListener;)Ljava/lang/Runnable;
      26: getstatic     #144                // Field LOOKUP_INTERVAL:J
      29: getstatic     #144                // Field LOOKUP_INTERVAL:J
      32: getstatic     #145                // Field java/util/concurrent/TimeUnit.SECONDS:Ljava/util/concurrent/TimeUnit;
      35: invokeinterface #146,  7          // InterfaceMethod java/util/concurrent/ScheduledExecutorService.scheduleAtFixedRate:(Ljava/lang/Runnable;JJLjava/util/concurrent/TimeUnit;)Ljava/util/concurrent/ScheduledFuture;
      40: pop
      41: return

  private java.util.Set<java.lang.String> getServiceNamesForOps(org.apache.dubbo.common.URL);
    Code:
       0: aload_0
       1: invokespecial #147                // Method getAllServiceNames:()Ljava/util/Set;
       4: astore_2
       5: aload_0
       6: aload_2
       7: aload_1
       8: invokespecial #148                // Method filterServiceNames:(Ljava/util/Set;Lorg/apache/dubbo/common/URL;)V
      11: aload_2
      12: areturn

  private java.util.Set<java.lang.String> getAllServiceNames();
    Code:
       0: new           #108                // class java/util/LinkedHashSet
       3: dup
       4: invokespecial #109                // Method java/util/LinkedHashSet."<init>":()V
       7: astore_1
       8: iconst_1
       9: istore_2
      10: aload_0
      11: getfield      #12                 // Field namingService:Lorg/apache/dubbo/registry/nacos/NacosNamingServiceWrapper;
      14: iload_2
      15: getstatic     #149                // Field PAGINATION_SIZE:I
      18: aload_0
      19: invokevirtual #30                 // Method getUrl:()Lorg/apache/dubbo/common/URL;
      22: ldc           #32                 // String DEFAULT_GROUP
      24: invokevirtual #33                 // Method org/apache/dubbo/common/URL.getGroup:(Ljava/lang/String;)Ljava/lang/String;
      27: invokevirtual #116                // Method org/apache/dubbo/registry/nacos/NacosNamingServiceWrapper.getServicesOfServer:(IILjava/lang/String;)Lcom/alibaba/nacos/api/naming/pojo/ListView;
      30: astore_3
      31: aload_3
      32: invokevirtual #117                // Method com/alibaba/nacos/api/naming/pojo/ListView.getData:()Ljava/util/List;
      35: astore        4
      37: aload_1
      38: aload         4
      40: invokeinterface #129,  2          // InterfaceMethod java/util/Set.addAll:(Ljava/util/Collection;)Z
      45: pop
      46: aload_3
      47: invokevirtual #150                // Method com/alibaba/nacos/api/naming/pojo/ListView.getCount:()I
      50: istore        5
      52: iload         5
      54: getstatic     #149                // Field PAGINATION_SIZE:I
      57: idiv
      58: istore        6
      60: iload         5
      62: getstatic     #149                // Field PAGINATION_SIZE:I
      65: irem
      66: istore        7
      68: iload         7
      70: ifle          76
      73: iinc          6, 1
      76: iload_2
      77: iload         6
      79: if_icmpge     120
      82: aload_0
      83: getfield      #12                 // Field namingService:Lorg/apache/dubbo/registry/nacos/NacosNamingServiceWrapper;
      86: iinc          2, 1
      89: iload_2
      90: getstatic     #149                // Field PAGINATION_SIZE:I
      93: aload_0
      94: invokevirtual #30                 // Method getUrl:()Lorg/apache/dubbo/common/URL;
      97: ldc           #32                 // String DEFAULT_GROUP
      99: invokevirtual #33                 // Method org/apache/dubbo/common/URL.getGroup:(Ljava/lang/String;)Ljava/lang/String;
     102: invokevirtual #116                // Method org/apache/dubbo/registry/nacos/NacosNamingServiceWrapper.getServicesOfServer:(IILjava/lang/String;)Lcom/alibaba/nacos/api/naming/pojo/ListView;
     105: astore_3
     106: aload_1
     107: aload_3
     108: invokevirtual #117                // Method com/alibaba/nacos/api/naming/pojo/ListView.getData:()Ljava/util/List;
     111: invokeinterface #129,  2          // InterfaceMethod java/util/Set.addAll:(Ljava/util/Collection;)Z
     116: pop
     117: goto          76
     120: aload_1
     121: areturn
     122: astore_1
     123: new           #38                 // class org/apache/dubbo/rpc/RpcException
     126: dup
     127: new           #39                 // class java/lang/StringBuilder
     130: dup
     131: invokespecial #40                 // Method java/lang/StringBuilder."<init>":()V
     134: ldc           #151                // String Failed to get all serviceName from nacos, url:
     136: invokevirtual #42                 // Method java/lang/StringBuilder.append:(Ljava/lang/String;)Ljava/lang/StringBuilder;
     139: aload_0
     140: invokevirtual #30                 // Method getUrl:()Lorg/apache/dubbo/common/URL;
     143: invokevirtual #43                 // Method java/lang/StringBuilder.append:(Ljava/lang/Object;)Ljava/lang/StringBuilder;
     146: ldc           #45                 // String , cause:
     148: invokevirtual #42                 // Method java/lang/StringBuilder.append:(Ljava/lang/String;)Ljava/lang/StringBuilder;
     151: aload_1
     152: invokevirtual #82                 // Method java/lang/Throwable.getMessage:()Ljava/lang/String;
     155: invokevirtual #42                 // Method java/lang/StringBuilder.append:(Ljava/lang/String;)Ljava/lang/StringBuilder;
     158: invokevirtual #47                 // Method java/lang/StringBuilder.toString:()Ljava/lang/String;
     161: aload_1
     162: invokespecial #48                 // Method org/apache/dubbo/rpc/RpcException."<init>":(Ljava/lang/String;Ljava/lang/Throwable;)V
     165: athrow
    Exception table:
       from    to  target type
           0   121   122   Class java/lang/Throwable

  private void filterServiceNames(java.util.Set<java.lang.String>, org.apache.dubbo.common.URL);
    Code:
       0: aload_0
       1: aload_2
       2: invokespecial #152                // Method getCategories:(Lorg/apache/dubbo/common/URL;)Ljava/util/List;
       5: astore_3
       6: aload_2
       7: invokevirtual #153                // Method org/apache/dubbo/common/URL.getServiceInterface:()Ljava/lang/String;
      10: astore        4
      12: aload_2
      13: ldc           #89                 // String
      15: invokevirtual #154                // Method org/apache/dubbo/common/URL.getVersion:(Ljava/lang/String;)Ljava/lang/String;
      18: astore        5
      20: aload_2
      21: ldc           #89                 // String
      23: invokevirtual #33                 // Method org/apache/dubbo/common/URL.getGroup:(Ljava/lang/String;)Ljava/lang/String;
      26: astore        6
      28: aload_0
      29: aload_1
      30: aload_3
      31: aload         4
      33: aload         5
      35: aload         6
      37: invokedynamic #155,  0            // InvokeDynamic #6:accept:(Ljava/util/List;Ljava/lang/String;Ljava/lang/String;Ljava/lang/String;)Lorg/apache/dubbo/registry/nacos/NacosRegistry$NacosDataFilter;
      42: invokespecial #156                // Method filterData:(Ljava/util/Collection;Lorg/apache/dubbo/registry/nacos/NacosRegistry$NacosDataFilter;)V
      45: return

  private <T> void filterData(java.util.Collection<T>, org.apache.dubbo.registry.nacos.NacosRegistry$NacosDataFilter<T>);
    Code:
       0: aload_1
       1: aload_2
       2: invokedynamic #157,  0            // InvokeDynamic #7:test:(Lorg/apache/dubbo/registry/nacos/NacosRegistry$NacosDataFilter;)Ljava/util/function/Predicate;
       7: invokeinterface #158,  2          // InterfaceMethod java/util/Collection.removeIf:(Ljava/util/function/Predicate;)Z
      12: pop
      13: return

  private java.util.List<java.lang.String> doGetServiceNames(org.apache.dubbo.common.URL);
    Code:
       0: aload_0
       1: aload_1
       2: invokespecial #152                // Method getCategories:(Lorg/apache/dubbo/common/URL;)Ljava/util/List;
       5: astore_2
       6: new           #159                // class java/util/ArrayList
       9: dup
      10: aload_2
      11: invokeinterface #160,  1          // InterfaceMethod java/util/List.size:()I
      16: invokespecial #161                // Method java/util/ArrayList."<init>":(I)V
      19: astore_3
      20: aload_2
      21: invokeinterface #162,  1          // InterfaceMethod java/util/List.iterator:()Ljava/util/Iterator;
      26: astore        4
      28: aload         4
      30: invokeinterface #27,  1           // InterfaceMethod java/util/Iterator.hasNext:()Z
      35: ifeq          71
      38: aload         4
      40: invokeinterface #28,  1           // InterfaceMethod java/util/Iterator.next:()Ljava/lang/Object;
      45: checkcast     #29                 // class java/lang/String
      48: astore        5
      50: aload_0
      51: aload_1
      52: aload         5
      54: invokespecial #163                // Method getServiceName:(Lorg/apache/dubbo/common/URL;Ljava/lang/String;)Ljava/lang/String;
      57: astore        6
      59: aload_3
      60: aload         6
      62: invokeinterface #164,  2          // InterfaceMethod java/util/List.add:(Ljava/lang/Object;)Z
      67: pop
      68: goto          28
      71: aload_3
      72: areturn

  public void destroy();
    Code:
       0: aload_0
       1: invokespecial #165                // Method org/apache/dubbo/registry/support/FailbackRegistry.destroy:()V
       4: aload_0
       5: getfield      #12                 // Field namingService:Lorg/apache/dubbo/registry/nacos/NacosNamingServiceWrapper;
       8: invokevirtual #166                // Method org/apache/dubbo/registry/nacos/NacosNamingServiceWrapper.shutdown:()V
      11: goto          32
      14: astore_1
      15: getstatic     #55                 // Field logger:Lorg/apache/dubbo/common/logger/ErrorTypeAwareLogger;
      18: ldc           #88                 // String 1-37
      20: ldc           #89                 // String
      22: ldc           #89                 // String
      24: ldc           #167                // String Unable to shutdown nacos naming service
      26: aload_1
      27: invokeinterface #168,  6          // InterfaceMethod org/apache/dubbo/common/logger/ErrorTypeAwareLogger.warn:(Ljava/lang/String;Ljava/lang/String;Ljava/lang/String;Ljava/lang/String;Ljava/lang/Throwable;)V
      32: aload_0
      33: getfield      #11                 // Field nacosListeners:Ljava/util/Map;
      36: invokeinterface #169,  1          // InterfaceMethod java/util/Map.clear:()V
      41: return
    Exception table:
       from    to  target type
           4    11    14   Class com/alibaba/nacos/api/exception/NacosException

  private java.util.List<org.apache.dubbo.common.URL> toUrlWithEmpty(org.apache.dubbo.common.URL, java.util.Collection<com.alibaba.nacos.api.naming.pojo.Instance>);
    Code:
       0: aload_0
       1: aload_1
       2: aload_2
       3: invokespecial #35                 // Method buildURLs:(Lorg/apache/dubbo/common/URL;Ljava/util/Collection;)Ljava/util/List;
       6: astore_3
       7: aload_3
       8: invokeinterface #160,  1          // InterfaceMethod java/util/List.size:()I
      13: ifne          75
      16: aload_0
      17: invokevirtual #30                 // Method getUrl:()Lorg/apache/dubbo/common/URL;
      20: ldc           #170                // String enable-empty-protection
      22: iconst_0
      23: invokevirtual #14                 // Method org/apache/dubbo/common/URL.getParameter:(Ljava/lang/String;Z)Z
      26: ifne          75
      29: getstatic     #55                 // Field logger:Lorg/apache/dubbo/common/logger/ErrorTypeAwareLogger;
      32: ldc           #88                 // String 1-37
      34: ldc           #89                 // String
      36: ldc           #89                 // String
      38: ldc           #171                // String Received empty url address list and empty protection is disabled, will clear current available addresses
      40: invokeinterface #93,  5           // InterfaceMethod org/apache/dubbo/common/logger/ErrorTypeAwareLogger.warn:(Ljava/lang/String;Ljava/lang/String;Ljava/lang/String;Ljava/lang/String;)V
      45: aload_1
      46: invokestatic  #172                // Method org/apache/dubbo/common/URLBuilder.from:(Lorg/apache/dubbo/common/URL;)Lorg/apache/dubbo/common/URLBuilder;
      49: ldc           #173                // String empty
      51: invokevirtual #174                // Method org/apache/dubbo/common/URLBuilder.setProtocol:(Ljava/lang/String;)Lorg/apache/dubbo/common/URLBuilder;
      54: ldc           #175                // String category
      56: ldc           #133                // String providers
      58: invokevirtual #176                // Method org/apache/dubbo/common/URLBuilder.addParameter:(Ljava/lang/String;Ljava/lang/String;)Lorg/apache/dubbo/common/URLBuilder;
      61: invokevirtual #177                // Method org/apache/dubbo/common/URLBuilder.build:()Lorg/apache/dubbo/common/url/component/ServiceConfigURL;
      64: astore        4
      66: aload_3
      67: aload         4
      69: invokeinterface #164,  2          // InterfaceMethod java/util/List.add:(Ljava/lang/Object;)Z
      74: pop
      75: aload_3
      76: areturn

  private java.util.List<org.apache.dubbo.common.URL> buildURLs(org.apache.dubbo.common.URL, java.util.Collection<com.alibaba.nacos.api.naming.pojo.Instance>);
    Code:
       0: new           #23                 // class java/util/LinkedList
       3: dup
       4: invokespecial #24                 // Method java/util/LinkedList."<init>":()V
       7: astore_3
       8: aload_2
       9: ifnull        81
      12: aload_2
      13: invokeinterface #178,  1          // InterfaceMethod java/util/Collection.isEmpty:()Z
      18: ifne          81
      21: aload_2
      22: invokeinterface #179,  1          // InterfaceMethod java/util/Collection.iterator:()Ljava/util/Iterator;
      27: astore        4
      29: aload         4
      31: invokeinterface #27,  1           // InterfaceMethod java/util/Iterator.hasNext:()Z
      36: ifeq          81
      39: aload         4
      41: invokeinterface #28,  1           // InterfaceMethod java/util/Iterator.next:()Ljava/lang/Object;
      46: checkcast     #180                // class com/alibaba/nacos/api/naming/pojo/Instance
      49: astore        5
      51: aload_0
      52: aload_1
      53: aload         5
      55: invokespecial #181                // Method buildURL:(Lorg/apache/dubbo/common/URL;Lcom/alibaba/nacos/api/naming/pojo/Instance;)Lorg/apache/dubbo/common/URL;
      58: astore        6
      60: aload_1
      61: aload         6
      63: invokestatic  #182                // Method org/apache/dubbo/common/utils/UrlUtils.isMatch:(Lorg/apache/dubbo/common/URL;Lorg/apache/dubbo/common/URL;)Z
      66: ifeq          78
      69: aload_3
      70: aload         6
      72: invokeinterface #164,  2          // InterfaceMethod java/util/List.add:(Ljava/lang/Object;)Z
      77: pop
      78: goto          29
      81: aload_3
      82: areturn

  private void subscribeEventListener(java.lang.String, org.apache.dubbo.common.URL, org.apache.dubbo.registry.nacos.NacosAggregateListener) throws com.alibaba.nacos.api.exception.NacosException;
    Code:
       0: aload_0
       1: getfield      #11                 // Field nacosListeners:Ljava/util/Map;
       4: aload_2
       5: invokedynamic #183,  0            // InvokeDynamic #8:apply:()Ljava/util/function/Function;
      10: invokeinterface #67,  3           // InterfaceMethod java/util/Map.computeIfAbsent:(Ljava/lang/Object;Ljava/util/function/Function;)Ljava/lang/Object;
      15: checkcast     #68                 // class java/util/Map
      18: astore        4
      20: aload         4
      22: aload_3
      23: invokedynamic #184,  0            // InvokeDynamic #9:apply:()Ljava/util/function/Function;
      28: invokeinterface #67,  3           // InterfaceMethod java/util/Map.computeIfAbsent:(Ljava/lang/Object;Ljava/util/function/Function;)Ljava/lang/Object;
      33: checkcast     #68                 // class java/util/Map
      36: astore        5
      38: aload         5
      40: aload_1
      41: aload_0
      42: aload_1
      43: aload_2
      44: aload_3
      45: invokedynamic #185,  0            // InvokeDynamic #10:apply:(Lorg/apache/dubbo/registry/nacos/NacosRegistry;Ljava/lang/String;Lorg/apache/dubbo/common/URL;Lorg/apache/dubbo/registry/nacos/NacosAggregateListener;)Ljava/util/function/Function;
      50: invokeinterface #67,  3           // InterfaceMethod java/util/Map.computeIfAbsent:(Ljava/lang/Object;Ljava/util/function/Function;)Ljava/lang/Object;
      55: checkcast     #186                // class com/alibaba/nacos/api/naming/listener/EventListener
      58: astore        6
      60: aload_0
      61: getfield      #12                 // Field namingService:Lorg/apache/dubbo/registry/nacos/NacosNamingServiceWrapper;
      64: aload_1
      65: aload_0
      66: invokevirtual #30                 // Method getUrl:()Lorg/apache/dubbo/common/URL;
      69: ldc           #32                 // String DEFAULT_GROUP
      71: invokevirtual #33                 // Method org/apache/dubbo/common/URL.getGroup:(Ljava/lang/String;)Ljava/lang/String;
      74: aload         6
      76: invokevirtual #187                // Method org/apache/dubbo/registry/nacos/NacosNamingServiceWrapper.subscribe:(Ljava/lang/String;Ljava/lang/String;Lcom/alibaba/nacos/api/naming/listener/EventListener;)V
      79: return

  private void unsubscribeEventListener(java.lang.String, org.apache.dubbo.common.URL, org.apache.dubbo.registry.nacos.NacosAggregateListener) throws com.alibaba.nacos.api.exception.NacosException;
    Code:
       0: aload_0
       1: getfield      #11                 // Field nacosListeners:Ljava/util/Map;
       4: aload_2
       5: invokeinterface #87,  2           // InterfaceMethod java/util/Map.get:(Ljava/lang/Object;)Ljava/lang/Object;
      10: checkcast     #68                 // class java/util/Map
      13: astore        4
      15: aload         4
      17: ifnonnull     21
      20: return
      21: aload         4
      23: aload_3
      24: invokeinterface #87,  2           // InterfaceMethod java/util/Map.get:(Ljava/lang/Object;)Ljava/lang/Object;
      29: checkcast     #68                 // class java/util/Map
      32: astore        5
      34: aload         5
      36: ifnonnull     40
      39: return
      40: aload         5
      42: aload_1
      43: invokeinterface #94,  2           // InterfaceMethod java/util/Map.remove:(Ljava/lang/Object;)Ljava/lang/Object;
      48: checkcast     #186                // class com/alibaba/nacos/api/naming/listener/EventListener
      51: astore        6
      53: aload         6
      55: ifnonnull     59
      58: return
      59: aload_0
      60: getfield      #12                 // Field namingService:Lorg/apache/dubbo/registry/nacos/NacosNamingServiceWrapper;
      63: aload_1
      64: aload_0
      65: invokevirtual #30                 // Method getUrl:()Lorg/apache/dubbo/common/URL;
      68: ldc           #137                // String group
      70: ldc           #32                 // String DEFAULT_GROUP
      72: invokevirtual #188                // Method org/apache/dubbo/common/URL.getParameter:(Ljava/lang/String;Ljava/lang/String;)Ljava/lang/String;
      75: aload         6
      77: invokevirtual #189                // Method org/apache/dubbo/registry/nacos/NacosNamingServiceWrapper.unsubscribe:(Ljava/lang/String;Ljava/lang/String;Lcom/alibaba/nacos/api/naming/listener/EventListener;)V
      80: aload         5
      82: invokeinterface #101,  1          // InterfaceMethod java/util/Map.isEmpty:()Z
      87: ifeq          99
      90: aload         4
      92: aload_3
      93: invokeinterface #94,  2           // InterfaceMethod java/util/Map.remove:(Ljava/lang/Object;)Ljava/lang/Object;
      98: pop
      99: aload         4
     101: invokeinterface #101,  1          // InterfaceMethod java/util/Map.isEmpty:()Z
     106: ifeq          120
     109: aload_0
     110: getfield      #11                 // Field nacosListeners:Ljava/util/Map;
     113: aload_2
     114: invokeinterface #94,  2           // InterfaceMethod java/util/Map.remove:(Ljava/lang/Object;)Ljava/lang/Object;
     119: pop
     120: return

  private void notifySubscriber(org.apache.dubbo.common.URL, java.lang.String, org.apache.dubbo.registry.nacos.NacosAggregateListener, java.util.Collection<com.alibaba.nacos.api.naming.pojo.Instance>);
    Code:
       0: new           #23                 // class java/util/LinkedList
       3: dup
       4: aload         4
       6: invokespecial #190                // Method java/util/LinkedList."<init>":(Ljava/util/Collection;)V
       9: astore        5
      11: aload         5
      13: invokeinterface #160,  1          // InterfaceMethod java/util/List.size:()I
      18: ifle          27
      21: aload_0
      22: aload         5
      24: invokespecial #191                // Method filterEnabledInstances:(Ljava/util/Collection;)V
      27: aload_0
      28: aload_1
      29: aload_3
      30: aload_2
      31: aload         5
      33: invokevirtual #192                // Method org/apache/dubbo/registry/nacos/NacosAggregateListener.saveAndAggregateAllInstances:(Ljava/lang/String;Ljava/util/List;)Ljava/util/List;
      36: invokespecial #193                // Method toUrlWithEmpty:(Lorg/apache/dubbo/common/URL;Ljava/util/Collection;)Ljava/util/List;
      39: astore        6
      41: aload_0
      42: aload_1
      43: aload_3
      44: invokevirtual #194                // Method org/apache/dubbo/registry/nacos/NacosAggregateListener.getNotifyListener:()Lorg/apache/dubbo/registry/NotifyListener;
      47: aload         6
      49: invokevirtual #195                // Method notify:(Lorg/apache/dubbo/common/URL;Lorg/apache/dubbo/registry/NotifyListener;Ljava/util/List;)V
      52: return

  private java.util.List<java.lang.String> getCategories(org.apache.dubbo.common.URL);
    Code:
       0: ldc           #196                // String *
       2: aload_1
       3: invokevirtual #153                // Method org/apache/dubbo/common/URL.getServiceInterface:()Ljava/lang/String;
       6: invokevirtual #19                 // Method java/lang/String.equals:(Ljava/lang/Object;)Z
       9: ifeq          18
      12: getstatic     #197                // Field ALL_SUPPORTED_CATEGORIES:Ljava/util/List;
      15: goto          30
      18: iconst_1
      19: anewarray     #29                 // class java/lang/String
      22: dup
      23: iconst_0
      24: ldc           #133                // String providers
      26: aastore
      27: invokestatic  #198                // Method java/util/Arrays.asList:([Ljava/lang/Object;)Ljava/util/List;
      30: areturn

  private org.apache.dubbo.common.URL buildURL(org.apache.dubbo.common.URL, com.alibaba.nacos.api.naming.pojo.Instance);
    Code:
       0: aload_2
       1: invokevirtual #199                // Method com/alibaba/nacos/api/naming/pojo/Instance.getMetadata:()Ljava/util/Map;
       4: astore_3
       5: aload_3
       6: ldc           #200                // String protocol
       8: invokeinterface #87,  2           // InterfaceMethod java/util/Map.get:(Ljava/lang/Object;)Ljava/lang/Object;
      13: checkcast     #29                 // class java/lang/String
      16: astore        4
      18: aload_3
      19: ldc           #201                // String path
      21: invokeinterface #87,  2           // InterfaceMethod java/util/Map.get:(Ljava/lang/Object;)Ljava/lang/Object;
      26: checkcast     #29                 // class java/lang/String
      29: astore        5
      31: new           #202                // class org/apache/dubbo/common/url/component/ServiceConfigURL
      34: dup
      35: aload         4
      37: aload_2
      38: invokevirtual #60                 // Method com/alibaba/nacos/api/naming/pojo/Instance.getIp:()Ljava/lang/String;
      41: aload_2
      42: invokevirtual #61                 // Method com/alibaba/nacos/api/naming/pojo/Instance.getPort:()I
      45: aload         5
      47: aload_2
      48: invokevirtual #199                // Method com/alibaba/nacos/api/naming/pojo/Instance.getMetadata:()Ljava/util/Map;
      51: invokespecial #203                // Method org/apache/dubbo/common/url/component/ServiceConfigURL."<init>":(Ljava/lang/String;Ljava/lang/String;ILjava/lang/String;Ljava/util/Map;)V
      54: astore        6
      56: new           #204                // class org/apache/dubbo/common/url/component/DubboServiceAddressURL
      59: dup
      60: aload         6
      62: invokevirtual #205                // Method org/apache/dubbo/common/URL.getUrlAddress:()Lorg/apache/dubbo/common/url/component/URLAddress;
      65: aload         6
      67: invokevirtual #206                // Method org/apache/dubbo/common/URL.getUrlParam:()Lorg/apache/dubbo/common/url/component/URLParam;
      70: aload_1
      71: aconst_null
      72: invokespecial #207                // Method org/apache/dubbo/common/url/component/DubboServiceAddressURL."<init>":(Lorg/apache/dubbo/common/url/component/URLAddress;Lorg/apache/dubbo/common/url/component/URLParam;Lorg/apache/dubbo/common/URL;Lorg/apache/dubbo/common/url/component/ServiceConfigURL;)V
      75: areturn

  private com.alibaba.nacos.api.naming.pojo.Instance createInstance(org.apache.dubbo.common.URL);
    Code:
       0: aload_1
       1: ldc           #133                // String providers
       3: invokevirtual #208                // Method org/apache/dubbo/common/URL.getCategory:(Ljava/lang/String;)Ljava/lang/String;
       6: astore_2
       7: aload_1
       8: ldc           #175                // String category
      10: aload_2
      11: invokevirtual #209                // Method org/apache/dubbo/common/URL.addParameter:(Ljava/lang/String;Ljava/lang/String;)Lorg/apache/dubbo/common/URL;
      14: astore_3
      15: aload_3
      16: ldc           #200                // String protocol
      18: aload_1
      19: invokevirtual #141                // Method org/apache/dubbo/common/URL.getProtocol:()Ljava/lang/String;
      22: invokevirtual #209                // Method org/apache/dubbo/common/URL.addParameter:(Ljava/lang/String;Ljava/lang/String;)Lorg/apache/dubbo/common/URL;
      25: astore_3
      26: aload_3
      27: ldc           #201                // String path
      29: aload_1
      30: invokevirtual #210                // Method org/apache/dubbo/common/URL.getPath:()Ljava/lang/String;
      33: invokevirtual #209                // Method org/apache/dubbo/common/URL.addParameter:(Ljava/lang/String;Ljava/lang/String;)Lorg/apache/dubbo/common/URL;
      36: astore_3
      37: aload_1
      38: invokevirtual #211                // Method org/apache/dubbo/common/URL.getHost:()Ljava/lang/String;
      41: astore        4
      43: aload_1
      44: invokevirtual #212                // Method org/apache/dubbo/common/URL.getPort:()I
      47: istore        5
      49: new           #180                // class com/alibaba/nacos/api/naming/pojo/Instance
      52: dup
      53: invokespecial #213                // Method com/alibaba/nacos/api/naming/pojo/Instance."<init>":()V
      56: astore        6
      58: aload         6
      60: aload         4
      62: invokevirtual #214                // Method com/alibaba/nacos/api/naming/pojo/Instance.setIp:(Ljava/lang/String;)V
      65: aload         6
      67: iload         5
      69: invokevirtual #215                // Method com/alibaba/nacos/api/naming/pojo/Instance.setPort:(I)V
      72: aload         6
      74: new           #216                // class java/util/HashMap
      77: dup
      78: aload_3
      79: invokevirtual #217                // Method org/apache/dubbo/common/URL.getParameters:()Ljava/util/Map;
      82: invokespecial #218                // Method java/util/HashMap."<init>":(Ljava/util/Map;)V
      85: invokevirtual #219                // Method com/alibaba/nacos/api/naming/pojo/Instance.setMetadata:(Ljava/util/Map;)V
      88: aload         6
      90: areturn

  private org.apache.dubbo.registry.nacos.NacosServiceName createServiceName(org.apache.dubbo.common.URL);
    Code:
       0: aload_1
       1: invokestatic  #220                // Method org/apache/dubbo/registry/nacos/NacosServiceName.valueOf:(Lorg/apache/dubbo/common/URL;)Lorg/apache/dubbo/registry/nacos/NacosServiceName;
       4: areturn

  private java.lang.String getServiceName(org.apache.dubbo.common.URL);
    Code:
       0: aload_0
       1: aload_1
       2: aload_1
       3: ldc           #133                // String providers
       5: invokevirtual #208                // Method org/apache/dubbo/common/URL.getCategory:(Ljava/lang/String;)Ljava/lang/String;
       8: invokespecial #163                // Method getServiceName:(Lorg/apache/dubbo/common/URL;Ljava/lang/String;)Ljava/lang/String;
      11: areturn

  private java.lang.String getServiceName(org.apache.dubbo.common.URL, java.lang.String);
    Code:
       0: new           #39                 // class java/lang/StringBuilder
       3: dup
       4: invokespecial #40                 // Method java/lang/StringBuilder."<init>":()V
       7: aload_2
       8: invokevirtual #42                 // Method java/lang/StringBuilder.append:(Ljava/lang/String;)Ljava/lang/StringBuilder;
      11: getstatic     #73                 // Field SERVICE_NAME_SEPARATOR:Ljava/lang/String;
      14: invokevirtual #42                 // Method java/lang/StringBuilder.append:(Ljava/lang/String;)Ljava/lang/StringBuilder;
      17: aload_1
      18: invokevirtual #221                // Method org/apache/dubbo/common/URL.getColonSeparatedKey:()Ljava/lang/String;
      21: invokevirtual #42                 // Method java/lang/StringBuilder.append:(Ljava/lang/String;)Ljava/lang/StringBuilder;
      24: invokevirtual #47                 // Method java/lang/StringBuilder.toString:()Ljava/lang/String;
      27: areturn

  private void filterEnabledInstances(java.util.Collection<com.alibaba.nacos.api.naming.pojo.Instance>);
    Code:
       0: aload_0
       1: aload_1
       2: invokedynamic #222,  0            // InvokeDynamic #11:accept:()Lorg/apache/dubbo/registry/nacos/NacosRegistry$NacosDataFilter;
       7: invokespecial #156                // Method filterData:(Ljava/util/Collection;Lorg/apache/dubbo/registry/nacos/NacosRegistry$NacosDataFilter;)V
      10: return

  private com.alibaba.nacos.api.naming.listener.EventListener lambda$subscribeEventListener$7(java.lang.String, org.apache.dubbo.common.URL, org.apache.dubbo.registry.nacos.NacosAggregateListener, java.lang.String);
    Code:
       0: new           #223                // class org/apache/dubbo/registry/nacos/NacosRegistry$RegistryChildListenerImpl
       3: dup
       4: aload_0
       5: aload_1
       6: aload_2
       7: aload_3
       8: invokespecial #224                // Method org/apache/dubbo/registry/nacos/NacosRegistry$RegistryChildListenerImpl."<init>":(Lorg/apache/dubbo/registry/nacos/NacosRegistry;Ljava/lang/String;Lorg/apache/dubbo/common/URL;Lorg/apache/dubbo/registry/nacos/NacosAggregateListener;)V
      11: areturn

  private static java.util.Map lambda$subscribeEventListener$6(org.apache.dubbo.registry.nacos.NacosAggregateListener);
    Code:
       0: new           #8                  // class java/util/concurrent/ConcurrentHashMap
       3: dup
       4: invokespecial #9                  // Method java/util/concurrent/ConcurrentHashMap."<init>":()V
       7: areturn

  private static java.util.Map lambda$subscribeEventListener$5(org.apache.dubbo.common.URL);
    Code:
       0: new           #8                  // class java/util/concurrent/ConcurrentHashMap
       3: dup
       4: invokespecial #9                  // Method java/util/concurrent/ConcurrentHashMap."<init>":()V
       7: areturn

  private static boolean lambda$filterData$4(org.apache.dubbo.registry.nacos.NacosRegistry$NacosDataFilter, java.lang.Object);
    Code:
       0: aload_0
       1: aload_1
       2: invokeinterface #225,  2          // InterfaceMethod org/apache/dubbo/registry/nacos/NacosRegistry$NacosDataFilter.accept:(Ljava/lang/Object;)Z
       7: ifne          14
      10: iconst_1
      11: goto          15
      14: iconst_0
      15: ireturn

  private static boolean lambda$filterServiceNames$3(java.util.List, java.lang.String, java.lang.String, java.lang.String, java.lang.String);
    Code:
       0: aload         4
       2: getstatic     #73                 // Field SERVICE_NAME_SEPARATOR:Ljava/lang/String;
       5: iconst_m1
       6: invokevirtual #74                 // Method java/lang/String.split:(Ljava/lang/String;I)[Ljava/lang/String;
       9: astore        5
      11: aload         5
      13: arraylength
      14: istore        6
      16: iload         6
      18: iconst_4
      19: if_icmpeq     24
      22: iconst_0
      23: ireturn
      24: aload         5
      26: iconst_0
      27: aaload
      28: astore        7
      30: aload_0
      31: aload         7
      33: invokeinterface #226,  2          // InterfaceMethod java/util/List.contains:(Ljava/lang/Object;)Z
      38: ifne          43
      41: iconst_0
      42: ireturn
      43: aload         5
      45: iconst_1
      46: aaload
      47: astore        8
      49: ldc           #196                // String *
      51: aload_1
      52: invokevirtual #19                 // Method java/lang/String.equals:(Ljava/lang/Object;)Z
      55: ifne          69
      58: aload_1
      59: aload         8
      61: invokestatic  #227                // Method org/apache/dubbo/common/utils/StringUtils.isEquals:(Ljava/lang/String;Ljava/lang/String;)Z
      64: ifne          69
      67: iconst_0
      68: ireturn
      69: aload         5
      71: iconst_2
      72: aaload
      73: astore        9
      75: ldc           #196                // String *
      77: aload_2
      78: invokevirtual #19                 // Method java/lang/String.equals:(Ljava/lang/Object;)Z
      81: ifne          95
      84: aload_2
      85: aload         9
      87: invokestatic  #227                // Method org/apache/dubbo/common/utils/StringUtils.isEquals:(Ljava/lang/String;Ljava/lang/String;)Z
      90: ifne          95
      93: iconst_0
      94: ireturn
      95: aload         5
      97: iconst_3
      98: aaload
      99: astore        10
     101: aload         10
     103: ifnull        124
     106: ldc           #196                // String *
     108: aload_3
     109: invokevirtual #19                 // Method java/lang/String.equals:(Ljava/lang/Object;)Z
     112: ifne          124
     115: aload_3
     116: aload         10
     118: invokestatic  #227                // Method org/apache/dubbo/common/utils/StringUtils.isEquals:(Ljava/lang/String;Ljava/lang/String;)Z
     121: ifeq          128
     124: iconst_1
     125: goto          129
     128: iconst_0
     129: ireturn

  private void lambda$scheduleServiceNamesLookup$2(org.apache.dubbo.common.URL, org.apache.dubbo.registry.nacos.NacosAggregateListener);
    Code:
       0: aload_0
       1: invokespecial #147                // Method getAllServiceNames:()Ljava/util/Set;
       4: astore_3
       5: aload_0
       6: aload_3
       7: invokedynamic #228,  0            // InvokeDynamic #12:accept:()Lorg/apache/dubbo/registry/nacos/NacosRegistry$NacosDataFilter;
      12: invokespecial #156                // Method filterData:(Ljava/util/Collection;Lorg/apache/dubbo/registry/nacos/NacosRegistry$NacosDataFilter;)V
      15: aload_0
      16: aload_1
      17: aload_2
      18: aload_3
      19: invokespecial #70                 // Method doSubscribe:(Lorg/apache/dubbo/common/URL;Lorg/apache/dubbo/registry/nacos/NacosAggregateListener;Ljava/util/Set;)V
      22: return

  private static boolean lambda$null$1(java.lang.String);
    Code:
       0: iconst_0
       1: istore_1
       2: getstatic     #197                // Field ALL_SUPPORTED_CATEGORIES:Ljava/util/List;
       5: invokeinterface #162,  1          // InterfaceMethod java/util/List.iterator:()Ljava/util/Iterator;
      10: astore_2
      11: aload_2
      12: invokeinterface #27,  1           // InterfaceMethod java/util/Iterator.hasNext:()Z
      17: ifeq          73
      20: aload_2
      21: invokeinterface #28,  1           // InterfaceMethod java/util/Iterator.next:()Ljava/lang/Object;
      26: checkcast     #29                 // class java/lang/String
      29: astore_3
      30: new           #39                 // class java/lang/StringBuilder
      33: dup
      34: invokespecial #40                 // Method java/lang/StringBuilder."<init>":()V
      37: aload_3
      38: invokevirtual #42                 // Method java/lang/StringBuilder.append:(Ljava/lang/String;)Ljava/lang/StringBuilder;
      41: getstatic     #73                 // Field SERVICE_NAME_SEPARATOR:Ljava/lang/String;
      44: invokevirtual #42                 // Method java/lang/StringBuilder.append:(Ljava/lang/String;)Ljava/lang/StringBuilder;
      47: invokevirtual #47                 // Method java/lang/StringBuilder.toString:()Ljava/lang/String;
      50: astore        4
      52: aload_0
      53: ifnull        70
      56: aload_0
      57: aload         4
      59: invokevirtual #229                // Method java/lang/String.startsWith:(Ljava/lang/String;)Z
      62: ifeq          70
      65: iconst_1
      66: istore_1
      67: goto          73
      70: goto          11
      73: iload_1
      74: ireturn

  private static java.util.Map lambda$doSubscribe$0(org.apache.dubbo.common.URL);
    Code:
       0: new           #8                  // class java/util/concurrent/ConcurrentHashMap
       3: dup
       4: invokespecial #9                  // Method java/util/concurrent/ConcurrentHashMap."<init>":()V
       7: areturn

  static void access$000(org.apache.dubbo.registry.nacos.NacosRegistry, org.apache.dubbo.common.URL, java.lang.String, org.apache.dubbo.registry.nacos.NacosAggregateListener, java.util.Collection);
    Code:
       0: aload_0
       1: aload_1
       2: aload_2
       3: aload_3
       4: aload         4
       6: invokespecial #6                  // Method notifySubscriber:(Lorg/apache/dubbo/common/URL;Ljava/lang/String;Lorg/apache/dubbo/registry/nacos/NacosAggregateListener;Ljava/util/Collection;)V
       9: return

  static {};
    Code:
       0: iconst_4
       1: anewarray     #29                 // class java/lang/String
       4: dup
       5: iconst_0
       6: ldc           #133                // String providers
       8: aastore
       9: dup
      10: iconst_1
      11: ldc           #230                // String consumers
      13: aastore
      14: dup
      15: iconst_2
      16: ldc           #231                // String routers
      18: aastore
      19: dup
      20: iconst_3
      21: ldc           #232                // String configurators
      23: aastore
      24: invokestatic  #198                // Method java/util/Arrays.asList:([Ljava/lang/Object;)Ljava/util/List;
      27: putstatic     #197                // Field ALL_SUPPORTED_CATEGORIES:Ljava/util/List;
      30: ldc           #233                // String nacos.service.name.separator
      32: ldc           #132                // String :
      34: invokestatic  #234                // Method java/lang/System.getProperty:(Ljava/lang/String;Ljava/lang/String;)Ljava/lang/String;
      37: putstatic     #73                 // Field SERVICE_NAME_SEPARATOR:Ljava/lang/String;
      40: ldc           #235                // String nacos.service.names.pagination.size
      42: bipush        100
      44: invokestatic  #236                // Method java/lang/Integer.getInteger:(Ljava/lang/String;I)Ljava/lang/Integer;
      47: invokevirtual #237                // Method java/lang/Integer.intValue:()I
      50: putstatic     #149                // Field PAGINATION_SIZE:I
      53: ldc           #238                // String nacos.service.names.lookup.interval
      55: ldc2_w        #239                // long 30l
      58: invokestatic  #241                // Method java/lang/Long.getLong:(Ljava/lang/String;J)Ljava/lang/Long;
      61: invokevirtual #242                // Method java/lang/Long.longValue:()J
      64: putstatic     #144                // Field LOOKUP_INTERVAL:J
      67: ldc           #16                 // class org/apache/dubbo/registry/nacos/NacosRegistry
      69: invokestatic  #243                // Method org/apache/dubbo/common/logger/LoggerFactory.getErrorTypeAwareLogger:(Ljava/lang/Class;)Lorg/apache/dubbo/common/logger/ErrorTypeAwareLogger;
      72: putstatic     #55                 // Field logger:Lorg/apache/dubbo/common/logger/ErrorTypeAwareLogger;
      75: return
}
