Compiled from "NacosNamingServiceWrapper.java"
class org.apache.dubbo.registry.nacos.NacosNamingServiceWrapper$SubscribeInfo {
  private final java.lang.String serviceName;

  private final java.lang.String group;

  private final com.alibaba.nacos.api.naming.listener.EventListener eventListener;

  public org.apache.dubbo.registry.nacos.NacosNamingServiceWrapper$SubscribeInfo(java.lang.String, java.lang.String, com.alibaba.nacos.api.naming.listener.EventListener);
    Code:
       0: aload_0
       1: invokespecial #1                  // Method java/lang/Object."<init>":()V
       4: aload_0
       5: aload_1
       6: putfield      #2                  // Field serviceName:Ljava/lang/String;
       9: aload_0
      10: aload_2
      11: putfield      #3                  // Field group:Ljava/lang/String;
      14: aload_0
      15: aload_3
      16: putfield      #4                  // Field eventListener:Lcom/alibaba/nacos/api/naming/listener/EventListener;
      19: return

  public boolean equals(java.lang.Object);
    Code:
       0: aload_0
       1: aload_1
       2: if_acmpne     7
       5: iconst_1
       6: ireturn
       7: aload_1
       8: ifnull        22
      11: aload_0
      12: invokevirtual #5                  // Method java/lang/Object.getClass:()Ljava/lang/Class;
      15: aload_1
      16: invokevirtual #5                  // Method java/lang/Object.getClass:()Ljava/lang/Class;
      19: if_acmpeq     24
      22: iconst_0
      23: ireturn
      24: aload_1
      25: checkcast     #6                  // class org/apache/dubbo/registry/nacos/NacosNamingServiceWrapper$SubscribeInfo
      28: astore_2
      29: aload_0
      30: getfield      #2                  // Field serviceName:Ljava/lang/String;
      33: aload_2
      34: getfield      #2                  // Field serviceName:Ljava/lang/String;
      37: invokestatic  #7                  // Method java/util/Objects.equals:(Ljava/lang/Object;Ljava/lang/Object;)Z
      40: ifeq          75
      43: aload_0
      44: getfield      #3                  // Field group:Ljava/lang/String;
      47: aload_2
      48: getfield      #3                  // Field group:Ljava/lang/String;
      51: invokestatic  #7                  // Method java/util/Objects.equals:(Ljava/lang/Object;Ljava/lang/Object;)Z
      54: ifeq          75
      57: aload_0
      58: getfield      #4                  // Field eventListener:Lcom/alibaba/nacos/api/naming/listener/EventListener;
      61: aload_2
      62: getfield      #4                  // Field eventListener:Lcom/alibaba/nacos/api/naming/listener/EventListener;
      65: invokestatic  #7                  // Method java/util/Objects.equals:(Ljava/lang/Object;Ljava/lang/Object;)Z
      68: ifeq          75
      71: iconst_1
      72: goto          76
      75: iconst_0
      76: ireturn

  public int hashCode();
    Code:
       0: iconst_3
       1: anewarray     #8                  // class java/lang/Object
       4: dup
       5: iconst_0
       6: aload_0
       7: getfield      #2                  // Field serviceName:Ljava/lang/String;
      10: aastore
      11: dup
      12: iconst_1
      13: aload_0
      14: getfield      #3                  // Field group:Ljava/lang/String;
      17: aastore
      18: dup
      19: iconst_2
      20: aload_0
      21: getfield      #4                  // Field eventListener:Lcom/alibaba/nacos/api/naming/listener/EventListener;
      24: aastore
      25: invokestatic  #9                  // Method java/util/Objects.hash:([Ljava/lang/Object;)I
      28: ireturn
}
