Compiled from "NacosServiceDiscovery.java"
public class org.apache.dubbo.registry.nacos.NacosServiceDiscovery$NacosEventListener implements com.alibaba.nacos.api.naming.listener.EventListener {
  private final java.util.Set<org.apache.dubbo.registry.client.event.listener.ServiceInstancesChangedListener> listeners;

  final org.apache.dubbo.registry.nacos.NacosServiceDiscovery this$0;

  public org.apache.dubbo.registry.nacos.NacosServiceDiscovery$NacosEventListener(org.apache.dubbo.registry.nacos.NacosServiceDiscovery);
    Code:
       0: aload_0
       1: aload_1
       2: putfield      #1                  // Field this$0:Lorg/apache/dubbo/registry/nacos/NacosServiceDiscovery;
       5: aload_0
       6: invokespecial #2                  // Method java/lang/Object."<init>":()V
       9: aload_0
      10: new           #3                  // class org/apache/dubbo/common/utils/ConcurrentHashSet
      13: dup
      14: invokespecial #4                  // Method org/apache/dubbo/common/utils/ConcurrentHashSet."<init>":()V
      17: putfield      #5                  // Field listeners:Ljava/util/Set;
      20: return

  public void onEvent(com.alibaba.nacos.api.naming.listener.Event);
    Code:
       0: aload_1
       1: instanceof    #6                  // class com/alibaba/nacos/api/naming/listener/NamingEvent
       4: ifeq          55
       7: aload_0
       8: getfield      #5                  // Field listeners:Ljava/util/Set;
      11: invokeinterface #7,  1            // InterfaceMethod java/util/Set.iterator:()Ljava/util/Iterator;
      16: astore_2
      17: aload_2
      18: invokeinterface #8,  1            // InterfaceMethod java/util/Iterator.hasNext:()Z
      23: ifeq          55
      26: aload_2
      27: invokeinterface #9,  1            // InterfaceMethod java/util/Iterator.next:()Ljava/lang/Object;
      32: checkcast     #10                 // class org/apache/dubbo/registry/client/event/listener/ServiceInstancesChangedListener
      35: astore_3
      36: aload_1
      37: checkcast     #6                  // class com/alibaba/nacos/api/naming/listener/NamingEvent
      40: astore        4
      42: aload_0
      43: getfield      #1                  // Field this$0:Lorg/apache/dubbo/registry/nacos/NacosServiceDiscovery;
      46: aload         4
      48: aload_3
      49: invokestatic  #11                 // Method org/apache/dubbo/registry/nacos/NacosServiceDiscovery.access$000:(Lorg/apache/dubbo/registry/nacos/NacosServiceDiscovery;Lcom/alibaba/nacos/api/naming/listener/NamingEvent;Lorg/apache/dubbo/registry/client/event/listener/ServiceInstancesChangedListener;)V
      52: goto          17
      55: return

  public void addListener(org.apache.dubbo.registry.client.event.listener.ServiceInstancesChangedListener);
    Code:
       0: aload_0
       1: getfield      #5                  // Field listeners:Ljava/util/Set;
       4: aload_1
       5: invokeinterface #12,  2           // InterfaceMethod java/util/Set.add:(Ljava/lang/Object;)Z
      10: pop
      11: return

  public void removeListener(org.apache.dubbo.registry.client.event.listener.ServiceInstancesChangedListener);
    Code:
       0: aload_0
       1: getfield      #5                  // Field listeners:Ljava/util/Set;
       4: aload_1
       5: invokeinterface #13,  2           // InterfaceMethod java/util/Set.remove:(Ljava/lang/Object;)Z
      10: pop
      11: return

  public boolean isEmpty();
    Code:
       0: aload_0
       1: getfield      #5                  // Field listeners:Ljava/util/Set;
       4: invokeinterface #14,  1           // InterfaceMethod java/util/Set.isEmpty:()Z
       9: ireturn
}
