Compiled from "NacosRegistry.java"
class org.apache.dubbo.registry.nacos.NacosRegistry$RegistryChildListenerImpl$1 extends org.apache.dubbo.registry.RegistryNotifier {
  final org.apache.dubbo.registry.nacos.NacosRegistry val$this$0;

  final org.apache.dubbo.common.URL val$consumerUrl;

  final java.lang.String val$serviceName;

  final org.apache.dubbo.registry.nacos.NacosAggregateListener val$listener;

  final org.apache.dubbo.registry.nacos.NacosRegistry$RegistryChildListenerImpl this$1;

  org.apache.dubbo.registry.nacos.NacosRegistry$RegistryChildListenerImpl$1(org.apache.dubbo.registry.nacos.NacosRegistry$RegistryChildListenerImpl, org.apache.dubbo.common.URL, long, org.apache.dubbo.registry.nacos.NacosRegistry, org.apache.dubbo.common.URL, java.lang.String, org.apache.dubbo.registry.nacos.NacosAggregateListener);
    Code:
       0: aload_0
       1: aload_1
       2: putfield      #1                  // Field this$1:Lorg/apache/dubbo/registry/nacos/NacosRegistry$RegistryChildListenerImpl;
       5: aload_0
       6: aload         5
       8: putfield      #2                  // Field val$this$0:Lorg/apache/dubbo/registry/nacos/NacosRegistry;
      11: aload_0
      12: aload         6
      14: putfield      #3                  // Field val$consumerUrl:Lorg/apache/dubbo/common/URL;
      17: aload_0
      18: aload         7
      20: putfield      #4                  // Field val$serviceName:Ljava/lang/String;
      23: aload_0
      24: aload         8
      26: putfield      #5                  // Field val$listener:Lorg/apache/dubbo/registry/nacos/NacosAggregateListener;
      29: aload_0
      30: aload_2
      31: lload_3
      32: invokespecial #6                  // Method org/apache/dubbo/registry/RegistryNotifier."<init>":(Lorg/apache/dubbo/common/URL;J)V
      35: return

  protected void doNotify(java.lang.Object);
    Code:
       0: aload_1
       1: checkcast     #7                  // class java/util/List
       4: astore_2
       5: aload_0
       6: getfield      #1                  // Field this$1:Lorg/apache/dubbo/registry/nacos/NacosRegistry$RegistryChildListenerImpl;
       9: getfield      #8                  // Field org/apache/dubbo/registry/nacos/NacosRegistry$RegistryChildListenerImpl.this$0:Lorg/apache/dubbo/registry/nacos/NacosRegistry;
      12: aload_0
      13: getfield      #3                  // Field val$consumerUrl:Lorg/apache/dubbo/common/URL;
      16: aload_0
      17: getfield      #4                  // Field val$serviceName:Ljava/lang/String;
      20: aload_0
      21: getfield      #5                  // Field val$listener:Lorg/apache/dubbo/registry/nacos/NacosAggregateListener;
      24: aload_2
      25: invokestatic  #9                  // Method org/apache/dubbo/registry/nacos/NacosRegistry.access$000:(Lorg/apache/dubbo/registry/nacos/NacosRegistry;Lorg/apache/dubbo/common/URL;Ljava/lang/String;Lorg/apache/dubbo/registry/nacos/NacosAggregateListener;Ljava/util/Collection;)V
      28: return
}
