Compiled from "NacosNamingServiceWrapper.java"
public class org.apache.dubbo.registry.nacos.NacosNamingServiceWrapper {
  private static final org.apache.dubbo.common.logger.ErrorTypeAwareLogger logger;

  private static final java.lang.String INNERCLASS_SYMBOL;

  private static final java.lang.String INNERCLASS_COMPATIBLE_SYMBOL;

  private final org.apache.dubbo.registry.nacos.NacosConnectionManager nacosConnectionManager;

  private final int retryTimes;

  private final int sleepMsBetweenRetries;

  private final boolean isSupportBatchRegister;

  private final java.util.concurrent.ConcurrentMap<org.apache.dubbo.registry.nacos.NacosNamingServiceWrapper$InstanceId, org.apache.dubbo.registry.nacos.NacosNamingServiceWrapper$InstancesInfo> registerStatus;

  private final java.util.concurrent.ConcurrentMap<org.apache.dubbo.registry.nacos.NacosNamingServiceWrapper$SubscribeInfo, com.alibaba.nacos.api.naming.NamingService> subscribeStatus;

  public org.apache.dubbo.registry.nacos.NacosNamingServiceWrapper(org.apache.dubbo.registry.nacos.NacosConnectionManager, int, int);
    Code:
       0: aload_0
       1: invokespecial #1                  // Method java/lang/Object."<init>":()V
       4: aload_0
       5: new           #2                  // class java/util/concurrent/ConcurrentHashMap
       8: dup
       9: invokespecial #3                  // Method java/util/concurrent/ConcurrentHashMap."<init>":()V
      12: putfield      #4                  // Field registerStatus:Ljava/util/concurrent/ConcurrentMap;
      15: aload_0
      16: new           #2                  // class java/util/concurrent/ConcurrentHashMap
      19: dup
      20: invokespecial #3                  // Method java/util/concurrent/ConcurrentHashMap."<init>":()V
      23: putfield      #5                  // Field subscribeStatus:Ljava/util/concurrent/ConcurrentMap;
      26: aload_0
      27: aload_1
      28: putfield      #6                  // Field nacosConnectionManager:Lorg/apache/dubbo/registry/nacos/NacosConnectionManager;
      31: aload_0
      32: ldc           #7                  // class com/alibaba/nacos/api/naming/NamingService
      34: ldc           #8                  // String batchRegisterInstance
      36: iconst_3
      37: anewarray     #9                  // class java/lang/Class
      40: dup
      41: iconst_0
      42: ldc           #10                 // class java/lang/String
      44: aastore
      45: dup
      46: iconst_1
      47: ldc           #10                 // class java/lang/String
      49: aastore
      50: dup
      51: iconst_2
      52: ldc           #11                 // class java/util/List
      54: aastore
      55: invokestatic  #12                 // InterfaceMethod org/apache/dubbo/common/utils/MethodUtils.findMethod:(Ljava/lang/Class;Ljava/lang/String;[Ljava/lang/Class;)Ljava/lang/reflect/Method;
      58: ifnull        65
      61: iconst_1
      62: goto          66
      65: iconst_0
      66: putfield      #13                 // Field isSupportBatchRegister:Z
      69: getstatic     #14                 // Field logger:Lorg/apache/dubbo/common/logger/ErrorTypeAwareLogger;
      72: new           #15                 // class java/lang/StringBuilder
      75: dup
      76: invokespecial #16                 // Method java/lang/StringBuilder."<init>":()V
      79: ldc           #17                 // String Nacos batch register enable:
      81: invokevirtual #18                 // Method java/lang/StringBuilder.append:(Ljava/lang/String;)Ljava/lang/StringBuilder;
      84: aload_0
      85: getfield      #13                 // Field isSupportBatchRegister:Z
      88: invokevirtual #19                 // Method java/lang/StringBuilder.append:(Z)Ljava/lang/StringBuilder;
      91: invokevirtual #20                 // Method java/lang/StringBuilder.toString:()Ljava/lang/String;
      94: invokeinterface #21,  2           // InterfaceMethod org/apache/dubbo/common/logger/ErrorTypeAwareLogger.info:(Ljava/lang/String;)V
      99: aload_0
     100: iload_2
     101: iconst_0
     102: invokestatic  #22                 // Method java/lang/Math.max:(II)I
     105: putfield      #23                 // Field retryTimes:I
     108: aload_0
     109: iload_3
     110: putfield      #24                 // Field sleepMsBetweenRetries:I
     113: return

  protected org.apache.dubbo.registry.nacos.NacosNamingServiceWrapper(org.apache.dubbo.registry.nacos.NacosConnectionManager, boolean, int, int);
    Code:
       0: aload_0
       1: invokespecial #1                  // Method java/lang/Object."<init>":()V
       4: aload_0
       5: new           #2                  // class java/util/concurrent/ConcurrentHashMap
       8: dup
       9: invokespecial #3                  // Method java/util/concurrent/ConcurrentHashMap."<init>":()V
      12: putfield      #4                  // Field registerStatus:Ljava/util/concurrent/ConcurrentMap;
      15: aload_0
      16: new           #2                  // class java/util/concurrent/ConcurrentHashMap
      19: dup
      20: invokespecial #3                  // Method java/util/concurrent/ConcurrentHashMap."<init>":()V
      23: putfield      #5                  // Field subscribeStatus:Ljava/util/concurrent/ConcurrentMap;
      26: aload_0
      27: aload_1
      28: putfield      #6                  // Field nacosConnectionManager:Lorg/apache/dubbo/registry/nacos/NacosConnectionManager;
      31: aload_0
      32: iload_2
      33: putfield      #13                 // Field isSupportBatchRegister:Z
      36: aload_0
      37: iload_3
      38: iconst_0
      39: invokestatic  #22                 // Method java/lang/Math.max:(II)I
      42: putfield      #23                 // Field retryTimes:I
      45: aload_0
      46: iload         4
      48: putfield      #24                 // Field sleepMsBetweenRetries:I
      51: return

  public java.lang.String getServerStatus();
    Code:
       0: aload_0
       1: getfield      #6                  // Field nacosConnectionManager:Lorg/apache/dubbo/registry/nacos/NacosConnectionManager;
       4: invokevirtual #25                 // Method org/apache/dubbo/registry/nacos/NacosConnectionManager.getNamingService:()Lcom/alibaba/nacos/api/naming/NamingService;
       7: invokeinterface #26,  1           // InterfaceMethod com/alibaba/nacos/api/naming/NamingService.getServerStatus:()Ljava/lang/String;
      12: areturn

  public void subscribe(java.lang.String, java.lang.String, com.alibaba.nacos.api.naming.listener.EventListener) throws com.alibaba.nacos.api.exception.NacosException;
    Code:
       0: aload_0
       1: aload_1
       2: invokespecial #27                 // Method handleInnerSymbol:(Ljava/lang/String;)Ljava/lang/String;
       5: astore        4
       7: new           #28                 // class org/apache/dubbo/registry/nacos/NacosNamingServiceWrapper$SubscribeInfo
      10: dup
      11: aload         4
      13: aload_2
      14: aload_3
      15: invokespecial #29                 // Method org/apache/dubbo/registry/nacos/NacosNamingServiceWrapper$SubscribeInfo."<init>":(Ljava/lang/String;Ljava/lang/String;Lcom/alibaba/nacos/api/naming/listener/EventListener;)V
      18: astore        5
      20: aload_0
      21: getfield      #5                  // Field subscribeStatus:Ljava/util/concurrent/ConcurrentMap;
      24: aload         5
      26: aload_0
      27: invokedynamic #30,  0             // InvokeDynamic #0:apply:(Lorg/apache/dubbo/registry/nacos/NacosNamingServiceWrapper;)Ljava/util/function/Function;
      32: invokestatic  #31                 // Method org/apache/dubbo/common/utils/ConcurrentHashMapUtils.computeIfAbsent:(Ljava/util/concurrent/ConcurrentMap;Ljava/lang/Object;Ljava/util/function/Function;)Ljava/lang/Object;
      35: checkcast     #7                  // class com/alibaba/nacos/api/naming/NamingService
      38: astore        6
      40: aload_0
      41: aload         6
      43: aload         4
      45: aload_2
      46: aload_3
      47: invokedynamic #32,  0             // InvokeDynamic #1:accept:(Lcom/alibaba/nacos/api/naming/NamingService;Ljava/lang/String;Ljava/lang/String;Lcom/alibaba/nacos/api/naming/listener/EventListener;)Lorg/apache/dubbo/registry/nacos/function/NacosConsumer;
      52: invokespecial #33                 // Method accept:(Lorg/apache/dubbo/registry/nacos/function/NacosConsumer;)V
      55: return

  public void unsubscribe(java.lang.String, java.lang.String, com.alibaba.nacos.api.naming.listener.EventListener) throws com.alibaba.nacos.api.exception.NacosException;
    Code:
       0: aload_0
       1: aload_1
       2: invokespecial #27                 // Method handleInnerSymbol:(Ljava/lang/String;)Ljava/lang/String;
       5: astore        4
       7: new           #28                 // class org/apache/dubbo/registry/nacos/NacosNamingServiceWrapper$SubscribeInfo
      10: dup
      11: aload         4
      13: aload_2
      14: aload_3
      15: invokespecial #29                 // Method org/apache/dubbo/registry/nacos/NacosNamingServiceWrapper$SubscribeInfo."<init>":(Ljava/lang/String;Ljava/lang/String;Lcom/alibaba/nacos/api/naming/listener/EventListener;)V
      18: astore        5
      20: aload_0
      21: getfield      #5                  // Field subscribeStatus:Ljava/util/concurrent/ConcurrentMap;
      24: aload         5
      26: invokeinterface #34,  2           // InterfaceMethod java/util/concurrent/ConcurrentMap.get:(Ljava/lang/Object;)Ljava/lang/Object;
      31: checkcast     #7                  // class com/alibaba/nacos/api/naming/NamingService
      34: astore        6
      36: aload         6
      38: ifnull        68
      41: aload_0
      42: aload         6
      44: aload         4
      46: aload_2
      47: aload_3
      48: invokedynamic #35,  0             // InvokeDynamic #2:accept:(Lcom/alibaba/nacos/api/naming/NamingService;Ljava/lang/String;Ljava/lang/String;Lcom/alibaba/nacos/api/naming/listener/EventListener;)Lorg/apache/dubbo/registry/nacos/function/NacosConsumer;
      53: invokespecial #33                 // Method accept:(Lorg/apache/dubbo/registry/nacos/function/NacosConsumer;)V
      56: aload_0
      57: getfield      #5                  // Field subscribeStatus:Ljava/util/concurrent/ConcurrentMap;
      60: aload         5
      62: invokeinterface #36,  2           // InterfaceMethod java/util/concurrent/ConcurrentMap.remove:(Ljava/lang/Object;)Ljava/lang/Object;
      67: pop
      68: return

  public java.util.List<com.alibaba.nacos.api.naming.pojo.Instance> getAllInstances(java.lang.String, java.lang.String) throws com.alibaba.nacos.api.exception.NacosException;
    Code:
       0: aload_0
       1: aload_0
       2: aload_1
       3: aload_2
       4: invokedynamic #37,  0             // InvokeDynamic #3:apply:(Lorg/apache/dubbo/registry/nacos/NacosNamingServiceWrapper;Ljava/lang/String;Ljava/lang/String;)Lorg/apache/dubbo/registry/nacos/function/NacosFunction;
       9: invokespecial #38                 // Method apply:(Lorg/apache/dubbo/registry/nacos/function/NacosFunction;)Ljava/lang/Object;
      12: checkcast     #11                 // class java/util/List
      15: areturn

  public void registerInstance(java.lang.String, java.lang.String, com.alibaba.nacos.api.naming.pojo.Instance) throws com.alibaba.nacos.api.exception.NacosException;
    Code:
       0: aload_0
       1: aload_1
       2: invokespecial #27                 // Method handleInnerSymbol:(Ljava/lang/String;)Ljava/lang/String;
       5: astore        4
       7: aload_0
       8: getfield      #4                  // Field registerStatus:Ljava/util/concurrent/ConcurrentMap;
      11: new           #39                 // class org/apache/dubbo/registry/nacos/NacosNamingServiceWrapper$InstanceId
      14: dup
      15: aload         4
      17: aload_2
      18: invokespecial #40                 // Method org/apache/dubbo/registry/nacos/NacosNamingServiceWrapper$InstanceId."<init>":(Ljava/lang/String;Ljava/lang/String;)V
      21: invokedynamic #41,  0             // InvokeDynamic #4:apply:()Ljava/util/function/Function;
      26: invokestatic  #31                 // Method org/apache/dubbo/common/utils/ConcurrentHashMapUtils.computeIfAbsent:(Ljava/util/concurrent/ConcurrentMap;Ljava/lang/Object;Ljava/util/function/Function;)Ljava/lang/Object;
      29: checkcast     #42                 // class org/apache/dubbo/registry/nacos/NacosNamingServiceWrapper$InstancesInfo
      32: astore        5
      34: aload         5
      36: invokevirtual #43                 // Method org/apache/dubbo/registry/nacos/NacosNamingServiceWrapper$InstancesInfo.lock:()V
      39: aload         5
      41: invokevirtual #44                 // Method org/apache/dubbo/registry/nacos/NacosNamingServiceWrapper$InstancesInfo.isValid:()Z
      44: ifne          60
      47: aload_0
      48: aload_1
      49: aload_2
      50: aload_3
      51: invokevirtual #45                 // Method registerInstance:(Ljava/lang/String;Ljava/lang/String;Lcom/alibaba/nacos/api/naming/pojo/Instance;)V
      54: aload         5
      56: invokevirtual #46                 // Method org/apache/dubbo/registry/nacos/NacosNamingServiceWrapper$InstancesInfo.unlock:()V
      59: return
      60: aload         5
      62: invokevirtual #47                 // Method org/apache/dubbo/registry/nacos/NacosNamingServiceWrapper$InstancesInfo.getInstances:()Ljava/util/List;
      65: invokeinterface #48,  1           // InterfaceMethod java/util/List.isEmpty:()Z
      70: ifeq          124
      73: aload_0
      74: getfield      #6                  // Field nacosConnectionManager:Lorg/apache/dubbo/registry/nacos/NacosConnectionManager;
      77: invokevirtual #25                 // Method org/apache/dubbo/registry/nacos/NacosConnectionManager.getNamingService:()Lcom/alibaba/nacos/api/naming/NamingService;
      80: astore        6
      82: aload_0
      83: aload         6
      85: aload         4
      87: aload_2
      88: aload_3
      89: invokedynamic #49,  0             // InvokeDynamic #5:accept:(Lcom/alibaba/nacos/api/naming/NamingService;Ljava/lang/String;Ljava/lang/String;Lcom/alibaba/nacos/api/naming/pojo/Instance;)Lorg/apache/dubbo/registry/nacos/function/NacosConsumer;
      94: invokespecial #33                 // Method accept:(Lorg/apache/dubbo/registry/nacos/function/NacosConsumer;)V
      97: aload         5
      99: invokevirtual #47                 // Method org/apache/dubbo/registry/nacos/NacosNamingServiceWrapper$InstancesInfo.getInstances:()Ljava/util/List;
     102: new           #50                 // class org/apache/dubbo/registry/nacos/NacosNamingServiceWrapper$InstanceInfo
     105: dup
     106: aload_3
     107: aload         6
     109: invokespecial #51                 // Method org/apache/dubbo/registry/nacos/NacosNamingServiceWrapper$InstanceInfo."<init>":(Lcom/alibaba/nacos/api/naming/pojo/Instance;Lcom/alibaba/nacos/api/naming/NamingService;)V
     112: invokeinterface #52,  2           // InterfaceMethod java/util/List.add:(Ljava/lang/Object;)Z
     117: pop
     118: aload         5
     120: invokevirtual #46                 // Method org/apache/dubbo/registry/nacos/NacosNamingServiceWrapper$InstancesInfo.unlock:()V
     123: return
     124: aload         5
     126: invokevirtual #47                 // Method org/apache/dubbo/registry/nacos/NacosNamingServiceWrapper$InstancesInfo.getInstances:()Ljava/util/List;
     129: invokeinterface #53,  1           // InterfaceMethod java/util/List.size:()I
     134: iconst_1
     135: if_icmpne     282
     138: aload_0
     139: getfield      #13                 // Field isSupportBatchRegister:Z
     142: ifeq          282
     145: aload         5
     147: invokevirtual #47                 // Method org/apache/dubbo/registry/nacos/NacosNamingServiceWrapper$InstancesInfo.getInstances:()Ljava/util/List;
     150: iconst_0
     151: invokeinterface #54,  2           // InterfaceMethod java/util/List.get:(I)Ljava/lang/Object;
     156: checkcast     #50                 // class org/apache/dubbo/registry/nacos/NacosNamingServiceWrapper$InstanceInfo
     159: astore        6
     161: new           #55                 // class java/util/ArrayList
     164: dup
     165: invokespecial #56                 // Method java/util/ArrayList."<init>":()V
     168: astore        7
     170: aload         6
     172: invokevirtual #57                 // Method org/apache/dubbo/registry/nacos/NacosNamingServiceWrapper$InstanceInfo.getNamingService:()Lcom/alibaba/nacos/api/naming/NamingService;
     175: astore        8
     177: aload         7
     179: aload         6
     181: invokevirtual #58                 // Method org/apache/dubbo/registry/nacos/NacosNamingServiceWrapper$InstanceInfo.getInstance:()Lcom/alibaba/nacos/api/naming/pojo/Instance;
     184: invokeinterface #52,  2           // InterfaceMethod java/util/List.add:(Ljava/lang/Object;)Z
     189: pop
     190: aload         7
     192: aload_3
     193: invokeinterface #52,  2           // InterfaceMethod java/util/List.add:(Ljava/lang/Object;)Z
     198: pop
     199: aload_0
     200: aload         8
     202: aload         4
     204: aload_2
     205: aload         7
     207: invokedynamic #59,  0             // InvokeDynamic #6:accept:(Lcom/alibaba/nacos/api/naming/NamingService;Ljava/lang/String;Ljava/lang/String;Ljava/util/List;)Lorg/apache/dubbo/registry/nacos/function/NacosConsumer;
     212: invokespecial #33                 // Method accept:(Lorg/apache/dubbo/registry/nacos/function/NacosConsumer;)V
     215: aload         5
     217: invokevirtual #47                 // Method org/apache/dubbo/registry/nacos/NacosNamingServiceWrapper$InstancesInfo.getInstances:()Ljava/util/List;
     220: new           #50                 // class org/apache/dubbo/registry/nacos/NacosNamingServiceWrapper$InstanceInfo
     223: dup
     224: aload_3
     225: aload         8
     227: invokespecial #51                 // Method org/apache/dubbo/registry/nacos/NacosNamingServiceWrapper$InstanceInfo."<init>":(Lcom/alibaba/nacos/api/naming/pojo/Instance;Lcom/alibaba/nacos/api/naming/NamingService;)V
     230: invokeinterface #52,  2           // InterfaceMethod java/util/List.add:(Ljava/lang/Object;)Z
     235: pop
     236: aload         5
     238: iconst_1
     239: invokevirtual #60                 // Method org/apache/dubbo/registry/nacos/NacosNamingServiceWrapper$InstancesInfo.setBatchRegistered:(Z)V
     242: aload         5
     244: invokevirtual #46                 // Method org/apache/dubbo/registry/nacos/NacosNamingServiceWrapper$InstancesInfo.unlock:()V
     247: return
     248: astore        9
     250: getstatic     #14                 // Field logger:Lorg/apache/dubbo/common/logger/ErrorTypeAwareLogger;
     253: new           #15                 // class java/lang/StringBuilder
     256: dup
     257: invokespecial #16                 // Method java/lang/StringBuilder."<init>":()V
     260: ldc           #62                 // String Failed to batch register to nacos. Service Name:
     262: invokevirtual #18                 // Method java/lang/StringBuilder.append:(Ljava/lang/String;)Ljava/lang/StringBuilder;
     265: aload_1
     266: invokevirtual #18                 // Method java/lang/StringBuilder.append:(Ljava/lang/String;)Ljava/lang/StringBuilder;
     269: ldc           #63                 // String . Maybe nacos server not support. Will fallback to multi connection register.
     271: invokevirtual #18                 // Method java/lang/StringBuilder.append:(Ljava/lang/String;)Ljava/lang/StringBuilder;
     274: invokevirtual #20                 // Method java/lang/StringBuilder.toString:()Ljava/lang/String;
     277: invokeinterface #21,  2           // InterfaceMethod org/apache/dubbo/common/logger/ErrorTypeAwareLogger.info:(Ljava/lang/String;)V
     282: aload         5
     284: invokevirtual #64                 // Method org/apache/dubbo/registry/nacos/NacosNamingServiceWrapper$InstancesInfo.isBatchRegistered:()Z
     287: ifeq          420
     290: aload         5
     292: invokevirtual #47                 // Method org/apache/dubbo/registry/nacos/NacosNamingServiceWrapper$InstancesInfo.getInstances:()Ljava/util/List;
     295: iconst_0
     296: invokeinterface #54,  2           // InterfaceMethod java/util/List.get:(I)Ljava/lang/Object;
     301: checkcast     #50                 // class org/apache/dubbo/registry/nacos/NacosNamingServiceWrapper$InstanceInfo
     304: invokevirtual #57                 // Method org/apache/dubbo/registry/nacos/NacosNamingServiceWrapper$InstanceInfo.getNamingService:()Lcom/alibaba/nacos/api/naming/NamingService;
     307: astore        6
     309: new           #55                 // class java/util/ArrayList
     312: dup
     313: invokespecial #56                 // Method java/util/ArrayList."<init>":()V
     316: astore        7
     318: aload         5
     320: invokevirtual #47                 // Method org/apache/dubbo/registry/nacos/NacosNamingServiceWrapper$InstancesInfo.getInstances:()Ljava/util/List;
     323: invokeinterface #65,  1           // InterfaceMethod java/util/List.iterator:()Ljava/util/Iterator;
     328: astore        8
     330: aload         8
     332: invokeinterface #66,  1           // InterfaceMethod java/util/Iterator.hasNext:()Z
     337: ifeq          368
     340: aload         8
     342: invokeinterface #67,  1           // InterfaceMethod java/util/Iterator.next:()Ljava/lang/Object;
     347: checkcast     #50                 // class org/apache/dubbo/registry/nacos/NacosNamingServiceWrapper$InstanceInfo
     350: astore        9
     352: aload         7
     354: aload         9
     356: invokevirtual #58                 // Method org/apache/dubbo/registry/nacos/NacosNamingServiceWrapper$InstanceInfo.getInstance:()Lcom/alibaba/nacos/api/naming/pojo/Instance;
     359: invokeinterface #52,  2           // InterfaceMethod java/util/List.add:(Ljava/lang/Object;)Z
     364: pop
     365: goto          330
     368: aload         7
     370: aload_3
     371: invokeinterface #52,  2           // InterfaceMethod java/util/List.add:(Ljava/lang/Object;)Z
     376: pop
     377: aload_0
     378: aload         6
     380: aload         4
     382: aload_2
     383: aload         7
     385: invokedynamic #68,  0             // InvokeDynamic #7:accept:(Lcom/alibaba/nacos/api/naming/NamingService;Ljava/lang/String;Ljava/lang/String;Ljava/util/List;)Lorg/apache/dubbo/registry/nacos/function/NacosConsumer;
     390: invokespecial #33                 // Method accept:(Lorg/apache/dubbo/registry/nacos/function/NacosConsumer;)V
     393: aload         5
     395: invokevirtual #47                 // Method org/apache/dubbo/registry/nacos/NacosNamingServiceWrapper$InstancesInfo.getInstances:()Ljava/util/List;
     398: new           #50                 // class org/apache/dubbo/registry/nacos/NacosNamingServiceWrapper$InstanceInfo
     401: dup
     402: aload_3
     403: aload         6
     405: invokespecial #51                 // Method org/apache/dubbo/registry/nacos/NacosNamingServiceWrapper$InstanceInfo."<init>":(Lcom/alibaba/nacos/api/naming/pojo/Instance;Lcom/alibaba/nacos/api/naming/NamingService;)V
     408: invokeinterface #52,  2           // InterfaceMethod java/util/List.add:(Ljava/lang/Object;)Z
     413: pop
     414: aload         5
     416: invokevirtual #46                 // Method org/apache/dubbo/registry/nacos/NacosNamingServiceWrapper$InstancesInfo.unlock:()V
     419: return
     420: aload         5
     422: invokevirtual #47                 // Method org/apache/dubbo/registry/nacos/NacosNamingServiceWrapper$InstancesInfo.getInstances:()Ljava/util/List;
     425: invokeinterface #69,  1           // InterfaceMethod java/util/List.stream:()Ljava/util/stream/Stream;
     430: invokedynamic #70,  0             // InvokeDynamic #8:apply:()Ljava/util/function/Function;
     435: invokeinterface #71,  2           // InterfaceMethod java/util/stream/Stream.map:(Ljava/util/function/Function;)Ljava/util/stream/Stream;
     440: invokestatic  #72                 // Method java/util/stream/Collectors.toSet:()Ljava/util/stream/Collector;
     443: invokeinterface #73,  2           // InterfaceMethod java/util/stream/Stream.collect:(Ljava/util/stream/Collector;)Ljava/lang/Object;
     448: checkcast     #74                 // class java/util/Set
     451: astore        6
     453: aload_0
     454: getfield      #6                  // Field nacosConnectionManager:Lorg/apache/dubbo/registry/nacos/NacosConnectionManager;
     457: aload         6
     459: invokevirtual #75                 // Method org/apache/dubbo/registry/nacos/NacosConnectionManager.getNamingService:(Ljava/util/Set;)Lcom/alibaba/nacos/api/naming/NamingService;
     462: astore        7
     464: aload_0
     465: aload         7
     467: aload         4
     469: aload_2
     470: aload_3
     471: invokedynamic #76,  0             // InvokeDynamic #9:accept:(Lcom/alibaba/nacos/api/naming/NamingService;Ljava/lang/String;Ljava/lang/String;Lcom/alibaba/nacos/api/naming/pojo/Instance;)Lorg/apache/dubbo/registry/nacos/function/NacosConsumer;
     476: invokespecial #33                 // Method accept:(Lorg/apache/dubbo/registry/nacos/function/NacosConsumer;)V
     479: aload         5
     481: invokevirtual #47                 // Method org/apache/dubbo/registry/nacos/NacosNamingServiceWrapper$InstancesInfo.getInstances:()Ljava/util/List;
     484: new           #50                 // class org/apache/dubbo/registry/nacos/NacosNamingServiceWrapper$InstanceInfo
     487: dup
     488: aload_3
     489: aload         7
     491: invokespecial #51                 // Method org/apache/dubbo/registry/nacos/NacosNamingServiceWrapper$InstanceInfo."<init>":(Lcom/alibaba/nacos/api/naming/pojo/Instance;Lcom/alibaba/nacos/api/naming/NamingService;)V
     494: invokeinterface #52,  2           // InterfaceMethod java/util/List.add:(Ljava/lang/Object;)Z
     499: pop
     500: aload         5
     502: invokevirtual #46                 // Method org/apache/dubbo/registry/nacos/NacosNamingServiceWrapper$InstancesInfo.unlock:()V
     505: goto          518
     508: astore        10
     510: aload         5
     512: invokevirtual #46                 // Method org/apache/dubbo/registry/nacos/NacosNamingServiceWrapper$InstancesInfo.unlock:()V
     515: aload         10
     517: athrow
     518: return
    Exception table:
       from    to  target type
         199   242   248   Class com/alibaba/nacos/api/exception/NacosException
          34    54   508   any
          60   118   508   any
         124   242   508   any
         248   414   508   any
         420   500   508   any
         508   510   508   any

  public void updateInstance(java.lang.String, java.lang.String, com.alibaba.nacos.api.naming.pojo.Instance, com.alibaba.nacos.api.naming.pojo.Instance) throws com.alibaba.nacos.api.exception.NacosException;
    Code:
       0: aload_0
       1: aload_1
       2: invokespecial #27                 // Method handleInnerSymbol:(Ljava/lang/String;)Ljava/lang/String;
       5: astore        5
       7: aload_0
       8: getfield      #4                  // Field registerStatus:Ljava/util/concurrent/ConcurrentMap;
      11: new           #39                 // class org/apache/dubbo/registry/nacos/NacosNamingServiceWrapper$InstanceId
      14: dup
      15: aload         5
      17: aload_2
      18: invokespecial #40                 // Method org/apache/dubbo/registry/nacos/NacosNamingServiceWrapper$InstanceId."<init>":(Ljava/lang/String;Ljava/lang/String;)V
      21: invokedynamic #77,  0             // InvokeDynamic #10:apply:()Ljava/util/function/Function;
      26: invokestatic  #31                 // Method org/apache/dubbo/common/utils/ConcurrentHashMapUtils.computeIfAbsent:(Ljava/util/concurrent/ConcurrentMap;Ljava/lang/Object;Ljava/util/function/Function;)Ljava/lang/Object;
      29: checkcast     #42                 // class org/apache/dubbo/registry/nacos/NacosNamingServiceWrapper$InstancesInfo
      32: astore        6
      34: aload         6
      36: invokevirtual #43                 // Method org/apache/dubbo/registry/nacos/NacosNamingServiceWrapper$InstancesInfo.lock:()V
      39: aload         6
      41: invokevirtual #44                 // Method org/apache/dubbo/registry/nacos/NacosNamingServiceWrapper$InstancesInfo.isValid:()Z
      44: ifeq          60
      47: aload         6
      49: invokevirtual #47                 // Method org/apache/dubbo/registry/nacos/NacosNamingServiceWrapper$InstancesInfo.getInstances:()Ljava/util/List;
      52: invokeinterface #48,  1           // InterfaceMethod java/util/List.isEmpty:()Z
      57: ifeq          87
      60: new           #78                 // class java/lang/IllegalArgumentException
      63: dup
      64: new           #15                 // class java/lang/StringBuilder
      67: dup
      68: invokespecial #16                 // Method java/lang/StringBuilder."<init>":()V
      71: aload_1
      72: invokevirtual #18                 // Method java/lang/StringBuilder.append:(Ljava/lang/String;)Ljava/lang/StringBuilder;
      75: ldc           #79                 // String  has not been registered to nacos.
      77: invokevirtual #18                 // Method java/lang/StringBuilder.append:(Ljava/lang/String;)Ljava/lang/StringBuilder;
      80: invokevirtual #20                 // Method java/lang/StringBuilder.toString:()Ljava/lang/String;
      83: invokespecial #80                 // Method java/lang/IllegalArgumentException."<init>":(Ljava/lang/String;)V
      86: athrow
      87: aload         6
      89: invokevirtual #47                 // Method org/apache/dubbo/registry/nacos/NacosNamingServiceWrapper$InstancesInfo.getInstances:()Ljava/util/List;
      92: invokeinterface #69,  1           // InterfaceMethod java/util/List.stream:()Ljava/util/stream/Stream;
      97: aload_3
      98: invokedynamic #81,  0             // InvokeDynamic #11:test:(Lcom/alibaba/nacos/api/naming/pojo/Instance;)Ljava/util/function/Predicate;
     103: invokeinterface #82,  2           // InterfaceMethod java/util/stream/Stream.filter:(Ljava/util/function/Predicate;)Ljava/util/stream/Stream;
     108: invokeinterface #83,  1           // InterfaceMethod java/util/stream/Stream.findAny:()Ljava/util/Optional;
     113: astore        7
     115: aload         7
     117: invokevirtual #84                 // Method java/util/Optional.isPresent:()Z
     120: ifne          150
     123: new           #78                 // class java/lang/IllegalArgumentException
     126: dup
     127: new           #15                 // class java/lang/StringBuilder
     130: dup
     131: invokespecial #16                 // Method java/lang/StringBuilder."<init>":()V
     134: aload_3
     135: invokevirtual #85                 // Method java/lang/StringBuilder.append:(Ljava/lang/Object;)Ljava/lang/StringBuilder;
     138: ldc           #79                 // String  has not been registered to nacos.
     140: invokevirtual #18                 // Method java/lang/StringBuilder.append:(Ljava/lang/String;)Ljava/lang/StringBuilder;
     143: invokevirtual #20                 // Method java/lang/StringBuilder.toString:()Ljava/lang/String;
     146: invokespecial #80                 // Method java/lang/IllegalArgumentException."<init>":(Ljava/lang/String;)V
     149: athrow
     150: aload         7
     152: invokevirtual #86                 // Method java/util/Optional.get:()Ljava/lang/Object;
     155: checkcast     #50                 // class org/apache/dubbo/registry/nacos/NacosNamingServiceWrapper$InstanceInfo
     158: astore        8
     160: aload         6
     162: invokevirtual #47                 // Method org/apache/dubbo/registry/nacos/NacosNamingServiceWrapper$InstancesInfo.getInstances:()Ljava/util/List;
     165: aload         8
     167: invokeinterface #87,  2           // InterfaceMethod java/util/List.remove:(Ljava/lang/Object;)Z
     172: pop
     173: aload         6
     175: invokevirtual #47                 // Method org/apache/dubbo/registry/nacos/NacosNamingServiceWrapper$InstancesInfo.getInstances:()Ljava/util/List;
     178: new           #50                 // class org/apache/dubbo/registry/nacos/NacosNamingServiceWrapper$InstanceInfo
     181: dup
     182: aload         4
     184: aload         8
     186: invokevirtual #57                 // Method org/apache/dubbo/registry/nacos/NacosNamingServiceWrapper$InstanceInfo.getNamingService:()Lcom/alibaba/nacos/api/naming/NamingService;
     189: invokespecial #51                 // Method org/apache/dubbo/registry/nacos/NacosNamingServiceWrapper$InstanceInfo."<init>":(Lcom/alibaba/nacos/api/naming/pojo/Instance;Lcom/alibaba/nacos/api/naming/NamingService;)V
     192: invokeinterface #52,  2           // InterfaceMethod java/util/List.add:(Ljava/lang/Object;)Z
     197: pop
     198: aload_0
     199: getfield      #13                 // Field isSupportBatchRegister:Z
     202: ifeq          275
     205: aload         6
     207: invokevirtual #64                 // Method org/apache/dubbo/registry/nacos/NacosNamingServiceWrapper$InstancesInfo.isBatchRegistered:()Z
     210: ifeq          275
     213: aload         8
     215: invokevirtual #57                 // Method org/apache/dubbo/registry/nacos/NacosNamingServiceWrapper$InstanceInfo.getNamingService:()Lcom/alibaba/nacos/api/naming/NamingService;
     218: astore        9
     220: aload         6
     222: invokevirtual #47                 // Method org/apache/dubbo/registry/nacos/NacosNamingServiceWrapper$InstancesInfo.getInstances:()Ljava/util/List;
     225: invokeinterface #69,  1           // InterfaceMethod java/util/List.stream:()Ljava/util/stream/Stream;
     230: invokedynamic #88,  0             // InvokeDynamic #12:apply:()Ljava/util/function/Function;
     235: invokeinterface #71,  2           // InterfaceMethod java/util/stream/Stream.map:(Ljava/util/function/Function;)Ljava/util/stream/Stream;
     240: invokestatic  #89                 // Method java/util/stream/Collectors.toList:()Ljava/util/stream/Collector;
     243: invokeinterface #73,  2           // InterfaceMethod java/util/stream/Stream.collect:(Ljava/util/stream/Collector;)Ljava/lang/Object;
     248: checkcast     #11                 // class java/util/List
     251: astore        10
     253: aload_0
     254: aload         9
     256: aload         5
     258: aload_2
     259: aload         10
     261: invokedynamic #90,  0             // InvokeDynamic #13:accept:(Lcom/alibaba/nacos/api/naming/NamingService;Ljava/lang/String;Ljava/lang/String;Ljava/util/List;)Lorg/apache/dubbo/registry/nacos/function/NacosConsumer;
     266: invokespecial #33                 // Method accept:(Lorg/apache/dubbo/registry/nacos/function/NacosConsumer;)V
     269: aload         6
     271: invokevirtual #46                 // Method org/apache/dubbo/registry/nacos/NacosNamingServiceWrapper$InstancesInfo.unlock:()V
     274: return
     275: aload_0
     276: aload         8
     278: aload         5
     280: aload_2
     281: aload         4
     283: invokedynamic #91,  0             // InvokeDynamic #14:accept:(Lorg/apache/dubbo/registry/nacos/NacosNamingServiceWrapper$InstanceInfo;Ljava/lang/String;Ljava/lang/String;Lcom/alibaba/nacos/api/naming/pojo/Instance;)Lorg/apache/dubbo/registry/nacos/function/NacosConsumer;
     288: invokespecial #33                 // Method accept:(Lorg/apache/dubbo/registry/nacos/function/NacosConsumer;)V
     291: aload         6
     293: invokevirtual #46                 // Method org/apache/dubbo/registry/nacos/NacosNamingServiceWrapper$InstancesInfo.unlock:()V
     296: goto          309
     299: astore        11
     301: aload         6
     303: invokevirtual #46                 // Method org/apache/dubbo/registry/nacos/NacosNamingServiceWrapper$InstancesInfo.unlock:()V
     306: aload         11
     308: athrow
     309: return
    Exception table:
       from    to  target type
          34   269   299   any
         275   291   299   any
         299   301   299   any

  public void deregisterInstance(java.lang.String, java.lang.String, java.lang.String, int) throws com.alibaba.nacos.api.exception.NacosException;
    Code:
       0: aload_0
       1: aload_1
       2: invokespecial #27                 // Method handleInnerSymbol:(Ljava/lang/String;)Ljava/lang/String;
       5: astore        5
       7: aload_0
       8: getfield      #4                  // Field registerStatus:Ljava/util/concurrent/ConcurrentMap;
      11: new           #39                 // class org/apache/dubbo/registry/nacos/NacosNamingServiceWrapper$InstanceId
      14: dup
      15: aload         5
      17: aload_2
      18: invokespecial #40                 // Method org/apache/dubbo/registry/nacos/NacosNamingServiceWrapper$InstanceId."<init>":(Ljava/lang/String;Ljava/lang/String;)V
      21: invokedynamic #92,  0             // InvokeDynamic #15:apply:()Ljava/util/function/Function;
      26: invokestatic  #31                 // Method org/apache/dubbo/common/utils/ConcurrentHashMapUtils.computeIfAbsent:(Ljava/util/concurrent/ConcurrentMap;Ljava/lang/Object;Ljava/util/function/Function;)Ljava/lang/Object;
      29: checkcast     #42                 // class org/apache/dubbo/registry/nacos/NacosNamingServiceWrapper$InstancesInfo
      32: astore        6
      34: aload         6
      36: invokevirtual #43                 // Method org/apache/dubbo/registry/nacos/NacosNamingServiceWrapper$InstancesInfo.lock:()V
      39: aload         6
      41: invokevirtual #47                 // Method org/apache/dubbo/registry/nacos/NacosNamingServiceWrapper$InstancesInfo.getInstances:()Ljava/util/List;
      44: invokeinterface #69,  1           // InterfaceMethod java/util/List.stream:()Ljava/util/stream/Stream;
      49: invokedynamic #88,  0             // InvokeDynamic #12:apply:()Ljava/util/function/Function;
      54: invokeinterface #71,  2           // InterfaceMethod java/util/stream/Stream.map:(Ljava/util/function/Function;)Ljava/util/stream/Stream;
      59: aload_3
      60: iload         4
      62: invokedynamic #93,  0             // InvokeDynamic #16:test:(Ljava/lang/String;I)Ljava/util/function/Predicate;
      67: invokeinterface #82,  2           // InterfaceMethod java/util/stream/Stream.filter:(Ljava/util/function/Predicate;)Ljava/util/stream/Stream;
      72: invokestatic  #89                 // Method java/util/stream/Collectors.toList:()Ljava/util/stream/Collector;
      75: invokeinterface #73,  2           // InterfaceMethod java/util/stream/Stream.collect:(Ljava/util/stream/Collector;)Ljava/lang/Object;
      80: checkcast     #11                 // class java/util/List
      83: astore        7
      85: aload         7
      87: invokeinterface #65,  1           // InterfaceMethod java/util/List.iterator:()Ljava/util/Iterator;
      92: astore        8
      94: aload         8
      96: invokeinterface #66,  1           // InterfaceMethod java/util/Iterator.hasNext:()Z
     101: ifeq          127
     104: aload         8
     106: invokeinterface #67,  1           // InterfaceMethod java/util/Iterator.next:()Ljava/lang/Object;
     111: checkcast     #94                 // class com/alibaba/nacos/api/naming/pojo/Instance
     114: astore        9
     116: aload_0
     117: aload_1
     118: aload_2
     119: aload         9
     121: invokevirtual #95                 // Method deregisterInstance:(Ljava/lang/String;Ljava/lang/String;Lcom/alibaba/nacos/api/naming/pojo/Instance;)V
     124: goto          94
     127: aload         6
     129: invokevirtual #46                 // Method org/apache/dubbo/registry/nacos/NacosNamingServiceWrapper$InstancesInfo.unlock:()V
     132: goto          145
     135: astore        10
     137: aload         6
     139: invokevirtual #46                 // Method org/apache/dubbo/registry/nacos/NacosNamingServiceWrapper$InstancesInfo.unlock:()V
     142: aload         10
     144: athrow
     145: return
    Exception table:
       from    to  target type
          34   127   135   any
         135   137   135   any

  public void deregisterInstance(java.lang.String, java.lang.String, com.alibaba.nacos.api.naming.pojo.Instance) throws com.alibaba.nacos.api.exception.NacosException;
    Code:
       0: aload_0
       1: aload_1
       2: invokespecial #27                 // Method handleInnerSymbol:(Ljava/lang/String;)Ljava/lang/String;
       5: astore        4
       7: aload_0
       8: getfield      #4                  // Field registerStatus:Ljava/util/concurrent/ConcurrentMap;
      11: new           #39                 // class org/apache/dubbo/registry/nacos/NacosNamingServiceWrapper$InstanceId
      14: dup
      15: aload         4
      17: aload_2
      18: invokespecial #40                 // Method org/apache/dubbo/registry/nacos/NacosNamingServiceWrapper$InstanceId."<init>":(Ljava/lang/String;Ljava/lang/String;)V
      21: invokedynamic #96,  0             // InvokeDynamic #17:apply:()Ljava/util/function/Function;
      26: invokestatic  #31                 // Method org/apache/dubbo/common/utils/ConcurrentHashMapUtils.computeIfAbsent:(Ljava/util/concurrent/ConcurrentMap;Ljava/lang/Object;Ljava/util/function/Function;)Ljava/lang/Object;
      29: checkcast     #42                 // class org/apache/dubbo/registry/nacos/NacosNamingServiceWrapper$InstancesInfo
      32: astore        5
      34: aload         5
      36: invokevirtual #43                 // Method org/apache/dubbo/registry/nacos/NacosNamingServiceWrapper$InstancesInfo.lock:()V
      39: aload         5
      41: invokevirtual #47                 // Method org/apache/dubbo/registry/nacos/NacosNamingServiceWrapper$InstancesInfo.getInstances:()Ljava/util/List;
      44: invokeinterface #69,  1           // InterfaceMethod java/util/List.stream:()Ljava/util/stream/Stream;
      49: aload_3
      50: invokedynamic #97,  0             // InvokeDynamic #18:test:(Lcom/alibaba/nacos/api/naming/pojo/Instance;)Ljava/util/function/Predicate;
      55: invokeinterface #82,  2           // InterfaceMethod java/util/stream/Stream.filter:(Ljava/util/function/Predicate;)Ljava/util/stream/Stream;
      60: invokeinterface #83,  1           // InterfaceMethod java/util/stream/Stream.findAny:()Ljava/util/Optional;
      65: astore        6
      67: aload         6
      69: invokevirtual #84                 // Method java/util/Optional.isPresent:()Z
      72: ifne          81
      75: aload         5
      77: invokevirtual #46                 // Method org/apache/dubbo/registry/nacos/NacosNamingServiceWrapper$InstancesInfo.unlock:()V
      80: return
      81: aload         6
      83: invokevirtual #86                 // Method java/util/Optional.get:()Ljava/lang/Object;
      86: checkcast     #50                 // class org/apache/dubbo/registry/nacos/NacosNamingServiceWrapper$InstanceInfo
      89: astore        7
      91: aload         5
      93: invokevirtual #47                 // Method org/apache/dubbo/registry/nacos/NacosNamingServiceWrapper$InstancesInfo.getInstances:()Ljava/util/List;
      96: aload         7
      98: invokeinterface #87,  2           // InterfaceMethod java/util/List.remove:(Ljava/lang/Object;)Z
     103: pop
     104: aload         5
     106: invokevirtual #47                 // Method org/apache/dubbo/registry/nacos/NacosNamingServiceWrapper$InstancesInfo.getInstances:()Ljava/util/List;
     109: invokeinterface #48,  1           // InterfaceMethod java/util/List.isEmpty:()Z
     114: ifeq          143
     117: aload_0
     118: getfield      #4                  // Field registerStatus:Ljava/util/concurrent/ConcurrentMap;
     121: new           #39                 // class org/apache/dubbo/registry/nacos/NacosNamingServiceWrapper$InstanceId
     124: dup
     125: aload         4
     127: aload_2
     128: invokespecial #40                 // Method org/apache/dubbo/registry/nacos/NacosNamingServiceWrapper$InstanceId."<init>":(Ljava/lang/String;Ljava/lang/String;)V
     131: invokeinterface #36,  2           // InterfaceMethod java/util/concurrent/ConcurrentMap.remove:(Ljava/lang/Object;)Ljava/lang/Object;
     136: pop
     137: aload         5
     139: iconst_0
     140: invokevirtual #98                 // Method org/apache/dubbo/registry/nacos/NacosNamingServiceWrapper$InstancesInfo.setValid:(Z)V
     143: aload         5
     145: invokevirtual #47                 // Method org/apache/dubbo/registry/nacos/NacosNamingServiceWrapper$InstancesInfo.getInstances:()Ljava/util/List;
     148: invokeinterface #48,  1           // InterfaceMethod java/util/List.isEmpty:()Z
     153: ifeq          183
     156: aload_0
     157: aload         7
     159: aload         4
     161: aload_2
     162: aload_3
     163: invokedynamic #99,  0             // InvokeDynamic #19:accept:(Lorg/apache/dubbo/registry/nacos/NacosNamingServiceWrapper$InstanceInfo;Ljava/lang/String;Ljava/lang/String;Lcom/alibaba/nacos/api/naming/pojo/Instance;)Lorg/apache/dubbo/registry/nacos/function/NacosConsumer;
     168: invokespecial #33                 // Method accept:(Lorg/apache/dubbo/registry/nacos/function/NacosConsumer;)V
     171: aload         5
     173: iconst_0
     174: invokevirtual #60                 // Method org/apache/dubbo/registry/nacos/NacosNamingServiceWrapper$InstancesInfo.setBatchRegistered:(Z)V
     177: aload         5
     179: invokevirtual #46                 // Method org/apache/dubbo/registry/nacos/NacosNamingServiceWrapper$InstancesInfo.unlock:()V
     182: return
     183: aload         5
     185: invokevirtual #64                 // Method org/apache/dubbo/registry/nacos/NacosNamingServiceWrapper$InstancesInfo.isBatchRegistered:()Z
     188: ifeq          269
     191: new           #55                 // class java/util/ArrayList
     194: dup
     195: invokespecial #56                 // Method java/util/ArrayList."<init>":()V
     198: astore        8
     200: aload         5
     202: invokevirtual #47                 // Method org/apache/dubbo/registry/nacos/NacosNamingServiceWrapper$InstancesInfo.getInstances:()Ljava/util/List;
     205: invokeinterface #65,  1           // InterfaceMethod java/util/List.iterator:()Ljava/util/Iterator;
     210: astore        9
     212: aload         9
     214: invokeinterface #66,  1           // InterfaceMethod java/util/Iterator.hasNext:()Z
     219: ifeq          250
     222: aload         9
     224: invokeinterface #67,  1           // InterfaceMethod java/util/Iterator.next:()Ljava/lang/Object;
     229: checkcast     #50                 // class org/apache/dubbo/registry/nacos/NacosNamingServiceWrapper$InstanceInfo
     232: astore        10
     234: aload         8
     236: aload         10
     238: invokevirtual #58                 // Method org/apache/dubbo/registry/nacos/NacosNamingServiceWrapper$InstanceInfo.getInstance:()Lcom/alibaba/nacos/api/naming/pojo/Instance;
     241: invokeinterface #52,  2           // InterfaceMethod java/util/List.add:(Ljava/lang/Object;)Z
     246: pop
     247: goto          212
     250: aload_0
     251: aload         7
     253: aload         4
     255: aload_2
     256: aload         8
     258: invokedynamic #100,  0            // InvokeDynamic #20:accept:(Lorg/apache/dubbo/registry/nacos/NacosNamingServiceWrapper$InstanceInfo;Ljava/lang/String;Ljava/lang/String;Ljava/util/List;)Lorg/apache/dubbo/registry/nacos/function/NacosConsumer;
     263: invokespecial #33                 // Method accept:(Lorg/apache/dubbo/registry/nacos/function/NacosConsumer;)V
     266: goto          284
     269: aload_0
     270: aload         7
     272: aload         4
     274: aload_2
     275: aload_3
     276: invokedynamic #101,  0            // InvokeDynamic #21:accept:(Lorg/apache/dubbo/registry/nacos/NacosNamingServiceWrapper$InstanceInfo;Ljava/lang/String;Ljava/lang/String;Lcom/alibaba/nacos/api/naming/pojo/Instance;)Lorg/apache/dubbo/registry/nacos/function/NacosConsumer;
     281: invokespecial #33                 // Method accept:(Lorg/apache/dubbo/registry/nacos/function/NacosConsumer;)V
     284: aload         5
     286: invokevirtual #46                 // Method org/apache/dubbo/registry/nacos/NacosNamingServiceWrapper$InstancesInfo.unlock:()V
     289: goto          302
     292: astore        11
     294: aload         5
     296: invokevirtual #46                 // Method org/apache/dubbo/registry/nacos/NacosNamingServiceWrapper$InstancesInfo.unlock:()V
     299: aload         11
     301: athrow
     302: return
    Exception table:
       from    to  target type
          34    75   292   any
          81   177   292   any
         183   284   292   any
         292   294   292   any

  public com.alibaba.nacos.api.naming.pojo.ListView<java.lang.String> getServicesOfServer(int, int, java.lang.String) throws com.alibaba.nacos.api.exception.NacosException;
    Code:
       0: aload_0
       1: aload_0
       2: iload_1
       3: iload_2
       4: aload_3
       5: invokedynamic #102,  0            // InvokeDynamic #22:apply:(Lorg/apache/dubbo/registry/nacos/NacosNamingServiceWrapper;IILjava/lang/String;)Lorg/apache/dubbo/registry/nacos/function/NacosFunction;
      10: invokespecial #38                 // Method apply:(Lorg/apache/dubbo/registry/nacos/function/NacosFunction;)Ljava/lang/Object;
      13: checkcast     #103                // class com/alibaba/nacos/api/naming/pojo/ListView
      16: areturn

  public java.util.List<com.alibaba.nacos.api.naming.pojo.Instance> selectInstances(java.lang.String, java.lang.String, boolean) throws com.alibaba.nacos.api.exception.NacosException;
    Code:
       0: aload_0
       1: aload_0
       2: aload_1
       3: aload_2
       4: iload_3
       5: invokedynamic #104,  0            // InvokeDynamic #23:apply:(Lorg/apache/dubbo/registry/nacos/NacosNamingServiceWrapper;Ljava/lang/String;Ljava/lang/String;Z)Lorg/apache/dubbo/registry/nacos/function/NacosFunction;
      10: invokespecial #38                 // Method apply:(Lorg/apache/dubbo/registry/nacos/function/NacosFunction;)Ljava/lang/Object;
      13: checkcast     #11                 // class java/util/List
      16: areturn

  public void shutdown() throws com.alibaba.nacos.api.exception.NacosException;
    Code:
       0: aload_0
       1: getfield      #6                  // Field nacosConnectionManager:Lorg/apache/dubbo/registry/nacos/NacosConnectionManager;
       4: invokevirtual #105                // Method org/apache/dubbo/registry/nacos/NacosConnectionManager.shutdownAll:()V
       7: return

  private java.lang.String handleInnerSymbol(java.lang.String);
    Code:
       0: aload_1
       1: invokestatic  #106                // Method org/apache/dubbo/common/utils/StringUtils.isEmpty:(Ljava/lang/String;)Z
       4: ifeq          9
       7: aconst_null
       8: areturn
       9: aload_1
      10: ldc           #108                // String $
      12: ldc           #109                // String ___
      14: invokevirtual #110                // Method java/lang/String.replace:(Ljava/lang/CharSequence;Ljava/lang/CharSequence;)Ljava/lang/String;
      17: areturn

  protected java.util.Map<org.apache.dubbo.registry.nacos.NacosNamingServiceWrapper$InstanceId, org.apache.dubbo.registry.nacos.NacosNamingServiceWrapper$InstancesInfo> getRegisterStatus();
    Code:
       0: aload_0
       1: getfield      #4                  // Field registerStatus:Ljava/util/concurrent/ConcurrentMap;
       4: areturn

  private <R> R apply(org.apache.dubbo.registry.nacos.function.NacosFunction<R>) throws com.alibaba.nacos.api.exception.NacosException;
    Code:
       0: aconst_null
       1: astore_2
       2: aconst_null
       3: astore_3
       4: iconst_0
       5: istore        4
       7: iload         4
       9: aload_0
      10: getfield      #23                 // Field retryTimes:I
      13: iconst_1
      14: iadd
      15: if_icmpge     174
      18: aload_1
      19: invokeinterface #111,  1          // InterfaceMethod org/apache/dubbo/registry/nacos/function/NacosFunction.apply:()Ljava/lang/Object;
      24: astore_3
      25: aconst_null
      26: astore_2
      27: goto          174
      30: astore        5
      32: aload         5
      34: astore_2
      35: getstatic     #14                 // Field logger:Lorg/apache/dubbo/common/logger/ErrorTypeAwareLogger;
      38: ldc           #113                // String 1-37
      40: ldc           #114                // String
      42: ldc           #114                // String
      44: new           #15                 // class java/lang/StringBuilder
      47: dup
      48: invokespecial #16                 // Method java/lang/StringBuilder."<init>":()V
      51: ldc           #115                // String Failed to request nacos naming server.
      53: invokevirtual #18                 // Method java/lang/StringBuilder.append:(Ljava/lang/String;)Ljava/lang/StringBuilder;
      56: iload         4
      58: aload_0
      59: getfield      #23                 // Field retryTimes:I
      62: if_icmpge     95
      65: new           #15                 // class java/lang/StringBuilder
      68: dup
      69: invokespecial #16                 // Method java/lang/StringBuilder."<init>":()V
      72: ldc           #116                // String Dubbo will try to retry in
      74: invokevirtual #18                 // Method java/lang/StringBuilder.append:(Ljava/lang/String;)Ljava/lang/StringBuilder;
      77: aload_0
      78: getfield      #24                 // Field sleepMsBetweenRetries:I
      81: invokevirtual #117                // Method java/lang/StringBuilder.append:(I)Ljava/lang/StringBuilder;
      84: ldc           #118                // String .
      86: invokevirtual #18                 // Method java/lang/StringBuilder.append:(Ljava/lang/String;)Ljava/lang/StringBuilder;
      89: invokevirtual #20                 // Method java/lang/StringBuilder.toString:()Ljava/lang/String;
      92: goto          97
      95: ldc           #119                // String Exceed retry max times.
      97: invokevirtual #18                 // Method java/lang/StringBuilder.append:(Ljava/lang/String;)Ljava/lang/StringBuilder;
     100: ldc           #120                // String Try times:
     102: invokevirtual #18                 // Method java/lang/StringBuilder.append:(Ljava/lang/String;)Ljava/lang/StringBuilder;
     105: iload         4
     107: iconst_1
     108: iadd
     109: invokevirtual #117                // Method java/lang/StringBuilder.append:(I)Ljava/lang/StringBuilder;
     112: invokevirtual #20                 // Method java/lang/StringBuilder.toString:()Ljava/lang/String;
     115: aload         5
     117: invokeinterface #121,  6          // InterfaceMethod org/apache/dubbo/common/logger/ErrorTypeAwareLogger.warn:(Ljava/lang/String;Ljava/lang/String;Ljava/lang/String;Ljava/lang/String;Ljava/lang/Throwable;)V
     122: iload         4
     124: aload_0
     125: getfield      #23                 // Field retryTimes:I
     128: if_icmpge     168
     131: aload_0
     132: getfield      #24                 // Field sleepMsBetweenRetries:I
     135: i2l
     136: invokestatic  #122                // Method java/lang/Thread.sleep:(J)V
     139: goto          168
     142: astore        6
     144: getstatic     #14                 // Field logger:Lorg/apache/dubbo/common/logger/ErrorTypeAwareLogger;
     147: ldc           #124                // String 99-1
     149: ldc           #114                // String
     151: ldc           #114                // String
     153: ldc           #125                // String Interrupted when waiting to retry.
     155: aload         6
     157: invokeinterface #121,  6          // InterfaceMethod org/apache/dubbo/common/logger/ErrorTypeAwareLogger.warn:(Ljava/lang/String;Ljava/lang/String;Ljava/lang/String;Ljava/lang/String;Ljava/lang/Throwable;)V
     162: invokestatic  #126                // Method java/lang/Thread.currentThread:()Ljava/lang/Thread;
     165: invokevirtual #127                // Method java/lang/Thread.interrupt:()V
     168: iinc          4, 1
     171: goto          7
     174: aload_2
     175: ifnull        180
     178: aload_2
     179: athrow
     180: iload         4
     182: iconst_1
     183: if_icmple     221
     186: getstatic     #14                 // Field logger:Lorg/apache/dubbo/common/logger/ErrorTypeAwareLogger;
     189: new           #15                 // class java/lang/StringBuilder
     192: dup
     193: invokespecial #16                 // Method java/lang/StringBuilder."<init>":()V
     196: ldc           #128                // String Failed to request nacos naming server for
     198: invokevirtual #18                 // Method java/lang/StringBuilder.append:(Ljava/lang/String;)Ljava/lang/StringBuilder;
     201: iload         4
     203: iconst_1
     204: isub
     205: invokevirtual #117                // Method java/lang/StringBuilder.append:(I)Ljava/lang/StringBuilder;
     208: ldc           #129                // String  times and finally success. This may caused by high stress of nacos server.
     210: invokevirtual #18                 // Method java/lang/StringBuilder.append:(Ljava/lang/String;)Ljava/lang/StringBuilder;
     213: invokevirtual #20                 // Method java/lang/StringBuilder.toString:()Ljava/lang/String;
     216: invokeinterface #21,  2           // InterfaceMethod org/apache/dubbo/common/logger/ErrorTypeAwareLogger.info:(Ljava/lang/String;)V
     221: aload_3
     222: areturn
    Exception table:
       from    to  target type
          18    27    30   Class com/alibaba/nacos/api/exception/NacosException
         131   139   142   Class java/lang/InterruptedException

  private void accept(org.apache.dubbo.registry.nacos.function.NacosConsumer) throws com.alibaba.nacos.api.exception.NacosException;
    Code:
       0: aconst_null
       1: astore_2
       2: iconst_0
       3: istore_3
       4: iload_3
       5: aload_0
       6: getfield      #23                 // Field retryTimes:I
       9: iconst_1
      10: iadd
      11: if_icmpge     166
      14: aload_1
      15: invokeinterface #130,  1          // InterfaceMethod org/apache/dubbo/registry/nacos/function/NacosConsumer.accept:()V
      20: aconst_null
      21: astore_2
      22: goto          166
      25: astore        4
      27: aload         4
      29: astore_2
      30: getstatic     #14                 // Field logger:Lorg/apache/dubbo/common/logger/ErrorTypeAwareLogger;
      33: ldc           #113                // String 1-37
      35: ldc           #114                // String
      37: ldc           #114                // String
      39: new           #15                 // class java/lang/StringBuilder
      42: dup
      43: invokespecial #16                 // Method java/lang/StringBuilder."<init>":()V
      46: ldc           #115                // String Failed to request nacos naming server.
      48: invokevirtual #18                 // Method java/lang/StringBuilder.append:(Ljava/lang/String;)Ljava/lang/StringBuilder;
      51: iload_3
      52: aload_0
      53: getfield      #23                 // Field retryTimes:I
      56: if_icmpge     89
      59: new           #15                 // class java/lang/StringBuilder
      62: dup
      63: invokespecial #16                 // Method java/lang/StringBuilder."<init>":()V
      66: ldc           #116                // String Dubbo will try to retry in
      68: invokevirtual #18                 // Method java/lang/StringBuilder.append:(Ljava/lang/String;)Ljava/lang/StringBuilder;
      71: aload_0
      72: getfield      #24                 // Field sleepMsBetweenRetries:I
      75: invokevirtual #117                // Method java/lang/StringBuilder.append:(I)Ljava/lang/StringBuilder;
      78: ldc           #118                // String .
      80: invokevirtual #18                 // Method java/lang/StringBuilder.append:(Ljava/lang/String;)Ljava/lang/StringBuilder;
      83: invokevirtual #20                 // Method java/lang/StringBuilder.toString:()Ljava/lang/String;
      86: goto          91
      89: ldc           #119                // String Exceed retry max times.
      91: invokevirtual #18                 // Method java/lang/StringBuilder.append:(Ljava/lang/String;)Ljava/lang/StringBuilder;
      94: ldc           #120                // String Try times:
      96: invokevirtual #18                 // Method java/lang/StringBuilder.append:(Ljava/lang/String;)Ljava/lang/StringBuilder;
      99: iload_3
     100: iconst_1
     101: iadd
     102: invokevirtual #117                // Method java/lang/StringBuilder.append:(I)Ljava/lang/StringBuilder;
     105: invokevirtual #20                 // Method java/lang/StringBuilder.toString:()Ljava/lang/String;
     108: aload         4
     110: invokeinterface #121,  6          // InterfaceMethod org/apache/dubbo/common/logger/ErrorTypeAwareLogger.warn:(Ljava/lang/String;Ljava/lang/String;Ljava/lang/String;Ljava/lang/String;Ljava/lang/Throwable;)V
     115: iload_3
     116: aload_0
     117: getfield      #23                 // Field retryTimes:I
     120: if_icmpge     160
     123: aload_0
     124: getfield      #24                 // Field sleepMsBetweenRetries:I
     127: i2l
     128: invokestatic  #122                // Method java/lang/Thread.sleep:(J)V
     131: goto          160
     134: astore        5
     136: getstatic     #14                 // Field logger:Lorg/apache/dubbo/common/logger/ErrorTypeAwareLogger;
     139: ldc           #124                // String 99-1
     141: ldc           #114                // String
     143: ldc           #114                // String
     145: ldc           #125                // String Interrupted when waiting to retry.
     147: aload         5
     149: invokeinterface #121,  6          // InterfaceMethod org/apache/dubbo/common/logger/ErrorTypeAwareLogger.warn:(Ljava/lang/String;Ljava/lang/String;Ljava/lang/String;Ljava/lang/String;Ljava/lang/Throwable;)V
     154: invokestatic  #126                // Method java/lang/Thread.currentThread:()Ljava/lang/Thread;
     157: invokevirtual #127                // Method java/lang/Thread.interrupt:()V
     160: iinc          3, 1
     163: goto          4
     166: aload_2
     167: ifnull        172
     170: aload_2
     171: athrow
     172: iload_3
     173: iconst_1
     174: if_icmple     211
     177: getstatic     #14                 // Field logger:Lorg/apache/dubbo/common/logger/ErrorTypeAwareLogger;
     180: new           #15                 // class java/lang/StringBuilder
     183: dup
     184: invokespecial #16                 // Method java/lang/StringBuilder."<init>":()V
     187: ldc           #128                // String Failed to request nacos naming server for
     189: invokevirtual #18                 // Method java/lang/StringBuilder.append:(Ljava/lang/String;)Ljava/lang/StringBuilder;
     192: iload_3
     193: iconst_1
     194: isub
     195: invokevirtual #117                // Method java/lang/StringBuilder.append:(I)Ljava/lang/StringBuilder;
     198: ldc           #129                // String  times and finally success. This may caused by high stress of nacos server.
     200: invokevirtual #18                 // Method java/lang/StringBuilder.append:(Ljava/lang/String;)Ljava/lang/StringBuilder;
     203: invokevirtual #20                 // Method java/lang/StringBuilder.toString:()Ljava/lang/String;
     206: invokeinterface #21,  2           // InterfaceMethod org/apache/dubbo/common/logger/ErrorTypeAwareLogger.info:(Ljava/lang/String;)V
     211: return
    Exception table:
       from    to  target type
          14    22    25   Class com/alibaba/nacos/api/exception/NacosException
         123   131   134   Class java/lang/InterruptedException

  private java.util.List lambda$selectInstances$21(java.lang.String, java.lang.String, boolean) throws com.alibaba.nacos.api.exception.NacosException;
    Code:
       0: aload_0
       1: getfield      #6                  // Field nacosConnectionManager:Lorg/apache/dubbo/registry/nacos/NacosConnectionManager;
       4: invokevirtual #25                 // Method org/apache/dubbo/registry/nacos/NacosConnectionManager.getNamingService:()Lcom/alibaba/nacos/api/naming/NamingService;
       7: aload_0
       8: aload_1
       9: invokespecial #27                 // Method handleInnerSymbol:(Ljava/lang/String;)Ljava/lang/String;
      12: aload_2
      13: iload_3
      14: invokeinterface #131,  4          // InterfaceMethod com/alibaba/nacos/api/naming/NamingService.selectInstances:(Ljava/lang/String;Ljava/lang/String;Z)Ljava/util/List;
      19: areturn

  private com.alibaba.nacos.api.naming.pojo.ListView lambda$getServicesOfServer$20(int, int, java.lang.String) throws com.alibaba.nacos.api.exception.NacosException;
    Code:
       0: aload_0
       1: getfield      #6                  // Field nacosConnectionManager:Lorg/apache/dubbo/registry/nacos/NacosConnectionManager;
       4: invokevirtual #25                 // Method org/apache/dubbo/registry/nacos/NacosConnectionManager.getNamingService:()Lcom/alibaba/nacos/api/naming/NamingService;
       7: iload_1
       8: iload_2
       9: aload_3
      10: invokeinterface #132,  4          // InterfaceMethod com/alibaba/nacos/api/naming/NamingService.getServicesOfServer:(IILjava/lang/String;)Lcom/alibaba/nacos/api/naming/pojo/ListView;
      15: areturn

  private static void lambda$deregisterInstance$19(org.apache.dubbo.registry.nacos.NacosNamingServiceWrapper$InstanceInfo, java.lang.String, java.lang.String, com.alibaba.nacos.api.naming.pojo.Instance) throws com.alibaba.nacos.api.exception.NacosException;
    Code:
       0: aload_0
       1: invokevirtual #57                 // Method org/apache/dubbo/registry/nacos/NacosNamingServiceWrapper$InstanceInfo.getNamingService:()Lcom/alibaba/nacos/api/naming/NamingService;
       4: aload_1
       5: aload_2
       6: aload_3
       7: invokeinterface #133,  4          // InterfaceMethod com/alibaba/nacos/api/naming/NamingService.deregisterInstance:(Ljava/lang/String;Ljava/lang/String;Lcom/alibaba/nacos/api/naming/pojo/Instance;)V
      12: return

  private static void lambda$deregisterInstance$18(org.apache.dubbo.registry.nacos.NacosNamingServiceWrapper$InstanceInfo, java.lang.String, java.lang.String, java.util.List) throws com.alibaba.nacos.api.exception.NacosException;
    Code:
       0: aload_0
       1: invokevirtual #57                 // Method org/apache/dubbo/registry/nacos/NacosNamingServiceWrapper$InstanceInfo.getNamingService:()Lcom/alibaba/nacos/api/naming/NamingService;
       4: aload_1
       5: aload_2
       6: aload_3
       7: invokeinterface #134,  4          // InterfaceMethod com/alibaba/nacos/api/naming/NamingService.batchRegisterInstance:(Ljava/lang/String;Ljava/lang/String;Ljava/util/List;)V
      12: return

  private static void lambda$deregisterInstance$17(org.apache.dubbo.registry.nacos.NacosNamingServiceWrapper$InstanceInfo, java.lang.String, java.lang.String, com.alibaba.nacos.api.naming.pojo.Instance) throws com.alibaba.nacos.api.exception.NacosException;
    Code:
       0: aload_0
       1: invokevirtual #57                 // Method org/apache/dubbo/registry/nacos/NacosNamingServiceWrapper$InstanceInfo.getNamingService:()Lcom/alibaba/nacos/api/naming/NamingService;
       4: aload_1
       5: aload_2
       6: aload_3
       7: invokeinterface #133,  4          // InterfaceMethod com/alibaba/nacos/api/naming/NamingService.deregisterInstance:(Ljava/lang/String;Ljava/lang/String;Lcom/alibaba/nacos/api/naming/pojo/Instance;)V
      12: return

  private static boolean lambda$deregisterInstance$16(com.alibaba.nacos.api.naming.pojo.Instance, org.apache.dubbo.registry.nacos.NacosNamingServiceWrapper$InstanceInfo);
    Code:
       0: aload_1
       1: invokevirtual #58                 // Method org/apache/dubbo/registry/nacos/NacosNamingServiceWrapper$InstanceInfo.getInstance:()Lcom/alibaba/nacos/api/naming/pojo/Instance;
       4: aload_0
       5: invokevirtual #135                // Method com/alibaba/nacos/api/naming/pojo/Instance.equals:(Ljava/lang/Object;)Z
       8: ireturn

  private static org.apache.dubbo.registry.nacos.NacosNamingServiceWrapper$InstancesInfo lambda$deregisterInstance$15(org.apache.dubbo.registry.nacos.NacosNamingServiceWrapper$InstanceId);
    Code:
       0: new           #42                 // class org/apache/dubbo/registry/nacos/NacosNamingServiceWrapper$InstancesInfo
       3: dup
       4: invokespecial #136                // Method org/apache/dubbo/registry/nacos/NacosNamingServiceWrapper$InstancesInfo."<init>":()V
       7: areturn

  private static boolean lambda$deregisterInstance$14(java.lang.String, int, com.alibaba.nacos.api.naming.pojo.Instance);
    Code:
       0: aload_2
       1: invokevirtual #137                // Method com/alibaba/nacos/api/naming/pojo/Instance.getIp:()Ljava/lang/String;
       4: aload_0
       5: invokestatic  #138                // Method java/util/Objects.equals:(Ljava/lang/Object;Ljava/lang/Object;)Z
       8: ifeq          23
      11: aload_2
      12: invokevirtual #139                // Method com/alibaba/nacos/api/naming/pojo/Instance.getPort:()I
      15: iload_1
      16: if_icmpne     23
      19: iconst_1
      20: goto          24
      23: iconst_0
      24: ireturn

  private static org.apache.dubbo.registry.nacos.NacosNamingServiceWrapper$InstancesInfo lambda$deregisterInstance$13(org.apache.dubbo.registry.nacos.NacosNamingServiceWrapper$InstanceId);
    Code:
       0: new           #42                 // class org/apache/dubbo/registry/nacos/NacosNamingServiceWrapper$InstancesInfo
       3: dup
       4: invokespecial #136                // Method org/apache/dubbo/registry/nacos/NacosNamingServiceWrapper$InstancesInfo."<init>":()V
       7: areturn

  private static void lambda$updateInstance$12(org.apache.dubbo.registry.nacos.NacosNamingServiceWrapper$InstanceInfo, java.lang.String, java.lang.String, com.alibaba.nacos.api.naming.pojo.Instance) throws com.alibaba.nacos.api.exception.NacosException;
    Code:
       0: aload_0
       1: invokevirtual #57                 // Method org/apache/dubbo/registry/nacos/NacosNamingServiceWrapper$InstanceInfo.getNamingService:()Lcom/alibaba/nacos/api/naming/NamingService;
       4: aload_1
       5: aload_2
       6: aload_3
       7: invokeinterface #140,  4          // InterfaceMethod com/alibaba/nacos/api/naming/NamingService.registerInstance:(Ljava/lang/String;Ljava/lang/String;Lcom/alibaba/nacos/api/naming/pojo/Instance;)V
      12: return

  private static void lambda$updateInstance$11(com.alibaba.nacos.api.naming.NamingService, java.lang.String, java.lang.String, java.util.List) throws com.alibaba.nacos.api.exception.NacosException;
    Code:
       0: aload_0
       1: aload_1
       2: aload_2
       3: aload_3
       4: invokeinterface #134,  4          // InterfaceMethod com/alibaba/nacos/api/naming/NamingService.batchRegisterInstance:(Ljava/lang/String;Ljava/lang/String;Ljava/util/List;)V
       9: return

  private static boolean lambda$updateInstance$10(com.alibaba.nacos.api.naming.pojo.Instance, org.apache.dubbo.registry.nacos.NacosNamingServiceWrapper$InstanceInfo);
    Code:
       0: aload_1
       1: invokevirtual #58                 // Method org/apache/dubbo/registry/nacos/NacosNamingServiceWrapper$InstanceInfo.getInstance:()Lcom/alibaba/nacos/api/naming/pojo/Instance;
       4: aload_0
       5: invokevirtual #135                // Method com/alibaba/nacos/api/naming/pojo/Instance.equals:(Ljava/lang/Object;)Z
       8: ireturn

  private static org.apache.dubbo.registry.nacos.NacosNamingServiceWrapper$InstancesInfo lambda$updateInstance$9(org.apache.dubbo.registry.nacos.NacosNamingServiceWrapper$InstanceId);
    Code:
       0: new           #42                 // class org/apache/dubbo/registry/nacos/NacosNamingServiceWrapper$InstancesInfo
       3: dup
       4: invokespecial #136                // Method org/apache/dubbo/registry/nacos/NacosNamingServiceWrapper$InstancesInfo."<init>":()V
       7: areturn

  private static void lambda$registerInstance$8(com.alibaba.nacos.api.naming.NamingService, java.lang.String, java.lang.String, com.alibaba.nacos.api.naming.pojo.Instance) throws com.alibaba.nacos.api.exception.NacosException;
    Code:
       0: aload_0
       1: aload_1
       2: aload_2
       3: aload_3
       4: invokeinterface #140,  4          // InterfaceMethod com/alibaba/nacos/api/naming/NamingService.registerInstance:(Ljava/lang/String;Ljava/lang/String;Lcom/alibaba/nacos/api/naming/pojo/Instance;)V
       9: return

  private static void lambda$registerInstance$7(com.alibaba.nacos.api.naming.NamingService, java.lang.String, java.lang.String, java.util.List) throws com.alibaba.nacos.api.exception.NacosException;
    Code:
       0: aload_0
       1: aload_1
       2: aload_2
       3: aload_3
       4: invokeinterface #134,  4          // InterfaceMethod com/alibaba/nacos/api/naming/NamingService.batchRegisterInstance:(Ljava/lang/String;Ljava/lang/String;Ljava/util/List;)V
       9: return

  private static void lambda$registerInstance$6(com.alibaba.nacos.api.naming.NamingService, java.lang.String, java.lang.String, java.util.List) throws com.alibaba.nacos.api.exception.NacosException;
    Code:
       0: aload_0
       1: aload_1
       2: aload_2
       3: aload_3
       4: invokeinterface #134,  4          // InterfaceMethod com/alibaba/nacos/api/naming/NamingService.batchRegisterInstance:(Ljava/lang/String;Ljava/lang/String;Ljava/util/List;)V
       9: return

  private static void lambda$registerInstance$5(com.alibaba.nacos.api.naming.NamingService, java.lang.String, java.lang.String, com.alibaba.nacos.api.naming.pojo.Instance) throws com.alibaba.nacos.api.exception.NacosException;
    Code:
       0: aload_0
       1: aload_1
       2: aload_2
       3: aload_3
       4: invokeinterface #140,  4          // InterfaceMethod com/alibaba/nacos/api/naming/NamingService.registerInstance:(Ljava/lang/String;Ljava/lang/String;Lcom/alibaba/nacos/api/naming/pojo/Instance;)V
       9: return

  private static org.apache.dubbo.registry.nacos.NacosNamingServiceWrapper$InstancesInfo lambda$registerInstance$4(org.apache.dubbo.registry.nacos.NacosNamingServiceWrapper$InstanceId);
    Code:
       0: new           #42                 // class org/apache/dubbo/registry/nacos/NacosNamingServiceWrapper$InstancesInfo
       3: dup
       4: invokespecial #136                // Method org/apache/dubbo/registry/nacos/NacosNamingServiceWrapper$InstancesInfo."<init>":()V
       7: areturn

  private java.util.List lambda$getAllInstances$3(java.lang.String, java.lang.String) throws com.alibaba.nacos.api.exception.NacosException;
    Code:
       0: aload_0
       1: getfield      #6                  // Field nacosConnectionManager:Lorg/apache/dubbo/registry/nacos/NacosConnectionManager;
       4: invokevirtual #25                 // Method org/apache/dubbo/registry/nacos/NacosConnectionManager.getNamingService:()Lcom/alibaba/nacos/api/naming/NamingService;
       7: aload_0
       8: aload_1
       9: invokespecial #27                 // Method handleInnerSymbol:(Ljava/lang/String;)Ljava/lang/String;
      12: aload_2
      13: invokeinterface #141,  3          // InterfaceMethod com/alibaba/nacos/api/naming/NamingService.getAllInstances:(Ljava/lang/String;Ljava/lang/String;)Ljava/util/List;
      18: areturn

  private static void lambda$unsubscribe$2(com.alibaba.nacos.api.naming.NamingService, java.lang.String, java.lang.String, com.alibaba.nacos.api.naming.listener.EventListener) throws com.alibaba.nacos.api.exception.NacosException;
    Code:
       0: aload_0
       1: aload_1
       2: aload_2
       3: aload_3
       4: invokeinterface #142,  4          // InterfaceMethod com/alibaba/nacos/api/naming/NamingService.unsubscribe:(Ljava/lang/String;Ljava/lang/String;Lcom/alibaba/nacos/api/naming/listener/EventListener;)V
       9: return

  private static void lambda$subscribe$1(com.alibaba.nacos.api.naming.NamingService, java.lang.String, java.lang.String, com.alibaba.nacos.api.naming.listener.EventListener) throws com.alibaba.nacos.api.exception.NacosException;
    Code:
       0: aload_0
       1: aload_1
       2: aload_2
       3: aload_3
       4: invokeinterface #143,  4          // InterfaceMethod com/alibaba/nacos/api/naming/NamingService.subscribe:(Ljava/lang/String;Ljava/lang/String;Lcom/alibaba/nacos/api/naming/listener/EventListener;)V
       9: return

  private com.alibaba.nacos.api.naming.NamingService lambda$subscribe$0(org.apache.dubbo.registry.nacos.NacosNamingServiceWrapper$SubscribeInfo);
    Code:
       0: aload_0
       1: getfield      #6                  // Field nacosConnectionManager:Lorg/apache/dubbo/registry/nacos/NacosConnectionManager;
       4: invokevirtual #25                 // Method org/apache/dubbo/registry/nacos/NacosConnectionManager.getNamingService:()Lcom/alibaba/nacos/api/naming/NamingService;
       7: areturn

  static {};
    Code:
       0: ldc           #107                // class org/apache/dubbo/registry/nacos/NacosNamingServiceWrapper
       2: invokestatic  #144                // Method org/apache/dubbo/common/logger/LoggerFactory.getErrorTypeAwareLogger:(Ljava/lang/Class;)Lorg/apache/dubbo/common/logger/ErrorTypeAwareLogger;
       5: putstatic     #14                 // Field logger:Lorg/apache/dubbo/common/logger/ErrorTypeAwareLogger;
       8: return
}
