Compiled from "NacosRegistry.java"
class org.apache.dubbo.registry.nacos.NacosRegistry$RegistryChildListenerImpl implements com.alibaba.nacos.api.naming.listener.EventListener {
  private final org.apache.dubbo.registry.RegistryNotifier notifier;

  private final java.lang.String serviceName;

  private final org.apache.dubbo.common.URL consumerUrl;

  private final org.apache.dubbo.registry.nacos.NacosAggregateListener listener;

  final org.apache.dubbo.registry.nacos.NacosRegistry this$0;

  public org.apache.dubbo.registry.nacos.NacosRegistry$RegistryChildListenerImpl(org.apache.dubbo.registry.nacos.NacosRegistry, java.lang.String, org.apache.dubbo.common.URL, org.apache.dubbo.registry.nacos.NacosAggregateListener);
    Code:
       0: aload_0
       1: aload_1
       2: putfield      #1                  // Field this$0:Lorg/apache/dubbo/registry/nacos/NacosRegistry;
       5: aload_0
       6: invokespecial #2                  // Method java/lang/Object."<init>":()V
       9: aload_0
      10: aload_2
      11: putfield      #3                  // Field serviceName:Ljava/lang/String;
      14: aload_0
      15: aload_3
      16: putfield      #4                  // Field consumerUrl:Lorg/apache/dubbo/common/URL;
      19: aload_0
      20: aload         4
      22: putfield      #5                  // Field listener:Lorg/apache/dubbo/registry/nacos/NacosAggregateListener;
      25: aload_0
      26: new           #6                  // class org/apache/dubbo/registry/nacos/NacosRegistry$RegistryChildListenerImpl$1
      29: dup
      30: aload_0
      31: aload_1
      32: invokevirtual #7                  // Method org/apache/dubbo/registry/nacos/NacosRegistry.getUrl:()Lorg/apache/dubbo/common/URL;
      35: aload_1
      36: invokevirtual #8                  // Method org/apache/dubbo/registry/nacos/NacosRegistry.getDelay:()I
      39: i2l
      40: aload_1
      41: aload_3
      42: aload_2
      43: aload         4
      45: invokespecial #9                  // Method org/apache/dubbo/registry/nacos/NacosRegistry$RegistryChildListenerImpl$1."<init>":(Lorg/apache/dubbo/registry/nacos/NacosRegistry$RegistryChildListenerImpl;Lorg/apache/dubbo/common/URL;JLorg/apache/dubbo/registry/nacos/NacosRegistry;Lorg/apache/dubbo/common/URL;Ljava/lang/String;Lorg/apache/dubbo/registry/nacos/NacosAggregateListener;)V
      48: putfield      #10                 // Field notifier:Lorg/apache/dubbo/registry/RegistryNotifier;
      51: return

  public void onEvent(com.alibaba.nacos.api.naming.listener.Event);
    Code:
       0: aload_1
       1: instanceof    #11                 // class com/alibaba/nacos/api/naming/listener/NamingEvent
       4: ifeq          23
       7: aload_1
       8: checkcast     #11                 // class com/alibaba/nacos/api/naming/listener/NamingEvent
      11: astore_2
      12: aload_0
      13: getfield      #10                 // Field notifier:Lorg/apache/dubbo/registry/RegistryNotifier;
      16: aload_2
      17: invokevirtual #12                 // Method com/alibaba/nacos/api/naming/listener/NamingEvent.getInstances:()Ljava/util/List;
      20: invokevirtual #13                 // Method org/apache/dubbo/registry/RegistryNotifier.notify:(Ljava/lang/Object;)V
      23: return

  public boolean equals(java.lang.Object);
    Code:
       0: aload_0
       1: aload_1
       2: if_acmpne     7
       5: iconst_1
       6: ireturn
       7: aload_1
       8: ifnull        22
      11: aload_0
      12: invokevirtual #14                 // Method java/lang/Object.getClass:()Ljava/lang/Class;
      15: aload_1
      16: invokevirtual #14                 // Method java/lang/Object.getClass:()Ljava/lang/Class;
      19: if_acmpeq     24
      22: iconst_0
      23: ireturn
      24: aload_1
      25: checkcast     #15                 // class org/apache/dubbo/registry/nacos/NacosRegistry$RegistryChildListenerImpl
      28: astore_2
      29: aload_0
      30: getfield      #3                  // Field serviceName:Ljava/lang/String;
      33: aload_2
      34: getfield      #3                  // Field serviceName:Ljava/lang/String;
      37: invokestatic  #16                 // Method java/util/Objects.equals:(Ljava/lang/Object;Ljava/lang/Object;)Z
      40: ifeq          75
      43: aload_0
      44: getfield      #4                  // Field consumerUrl:Lorg/apache/dubbo/common/URL;
      47: aload_2
      48: getfield      #4                  // Field consumerUrl:Lorg/apache/dubbo/common/URL;
      51: invokestatic  #16                 // Method java/util/Objects.equals:(Ljava/lang/Object;Ljava/lang/Object;)Z
      54: ifeq          75
      57: aload_0
      58: getfield      #5                  // Field listener:Lorg/apache/dubbo/registry/nacos/NacosAggregateListener;
      61: aload_2
      62: getfield      #5                  // Field listener:Lorg/apache/dubbo/registry/nacos/NacosAggregateListener;
      65: invokestatic  #16                 // Method java/util/Objects.equals:(Ljava/lang/Object;Ljava/lang/Object;)Z
      68: ifeq          75
      71: iconst_1
      72: goto          76
      75: iconst_0
      76: ireturn

  public int hashCode();
    Code:
       0: iconst_3
       1: anewarray     #17                 // class java/lang/Object
       4: dup
       5: iconst_0
       6: aload_0
       7: getfield      #3                  // Field serviceName:Ljava/lang/String;
      10: aastore
      11: dup
      12: iconst_1
      13: aload_0
      14: getfield      #4                  // Field consumerUrl:Lorg/apache/dubbo/common/URL;
      17: aastore
      18: dup
      19: iconst_2
      20: aload_0
      21: getfield      #5                  // Field listener:Lorg/apache/dubbo/registry/nacos/NacosAggregateListener;
      24: aastore
      25: invokestatic  #18                 // Method java/util/Objects.hash:([Ljava/lang/Object;)I
      28: ireturn
}
