Compiled from "NacosNamingServiceWrapper.java"
public class org.apache.dubbo.registry.nacos.NacosNamingServiceWrapper$InstanceInfo {
  private final com.alibaba.nacos.api.naming.pojo.Instance instance;

  private final com.alibaba.nacos.api.naming.NamingService namingService;

  public org.apache.dubbo.registry.nacos.NacosNamingServiceWrapper$InstanceInfo(com.alibaba.nacos.api.naming.pojo.Instance, com.alibaba.nacos.api.naming.NamingService);
    Code:
       0: aload_0
       1: invokespecial #1                  // Method java/lang/Object."<init>":()V
       4: aload_0
       5: aload_1
       6: putfield      #2                  // Field instance:Lcom/alibaba/nacos/api/naming/pojo/Instance;
       9: aload_0
      10: aload_2
      11: putfield      #3                  // Field namingService:Lcom/alibaba/nacos/api/naming/NamingService;
      14: return

  public com.alibaba.nacos.api.naming.pojo.Instance getInstance();
    Code:
       0: aload_0
       1: getfield      #2                  // Field instance:Lcom/alibaba/nacos/api/naming/pojo/Instance;
       4: areturn

  public com.alibaba.nacos.api.naming.NamingService getNamingService();
    Code:
       0: aload_0
       1: getfield      #3                  // Field namingService:Lcom/alibaba/nacos/api/naming/NamingService;
       4: areturn
}
