Compiled from "NacosNamingServiceWrapper.java"
public class org.apache.dubbo.registry.nacos.NacosNamingServiceWrapper$InstancesInfo {
  private final java.util.concurrent.locks.Lock lock;

  private final java.util.List<org.apache.dubbo.registry.nacos.NacosNamingServiceWrapper$InstanceInfo> instances;

  private volatile boolean batchRegistered;

  private volatile boolean valid;

  protected org.apache.dubbo.registry.nacos.NacosNamingServiceWrapper$InstancesInfo();
    Code:
       0: aload_0
       1: invokespecial #1                  // Method java/lang/Object."<init>":()V
       4: aload_0
       5: new           #2                  // class java/util/concurrent/locks/ReentrantLock
       8: dup
       9: invokespecial #3                  // Method java/util/concurrent/locks/ReentrantLock."<init>":()V
      12: putfield      #4                  // Field lock:Ljava/util/concurrent/locks/Lock;
      15: aload_0
      16: new           #5                  // class java/util/ArrayList
      19: dup
      20: invokespecial #6                  // Method java/util/ArrayList."<init>":()V
      23: putfield      #7                  // Field instances:Ljava/util/List;
      26: aload_0
      27: iconst_0
      28: putfield      #8                  // Field batchRegistered:Z
      31: aload_0
      32: iconst_1
      33: putfield      #9                  // Field valid:Z
      36: return

  public void lock();
    Code:
       0: aload_0
       1: getfield      #4                  // Field lock:Ljava/util/concurrent/locks/Lock;
       4: invokeinterface #10,  1           // InterfaceMethod java/util/concurrent/locks/Lock.lock:()V
       9: return

  public void unlock();
    Code:
       0: aload_0
       1: getfield      #4                  // Field lock:Ljava/util/concurrent/locks/Lock;
       4: invokeinterface #11,  1           // InterfaceMethod java/util/concurrent/locks/Lock.unlock:()V
       9: return

  public java.util.List<org.apache.dubbo.registry.nacos.NacosNamingServiceWrapper$InstanceInfo> getInstances();
    Code:
       0: aload_0
       1: getfield      #7                  // Field instances:Ljava/util/List;
       4: areturn

  public boolean isBatchRegistered();
    Code:
       0: aload_0
       1: getfield      #8                  // Field batchRegistered:Z
       4: ireturn

  public void setBatchRegistered(boolean);
    Code:
       0: aload_0
       1: iload_1
       2: putfield      #8                  // Field batchRegistered:Z
       5: return

  public boolean isValid();
    Code:
       0: aload_0
       1: getfield      #9                  // Field valid:Z
       4: ireturn

  public void setValid(boolean);
    Code:
       0: aload_0
       1: iload_1
       2: putfield      #9                  // Field valid:Z
       5: return
}
