Compiled from "DefaultMigrationAddressComparator.java"
public class org.apache.dubbo.registry.client.migration.DefaultMigrationAddressComparator implements org.apache.dubbo.registry.client.migration.MigrationAddressComparator {
  private static final org.apache.dubbo.common.logger.ErrorTypeAwareLogger logger;

  private static final java.lang.String MIGRATION_THRESHOLD;

  private static final java.lang.String DEFAULT_THRESHOLD_STRING;

  private static final float DEFAULT_THREAD;

  public static final java.lang.String OLD_ADDRESS_SIZE;

  public static final java.lang.String NEW_ADDRESS_SIZE;

  private final java.util.concurrent.ConcurrentMap<java.lang.String, java.util.Map<java.lang.String, java.lang.Integer>> serviceMigrationData;

  public org.apache.dubbo.registry.client.migration.DefaultMigrationAddressComparator();
    Code:
       0: aload_0
       1: invokespecial #2                  // Method java/lang/Object."<init>":()V
       4: aload_0
       5: new           #3                  // class java/util/concurrent/ConcurrentHashMap
       8: dup
       9: invokespecial #4                  // Method java/util/concurrent/ConcurrentHashMap."<init>":()V
      12: putfield      #5                  // Field serviceMigrationData:Ljava/util/concurrent/ConcurrentMap;
      15: return

  public <T> boolean shouldMigrate(org.apache.dubbo.rpc.cluster.ClusterInvoker<T>, org.apache.dubbo.rpc.cluster.ClusterInvoker<T>, org.apache.dubbo.registry.client.migration.model.MigrationRule);
    Code:
       0: aload_0
       1: getfield      #5                  // Field serviceMigrationData:Ljava/util/concurrent/ConcurrentMap;
       4: aload_2
       5: invokeinterface #6,  1            // InterfaceMethod org/apache/dubbo/rpc/cluster/ClusterInvoker.getUrl:()Lorg/apache/dubbo/common/URL;
      10: invokevirtual #7                  // Method org/apache/dubbo/common/URL.getDisplayServiceKey:()Ljava/lang/String;
      13: invokedynamic #8,  0              // InvokeDynamic #0:apply:()Ljava/util/function/Function;
      18: invokestatic  #9                  // Method org/apache/dubbo/common/utils/ConcurrentHashMapUtils.computeIfAbsent:(Ljava/util/concurrent/ConcurrentMap;Ljava/lang/Object;Ljava/util/function/Function;)Ljava/lang/Object;
      21: checkcast     #10                 // class java/util/Map
      24: astore        4
      26: aload_1
      27: invokeinterface #11,  1           // InterfaceMethod org/apache/dubbo/rpc/cluster/ClusterInvoker.hasProxyInvokers:()Z
      32: ifne          105
      35: aload         4
      37: ldc           #13                 // String OLD_ADDRESS_SIZE
      39: aload_0
      40: aload_2
      41: invokespecial #14                 // Method getAddressSize:(Lorg/apache/dubbo/rpc/cluster/ClusterInvoker;)I
      44: invokestatic  #15                 // Method java/lang/Integer.valueOf:(I)Ljava/lang/Integer;
      47: invokeinterface #16,  3           // InterfaceMethod java/util/Map.put:(Ljava/lang/Object;Ljava/lang/Object;)Ljava/lang/Object;
      52: pop
      53: aload         4
      55: ldc           #17                 // String NEW_ADDRESS_SIZE
      57: iconst_m1
      58: invokestatic  #15                 // Method java/lang/Integer.valueOf:(I)Ljava/lang/Integer;
      61: invokeinterface #16,  3           // InterfaceMethod java/util/Map.put:(Ljava/lang/Object;Ljava/lang/Object;)Ljava/lang/Object;
      66: pop
      67: getstatic     #18                 // Field logger:Lorg/apache/dubbo/common/logger/ErrorTypeAwareLogger;
      70: new           #19                 // class java/lang/StringBuilder
      73: dup
      74: invokespecial #20                 // Method java/lang/StringBuilder."<init>":()V
      77: ldc           #21                 // String No
      79: invokevirtual #22                 // Method java/lang/StringBuilder.append:(Ljava/lang/String;)Ljava/lang/StringBuilder;
      82: aload_0
      83: aload_1
      84: invokespecial #23                 // Method getInvokerType:(Lorg/apache/dubbo/rpc/cluster/ClusterInvoker;)Ljava/lang/String;
      87: invokevirtual #22                 // Method java/lang/StringBuilder.append:(Ljava/lang/String;)Ljava/lang/StringBuilder;
      90: ldc           #24                 // String  address available, stop compare.
      92: invokevirtual #22                 // Method java/lang/StringBuilder.append:(Ljava/lang/String;)Ljava/lang/StringBuilder;
      95: invokevirtual #25                 // Method java/lang/StringBuilder.toString:()Ljava/lang/String;
      98: invokeinterface #26,  2           // InterfaceMethod org/apache/dubbo/common/logger/ErrorTypeAwareLogger.info:(Ljava/lang/String;)V
     103: iconst_0
     104: ireturn
     105: aload_2
     106: invokeinterface #11,  1           // InterfaceMethod org/apache/dubbo/rpc/cluster/ClusterInvoker.hasProxyInvokers:()Z
     111: ifne          184
     114: aload         4
     116: ldc           #13                 // String OLD_ADDRESS_SIZE
     118: iconst_m1
     119: invokestatic  #15                 // Method java/lang/Integer.valueOf:(I)Ljava/lang/Integer;
     122: invokeinterface #16,  3           // InterfaceMethod java/util/Map.put:(Ljava/lang/Object;Ljava/lang/Object;)Ljava/lang/Object;
     127: pop
     128: aload         4
     130: ldc           #17                 // String NEW_ADDRESS_SIZE
     132: aload_0
     133: aload_1
     134: invokespecial #14                 // Method getAddressSize:(Lorg/apache/dubbo/rpc/cluster/ClusterInvoker;)I
     137: invokestatic  #15                 // Method java/lang/Integer.valueOf:(I)Ljava/lang/Integer;
     140: invokeinterface #16,  3           // InterfaceMethod java/util/Map.put:(Ljava/lang/Object;Ljava/lang/Object;)Ljava/lang/Object;
     145: pop
     146: getstatic     #18                 // Field logger:Lorg/apache/dubbo/common/logger/ErrorTypeAwareLogger;
     149: new           #19                 // class java/lang/StringBuilder
     152: dup
     153: invokespecial #20                 // Method java/lang/StringBuilder."<init>":()V
     156: ldc           #21                 // String No
     158: invokevirtual #22                 // Method java/lang/StringBuilder.append:(Ljava/lang/String;)Ljava/lang/StringBuilder;
     161: aload_0
     162: aload_2
     163: invokespecial #23                 // Method getInvokerType:(Lorg/apache/dubbo/rpc/cluster/ClusterInvoker;)Ljava/lang/String;
     166: invokevirtual #22                 // Method java/lang/StringBuilder.append:(Ljava/lang/String;)Ljava/lang/StringBuilder;
     169: ldc           #24                 // String  address available, stop compare.
     171: invokevirtual #22                 // Method java/lang/StringBuilder.append:(Ljava/lang/String;)Ljava/lang/StringBuilder;
     174: invokevirtual #25                 // Method java/lang/StringBuilder.toString:()Ljava/lang/String;
     177: invokeinterface #26,  2           // InterfaceMethod org/apache/dubbo/common/logger/ErrorTypeAwareLogger.info:(Ljava/lang/String;)V
     182: iconst_1
     183: ireturn
     184: aload_0
     185: aload_1
     186: invokespecial #14                 // Method getAddressSize:(Lorg/apache/dubbo/rpc/cluster/ClusterInvoker;)I
     189: istore        5
     191: aload_0
     192: aload_2
     193: invokespecial #14                 // Method getAddressSize:(Lorg/apache/dubbo/rpc/cluster/ClusterInvoker;)I
     196: istore        6
     198: aload         4
     200: ldc           #13                 // String OLD_ADDRESS_SIZE
     202: iload         6
     204: invokestatic  #15                 // Method java/lang/Integer.valueOf:(I)Ljava/lang/Integer;
     207: invokeinterface #16,  3           // InterfaceMethod java/util/Map.put:(Ljava/lang/Object;Ljava/lang/Object;)Ljava/lang/Object;
     212: pop
     213: aload         4
     215: ldc           #17                 // String NEW_ADDRESS_SIZE
     217: iload         5
     219: invokestatic  #15                 // Method java/lang/Integer.valueOf:(I)Ljava/lang/Integer;
     222: invokeinterface #16,  3           // InterfaceMethod java/util/Map.put:(Ljava/lang/Object;Ljava/lang/Object;)Ljava/lang/Object;
     227: pop
     228: aconst_null
     229: astore        7
     231: aload_3
     232: ifnonnull     239
     235: aconst_null
     236: goto          252
     239: aload_3
     240: aload_2
     241: invokeinterface #6,  1            // InterfaceMethod org/apache/dubbo/rpc/cluster/ClusterInvoker.getUrl:()Lorg/apache/dubbo/common/URL;
     246: invokevirtual #27                 // Method org/apache/dubbo/registry/client/migration/model/MigrationRule.getThreshold:(Lorg/apache/dubbo/common/URL;)F
     249: invokestatic  #28                 // Method java/lang/Float.valueOf:(F)Ljava/lang/Float;
     252: astore        8
     254: aload         8
     256: ifnull        276
     259: aload         8
     261: invokevirtual #29                 // Method java/lang/Float.floatValue:()F
     264: fconst_0
     265: fcmpl
     266: iflt          276
     269: aload         8
     271: invokestatic  #30                 // Method java/lang/String.valueOf:(Ljava/lang/Object;)Ljava/lang/String;
     274: astore        7
     276: aload         7
     278: invokestatic  #31                 // Method org/apache/dubbo/common/utils/StringUtils.isNotEmpty:(Ljava/lang/String;)Z
     281: ifeq          289
     284: aload         7
     286: goto          305
     289: aload_1
     290: invokeinterface #6,  1            // InterfaceMethod org/apache/dubbo/rpc/cluster/ClusterInvoker.getUrl:()Lorg/apache/dubbo/common/URL;
     295: invokevirtual #32                 // Method org/apache/dubbo/common/URL.getScopeModel:()Lorg/apache/dubbo/rpc/model/ScopeModel;
     298: ldc           #33                 // String dubbo.application.migration.threshold
     300: ldc           #34                 // String 0.0
     302: invokestatic  #35                 // Method org/apache/dubbo/common/config/ConfigurationUtils.getCachedDynamicProperty:(Lorg/apache/dubbo/rpc/model/ScopeModel;Ljava/lang/String;Ljava/lang/String;)Ljava/lang/String;
     305: astore        7
     307: aload         7
     309: invokestatic  #36                 // Method java/lang/Float.parseFloat:(Ljava/lang/String;)F
     312: fstore        9
     314: goto          356
     317: astore        10
     319: getstatic     #18                 // Field logger:Lorg/apache/dubbo/common/logger/ErrorTypeAwareLogger;
     322: ldc           #38                 // String 0-2
     324: ldc           #39                 // String
     326: ldc           #39                 // String
     328: new           #19                 // class java/lang/StringBuilder
     331: dup
     332: invokespecial #20                 // Method java/lang/StringBuilder."<init>":()V
     335: ldc           #40                 // String Invalid migration threshold
     337: invokevirtual #22                 // Method java/lang/StringBuilder.append:(Ljava/lang/String;)Ljava/lang/StringBuilder;
     340: aload         7
     342: invokevirtual #22                 // Method java/lang/StringBuilder.append:(Ljava/lang/String;)Ljava/lang/StringBuilder;
     345: invokevirtual #25                 // Method java/lang/StringBuilder.toString:()Ljava/lang/String;
     348: invokeinterface #41,  5           // InterfaceMethod org/apache/dubbo/common/logger/ErrorTypeAwareLogger.error:(Ljava/lang/String;Ljava/lang/String;Ljava/lang/String;Ljava/lang/String;)V
     353: fconst_0
     354: fstore        9
     356: getstatic     #18                 // Field logger:Lorg/apache/dubbo/common/logger/ErrorTypeAwareLogger;
     359: new           #19                 // class java/lang/StringBuilder
     362: dup
     363: invokespecial #20                 // Method java/lang/StringBuilder."<init>":()V
     366: ldc           #42                 // String serviceKey:
     368: invokevirtual #22                 // Method java/lang/StringBuilder.append:(Ljava/lang/String;)Ljava/lang/StringBuilder;
     371: aload_2
     372: invokeinterface #6,  1            // InterfaceMethod org/apache/dubbo/rpc/cluster/ClusterInvoker.getUrl:()Lorg/apache/dubbo/common/URL;
     377: invokevirtual #43                 // Method org/apache/dubbo/common/URL.getServiceKey:()Ljava/lang/String;
     380: invokevirtual #22                 // Method java/lang/StringBuilder.append:(Ljava/lang/String;)Ljava/lang/StringBuilder;
     383: ldc           #44                 // String  Instance address size
     385: invokevirtual #22                 // Method java/lang/StringBuilder.append:(Ljava/lang/String;)Ljava/lang/StringBuilder;
     388: iload         5
     390: invokevirtual #45                 // Method java/lang/StringBuilder.append:(I)Ljava/lang/StringBuilder;
     393: ldc           #46                 // String , interface address size
     395: invokevirtual #22                 // Method java/lang/StringBuilder.append:(Ljava/lang/String;)Ljava/lang/StringBuilder;
     398: iload         6
     400: invokevirtual #45                 // Method java/lang/StringBuilder.append:(I)Ljava/lang/StringBuilder;
     403: ldc           #47                 // String , threshold
     405: invokevirtual #22                 // Method java/lang/StringBuilder.append:(Ljava/lang/String;)Ljava/lang/StringBuilder;
     408: fload         9
     410: invokevirtual #48                 // Method java/lang/StringBuilder.append:(F)Ljava/lang/StringBuilder;
     413: invokevirtual #25                 // Method java/lang/StringBuilder.toString:()Ljava/lang/String;
     416: invokeinterface #26,  2           // InterfaceMethod org/apache/dubbo/common/logger/ErrorTypeAwareLogger.info:(Ljava/lang/String;)V
     421: iload         5
     423: ifeq          433
     426: iload         6
     428: ifne          433
     431: iconst_1
     432: ireturn
     433: iload         5
     435: ifne          445
     438: iload         6
     440: ifne          445
     443: iconst_0
     444: ireturn
     445: iload         5
     447: i2f
     448: iload         6
     450: i2f
     451: fdiv
     452: fload         9
     454: fcmpl
     455: iflt          462
     458: iconst_1
     459: goto          463
     462: iconst_0
     463: ireturn
    Exception table:
       from    to  target type
         307   314   317   Class java/lang/Exception

  private <T> int getAddressSize(org.apache.dubbo.rpc.cluster.ClusterInvoker<T>);
    Code:
       0: aload_1
       1: ifnonnull     6
       4: iconst_m1
       5: ireturn
       6: aload_1
       7: invokeinterface #49,  1           // InterfaceMethod org/apache/dubbo/rpc/cluster/ClusterInvoker.getDirectory:()Lorg/apache/dubbo/rpc/cluster/Directory;
      12: invokeinterface #50,  1           // InterfaceMethod org/apache/dubbo/rpc/cluster/Directory.getAllInvokers:()Ljava/util/List;
      17: astore_2
      18: aload_2
      19: invokestatic  #51                 // Method org/apache/dubbo/common/utils/CollectionUtils.isNotEmpty:(Ljava/util/Collection;)Z
      22: ifeq          34
      25: aload_2
      26: invokeinterface #52,  1           // InterfaceMethod java/util/List.size:()I
      31: goto          35
      34: iconst_0
      35: ireturn

  public java.util.Map<java.lang.String, java.lang.Integer> getAddressSize(java.lang.String);
    Code:
       0: aload_0
       1: getfield      #5                  // Field serviceMigrationData:Ljava/util/concurrent/ConcurrentMap;
       4: aload_1
       5: invokeinterface #53,  2           // InterfaceMethod java/util/concurrent/ConcurrentMap.get:(Ljava/lang/Object;)Ljava/lang/Object;
      10: checkcast     #10                 // class java/util/Map
      13: areturn

  private java.lang.String getInvokerType(org.apache.dubbo.rpc.cluster.ClusterInvoker<?>);
    Code:
       0: aload_1
       1: invokeinterface #54,  1           // InterfaceMethod org/apache/dubbo/rpc/cluster/ClusterInvoker.isServiceDiscovery:()Z
       6: ifeq          12
       9: ldc           #55                 // String instance
      11: areturn
      12: ldc           #56                 // String interface
      14: areturn

  private static java.util.Map lambda$shouldMigrate$0(java.lang.String);
    Code:
       0: new           #3                  // class java/util/concurrent/ConcurrentHashMap
       3: dup
       4: invokespecial #4                  // Method java/util/concurrent/ConcurrentHashMap."<init>":()V
       7: areturn

  static {};
    Code:
       0: ldc           #12                 // class org/apache/dubbo/registry/client/migration/DefaultMigrationAddressComparator
       2: invokestatic  #57                 // Method org/apache/dubbo/common/logger/LoggerFactory.getErrorTypeAwareLogger:(Ljava/lang/Class;)Lorg/apache/dubbo/common/logger/ErrorTypeAwareLogger;
       5: putstatic     #18                 // Field logger:Lorg/apache/dubbo/common/logger/ErrorTypeAwareLogger;
       8: return
}
