Compiled from "ServiceDiscoveryMigrationInvoker.java"
public class org.apache.dubbo.registry.client.migration.ServiceDiscoveryMigrationInvoker<T> extends org.apache.dubbo.registry.client.migration.MigrationInvoker<T> {
  private static final org.apache.dubbo.common.logger.ErrorTypeAwareLogger logger;

  public org.apache.dubbo.registry.client.migration.ServiceDiscoveryMigrationInvoker(org.apache.dubbo.registry.integration.RegistryProtocol, org.apache.dubbo.rpc.cluster.Cluster, org.apache.dubbo.registry.Registry, java.lang.Class<T>, org.apache.dubbo.common.URL, org.apache.dubbo.common.URL);
    Code:
       0: aload_0
       1: aload_1
       2: aload_2
       3: aload_3
       4: aload         4
       6: aload         5
       8: aload         6
      10: invokespecial #1                  // Method org/apache/dubbo/registry/client/migration/MigrationInvoker."<init>":(Lorg/apache/dubbo/registry/integration/RegistryProtocol;Lorg/apache/dubbo/rpc/cluster/Cluster;Lorg/apache/dubbo/registry/Registry;Ljava/lang/Class;Lorg/apache/dubbo/common/URL;Lorg/apache/dubbo/common/URL;)V
      13: return

  public boolean isServiceDiscovery();
    Code:
       0: iconst_1
       1: ireturn

  public boolean migrateToForceInterfaceInvoker(org.apache.dubbo.registry.client.migration.model.MigrationRule);
    Code:
       0: new           #2                  // class java/util/concurrent/CountDownLatch
       3: dup
       4: iconst_0
       5: invokespecial #3                  // Method java/util/concurrent/CountDownLatch."<init>":(I)V
       8: astore_2
       9: aload_0
      10: aload_2
      11: invokevirtual #4                  // Method refreshServiceDiscoveryInvoker:(Ljava/util/concurrent/CountDownLatch;)V
      14: aload_0
      15: aload_0
      16: invokevirtual #5                  // Method getServiceDiscoveryInvoker:()Lorg/apache/dubbo/rpc/cluster/ClusterInvoker;
      19: invokevirtual #6                  // Method setCurrentAvailableInvoker:(Lorg/apache/dubbo/rpc/cluster/ClusterInvoker;)V
      22: iconst_1
      23: ireturn

  public void migrateToApplicationFirstInvoker(org.apache.dubbo.registry.client.migration.model.MigrationRule);
    Code:
       0: new           #2                  // class java/util/concurrent/CountDownLatch
       3: dup
       4: iconst_0
       5: invokespecial #3                  // Method java/util/concurrent/CountDownLatch."<init>":(I)V
       8: astore_2
       9: aload_0
      10: aload_2
      11: invokevirtual #4                  // Method refreshServiceDiscoveryInvoker:(Ljava/util/concurrent/CountDownLatch;)V
      14: aload_0
      15: aload_0
      16: invokevirtual #5                  // Method getServiceDiscoveryInvoker:()Lorg/apache/dubbo/rpc/cluster/ClusterInvoker;
      19: invokevirtual #6                  // Method setCurrentAvailableInvoker:(Lorg/apache/dubbo/rpc/cluster/ClusterInvoker;)V
      22: return

  public org.apache.dubbo.rpc.Result invoke(org.apache.dubbo.rpc.Invocation) throws org.apache.dubbo.rpc.RpcException;
    Code:
       0: aload_0
       1: invokevirtual #5                  // Method getServiceDiscoveryInvoker:()Lorg/apache/dubbo/rpc/cluster/ClusterInvoker;
       4: astore_2
       5: aload_2
       6: ifnonnull     41
       9: new           #7                  // class java/lang/IllegalStateException
      12: dup
      13: new           #8                  // class java/lang/StringBuilder
      16: dup
      17: invokespecial #9                  // Method java/lang/StringBuilder."<init>":()V
      20: ldc           #10                 // String There\'s no service discovery invoker available for service
      22: invokevirtual #11                 // Method java/lang/StringBuilder.append:(Ljava/lang/String;)Ljava/lang/StringBuilder;
      25: aload_1
      26: invokeinterface #12,  1           // InterfaceMethod org/apache/dubbo/rpc/Invocation.getServiceName:()Ljava/lang/String;
      31: invokevirtual #11                 // Method java/lang/StringBuilder.append:(Ljava/lang/String;)Ljava/lang/StringBuilder;
      34: invokevirtual #13                 // Method java/lang/StringBuilder.toString:()Ljava/lang/String;
      37: invokespecial #14                 // Method java/lang/IllegalStateException."<init>":(Ljava/lang/String;)V
      40: athrow
      41: aload_2
      42: aload_1
      43: invokeinterface #15,  2           // InterfaceMethod org/apache/dubbo/rpc/cluster/ClusterInvoker.invoke:(Lorg/apache/dubbo/rpc/Invocation;)Lorg/apache/dubbo/rpc/Result;
      48: areturn

  static {};
    Code:
       0: ldc           #16                 // class org/apache/dubbo/registry/client/migration/ServiceDiscoveryMigrationInvoker
       2: invokestatic  #17                 // Method org/apache/dubbo/common/logger/LoggerFactory.getErrorTypeAwareLogger:(Ljava/lang/Class;)Lorg/apache/dubbo/common/logger/ErrorTypeAwareLogger;
       5: putstatic     #18                 // Field logger:Lorg/apache/dubbo/common/logger/ErrorTypeAwareLogger;
       8: return
}
