Compiled from "ClearTelnetHandler.java"
public class org.apache.dubbo.remoting.telnet.support.command.ClearTelnetHandler implements org.apache.dubbo.remoting.telnet.TelnetHandler {
  private static final int MAX_LINES;

  public org.apache.dubbo.remoting.telnet.support.command.ClearTelnetHandler();
    Code:
       0: aload_0
       1: invokespecial #1                  // Method java/lang/Object."<init>":()V
       4: return

  public java.lang.String telnet(org.apache.dubbo.remoting.Channel, java.lang.String);
    Code:
       0: bipush        100
       2: istore_3
       3: aload_2
       4: invokevirtual #2                  // Method java/lang/String.length:()I
       7: ifle          53
      10: aload_2
      11: invokestatic  #3                  // Method org/apache/dubbo/common/utils/StringUtils.isNumber:(Ljava/lang/String;)Z
      14: ifne          42
      17: new           #4                  // class java/lang/StringBuilder
      20: dup
      21: invokespecial #5                  // Method java/lang/StringBuilder."<init>":()V
      24: ldc           #6                  // String Illegal lines
      26: invokevirtual #7                  // Method java/lang/StringBuilder.append:(Ljava/lang/String;)Ljava/lang/StringBuilder;
      29: aload_2
      30: invokevirtual #7                  // Method java/lang/StringBuilder.append:(Ljava/lang/String;)Ljava/lang/StringBuilder;
      33: ldc           #8                  // String , must be integer.
      35: invokevirtual #7                  // Method java/lang/StringBuilder.append:(Ljava/lang/String;)Ljava/lang/StringBuilder;
      38: invokevirtual #9                  // Method java/lang/StringBuilder.toString:()Ljava/lang/String;
      41: areturn
      42: sipush        1000
      45: aload_2
      46: invokestatic  #11                 // Method java/lang/Integer.parseInt:(Ljava/lang/String;)I
      49: invokestatic  #12                 // Method java/lang/Math.min:(II)I
      52: istore_3
      53: new           #4                  // class java/lang/StringBuilder
      56: dup
      57: invokespecial #5                  // Method java/lang/StringBuilder."<init>":()V
      60: astore        4
      62: iconst_0
      63: istore        5
      65: iload         5
      67: iload_3
      68: if_icmpge     85
      71: aload         4
      73: ldc           #13                 // String \r\n
      75: invokevirtual #7                  // Method java/lang/StringBuilder.append:(Ljava/lang/String;)Ljava/lang/StringBuilder;
      78: pop
      79: iinc          5, 1
      82: goto          65
      85: aload         4
      87: invokevirtual #9                  // Method java/lang/StringBuilder.toString:()Ljava/lang/String;
      90: areturn
}
