Compiled from "HelpTelnetHandler.java"
public class org.apache.dubbo.remoting.telnet.support.command.HelpTelnetHandler implements org.apache.dubbo.remoting.telnet.TelnetHandler {
  private final org.apache.dubbo.common.extension.ExtensionLoader<org.apache.dubbo.remoting.telnet.TelnetHandler> extensionLoader;

  private static final java.lang.String MAIN_HELP;

  private static java.util.Map<java.lang.String, java.lang.String> processedTable;

  public org.apache.dubbo.remoting.telnet.support.command.HelpTelnetHandler(org.apache.dubbo.rpc.model.FrameworkModel);
    Code:
       0: aload_0
       1: invokespecial #1                  // Method java/lang/Object."<init>":()V
       4: aload_0
       5: aload_1
       6: ldc           #2                  // class org/apache/dubbo/remoting/telnet/TelnetHandler
       8: invokevirtual #3                  // Method org/apache/dubbo/rpc/model/FrameworkModel.getExtensionLoader:(Ljava/lang/Class;)Lorg/apache/dubbo/common/extension/ExtensionLoader;
      11: putfield      #4                  // Field extensionLoader:Lorg/apache/dubbo/common/extension/ExtensionLoader;
      14: return

  public java.lang.String telnet(org.apache.dubbo.remoting.Channel, java.lang.String);
    Code:
       0: aload_2
       1: invokevirtual #5                  // Method java/lang/String.length:()I
       4: ifle          26
       7: getstatic     #6                  // Field processedTable:Ljava/util/Map;
      10: aload_2
      11: aload_0
      12: invokedynamic #7,  0              // InvokeDynamic #0:apply:(Lorg/apache/dubbo/remoting/telnet/support/command/HelpTelnetHandler;)Ljava/util/function/Function;
      17: invokeinterface #8,  3            // InterfaceMethod java/util/Map.computeIfAbsent:(Ljava/lang/Object;Ljava/util/function/Function;)Ljava/lang/Object;
      22: checkcast     #9                  // class java/lang/String
      25: areturn
      26: getstatic     #6                  // Field processedTable:Ljava/util/Map;
      29: ldc           #11                 // String mainHelp
      31: aload_0
      32: aload_1
      33: invokedynamic #12,  0             // InvokeDynamic #1:apply:(Lorg/apache/dubbo/remoting/telnet/support/command/HelpTelnetHandler;Lorg/apache/dubbo/remoting/Channel;)Ljava/util/function/Function;
      38: invokeinterface #8,  3            // InterfaceMethod java/util/Map.computeIfAbsent:(Ljava/lang/Object;Ljava/util/function/Function;)Ljava/lang/Object;
      43: checkcast     #9                  // class java/lang/String
      46: areturn

  private java.lang.String generateForOneCommand(java.lang.String);
    Code:
       0: aload_0
       1: getfield      #4                  // Field extensionLoader:Lorg/apache/dubbo/common/extension/ExtensionLoader;
       4: aload_1
       5: invokevirtual #13                 // Method org/apache/dubbo/common/extension/ExtensionLoader.hasExtension:(Ljava/lang/String;)Z
       8: ifne          31
      11: new           #14                 // class java/lang/StringBuilder
      14: dup
      15: invokespecial #15                 // Method java/lang/StringBuilder."<init>":()V
      18: ldc           #16                 // String No such command
      20: invokevirtual #17                 // Method java/lang/StringBuilder.append:(Ljava/lang/String;)Ljava/lang/StringBuilder;
      23: aload_1
      24: invokevirtual #17                 // Method java/lang/StringBuilder.append:(Ljava/lang/String;)Ljava/lang/StringBuilder;
      27: invokevirtual #18                 // Method java/lang/StringBuilder.toString:()Ljava/lang/String;
      30: areturn
      31: aload_0
      32: getfield      #4                  // Field extensionLoader:Lorg/apache/dubbo/common/extension/ExtensionLoader;
      35: aload_1
      36: invokevirtual #19                 // Method org/apache/dubbo/common/extension/ExtensionLoader.getExtension:(Ljava/lang/String;)Ljava/lang/Object;
      39: checkcast     #2                  // class org/apache/dubbo/remoting/telnet/TelnetHandler
      42: astore_2
      43: aload_2
      44: invokevirtual #20                 // Method java/lang/Object.getClass:()Ljava/lang/Class;
      47: ldc           #21                 // class org/apache/dubbo/remoting/telnet/support/Help
      49: invokevirtual #22                 // Method java/lang/Class.getAnnotation:(Ljava/lang/Class;)Ljava/lang/annotation/Annotation;
      52: checkcast     #21                 // class org/apache/dubbo/remoting/telnet/support/Help
      55: astore_3
      56: new           #14                 // class java/lang/StringBuilder
      59: dup
      60: invokespecial #15                 // Method java/lang/StringBuilder."<init>":()V
      63: astore        4
      65: aload         4
      67: ldc           #23                 // String Command:\r\n
      69: invokevirtual #17                 // Method java/lang/StringBuilder.append:(Ljava/lang/String;)Ljava/lang/StringBuilder;
      72: pop
      73: aload         4
      75: new           #14                 // class java/lang/StringBuilder
      78: dup
      79: invokespecial #15                 // Method java/lang/StringBuilder."<init>":()V
      82: aload_1
      83: invokevirtual #17                 // Method java/lang/StringBuilder.append:(Ljava/lang/String;)Ljava/lang/StringBuilder;
      86: ldc           #24                 // String
      88: invokevirtual #17                 // Method java/lang/StringBuilder.append:(Ljava/lang/String;)Ljava/lang/StringBuilder;
      91: aload_3
      92: invokeinterface #25,  1           // InterfaceMethod org/apache/dubbo/remoting/telnet/support/Help.parameter:()Ljava/lang/String;
      97: ldc           #26                 // String \r\n
      99: ldc           #24                 // String
     101: invokevirtual #27                 // Method java/lang/String.replace:(Ljava/lang/CharSequence;Ljava/lang/CharSequence;)Ljava/lang/String;
     104: ldc           #28                 // String \n
     106: ldc           #24                 // String
     108: invokevirtual #27                 // Method java/lang/String.replace:(Ljava/lang/CharSequence;Ljava/lang/CharSequence;)Ljava/lang/String;
     111: invokevirtual #17                 // Method java/lang/StringBuilder.append:(Ljava/lang/String;)Ljava/lang/StringBuilder;
     114: invokevirtual #18                 // Method java/lang/StringBuilder.toString:()Ljava/lang/String;
     117: invokevirtual #17                 // Method java/lang/StringBuilder.append:(Ljava/lang/String;)Ljava/lang/StringBuilder;
     120: pop
     121: aload         4
     123: ldc           #29                 // String \r\nSummary:\r\n
     125: invokevirtual #17                 // Method java/lang/StringBuilder.append:(Ljava/lang/String;)Ljava/lang/StringBuilder;
     128: pop
     129: aload         4
     131: aload_3
     132: invokeinterface #30,  1           // InterfaceMethod org/apache/dubbo/remoting/telnet/support/Help.summary:()Ljava/lang/String;
     137: ldc           #26                 // String \r\n
     139: ldc           #24                 // String
     141: invokevirtual #27                 // Method java/lang/String.replace:(Ljava/lang/CharSequence;Ljava/lang/CharSequence;)Ljava/lang/String;
     144: ldc           #28                 // String \n
     146: ldc           #24                 // String
     148: invokevirtual #27                 // Method java/lang/String.replace:(Ljava/lang/CharSequence;Ljava/lang/CharSequence;)Ljava/lang/String;
     151: invokevirtual #17                 // Method java/lang/StringBuilder.append:(Ljava/lang/String;)Ljava/lang/StringBuilder;
     154: pop
     155: aload         4
     157: ldc           #31                 // String \r\nDetail:\r\n
     159: invokevirtual #17                 // Method java/lang/StringBuilder.append:(Ljava/lang/String;)Ljava/lang/StringBuilder;
     162: pop
     163: aload         4
     165: aload_3
     166: invokeinterface #32,  1           // InterfaceMethod org/apache/dubbo/remoting/telnet/support/Help.detail:()Ljava/lang/String;
     171: ldc           #26                 // String \r\n
     173: ldc           #33                 // String     \r\n
     175: invokevirtual #27                 // Method java/lang/String.replace:(Ljava/lang/CharSequence;Ljava/lang/CharSequence;)Ljava/lang/String;
     178: ldc           #28                 // String \n
     180: ldc           #34                 // String     \n
     182: invokevirtual #27                 // Method java/lang/String.replace:(Ljava/lang/CharSequence;Ljava/lang/CharSequence;)Ljava/lang/String;
     185: invokevirtual #17                 // Method java/lang/StringBuilder.append:(Ljava/lang/String;)Ljava/lang/StringBuilder;
     188: pop
     189: aload         4
     191: invokevirtual #18                 // Method java/lang/StringBuilder.toString:()Ljava/lang/String;
     194: areturn

  private java.lang.String generateForAllCommand(org.apache.dubbo.remoting.Channel);
    Code:
       0: new           #35                 // class java/util/ArrayList
       3: dup
       4: invokespecial #36                 // Method java/util/ArrayList."<init>":()V
       7: astore_2
       8: aload_0
       9: getfield      #4                  // Field extensionLoader:Lorg/apache/dubbo/common/extension/ExtensionLoader;
      12: aload_1
      13: invokeinterface #37,  1           // InterfaceMethod org/apache/dubbo/remoting/Channel.getUrl:()Lorg/apache/dubbo/common/URL;
      18: ldc           #38                 // String telnet
      20: invokevirtual #39                 // Method org/apache/dubbo/common/extension/ExtensionLoader.getActivateExtension:(Lorg/apache/dubbo/common/URL;Ljava/lang/String;)Ljava/util/List;
      23: astore_3
      24: aload_3
      25: invokestatic  #40                 // Method org/apache/dubbo/common/utils/CollectionUtils.isNotEmpty:(Ljava/util/Collection;)Z
      28: ifeq          296
      31: aload_3
      32: invokeinterface #41,  1           // InterfaceMethod java/util/List.iterator:()Ljava/util/Iterator;
      37: astore        4
      39: aload         4
      41: invokeinterface #42,  1           // InterfaceMethod java/util/Iterator.hasNext:()Z
      46: ifeq          296
      49: aload         4
      51: invokeinterface #43,  1           // InterfaceMethod java/util/Iterator.next:()Ljava/lang/Object;
      56: checkcast     #2                  // class org/apache/dubbo/remoting/telnet/TelnetHandler
      59: astore        5
      61: aload         5
      63: invokevirtual #20                 // Method java/lang/Object.getClass:()Ljava/lang/Class;
      66: ldc           #21                 // class org/apache/dubbo/remoting/telnet/support/Help
      68: invokevirtual #22                 // Method java/lang/Class.getAnnotation:(Ljava/lang/Class;)Ljava/lang/annotation/Annotation;
      71: checkcast     #21                 // class org/apache/dubbo/remoting/telnet/support/Help
      74: astore        6
      76: new           #35                 // class java/util/ArrayList
      79: dup
      80: invokespecial #36                 // Method java/util/ArrayList."<init>":()V
      83: astore        7
      85: new           #14                 // class java/lang/StringBuilder
      88: dup
      89: invokespecial #15                 // Method java/lang/StringBuilder."<init>":()V
      92: ldc           #24                 // String
      94: invokevirtual #17                 // Method java/lang/StringBuilder.append:(Ljava/lang/String;)Ljava/lang/StringBuilder;
      97: aload_0
      98: getfield      #4                  // Field extensionLoader:Lorg/apache/dubbo/common/extension/ExtensionLoader;
     101: aload         5
     103: invokevirtual #44                 // Method org/apache/dubbo/common/extension/ExtensionLoader.getExtensionName:(Ljava/lang/Object;)Ljava/lang/String;
     106: invokevirtual #17                 // Method java/lang/StringBuilder.append:(Ljava/lang/String;)Ljava/lang/StringBuilder;
     109: ldc           #24                 // String
     111: invokevirtual #17                 // Method java/lang/StringBuilder.append:(Ljava/lang/String;)Ljava/lang/StringBuilder;
     114: aload         6
     116: ifnull        143
     119: aload         6
     121: invokeinterface #25,  1           // InterfaceMethod org/apache/dubbo/remoting/telnet/support/Help.parameter:()Ljava/lang/String;
     126: ldc           #26                 // String \r\n
     128: ldc           #24                 // String
     130: invokevirtual #27                 // Method java/lang/String.replace:(Ljava/lang/CharSequence;Ljava/lang/CharSequence;)Ljava/lang/String;
     133: ldc           #28                 // String \n
     135: ldc           #24                 // String
     137: invokevirtual #27                 // Method java/lang/String.replace:(Ljava/lang/CharSequence;Ljava/lang/CharSequence;)Ljava/lang/String;
     140: goto          145
     143: ldc           #45                 // String
     145: invokevirtual #17                 // Method java/lang/StringBuilder.append:(Ljava/lang/String;)Ljava/lang/StringBuilder;
     148: invokevirtual #18                 // Method java/lang/StringBuilder.toString:()Ljava/lang/String;
     151: astore        8
     153: aload         7
     155: aload         8
     157: invokevirtual #5                  // Method java/lang/String.length:()I
     160: bipush        55
     162: if_icmple     194
     165: new           #14                 // class java/lang/StringBuilder
     168: dup
     169: invokespecial #15                 // Method java/lang/StringBuilder."<init>":()V
     172: aload         8
     174: iconst_0
     175: bipush        55
     177: invokevirtual #46                 // Method java/lang/String.substring:(II)Ljava/lang/String;
     180: invokevirtual #17                 // Method java/lang/StringBuilder.append:(Ljava/lang/String;)Ljava/lang/StringBuilder;
     183: ldc           #47                 // String ...
     185: invokevirtual #17                 // Method java/lang/StringBuilder.append:(Ljava/lang/String;)Ljava/lang/StringBuilder;
     188: invokevirtual #18                 // Method java/lang/StringBuilder.toString:()Ljava/lang/String;
     191: goto          196
     194: aload         8
     196: invokeinterface #48,  2           // InterfaceMethod java/util/List.add:(Ljava/lang/Object;)Z
     201: pop
     202: aload         6
     204: ifnull        231
     207: aload         6
     209: invokeinterface #30,  1           // InterfaceMethod org/apache/dubbo/remoting/telnet/support/Help.summary:()Ljava/lang/String;
     214: ldc           #26                 // String \r\n
     216: ldc           #24                 // String
     218: invokevirtual #27                 // Method java/lang/String.replace:(Ljava/lang/CharSequence;Ljava/lang/CharSequence;)Ljava/lang/String;
     221: ldc           #28                 // String \n
     223: ldc           #24                 // String
     225: invokevirtual #27                 // Method java/lang/String.replace:(Ljava/lang/CharSequence;Ljava/lang/CharSequence;)Ljava/lang/String;
     228: goto          233
     231: ldc           #45                 // String
     233: astore        9
     235: aload         7
     237: aload         9
     239: invokevirtual #5                  // Method java/lang/String.length:()I
     242: bipush        55
     244: if_icmple     276
     247: new           #14                 // class java/lang/StringBuilder
     250: dup
     251: invokespecial #15                 // Method java/lang/StringBuilder."<init>":()V
     254: aload         9
     256: iconst_0
     257: bipush        55
     259: invokevirtual #46                 // Method java/lang/String.substring:(II)Ljava/lang/String;
     262: invokevirtual #17                 // Method java/lang/StringBuilder.append:(Ljava/lang/String;)Ljava/lang/StringBuilder;
     265: ldc           #47                 // String ...
     267: invokevirtual #17                 // Method java/lang/StringBuilder.append:(Ljava/lang/String;)Ljava/lang/StringBuilder;
     270: invokevirtual #18                 // Method java/lang/StringBuilder.toString:()Ljava/lang/String;
     273: goto          278
     276: aload         9
     278: invokeinterface #48,  2           // InterfaceMethod java/util/List.add:(Ljava/lang/Object;)Z
     283: pop
     284: aload_2
     285: aload         7
     287: invokeinterface #48,  2           // InterfaceMethod java/util/List.add:(Ljava/lang/Object;)Z
     292: pop
     293: goto          39
     296: new           #14                 // class java/lang/StringBuilder
     299: dup
     300: invokespecial #15                 // Method java/lang/StringBuilder."<init>":()V
     303: ldc           #49                 // String Please input \"help [command]\" show detail.\r\n
     305: invokevirtual #17                 // Method java/lang/StringBuilder.append:(Ljava/lang/String;)Ljava/lang/StringBuilder;
     308: aload_2
     309: invokestatic  #50                 // Method org/apache/dubbo/remoting/telnet/support/TelnetUtils.toList:(Ljava/util/List;)Ljava/lang/String;
     312: invokevirtual #17                 // Method java/lang/StringBuilder.append:(Ljava/lang/String;)Ljava/lang/StringBuilder;
     315: invokevirtual #18                 // Method java/lang/StringBuilder.toString:()Ljava/lang/String;
     318: areturn

  private java.lang.String lambda$telnet$1(org.apache.dubbo.remoting.Channel, java.lang.String);
    Code:
       0: aload_0
       1: aload_1
       2: invokespecial #51                 // Method generateForAllCommand:(Lorg/apache/dubbo/remoting/Channel;)Ljava/lang/String;
       5: areturn

  private java.lang.String lambda$telnet$0(java.lang.String);
    Code:
       0: aload_0
       1: aload_1
       2: invokespecial #52                 // Method generateForOneCommand:(Ljava/lang/String;)Ljava/lang/String;
       5: areturn

  static {};
    Code:
       0: new           #53                 // class java/util/WeakHashMap
       3: dup
       4: invokespecial #54                 // Method java/util/WeakHashMap."<init>":()V
       7: putstatic     #6                  // Field processedTable:Ljava/util/Map;
      10: return
}
