Compiled from "StatusTelnetHandler.java"
public class org.apache.dubbo.remoting.telnet.support.command.StatusTelnetHandler implements org.apache.dubbo.remoting.telnet.TelnetHandler {
  public org.apache.dubbo.remoting.telnet.support.command.StatusTelnetHandler();
    Code:
       0: aload_0
       1: invokespecial #2                  // Method java/lang/Object."<init>":()V
       4: return

  public java.lang.String telnet(org.apache.dubbo.remoting.Channel, java.lang.String);
    Code:
       0: aload_1
       1: invokeinterface #3,  1            // InterfaceMethod org/apache/dubbo/remoting/Channel.getUrl:()Lorg/apache/dubbo/common/URL;
       6: invokevirtual #4                  // Method org/apache/dubbo/common/URL.getScopeModel:()Lorg/apache/dubbo/rpc/model/ScopeModel;
       9: invokestatic  #5                  // Method org/apache/dubbo/rpc/model/ScopeModelUtil.getApplicationModel:(Lorg/apache/dubbo/rpc/model/ScopeModel;)Lorg/apache/dubbo/rpc/model/ApplicationModel;
      12: astore_3
      13: aload_3
      14: ldc           #6                  // class org/apache/dubbo/common/status/StatusChecker
      16: invokevirtual #7                  // Method org/apache/dubbo/rpc/model/ApplicationModel.getExtensionLoader:(Ljava/lang/Class;)Lorg/apache/dubbo/common/extension/ExtensionLoader;
      19: astore        4
      21: ldc           #8                  // String -l
      23: aload_2
      24: invokevirtual #9                  // Method java/lang/String.equals:(Ljava/lang/Object;)Z
      27: ifeq          341
      30: aload         4
      32: aload_1
      33: invokeinterface #3,  1            // InterfaceMethod org/apache/dubbo/remoting/Channel.getUrl:()Lorg/apache/dubbo/common/URL;
      38: ldc           #10                 // String status
      40: invokevirtual #11                 // Method org/apache/dubbo/common/extension/ExtensionLoader.getActivateExtension:(Lorg/apache/dubbo/common/URL;Ljava/lang/String;)Ljava/util/List;
      43: astore        5
      45: iconst_3
      46: anewarray     #12                 // class java/lang/String
      49: dup
      50: iconst_0
      51: ldc           #13                 // String resource
      53: aastore
      54: dup
      55: iconst_1
      56: ldc           #10                 // String status
      58: aastore
      59: dup
      60: iconst_2
      61: ldc           #14                 // String message
      63: aastore
      64: astore        6
      66: new           #15                 // class java/util/ArrayList
      69: dup
      70: invokespecial #16                 // Method java/util/ArrayList."<init>":()V
      73: astore        7
      75: new           #17                 // class java/util/HashMap
      78: dup
      79: invokespecial #18                 // Method java/util/HashMap."<init>":()V
      82: astore        8
      84: aload         5
      86: invokestatic  #19                 // Method org/apache/dubbo/common/utils/CollectionUtils.isNotEmpty:(Ljava/util/Collection;)Z
      89: ifeq          268
      92: aload         5
      94: invokeinterface #20,  1           // InterfaceMethod java/util/List.iterator:()Ljava/util/Iterator;
      99: astore        9
     101: aload         9
     103: invokeinterface #21,  1           // InterfaceMethod java/util/Iterator.hasNext:()Z
     108: ifeq          268
     111: aload         9
     113: invokeinterface #22,  1           // InterfaceMethod java/util/Iterator.next:()Ljava/lang/Object;
     118: checkcast     #6                  // class org/apache/dubbo/common/status/StatusChecker
     121: astore        10
     123: aload         4
     125: aload         10
     127: invokevirtual #23                 // Method org/apache/dubbo/common/extension/ExtensionLoader.getExtensionName:(Ljava/lang/Object;)Ljava/lang/String;
     130: astore        11
     132: aload         10
     134: invokeinterface #24,  1           // InterfaceMethod org/apache/dubbo/common/status/StatusChecker.check:()Lorg/apache/dubbo/common/status/Status;
     139: astore        12
     141: goto          163
     144: astore        13
     146: new           #26                 // class org/apache/dubbo/common/status/Status
     149: dup
     150: getstatic     #27                 // Field org/apache/dubbo/common/status/Status$Level.ERROR:Lorg/apache/dubbo/common/status/Status$Level;
     153: aload         13
     155: invokevirtual #28                 // Method java/lang/Throwable.getMessage:()Ljava/lang/String;
     158: invokespecial #29                 // Method org/apache/dubbo/common/status/Status."<init>":(Lorg/apache/dubbo/common/status/Status$Level;Ljava/lang/String;)V
     161: astore        12
     163: aload         8
     165: aload         11
     167: aload         12
     169: invokeinterface #30,  3           // InterfaceMethod java/util/Map.put:(Ljava/lang/Object;Ljava/lang/Object;)Ljava/lang/Object;
     174: pop
     175: aload         12
     177: invokevirtual #31                 // Method org/apache/dubbo/common/status/Status.getLevel:()Lorg/apache/dubbo/common/status/Status$Level;
     180: ifnull        265
     183: aload         12
     185: invokevirtual #31                 // Method org/apache/dubbo/common/status/Status.getLevel:()Lorg/apache/dubbo/common/status/Status$Level;
     188: getstatic     #32                 // Field org/apache/dubbo/common/status/Status$Level.UNKNOWN:Lorg/apache/dubbo/common/status/Status$Level;
     191: if_acmpeq     265
     194: new           #15                 // class java/util/ArrayList
     197: dup
     198: invokespecial #16                 // Method java/util/ArrayList."<init>":()V
     201: astore        13
     203: aload         13
     205: aload         11
     207: invokeinterface #33,  2           // InterfaceMethod java/util/List.add:(Ljava/lang/Object;)Z
     212: pop
     213: aload         13
     215: aload         12
     217: invokevirtual #31                 // Method org/apache/dubbo/common/status/Status.getLevel:()Lorg/apache/dubbo/common/status/Status$Level;
     220: invokestatic  #34                 // Method java/lang/String.valueOf:(Ljava/lang/Object;)Ljava/lang/String;
     223: invokeinterface #33,  2           // InterfaceMethod java/util/List.add:(Ljava/lang/Object;)Z
     228: pop
     229: aload         13
     231: aload         12
     233: invokevirtual #35                 // Method org/apache/dubbo/common/status/Status.getMessage:()Ljava/lang/String;
     236: ifnonnull     244
     239: ldc           #36                 // String
     241: goto          249
     244: aload         12
     246: invokevirtual #35                 // Method org/apache/dubbo/common/status/Status.getMessage:()Ljava/lang/String;
     249: invokeinterface #33,  2           // InterfaceMethod java/util/List.add:(Ljava/lang/Object;)Z
     254: pop
     255: aload         7
     257: aload         13
     259: invokeinterface #33,  2           // InterfaceMethod java/util/List.add:(Ljava/lang/Object;)Z
     264: pop
     265: goto          101
     268: aload         8
     270: invokestatic  #37                 // Method org/apache/dubbo/common/status/support/StatusUtils.getSummaryStatus:(Ljava/util/Map;)Lorg/apache/dubbo/common/status/Status;
     273: astore        9
     275: new           #15                 // class java/util/ArrayList
     278: dup
     279: invokespecial #16                 // Method java/util/ArrayList."<init>":()V
     282: astore        10
     284: aload         10
     286: ldc           #38                 // String summary
     288: invokeinterface #33,  2           // InterfaceMethod java/util/List.add:(Ljava/lang/Object;)Z
     293: pop
     294: aload         10
     296: aload         9
     298: invokevirtual #31                 // Method org/apache/dubbo/common/status/Status.getLevel:()Lorg/apache/dubbo/common/status/Status$Level;
     301: invokestatic  #34                 // Method java/lang/String.valueOf:(Ljava/lang/Object;)Ljava/lang/String;
     304: invokeinterface #33,  2           // InterfaceMethod java/util/List.add:(Ljava/lang/Object;)Z
     309: pop
     310: aload         10
     312: aload         9
     314: invokevirtual #35                 // Method org/apache/dubbo/common/status/Status.getMessage:()Ljava/lang/String;
     317: invokeinterface #33,  2           // InterfaceMethod java/util/List.add:(Ljava/lang/Object;)Z
     322: pop
     323: aload         7
     325: aload         10
     327: invokeinterface #33,  2           // InterfaceMethod java/util/List.add:(Ljava/lang/Object;)Z
     332: pop
     333: aload         6
     335: aload         7
     337: invokestatic  #39                 // Method org/apache/dubbo/remoting/telnet/support/TelnetUtils.toTable:([Ljava/lang/String;Ljava/util/List;)Ljava/lang/String;
     340: areturn
     341: aload_2
     342: invokevirtual #40                 // Method java/lang/String.length:()I
     345: ifle          373
     348: new           #41                 // class java/lang/StringBuilder
     351: dup
     352: invokespecial #42                 // Method java/lang/StringBuilder."<init>":()V
     355: ldc           #43                 // String Unsupported parameter
     357: invokevirtual #44                 // Method java/lang/StringBuilder.append:(Ljava/lang/String;)Ljava/lang/StringBuilder;
     360: aload_2
     361: invokevirtual #44                 // Method java/lang/StringBuilder.append:(Ljava/lang/String;)Ljava/lang/StringBuilder;
     364: ldc           #45                 // String  for status.
     366: invokevirtual #44                 // Method java/lang/StringBuilder.append:(Ljava/lang/String;)Ljava/lang/StringBuilder;
     369: invokevirtual #46                 // Method java/lang/StringBuilder.toString:()Ljava/lang/String;
     372: areturn
     373: aload_1
     374: invokeinterface #3,  1            // InterfaceMethod org/apache/dubbo/remoting/Channel.getUrl:()Lorg/apache/dubbo/common/URL;
     379: ldc           #10                 // String status
     381: invokevirtual #47                 // Method org/apache/dubbo/common/URL.getParameter:(Ljava/lang/String;)Ljava/lang/String;
     384: astore        5
     386: new           #17                 // class java/util/HashMap
     389: dup
     390: invokespecial #18                 // Method java/util/HashMap."<init>":()V
     393: astore        6
     395: aload         5
     397: invokestatic  #48                 // Method org/apache/dubbo/common/utils/StringUtils.isNotEmpty:(Ljava/lang/String;)Z
     400: ifeq          500
     403: getstatic     #49                 // Field org/apache/dubbo/common/constants/CommonConstants.COMMA_SPLIT_PATTERN:Ljava/util/regex/Pattern;
     406: aload         5
     408: invokevirtual #50                 // Method java/util/regex/Pattern.split:(Ljava/lang/CharSequence;)[Ljava/lang/String;
     411: astore        7
     413: aload         7
     415: astore        8
     417: aload         8
     419: arraylength
     420: istore        9
     422: iconst_0
     423: istore        10
     425: iload         10
     427: iload         9
     429: if_icmpge     500
     432: aload         8
     434: iload         10
     436: aaload
     437: astore        11
     439: aload         4
     441: aload         11
     443: invokevirtual #51                 // Method org/apache/dubbo/common/extension/ExtensionLoader.getExtension:(Ljava/lang/String;)Ljava/lang/Object;
     446: checkcast     #6                  // class org/apache/dubbo/common/status/StatusChecker
     449: astore        12
     451: aload         12
     453: invokeinterface #24,  1           // InterfaceMethod org/apache/dubbo/common/status/StatusChecker.check:()Lorg/apache/dubbo/common/status/Status;
     458: astore        13
     460: goto          482
     463: astore        14
     465: new           #26                 // class org/apache/dubbo/common/status/Status
     468: dup
     469: getstatic     #27                 // Field org/apache/dubbo/common/status/Status$Level.ERROR:Lorg/apache/dubbo/common/status/Status$Level;
     472: aload         14
     474: invokevirtual #28                 // Method java/lang/Throwable.getMessage:()Ljava/lang/String;
     477: invokespecial #29                 // Method org/apache/dubbo/common/status/Status."<init>":(Lorg/apache/dubbo/common/status/Status$Level;Ljava/lang/String;)V
     480: astore        13
     482: aload         6
     484: aload         11
     486: aload         13
     488: invokeinterface #30,  3           // InterfaceMethod java/util/Map.put:(Ljava/lang/Object;Ljava/lang/Object;)Ljava/lang/Object;
     493: pop
     494: iinc          10, 1
     497: goto          425
     500: aload         6
     502: invokestatic  #37                 // Method org/apache/dubbo/common/status/support/StatusUtils.getSummaryStatus:(Ljava/util/Map;)Lorg/apache/dubbo/common/status/Status;
     505: astore        7
     507: aload         7
     509: invokevirtual #31                 // Method org/apache/dubbo/common/status/Status.getLevel:()Lorg/apache/dubbo/common/status/Status$Level;
     512: invokestatic  #34                 // Method java/lang/String.valueOf:(Ljava/lang/Object;)Ljava/lang/String;
     515: areturn
    Exception table:
       from    to  target type
         132   141   144   Class java/lang/Throwable
         451   460   463   Class java/lang/Throwable
}
