Compiled from "AccessLogFilter.java"
public class org.apache.dubbo.rpc.filter.AccessLogFilter implements org.apache.dubbo.rpc.Filter {
  public static org.apache.dubbo.common.logger.ErrorTypeAwareLogger logger;

  private static final java.lang.String LOG_KEY;

  private static final int LOG_MAX_BUFFER;

  private static long LOG_OUTPUT_INTERVAL;

  private static final java.lang.String FILE_DATE_FORMAT;

  private final java.text.DateFormat fileNameFormatter;

  private final java.util.concurrent.ConcurrentMap<java.lang.String, java.util.Queue<org.apache.dubbo.rpc.support.AccessLogData>> logEntries;

  private final java.util.concurrent.atomic.AtomicBoolean scheduled;

  private java.util.concurrent.ScheduledFuture<?> future;

  private static final java.lang.String LINE_SEPARATOR;

  public org.apache.dubbo.rpc.filter.AccessLogFilter();
    Code:
       0: aload_0
       1: invokespecial #5                  // Method java/lang/Object."<init>":()V
       4: aload_0
       5: new           #6                  // class java/text/SimpleDateFormat
       8: dup
       9: ldc           #8                  // String yyyyMMdd
      11: invokespecial #9                  // Method java/text/SimpleDateFormat."<init>":(Ljava/lang/String;)V
      14: putfield      #10                 // Field fileNameFormatter:Ljava/text/DateFormat;
      17: aload_0
      18: new           #11                 // class java/util/concurrent/ConcurrentHashMap
      21: dup
      22: invokespecial #12                 // Method java/util/concurrent/ConcurrentHashMap."<init>":()V
      25: putfield      #4                  // Field logEntries:Ljava/util/concurrent/ConcurrentMap;
      28: aload_0
      29: new           #13                 // class java/util/concurrent/atomic/AtomicBoolean
      32: dup
      33: invokespecial #14                 // Method java/util/concurrent/atomic/AtomicBoolean."<init>":()V
      36: putfield      #15                 // Field scheduled:Ljava/util/concurrent/atomic/AtomicBoolean;
      39: return

  public org.apache.dubbo.rpc.Result invoke(org.apache.dubbo.rpc.Invoker<?>, org.apache.dubbo.rpc.Invocation) throws org.apache.dubbo.rpc.RpcException;
    Code:
       0: aload_1
       1: invokeinterface #16,  1           // InterfaceMethod org/apache/dubbo/rpc/Invoker.getUrl:()Lorg/apache/dubbo/common/URL;
       6: ldc           #17                 // String accesslog
       8: invokevirtual #18                 // Method org/apache/dubbo/common/URL.getParameter:(Ljava/lang/String;)Ljava/lang/String;
      11: astore_3
      12: aload_1
      13: invokeinterface #16,  1           // InterfaceMethod org/apache/dubbo/rpc/Invoker.getUrl:()Lorg/apache/dubbo/common/URL;
      18: ldc           #19                 // String accesslog.fixed.path
      20: iconst_1
      21: invokevirtual #20                 // Method org/apache/dubbo/common/URL.getParameter:(Ljava/lang/String;Z)Z
      24: istore        4
      26: aload_3
      27: invokestatic  #21                 // Method org/apache/dubbo/common/utils/StringUtils.isEmpty:(Ljava/lang/String;)Z
      30: ifeq          81
      33: aload_0
      34: getfield      #22                 // Field future:Ljava/util/concurrent/ScheduledFuture;
      37: ifnull        73
      40: aload_0
      41: getfield      #22                 // Field future:Ljava/util/concurrent/ScheduledFuture;
      44: invokeinterface #23,  1           // InterfaceMethod java/util/concurrent/ScheduledFuture.isCancelled:()Z
      49: ifne          73
      52: aload_0
      53: getfield      #22                 // Field future:Ljava/util/concurrent/ScheduledFuture;
      56: iconst_1
      57: invokeinterface #24,  2           // InterfaceMethod java/util/concurrent/ScheduledFuture.cancel:(Z)Z
      62: pop
      63: getstatic     #25                 // Field logger:Lorg/apache/dubbo/common/logger/ErrorTypeAwareLogger;
      66: ldc           #26                 // String Access log task cancelled ...
      68: invokeinterface #27,  2           // InterfaceMethod org/apache/dubbo/common/logger/ErrorTypeAwareLogger.info:(Ljava/lang/String;)V
      73: aload_1
      74: aload_2
      75: invokeinterface #28,  2           // InterfaceMethod org/apache/dubbo/rpc/Invoker.invoke:(Lorg/apache/dubbo/rpc/Invocation;)Lorg/apache/dubbo/rpc/Result;
      80: areturn
      81: aload_0
      82: getfield      #15                 // Field scheduled:Ljava/util/concurrent/atomic/AtomicBoolean;
      85: iconst_0
      86: iconst_1
      87: invokevirtual #29                 // Method java/util/concurrent/atomic/AtomicBoolean.compareAndSet:(ZZ)Z
      90: ifeq          157
      93: aload_0
      94: aload_2
      95: invokeinterface #30,  1           // InterfaceMethod org/apache/dubbo/rpc/Invocation.getModuleModel:()Lorg/apache/dubbo/rpc/model/ModuleModel;
     100: invokevirtual #31                 // Method org/apache/dubbo/rpc/model/ModuleModel.getApplicationModel:()Lorg/apache/dubbo/rpc/model/ApplicationModel;
     103: invokevirtual #32                 // Method org/apache/dubbo/rpc/model/ApplicationModel.getFrameworkModel:()Lorg/apache/dubbo/rpc/model/FrameworkModel;
     106: invokevirtual #33                 // Method org/apache/dubbo/rpc/model/FrameworkModel.getBeanFactory:()Lorg/apache/dubbo/common/beans/factory/ScopeBeanFactory;
     109: ldc           #34                 // class org/apache/dubbo/common/threadpool/manager/FrameworkExecutorRepository
     111: invokevirtual #35                 // Method org/apache/dubbo/common/beans/factory/ScopeBeanFactory.getBean:(Ljava/lang/Class;)Ljava/lang/Object;
     114: checkcast     #34                 // class org/apache/dubbo/common/threadpool/manager/FrameworkExecutorRepository
     117: invokevirtual #36                 // Method org/apache/dubbo/common/threadpool/manager/FrameworkExecutorRepository.getSharedScheduledExecutor:()Ljava/util/concurrent/ScheduledExecutorService;
     120: new           #37                 // class org/apache/dubbo/rpc/filter/AccessLogFilter$AccesslogRefreshTask
     123: dup
     124: aload_0
     125: iload         4
     127: invokespecial #38                 // Method org/apache/dubbo/rpc/filter/AccessLogFilter$AccesslogRefreshTask."<init>":(Lorg/apache/dubbo/rpc/filter/AccessLogFilter;Z)V
     130: getstatic     #39                 // Field LOG_OUTPUT_INTERVAL:J
     133: getstatic     #39                 // Field LOG_OUTPUT_INTERVAL:J
     136: getstatic     #40                 // Field java/util/concurrent/TimeUnit.MILLISECONDS:Ljava/util/concurrent/TimeUnit;
     139: invokeinterface #41,  7           // InterfaceMethod java/util/concurrent/ScheduledExecutorService.scheduleWithFixedDelay:(Ljava/lang/Runnable;JJLjava/util/concurrent/TimeUnit;)Ljava/util/concurrent/ScheduledFuture;
     144: putfield      #22                 // Field future:Ljava/util/concurrent/ScheduledFuture;
     147: getstatic     #25                 // Field logger:Lorg/apache/dubbo/common/logger/ErrorTypeAwareLogger;
     150: ldc           #42                 // String Access log task started ...
     152: invokeinterface #27,  2           // InterfaceMethod org/apache/dubbo/common/logger/ErrorTypeAwareLogger.info:(Ljava/lang/String;)V
     157: invokestatic  #43                 // Method java/util/Optional.empty:()Ljava/util/Optional;
     160: astore        5
     162: aload_0
     163: aload_1
     164: aload_2
     165: invokespecial #44                 // Method buildAccessLogData:(Lorg/apache/dubbo/rpc/Invoker;Lorg/apache/dubbo/rpc/Invocation;)Lorg/apache/dubbo/rpc/support/AccessLogData;
     168: invokestatic  #45                 // Method java/util/Optional.of:(Ljava/lang/Object;)Ljava/util/Optional;
     171: astore        5
     173: goto          227
     176: astore        6
     178: getstatic     #25                 // Field logger:Lorg/apache/dubbo/common/logger/ErrorTypeAwareLogger;
     181: ldc           #47                 // String 5-36
     183: ldc           #48                 // String
     185: ldc           #48                 // String
     187: new           #49                 // class java/lang/StringBuilder
     190: dup
     191: invokespecial #50                 // Method java/lang/StringBuilder."<init>":()V
     194: ldc           #51                 // String Exception in AccessLogFilter of service(
     196: invokevirtual #52                 // Method java/lang/StringBuilder.append:(Ljava/lang/String;)Ljava/lang/StringBuilder;
     199: aload_1
     200: invokevirtual #53                 // Method java/lang/StringBuilder.append:(Ljava/lang/Object;)Ljava/lang/StringBuilder;
     203: ldc           #54                 // String  ->
     205: invokevirtual #52                 // Method java/lang/StringBuilder.append:(Ljava/lang/String;)Ljava/lang/StringBuilder;
     208: aload_2
     209: invokevirtual #53                 // Method java/lang/StringBuilder.append:(Ljava/lang/Object;)Ljava/lang/StringBuilder;
     212: ldc           #55                 // String )
     214: invokevirtual #52                 // Method java/lang/StringBuilder.append:(Ljava/lang/String;)Ljava/lang/StringBuilder;
     217: invokevirtual #56                 // Method java/lang/StringBuilder.toString:()Ljava/lang/String;
     220: aload         6
     222: invokeinterface #57,  6           // InterfaceMethod org/apache/dubbo/common/logger/ErrorTypeAwareLogger.warn:(Ljava/lang/String;Ljava/lang/String;Ljava/lang/String;Ljava/lang/String;Ljava/lang/Throwable;)V
     227: aload_1
     228: aload_2
     229: invokeinterface #28,  2           // InterfaceMethod org/apache/dubbo/rpc/Invoker.invoke:(Lorg/apache/dubbo/rpc/Invocation;)Lorg/apache/dubbo/rpc/Result;
     234: astore        6
     236: aload_3
     237: astore        7
     239: aload         5
     241: aload_0
     242: aload         7
     244: iload         4
     246: invokedynamic #58,  0             // InvokeDynamic #0:accept:(Lorg/apache/dubbo/rpc/filter/AccessLogFilter;Ljava/lang/String;Z)Ljava/util/function/Consumer;
     251: invokevirtual #59                 // Method java/util/Optional.ifPresent:(Ljava/util/function/Consumer;)V
     254: aload         6
     256: areturn
     257: astore        8
     259: aload_3
     260: astore        9
     262: aload         5
     264: aload_0
     265: aload         9
     267: iload         4
     269: invokedynamic #58,  0             // InvokeDynamic #0:accept:(Lorg/apache/dubbo/rpc/filter/AccessLogFilter;Ljava/lang/String;Z)Ljava/util/function/Consumer;
     274: invokevirtual #59                 // Method java/util/Optional.ifPresent:(Ljava/util/function/Consumer;)V
     277: aload         8
     279: athrow
    Exception table:
       from    to  target type
         162   173   176   Class java/lang/Throwable
         227   236   257   any
         257   259   257   any

  private void log(java.lang.String, org.apache.dubbo.rpc.support.AccessLogData, boolean);
    Code:
       0: aload_0
       1: getfield      #4                  // Field logEntries:Ljava/util/concurrent/ConcurrentMap;
       4: aload_1
       5: invokedynamic #60,  0             // InvokeDynamic #1:apply:()Ljava/util/function/Function;
      10: invokestatic  #61                 // Method org/apache/dubbo/common/utils/ConcurrentHashMapUtils.computeIfAbsent:(Ljava/util/concurrent/ConcurrentMap;Ljava/lang/Object;Ljava/util/function/Function;)Ljava/lang/Object;
      13: checkcast     #62                 // class java/util/Queue
      16: astore        4
      18: aload         4
      20: invokeinterface #63,  1           // InterfaceMethod java/util/Queue.size:()I
      25: sipush        5000
      28: if_icmpge     43
      31: aload         4
      33: aload_2
      34: invokeinterface #64,  2           // InterfaceMethod java/util/Queue.add:(Ljava/lang/Object;)Z
      39: pop
      40: goto          76
      43: getstatic     #25                 // Field logger:Lorg/apache/dubbo/common/logger/ErrorTypeAwareLogger;
      46: ldc           #47                 // String 5-36
      48: ldc           #48                 // String
      50: ldc           #48                 // String
      52: ldc           #65                 // String AccessLog buffer is full. Do a force writing to file to clear buffer.
      54: invokeinterface #66,  5           // InterfaceMethod org/apache/dubbo/common/logger/ErrorTypeAwareLogger.warn:(Ljava/lang/String;Ljava/lang/String;Ljava/lang/String;Ljava/lang/String;)V
      59: aload_0
      60: aload_1
      61: aload         4
      63: iload_3
      64: invokespecial #3                  // Method writeLogSetToFile:(Ljava/lang/String;Ljava/util/Queue;Z)V
      67: aload         4
      69: aload_2
      70: invokeinterface #64,  2           // InterfaceMethod java/util/Queue.add:(Ljava/lang/Object;)Z
      75: pop
      76: return

  private void writeLogSetToFile(java.lang.String, java.util.Queue<org.apache.dubbo.rpc.support.AccessLogData>, boolean);
    Code:
       0: aload_1
       1: invokestatic  #67                 // Method org/apache/dubbo/common/utils/ConfigUtils.isDefault:(Ljava/lang/String;)Z
       4: ifeq          15
       7: aload_0
       8: aload_2
       9: invokespecial #68                 // Method processWithServiceLogger:(Ljava/util/Queue;)V
      12: goto          148
      15: iload_3
      16: ifeq          43
      19: getstatic     #25                 // Field logger:Lorg/apache/dubbo/common/logger/ErrorTypeAwareLogger;
      22: ldc           #69                 // String 0-28
      24: ldc           #70                 // String Change of accesslog file path not allowed.
      26: ldc           #48                 // String
      28: ldc           #71                 // String Will write to the default location, \" +\n                        \"please enable this feature by setting \'accesslog.fixed.path=true\' and restart the process. \" +\n                        \"We highly recommend to not enable this feature in production for security concerns, \" +\n                        \"please be fully aware of the potential risks before doing so!
      30: invokeinterface #66,  5           // InterfaceMethod org/apache/dubbo/common/logger/ErrorTypeAwareLogger.warn:(Ljava/lang/String;Ljava/lang/String;Ljava/lang/String;Ljava/lang/String;)V
      35: aload_0
      36: aload_2
      37: invokespecial #68                 // Method processWithServiceLogger:(Ljava/util/Queue;)V
      40: goto          148
      43: getstatic     #25                 // Field logger:Lorg/apache/dubbo/common/logger/ErrorTypeAwareLogger;
      46: ldc           #69                 // String 0-28
      48: new           #49                 // class java/lang/StringBuilder
      51: dup
      52: invokespecial #50                 // Method java/lang/StringBuilder."<init>":()V
      55: ldc           #72                 // String Accesslog file path changed to
      57: invokevirtual #52                 // Method java/lang/StringBuilder.append:(Ljava/lang/String;)Ljava/lang/StringBuilder;
      60: aload_1
      61: invokevirtual #52                 // Method java/lang/StringBuilder.append:(Ljava/lang/String;)Ljava/lang/StringBuilder;
      64: ldc           #73                 // String , be aware of possible vulnerabilities!
      66: invokevirtual #52                 // Method java/lang/StringBuilder.append:(Ljava/lang/String;)Ljava/lang/StringBuilder;
      69: invokevirtual #56                 // Method java/lang/StringBuilder.toString:()Ljava/lang/String;
      72: ldc           #48                 // String
      74: ldc           #48                 // String
      76: invokeinterface #66,  5           // InterfaceMethod org/apache/dubbo/common/logger/ErrorTypeAwareLogger.warn:(Ljava/lang/String;Ljava/lang/String;Ljava/lang/String;Ljava/lang/String;)V
      81: new           #74                 // class java/io/File
      84: dup
      85: aload_1
      86: invokespecial #75                 // Method java/io/File."<init>":(Ljava/lang/String;)V
      89: astore        4
      91: aload_0
      92: aload         4
      94: invokespecial #76                 // Method createIfLogDirAbsent:(Ljava/io/File;)V
      97: getstatic     #25                 // Field logger:Lorg/apache/dubbo/common/logger/ErrorTypeAwareLogger;
     100: invokeinterface #77,  1           // InterfaceMethod org/apache/dubbo/common/logger/ErrorTypeAwareLogger.isDebugEnabled:()Z
     105: ifeq          135
     108: getstatic     #25                 // Field logger:Lorg/apache/dubbo/common/logger/ErrorTypeAwareLogger;
     111: new           #49                 // class java/lang/StringBuilder
     114: dup
     115: invokespecial #50                 // Method java/lang/StringBuilder."<init>":()V
     118: ldc           #78                 // String Append log to
     120: invokevirtual #52                 // Method java/lang/StringBuilder.append:(Ljava/lang/String;)Ljava/lang/StringBuilder;
     123: aload_1
     124: invokevirtual #52                 // Method java/lang/StringBuilder.append:(Ljava/lang/String;)Ljava/lang/StringBuilder;
     127: invokevirtual #56                 // Method java/lang/StringBuilder.toString:()Ljava/lang/String;
     130: invokeinterface #79,  2           // InterfaceMethod org/apache/dubbo/common/logger/ErrorTypeAwareLogger.debug:(Ljava/lang/String;)V
     135: aload_0
     136: aload         4
     138: invokespecial #80                 // Method renameFile:(Ljava/io/File;)V
     141: aload_0
     142: aload_2
     143: aload         4
     145: invokespecial #81                 // Method processWithAccessKeyLogger:(Ljava/util/Queue;Ljava/io/File;)V
     148: goto          174
     151: astore        4
     153: getstatic     #25                 // Field logger:Lorg/apache/dubbo/common/logger/ErrorTypeAwareLogger;
     156: ldc           #47                 // String 5-36
     158: ldc           #48                 // String
     160: ldc           #48                 // String
     162: aload         4
     164: invokevirtual #83                 // Method java/lang/Exception.getMessage:()Ljava/lang/String;
     167: aload         4
     169: invokeinterface #84,  6           // InterfaceMethod org/apache/dubbo/common/logger/ErrorTypeAwareLogger.error:(Ljava/lang/String;Ljava/lang/String;Ljava/lang/String;Ljava/lang/String;Ljava/lang/Throwable;)V
     174: return
    Exception table:
       from    to  target type
           0   148   151   Class java/lang/Exception

  private void processWithAccessKeyLogger(java.util.Queue<org.apache.dubbo.rpc.support.AccessLogData>, java.io.File) throws java.io.IOException;
    Code:
       0: new           #85                 // class java/io/FileWriter
       3: dup
       4: aload_2
       5: iconst_1
       6: invokespecial #86                 // Method java/io/FileWriter."<init>":(Ljava/io/File;Z)V
       9: astore_3
      10: aload_1
      11: invokeinterface #87,  1           // InterfaceMethod java/util/Queue.isEmpty:()Z
      16: ifne          47
      19: aload_3
      20: aload_1
      21: invokeinterface #88,  1           // InterfaceMethod java/util/Queue.poll:()Ljava/lang/Object;
      26: checkcast     #89                 // class org/apache/dubbo/rpc/support/AccessLogData
      29: invokevirtual #90                 // Method org/apache/dubbo/rpc/support/AccessLogData.getLogMessage:()Ljava/lang/String;
      32: invokevirtual #91                 // Method java/io/FileWriter.write:(Ljava/lang/String;)V
      35: aload_3
      36: ldc           #92                 // String line.separator
      38: invokestatic  #93                 // Method java/lang/System.getProperty:(Ljava/lang/String;)Ljava/lang/String;
      41: invokevirtual #91                 // Method java/io/FileWriter.write:(Ljava/lang/String;)V
      44: goto          10
      47: aload_3
      48: invokevirtual #94                 // Method java/io/FileWriter.flush:()V
      51: aload_3
      52: invokevirtual #95                 // Method java/io/FileWriter.close:()V
      55: goto          71
      58: astore        4
      60: aload_3
      61: invokevirtual #94                 // Method java/io/FileWriter.flush:()V
      64: aload_3
      65: invokevirtual #95                 // Method java/io/FileWriter.close:()V
      68: aload         4
      70: athrow
      71: return
    Exception table:
       from    to  target type
          10    47    58   any
          58    60    58   any

  private org.apache.dubbo.rpc.support.AccessLogData buildAccessLogData(org.apache.dubbo.rpc.Invoker<?>, org.apache.dubbo.rpc.Invocation);
    Code:
       0: invokestatic  #96                 // Method org/apache/dubbo/rpc/support/AccessLogData.newLogData:()Lorg/apache/dubbo/rpc/support/AccessLogData;
       3: astore_3
       4: aload_3
       5: aload_1
       6: invokeinterface #97,  1           // InterfaceMethod org/apache/dubbo/rpc/Invoker.getInterface:()Ljava/lang/Class;
      11: invokevirtual #98                 // Method java/lang/Class.getName:()Ljava/lang/String;
      14: invokevirtual #99                 // Method org/apache/dubbo/rpc/support/AccessLogData.setServiceName:(Ljava/lang/String;)V
      17: aload_3
      18: aload_2
      19: invokeinterface #100,  1          // InterfaceMethod org/apache/dubbo/rpc/Invocation.getMethodName:()Ljava/lang/String;
      24: invokevirtual #101                // Method org/apache/dubbo/rpc/support/AccessLogData.setMethodName:(Ljava/lang/String;)V
      27: aload_3
      28: aload_1
      29: invokeinterface #16,  1           // InterfaceMethod org/apache/dubbo/rpc/Invoker.getUrl:()Lorg/apache/dubbo/common/URL;
      34: invokevirtual #102                // Method org/apache/dubbo/common/URL.getVersion:()Ljava/lang/String;
      37: invokevirtual #103                // Method org/apache/dubbo/rpc/support/AccessLogData.setVersion:(Ljava/lang/String;)V
      40: aload_3
      41: aload_1
      42: invokeinterface #16,  1           // InterfaceMethod org/apache/dubbo/rpc/Invoker.getUrl:()Lorg/apache/dubbo/common/URL;
      47: invokevirtual #104                // Method org/apache/dubbo/common/URL.getGroup:()Ljava/lang/String;
      50: invokevirtual #105                // Method org/apache/dubbo/rpc/support/AccessLogData.setGroup:(Ljava/lang/String;)V
      53: aload_3
      54: new           #106                // class java/util/Date
      57: dup
      58: invokespecial #107                // Method java/util/Date."<init>":()V
      61: invokevirtual #108                // Method org/apache/dubbo/rpc/support/AccessLogData.setInvocationTime:(Ljava/util/Date;)V
      64: aload_3
      65: aload_2
      66: invokeinterface #109,  1          // InterfaceMethod org/apache/dubbo/rpc/Invocation.getParameterTypes:()[Ljava/lang/Class;
      71: invokevirtual #110                // Method org/apache/dubbo/rpc/support/AccessLogData.setTypes:([Ljava/lang/Class;)V
      74: aload_3
      75: aload_2
      76: invokeinterface #111,  1          // InterfaceMethod org/apache/dubbo/rpc/Invocation.getArguments:()[Ljava/lang/Object;
      81: invokevirtual #112                // Method org/apache/dubbo/rpc/support/AccessLogData.setArguments:([Ljava/lang/Object;)V
      84: aload_3
      85: areturn

  private void processWithServiceLogger(java.util.Queue<org.apache.dubbo.rpc.support.AccessLogData>);
    Code:
       0: aload_1
       1: invokeinterface #87,  1           // InterfaceMethod java/util/Queue.isEmpty:()Z
       6: ifne          56
       9: aload_1
      10: invokeinterface #88,  1           // InterfaceMethod java/util/Queue.poll:()Ljava/lang/Object;
      15: checkcast     #89                 // class org/apache/dubbo/rpc/support/AccessLogData
      18: astore_2
      19: new           #49                 // class java/lang/StringBuilder
      22: dup
      23: invokespecial #50                 // Method java/lang/StringBuilder."<init>":()V
      26: ldc           #113                // String dubbo.accesslog.
      28: invokevirtual #52                 // Method java/lang/StringBuilder.append:(Ljava/lang/String;)Ljava/lang/StringBuilder;
      31: aload_2
      32: invokevirtual #114                // Method org/apache/dubbo/rpc/support/AccessLogData.getServiceName:()Ljava/lang/String;
      35: invokevirtual #52                 // Method java/lang/StringBuilder.append:(Ljava/lang/String;)Ljava/lang/StringBuilder;
      38: invokevirtual #56                 // Method java/lang/StringBuilder.toString:()Ljava/lang/String;
      41: invokestatic  #115                // Method org/apache/dubbo/common/logger/LoggerFactory.getLogger:(Ljava/lang/String;)Lorg/apache/dubbo/common/logger/Logger;
      44: aload_2
      45: invokevirtual #90                 // Method org/apache/dubbo/rpc/support/AccessLogData.getLogMessage:()Ljava/lang/String;
      48: invokeinterface #116,  2          // InterfaceMethod org/apache/dubbo/common/logger/Logger.info:(Ljava/lang/String;)V
      53: goto          0
      56: return

  private void createIfLogDirAbsent(java.io.File);
    Code:
       0: aload_1
       1: invokevirtual #117                // Method java/io/File.getParentFile:()Ljava/io/File;
       4: astore_2
       5: aconst_null
       6: aload_2
       7: if_acmpeq     22
      10: aload_2
      11: invokevirtual #118                // Method java/io/File.exists:()Z
      14: ifne          22
      17: aload_2
      18: invokevirtual #119                // Method java/io/File.mkdirs:()Z
      21: pop
      22: return

  private void renameFile(java.io.File);
    Code:
       0: aload_1
       1: invokevirtual #118                // Method java/io/File.exists:()Z
       4: ifeq          91
       7: aload_0
       8: getfield      #10                 // Field fileNameFormatter:Ljava/text/DateFormat;
      11: new           #106                // class java/util/Date
      14: dup
      15: invokespecial #107                // Method java/util/Date."<init>":()V
      18: invokevirtual #120                // Method java/text/DateFormat.format:(Ljava/util/Date;)Ljava/lang/String;
      21: astore_2
      22: aload_0
      23: getfield      #10                 // Field fileNameFormatter:Ljava/text/DateFormat;
      26: new           #106                // class java/util/Date
      29: dup
      30: aload_1
      31: invokevirtual #121                // Method java/io/File.lastModified:()J
      34: invokespecial #122                // Method java/util/Date."<init>":(J)V
      37: invokevirtual #120                // Method java/text/DateFormat.format:(Ljava/util/Date;)Ljava/lang/String;
      40: astore_3
      41: aload_2
      42: aload_3
      43: invokevirtual #123                // Method java/lang/String.equals:(Ljava/lang/Object;)Z
      46: ifne          91
      49: new           #74                 // class java/io/File
      52: dup
      53: new           #49                 // class java/lang/StringBuilder
      56: dup
      57: invokespecial #50                 // Method java/lang/StringBuilder."<init>":()V
      60: aload_1
      61: invokevirtual #124                // Method java/io/File.getAbsolutePath:()Ljava/lang/String;
      64: invokevirtual #52                 // Method java/lang/StringBuilder.append:(Ljava/lang/String;)Ljava/lang/StringBuilder;
      67: ldc           #125                // String .
      69: invokevirtual #52                 // Method java/lang/StringBuilder.append:(Ljava/lang/String;)Ljava/lang/StringBuilder;
      72: aload_2
      73: invokevirtual #52                 // Method java/lang/StringBuilder.append:(Ljava/lang/String;)Ljava/lang/StringBuilder;
      76: invokevirtual #56                 // Method java/lang/StringBuilder.toString:()Ljava/lang/String;
      79: invokespecial #75                 // Method java/io/File."<init>":(Ljava/lang/String;)V
      82: astore        4
      84: aload_1
      85: aload         4
      87: invokevirtual #126                // Method java/io/File.renameTo:(Ljava/io/File;)Z
      90: pop
      91: return

  public static void setInterval(long);
    Code:
       0: lload_0
       1: putstatic     #39                 // Field LOG_OUTPUT_INTERVAL:J
       4: return

  public static long getInterval();
    Code:
       0: getstatic     #39                 // Field LOG_OUTPUT_INTERVAL:J
       3: lreturn

  public void destroy();
    Code:
       0: aload_0
       1: getfield      #22                 // Field future:Ljava/util/concurrent/ScheduledFuture;
       4: iconst_1
       5: invokeinterface #24,  2           // InterfaceMethod java/util/concurrent/ScheduledFuture.cancel:(Z)Z
      10: pop
      11: return

  private static java.util.Queue lambda$log$1(java.lang.String);
    Code:
       0: new           #127                // class java/util/concurrent/ConcurrentLinkedQueue
       3: dup
       4: invokespecial #128                // Method java/util/concurrent/ConcurrentLinkedQueue."<init>":()V
       7: areturn

  private void lambda$invoke$0(java.lang.String, boolean, org.apache.dubbo.rpc.support.AccessLogData);
    Code:
       0: aload_3
       1: new           #106                // class java/util/Date
       4: dup
       5: invokespecial #107                // Method java/util/Date."<init>":()V
       8: invokevirtual #129                // Method org/apache/dubbo/rpc/support/AccessLogData.setOutTime:(Ljava/util/Date;)V
      11: aload_0
      12: aload_1
      13: aload_3
      14: iload_2
      15: invokespecial #130                // Method log:(Ljava/lang/String;Lorg/apache/dubbo/rpc/support/AccessLogData;Z)V
      18: return

  static java.util.concurrent.ConcurrentMap access$000(org.apache.dubbo.rpc.filter.AccessLogFilter);
    Code:
       0: aload_0
       1: getfield      #4                  // Field logEntries:Ljava/util/concurrent/ConcurrentMap;
       4: areturn

  static void access$100(org.apache.dubbo.rpc.filter.AccessLogFilter, java.lang.String, java.util.Queue, boolean);
    Code:
       0: aload_0
       1: aload_1
       2: aload_2
       3: iload_3
       4: invokespecial #3                  // Method writeLogSetToFile:(Ljava/lang/String;Ljava/util/Queue;Z)V
       7: return

  static {};
    Code:
       0: ldc           #7                  // class org/apache/dubbo/rpc/filter/AccessLogFilter
       2: invokestatic  #131                // Method org/apache/dubbo/common/logger/LoggerFactory.getErrorTypeAwareLogger:(Ljava/lang/Class;)Lorg/apache/dubbo/common/logger/ErrorTypeAwareLogger;
       5: putstatic     #25                 // Field logger:Lorg/apache/dubbo/common/logger/ErrorTypeAwareLogger;
       8: ldc2_w        #132                // long 5000l
      11: putstatic     #39                 // Field LOG_OUTPUT_INTERVAL:J
      14: return
}
