Compiled from "AccessLogFilter.java"
class org.apache.dubbo.rpc.filter.AccessLogFilter$AccesslogRefreshTask implements java.lang.Runnable {
  private final boolean isFixedPath;

  final org.apache.dubbo.rpc.filter.AccessLogFilter this$0;

  public org.apache.dubbo.rpc.filter.AccessLogFilter$AccesslogRefreshTask(org.apache.dubbo.rpc.filter.AccessLogFilter, boolean);
    Code:
       0: aload_0
       1: aload_1
       2: putfield      #1                  // Field this$0:Lorg/apache/dubbo/rpc/filter/AccessLogFilter;
       5: aload_0
       6: invokespecial #2                  // Method java/lang/Object."<init>":()V
       9: aload_0
      10: iload_2
      11: putfield      #3                  // Field isFixedPath:Z
      14: return

  public void run();
    Code:
       0: aload_0
       1: getfield      #1                  // Field this$0:Lorg/apache/dubbo/rpc/filter/AccessLogFilter;
       4: invokestatic  #4                  // Method org/apache/dubbo/rpc/filter/AccessLogFilter.access$000:(Lorg/apache/dubbo/rpc/filter/AccessLogFilter;)Ljava/util/concurrent/ConcurrentMap;
       7: invokeinterface #5,  1            // InterfaceMethod java/util/concurrent/ConcurrentMap.isEmpty:()Z
      12: ifne          90
      15: aload_0
      16: getfield      #1                  // Field this$0:Lorg/apache/dubbo/rpc/filter/AccessLogFilter;
      19: invokestatic  #4                  // Method org/apache/dubbo/rpc/filter/AccessLogFilter.access$000:(Lorg/apache/dubbo/rpc/filter/AccessLogFilter;)Ljava/util/concurrent/ConcurrentMap;
      22: invokeinterface #6,  1            // InterfaceMethod java/util/concurrent/ConcurrentMap.entrySet:()Ljava/util/Set;
      27: invokeinterface #7,  1            // InterfaceMethod java/util/Set.iterator:()Ljava/util/Iterator;
      32: astore_1
      33: aload_1
      34: invokeinterface #8,  1            // InterfaceMethod java/util/Iterator.hasNext:()Z
      39: ifeq          90
      42: aload_1
      43: invokeinterface #9,  1            // InterfaceMethod java/util/Iterator.next:()Ljava/lang/Object;
      48: checkcast     #10                 // class java/util/Map$Entry
      51: astore_2
      52: aload_2
      53: invokeinterface #11,  1           // InterfaceMethod java/util/Map$Entry.getKey:()Ljava/lang/Object;
      58: checkcast     #12                 // class java/lang/String
      61: astore_3
      62: aload_2
      63: invokeinterface #13,  1           // InterfaceMethod java/util/Map$Entry.getValue:()Ljava/lang/Object;
      68: checkcast     #14                 // class java/util/Queue
      71: astore        4
      73: aload_0
      74: getfield      #1                  // Field this$0:Lorg/apache/dubbo/rpc/filter/AccessLogFilter;
      77: aload_3
      78: aload         4
      80: aload_0
      81: getfield      #3                  // Field isFixedPath:Z
      84: invokestatic  #15                 // Method org/apache/dubbo/rpc/filter/AccessLogFilter.access$100:(Lorg/apache/dubbo/rpc/filter/AccessLogFilter;Ljava/lang/String;Ljava/util/Queue;Z)V
      87: goto          33
      90: return
}
