Compiled from "AdaptiveLoadBalanceFilter.java"
public class org.apache.dubbo.rpc.filter.AdaptiveLoadBalanceFilter implements org.apache.dubbo.rpc.Filter,org.apache.dubbo.rpc.BaseFilter$Listener {
  private volatile java.util.concurrent.ThreadPoolExecutor executor;

  private final org.apache.dubbo.rpc.AdaptiveMetrics adaptiveMetrics;

  public org.apache.dubbo.rpc.filter.AdaptiveLoadBalanceFilter(org.apache.dubbo.rpc.model.ApplicationModel);
    Code:
       0: aload_0
       1: invokespecial #2                  // Method java/lang/Object."<init>":()V
       4: aload_0
       5: aconst_null
       6: putfield      #3                  // Field executor:Ljava/util/concurrent/ThreadPoolExecutor;
       9: aload_0
      10: aload_1
      11: invokevirtual #4                  // Method org/apache/dubbo/rpc/model/ApplicationModel.getBeanFactory:()Lorg/apache/dubbo/common/beans/factory/ScopeBeanFactory;
      14: ldc           #5                  // class org/apache/dubbo/rpc/AdaptiveMetrics
      16: invokevirtual #6                  // Method org/apache/dubbo/common/beans/factory/ScopeBeanFactory.getBean:(Ljava/lang/Class;)Ljava/lang/Object;
      19: checkcast     #5                  // class org/apache/dubbo/rpc/AdaptiveMetrics
      22: putfield      #7                  // Field adaptiveMetrics:Lorg/apache/dubbo/rpc/AdaptiveMetrics;
      25: return

  private java.util.concurrent.ThreadPoolExecutor getExecutor();
    Code:
       0: aconst_null
       1: aload_0
       2: getfield      #3                  // Field executor:Ljava/util/concurrent/ThreadPoolExecutor;
       5: if_acmpne     86
       8: aload_0
       9: dup
      10: astore_1
      11: monitorenter
      12: aconst_null
      13: aload_0
      14: getfield      #3                  // Field executor:Ljava/util/concurrent/ThreadPoolExecutor;
      17: if_acmpne     76
      20: aload_0
      21: new           #8                  // class java/util/concurrent/ThreadPoolExecutor
      24: dup
      25: iconst_1
      26: iconst_1
      27: lconst_0
      28: getstatic     #9                  // Field java/util/concurrent/TimeUnit.MILLISECONDS:Ljava/util/concurrent/TimeUnit;
      31: new           #10                 // class java/util/concurrent/LinkedBlockingQueue
      34: dup
      35: sipush        1024
      38: invokespecial #11                 // Method java/util/concurrent/LinkedBlockingQueue."<init>":(I)V
      41: new           #12                 // class org/apache/dubbo/common/threadlocal/NamedInternalThreadFactory
      44: dup
      45: ldc           #13                 // String Dubbo-framework-loadbalance-adaptive
      47: iconst_1
      48: invokespecial #14                 // Method org/apache/dubbo/common/threadlocal/NamedInternalThreadFactory."<init>":(Ljava/lang/String;Z)V
      51: new           #15                 // class java/util/concurrent/ThreadPoolExecutor$DiscardOldestPolicy
      54: dup
      55: invokespecial #16                 // Method java/util/concurrent/ThreadPoolExecutor$DiscardOldestPolicy."<init>":()V
      58: invokespecial #17                 // Method java/util/concurrent/ThreadPoolExecutor."<init>":(IIJLjava/util/concurrent/TimeUnit;Ljava/util/concurrent/BlockingQueue;Ljava/util/concurrent/ThreadFactory;Ljava/util/concurrent/RejectedExecutionHandler;)V
      61: putfield      #3                  // Field executor:Ljava/util/concurrent/ThreadPoolExecutor;
      64: invokestatic  #18                 // Method org/apache/dubbo/common/resource/GlobalResourcesRepository.getInstance:()Lorg/apache/dubbo/common/resource/GlobalResourcesRepository;
      67: aload_0
      68: invokedynamic #19,  0             // InvokeDynamic #0:destroy:(Lorg/apache/dubbo/rpc/filter/AdaptiveLoadBalanceFilter;)Lorg/apache/dubbo/common/resource/Disposable;
      73: invokevirtual #20                 // Method org/apache/dubbo/common/resource/GlobalResourcesRepository.registerDisposable:(Lorg/apache/dubbo/common/resource/Disposable;)V
      76: aload_1
      77: monitorexit
      78: goto          86
      81: astore_2
      82: aload_1
      83: monitorexit
      84: aload_2
      85: athrow
      86: aload_0
      87: getfield      #3                  // Field executor:Ljava/util/concurrent/ThreadPoolExecutor;
      90: areturn
    Exception table:
       from    to  target type
          12    78    81   any
          81    84    81   any

  public org.apache.dubbo.rpc.Result invoke(org.apache.dubbo.rpc.Invoker<?>, org.apache.dubbo.rpc.Invocation) throws org.apache.dubbo.rpc.RpcException;
    Code:
       0: aload_1
       1: aload_2
       2: invokeinterface #21,  2           // InterfaceMethod org/apache/dubbo/rpc/Invoker.invoke:(Lorg/apache/dubbo/rpc/Invocation;)Lorg/apache/dubbo/rpc/Result;
       7: areturn

  private java.lang.String buildServiceKey(org.apache.dubbo.rpc.Invocation);
    Code:
       0: new           #22                 // class java/lang/StringBuilder
       3: dup
       4: sipush        128
       7: invokespecial #23                 // Method java/lang/StringBuilder."<init>":(I)V
      10: astore_2
      11: aload_2
      12: aload_1
      13: invokeinterface #24,  1           // InterfaceMethod org/apache/dubbo/rpc/Invocation.getInvoker:()Lorg/apache/dubbo/rpc/Invoker;
      18: invokeinterface #25,  1           // InterfaceMethod org/apache/dubbo/rpc/Invoker.getUrl:()Lorg/apache/dubbo/common/URL;
      23: invokevirtual #26                 // Method org/apache/dubbo/common/URL.getAddress:()Ljava/lang/String;
      26: invokevirtual #27                 // Method java/lang/StringBuilder.append:(Ljava/lang/String;)Ljava/lang/StringBuilder;
      29: ldc           #28                 // String :
      31: invokevirtual #27                 // Method java/lang/StringBuilder.append:(Ljava/lang/String;)Ljava/lang/StringBuilder;
      34: aload_1
      35: invokeinterface #29,  1           // InterfaceMethod org/apache/dubbo/rpc/Invocation.getProtocolServiceKey:()Ljava/lang/String;
      40: invokevirtual #27                 // Method java/lang/StringBuilder.append:(Ljava/lang/String;)Ljava/lang/StringBuilder;
      43: pop
      44: aload_2
      45: invokevirtual #30                 // Method java/lang/StringBuilder.toString:()Ljava/lang/String;
      48: areturn

  private java.lang.String getServiceKey(org.apache.dubbo.rpc.Invocation);
    Code:
       0: aload_1
       1: invokeinterface #31,  1           // InterfaceMethod org/apache/dubbo/rpc/Invocation.getAttributes:()Ljava/util/Map;
       6: aload_1
       7: invokeinterface #24,  1           // InterfaceMethod org/apache/dubbo/rpc/Invocation.getInvoker:()Lorg/apache/dubbo/rpc/Invoker;
      12: invokeinterface #32,  2           // InterfaceMethod java/util/Map.get:(Ljava/lang/Object;)Ljava/lang/Object;
      17: checkcast     #33                 // class java/lang/String
      20: astore_2
      21: aload_2
      22: invokestatic  #34                 // Method org/apache/dubbo/common/utils/StringUtils.isNotEmpty:(Ljava/lang/String;)Z
      25: ifeq          30
      28: aload_2
      29: areturn
      30: aload_0
      31: aload_1
      32: invokespecial #35                 // Method buildServiceKey:(Lorg/apache/dubbo/rpc/Invocation;)Ljava/lang/String;
      35: astore_2
      36: aload_1
      37: invokeinterface #31,  1           // InterfaceMethod org/apache/dubbo/rpc/Invocation.getAttributes:()Ljava/util/Map;
      42: aload_1
      43: invokeinterface #24,  1           // InterfaceMethod org/apache/dubbo/rpc/Invocation.getInvoker:()Lorg/apache/dubbo/rpc/Invoker;
      48: aload_2
      49: invokeinterface #36,  3           // InterfaceMethod java/util/Map.put:(Ljava/lang/Object;Ljava/lang/Object;)Ljava/lang/Object;
      54: pop
      55: aload_2
      56: areturn

  public void onResponse(org.apache.dubbo.rpc.Result, org.apache.dubbo.rpc.Invoker<?>, org.apache.dubbo.rpc.Invocation);
    Code:
       0: aload_3
       1: invokeinterface #31,  1           // InterfaceMethod org/apache/dubbo/rpc/Invocation.getAttributes:()Ljava/util/Map;
       6: ldc           #37                 // String loadbalance
       8: invokeinterface #32,  2           // InterfaceMethod java/util/Map.get:(Ljava/lang/Object;)Ljava/lang/Object;
      13: checkcast     #33                 // class java/lang/String
      16: astore        4
      18: aload         4
      20: invokestatic  #38                 // Method org/apache/dubbo/common/utils/StringUtils.isEmpty:(Ljava/lang/String;)Z
      23: ifne          36
      26: ldc           #40                 // String adaptive
      28: aload         4
      30: invokevirtual #41                 // Method java/lang/String.equals:(Ljava/lang/Object;)Z
      33: ifne          51
      36: aload_1
      37: invokeinterface #42,  1           // InterfaceMethod org/apache/dubbo/rpc/Result.getAttachments:()Ljava/util/Map;
      42: ldc           #44                 // String lb_adaptive
      44: invokeinterface #45,  2           // InterfaceMethod java/util/Map.remove:(Ljava/lang/Object;)Ljava/lang/Object;
      49: pop
      50: return
      51: aload_0
      52: getfield      #7                  // Field adaptiveMetrics:Lorg/apache/dubbo/rpc/AdaptiveMetrics;
      55: aload_0
      56: aload_3
      57: invokespecial #46                 // Method getServiceKey:(Lorg/apache/dubbo/rpc/Invocation;)Ljava/lang/String;
      60: invokevirtual #47                 // Method org/apache/dubbo/rpc/AdaptiveMetrics.addConsumerSuccess:(Ljava/lang/String;)V
      63: aload_1
      64: ldc           #44                 // String lb_adaptive
      66: invokeinterface #48,  2           // InterfaceMethod org/apache/dubbo/rpc/Result.getAttachment:(Ljava/lang/String;)Ljava/lang/String;
      71: astore        5
      73: aload         5
      75: invokestatic  #34                 // Method org/apache/dubbo/common/utils/StringUtils.isNotEmpty:(Ljava/lang/String;)Z
      78: ifeq          250
      81: getstatic     #49                 // Field org/apache/dubbo/common/constants/CommonConstants.COMMA_SPLIT_PATTERN:Ljava/util/regex/Pattern;
      84: aload         5
      86: invokevirtual #50                 // Method java/util/regex/Pattern.split:(Ljava/lang/CharSequence;)[Ljava/lang/String;
      89: astore        6
      91: aload         6
      93: arraylength
      94: ifne          112
      97: aload_1
      98: invokeinterface #42,  1           // InterfaceMethod org/apache/dubbo/rpc/Result.getAttachments:()Ljava/util/Map;
     103: ldc           #44                 // String lb_adaptive
     105: invokeinterface #45,  2           // InterfaceMethod java/util/Map.remove:(Ljava/lang/Object;)Ljava/lang/Object;
     110: pop
     111: return
     112: new           #51                 // class java/util/HashMap
     115: dup
     116: invokespecial #52                 // Method java/util/HashMap."<init>":()V
     119: astore        7
     121: aload         6
     123: astore        8
     125: aload         8
     127: arraylength
     128: istore        9
     130: iconst_0
     131: istore        10
     133: iload         10
     135: iload         9
     137: if_icmpge     188
     140: aload         8
     142: iload         10
     144: aaload
     145: astore        11
     147: aload         11
     149: ldc           #28                 // String :
     151: invokevirtual #53                 // Method java/lang/String.split:(Ljava/lang/String;)[Ljava/lang/String;
     154: astore        12
     156: aload         12
     158: arraylength
     159: iconst_2
     160: if_icmpeq     166
     163: goto          182
     166: aload         7
     168: aload         12
     170: iconst_0
     171: aaload
     172: aload         12
     174: iconst_1
     175: aaload
     176: invokeinterface #36,  3           // InterfaceMethod java/util/Map.put:(Ljava/lang/Object;Ljava/lang/Object;)Ljava/lang/Object;
     181: pop
     182: iinc          10, 1
     185: goto          133
     188: aload_3
     189: invokeinterface #31,  1           // InterfaceMethod org/apache/dubbo/rpc/Invocation.getAttributes:()Ljava/util/Map;
     194: ldc           #54                 // String adaptive_startTime
     196: invokeinterface #32,  2           // InterfaceMethod java/util/Map.get:(Ljava/lang/Object;)Ljava/lang/Object;
     201: checkcast     #55                 // class java/lang/Long
     204: astore        8
     206: aconst_null
     207: aload         8
     209: if_acmpeq     234
     212: aload         7
     214: ldc           #56                 // String rt
     216: invokestatic  #57                 // Method java/lang/System.currentTimeMillis:()J
     219: aload         8
     221: invokevirtual #58                 // Method java/lang/Long.longValue:()J
     224: lsub
     225: invokestatic  #59                 // Method java/lang/String.valueOf:(J)Ljava/lang/String;
     228: invokeinterface #36,  3           // InterfaceMethod java/util/Map.put:(Ljava/lang/Object;Ljava/lang/Object;)Ljava/lang/Object;
     233: pop
     234: aload_0
     235: invokespecial #60                 // Method getExecutor:()Ljava/util/concurrent/ThreadPoolExecutor;
     238: aload_0
     239: aload_3
     240: aload         7
     242: invokedynamic #61,  0             // InvokeDynamic #1:run:(Lorg/apache/dubbo/rpc/filter/AdaptiveLoadBalanceFilter;Lorg/apache/dubbo/rpc/Invocation;Ljava/util/Map;)Ljava/lang/Runnable;
     247: invokevirtual #62                 // Method java/util/concurrent/ThreadPoolExecutor.execute:(Ljava/lang/Runnable;)V
     250: aload_1
     251: invokeinterface #42,  1           // InterfaceMethod org/apache/dubbo/rpc/Result.getAttachments:()Ljava/util/Map;
     256: ldc           #44                 // String lb_adaptive
     258: invokeinterface #45,  2           // InterfaceMethod java/util/Map.remove:(Ljava/lang/Object;)Ljava/lang/Object;
     263: pop
     264: goto          286
     267: astore        13
     269: aload_1
     270: invokeinterface #42,  1           // InterfaceMethod org/apache/dubbo/rpc/Result.getAttachments:()Ljava/util/Map;
     275: ldc           #44                 // String lb_adaptive
     277: invokeinterface #45,  2           // InterfaceMethod java/util/Map.remove:(Ljava/lang/Object;)Ljava/lang/Object;
     282: pop
     283: aload         13
     285: athrow
     286: return
    Exception table:
       from    to  target type
           0    36   267   any
          51    97   267   any
         112   250   267   any
         267   269   267   any

  public void onError(java.lang.Throwable, org.apache.dubbo.rpc.Invoker<?>, org.apache.dubbo.rpc.Invocation);
    Code:
       0: aload_3
       1: invokeinterface #31,  1           // InterfaceMethod org/apache/dubbo/rpc/Invocation.getAttributes:()Ljava/util/Map;
       6: ldc           #37                 // String loadbalance
       8: invokeinterface #32,  2           // InterfaceMethod java/util/Map.get:(Ljava/lang/Object;)Ljava/lang/Object;
      13: checkcast     #33                 // class java/lang/String
      16: astore        4
      18: aload         4
      20: invokestatic  #34                 // Method org/apache/dubbo/common/utils/StringUtils.isNotEmpty:(Ljava/lang/String;)Z
      23: ifeq          50
      26: ldc           #40                 // String adaptive
      28: aload         4
      30: invokevirtual #41                 // Method java/lang/String.equals:(Ljava/lang/Object;)Z
      33: ifeq          50
      36: aload_0
      37: invokespecial #60                 // Method getExecutor:()Ljava/util/concurrent/ThreadPoolExecutor;
      40: aload_0
      41: aload_3
      42: invokedynamic #63,  0             // InvokeDynamic #2:run:(Lorg/apache/dubbo/rpc/filter/AdaptiveLoadBalanceFilter;Lorg/apache/dubbo/rpc/Invocation;)Ljava/lang/Runnable;
      47: invokevirtual #62                 // Method java/util/concurrent/ThreadPoolExecutor.execute:(Ljava/lang/Runnable;)V
      50: return

  private void lambda$onError$2(org.apache.dubbo.rpc.Invocation);
    Code:
       0: aload_0
       1: getfield      #7                  // Field adaptiveMetrics:Lorg/apache/dubbo/rpc/AdaptiveMetrics;
       4: aload_0
       5: aload_1
       6: invokespecial #46                 // Method getServiceKey:(Lorg/apache/dubbo/rpc/Invocation;)Ljava/lang/String;
       9: invokevirtual #64                 // Method org/apache/dubbo/rpc/AdaptiveMetrics.addErrorReq:(Ljava/lang/String;)V
      12: return

  private void lambda$onResponse$1(org.apache.dubbo.rpc.Invocation, java.util.Map);
    Code:
       0: aload_0
       1: getfield      #7                  // Field adaptiveMetrics:Lorg/apache/dubbo/rpc/AdaptiveMetrics;
       4: aload_0
       5: aload_1
       6: invokespecial #46                 // Method getServiceKey:(Lorg/apache/dubbo/rpc/Invocation;)Ljava/lang/String;
       9: aload_2
      10: invokevirtual #65                 // Method org/apache/dubbo/rpc/AdaptiveMetrics.setProviderMetrics:(Ljava/lang/String;Ljava/util/Map;)V
      13: return

  private void lambda$getExecutor$0();
    Code:
       0: aload_0
       1: getfield      #3                  // Field executor:Ljava/util/concurrent/ThreadPoolExecutor;
       4: invokevirtual #66                 // Method java/util/concurrent/ThreadPoolExecutor.shutdown:()V
       7: return
}
