Compiled from "ClassLoaderCallbackFilter.java"
public class org.apache.dubbo.rpc.filter.ClassLoaderCallbackFilter implements org.apache.dubbo.rpc.Filter,org.apache.dubbo.rpc.BaseFilter$Listener {
  public org.apache.dubbo.rpc.filter.ClassLoaderCallbackFilter();
    Code:
       0: aload_0
       1: invokespecial #2                  // Method java/lang/Object."<init>":()V
       4: return

  public org.apache.dubbo.rpc.Result invoke(org.apache.dubbo.rpc.Invoker<?>, org.apache.dubbo.rpc.Invocation) throws org.apache.dubbo.rpc.RpcException;
    Code:
       0: aload_1
       1: aload_2
       2: invokeinterface #3,  2            // InterfaceMethod org/apache/dubbo/rpc/Invoker.invoke:(Lorg/apache/dubbo/rpc/Invocation;)Lorg/apache/dubbo/rpc/Result;
       7: areturn

  public void onResponse(org.apache.dubbo.rpc.Result, org.apache.dubbo.rpc.Invoker<?>, org.apache.dubbo.rpc.Invocation);
    Code:
       0: aload_0
       1: aload_2
       2: aload_3
       3: invokespecial #4                  // Method setClassLoader:(Lorg/apache/dubbo/rpc/Invoker;Lorg/apache/dubbo/rpc/Invocation;)V
       6: return

  public void onError(java.lang.Throwable, org.apache.dubbo.rpc.Invoker<?>, org.apache.dubbo.rpc.Invocation);
    Code:
       0: aload_0
       1: aload_2
       2: aload_3
       3: invokespecial #4                  // Method setClassLoader:(Lorg/apache/dubbo/rpc/Invoker;Lorg/apache/dubbo/rpc/Invocation;)V
       6: return

  private void setClassLoader(org.apache.dubbo.rpc.Invoker<?>, org.apache.dubbo.rpc.Invocation);
    Code:
       0: aload_2
       1: ldc           #5                  // String WORKING_CLASSLOADER
       3: invokeinterface #6,  2            // InterfaceMethod org/apache/dubbo/rpc/Invocation.get:(Ljava/lang/Object;)Ljava/lang/Object;
       8: checkcast     #7                  // class java/lang/ClassLoader
      11: astore_3
      12: aload_3
      13: ifnull        23
      16: invokestatic  #8                  // Method java/lang/Thread.currentThread:()Ljava/lang/Thread;
      19: aload_3
      20: invokevirtual #9                  // Method java/lang/Thread.setContextClassLoader:(Ljava/lang/ClassLoader;)V
      23: return
}
