Compiled from "ClassLoaderFilter.java"
public class org.apache.dubbo.rpc.filter.ClassLoaderFilter implements org.apache.dubbo.rpc.Filter,org.apache.dubbo.rpc.BaseFilter$Listener {
  public org.apache.dubbo.rpc.filter.ClassLoaderFilter();
    Code:
       0: aload_0
       1: invokespecial #2                  // Method java/lang/Object."<init>":()V
       4: return

  public org.apache.dubbo.rpc.Result invoke(org.apache.dubbo.rpc.Invoker<?>, org.apache.dubbo.rpc.Invocation) throws org.apache.dubbo.rpc.RpcException;
    Code:
       0: invokestatic  #3                  // Method java/lang/Thread.currentThread:()Ljava/lang/Thread;
       3: invokevirtual #4                  // Method java/lang/Thread.getContextClassLoader:()Ljava/lang/ClassLoader;
       6: astore_3
       7: aload_2
       8: invokeinterface #5,  1            // InterfaceMethod org/apache/dubbo/rpc/Invocation.getServiceModel:()Lorg/apache/dubbo/rpc/model/ServiceModel;
      13: ifnull        30
      16: aload_2
      17: invokeinterface #5,  1            // InterfaceMethod org/apache/dubbo/rpc/Invocation.getServiceModel:()Lorg/apache/dubbo/rpc/model/ServiceModel;
      22: invokevirtual #6                  // Method org/apache/dubbo/rpc/model/ServiceModel.getClassLoader:()Ljava/lang/ClassLoader;
      25: astore        4
      27: goto          39
      30: aload_1
      31: invokevirtual #7                  // Method java/lang/Object.getClass:()Ljava/lang/Class;
      34: invokevirtual #8                  // Method java/lang/Class.getClassLoader:()Ljava/lang/ClassLoader;
      37: astore        4
      39: aload         4
      41: ifnull        73
      44: aload_2
      45: ldc           #9                  // String STAGED_CLASSLOADER
      47: aload_3
      48: invokeinterface #10,  3           // InterfaceMethod org/apache/dubbo/rpc/Invocation.put:(Ljava/lang/Object;Ljava/lang/Object;)Ljava/lang/Object;
      53: pop
      54: aload_2
      55: ldc           #11                 // String WORKING_CLASSLOADER
      57: aload         4
      59: invokeinterface #10,  3           // InterfaceMethod org/apache/dubbo/rpc/Invocation.put:(Ljava/lang/Object;Ljava/lang/Object;)Ljava/lang/Object;
      64: pop
      65: invokestatic  #3                  // Method java/lang/Thread.currentThread:()Ljava/lang/Thread;
      68: aload         4
      70: invokevirtual #12                 // Method java/lang/Thread.setContextClassLoader:(Ljava/lang/ClassLoader;)V
      73: aload_1
      74: aload_2
      75: invokeinterface #13,  2           // InterfaceMethod org/apache/dubbo/rpc/Invoker.invoke:(Lorg/apache/dubbo/rpc/Invocation;)Lorg/apache/dubbo/rpc/Result;
      80: astore        5
      82: invokestatic  #3                  // Method java/lang/Thread.currentThread:()Ljava/lang/Thread;
      85: aload_3
      86: invokevirtual #12                 // Method java/lang/Thread.setContextClassLoader:(Ljava/lang/ClassLoader;)V
      89: aload         5
      91: areturn
      92: astore        6
      94: invokestatic  #3                  // Method java/lang/Thread.currentThread:()Ljava/lang/Thread;
      97: aload_3
      98: invokevirtual #12                 // Method java/lang/Thread.setContextClassLoader:(Ljava/lang/ClassLoader;)V
     101: aload         6
     103: athrow
    Exception table:
       from    to  target type
          73    82    92   any
          92    94    92   any

  public void onResponse(org.apache.dubbo.rpc.Result, org.apache.dubbo.rpc.Invoker<?>, org.apache.dubbo.rpc.Invocation);
    Code:
       0: aload_0
       1: aload_2
       2: aload_3
       3: invokespecial #14                 // Method resetClassLoader:(Lorg/apache/dubbo/rpc/Invoker;Lorg/apache/dubbo/rpc/Invocation;)V
       6: return

  public void onError(java.lang.Throwable, org.apache.dubbo.rpc.Invoker<?>, org.apache.dubbo.rpc.Invocation);
    Code:
       0: aload_0
       1: aload_2
       2: aload_3
       3: invokespecial #14                 // Method resetClassLoader:(Lorg/apache/dubbo/rpc/Invoker;Lorg/apache/dubbo/rpc/Invocation;)V
       6: return

  private void resetClassLoader(org.apache.dubbo.rpc.Invoker<?>, org.apache.dubbo.rpc.Invocation);
    Code:
       0: aload_2
       1: ldc           #9                  // String STAGED_CLASSLOADER
       3: invokeinterface #15,  2           // InterfaceMethod org/apache/dubbo/rpc/Invocation.get:(Ljava/lang/Object;)Ljava/lang/Object;
       8: checkcast     #16                 // class java/lang/ClassLoader
      11: astore_3
      12: aload_3
      13: ifnull        23
      16: invokestatic  #3                  // Method java/lang/Thread.currentThread:()Ljava/lang/Thread;
      19: aload_3
      20: invokevirtual #12                 // Method java/lang/Thread.setContextClassLoader:(Ljava/lang/ClassLoader;)V
      23: return
}
