Compiled from "ContextFilter.java"
public class org.apache.dubbo.rpc.filter.ContextFilter implements org.apache.dubbo.rpc.Filter,org.apache.dubbo.rpc.BaseFilter$Listener {
  private final java.util.Set<org.apache.dubbo.rpc.PenetrateAttachmentSelector> supportedSelectors;

  private static final java.util.Set<java.lang.String> UNLOADING_KEYS;

  public org.apache.dubbo.rpc.filter.ContextFilter(org.apache.dubbo.rpc.model.ApplicationModel);
    Code:
       0: aload_0
       1: invokespecial #3                  // Method java/lang/Object."<init>":()V
       4: aload_1
       5: ldc           #4                  // class org/apache/dubbo/rpc/PenetrateAttachmentSelector
       7: invokevirtual #5                  // Method org/apache/dubbo/rpc/model/ApplicationModel.getExtensionLoader:(Ljava/lang/Class;)Lorg/apache/dubbo/common/extension/ExtensionLoader;
      10: astore_2
      11: aload_0
      12: aload_2
      13: invokevirtual #6                  // Method org/apache/dubbo/common/extension/ExtensionLoader.getSupportedExtensionInstances:()Ljava/util/Set;
      16: putfield      #7                  // Field supportedSelectors:Ljava/util/Set;
      19: return

  public org.apache.dubbo.rpc.Result invoke(org.apache.dubbo.rpc.Invoker<?>, org.apache.dubbo.rpc.Invocation) throws org.apache.dubbo.rpc.RpcException;
    Code:
       0: aload_2
       1: invokeinterface #8,  1            // InterfaceMethod org/apache/dubbo/rpc/Invocation.getObjectAttachments:()Ljava/util/Map;
       6: astore_3
       7: aload_3
       8: ifnull        109
      11: new           #9                  // class java/util/HashMap
      14: dup
      15: aload_3
      16: invokeinterface #10,  1           // InterfaceMethod java/util/Map.size:()I
      21: invokespecial #11                 // Method java/util/HashMap."<init>":(I)V
      24: astore        4
      26: aload_3
      27: invokeinterface #12,  1           // InterfaceMethod java/util/Map.entrySet:()Ljava/util/Set;
      32: invokeinterface #13,  1           // InterfaceMethod java/util/Set.iterator:()Ljava/util/Iterator;
      37: astore        5
      39: aload         5
      41: invokeinterface #14,  1           // InterfaceMethod java/util/Iterator.hasNext:()Z
      46: ifeq          106
      49: aload         5
      51: invokeinterface #15,  1           // InterfaceMethod java/util/Iterator.next:()Ljava/lang/Object;
      56: checkcast     #16                 // class java/util/Map$Entry
      59: astore        6
      61: aload         6
      63: invokeinterface #17,  1           // InterfaceMethod java/util/Map$Entry.getKey:()Ljava/lang/Object;
      68: checkcast     #18                 // class java/lang/String
      71: astore        7
      73: getstatic     #19                 // Field UNLOADING_KEYS:Ljava/util/Set;
      76: aload         7
      78: invokeinterface #20,  2           // InterfaceMethod java/util/Set.contains:(Ljava/lang/Object;)Z
      83: ifne          103
      86: aload         4
      88: aload         7
      90: aload         6
      92: invokeinterface #21,  1           // InterfaceMethod java/util/Map$Entry.getValue:()Ljava/lang/Object;
      97: invokeinterface #22,  3           // InterfaceMethod java/util/Map.put:(Ljava/lang/Object;Ljava/lang/Object;)Ljava/lang/Object;
     102: pop
     103: goto          39
     106: aload         4
     108: astore_3
     109: invokestatic  #23                 // Method org/apache/dubbo/rpc/RpcContext.getServiceContext:()Lorg/apache/dubbo/rpc/RpcServiceContext;
     112: aload_1
     113: invokevirtual #24                 // Method org/apache/dubbo/rpc/RpcServiceContext.setInvoker:(Lorg/apache/dubbo/rpc/Invoker;)Lorg/apache/dubbo/rpc/RpcServiceContext;
     116: aload_2
     117: invokevirtual #25                 // Method org/apache/dubbo/rpc/RpcServiceContext.setInvocation:(Lorg/apache/dubbo/rpc/Invocation;)Lorg/apache/dubbo/rpc/RpcServiceContext;
     120: pop
     121: invokestatic  #26                 // Method org/apache/dubbo/rpc/RpcContext.getServerAttachment:()Lorg/apache/dubbo/rpc/RpcContextAttachment;
     124: astore        4
     126: aload         4
     128: invokevirtual #27                 // Method org/apache/dubbo/rpc/RpcContext.getLocalAddress:()Ljava/net/InetSocketAddress;
     131: ifnonnull     158
     134: aload         4
     136: aload_1
     137: invokeinterface #28,  1           // InterfaceMethod org/apache/dubbo/rpc/Invoker.getUrl:()Lorg/apache/dubbo/common/URL;
     142: invokevirtual #29                 // Method org/apache/dubbo/common/URL.getHost:()Ljava/lang/String;
     145: aload_1
     146: invokeinterface #28,  1           // InterfaceMethod org/apache/dubbo/rpc/Invoker.getUrl:()Lorg/apache/dubbo/common/URL;
     151: invokevirtual #30                 // Method org/apache/dubbo/common/URL.getPort:()I
     154: invokevirtual #31                 // Method org/apache/dubbo/rpc/RpcContext.setLocalAddress:(Ljava/lang/String;I)Lorg/apache/dubbo/rpc/RpcContext;
     157: pop
     158: aload_2
     159: ldc           #32                 // String remote.application
     161: invokeinterface #33,  2           // InterfaceMethod org/apache/dubbo/rpc/Invocation.getAttachment:(Ljava/lang/String;)Ljava/lang/String;
     166: astore        5
     168: aload         5
     170: invokestatic  #34                 // Method org/apache/dubbo/common/utils/StringUtils.isNotEmpty:(Ljava/lang/String;)Z
     173: ifeq          188
     176: invokestatic  #23                 // Method org/apache/dubbo/rpc/RpcContext.getServiceContext:()Lorg/apache/dubbo/rpc/RpcServiceContext;
     179: aload         5
     181: invokevirtual #35                 // Method org/apache/dubbo/rpc/RpcServiceContext.setRemoteApplicationName:(Ljava/lang/String;)Lorg/apache/dubbo/rpc/RpcServiceContext;
     184: pop
     185: goto          202
     188: invokestatic  #23                 // Method org/apache/dubbo/rpc/RpcContext.getServiceContext:()Lorg/apache/dubbo/rpc/RpcServiceContext;
     191: aload         4
     193: ldc           #32                 // String remote.application
     195: invokevirtual #36                 // Method org/apache/dubbo/rpc/RpcContext.getAttachment:(Ljava/lang/String;)Ljava/lang/String;
     198: invokevirtual #35                 // Method org/apache/dubbo/rpc/RpcServiceContext.setRemoteApplicationName:(Ljava/lang/String;)Lorg/apache/dubbo/rpc/RpcServiceContext;
     201: pop
     202: aload_2
     203: ldc2_w        #37                 // long -1l
     206: invokestatic  #39                 // Method org/apache/dubbo/rpc/support/RpcUtils.getTimeout:(Lorg/apache/dubbo/rpc/Invocation;J)J
     209: lstore        6
     211: lload         6
     213: ldc2_w        #37                 // long -1l
     216: lcmp
     217: ifeq          237
     220: invokestatic  #26                 // Method org/apache/dubbo/rpc/RpcContext.getServerAttachment:()Lorg/apache/dubbo/rpc/RpcContextAttachment;
     223: ldc           #40                 // String timeout-countdown
     225: lload         6
     227: getstatic     #41                 // Field java/util/concurrent/TimeUnit.MILLISECONDS:Ljava/util/concurrent/TimeUnit;
     230: invokestatic  #42                 // Method org/apache/dubbo/rpc/TimeoutCountDown.newCountDown:(JLjava/util/concurrent/TimeUnit;)Lorg/apache/dubbo/rpc/TimeoutCountDown;
     233: invokevirtual #43                 // Method org/apache/dubbo/rpc/RpcContextAttachment.setObjectAttachment:(Ljava/lang/String;Ljava/lang/Object;)Lorg/apache/dubbo/rpc/RpcContextAttachment;
     236: pop
     237: aload_3
     238: invokestatic  #44                 // Method org/apache/dubbo/common/utils/CollectionUtils.isNotEmptyMap:(Ljava/util/Map;)Z
     241: ifeq          278
     244: aload         4
     246: invokevirtual #45                 // Method org/apache/dubbo/rpc/RpcContext.getObjectAttachments:()Ljava/util/Map;
     249: invokeinterface #10,  1           // InterfaceMethod java/util/Map.size:()I
     254: ifle          271
     257: aload         4
     259: invokevirtual #45                 // Method org/apache/dubbo/rpc/RpcContext.getObjectAttachments:()Ljava/util/Map;
     262: aload_3
     263: invokeinterface #46,  2           // InterfaceMethod java/util/Map.putAll:(Ljava/util/Map;)V
     268: goto          278
     271: aload         4
     273: aload_3
     274: invokevirtual #47                 // Method org/apache/dubbo/rpc/RpcContext.setObjectAttachments:(Ljava/util/Map;)Lorg/apache/dubbo/rpc/RpcContext;
     277: pop
     278: aload_2
     279: instanceof    #48                 // class org/apache/dubbo/rpc/RpcInvocation
     282: ifeq          297
     285: aload_2
     286: checkcast     #48                 // class org/apache/dubbo/rpc/RpcInvocation
     289: astore        8
     291: aload         8
     293: aload_1
     294: invokevirtual #49                 // Method org/apache/dubbo/rpc/RpcInvocation.setInvoker:(Lorg/apache/dubbo/rpc/Invoker;)V
     297: aload         4
     299: iconst_0
     300: invokevirtual #50                 // Method org/apache/dubbo/rpc/RpcContext.clearAfterEachInvoke:(Z)V
     303: aload_1
     304: aload_2
     305: invokeinterface #51,  2           // InterfaceMethod org/apache/dubbo/rpc/Invoker.invoke:(Lorg/apache/dubbo/rpc/Invocation;)Lorg/apache/dubbo/rpc/Result;
     310: astore        8
     312: aload         4
     314: iconst_1
     315: invokevirtual #50                 // Method org/apache/dubbo/rpc/RpcContext.clearAfterEachInvoke:(Z)V
     318: aload         4
     320: invokevirtual #52                 // Method org/apache/dubbo/rpc/RpcContext.isAsyncStarted:()Z
     323: ifeq          330
     326: aload_0
     327: invokespecial #53                 // Method removeContext:()V
     330: aload         8
     332: areturn
     333: astore        9
     335: aload         4
     337: iconst_1
     338: invokevirtual #50                 // Method org/apache/dubbo/rpc/RpcContext.clearAfterEachInvoke:(Z)V
     341: aload         4
     343: invokevirtual #52                 // Method org/apache/dubbo/rpc/RpcContext.isAsyncStarted:()Z
     346: ifeq          353
     349: aload_0
     350: invokespecial #53                 // Method removeContext:()V
     353: aload         9
     355: athrow
    Exception table:
       from    to  target type
         297   312   333   any
         333   335   333   any

  public void onResponse(org.apache.dubbo.rpc.Result, org.apache.dubbo.rpc.Invoker<?>, org.apache.dubbo.rpc.Invocation);
    Code:
       0: aload_0
       1: getfield      #7                  // Field supportedSelectors:Ljava/util/Set;
       4: invokestatic  #54                 // Method org/apache/dubbo/common/utils/CollectionUtils.isNotEmpty:(Ljava/util/Collection;)Z
       7: ifeq          81
      10: aload_0
      11: getfield      #7                  // Field supportedSelectors:Ljava/util/Set;
      14: invokeinterface #13,  1           // InterfaceMethod java/util/Set.iterator:()Ljava/util/Iterator;
      19: astore        4
      21: aload         4
      23: invokeinterface #14,  1           // InterfaceMethod java/util/Iterator.hasNext:()Z
      28: ifeq          78
      31: aload         4
      33: invokeinterface #15,  1           // InterfaceMethod java/util/Iterator.next:()Ljava/lang/Object;
      38: checkcast     #4                  // class org/apache/dubbo/rpc/PenetrateAttachmentSelector
      41: astore        5
      43: aload         5
      45: aload_3
      46: invokestatic  #55                 // Method org/apache/dubbo/rpc/RpcContext.getClientResponseContext:()Lorg/apache/dubbo/rpc/RpcContextAttachment;
      49: invokestatic  #56                 // Method org/apache/dubbo/rpc/RpcContext.getServerResponseContext:()Lorg/apache/dubbo/rpc/RpcContextAttachment;
      52: invokeinterface #57,  4           // InterfaceMethod org/apache/dubbo/rpc/PenetrateAttachmentSelector.selectReverse:(Lorg/apache/dubbo/rpc/Invocation;Lorg/apache/dubbo/rpc/RpcContextAttachment;Lorg/apache/dubbo/rpc/RpcContextAttachment;)Ljava/util/Map;
      57: astore        6
      59: aload         6
      61: invokestatic  #44                 // Method org/apache/dubbo/common/utils/CollectionUtils.isNotEmptyMap:(Ljava/util/Map;)Z
      64: ifeq          75
      67: aload_1
      68: aload         6
      70: invokeinterface #58,  2           // InterfaceMethod org/apache/dubbo/rpc/Result.addObjectAttachments:(Ljava/util/Map;)V
      75: goto          21
      78: goto          93
      81: aload_1
      82: invokestatic  #55                 // Method org/apache/dubbo/rpc/RpcContext.getClientResponseContext:()Lorg/apache/dubbo/rpc/RpcContextAttachment;
      85: invokevirtual #59                 // Method org/apache/dubbo/rpc/RpcContextAttachment.getObjectAttachments:()Ljava/util/Map;
      88: invokeinterface #58,  2           // InterfaceMethod org/apache/dubbo/rpc/Result.addObjectAttachments:(Ljava/util/Map;)V
      93: aload_1
      94: invokestatic  #56                 // Method org/apache/dubbo/rpc/RpcContext.getServerResponseContext:()Lorg/apache/dubbo/rpc/RpcContextAttachment;
      97: invokevirtual #59                 // Method org/apache/dubbo/rpc/RpcContextAttachment.getObjectAttachments:()Ljava/util/Map;
     100: invokeinterface #58,  2           // InterfaceMethod org/apache/dubbo/rpc/Result.addObjectAttachments:(Ljava/util/Map;)V
     105: aload_0
     106: invokespecial #53                 // Method removeContext:()V
     109: return

  public void onError(java.lang.Throwable, org.apache.dubbo.rpc.Invoker<?>, org.apache.dubbo.rpc.Invocation);
    Code:
       0: aload_0
       1: invokespecial #53                 // Method removeContext:()V
       4: return

  private void removeContext();
    Code:
       0: invokestatic  #60                 // Method org/apache/dubbo/rpc/RpcContext.removeServerAttachment:()V
       3: invokestatic  #61                 // Method org/apache/dubbo/rpc/RpcContext.removeClientAttachment:()V
       6: invokestatic  #62                 // Method org/apache/dubbo/rpc/RpcContext.removeServiceContext:()V
       9: invokestatic  #63                 // Method org/apache/dubbo/rpc/RpcContext.removeClientResponseContext:()V
      12: invokestatic  #64                 // Method org/apache/dubbo/rpc/RpcContext.removeServerResponseContext:()V
      15: return

  static {};
    Code:
       0: new           #65                 // class java/util/HashSet
       3: dup
       4: bipush        16
       6: invokespecial #66                 // Method java/util/HashSet."<init>":(I)V
       9: putstatic     #19                 // Field UNLOADING_KEYS:Ljava/util/Set;
      12: getstatic     #19                 // Field UNLOADING_KEYS:Ljava/util/Set;
      15: ldc           #67                 // String path
      17: invokeinterface #68,  2           // InterfaceMethod java/util/Set.add:(Ljava/lang/Object;)Z
      22: pop
      23: getstatic     #19                 // Field UNLOADING_KEYS:Ljava/util/Set;
      26: ldc           #69                 // String interface
      28: invokeinterface #68,  2           // InterfaceMethod java/util/Set.add:(Ljava/lang/Object;)Z
      33: pop
      34: getstatic     #19                 // Field UNLOADING_KEYS:Ljava/util/Set;
      37: ldc           #70                 // String group
      39: invokeinterface #68,  2           // InterfaceMethod java/util/Set.add:(Ljava/lang/Object;)Z
      44: pop
      45: getstatic     #19                 // Field UNLOADING_KEYS:Ljava/util/Set;
      48: ldc           #71                 // String version
      50: invokeinterface #68,  2           // InterfaceMethod java/util/Set.add:(Ljava/lang/Object;)Z
      55: pop
      56: getstatic     #19                 // Field UNLOADING_KEYS:Ljava/util/Set;
      59: ldc           #72                 // String dubbo
      61: invokeinterface #68,  2           // InterfaceMethod java/util/Set.add:(Ljava/lang/Object;)Z
      66: pop
      67: getstatic     #19                 // Field UNLOADING_KEYS:Ljava/util/Set;
      70: ldc           #73                 // String token
      72: invokeinterface #68,  2           // InterfaceMethod java/util/Set.add:(Ljava/lang/Object;)Z
      77: pop
      78: getstatic     #19                 // Field UNLOADING_KEYS:Ljava/util/Set;
      81: ldc           #74                 // String timeout
      83: invokeinterface #68,  2           // InterfaceMethod java/util/Set.add:(Ljava/lang/Object;)Z
      88: pop
      89: getstatic     #19                 // Field UNLOADING_KEYS:Ljava/util/Set;
      92: ldc           #75                 // String _TO
      94: invokeinterface #68,  2           // InterfaceMethod java/util/Set.add:(Ljava/lang/Object;)Z
      99: pop
     100: getstatic     #19                 // Field UNLOADING_KEYS:Ljava/util/Set;
     103: ldc           #76                 // String async
     105: invokeinterface #68,  2           // InterfaceMethod java/util/Set.add:(Ljava/lang/Object;)Z
     110: pop
     111: getstatic     #19                 // Field UNLOADING_KEYS:Ljava/util/Set;
     114: ldc           #77                 // String dubbo.tag
     116: invokeinterface #68,  2           // InterfaceMethod java/util/Set.add:(Ljava/lang/Object;)Z
     121: pop
     122: getstatic     #19                 // Field UNLOADING_KEYS:Ljava/util/Set;
     125: ldc           #78                 // String dubbo.force.tag
     127: invokeinterface #68,  2           // InterfaceMethod java/util/Set.add:(Ljava/lang/Object;)Z
     132: pop
     133: return
}
