Compiled from "DeprecatedFilter.java"
public class org.apache.dubbo.rpc.filter.DeprecatedFilter implements org.apache.dubbo.rpc.Filter {
  private static final org.apache.dubbo.common.logger.ErrorTypeAwareLogger LOGGER;

  private static final java.util.Set<java.lang.String> LOGGED;

  public org.apache.dubbo.rpc.filter.DeprecatedFilter();
    Code:
       0: aload_0
       1: invokespecial #3                  // Method java/lang/Object."<init>":()V
       4: return

  public org.apache.dubbo.rpc.Result invoke(org.apache.dubbo.rpc.Invoker<?>, org.apache.dubbo.rpc.Invocation) throws org.apache.dubbo.rpc.RpcException;
    Code:
       0: new           #4                  // class java/lang/StringBuilder
       3: dup
       4: invokespecial #5                  // Method java/lang/StringBuilder."<init>":()V
       7: aload_1
       8: invokeinterface #6,  1            // InterfaceMethod org/apache/dubbo/rpc/Invoker.getInterface:()Ljava/lang/Class;
      13: invokevirtual #7                  // Method java/lang/Class.getName:()Ljava/lang/String;
      16: invokevirtual #8                  // Method java/lang/StringBuilder.append:(Ljava/lang/String;)Ljava/lang/StringBuilder;
      19: ldc           #9                  // String .
      21: invokevirtual #8                  // Method java/lang/StringBuilder.append:(Ljava/lang/String;)Ljava/lang/StringBuilder;
      24: aload_2
      25: invokeinterface #10,  1           // InterfaceMethod org/apache/dubbo/rpc/Invocation.getMethodName:()Ljava/lang/String;
      30: invokevirtual #8                  // Method java/lang/StringBuilder.append:(Ljava/lang/String;)Ljava/lang/StringBuilder;
      33: invokevirtual #11                 // Method java/lang/StringBuilder.toString:()Ljava/lang/String;
      36: astore_3
      37: getstatic     #12                 // Field LOGGED:Ljava/util/Set;
      40: aload_3
      41: invokeinterface #13,  2           // InterfaceMethod java/util/Set.contains:(Ljava/lang/Object;)Z
      46: ifne          148
      49: getstatic     #12                 // Field LOGGED:Ljava/util/Set;
      52: aload_3
      53: invokeinterface #14,  2           // InterfaceMethod java/util/Set.add:(Ljava/lang/Object;)Z
      58: pop
      59: aload_1
      60: invokeinterface #15,  1           // InterfaceMethod org/apache/dubbo/rpc/Invoker.getUrl:()Lorg/apache/dubbo/common/URL;
      65: aload_2
      66: invokeinterface #10,  1           // InterfaceMethod org/apache/dubbo/rpc/Invocation.getMethodName:()Ljava/lang/String;
      71: ldc           #16                 // String deprecated
      73: iconst_0
      74: invokevirtual #17                 // Method org/apache/dubbo/common/URL.getMethodParameter:(Ljava/lang/String;Ljava/lang/String;Z)Z
      77: ifeq          148
      80: getstatic     #18                 // Field LOGGER:Lorg/apache/dubbo/common/logger/ErrorTypeAwareLogger;
      83: ldc           #19                 // String 0-10
      85: ldc           #20                 // String
      87: ldc           #20                 // String
      89: new           #4                  // class java/lang/StringBuilder
      92: dup
      93: invokespecial #5                  // Method java/lang/StringBuilder."<init>":()V
      96: ldc           #21                 // String The service method
      98: invokevirtual #8                  // Method java/lang/StringBuilder.append:(Ljava/lang/String;)Ljava/lang/StringBuilder;
     101: aload_1
     102: invokeinterface #6,  1            // InterfaceMethod org/apache/dubbo/rpc/Invoker.getInterface:()Ljava/lang/Class;
     107: invokevirtual #7                  // Method java/lang/Class.getName:()Ljava/lang/String;
     110: invokevirtual #8                  // Method java/lang/StringBuilder.append:(Ljava/lang/String;)Ljava/lang/StringBuilder;
     113: ldc           #9                  // String .
     115: invokevirtual #8                  // Method java/lang/StringBuilder.append:(Ljava/lang/String;)Ljava/lang/StringBuilder;
     118: aload_0
     119: aload_2
     120: invokespecial #22                 // Method getMethodSignature:(Lorg/apache/dubbo/rpc/Invocation;)Ljava/lang/String;
     123: invokevirtual #8                  // Method java/lang/StringBuilder.append:(Ljava/lang/String;)Ljava/lang/StringBuilder;
     126: ldc           #23                 // String  is DEPRECATED! Declare from
     128: invokevirtual #8                  // Method java/lang/StringBuilder.append:(Ljava/lang/String;)Ljava/lang/StringBuilder;
     131: aload_1
     132: invokeinterface #15,  1           // InterfaceMethod org/apache/dubbo/rpc/Invoker.getUrl:()Lorg/apache/dubbo/common/URL;
     137: invokevirtual #24                 // Method java/lang/StringBuilder.append:(Ljava/lang/Object;)Ljava/lang/StringBuilder;
     140: invokevirtual #11                 // Method java/lang/StringBuilder.toString:()Ljava/lang/String;
     143: invokeinterface #25,  5           // InterfaceMethod org/apache/dubbo/common/logger/ErrorTypeAwareLogger.error:(Ljava/lang/String;Ljava/lang/String;Ljava/lang/String;Ljava/lang/String;)V
     148: aload_1
     149: aload_2
     150: invokeinterface #26,  2           // InterfaceMethod org/apache/dubbo/rpc/Invoker.invoke:(Lorg/apache/dubbo/rpc/Invocation;)Lorg/apache/dubbo/rpc/Result;
     155: areturn

  private java.lang.String getMethodSignature(org.apache.dubbo.rpc.Invocation);
    Code:
       0: new           #4                  // class java/lang/StringBuilder
       3: dup
       4: aload_1
       5: invokeinterface #10,  1           // InterfaceMethod org/apache/dubbo/rpc/Invocation.getMethodName:()Ljava/lang/String;
      10: invokespecial #27                 // Method java/lang/StringBuilder."<init>":(Ljava/lang/String;)V
      13: astore_2
      14: aload_2
      15: bipush        40
      17: invokevirtual #28                 // Method java/lang/StringBuilder.append:(C)Ljava/lang/StringBuilder;
      20: pop
      21: aload_1
      22: invokeinterface #29,  1           // InterfaceMethod org/apache/dubbo/rpc/Invocation.getParameterTypes:()[Ljava/lang/Class;
      27: astore_3
      28: aload_3
      29: ifnull        99
      32: aload_3
      33: arraylength
      34: ifle          99
      37: iconst_1
      38: istore        4
      40: aload_3
      41: astore        5
      43: aload         5
      45: arraylength
      46: istore        6
      48: iconst_0
      49: istore        7
      51: iload         7
      53: iload         6
      55: if_icmpge     99
      58: aload         5
      60: iload         7
      62: aaload
      63: astore        8
      65: iload         4
      67: ifeq          76
      70: iconst_0
      71: istore        4
      73: goto          83
      76: aload_2
      77: ldc           #30                 // String ,
      79: invokevirtual #8                  // Method java/lang/StringBuilder.append:(Ljava/lang/String;)Ljava/lang/StringBuilder;
      82: pop
      83: aload_2
      84: aload         8
      86: invokevirtual #31                 // Method java/lang/Class.getSimpleName:()Ljava/lang/String;
      89: invokevirtual #8                  // Method java/lang/StringBuilder.append:(Ljava/lang/String;)Ljava/lang/StringBuilder;
      92: pop
      93: iinc          7, 1
      96: goto          51
      99: aload_2
     100: bipush        41
     102: invokevirtual #28                 // Method java/lang/StringBuilder.append:(C)Ljava/lang/StringBuilder;
     105: pop
     106: aload_2
     107: invokevirtual #11                 // Method java/lang/StringBuilder.toString:()Ljava/lang/String;
     110: areturn

  static {};
    Code:
       0: ldc           #32                 // class org/apache/dubbo/rpc/filter/DeprecatedFilter
       2: invokestatic  #33                 // Method org/apache/dubbo/common/logger/LoggerFactory.getErrorTypeAwareLogger:(Ljava/lang/Class;)Lorg/apache/dubbo/common/logger/ErrorTypeAwareLogger;
       5: putstatic     #18                 // Field LOGGER:Lorg/apache/dubbo/common/logger/ErrorTypeAwareLogger;
       8: new           #34                 // class org/apache/dubbo/common/utils/ConcurrentHashSet
      11: dup
      12: invokespecial #35                 // Method org/apache/dubbo/common/utils/ConcurrentHashSet."<init>":()V
      15: putstatic     #12                 // Field LOGGED:Ljava/util/Set;
      18: return
}
