Compiled from "EchoFilter.java"
public class org.apache.dubbo.rpc.filter.EchoFilter implements org.apache.dubbo.rpc.Filter {
  public org.apache.dubbo.rpc.filter.EchoFilter();
    Code:
       0: aload_0
       1: invokespecial #2                  // Method java/lang/Object."<init>":()V
       4: return

  public org.apache.dubbo.rpc.Result invoke(org.apache.dubbo.rpc.Invoker<?>, org.apache.dubbo.rpc.Invocation) throws org.apache.dubbo.rpc.RpcException;
    Code:
       0: aload_2
       1: invokeinterface #3,  1            // InterfaceMethod org/apache/dubbo/rpc/Invocation.getMethodName:()Ljava/lang/String;
       6: ldc           #4                  // String $echo
       8: invokevirtual #5                  // Method java/lang/String.equals:(Ljava/lang/Object;)Z
      11: ifeq          47
      14: aload_2
      15: invokeinterface #6,  1            // InterfaceMethod org/apache/dubbo/rpc/Invocation.getArguments:()[Ljava/lang/Object;
      20: ifnull        47
      23: aload_2
      24: invokeinterface #6,  1            // InterfaceMethod org/apache/dubbo/rpc/Invocation.getArguments:()[Ljava/lang/Object;
      29: arraylength
      30: iconst_1
      31: if_icmpne     47
      34: aload_2
      35: invokeinterface #6,  1            // InterfaceMethod org/apache/dubbo/rpc/Invocation.getArguments:()[Ljava/lang/Object;
      40: iconst_0
      41: aaload
      42: aload_2
      43: invokestatic  #7                  // Method org/apache/dubbo/rpc/AsyncRpcResult.newDefaultAsyncResult:(Ljava/lang/Object;Lorg/apache/dubbo/rpc/Invocation;)Lorg/apache/dubbo/rpc/AsyncRpcResult;
      46: areturn
      47: aload_1
      48: aload_2
      49: invokeinterface #8,  2            // InterfaceMethod org/apache/dubbo/rpc/Invoker.invoke:(Lorg/apache/dubbo/rpc/Invocation;)Lorg/apache/dubbo/rpc/Result;
      54: areturn
}
