Compiled from "ExceptionFilter.java"
public class org.apache.dubbo.rpc.filter.ExceptionFilter implements org.apache.dubbo.rpc.Filter,org.apache.dubbo.rpc.BaseFilter$Listener {
  private org.apache.dubbo.common.logger.ErrorTypeAwareLogger logger;

  public org.apache.dubbo.rpc.filter.ExceptionFilter();
    Code:
       0: aload_0
       1: invokespecial #2                  // Method java/lang/Object."<init>":()V
       4: aload_0
       5: ldc           #3                  // class org/apache/dubbo/rpc/filter/ExceptionFilter
       7: invokestatic  #4                  // Method org/apache/dubbo/common/logger/LoggerFactory.getErrorTypeAwareLogger:(Ljava/lang/Class;)Lorg/apache/dubbo/common/logger/ErrorTypeAwareLogger;
      10: putfield      #5                  // Field logger:Lorg/apache/dubbo/common/logger/ErrorTypeAwareLogger;
      13: return

  public org.apache.dubbo.rpc.Result invoke(org.apache.dubbo.rpc.Invoker<?>, org.apache.dubbo.rpc.Invocation) throws org.apache.dubbo.rpc.RpcException;
    Code:
       0: aload_1
       1: aload_2
       2: invokeinterface #6,  2            // InterfaceMethod org/apache/dubbo/rpc/Invoker.invoke:(Lorg/apache/dubbo/rpc/Invocation;)Lorg/apache/dubbo/rpc/Result;
       7: areturn

  public void onResponse(org.apache.dubbo.rpc.Result, org.apache.dubbo.rpc.Invoker<?>, org.apache.dubbo.rpc.Invocation);
    Code:
       0: aload_1
       1: invokeinterface #7,  1            // InterfaceMethod org/apache/dubbo/rpc/Result.hasException:()Z
       6: ifeq          434
       9: ldc           #8                  // class org/apache/dubbo/rpc/service/GenericService
      11: aload_2
      12: invokeinterface #9,  1            // InterfaceMethod org/apache/dubbo/rpc/Invoker.getInterface:()Ljava/lang/Class;
      17: if_acmpeq     434
      20: aload_1
      21: invokeinterface #10,  1           // InterfaceMethod org/apache/dubbo/rpc/Result.getException:()Ljava/lang/Throwable;
      26: astore        4
      28: aload         4
      30: instanceof    #11                 // class java/lang/RuntimeException
      33: ifne          45
      36: aload         4
      38: instanceof    #12                 // class java/lang/Exception
      41: ifeq          45
      44: return
      45: aload_2
      46: invokeinterface #9,  1            // InterfaceMethod org/apache/dubbo/rpc/Invoker.getInterface:()Ljava/lang/Class;
      51: aload_3
      52: invokeinterface #13,  1           // InterfaceMethod org/apache/dubbo/rpc/Invocation.getMethodName:()Ljava/lang/String;
      57: aload_3
      58: invokeinterface #14,  1           // InterfaceMethod org/apache/dubbo/rpc/Invocation.getParameterTypes:()[Ljava/lang/Class;
      63: invokevirtual #15                 // Method java/lang/Class.getMethod:(Ljava/lang/String;[Ljava/lang/Class;)Ljava/lang/reflect/Method;
      66: astore        5
      68: aload         5
      70: invokevirtual #16                 // Method java/lang/reflect/Method.getExceptionTypes:()[Ljava/lang/Class;
      73: astore        6
      75: aload         6
      77: astore        7
      79: aload         7
      81: arraylength
      82: istore        8
      84: iconst_0
      85: istore        9
      87: iload         9
      89: iload         8
      91: if_icmpge     121
      94: aload         7
      96: iload         9
      98: aaload
      99: astore        10
     101: aload         4
     103: invokevirtual #17                 // Method java/lang/Object.getClass:()Ljava/lang/Class;
     106: aload         10
     108: invokevirtual #18                 // Method java/lang/Object.equals:(Ljava/lang/Object;)Z
     111: ifeq          115
     114: return
     115: iinc          9, 1
     118: goto          87
     121: goto          127
     124: astore        5
     126: return
     127: aload_0
     128: getfield      #5                  // Field logger:Lorg/apache/dubbo/common/logger/ErrorTypeAwareLogger;
     131: ldc           #20                 // String 5-36
     133: ldc           #21                 // String
     135: ldc           #21                 // String
     137: new           #22                 // class java/lang/StringBuilder
     140: dup
     141: invokespecial #23                 // Method java/lang/StringBuilder."<init>":()V
     144: ldc           #24                 // String Got unchecked and undeclared exception which called by
     146: invokevirtual #25                 // Method java/lang/StringBuilder.append:(Ljava/lang/String;)Ljava/lang/StringBuilder;
     149: invokestatic  #26                 // Method org/apache/dubbo/rpc/RpcContext.getServiceContext:()Lorg/apache/dubbo/rpc/RpcServiceContext;
     152: invokevirtual #27                 // Method org/apache/dubbo/rpc/RpcServiceContext.getRemoteHost:()Ljava/lang/String;
     155: invokevirtual #25                 // Method java/lang/StringBuilder.append:(Ljava/lang/String;)Ljava/lang/StringBuilder;
     158: ldc           #28                 // String . service:
     160: invokevirtual #25                 // Method java/lang/StringBuilder.append:(Ljava/lang/String;)Ljava/lang/StringBuilder;
     163: aload_2
     164: invokeinterface #9,  1            // InterfaceMethod org/apache/dubbo/rpc/Invoker.getInterface:()Ljava/lang/Class;
     169: invokevirtual #29                 // Method java/lang/Class.getName:()Ljava/lang/String;
     172: invokevirtual #25                 // Method java/lang/StringBuilder.append:(Ljava/lang/String;)Ljava/lang/StringBuilder;
     175: ldc           #30                 // String , method:
     177: invokevirtual #25                 // Method java/lang/StringBuilder.append:(Ljava/lang/String;)Ljava/lang/StringBuilder;
     180: aload_3
     181: invokeinterface #13,  1           // InterfaceMethod org/apache/dubbo/rpc/Invocation.getMethodName:()Ljava/lang/String;
     186: invokevirtual #25                 // Method java/lang/StringBuilder.append:(Ljava/lang/String;)Ljava/lang/StringBuilder;
     189: ldc           #31                 // String , exception:
     191: invokevirtual #25                 // Method java/lang/StringBuilder.append:(Ljava/lang/String;)Ljava/lang/StringBuilder;
     194: aload         4
     196: invokevirtual #17                 // Method java/lang/Object.getClass:()Ljava/lang/Class;
     199: invokevirtual #29                 // Method java/lang/Class.getName:()Ljava/lang/String;
     202: invokevirtual #25                 // Method java/lang/StringBuilder.append:(Ljava/lang/String;)Ljava/lang/StringBuilder;
     205: ldc           #32                 // String :
     207: invokevirtual #25                 // Method java/lang/StringBuilder.append:(Ljava/lang/String;)Ljava/lang/StringBuilder;
     210: aload         4
     212: invokevirtual #33                 // Method java/lang/Throwable.getMessage:()Ljava/lang/String;
     215: invokevirtual #25                 // Method java/lang/StringBuilder.append:(Ljava/lang/String;)Ljava/lang/StringBuilder;
     218: invokevirtual #34                 // Method java/lang/StringBuilder.toString:()Ljava/lang/String;
     221: aload         4
     223: invokeinterface #35,  6           // InterfaceMethod org/apache/dubbo/common/logger/ErrorTypeAwareLogger.error:(Ljava/lang/String;Ljava/lang/String;Ljava/lang/String;Ljava/lang/String;Ljava/lang/Throwable;)V
     228: aload_2
     229: invokeinterface #9,  1            // InterfaceMethod org/apache/dubbo/rpc/Invoker.getInterface:()Ljava/lang/Class;
     234: invokestatic  #36                 // Method org/apache/dubbo/common/utils/ReflectUtils.getCodeBase:(Ljava/lang/Class;)Ljava/lang/String;
     237: astore        5
     239: aload         4
     241: invokevirtual #17                 // Method java/lang/Object.getClass:()Ljava/lang/Class;
     244: invokestatic  #36                 // Method org/apache/dubbo/common/utils/ReflectUtils.getCodeBase:(Ljava/lang/Class;)Ljava/lang/String;
     247: astore        6
     249: aload         5
     251: ifnull        269
     254: aload         6
     256: ifnull        269
     259: aload         5
     261: aload         6
     263: invokevirtual #37                 // Method java/lang/String.equals:(Ljava/lang/Object;)Z
     266: ifeq          270
     269: return
     270: aload         4
     272: invokevirtual #17                 // Method java/lang/Object.getClass:()Ljava/lang/Class;
     275: invokevirtual #29                 // Method java/lang/Class.getName:()Ljava/lang/String;
     278: astore        7
     280: aload         7
     282: ldc           #38                 // String java.
     284: invokevirtual #39                 // Method java/lang/String.startsWith:(Ljava/lang/String;)Z
     287: ifne          300
     290: aload         7
     292: ldc           #40                 // String javax.
     294: invokevirtual #39                 // Method java/lang/String.startsWith:(Ljava/lang/String;)Z
     297: ifeq          301
     300: return
     301: aload         4
     303: instanceof    #41                 // class org/apache/dubbo/rpc/RpcException
     306: ifeq          310
     309: return
     310: aload_1
     311: new           #11                 // class java/lang/RuntimeException
     314: dup
     315: aload         4
     317: invokestatic  #42                 // Method org/apache/dubbo/common/utils/StringUtils.toString:(Ljava/lang/Throwable;)Ljava/lang/String;
     320: invokespecial #43                 // Method java/lang/RuntimeException."<init>":(Ljava/lang/String;)V
     323: invokeinterface #44,  2           // InterfaceMethod org/apache/dubbo/rpc/Result.setException:(Ljava/lang/Throwable;)V
     328: goto          434
     331: astore        4
     333: aload_0
     334: getfield      #5                  // Field logger:Lorg/apache/dubbo/common/logger/ErrorTypeAwareLogger;
     337: ldc           #20                 // String 5-36
     339: ldc           #21                 // String
     341: ldc           #21                 // String
     343: new           #22                 // class java/lang/StringBuilder
     346: dup
     347: invokespecial #23                 // Method java/lang/StringBuilder."<init>":()V
     350: ldc           #46                 // String Fail to ExceptionFilter when called by
     352: invokevirtual #25                 // Method java/lang/StringBuilder.append:(Ljava/lang/String;)Ljava/lang/StringBuilder;
     355: invokestatic  #26                 // Method org/apache/dubbo/rpc/RpcContext.getServiceContext:()Lorg/apache/dubbo/rpc/RpcServiceContext;
     358: invokevirtual #27                 // Method org/apache/dubbo/rpc/RpcServiceContext.getRemoteHost:()Ljava/lang/String;
     361: invokevirtual #25                 // Method java/lang/StringBuilder.append:(Ljava/lang/String;)Ljava/lang/StringBuilder;
     364: ldc           #28                 // String . service:
     366: invokevirtual #25                 // Method java/lang/StringBuilder.append:(Ljava/lang/String;)Ljava/lang/StringBuilder;
     369: aload_2
     370: invokeinterface #9,  1            // InterfaceMethod org/apache/dubbo/rpc/Invoker.getInterface:()Ljava/lang/Class;
     375: invokevirtual #29                 // Method java/lang/Class.getName:()Ljava/lang/String;
     378: invokevirtual #25                 // Method java/lang/StringBuilder.append:(Ljava/lang/String;)Ljava/lang/StringBuilder;
     381: ldc           #30                 // String , method:
     383: invokevirtual #25                 // Method java/lang/StringBuilder.append:(Ljava/lang/String;)Ljava/lang/StringBuilder;
     386: aload_3
     387: invokeinterface #13,  1           // InterfaceMethod org/apache/dubbo/rpc/Invocation.getMethodName:()Ljava/lang/String;
     392: invokevirtual #25                 // Method java/lang/StringBuilder.append:(Ljava/lang/String;)Ljava/lang/StringBuilder;
     395: ldc           #31                 // String , exception:
     397: invokevirtual #25                 // Method java/lang/StringBuilder.append:(Ljava/lang/String;)Ljava/lang/StringBuilder;
     400: aload         4
     402: invokevirtual #17                 // Method java/lang/Object.getClass:()Ljava/lang/Class;
     405: invokevirtual #29                 // Method java/lang/Class.getName:()Ljava/lang/String;
     408: invokevirtual #25                 // Method java/lang/StringBuilder.append:(Ljava/lang/String;)Ljava/lang/StringBuilder;
     411: ldc           #32                 // String :
     413: invokevirtual #25                 // Method java/lang/StringBuilder.append:(Ljava/lang/String;)Ljava/lang/StringBuilder;
     416: aload         4
     418: invokevirtual #33                 // Method java/lang/Throwable.getMessage:()Ljava/lang/String;
     421: invokevirtual #25                 // Method java/lang/StringBuilder.append:(Ljava/lang/String;)Ljava/lang/StringBuilder;
     424: invokevirtual #34                 // Method java/lang/StringBuilder.toString:()Ljava/lang/String;
     427: aload         4
     429: invokeinterface #47,  6           // InterfaceMethod org/apache/dubbo/common/logger/ErrorTypeAwareLogger.warn:(Ljava/lang/String;Ljava/lang/String;Ljava/lang/String;Ljava/lang/String;Ljava/lang/Throwable;)V
     434: return
    Exception table:
       from    to  target type
          45   114   124   Class java/lang/NoSuchMethodException
         115   121   124   Class java/lang/NoSuchMethodException
          20    44   331   Class java/lang/Throwable
          45   114   331   Class java/lang/Throwable
         115   126   331   Class java/lang/Throwable
         127   269   331   Class java/lang/Throwable
         270   300   331   Class java/lang/Throwable
         301   309   331   Class java/lang/Throwable
         310   328   331   Class java/lang/Throwable

  public void onError(java.lang.Throwable, org.apache.dubbo.rpc.Invoker<?>, org.apache.dubbo.rpc.Invocation);
    Code:
       0: aload_0
       1: getfield      #5                  // Field logger:Lorg/apache/dubbo/common/logger/ErrorTypeAwareLogger;
       4: ldc           #20                 // String 5-36
       6: ldc           #21                 // String
       8: ldc           #21                 // String
      10: new           #22                 // class java/lang/StringBuilder
      13: dup
      14: invokespecial #23                 // Method java/lang/StringBuilder."<init>":()V
      17: ldc           #24                 // String Got unchecked and undeclared exception which called by
      19: invokevirtual #25                 // Method java/lang/StringBuilder.append:(Ljava/lang/String;)Ljava/lang/StringBuilder;
      22: invokestatic  #26                 // Method org/apache/dubbo/rpc/RpcContext.getServiceContext:()Lorg/apache/dubbo/rpc/RpcServiceContext;
      25: invokevirtual #27                 // Method org/apache/dubbo/rpc/RpcServiceContext.getRemoteHost:()Ljava/lang/String;
      28: invokevirtual #25                 // Method java/lang/StringBuilder.append:(Ljava/lang/String;)Ljava/lang/StringBuilder;
      31: ldc           #28                 // String . service:
      33: invokevirtual #25                 // Method java/lang/StringBuilder.append:(Ljava/lang/String;)Ljava/lang/StringBuilder;
      36: aload_2
      37: invokeinterface #9,  1            // InterfaceMethod org/apache/dubbo/rpc/Invoker.getInterface:()Ljava/lang/Class;
      42: invokevirtual #29                 // Method java/lang/Class.getName:()Ljava/lang/String;
      45: invokevirtual #25                 // Method java/lang/StringBuilder.append:(Ljava/lang/String;)Ljava/lang/StringBuilder;
      48: ldc           #30                 // String , method:
      50: invokevirtual #25                 // Method java/lang/StringBuilder.append:(Ljava/lang/String;)Ljava/lang/StringBuilder;
      53: aload_3
      54: invokeinterface #13,  1           // InterfaceMethod org/apache/dubbo/rpc/Invocation.getMethodName:()Ljava/lang/String;
      59: invokevirtual #25                 // Method java/lang/StringBuilder.append:(Ljava/lang/String;)Ljava/lang/StringBuilder;
      62: ldc           #31                 // String , exception:
      64: invokevirtual #25                 // Method java/lang/StringBuilder.append:(Ljava/lang/String;)Ljava/lang/StringBuilder;
      67: aload_1
      68: invokevirtual #17                 // Method java/lang/Object.getClass:()Ljava/lang/Class;
      71: invokevirtual #29                 // Method java/lang/Class.getName:()Ljava/lang/String;
      74: invokevirtual #25                 // Method java/lang/StringBuilder.append:(Ljava/lang/String;)Ljava/lang/StringBuilder;
      77: ldc           #32                 // String :
      79: invokevirtual #25                 // Method java/lang/StringBuilder.append:(Ljava/lang/String;)Ljava/lang/StringBuilder;
      82: aload_1
      83: invokevirtual #33                 // Method java/lang/Throwable.getMessage:()Ljava/lang/String;
      86: invokevirtual #25                 // Method java/lang/StringBuilder.append:(Ljava/lang/String;)Ljava/lang/StringBuilder;
      89: invokevirtual #34                 // Method java/lang/StringBuilder.toString:()Ljava/lang/String;
      92: aload_1
      93: invokeinterface #35,  6           // InterfaceMethod org/apache/dubbo/common/logger/ErrorTypeAwareLogger.error:(Ljava/lang/String;Ljava/lang/String;Ljava/lang/String;Ljava/lang/String;Ljava/lang/Throwable;)V
      98: return

  public void setLogger(org.apache.dubbo.common.logger.ErrorTypeAwareLogger);
    Code:
       0: aload_0
       1: aload_1
       2: putfield      #5                  // Field logger:Lorg/apache/dubbo/common/logger/ErrorTypeAwareLogger;
       5: return
}
