Compiled from "ExecuteLimitFilter.java"
public class org.apache.dubbo.rpc.filter.ExecuteLimitFilter implements org.apache.dubbo.rpc.Filter,org.apache.dubbo.rpc.BaseFilter$Listener {
  private static final java.lang.String EXECUTE_LIMIT_FILTER_START_TIME;

  public org.apache.dubbo.rpc.filter.ExecuteLimitFilter();
    Code:
       0: aload_0
       1: invokespecial #3                  // Method java/lang/Object."<init>":()V
       4: return

  public org.apache.dubbo.rpc.Result invoke(org.apache.dubbo.rpc.Invoker<?>, org.apache.dubbo.rpc.Invocation) throws org.apache.dubbo.rpc.RpcException;
    Code:
       0: aload_1
       1: invokeinterface #4,  1            // InterfaceMethod org/apache/dubbo/rpc/Invoker.getUrl:()Lorg/apache/dubbo/common/URL;
       6: astore_3
       7: aload_2
       8: invokeinterface #5,  1            // InterfaceMethod org/apache/dubbo/rpc/Invocation.getMethodName:()Ljava/lang/String;
      13: astore        4
      15: aload_3
      16: aload         4
      18: ldc           #6                  // String executes
      20: iconst_0
      21: invokevirtual #7                  // Method org/apache/dubbo/common/URL.getMethodParameter:(Ljava/lang/String;Ljava/lang/String;I)I
      24: istore        5
      26: aload_3
      27: aload         4
      29: iload         5
      31: invokestatic  #8                  // Method org/apache/dubbo/rpc/RpcStatus.beginCount:(Lorg/apache/dubbo/common/URL;Ljava/lang/String;I)Z
      34: ifne          95
      37: new           #9                  // class org/apache/dubbo/rpc/RpcException
      40: dup
      41: bipush        7
      43: new           #10                 // class java/lang/StringBuilder
      46: dup
      47: invokespecial #11                 // Method java/lang/StringBuilder."<init>":()V
      50: ldc           #12                 // String Failed to invoke method
      52: invokevirtual #13                 // Method java/lang/StringBuilder.append:(Ljava/lang/String;)Ljava/lang/StringBuilder;
      55: aload_2
      56: invokeinterface #5,  1            // InterfaceMethod org/apache/dubbo/rpc/Invocation.getMethodName:()Ljava/lang/String;
      61: invokevirtual #13                 // Method java/lang/StringBuilder.append:(Ljava/lang/String;)Ljava/lang/StringBuilder;
      64: ldc           #14                 // String  in provider
      66: invokevirtual #13                 // Method java/lang/StringBuilder.append:(Ljava/lang/String;)Ljava/lang/StringBuilder;
      69: aload_3
      70: invokevirtual #15                 // Method java/lang/StringBuilder.append:(Ljava/lang/Object;)Ljava/lang/StringBuilder;
      73: ldc           #16                 // String , cause: The service using threads greater than <dubbo:service executes=\"
      75: invokevirtual #13                 // Method java/lang/StringBuilder.append:(Ljava/lang/String;)Ljava/lang/StringBuilder;
      78: iload         5
      80: invokevirtual #17                 // Method java/lang/StringBuilder.append:(I)Ljava/lang/StringBuilder;
      83: ldc           #18                 // String \" /> limited.
      85: invokevirtual #13                 // Method java/lang/StringBuilder.append:(Ljava/lang/String;)Ljava/lang/StringBuilder;
      88: invokevirtual #19                 // Method java/lang/StringBuilder.toString:()Ljava/lang/String;
      91: invokespecial #20                 // Method org/apache/dubbo/rpc/RpcException."<init>":(ILjava/lang/String;)V
      94: athrow
      95: aload_2
      96: ldc           #22                 // String execute_limit_filter_start_time
      98: invokestatic  #23                 // Method java/lang/System.currentTimeMillis:()J
     101: invokestatic  #24                 // Method java/lang/Long.valueOf:(J)Ljava/lang/Long;
     104: invokeinterface #25,  3           // InterfaceMethod org/apache/dubbo/rpc/Invocation.put:(Ljava/lang/Object;Ljava/lang/Object;)Ljava/lang/Object;
     109: pop
     110: aload_1
     111: aload_2
     112: invokeinterface #26,  2           // InterfaceMethod org/apache/dubbo/rpc/Invoker.invoke:(Lorg/apache/dubbo/rpc/Invocation;)Lorg/apache/dubbo/rpc/Result;
     117: areturn
     118: astore        6
     120: aload         6
     122: instanceof    #28                 // class java/lang/RuntimeException
     125: ifeq          134
     128: aload         6
     130: checkcast     #28                 // class java/lang/RuntimeException
     133: athrow
     134: new           #9                  // class org/apache/dubbo/rpc/RpcException
     137: dup
     138: ldc           #29                 // String unexpected exception when ExecuteLimitFilter
     140: aload         6
     142: invokespecial #30                 // Method org/apache/dubbo/rpc/RpcException."<init>":(Ljava/lang/String;Ljava/lang/Throwable;)V
     145: athrow
    Exception table:
       from    to  target type
         110   117   118   Class java/lang/Throwable

  public void onResponse(org.apache.dubbo.rpc.Result, org.apache.dubbo.rpc.Invoker<?>, org.apache.dubbo.rpc.Invocation);
    Code:
       0: aload_2
       1: invokeinterface #4,  1            // InterfaceMethod org/apache/dubbo/rpc/Invoker.getUrl:()Lorg/apache/dubbo/common/URL;
       6: aload_0
       7: aload_2
       8: aload_3
       9: invokespecial #31                 // Method getRealMethodName:(Lorg/apache/dubbo/rpc/Invoker;Lorg/apache/dubbo/rpc/Invocation;)Ljava/lang/String;
      12: aload_0
      13: aload_3
      14: invokespecial #32                 // Method getElapsed:(Lorg/apache/dubbo/rpc/Invocation;)J
      17: iconst_1
      18: invokestatic  #33                 // Method org/apache/dubbo/rpc/RpcStatus.endCount:(Lorg/apache/dubbo/common/URL;Ljava/lang/String;JZ)V
      21: return

  public void onError(java.lang.Throwable, org.apache.dubbo.rpc.Invoker<?>, org.apache.dubbo.rpc.Invocation);
    Code:
       0: aload_1
       1: instanceof    #9                  // class org/apache/dubbo/rpc/RpcException
       4: ifeq          22
       7: aload_1
       8: checkcast     #9                  // class org/apache/dubbo/rpc/RpcException
      11: astore        4
      13: aload         4
      15: invokevirtual #34                 // Method org/apache/dubbo/rpc/RpcException.isLimitExceed:()Z
      18: ifeq          22
      21: return
      22: aload_2
      23: invokeinterface #4,  1            // InterfaceMethod org/apache/dubbo/rpc/Invoker.getUrl:()Lorg/apache/dubbo/common/URL;
      28: aload_0
      29: aload_2
      30: aload_3
      31: invokespecial #31                 // Method getRealMethodName:(Lorg/apache/dubbo/rpc/Invoker;Lorg/apache/dubbo/rpc/Invocation;)Ljava/lang/String;
      34: aload_0
      35: aload_3
      36: invokespecial #32                 // Method getElapsed:(Lorg/apache/dubbo/rpc/Invocation;)J
      39: iconst_0
      40: invokestatic  #33                 // Method org/apache/dubbo/rpc/RpcStatus.endCount:(Lorg/apache/dubbo/common/URL;Ljava/lang/String;JZ)V
      43: return

  private java.lang.String getRealMethodName(org.apache.dubbo.rpc.Invoker<?>, org.apache.dubbo.rpc.Invocation);
    Code:
       0: aload_2
       1: invokeinterface #5,  1            // InterfaceMethod org/apache/dubbo/rpc/Invocation.getMethodName:()Ljava/lang/String;
       6: ldc           #35                 // String $invoke
       8: invokevirtual #36                 // Method java/lang/String.equals:(Ljava/lang/Object;)Z
      11: ifne          28
      14: aload_2
      15: invokeinterface #5,  1            // InterfaceMethod org/apache/dubbo/rpc/Invocation.getMethodName:()Ljava/lang/String;
      20: ldc           #37                 // String $invokeAsync
      22: invokevirtual #36                 // Method java/lang/String.equals:(Ljava/lang/Object;)Z
      25: ifeq          77
      28: aload_2
      29: invokeinterface #38,  1           // InterfaceMethod org/apache/dubbo/rpc/Invocation.getArguments:()[Ljava/lang/Object;
      34: ifnull        77
      37: aload_2
      38: invokeinterface #38,  1           // InterfaceMethod org/apache/dubbo/rpc/Invocation.getArguments:()[Ljava/lang/Object;
      43: arraylength
      44: iconst_3
      45: if_icmpne     77
      48: ldc           #39                 // class org/apache/dubbo/rpc/service/GenericService
      50: aload_1
      51: invokeinterface #40,  1           // InterfaceMethod org/apache/dubbo/rpc/Invoker.getInterface:()Ljava/lang/Class;
      56: invokevirtual #41                 // Method java/lang/Class.isAssignableFrom:(Ljava/lang/Class;)Z
      59: ifne          77
      62: aload_2
      63: invokeinterface #38,  1           // InterfaceMethod org/apache/dubbo/rpc/Invocation.getArguments:()[Ljava/lang/Object;
      68: iconst_0
      69: aaload
      70: checkcast     #42                 // class java/lang/String
      73: invokevirtual #43                 // Method java/lang/String.trim:()Ljava/lang/String;
      76: areturn
      77: aload_2
      78: invokeinterface #5,  1            // InterfaceMethod org/apache/dubbo/rpc/Invocation.getMethodName:()Ljava/lang/String;
      83: areturn

  private long getElapsed(org.apache.dubbo.rpc.Invocation);
    Code:
       0: aload_1
       1: ldc           #22                 // String execute_limit_filter_start_time
       3: invokeinterface #44,  2           // InterfaceMethod org/apache/dubbo/rpc/Invocation.get:(Ljava/lang/Object;)Ljava/lang/Object;
       8: astore_2
       9: aload_2
      10: ifnull        27
      13: invokestatic  #23                 // Method java/lang/System.currentTimeMillis:()J
      16: aload_2
      17: checkcast     #45                 // class java/lang/Long
      20: invokevirtual #46                 // Method java/lang/Long.longValue:()J
      23: lsub
      24: goto          28
      27: lconst_0
      28: lreturn
}
