Compiled from "GenericImplFilter.java"
public class org.apache.dubbo.rpc.filter.GenericImplFilter implements org.apache.dubbo.rpc.Filter,org.apache.dubbo.rpc.BaseFilter$Listener {
  private static final org.apache.dubbo.common.logger.ErrorTypeAwareLogger logger;

  private static final java.lang.Class<?>[] GENERIC_PARAMETER_TYPES;

  private static final java.lang.String GENERIC_IMPL_MARKER;

  private final org.apache.dubbo.rpc.model.ModuleModel moduleModel;

  public org.apache.dubbo.rpc.filter.GenericImplFilter(org.apache.dubbo.rpc.model.ModuleModel);
    Code:
       0: aload_0
       1: invokespecial #4                  // Method java/lang/Object."<init>":()V
       4: aload_0
       5: aload_1
       6: putfield      #5                  // Field moduleModel:Lorg/apache/dubbo/rpc/model/ModuleModel;
       9: return

  public org.apache.dubbo.rpc.Result invoke(org.apache.dubbo.rpc.Invoker<?>, org.apache.dubbo.rpc.Invocation) throws org.apache.dubbo.rpc.RpcException;
    Code:
       0: aload_1
       1: invokeinterface #6,  1            // InterfaceMethod org/apache/dubbo/rpc/Invoker.getUrl:()Lorg/apache/dubbo/common/URL;
       6: ldc           #7                  // String generic
       8: invokevirtual #8                  // Method org/apache/dubbo/common/URL.getParameter:(Ljava/lang/String;)Ljava/lang/String;
      11: astore_3
      12: aload_0
      13: aload_3
      14: aload_2
      15: invokespecial #9                  // Method isCallingGenericImpl:(Ljava/lang/String;Lorg/apache/dubbo/rpc/Invocation;)Z
      18: ifeq          232
      21: new           #10                 // class org/apache/dubbo/rpc/RpcInvocation
      24: dup
      25: aload_2
      26: invokespecial #11                 // Method org/apache/dubbo/rpc/RpcInvocation."<init>":(Lorg/apache/dubbo/rpc/Invocation;)V
      29: astore        4
      31: aload         4
      33: ldc           #13                 // String GENERIC_IMPL
      35: iconst_1
      36: invokestatic  #14                 // Method java/lang/Boolean.valueOf:(Z)Ljava/lang/Boolean;
      39: invokevirtual #15                 // Method org/apache/dubbo/rpc/RpcInvocation.put:(Ljava/lang/Object;Ljava/lang/Object;)Ljava/lang/Object;
      42: pop
      43: aload         4
      45: invokevirtual #16                 // Method org/apache/dubbo/rpc/RpcInvocation.getMethodName:()Ljava/lang/String;
      48: astore        5
      50: aload         4
      52: invokevirtual #17                 // Method org/apache/dubbo/rpc/RpcInvocation.getParameterTypes:()[Ljava/lang/Class;
      55: astore        6
      57: aload         4
      59: invokevirtual #18                 // Method org/apache/dubbo/rpc/RpcInvocation.getArguments:()[Ljava/lang/Object;
      62: astore        7
      64: aload         6
      66: arraylength
      67: anewarray     #19                 // class java/lang/String
      70: astore        8
      72: iconst_0
      73: istore        9
      75: iload         9
      77: aload         6
      79: arraylength
      80: if_icmpge     102
      83: aload         8
      85: iload         9
      87: aload         6
      89: iload         9
      91: aaload
      92: invokestatic  #20                 // Method org/apache/dubbo/common/utils/ReflectUtils.getName:(Ljava/lang/Class;)Ljava/lang/String;
      95: aastore
      96: iinc          9, 1
      99: goto          75
     102: aload_3
     103: invokestatic  #21                 // Method org/apache/dubbo/rpc/support/ProtocolUtils.isBeanGenericSerialization:(Ljava/lang/String;)Z
     106: ifeq          153
     109: aload         7
     111: arraylength
     112: anewarray     #22                 // class java/lang/Object
     115: astore        9
     117: iconst_0
     118: istore        10
     120: iload         10
     122: aload         7
     124: arraylength
     125: if_icmpge     150
     128: aload         9
     130: iload         10
     132: aload         7
     134: iload         10
     136: aaload
     137: getstatic     #23                 // Field org/apache/dubbo/common/beanutil/JavaBeanAccessor.METHOD:Lorg/apache/dubbo/common/beanutil/JavaBeanAccessor;
     140: invokestatic  #24                 // Method org/apache/dubbo/common/beanutil/JavaBeanSerializeUtil.serialize:(Ljava/lang/Object;Lorg/apache/dubbo/common/beanutil/JavaBeanAccessor;)Lorg/apache/dubbo/common/beanutil/JavaBeanDescriptor;
     143: aastore
     144: iinc          10, 1
     147: goto          120
     150: goto          160
     153: aload         7
     155: invokestatic  #25                 // Method org/apache/dubbo/common/utils/PojoUtils.generalize:([Ljava/lang/Object;)[Ljava/lang/Object;
     158: astore        9
     160: aload_2
     161: invokestatic  #26                 // Method org/apache/dubbo/rpc/support/RpcUtils.isReturnTypeFuture:(Lorg/apache/dubbo/rpc/Invocation;)Z
     164: ifeq          177
     167: aload         4
     169: ldc           #27                 // String $invokeAsync
     171: invokevirtual #28                 // Method org/apache/dubbo/rpc/RpcInvocation.setMethodName:(Ljava/lang/String;)V
     174: goto          184
     177: aload         4
     179: ldc           #29                 // String $invoke
     181: invokevirtual #28                 // Method org/apache/dubbo/rpc/RpcInvocation.setMethodName:(Ljava/lang/String;)V
     184: aload         4
     186: getstatic     #30                 // Field GENERIC_PARAMETER_TYPES:[Ljava/lang/Class;
     189: invokevirtual #31                 // Method org/apache/dubbo/rpc/RpcInvocation.setParameterTypes:([Ljava/lang/Class;)V
     192: aload         4
     194: ldc           #32                 // String Ljava/lang/String;[Ljava/lang/String;[Ljava/lang/Object;
     196: invokevirtual #33                 // Method org/apache/dubbo/rpc/RpcInvocation.setParameterTypesDesc:(Ljava/lang/String;)V
     199: aload         4
     201: iconst_3
     202: anewarray     #22                 // class java/lang/Object
     205: dup
     206: iconst_0
     207: aload         5
     209: aastore
     210: dup
     211: iconst_1
     212: aload         8
     214: aastore
     215: dup
     216: iconst_2
     217: aload         9
     219: aastore
     220: invokevirtual #34                 // Method org/apache/dubbo/rpc/RpcInvocation.setArguments:([Ljava/lang/Object;)V
     223: aload_1
     224: aload         4
     226: invokeinterface #35,  2           // InterfaceMethod org/apache/dubbo/rpc/Invoker.invoke:(Lorg/apache/dubbo/rpc/Invocation;)Lorg/apache/dubbo/rpc/Result;
     231: areturn
     232: aload_0
     233: aload_3
     234: aload_2
     235: invokespecial #36                 // Method isMakingGenericCall:(Ljava/lang/String;Lorg/apache/dubbo/rpc/Invocation;)Z
     238: ifeq          416
     241: aload_2
     242: invokeinterface #37,  1           // InterfaceMethod org/apache/dubbo/rpc/Invocation.getArguments:()[Ljava/lang/Object;
     247: iconst_2
     248: aaload
     249: checkcast     #38                 // class "[Ljava/lang/Object;"
     252: checkcast     #38                 // class "[Ljava/lang/Object;"
     255: astore        4
     257: aload_3
     258: invokestatic  #39                 // Method org/apache/dubbo/rpc/support/ProtocolUtils.isJavaGenericSerialization:(Ljava/lang/String;)Z
     261: ifeq          327
     264: aload         4
     266: astore        5
     268: aload         5
     270: arraylength
     271: istore        6
     273: iconst_0
     274: istore        7
     276: iload         7
     278: iload         6
     280: if_icmpge     324
     283: aload         5
     285: iload         7
     287: aaload
     288: astore        8
     290: ldc           #40                 // class "[B"
     292: aload         8
     294: invokevirtual #41                 // Method java/lang/Object.getClass:()Ljava/lang/Class;
     297: if_acmpeq     318
     300: aload_0
     301: aload_3
     302: ldc           #40                 // class "[B"
     304: invokevirtual #42                 // Method java/lang/Class.getName:()Ljava/lang/String;
     307: aload         8
     309: invokevirtual #41                 // Method java/lang/Object.getClass:()Ljava/lang/Class;
     312: invokevirtual #42                 // Method java/lang/Class.getName:()Ljava/lang/String;
     315: invokespecial #43                 // Method error:(Ljava/lang/String;Ljava/lang/String;Ljava/lang/String;)V
     318: iinc          7, 1
     321: goto          276
     324: goto          397
     327: aload_3
     328: invokestatic  #21                 // Method org/apache/dubbo/rpc/support/ProtocolUtils.isBeanGenericSerialization:(Ljava/lang/String;)Z
     331: ifeq          397
     334: aload         4
     336: astore        5
     338: aload         5
     340: arraylength
     341: istore        6
     343: iconst_0
     344: istore        7
     346: iload         7
     348: iload         6
     350: if_icmpge     397
     353: aload         5
     355: iload         7
     357: aaload
     358: astore        8
     360: aload         8
     362: ifnull        391
     365: aload         8
     367: instanceof    #44                 // class org/apache/dubbo/common/beanutil/JavaBeanDescriptor
     370: ifne          391
     373: aload_0
     374: aload_3
     375: ldc           #44                 // class org/apache/dubbo/common/beanutil/JavaBeanDescriptor
     377: invokevirtual #42                 // Method java/lang/Class.getName:()Ljava/lang/String;
     380: aload         8
     382: invokevirtual #41                 // Method java/lang/Object.getClass:()Ljava/lang/Class;
     385: invokevirtual #42                 // Method java/lang/Class.getName:()Ljava/lang/String;
     388: invokespecial #43                 // Method error:(Ljava/lang/String;Ljava/lang/String;Ljava/lang/String;)V
     391: iinc          7, 1
     394: goto          346
     397: aload_2
     398: ldc           #7                  // String generic
     400: aload_1
     401: invokeinterface #6,  1            // InterfaceMethod org/apache/dubbo/rpc/Invoker.getUrl:()Lorg/apache/dubbo/common/URL;
     406: ldc           #7                  // String generic
     408: invokevirtual #8                  // Method org/apache/dubbo/common/URL.getParameter:(Ljava/lang/String;)Ljava/lang/String;
     411: invokeinterface #45,  3           // InterfaceMethod org/apache/dubbo/rpc/Invocation.setAttachment:(Ljava/lang/String;Ljava/lang/String;)V
     416: aload_1
     417: aload_2
     418: invokeinterface #35,  2           // InterfaceMethod org/apache/dubbo/rpc/Invoker.invoke:(Lorg/apache/dubbo/rpc/Invocation;)Lorg/apache/dubbo/rpc/Result;
     423: areturn

  private void error(java.lang.String, java.lang.String, java.lang.String) throws org.apache.dubbo.rpc.RpcException;
    Code:
       0: new           #46                 // class org/apache/dubbo/rpc/RpcException
       3: dup
       4: new           #47                 // class java/lang/StringBuilder
       7: dup
       8: invokespecial #48                 // Method java/lang/StringBuilder."<init>":()V
      11: ldc           #49                 // String Generic serialization [
      13: invokevirtual #50                 // Method java/lang/StringBuilder.append:(Ljava/lang/String;)Ljava/lang/StringBuilder;
      16: aload_1
      17: invokevirtual #50                 // Method java/lang/StringBuilder.append:(Ljava/lang/String;)Ljava/lang/StringBuilder;
      20: ldc           #51                 // String ] only support message type
      22: invokevirtual #50                 // Method java/lang/StringBuilder.append:(Ljava/lang/String;)Ljava/lang/StringBuilder;
      25: aload_2
      26: invokevirtual #50                 // Method java/lang/StringBuilder.append:(Ljava/lang/String;)Ljava/lang/StringBuilder;
      29: ldc           #52                 // String  and your message type is
      31: invokevirtual #50                 // Method java/lang/StringBuilder.append:(Ljava/lang/String;)Ljava/lang/StringBuilder;
      34: aload_3
      35: invokevirtual #50                 // Method java/lang/StringBuilder.append:(Ljava/lang/String;)Ljava/lang/StringBuilder;
      38: invokevirtual #53                 // Method java/lang/StringBuilder.toString:()Ljava/lang/String;
      41: invokespecial #54                 // Method org/apache/dubbo/rpc/RpcException."<init>":(Ljava/lang/String;)V
      44: athrow

  public void onResponse(org.apache.dubbo.rpc.Result, org.apache.dubbo.rpc.Invoker<?>, org.apache.dubbo.rpc.Invocation);
    Code:
       0: aload_2
       1: invokeinterface #6,  1            // InterfaceMethod org/apache/dubbo/rpc/Invoker.getUrl:()Lorg/apache/dubbo/common/URL;
       6: ldc           #7                  // String generic
       8: invokevirtual #8                  // Method org/apache/dubbo/common/URL.getParameter:(Ljava/lang/String;)Ljava/lang/String;
      11: astore        4
      13: aload_3
      14: invokeinterface #55,  1           // InterfaceMethod org/apache/dubbo/rpc/Invocation.getMethodName:()Ljava/lang/String;
      19: astore        5
      21: aload_3
      22: invokeinterface #56,  1           // InterfaceMethod org/apache/dubbo/rpc/Invocation.getParameterTypes:()[Ljava/lang/Class;
      27: astore        6
      29: aload_3
      30: ldc           #13                 // String GENERIC_IMPL
      32: invokeinterface #57,  2           // InterfaceMethod org/apache/dubbo/rpc/Invocation.get:(Ljava/lang/Object;)Ljava/lang/Object;
      37: astore        7
      39: aload         7
      41: ifnull        613
      44: aload_3
      45: ldc           #13                 // String GENERIC_IMPL
      47: invokeinterface #57,  2           // InterfaceMethod org/apache/dubbo/rpc/Invocation.get:(Ljava/lang/Object;)Ljava/lang/Object;
      52: checkcast     #58                 // class java/lang/Boolean
      55: invokevirtual #59                 // Method java/lang/Boolean.booleanValue:()Z
      58: ifeq          613
      61: aload_1
      62: invokeinterface #60,  1           // InterfaceMethod org/apache/dubbo/rpc/Result.hasException:()Z
      67: ifne          310
      70: aload_1
      71: invokeinterface #61,  1           // InterfaceMethod org/apache/dubbo/rpc/Result.getValue:()Ljava/lang/Object;
      76: astore        8
      78: aload_2
      79: invokeinterface #62,  1           // InterfaceMethod org/apache/dubbo/rpc/Invoker.getInterface:()Ljava/lang/Class;
      84: astore        9
      86: ldc           #29                 // String $invoke
      88: aload         5
      90: invokevirtual #63                 // Method java/lang/String.equals:(Ljava/lang/Object;)Z
      93: ifne          141
      96: ldc           #27                 // String $invokeAsync
      98: aload         5
     100: invokevirtual #63                 // Method java/lang/String.equals:(Ljava/lang/Object;)Z
     103: ifne          141
     106: aload         9
     108: ldc           #64                 // class org/apache/dubbo/rpc/service/GenericService
     110: invokevirtual #65                 // Method java/lang/Class.isAssignableFrom:(Ljava/lang/Class;)Z
     113: ifeq          141
     116: aload_2
     117: invokeinterface #6,  1            // InterfaceMethod org/apache/dubbo/rpc/Invoker.getUrl:()Lorg/apache/dubbo/common/URL;
     122: ldc           #66                 // String interface
     124: invokevirtual #8                  // Method org/apache/dubbo/common/URL.getParameter:(Ljava/lang/String;)Ljava/lang/String;
     127: astore        10
     129: aload         10
     131: invokestatic  #67                 // Method org/apache/dubbo/common/utils/ReflectUtils.forName:(Ljava/lang/String;)Ljava/lang/Class;
     134: astore        9
     136: goto          141
     139: astore        10
     141: aload         9
     143: aload         5
     145: aload         6
     147: invokevirtual #69                 // Method java/lang/Class.getMethod:(Ljava/lang/String;[Ljava/lang/Class;)Ljava/lang/reflect/Method;
     150: astore        10
     152: aload         4
     154: invokestatic  #21                 // Method org/apache/dubbo/rpc/support/ProtocolUtils.isBeanGenericSerialization:(Ljava/lang/String;)Z
     157: ifeq          258
     160: aload         8
     162: ifnonnull     176
     165: aload_1
     166: aload         8
     168: invokeinterface #70,  2           // InterfaceMethod org/apache/dubbo/rpc/Result.setValue:(Ljava/lang/Object;)V
     173: goto          287
     176: aload         8
     178: instanceof    #44                 // class org/apache/dubbo/common/beanutil/JavaBeanDescriptor
     181: ifeq          201
     184: aload_1
     185: aload         8
     187: checkcast     #44                 // class org/apache/dubbo/common/beanutil/JavaBeanDescriptor
     190: invokestatic  #71                 // Method org/apache/dubbo/common/beanutil/JavaBeanSerializeUtil.deserialize:(Lorg/apache/dubbo/common/beanutil/JavaBeanDescriptor;)Ljava/lang/Object;
     193: invokeinterface #70,  2           // InterfaceMethod org/apache/dubbo/rpc/Result.setValue:(Ljava/lang/Object;)V
     198: goto          287
     201: new           #46                 // class org/apache/dubbo/rpc/RpcException
     204: dup
     205: new           #47                 // class java/lang/StringBuilder
     208: dup
     209: invokespecial #48                 // Method java/lang/StringBuilder."<init>":()V
     212: ldc           #72                 // String The type of result value is
     214: invokevirtual #50                 // Method java/lang/StringBuilder.append:(Ljava/lang/String;)Ljava/lang/StringBuilder;
     217: aload         8
     219: invokevirtual #41                 // Method java/lang/Object.getClass:()Ljava/lang/Class;
     222: invokevirtual #42                 // Method java/lang/Class.getName:()Ljava/lang/String;
     225: invokevirtual #50                 // Method java/lang/StringBuilder.append:(Ljava/lang/String;)Ljava/lang/StringBuilder;
     228: ldc           #73                 // String  other than
     230: invokevirtual #50                 // Method java/lang/StringBuilder.append:(Ljava/lang/String;)Ljava/lang/StringBuilder;
     233: ldc           #44                 // class org/apache/dubbo/common/beanutil/JavaBeanDescriptor
     235: invokevirtual #42                 // Method java/lang/Class.getName:()Ljava/lang/String;
     238: invokevirtual #50                 // Method java/lang/StringBuilder.append:(Ljava/lang/String;)Ljava/lang/StringBuilder;
     241: ldc           #74                 // String , and the result is
     243: invokevirtual #50                 // Method java/lang/StringBuilder.append:(Ljava/lang/String;)Ljava/lang/StringBuilder;
     246: aload         8
     248: invokevirtual #75                 // Method java/lang/StringBuilder.append:(Ljava/lang/Object;)Ljava/lang/StringBuilder;
     251: invokevirtual #53                 // Method java/lang/StringBuilder.toString:()Ljava/lang/String;
     254: invokespecial #54                 // Method org/apache/dubbo/rpc/RpcException."<init>":(Ljava/lang/String;)V
     257: athrow
     258: aload         10
     260: invokestatic  #76                 // Method org/apache/dubbo/common/utils/ReflectUtils.getReturnTypes:(Ljava/lang/reflect/Method;)[Ljava/lang/reflect/Type;
     263: astore        11
     265: aload_1
     266: aload         8
     268: aload         11
     270: iconst_0
     271: aaload
     272: checkcast     #77                 // class java/lang/Class
     275: aload         11
     277: iconst_1
     278: aaload
     279: invokestatic  #78                 // Method org/apache/dubbo/common/utils/PojoUtils.realize:(Ljava/lang/Object;Ljava/lang/Class;Ljava/lang/reflect/Type;)Ljava/lang/Object;
     282: invokeinterface #70,  2           // InterfaceMethod org/apache/dubbo/rpc/Result.setValue:(Ljava/lang/Object;)V
     287: goto          307
     290: astore        9
     292: new           #46                 // class org/apache/dubbo/rpc/RpcException
     295: dup
     296: aload         9
     298: invokevirtual #80                 // Method java/lang/NoSuchMethodException.getMessage:()Ljava/lang/String;
     301: aload         9
     303: invokespecial #81                 // Method org/apache/dubbo/rpc/RpcException."<init>":(Ljava/lang/String;Ljava/lang/Throwable;)V
     306: athrow
     307: goto          613
     310: aload_1
     311: invokeinterface #82,  1           // InterfaceMethod org/apache/dubbo/rpc/Result.getException:()Ljava/lang/Throwable;
     316: instanceof    #83                 // class com/alibaba/dubbo/rpc/service/GenericException
     319: ifeq          613
     322: aload_1
     323: invokeinterface #82,  1           // InterfaceMethod org/apache/dubbo/rpc/Result.getException:()Ljava/lang/Throwable;
     328: checkcast     #83                 // class com/alibaba/dubbo/rpc/service/GenericException
     331: astore        8
     333: aload         8
     335: invokevirtual #84                 // Method com/alibaba/dubbo/rpc/service/GenericException.getExceptionClass:()Ljava/lang/String;
     338: astore        9
     340: aload_0
     341: getfield      #5                  // Field moduleModel:Lorg/apache/dubbo/rpc/model/ModuleModel;
     344: invokevirtual #85                 // Method org/apache/dubbo/rpc/model/ModuleModel.getApplicationModel:()Lorg/apache/dubbo/rpc/model/ApplicationModel;
     347: invokevirtual #86                 // Method org/apache/dubbo/rpc/model/ApplicationModel.getFrameworkModel:()Lorg/apache/dubbo/rpc/model/FrameworkModel;
     350: invokevirtual #87                 // Method org/apache/dubbo/rpc/model/FrameworkModel.getBeanFactory:()Lorg/apache/dubbo/common/beans/factory/ScopeBeanFactory;
     353: ldc           #88                 // class org/apache/dubbo/common/utils/DefaultSerializeClassChecker
     355: invokevirtual #89                 // Method org/apache/dubbo/common/beans/factory/ScopeBeanFactory.getBean:(Ljava/lang/Class;)Ljava/lang/Object;
     358: checkcast     #88                 // class org/apache/dubbo/common/utils/DefaultSerializeClassChecker
     361: astore        10
     363: aload         10
     365: invokestatic  #90                 // Method java/lang/Thread.currentThread:()Ljava/lang/Thread;
     368: invokevirtual #91                 // Method java/lang/Thread.getContextClassLoader:()Ljava/lang/ClassLoader;
     371: aload         9
     373: invokevirtual #92                 // Method org/apache/dubbo/common/utils/DefaultSerializeClassChecker.loadClass:(Ljava/lang/ClassLoader;Ljava/lang/String;)Ljava/lang/Class;
     376: astore        11
     378: aconst_null
     379: astore        12
     381: aconst_null
     382: astore        13
     384: aload         11
     386: iconst_0
     387: anewarray     #77                 // class java/lang/Class
     390: invokevirtual #93                 // Method java/lang/Class.getDeclaredConstructor:([Ljava/lang/Class;)Ljava/lang/reflect/Constructor;
     393: iconst_0
     394: anewarray     #22                 // class java/lang/Object
     397: invokevirtual #94                 // Method java/lang/reflect/Constructor.newInstance:([Ljava/lang/Object;)Ljava/lang/Object;
     400: checkcast     #95                 // class java/lang/Throwable
     403: astore        12
     405: goto          477
     408: astore        14
     410: aload         14
     412: astore        13
     414: aload         11
     416: invokevirtual #96                 // Method java/lang/Class.getConstructors:()[Ljava/lang/reflect/Constructor;
     419: astore        15
     421: aload         15
     423: arraylength
     424: istore        16
     426: iconst_0
     427: istore        17
     429: iload         17
     431: iload         16
     433: if_icmpge     477
     436: aload         15
     438: iload         17
     440: aaload
     441: astore        18
     443: aload         18
     445: aload         18
     447: invokevirtual #97                 // Method java/lang/reflect/Constructor.getParameterTypes:()[Ljava/lang/Class;
     450: arraylength
     451: anewarray     #22                 // class java/lang/Object
     454: invokevirtual #94                 // Method java/lang/reflect/Constructor.newInstance:([Ljava/lang/Object;)Ljava/lang/Object;
     457: checkcast     #95                 // class java/lang/Throwable
     460: astore        12
     462: goto          477
     465: astore        19
     467: aload         19
     469: astore        13
     471: iinc          17, 1
     474: goto          429
     477: aload         12
     479: ifnull        554
     482: ldc           #95                 // class java/lang/Throwable
     484: ldc           #98                 // String detailMessage
     486: invokevirtual #99                 // Method java/lang/Class.getDeclaredField:(Ljava/lang/String;)Ljava/lang/reflect/Field;
     489: astore        14
     491: aload         14
     493: invokevirtual #100                // Method java/lang/reflect/Field.isAccessible:()Z
     496: ifne          505
     499: aload         14
     501: iconst_1
     502: invokevirtual #101                // Method java/lang/reflect/Field.setAccessible:(Z)V
     505: aload         14
     507: aload         12
     509: aload         8
     511: invokevirtual #102                // Method com/alibaba/dubbo/rpc/service/GenericException.getExceptionMessage:()Ljava/lang/String;
     514: invokevirtual #103                // Method java/lang/reflect/Field.set:(Ljava/lang/Object;Ljava/lang/Object;)V
     517: goto          543
     520: astore        14
     522: getstatic     #104                // Field logger:Lorg/apache/dubbo/common/logger/ErrorTypeAwareLogger;
     525: ldc           #105                // String 0-8
     527: ldc           #106                // String
     529: ldc           #106                // String
     531: aload         14
     533: invokevirtual #107                // Method java/lang/Throwable.getMessage:()Ljava/lang/String;
     536: aload         14
     538: invokeinterface #108,  6          // InterfaceMethod org/apache/dubbo/common/logger/ErrorTypeAwareLogger.warn:(Ljava/lang/String;Ljava/lang/String;Ljava/lang/String;Ljava/lang/String;Ljava/lang/Throwable;)V
     543: aload_1
     544: aload         12
     546: invokeinterface #109,  2          // InterfaceMethod org/apache/dubbo/rpc/Result.setException:(Ljava/lang/Throwable;)V
     551: goto          562
     554: aload         13
     556: ifnull        562
     559: aload         13
     561: athrow
     562: goto          613
     565: astore        9
     567: new           #46                 // class org/apache/dubbo/rpc/RpcException
     570: dup
     571: new           #47                 // class java/lang/StringBuilder
     574: dup
     575: invokespecial #48                 // Method java/lang/StringBuilder."<init>":()V
     578: ldc           #110                // String Can not deserialize exception
     580: invokevirtual #50                 // Method java/lang/StringBuilder.append:(Ljava/lang/String;)Ljava/lang/StringBuilder;
     583: aload         8
     585: invokevirtual #84                 // Method com/alibaba/dubbo/rpc/service/GenericException.getExceptionClass:()Ljava/lang/String;
     588: invokevirtual #50                 // Method java/lang/StringBuilder.append:(Ljava/lang/String;)Ljava/lang/StringBuilder;
     591: ldc           #111                // String , message:
     593: invokevirtual #50                 // Method java/lang/StringBuilder.append:(Ljava/lang/String;)Ljava/lang/StringBuilder;
     596: aload         8
     598: invokevirtual #102                // Method com/alibaba/dubbo/rpc/service/GenericException.getExceptionMessage:()Ljava/lang/String;
     601: invokevirtual #50                 // Method java/lang/StringBuilder.append:(Ljava/lang/String;)Ljava/lang/StringBuilder;
     604: invokevirtual #53                 // Method java/lang/StringBuilder.toString:()Ljava/lang/String;
     607: aload         9
     609: invokespecial #81                 // Method org/apache/dubbo/rpc/RpcException."<init>":(Ljava/lang/String;Ljava/lang/Throwable;)V
     612: athrow
     613: return
    Exception table:
       from    to  target type
         116   136   139   Class java/lang/Exception
          78   287   290   Class java/lang/NoSuchMethodException
         384   405   408   Class java/lang/Throwable
         443   462   465   Class java/lang/Throwable
         482   517   520   Class java/lang/Throwable
         333   562   565   Class java/lang/Throwable

  public void onError(java.lang.Throwable, org.apache.dubbo.rpc.Invoker<?>, org.apache.dubbo.rpc.Invocation);
    Code:
       0: return

  private boolean isCallingGenericImpl(java.lang.String, org.apache.dubbo.rpc.Invocation);
    Code:
       0: aload_1
       1: invokestatic  #112                // Method org/apache/dubbo/rpc/support/ProtocolUtils.isGeneric:(Ljava/lang/String;)Z
       4: ifeq          46
       7: ldc           #29                 // String $invoke
       9: aload_2
      10: invokeinterface #55,  1           // InterfaceMethod org/apache/dubbo/rpc/Invocation.getMethodName:()Ljava/lang/String;
      15: invokevirtual #63                 // Method java/lang/String.equals:(Ljava/lang/Object;)Z
      18: ifne          46
      21: ldc           #27                 // String $invokeAsync
      23: aload_2
      24: invokeinterface #55,  1           // InterfaceMethod org/apache/dubbo/rpc/Invocation.getMethodName:()Ljava/lang/String;
      29: invokevirtual #63                 // Method java/lang/String.equals:(Ljava/lang/Object;)Z
      32: ifne          46
      35: aload_2
      36: instanceof    #10                 // class org/apache/dubbo/rpc/RpcInvocation
      39: ifeq          46
      42: iconst_1
      43: goto          47
      46: iconst_0
      47: ireturn

  private boolean isMakingGenericCall(java.lang.String, org.apache.dubbo.rpc.Invocation);
    Code:
       0: aload_2
       1: invokeinterface #55,  1           // InterfaceMethod org/apache/dubbo/rpc/Invocation.getMethodName:()Ljava/lang/String;
       6: ldc           #29                 // String $invoke
       8: invokevirtual #63                 // Method java/lang/String.equals:(Ljava/lang/Object;)Z
      11: ifne          28
      14: aload_2
      15: invokeinterface #55,  1           // InterfaceMethod org/apache/dubbo/rpc/Invocation.getMethodName:()Ljava/lang/String;
      20: ldc           #27                 // String $invokeAsync
      22: invokevirtual #63                 // Method java/lang/String.equals:(Ljava/lang/Object;)Z
      25: ifeq          59
      28: aload_2
      29: invokeinterface #37,  1           // InterfaceMethod org/apache/dubbo/rpc/Invocation.getArguments:()[Ljava/lang/Object;
      34: ifnull        59
      37: aload_2
      38: invokeinterface #37,  1           // InterfaceMethod org/apache/dubbo/rpc/Invocation.getArguments:()[Ljava/lang/Object;
      43: arraylength
      44: iconst_3
      45: if_icmpne     59
      48: aload_1
      49: invokestatic  #112                // Method org/apache/dubbo/rpc/support/ProtocolUtils.isGeneric:(Ljava/lang/String;)Z
      52: ifeq          59
      55: iconst_1
      56: goto          60
      59: iconst_0
      60: ireturn

  static {};
    Code:
       0: ldc           #12                 // class org/apache/dubbo/rpc/filter/GenericImplFilter
       2: invokestatic  #113                // Method org/apache/dubbo/common/logger/LoggerFactory.getErrorTypeAwareLogger:(Ljava/lang/Class;)Lorg/apache/dubbo/common/logger/ErrorTypeAwareLogger;
       5: putstatic     #104                // Field logger:Lorg/apache/dubbo/common/logger/ErrorTypeAwareLogger;
       8: iconst_3
       9: anewarray     #77                 // class java/lang/Class
      12: dup
      13: iconst_0
      14: ldc           #19                 // class java/lang/String
      16: aastore
      17: dup
      18: iconst_1
      19: ldc           #114                // class "[Ljava/lang/String;"
      21: aastore
      22: dup
      23: iconst_2
      24: ldc           #38                 // class "[Ljava/lang/Object;"
      26: aastore
      27: putstatic     #30                 // Field GENERIC_PARAMETER_TYPES:[Ljava/lang/Class;
      30: return
}
