Compiled from "ProfilerServerFilter.java"
public class org.apache.dubbo.rpc.filter.ProfilerServerFilter implements org.apache.dubbo.rpc.Filter,org.apache.dubbo.rpc.BaseFilter$Listener {
  private static final java.lang.String CLIENT_IP_KEY;

  private static final org.apache.dubbo.common.logger.ErrorTypeAwareLogger logger;

  public org.apache.dubbo.rpc.filter.ProfilerServerFilter();
    Code:
       0: aload_0
       1: invokespecial #3                  // Method java/lang/Object."<init>":()V
       4: return

  public org.apache.dubbo.rpc.Result invoke(org.apache.dubbo.rpc.Invoker<?>, org.apache.dubbo.rpc.Invocation) throws org.apache.dubbo.rpc.RpcException;
    Code:
       0: invokestatic  #4                  // Method org/apache/dubbo/common/profiler/ProfilerSwitch.isEnableSimpleProfiler:()Z
       3: ifeq          69
       6: aload_2
       7: ldc           #6                  // String DUBBO_INVOKE_PROFILER
       9: invokeinterface #7,  2            // InterfaceMethod org/apache/dubbo/rpc/Invocation.get:(Ljava/lang/Object;)Ljava/lang/Object;
      14: astore        4
      16: aload         4
      18: instanceof    #8                  // class org/apache/dubbo/common/profiler/ProfilerEntry
      21: ifeq          38
      24: aload         4
      26: checkcast     #8                  // class org/apache/dubbo/common/profiler/ProfilerEntry
      29: ldc           #9                  // String Receive request. Local server invoke begin.
      31: invokestatic  #10                 // Method org/apache/dubbo/common/profiler/Profiler.enter:(Lorg/apache/dubbo/common/profiler/ProfilerEntry;Ljava/lang/String;)Lorg/apache/dubbo/common/profiler/ProfilerEntry;
      34: astore_3
      35: goto          44
      38: ldc           #11                 // String Receive request. Server invoke begin.
      40: invokestatic  #12                 // Method org/apache/dubbo/common/profiler/Profiler.start:(Ljava/lang/String;)Lorg/apache/dubbo/common/profiler/ProfilerEntry;
      43: astore_3
      44: aload_2
      45: ldc           #6                  // String DUBBO_INVOKE_PROFILER
      47: aload_3
      48: invokeinterface #13,  3           // InterfaceMethod org/apache/dubbo/rpc/Invocation.put:(Ljava/lang/Object;Ljava/lang/Object;)Ljava/lang/Object;
      53: pop
      54: aload_2
      55: ldc           #15                 // String client_ip
      57: invokestatic  #16                 // Method org/apache/dubbo/rpc/RpcContext.getServiceContext:()Lorg/apache/dubbo/rpc/RpcServiceContext;
      60: invokevirtual #17                 // Method org/apache/dubbo/rpc/RpcServiceContext.getRemoteAddressString:()Ljava/lang/String;
      63: invokeinterface #13,  3           // InterfaceMethod org/apache/dubbo/rpc/Invocation.put:(Ljava/lang/Object;Ljava/lang/Object;)Ljava/lang/Object;
      68: pop
      69: aload_1
      70: aload_2
      71: invokeinterface #18,  2           // InterfaceMethod org/apache/dubbo/rpc/Invoker.invoke:(Lorg/apache/dubbo/rpc/Invocation;)Lorg/apache/dubbo/rpc/Result;
      76: areturn

  public void onResponse(org.apache.dubbo.rpc.Result, org.apache.dubbo.rpc.Invoker<?>, org.apache.dubbo.rpc.Invocation);
    Code:
       0: aload_0
       1: aload_2
       2: aload_3
       3: invokespecial #19                 // Method afterInvoke:(Lorg/apache/dubbo/rpc/Invoker;Lorg/apache/dubbo/rpc/Invocation;)V
       6: aload_0
       7: aload_1
       8: aload_3
       9: invokespecial #20                 // Method addAdaptiveResponse:(Lorg/apache/dubbo/rpc/Result;Lorg/apache/dubbo/rpc/Invocation;)V
      12: return

  public void onError(java.lang.Throwable, org.apache.dubbo.rpc.Invoker<?>, org.apache.dubbo.rpc.Invocation);
    Code:
       0: aload_0
       1: aload_2
       2: aload_3
       3: invokespecial #19                 // Method afterInvoke:(Lorg/apache/dubbo/rpc/Invoker;Lorg/apache/dubbo/rpc/Invocation;)V
       6: return

  private void afterInvoke(org.apache.dubbo.rpc.Invoker<?>, org.apache.dubbo.rpc.Invocation);
    Code:
       0: invokestatic  #4                  // Method org/apache/dubbo/common/profiler/ProfilerSwitch.isEnableSimpleProfiler:()Z
       3: ifeq          52
       6: aload_2
       7: ldc           #6                  // String DUBBO_INVOKE_PROFILER
       9: invokeinterface #7,  2            // InterfaceMethod org/apache/dubbo/rpc/Invocation.get:(Ljava/lang/Object;)Ljava/lang/Object;
      14: astore_3
      15: aload_3
      16: instanceof    #8                  // class org/apache/dubbo/common/profiler/ProfilerEntry
      19: ifeq          52
      22: aload_3
      23: checkcast     #8                  // class org/apache/dubbo/common/profiler/ProfilerEntry
      26: invokestatic  #21                 // Method org/apache/dubbo/common/profiler/Profiler.release:(Lorg/apache/dubbo/common/profiler/ProfilerEntry;)Lorg/apache/dubbo/common/profiler/ProfilerEntry;
      29: astore        4
      31: aload_2
      32: ldc           #6                  // String DUBBO_INVOKE_PROFILER
      34: aload         4
      36: invokeinterface #13,  3           // InterfaceMethod org/apache/dubbo/rpc/Invocation.put:(Ljava/lang/Object;Ljava/lang/Object;)Ljava/lang/Object;
      41: pop
      42: aload_0
      43: aload_1
      44: aload_2
      45: aload_3
      46: checkcast     #8                  // class org/apache/dubbo/common/profiler/ProfilerEntry
      49: invokespecial #22                 // Method dumpIfNeed:(Lorg/apache/dubbo/rpc/Invoker;Lorg/apache/dubbo/rpc/Invocation;Lorg/apache/dubbo/common/profiler/ProfilerEntry;)V
      52: return

  private void addAdaptiveResponse(org.apache.dubbo.rpc.Result, org.apache.dubbo.rpc.Invocation);
    Code:
       0: aload_2
       1: ldc           #24                 // String lb_adaptive
       3: invokeinterface #25,  2           // InterfaceMethod org/apache/dubbo/rpc/Invocation.getAttachment:(Ljava/lang/String;)Ljava/lang/String;
       8: astore_3
       9: aload_3
      10: invokestatic  #26                 // Method org/apache/dubbo/common/utils/StringUtils.isNotEmpty:(Ljava/lang/String;)Z
      13: ifeq          95
      16: invokestatic  #27                 // Method java/lang/management/ManagementFactory.getOperatingSystemMXBean:()Ljava/lang/management/OperatingSystemMXBean;
      19: astore        4
      21: new           #28                 // class java/lang/StringBuilder
      24: dup
      25: bipush        64
      27: invokespecial #29                 // Method java/lang/StringBuilder."<init>":(I)V
      30: astore        5
      32: aload         5
      34: ldc           #30                 // String curTime:
      36: invokevirtual #31                 // Method java/lang/StringBuilder.append:(Ljava/lang/String;)Ljava/lang/StringBuilder;
      39: invokestatic  #32                 // Method java/lang/System.currentTimeMillis:()J
      42: invokevirtual #33                 // Method java/lang/StringBuilder.append:(J)Ljava/lang/StringBuilder;
      45: pop
      46: aload         5
      48: ldc           #34                 // String ,
      50: invokevirtual #31                 // Method java/lang/StringBuilder.append:(Ljava/lang/String;)Ljava/lang/StringBuilder;
      53: ldc           #35                 // String load:
      55: invokevirtual #31                 // Method java/lang/StringBuilder.append:(Ljava/lang/String;)Ljava/lang/StringBuilder;
      58: aload         4
      60: invokeinterface #36,  1           // InterfaceMethod java/lang/management/OperatingSystemMXBean.getSystemLoadAverage:()D
      65: ldc2_w        #37                 // double 100.0d
      68: dmul
      69: aload         4
      71: invokeinterface #39,  1           // InterfaceMethod java/lang/management/OperatingSystemMXBean.getAvailableProcessors:()I
      76: i2d
      77: ddiv
      78: invokevirtual #40                 // Method java/lang/StringBuilder.append:(D)Ljava/lang/StringBuilder;
      81: pop
      82: aload_1
      83: ldc           #24                 // String lb_adaptive
      85: aload         5
      87: invokevirtual #41                 // Method java/lang/StringBuilder.toString:()Ljava/lang/String;
      90: invokeinterface #42,  3           // InterfaceMethod org/apache/dubbo/rpc/Result.setAttachment:(Ljava/lang/String;Ljava/lang/String;)V
      95: return

  private void dumpIfNeed(org.apache.dubbo.rpc.Invoker<?>, org.apache.dubbo.rpc.Invocation, org.apache.dubbo.common.profiler.ProfilerEntry);
    Code:
       0: aload_2
       1: ldc           #43                 // String timeout
       3: invokeinterface #44,  2           // InterfaceMethod org/apache/dubbo/rpc/Invocation.getObjectAttachmentWithoutConvert:(Ljava/lang/String;)Ljava/lang/Object;
       8: invokestatic  #45                 // Method org/apache/dubbo/rpc/support/RpcUtils.convertToNumber:(Ljava/lang/Object;)Ljava/lang/Long;
      11: astore        4
      13: aload         4
      15: ifnonnull     44
      18: aload_1
      19: invokeinterface #46,  1           // InterfaceMethod org/apache/dubbo/rpc/Invoker.getUrl:()Lorg/apache/dubbo/common/URL;
      24: aload_2
      25: invokeinterface #47,  1           // InterfaceMethod org/apache/dubbo/rpc/Invocation.getMethodName:()Ljava/lang/String;
      30: ldc           #43                 // String timeout
      32: sipush        1000
      35: invokevirtual #48                 // Method org/apache/dubbo/common/URL.getMethodPositiveParameter:(Ljava/lang/String;Ljava/lang/String;I)I
      38: i2l
      39: invokestatic  #49                 // Method java/lang/Long.valueOf:(J)Ljava/lang/Long;
      42: astore        4
      44: aload_3
      45: invokevirtual #50                 // Method org/apache/dubbo/common/profiler/ProfilerEntry.getEndTime:()J
      48: aload_3
      49: invokevirtual #51                 // Method org/apache/dubbo/common/profiler/ProfilerEntry.getStartTime:()J
      52: lsub
      53: lstore        5
      55: lload         5
      57: l2d
      58: ldc2_w        #52                 // double 1000000.0d
      61: invokestatic  #54                 // Method org/apache/dubbo/common/profiler/ProfilerSwitch.getWarnPercent:()D
      64: dmul
      65: ddiv
      66: aload         4
      68: invokevirtual #55                 // Method java/lang/Long.longValue:()J
      71: l2d
      72: dcmpl
      73: ifle          206
      76: aload         4
      78: invokevirtual #55                 // Method java/lang/Long.longValue:()J
      81: ldc2_w        #56                 // long -1l
      84: lcmp
      85: ifeq          206
      88: new           #28                 // class java/lang/StringBuilder
      91: dup
      92: invokespecial #58                 // Method java/lang/StringBuilder."<init>":()V
      95: astore        7
      97: aload_2
      98: aload         7
     100: invokedynamic #59,  0             // InvokeDynamic #0:accept:(Ljava/lang/StringBuilder;)Ljava/util/function/Consumer;
     105: invokeinterface #60,  2           // InterfaceMethod org/apache/dubbo/rpc/Invocation.foreachAttachment:(Ljava/util/function/Consumer;)V
     110: getstatic     #61                 // Field logger:Lorg/apache/dubbo/common/logger/ErrorTypeAwareLogger;
     113: ldc           #62                 // String 3-7
     115: ldc           #63                 // String
     117: ldc           #63                 // String
     119: ldc           #64                 // String [Dubbo-Provider] execute service %s#%s cost %d.%06d ms, this invocation almost (maybe already) timeout. Timeout: %dms\nclient: %s\ninvocation context:\n%sthread info: \n%s
     121: bipush        8
     123: anewarray     #65                 // class java/lang/Object
     126: dup
     127: iconst_0
     128: aload_2
     129: invokeinterface #66,  1           // InterfaceMethod org/apache/dubbo/rpc/Invocation.getTargetServiceUniqueName:()Ljava/lang/String;
     134: aastore
     135: dup
     136: iconst_1
     137: aload_2
     138: invokeinterface #47,  1           // InterfaceMethod org/apache/dubbo/rpc/Invocation.getMethodName:()Ljava/lang/String;
     143: aastore
     144: dup
     145: iconst_2
     146: lload         5
     148: ldc2_w        #67                 // long 1000000l
     151: ldiv
     152: invokestatic  #49                 // Method java/lang/Long.valueOf:(J)Ljava/lang/Long;
     155: aastore
     156: dup
     157: iconst_3
     158: lload         5
     160: ldc2_w        #67                 // long 1000000l
     163: lrem
     164: invokestatic  #49                 // Method java/lang/Long.valueOf:(J)Ljava/lang/Long;
     167: aastore
     168: dup
     169: iconst_4
     170: aload         4
     172: aastore
     173: dup
     174: iconst_5
     175: aload_2
     176: ldc           #15                 // String client_ip
     178: invokeinterface #7,  2            // InterfaceMethod org/apache/dubbo/rpc/Invocation.get:(Ljava/lang/Object;)Ljava/lang/Object;
     183: aastore
     184: dup
     185: bipush        6
     187: aload         7
     189: aastore
     190: dup
     191: bipush        7
     193: aload_3
     194: invokestatic  #69                 // Method org/apache/dubbo/common/profiler/Profiler.buildDetail:(Lorg/apache/dubbo/common/profiler/ProfilerEntry;)Ljava/lang/String;
     197: aastore
     198: invokestatic  #70                 // Method java/lang/String.format:(Ljava/lang/String;[Ljava/lang/Object;)Ljava/lang/String;
     201: invokeinterface #71,  5           // InterfaceMethod org/apache/dubbo/common/logger/ErrorTypeAwareLogger.warn:(Ljava/lang/String;Ljava/lang/String;Ljava/lang/String;Ljava/lang/String;)V
     206: return

  private static void lambda$dumpIfNeed$0(java.lang.StringBuilder, java.util.Map$Entry);
    Code:
       0: aload_0
       1: aload_1
       2: invokeinterface #72,  1           // InterfaceMethod java/util/Map$Entry.getKey:()Ljava/lang/Object;
       7: checkcast     #73                 // class java/lang/String
      10: invokevirtual #31                 // Method java/lang/StringBuilder.append:(Ljava/lang/String;)Ljava/lang/StringBuilder;
      13: ldc           #74                 // String =
      15: invokevirtual #31                 // Method java/lang/StringBuilder.append:(Ljava/lang/String;)Ljava/lang/StringBuilder;
      18: aload_1
      19: invokeinterface #75,  1           // InterfaceMethod java/util/Map$Entry.getValue:()Ljava/lang/Object;
      24: invokevirtual #76                 // Method java/lang/StringBuilder.append:(Ljava/lang/Object;)Ljava/lang/StringBuilder;
      27: ldc           #77                 // String ;\n
      29: invokevirtual #31                 // Method java/lang/StringBuilder.append:(Ljava/lang/String;)Ljava/lang/StringBuilder;
      32: pop
      33: return

  static {};
    Code:
       0: ldc           #14                 // class org/apache/dubbo/rpc/filter/ProfilerServerFilter
       2: invokestatic  #78                 // Method org/apache/dubbo/common/logger/LoggerFactory.getErrorTypeAwareLogger:(Ljava/lang/Class;)Lorg/apache/dubbo/common/logger/ErrorTypeAwareLogger;
       5: putstatic     #61                 // Field logger:Lorg/apache/dubbo/common/logger/ErrorTypeAwareLogger;
       8: return
}
