Compiled from "TimeoutFilter.java"
public class org.apache.dubbo.rpc.filter.TimeoutFilter implements org.apache.dubbo.rpc.Filter,org.apache.dubbo.rpc.BaseFilter$Listener {
  private static final org.apache.dubbo.common.logger.ErrorTypeAwareLogger logger;

  public org.apache.dubbo.rpc.filter.TimeoutFilter();
    Code:
       0: aload_0
       1: invokespecial #3                  // Method java/lang/Object."<init>":()V
       4: return

  public org.apache.dubbo.rpc.Result invoke(org.apache.dubbo.rpc.Invoker<?>, org.apache.dubbo.rpc.Invocation) throws org.apache.dubbo.rpc.RpcException;
    Code:
       0: aload_1
       1: aload_2
       2: invokeinterface #4,  2            // InterfaceMethod org/apache/dubbo/rpc/Invoker.invoke:(Lorg/apache/dubbo/rpc/Invocation;)Lorg/apache/dubbo/rpc/Result;
       7: areturn

  public void onResponse(org.apache.dubbo.rpc.Result, org.apache.dubbo.rpc.Invoker<?>, org.apache.dubbo.rpc.Invocation);
    Code:
       0: invokestatic  #5                  // Method org/apache/dubbo/rpc/RpcContext.getServerAttachment:()Lorg/apache/dubbo/rpc/RpcContextAttachment;
       3: ldc           #6                  // String timeout-countdown
       5: invokevirtual #7                  // Method org/apache/dubbo/rpc/RpcContextAttachment.getObjectAttachment:(Ljava/lang/String;)Ljava/lang/Object;
       8: astore        4
      10: aload         4
      12: ifnull        111
      15: aload         4
      17: checkcast     #8                  // class org/apache/dubbo/rpc/TimeoutCountDown
      20: astore        5
      22: aload         5
      24: invokevirtual #9                  // Method org/apache/dubbo/rpc/TimeoutCountDown.isExpired:()Z
      27: ifeq          111
      30: getstatic     #10                 // Field logger:Lorg/apache/dubbo/common/logger/ErrorTypeAwareLogger;
      33: invokeinterface #11,  1           // InterfaceMethod org/apache/dubbo/common/logger/ErrorTypeAwareLogger.isWarnEnabled:()Z
      38: ifeq          111
      41: getstatic     #10                 // Field logger:Lorg/apache/dubbo/common/logger/ErrorTypeAwareLogger;
      44: ldc           #12                 // String 3-4
      46: ldc           #13                 // String
      48: ldc           #13                 // String
      50: new           #14                 // class java/lang/StringBuilder
      53: dup
      54: invokespecial #15                 // Method java/lang/StringBuilder."<init>":()V
      57: ldc           #16                 // String invoke timed out. method:
      59: invokevirtual #17                 // Method java/lang/StringBuilder.append:(Ljava/lang/String;)Ljava/lang/StringBuilder;
      62: aload_3
      63: invokeinterface #18,  1           // InterfaceMethod org/apache/dubbo/rpc/Invocation.getMethodName:()Ljava/lang/String;
      68: invokevirtual #17                 // Method java/lang/StringBuilder.append:(Ljava/lang/String;)Ljava/lang/StringBuilder;
      71: ldc           #19                 // String  url is
      73: invokevirtual #17                 // Method java/lang/StringBuilder.append:(Ljava/lang/String;)Ljava/lang/StringBuilder;
      76: aload_2
      77: invokeinterface #20,  1           // InterfaceMethod org/apache/dubbo/rpc/Invoker.getUrl:()Lorg/apache/dubbo/common/URL;
      82: invokevirtual #21                 // Method java/lang/StringBuilder.append:(Ljava/lang/Object;)Ljava/lang/StringBuilder;
      85: ldc           #22                 // String , invoke elapsed
      87: invokevirtual #17                 // Method java/lang/StringBuilder.append:(Ljava/lang/String;)Ljava/lang/StringBuilder;
      90: aload         5
      92: invokevirtual #23                 // Method org/apache/dubbo/rpc/TimeoutCountDown.elapsedMillis:()J
      95: invokevirtual #24                 // Method java/lang/StringBuilder.append:(J)Ljava/lang/StringBuilder;
      98: ldc           #25                 // String  ms.
     100: invokevirtual #17                 // Method java/lang/StringBuilder.append:(Ljava/lang/String;)Ljava/lang/StringBuilder;
     103: invokevirtual #26                 // Method java/lang/StringBuilder.toString:()Ljava/lang/String;
     106: invokeinterface #27,  5           // InterfaceMethod org/apache/dubbo/common/logger/ErrorTypeAwareLogger.warn:(Ljava/lang/String;Ljava/lang/String;Ljava/lang/String;Ljava/lang/String;)V
     111: return

  public void onError(java.lang.Throwable, org.apache.dubbo.rpc.Invoker<?>, org.apache.dubbo.rpc.Invocation);
    Code:
       0: return

  static {};
    Code:
       0: ldc           #28                 // class org/apache/dubbo/rpc/filter/TimeoutFilter
       2: invokestatic  #29                 // Method org/apache/dubbo/common/logger/LoggerFactory.getErrorTypeAwareLogger:(Ljava/lang/Class;)Lorg/apache/dubbo/common/logger/ErrorTypeAwareLogger;
       5: putstatic     #10                 // Field logger:Lorg/apache/dubbo/common/logger/ErrorTypeAwareLogger;
       8: return
}
