Compiled from "TokenFilter.java"
public class org.apache.dubbo.rpc.filter.TokenFilter implements org.apache.dubbo.rpc.Filter {
  public org.apache.dubbo.rpc.filter.TokenFilter();
    Code:
       0: aload_0
       1: invokespecial #2                  // Method java/lang/Object."<init>":()V
       4: return

  public org.apache.dubbo.rpc.Result invoke(org.apache.dubbo.rpc.Invoker<?>, org.apache.dubbo.rpc.Invocation) throws org.apache.dubbo.rpc.RpcException;
    Code:
       0: aload_1
       1: invokeinterface #3,  1            // InterfaceMethod org/apache/dubbo/rpc/Invoker.getUrl:()Lorg/apache/dubbo/common/URL;
       6: ldc           #4                  // String token
       8: invokevirtual #5                  // Method org/apache/dubbo/common/URL.getParameter:(Ljava/lang/String;)Ljava/lang/String;
      11: astore_3
      12: aload_3
      13: invokestatic  #6                  // Method org/apache/dubbo/common/utils/ConfigUtils.isNotEmpty:(Ljava/lang/String;)Z
      16: ifeq          129
      19: aload_1
      20: invokeinterface #7,  1            // InterfaceMethod org/apache/dubbo/rpc/Invoker.getInterface:()Ljava/lang/Class;
      25: astore        4
      27: aload_2
      28: ldc           #4                  // String token
      30: invokeinterface #8,  2            // InterfaceMethod org/apache/dubbo/rpc/Invocation.getObjectAttachmentWithoutConvert:(Ljava/lang/String;)Ljava/lang/Object;
      35: checkcast     #9                  // class java/lang/String
      38: astore        5
      40: aload_3
      41: aload         5
      43: invokevirtual #10                 // Method java/lang/String.equals:(Ljava/lang/Object;)Z
      46: ifne          129
      49: new           #11                 // class org/apache/dubbo/rpc/RpcException
      52: dup
      53: new           #12                 // class java/lang/StringBuilder
      56: dup
      57: invokespecial #13                 // Method java/lang/StringBuilder."<init>":()V
      60: ldc           #14                 // String Invalid token! Forbid invoke remote service
      62: invokevirtual #15                 // Method java/lang/StringBuilder.append:(Ljava/lang/String;)Ljava/lang/StringBuilder;
      65: aload         4
      67: invokevirtual #16                 // Method java/lang/StringBuilder.append:(Ljava/lang/Object;)Ljava/lang/StringBuilder;
      70: ldc           #17                 // String  method
      72: invokevirtual #15                 // Method java/lang/StringBuilder.append:(Ljava/lang/String;)Ljava/lang/StringBuilder;
      75: aload_2
      76: invokeinterface #18,  1           // InterfaceMethod org/apache/dubbo/rpc/Invocation.getMethodName:()Ljava/lang/String;
      81: invokevirtual #15                 // Method java/lang/StringBuilder.append:(Ljava/lang/String;)Ljava/lang/StringBuilder;
      84: ldc           #19                 // String () from consumer
      86: invokevirtual #15                 // Method java/lang/StringBuilder.append:(Ljava/lang/String;)Ljava/lang/StringBuilder;
      89: invokestatic  #20                 // Method org/apache/dubbo/rpc/RpcContext.getServiceContext:()Lorg/apache/dubbo/rpc/RpcServiceContext;
      92: invokevirtual #21                 // Method org/apache/dubbo/rpc/RpcServiceContext.getRemoteHost:()Ljava/lang/String;
      95: invokevirtual #15                 // Method java/lang/StringBuilder.append:(Ljava/lang/String;)Ljava/lang/StringBuilder;
      98: ldc           #22                 // String  to provider
     100: invokevirtual #15                 // Method java/lang/StringBuilder.append:(Ljava/lang/String;)Ljava/lang/StringBuilder;
     103: invokestatic  #20                 // Method org/apache/dubbo/rpc/RpcContext.getServiceContext:()Lorg/apache/dubbo/rpc/RpcServiceContext;
     106: invokevirtual #23                 // Method org/apache/dubbo/rpc/RpcServiceContext.getLocalHost:()Ljava/lang/String;
     109: invokevirtual #15                 // Method java/lang/StringBuilder.append:(Ljava/lang/String;)Ljava/lang/StringBuilder;
     112: ldc           #24                 // String , consumer incorrect token is
     114: invokevirtual #15                 // Method java/lang/StringBuilder.append:(Ljava/lang/String;)Ljava/lang/StringBuilder;
     117: aload         5
     119: invokevirtual #15                 // Method java/lang/StringBuilder.append:(Ljava/lang/String;)Ljava/lang/StringBuilder;
     122: invokevirtual #25                 // Method java/lang/StringBuilder.toString:()Ljava/lang/String;
     125: invokespecial #26                 // Method org/apache/dubbo/rpc/RpcException."<init>":(Ljava/lang/String;)V
     128: athrow
     129: aload_1
     130: aload_2
     131: invokeinterface #27,  2           // InterfaceMethod org/apache/dubbo/rpc/Invoker.invoke:(Lorg/apache/dubbo/rpc/Invocation;)Lorg/apache/dubbo/rpc/Result;
     136: areturn
}
