Compiled from "TpsLimitFilter.java"
public class org.apache.dubbo.rpc.filter.TpsLimitFilter implements org.apache.dubbo.rpc.Filter {
  private final org.apache.dubbo.rpc.filter.tps.TPSLimiter tpsLimiter;

  public org.apache.dubbo.rpc.filter.TpsLimitFilter();
    Code:
       0: aload_0
       1: invokespecial #1                  // Method java/lang/Object."<init>":()V
       4: aload_0
       5: new           #2                  // class org/apache/dubbo/rpc/filter/tps/DefaultTPSLimiter
       8: dup
       9: invokespecial #3                  // Method org/apache/dubbo/rpc/filter/tps/DefaultTPSLimiter."<init>":()V
      12: putfield      #4                  // Field tpsLimiter:Lorg/apache/dubbo/rpc/filter/tps/TPSLimiter;
      15: return

  public org.apache.dubbo.rpc.Result invoke(org.apache.dubbo.rpc.Invoker<?>, org.apache.dubbo.rpc.Invocation) throws org.apache.dubbo.rpc.RpcException;
    Code:
       0: aload_0
       1: getfield      #4                  // Field tpsLimiter:Lorg/apache/dubbo/rpc/filter/tps/TPSLimiter;
       4: aload_1
       5: invokeinterface #5,  1            // InterfaceMethod org/apache/dubbo/rpc/Invoker.getUrl:()Lorg/apache/dubbo/common/URL;
      10: aload_2
      11: invokeinterface #6,  3            // InterfaceMethod org/apache/dubbo/rpc/filter/tps/TPSLimiter.isAllowable:(Lorg/apache/dubbo/common/URL;Lorg/apache/dubbo/rpc/Invocation;)Z
      16: ifne          73
      19: new           #7                  // class org/apache/dubbo/rpc/RpcException
      22: dup
      23: new           #8                  // class java/lang/StringBuilder
      26: dup
      27: invokespecial #9                  // Method java/lang/StringBuilder."<init>":()V
      30: ldc           #10                 // String Failed to invoke service
      32: invokevirtual #11                 // Method java/lang/StringBuilder.append:(Ljava/lang/String;)Ljava/lang/StringBuilder;
      35: aload_1
      36: invokeinterface #12,  1           // InterfaceMethod org/apache/dubbo/rpc/Invoker.getInterface:()Ljava/lang/Class;
      41: invokevirtual #13                 // Method java/lang/Class.getName:()Ljava/lang/String;
      44: invokevirtual #11                 // Method java/lang/StringBuilder.append:(Ljava/lang/String;)Ljava/lang/StringBuilder;
      47: ldc           #14                 // String .
      49: invokevirtual #11                 // Method java/lang/StringBuilder.append:(Ljava/lang/String;)Ljava/lang/StringBuilder;
      52: aload_2
      53: invokeinterface #15,  1           // InterfaceMethod org/apache/dubbo/rpc/Invocation.getMethodName:()Ljava/lang/String;
      58: invokevirtual #11                 // Method java/lang/StringBuilder.append:(Ljava/lang/String;)Ljava/lang/StringBuilder;
      61: ldc           #16                 // String  because exceed max service tps.
      63: invokevirtual #11                 // Method java/lang/StringBuilder.append:(Ljava/lang/String;)Ljava/lang/StringBuilder;
      66: invokevirtual #17                 // Method java/lang/StringBuilder.toString:()Ljava/lang/String;
      69: invokespecial #18                 // Method org/apache/dubbo/rpc/RpcException."<init>":(Ljava/lang/String;)V
      72: athrow
      73: aload_1
      74: aload_2
      75: invokeinterface #19,  2           // InterfaceMethod org/apache/dubbo/rpc/Invoker.invoke:(Lorg/apache/dubbo/rpc/Invocation;)Lorg/apache/dubbo/rpc/Result;
      80: areturn
}
