Compiled from "CloudPlatform.java"
public abstract class org.springframework.boot.cloud.CloudPlatform extends java.lang.Enum<org.springframework.boot.cloud.CloudPlatform> {
  public static final org.springframework.boot.cloud.CloudPlatform NONE;

  public static final org.springframework.boot.cloud.CloudPlatform CLOUD_FOUNDRY;

  public static final org.springframework.boot.cloud.CloudPlatform HEROKU;

  public static final org.springframework.boot.cloud.CloudPlatform SAP;

  public static final org.springframework.boot.cloud.CloudPlatform NOMAD;

  public static final org.springframework.boot.cloud.CloudPlatform KUBERNETES;

  public static final org.springframework.boot.cloud.CloudPlatform AZURE_APP_SERVICE;

  private static final java.lang.String PROPERTY_NAME;

  private static final org.springframework.boot.cloud.CloudPlatform[] $VALUES;

  public static org.springframework.boot.cloud.CloudPlatform[] values();
    Code:
       0: getstatic     #25                 // Field $VALUES:[Lorg/springframework/boot/cloud/CloudPlatform;
       3: invokevirtual #29                 // Method "[Lorg/springframework/boot/cloud/CloudPlatform;".clone:()Ljava/lang/Object;
       6: checkcast     #30                 // class "[Lorg/springframework/boot/cloud/CloudPlatform;"
       9: areturn

  public static org.springframework.boot.cloud.CloudPlatform valueOf(java.lang.String);
    Code:
       0: ldc           #1                  // class org/springframework/boot/cloud/CloudPlatform
       2: aload_0
       3: invokestatic  #34                 // Method java/lang/Enum.valueOf:(Ljava/lang/Class;Ljava/lang/String;)Ljava/lang/Enum;
       6: checkcast     #1                  // class org/springframework/boot/cloud/CloudPlatform
       9: areturn

  private org.springframework.boot.cloud.CloudPlatform();
    Code:
       0: aload_0
       1: aload_1
       2: iload_2
       3: invokespecial #40                 // Method java/lang/Enum."<init>":(Ljava/lang/String;I)V
       6: return

  public boolean isActive(org.springframework.core.env.Environment);
    Code:
       0: aload_1
       1: ldc           #44                 // String spring.main.cloud-platform
       3: invokeinterface #46,  2           // InterfaceMethod org/springframework/core/env/Environment.getProperty:(Ljava/lang/String;)Ljava/lang/String;
       8: astore_2
       9: aload_0
      10: aload_2
      11: invokevirtual #52                 // Method isEnforced:(Ljava/lang/String;)Z
      14: ifne          29
      17: aload_2
      18: ifnonnull     33
      21: aload_0
      22: aload_1
      23: invokevirtual #56                 // Method isDetected:(Lorg/springframework/core/env/Environment;)Z
      26: ifeq          33
      29: iconst_1
      30: goto          34
      33: iconst_0
      34: ireturn

  public boolean isEnforced(org.springframework.core.env.Environment);
    Code:
       0: aload_0
       1: aload_1
       2: ldc           #44                 // String spring.main.cloud-platform
       4: invokeinterface #46,  2           // InterfaceMethod org/springframework/core/env/Environment.getProperty:(Ljava/lang/String;)Ljava/lang/String;
       9: invokevirtual #52                 // Method isEnforced:(Ljava/lang/String;)Z
      12: ireturn

  public boolean isEnforced(org.springframework.boot.context.properties.bind.Binder);
    Code:
       0: aload_0
       1: aload_1
       2: ldc           #44                 // String spring.main.cloud-platform
       4: ldc           #60                 // class java/lang/String
       6: invokevirtual #62                 // Method org/springframework/boot/context/properties/bind/Binder.bind:(Ljava/lang/String;Ljava/lang/Class;)Lorg/springframework/boot/context/properties/bind/BindResult;
       9: aconst_null
      10: invokevirtual #68                 // Method org/springframework/boot/context/properties/bind/BindResult.orElse:(Ljava/lang/Object;)Ljava/lang/Object;
      13: checkcast     #60                 // class java/lang/String
      16: invokevirtual #52                 // Method isEnforced:(Ljava/lang/String;)Z
      19: ireturn

  private boolean isEnforced(java.lang.String);
    Code:
       0: aload_0
       1: invokevirtual #74                 // Method name:()Ljava/lang/String;
       4: aload_1
       5: invokevirtual #78                 // Method java/lang/String.equalsIgnoreCase:(Ljava/lang/String;)Z
       8: ireturn

  public abstract boolean isDetected(org.springframework.core.env.Environment);

  public boolean isUsingForwardHeaders();
    Code:
       0: iconst_1
       1: ireturn

  public static org.springframework.boot.cloud.CloudPlatform getActive(org.springframework.core.env.Environment);
    Code:
       0: aload_0
       1: ifnull        41
       4: invokestatic  #81                 // Method values:()[Lorg/springframework/boot/cloud/CloudPlatform;
       7: astore_1
       8: aload_1
       9: arraylength
      10: istore_2
      11: iconst_0
      12: istore_3
      13: iload_3
      14: iload_2
      15: if_icmpge     41
      18: aload_1
      19: iload_3
      20: aaload
      21: astore        4
      23: aload         4
      25: aload_0
      26: invokevirtual #85                 // Method isActive:(Lorg/springframework/core/env/Environment;)Z
      29: ifeq          35
      32: aload         4
      34: areturn
      35: iinc          3, 1
      38: goto          13
      41: aconst_null
      42: areturn

  private static org.springframework.boot.cloud.CloudPlatform[] $values();
    Code:
       0: bipush        7
       2: anewarray     #1                  // class org/springframework/boot/cloud/CloudPlatform
       5: dup
       6: iconst_0
       7: getstatic     #3                  // Field NONE:Lorg/springframework/boot/cloud/CloudPlatform;
      10: aastore
      11: dup
      12: iconst_1
      13: getstatic     #7                  // Field CLOUD_FOUNDRY:Lorg/springframework/boot/cloud/CloudPlatform;
      16: aastore
      17: dup
      18: iconst_2
      19: getstatic     #10                 // Field HEROKU:Lorg/springframework/boot/cloud/CloudPlatform;
      22: aastore
      23: dup
      24: iconst_3
      25: getstatic     #13                 // Field SAP:Lorg/springframework/boot/cloud/CloudPlatform;
      28: aastore
      29: dup
      30: iconst_4
      31: getstatic     #16                 // Field NOMAD:Lorg/springframework/boot/cloud/CloudPlatform;
      34: aastore
      35: dup
      36: iconst_5
      37: getstatic     #19                 // Field KUBERNETES:Lorg/springframework/boot/cloud/CloudPlatform;
      40: aastore
      41: dup
      42: bipush        6
      44: getstatic     #22                 // Field AZURE_APP_SERVICE:Lorg/springframework/boot/cloud/CloudPlatform;
      47: aastore
      48: areturn

  static {};
    Code:
       0: new           #88                 // class org/springframework/boot/cloud/CloudPlatform$1
       3: dup
       4: ldc           #90                 // String NONE
       6: iconst_0
       7: invokespecial #91                 // Method org/springframework/boot/cloud/CloudPlatform$1."<init>":(Ljava/lang/String;I)V
      10: putstatic     #3                  // Field NONE:Lorg/springframework/boot/cloud/CloudPlatform;
      13: new           #92                 // class org/springframework/boot/cloud/CloudPlatform$2
      16: dup
      17: ldc           #94                 // String CLOUD_FOUNDRY
      19: iconst_1
      20: invokespecial #95                 // Method org/springframework/boot/cloud/CloudPlatform$2."<init>":(Ljava/lang/String;I)V
      23: putstatic     #7                  // Field CLOUD_FOUNDRY:Lorg/springframework/boot/cloud/CloudPlatform;
      26: new           #96                 // class org/springframework/boot/cloud/CloudPlatform$3
      29: dup
      30: ldc           #98                 // String HEROKU
      32: iconst_2
      33: invokespecial #99                 // Method org/springframework/boot/cloud/CloudPlatform$3."<init>":(Ljava/lang/String;I)V
      36: putstatic     #10                 // Field HEROKU:Lorg/springframework/boot/cloud/CloudPlatform;
      39: new           #100                // class org/springframework/boot/cloud/CloudPlatform$4
      42: dup
      43: ldc           #102                // String SAP
      45: iconst_3
      46: invokespecial #103                // Method org/springframework/boot/cloud/CloudPlatform$4."<init>":(Ljava/lang/String;I)V
      49: putstatic     #13                 // Field SAP:Lorg/springframework/boot/cloud/CloudPlatform;
      52: new           #104                // class org/springframework/boot/cloud/CloudPlatform$5
      55: dup
      56: ldc           #106                // String NOMAD
      58: iconst_4
      59: invokespecial #107                // Method org/springframework/boot/cloud/CloudPlatform$5."<init>":(Ljava/lang/String;I)V
      62: putstatic     #16                 // Field NOMAD:Lorg/springframework/boot/cloud/CloudPlatform;
      65: new           #108                // class org/springframework/boot/cloud/CloudPlatform$6
      68: dup
      69: ldc           #110                // String KUBERNETES
      71: iconst_5
      72: invokespecial #111                // Method org/springframework/boot/cloud/CloudPlatform$6."<init>":(Ljava/lang/String;I)V
      75: putstatic     #19                 // Field KUBERNETES:Lorg/springframework/boot/cloud/CloudPlatform;
      78: new           #112                // class org/springframework/boot/cloud/CloudPlatform$7
      81: dup
      82: ldc           #114                // String AZURE_APP_SERVICE
      84: bipush        6
      86: invokespecial #115                // Method org/springframework/boot/cloud/CloudPlatform$7."<init>":(Ljava/lang/String;I)V
      89: putstatic     #22                 // Field AZURE_APP_SERVICE:Lorg/springframework/boot/cloud/CloudPlatform;
      92: invokestatic  #116                // Method $values:()[Lorg/springframework/boot/cloud/CloudPlatform;
      95: putstatic     #25                 // Field $VALUES:[Lorg/springframework/boot/cloud/CloudPlatform;
      98: return
}
