Compiled from "CloudPlatform.java"
final class org.springframework.boot.cloud.CloudPlatform$7 extends org.springframework.boot.cloud.CloudPlatform {
  private final java.util.List<java.lang.String> azureEnvVariables;

  private org.springframework.boot.cloud.CloudPlatform$7(java.lang.String, int);
    Code:
       0: aload_0
       1: aload_1
       2: iload_2
       3: invokespecial #1                  // Method org/springframework/boot/cloud/CloudPlatform."<init>":(Ljava/lang/String;I)V
       6: aload_0
       7: iconst_4
       8: anewarray     #7                  // class java/lang/String
      11: dup
      12: iconst_0
      13: ldc           #9                  // String WEBSITE_SITE_NAME
      15: aastore
      16: dup
      17: iconst_1
      18: ldc           #11                 // String WEBSITE_INSTANCE_ID
      20: aastore
      21: dup
      22: iconst_2
      23: ldc           #13                 // String WEBSITE_RESOURCE_GROUP
      25: aastore
      26: dup
      27: iconst_3
      28: ldc           #15                 // String WEBSITE_SKU
      30: aastore
      31: invokestatic  #17                 // Method java/util/Arrays.asList:([Ljava/lang/Object;)Ljava/util/List;
      34: putfield      #23                 // Field azureEnvVariables:Ljava/util/List;
      37: return

  public boolean isDetected(org.springframework.core.env.Environment);
    Code:
       0: aload_0
       1: getfield      #23                 // Field azureEnvVariables:Ljava/util/List;
       4: invokeinterface #29,  1           // InterfaceMethod java/util/List.stream:()Ljava/util/stream/Stream;
       9: aload_1
      10: dup
      11: invokestatic  #35                 // Method java/util/Objects.requireNonNull:(Ljava/lang/Object;)Ljava/lang/Object;
      14: pop
      15: invokedynamic #41,  0             // InvokeDynamic #0:test:(Lorg/springframework/core/env/Environment;)Ljava/util/function/Predicate;
      20: invokeinterface #45,  2           // InterfaceMethod java/util/stream/Stream.allMatch:(Ljava/util/function/Predicate;)Z
      25: ireturn
}
