Compiled from "RpcAuthenticationException.java"
public class org.apache.dubbo.auth.exception.RpcAuthenticationException extends java.lang.Exception {
  public org.apache.dubbo.auth.exception.RpcAuthenticationException();
    Code:
       0: aload_0
       1: invokespecial #1                  // Method java/lang/Exception."<init>":()V
       4: return

  public org.apache.dubbo.auth.exception.RpcAuthenticationException(java.lang.String);
    Code:
       0: aload_0
       1: aload_1
       2: invokespecial #2                  // Method java/lang/Exception."<init>":(Ljava/lang/String;)V
       5: return

  public org.apache.dubbo.auth.exception.RpcAuthenticationException(java.lang.String, java.lang.Throwable);
    Code:
       0: aload_0
       1: aload_1
       2: aload_2
       3: invokespecial #3                  // Method java/lang/Exception."<init>":(Ljava/lang/String;Ljava/lang/Throwable;)V
       6: return
}
