Compiled from "AbstractDirectTask.java"
abstract class io.reactivex.rxjava3.internal.schedulers.AbstractDirectTask extends java.util.concurrent.atomic.AtomicReference<java.util.concurrent.Future<?>> implements io.reactivex.rxjava3.disposables.Disposable, io.reactivex.rxjava3.schedulers.SchedulerRunnableIntrospection {
  private static final long serialVersionUID;

  protected final java.lang.Runnable runnable;

  protected final boolean interruptOnCancel;

  protected java.lang.Thread runner;

  protected static final java.util.concurrent.FutureTask<java.lang.Void> FINISHED;

  protected static final java.util.concurrent.FutureTask<java.lang.Void> DISPOSED;

  io.reactivex.rxjava3.internal.schedulers.AbstractDirectTask(java.lang.Runnable, boolean);
    Code:
       0: aload_0
       1: invokespecial #1                  // Method java/util/concurrent/atomic/AtomicReference."<init>":()V
       4: aload_0
       5: aload_1
       6: putfield      #2                  // Field runnable:Ljava/lang/Runnable;
       9: aload_0
      10: iload_2
      11: putfield      #3                  // Field interruptOnCancel:Z
      14: return

  public final void dispose();
    Code:
       0: aload_0
       1: invokevirtual #4                  // Method get:()Ljava/lang/Object;
       4: checkcast     #5                  // class java/util/concurrent/Future
       7: astore_1
       8: aload_1
       9: getstatic     #6                  // Field FINISHED:Ljava/util/concurrent/FutureTask;
      12: if_acmpeq     42
      15: aload_1
      16: getstatic     #7                  // Field DISPOSED:Ljava/util/concurrent/FutureTask;
      19: if_acmpeq     42
      22: aload_0
      23: aload_1
      24: getstatic     #7                  // Field DISPOSED:Ljava/util/concurrent/FutureTask;
      27: invokevirtual #8                  // Method compareAndSet:(Ljava/lang/Object;Ljava/lang/Object;)Z
      30: ifeq          42
      33: aload_1
      34: ifnull        42
      37: aload_0
      38: aload_1
      39: invokespecial #9                  // Method cancelFuture:(Ljava/util/concurrent/Future;)V
      42: return

  public final boolean isDisposed();
    Code:
       0: aload_0
       1: invokevirtual #4                  // Method get:()Ljava/lang/Object;
       4: checkcast     #5                  // class java/util/concurrent/Future
       7: astore_1
       8: aload_1
       9: getstatic     #6                  // Field FINISHED:Ljava/util/concurrent/FutureTask;
      12: if_acmpeq     22
      15: aload_1
      16: getstatic     #7                  // Field DISPOSED:Ljava/util/concurrent/FutureTask;
      19: if_acmpne     26
      22: iconst_1
      23: goto          27
      26: iconst_0
      27: ireturn

  public final void setFuture(java.util.concurrent.Future<?>);
    Code:
       0: aload_0
       1: invokevirtual #4                  // Method get:()Ljava/lang/Object;
       4: checkcast     #5                  // class java/util/concurrent/Future
       7: astore_2
       8: aload_2
       9: getstatic     #6                  // Field FINISHED:Ljava/util/concurrent/FutureTask;
      12: if_acmpne     18
      15: goto          48
      18: aload_2
      19: getstatic     #7                  // Field DISPOSED:Ljava/util/concurrent/FutureTask;
      22: if_acmpne     33
      25: aload_0
      26: aload_1
      27: invokespecial #9                  // Method cancelFuture:(Ljava/util/concurrent/Future;)V
      30: goto          48
      33: aload_0
      34: aload_2
      35: aload_1
      36: invokevirtual #8                  // Method compareAndSet:(Ljava/lang/Object;Ljava/lang/Object;)Z
      39: ifeq          45
      42: goto          48
      45: goto          0
      48: return

  private void cancelFuture(java.util.concurrent.Future<?>);
    Code:
       0: aload_0
       1: getfield      #10                 // Field runner:Ljava/lang/Thread;
       4: invokestatic  #11                 // Method java/lang/Thread.currentThread:()Ljava/lang/Thread;
       7: if_acmpne     21
      10: aload_1
      11: iconst_0
      12: invokeinterface #12,  2           // InterfaceMethod java/util/concurrent/Future.cancel:(Z)Z
      17: pop
      18: goto          32
      21: aload_1
      22: aload_0
      23: getfield      #3                  // Field interruptOnCancel:Z
      26: invokeinterface #12,  2           // InterfaceMethod java/util/concurrent/Future.cancel:(Z)Z
      31: pop
      32: return

  public java.lang.Runnable getWrappedRunnable();
    Code:
       0: aload_0
       1: getfield      #2                  // Field runnable:Ljava/lang/Runnable;
       4: areturn

  public java.lang.String toString();
    Code:
       0: aload_0
       1: invokevirtual #4                  // Method get:()Ljava/lang/Object;
       4: checkcast     #5                  // class java/util/concurrent/Future
       7: astore_2
       8: aload_2
       9: getstatic     #6                  // Field FINISHED:Ljava/util/concurrent/FutureTask;
      12: if_acmpne     21
      15: ldc           #13                 // String Finished
      17: astore_1
      18: goto          72
      21: aload_2
      22: getstatic     #7                  // Field DISPOSED:Ljava/util/concurrent/FutureTask;
      25: if_acmpne     34
      28: ldc           #14                 // String Disposed
      30: astore_1
      31: goto          72
      34: aload_0
      35: getfield      #10                 // Field runner:Ljava/lang/Thread;
      38: astore_3
      39: aload_3
      40: ifnull        69
      43: new           #15                 // class java/lang/StringBuilder
      46: dup
      47: invokespecial #16                 // Method java/lang/StringBuilder."<init>":()V
      50: ldc           #17                 // String Running on
      52: invokevirtual #18                 // Method java/lang/StringBuilder.append:(Ljava/lang/String;)Ljava/lang/StringBuilder;
      55: aload_0
      56: getfield      #10                 // Field runner:Ljava/lang/Thread;
      59: invokevirtual #19                 // Method java/lang/StringBuilder.append:(Ljava/lang/Object;)Ljava/lang/StringBuilder;
      62: invokevirtual #20                 // Method java/lang/StringBuilder.toString:()Ljava/lang/String;
      65: astore_1
      66: goto          72
      69: ldc           #21                 // String Waiting
      71: astore_1
      72: new           #15                 // class java/lang/StringBuilder
      75: dup
      76: invokespecial #16                 // Method java/lang/StringBuilder."<init>":()V
      79: aload_0
      80: invokevirtual #22                 // Method java/lang/Object.getClass:()Ljava/lang/Class;
      83: invokevirtual #23                 // Method java/lang/Class.getSimpleName:()Ljava/lang/String;
      86: invokevirtual #18                 // Method java/lang/StringBuilder.append:(Ljava/lang/String;)Ljava/lang/StringBuilder;
      89: ldc           #24                 // String [
      91: invokevirtual #18                 // Method java/lang/StringBuilder.append:(Ljava/lang/String;)Ljava/lang/StringBuilder;
      94: aload_1
      95: invokevirtual #18                 // Method java/lang/StringBuilder.append:(Ljava/lang/String;)Ljava/lang/StringBuilder;
      98: ldc           #25                 // String ]
     100: invokevirtual #18                 // Method java/lang/StringBuilder.append:(Ljava/lang/String;)Ljava/lang/StringBuilder;
     103: invokevirtual #20                 // Method java/lang/StringBuilder.toString:()Ljava/lang/String;
     106: areturn

  static {};
    Code:
       0: new           #26                 // class java/util/concurrent/FutureTask
       3: dup
       4: getstatic     #27                 // Field io/reactivex/rxjava3/internal/functions/Functions.EMPTY_RUNNABLE:Ljava/lang/Runnable;
       7: aconst_null
       8: invokespecial #28                 // Method java/util/concurrent/FutureTask."<init>":(Ljava/lang/Runnable;Ljava/lang/Object;)V
      11: putstatic     #6                  // Field FINISHED:Ljava/util/concurrent/FutureTask;
      14: new           #26                 // class java/util/concurrent/FutureTask
      17: dup
      18: getstatic     #27                 // Field io/reactivex/rxjava3/internal/functions/Functions.EMPTY_RUNNABLE:Ljava/lang/Runnable;
      21: aconst_null
      22: invokespecial #28                 // Method java/util/concurrent/FutureTask."<init>":(Ljava/lang/Runnable;Ljava/lang/Object;)V
      25: putstatic     #7                  // Field DISPOSED:Ljava/util/concurrent/FutureTask;
      28: return
}
