Compiled from "ComputationScheduler.java"
final class io.reactivex.rxjava3.internal.schedulers.ComputationScheduler$EventLoopWorker extends io.reactivex.rxjava3.core.Scheduler$Worker {
  private final io.reactivex.rxjava3.internal.disposables.ListCompositeDisposable serial;

  private final io.reactivex.rxjava3.disposables.CompositeDisposable timed;

  private final io.reactivex.rxjava3.internal.disposables.ListCompositeDisposable both;

  private final io.reactivex.rxjava3.internal.schedulers.ComputationScheduler$PoolWorker poolWorker;

  volatile boolean disposed;

  io.reactivex.rxjava3.internal.schedulers.ComputationScheduler$EventLoopWorker(io.reactivex.rxjava3.internal.schedulers.ComputationScheduler$PoolWorker);
    Code:
       0: aload_0
       1: invokespecial #1                  // Method io/reactivex/rxjava3/core/Scheduler$Worker."<init>":()V
       4: aload_0
       5: aload_1
       6: putfield      #2                  // Field poolWorker:Lio/reactivex/rxjava3/internal/schedulers/ComputationScheduler$PoolWorker;
       9: aload_0
      10: new           #3                  // class io/reactivex/rxjava3/internal/disposables/ListCompositeDisposable
      13: dup
      14: invokespecial #4                  // Method io/reactivex/rxjava3/internal/disposables/ListCompositeDisposable."<init>":()V
      17: putfield      #5                  // Field serial:Lio/reactivex/rxjava3/internal/disposables/ListCompositeDisposable;
      20: aload_0
      21: new           #6                  // class io/reactivex/rxjava3/disposables/CompositeDisposable
      24: dup
      25: invokespecial #7                  // Method io/reactivex/rxjava3/disposables/CompositeDisposable."<init>":()V
      28: putfield      #8                  // Field timed:Lio/reactivex/rxjava3/disposables/CompositeDisposable;
      31: aload_0
      32: new           #3                  // class io/reactivex/rxjava3/internal/disposables/ListCompositeDisposable
      35: dup
      36: invokespecial #4                  // Method io/reactivex/rxjava3/internal/disposables/ListCompositeDisposable."<init>":()V
      39: putfield      #9                  // Field both:Lio/reactivex/rxjava3/internal/disposables/ListCompositeDisposable;
      42: aload_0
      43: getfield      #9                  // Field both:Lio/reactivex/rxjava3/internal/disposables/ListCompositeDisposable;
      46: aload_0
      47: getfield      #5                  // Field serial:Lio/reactivex/rxjava3/internal/disposables/ListCompositeDisposable;
      50: invokevirtual #10                 // Method io/reactivex/rxjava3/internal/disposables/ListCompositeDisposable.add:(Lio/reactivex/rxjava3/disposables/Disposable;)Z
      53: pop
      54: aload_0
      55: getfield      #9                  // Field both:Lio/reactivex/rxjava3/internal/disposables/ListCompositeDisposable;
      58: aload_0
      59: getfield      #8                  // Field timed:Lio/reactivex/rxjava3/disposables/CompositeDisposable;
      62: invokevirtual #10                 // Method io/reactivex/rxjava3/internal/disposables/ListCompositeDisposable.add:(Lio/reactivex/rxjava3/disposables/Disposable;)Z
      65: pop
      66: return

  public void dispose();
    Code:
       0: aload_0
       1: getfield      #11                 // Field disposed:Z
       4: ifne          19
       7: aload_0
       8: iconst_1
       9: putfield      #11                 // Field disposed:Z
      12: aload_0
      13: getfield      #9                  // Field both:Lio/reactivex/rxjava3/internal/disposables/ListCompositeDisposable;
      16: invokevirtual #12                 // Method io/reactivex/rxjava3/internal/disposables/ListCompositeDisposable.dispose:()V
      19: return

  public boolean isDisposed();
    Code:
       0: aload_0
       1: getfield      #11                 // Field disposed:Z
       4: ireturn

  public io.reactivex.rxjava3.disposables.Disposable schedule(java.lang.Runnable);
    Code:
       0: aload_0
       1: getfield      #11                 // Field disposed:Z
       4: ifeq          11
       7: getstatic     #13                 // Field io/reactivex/rxjava3/internal/disposables/EmptyDisposable.INSTANCE:Lio/reactivex/rxjava3/internal/disposables/EmptyDisposable;
      10: areturn
      11: aload_0
      12: getfield      #2                  // Field poolWorker:Lio/reactivex/rxjava3/internal/schedulers/ComputationScheduler$PoolWorker;
      15: aload_1
      16: lconst_0
      17: getstatic     #14                 // Field java/util/concurrent/TimeUnit.MILLISECONDS:Ljava/util/concurrent/TimeUnit;
      20: aload_0
      21: getfield      #5                  // Field serial:Lio/reactivex/rxjava3/internal/disposables/ListCompositeDisposable;
      24: invokevirtual #15                 // Method io/reactivex/rxjava3/internal/schedulers/ComputationScheduler$PoolWorker.scheduleActual:(Ljava/lang/Runnable;JLjava/util/concurrent/TimeUnit;Lio/reactivex/rxjava3/disposables/DisposableContainer;)Lio/reactivex/rxjava3/internal/schedulers/ScheduledRunnable;
      27: areturn

  public io.reactivex.rxjava3.disposables.Disposable schedule(java.lang.Runnable, long, java.util.concurrent.TimeUnit);
    Code:
       0: aload_0
       1: getfield      #11                 // Field disposed:Z
       4: ifeq          11
       7: getstatic     #13                 // Field io/reactivex/rxjava3/internal/disposables/EmptyDisposable.INSTANCE:Lio/reactivex/rxjava3/internal/disposables/EmptyDisposable;
      10: areturn
      11: aload_0
      12: getfield      #2                  // Field poolWorker:Lio/reactivex/rxjava3/internal/schedulers/ComputationScheduler$PoolWorker;
      15: aload_1
      16: lload_2
      17: aload         4
      19: aload_0
      20: getfield      #8                  // Field timed:Lio/reactivex/rxjava3/disposables/CompositeDisposable;
      23: invokevirtual #15                 // Method io/reactivex/rxjava3/internal/schedulers/ComputationScheduler$PoolWorker.scheduleActual:(Ljava/lang/Runnable;JLjava/util/concurrent/TimeUnit;Lio/reactivex/rxjava3/disposables/DisposableContainer;)Lio/reactivex/rxjava3/internal/schedulers/ScheduledRunnable;
      26: areturn
}
