Compiled from "DisposeOnCancel.java"
final class io.reactivex.rxjava3.internal.schedulers.DisposeOnCancel implements java.util.concurrent.Future<java.lang.Object> {
  final io.reactivex.rxjava3.disposables.Disposable upstream;

  io.reactivex.rxjava3.internal.schedulers.DisposeOnCancel(io.reactivex.rxjava3.disposables.Disposable);
    Code:
       0: aload_0
       1: invokespecial #1                  // Method java/lang/Object."<init>":()V
       4: aload_0
       5: aload_1
       6: putfield      #2                  // Field upstream:Lio/reactivex/rxjava3/disposables/Disposable;
       9: return

  public boolean cancel(boolean);
    Code:
       0: aload_0
       1: getfield      #2                  // Field upstream:Lio/reactivex/rxjava3/disposables/Disposable;
       4: invokeinterface #3,  1            // InterfaceMethod io/reactivex/rxjava3/disposables/Disposable.dispose:()V
       9: iconst_0
      10: ireturn

  public boolean isCancelled();
    Code:
       0: iconst_0
       1: ireturn

  public boolean isDone();
    Code:
       0: iconst_0
       1: ireturn

  public java.lang.Object get();
    Code:
       0: aconst_null
       1: areturn

  public java.lang.Object get(long, java.util.concurrent.TimeUnit);
    Code:
       0: aconst_null
       1: areturn
}
