Compiled from "ExecutorScheduler.java"
final class io.reactivex.rxjava3.internal.schedulers.ExecutorScheduler$DelayedRunnable extends java.util.concurrent.atomic.AtomicReference<java.lang.Runnable> implements java.lang.Runnable, io.reactivex.rxjava3.disposables.Disposable, io.reactivex.rxjava3.schedulers.SchedulerRunnableIntrospection {
  private static final long serialVersionUID;

  final io.reactivex.rxjava3.internal.disposables.SequentialDisposable timed;

  final io.reactivex.rxjava3.internal.disposables.SequentialDisposable direct;

  io.reactivex.rxjava3.internal.schedulers.ExecutorScheduler$DelayedRunnable(java.lang.Runnable);
    Code:
       0: aload_0
       1: aload_1
       2: invokespecial #1                  // Method java/util/concurrent/atomic/AtomicReference."<init>":(Ljava/lang/Object;)V
       5: aload_0
       6: new           #2                  // class io/reactivex/rxjava3/internal/disposables/SequentialDisposable
       9: dup
      10: invokespecial #3                  // Method io/reactivex/rxjava3/internal/disposables/SequentialDisposable."<init>":()V
      13: putfield      #4                  // Field timed:Lio/reactivex/rxjava3/internal/disposables/SequentialDisposable;
      16: aload_0
      17: new           #2                  // class io/reactivex/rxjava3/internal/disposables/SequentialDisposable
      20: dup
      21: invokespecial #3                  // Method io/reactivex/rxjava3/internal/disposables/SequentialDisposable."<init>":()V
      24: putfield      #5                  // Field direct:Lio/reactivex/rxjava3/internal/disposables/SequentialDisposable;
      27: return

  public void run();
    Code:
       0: aload_0
       1: invokevirtual #6                  // Method get:()Ljava/lang/Object;
       4: checkcast     #7                  // class java/lang/Runnable
       7: astore_1
       8: aload_1
       9: ifnull        84
      12: aload_1
      13: invokeinterface #8,  1            // InterfaceMethod java/lang/Runnable.run:()V
      18: aload_0
      19: aconst_null
      20: invokevirtual #9                  // Method lazySet:(Ljava/lang/Object;)V
      23: aload_0
      24: getfield      #4                  // Field timed:Lio/reactivex/rxjava3/internal/disposables/SequentialDisposable;
      27: getstatic     #10                 // Field io/reactivex/rxjava3/internal/disposables/DisposableHelper.DISPOSED:Lio/reactivex/rxjava3/internal/disposables/DisposableHelper;
      30: invokevirtual #11                 // Method io/reactivex/rxjava3/internal/disposables/SequentialDisposable.lazySet:(Ljava/lang/Object;)V
      33: aload_0
      34: getfield      #5                  // Field direct:Lio/reactivex/rxjava3/internal/disposables/SequentialDisposable;
      37: getstatic     #10                 // Field io/reactivex/rxjava3/internal/disposables/DisposableHelper.DISPOSED:Lio/reactivex/rxjava3/internal/disposables/DisposableHelper;
      40: invokevirtual #11                 // Method io/reactivex/rxjava3/internal/disposables/SequentialDisposable.lazySet:(Ljava/lang/Object;)V
      43: goto          74
      46: astore_2
      47: aload_0
      48: aconst_null
      49: invokevirtual #9                  // Method lazySet:(Ljava/lang/Object;)V
      52: aload_0
      53: getfield      #4                  // Field timed:Lio/reactivex/rxjava3/internal/disposables/SequentialDisposable;
      56: getstatic     #10                 // Field io/reactivex/rxjava3/internal/disposables/DisposableHelper.DISPOSED:Lio/reactivex/rxjava3/internal/disposables/DisposableHelper;
      59: invokevirtual #11                 // Method io/reactivex/rxjava3/internal/disposables/SequentialDisposable.lazySet:(Ljava/lang/Object;)V
      62: aload_0
      63: getfield      #5                  // Field direct:Lio/reactivex/rxjava3/internal/disposables/SequentialDisposable;
      66: getstatic     #10                 // Field io/reactivex/rxjava3/internal/disposables/DisposableHelper.DISPOSED:Lio/reactivex/rxjava3/internal/disposables/DisposableHelper;
      69: invokevirtual #11                 // Method io/reactivex/rxjava3/internal/disposables/SequentialDisposable.lazySet:(Ljava/lang/Object;)V
      72: aload_2
      73: athrow
      74: goto          84
      77: astore_2
      78: aload_2
      79: invokestatic  #13                 // Method io/reactivex/rxjava3/plugins/RxJavaPlugins.onError:(Ljava/lang/Throwable;)V
      82: aload_2
      83: athrow
      84: return
    Exception table:
       from    to  target type
          12    18    46   any
          12    74    77   Class java/lang/Throwable

  public boolean isDisposed();
    Code:
       0: aload_0
       1: invokevirtual #6                  // Method get:()Ljava/lang/Object;
       4: ifnonnull     11
       7: iconst_1
       8: goto          12
      11: iconst_0
      12: ireturn

  public void dispose();
    Code:
       0: aload_0
       1: aconst_null
       2: invokevirtual #14                 // Method getAndSet:(Ljava/lang/Object;)Ljava/lang/Object;
       5: ifnull        22
       8: aload_0
       9: getfield      #4                  // Field timed:Lio/reactivex/rxjava3/internal/disposables/SequentialDisposable;
      12: invokevirtual #15                 // Method io/reactivex/rxjava3/internal/disposables/SequentialDisposable.dispose:()V
      15: aload_0
      16: getfield      #5                  // Field direct:Lio/reactivex/rxjava3/internal/disposables/SequentialDisposable;
      19: invokevirtual #15                 // Method io/reactivex/rxjava3/internal/disposables/SequentialDisposable.dispose:()V
      22: return

  public java.lang.Runnable getWrappedRunnable();
    Code:
       0: aload_0
       1: invokevirtual #6                  // Method get:()Ljava/lang/Object;
       4: checkcast     #7                  // class java/lang/Runnable
       7: astore_1
       8: aload_1
       9: ifnull        16
      12: aload_1
      13: goto          19
      16: getstatic     #16                 // Field io/reactivex/rxjava3/internal/functions/Functions.EMPTY_RUNNABLE:Ljava/lang/Runnable;
      19: areturn
}
