Compiled from "ExecutorScheduler.java"
public final class io.reactivex.rxjava3.internal.schedulers.ExecutorScheduler$ExecutorWorker extends io.reactivex.rxjava3.core.Scheduler$Worker implements java.lang.Runnable {
  final boolean interruptibleWorker;

  final boolean fair;

  final java.util.concurrent.Executor executor;

  final io.reactivex.rxjava3.internal.queue.MpscLinkedQueue<java.lang.Runnable> queue;

  volatile boolean disposed;

  final java.util.concurrent.atomic.AtomicInteger wip;

  final io.reactivex.rxjava3.disposables.CompositeDisposable tasks;

  public io.reactivex.rxjava3.internal.schedulers.ExecutorScheduler$ExecutorWorker(java.util.concurrent.Executor, boolean, boolean);
    Code:
       0: aload_0
       1: invokespecial #1                  // Method io/reactivex/rxjava3/core/Scheduler$Worker."<init>":()V
       4: aload_0
       5: new           #2                  // class java/util/concurrent/atomic/AtomicInteger
       8: dup
       9: invokespecial #3                  // Method java/util/concurrent/atomic/AtomicInteger."<init>":()V
      12: putfield      #4                  // Field wip:Ljava/util/concurrent/atomic/AtomicInteger;
      15: aload_0
      16: new           #5                  // class io/reactivex/rxjava3/disposables/CompositeDisposable
      19: dup
      20: invokespecial #6                  // Method io/reactivex/rxjava3/disposables/CompositeDisposable."<init>":()V
      23: putfield      #7                  // Field tasks:Lio/reactivex/rxjava3/disposables/CompositeDisposable;
      26: aload_0
      27: aload_1
      28: putfield      #8                  // Field executor:Ljava/util/concurrent/Executor;
      31: aload_0
      32: new           #9                  // class io/reactivex/rxjava3/internal/queue/MpscLinkedQueue
      35: dup
      36: invokespecial #10                 // Method io/reactivex/rxjava3/internal/queue/MpscLinkedQueue."<init>":()V
      39: putfield      #11                 // Field queue:Lio/reactivex/rxjava3/internal/queue/MpscLinkedQueue;
      42: aload_0
      43: iload_2
      44: putfield      #12                 // Field interruptibleWorker:Z
      47: aload_0
      48: iload_3
      49: putfield      #13                 // Field fair:Z
      52: return

  public io.reactivex.rxjava3.disposables.Disposable schedule(java.lang.Runnable);
    Code:
       0: aload_0
       1: getfield      #14                 // Field disposed:Z
       4: ifeq          11
       7: getstatic     #15                 // Field io/reactivex/rxjava3/internal/disposables/EmptyDisposable.INSTANCE:Lio/reactivex/rxjava3/internal/disposables/EmptyDisposable;
      10: areturn
      11: aload_1
      12: invokestatic  #16                 // Method io/reactivex/rxjava3/plugins/RxJavaPlugins.onSchedule:(Ljava/lang/Runnable;)Ljava/lang/Runnable;
      15: astore_2
      16: aload_0
      17: getfield      #12                 // Field interruptibleWorker:Z
      20: ifeq          57
      23: new           #17                 // class io/reactivex/rxjava3/internal/schedulers/ExecutorScheduler$ExecutorWorker$InterruptibleRunnable
      26: dup
      27: aload_2
      28: aload_0
      29: getfield      #7                  // Field tasks:Lio/reactivex/rxjava3/disposables/CompositeDisposable;
      32: invokespecial #18                 // Method io/reactivex/rxjava3/internal/schedulers/ExecutorScheduler$ExecutorWorker$InterruptibleRunnable."<init>":(Ljava/lang/Runnable;Lio/reactivex/rxjava3/disposables/DisposableContainer;)V
      35: astore        5
      37: aload_0
      38: getfield      #7                  // Field tasks:Lio/reactivex/rxjava3/disposables/CompositeDisposable;
      41: aload         5
      43: invokevirtual #19                 // Method io/reactivex/rxjava3/disposables/CompositeDisposable.add:(Lio/reactivex/rxjava3/disposables/Disposable;)Z
      46: pop
      47: aload         5
      49: astore_3
      50: aload         5
      52: astore        4
      54: goto          74
      57: new           #20                 // class io/reactivex/rxjava3/internal/schedulers/ExecutorScheduler$ExecutorWorker$BooleanRunnable
      60: dup
      61: aload_2
      62: invokespecial #21                 // Method io/reactivex/rxjava3/internal/schedulers/ExecutorScheduler$ExecutorWorker$BooleanRunnable."<init>":(Ljava/lang/Runnable;)V
      65: astore        5
      67: aload         5
      69: astore_3
      70: aload         5
      72: astore        4
      74: aload_0
      75: getfield      #11                 // Field queue:Lio/reactivex/rxjava3/internal/queue/MpscLinkedQueue;
      78: aload_3
      79: invokevirtual #22                 // Method io/reactivex/rxjava3/internal/queue/MpscLinkedQueue.offer:(Ljava/lang/Object;)Z
      82: pop
      83: aload_0
      84: getfield      #4                  // Field wip:Ljava/util/concurrent/atomic/AtomicInteger;
      87: invokevirtual #23                 // Method java/util/concurrent/atomic/AtomicInteger.getAndIncrement:()I
      90: ifne          129
      93: aload_0
      94: getfield      #8                  // Field executor:Ljava/util/concurrent/Executor;
      97: aload_0
      98: invokeinterface #24,  2           // InterfaceMethod java/util/concurrent/Executor.execute:(Ljava/lang/Runnable;)V
     103: goto          129
     106: astore        5
     108: aload_0
     109: iconst_1
     110: putfield      #14                 // Field disposed:Z
     113: aload_0
     114: getfield      #11                 // Field queue:Lio/reactivex/rxjava3/internal/queue/MpscLinkedQueue;
     117: invokevirtual #26                 // Method io/reactivex/rxjava3/internal/queue/MpscLinkedQueue.clear:()V
     120: aload         5
     122: invokestatic  #27                 // Method io/reactivex/rxjava3/plugins/RxJavaPlugins.onError:(Ljava/lang/Throwable;)V
     125: getstatic     #15                 // Field io/reactivex/rxjava3/internal/disposables/EmptyDisposable.INSTANCE:Lio/reactivex/rxjava3/internal/disposables/EmptyDisposable;
     128: areturn
     129: aload         4
     131: areturn
    Exception table:
       from    to  target type
          93   103   106   Class java/util/concurrent/RejectedExecutionException

  public io.reactivex.rxjava3.disposables.Disposable schedule(java.lang.Runnable, long, java.util.concurrent.TimeUnit);
    Code:
       0: lload_2
       1: lconst_0
       2: lcmp
       3: ifgt          12
       6: aload_0
       7: aload_1
       8: invokevirtual #28                 // Method schedule:(Ljava/lang/Runnable;)Lio/reactivex/rxjava3/disposables/Disposable;
      11: areturn
      12: aload_0
      13: getfield      #14                 // Field disposed:Z
      16: ifeq          23
      19: getstatic     #15                 // Field io/reactivex/rxjava3/internal/disposables/EmptyDisposable.INSTANCE:Lio/reactivex/rxjava3/internal/disposables/EmptyDisposable;
      22: areturn
      23: new           #29                 // class io/reactivex/rxjava3/internal/disposables/SequentialDisposable
      26: dup
      27: invokespecial #30                 // Method io/reactivex/rxjava3/internal/disposables/SequentialDisposable."<init>":()V
      30: astore        5
      32: new           #29                 // class io/reactivex/rxjava3/internal/disposables/SequentialDisposable
      35: dup
      36: aload         5
      38: invokespecial #31                 // Method io/reactivex/rxjava3/internal/disposables/SequentialDisposable."<init>":(Lio/reactivex/rxjava3/disposables/Disposable;)V
      41: astore        6
      43: aload_1
      44: invokestatic  #16                 // Method io/reactivex/rxjava3/plugins/RxJavaPlugins.onSchedule:(Ljava/lang/Runnable;)Ljava/lang/Runnable;
      47: astore        7
      49: new           #32                 // class io/reactivex/rxjava3/internal/schedulers/ScheduledRunnable
      52: dup
      53: new           #33                 // class io/reactivex/rxjava3/internal/schedulers/ExecutorScheduler$ExecutorWorker$SequentialDispose
      56: dup
      57: aload_0
      58: aload         6
      60: aload         7
      62: invokespecial #34                 // Method io/reactivex/rxjava3/internal/schedulers/ExecutorScheduler$ExecutorWorker$SequentialDispose."<init>":(Lio/reactivex/rxjava3/internal/schedulers/ExecutorScheduler$ExecutorWorker;Lio/reactivex/rxjava3/internal/disposables/SequentialDisposable;Ljava/lang/Runnable;)V
      65: aload_0
      66: getfield      #7                  // Field tasks:Lio/reactivex/rxjava3/disposables/CompositeDisposable;
      69: invokespecial #35                 // Method io/reactivex/rxjava3/internal/schedulers/ScheduledRunnable."<init>":(Ljava/lang/Runnable;Lio/reactivex/rxjava3/disposables/DisposableContainer;)V
      72: astore        8
      74: aload_0
      75: getfield      #7                  // Field tasks:Lio/reactivex/rxjava3/disposables/CompositeDisposable;
      78: aload         8
      80: invokevirtual #19                 // Method io/reactivex/rxjava3/disposables/CompositeDisposable.add:(Lio/reactivex/rxjava3/disposables/Disposable;)Z
      83: pop
      84: aload_0
      85: getfield      #8                  // Field executor:Ljava/util/concurrent/Executor;
      88: instanceof    #36                 // class java/util/concurrent/ScheduledExecutorService
      91: ifeq          139
      94: aload_0
      95: getfield      #8                  // Field executor:Ljava/util/concurrent/Executor;
      98: checkcast     #36                 // class java/util/concurrent/ScheduledExecutorService
     101: aload         8
     103: lload_2
     104: aload         4
     106: invokeinterface #37,  5           // InterfaceMethod java/util/concurrent/ScheduledExecutorService.schedule:(Ljava/util/concurrent/Callable;JLjava/util/concurrent/TimeUnit;)Ljava/util/concurrent/ScheduledFuture;
     111: astore        9
     113: aload         8
     115: aload         9
     117: invokevirtual #38                 // Method io/reactivex/rxjava3/internal/schedulers/ScheduledRunnable.setFuture:(Ljava/util/concurrent/Future;)V
     120: goto          166
     123: astore        9
     125: aload_0
     126: iconst_1
     127: putfield      #14                 // Field disposed:Z
     130: aload         9
     132: invokestatic  #27                 // Method io/reactivex/rxjava3/plugins/RxJavaPlugins.onError:(Ljava/lang/Throwable;)V
     135: getstatic     #15                 // Field io/reactivex/rxjava3/internal/disposables/EmptyDisposable.INSTANCE:Lio/reactivex/rxjava3/internal/disposables/EmptyDisposable;
     138: areturn
     139: getstatic     #39                 // Field io/reactivex/rxjava3/internal/schedulers/ExecutorScheduler$SingleHolder.HELPER:Lio/reactivex/rxjava3/core/Scheduler;
     142: aload         8
     144: lload_2
     145: aload         4
     147: invokevirtual #40                 // Method io/reactivex/rxjava3/core/Scheduler.scheduleDirect:(Ljava/lang/Runnable;JLjava/util/concurrent/TimeUnit;)Lio/reactivex/rxjava3/disposables/Disposable;
     150: astore        9
     152: aload         8
     154: new           #41                 // class io/reactivex/rxjava3/internal/schedulers/DisposeOnCancel
     157: dup
     158: aload         9
     160: invokespecial #42                 // Method io/reactivex/rxjava3/internal/schedulers/DisposeOnCancel."<init>":(Lio/reactivex/rxjava3/disposables/Disposable;)V
     163: invokevirtual #38                 // Method io/reactivex/rxjava3/internal/schedulers/ScheduledRunnable.setFuture:(Ljava/util/concurrent/Future;)V
     166: aload         5
     168: aload         8
     170: invokevirtual #43                 // Method io/reactivex/rxjava3/internal/disposables/SequentialDisposable.replace:(Lio/reactivex/rxjava3/disposables/Disposable;)Z
     173: pop
     174: aload         6
     176: areturn
    Exception table:
       from    to  target type
          94   120   123   Class java/util/concurrent/RejectedExecutionException

  public void dispose();
    Code:
       0: aload_0
       1: getfield      #14                 // Field disposed:Z
       4: ifne          36
       7: aload_0
       8: iconst_1
       9: putfield      #14                 // Field disposed:Z
      12: aload_0
      13: getfield      #7                  // Field tasks:Lio/reactivex/rxjava3/disposables/CompositeDisposable;
      16: invokevirtual #44                 // Method io/reactivex/rxjava3/disposables/CompositeDisposable.dispose:()V
      19: aload_0
      20: getfield      #4                  // Field wip:Ljava/util/concurrent/atomic/AtomicInteger;
      23: invokevirtual #23                 // Method java/util/concurrent/atomic/AtomicInteger.getAndIncrement:()I
      26: ifne          36
      29: aload_0
      30: getfield      #11                 // Field queue:Lio/reactivex/rxjava3/internal/queue/MpscLinkedQueue;
      33: invokevirtual #26                 // Method io/reactivex/rxjava3/internal/queue/MpscLinkedQueue.clear:()V
      36: return

  public boolean isDisposed();
    Code:
       0: aload_0
       1: getfield      #14                 // Field disposed:Z
       4: ireturn

  public void run();
    Code:
       0: aload_0
       1: getfield      #13                 // Field fair:Z
       4: ifeq          14
       7: aload_0
       8: invokevirtual #45                 // Method runFair:()V
      11: goto          18
      14: aload_0
      15: invokevirtual #46                 // Method runEager:()V
      18: return

  void runFair();
    Code:
       0: aload_0
       1: getfield      #11                 // Field queue:Lio/reactivex/rxjava3/internal/queue/MpscLinkedQueue;
       4: astore_1
       5: aload_0
       6: getfield      #14                 // Field disposed:Z
       9: ifeq          17
      12: aload_1
      13: invokevirtual #26                 // Method io/reactivex/rxjava3/internal/queue/MpscLinkedQueue.clear:()V
      16: return
      17: aload_1
      18: invokevirtual #47                 // Method io/reactivex/rxjava3/internal/queue/MpscLinkedQueue.poll:()Ljava/lang/Object;
      21: checkcast     #48                 // class java/lang/Runnable
      24: astore_2
      25: aload_2
      26: invokeinterface #49,  1           // InterfaceMethod java/lang/Runnable.run:()V
      31: aload_0
      32: getfield      #14                 // Field disposed:Z
      35: ifeq          43
      38: aload_1
      39: invokevirtual #26                 // Method io/reactivex/rxjava3/internal/queue/MpscLinkedQueue.clear:()V
      42: return
      43: aload_0
      44: getfield      #4                  // Field wip:Ljava/util/concurrent/atomic/AtomicInteger;
      47: invokevirtual #50                 // Method java/util/concurrent/atomic/AtomicInteger.decrementAndGet:()I
      50: ifeq          63
      53: aload_0
      54: getfield      #8                  // Field executor:Ljava/util/concurrent/Executor;
      57: aload_0
      58: invokeinterface #24,  2           // InterfaceMethod java/util/concurrent/Executor.execute:(Ljava/lang/Runnable;)V
      63: return

  void runEager();
    Code:
       0: iconst_1
       1: istore_1
       2: aload_0
       3: getfield      #11                 // Field queue:Lio/reactivex/rxjava3/internal/queue/MpscLinkedQueue;
       6: astore_2
       7: aload_0
       8: getfield      #14                 // Field disposed:Z
      11: ifeq          19
      14: aload_2
      15: invokevirtual #26                 // Method io/reactivex/rxjava3/internal/queue/MpscLinkedQueue.clear:()V
      18: return
      19: aload_2
      20: invokevirtual #47                 // Method io/reactivex/rxjava3/internal/queue/MpscLinkedQueue.poll:()Ljava/lang/Object;
      23: checkcast     #48                 // class java/lang/Runnable
      26: astore_3
      27: aload_3
      28: ifnonnull     34
      31: goto          55
      34: aload_3
      35: invokeinterface #49,  1           // InterfaceMethod java/lang/Runnable.run:()V
      40: aload_0
      41: getfield      #14                 // Field disposed:Z
      44: ifeq          52
      47: aload_2
      48: invokevirtual #26                 // Method io/reactivex/rxjava3/internal/queue/MpscLinkedQueue.clear:()V
      51: return
      52: goto          19
      55: aload_0
      56: getfield      #14                 // Field disposed:Z
      59: ifeq          67
      62: aload_2
      63: invokevirtual #26                 // Method io/reactivex/rxjava3/internal/queue/MpscLinkedQueue.clear:()V
      66: return
      67: aload_0
      68: getfield      #4                  // Field wip:Ljava/util/concurrent/atomic/AtomicInteger;
      71: iload_1
      72: ineg
      73: invokevirtual #51                 // Method java/util/concurrent/atomic/AtomicInteger.addAndGet:(I)I
      76: istore_1
      77: iload_1
      78: ifne          7
      81: goto          84
      84: return
}
