Compiled from "ExecutorScheduler.java"
final class io.reactivex.rxjava3.internal.schedulers.ExecutorScheduler$ExecutorWorker$SequentialDispose implements java.lang.Runnable {
  private final io.reactivex.rxjava3.internal.disposables.SequentialDisposable mar;

  private final java.lang.Runnable decoratedRun;

  final io.reactivex.rxjava3.internal.schedulers.ExecutorScheduler$ExecutorWorker this$0;

  io.reactivex.rxjava3.internal.schedulers.ExecutorScheduler$ExecutorWorker$SequentialDispose(io.reactivex.rxjava3.internal.schedulers.ExecutorScheduler$ExecutorWorker, io.reactivex.rxjava3.internal.disposables.SequentialDisposable, java.lang.Runnable);
    Code:
       0: aload_0
       1: aload_1
       2: putfield      #1                  // Field this$0:Lio/reactivex/rxjava3/internal/schedulers/ExecutorScheduler$ExecutorWorker;
       5: aload_0
       6: invokespecial #2                  // Method java/lang/Object."<init>":()V
       9: aload_0
      10: aload_2
      11: putfield      #3                  // Field mar:Lio/reactivex/rxjava3/internal/disposables/SequentialDisposable;
      14: aload_0
      15: aload_3
      16: putfield      #4                  // Field decoratedRun:Ljava/lang/Runnable;
      19: return

  public void run();
    Code:
       0: aload_0
       1: getfield      #3                  // Field mar:Lio/reactivex/rxjava3/internal/disposables/SequentialDisposable;
       4: aload_0
       5: getfield      #1                  // Field this$0:Lio/reactivex/rxjava3/internal/schedulers/ExecutorScheduler$ExecutorWorker;
       8: aload_0
       9: getfield      #4                  // Field decoratedRun:Ljava/lang/Runnable;
      12: invokevirtual #5                  // Method io/reactivex/rxjava3/internal/schedulers/ExecutorScheduler$ExecutorWorker.schedule:(Ljava/lang/Runnable;)Lio/reactivex/rxjava3/disposables/Disposable;
      15: invokevirtual #6                  // Method io/reactivex/rxjava3/internal/disposables/SequentialDisposable.replace:(Lio/reactivex/rxjava3/disposables/Disposable;)Z
      18: pop
      19: return
}
