Compiled from "ExecutorScheduler.java"
public final class io.reactivex.rxjava3.internal.schedulers.ExecutorScheduler extends io.reactivex.rxjava3.core.Scheduler {
  final boolean interruptibleWorker;

  final boolean fair;

  final java.util.concurrent.Executor executor;

  public io.reactivex.rxjava3.internal.schedulers.ExecutorScheduler(java.util.concurrent.Executor, boolean, boolean);
    Code:
       0: aload_0
       1: invokespecial #1                  // Method io/reactivex/rxjava3/core/Scheduler."<init>":()V
       4: aload_0
       5: aload_1
       6: putfield      #2                  // Field executor:Ljava/util/concurrent/Executor;
       9: aload_0
      10: iload_2
      11: putfield      #3                  // Field interruptibleWorker:Z
      14: aload_0
      15: iload_3
      16: putfield      #4                  // Field fair:Z
      19: return

  public io.reactivex.rxjava3.core.Scheduler$Worker createWorker();
    Code:
       0: new           #5                  // class io/reactivex/rxjava3/internal/schedulers/ExecutorScheduler$ExecutorWorker
       3: dup
       4: aload_0
       5: getfield      #2                  // Field executor:Ljava/util/concurrent/Executor;
       8: aload_0
       9: getfield      #3                  // Field interruptibleWorker:Z
      12: aload_0
      13: getfield      #4                  // Field fair:Z
      16: invokespecial #6                  // Method io/reactivex/rxjava3/internal/schedulers/ExecutorScheduler$ExecutorWorker."<init>":(Ljava/util/concurrent/Executor;ZZ)V
      19: areturn

  public io.reactivex.rxjava3.disposables.Disposable scheduleDirect(java.lang.Runnable);
    Code:
       0: aload_1
       1: invokestatic  #7                  // Method io/reactivex/rxjava3/plugins/RxJavaPlugins.onSchedule:(Ljava/lang/Runnable;)Ljava/lang/Runnable;
       4: astore_2
       5: aload_0
       6: getfield      #2                  // Field executor:Ljava/util/concurrent/Executor;
       9: instanceof    #8                  // class java/util/concurrent/ExecutorService
      12: ifeq          51
      15: new           #9                  // class io/reactivex/rxjava3/internal/schedulers/ScheduledDirectTask
      18: dup
      19: aload_2
      20: aload_0
      21: getfield      #3                  // Field interruptibleWorker:Z
      24: invokespecial #10                 // Method io/reactivex/rxjava3/internal/schedulers/ScheduledDirectTask."<init>":(Ljava/lang/Runnable;Z)V
      27: astore_3
      28: aload_0
      29: getfield      #2                  // Field executor:Ljava/util/concurrent/Executor;
      32: checkcast     #8                  // class java/util/concurrent/ExecutorService
      35: aload_3
      36: invokeinterface #11,  2           // InterfaceMethod java/util/concurrent/ExecutorService.submit:(Ljava/util/concurrent/Callable;)Ljava/util/concurrent/Future;
      41: astore        4
      43: aload_3
      44: aload         4
      46: invokevirtual #12                 // Method io/reactivex/rxjava3/internal/schedulers/ScheduledDirectTask.setFuture:(Ljava/util/concurrent/Future;)V
      49: aload_3
      50: areturn
      51: aload_0
      52: getfield      #3                  // Field interruptibleWorker:Z
      55: ifeq          80
      58: new           #13                 // class io/reactivex/rxjava3/internal/schedulers/ExecutorScheduler$ExecutorWorker$InterruptibleRunnable
      61: dup
      62: aload_2
      63: aconst_null
      64: invokespecial #14                 // Method io/reactivex/rxjava3/internal/schedulers/ExecutorScheduler$ExecutorWorker$InterruptibleRunnable."<init>":(Ljava/lang/Runnable;Lio/reactivex/rxjava3/disposables/DisposableContainer;)V
      67: astore_3
      68: aload_0
      69: getfield      #2                  // Field executor:Ljava/util/concurrent/Executor;
      72: aload_3
      73: invokeinterface #15,  2           // InterfaceMethod java/util/concurrent/Executor.execute:(Ljava/lang/Runnable;)V
      78: aload_3
      79: areturn
      80: new           #16                 // class io/reactivex/rxjava3/internal/schedulers/ExecutorScheduler$ExecutorWorker$BooleanRunnable
      83: dup
      84: aload_2
      85: invokespecial #17                 // Method io/reactivex/rxjava3/internal/schedulers/ExecutorScheduler$ExecutorWorker$BooleanRunnable."<init>":(Ljava/lang/Runnable;)V
      88: astore_3
      89: aload_0
      90: getfield      #2                  // Field executor:Ljava/util/concurrent/Executor;
      93: aload_3
      94: invokeinterface #15,  2           // InterfaceMethod java/util/concurrent/Executor.execute:(Ljava/lang/Runnable;)V
      99: aload_3
     100: areturn
     101: astore_3
     102: aload_3
     103: invokestatic  #19                 // Method io/reactivex/rxjava3/plugins/RxJavaPlugins.onError:(Ljava/lang/Throwable;)V
     106: getstatic     #20                 // Field io/reactivex/rxjava3/internal/disposables/EmptyDisposable.INSTANCE:Lio/reactivex/rxjava3/internal/disposables/EmptyDisposable;
     109: areturn
    Exception table:
       from    to  target type
           5    50   101   Class java/util/concurrent/RejectedExecutionException
          51    79   101   Class java/util/concurrent/RejectedExecutionException
          80   100   101   Class java/util/concurrent/RejectedExecutionException

  public io.reactivex.rxjava3.disposables.Disposable scheduleDirect(java.lang.Runnable, long, java.util.concurrent.TimeUnit);
    Code:
       0: aload_1
       1: invokestatic  #7                  // Method io/reactivex/rxjava3/plugins/RxJavaPlugins.onSchedule:(Ljava/lang/Runnable;)Ljava/lang/Runnable;
       4: astore        5
       6: aload_0
       7: getfield      #2                  // Field executor:Ljava/util/concurrent/Executor;
      10: instanceof    #21                 // class java/util/concurrent/ScheduledExecutorService
      13: ifeq          71
      16: new           #9                  // class io/reactivex/rxjava3/internal/schedulers/ScheduledDirectTask
      19: dup
      20: aload         5
      22: aload_0
      23: getfield      #3                  // Field interruptibleWorker:Z
      26: invokespecial #10                 // Method io/reactivex/rxjava3/internal/schedulers/ScheduledDirectTask."<init>":(Ljava/lang/Runnable;Z)V
      29: astore        6
      31: aload_0
      32: getfield      #2                  // Field executor:Ljava/util/concurrent/Executor;
      35: checkcast     #21                 // class java/util/concurrent/ScheduledExecutorService
      38: aload         6
      40: lload_2
      41: aload         4
      43: invokeinterface #22,  5           // InterfaceMethod java/util/concurrent/ScheduledExecutorService.schedule:(Ljava/util/concurrent/Callable;JLjava/util/concurrent/TimeUnit;)Ljava/util/concurrent/ScheduledFuture;
      48: astore        7
      50: aload         6
      52: aload         7
      54: invokevirtual #12                 // Method io/reactivex/rxjava3/internal/schedulers/ScheduledDirectTask.setFuture:(Ljava/util/concurrent/Future;)V
      57: aload         6
      59: areturn
      60: astore        6
      62: aload         6
      64: invokestatic  #19                 // Method io/reactivex/rxjava3/plugins/RxJavaPlugins.onError:(Ljava/lang/Throwable;)V
      67: getstatic     #20                 // Field io/reactivex/rxjava3/internal/disposables/EmptyDisposable.INSTANCE:Lio/reactivex/rxjava3/internal/disposables/EmptyDisposable;
      70: areturn
      71: new           #23                 // class io/reactivex/rxjava3/internal/schedulers/ExecutorScheduler$DelayedRunnable
      74: dup
      75: aload         5
      77: invokespecial #24                 // Method io/reactivex/rxjava3/internal/schedulers/ExecutorScheduler$DelayedRunnable."<init>":(Ljava/lang/Runnable;)V
      80: astore        6
      82: getstatic     #25                 // Field io/reactivex/rxjava3/internal/schedulers/ExecutorScheduler$SingleHolder.HELPER:Lio/reactivex/rxjava3/core/Scheduler;
      85: new           #26                 // class io/reactivex/rxjava3/internal/schedulers/ExecutorScheduler$DelayedDispose
      88: dup
      89: aload_0
      90: aload         6
      92: invokespecial #27                 // Method io/reactivex/rxjava3/internal/schedulers/ExecutorScheduler$DelayedDispose."<init>":(Lio/reactivex/rxjava3/internal/schedulers/ExecutorScheduler;Lio/reactivex/rxjava3/internal/schedulers/ExecutorScheduler$DelayedRunnable;)V
      95: lload_2
      96: aload         4
      98: invokevirtual #28                 // Method io/reactivex/rxjava3/core/Scheduler.scheduleDirect:(Ljava/lang/Runnable;JLjava/util/concurrent/TimeUnit;)Lio/reactivex/rxjava3/disposables/Disposable;
     101: astore        7
     103: aload         6
     105: getfield      #29                 // Field io/reactivex/rxjava3/internal/schedulers/ExecutorScheduler$DelayedRunnable.timed:Lio/reactivex/rxjava3/internal/disposables/SequentialDisposable;
     108: aload         7
     110: invokevirtual #30                 // Method io/reactivex/rxjava3/internal/disposables/SequentialDisposable.replace:(Lio/reactivex/rxjava3/disposables/Disposable;)Z
     113: pop
     114: aload         6
     116: areturn
    Exception table:
       from    to  target type
          16    59    60   Class java/util/concurrent/RejectedExecutionException

  public io.reactivex.rxjava3.disposables.Disposable schedulePeriodicallyDirect(java.lang.Runnable, long, long, java.util.concurrent.TimeUnit);
    Code:
       0: aload_0
       1: getfield      #2                  // Field executor:Ljava/util/concurrent/Executor;
       4: instanceof    #21                 // class java/util/concurrent/ScheduledExecutorService
       7: ifeq          73
      10: aload_1
      11: invokestatic  #7                  // Method io/reactivex/rxjava3/plugins/RxJavaPlugins.onSchedule:(Ljava/lang/Runnable;)Ljava/lang/Runnable;
      14: astore        7
      16: new           #31                 // class io/reactivex/rxjava3/internal/schedulers/ScheduledDirectPeriodicTask
      19: dup
      20: aload         7
      22: aload_0
      23: getfield      #3                  // Field interruptibleWorker:Z
      26: invokespecial #32                 // Method io/reactivex/rxjava3/internal/schedulers/ScheduledDirectPeriodicTask."<init>":(Ljava/lang/Runnable;Z)V
      29: astore        8
      31: aload_0
      32: getfield      #2                  // Field executor:Ljava/util/concurrent/Executor;
      35: checkcast     #21                 // class java/util/concurrent/ScheduledExecutorService
      38: aload         8
      40: lload_2
      41: lload         4
      43: aload         6
      45: invokeinterface #33,  7           // InterfaceMethod java/util/concurrent/ScheduledExecutorService.scheduleAtFixedRate:(Ljava/lang/Runnable;JJLjava/util/concurrent/TimeUnit;)Ljava/util/concurrent/ScheduledFuture;
      50: astore        9
      52: aload         8
      54: aload         9
      56: invokevirtual #34                 // Method io/reactivex/rxjava3/internal/schedulers/ScheduledDirectPeriodicTask.setFuture:(Ljava/util/concurrent/Future;)V
      59: aload         8
      61: areturn
      62: astore        8
      64: aload         8
      66: invokestatic  #19                 // Method io/reactivex/rxjava3/plugins/RxJavaPlugins.onError:(Ljava/lang/Throwable;)V
      69: getstatic     #20                 // Field io/reactivex/rxjava3/internal/disposables/EmptyDisposable.INSTANCE:Lio/reactivex/rxjava3/internal/disposables/EmptyDisposable;
      72: areturn
      73: aload_0
      74: aload_1
      75: lload_2
      76: lload         4
      78: aload         6
      80: invokespecial #35                 // Method io/reactivex/rxjava3/core/Scheduler.schedulePeriodicallyDirect:(Ljava/lang/Runnable;JJLjava/util/concurrent/TimeUnit;)Lio/reactivex/rxjava3/disposables/Disposable;
      83: areturn
    Exception table:
       from    to  target type
          16    61    62   Class java/util/concurrent/RejectedExecutionException
}
