Compiled from "ExecutorScheduler.java"
final class io.reactivex.rxjava3.internal.schedulers.ExecutorScheduler$DelayedDispose implements java.lang.Runnable {
  private final io.reactivex.rxjava3.internal.schedulers.ExecutorScheduler$DelayedRunnable dr;

  final io.reactivex.rxjava3.internal.schedulers.ExecutorScheduler this$0;

  io.reactivex.rxjava3.internal.schedulers.ExecutorScheduler$DelayedDispose(io.reactivex.rxjava3.internal.schedulers.ExecutorScheduler, io.reactivex.rxjava3.internal.schedulers.ExecutorScheduler$DelayedRunnable);
    Code:
       0: aload_0
       1: aload_1
       2: putfield      #1                  // Field this$0:Lio/reactivex/rxjava3/internal/schedulers/ExecutorScheduler;
       5: aload_0
       6: invokespecial #2                  // Method java/lang/Object."<init>":()V
       9: aload_0
      10: aload_2
      11: putfield      #3                  // Field dr:Lio/reactivex/rxjava3/internal/schedulers/ExecutorScheduler$DelayedRunnable;
      14: return

  public void run();
    Code:
       0: aload_0
       1: getfield      #3                  // Field dr:Lio/reactivex/rxjava3/internal/schedulers/ExecutorScheduler$DelayedRunnable;
       4: getfield      #4                  // Field io/reactivex/rxjava3/internal/schedulers/ExecutorScheduler$DelayedRunnable.direct:Lio/reactivex/rxjava3/internal/disposables/SequentialDisposable;
       7: aload_0
       8: getfield      #1                  // Field this$0:Lio/reactivex/rxjava3/internal/schedulers/ExecutorScheduler;
      11: aload_0
      12: getfield      #3                  // Field dr:Lio/reactivex/rxjava3/internal/schedulers/ExecutorScheduler$DelayedRunnable;
      15: invokevirtual #5                  // Method io/reactivex/rxjava3/internal/schedulers/ExecutorScheduler.scheduleDirect:(Ljava/lang/Runnable;)Lio/reactivex/rxjava3/disposables/Disposable;
      18: invokevirtual #6                  // Method io/reactivex/rxjava3/internal/disposables/SequentialDisposable.replace:(Lio/reactivex/rxjava3/disposables/Disposable;)Z
      21: pop
      22: return
}
