Compiled from "ImmediateThinScheduler.java"
public final class io.reactivex.rxjava3.internal.schedulers.ImmediateThinScheduler extends io.reactivex.rxjava3.core.Scheduler {
  public static final io.reactivex.rxjava3.core.Scheduler INSTANCE;

  static final io.reactivex.rxjava3.core.Scheduler$Worker WORKER;

  static final io.reactivex.rxjava3.disposables.Disposable DISPOSED;

  private io.reactivex.rxjava3.internal.schedulers.ImmediateThinScheduler();
    Code:
       0: aload_0
       1: invokespecial #1                  // Method io/reactivex/rxjava3/core/Scheduler."<init>":()V
       4: return

  public io.reactivex.rxjava3.disposables.Disposable scheduleDirect(java.lang.Runnable);
    Code:
       0: aload_1
       1: invokeinterface #2,  1            // InterfaceMethod java/lang/Runnable.run:()V
       6: getstatic     #3                  // Field DISPOSED:Lio/reactivex/rxjava3/disposables/Disposable;
       9: areturn

  public io.reactivex.rxjava3.disposables.Disposable scheduleDirect(java.lang.Runnable, long, java.util.concurrent.TimeUnit);
    Code:
       0: new           #4                  // class java/lang/UnsupportedOperationException
       3: dup
       4: ldc           #5                  // String This scheduler doesn\'t support delayed execution
       6: invokespecial #6                  // Method java/lang/UnsupportedOperationException."<init>":(Ljava/lang/String;)V
       9: athrow

  public io.reactivex.rxjava3.disposables.Disposable schedulePeriodicallyDirect(java.lang.Runnable, long, long, java.util.concurrent.TimeUnit);
    Code:
       0: new           #4                  // class java/lang/UnsupportedOperationException
       3: dup
       4: ldc           #7                  // String This scheduler doesn\'t support periodic execution
       6: invokespecial #6                  // Method java/lang/UnsupportedOperationException."<init>":(Ljava/lang/String;)V
       9: athrow

  public io.reactivex.rxjava3.core.Scheduler$Worker createWorker();
    Code:
       0: getstatic     #8                  // Field WORKER:Lio/reactivex/rxjava3/core/Scheduler$Worker;
       3: areturn

  static {};
    Code:
       0: new           #9                  // class io/reactivex/rxjava3/internal/schedulers/ImmediateThinScheduler
       3: dup
       4: invokespecial #10                 // Method "<init>":()V
       7: putstatic     #11                 // Field INSTANCE:Lio/reactivex/rxjava3/core/Scheduler;
      10: new           #12                 // class io/reactivex/rxjava3/internal/schedulers/ImmediateThinScheduler$ImmediateThinWorker
      13: dup
      14: invokespecial #13                 // Method io/reactivex/rxjava3/internal/schedulers/ImmediateThinScheduler$ImmediateThinWorker."<init>":()V
      17: putstatic     #8                  // Field WORKER:Lio/reactivex/rxjava3/core/Scheduler$Worker;
      20: invokestatic  #14                 // InterfaceMethod io/reactivex/rxjava3/disposables/Disposable.empty:()Lio/reactivex/rxjava3/disposables/Disposable;
      23: putstatic     #3                  // Field DISPOSED:Lio/reactivex/rxjava3/disposables/Disposable;
      26: getstatic     #3                  // Field DISPOSED:Lio/reactivex/rxjava3/disposables/Disposable;
      29: invokeinterface #15,  1           // InterfaceMethod io/reactivex/rxjava3/disposables/Disposable.dispose:()V
      34: return
}
