Compiled from "ImmediateThinScheduler.java"
final class io.reactivex.rxjava3.internal.schedulers.ImmediateThinScheduler$ImmediateThinWorker extends io.reactivex.rxjava3.core.Scheduler$Worker {
  io.reactivex.rxjava3.internal.schedulers.ImmediateThinScheduler$ImmediateThinWorker();
    Code:
       0: aload_0
       1: invokespecial #1                  // Method io/reactivex/rxjava3/core/Scheduler$Worker."<init>":()V
       4: return

  public void dispose();
    Code:
       0: return

  public boolean isDisposed();
    Code:
       0: iconst_0
       1: ireturn

  public io.reactivex.rxjava3.disposables.Disposable schedule(java.lang.Runnable);
    Code:
       0: aload_1
       1: invokeinterface #2,  1            // InterfaceMethod java/lang/Runnable.run:()V
       6: getstatic     #3                  // Field io/reactivex/rxjava3/internal/schedulers/ImmediateThinScheduler.DISPOSED:Lio/reactivex/rxjava3/disposables/Disposable;
       9: areturn

  public io.reactivex.rxjava3.disposables.Disposable schedule(java.lang.Runnable, long, java.util.concurrent.TimeUnit);
    Code:
       0: new           #4                  // class java/lang/UnsupportedOperationException
       3: dup
       4: ldc           #5                  // String This scheduler doesn\'t support delayed execution
       6: invokespecial #6                  // Method java/lang/UnsupportedOperationException."<init>":(Ljava/lang/String;)V
       9: athrow

  public io.reactivex.rxjava3.disposables.Disposable schedulePeriodically(java.lang.Runnable, long, long, java.util.concurrent.TimeUnit);
    Code:
       0: new           #4                  // class java/lang/UnsupportedOperationException
       3: dup
       4: ldc           #7                  // String This scheduler doesn\'t support periodic execution
       6: invokespecial #6                  // Method java/lang/UnsupportedOperationException."<init>":(Ljava/lang/String;)V
       9: athrow
}
