Compiled from "IoScheduler.java"
final class io.reactivex.rxjava3.internal.schedulers.IoScheduler$ThreadWorker extends io.reactivex.rxjava3.internal.schedulers.NewThreadWorker {
  long expirationTime;

  io.reactivex.rxjava3.internal.schedulers.IoScheduler$ThreadWorker(java.util.concurrent.ThreadFactory);
    Code:
       0: aload_0
       1: aload_1
       2: invokespecial #1                  // Method io/reactivex/rxjava3/internal/schedulers/NewThreadWorker."<init>":(Ljava/util/concurrent/ThreadFactory;)V
       5: aload_0
       6: lconst_0
       7: putfield      #2                  // Field expirationTime:J
      10: return

  public long getExpirationTime();
    Code:
       0: aload_0
       1: getfield      #2                  // Field expirationTime:J
       4: lreturn

  public void setExpirationTime(long);
    Code:
       0: aload_0
       1: lload_1
       2: putfield      #2                  // Field expirationTime:J
       5: return
}
