Compiled from "NewThreadWorker.java"
public class io.reactivex.rxjava3.internal.schedulers.NewThreadWorker extends io.reactivex.rxjava3.core.Scheduler$Worker {
  private final java.util.concurrent.ScheduledExecutorService executor;

  volatile boolean disposed;

  public io.reactivex.rxjava3.internal.schedulers.NewThreadWorker(java.util.concurrent.ThreadFactory);
    Code:
       0: aload_0
       1: invokespecial #1                  // Method io/reactivex/rxjava3/core/Scheduler$Worker."<init>":()V
       4: aload_0
       5: aload_1
       6: invokestatic  #2                  // Method io/reactivex/rxjava3/internal/schedulers/SchedulerPoolFactory.create:(Ljava/util/concurrent/ThreadFactory;)Ljava/util/concurrent/ScheduledExecutorService;
       9: putfield      #3                  // Field executor:Ljava/util/concurrent/ScheduledExecutorService;
      12: return

  public io.reactivex.rxjava3.disposables.Disposable schedule(java.lang.Runnable);
    Code:
       0: aload_0
       1: aload_1
       2: lconst_0
       3: aconst_null
       4: invokevirtual #4                  // Method schedule:(Ljava/lang/Runnable;JLjava/util/concurrent/TimeUnit;)Lio/reactivex/rxjava3/disposables/Disposable;
       7: areturn

  public io.reactivex.rxjava3.disposables.Disposable schedule(java.lang.Runnable, long, java.util.concurrent.TimeUnit);
    Code:
       0: aload_0
       1: getfield      #5                  // Field disposed:Z
       4: ifeq          11
       7: getstatic     #6                  // Field io/reactivex/rxjava3/internal/disposables/EmptyDisposable.INSTANCE:Lio/reactivex/rxjava3/internal/disposables/EmptyDisposable;
      10: areturn
      11: aload_0
      12: aload_1
      13: lload_2
      14: aload         4
      16: aconst_null
      17: invokevirtual #7                  // Method scheduleActual:(Ljava/lang/Runnable;JLjava/util/concurrent/TimeUnit;Lio/reactivex/rxjava3/disposables/DisposableContainer;)Lio/reactivex/rxjava3/internal/schedulers/ScheduledRunnable;
      20: areturn

  public io.reactivex.rxjava3.disposables.Disposable scheduleDirect(java.lang.Runnable, long, java.util.concurrent.TimeUnit);
    Code:
       0: new           #8                  // class io/reactivex/rxjava3/internal/schedulers/ScheduledDirectTask
       3: dup
       4: aload_1
       5: invokestatic  #9                  // Method io/reactivex/rxjava3/plugins/RxJavaPlugins.onSchedule:(Ljava/lang/Runnable;)Ljava/lang/Runnable;
       8: iconst_1
       9: invokespecial #10                 // Method io/reactivex/rxjava3/internal/schedulers/ScheduledDirectTask."<init>":(Ljava/lang/Runnable;Z)V
      12: astore        5
      14: lload_2
      15: lconst_0
      16: lcmp
      17: ifgt          36
      20: aload_0
      21: getfield      #3                  // Field executor:Ljava/util/concurrent/ScheduledExecutorService;
      24: aload         5
      26: invokeinterface #11,  2           // InterfaceMethod java/util/concurrent/ScheduledExecutorService.submit:(Ljava/util/concurrent/Callable;)Ljava/util/concurrent/Future;
      31: astore        6
      33: goto          52
      36: aload_0
      37: getfield      #3                  // Field executor:Ljava/util/concurrent/ScheduledExecutorService;
      40: aload         5
      42: lload_2
      43: aload         4
      45: invokeinterface #12,  5           // InterfaceMethod java/util/concurrent/ScheduledExecutorService.schedule:(Ljava/util/concurrent/Callable;JLjava/util/concurrent/TimeUnit;)Ljava/util/concurrent/ScheduledFuture;
      50: astore        6
      52: aload         5
      54: aload         6
      56: invokevirtual #13                 // Method io/reactivex/rxjava3/internal/schedulers/ScheduledDirectTask.setFuture:(Ljava/util/concurrent/Future;)V
      59: aload         5
      61: areturn
      62: astore        6
      64: aload         6
      66: invokestatic  #15                 // Method io/reactivex/rxjava3/plugins/RxJavaPlugins.onError:(Ljava/lang/Throwable;)V
      69: getstatic     #6                  // Field io/reactivex/rxjava3/internal/disposables/EmptyDisposable.INSTANCE:Lio/reactivex/rxjava3/internal/disposables/EmptyDisposable;
      72: areturn
    Exception table:
       from    to  target type
          14    61    62   Class java/util/concurrent/RejectedExecutionException

  public io.reactivex.rxjava3.disposables.Disposable schedulePeriodicallyDirect(java.lang.Runnable, long, long, java.util.concurrent.TimeUnit);
    Code:
       0: aload_1
       1: invokestatic  #9                  // Method io/reactivex/rxjava3/plugins/RxJavaPlugins.onSchedule:(Ljava/lang/Runnable;)Ljava/lang/Runnable;
       4: astore        7
       6: lload         4
       8: lconst_0
       9: lcmp
      10: ifgt          90
      13: new           #16                 // class io/reactivex/rxjava3/internal/schedulers/InstantPeriodicTask
      16: dup
      17: aload         7
      19: aload_0
      20: getfield      #3                  // Field executor:Ljava/util/concurrent/ScheduledExecutorService;
      23: invokespecial #17                 // Method io/reactivex/rxjava3/internal/schedulers/InstantPeriodicTask."<init>":(Ljava/lang/Runnable;Ljava/util/concurrent/ExecutorService;)V
      26: astore        8
      28: lload_2
      29: lconst_0
      30: lcmp
      31: ifgt          50
      34: aload_0
      35: getfield      #3                  // Field executor:Ljava/util/concurrent/ScheduledExecutorService;
      38: aload         8
      40: invokeinterface #11,  2           // InterfaceMethod java/util/concurrent/ScheduledExecutorService.submit:(Ljava/util/concurrent/Callable;)Ljava/util/concurrent/Future;
      45: astore        9
      47: goto          66
      50: aload_0
      51: getfield      #3                  // Field executor:Ljava/util/concurrent/ScheduledExecutorService;
      54: aload         8
      56: lload_2
      57: aload         6
      59: invokeinterface #12,  5           // InterfaceMethod java/util/concurrent/ScheduledExecutorService.schedule:(Ljava/util/concurrent/Callable;JLjava/util/concurrent/TimeUnit;)Ljava/util/concurrent/ScheduledFuture;
      64: astore        9
      66: aload         8
      68: aload         9
      70: invokevirtual #18                 // Method io/reactivex/rxjava3/internal/schedulers/InstantPeriodicTask.setFirst:(Ljava/util/concurrent/Future;)V
      73: goto          87
      76: astore        9
      78: aload         9
      80: invokestatic  #15                 // Method io/reactivex/rxjava3/plugins/RxJavaPlugins.onError:(Ljava/lang/Throwable;)V
      83: getstatic     #6                  // Field io/reactivex/rxjava3/internal/disposables/EmptyDisposable.INSTANCE:Lio/reactivex/rxjava3/internal/disposables/EmptyDisposable;
      86: areturn
      87: aload         8
      89: areturn
      90: new           #19                 // class io/reactivex/rxjava3/internal/schedulers/ScheduledDirectPeriodicTask
      93: dup
      94: aload         7
      96: iconst_1
      97: invokespecial #20                 // Method io/reactivex/rxjava3/internal/schedulers/ScheduledDirectPeriodicTask."<init>":(Ljava/lang/Runnable;Z)V
     100: astore        8
     102: aload_0
     103: getfield      #3                  // Field executor:Ljava/util/concurrent/ScheduledExecutorService;
     106: aload         8
     108: lload_2
     109: lload         4
     111: aload         6
     113: invokeinterface #21,  7           // InterfaceMethod java/util/concurrent/ScheduledExecutorService.scheduleAtFixedRate:(Ljava/lang/Runnable;JJLjava/util/concurrent/TimeUnit;)Ljava/util/concurrent/ScheduledFuture;
     118: astore        9
     120: aload         8
     122: aload         9
     124: invokevirtual #22                 // Method io/reactivex/rxjava3/internal/schedulers/ScheduledDirectPeriodicTask.setFuture:(Ljava/util/concurrent/Future;)V
     127: aload         8
     129: areturn
     130: astore        9
     132: aload         9
     134: invokestatic  #15                 // Method io/reactivex/rxjava3/plugins/RxJavaPlugins.onError:(Ljava/lang/Throwable;)V
     137: getstatic     #6                  // Field io/reactivex/rxjava3/internal/disposables/EmptyDisposable.INSTANCE:Lio/reactivex/rxjava3/internal/disposables/EmptyDisposable;
     140: areturn
    Exception table:
       from    to  target type
          28    73    76   Class java/util/concurrent/RejectedExecutionException
         102   129   130   Class java/util/concurrent/RejectedExecutionException

  public io.reactivex.rxjava3.internal.schedulers.ScheduledRunnable scheduleActual(java.lang.Runnable, long, java.util.concurrent.TimeUnit, io.reactivex.rxjava3.disposables.DisposableContainer);
    Code:
       0: aload_1
       1: invokestatic  #9                  // Method io/reactivex/rxjava3/plugins/RxJavaPlugins.onSchedule:(Ljava/lang/Runnable;)Ljava/lang/Runnable;
       4: astore        6
       6: new           #23                 // class io/reactivex/rxjava3/internal/schedulers/ScheduledRunnable
       9: dup
      10: aload         6
      12: aload         5
      14: invokespecial #24                 // Method io/reactivex/rxjava3/internal/schedulers/ScheduledRunnable."<init>":(Ljava/lang/Runnable;Lio/reactivex/rxjava3/disposables/DisposableContainer;)V
      17: astore        7
      19: aload         5
      21: ifnull        39
      24: aload         5
      26: aload         7
      28: invokeinterface #25,  2           // InterfaceMethod io/reactivex/rxjava3/disposables/DisposableContainer.add:(Lio/reactivex/rxjava3/disposables/Disposable;)Z
      33: ifne          39
      36: aload         7
      38: areturn
      39: lload_2
      40: lconst_0
      41: lcmp
      42: ifgt          61
      45: aload_0
      46: getfield      #3                  // Field executor:Ljava/util/concurrent/ScheduledExecutorService;
      49: aload         7
      51: invokeinterface #11,  2           // InterfaceMethod java/util/concurrent/ScheduledExecutorService.submit:(Ljava/util/concurrent/Callable;)Ljava/util/concurrent/Future;
      56: astore        8
      58: goto          77
      61: aload_0
      62: getfield      #3                  // Field executor:Ljava/util/concurrent/ScheduledExecutorService;
      65: aload         7
      67: lload_2
      68: aload         4
      70: invokeinterface #12,  5           // InterfaceMethod java/util/concurrent/ScheduledExecutorService.schedule:(Ljava/util/concurrent/Callable;JLjava/util/concurrent/TimeUnit;)Ljava/util/concurrent/ScheduledFuture;
      75: astore        8
      77: aload         7
      79: aload         8
      81: invokevirtual #26                 // Method io/reactivex/rxjava3/internal/schedulers/ScheduledRunnable.setFuture:(Ljava/util/concurrent/Future;)V
      84: goto          109
      87: astore        9
      89: aload         5
      91: ifnull        104
      94: aload         5
      96: aload         7
      98: invokeinterface #27,  2           // InterfaceMethod io/reactivex/rxjava3/disposables/DisposableContainer.remove:(Lio/reactivex/rxjava3/disposables/Disposable;)Z
     103: pop
     104: aload         9
     106: invokestatic  #15                 // Method io/reactivex/rxjava3/plugins/RxJavaPlugins.onError:(Ljava/lang/Throwable;)V
     109: aload         7
     111: areturn
    Exception table:
       from    to  target type
          39    84    87   Class java/util/concurrent/RejectedExecutionException

  public void dispose();
    Code:
       0: aload_0
       1: getfield      #5                  // Field disposed:Z
       4: ifne          22
       7: aload_0
       8: iconst_1
       9: putfield      #5                  // Field disposed:Z
      12: aload_0
      13: getfield      #3                  // Field executor:Ljava/util/concurrent/ScheduledExecutorService;
      16: invokeinterface #28,  1           // InterfaceMethod java/util/concurrent/ScheduledExecutorService.shutdownNow:()Ljava/util/List;
      21: pop
      22: return

  public void shutdown();
    Code:
       0: aload_0
       1: getfield      #5                  // Field disposed:Z
       4: ifne          21
       7: aload_0
       8: iconst_1
       9: putfield      #5                  // Field disposed:Z
      12: aload_0
      13: getfield      #3                  // Field executor:Ljava/util/concurrent/ScheduledExecutorService;
      16: invokeinterface #29,  1           // InterfaceMethod java/util/concurrent/ScheduledExecutorService.shutdown:()V
      21: return

  public boolean isDisposed();
    Code:
       0: aload_0
       1: getfield      #5                  // Field disposed:Z
       4: ireturn
}
