Compiled from "NewThreadScheduler.java"
public final class io.reactivex.rxjava3.internal.schedulers.NewThreadScheduler extends io.reactivex.rxjava3.core.Scheduler {
  final java.util.concurrent.ThreadFactory threadFactory;

  private static final java.lang.String THREAD_NAME_PREFIX;

  private static final io.reactivex.rxjava3.internal.schedulers.RxThreadFactory THREAD_FACTORY;

  private static final java.lang.String KEY_NEWTHREAD_PRIORITY;

  public io.reactivex.rxjava3.internal.schedulers.NewThreadScheduler();
    Code:
       0: aload_0
       1: getstatic     #1                  // Field THREAD_FACTORY:Lio/reactivex/rxjava3/internal/schedulers/RxThreadFactory;
       4: invokespecial #2                  // Method "<init>":(Ljava/util/concurrent/ThreadFactory;)V
       7: return

  public io.reactivex.rxjava3.internal.schedulers.NewThreadScheduler(java.util.concurrent.ThreadFactory);
    Code:
       0: aload_0
       1: invokespecial #3                  // Method io/reactivex/rxjava3/core/Scheduler."<init>":()V
       4: aload_0
       5: aload_1
       6: putfield      #4                  // Field threadFactory:Ljava/util/concurrent/ThreadFactory;
       9: return

  public io.reactivex.rxjava3.core.Scheduler$Worker createWorker();
    Code:
       0: new           #5                  // class io/reactivex/rxjava3/internal/schedulers/NewThreadWorker
       3: dup
       4: aload_0
       5: getfield      #4                  // Field threadFactory:Ljava/util/concurrent/ThreadFactory;
       8: invokespecial #6                  // Method io/reactivex/rxjava3/internal/schedulers/NewThreadWorker."<init>":(Ljava/util/concurrent/ThreadFactory;)V
      11: areturn

  static {};
    Code:
       0: iconst_1
       1: bipush        10
       3: ldc           #9                  // String rx3.newthread-priority
       5: iconst_5
       6: invokestatic  #10                 // Method java/lang/Integer.getInteger:(Ljava/lang/String;I)Ljava/lang/Integer;
       9: invokevirtual #11                 // Method java/lang/Integer.intValue:()I
      12: invokestatic  #12                 // Method java/lang/Math.min:(II)I
      15: invokestatic  #13                 // Method java/lang/Math.max:(II)I
      18: istore_0
      19: new           #14                 // class io/reactivex/rxjava3/internal/schedulers/RxThreadFactory
      22: dup
      23: ldc           #15                 // String RxNewThreadScheduler
      25: iload_0
      26: invokespecial #16                 // Method io/reactivex/rxjava3/internal/schedulers/RxThreadFactory."<init>":(Ljava/lang/String;I)V
      29: putstatic     #1                  // Field THREAD_FACTORY:Lio/reactivex/rxjava3/internal/schedulers/RxThreadFactory;
      32: return
}
