Compiled from "RxThreadFactory.java"
public final class io.reactivex.rxjava3.internal.schedulers.RxThreadFactory extends java.util.concurrent.atomic.AtomicLong implements java.util.concurrent.ThreadFactory {
  private static final long serialVersionUID;

  final java.lang.String prefix;

  final int priority;

  final boolean nonBlocking;

  public io.reactivex.rxjava3.internal.schedulers.RxThreadFactory(java.lang.String);
    Code:
       0: aload_0
       1: aload_1
       2: iconst_5
       3: iconst_0
       4: invokespecial #2                  // Method "<init>":(Ljava/lang/String;IZ)V
       7: return

  public io.reactivex.rxjava3.internal.schedulers.RxThreadFactory(java.lang.String, int);
    Code:
       0: aload_0
       1: aload_1
       2: iload_2
       3: iconst_0
       4: invokespecial #2                  // Method "<init>":(Ljava/lang/String;IZ)V
       7: return

  public io.reactivex.rxjava3.internal.schedulers.RxThreadFactory(java.lang.String, int, boolean);
    Code:
       0: aload_0
       1: invokespecial #3                  // Method java/util/concurrent/atomic/AtomicLong."<init>":()V
       4: aload_0
       5: aload_1
       6: putfield      #4                  // Field prefix:Ljava/lang/String;
       9: aload_0
      10: iload_2
      11: putfield      #5                  // Field priority:I
      14: aload_0
      15: iload_3
      16: putfield      #6                  // Field nonBlocking:Z
      19: return

  public java.lang.Thread newThread(java.lang.Runnable);
    Code:
       0: new           #7                  // class java/lang/StringBuilder
       3: dup
       4: aload_0
       5: getfield      #4                  // Field prefix:Ljava/lang/String;
       8: invokespecial #8                  // Method java/lang/StringBuilder."<init>":(Ljava/lang/String;)V
      11: bipush        45
      13: invokevirtual #9                  // Method java/lang/StringBuilder.append:(C)Ljava/lang/StringBuilder;
      16: aload_0
      17: invokevirtual #10                 // Method incrementAndGet:()J
      20: invokevirtual #11                 // Method java/lang/StringBuilder.append:(J)Ljava/lang/StringBuilder;
      23: astore_2
      24: aload_2
      25: invokevirtual #12                 // Method java/lang/StringBuilder.toString:()Ljava/lang/String;
      28: astore_3
      29: aload_0
      30: getfield      #6                  // Field nonBlocking:Z
      33: ifeq          48
      36: new           #13                 // class io/reactivex/rxjava3/internal/schedulers/RxThreadFactory$RxCustomThread
      39: dup
      40: aload_1
      41: aload_3
      42: invokespecial #14                 // Method io/reactivex/rxjava3/internal/schedulers/RxThreadFactory$RxCustomThread."<init>":(Ljava/lang/Runnable;Ljava/lang/String;)V
      45: goto          57
      48: new           #1                  // class java/lang/Thread
      51: dup
      52: aload_1
      53: aload_3
      54: invokespecial #15                 // Method java/lang/Thread."<init>":(Ljava/lang/Runnable;Ljava/lang/String;)V
      57: astore        4
      59: aload         4
      61: aload_0
      62: getfield      #5                  // Field priority:I
      65: invokevirtual #16                 // Method java/lang/Thread.setPriority:(I)V
      68: aload         4
      70: iconst_1
      71: invokevirtual #17                 // Method java/lang/Thread.setDaemon:(Z)V
      74: aload         4
      76: areturn

  public java.lang.String toString();
    Code:
       0: new           #7                  // class java/lang/StringBuilder
       3: dup
       4: invokespecial #18                 // Method java/lang/StringBuilder."<init>":()V
       7: ldc           #19                 // String RxThreadFactory[
       9: invokevirtual #20                 // Method java/lang/StringBuilder.append:(Ljava/lang/String;)Ljava/lang/StringBuilder;
      12: aload_0
      13: getfield      #4                  // Field prefix:Ljava/lang/String;
      16: invokevirtual #20                 // Method java/lang/StringBuilder.append:(Ljava/lang/String;)Ljava/lang/StringBuilder;
      19: ldc           #21                 // String ]
      21: invokevirtual #20                 // Method java/lang/StringBuilder.append:(Ljava/lang/String;)Ljava/lang/StringBuilder;
      24: invokevirtual #12                 // Method java/lang/StringBuilder.toString:()Ljava/lang/String;
      27: areturn
}
