Compiled from "SchedulerWhen.java"
final class io.reactivex.rxjava3.internal.schedulers.SchedulerWhen$CreateWorkerFunction$WorkerCompletable extends io.reactivex.rxjava3.core.Completable {
  final io.reactivex.rxjava3.internal.schedulers.SchedulerWhen$ScheduledAction action;

  final io.reactivex.rxjava3.internal.schedulers.SchedulerWhen$CreateWorkerFunction this$0;

  io.reactivex.rxjava3.internal.schedulers.SchedulerWhen$CreateWorkerFunction$WorkerCompletable(io.reactivex.rxjava3.internal.schedulers.SchedulerWhen$CreateWorkerFunction, io.reactivex.rxjava3.internal.schedulers.SchedulerWhen$ScheduledAction);
    Code:
       0: aload_0
       1: aload_1
       2: putfield      #1                  // Field this$0:Lio/reactivex/rxjava3/internal/schedulers/SchedulerWhen$CreateWorkerFunction;
       5: aload_0
       6: invokespecial #2                  // Method io/reactivex/rxjava3/core/Completable."<init>":()V
       9: aload_0
      10: aload_2
      11: putfield      #3                  // Field action:Lio/reactivex/rxjava3/internal/schedulers/SchedulerWhen$ScheduledAction;
      14: return

  protected void subscribeActual(io.reactivex.rxjava3.core.CompletableObserver);
    Code:
       0: aload_1
       1: aload_0
       2: getfield      #3                  // Field action:Lio/reactivex/rxjava3/internal/schedulers/SchedulerWhen$ScheduledAction;
       5: invokeinterface #4,  2            // InterfaceMethod io/reactivex/rxjava3/core/CompletableObserver.onSubscribe:(Lio/reactivex/rxjava3/disposables/Disposable;)V
      10: aload_0
      11: getfield      #3                  // Field action:Lio/reactivex/rxjava3/internal/schedulers/SchedulerWhen$ScheduledAction;
      14: aload_0
      15: getfield      #1                  // Field this$0:Lio/reactivex/rxjava3/internal/schedulers/SchedulerWhen$CreateWorkerFunction;
      18: getfield      #5                  // Field io/reactivex/rxjava3/internal/schedulers/SchedulerWhen$CreateWorkerFunction.actualWorker:Lio/reactivex/rxjava3/core/Scheduler$Worker;
      21: aload_1
      22: invokevirtual #6                  // Method io/reactivex/rxjava3/internal/schedulers/SchedulerWhen$ScheduledAction.call:(Lio/reactivex/rxjava3/core/Scheduler$Worker;Lio/reactivex/rxjava3/core/CompletableObserver;)V
      25: return
}
