Compiled from "SchedulerWhen.java"
abstract class io.reactivex.rxjava3.internal.schedulers.SchedulerWhen$ScheduledAction extends java.util.concurrent.atomic.AtomicReference<io.reactivex.rxjava3.disposables.Disposable> implements io.reactivex.rxjava3.disposables.Disposable {
  io.reactivex.rxjava3.internal.schedulers.SchedulerWhen$ScheduledAction();
    Code:
       0: aload_0
       1: getstatic     #1                  // Field io/reactivex/rxjava3/internal/schedulers/SchedulerWhen.SUBSCRIBED:Lio/reactivex/rxjava3/disposables/Disposable;
       4: invokespecial #2                  // Method java/util/concurrent/atomic/AtomicReference."<init>":(Ljava/lang/Object;)V
       7: return

  void call(io.reactivex.rxjava3.core.Scheduler$Worker, io.reactivex.rxjava3.core.CompletableObserver);
    Code:
       0: aload_0
       1: invokevirtual #3                  // Method get:()Ljava/lang/Object;
       4: checkcast     #4                  // class io/reactivex/rxjava3/disposables/Disposable
       7: astore_3
       8: aload_3
       9: getstatic     #5                  // Field io/reactivex/rxjava3/internal/schedulers/SchedulerWhen.DISPOSED:Lio/reactivex/rxjava3/disposables/Disposable;
      12: if_acmpne     16
      15: return
      16: aload_3
      17: getstatic     #1                  // Field io/reactivex/rxjava3/internal/schedulers/SchedulerWhen.SUBSCRIBED:Lio/reactivex/rxjava3/disposables/Disposable;
      20: if_acmpeq     24
      23: return
      24: aload_0
      25: aload_1
      26: aload_2
      27: invokevirtual #6                  // Method callActual:(Lio/reactivex/rxjava3/core/Scheduler$Worker;Lio/reactivex/rxjava3/core/CompletableObserver;)Lio/reactivex/rxjava3/disposables/Disposable;
      30: astore        4
      32: aload_0
      33: getstatic     #1                  // Field io/reactivex/rxjava3/internal/schedulers/SchedulerWhen.SUBSCRIBED:Lio/reactivex/rxjava3/disposables/Disposable;
      36: aload         4
      38: invokevirtual #7                  // Method compareAndSet:(Ljava/lang/Object;Ljava/lang/Object;)Z
      41: ifne          51
      44: aload         4
      46: invokeinterface #8,  1            // InterfaceMethod io/reactivex/rxjava3/disposables/Disposable.dispose:()V
      51: return

  protected abstract io.reactivex.rxjava3.disposables.Disposable callActual(io.reactivex.rxjava3.core.Scheduler$Worker, io.reactivex.rxjava3.core.CompletableObserver);

  public boolean isDisposed();
    Code:
       0: aload_0
       1: invokevirtual #3                  // Method get:()Ljava/lang/Object;
       4: checkcast     #4                  // class io/reactivex/rxjava3/disposables/Disposable
       7: invokeinterface #9,  1            // InterfaceMethod io/reactivex/rxjava3/disposables/Disposable.isDisposed:()Z
      12: ireturn

  public void dispose();
    Code:
       0: aload_0
       1: getstatic     #5                  // Field io/reactivex/rxjava3/internal/schedulers/SchedulerWhen.DISPOSED:Lio/reactivex/rxjava3/disposables/Disposable;
       4: invokevirtual #10                 // Method getAndSet:(Ljava/lang/Object;)Ljava/lang/Object;
       7: checkcast     #4                  // class io/reactivex/rxjava3/disposables/Disposable
      10: invokeinterface #8,  1            // InterfaceMethod io/reactivex/rxjava3/disposables/Disposable.dispose:()V
      15: return
}
