Compiled from "SchedulerWhen.java"
class io.reactivex.rxjava3.internal.schedulers.SchedulerWhen$OnCompletedAction implements java.lang.Runnable {
  final io.reactivex.rxjava3.core.CompletableObserver actionCompletable;

  final java.lang.Runnable action;

  io.reactivex.rxjava3.internal.schedulers.SchedulerWhen$OnCompletedAction(java.lang.Runnable, io.reactivex.rxjava3.core.CompletableObserver);
    Code:
       0: aload_0
       1: invokespecial #1                  // Method java/lang/Object."<init>":()V
       4: aload_0
       5: aload_1
       6: putfield      #2                  // Field action:Ljava/lang/Runnable;
       9: aload_0
      10: aload_2
      11: putfield      #3                  // Field actionCompletable:Lio/reactivex/rxjava3/core/CompletableObserver;
      14: return

  public void run();
    Code:
       0: aload_0
       1: getfield      #2                  // Field action:Ljava/lang/Runnable;
       4: invokeinterface #4,  1            // InterfaceMethod java/lang/Runnable.run:()V
       9: aload_0
      10: getfield      #3                  // Field actionCompletable:Lio/reactivex/rxjava3/core/CompletableObserver;
      13: invokeinterface #5,  1            // InterfaceMethod io/reactivex/rxjava3/core/CompletableObserver.onComplete:()V
      18: goto          33
      21: astore_1
      22: aload_0
      23: getfield      #3                  // Field actionCompletable:Lio/reactivex/rxjava3/core/CompletableObserver;
      26: invokeinterface #5,  1            // InterfaceMethod io/reactivex/rxjava3/core/CompletableObserver.onComplete:()V
      31: aload_1
      32: athrow
      33: return
    Exception table:
       from    to  target type
           0     9    21   any
}
