Compiled from "SchedulerWhen.java"
class io.reactivex.rxjava3.internal.schedulers.SchedulerWhen$DelayedAction extends io.reactivex.rxjava3.internal.schedulers.SchedulerWhen$ScheduledAction {
  private final java.lang.Runnable action;

  private final long delayTime;

  private final java.util.concurrent.TimeUnit unit;

  io.reactivex.rxjava3.internal.schedulers.SchedulerWhen$DelayedAction(java.lang.Runnable, long, java.util.concurrent.TimeUnit);
    Code:
       0: aload_0
       1: invokespecial #1                  // Method io/reactivex/rxjava3/internal/schedulers/SchedulerWhen$ScheduledAction."<init>":()V
       4: aload_0
       5: aload_1
       6: putfield      #2                  // Field action:Ljava/lang/Runnable;
       9: aload_0
      10: lload_2
      11: putfield      #3                  // Field delayTime:J
      14: aload_0
      15: aload         4
      17: putfield      #4                  // Field unit:Ljava/util/concurrent/TimeUnit;
      20: return

  protected io.reactivex.rxjava3.disposables.Disposable callActual(io.reactivex.rxjava3.core.Scheduler$Worker, io.reactivex.rxjava3.core.CompletableObserver);
    Code:
       0: aload_1
       1: new           #5                  // class io/reactivex/rxjava3/internal/schedulers/SchedulerWhen$OnCompletedAction
       4: dup
       5: aload_0
       6: getfield      #2                  // Field action:Ljava/lang/Runnable;
       9: aload_2
      10: invokespecial #6                  // Method io/reactivex/rxjava3/internal/schedulers/SchedulerWhen$OnCompletedAction."<init>":(Ljava/lang/Runnable;Lio/reactivex/rxjava3/core/CompletableObserver;)V
      13: aload_0
      14: getfield      #3                  // Field delayTime:J
      17: aload_0
      18: getfield      #4                  // Field unit:Ljava/util/concurrent/TimeUnit;
      21: invokevirtual #7                  // Method io/reactivex/rxjava3/core/Scheduler$Worker.schedule:(Ljava/lang/Runnable;JLjava/util/concurrent/TimeUnit;)Lio/reactivex/rxjava3/disposables/Disposable;
      24: areturn
}
