Compiled from "SchedulerPoolFactory.java"
final class io.reactivex.rxjava3.internal.schedulers.SchedulerPoolFactory$SystemPropertyAccessor implements io.reactivex.rxjava3.functions.Function<java.lang.String, java.lang.String> {
  io.reactivex.rxjava3.internal.schedulers.SchedulerPoolFactory$SystemPropertyAccessor();
    Code:
       0: aload_0
       1: invokespecial #1                  // Method java/lang/Object."<init>":()V
       4: return

  public java.lang.String apply(java.lang.String);
    Code:
       0: aload_1
       1: invokestatic  #2                  // Method java/lang/System.getProperty:(Ljava/lang/String;)Ljava/lang/String;
       4: areturn

  public java.lang.Object apply(java.lang.Object) throws java.lang.Throwable;
    Code:
       0: aload_0
       1: aload_1
       2: checkcast     #3                  // class java/lang/String
       5: invokevirtual #4                  // Method apply:(Ljava/lang/String;)Ljava/lang/String;
       8: areturn
}
