Compiled from "SchedulerPoolFactory.java"
public final class io.reactivex.rxjava3.internal.schedulers.SchedulerPoolFactory {
  static final java.lang.String PURGE_ENABLED_KEY;

  public static final boolean PURGE_ENABLED;

  private io.reactivex.rxjava3.internal.schedulers.SchedulerPoolFactory();
    Code:
       0: aload_0
       1: invokespecial #1                  // Method java/lang/Object."<init>":()V
       4: new           #2                  // class java/lang/IllegalStateException
       7: dup
       8: ldc           #3                  // String No instances!
      10: invokespecial #4                  // Method java/lang/IllegalStateException."<init>":(Ljava/lang/String;)V
      13: athrow

  static boolean getBooleanProperty(boolean, java.lang.String, boolean, boolean, io.reactivex.rxjava3.functions.Function<java.lang.String, java.lang.String>);
    Code:
       0: iload_0
       1: ifeq          41
       4: aload         4
       6: aload_1
       7: invokeinterface #5,  2            // InterfaceMethod io/reactivex/rxjava3/functions/Function.apply:(Ljava/lang/Object;)Ljava/lang/Object;
      12: checkcast     #6                  // class java/lang/String
      15: astore        5
      17: aload         5
      19: ifnonnull     24
      22: iload_2
      23: ireturn
      24: ldc           #7                  // String true
      26: aload         5
      28: invokevirtual #8                  // Method java/lang/String.equals:(Ljava/lang/Object;)Z
      31: ireturn
      32: astore        5
      34: aload         5
      36: invokestatic  #10                 // Method io/reactivex/rxjava3/exceptions/Exceptions.throwIfFatal:(Ljava/lang/Throwable;)V
      39: iload_2
      40: ireturn
      41: iload_3
      42: ireturn
    Exception table:
       from    to  target type
           4    23    32   Class java/lang/Throwable
          24    31    32   Class java/lang/Throwable

  public static java.util.concurrent.ScheduledExecutorService create(java.util.concurrent.ThreadFactory);
    Code:
       0: new           #11                 // class java/util/concurrent/ScheduledThreadPoolExecutor
       3: dup
       4: iconst_1
       5: aload_0
       6: invokespecial #12                 // Method java/util/concurrent/ScheduledThreadPoolExecutor."<init>":(ILjava/util/concurrent/ThreadFactory;)V
       9: astore_1
      10: aload_1
      11: getstatic     #13                 // Field PURGE_ENABLED:Z
      14: invokevirtual #14                 // Method java/util/concurrent/ScheduledThreadPoolExecutor.setRemoveOnCancelPolicy:(Z)V
      17: aload_1
      18: areturn

  static {};
    Code:
       0: new           #15                 // class io/reactivex/rxjava3/internal/schedulers/SchedulerPoolFactory$SystemPropertyAccessor
       3: dup
       4: invokespecial #16                 // Method io/reactivex/rxjava3/internal/schedulers/SchedulerPoolFactory$SystemPropertyAccessor."<init>":()V
       7: astore_0
       8: iconst_1
       9: ldc           #18                 // String rx3.purge-enabled
      11: iconst_1
      12: iconst_1
      13: aload_0
      14: invokestatic  #19                 // Method getBooleanProperty:(ZLjava/lang/String;ZZLio/reactivex/rxjava3/functions/Function;)Z
      17: putstatic     #13                 // Field PURGE_ENABLED:Z
      20: return
}
