Compiled from "SchedulerWhen.java"
final class io.reactivex.rxjava3.internal.schedulers.SchedulerWhen$QueueWorker extends io.reactivex.rxjava3.core.Scheduler$Worker {
  private final java.util.concurrent.atomic.AtomicBoolean unsubscribed;

  private final io.reactivex.rxjava3.processors.FlowableProcessor<io.reactivex.rxjava3.internal.schedulers.SchedulerWhen$ScheduledAction> actionProcessor;

  private final io.reactivex.rxjava3.core.Scheduler$Worker actualWorker;

  io.reactivex.rxjava3.internal.schedulers.SchedulerWhen$QueueWorker(io.reactivex.rxjava3.processors.FlowableProcessor<io.reactivex.rxjava3.internal.schedulers.SchedulerWhen$ScheduledAction>, io.reactivex.rxjava3.core.Scheduler$Worker);
    Code:
       0: aload_0
       1: invokespecial #1                  // Method io/reactivex/rxjava3/core/Scheduler$Worker."<init>":()V
       4: aload_0
       5: aload_1
       6: putfield      #2                  // Field actionProcessor:Lio/reactivex/rxjava3/processors/FlowableProcessor;
       9: aload_0
      10: aload_2
      11: putfield      #3                  // Field actualWorker:Lio/reactivex/rxjava3/core/Scheduler$Worker;
      14: aload_0
      15: new           #4                  // class java/util/concurrent/atomic/AtomicBoolean
      18: dup
      19: invokespecial #5                  // Method java/util/concurrent/atomic/AtomicBoolean."<init>":()V
      22: putfield      #6                  // Field unsubscribed:Ljava/util/concurrent/atomic/AtomicBoolean;
      25: return

  public void dispose();
    Code:
       0: aload_0
       1: getfield      #6                  // Field unsubscribed:Ljava/util/concurrent/atomic/AtomicBoolean;
       4: iconst_0
       5: iconst_1
       6: invokevirtual #7                  // Method java/util/concurrent/atomic/AtomicBoolean.compareAndSet:(ZZ)Z
       9: ifeq          26
      12: aload_0
      13: getfield      #2                  // Field actionProcessor:Lio/reactivex/rxjava3/processors/FlowableProcessor;
      16: invokevirtual #8                  // Method io/reactivex/rxjava3/processors/FlowableProcessor.onComplete:()V
      19: aload_0
      20: getfield      #3                  // Field actualWorker:Lio/reactivex/rxjava3/core/Scheduler$Worker;
      23: invokevirtual #9                  // Method io/reactivex/rxjava3/core/Scheduler$Worker.dispose:()V
      26: return

  public boolean isDisposed();
    Code:
       0: aload_0
       1: getfield      #6                  // Field unsubscribed:Ljava/util/concurrent/atomic/AtomicBoolean;
       4: invokevirtual #10                 // Method java/util/concurrent/atomic/AtomicBoolean.get:()Z
       7: ireturn

  public io.reactivex.rxjava3.disposables.Disposable schedule(java.lang.Runnable, long, java.util.concurrent.TimeUnit);
    Code:
       0: new           #11                 // class io/reactivex/rxjava3/internal/schedulers/SchedulerWhen$DelayedAction
       3: dup
       4: aload_1
       5: lload_2
       6: aload         4
       8: invokespecial #12                 // Method io/reactivex/rxjava3/internal/schedulers/SchedulerWhen$DelayedAction."<init>":(Ljava/lang/Runnable;JLjava/util/concurrent/TimeUnit;)V
      11: astore        5
      13: aload_0
      14: getfield      #2                  // Field actionProcessor:Lio/reactivex/rxjava3/processors/FlowableProcessor;
      17: aload         5
      19: invokevirtual #13                 // Method io/reactivex/rxjava3/processors/FlowableProcessor.onNext:(Ljava/lang/Object;)V
      22: aload         5
      24: areturn

  public io.reactivex.rxjava3.disposables.Disposable schedule(java.lang.Runnable);
    Code:
       0: new           #14                 // class io/reactivex/rxjava3/internal/schedulers/SchedulerWhen$ImmediateAction
       3: dup
       4: aload_1
       5: invokespecial #15                 // Method io/reactivex/rxjava3/internal/schedulers/SchedulerWhen$ImmediateAction."<init>":(Ljava/lang/Runnable;)V
       8: astore_2
       9: aload_0
      10: getfield      #2                  // Field actionProcessor:Lio/reactivex/rxjava3/processors/FlowableProcessor;
      13: aload_2
      14: invokevirtual #13                 // Method io/reactivex/rxjava3/processors/FlowableProcessor.onNext:(Ljava/lang/Object;)V
      17: aload_2
      18: areturn
}
