Compiled from "SchedulerWhen.java"
final class io.reactivex.rxjava3.internal.schedulers.SchedulerWhen$CreateWorkerFunction implements io.reactivex.rxjava3.functions.Function<io.reactivex.rxjava3.internal.schedulers.SchedulerWhen$ScheduledAction, io.reactivex.rxjava3.core.Completable> {
  final io.reactivex.rxjava3.core.Scheduler$Worker actualWorker;

  io.reactivex.rxjava3.internal.schedulers.SchedulerWhen$CreateWorkerFunction(io.reactivex.rxjava3.core.Scheduler$Worker);
    Code:
       0: aload_0
       1: invokespecial #1                  // Method java/lang/Object."<init>":()V
       4: aload_0
       5: aload_1
       6: putfield      #2                  // Field actualWorker:Lio/reactivex/rxjava3/core/Scheduler$Worker;
       9: return

  public io.reactivex.rxjava3.core.Completable apply(io.reactivex.rxjava3.internal.schedulers.SchedulerWhen$ScheduledAction);
    Code:
       0: new           #3                  // class io/reactivex/rxjava3/internal/schedulers/SchedulerWhen$CreateWorkerFunction$WorkerCompletable
       3: dup
       4: aload_0
       5: aload_1
       6: invokespecial #4                  // Method io/reactivex/rxjava3/internal/schedulers/SchedulerWhen$CreateWorkerFunction$WorkerCompletable."<init>":(Lio/reactivex/rxjava3/internal/schedulers/SchedulerWhen$CreateWorkerFunction;Lio/reactivex/rxjava3/internal/schedulers/SchedulerWhen$ScheduledAction;)V
       9: areturn

  public java.lang.Object apply(java.lang.Object) throws java.lang.Throwable;
    Code:
       0: aload_0
       1: aload_1
       2: checkcast     #5                  // class io/reactivex/rxjava3/internal/schedulers/SchedulerWhen$ScheduledAction
       5: invokevirtual #6                  // Method apply:(Lio/reactivex/rxjava3/internal/schedulers/SchedulerWhen$ScheduledAction;)Lio/reactivex/rxjava3/core/Completable;
       8: areturn
}
