Compiled from "ScheduledDirectTask.java"
public final class io.reactivex.rxjava3.internal.schedulers.ScheduledDirectTask extends io.reactivex.rxjava3.internal.schedulers.AbstractDirectTask implements java.util.concurrent.Callable<java.lang.Void> {
  private static final long serialVersionUID;

  public io.reactivex.rxjava3.internal.schedulers.ScheduledDirectTask(java.lang.Runnable, boolean);
    Code:
       0: aload_0
       1: aload_1
       2: iload_2
       3: invokespecial #1                  // Method io/reactivex/rxjava3/internal/schedulers/AbstractDirectTask."<init>":(Ljava/lang/Runnable;Z)V
       6: return

  public java.lang.Void call();
    Code:
       0: aload_0
       1: invokestatic  #2                  // Method java/lang/Thread.currentThread:()Ljava/lang/Thread;
       4: putfield      #3                  // Field runner:Ljava/lang/Thread;
       7: aload_0
       8: getfield      #4                  // Field runnable:Ljava/lang/Runnable;
      11: invokeinterface #5,  1            // InterfaceMethod java/lang/Runnable.run:()V
      16: aload_0
      17: getstatic     #6                  // Field FINISHED:Ljava/util/concurrent/FutureTask;
      20: invokevirtual #7                  // Method lazySet:(Ljava/lang/Object;)V
      23: aload_0
      24: aconst_null
      25: putfield      #3                  // Field runner:Ljava/lang/Thread;
      28: goto          46
      31: astore_1
      32: aload_0
      33: getstatic     #6                  // Field FINISHED:Ljava/util/concurrent/FutureTask;
      36: invokevirtual #7                  // Method lazySet:(Ljava/lang/Object;)V
      39: aload_0
      40: aconst_null
      41: putfield      #3                  // Field runner:Ljava/lang/Thread;
      44: aload_1
      45: athrow
      46: goto          56
      49: astore_1
      50: aload_1
      51: invokestatic  #9                  // Method io/reactivex/rxjava3/plugins/RxJavaPlugins.onError:(Ljava/lang/Throwable;)V
      54: aload_1
      55: athrow
      56: aconst_null
      57: areturn
    Exception table:
       from    to  target type
           7    16    31   any
           7    46    49   Class java/lang/Throwable

  public java.lang.String toString();
    Code:
       0: aload_0
       1: invokespecial #10                 // Method io/reactivex/rxjava3/internal/schedulers/AbstractDirectTask.toString:()Ljava/lang/String;
       4: areturn

  public java.lang.Runnable getWrappedRunnable();
    Code:
       0: aload_0
       1: invokespecial #11                 // Method io/reactivex/rxjava3/internal/schedulers/AbstractDirectTask.getWrappedRunnable:()Ljava/lang/Runnable;
       4: areturn

  public java.lang.Object call() throws java.lang.Exception;
    Code:
       0: aload_0
       1: invokevirtual #12                 // Method call:()Ljava/lang/Void;
       4: areturn
}
