Compiled from "SingleScheduler.java"
public final class io.reactivex.rxjava3.internal.schedulers.SingleScheduler extends io.reactivex.rxjava3.core.Scheduler {
  final java.util.concurrent.ThreadFactory threadFactory;

  final java.util.concurrent.atomic.AtomicReference<java.util.concurrent.ScheduledExecutorService> executor;

  private static final java.lang.String KEY_SINGLE_PRIORITY;

  private static final java.lang.String THREAD_NAME_PREFIX;

  static final io.reactivex.rxjava3.internal.schedulers.RxThreadFactory SINGLE_THREAD_FACTORY;

  static final java.util.concurrent.ScheduledExecutorService SHUTDOWN;

  public io.reactivex.rxjava3.internal.schedulers.SingleScheduler();
    Code:
       0: aload_0
       1: getstatic     #1                  // Field SINGLE_THREAD_FACTORY:Lio/reactivex/rxjava3/internal/schedulers/RxThreadFactory;
       4: invokespecial #2                  // Method "<init>":(Ljava/util/concurrent/ThreadFactory;)V
       7: return

  public io.reactivex.rxjava3.internal.schedulers.SingleScheduler(java.util.concurrent.ThreadFactory);
    Code:
       0: aload_0
       1: invokespecial #3                  // Method io/reactivex/rxjava3/core/Scheduler."<init>":()V
       4: aload_0
       5: new           #4                  // class java/util/concurrent/atomic/AtomicReference
       8: dup
       9: invokespecial #5                  // Method java/util/concurrent/atomic/AtomicReference."<init>":()V
      12: putfield      #6                  // Field executor:Ljava/util/concurrent/atomic/AtomicReference;
      15: aload_0
      16: aload_1
      17: putfield      #7                  // Field threadFactory:Ljava/util/concurrent/ThreadFactory;
      20: aload_0
      21: getfield      #6                  // Field executor:Ljava/util/concurrent/atomic/AtomicReference;
      24: aload_1
      25: invokestatic  #8                  // Method createExecutor:(Ljava/util/concurrent/ThreadFactory;)Ljava/util/concurrent/ScheduledExecutorService;
      28: invokevirtual #9                  // Method java/util/concurrent/atomic/AtomicReference.lazySet:(Ljava/lang/Object;)V
      31: return

  static java.util.concurrent.ScheduledExecutorService createExecutor(java.util.concurrent.ThreadFactory);
    Code:
       0: aload_0
       1: invokestatic  #10                 // Method io/reactivex/rxjava3/internal/schedulers/SchedulerPoolFactory.create:(Ljava/util/concurrent/ThreadFactory;)Ljava/util/concurrent/ScheduledExecutorService;
       4: areturn

  public void start();
    Code:
       0: aconst_null
       1: astore_1
       2: aload_0
       3: getfield      #6                  // Field executor:Ljava/util/concurrent/atomic/AtomicReference;
       6: invokevirtual #11                 // Method java/util/concurrent/atomic/AtomicReference.get:()Ljava/lang/Object;
       9: checkcast     #12                 // class java/util/concurrent/ScheduledExecutorService
      12: astore_2
      13: aload_2
      14: getstatic     #13                 // Field SHUTDOWN:Ljava/util/concurrent/ScheduledExecutorService;
      17: if_acmpeq     31
      20: aload_1
      21: ifnull        30
      24: aload_1
      25: invokeinterface #14,  1           // InterfaceMethod java/util/concurrent/ScheduledExecutorService.shutdown:()V
      30: return
      31: aload_1
      32: ifnonnull     43
      35: aload_0
      36: getfield      #7                  // Field threadFactory:Ljava/util/concurrent/ThreadFactory;
      39: invokestatic  #8                  // Method createExecutor:(Ljava/util/concurrent/ThreadFactory;)Ljava/util/concurrent/ScheduledExecutorService;
      42: astore_1
      43: aload_0
      44: getfield      #6                  // Field executor:Ljava/util/concurrent/atomic/AtomicReference;
      47: aload_2
      48: aload_1
      49: invokevirtual #15                 // Method java/util/concurrent/atomic/AtomicReference.compareAndSet:(Ljava/lang/Object;Ljava/lang/Object;)Z
      52: ifeq          56
      55: return
      56: goto          2

  public void shutdown();
    Code:
       0: aload_0
       1: getfield      #6                  // Field executor:Ljava/util/concurrent/atomic/AtomicReference;
       4: getstatic     #13                 // Field SHUTDOWN:Ljava/util/concurrent/ScheduledExecutorService;
       7: invokevirtual #16                 // Method java/util/concurrent/atomic/AtomicReference.getAndSet:(Ljava/lang/Object;)Ljava/lang/Object;
      10: checkcast     #12                 // class java/util/concurrent/ScheduledExecutorService
      13: astore_1
      14: aload_1
      15: getstatic     #13                 // Field SHUTDOWN:Ljava/util/concurrent/ScheduledExecutorService;
      18: if_acmpeq     28
      21: aload_1
      22: invokeinterface #17,  1           // InterfaceMethod java/util/concurrent/ScheduledExecutorService.shutdownNow:()Ljava/util/List;
      27: pop
      28: return

  public io.reactivex.rxjava3.core.Scheduler$Worker createWorker();
    Code:
       0: new           #18                 // class io/reactivex/rxjava3/internal/schedulers/SingleScheduler$ScheduledWorker
       3: dup
       4: aload_0
       5: getfield      #6                  // Field executor:Ljava/util/concurrent/atomic/AtomicReference;
       8: invokevirtual #11                 // Method java/util/concurrent/atomic/AtomicReference.get:()Ljava/lang/Object;
      11: checkcast     #12                 // class java/util/concurrent/ScheduledExecutorService
      14: invokespecial #19                 // Method io/reactivex/rxjava3/internal/schedulers/SingleScheduler$ScheduledWorker."<init>":(Ljava/util/concurrent/ScheduledExecutorService;)V
      17: areturn

  public io.reactivex.rxjava3.disposables.Disposable scheduleDirect(java.lang.Runnable, long, java.util.concurrent.TimeUnit);
    Code:
       0: new           #20                 // class io/reactivex/rxjava3/internal/schedulers/ScheduledDirectTask
       3: dup
       4: aload_1
       5: invokestatic  #21                 // Method io/reactivex/rxjava3/plugins/RxJavaPlugins.onSchedule:(Ljava/lang/Runnable;)Ljava/lang/Runnable;
       8: iconst_1
       9: invokespecial #22                 // Method io/reactivex/rxjava3/internal/schedulers/ScheduledDirectTask."<init>":(Ljava/lang/Runnable;Z)V
      12: astore        5
      14: lload_2
      15: lconst_0
      16: lcmp
      17: ifgt          42
      20: aload_0
      21: getfield      #6                  // Field executor:Ljava/util/concurrent/atomic/AtomicReference;
      24: invokevirtual #11                 // Method java/util/concurrent/atomic/AtomicReference.get:()Ljava/lang/Object;
      27: checkcast     #12                 // class java/util/concurrent/ScheduledExecutorService
      30: aload         5
      32: invokeinterface #23,  2           // InterfaceMethod java/util/concurrent/ScheduledExecutorService.submit:(Ljava/util/concurrent/Callable;)Ljava/util/concurrent/Future;
      37: astore        6
      39: goto          64
      42: aload_0
      43: getfield      #6                  // Field executor:Ljava/util/concurrent/atomic/AtomicReference;
      46: invokevirtual #11                 // Method java/util/concurrent/atomic/AtomicReference.get:()Ljava/lang/Object;
      49: checkcast     #12                 // class java/util/concurrent/ScheduledExecutorService
      52: aload         5
      54: lload_2
      55: aload         4
      57: invokeinterface #24,  5           // InterfaceMethod java/util/concurrent/ScheduledExecutorService.schedule:(Ljava/util/concurrent/Callable;JLjava/util/concurrent/TimeUnit;)Ljava/util/concurrent/ScheduledFuture;
      62: astore        6
      64: aload         5
      66: aload         6
      68: invokevirtual #25                 // Method io/reactivex/rxjava3/internal/schedulers/ScheduledDirectTask.setFuture:(Ljava/util/concurrent/Future;)V
      71: aload         5
      73: areturn
      74: astore        6
      76: aload         6
      78: invokestatic  #27                 // Method io/reactivex/rxjava3/plugins/RxJavaPlugins.onError:(Ljava/lang/Throwable;)V
      81: getstatic     #28                 // Field io/reactivex/rxjava3/internal/disposables/EmptyDisposable.INSTANCE:Lio/reactivex/rxjava3/internal/disposables/EmptyDisposable;
      84: areturn
    Exception table:
       from    to  target type
          14    73    74   Class java/util/concurrent/RejectedExecutionException

  public io.reactivex.rxjava3.disposables.Disposable schedulePeriodicallyDirect(java.lang.Runnable, long, long, java.util.concurrent.TimeUnit);
    Code:
       0: aload_1
       1: invokestatic  #21                 // Method io/reactivex/rxjava3/plugins/RxJavaPlugins.onSchedule:(Ljava/lang/Runnable;)Ljava/lang/Runnable;
       4: astore        7
       6: lload         4
       8: lconst_0
       9: lcmp
      10: ifgt          96
      13: aload_0
      14: getfield      #6                  // Field executor:Ljava/util/concurrent/atomic/AtomicReference;
      17: invokevirtual #11                 // Method java/util/concurrent/atomic/AtomicReference.get:()Ljava/lang/Object;
      20: checkcast     #12                 // class java/util/concurrent/ScheduledExecutorService
      23: astore        8
      25: new           #29                 // class io/reactivex/rxjava3/internal/schedulers/InstantPeriodicTask
      28: dup
      29: aload         7
      31: aload         8
      33: invokespecial #30                 // Method io/reactivex/rxjava3/internal/schedulers/InstantPeriodicTask."<init>":(Ljava/lang/Runnable;Ljava/util/concurrent/ExecutorService;)V
      36: astore        9
      38: lload_2
      39: lconst_0
      40: lcmp
      41: ifgt          58
      44: aload         8
      46: aload         9
      48: invokeinterface #23,  2           // InterfaceMethod java/util/concurrent/ScheduledExecutorService.submit:(Ljava/util/concurrent/Callable;)Ljava/util/concurrent/Future;
      53: astore        10
      55: goto          72
      58: aload         8
      60: aload         9
      62: lload_2
      63: aload         6
      65: invokeinterface #24,  5           // InterfaceMethod java/util/concurrent/ScheduledExecutorService.schedule:(Ljava/util/concurrent/Callable;JLjava/util/concurrent/TimeUnit;)Ljava/util/concurrent/ScheduledFuture;
      70: astore        10
      72: aload         9
      74: aload         10
      76: invokevirtual #31                 // Method io/reactivex/rxjava3/internal/schedulers/InstantPeriodicTask.setFirst:(Ljava/util/concurrent/Future;)V
      79: goto          93
      82: astore        11
      84: aload         11
      86: invokestatic  #27                 // Method io/reactivex/rxjava3/plugins/RxJavaPlugins.onError:(Ljava/lang/Throwable;)V
      89: getstatic     #28                 // Field io/reactivex/rxjava3/internal/disposables/EmptyDisposable.INSTANCE:Lio/reactivex/rxjava3/internal/disposables/EmptyDisposable;
      92: areturn
      93: aload         9
      95: areturn
      96: new           #32                 // class io/reactivex/rxjava3/internal/schedulers/ScheduledDirectPeriodicTask
      99: dup
     100: aload         7
     102: iconst_1
     103: invokespecial #33                 // Method io/reactivex/rxjava3/internal/schedulers/ScheduledDirectPeriodicTask."<init>":(Ljava/lang/Runnable;Z)V
     106: astore        8
     108: aload_0
     109: getfield      #6                  // Field executor:Ljava/util/concurrent/atomic/AtomicReference;
     112: invokevirtual #11                 // Method java/util/concurrent/atomic/AtomicReference.get:()Ljava/lang/Object;
     115: checkcast     #12                 // class java/util/concurrent/ScheduledExecutorService
     118: aload         8
     120: lload_2
     121: lload         4
     123: aload         6
     125: invokeinterface #34,  7           // InterfaceMethod java/util/concurrent/ScheduledExecutorService.scheduleAtFixedRate:(Ljava/lang/Runnable;JJLjava/util/concurrent/TimeUnit;)Ljava/util/concurrent/ScheduledFuture;
     130: astore        9
     132: aload         8
     134: aload         9
     136: invokevirtual #35                 // Method io/reactivex/rxjava3/internal/schedulers/ScheduledDirectPeriodicTask.setFuture:(Ljava/util/concurrent/Future;)V
     139: aload         8
     141: areturn
     142: astore        9
     144: aload         9
     146: invokestatic  #27                 // Method io/reactivex/rxjava3/plugins/RxJavaPlugins.onError:(Ljava/lang/Throwable;)V
     149: getstatic     #28                 // Field io/reactivex/rxjava3/internal/disposables/EmptyDisposable.INSTANCE:Lio/reactivex/rxjava3/internal/disposables/EmptyDisposable;
     152: areturn
    Exception table:
       from    to  target type
          38    79    82   Class java/util/concurrent/RejectedExecutionException
         108   141   142   Class java/util/concurrent/RejectedExecutionException

  static {};
    Code:
       0: iconst_0
       1: invokestatic  #36                 // Method java/util/concurrent/Executors.newScheduledThreadPool:(I)Ljava/util/concurrent/ScheduledExecutorService;
       4: putstatic     #13                 // Field SHUTDOWN:Ljava/util/concurrent/ScheduledExecutorService;
       7: getstatic     #13                 // Field SHUTDOWN:Ljava/util/concurrent/ScheduledExecutorService;
      10: invokeinterface #14,  1           // InterfaceMethod java/util/concurrent/ScheduledExecutorService.shutdown:()V
      15: iconst_1
      16: bipush        10
      18: ldc           #39                 // String rx3.single-priority
      20: iconst_5
      21: invokestatic  #40                 // Method java/lang/Integer.getInteger:(Ljava/lang/String;I)Ljava/lang/Integer;
      24: invokevirtual #41                 // Method java/lang/Integer.intValue:()I
      27: invokestatic  #42                 // Method java/lang/Math.min:(II)I
      30: invokestatic  #43                 // Method java/lang/Math.max:(II)I
      33: istore_0
      34: new           #44                 // class io/reactivex/rxjava3/internal/schedulers/RxThreadFactory
      37: dup
      38: ldc           #45                 // String RxSingleScheduler
      40: iload_0
      41: iconst_1
      42: invokespecial #46                 // Method io/reactivex/rxjava3/internal/schedulers/RxThreadFactory."<init>":(Ljava/lang/String;IZ)V
      45: putstatic     #1                  // Field SINGLE_THREAD_FACTORY:Lio/reactivex/rxjava3/internal/schedulers/RxThreadFactory;
      48: return
}
