Compiled from "TrampolineScheduler.java"
final class io.reactivex.rxjava3.internal.schedulers.TrampolineScheduler$TimedRunnable implements java.lang.Comparable<io.reactivex.rxjava3.internal.schedulers.TrampolineScheduler$TimedRunnable> {
  final java.lang.Runnable run;

  final long execTime;

  final int count;

  volatile boolean disposed;

  io.reactivex.rxjava3.internal.schedulers.TrampolineScheduler$TimedRunnable(java.lang.Runnable, java.lang.Long, int);
    Code:
       0: aload_0
       1: invokespecial #1                  // Method java/lang/Object."<init>":()V
       4: aload_0
       5: aload_1
       6: putfield      #2                  // Field run:Ljava/lang/Runnable;
       9: aload_0
      10: aload_2
      11: invokevirtual #3                  // Method java/lang/Long.longValue:()J
      14: putfield      #4                  // Field execTime:J
      17: aload_0
      18: iload_3
      19: putfield      #5                  // Field count:I
      22: return

  public int compareTo(io.reactivex.rxjava3.internal.schedulers.TrampolineScheduler$TimedRunnable);
    Code:
       0: aload_0
       1: getfield      #4                  // Field execTime:J
       4: aload_1
       5: getfield      #4                  // Field execTime:J
       8: invokestatic  #6                  // Method java/lang/Long.compare:(JJ)I
      11: istore_2
      12: iload_2
      13: ifne          28
      16: aload_0
      17: getfield      #5                  // Field count:I
      20: aload_1
      21: getfield      #5                  // Field count:I
      24: invokestatic  #7                  // Method java/lang/Integer.compare:(II)I
      27: ireturn
      28: iload_2
      29: ireturn

  public int compareTo(java.lang.Object);
    Code:
       0: aload_0
       1: aload_1
       2: checkcast     #8                  // class io/reactivex/rxjava3/internal/schedulers/TrampolineScheduler$TimedRunnable
       5: invokevirtual #9                  // Method compareTo:(Lio/reactivex/rxjava3/internal/schedulers/TrampolineScheduler$TimedRunnable;)I
       8: ireturn
}
