Compiled from "TrampolineScheduler.java"
final class io.reactivex.rxjava3.internal.schedulers.TrampolineScheduler$TrampolineWorker$AppendToQueueTask implements java.lang.Runnable {
  final io.reactivex.rxjava3.internal.schedulers.TrampolineScheduler$TimedRunnable timedRunnable;

  final io.reactivex.rxjava3.internal.schedulers.TrampolineScheduler$TrampolineWorker this$0;

  io.reactivex.rxjava3.internal.schedulers.TrampolineScheduler$TrampolineWorker$AppendToQueueTask(io.reactivex.rxjava3.internal.schedulers.TrampolineScheduler$TrampolineWorker, io.reactivex.rxjava3.internal.schedulers.TrampolineScheduler$TimedRunnable);
    Code:
       0: aload_0
       1: aload_1
       2: putfield      #1                  // Field this$0:Lio/reactivex/rxjava3/internal/schedulers/TrampolineScheduler$TrampolineWorker;
       5: aload_0
       6: invokespecial #2                  // Method java/lang/Object."<init>":()V
       9: aload_0
      10: aload_2
      11: putfield      #3                  // Field timedRunnable:Lio/reactivex/rxjava3/internal/schedulers/TrampolineScheduler$TimedRunnable;
      14: return

  public void run();
    Code:
       0: aload_0
       1: getfield      #3                  // Field timedRunnable:Lio/reactivex/rxjava3/internal/schedulers/TrampolineScheduler$TimedRunnable;
       4: iconst_1
       5: putfield      #4                  // Field io/reactivex/rxjava3/internal/schedulers/TrampolineScheduler$TimedRunnable.disposed:Z
       8: aload_0
       9: getfield      #1                  // Field this$0:Lio/reactivex/rxjava3/internal/schedulers/TrampolineScheduler$TrampolineWorker;
      12: getfield      #5                  // Field io/reactivex/rxjava3/internal/schedulers/TrampolineScheduler$TrampolineWorker.queue:Ljava/util/concurrent/PriorityBlockingQueue;
      15: aload_0
      16: getfield      #3                  // Field timedRunnable:Lio/reactivex/rxjava3/internal/schedulers/TrampolineScheduler$TimedRunnable;
      19: invokevirtual #6                  // Method java/util/concurrent/PriorityBlockingQueue.remove:(Ljava/lang/Object;)Z
      22: pop
      23: return
}
