Compiled from "TrampolineScheduler.java"
public final class io.reactivex.rxjava3.internal.schedulers.TrampolineScheduler extends io.reactivex.rxjava3.core.Scheduler {
  private static final io.reactivex.rxjava3.internal.schedulers.TrampolineScheduler INSTANCE;

  public static io.reactivex.rxjava3.internal.schedulers.TrampolineScheduler instance();
    Code:
       0: getstatic     #1                  // Field INSTANCE:Lio/reactivex/rxjava3/internal/schedulers/TrampolineScheduler;
       3: areturn

  public io.reactivex.rxjava3.core.Scheduler$Worker createWorker();
    Code:
       0: new           #2                  // class io/reactivex/rxjava3/internal/schedulers/TrampolineScheduler$TrampolineWorker
       3: dup
       4: invokespecial #3                  // Method io/reactivex/rxjava3/internal/schedulers/TrampolineScheduler$TrampolineWorker."<init>":()V
       7: areturn

  io.reactivex.rxjava3.internal.schedulers.TrampolineScheduler();
    Code:
       0: aload_0
       1: invokespecial #4                  // Method io/reactivex/rxjava3/core/Scheduler."<init>":()V
       4: return

  public io.reactivex.rxjava3.disposables.Disposable scheduleDirect(java.lang.Runnable);
    Code:
       0: aload_1
       1: invokestatic  #5                  // Method io/reactivex/rxjava3/plugins/RxJavaPlugins.onSchedule:(Ljava/lang/Runnable;)Ljava/lang/Runnable;
       4: invokeinterface #6,  1            // InterfaceMethod java/lang/Runnable.run:()V
       9: getstatic     #7                  // Field io/reactivex/rxjava3/internal/disposables/EmptyDisposable.INSTANCE:Lio/reactivex/rxjava3/internal/disposables/EmptyDisposable;
      12: areturn

  public io.reactivex.rxjava3.disposables.Disposable scheduleDirect(java.lang.Runnable, long, java.util.concurrent.TimeUnit);
    Code:
       0: aload         4
       2: lload_2
       3: invokevirtual #8                  // Method java/util/concurrent/TimeUnit.sleep:(J)V
       6: aload_1
       7: invokestatic  #5                  // Method io/reactivex/rxjava3/plugins/RxJavaPlugins.onSchedule:(Ljava/lang/Runnable;)Ljava/lang/Runnable;
      10: invokeinterface #6,  1            // InterfaceMethod java/lang/Runnable.run:()V
      15: goto          31
      18: astore        5
      20: invokestatic  #10                 // Method java/lang/Thread.currentThread:()Ljava/lang/Thread;
      23: invokevirtual #11                 // Method java/lang/Thread.interrupt:()V
      26: aload         5
      28: invokestatic  #12                 // Method io/reactivex/rxjava3/plugins/RxJavaPlugins.onError:(Ljava/lang/Throwable;)V
      31: getstatic     #7                  // Field io/reactivex/rxjava3/internal/disposables/EmptyDisposable.INSTANCE:Lio/reactivex/rxjava3/internal/disposables/EmptyDisposable;
      34: areturn
    Exception table:
       from    to  target type
           0    15    18   Class java/lang/InterruptedException

  static {};
    Code:
       0: new           #13                 // class io/reactivex/rxjava3/internal/schedulers/TrampolineScheduler
       3: dup
       4: invokespecial #14                 // Method "<init>":()V
       7: putstatic     #1                  // Field INSTANCE:Lio/reactivex/rxjava3/internal/schedulers/TrampolineScheduler;
      10: return
}
