Compiled from "TrampolineScheduler.java"
final class io.reactivex.rxjava3.internal.schedulers.TrampolineScheduler$SleepingRunnable implements java.lang.Runnable {
  private final java.lang.Runnable run;

  private final io.reactivex.rxjava3.internal.schedulers.TrampolineScheduler$TrampolineWorker worker;

  private final long execTime;

  io.reactivex.rxjava3.internal.schedulers.TrampolineScheduler$SleepingRunnable(java.lang.Runnable, io.reactivex.rxjava3.internal.schedulers.TrampolineScheduler$TrampolineWorker, long);
    Code:
       0: aload_0
       1: invokespecial #1                  // Method java/lang/Object."<init>":()V
       4: aload_0
       5: aload_1
       6: putfield      #2                  // Field run:Ljava/lang/Runnable;
       9: aload_0
      10: aload_2
      11: putfield      #3                  // Field worker:Lio/reactivex/rxjava3/internal/schedulers/TrampolineScheduler$TrampolineWorker;
      14: aload_0
      15: lload_3
      16: putfield      #4                  // Field execTime:J
      19: return

  public void run();
    Code:
       0: aload_0
       1: getfield      #3                  // Field worker:Lio/reactivex/rxjava3/internal/schedulers/TrampolineScheduler$TrampolineWorker;
       4: getfield      #5                  // Field io/reactivex/rxjava3/internal/schedulers/TrampolineScheduler$TrampolineWorker.disposed:Z
       7: ifne          77
      10: aload_0
      11: getfield      #3                  // Field worker:Lio/reactivex/rxjava3/internal/schedulers/TrampolineScheduler$TrampolineWorker;
      14: getstatic     #6                  // Field java/util/concurrent/TimeUnit.MILLISECONDS:Ljava/util/concurrent/TimeUnit;
      17: invokevirtual #7                  // Method io/reactivex/rxjava3/internal/schedulers/TrampolineScheduler$TrampolineWorker.now:(Ljava/util/concurrent/TimeUnit;)J
      20: lstore_1
      21: aload_0
      22: getfield      #4                  // Field execTime:J
      25: lload_1
      26: lcmp
      27: ifle          58
      30: aload_0
      31: getfield      #4                  // Field execTime:J
      34: lload_1
      35: lsub
      36: lstore_3
      37: lload_3
      38: invokestatic  #8                  // Method java/lang/Thread.sleep:(J)V
      41: goto          58
      44: astore        5
      46: invokestatic  #10                 // Method java/lang/Thread.currentThread:()Ljava/lang/Thread;
      49: invokevirtual #11                 // Method java/lang/Thread.interrupt:()V
      52: aload         5
      54: invokestatic  #12                 // Method io/reactivex/rxjava3/plugins/RxJavaPlugins.onError:(Ljava/lang/Throwable;)V
      57: return
      58: aload_0
      59: getfield      #3                  // Field worker:Lio/reactivex/rxjava3/internal/schedulers/TrampolineScheduler$TrampolineWorker;
      62: getfield      #5                  // Field io/reactivex/rxjava3/internal/schedulers/TrampolineScheduler$TrampolineWorker.disposed:Z
      65: ifne          77
      68: aload_0
      69: getfield      #2                  // Field run:Ljava/lang/Runnable;
      72: invokeinterface #13,  1           // InterfaceMethod java/lang/Runnable.run:()V
      77: return
    Exception table:
       from    to  target type
          37    41    44   Class java/lang/InterruptedException
}
