Compiled from "AccessKeyPair.java"
public class org.apache.dubbo.auth.model.AccessKeyPair {
  private java.lang.String accessKey;

  private java.lang.String secretKey;

  private java.lang.String consumerSide;

  private java.lang.String providerSide;

  private java.lang.String creator;

  private java.lang.String options;

  public org.apache.dubbo.auth.model.AccessKeyPair();
    Code:
       0: aload_0
       1: invokespecial #1                  // Method java/lang/Object."<init>":()V
       4: return

  public java.lang.String getAccessKey();
    Code:
       0: aload_0
       1: getfield      #2                  // Field accessKey:Ljava/lang/String;
       4: areturn

  public void setAccessKey(java.lang.String);
    Code:
       0: aload_0
       1: aload_1
       2: putfield      #2                  // Field accessKey:Ljava/lang/String;
       5: return

  public java.lang.String getSecretKey();
    Code:
       0: aload_0
       1: getfield      #3                  // Field secretKey:Ljava/lang/String;
       4: areturn

  public void setSecretKey(java.lang.String);
    Code:
       0: aload_0
       1: aload_1
       2: putfield      #3                  // Field secretKey:Ljava/lang/String;
       5: return

  public java.lang.String getConsumerSide();
    Code:
       0: aload_0
       1: getfield      #4                  // Field consumerSide:Ljava/lang/String;
       4: areturn

  public void setConsumerSide(java.lang.String);
    Code:
       0: aload_0
       1: aload_1
       2: putfield      #4                  // Field consumerSide:Ljava/lang/String;
       5: return

  public java.lang.String getProviderSide();
    Code:
       0: aload_0
       1: getfield      #5                  // Field providerSide:Ljava/lang/String;
       4: areturn

  public void setProviderSide(java.lang.String);
    Code:
       0: aload_0
       1: aload_1
       2: putfield      #5                  // Field providerSide:Ljava/lang/String;
       5: return

  public java.lang.String getCreator();
    Code:
       0: aload_0
       1: getfield      #6                  // Field creator:Ljava/lang/String;
       4: areturn

  public void setCreator(java.lang.String);
    Code:
       0: aload_0
       1: aload_1
       2: putfield      #6                  // Field creator:Ljava/lang/String;
       5: return

  public java.lang.String getOptions();
    Code:
       0: aload_0
       1: getfield      #7                  // Field options:Ljava/lang/String;
       4: areturn

  public void setOptions(java.lang.String);
    Code:
       0: aload_0
       1: aload_1
       2: putfield      #7                  // Field options:Ljava/lang/String;
       5: return

  public java.lang.String toString();
    Code:
       0: new           #8                  // class java/lang/StringBuilder
       3: dup
       4: invokespecial #9                  // Method java/lang/StringBuilder."<init>":()V
       7: ldc           #10                 // String AccessKeyPair{accessKey=\'
       9: invokevirtual #11                 // Method java/lang/StringBuilder.append:(Ljava/lang/String;)Ljava/lang/StringBuilder;
      12: aload_0
      13: getfield      #2                  // Field accessKey:Ljava/lang/String;
      16: invokevirtual #11                 // Method java/lang/StringBuilder.append:(Ljava/lang/String;)Ljava/lang/StringBuilder;
      19: bipush        39
      21: invokevirtual #12                 // Method java/lang/StringBuilder.append:(C)Ljava/lang/StringBuilder;
      24: ldc           #13                 // String , secretKey=\'
      26: invokevirtual #11                 // Method java/lang/StringBuilder.append:(Ljava/lang/String;)Ljava/lang/StringBuilder;
      29: aload_0
      30: getfield      #3                  // Field secretKey:Ljava/lang/String;
      33: invokevirtual #11                 // Method java/lang/StringBuilder.append:(Ljava/lang/String;)Ljava/lang/StringBuilder;
      36: bipush        39
      38: invokevirtual #12                 // Method java/lang/StringBuilder.append:(C)Ljava/lang/StringBuilder;
      41: ldc           #14                 // String , consumerSide=\'
      43: invokevirtual #11                 // Method java/lang/StringBuilder.append:(Ljava/lang/String;)Ljava/lang/StringBuilder;
      46: aload_0
      47: getfield      #4                  // Field consumerSide:Ljava/lang/String;
      50: invokevirtual #11                 // Method java/lang/StringBuilder.append:(Ljava/lang/String;)Ljava/lang/StringBuilder;
      53: bipush        39
      55: invokevirtual #12                 // Method java/lang/StringBuilder.append:(C)Ljava/lang/StringBuilder;
      58: ldc           #15                 // String , providerSide=\'
      60: invokevirtual #11                 // Method java/lang/StringBuilder.append:(Ljava/lang/String;)Ljava/lang/StringBuilder;
      63: aload_0
      64: getfield      #5                  // Field providerSide:Ljava/lang/String;
      67: invokevirtual #11                 // Method java/lang/StringBuilder.append:(Ljava/lang/String;)Ljava/lang/StringBuilder;
      70: bipush        39
      72: invokevirtual #12                 // Method java/lang/StringBuilder.append:(C)Ljava/lang/StringBuilder;
      75: ldc           #16                 // String , creator=\'
      77: invokevirtual #11                 // Method java/lang/StringBuilder.append:(Ljava/lang/String;)Ljava/lang/StringBuilder;
      80: aload_0
      81: getfield      #6                  // Field creator:Ljava/lang/String;
      84: invokevirtual #11                 // Method java/lang/StringBuilder.append:(Ljava/lang/String;)Ljava/lang/StringBuilder;
      87: bipush        39
      89: invokevirtual #12                 // Method java/lang/StringBuilder.append:(C)Ljava/lang/StringBuilder;
      92: ldc           #17                 // String , options=\'
      94: invokevirtual #11                 // Method java/lang/StringBuilder.append:(Ljava/lang/String;)Ljava/lang/StringBuilder;
      97: aload_0
      98: getfield      #7                  // Field options:Ljava/lang/String;
     101: invokevirtual #11                 // Method java/lang/StringBuilder.append:(Ljava/lang/String;)Ljava/lang/StringBuilder;
     104: bipush        39
     106: invokevirtual #12                 // Method java/lang/StringBuilder.append:(C)Ljava/lang/StringBuilder;
     109: bipush        125
     111: invokevirtual #12                 // Method java/lang/StringBuilder.append:(C)Ljava/lang/StringBuilder;
     114: invokevirtual #18                 // Method java/lang/StringBuilder.toString:()Ljava/lang/String;
     117: areturn
}
