Compiled from "AbstractRequestAnnotationParameterProcessor.java"
public abstract class org.apache.dubbo.metadata.rest.springmvc.AbstractRequestAnnotationParameterProcessor extends org.apache.dubbo.metadata.rest.AbstractAnnotatedMethodParameterProcessor {
  public org.apache.dubbo.metadata.rest.springmvc.AbstractRequestAnnotationParameterProcessor();
    Code:
       0: aload_0
       1: invokespecial #1                  // Method org/apache/dubbo/metadata/rest/AbstractAnnotatedMethodParameterProcessor."<init>":()V
       4: return

  protected java.lang.String getAnnotationValue(java.lang.annotation.Annotation, java.lang.reflect.Parameter, int);
    Code:
       0: aload_0
       1: aload_1
       2: aload_2
       3: iload_3
       4: invokespecial #2                  // Method org/apache/dubbo/metadata/rest/AbstractAnnotatedMethodParameterProcessor.getAnnotationValue:(Ljava/lang/annotation/Annotation;Ljava/lang/reflect/Parameter;I)Ljava/lang/String;
       7: astore        4
       9: aload_0
      10: aload         4
      12: invokevirtual #3                  // Method isEmpty:(Ljava/lang/String;)Z
      15: ifeq          29
      18: aload_1
      19: ldc           #4                  // String name
      21: invokestatic  #5                  // InterfaceMethod org/apache/dubbo/common/utils/AnnotationUtils.getAttribute:(Ljava/lang/annotation/Annotation;Ljava/lang/String;)Ljava/lang/Object;
      24: checkcast     #6                  // class java/lang/String
      27: astore        4
      29: aload_0
      30: aload         4
      32: invokevirtual #3                  // Method isEmpty:(Ljava/lang/String;)Z
      35: ifeq          44
      38: aload_2
      39: invokevirtual #7                  // Method java/lang/reflect/Parameter.getName:()Ljava/lang/String;
      42: astore        4
      44: aload         4
      46: areturn

  protected java.lang.String getDefaultValue(java.lang.annotation.Annotation, java.lang.reflect.Parameter, int);
    Code:
       0: ldc           #8                  // String defaultValue
       2: astore        4
       4: aload_1
       5: aload         4
       7: invokestatic  #5                  // InterfaceMethod org/apache/dubbo/common/utils/AnnotationUtils.getAttribute:(Ljava/lang/annotation/Annotation;Ljava/lang/String;)Ljava/lang/Object;
      10: checkcast     #6                  // class java/lang/String
      13: astore        5
      15: aload_0
      16: aload         5
      18: invokevirtual #3                  // Method isEmpty:(Ljava/lang/String;)Z
      21: ifne          36
      24: aload_0
      25: aload_1
      26: aload         4
      28: aload         5
      30: invokespecial #9                  // Method isDefaultValue:(Ljava/lang/annotation/Annotation;Ljava/lang/String;Ljava/lang/Object;)Z
      33: ifeq          45
      36: aload_0
      37: aload_1
      38: aload_2
      39: iload_3
      40: invokespecial #10                 // Method org/apache/dubbo/metadata/rest/AbstractAnnotatedMethodParameterProcessor.getDefaultValue:(Ljava/lang/annotation/Annotation;Ljava/lang/reflect/Parameter;I)Ljava/lang/String;
      43: astore        5
      45: aload         5
      47: areturn

  private boolean isDefaultValue(java.lang.annotation.Annotation, java.lang.String, java.lang.Object);
    Code:
       0: aload_1
       1: aload_2
       2: invokestatic  #11                 // InterfaceMethod org/apache/dubbo/common/utils/AnnotationUtils.getDefaultValue:(Ljava/lang/annotation/Annotation;Ljava/lang/String;)Ljava/lang/Object;
       5: checkcast     #6                  // class java/lang/String
       8: astore        4
      10: aload_3
      11: aload         4
      13: invokestatic  #12                 // Method java/util/Objects.deepEquals:(Ljava/lang/Object;Ljava/lang/Object;)Z
      16: ireturn

  protected boolean isEmpty(java.lang.String);
    Code:
       0: aload_1
       1: ifnull        11
       4: aload_1
       5: invokevirtual #13                 // Method java/lang/String.isEmpty:()Z
       8: ifeq          15
      11: iconst_1
      12: goto          16
      15: iconst_0
      16: ireturn
}
