Compiled from "ParamNoAnnotatedProcessor.java"
public class org.apache.dubbo.metadata.rest.springmvc.ParamNoAnnotatedProcessor extends org.apache.dubbo.metadata.rest.AbstractNoAnnotatedParameterProcessor {
  public org.apache.dubbo.metadata.rest.springmvc.ParamNoAnnotatedProcessor();
    Code:
       0: aload_0
       1: invokespecial #1                  // Method org/apache/dubbo/metadata/rest/AbstractNoAnnotatedParameterProcessor."<init>":()V
       4: return

  public org.apache.dubbo.metadata.rest.media.MediaType consumerContentType();
    Code:
       0: getstatic     #2                  // Field org/apache/dubbo/metadata/rest/media/MediaType.ALL_VALUE:Lorg/apache/dubbo/metadata/rest/media/MediaType;
       3: areturn

  public java.lang.String defaultAnnotationClassName(org.apache.dubbo.metadata.rest.RestMethodMetadata);
    Code:
       0: ldc           #3                  // class org/apache/dubbo/metadata/rest/jaxrs/JAXRSServiceRestMetadataResolver
       2: aload_1
       3: invokevirtual #4                  // Method org/apache/dubbo/metadata/rest/RestMethodMetadata.getCodeStyle:()Ljava/lang/Class;
       6: invokevirtual #5                  // Method java/lang/Object.equals:(Ljava/lang/Object;)Z
       9: ifeq          18
      12: ldc           #6                  // class org/apache/dubbo/metadata/rest/tag/BodyTag
      14: invokevirtual #7                  // Method java/lang/Class.getName:()Ljava/lang/String;
      17: areturn
      18: ldc           #8                  // class org/apache/dubbo/metadata/rest/tag/ParamTag
      20: invokevirtual #7                  // Method java/lang/Class.getName:()Ljava/lang/String;
      23: areturn
}
