Compiled from "RequestHeaderParameterProcessor.java"
public class org.apache.dubbo.metadata.rest.springmvc.RequestHeaderParameterProcessor extends org.apache.dubbo.metadata.rest.springmvc.AbstractRequestAnnotationParameterProcessor {
  public org.apache.dubbo.metadata.rest.springmvc.RequestHeaderParameterProcessor();
    Code:
       0: aload_0
       1: invokespecial #2                  // Method org/apache/dubbo/metadata/rest/springmvc/AbstractRequestAnnotationParameterProcessor."<init>":()V
       4: return

  public java.lang.String getAnnotationName();
    Code:
       0: ldc           #3                  // String org.springframework.web.bind.annotation.RequestHeader
       2: areturn

  protected void process(java.lang.String, java.lang.String, java.lang.annotation.Annotation, java.lang.reflect.Parameter, int, java.lang.reflect.Method, org.apache.dubbo.metadata.rest.RestMethodMetadata);
    Code:
       0: aload         7
       2: invokevirtual #4                  // Method org/apache/dubbo/metadata/rest/RestMethodMetadata.getRequest:()Lorg/apache/dubbo/metadata/rest/RequestMetadata;
       5: aload_1
       6: aload_2
       7: invokevirtual #5                  // Method org/apache/dubbo/metadata/rest/RequestMetadata.addHeader:(Ljava/lang/String;Ljava/lang/String;)Lorg/apache/dubbo/metadata/rest/RequestMetadata;
      10: pop
      11: return
}
