Compiled from "RequestBodyParameterProcessor.java"
public class org.apache.dubbo.metadata.rest.springmvc.RequestBodyParameterProcessor extends org.apache.dubbo.metadata.rest.AbstractAnnotatedMethodParameterProcessor {
  public org.apache.dubbo.metadata.rest.springmvc.RequestBodyParameterProcessor();
    Code:
       0: aload_0
       1: invokespecial #2                  // Method org/apache/dubbo/metadata/rest/AbstractAnnotatedMethodParameterProcessor."<init>":()V
       4: return

  public java.lang.String getAnnotationName();
    Code:
       0: ldc           #3                  // String org.springframework.web.bind.annotation.RequestBody
       2: areturn

  protected java.lang.String getAnnotationValue(java.lang.annotation.Annotation, java.lang.reflect.Parameter, int);
    Code:
       0: aconst_null
       1: areturn

  protected java.lang.String getDefaultValue(java.lang.annotation.Annotation, java.lang.reflect.Parameter, int);
    Code:
       0: aconst_null
       1: areturn
}
