Compiled from "SpringMvcServiceRestMetadataResolver.java"
public class org.apache.dubbo.metadata.rest.springmvc.SpringMvcServiceRestMetadataResolver extends org.apache.dubbo.metadata.rest.AbstractServiceRestMetadataResolver {
  private static final int FIRST_ELEMENT_INDEX;

  public org.apache.dubbo.metadata.rest.springmvc.SpringMvcServiceRestMetadataResolver(org.apache.dubbo.rpc.model.ApplicationModel);
    Code:
       0: aload_0
       1: aload_1
       2: invokespecial #1                  // Method org/apache/dubbo/metadata/rest/AbstractServiceRestMetadataResolver."<init>":(Lorg/apache/dubbo/rpc/model/ApplicationModel;)V
       5: return

  protected boolean supports0(java.lang.Class<?>);
    Code:
       0: aload_1
       1: getstatic     #2                  // Field org/apache/dubbo/metadata/rest/RestMetadataConstants$SPRING_MVC.CONTROLLER_ANNOTATION_CLASS:Ljava/lang/Class;
       4: invokestatic  #3                  // InterfaceMethod org/apache/dubbo/common/utils/AnnotationUtils.isAnnotationPresent:(Ljava/lang/Class;Ljava/lang/Class;)Z
       7: ifne          20
      10: aload_1
      11: getstatic     #4                  // Field org/apache/dubbo/metadata/rest/RestMetadataConstants$SPRING_MVC.REQUEST_MAPPING_ANNOTATION_CLASS:Ljava/lang/Class;
      14: invokestatic  #3                  // InterfaceMethod org/apache/dubbo/common/utils/AnnotationUtils.isAnnotationPresent:(Ljava/lang/Class;Ljava/lang/Class;)Z
      17: ifeq          24
      20: iconst_1
      21: goto          25
      24: iconst_0
      25: ireturn

  protected boolean isRestCapableMethod(java.lang.reflect.Method, java.lang.Class<?>, java.lang.Class<?>);
    Code:
       0: aload_1
       1: getstatic     #4                  // Field org/apache/dubbo/metadata/rest/RestMetadataConstants$SPRING_MVC.REQUEST_MAPPING_ANNOTATION_CLASS:Ljava/lang/Class;
       4: invokestatic  #5                  // InterfaceMethod org/apache/dubbo/common/utils/AnnotationUtils.isAnnotationPresent:(Ljava/lang/reflect/AnnotatedElement;Ljava/lang/Class;)Z
       7: ireturn

  protected java.lang.String resolveRequestMethod(java.lang.reflect.Method, java.lang.Class<?>, java.lang.Class<?>);
    Code:
       0: aload_0
       1: aload_1
       2: invokespecial #6                  // Method getRequestMapping:(Ljava/lang/reflect/AnnotatedElement;)Ljava/lang/annotation/Annotation;
       5: astore        4
       7: aload         4
       9: ldc           #7                  // String method
      11: invokestatic  #8                  // InterfaceMethod org/apache/dubbo/common/utils/AnnotationUtils.getAttribute:(Ljava/lang/annotation/Annotation;Ljava/lang/String;)Ljava/lang/Object;
      14: astore        5
      16: aload         5
      18: ifnull        30
      21: aload         5
      23: invokestatic  #9                  // Method java/lang/reflect/Array.getLength:(Ljava/lang/Object;)I
      26: iconst_1
      27: if_icmpge     32
      30: aconst_null
      31: areturn
      32: aload         5
      34: iconst_0
      35: invokestatic  #11                 // Method java/lang/reflect/Array.get:(Ljava/lang/Object;I)Ljava/lang/Object;
      38: invokestatic  #12                 // Method java/lang/String.valueOf:(Ljava/lang/Object;)Ljava/lang/String;
      41: areturn

  protected java.lang.String resolveRequestPath(java.lang.reflect.Method, java.lang.Class<?>, java.lang.Class<?>);
    Code:
       0: aload_0
       1: aload_2
       2: invokespecial #13                 // Method resolveRequestPath:(Ljava/lang/reflect/AnnotatedElement;)Ljava/lang/String;
       5: astore        4
       7: aload_0
       8: aload_1
       9: invokespecial #13                 // Method resolveRequestPath:(Ljava/lang/reflect/AnnotatedElement;)Ljava/lang/String;
      12: astore        5
      14: aload         4
      16: iconst_1
      17: anewarray     #14                 // class java/lang/String
      20: dup
      21: iconst_0
      22: aload         5
      24: aastore
      25: invokestatic  #15                 // InterfaceMethod org/apache/dubbo/common/utils/PathUtils.buildPath:(Ljava/lang/String;[Ljava/lang/String;)Ljava/lang/String;
      28: areturn

  protected void processProduces(java.lang.reflect.Method, java.lang.Class<?>, java.lang.Class<?>, java.util.Set<java.lang.String>);
    Code:
       0: aload_0
       1: aload_1
       2: ldc           #16                 // String produces
       4: aload         4
       6: invokespecial #17                 // Method addMediaTypes:(Ljava/lang/reflect/Method;Ljava/lang/String;Ljava/util/Set;)V
       9: aload_0
      10: aload_2
      11: ldc           #16                 // String produces
      13: aload         4
      15: invokespecial #18                 // Method addMediaTypes:(Ljava/lang/Class;Ljava/lang/String;Ljava/util/Set;)V
      18: aload_0
      19: aload_3
      20: ldc           #16                 // String produces
      22: aload         4
      24: invokespecial #18                 // Method addMediaTypes:(Ljava/lang/Class;Ljava/lang/String;Ljava/util/Set;)V
      27: return

  protected void processConsumes(java.lang.reflect.Method, java.lang.Class<?>, java.lang.Class<?>, java.util.Set<java.lang.String>);
    Code:
       0: aload_0
       1: aload_1
       2: ldc           #19                 // String consumes
       4: aload         4
       6: invokespecial #17                 // Method addMediaTypes:(Ljava/lang/reflect/Method;Ljava/lang/String;Ljava/util/Set;)V
       9: aload_0
      10: aload_2
      11: ldc           #19                 // String consumes
      13: aload         4
      15: invokespecial #18                 // Method addMediaTypes:(Ljava/lang/Class;Ljava/lang/String;Ljava/util/Set;)V
      18: aload_0
      19: aload_3
      20: ldc           #19                 // String consumes
      22: aload         4
      24: invokespecial #18                 // Method addMediaTypes:(Ljava/lang/Class;Ljava/lang/String;Ljava/util/Set;)V
      27: return

  private java.lang.String resolveRequestPath(java.lang.reflect.AnnotatedElement);
    Code:
       0: aload_0
       1: aload_1
       2: invokespecial #6                  // Method getRequestMapping:(Ljava/lang/reflect/AnnotatedElement;)Ljava/lang/annotation/Annotation;
       5: astore_2
       6: aload_2
       7: ldc           #20                 // String value
       9: invokestatic  #8                  // InterfaceMethod org/apache/dubbo/common/utils/AnnotationUtils.getAttribute:(Ljava/lang/annotation/Annotation;Ljava/lang/String;)Ljava/lang/Object;
      12: checkcast     #21                 // class "[Ljava/lang/String;"
      15: astore_3
      16: aload_3
      17: invokestatic  #22                 // Method org/apache/dubbo/common/utils/ArrayUtils.isEmpty:([Ljava/lang/Object;)Z
      20: ifeq          33
      23: aload_2
      24: ldc           #23                 // String path
      26: invokestatic  #8                  // InterfaceMethod org/apache/dubbo/common/utils/AnnotationUtils.getAttribute:(Ljava/lang/annotation/Annotation;Ljava/lang/String;)Ljava/lang/Object;
      29: checkcast     #21                 // class "[Ljava/lang/String;"
      32: astore_3
      33: aload_3
      34: invokestatic  #22                 // Method org/apache/dubbo/common/utils/ArrayUtils.isEmpty:([Ljava/lang/Object;)Z
      37: ifeq          43
      40: ldc           #24                 // String
      42: areturn
      43: aload_3
      44: iconst_0
      45: aaload
      46: areturn

  private void addMediaTypes(java.lang.reflect.Method, java.lang.String, java.util.Set<java.lang.String>);
    Code:
       0: aload_0
       1: aload_1
       2: invokespecial #6                  // Method getRequestMapping:(Ljava/lang/reflect/AnnotatedElement;)Ljava/lang/annotation/Annotation;
       5: astore        4
       7: aload         4
       9: aload_2
      10: invokestatic  #8                  // InterfaceMethod org/apache/dubbo/common/utils/AnnotationUtils.getAttribute:(Ljava/lang/annotation/Annotation;Ljava/lang/String;)Ljava/lang/Object;
      13: checkcast     #21                 // class "[Ljava/lang/String;"
      16: astore        5
      18: aload         5
      20: invokestatic  #25                 // Method org/apache/dubbo/common/utils/ArrayUtils.isNotEmpty:([Ljava/lang/Object;)Z
      23: ifeq          47
      26: aload         5
      28: invokestatic  #26                 // InterfaceMethod java/util/stream/Stream.of:([Ljava/lang/Object;)Ljava/util/stream/Stream;
      31: aload_3
      32: dup
      33: invokevirtual #27                 // Method java/lang/Object.getClass:()Ljava/lang/Class;
      36: pop
      37: invokedynamic #28,  0             // InvokeDynamic #0:accept:(Ljava/util/Set;)Ljava/util/function/Consumer;
      42: invokeinterface #29,  2           // InterfaceMethod java/util/stream/Stream.forEach:(Ljava/util/function/Consumer;)V
      47: return

  private void addMediaTypes(java.lang.Class, java.lang.String, java.util.Set<java.lang.String>);
    Code:
       0: aload_0
       1: aload_1
       2: invokespecial #6                  // Method getRequestMapping:(Ljava/lang/reflect/AnnotatedElement;)Ljava/lang/annotation/Annotation;
       5: astore        4
       7: aload         4
       9: aload_2
      10: invokestatic  #8                  // InterfaceMethod org/apache/dubbo/common/utils/AnnotationUtils.getAttribute:(Ljava/lang/annotation/Annotation;Ljava/lang/String;)Ljava/lang/Object;
      13: checkcast     #21                 // class "[Ljava/lang/String;"
      16: astore        5
      18: aload         5
      20: invokestatic  #25                 // Method org/apache/dubbo/common/utils/ArrayUtils.isNotEmpty:([Ljava/lang/Object;)Z
      23: ifeq          47
      26: aload         5
      28: invokestatic  #26                 // InterfaceMethod java/util/stream/Stream.of:([Ljava/lang/Object;)Ljava/util/stream/Stream;
      31: aload_3
      32: dup
      33: invokevirtual #27                 // Method java/lang/Object.getClass:()Ljava/lang/Class;
      36: pop
      37: invokedynamic #28,  0             // InvokeDynamic #0:accept:(Ljava/util/Set;)Ljava/util/function/Consumer;
      42: invokeinterface #29,  2           // InterfaceMethod java/util/stream/Stream.forEach:(Ljava/util/function/Consumer;)V
      47: return

  private java.lang.annotation.Annotation getRequestMapping(java.lang.reflect.AnnotatedElement);
    Code:
       0: aload_1
       1: getstatic     #4                  // Field org/apache/dubbo/metadata/rest/RestMetadataConstants$SPRING_MVC.REQUEST_MAPPING_ANNOTATION_CLASS:Ljava/lang/Class;
       4: invokestatic  #30                 // InterfaceMethod org/apache/dubbo/common/utils/AnnotationUtils.findAnnotation:(Ljava/lang/reflect/AnnotatedElement;Ljava/lang/Class;)Ljava/lang/annotation/Annotation;
       7: astore_2
       8: aload_2
       9: ifnonnull     67
      12: getstatic     #31                 // Field org/apache/dubbo/metadata/rest/RestMetadataConstants$SPRING_MVC.ANNOTATED_ELEMENT_UTILS_CLASS:Ljava/lang/Class;
      15: ldc           #32                 // String findMergedAnnotation
      17: iconst_2
      18: anewarray     #33                 // class java/lang/Class
      21: dup
      22: iconst_0
      23: ldc           #34                 // class java/lang/reflect/AnnotatedElement
      25: aastore
      26: dup
      27: iconst_1
      28: ldc           #33                 // class java/lang/Class
      30: aastore
      31: invokestatic  #35                 // InterfaceMethod org/apache/dubbo/common/utils/MethodUtils.findMethod:(Ljava/lang/Class;Ljava/lang/String;[Ljava/lang/Class;)Ljava/lang/reflect/Method;
      34: astore_3
      35: aload_3
      36: ifnull        67
      39: aload_3
      40: aconst_null
      41: iconst_2
      42: anewarray     #36                 // class java/lang/Object
      45: dup
      46: iconst_0
      47: aload_1
      48: aastore
      49: dup
      50: iconst_1
      51: getstatic     #4                  // Field org/apache/dubbo/metadata/rest/RestMetadataConstants$SPRING_MVC.REQUEST_MAPPING_ANNOTATION_CLASS:Ljava/lang/Class;
      54: aastore
      55: invokevirtual #37                 // Method java/lang/reflect/Method.invoke:(Ljava/lang/Object;[Ljava/lang/Object;)Ljava/lang/Object;
      58: checkcast     #38                 // class java/lang/annotation/Annotation
      61: astore_2
      62: goto          67
      65: astore        4
      67: aload_2
      68: areturn
    Exception table:
       from    to  target type
          39    62    65   Class java/lang/Exception
}
