Compiled from "ActivateComparator.java"
public class org.apache.dubbo.common.extension.support.ActivateComparator implements java.util.Comparator<java.lang.Class<?>> {
  private final java.util.List<org.apache.dubbo.common.extension.ExtensionDirector> extensionDirectors;

  private final java.util.Map<java.lang.Class<?>, org.apache.dubbo.common.extension.support.ActivateComparator$ActivateInfo> activateInfoMap;

  public org.apache.dubbo.common.extension.support.ActivateComparator(org.apache.dubbo.common.extension.ExtensionDirector);
    Code:
       0: aload_0
       1: invokespecial #1                  // Method java/lang/Object."<init>":()V
       4: aload_0
       5: new           #2                  // class java/util/concurrent/ConcurrentHashMap
       8: dup
       9: invokespecial #3                  // Method java/util/concurrent/ConcurrentHashMap."<init>":()V
      12: putfield      #4                  // Field activateInfoMap:Ljava/util/Map;
      15: aload_0
      16: new           #5                  // class java/util/ArrayList
      19: dup
      20: invokespecial #6                  // Method java/util/ArrayList."<init>":()V
      23: putfield      #7                  // Field extensionDirectors:Ljava/util/List;
      26: aload_0
      27: getfield      #7                  // Field extensionDirectors:Ljava/util/List;
      30: aload_1
      31: invokeinterface #8,  2            // InterfaceMethod java/util/List.add:(Ljava/lang/Object;)Z
      36: pop
      37: return

  public org.apache.dubbo.common.extension.support.ActivateComparator(java.util.List<org.apache.dubbo.common.extension.ExtensionDirector>);
    Code:
       0: aload_0
       1: invokespecial #1                  // Method java/lang/Object."<init>":()V
       4: aload_0
       5: new           #2                  // class java/util/concurrent/ConcurrentHashMap
       8: dup
       9: invokespecial #3                  // Method java/util/concurrent/ConcurrentHashMap."<init>":()V
      12: putfield      #4                  // Field activateInfoMap:Ljava/util/Map;
      15: aload_0
      16: aload_1
      17: putfield      #7                  // Field extensionDirectors:Ljava/util/List;
      20: return

  public int compare(java.lang.Class, java.lang.Class);
    Code:
       0: aload_1
       1: ifnonnull     10
       4: aload_2
       5: ifnonnull     10
       8: iconst_0
       9: ireturn
      10: aload_1
      11: ifnonnull     16
      14: iconst_m1
      15: ireturn
      16: aload_2
      17: ifnonnull     22
      20: iconst_1
      21: ireturn
      22: aload_1
      23: aload_2
      24: invokevirtual #9                  // Method java/lang/Object.equals:(Ljava/lang/Object;)Z
      27: ifeq          32
      30: iconst_0
      31: ireturn
      32: aload_0
      33: aload_1
      34: invokespecial #10                 // Method findSpi:(Ljava/lang/Class;)Ljava/lang/Class;
      37: astore_3
      38: aload_0
      39: aload_1
      40: invokespecial #11                 // Method parseActivate:(Ljava/lang/Class;)Lorg/apache/dubbo/common/extension/support/ActivateComparator$ActivateInfo;
      43: astore        4
      45: aload_0
      46: aload_2
      47: invokespecial #11                 // Method parseActivate:(Ljava/lang/Class;)Lorg/apache/dubbo/common/extension/support/ActivateComparator$ActivateInfo;
      50: astore        5
      52: aload         4
      54: invokestatic  #12                 // Method org/apache/dubbo/common/extension/support/ActivateComparator$ActivateInfo.access$000:(Lorg/apache/dubbo/common/extension/support/ActivateComparator$ActivateInfo;)Z
      57: ifne          68
      60: aload         5
      62: invokestatic  #12                 // Method org/apache/dubbo/common/extension/support/ActivateComparator$ActivateInfo.access$000:(Lorg/apache/dubbo/common/extension/support/ActivateComparator$ActivateInfo;)Z
      65: ifeq          281
      68: aload_3
      69: ifnull        281
      72: aload         4
      74: invokestatic  #12                 // Method org/apache/dubbo/common/extension/support/ActivateComparator$ActivateInfo.access$000:(Lorg/apache/dubbo/common/extension/support/ActivateComparator$ActivateInfo;)Z
      77: ifeq          167
      80: aconst_null
      81: astore        6
      83: aload_0
      84: getfield      #7                  // Field extensionDirectors:Ljava/util/List;
      87: invokeinterface #13,  1           // InterfaceMethod java/util/List.iterator:()Ljava/util/Iterator;
      92: astore        7
      94: aload         7
      96: invokeinterface #14,  1           // InterfaceMethod java/util/Iterator.hasNext:()Z
     101: ifeq          143
     104: aload         7
     106: invokeinterface #15,  1           // InterfaceMethod java/util/Iterator.next:()Ljava/lang/Object;
     111: checkcast     #16                 // class org/apache/dubbo/common/extension/ExtensionDirector
     114: astore        8
     116: aload         8
     118: aload_3
     119: invokevirtual #17                 // Method org/apache/dubbo/common/extension/ExtensionDirector.getExtensionLoader:(Ljava/lang/Class;)Lorg/apache/dubbo/common/extension/ExtensionLoader;
     122: astore        9
     124: aload         9
     126: aload_2
     127: invokevirtual #18                 // Method org/apache/dubbo/common/extension/ExtensionLoader.getExtensionName:(Ljava/lang/Class;)Ljava/lang/String;
     130: astore        6
     132: aload         6
     134: ifnull        140
     137: goto          143
     140: goto          94
     143: aload         4
     145: aload         6
     147: invokestatic  #19                 // Method org/apache/dubbo/common/extension/support/ActivateComparator$ActivateInfo.access$100:(Lorg/apache/dubbo/common/extension/support/ActivateComparator$ActivateInfo;Ljava/lang/String;)Z
     150: ifeq          155
     153: iconst_m1
     154: ireturn
     155: aload         4
     157: aload         6
     159: invokestatic  #20                 // Method org/apache/dubbo/common/extension/support/ActivateComparator$ActivateInfo.access$200:(Lorg/apache/dubbo/common/extension/support/ActivateComparator$ActivateInfo;Ljava/lang/String;)Z
     162: ifeq          167
     165: iconst_1
     166: ireturn
     167: aload         5
     169: invokestatic  #12                 // Method org/apache/dubbo/common/extension/support/ActivateComparator$ActivateInfo.access$000:(Lorg/apache/dubbo/common/extension/support/ActivateComparator$ActivateInfo;)Z
     172: ifeq          262
     175: aconst_null
     176: astore        6
     178: aload_0
     179: getfield      #7                  // Field extensionDirectors:Ljava/util/List;
     182: invokeinterface #13,  1           // InterfaceMethod java/util/List.iterator:()Ljava/util/Iterator;
     187: astore        7
     189: aload         7
     191: invokeinterface #14,  1           // InterfaceMethod java/util/Iterator.hasNext:()Z
     196: ifeq          238
     199: aload         7
     201: invokeinterface #15,  1           // InterfaceMethod java/util/Iterator.next:()Ljava/lang/Object;
     206: checkcast     #16                 // class org/apache/dubbo/common/extension/ExtensionDirector
     209: astore        8
     211: aload         8
     213: aload_3
     214: invokevirtual #17                 // Method org/apache/dubbo/common/extension/ExtensionDirector.getExtensionLoader:(Ljava/lang/Class;)Lorg/apache/dubbo/common/extension/ExtensionLoader;
     217: astore        9
     219: aload         9
     221: aload_1
     222: invokevirtual #18                 // Method org/apache/dubbo/common/extension/ExtensionLoader.getExtensionName:(Ljava/lang/Class;)Ljava/lang/String;
     225: astore        6
     227: aload         6
     229: ifnull        235
     232: goto          238
     235: goto          189
     238: aload         5
     240: aload         6
     242: invokestatic  #19                 // Method org/apache/dubbo/common/extension/support/ActivateComparator$ActivateInfo.access$100:(Lorg/apache/dubbo/common/extension/support/ActivateComparator$ActivateInfo;Ljava/lang/String;)Z
     245: ifeq          250
     248: iconst_1
     249: ireturn
     250: aload         5
     252: aload         6
     254: invokestatic  #20                 // Method org/apache/dubbo/common/extension/support/ActivateComparator$ActivateInfo.access$200:(Lorg/apache/dubbo/common/extension/support/ActivateComparator$ActivateInfo;Ljava/lang/String;)Z
     257: ifeq          262
     260: iconst_m1
     261: ireturn
     262: aload         4
     264: invokestatic  #21                 // Method org/apache/dubbo/common/extension/support/ActivateComparator$ActivateInfo.access$300:(Lorg/apache/dubbo/common/extension/support/ActivateComparator$ActivateInfo;)I
     267: aload         5
     269: invokestatic  #21                 // Method org/apache/dubbo/common/extension/support/ActivateComparator$ActivateInfo.access$300:(Lorg/apache/dubbo/common/extension/support/ActivateComparator$ActivateInfo;)I
     272: if_icmple     279
     275: iconst_1
     276: goto          280
     279: iconst_m1
     280: ireturn
     281: aload         4
     283: invokestatic  #21                 // Method org/apache/dubbo/common/extension/support/ActivateComparator$ActivateInfo.access$300:(Lorg/apache/dubbo/common/extension/support/ActivateComparator$ActivateInfo;)I
     286: aload         5
     288: invokestatic  #21                 // Method org/apache/dubbo/common/extension/support/ActivateComparator$ActivateInfo.access$300:(Lorg/apache/dubbo/common/extension/support/ActivateComparator$ActivateInfo;)I
     291: if_icmple     296
     294: iconst_1
     295: ireturn
     296: aload         4
     298: invokestatic  #21                 // Method org/apache/dubbo/common/extension/support/ActivateComparator$ActivateInfo.access$300:(Lorg/apache/dubbo/common/extension/support/ActivateComparator$ActivateInfo;)I
     301: aload         5
     303: invokestatic  #21                 // Method org/apache/dubbo/common/extension/support/ActivateComparator$ActivateInfo.access$300:(Lorg/apache/dubbo/common/extension/support/ActivateComparator$ActivateInfo;)I
     306: if_icmpne     329
     309: aload_1
     310: invokevirtual #22                 // Method java/lang/Class.getSimpleName:()Ljava/lang/String;
     313: aload_2
     314: invokevirtual #22                 // Method java/lang/Class.getSimpleName:()Ljava/lang/String;
     317: invokevirtual #23                 // Method java/lang/String.compareTo:(Ljava/lang/String;)I
     320: ifle          327
     323: iconst_1
     324: goto          328
     327: iconst_m1
     328: ireturn
     329: iconst_m1
     330: ireturn

  private java.lang.Class<?> findSpi(java.lang.Class<?>);
    Code:
       0: aload_1
       1: invokevirtual #24                 // Method java/lang/Class.getInterfaces:()[Ljava/lang/Class;
       4: arraylength
       5: ifne          10
       8: aconst_null
       9: areturn
      10: aload_1
      11: invokevirtual #24                 // Method java/lang/Class.getInterfaces:()[Ljava/lang/Class;
      14: astore_2
      15: aload_2
      16: arraylength
      17: istore_3
      18: iconst_0
      19: istore        4
      21: iload         4
      23: iload_3
      24: if_icmpge     68
      27: aload_2
      28: iload         4
      30: aaload
      31: astore        5
      33: aload         5
      35: ldc           #25                 // class org/apache/dubbo/common/extension/SPI
      37: invokevirtual #26                 // Method java/lang/Class.isAnnotationPresent:(Ljava/lang/Class;)Z
      40: ifeq          46
      43: aload         5
      45: areturn
      46: aload_0
      47: aload         5
      49: invokespecial #10                 // Method findSpi:(Ljava/lang/Class;)Ljava/lang/Class;
      52: astore        6
      54: aload         6
      56: ifnull        62
      59: aload         6
      61: areturn
      62: iinc          4, 1
      65: goto          21
      68: aconst_null
      69: areturn

  private org.apache.dubbo.common.extension.support.ActivateComparator$ActivateInfo parseActivate(java.lang.Class<?>);
    Code:
       0: aload_0
       1: getfield      #4                  // Field activateInfoMap:Ljava/util/Map;
       4: aload_1
       5: invokeinterface #27,  2           // InterfaceMethod java/util/Map.get:(Ljava/lang/Object;)Ljava/lang/Object;
      10: checkcast     #28                 // class org/apache/dubbo/common/extension/support/ActivateComparator$ActivateInfo
      13: astore_2
      14: aload_2
      15: ifnull        20
      18: aload_2
      19: areturn
      20: new           #28                 // class org/apache/dubbo/common/extension/support/ActivateComparator$ActivateInfo
      23: dup
      24: aconst_null
      25: invokespecial #29                 // Method org/apache/dubbo/common/extension/support/ActivateComparator$ActivateInfo."<init>":(Lorg/apache/dubbo/common/extension/support/ActivateComparator$1;)V
      28: astore_2
      29: aload_1
      30: ldc           #30                 // class org/apache/dubbo/common/extension/Activate
      32: invokevirtual #26                 // Method java/lang/Class.isAnnotationPresent:(Ljava/lang/Class;)Z
      35: ifeq          84
      38: aload_1
      39: ldc           #30                 // class org/apache/dubbo/common/extension/Activate
      41: invokevirtual #31                 // Method java/lang/Class.getAnnotation:(Ljava/lang/Class;)Ljava/lang/annotation/Annotation;
      44: checkcast     #30                 // class org/apache/dubbo/common/extension/Activate
      47: astore_3
      48: aload_2
      49: aload_3
      50: invokeinterface #32,  1           // InterfaceMethod org/apache/dubbo/common/extension/Activate.before:()[Ljava/lang/String;
      55: invokestatic  #33                 // Method org/apache/dubbo/common/extension/support/ActivateComparator$ActivateInfo.access$502:(Lorg/apache/dubbo/common/extension/support/ActivateComparator$ActivateInfo;[Ljava/lang/String;)[Ljava/lang/String;
      58: pop
      59: aload_2
      60: aload_3
      61: invokeinterface #34,  1           // InterfaceMethod org/apache/dubbo/common/extension/Activate.after:()[Ljava/lang/String;
      66: invokestatic  #35                 // Method org/apache/dubbo/common/extension/support/ActivateComparator$ActivateInfo.access$602:(Lorg/apache/dubbo/common/extension/support/ActivateComparator$ActivateInfo;[Ljava/lang/String;)[Ljava/lang/String;
      69: pop
      70: aload_2
      71: aload_3
      72: invokeinterface #36,  1           // InterfaceMethod org/apache/dubbo/common/extension/Activate.order:()I
      77: invokestatic  #37                 // Method org/apache/dubbo/common/extension/support/ActivateComparator$ActivateInfo.access$302:(Lorg/apache/dubbo/common/extension/support/ActivateComparator$ActivateInfo;I)I
      80: pop
      81: goto          145
      84: aload_1
      85: ldc           #38                 // class com/alibaba/dubbo/common/extension/Activate
      87: invokevirtual #26                 // Method java/lang/Class.isAnnotationPresent:(Ljava/lang/Class;)Z
      90: ifeq          139
      93: aload_1
      94: ldc           #38                 // class com/alibaba/dubbo/common/extension/Activate
      96: invokevirtual #31                 // Method java/lang/Class.getAnnotation:(Ljava/lang/Class;)Ljava/lang/annotation/Annotation;
      99: checkcast     #38                 // class com/alibaba/dubbo/common/extension/Activate
     102: astore_3
     103: aload_2
     104: aload_3
     105: invokeinterface #39,  1           // InterfaceMethod com/alibaba/dubbo/common/extension/Activate.before:()[Ljava/lang/String;
     110: invokestatic  #33                 // Method org/apache/dubbo/common/extension/support/ActivateComparator$ActivateInfo.access$502:(Lorg/apache/dubbo/common/extension/support/ActivateComparator$ActivateInfo;[Ljava/lang/String;)[Ljava/lang/String;
     113: pop
     114: aload_2
     115: aload_3
     116: invokeinterface #40,  1           // InterfaceMethod com/alibaba/dubbo/common/extension/Activate.after:()[Ljava/lang/String;
     121: invokestatic  #35                 // Method org/apache/dubbo/common/extension/support/ActivateComparator$ActivateInfo.access$602:(Lorg/apache/dubbo/common/extension/support/ActivateComparator$ActivateInfo;[Ljava/lang/String;)[Ljava/lang/String;
     124: pop
     125: aload_2
     126: aload_3
     127: invokeinterface #41,  1           // InterfaceMethod com/alibaba/dubbo/common/extension/Activate.order:()I
     132: invokestatic  #37                 // Method org/apache/dubbo/common/extension/support/ActivateComparator$ActivateInfo.access$302:(Lorg/apache/dubbo/common/extension/support/ActivateComparator$ActivateInfo;I)I
     135: pop
     136: goto          145
     139: aload_2
     140: iconst_0
     141: invokestatic  #37                 // Method org/apache/dubbo/common/extension/support/ActivateComparator$ActivateInfo.access$302:(Lorg/apache/dubbo/common/extension/support/ActivateComparator$ActivateInfo;I)I
     144: pop
     145: aload_0
     146: getfield      #4                  // Field activateInfoMap:Ljava/util/Map;
     149: aload_1
     150: aload_2
     151: invokeinterface #42,  3           // InterfaceMethod java/util/Map.put:(Ljava/lang/Object;Ljava/lang/Object;)Ljava/lang/Object;
     156: pop
     157: aload_2
     158: areturn

  public int compare(java.lang.Object, java.lang.Object);
    Code:
       0: aload_0
       1: aload_1
       2: checkcast     #43                 // class java/lang/Class
       5: aload_2
       6: checkcast     #43                 // class java/lang/Class
       9: invokevirtual #44                 // Method compare:(Ljava/lang/Class;Ljava/lang/Class;)I
      12: ireturn
}
