Compiled from "WrapperComparator.java"
public class org.apache.dubbo.common.extension.support.WrapperComparator implements java.util.Comparator<java.lang.Object> {
  public static final java.util.Comparator<java.lang.Object> COMPARATOR;

  public org.apache.dubbo.common.extension.support.WrapperComparator();
    Code:
       0: aload_0
       1: invokespecial #1                  // Method java/lang/Object."<init>":()V
       4: return

  public int compare(java.lang.Object, java.lang.Object);
    Code:
       0: aload_1
       1: ifnonnull     10
       4: aload_2
       5: ifnonnull     10
       8: iconst_0
       9: ireturn
      10: aload_1
      11: ifnonnull     16
      14: iconst_m1
      15: ireturn
      16: aload_2
      17: ifnonnull     22
      20: iconst_1
      21: ireturn
      22: aload_1
      23: aload_2
      24: invokevirtual #2                  // Method java/lang/Object.equals:(Ljava/lang/Object;)Z
      27: ifeq          32
      30: iconst_0
      31: ireturn
      32: aload_1
      33: checkcast     #3                  // class java/lang/Class
      36: astore_3
      37: aload_2
      38: checkcast     #3                  // class java/lang/Class
      41: astore        4
      43: aload_0
      44: aload_3
      45: invokespecial #4                  // Method parseOrder:(Ljava/lang/Class;)Lorg/apache/dubbo/common/extension/support/WrapperComparator$OrderInfo;
      48: astore        5
      50: aload_0
      51: aload         4
      53: invokespecial #4                  // Method parseOrder:(Ljava/lang/Class;)Lorg/apache/dubbo/common/extension/support/WrapperComparator$OrderInfo;
      56: astore        6
      58: aload         5
      60: invokestatic  #5                  // Method org/apache/dubbo/common/extension/support/WrapperComparator$OrderInfo.access$000:(Lorg/apache/dubbo/common/extension/support/WrapperComparator$OrderInfo;)I
      63: istore        7
      65: aload         6
      67: invokestatic  #5                  // Method org/apache/dubbo/common/extension/support/WrapperComparator$OrderInfo.access$000:(Lorg/apache/dubbo/common/extension/support/WrapperComparator$OrderInfo;)I
      70: istore        8
      72: iload         7
      74: iload         8
      76: if_icmple     83
      79: iconst_1
      80: goto          84
      83: iconst_m1
      84: ireturn

  private org.apache.dubbo.common.extension.support.WrapperComparator$OrderInfo parseOrder(java.lang.Class<?>);
    Code:
       0: new           #6                  // class org/apache/dubbo/common/extension/support/WrapperComparator$OrderInfo
       3: dup
       4: aconst_null
       5: invokespecial #7                  // Method org/apache/dubbo/common/extension/support/WrapperComparator$OrderInfo."<init>":(Lorg/apache/dubbo/common/extension/support/WrapperComparator$1;)V
       8: astore_2
       9: aload_1
      10: ldc           #8                  // class org/apache/dubbo/common/extension/Activate
      12: invokevirtual #9                  // Method java/lang/Class.isAnnotationPresent:(Ljava/lang/Class;)Z
      15: ifeq          42
      18: aload_1
      19: ldc           #8                  // class org/apache/dubbo/common/extension/Activate
      21: invokevirtual #10                 // Method java/lang/Class.getAnnotation:(Ljava/lang/Class;)Ljava/lang/annotation/Annotation;
      24: checkcast     #8                  // class org/apache/dubbo/common/extension/Activate
      27: astore_3
      28: aload_2
      29: aload_3
      30: invokeinterface #11,  1           // InterfaceMethod org/apache/dubbo/common/extension/Activate.order:()I
      35: invokestatic  #12                 // Method org/apache/dubbo/common/extension/support/WrapperComparator$OrderInfo.access$002:(Lorg/apache/dubbo/common/extension/support/WrapperComparator$OrderInfo;I)I
      38: pop
      39: goto          105
      42: aload_1
      43: ldc           #13                 // class com/alibaba/dubbo/common/extension/Activate
      45: invokevirtual #9                  // Method java/lang/Class.isAnnotationPresent:(Ljava/lang/Class;)Z
      48: ifeq          75
      51: aload_1
      52: ldc           #13                 // class com/alibaba/dubbo/common/extension/Activate
      54: invokevirtual #10                 // Method java/lang/Class.getAnnotation:(Ljava/lang/Class;)Ljava/lang/annotation/Annotation;
      57: checkcast     #13                 // class com/alibaba/dubbo/common/extension/Activate
      60: astore_3
      61: aload_2
      62: aload_3
      63: invokeinterface #14,  1           // InterfaceMethod com/alibaba/dubbo/common/extension/Activate.order:()I
      68: invokestatic  #12                 // Method org/apache/dubbo/common/extension/support/WrapperComparator$OrderInfo.access$002:(Lorg/apache/dubbo/common/extension/support/WrapperComparator$OrderInfo;I)I
      71: pop
      72: goto          105
      75: aload_1
      76: ldc           #15                 // class org/apache/dubbo/common/extension/Wrapper
      78: invokevirtual #9                  // Method java/lang/Class.isAnnotationPresent:(Ljava/lang/Class;)Z
      81: ifeq          105
      84: aload_1
      85: ldc           #15                 // class org/apache/dubbo/common/extension/Wrapper
      87: invokevirtual #10                 // Method java/lang/Class.getAnnotation:(Ljava/lang/Class;)Ljava/lang/annotation/Annotation;
      90: checkcast     #15                 // class org/apache/dubbo/common/extension/Wrapper
      93: astore_3
      94: aload_2
      95: aload_3
      96: invokeinterface #16,  1           // InterfaceMethod org/apache/dubbo/common/extension/Wrapper.order:()I
     101: invokestatic  #12                 // Method org/apache/dubbo/common/extension/support/WrapperComparator$OrderInfo.access$002:(Lorg/apache/dubbo/common/extension/support/WrapperComparator$OrderInfo;I)I
     104: pop
     105: aload_2
     106: areturn

  static {};
    Code:
       0: new           #17                 // class org/apache/dubbo/common/extension/support/WrapperComparator
       3: dup
       4: invokespecial #18                 // Method "<init>":()V
       7: putstatic     #19                 // Field COMPARATOR:Ljava/util/Comparator;
      10: return
}
