Compiled from "WrapperComparator.java"
class org.apache.dubbo.common.extension.support.WrapperComparator$OrderInfo {
  private int order;

  private org.apache.dubbo.common.extension.support.WrapperComparator$OrderInfo();
    Code:
       0: aload_0
       1: invokespecial #3                  // Method java/lang/Object."<init>":()V
       4: return

  static int access$000(org.apache.dubbo.common.extension.support.WrapperComparator$OrderInfo);
    Code:
       0: aload_0
       1: getfield      #2                  // Field order:I
       4: ireturn

  org.apache.dubbo.common.extension.support.WrapperComparator$OrderInfo(org.apache.dubbo.common.extension.support.WrapperComparator$1);
    Code:
       0: aload_0
       1: invokespecial #1                  // Method "<init>":()V
       4: return

  static int access$002(org.apache.dubbo.common.extension.support.WrapperComparator$OrderInfo, int);
    Code:
       0: aload_0
       1: iload_1
       2: dup_x1
       3: putfield      #2                  // Field order:I
       6: ireturn
}
