Compiled from "CollectionTypeBuilder.java"
public class org.apache.dubbo.metadata.definition.builder.CollectionTypeBuilder implements org.apache.dubbo.metadata.definition.builder.TypeBuilder {
  public org.apache.dubbo.metadata.definition.builder.CollectionTypeBuilder();
    Code:
       0: aload_0
       1: invokespecial #1                  // Method java/lang/Object."<init>":()V
       4: return

  public boolean accept(java.lang.Class<?>);
    Code:
       0: aload_1
       1: ifnonnull     6
       4: iconst_0
       5: ireturn
       6: ldc           #2                  // class java/util/Collection
       8: aload_1
       9: invokevirtual #3                  // Method java/lang/Class.isAssignableFrom:(Ljava/lang/Class;)Z
      12: ireturn

  public org.apache.dubbo.metadata.definition.model.TypeDefinition build(java.lang.reflect.Type, java.lang.Class<?>, java.util.Map<java.lang.String, org.apache.dubbo.metadata.definition.model.TypeDefinition>);
    Code:
       0: aload_1
       1: instanceof    #4                  // class java/lang/reflect/ParameterizedType
       4: ifne          19
       7: new           #5                  // class org/apache/dubbo/metadata/definition/model/TypeDefinition
      10: dup
      11: aload_2
      12: invokevirtual #6                  // Method java/lang/Class.getCanonicalName:()Ljava/lang/String;
      15: invokespecial #7                  // Method org/apache/dubbo/metadata/definition/model/TypeDefinition."<init>":(Ljava/lang/String;)V
      18: areturn
      19: aload_1
      20: checkcast     #4                  // class java/lang/reflect/ParameterizedType
      23: astore        4
      25: aload         4
      27: invokeinterface #8,  1            // InterfaceMethod java/lang/reflect/ParameterizedType.getActualTypeArguments:()[Ljava/lang/reflect/Type;
      32: astore        5
      34: aload         5
      36: ifnull        46
      39: aload         5
      41: arraylength
      42: iconst_1
      43: if_icmpeq     93
      46: new           #9                  // class java/lang/IllegalArgumentException
      49: dup
      50: new           #10                 // class java/lang/StringBuilder
      53: dup
      54: invokespecial #11                 // Method java/lang/StringBuilder."<init>":()V
      57: ldc           #12                 // String [ServiceDefinitionBuilder] Collection type [{0}] with unexpected amount of arguments [{1}].
      59: invokevirtual #13                 // Method java/lang/StringBuilder.append:(Ljava/lang/String;)Ljava/lang/StringBuilder;
      62: aload         5
      64: invokestatic  #14                 // Method java/util/Arrays.toString:([Ljava/lang/Object;)Ljava/lang/String;
      67: invokevirtual #13                 // Method java/lang/StringBuilder.append:(Ljava/lang/String;)Ljava/lang/StringBuilder;
      70: invokevirtual #15                 // Method java/lang/StringBuilder.toString:()Ljava/lang/String;
      73: iconst_2
      74: anewarray     #16                 // class java/lang/Object
      77: dup
      78: iconst_0
      79: aload_1
      80: aastore
      81: dup
      82: iconst_1
      83: aload         5
      85: aastore
      86: invokestatic  #17                 // Method java/text/MessageFormat.format:(Ljava/lang/String;[Ljava/lang/Object;)Ljava/lang/String;
      89: invokespecial #18                 // Method java/lang/IllegalArgumentException."<init>":(Ljava/lang/String;)V
      92: athrow
      93: aload         4
      95: invokestatic  #19                 // Method org/apache/dubbo/metadata/definition/util/ClassUtils.getCanonicalNameForParameterizedType:(Ljava/lang/reflect/ParameterizedType;)Ljava/lang/String;
      98: astore        6
     100: aload_3
     101: aload         6
     103: invokeinterface #20,  2           // InterfaceMethod java/util/Map.get:(Ljava/lang/Object;)Ljava/lang/Object;
     108: checkcast     #5                  // class org/apache/dubbo/metadata/definition/model/TypeDefinition
     111: astore        7
     113: aload         7
     115: ifnull        121
     118: aload         7
     120: areturn
     121: new           #5                  // class org/apache/dubbo/metadata/definition/model/TypeDefinition
     124: dup
     125: aload         6
     127: invokespecial #7                  // Method org/apache/dubbo/metadata/definition/model/TypeDefinition."<init>":(Ljava/lang/String;)V
     130: astore        7
     132: aload_3
     133: aload         6
     135: aload         7
     137: invokeinterface #21,  3           // InterfaceMethod java/util/Map.put:(Ljava/lang/Object;Ljava/lang/Object;)Ljava/lang/Object;
     142: pop
     143: aload         5
     145: iconst_0
     146: aaload
     147: astore        8
     149: aconst_null
     150: astore        9
     152: aload         8
     154: instanceof    #4                  // class java/lang/reflect/ParameterizedType
     157: ifeq          188
     160: aload         8
     162: checkcast     #4                  // class java/lang/reflect/ParameterizedType
     165: invokeinterface #22,  1           // InterfaceMethod java/lang/reflect/ParameterizedType.getRawType:()Ljava/lang/reflect/Type;
     170: checkcast     #23                 // class java/lang/Class
     173: astore        10
     175: aload         8
     177: aload         10
     179: aload_3
     180: invokestatic  #24                 // Method org/apache/dubbo/metadata/definition/TypeDefinitionBuilder.build:(Ljava/lang/reflect/Type;Ljava/lang/Class;Ljava/util/Map;)Lorg/apache/dubbo/metadata/definition/model/TypeDefinition;
     183: astore        9
     185: goto          212
     188: aload         8
     190: instanceof    #23                 // class java/lang/Class
     193: ifeq          212
     196: aload         8
     198: checkcast     #23                 // class java/lang/Class
     201: astore        10
     203: aconst_null
     204: aload         10
     206: aload_3
     207: invokestatic  #24                 // Method org/apache/dubbo/metadata/definition/TypeDefinitionBuilder.build:(Ljava/lang/reflect/Type;Ljava/lang/Class;Ljava/util/Map;)Lorg/apache/dubbo/metadata/definition/model/TypeDefinition;
     210: astore        9
     212: aload         9
     214: ifnull        233
     217: aload         7
     219: invokevirtual #25                 // Method org/apache/dubbo/metadata/definition/model/TypeDefinition.getItems:()Ljava/util/List;
     222: aload         9
     224: invokevirtual #26                 // Method org/apache/dubbo/metadata/definition/model/TypeDefinition.getType:()Ljava/lang/String;
     227: invokeinterface #27,  2           // InterfaceMethod java/util/List.add:(Ljava/lang/Object;)Z
     232: pop
     233: aload         7
     235: areturn
}
