Compiled from "DefaultTypeBuilder.java"
public final class org.apache.dubbo.metadata.definition.builder.DefaultTypeBuilder {
  public static org.apache.dubbo.metadata.definition.model.TypeDefinition build(java.lang.Class<?>, java.util.Map<java.lang.String, org.apache.dubbo.metadata.definition.model.TypeDefinition>);
    Code:
       0: aload_0
       1: invokevirtual #1                  // Method java/lang/Class.getCanonicalName:()Ljava/lang/String;
       4: astore_2
       5: aload_1
       6: aload_2
       7: invokeinterface #2,  2            // InterfaceMethod java/util/Map.get:(Ljava/lang/Object;)Ljava/lang/Object;
      12: checkcast     #3                  // class org/apache/dubbo/metadata/definition/model/TypeDefinition
      15: astore_3
      16: aload_3
      17: ifnull        22
      20: aload_3
      21: areturn
      22: new           #3                  // class org/apache/dubbo/metadata/definition/model/TypeDefinition
      25: dup
      26: aload_2
      27: invokespecial #4                  // Method org/apache/dubbo/metadata/definition/model/TypeDefinition."<init>":(Ljava/lang/String;)V
      30: astore_3
      31: aload_1
      32: aload_2
      33: aload_3
      34: invokeinterface #5,  3            // InterfaceMethod java/util/Map.put:(Ljava/lang/Object;Ljava/lang/Object;)Ljava/lang/Object;
      39: pop
      40: aload_0
      41: invokestatic  #6                  // Method org/apache/dubbo/metadata/definition/util/JaketConfigurationUtils.needAnalyzing:(Ljava/lang/Class;)Z
      44: ifne          49
      47: aload_3
      48: areturn
      49: aload_0
      50: invokestatic  #7                  // Method org/apache/dubbo/metadata/definition/util/ClassUtils.getNonStaticFields:(Ljava/lang/Class;)Ljava/util/List;
      53: astore        4
      55: aload         4
      57: invokeinterface #8,  1            // InterfaceMethod java/util/List.iterator:()Ljava/util/Iterator;
      62: astore        5
      64: aload         5
      66: invokeinterface #9,  1            // InterfaceMethod java/util/Iterator.hasNext:()Z
      71: ifeq          137
      74: aload         5
      76: invokeinterface #10,  1           // InterfaceMethod java/util/Iterator.next:()Ljava/lang/Object;
      81: checkcast     #11                 // class java/lang/reflect/Field
      84: astore        6
      86: aload         6
      88: invokevirtual #12                 // Method java/lang/reflect/Field.getName:()Ljava/lang/String;
      91: astore        7
      93: aload         6
      95: invokevirtual #13                 // Method java/lang/reflect/Field.getType:()Ljava/lang/Class;
      98: astore        8
     100: aload         6
     102: invokevirtual #14                 // Method java/lang/reflect/Field.getGenericType:()Ljava/lang/reflect/Type;
     105: astore        9
     107: aload         9
     109: aload         8
     111: aload_1
     112: invokestatic  #15                 // Method org/apache/dubbo/metadata/definition/TypeDefinitionBuilder.build:(Ljava/lang/reflect/Type;Ljava/lang/Class;Ljava/util/Map;)Lorg/apache/dubbo/metadata/definition/model/TypeDefinition;
     115: astore        10
     117: aload_3
     118: invokevirtual #16                 // Method org/apache/dubbo/metadata/definition/model/TypeDefinition.getProperties:()Ljava/util/Map;
     121: aload         7
     123: aload         10
     125: invokevirtual #17                 // Method org/apache/dubbo/metadata/definition/model/TypeDefinition.getType:()Ljava/lang/String;
     128: invokeinterface #5,  3            // InterfaceMethod java/util/Map.put:(Ljava/lang/Object;Ljava/lang/Object;)Ljava/lang/Object;
     133: pop
     134: goto          64
     137: aload_3
     138: areturn

  private org.apache.dubbo.metadata.definition.builder.DefaultTypeBuilder();
    Code:
       0: aload_0
       1: invokespecial #18                 // Method java/lang/Object."<init>":()V
       4: return
}
