Compiled from "EnumTypeBuilder.java"
public class org.apache.dubbo.metadata.definition.builder.EnumTypeBuilder implements org.apache.dubbo.metadata.definition.builder.TypeBuilder {
  private static final org.apache.dubbo.common.logger.ErrorTypeAwareLogger logger;

  public org.apache.dubbo.metadata.definition.builder.EnumTypeBuilder();
    Code:
       0: aload_0
       1: invokespecial #2                  // Method java/lang/Object."<init>":()V
       4: return

  public boolean accept(java.lang.Class<?>);
    Code:
       0: aload_1
       1: ifnonnull     6
       4: iconst_0
       5: ireturn
       6: aload_1
       7: invokevirtual #3                  // Method java/lang/Class.isEnum:()Z
      10: ireturn

  public org.apache.dubbo.metadata.definition.model.TypeDefinition build(java.lang.reflect.Type, java.lang.Class<?>, java.util.Map<java.lang.String, org.apache.dubbo.metadata.definition.model.TypeDefinition>);
    Code:
       0: aload_2
       1: invokevirtual #4                  // Method java/lang/Class.getCanonicalName:()Ljava/lang/String;
       4: astore        4
       6: aload_3
       7: aload         4
       9: invokeinterface #5,  2            // InterfaceMethod java/util/Map.get:(Ljava/lang/Object;)Ljava/lang/Object;
      14: checkcast     #6                  // class org/apache/dubbo/metadata/definition/model/TypeDefinition
      17: astore        5
      19: aload         5
      21: ifnull        27
      24: aload         5
      26: areturn
      27: new           #6                  // class org/apache/dubbo/metadata/definition/model/TypeDefinition
      30: dup
      31: aload         4
      33: invokespecial #7                  // Method org/apache/dubbo/metadata/definition/model/TypeDefinition."<init>":(Ljava/lang/String;)V
      36: astore        5
      38: aload_3
      39: aload         4
      41: aload         5
      43: invokeinterface #8,  3            // InterfaceMethod java/util/Map.put:(Ljava/lang/Object;Ljava/lang/Object;)Ljava/lang/Object;
      48: pop
      49: aload_2
      50: ldc           #9                  // String values
      52: iconst_0
      53: anewarray     #10                 // class java/lang/Class
      56: invokevirtual #11                 // Method java/lang/Class.getDeclaredMethod:(Ljava/lang/String;[Ljava/lang/Class;)Ljava/lang/reflect/Method;
      59: astore        6
      61: aload         6
      63: iconst_1
      64: invokevirtual #12                 // Method java/lang/reflect/Method.setAccessible:(Z)V
      67: aload         6
      69: aload_2
      70: iconst_0
      71: anewarray     #13                 // class java/lang/Object
      74: invokevirtual #14                 // Method java/lang/reflect/Method.invoke:(Ljava/lang/Object;[Ljava/lang/Object;)Ljava/lang/Object;
      77: checkcast     #15                 // class "[Ljava/lang/Object;"
      80: checkcast     #15                 // class "[Ljava/lang/Object;"
      83: astore        7
      85: aload         7
      87: arraylength
      88: istore        8
      90: iconst_0
      91: istore        9
      93: iload         9
      95: iload         8
      97: if_icmpge     129
     100: aload         7
     102: iload         9
     104: aaload
     105: astore        10
     107: aload         5
     109: invokevirtual #16                 // Method org/apache/dubbo/metadata/definition/model/TypeDefinition.getEnums:()Ljava/util/List;
     112: aload         10
     114: invokevirtual #17                 // Method java/lang/Object.toString:()Ljava/lang/String;
     117: invokeinterface #18,  2           // InterfaceMethod java/util/List.add:(Ljava/lang/Object;)Z
     122: pop
     123: iinc          9, 1
     126: goto          93
     129: aload         5
     131: areturn
     132: astore        6
     134: getstatic     #20                 // Field logger:Lorg/apache/dubbo/common/logger/ErrorTypeAwareLogger;
     137: ldc           #21                 // String 0-12
     139: ldc           #22                 // String
     141: ldc           #22                 // String
     143: new           #23                 // class java/lang/StringBuilder
     146: dup
     147: invokespecial #24                 // Method java/lang/StringBuilder."<init>":()V
     150: ldc           #25                 // String There is an error while process class
     152: invokevirtual #26                 // Method java/lang/StringBuilder.append:(Ljava/lang/String;)Ljava/lang/StringBuilder;
     155: aload_2
     156: invokevirtual #27                 // Method java/lang/StringBuilder.append:(Ljava/lang/Object;)Ljava/lang/StringBuilder;
     159: invokevirtual #28                 // Method java/lang/StringBuilder.toString:()Ljava/lang/String;
     162: aload         6
     164: invokeinterface #29,  6           // InterfaceMethod org/apache/dubbo/common/logger/ErrorTypeAwareLogger.error:(Ljava/lang/String;Ljava/lang/String;Ljava/lang/String;Ljava/lang/String;Ljava/lang/Throwable;)V
     169: aload         5
     171: areturn
    Exception table:
       from    to  target type
          49   131   132   Class java/lang/Throwable

  static {};
    Code:
       0: ldc           #30                 // class org/apache/dubbo/metadata/definition/TypeDefinitionBuilder
       2: invokestatic  #31                 // Method org/apache/dubbo/common/logger/LoggerFactory.getErrorTypeAwareLogger:(Ljava/lang/Class;)Lorg/apache/dubbo/common/logger/ErrorTypeAwareLogger;
       5: putstatic     #20                 // Field logger:Lorg/apache/dubbo/common/logger/ErrorTypeAwareLogger;
       8: return
}
