Compiled from "ThreadPoolExhaustedEvent.java"
public class org.apache.dubbo.common.threadpool.event.ThreadPoolExhaustedEvent {
  final java.lang.String msg;

  public org.apache.dubbo.common.threadpool.event.ThreadPoolExhaustedEvent(java.lang.String);
    Code:
       0: aload_0
       1: invokespecial #1                  // Method java/lang/Object."<init>":()V
       4: aload_0
       5: aload_1
       6: putfield      #2                  // Field msg:Ljava/lang/String;
       9: return

  public java.lang.String getMsg();
    Code:
       0: aload_0
       1: getfield      #2                  // Field msg:Ljava/lang/String;
       4: areturn
}
