Compiled from "ConditionMatch.java"
public class org.apache.dubbo.rpc.cluster.configurator.parser.model.ConditionMatch {
  private org.apache.dubbo.rpc.cluster.router.mesh.rule.virtualservice.match.AddressMatch address;

  private org.apache.dubbo.rpc.cluster.router.mesh.rule.virtualservice.match.ListStringMatch service;

  private org.apache.dubbo.rpc.cluster.router.mesh.rule.virtualservice.match.ListStringMatch app;

  private java.util.List<org.apache.dubbo.rpc.cluster.configurator.parser.model.ParamMatch> param;

  public org.apache.dubbo.rpc.cluster.configurator.parser.model.ConditionMatch();
    Code:
       0: aload_0
       1: invokespecial #2                  // Method java/lang/Object."<init>":()V
       4: return

  public org.apache.dubbo.rpc.cluster.router.mesh.rule.virtualservice.match.AddressMatch getAddress();
    Code:
       0: aload_0
       1: getfield      #3                  // Field address:Lorg/apache/dubbo/rpc/cluster/router/mesh/rule/virtualservice/match/AddressMatch;
       4: areturn

  public void setAddress(org.apache.dubbo.rpc.cluster.router.mesh.rule.virtualservice.match.AddressMatch);
    Code:
       0: aload_0
       1: aload_1
       2: putfield      #3                  // Field address:Lorg/apache/dubbo/rpc/cluster/router/mesh/rule/virtualservice/match/AddressMatch;
       5: return

  public org.apache.dubbo.rpc.cluster.router.mesh.rule.virtualservice.match.ListStringMatch getService();
    Code:
       0: aload_0
       1: getfield      #4                  // Field service:Lorg/apache/dubbo/rpc/cluster/router/mesh/rule/virtualservice/match/ListStringMatch;
       4: areturn

  public void setService(org.apache.dubbo.rpc.cluster.router.mesh.rule.virtualservice.match.ListStringMatch);
    Code:
       0: aload_0
       1: aload_1
       2: putfield      #4                  // Field service:Lorg/apache/dubbo/rpc/cluster/router/mesh/rule/virtualservice/match/ListStringMatch;
       5: return

  public org.apache.dubbo.rpc.cluster.router.mesh.rule.virtualservice.match.ListStringMatch getApp();
    Code:
       0: aload_0
       1: getfield      #5                  // Field app:Lorg/apache/dubbo/rpc/cluster/router/mesh/rule/virtualservice/match/ListStringMatch;
       4: areturn

  public void setApp(org.apache.dubbo.rpc.cluster.router.mesh.rule.virtualservice.match.ListStringMatch);
    Code:
       0: aload_0
       1: aload_1
       2: putfield      #5                  // Field app:Lorg/apache/dubbo/rpc/cluster/router/mesh/rule/virtualservice/match/ListStringMatch;
       5: return

  public java.util.List<org.apache.dubbo.rpc.cluster.configurator.parser.model.ParamMatch> getParam();
    Code:
       0: aload_0
       1: getfield      #6                  // Field param:Ljava/util/List;
       4: areturn

  public void setParam(java.util.List<org.apache.dubbo.rpc.cluster.configurator.parser.model.ParamMatch>);
    Code:
       0: aload_0
       1: aload_1
       2: putfield      #6                  // Field param:Ljava/util/List;
       5: return

  public boolean isMatch(org.apache.dubbo.common.URL);
    Code:
       0: aload_0
       1: invokevirtual #7                  // Method getAddress:()Lorg/apache/dubbo/rpc/cluster/router/mesh/rule/virtualservice/match/AddressMatch;
       4: ifnull        23
       7: aload_0
       8: invokevirtual #7                  // Method getAddress:()Lorg/apache/dubbo/rpc/cluster/router/mesh/rule/virtualservice/match/AddressMatch;
      11: aload_1
      12: invokevirtual #8                  // Method org/apache/dubbo/common/URL.getAddress:()Ljava/lang/String;
      15: invokevirtual #9                  // Method org/apache/dubbo/rpc/cluster/router/mesh/rule/virtualservice/match/AddressMatch.isMatch:(Ljava/lang/String;)Z
      18: ifne          23
      21: iconst_0
      22: ireturn
      23: aload_0
      24: invokevirtual #10                 // Method getService:()Lorg/apache/dubbo/rpc/cluster/router/mesh/rule/virtualservice/match/ListStringMatch;
      27: ifnull        46
      30: aload_0
      31: invokevirtual #10                 // Method getService:()Lorg/apache/dubbo/rpc/cluster/router/mesh/rule/virtualservice/match/ListStringMatch;
      34: aload_1
      35: invokevirtual #11                 // Method org/apache/dubbo/common/URL.getServiceKey:()Ljava/lang/String;
      38: invokevirtual #12                 // Method org/apache/dubbo/rpc/cluster/router/mesh/rule/virtualservice/match/ListStringMatch.isMatch:(Ljava/lang/String;)Z
      41: ifne          46
      44: iconst_0
      45: ireturn
      46: aload_0
      47: invokevirtual #13                 // Method getApp:()Lorg/apache/dubbo/rpc/cluster/router/mesh/rule/virtualservice/match/ListStringMatch;
      50: ifnull        71
      53: aload_0
      54: invokevirtual #13                 // Method getApp:()Lorg/apache/dubbo/rpc/cluster/router/mesh/rule/virtualservice/match/ListStringMatch;
      57: aload_1
      58: ldc           #14                 // String application
      60: invokevirtual #15                 // Method org/apache/dubbo/common/URL.getParameter:(Ljava/lang/String;)Ljava/lang/String;
      63: invokevirtual #12                 // Method org/apache/dubbo/rpc/cluster/router/mesh/rule/virtualservice/match/ListStringMatch.isMatch:(Ljava/lang/String;)Z
      66: ifne          71
      69: iconst_0
      70: ireturn
      71: aload_0
      72: invokevirtual #16                 // Method getParam:()Ljava/util/List;
      75: ifnull        120
      78: aload_0
      79: getfield      #6                  // Field param:Ljava/util/List;
      82: invokeinterface #17,  1           // InterfaceMethod java/util/List.iterator:()Ljava/util/Iterator;
      87: astore_2
      88: aload_2
      89: invokeinterface #18,  1           // InterfaceMethod java/util/Iterator.hasNext:()Z
      94: ifeq          120
      97: aload_2
      98: invokeinterface #19,  1           // InterfaceMethod java/util/Iterator.next:()Ljava/lang/Object;
     103: checkcast     #20                 // class org/apache/dubbo/rpc/cluster/configurator/parser/model/ParamMatch
     106: astore_3
     107: aload_3
     108: aload_1
     109: invokevirtual #21                 // Method org/apache/dubbo/rpc/cluster/configurator/parser/model/ParamMatch.isMatch:(Lorg/apache/dubbo/common/URL;)Z
     112: ifne          117
     115: iconst_0
     116: ireturn
     117: goto          88
     120: iconst_1
     121: ireturn

  public java.lang.String toString();
    Code:
       0: new           #22                 // class java/lang/StringBuilder
       3: dup
       4: invokespecial #23                 // Method java/lang/StringBuilder."<init>":()V
       7: ldc           #24                 // String ConditionMatch{address=\'
       9: invokevirtual #25                 // Method java/lang/StringBuilder.append:(Ljava/lang/String;)Ljava/lang/StringBuilder;
      12: aload_0
      13: getfield      #3                  // Field address:Lorg/apache/dubbo/rpc/cluster/router/mesh/rule/virtualservice/match/AddressMatch;
      16: invokevirtual #26                 // Method java/lang/StringBuilder.append:(Ljava/lang/Object;)Ljava/lang/StringBuilder;
      19: bipush        39
      21: invokevirtual #27                 // Method java/lang/StringBuilder.append:(C)Ljava/lang/StringBuilder;
      24: ldc           #28                 // String , service=\'
      26: invokevirtual #25                 // Method java/lang/StringBuilder.append:(Ljava/lang/String;)Ljava/lang/StringBuilder;
      29: aload_0
      30: getfield      #4                  // Field service:Lorg/apache/dubbo/rpc/cluster/router/mesh/rule/virtualservice/match/ListStringMatch;
      33: invokevirtual #26                 // Method java/lang/StringBuilder.append:(Ljava/lang/Object;)Ljava/lang/StringBuilder;
      36: bipush        39
      38: invokevirtual #27                 // Method java/lang/StringBuilder.append:(C)Ljava/lang/StringBuilder;
      41: ldc           #29                 // String , app=\'
      43: invokevirtual #25                 // Method java/lang/StringBuilder.append:(Ljava/lang/String;)Ljava/lang/StringBuilder;
      46: aload_0
      47: getfield      #5                  // Field app:Lorg/apache/dubbo/rpc/cluster/router/mesh/rule/virtualservice/match/ListStringMatch;
      50: invokevirtual #26                 // Method java/lang/StringBuilder.append:(Ljava/lang/Object;)Ljava/lang/StringBuilder;
      53: bipush        39
      55: invokevirtual #27                 // Method java/lang/StringBuilder.append:(C)Ljava/lang/StringBuilder;
      58: ldc           #30                 // String , param=\'
      60: invokevirtual #25                 // Method java/lang/StringBuilder.append:(Ljava/lang/String;)Ljava/lang/StringBuilder;
      63: aload_0
      64: getfield      #6                  // Field param:Ljava/util/List;
      67: invokevirtual #26                 // Method java/lang/StringBuilder.append:(Ljava/lang/Object;)Ljava/lang/StringBuilder;
      70: bipush        39
      72: invokevirtual #27                 // Method java/lang/StringBuilder.append:(C)Ljava/lang/StringBuilder;
      75: bipush        125
      77: invokevirtual #27                 // Method java/lang/StringBuilder.append:(C)Ljava/lang/StringBuilder;
      80: invokevirtual #31                 // Method java/lang/StringBuilder.toString:()Ljava/lang/String;
      83: areturn
}
