Compiled from "ConfiguratorConfig.java"
public class org.apache.dubbo.rpc.cluster.configurator.parser.model.ConfiguratorConfig {
  public static final java.lang.String MATCH_CONDITION;

  public static final java.lang.String SCOPE_SERVICE;

  public static final java.lang.String SCOPE_APPLICATION;

  public static final java.lang.String CONFIG_VERSION_KEY;

  public static final java.lang.String SCOPE_KEY;

  public static final java.lang.String CONFIG_KEY;

  public static final java.lang.String ENABLED_KEY;

  public static final java.lang.String CONFIGS_KEY;

  private java.lang.String configVersion;

  private java.lang.String scope;

  private java.lang.String key;

  private java.lang.Boolean enabled;

  private java.util.List<org.apache.dubbo.rpc.cluster.configurator.parser.model.ConfigItem> configs;

  public org.apache.dubbo.rpc.cluster.configurator.parser.model.ConfiguratorConfig();
    Code:
       0: aload_0
       1: invokespecial #1                  // Method java/lang/Object."<init>":()V
       4: aload_0
       5: iconst_1
       6: invokestatic  #2                  // Method java/lang/Boolean.valueOf:(Z)Ljava/lang/Boolean;
       9: putfield      #3                  // Field enabled:Ljava/lang/Boolean;
      12: return

  public static org.apache.dubbo.rpc.cluster.configurator.parser.model.ConfiguratorConfig parseFromMap(java.util.Map<java.lang.String, java.lang.Object>);
    Code:
       0: new           #4                  // class org/apache/dubbo/rpc/cluster/configurator/parser/model/ConfiguratorConfig
       3: dup
       4: invokespecial #5                  // Method "<init>":()V
       7: astore_1
       8: aload_1
       9: aload_0
      10: ldc           #6                  // String configVersion
      12: invokeinterface #7,  2            // InterfaceMethod java/util/Map.get:(Ljava/lang/Object;)Ljava/lang/Object;
      17: checkcast     #8                  // class java/lang/String
      20: invokevirtual #9                  // Method setConfigVersion:(Ljava/lang/String;)V
      23: aload_1
      24: aload_0
      25: ldc           #10                 // String scope
      27: invokeinterface #7,  2            // InterfaceMethod java/util/Map.get:(Ljava/lang/Object;)Ljava/lang/Object;
      32: checkcast     #8                  // class java/lang/String
      35: invokevirtual #11                 // Method setScope:(Ljava/lang/String;)V
      38: aload_1
      39: aload_0
      40: ldc           #12                 // String key
      42: invokeinterface #7,  2            // InterfaceMethod java/util/Map.get:(Ljava/lang/Object;)Ljava/lang/Object;
      47: checkcast     #8                  // class java/lang/String
      50: invokevirtual #13                 // Method setKey:(Ljava/lang/String;)V
      53: aload_0
      54: ldc           #14                 // String enabled
      56: invokeinterface #7,  2            // InterfaceMethod java/util/Map.get:(Ljava/lang/Object;)Ljava/lang/Object;
      61: astore_2
      62: aload_2
      63: ifnull        80
      66: aload_1
      67: aload_2
      68: invokevirtual #15                 // Method java/lang/Object.toString:()Ljava/lang/String;
      71: invokestatic  #16                 // Method java/lang/Boolean.parseBoolean:(Ljava/lang/String;)Z
      74: invokestatic  #2                  // Method java/lang/Boolean.valueOf:(Z)Ljava/lang/Boolean;
      77: invokevirtual #17                 // Method setEnabled:(Ljava/lang/Boolean;)V
      80: aload_0
      81: ldc           #18                 // String configs
      83: invokeinterface #7,  2            // InterfaceMethod java/util/Map.get:(Ljava/lang/Object;)Ljava/lang/Object;
      88: astore_3
      89: aload_3
      90: ifnull        139
      93: ldc           #19                 // class java/util/List
      95: aload_3
      96: invokevirtual #20                 // Method java/lang/Object.getClass:()Ljava/lang/Class;
      99: invokevirtual #21                 // Method java/lang/Class.isAssignableFrom:(Ljava/lang/Class;)Z
     102: ifeq          139
     105: aload_1
     106: aload_3
     107: checkcast     #19                 // class java/util/List
     110: invokeinterface #22,  1           // InterfaceMethod java/util/List.stream:()Ljava/util/stream/Stream;
     115: invokedynamic #23,  0             // InvokeDynamic #0:apply:()Ljava/util/function/Function;
     120: invokeinterface #24,  2           // InterfaceMethod java/util/stream/Stream.map:(Ljava/util/function/Function;)Ljava/util/stream/Stream;
     125: invokestatic  #25                 // Method java/util/stream/Collectors.toList:()Ljava/util/stream/Collector;
     128: invokeinterface #26,  2           // InterfaceMethod java/util/stream/Stream.collect:(Ljava/util/stream/Collector;)Ljava/lang/Object;
     133: checkcast     #19                 // class java/util/List
     136: invokevirtual #27                 // Method setConfigs:(Ljava/util/List;)V
     139: aload_1
     140: areturn

  public java.lang.String getConfigVersion();
    Code:
       0: aload_0
       1: getfield      #28                 // Field configVersion:Ljava/lang/String;
       4: areturn

  public void setConfigVersion(java.lang.String);
    Code:
       0: aload_0
       1: aload_1
       2: putfield      #28                 // Field configVersion:Ljava/lang/String;
       5: return

  public java.lang.String getScope();
    Code:
       0: aload_0
       1: getfield      #29                 // Field scope:Ljava/lang/String;
       4: areturn

  public void setScope(java.lang.String);
    Code:
       0: aload_0
       1: aload_1
       2: putfield      #29                 // Field scope:Ljava/lang/String;
       5: return

  public java.lang.String getKey();
    Code:
       0: aload_0
       1: getfield      #30                 // Field key:Ljava/lang/String;
       4: areturn

  public void setKey(java.lang.String);
    Code:
       0: aload_0
       1: aload_1
       2: putfield      #30                 // Field key:Ljava/lang/String;
       5: return

  public java.lang.Boolean getEnabled();
    Code:
       0: aload_0
       1: getfield      #3                  // Field enabled:Ljava/lang/Boolean;
       4: areturn

  public void setEnabled(java.lang.Boolean);
    Code:
       0: aload_0
       1: aload_1
       2: putfield      #3                  // Field enabled:Ljava/lang/Boolean;
       5: return

  public java.util.List<org.apache.dubbo.rpc.cluster.configurator.parser.model.ConfigItem> getConfigs();
    Code:
       0: aload_0
       1: getfield      #31                 // Field configs:Ljava/util/List;
       4: areturn

  public void setConfigs(java.util.List<org.apache.dubbo.rpc.cluster.configurator.parser.model.ConfigItem>);
    Code:
       0: aload_0
       1: aload_1
       2: putfield      #31                 // Field configs:Ljava/util/List;
       5: return
}
