Compiled from "ParamMatch.java"
public class org.apache.dubbo.rpc.cluster.configurator.parser.model.ParamMatch {
  private java.lang.String key;

  private org.apache.dubbo.rpc.cluster.router.mesh.rule.virtualservice.match.StringMatch value;

  public org.apache.dubbo.rpc.cluster.configurator.parser.model.ParamMatch();
    Code:
       0: aload_0
       1: invokespecial #1                  // Method java/lang/Object."<init>":()V
       4: return

  public java.lang.String getKey();
    Code:
       0: aload_0
       1: getfield      #2                  // Field key:Ljava/lang/String;
       4: areturn

  public void setKey(java.lang.String);
    Code:
       0: aload_0
       1: aload_1
       2: putfield      #2                  // Field key:Ljava/lang/String;
       5: return

  public org.apache.dubbo.rpc.cluster.router.mesh.rule.virtualservice.match.StringMatch getValue();
    Code:
       0: aload_0
       1: getfield      #3                  // Field value:Lorg/apache/dubbo/rpc/cluster/router/mesh/rule/virtualservice/match/StringMatch;
       4: areturn

  public void setValue(org.apache.dubbo.rpc.cluster.router.mesh.rule.virtualservice.match.StringMatch);
    Code:
       0: aload_0
       1: aload_1
       2: putfield      #3                  // Field value:Lorg/apache/dubbo/rpc/cluster/router/mesh/rule/virtualservice/match/StringMatch;
       5: return

  public boolean isMatch(org.apache.dubbo.common.URL);
    Code:
       0: aload_0
       1: getfield      #2                  // Field key:Ljava/lang/String;
       4: ifnonnull     9
       7: iconst_0
       8: ireturn
       9: aload_1
      10: aload_0
      11: getfield      #2                  // Field key:Ljava/lang/String;
      14: invokevirtual #4                  // Method org/apache/dubbo/common/URL.getParameter:(Ljava/lang/String;)Ljava/lang/String;
      17: astore_2
      18: aload_2
      19: ifnull        37
      22: aload_0
      23: getfield      #3                  // Field value:Lorg/apache/dubbo/rpc/cluster/router/mesh/rule/virtualservice/match/StringMatch;
      26: aload_2
      27: invokevirtual #5                  // Method org/apache/dubbo/rpc/cluster/router/mesh/rule/virtualservice/match/StringMatch.isMatch:(Ljava/lang/String;)Z
      30: ifeq          37
      33: iconst_1
      34: goto          38
      37: iconst_0
      38: ireturn

  public java.lang.String toString();
    Code:
       0: new           #6                  // class java/lang/StringBuilder
       3: dup
       4: invokespecial #7                  // Method java/lang/StringBuilder."<init>":()V
       7: ldc           #8                  // String ParamMatch{key=\'
       9: invokevirtual #9                  // Method java/lang/StringBuilder.append:(Ljava/lang/String;)Ljava/lang/StringBuilder;
      12: aload_0
      13: getfield      #2                  // Field key:Ljava/lang/String;
      16: invokevirtual #9                  // Method java/lang/StringBuilder.append:(Ljava/lang/String;)Ljava/lang/StringBuilder;
      19: bipush        39
      21: invokevirtual #10                 // Method java/lang/StringBuilder.append:(C)Ljava/lang/StringBuilder;
      24: ldc           #11                 // String , value=\'
      26: invokevirtual #9                  // Method java/lang/StringBuilder.append:(Ljava/lang/String;)Ljava/lang/StringBuilder;
      29: aload_0
      30: getfield      #3                  // Field value:Lorg/apache/dubbo/rpc/cluster/router/mesh/rule/virtualservice/match/StringMatch;
      33: invokevirtual #12                 // Method java/lang/StringBuilder.append:(Ljava/lang/Object;)Ljava/lang/StringBuilder;
      36: bipush        39
      38: invokevirtual #10                 // Method java/lang/StringBuilder.append:(C)Ljava/lang/StringBuilder;
      41: bipush        125
      43: invokevirtual #10                 // Method java/lang/StringBuilder.append:(C)Ljava/lang/StringBuilder;
      46: invokevirtual #13                 // Method java/lang/StringBuilder.toString:()Ljava/lang/String;
      49: areturn
}
