Compiled from "IstioCertificateResponse.java"
public final class istio.v1.auth.IstioCertificateResponse$Builder extends com.google.protobuf.GeneratedMessageV3$Builder<istio.v1.auth.IstioCertificateResponse$Builder> implements istio.v1.auth.IstioCertificateResponseOrBuilder {
  private int bitField0_;

  private com.google.protobuf.LazyStringArrayList certChain_;

  public static final com.google.protobuf.Descriptors$Descriptor getDescriptor();
    Code:
       0: getstatic     #3                  // Field istio/v1/auth/Ca.internal_static_istio_v1_auth_IstioCertificateResponse_descriptor:Lcom/google/protobuf/Descriptors$Descriptor;
       3: areturn

  protected com.google.protobuf.GeneratedMessageV3$FieldAccessorTable internalGetFieldAccessorTable();
    Code:
       0: getstatic     #4                  // Field istio/v1/auth/Ca.internal_static_istio_v1_auth_IstioCertificateResponse_fieldAccessorTable:Lcom/google/protobuf/GeneratedMessageV3$FieldAccessorTable;
       3: ldc           #5                  // class istio/v1/auth/IstioCertificateResponse
       5: ldc           #6                  // class istio/v1/auth/IstioCertificateResponse$Builder
       7: invokevirtual #7                  // Method com/google/protobuf/GeneratedMessageV3$FieldAccessorTable.ensureFieldAccessorsInitialized:(Ljava/lang/Class;Ljava/lang/Class;)Lcom/google/protobuf/GeneratedMessageV3$FieldAccessorTable;
      10: areturn

  private istio.v1.auth.IstioCertificateResponse$Builder();
    Code:
       0: aload_0
       1: invokespecial #8                  // Method com/google/protobuf/GeneratedMessageV3$Builder."<init>":()V
       4: aload_0
       5: invokestatic  #9                  // Method com/google/protobuf/LazyStringArrayList.emptyList:()Lcom/google/protobuf/LazyStringArrayList;
       8: putfield      #10                 // Field certChain_:Lcom/google/protobuf/LazyStringArrayList;
      11: return

  private istio.v1.auth.IstioCertificateResponse$Builder(com.google.protobuf.GeneratedMessageV3$BuilderParent);
    Code:
       0: aload_0
       1: aload_1
       2: invokespecial #11                 // Method com/google/protobuf/GeneratedMessageV3$Builder."<init>":(Lcom/google/protobuf/GeneratedMessageV3$BuilderParent;)V
       5: aload_0
       6: invokestatic  #9                  // Method com/google/protobuf/LazyStringArrayList.emptyList:()Lcom/google/protobuf/LazyStringArrayList;
       9: putfield      #10                 // Field certChain_:Lcom/google/protobuf/LazyStringArrayList;
      12: return

  public istio.v1.auth.IstioCertificateResponse$Builder clear();
    Code:
       0: aload_0
       1: invokespecial #12                 // Method com/google/protobuf/GeneratedMessageV3$Builder.clear:()Lcom/google/protobuf/GeneratedMessageV3$Builder;
       4: pop
       5: aload_0
       6: iconst_0
       7: putfield      #13                 // Field bitField0_:I
      10: aload_0
      11: invokestatic  #9                  // Method com/google/protobuf/LazyStringArrayList.emptyList:()Lcom/google/protobuf/LazyStringArrayList;
      14: putfield      #10                 // Field certChain_:Lcom/google/protobuf/LazyStringArrayList;
      17: aload_0
      18: areturn

  public com.google.protobuf.Descriptors$Descriptor getDescriptorForType();
    Code:
       0: getstatic     #3                  // Field istio/v1/auth/Ca.internal_static_istio_v1_auth_IstioCertificateResponse_descriptor:Lcom/google/protobuf/Descriptors$Descriptor;
       3: areturn

  public istio.v1.auth.IstioCertificateResponse getDefaultInstanceForType();
    Code:
       0: invokestatic  #14                 // Method istio/v1/auth/IstioCertificateResponse.getDefaultInstance:()Listio/v1/auth/IstioCertificateResponse;
       3: areturn

  public istio.v1.auth.IstioCertificateResponse build();
    Code:
       0: aload_0
       1: invokevirtual #15                 // Method buildPartial:()Listio/v1/auth/IstioCertificateResponse;
       4: astore_1
       5: aload_1
       6: invokevirtual #16                 // Method istio/v1/auth/IstioCertificateResponse.isInitialized:()Z
       9: ifne          17
      12: aload_1
      13: invokestatic  #17                 // Method newUninitializedMessageException:(Lcom/google/protobuf/Message;)Lcom/google/protobuf/UninitializedMessageException;
      16: athrow
      17: aload_1
      18: areturn

  public istio.v1.auth.IstioCertificateResponse buildPartial();
    Code:
       0: new           #5                  // class istio/v1/auth/IstioCertificateResponse
       3: dup
       4: aload_0
       5: aconst_null
       6: invokespecial #18                 // Method istio/v1/auth/IstioCertificateResponse."<init>":(Lcom/google/protobuf/GeneratedMessageV3$Builder;Listio/v1/auth/IstioCertificateResponse$1;)V
       9: astore_1
      10: aload_0
      11: getfield      #13                 // Field bitField0_:I
      14: ifeq          22
      17: aload_0
      18: aload_1
      19: invokespecial #19                 // Method buildPartial0:(Listio/v1/auth/IstioCertificateResponse;)V
      22: aload_0
      23: invokevirtual #20                 // Method onBuilt:()V
      26: aload_1
      27: areturn

  private void buildPartial0(istio.v1.auth.IstioCertificateResponse);
    Code:
       0: aload_0
       1: getfield      #13                 // Field bitField0_:I
       4: istore_2
       5: iload_2
       6: iconst_1
       7: iand
       8: ifeq          27
      11: aload_0
      12: getfield      #10                 // Field certChain_:Lcom/google/protobuf/LazyStringArrayList;
      15: invokevirtual #21                 // Method com/google/protobuf/LazyStringArrayList.makeImmutable:()V
      18: aload_1
      19: aload_0
      20: getfield      #10                 // Field certChain_:Lcom/google/protobuf/LazyStringArrayList;
      23: invokestatic  #22                 // Method istio/v1/auth/IstioCertificateResponse.access$302:(Listio/v1/auth/IstioCertificateResponse;Lcom/google/protobuf/LazyStringArrayList;)Lcom/google/protobuf/LazyStringArrayList;
      26: pop
      27: return

  public istio.v1.auth.IstioCertificateResponse$Builder mergeFrom(com.google.protobuf.Message);
    Code:
       0: aload_1
       1: instanceof    #5                  // class istio/v1/auth/IstioCertificateResponse
       4: ifeq          16
       7: aload_0
       8: aload_1
       9: checkcast     #5                  // class istio/v1/auth/IstioCertificateResponse
      12: invokevirtual #23                 // Method mergeFrom:(Listio/v1/auth/IstioCertificateResponse;)Listio/v1/auth/IstioCertificateResponse$Builder;
      15: areturn
      16: aload_0
      17: aload_1
      18: invokespecial #24                 // Method com/google/protobuf/GeneratedMessageV3$Builder.mergeFrom:(Lcom/google/protobuf/Message;)Lcom/google/protobuf/AbstractMessage$Builder;
      21: pop
      22: aload_0
      23: areturn

  public istio.v1.auth.IstioCertificateResponse$Builder mergeFrom(istio.v1.auth.IstioCertificateResponse);
    Code:
       0: aload_1
       1: invokestatic  #14                 // Method istio/v1/auth/IstioCertificateResponse.getDefaultInstance:()Listio/v1/auth/IstioCertificateResponse;
       4: if_acmpne     9
       7: aload_0
       8: areturn
       9: aload_1
      10: invokestatic  #25                 // Method istio/v1/auth/IstioCertificateResponse.access$300:(Listio/v1/auth/IstioCertificateResponse;)Lcom/google/protobuf/LazyStringArrayList;
      13: invokevirtual #26                 // Method com/google/protobuf/LazyStringArrayList.isEmpty:()Z
      16: ifne          70
      19: aload_0
      20: getfield      #10                 // Field certChain_:Lcom/google/protobuf/LazyStringArrayList;
      23: invokevirtual #26                 // Method com/google/protobuf/LazyStringArrayList.isEmpty:()Z
      26: ifeq          50
      29: aload_0
      30: aload_1
      31: invokestatic  #25                 // Method istio/v1/auth/IstioCertificateResponse.access$300:(Listio/v1/auth/IstioCertificateResponse;)Lcom/google/protobuf/LazyStringArrayList;
      34: putfield      #10                 // Field certChain_:Lcom/google/protobuf/LazyStringArrayList;
      37: aload_0
      38: dup
      39: getfield      #13                 // Field bitField0_:I
      42: iconst_1
      43: ior
      44: putfield      #13                 // Field bitField0_:I
      47: goto          66
      50: aload_0
      51: invokespecial #27                 // Method ensureCertChainIsMutable:()V
      54: aload_0
      55: getfield      #10                 // Field certChain_:Lcom/google/protobuf/LazyStringArrayList;
      58: aload_1
      59: invokestatic  #25                 // Method istio/v1/auth/IstioCertificateResponse.access$300:(Listio/v1/auth/IstioCertificateResponse;)Lcom/google/protobuf/LazyStringArrayList;
      62: invokevirtual #28                 // Method com/google/protobuf/LazyStringArrayList.addAll:(Ljava/util/Collection;)Z
      65: pop
      66: aload_0
      67: invokevirtual #29                 // Method onChanged:()V
      70: aload_0
      71: aload_1
      72: invokevirtual #30                 // Method istio/v1/auth/IstioCertificateResponse.getUnknownFields:()Lcom/google/protobuf/UnknownFieldSet;
      75: invokevirtual #31                 // Method mergeUnknownFields:(Lcom/google/protobuf/UnknownFieldSet;)Listio/v1/auth/IstioCertificateResponse$Builder;
      78: pop
      79: aload_0
      80: invokevirtual #29                 // Method onChanged:()V
      83: aload_0
      84: areturn

  public final boolean isInitialized();
    Code:
       0: iconst_1
       1: ireturn

  public istio.v1.auth.IstioCertificateResponse$Builder mergeFrom(com.google.protobuf.CodedInputStream, com.google.protobuf.ExtensionRegistryLite) throws java.io.IOException;
    Code:
       0: aload_2
       1: ifnonnull     12
       4: new           #32                 // class java/lang/NullPointerException
       7: dup
       8: invokespecial #33                 // Method java/lang/NullPointerException."<init>":()V
      11: athrow
      12: iconst_0
      13: istore_3
      14: iload_3
      15: ifne          96
      18: aload_1
      19: invokevirtual #34                 // Method com/google/protobuf/CodedInputStream.readTag:()I
      22: istore        4
      24: iload         4
      26: lookupswitch  { // 2
                     0: 52
                    10: 57
               default: 80
          }
      52: iconst_1
      53: istore_3
      54: goto          93
      57: aload_1
      58: invokevirtual #35                 // Method com/google/protobuf/CodedInputStream.readStringRequireUtf8:()Ljava/lang/String;
      61: astore        5
      63: aload_0
      64: invokespecial #27                 // Method ensureCertChainIsMutable:()V
      67: aload_0
      68: getfield      #10                 // Field certChain_:Lcom/google/protobuf/LazyStringArrayList;
      71: aload         5
      73: invokevirtual #36                 // Method com/google/protobuf/LazyStringArrayList.add:(Ljava/lang/Object;)Z
      76: pop
      77: goto          93
      80: aload_0
      81: aload_1
      82: aload_2
      83: iload         4
      85: invokespecial #37                 // Method com/google/protobuf/GeneratedMessageV3$Builder.parseUnknownField:(Lcom/google/protobuf/CodedInputStream;Lcom/google/protobuf/ExtensionRegistryLite;I)Z
      88: ifne          93
      91: iconst_1
      92: istore_3
      93: goto          14
      96: aload_0
      97: invokevirtual #29                 // Method onChanged:()V
     100: goto          118
     103: astore_3
     104: aload_3
     105: invokevirtual #39                 // Method com/google/protobuf/InvalidProtocolBufferException.unwrapIOException:()Ljava/io/IOException;
     108: athrow
     109: astore        6
     111: aload_0
     112: invokevirtual #29                 // Method onChanged:()V
     115: aload         6
     117: athrow
     118: aload_0
     119: areturn
    Exception table:
       from    to  target type
          12    96   103   Class com/google/protobuf/InvalidProtocolBufferException
          12    96   109   any
         103   111   109   any

  private void ensureCertChainIsMutable();
    Code:
       0: aload_0
       1: getfield      #10                 // Field certChain_:Lcom/google/protobuf/LazyStringArrayList;
       4: invokevirtual #40                 // Method com/google/protobuf/LazyStringArrayList.isModifiable:()Z
       7: ifne          25
      10: aload_0
      11: new           #41                 // class com/google/protobuf/LazyStringArrayList
      14: dup
      15: aload_0
      16: getfield      #10                 // Field certChain_:Lcom/google/protobuf/LazyStringArrayList;
      19: invokespecial #42                 // Method com/google/protobuf/LazyStringArrayList."<init>":(Lcom/google/protobuf/LazyStringList;)V
      22: putfield      #10                 // Field certChain_:Lcom/google/protobuf/LazyStringArrayList;
      25: aload_0
      26: dup
      27: getfield      #13                 // Field bitField0_:I
      30: iconst_1
      31: ior
      32: putfield      #13                 // Field bitField0_:I
      35: return

  public com.google.protobuf.ProtocolStringList getCertChainList();
    Code:
       0: aload_0
       1: getfield      #10                 // Field certChain_:Lcom/google/protobuf/LazyStringArrayList;
       4: invokevirtual #21                 // Method com/google/protobuf/LazyStringArrayList.makeImmutable:()V
       7: aload_0
       8: getfield      #10                 // Field certChain_:Lcom/google/protobuf/LazyStringArrayList;
      11: areturn

  public int getCertChainCount();
    Code:
       0: aload_0
       1: getfield      #10                 // Field certChain_:Lcom/google/protobuf/LazyStringArrayList;
       4: invokevirtual #43                 // Method com/google/protobuf/LazyStringArrayList.size:()I
       7: ireturn

  public java.lang.String getCertChain(int);
    Code:
       0: aload_0
       1: getfield      #10                 // Field certChain_:Lcom/google/protobuf/LazyStringArrayList;
       4: iload_1
       5: invokevirtual #44                 // Method com/google/protobuf/LazyStringArrayList.get:(I)Ljava/lang/String;
       8: areturn

  public com.google.protobuf.ByteString getCertChainBytes(int);
    Code:
       0: aload_0
       1: getfield      #10                 // Field certChain_:Lcom/google/protobuf/LazyStringArrayList;
       4: iload_1
       5: invokevirtual #45                 // Method com/google/protobuf/LazyStringArrayList.getByteString:(I)Lcom/google/protobuf/ByteString;
       8: areturn

  public istio.v1.auth.IstioCertificateResponse$Builder setCertChain(int, java.lang.String);
    Code:
       0: aload_2
       1: ifnonnull     12
       4: new           #32                 // class java/lang/NullPointerException
       7: dup
       8: invokespecial #33                 // Method java/lang/NullPointerException."<init>":()V
      11: athrow
      12: aload_0
      13: invokespecial #27                 // Method ensureCertChainIsMutable:()V
      16: aload_0
      17: getfield      #10                 // Field certChain_:Lcom/google/protobuf/LazyStringArrayList;
      20: iload_1
      21: aload_2
      22: invokevirtual #46                 // Method com/google/protobuf/LazyStringArrayList.set:(ILjava/lang/String;)Ljava/lang/String;
      25: pop
      26: aload_0
      27: dup
      28: getfield      #13                 // Field bitField0_:I
      31: iconst_1
      32: ior
      33: putfield      #13                 // Field bitField0_:I
      36: aload_0
      37: invokevirtual #29                 // Method onChanged:()V
      40: aload_0
      41: areturn

  public istio.v1.auth.IstioCertificateResponse$Builder addCertChain(java.lang.String);
    Code:
       0: aload_1
       1: ifnonnull     12
       4: new           #32                 // class java/lang/NullPointerException
       7: dup
       8: invokespecial #33                 // Method java/lang/NullPointerException."<init>":()V
      11: athrow
      12: aload_0
      13: invokespecial #27                 // Method ensureCertChainIsMutable:()V
      16: aload_0
      17: getfield      #10                 // Field certChain_:Lcom/google/protobuf/LazyStringArrayList;
      20: aload_1
      21: invokevirtual #36                 // Method com/google/protobuf/LazyStringArrayList.add:(Ljava/lang/Object;)Z
      24: pop
      25: aload_0
      26: dup
      27: getfield      #13                 // Field bitField0_:I
      30: iconst_1
      31: ior
      32: putfield      #13                 // Field bitField0_:I
      35: aload_0
      36: invokevirtual #29                 // Method onChanged:()V
      39: aload_0
      40: areturn

  public istio.v1.auth.IstioCertificateResponse$Builder addAllCertChain(java.lang.Iterable<java.lang.String>);
    Code:
       0: aload_0
       1: invokespecial #27                 // Method ensureCertChainIsMutable:()V
       4: aload_1
       5: aload_0
       6: getfield      #10                 // Field certChain_:Lcom/google/protobuf/LazyStringArrayList;
       9: invokestatic  #47                 // Method com/google/protobuf/AbstractMessageLite$Builder.addAll:(Ljava/lang/Iterable;Ljava/util/List;)V
      12: aload_0
      13: dup
      14: getfield      #13                 // Field bitField0_:I
      17: iconst_1
      18: ior
      19: putfield      #13                 // Field bitField0_:I
      22: aload_0
      23: invokevirtual #29                 // Method onChanged:()V
      26: aload_0
      27: areturn

  public istio.v1.auth.IstioCertificateResponse$Builder clearCertChain();
    Code:
       0: aload_0
       1: invokestatic  #9                  // Method com/google/protobuf/LazyStringArrayList.emptyList:()Lcom/google/protobuf/LazyStringArrayList;
       4: putfield      #10                 // Field certChain_:Lcom/google/protobuf/LazyStringArrayList;
       7: aload_0
       8: aload_0
       9: getfield      #13                 // Field bitField0_:I
      12: bipush        -2
      14: iand
      15: putfield      #13                 // Field bitField0_:I
      18: aload_0
      19: invokevirtual #29                 // Method onChanged:()V
      22: aload_0
      23: areturn

  public istio.v1.auth.IstioCertificateResponse$Builder addCertChainBytes(com.google.protobuf.ByteString);
    Code:
       0: aload_1
       1: ifnonnull     12
       4: new           #32                 // class java/lang/NullPointerException
       7: dup
       8: invokespecial #33                 // Method java/lang/NullPointerException."<init>":()V
      11: athrow
      12: aload_1
      13: invokestatic  #48                 // Method istio/v1/auth/IstioCertificateResponse.access$400:(Lcom/google/protobuf/ByteString;)V
      16: aload_0
      17: invokespecial #27                 // Method ensureCertChainIsMutable:()V
      20: aload_0
      21: getfield      #10                 // Field certChain_:Lcom/google/protobuf/LazyStringArrayList;
      24: aload_1
      25: invokevirtual #49                 // Method com/google/protobuf/LazyStringArrayList.add:(Lcom/google/protobuf/ByteString;)V
      28: aload_0
      29: dup
      30: getfield      #13                 // Field bitField0_:I
      33: iconst_1
      34: ior
      35: putfield      #13                 // Field bitField0_:I
      38: aload_0
      39: invokevirtual #29                 // Method onChanged:()V
      42: aload_0
      43: areturn

  public final istio.v1.auth.IstioCertificateResponse$Builder setUnknownFields(com.google.protobuf.UnknownFieldSet);
    Code:
       0: aload_0
       1: aload_1
       2: invokespecial #50                 // Method com/google/protobuf/GeneratedMessageV3$Builder.setUnknownFields:(Lcom/google/protobuf/UnknownFieldSet;)Lcom/google/protobuf/GeneratedMessageV3$Builder;
       5: checkcast     #6                  // class istio/v1/auth/IstioCertificateResponse$Builder
       8: areturn

  public final istio.v1.auth.IstioCertificateResponse$Builder mergeUnknownFields(com.google.protobuf.UnknownFieldSet);
    Code:
       0: aload_0
       1: aload_1
       2: invokespecial #51                 // Method com/google/protobuf/GeneratedMessageV3$Builder.mergeUnknownFields:(Lcom/google/protobuf/UnknownFieldSet;)Lcom/google/protobuf/GeneratedMessageV3$Builder;
       5: checkcast     #6                  // class istio/v1/auth/IstioCertificateResponse$Builder
       8: areturn

  public com.google.protobuf.GeneratedMessageV3$Builder mergeUnknownFields(com.google.protobuf.UnknownFieldSet);
    Code:
       0: aload_0
       1: aload_1
       2: invokevirtual #31                 // Method mergeUnknownFields:(Lcom/google/protobuf/UnknownFieldSet;)Listio/v1/auth/IstioCertificateResponse$Builder;
       5: areturn

  public com.google.protobuf.GeneratedMessageV3$Builder setUnknownFields(com.google.protobuf.UnknownFieldSet);
    Code:
       0: aload_0
       1: aload_1
       2: invokevirtual #52                 // Method setUnknownFields:(Lcom/google/protobuf/UnknownFieldSet;)Listio/v1/auth/IstioCertificateResponse$Builder;
       5: areturn

  public com.google.protobuf.GeneratedMessageV3$Builder clear();
    Code:
       0: aload_0
       1: invokevirtual #53                 // Method clear:()Listio/v1/auth/IstioCertificateResponse$Builder;
       4: areturn

  public com.google.protobuf.AbstractMessage$Builder mergeUnknownFields(com.google.protobuf.UnknownFieldSet);
    Code:
       0: aload_0
       1: aload_1
       2: invokevirtual #31                 // Method mergeUnknownFields:(Lcom/google/protobuf/UnknownFieldSet;)Listio/v1/auth/IstioCertificateResponse$Builder;
       5: areturn

  public com.google.protobuf.AbstractMessage$Builder mergeFrom(com.google.protobuf.CodedInputStream, com.google.protobuf.ExtensionRegistryLite) throws java.io.IOException;
    Code:
       0: aload_0
       1: aload_1
       2: aload_2
       3: invokevirtual #54                 // Method mergeFrom:(Lcom/google/protobuf/CodedInputStream;Lcom/google/protobuf/ExtensionRegistryLite;)Listio/v1/auth/IstioCertificateResponse$Builder;
       6: areturn

  public com.google.protobuf.AbstractMessage$Builder mergeFrom(com.google.protobuf.Message);
    Code:
       0: aload_0
       1: aload_1
       2: invokevirtual #55                 // Method mergeFrom:(Lcom/google/protobuf/Message;)Listio/v1/auth/IstioCertificateResponse$Builder;
       5: areturn

  public com.google.protobuf.AbstractMessage$Builder clear();
    Code:
       0: aload_0
       1: invokevirtual #53                 // Method clear:()Listio/v1/auth/IstioCertificateResponse$Builder;
       4: areturn

  public com.google.protobuf.Message$Builder mergeUnknownFields(com.google.protobuf.UnknownFieldSet);
    Code:
       0: aload_0
       1: aload_1
       2: invokevirtual #31                 // Method mergeUnknownFields:(Lcom/google/protobuf/UnknownFieldSet;)Listio/v1/auth/IstioCertificateResponse$Builder;
       5: areturn

  public com.google.protobuf.Message$Builder setUnknownFields(com.google.protobuf.UnknownFieldSet);
    Code:
       0: aload_0
       1: aload_1
       2: invokevirtual #52                 // Method setUnknownFields:(Lcom/google/protobuf/UnknownFieldSet;)Listio/v1/auth/IstioCertificateResponse$Builder;
       5: areturn

  public com.google.protobuf.Message$Builder mergeFrom(com.google.protobuf.CodedInputStream, com.google.protobuf.ExtensionRegistryLite) throws java.io.IOException;
    Code:
       0: aload_0
       1: aload_1
       2: aload_2
       3: invokevirtual #54                 // Method mergeFrom:(Lcom/google/protobuf/CodedInputStream;Lcom/google/protobuf/ExtensionRegistryLite;)Listio/v1/auth/IstioCertificateResponse$Builder;
       6: areturn

  public com.google.protobuf.Message buildPartial();
    Code:
       0: aload_0
       1: invokevirtual #15                 // Method buildPartial:()Listio/v1/auth/IstioCertificateResponse;
       4: areturn

  public com.google.protobuf.Message build();
    Code:
       0: aload_0
       1: invokevirtual #56                 // Method build:()Listio/v1/auth/IstioCertificateResponse;
       4: areturn

  public com.google.protobuf.Message$Builder mergeFrom(com.google.protobuf.Message);
    Code:
       0: aload_0
       1: aload_1
       2: invokevirtual #55                 // Method mergeFrom:(Lcom/google/protobuf/Message;)Listio/v1/auth/IstioCertificateResponse$Builder;
       5: areturn

  public com.google.protobuf.Message$Builder clear();
    Code:
       0: aload_0
       1: invokevirtual #53                 // Method clear:()Listio/v1/auth/IstioCertificateResponse$Builder;
       4: areturn

  public com.google.protobuf.MessageLite$Builder mergeFrom(com.google.protobuf.CodedInputStream, com.google.protobuf.ExtensionRegistryLite) throws java.io.IOException;
    Code:
       0: aload_0
       1: aload_1
       2: aload_2
       3: invokevirtual #54                 // Method mergeFrom:(Lcom/google/protobuf/CodedInputStream;Lcom/google/protobuf/ExtensionRegistryLite;)Listio/v1/auth/IstioCertificateResponse$Builder;
       6: areturn

  public com.google.protobuf.MessageLite buildPartial();
    Code:
       0: aload_0
       1: invokevirtual #15                 // Method buildPartial:()Listio/v1/auth/IstioCertificateResponse;
       4: areturn

  public com.google.protobuf.MessageLite build();
    Code:
       0: aload_0
       1: invokevirtual #56                 // Method build:()Listio/v1/auth/IstioCertificateResponse;
       4: areturn

  public com.google.protobuf.MessageLite$Builder clear();
    Code:
       0: aload_0
       1: invokevirtual #53                 // Method clear:()Listio/v1/auth/IstioCertificateResponse$Builder;
       4: areturn

  public com.google.protobuf.MessageLite getDefaultInstanceForType();
    Code:
       0: aload_0
       1: invokevirtual #57                 // Method getDefaultInstanceForType:()Listio/v1/auth/IstioCertificateResponse;
       4: areturn

  public com.google.protobuf.Message getDefaultInstanceForType();
    Code:
       0: aload_0
       1: invokevirtual #57                 // Method getDefaultInstanceForType:()Listio/v1/auth/IstioCertificateResponse;
       4: areturn

  public com.google.protobuf.AbstractMessageLite$Builder mergeFrom(com.google.protobuf.CodedInputStream, com.google.protobuf.ExtensionRegistryLite) throws java.io.IOException;
    Code:
       0: aload_0
       1: aload_1
       2: aload_2
       3: invokevirtual #54                 // Method mergeFrom:(Lcom/google/protobuf/CodedInputStream;Lcom/google/protobuf/ExtensionRegistryLite;)Listio/v1/auth/IstioCertificateResponse$Builder;
       6: areturn

  public java.util.List getCertChainList();
    Code:
       0: aload_0
       1: invokevirtual #58                 // Method getCertChainList:()Lcom/google/protobuf/ProtocolStringList;
       4: areturn

  istio.v1.auth.IstioCertificateResponse$Builder(istio.v1.auth.IstioCertificateResponse$1);
    Code:
       0: aload_0
       1: invokespecial #2                  // Method "<init>":()V
       4: return

  istio.v1.auth.IstioCertificateResponse$Builder(com.google.protobuf.GeneratedMessageV3$BuilderParent, istio.v1.auth.IstioCertificateResponse$1);
    Code:
       0: aload_0
       1: aload_1
       2: invokespecial #1                  // Method "<init>":(Lcom/google/protobuf/GeneratedMessageV3$BuilderParent;)V
       5: return
}
