Compiled from "IstioCertificateService.java"
public abstract class istio.v1.auth.IstioCertificateService implements com.google.protobuf.Service {
  protected istio.v1.auth.IstioCertificateService();
    Code:
       0: aload_0
       1: invokespecial #1                  // Method java/lang/Object."<init>":()V
       4: return

  public static com.google.protobuf.Service newReflectiveService(istio.v1.auth.IstioCertificateService$Interface);
    Code:
       0: new           #2                  // class istio/v1/auth/IstioCertificateService$1
       3: dup
       4: aload_0
       5: invokespecial #3                  // Method istio/v1/auth/IstioCertificateService$1."<init>":(Listio/v1/auth/IstioCertificateService$Interface;)V
       8: areturn

  public static com.google.protobuf.BlockingService newReflectiveBlockingService(istio.v1.auth.IstioCertificateService$BlockingInterface);
    Code:
       0: new           #4                  // class istio/v1/auth/IstioCertificateService$2
       3: dup
       4: aload_0
       5: invokespecial #5                  // Method istio/v1/auth/IstioCertificateService$2."<init>":(Listio/v1/auth/IstioCertificateService$BlockingInterface;)V
       8: areturn

  public abstract void createCertificate(com.google.protobuf.RpcController, istio.v1.auth.IstioCertificateRequest, com.google.protobuf.RpcCallback<istio.v1.auth.IstioCertificateResponse>);

  public static final com.google.protobuf.Descriptors$ServiceDescriptor getDescriptor();
    Code:
       0: invokestatic  #6                  // Method istio/v1/auth/Ca.getDescriptor:()Lcom/google/protobuf/Descriptors$FileDescriptor;
       3: invokevirtual #7                  // Method com/google/protobuf/Descriptors$FileDescriptor.getServices:()Ljava/util/List;
       6: iconst_0
       7: invokeinterface #8,  2            // InterfaceMethod java/util/List.get:(I)Ljava/lang/Object;
      12: checkcast     #9                  // class com/google/protobuf/Descriptors$ServiceDescriptor
      15: areturn

  public final com.google.protobuf.Descriptors$ServiceDescriptor getDescriptorForType();
    Code:
       0: invokestatic  #10                 // Method getDescriptor:()Lcom/google/protobuf/Descriptors$ServiceDescriptor;
       3: areturn

  public final void callMethod(com.google.protobuf.Descriptors$MethodDescriptor, com.google.protobuf.RpcController, com.google.protobuf.Message, com.google.protobuf.RpcCallback<com.google.protobuf.Message>);
    Code:
       0: aload_1
       1: invokevirtual #11                 // Method com/google/protobuf/Descriptors$MethodDescriptor.getService:()Lcom/google/protobuf/Descriptors$ServiceDescriptor;
       4: invokestatic  #10                 // Method getDescriptor:()Lcom/google/protobuf/Descriptors$ServiceDescriptor;
       7: if_acmpeq     20
      10: new           #12                 // class java/lang/IllegalArgumentException
      13: dup
      14: ldc           #13                 // String Service.callMethod() given method descriptor for wrong service type.
      16: invokespecial #14                 // Method java/lang/IllegalArgumentException."<init>":(Ljava/lang/String;)V
      19: athrow
      20: aload_1
      21: invokevirtual #15                 // Method com/google/protobuf/Descriptors$MethodDescriptor.getIndex:()I
      24: lookupswitch  { // 1
                     0: 44
               default: 59
          }
      44: aload_0
      45: aload_2
      46: aload_3
      47: checkcast     #16                 // class istio/v1/auth/IstioCertificateRequest
      50: aload         4
      52: invokestatic  #17                 // Method com/google/protobuf/RpcUtil.specializeCallback:(Lcom/google/protobuf/RpcCallback;)Lcom/google/protobuf/RpcCallback;
      55: invokevirtual #18                 // Method createCertificate:(Lcom/google/protobuf/RpcController;Listio/v1/auth/IstioCertificateRequest;Lcom/google/protobuf/RpcCallback;)V
      58: return
      59: new           #19                 // class java/lang/AssertionError
      62: dup
      63: ldc           #20                 // String Can\'t get here.
      65: invokespecial #21                 // Method java/lang/AssertionError."<init>":(Ljava/lang/Object;)V
      68: athrow

  public final com.google.protobuf.Message getRequestPrototype(com.google.protobuf.Descriptors$MethodDescriptor);
    Code:
       0: aload_1
       1: invokevirtual #11                 // Method com/google/protobuf/Descriptors$MethodDescriptor.getService:()Lcom/google/protobuf/Descriptors$ServiceDescriptor;
       4: invokestatic  #10                 // Method getDescriptor:()Lcom/google/protobuf/Descriptors$ServiceDescriptor;
       7: if_acmpeq     20
      10: new           #12                 // class java/lang/IllegalArgumentException
      13: dup
      14: ldc           #22                 // String Service.getRequestPrototype() given method descriptor for wrong service type.
      16: invokespecial #14                 // Method java/lang/IllegalArgumentException."<init>":(Ljava/lang/String;)V
      19: athrow
      20: aload_1
      21: invokevirtual #15                 // Method com/google/protobuf/Descriptors$MethodDescriptor.getIndex:()I
      24: lookupswitch  { // 1
                     0: 44
               default: 48
          }
      44: invokestatic  #23                 // Method istio/v1/auth/IstioCertificateRequest.getDefaultInstance:()Listio/v1/auth/IstioCertificateRequest;
      47: areturn
      48: new           #19                 // class java/lang/AssertionError
      51: dup
      52: ldc           #20                 // String Can\'t get here.
      54: invokespecial #21                 // Method java/lang/AssertionError."<init>":(Ljava/lang/Object;)V
      57: athrow

  public final com.google.protobuf.Message getResponsePrototype(com.google.protobuf.Descriptors$MethodDescriptor);
    Code:
       0: aload_1
       1: invokevirtual #11                 // Method com/google/protobuf/Descriptors$MethodDescriptor.getService:()Lcom/google/protobuf/Descriptors$ServiceDescriptor;
       4: invokestatic  #10                 // Method getDescriptor:()Lcom/google/protobuf/Descriptors$ServiceDescriptor;
       7: if_acmpeq     20
      10: new           #12                 // class java/lang/IllegalArgumentException
      13: dup
      14: ldc           #24                 // String Service.getResponsePrototype() given method descriptor for wrong service type.
      16: invokespecial #14                 // Method java/lang/IllegalArgumentException."<init>":(Ljava/lang/String;)V
      19: athrow
      20: aload_1
      21: invokevirtual #15                 // Method com/google/protobuf/Descriptors$MethodDescriptor.getIndex:()I
      24: lookupswitch  { // 1
                     0: 44
               default: 48
          }
      44: invokestatic  #25                 // Method istio/v1/auth/IstioCertificateResponse.getDefaultInstance:()Listio/v1/auth/IstioCertificateResponse;
      47: areturn
      48: new           #19                 // class java/lang/AssertionError
      51: dup
      52: ldc           #20                 // String Can\'t get here.
      54: invokespecial #21                 // Method java/lang/AssertionError."<init>":(Ljava/lang/Object;)V
      57: athrow

  public static istio.v1.auth.IstioCertificateService$Stub newStub(com.google.protobuf.RpcChannel);
    Code:
       0: new           #26                 // class istio/v1/auth/IstioCertificateService$Stub
       3: dup
       4: aload_0
       5: aconst_null
       6: invokespecial #27                 // Method istio/v1/auth/IstioCertificateService$Stub."<init>":(Lcom/google/protobuf/RpcChannel;Listio/v1/auth/IstioCertificateService$1;)V
       9: areturn

  public static istio.v1.auth.IstioCertificateService$BlockingInterface newBlockingStub(com.google.protobuf.BlockingRpcChannel);
    Code:
       0: new           #28                 // class istio/v1/auth/IstioCertificateService$BlockingStub
       3: dup
       4: aload_0
       5: aconst_null
       6: invokespecial #29                 // Method istio/v1/auth/IstioCertificateService$BlockingStub."<init>":(Lcom/google/protobuf/BlockingRpcChannel;Listio/v1/auth/IstioCertificateService$1;)V
       9: areturn
}
