Compiled from "IstioCertificateServiceGrpc.java"
public final class istio.v1.auth.IstioCertificateServiceGrpc$IstioCertificateServiceBlockingStub extends io.grpc.stub.AbstractBlockingStub<istio.v1.auth.IstioCertificateServiceGrpc$IstioCertificateServiceBlockingStub> {
  private istio.v1.auth.IstioCertificateServiceGrpc$IstioCertificateServiceBlockingStub(io.grpc.Channel, io.grpc.CallOptions);
    Code:
       0: aload_0
       1: aload_1
       2: aload_2
       3: invokespecial #2                  // Method io/grpc/stub/AbstractBlockingStub."<init>":(Lio/grpc/Channel;Lio/grpc/CallOptions;)V
       6: return

  protected istio.v1.auth.IstioCertificateServiceGrpc$IstioCertificateServiceBlockingStub build(io.grpc.Channel, io.grpc.CallOptions);
    Code:
       0: new           #3                  // class istio/v1/auth/IstioCertificateServiceGrpc$IstioCertificateServiceBlockingStub
       3: dup
       4: aload_1
       5: aload_2
       6: invokespecial #1                  // Method "<init>":(Lio/grpc/Channel;Lio/grpc/CallOptions;)V
       9: areturn

  public istio.v1.auth.IstioCertificateResponse createCertificate(istio.v1.auth.IstioCertificateRequest);
    Code:
       0: aload_0
       1: invokevirtual #4                  // Method getChannel:()Lio/grpc/Channel;
       4: invokestatic  #5                  // Method istio/v1/auth/IstioCertificateServiceGrpc.getCreateCertificateMethod:()Lio/grpc/MethodDescriptor;
       7: aload_0
       8: invokevirtual #6                  // Method getCallOptions:()Lio/grpc/CallOptions;
      11: aload_1
      12: invokestatic  #7                  // Method io/grpc/stub/ClientCalls.blockingUnaryCall:(Lio/grpc/Channel;Lio/grpc/MethodDescriptor;Lio/grpc/CallOptions;Ljava/lang/Object;)Ljava/lang/Object;
      15: checkcast     #8                  // class istio/v1/auth/IstioCertificateResponse
      18: areturn

  protected io.grpc.stub.AbstractStub build(io.grpc.Channel, io.grpc.CallOptions);
    Code:
       0: aload_0
       1: aload_1
       2: aload_2
       3: invokevirtual #9                  // Method build:(Lio/grpc/Channel;Lio/grpc/CallOptions;)Listio/v1/auth/IstioCertificateServiceGrpc$IstioCertificateServiceBlockingStub;
       6: areturn

  istio.v1.auth.IstioCertificateServiceGrpc$IstioCertificateServiceBlockingStub(io.grpc.Channel, io.grpc.CallOptions, istio.v1.auth.IstioCertificateServiceGrpc$1);
    Code:
       0: aload_0
       1: aload_1
       2: aload_2
       3: invokespecial #1                  // Method "<init>":(Lio/grpc/Channel;Lio/grpc/CallOptions;)V
       6: return
}
