Compiled from "IstioCertificateServiceGrpc.java"
public final class istio.v1.auth.IstioCertificateServiceGrpc {
  public static final java.lang.String SERVICE_NAME;

  private static volatile io.grpc.MethodDescriptor<istio.v1.auth.IstioCertificateRequest, istio.v1.auth.IstioCertificateResponse> getCreateCertificateMethod;

  private static final int METHODID_CREATE_CERTIFICATE;

  private static volatile io.grpc.ServiceDescriptor serviceDescriptor;

  private istio.v1.auth.IstioCertificateServiceGrpc();
    Code:
       0: aload_0
       1: invokespecial #1                  // Method java/lang/Object."<init>":()V
       4: return

  public static io.grpc.MethodDescriptor<istio.v1.auth.IstioCertificateRequest, istio.v1.auth.IstioCertificateResponse> getCreateCertificateMethod();
    Code:
       0: getstatic     #2                  // Field getCreateCertificateMethod:Lio/grpc/MethodDescriptor;
       3: dup
       4: astore_0
       5: ifnonnull     92
       8: ldc           #3                  // class istio/v1/auth/IstioCertificateServiceGrpc
      10: dup
      11: astore_1
      12: monitorenter
      13: getstatic     #2                  // Field getCreateCertificateMethod:Lio/grpc/MethodDescriptor;
      16: dup
      17: astore_0
      18: ifnonnull     82
      21: invokestatic  #4                  // Method io/grpc/MethodDescriptor.newBuilder:()Lio/grpc/MethodDescriptor$Builder;
      24: getstatic     #5                  // Field io/grpc/MethodDescriptor$MethodType.UNARY:Lio/grpc/MethodDescriptor$MethodType;
      27: invokevirtual #6                  // Method io/grpc/MethodDescriptor$Builder.setType:(Lio/grpc/MethodDescriptor$MethodType;)Lio/grpc/MethodDescriptor$Builder;
      30: ldc           #7                  // String istio.v1.auth.IstioCertificateService
      32: ldc           #8                  // String CreateCertificate
      34: invokestatic  #9                  // Method io/grpc/MethodDescriptor.generateFullMethodName:(Ljava/lang/String;Ljava/lang/String;)Ljava/lang/String;
      37: invokevirtual #10                 // Method io/grpc/MethodDescriptor$Builder.setFullMethodName:(Ljava/lang/String;)Lio/grpc/MethodDescriptor$Builder;
      40: iconst_1
      41: invokevirtual #11                 // Method io/grpc/MethodDescriptor$Builder.setSampledToLocalTracing:(Z)Lio/grpc/MethodDescriptor$Builder;
      44: invokestatic  #12                 // Method istio/v1/auth/IstioCertificateRequest.getDefaultInstance:()Listio/v1/auth/IstioCertificateRequest;
      47: invokestatic  #13                 // Method io/grpc/protobuf/ProtoUtils.marshaller:(Lcom/google/protobuf/Message;)Lio/grpc/MethodDescriptor$Marshaller;
      50: invokevirtual #14                 // Method io/grpc/MethodDescriptor$Builder.setRequestMarshaller:(Lio/grpc/MethodDescriptor$Marshaller;)Lio/grpc/MethodDescriptor$Builder;
      53: invokestatic  #15                 // Method istio/v1/auth/IstioCertificateResponse.getDefaultInstance:()Listio/v1/auth/IstioCertificateResponse;
      56: invokestatic  #13                 // Method io/grpc/protobuf/ProtoUtils.marshaller:(Lcom/google/protobuf/Message;)Lio/grpc/MethodDescriptor$Marshaller;
      59: invokevirtual #16                 // Method io/grpc/MethodDescriptor$Builder.setResponseMarshaller:(Lio/grpc/MethodDescriptor$Marshaller;)Lio/grpc/MethodDescriptor$Builder;
      62: new           #17                 // class istio/v1/auth/IstioCertificateServiceGrpc$IstioCertificateServiceMethodDescriptorSupplier
      65: dup
      66: ldc           #8                  // String CreateCertificate
      68: invokespecial #18                 // Method istio/v1/auth/IstioCertificateServiceGrpc$IstioCertificateServiceMethodDescriptorSupplier."<init>":(Ljava/lang/String;)V
      71: invokevirtual #19                 // Method io/grpc/MethodDescriptor$Builder.setSchemaDescriptor:(Ljava/lang/Object;)Lio/grpc/MethodDescriptor$Builder;
      74: invokevirtual #20                 // Method io/grpc/MethodDescriptor$Builder.build:()Lio/grpc/MethodDescriptor;
      77: dup
      78: astore_0
      79: putstatic     #2                  // Field getCreateCertificateMethod:Lio/grpc/MethodDescriptor;
      82: aload_1
      83: monitorexit
      84: goto          92
      87: astore_2
      88: aload_1
      89: monitorexit
      90: aload_2
      91: athrow
      92: aload_0
      93: areturn
    Exception table:
       from    to  target type
          13    84    87   any
          87    90    87   any

  public static istio.v1.auth.IstioCertificateServiceGrpc$IstioCertificateServiceStub newStub(io.grpc.Channel);
    Code:
       0: new           #21                 // class istio/v1/auth/IstioCertificateServiceGrpc$1
       3: dup
       4: invokespecial #22                 // Method istio/v1/auth/IstioCertificateServiceGrpc$1."<init>":()V
       7: astore_1
       8: aload_1
       9: aload_0
      10: invokestatic  #23                 // Method istio/v1/auth/IstioCertificateServiceGrpc$IstioCertificateServiceStub.newStub:(Lio/grpc/stub/AbstractStub$StubFactory;Lio/grpc/Channel;)Lio/grpc/stub/AbstractStub;
      13: checkcast     #24                 // class istio/v1/auth/IstioCertificateServiceGrpc$IstioCertificateServiceStub
      16: areturn

  public static istio.v1.auth.IstioCertificateServiceGrpc$IstioCertificateServiceBlockingStub newBlockingStub(io.grpc.Channel);
    Code:
       0: new           #25                 // class istio/v1/auth/IstioCertificateServiceGrpc$2
       3: dup
       4: invokespecial #26                 // Method istio/v1/auth/IstioCertificateServiceGrpc$2."<init>":()V
       7: astore_1
       8: aload_1
       9: aload_0
      10: invokestatic  #27                 // Method istio/v1/auth/IstioCertificateServiceGrpc$IstioCertificateServiceBlockingStub.newStub:(Lio/grpc/stub/AbstractStub$StubFactory;Lio/grpc/Channel;)Lio/grpc/stub/AbstractStub;
      13: checkcast     #28                 // class istio/v1/auth/IstioCertificateServiceGrpc$IstioCertificateServiceBlockingStub
      16: areturn

  public static istio.v1.auth.IstioCertificateServiceGrpc$IstioCertificateServiceFutureStub newFutureStub(io.grpc.Channel);
    Code:
       0: new           #29                 // class istio/v1/auth/IstioCertificateServiceGrpc$3
       3: dup
       4: invokespecial #30                 // Method istio/v1/auth/IstioCertificateServiceGrpc$3."<init>":()V
       7: astore_1
       8: aload_1
       9: aload_0
      10: invokestatic  #31                 // Method istio/v1/auth/IstioCertificateServiceGrpc$IstioCertificateServiceFutureStub.newStub:(Lio/grpc/stub/AbstractStub$StubFactory;Lio/grpc/Channel;)Lio/grpc/stub/AbstractStub;
      13: checkcast     #32                 // class istio/v1/auth/IstioCertificateServiceGrpc$IstioCertificateServiceFutureStub
      16: areturn

  public static final io.grpc.ServerServiceDefinition bindService(istio.v1.auth.IstioCertificateServiceGrpc$AsyncService);
    Code:
       0: invokestatic  #33                 // Method getServiceDescriptor:()Lio/grpc/ServiceDescriptor;
       3: invokestatic  #34                 // Method io/grpc/ServerServiceDefinition.builder:(Lio/grpc/ServiceDescriptor;)Lio/grpc/ServerServiceDefinition$Builder;
       6: invokestatic  #35                 // Method getCreateCertificateMethod:()Lio/grpc/MethodDescriptor;
       9: new           #36                 // class istio/v1/auth/IstioCertificateServiceGrpc$MethodHandlers
      12: dup
      13: aload_0
      14: iconst_0
      15: invokespecial #37                 // Method istio/v1/auth/IstioCertificateServiceGrpc$MethodHandlers."<init>":(Listio/v1/auth/IstioCertificateServiceGrpc$AsyncService;I)V
      18: invokestatic  #38                 // Method io/grpc/stub/ServerCalls.asyncUnaryCall:(Lio/grpc/stub/ServerCalls$UnaryMethod;)Lio/grpc/ServerCallHandler;
      21: invokevirtual #39                 // Method io/grpc/ServerServiceDefinition$Builder.addMethod:(Lio/grpc/MethodDescriptor;Lio/grpc/ServerCallHandler;)Lio/grpc/ServerServiceDefinition$Builder;
      24: invokevirtual #40                 // Method io/grpc/ServerServiceDefinition$Builder.build:()Lio/grpc/ServerServiceDefinition;
      27: areturn

  public static io.grpc.ServiceDescriptor getServiceDescriptor();
    Code:
       0: getstatic     #41                 // Field serviceDescriptor:Lio/grpc/ServiceDescriptor;
       3: astore_0
       4: aload_0
       5: ifnonnull     60
       8: ldc           #3                  // class istio/v1/auth/IstioCertificateServiceGrpc
      10: dup
      11: astore_1
      12: monitorenter
      13: getstatic     #41                 // Field serviceDescriptor:Lio/grpc/ServiceDescriptor;
      16: astore_0
      17: aload_0
      18: ifnonnull     50
      21: ldc           #7                  // String istio.v1.auth.IstioCertificateService
      23: invokestatic  #42                 // Method io/grpc/ServiceDescriptor.newBuilder:(Ljava/lang/String;)Lio/grpc/ServiceDescriptor$Builder;
      26: new           #43                 // class istio/v1/auth/IstioCertificateServiceGrpc$IstioCertificateServiceFileDescriptorSupplier
      29: dup
      30: invokespecial #44                 // Method istio/v1/auth/IstioCertificateServiceGrpc$IstioCertificateServiceFileDescriptorSupplier."<init>":()V
      33: invokevirtual #45                 // Method io/grpc/ServiceDescriptor$Builder.setSchemaDescriptor:(Ljava/lang/Object;)Lio/grpc/ServiceDescriptor$Builder;
      36: invokestatic  #35                 // Method getCreateCertificateMethod:()Lio/grpc/MethodDescriptor;
      39: invokevirtual #46                 // Method io/grpc/ServiceDescriptor$Builder.addMethod:(Lio/grpc/MethodDescriptor;)Lio/grpc/ServiceDescriptor$Builder;
      42: invokevirtual #47                 // Method io/grpc/ServiceDescriptor$Builder.build:()Lio/grpc/ServiceDescriptor;
      45: dup
      46: astore_0
      47: putstatic     #41                 // Field serviceDescriptor:Lio/grpc/ServiceDescriptor;
      50: aload_1
      51: monitorexit
      52: goto          60
      55: astore_2
      56: aload_1
      57: monitorexit
      58: aload_2
      59: athrow
      60: aload_0
      61: areturn
    Exception table:
       from    to  target type
          13    52    55   any
          55    58    55   any
}
