Compiled from "IstioCertificateServiceGrpc.java"
public final class istio.v1.auth.IstioCertificateServiceGrpc$IstioCertificateServiceStub extends io.grpc.stub.AbstractAsyncStub<istio.v1.auth.IstioCertificateServiceGrpc$IstioCertificateServiceStub> {
  private istio.v1.auth.IstioCertificateServiceGrpc$IstioCertificateServiceStub(io.grpc.Channel, io.grpc.CallOptions);
    Code:
       0: aload_0
       1: aload_1
       2: aload_2
       3: invokespecial #2                  // Method io/grpc/stub/AbstractAsyncStub."<init>":(Lio/grpc/Channel;Lio/grpc/CallOptions;)V
       6: return

  protected istio.v1.auth.IstioCertificateServiceGrpc$IstioCertificateServiceStub build(io.grpc.Channel, io.grpc.CallOptions);
    Code:
       0: new           #3                  // class istio/v1/auth/IstioCertificateServiceGrpc$IstioCertificateServiceStub
       3: dup
       4: aload_1
       5: aload_2
       6: invokespecial #1                  // Method "<init>":(Lio/grpc/Channel;Lio/grpc/CallOptions;)V
       9: areturn

  public void createCertificate(istio.v1.auth.IstioCertificateRequest, io.grpc.stub.StreamObserver<istio.v1.auth.IstioCertificateResponse>);
    Code:
       0: aload_0
       1: invokevirtual #4                  // Method getChannel:()Lio/grpc/Channel;
       4: invokestatic  #5                  // Method istio/v1/auth/IstioCertificateServiceGrpc.getCreateCertificateMethod:()Lio/grpc/MethodDescriptor;
       7: aload_0
       8: invokevirtual #6                  // Method getCallOptions:()Lio/grpc/CallOptions;
      11: invokevirtual #7                  // Method io/grpc/Channel.newCall:(Lio/grpc/MethodDescriptor;Lio/grpc/CallOptions;)Lio/grpc/ClientCall;
      14: aload_1
      15: aload_2
      16: invokestatic  #8                  // Method io/grpc/stub/ClientCalls.asyncUnaryCall:(Lio/grpc/ClientCall;Ljava/lang/Object;Lio/grpc/stub/StreamObserver;)V
      19: return

  protected io.grpc.stub.AbstractStub build(io.grpc.Channel, io.grpc.CallOptions);
    Code:
       0: aload_0
       1: aload_1
       2: aload_2
       3: invokevirtual #9                  // Method build:(Lio/grpc/Channel;Lio/grpc/CallOptions;)Listio/v1/auth/IstioCertificateServiceGrpc$IstioCertificateServiceStub;
       6: areturn

  istio.v1.auth.IstioCertificateServiceGrpc$IstioCertificateServiceStub(io.grpc.Channel, io.grpc.CallOptions, istio.v1.auth.IstioCertificateServiceGrpc$1);
    Code:
       0: aload_0
       1: aload_1
       2: aload_2
       3: invokespecial #1                  // Method "<init>":(Lio/grpc/Channel;Lio/grpc/CallOptions;)V
       6: return
}
