Compiled from "IstioCertificateRequest.java"
public final class istio.v1.auth.IstioCertificateRequest$Builder extends com.google.protobuf.GeneratedMessageV3$Builder<istio.v1.auth.IstioCertificateRequest$Builder> implements istio.v1.auth.IstioCertificateRequestOrBuilder {
  private int bitField0_;

  private java.lang.Object csr_;

  private long validityDuration_;

  private com.google.protobuf.Struct metadata_;

  private com.google.protobuf.SingleFieldBuilderV3<com.google.protobuf.Struct, com.google.protobuf.Struct$Builder, com.google.protobuf.StructOrBuilder> metadataBuilder_;

  public static final com.google.protobuf.Descriptors$Descriptor getDescriptor();
    Code:
       0: getstatic     #3                  // Field istio/v1/auth/Ca.internal_static_istio_v1_auth_IstioCertificateRequest_descriptor:Lcom/google/protobuf/Descriptors$Descriptor;
       3: areturn

  protected com.google.protobuf.GeneratedMessageV3$FieldAccessorTable internalGetFieldAccessorTable();
    Code:
       0: getstatic     #4                  // Field istio/v1/auth/Ca.internal_static_istio_v1_auth_IstioCertificateRequest_fieldAccessorTable:Lcom/google/protobuf/GeneratedMessageV3$FieldAccessorTable;
       3: ldc           #5                  // class istio/v1/auth/IstioCertificateRequest
       5: ldc           #6                  // class istio/v1/auth/IstioCertificateRequest$Builder
       7: invokevirtual #7                  // Method com/google/protobuf/GeneratedMessageV3$FieldAccessorTable.ensureFieldAccessorsInitialized:(Ljava/lang/Class;Ljava/lang/Class;)Lcom/google/protobuf/GeneratedMessageV3$FieldAccessorTable;
      10: areturn

  private istio.v1.auth.IstioCertificateRequest$Builder();
    Code:
       0: aload_0
       1: invokespecial #8                  // Method com/google/protobuf/GeneratedMessageV3$Builder."<init>":()V
       4: aload_0
       5: ldc           #9                  // String
       7: putfield      #10                 // Field csr_:Ljava/lang/Object;
      10: return

  private istio.v1.auth.IstioCertificateRequest$Builder(com.google.protobuf.GeneratedMessageV3$BuilderParent);
    Code:
       0: aload_0
       1: aload_1
       2: invokespecial #11                 // Method com/google/protobuf/GeneratedMessageV3$Builder."<init>":(Lcom/google/protobuf/GeneratedMessageV3$BuilderParent;)V
       5: aload_0
       6: ldc           #9                  // String
       8: putfield      #10                 // Field csr_:Ljava/lang/Object;
      11: return

  public istio.v1.auth.IstioCertificateRequest$Builder clear();
    Code:
       0: aload_0
       1: invokespecial #12                 // Method com/google/protobuf/GeneratedMessageV3$Builder.clear:()Lcom/google/protobuf/GeneratedMessageV3$Builder;
       4: pop
       5: aload_0
       6: iconst_0
       7: putfield      #13                 // Field bitField0_:I
      10: aload_0
      11: ldc           #9                  // String
      13: putfield      #10                 // Field csr_:Ljava/lang/Object;
      16: aload_0
      17: lconst_0
      18: putfield      #14                 // Field validityDuration_:J
      21: aload_0
      22: aconst_null
      23: putfield      #15                 // Field metadata_:Lcom/google/protobuf/Struct;
      26: aload_0
      27: getfield      #16                 // Field metadataBuilder_:Lcom/google/protobuf/SingleFieldBuilderV3;
      30: ifnull        45
      33: aload_0
      34: getfield      #16                 // Field metadataBuilder_:Lcom/google/protobuf/SingleFieldBuilderV3;
      37: invokevirtual #17                 // Method com/google/protobuf/SingleFieldBuilderV3.dispose:()V
      40: aload_0
      41: aconst_null
      42: putfield      #16                 // Field metadataBuilder_:Lcom/google/protobuf/SingleFieldBuilderV3;
      45: aload_0
      46: areturn

  public com.google.protobuf.Descriptors$Descriptor getDescriptorForType();
    Code:
       0: getstatic     #3                  // Field istio/v1/auth/Ca.internal_static_istio_v1_auth_IstioCertificateRequest_descriptor:Lcom/google/protobuf/Descriptors$Descriptor;
       3: areturn

  public istio.v1.auth.IstioCertificateRequest getDefaultInstanceForType();
    Code:
       0: invokestatic  #18                 // Method istio/v1/auth/IstioCertificateRequest.getDefaultInstance:()Listio/v1/auth/IstioCertificateRequest;
       3: areturn

  public istio.v1.auth.IstioCertificateRequest build();
    Code:
       0: aload_0
       1: invokevirtual #19                 // Method buildPartial:()Listio/v1/auth/IstioCertificateRequest;
       4: astore_1
       5: aload_1
       6: invokevirtual #20                 // Method istio/v1/auth/IstioCertificateRequest.isInitialized:()Z
       9: ifne          17
      12: aload_1
      13: invokestatic  #21                 // Method newUninitializedMessageException:(Lcom/google/protobuf/Message;)Lcom/google/protobuf/UninitializedMessageException;
      16: athrow
      17: aload_1
      18: areturn

  public istio.v1.auth.IstioCertificateRequest buildPartial();
    Code:
       0: new           #5                  // class istio/v1/auth/IstioCertificateRequest
       3: dup
       4: aload_0
       5: aconst_null
       6: invokespecial #22                 // Method istio/v1/auth/IstioCertificateRequest."<init>":(Lcom/google/protobuf/GeneratedMessageV3$Builder;Listio/v1/auth/IstioCertificateRequest$1;)V
       9: astore_1
      10: aload_0
      11: getfield      #13                 // Field bitField0_:I
      14: ifeq          22
      17: aload_0
      18: aload_1
      19: invokespecial #23                 // Method buildPartial0:(Listio/v1/auth/IstioCertificateRequest;)V
      22: aload_0
      23: invokevirtual #24                 // Method onBuilt:()V
      26: aload_1
      27: areturn

  private void buildPartial0(istio.v1.auth.IstioCertificateRequest);
    Code:
       0: aload_0
       1: getfield      #13                 // Field bitField0_:I
       4: istore_2
       5: iload_2
       6: iconst_1
       7: iand
       8: ifeq          20
      11: aload_1
      12: aload_0
      13: getfield      #10                 // Field csr_:Ljava/lang/Object;
      16: invokestatic  #25                 // Method istio/v1/auth/IstioCertificateRequest.access$302:(Listio/v1/auth/IstioCertificateRequest;Ljava/lang/Object;)Ljava/lang/Object;
      19: pop
      20: iload_2
      21: iconst_2
      22: iand
      23: ifeq          35
      26: aload_1
      27: aload_0
      28: getfield      #14                 // Field validityDuration_:J
      31: invokestatic  #26                 // Method istio/v1/auth/IstioCertificateRequest.access$402:(Listio/v1/auth/IstioCertificateRequest;J)J
      34: pop2
      35: iload_2
      36: iconst_4
      37: iand
      38: ifeq          70
      41: aload_1
      42: aload_0
      43: getfield      #16                 // Field metadataBuilder_:Lcom/google/protobuf/SingleFieldBuilderV3;
      46: ifnonnull     56
      49: aload_0
      50: getfield      #15                 // Field metadata_:Lcom/google/protobuf/Struct;
      53: goto          66
      56: aload_0
      57: getfield      #16                 // Field metadataBuilder_:Lcom/google/protobuf/SingleFieldBuilderV3;
      60: invokevirtual #27                 // Method com/google/protobuf/SingleFieldBuilderV3.build:()Lcom/google/protobuf/AbstractMessage;
      63: checkcast     #28                 // class com/google/protobuf/Struct
      66: invokestatic  #29                 // Method istio/v1/auth/IstioCertificateRequest.access$502:(Listio/v1/auth/IstioCertificateRequest;Lcom/google/protobuf/Struct;)Lcom/google/protobuf/Struct;
      69: pop
      70: return

  public istio.v1.auth.IstioCertificateRequest$Builder mergeFrom(com.google.protobuf.Message);
    Code:
       0: aload_1
       1: instanceof    #5                  // class istio/v1/auth/IstioCertificateRequest
       4: ifeq          16
       7: aload_0
       8: aload_1
       9: checkcast     #5                  // class istio/v1/auth/IstioCertificateRequest
      12: invokevirtual #30                 // Method mergeFrom:(Listio/v1/auth/IstioCertificateRequest;)Listio/v1/auth/IstioCertificateRequest$Builder;
      15: areturn
      16: aload_0
      17: aload_1
      18: invokespecial #31                 // Method com/google/protobuf/GeneratedMessageV3$Builder.mergeFrom:(Lcom/google/protobuf/Message;)Lcom/google/protobuf/AbstractMessage$Builder;
      21: pop
      22: aload_0
      23: areturn

  public istio.v1.auth.IstioCertificateRequest$Builder mergeFrom(istio.v1.auth.IstioCertificateRequest);
    Code:
       0: aload_1
       1: invokestatic  #18                 // Method istio/v1/auth/IstioCertificateRequest.getDefaultInstance:()Listio/v1/auth/IstioCertificateRequest;
       4: if_acmpne     9
       7: aload_0
       8: areturn
       9: aload_1
      10: invokevirtual #32                 // Method istio/v1/auth/IstioCertificateRequest.getCsr:()Ljava/lang/String;
      13: invokevirtual #33                 // Method java/lang/String.isEmpty:()Z
      16: ifne          41
      19: aload_0
      20: aload_1
      21: invokestatic  #34                 // Method istio/v1/auth/IstioCertificateRequest.access$300:(Listio/v1/auth/IstioCertificateRequest;)Ljava/lang/Object;
      24: putfield      #10                 // Field csr_:Ljava/lang/Object;
      27: aload_0
      28: dup
      29: getfield      #13                 // Field bitField0_:I
      32: iconst_1
      33: ior
      34: putfield      #13                 // Field bitField0_:I
      37: aload_0
      38: invokevirtual #35                 // Method onChanged:()V
      41: aload_1
      42: invokevirtual #36                 // Method istio/v1/auth/IstioCertificateRequest.getValidityDuration:()J
      45: lconst_0
      46: lcmp
      47: ifeq          59
      50: aload_0
      51: aload_1
      52: invokevirtual #36                 // Method istio/v1/auth/IstioCertificateRequest.getValidityDuration:()J
      55: invokevirtual #37                 // Method setValidityDuration:(J)Listio/v1/auth/IstioCertificateRequest$Builder;
      58: pop
      59: aload_1
      60: invokevirtual #38                 // Method istio/v1/auth/IstioCertificateRequest.hasMetadata:()Z
      63: ifeq          75
      66: aload_0
      67: aload_1
      68: invokevirtual #39                 // Method istio/v1/auth/IstioCertificateRequest.getMetadata:()Lcom/google/protobuf/Struct;
      71: invokevirtual #40                 // Method mergeMetadata:(Lcom/google/protobuf/Struct;)Listio/v1/auth/IstioCertificateRequest$Builder;
      74: pop
      75: aload_0
      76: aload_1
      77: invokevirtual #41                 // Method istio/v1/auth/IstioCertificateRequest.getUnknownFields:()Lcom/google/protobuf/UnknownFieldSet;
      80: invokevirtual #42                 // Method mergeUnknownFields:(Lcom/google/protobuf/UnknownFieldSet;)Listio/v1/auth/IstioCertificateRequest$Builder;
      83: pop
      84: aload_0
      85: invokevirtual #35                 // Method onChanged:()V
      88: aload_0
      89: areturn

  public final boolean isInitialized();
    Code:
       0: iconst_1
       1: ireturn

  public istio.v1.auth.IstioCertificateRequest$Builder mergeFrom(com.google.protobuf.CodedInputStream, com.google.protobuf.ExtensionRegistryLite) throws java.io.IOException;
    Code:
       0: aload_2
       1: ifnonnull     12
       4: new           #43                 // class java/lang/NullPointerException
       7: dup
       8: invokespecial #44                 // Method java/lang/NullPointerException."<init>":()V
      11: athrow
      12: iconst_0
      13: istore_3
      14: iload_3
      15: ifne          156
      18: aload_1
      19: invokevirtual #45                 // Method com/google/protobuf/CodedInputStream.readTag:()I
      22: istore        4
      24: iload         4
      26: lookupswitch  { // 4
                     0: 68
                    10: 73
                    24: 94
                    34: 115
               default: 140
          }
      68: iconst_1
      69: istore_3
      70: goto          153
      73: aload_0
      74: aload_1
      75: invokevirtual #46                 // Method com/google/protobuf/CodedInputStream.readStringRequireUtf8:()Ljava/lang/String;
      78: putfield      #10                 // Field csr_:Ljava/lang/Object;
      81: aload_0
      82: dup
      83: getfield      #13                 // Field bitField0_:I
      86: iconst_1
      87: ior
      88: putfield      #13                 // Field bitField0_:I
      91: goto          153
      94: aload_0
      95: aload_1
      96: invokevirtual #47                 // Method com/google/protobuf/CodedInputStream.readInt64:()J
      99: putfield      #14                 // Field validityDuration_:J
     102: aload_0
     103: dup
     104: getfield      #13                 // Field bitField0_:I
     107: iconst_2
     108: ior
     109: putfield      #13                 // Field bitField0_:I
     112: goto          153
     115: aload_1
     116: aload_0
     117: invokespecial #48                 // Method getMetadataFieldBuilder:()Lcom/google/protobuf/SingleFieldBuilderV3;
     120: invokevirtual #49                 // Method com/google/protobuf/SingleFieldBuilderV3.getBuilder:()Lcom/google/protobuf/AbstractMessage$Builder;
     123: aload_2
     124: invokevirtual #50                 // Method com/google/protobuf/CodedInputStream.readMessage:(Lcom/google/protobuf/MessageLite$Builder;Lcom/google/protobuf/ExtensionRegistryLite;)V
     127: aload_0
     128: dup
     129: getfield      #13                 // Field bitField0_:I
     132: iconst_4
     133: ior
     134: putfield      #13                 // Field bitField0_:I
     137: goto          153
     140: aload_0
     141: aload_1
     142: aload_2
     143: iload         4
     145: invokespecial #51                 // Method com/google/protobuf/GeneratedMessageV3$Builder.parseUnknownField:(Lcom/google/protobuf/CodedInputStream;Lcom/google/protobuf/ExtensionRegistryLite;I)Z
     148: ifne          153
     151: iconst_1
     152: istore_3
     153: goto          14
     156: aload_0
     157: invokevirtual #35                 // Method onChanged:()V
     160: goto          178
     163: astore_3
     164: aload_3
     165: invokevirtual #53                 // Method com/google/protobuf/InvalidProtocolBufferException.unwrapIOException:()Ljava/io/IOException;
     168: athrow
     169: astore        5
     171: aload_0
     172: invokevirtual #35                 // Method onChanged:()V
     175: aload         5
     177: athrow
     178: aload_0
     179: areturn
    Exception table:
       from    to  target type
          12   156   163   Class com/google/protobuf/InvalidProtocolBufferException
          12   156   169   any
         163   171   169   any

  public java.lang.String getCsr();
    Code:
       0: aload_0
       1: getfield      #10                 // Field csr_:Ljava/lang/Object;
       4: astore_1
       5: aload_1
       6: instanceof    #54                 // class java/lang/String
       9: ifne          29
      12: aload_1
      13: checkcast     #55                 // class com/google/protobuf/ByteString
      16: astore_2
      17: aload_2
      18: invokevirtual #56                 // Method com/google/protobuf/ByteString.toStringUtf8:()Ljava/lang/String;
      21: astore_3
      22: aload_0
      23: aload_3
      24: putfield      #10                 // Field csr_:Ljava/lang/Object;
      27: aload_3
      28: areturn
      29: aload_1
      30: checkcast     #54                 // class java/lang/String
      33: areturn

  public com.google.protobuf.ByteString getCsrBytes();
    Code:
       0: aload_0
       1: getfield      #10                 // Field csr_:Ljava/lang/Object;
       4: astore_1
       5: aload_1
       6: instanceof    #54                 // class java/lang/String
       9: ifeq          27
      12: aload_1
      13: checkcast     #54                 // class java/lang/String
      16: invokestatic  #57                 // Method com/google/protobuf/ByteString.copyFromUtf8:(Ljava/lang/String;)Lcom/google/protobuf/ByteString;
      19: astore_2
      20: aload_0
      21: aload_2
      22: putfield      #10                 // Field csr_:Ljava/lang/Object;
      25: aload_2
      26: areturn
      27: aload_1
      28: checkcast     #55                 // class com/google/protobuf/ByteString
      31: areturn

  public istio.v1.auth.IstioCertificateRequest$Builder setCsr(java.lang.String);
    Code:
       0: aload_1
       1: ifnonnull     12
       4: new           #43                 // class java/lang/NullPointerException
       7: dup
       8: invokespecial #44                 // Method java/lang/NullPointerException."<init>":()V
      11: athrow
      12: aload_0
      13: aload_1
      14: putfield      #10                 // Field csr_:Ljava/lang/Object;
      17: aload_0
      18: dup
      19: getfield      #13                 // Field bitField0_:I
      22: iconst_1
      23: ior
      24: putfield      #13                 // Field bitField0_:I
      27: aload_0
      28: invokevirtual #35                 // Method onChanged:()V
      31: aload_0
      32: areturn

  public istio.v1.auth.IstioCertificateRequest$Builder clearCsr();
    Code:
       0: aload_0
       1: invokestatic  #18                 // Method istio/v1/auth/IstioCertificateRequest.getDefaultInstance:()Listio/v1/auth/IstioCertificateRequest;
       4: invokevirtual #32                 // Method istio/v1/auth/IstioCertificateRequest.getCsr:()Ljava/lang/String;
       7: putfield      #10                 // Field csr_:Ljava/lang/Object;
      10: aload_0
      11: aload_0
      12: getfield      #13                 // Field bitField0_:I
      15: bipush        -2
      17: iand
      18: putfield      #13                 // Field bitField0_:I
      21: aload_0
      22: invokevirtual #35                 // Method onChanged:()V
      25: aload_0
      26: areturn

  public istio.v1.auth.IstioCertificateRequest$Builder setCsrBytes(com.google.protobuf.ByteString);
    Code:
       0: aload_1
       1: ifnonnull     12
       4: new           #43                 // class java/lang/NullPointerException
       7: dup
       8: invokespecial #44                 // Method java/lang/NullPointerException."<init>":()V
      11: athrow
      12: aload_1
      13: invokestatic  #58                 // Method istio/v1/auth/IstioCertificateRequest.access$600:(Lcom/google/protobuf/ByteString;)V
      16: aload_0
      17: aload_1
      18: putfield      #10                 // Field csr_:Ljava/lang/Object;
      21: aload_0
      22: dup
      23: getfield      #13                 // Field bitField0_:I
      26: iconst_1
      27: ior
      28: putfield      #13                 // Field bitField0_:I
      31: aload_0
      32: invokevirtual #35                 // Method onChanged:()V
      35: aload_0
      36: areturn

  public long getValidityDuration();
    Code:
       0: aload_0
       1: getfield      #14                 // Field validityDuration_:J
       4: lreturn

  public istio.v1.auth.IstioCertificateRequest$Builder setValidityDuration(long);
    Code:
       0: aload_0
       1: lload_1
       2: putfield      #14                 // Field validityDuration_:J
       5: aload_0
       6: dup
       7: getfield      #13                 // Field bitField0_:I
      10: iconst_2
      11: ior
      12: putfield      #13                 // Field bitField0_:I
      15: aload_0
      16: invokevirtual #35                 // Method onChanged:()V
      19: aload_0
      20: areturn

  public istio.v1.auth.IstioCertificateRequest$Builder clearValidityDuration();
    Code:
       0: aload_0
       1: aload_0
       2: getfield      #13                 // Field bitField0_:I
       5: bipush        -3
       7: iand
       8: putfield      #13                 // Field bitField0_:I
      11: aload_0
      12: lconst_0
      13: putfield      #14                 // Field validityDuration_:J
      16: aload_0
      17: invokevirtual #35                 // Method onChanged:()V
      20: aload_0
      21: areturn

  public boolean hasMetadata();
    Code:
       0: aload_0
       1: getfield      #13                 // Field bitField0_:I
       4: iconst_4
       5: iand
       6: ifeq          13
       9: iconst_1
      10: goto          14
      13: iconst_0
      14: ireturn

  public com.google.protobuf.Struct getMetadata();
    Code:
       0: aload_0
       1: getfield      #16                 // Field metadataBuilder_:Lcom/google/protobuf/SingleFieldBuilderV3;
       4: ifnonnull     25
       7: aload_0
       8: getfield      #15                 // Field metadata_:Lcom/google/protobuf/Struct;
      11: ifnonnull     20
      14: invokestatic  #59                 // Method com/google/protobuf/Struct.getDefaultInstance:()Lcom/google/protobuf/Struct;
      17: goto          24
      20: aload_0
      21: getfield      #15                 // Field metadata_:Lcom/google/protobuf/Struct;
      24: areturn
      25: aload_0
      26: getfield      #16                 // Field metadataBuilder_:Lcom/google/protobuf/SingleFieldBuilderV3;
      29: invokevirtual #60                 // Method com/google/protobuf/SingleFieldBuilderV3.getMessage:()Lcom/google/protobuf/AbstractMessage;
      32: checkcast     #28                 // class com/google/protobuf/Struct
      35: areturn

  public istio.v1.auth.IstioCertificateRequest$Builder setMetadata(com.google.protobuf.Struct);
    Code:
       0: aload_0
       1: getfield      #16                 // Field metadataBuilder_:Lcom/google/protobuf/SingleFieldBuilderV3;
       4: ifnonnull     27
       7: aload_1
       8: ifnonnull     19
      11: new           #43                 // class java/lang/NullPointerException
      14: dup
      15: invokespecial #44                 // Method java/lang/NullPointerException."<init>":()V
      18: athrow
      19: aload_0
      20: aload_1
      21: putfield      #15                 // Field metadata_:Lcom/google/protobuf/Struct;
      24: goto          36
      27: aload_0
      28: getfield      #16                 // Field metadataBuilder_:Lcom/google/protobuf/SingleFieldBuilderV3;
      31: aload_1
      32: invokevirtual #61                 // Method com/google/protobuf/SingleFieldBuilderV3.setMessage:(Lcom/google/protobuf/AbstractMessage;)Lcom/google/protobuf/SingleFieldBuilderV3;
      35: pop
      36: aload_0
      37: dup
      38: getfield      #13                 // Field bitField0_:I
      41: iconst_4
      42: ior
      43: putfield      #13                 // Field bitField0_:I
      46: aload_0
      47: invokevirtual #35                 // Method onChanged:()V
      50: aload_0
      51: areturn

  public istio.v1.auth.IstioCertificateRequest$Builder setMetadata(com.google.protobuf.Struct$Builder);
    Code:
       0: aload_0
       1: getfield      #16                 // Field metadataBuilder_:Lcom/google/protobuf/SingleFieldBuilderV3;
       4: ifnonnull     18
       7: aload_0
       8: aload_1
       9: invokevirtual #62                 // Method com/google/protobuf/Struct$Builder.build:()Lcom/google/protobuf/Struct;
      12: putfield      #15                 // Field metadata_:Lcom/google/protobuf/Struct;
      15: goto          30
      18: aload_0
      19: getfield      #16                 // Field metadataBuilder_:Lcom/google/protobuf/SingleFieldBuilderV3;
      22: aload_1
      23: invokevirtual #62                 // Method com/google/protobuf/Struct$Builder.build:()Lcom/google/protobuf/Struct;
      26: invokevirtual #61                 // Method com/google/protobuf/SingleFieldBuilderV3.setMessage:(Lcom/google/protobuf/AbstractMessage;)Lcom/google/protobuf/SingleFieldBuilderV3;
      29: pop
      30: aload_0
      31: dup
      32: getfield      #13                 // Field bitField0_:I
      35: iconst_4
      36: ior
      37: putfield      #13                 // Field bitField0_:I
      40: aload_0
      41: invokevirtual #35                 // Method onChanged:()V
      44: aload_0
      45: areturn

  public istio.v1.auth.IstioCertificateRequest$Builder mergeMetadata(com.google.protobuf.Struct);
    Code:
       0: aload_0
       1: getfield      #16                 // Field metadataBuilder_:Lcom/google/protobuf/SingleFieldBuilderV3;
       4: ifnonnull     53
       7: aload_0
       8: getfield      #13                 // Field bitField0_:I
      11: iconst_4
      12: iand
      13: ifeq          45
      16: aload_0
      17: getfield      #15                 // Field metadata_:Lcom/google/protobuf/Struct;
      20: ifnull        45
      23: aload_0
      24: getfield      #15                 // Field metadata_:Lcom/google/protobuf/Struct;
      27: invokestatic  #59                 // Method com/google/protobuf/Struct.getDefaultInstance:()Lcom/google/protobuf/Struct;
      30: if_acmpeq     45
      33: aload_0
      34: invokevirtual #63                 // Method getMetadataBuilder:()Lcom/google/protobuf/Struct$Builder;
      37: aload_1
      38: invokevirtual #64                 // Method com/google/protobuf/Struct$Builder.mergeFrom:(Lcom/google/protobuf/Struct;)Lcom/google/protobuf/Struct$Builder;
      41: pop
      42: goto          62
      45: aload_0
      46: aload_1
      47: putfield      #15                 // Field metadata_:Lcom/google/protobuf/Struct;
      50: goto          62
      53: aload_0
      54: getfield      #16                 // Field metadataBuilder_:Lcom/google/protobuf/SingleFieldBuilderV3;
      57: aload_1
      58: invokevirtual #65                 // Method com/google/protobuf/SingleFieldBuilderV3.mergeFrom:(Lcom/google/protobuf/AbstractMessage;)Lcom/google/protobuf/SingleFieldBuilderV3;
      61: pop
      62: aload_0
      63: dup
      64: getfield      #13                 // Field bitField0_:I
      67: iconst_4
      68: ior
      69: putfield      #13                 // Field bitField0_:I
      72: aload_0
      73: invokevirtual #35                 // Method onChanged:()V
      76: aload_0
      77: areturn

  public istio.v1.auth.IstioCertificateRequest$Builder clearMetadata();
    Code:
       0: aload_0
       1: aload_0
       2: getfield      #13                 // Field bitField0_:I
       5: bipush        -5
       7: iand
       8: putfield      #13                 // Field bitField0_:I
      11: aload_0
      12: aconst_null
      13: putfield      #15                 // Field metadata_:Lcom/google/protobuf/Struct;
      16: aload_0
      17: getfield      #16                 // Field metadataBuilder_:Lcom/google/protobuf/SingleFieldBuilderV3;
      20: ifnull        35
      23: aload_0
      24: getfield      #16                 // Field metadataBuilder_:Lcom/google/protobuf/SingleFieldBuilderV3;
      27: invokevirtual #17                 // Method com/google/protobuf/SingleFieldBuilderV3.dispose:()V
      30: aload_0
      31: aconst_null
      32: putfield      #16                 // Field metadataBuilder_:Lcom/google/protobuf/SingleFieldBuilderV3;
      35: aload_0
      36: invokevirtual #35                 // Method onChanged:()V
      39: aload_0
      40: areturn

  public com.google.protobuf.Struct$Builder getMetadataBuilder();
    Code:
       0: aload_0
       1: dup
       2: getfield      #13                 // Field bitField0_:I
       5: iconst_4
       6: ior
       7: putfield      #13                 // Field bitField0_:I
      10: aload_0
      11: invokevirtual #35                 // Method onChanged:()V
      14: aload_0
      15: invokespecial #48                 // Method getMetadataFieldBuilder:()Lcom/google/protobuf/SingleFieldBuilderV3;
      18: invokevirtual #49                 // Method com/google/protobuf/SingleFieldBuilderV3.getBuilder:()Lcom/google/protobuf/AbstractMessage$Builder;
      21: checkcast     #66                 // class com/google/protobuf/Struct$Builder
      24: areturn

  public com.google.protobuf.StructOrBuilder getMetadataOrBuilder();
    Code:
       0: aload_0
       1: getfield      #16                 // Field metadataBuilder_:Lcom/google/protobuf/SingleFieldBuilderV3;
       4: ifnull        18
       7: aload_0
       8: getfield      #16                 // Field metadataBuilder_:Lcom/google/protobuf/SingleFieldBuilderV3;
      11: invokevirtual #67                 // Method com/google/protobuf/SingleFieldBuilderV3.getMessageOrBuilder:()Lcom/google/protobuf/MessageOrBuilder;
      14: checkcast     #68                 // class com/google/protobuf/StructOrBuilder
      17: areturn
      18: aload_0
      19: getfield      #15                 // Field metadata_:Lcom/google/protobuf/Struct;
      22: ifnonnull     31
      25: invokestatic  #59                 // Method com/google/protobuf/Struct.getDefaultInstance:()Lcom/google/protobuf/Struct;
      28: goto          35
      31: aload_0
      32: getfield      #15                 // Field metadata_:Lcom/google/protobuf/Struct;
      35: areturn

  private com.google.protobuf.SingleFieldBuilderV3<com.google.protobuf.Struct, com.google.protobuf.Struct$Builder, com.google.protobuf.StructOrBuilder> getMetadataFieldBuilder();
    Code:
       0: aload_0
       1: getfield      #16                 // Field metadataBuilder_:Lcom/google/protobuf/SingleFieldBuilderV3;
       4: ifnonnull     35
       7: aload_0
       8: new           #69                 // class com/google/protobuf/SingleFieldBuilderV3
      11: dup
      12: aload_0
      13: invokevirtual #70                 // Method getMetadata:()Lcom/google/protobuf/Struct;
      16: aload_0
      17: invokevirtual #71                 // Method getParentForChildren:()Lcom/google/protobuf/GeneratedMessageV3$BuilderParent;
      20: aload_0
      21: invokevirtual #72                 // Method isClean:()Z
      24: invokespecial #73                 // Method com/google/protobuf/SingleFieldBuilderV3."<init>":(Lcom/google/protobuf/AbstractMessage;Lcom/google/protobuf/AbstractMessage$BuilderParent;Z)V
      27: putfield      #16                 // Field metadataBuilder_:Lcom/google/protobuf/SingleFieldBuilderV3;
      30: aload_0
      31: aconst_null
      32: putfield      #15                 // Field metadata_:Lcom/google/protobuf/Struct;
      35: aload_0
      36: getfield      #16                 // Field metadataBuilder_:Lcom/google/protobuf/SingleFieldBuilderV3;
      39: areturn

  public final istio.v1.auth.IstioCertificateRequest$Builder setUnknownFields(com.google.protobuf.UnknownFieldSet);
    Code:
       0: aload_0
       1: aload_1
       2: invokespecial #74                 // Method com/google/protobuf/GeneratedMessageV3$Builder.setUnknownFields:(Lcom/google/protobuf/UnknownFieldSet;)Lcom/google/protobuf/GeneratedMessageV3$Builder;
       5: checkcast     #6                  // class istio/v1/auth/IstioCertificateRequest$Builder
       8: areturn

  public final istio.v1.auth.IstioCertificateRequest$Builder mergeUnknownFields(com.google.protobuf.UnknownFieldSet);
    Code:
       0: aload_0
       1: aload_1
       2: invokespecial #75                 // Method com/google/protobuf/GeneratedMessageV3$Builder.mergeUnknownFields:(Lcom/google/protobuf/UnknownFieldSet;)Lcom/google/protobuf/GeneratedMessageV3$Builder;
       5: checkcast     #6                  // class istio/v1/auth/IstioCertificateRequest$Builder
       8: areturn

  public com.google.protobuf.GeneratedMessageV3$Builder mergeUnknownFields(com.google.protobuf.UnknownFieldSet);
    Code:
       0: aload_0
       1: aload_1
       2: invokevirtual #42                 // Method mergeUnknownFields:(Lcom/google/protobuf/UnknownFieldSet;)Listio/v1/auth/IstioCertificateRequest$Builder;
       5: areturn

  public com.google.protobuf.GeneratedMessageV3$Builder setUnknownFields(com.google.protobuf.UnknownFieldSet);
    Code:
       0: aload_0
       1: aload_1
       2: invokevirtual #76                 // Method setUnknownFields:(Lcom/google/protobuf/UnknownFieldSet;)Listio/v1/auth/IstioCertificateRequest$Builder;
       5: areturn

  public com.google.protobuf.GeneratedMessageV3$Builder clear();
    Code:
       0: aload_0
       1: invokevirtual #77                 // Method clear:()Listio/v1/auth/IstioCertificateRequest$Builder;
       4: areturn

  public com.google.protobuf.AbstractMessage$Builder mergeUnknownFields(com.google.protobuf.UnknownFieldSet);
    Code:
       0: aload_0
       1: aload_1
       2: invokevirtual #42                 // Method mergeUnknownFields:(Lcom/google/protobuf/UnknownFieldSet;)Listio/v1/auth/IstioCertificateRequest$Builder;
       5: areturn

  public com.google.protobuf.AbstractMessage$Builder mergeFrom(com.google.protobuf.CodedInputStream, com.google.protobuf.ExtensionRegistryLite) throws java.io.IOException;
    Code:
       0: aload_0
       1: aload_1
       2: aload_2
       3: invokevirtual #78                 // Method mergeFrom:(Lcom/google/protobuf/CodedInputStream;Lcom/google/protobuf/ExtensionRegistryLite;)Listio/v1/auth/IstioCertificateRequest$Builder;
       6: areturn

  public com.google.protobuf.AbstractMessage$Builder mergeFrom(com.google.protobuf.Message);
    Code:
       0: aload_0
       1: aload_1
       2: invokevirtual #79                 // Method mergeFrom:(Lcom/google/protobuf/Message;)Listio/v1/auth/IstioCertificateRequest$Builder;
       5: areturn

  public com.google.protobuf.AbstractMessage$Builder clear();
    Code:
       0: aload_0
       1: invokevirtual #77                 // Method clear:()Listio/v1/auth/IstioCertificateRequest$Builder;
       4: areturn

  public com.google.protobuf.Message$Builder mergeUnknownFields(com.google.protobuf.UnknownFieldSet);
    Code:
       0: aload_0
       1: aload_1
       2: invokevirtual #42                 // Method mergeUnknownFields:(Lcom/google/protobuf/UnknownFieldSet;)Listio/v1/auth/IstioCertificateRequest$Builder;
       5: areturn

  public com.google.protobuf.Message$Builder setUnknownFields(com.google.protobuf.UnknownFieldSet);
    Code:
       0: aload_0
       1: aload_1
       2: invokevirtual #76                 // Method setUnknownFields:(Lcom/google/protobuf/UnknownFieldSet;)Listio/v1/auth/IstioCertificateRequest$Builder;
       5: areturn

  public com.google.protobuf.Message$Builder mergeFrom(com.google.protobuf.CodedInputStream, com.google.protobuf.ExtensionRegistryLite) throws java.io.IOException;
    Code:
       0: aload_0
       1: aload_1
       2: aload_2
       3: invokevirtual #78                 // Method mergeFrom:(Lcom/google/protobuf/CodedInputStream;Lcom/google/protobuf/ExtensionRegistryLite;)Listio/v1/auth/IstioCertificateRequest$Builder;
       6: areturn

  public com.google.protobuf.Message buildPartial();
    Code:
       0: aload_0
       1: invokevirtual #19                 // Method buildPartial:()Listio/v1/auth/IstioCertificateRequest;
       4: areturn

  public com.google.protobuf.Message build();
    Code:
       0: aload_0
       1: invokevirtual #80                 // Method build:()Listio/v1/auth/IstioCertificateRequest;
       4: areturn

  public com.google.protobuf.Message$Builder mergeFrom(com.google.protobuf.Message);
    Code:
       0: aload_0
       1: aload_1
       2: invokevirtual #79                 // Method mergeFrom:(Lcom/google/protobuf/Message;)Listio/v1/auth/IstioCertificateRequest$Builder;
       5: areturn

  public com.google.protobuf.Message$Builder clear();
    Code:
       0: aload_0
       1: invokevirtual #77                 // Method clear:()Listio/v1/auth/IstioCertificateRequest$Builder;
       4: areturn

  public com.google.protobuf.MessageLite$Builder mergeFrom(com.google.protobuf.CodedInputStream, com.google.protobuf.ExtensionRegistryLite) throws java.io.IOException;
    Code:
       0: aload_0
       1: aload_1
       2: aload_2
       3: invokevirtual #78                 // Method mergeFrom:(Lcom/google/protobuf/CodedInputStream;Lcom/google/protobuf/ExtensionRegistryLite;)Listio/v1/auth/IstioCertificateRequest$Builder;
       6: areturn

  public com.google.protobuf.MessageLite buildPartial();
    Code:
       0: aload_0
       1: invokevirtual #19                 // Method buildPartial:()Listio/v1/auth/IstioCertificateRequest;
       4: areturn

  public com.google.protobuf.MessageLite build();
    Code:
       0: aload_0
       1: invokevirtual #80                 // Method build:()Listio/v1/auth/IstioCertificateRequest;
       4: areturn

  public com.google.protobuf.MessageLite$Builder clear();
    Code:
       0: aload_0
       1: invokevirtual #77                 // Method clear:()Listio/v1/auth/IstioCertificateRequest$Builder;
       4: areturn

  public com.google.protobuf.MessageLite getDefaultInstanceForType();
    Code:
       0: aload_0
       1: invokevirtual #81                 // Method getDefaultInstanceForType:()Listio/v1/auth/IstioCertificateRequest;
       4: areturn

  public com.google.protobuf.Message getDefaultInstanceForType();
    Code:
       0: aload_0
       1: invokevirtual #81                 // Method getDefaultInstanceForType:()Listio/v1/auth/IstioCertificateRequest;
       4: areturn

  public com.google.protobuf.AbstractMessageLite$Builder mergeFrom(com.google.protobuf.CodedInputStream, com.google.protobuf.ExtensionRegistryLite) throws java.io.IOException;
    Code:
       0: aload_0
       1: aload_1
       2: aload_2
       3: invokevirtual #78                 // Method mergeFrom:(Lcom/google/protobuf/CodedInputStream;Lcom/google/protobuf/ExtensionRegistryLite;)Listio/v1/auth/IstioCertificateRequest$Builder;
       6: areturn

  istio.v1.auth.IstioCertificateRequest$Builder(istio.v1.auth.IstioCertificateRequest$1);
    Code:
       0: aload_0
       1: invokespecial #2                  // Method "<init>":()V
       4: return

  istio.v1.auth.IstioCertificateRequest$Builder(com.google.protobuf.GeneratedMessageV3$BuilderParent, istio.v1.auth.IstioCertificateRequest$1);
    Code:
       0: aload_0
       1: aload_1
       2: invokespecial #1                  // Method "<init>":(Lcom/google/protobuf/GeneratedMessageV3$BuilderParent;)V
       5: return
}
