Compiled from "IstioCertificateServiceGrpc.java"
final class istio.v1.auth.IstioCertificateServiceGrpc$2 implements io.grpc.stub.AbstractStub$StubFactory<istio.v1.auth.IstioCertificateServiceGrpc$IstioCertificateServiceBlockingStub> {
  istio.v1.auth.IstioCertificateServiceGrpc$2();
    Code:
       0: aload_0
       1: invokespecial #1                  // Method java/lang/Object."<init>":()V
       4: return

  public istio.v1.auth.IstioCertificateServiceGrpc$IstioCertificateServiceBlockingStub newStub(io.grpc.Channel, io.grpc.CallOptions);
    Code:
       0: new           #2                  // class istio/v1/auth/IstioCertificateServiceGrpc$IstioCertificateServiceBlockingStub
       3: dup
       4: aload_1
       5: aload_2
       6: aconst_null
       7: invokespecial #3                  // Method istio/v1/auth/IstioCertificateServiceGrpc$IstioCertificateServiceBlockingStub."<init>":(Lio/grpc/Channel;Lio/grpc/CallOptions;Listio/v1/auth/IstioCertificateServiceGrpc$1;)V
      10: areturn

  public io.grpc.stub.AbstractStub newStub(io.grpc.Channel, io.grpc.CallOptions);
    Code:
       0: aload_0
       1: aload_1
       2: aload_2
       3: invokevirtual #4                  // Method newStub:(Lio/grpc/Channel;Lio/grpc/CallOptions;)Listio/v1/auth/IstioCertificateServiceGrpc$IstioCertificateServiceBlockingStub;
       6: areturn
}
