Compiled from "IstioCertificateService.java"
final class istio.v1.auth.IstioCertificateService$1 extends istio.v1.auth.IstioCertificateService {
  final istio.v1.auth.IstioCertificateService$Interface val$impl;

  istio.v1.auth.IstioCertificateService$1(istio.v1.auth.IstioCertificateService$Interface);
    Code:
       0: aload_0
       1: aload_1
       2: putfield      #1                  // Field val$impl:Listio/v1/auth/IstioCertificateService$Interface;
       5: aload_0
       6: invokespecial #2                  // Method istio/v1/auth/IstioCertificateService."<init>":()V
       9: return

  public void createCertificate(com.google.protobuf.RpcController, istio.v1.auth.IstioCertificateRequest, com.google.protobuf.RpcCallback<istio.v1.auth.IstioCertificateResponse>);
    Code:
       0: aload_0
       1: getfield      #1                  // Field val$impl:Listio/v1/auth/IstioCertificateService$Interface;
       4: aload_1
       5: aload_2
       6: aload_3
       7: invokeinterface #3,  4            // InterfaceMethod istio/v1/auth/IstioCertificateService$Interface.createCertificate:(Lcom/google/protobuf/RpcController;Listio/v1/auth/IstioCertificateRequest;Lcom/google/protobuf/RpcCallback;)V
      12: return
}
