Compiled from "IstioCertificateServiceGrpc.java"
final class istio.v1.auth.IstioCertificateServiceGrpc$MethodHandlers<Req, Resp> implements io.grpc.stub.ServerCalls$UnaryMethod<Req, Resp>, io.grpc.stub.ServerCalls$ServerStreamingMethod<Req, Resp>, io.grpc.stub.ServerCalls$ClientStreamingMethod<Req, Resp>, io.grpc.stub.ServerCalls$BidiStreamingMethod<Req, Resp> {
  private final istio.v1.auth.IstioCertificateServiceGrpc$AsyncService serviceImpl;

  private final int methodId;

  istio.v1.auth.IstioCertificateServiceGrpc$MethodHandlers(istio.v1.auth.IstioCertificateServiceGrpc$AsyncService, int);
    Code:
       0: aload_0
       1: invokespecial #2                  // Method java/lang/Object."<init>":()V
       4: aload_0
       5: aload_1
       6: putfield      #3                  // Field serviceImpl:Listio/v1/auth/IstioCertificateServiceGrpc$AsyncService;
       9: aload_0
      10: iload_2
      11: putfield      #4                  // Field methodId:I
      14: return

  public void invoke(Req, io.grpc.stub.StreamObserver<Resp>);
    Code:
       0: aload_0
       1: getfield      #4                  // Field methodId:I
       4: lookupswitch  { // 1
                     0: 24
               default: 41
          }
      24: aload_0
      25: getfield      #3                  // Field serviceImpl:Listio/v1/auth/IstioCertificateServiceGrpc$AsyncService;
      28: aload_1
      29: checkcast     #5                  // class istio/v1/auth/IstioCertificateRequest
      32: aload_2
      33: invokeinterface #6,  3            // InterfaceMethod istio/v1/auth/IstioCertificateServiceGrpc$AsyncService.createCertificate:(Listio/v1/auth/IstioCertificateRequest;Lio/grpc/stub/StreamObserver;)V
      38: goto          49
      41: new           #7                  // class java/lang/AssertionError
      44: dup
      45: invokespecial #8                  // Method java/lang/AssertionError."<init>":()V
      48: athrow
      49: return

  public io.grpc.stub.StreamObserver<Req> invoke(io.grpc.stub.StreamObserver<Resp>);
    Code:
       0: aload_0
       1: getfield      #4                  // Field methodId:I
       4: lookupswitch  { // 0
               default: 16
          }
      16: new           #7                  // class java/lang/AssertionError
      19: dup
      20: invokespecial #8                  // Method java/lang/AssertionError."<init>":()V
      23: athrow
}
