Compiled from "CompletableAndThenObservable.java"
public final class io.reactivex.rxjava3.internal.operators.mixed.CompletableAndThenObservable<R> extends io.reactivex.rxjava3.core.Observable<R> {
  final io.reactivex.rxjava3.core.CompletableSource source;

  final io.reactivex.rxjava3.core.ObservableSource<? extends R> other;

  public io.reactivex.rxjava3.internal.operators.mixed.CompletableAndThenObservable(io.reactivex.rxjava3.core.CompletableSource, io.reactivex.rxjava3.core.ObservableSource<? extends R>);
    Code:
       0: aload_0
       1: invokespecial #1                  // Method io/reactivex/rxjava3/core/Observable."<init>":()V
       4: aload_0
       5: aload_1
       6: putfield      #2                  // Field source:Lio/reactivex/rxjava3/core/CompletableSource;
       9: aload_0
      10: aload_2
      11: putfield      #3                  // Field other:Lio/reactivex/rxjava3/core/ObservableSource;
      14: return

  protected void subscribeActual(io.reactivex.rxjava3.core.Observer<? super R>);
    Code:
       0: new           #4                  // class io/reactivex/rxjava3/internal/operators/mixed/CompletableAndThenObservable$AndThenObservableObserver
       3: dup
       4: aload_1
       5: aload_0
       6: getfield      #3                  // Field other:Lio/reactivex/rxjava3/core/ObservableSource;
       9: invokespecial #5                  // Method io/reactivex/rxjava3/internal/operators/mixed/CompletableAndThenObservable$AndThenObservableObserver."<init>":(Lio/reactivex/rxjava3/core/Observer;Lio/reactivex/rxjava3/core/ObservableSource;)V
      12: astore_2
      13: aload_1
      14: aload_2
      15: invokeinterface #6,  2            // InterfaceMethod io/reactivex/rxjava3/core/Observer.onSubscribe:(Lio/reactivex/rxjava3/disposables/Disposable;)V
      20: aload_0
      21: getfield      #2                  // Field source:Lio/reactivex/rxjava3/core/CompletableSource;
      24: aload_2
      25: invokeinterface #7,  2            // InterfaceMethod io/reactivex/rxjava3/core/CompletableSource.subscribe:(Lio/reactivex/rxjava3/core/CompletableObserver;)V
      30: return
}
