Compiled from "FlowableConcatMapCompletable.java"
final class io.reactivex.rxjava3.internal.operators.mixed.FlowableConcatMapCompletable$ConcatMapCompletableObserver<T> extends io.reactivex.rxjava3.internal.operators.mixed.ConcatMapXMainSubscriber<T> implements io.reactivex.rxjava3.disposables.Disposable {
  private static final long serialVersionUID;

  final io.reactivex.rxjava3.core.CompletableObserver downstream;

  final io.reactivex.rxjava3.functions.Function<? super T, ? extends io.reactivex.rxjava3.core.CompletableSource> mapper;

  final io.reactivex.rxjava3.internal.operators.mixed.FlowableConcatMapCompletable$ConcatMapCompletableObserver$ConcatMapInnerObserver inner;

  volatile boolean active;

  int consumed;

  io.reactivex.rxjava3.internal.operators.mixed.FlowableConcatMapCompletable$ConcatMapCompletableObserver(io.reactivex.rxjava3.core.CompletableObserver, io.reactivex.rxjava3.functions.Function<? super T, ? extends io.reactivex.rxjava3.core.CompletableSource>, io.reactivex.rxjava3.internal.util.ErrorMode, int);
    Code:
       0: aload_0
       1: iload         4
       3: aload_3
       4: invokespecial #1                  // Method io/reactivex/rxjava3/internal/operators/mixed/ConcatMapXMainSubscriber."<init>":(ILio/reactivex/rxjava3/internal/util/ErrorMode;)V
       7: aload_0
       8: aload_1
       9: putfield      #2                  // Field downstream:Lio/reactivex/rxjava3/core/CompletableObserver;
      12: aload_0
      13: aload_2
      14: putfield      #3                  // Field mapper:Lio/reactivex/rxjava3/functions/Function;
      17: aload_0
      18: new           #4                  // class io/reactivex/rxjava3/internal/operators/mixed/FlowableConcatMapCompletable$ConcatMapCompletableObserver$ConcatMapInnerObserver
      21: dup
      22: aload_0
      23: invokespecial #5                  // Method io/reactivex/rxjava3/internal/operators/mixed/FlowableConcatMapCompletable$ConcatMapCompletableObserver$ConcatMapInnerObserver."<init>":(Lio/reactivex/rxjava3/internal/operators/mixed/FlowableConcatMapCompletable$ConcatMapCompletableObserver;)V
      26: putfield      #6                  // Field inner:Lio/reactivex/rxjava3/internal/operators/mixed/FlowableConcatMapCompletable$ConcatMapCompletableObserver$ConcatMapInnerObserver;
      29: return

  void onSubscribeDownstream();
    Code:
       0: aload_0
       1: getfield      #2                  // Field downstream:Lio/reactivex/rxjava3/core/CompletableObserver;
       4: aload_0
       5: invokeinterface #7,  2            // InterfaceMethod io/reactivex/rxjava3/core/CompletableObserver.onSubscribe:(Lio/reactivex/rxjava3/disposables/Disposable;)V
      10: return

  void disposeInner();
    Code:
       0: aload_0
       1: getfield      #6                  // Field inner:Lio/reactivex/rxjava3/internal/operators/mixed/FlowableConcatMapCompletable$ConcatMapCompletableObserver$ConcatMapInnerObserver;
       4: invokevirtual #8                  // Method io/reactivex/rxjava3/internal/operators/mixed/FlowableConcatMapCompletable$ConcatMapCompletableObserver$ConcatMapInnerObserver.dispose:()V
       7: return

  public void dispose();
    Code:
       0: aload_0
       1: invokevirtual #9                  // Method stop:()V
       4: return

  public boolean isDisposed();
    Code:
       0: aload_0
       1: getfield      #10                 // Field cancelled:Z
       4: ireturn

  void innerError(java.lang.Throwable);
    Code:
       0: aload_0
       1: getfield      #11                 // Field errors:Lio/reactivex/rxjava3/internal/util/AtomicThrowable;
       4: aload_1
       5: invokevirtual #12                 // Method io/reactivex/rxjava3/internal/util/AtomicThrowable.tryAddThrowableOrReport:(Ljava/lang/Throwable;)Z
       8: ifeq          69
      11: aload_0
      12: getfield      #13                 // Field errorMode:Lio/reactivex/rxjava3/internal/util/ErrorMode;
      15: getstatic     #14                 // Field io/reactivex/rxjava3/internal/util/ErrorMode.IMMEDIATE:Lio/reactivex/rxjava3/internal/util/ErrorMode;
      18: if_acmpne     60
      21: aload_0
      22: getfield      #15                 // Field upstream:Lorg/reactivestreams/Subscription;
      25: invokeinterface #16,  1           // InterfaceMethod org/reactivestreams/Subscription.cancel:()V
      30: aload_0
      31: getfield      #11                 // Field errors:Lio/reactivex/rxjava3/internal/util/AtomicThrowable;
      34: aload_0
      35: getfield      #2                  // Field downstream:Lio/reactivex/rxjava3/core/CompletableObserver;
      38: invokevirtual #17                 // Method io/reactivex/rxjava3/internal/util/AtomicThrowable.tryTerminateConsumer:(Lio/reactivex/rxjava3/core/CompletableObserver;)V
      41: aload_0
      42: invokevirtual #18                 // Method getAndIncrement:()I
      45: ifne          69
      48: aload_0
      49: getfield      #19                 // Field queue:Lio/reactivex/rxjava3/operators/SimpleQueue;
      52: invokeinterface #20,  1           // InterfaceMethod io/reactivex/rxjava3/operators/SimpleQueue.clear:()V
      57: goto          69
      60: aload_0
      61: iconst_0
      62: putfield      #21                 // Field active:Z
      65: aload_0
      66: invokevirtual #22                 // Method drain:()V
      69: return

  void innerComplete();
    Code:
       0: aload_0
       1: iconst_0
       2: putfield      #21                 // Field active:Z
       5: aload_0
       6: invokevirtual #22                 // Method drain:()V
       9: return

  void drain();
    Code:
       0: aload_0
       1: invokevirtual #18                 // Method getAndIncrement:()I
       4: ifeq          8
       7: return
       8: aload_0
       9: getfield      #13                 // Field errorMode:Lio/reactivex/rxjava3/internal/util/ErrorMode;
      12: astore_1
      13: aload_0
      14: getfield      #19                 // Field queue:Lio/reactivex/rxjava3/operators/SimpleQueue;
      17: astore_2
      18: aload_0
      19: getfield      #11                 // Field errors:Lio/reactivex/rxjava3/internal/util/AtomicThrowable;
      22: astore_3
      23: aload_0
      24: getfield      #23                 // Field syncFused:Z
      27: istore        4
      29: aload_0
      30: getfield      #10                 // Field cancelled:Z
      33: ifeq          43
      36: aload_2
      37: invokeinterface #20,  1           // InterfaceMethod io/reactivex/rxjava3/operators/SimpleQueue.clear:()V
      42: return
      43: aload_3
      44: invokevirtual #24                 // Method io/reactivex/rxjava3/internal/util/AtomicThrowable.get:()Ljava/lang/Object;
      47: ifnull        86
      50: aload_1
      51: getstatic     #14                 // Field io/reactivex/rxjava3/internal/util/ErrorMode.IMMEDIATE:Lio/reactivex/rxjava3/internal/util/ErrorMode;
      54: if_acmpeq     71
      57: aload_1
      58: getstatic     #25                 // Field io/reactivex/rxjava3/internal/util/ErrorMode.BOUNDARY:Lio/reactivex/rxjava3/internal/util/ErrorMode;
      61: if_acmpne     86
      64: aload_0
      65: getfield      #21                 // Field active:Z
      68: ifne          86
      71: aload_2
      72: invokeinterface #20,  1           // InterfaceMethod io/reactivex/rxjava3/operators/SimpleQueue.clear:()V
      77: aload_3
      78: aload_0
      79: getfield      #2                  // Field downstream:Lio/reactivex/rxjava3/core/CompletableObserver;
      82: invokevirtual #17                 // Method io/reactivex/rxjava3/internal/util/AtomicThrowable.tryTerminateConsumer:(Lio/reactivex/rxjava3/core/CompletableObserver;)V
      85: return
      86: aload_0
      87: getfield      #21                 // Field active:Z
      90: ifne          315
      93: aload_0
      94: getfield      #26                 // Field done:Z
      97: istore        5
      99: aload_2
     100: invokeinterface #27,  1           // InterfaceMethod io/reactivex/rxjava3/operators/SimpleQueue.poll:()Ljava/lang/Object;
     105: astore        6
     107: goto          142
     110: astore        7
     112: aload         7
     114: invokestatic  #29                 // Method io/reactivex/rxjava3/exceptions/Exceptions.throwIfFatal:(Ljava/lang/Throwable;)V
     117: aload_0
     118: getfield      #15                 // Field upstream:Lorg/reactivestreams/Subscription;
     121: invokeinterface #16,  1           // InterfaceMethod org/reactivestreams/Subscription.cancel:()V
     126: aload_3
     127: aload         7
     129: invokevirtual #12                 // Method io/reactivex/rxjava3/internal/util/AtomicThrowable.tryAddThrowableOrReport:(Ljava/lang/Throwable;)Z
     132: pop
     133: aload_3
     134: aload_0
     135: getfield      #2                  // Field downstream:Lio/reactivex/rxjava3/core/CompletableObserver;
     138: invokevirtual #17                 // Method io/reactivex/rxjava3/internal/util/AtomicThrowable.tryTerminateConsumer:(Lio/reactivex/rxjava3/core/CompletableObserver;)V
     141: return
     142: aload         6
     144: ifnonnull     151
     147: iconst_1
     148: goto          152
     151: iconst_0
     152: istore        7
     154: iload         5
     156: ifeq          173
     159: iload         7
     161: ifeq          173
     164: aload_3
     165: aload_0
     166: getfield      #2                  // Field downstream:Lio/reactivex/rxjava3/core/CompletableObserver;
     169: invokevirtual #17                 // Method io/reactivex/rxjava3/internal/util/AtomicThrowable.tryTerminateConsumer:(Lio/reactivex/rxjava3/core/CompletableObserver;)V
     172: return
     173: iload         7
     175: ifne          315
     178: aload_0
     179: getfield      #30                 // Field prefetch:I
     182: aload_0
     183: getfield      #30                 // Field prefetch:I
     186: iconst_1
     187: ishr
     188: isub
     189: istore        8
     191: iload         4
     193: ifne          237
     196: aload_0
     197: getfield      #31                 // Field consumed:I
     200: iconst_1
     201: iadd
     202: istore        9
     204: iload         9
     206: iload         8
     208: if_icmpne     231
     211: aload_0
     212: iconst_0
     213: putfield      #31                 // Field consumed:I
     216: aload_0
     217: getfield      #15                 // Field upstream:Lorg/reactivestreams/Subscription;
     220: iload         8
     222: i2l
     223: invokeinterface #32,  3           // InterfaceMethod org/reactivestreams/Subscription.request:(J)V
     228: goto          237
     231: aload_0
     232: iload         9
     234: putfield      #31                 // Field consumed:I
     237: aload_0
     238: getfield      #3                  // Field mapper:Lio/reactivex/rxjava3/functions/Function;
     241: aload         6
     243: invokeinterface #33,  2           // InterfaceMethod io/reactivex/rxjava3/functions/Function.apply:(Ljava/lang/Object;)Ljava/lang/Object;
     248: ldc           #34                 // String The mapper returned a null CompletableSource
     250: invokestatic  #35                 // Method java/util/Objects.requireNonNull:(Ljava/lang/Object;Ljava/lang/String;)Ljava/lang/Object;
     253: checkcast     #36                 // class io/reactivex/rxjava3/core/CompletableSource
     256: astore        9
     258: goto          299
     261: astore        10
     263: aload         10
     265: invokestatic  #29                 // Method io/reactivex/rxjava3/exceptions/Exceptions.throwIfFatal:(Ljava/lang/Throwable;)V
     268: aload_2
     269: invokeinterface #20,  1           // InterfaceMethod io/reactivex/rxjava3/operators/SimpleQueue.clear:()V
     274: aload_0
     275: getfield      #15                 // Field upstream:Lorg/reactivestreams/Subscription;
     278: invokeinterface #16,  1           // InterfaceMethod org/reactivestreams/Subscription.cancel:()V
     283: aload_3
     284: aload         10
     286: invokevirtual #12                 // Method io/reactivex/rxjava3/internal/util/AtomicThrowable.tryAddThrowableOrReport:(Ljava/lang/Throwable;)Z
     289: pop
     290: aload_3
     291: aload_0
     292: getfield      #2                  // Field downstream:Lio/reactivex/rxjava3/core/CompletableObserver;
     295: invokevirtual #17                 // Method io/reactivex/rxjava3/internal/util/AtomicThrowable.tryTerminateConsumer:(Lio/reactivex/rxjava3/core/CompletableObserver;)V
     298: return
     299: aload_0
     300: iconst_1
     301: putfield      #21                 // Field active:Z
     304: aload         9
     306: aload_0
     307: getfield      #6                  // Field inner:Lio/reactivex/rxjava3/internal/operators/mixed/FlowableConcatMapCompletable$ConcatMapCompletableObserver$ConcatMapInnerObserver;
     310: invokeinterface #37,  2           // InterfaceMethod io/reactivex/rxjava3/core/CompletableSource.subscribe:(Lio/reactivex/rxjava3/core/CompletableObserver;)V
     315: aload_0
     316: invokevirtual #38                 // Method decrementAndGet:()I
     319: ifne          29
     322: return
    Exception table:
       from    to  target type
          99   107   110   Class java/lang/Throwable
         237   258   261   Class java/lang/Throwable
}
