Compiled from "FlowableConcatMapSingle.java"
public final class io.reactivex.rxjava3.internal.operators.mixed.FlowableConcatMapSingle<T, R> extends io.reactivex.rxjava3.core.Flowable<R> {
  final io.reactivex.rxjava3.core.Flowable<T> source;

  final io.reactivex.rxjava3.functions.Function<? super T, ? extends io.reactivex.rxjava3.core.SingleSource<? extends R>> mapper;

  final io.reactivex.rxjava3.internal.util.ErrorMode errorMode;

  final int prefetch;

  public io.reactivex.rxjava3.internal.operators.mixed.FlowableConcatMapSingle(io.reactivex.rxjava3.core.Flowable<T>, io.reactivex.rxjava3.functions.Function<? super T, ? extends io.reactivex.rxjava3.core.SingleSource<? extends R>>, io.reactivex.rxjava3.internal.util.ErrorMode, int);
    Code:
       0: aload_0
       1: invokespecial #1                  // Method io/reactivex/rxjava3/core/Flowable."<init>":()V
       4: aload_0
       5: aload_1
       6: putfield      #2                  // Field source:Lio/reactivex/rxjava3/core/Flowable;
       9: aload_0
      10: aload_2
      11: putfield      #3                  // Field mapper:Lio/reactivex/rxjava3/functions/Function;
      14: aload_0
      15: aload_3
      16: putfield      #4                  // Field errorMode:Lio/reactivex/rxjava3/internal/util/ErrorMode;
      19: aload_0
      20: iload         4
      22: putfield      #5                  // Field prefetch:I
      25: return

  protected void subscribeActual(org.reactivestreams.Subscriber<? super R>);
    Code:
       0: aload_0
       1: getfield      #2                  // Field source:Lio/reactivex/rxjava3/core/Flowable;
       4: new           #6                  // class io/reactivex/rxjava3/internal/operators/mixed/FlowableConcatMapSingle$ConcatMapSingleSubscriber
       7: dup
       8: aload_1
       9: aload_0
      10: getfield      #3                  // Field mapper:Lio/reactivex/rxjava3/functions/Function;
      13: aload_0
      14: getfield      #5                  // Field prefetch:I
      17: aload_0
      18: getfield      #4                  // Field errorMode:Lio/reactivex/rxjava3/internal/util/ErrorMode;
      21: invokespecial #7                  // Method io/reactivex/rxjava3/internal/operators/mixed/FlowableConcatMapSingle$ConcatMapSingleSubscriber."<init>":(Lorg/reactivestreams/Subscriber;Lio/reactivex/rxjava3/functions/Function;ILio/reactivex/rxjava3/internal/util/ErrorMode;)V
      24: invokevirtual #8                  // Method io/reactivex/rxjava3/core/Flowable.subscribe:(Lio/reactivex/rxjava3/core/FlowableSubscriber;)V
      27: return
}
