Compiled from "FlowableSwitchMapCompletable.java"
public final class io.reactivex.rxjava3.internal.operators.mixed.FlowableSwitchMapCompletable<T> extends io.reactivex.rxjava3.core.Completable {
  final io.reactivex.rxjava3.core.Flowable<T> source;

  final io.reactivex.rxjava3.functions.Function<? super T, ? extends io.reactivex.rxjava3.core.CompletableSource> mapper;

  final boolean delayErrors;

  public io.reactivex.rxjava3.internal.operators.mixed.FlowableSwitchMapCompletable(io.reactivex.rxjava3.core.Flowable<T>, io.reactivex.rxjava3.functions.Function<? super T, ? extends io.reactivex.rxjava3.core.CompletableSource>, boolean);
    Code:
       0: aload_0
       1: invokespecial #1                  // Method io/reactivex/rxjava3/core/Completable."<init>":()V
       4: aload_0
       5: aload_1
       6: putfield      #2                  // Field source:Lio/reactivex/rxjava3/core/Flowable;
       9: aload_0
      10: aload_2
      11: putfield      #3                  // Field mapper:Lio/reactivex/rxjava3/functions/Function;
      14: aload_0
      15: iload_3
      16: putfield      #4                  // Field delayErrors:Z
      19: return

  protected void subscribeActual(io.reactivex.rxjava3.core.CompletableObserver);
    Code:
       0: aload_0
       1: getfield      #2                  // Field source:Lio/reactivex/rxjava3/core/Flowable;
       4: new           #5                  // class io/reactivex/rxjava3/internal/operators/mixed/FlowableSwitchMapCompletable$SwitchMapCompletableObserver
       7: dup
       8: aload_1
       9: aload_0
      10: getfield      #3                  // Field mapper:Lio/reactivex/rxjava3/functions/Function;
      13: aload_0
      14: getfield      #4                  // Field delayErrors:Z
      17: invokespecial #6                  // Method io/reactivex/rxjava3/internal/operators/mixed/FlowableSwitchMapCompletable$SwitchMapCompletableObserver."<init>":(Lio/reactivex/rxjava3/core/CompletableObserver;Lio/reactivex/rxjava3/functions/Function;Z)V
      20: invokevirtual #7                  // Method io/reactivex/rxjava3/core/Flowable.subscribe:(Lio/reactivex/rxjava3/core/FlowableSubscriber;)V
      23: return
}
