Compiled from "ObservableSwitchMapCompletable.java"
public final class io.reactivex.rxjava3.internal.operators.mixed.ObservableSwitchMapCompletable<T> extends io.reactivex.rxjava3.core.Completable {
  final io.reactivex.rxjava3.core.Observable<T> source;

  final io.reactivex.rxjava3.functions.Function<? super T, ? extends io.reactivex.rxjava3.core.CompletableSource> mapper;

  final boolean delayErrors;

  public io.reactivex.rxjava3.internal.operators.mixed.ObservableSwitchMapCompletable(io.reactivex.rxjava3.core.Observable<T>, io.reactivex.rxjava3.functions.Function<? super T, ? extends io.reactivex.rxjava3.core.CompletableSource>, boolean);
    Code:
       0: aload_0
       1: invokespecial #1                  // Method io/reactivex/rxjava3/core/Completable."<init>":()V
       4: aload_0
       5: aload_1
       6: putfield      #2                  // Field source:Lio/reactivex/rxjava3/core/Observable;
       9: aload_0
      10: aload_2
      11: putfield      #3                  // Field mapper:Lio/reactivex/rxjava3/functions/Function;
      14: aload_0
      15: iload_3
      16: putfield      #4                  // Field delayErrors:Z
      19: return

  protected void subscribeActual(io.reactivex.rxjava3.core.CompletableObserver);
    Code:
       0: aload_0
       1: getfield      #2                  // Field source:Lio/reactivex/rxjava3/core/Observable;
       4: aload_0
       5: getfield      #3                  // Field mapper:Lio/reactivex/rxjava3/functions/Function;
       8: aload_1
       9: invokestatic  #5                  // Method io/reactivex/rxjava3/internal/operators/mixed/ScalarXMapZHelper.tryAsCompletable:(Ljava/lang/Object;Lio/reactivex/rxjava3/functions/Function;Lio/reactivex/rxjava3/core/CompletableObserver;)Z
      12: ifne          38
      15: aload_0
      16: getfield      #2                  // Field source:Lio/reactivex/rxjava3/core/Observable;
      19: new           #6                  // class io/reactivex/rxjava3/internal/operators/mixed/ObservableSwitchMapCompletable$SwitchMapCompletableObserver
      22: dup
      23: aload_1
      24: aload_0
      25: getfield      #3                  // Field mapper:Lio/reactivex/rxjava3/functions/Function;
      28: aload_0
      29: getfield      #4                  // Field delayErrors:Z
      32: invokespecial #7                  // Method io/reactivex/rxjava3/internal/operators/mixed/ObservableSwitchMapCompletable$SwitchMapCompletableObserver."<init>":(Lio/reactivex/rxjava3/core/CompletableObserver;Lio/reactivex/rxjava3/functions/Function;Z)V
      35: invokevirtual #8                  // Method io/reactivex/rxjava3/core/Observable.subscribe:(Lio/reactivex/rxjava3/core/Observer;)V
      38: return
}
