Compiled from "ObservableSwitchMapMaybe.java"
final class io.reactivex.rxjava3.internal.operators.mixed.ObservableSwitchMapMaybe$SwitchMapMaybeMainObserver$SwitchMapMaybeObserver<R> extends java.util.concurrent.atomic.AtomicReference<io.reactivex.rxjava3.disposables.Disposable> implements io.reactivex.rxjava3.core.MaybeObserver<R> {
  private static final long serialVersionUID;

  final io.reactivex.rxjava3.internal.operators.mixed.ObservableSwitchMapMaybe$SwitchMapMaybeMainObserver<?, R> parent;

  volatile R item;

  io.reactivex.rxjava3.internal.operators.mixed.ObservableSwitchMapMaybe$SwitchMapMaybeMainObserver$SwitchMapMaybeObserver(io.reactivex.rxjava3.internal.operators.mixed.ObservableSwitchMapMaybe$SwitchMapMaybeMainObserver<?, R>);
    Code:
       0: aload_0
       1: invokespecial #1                  // Method java/util/concurrent/atomic/AtomicReference."<init>":()V
       4: aload_0
       5: aload_1
       6: putfield      #2                  // Field parent:Lio/reactivex/rxjava3/internal/operators/mixed/ObservableSwitchMapMaybe$SwitchMapMaybeMainObserver;
       9: return

  public void onSubscribe(io.reactivex.rxjava3.disposables.Disposable);
    Code:
       0: aload_0
       1: aload_1
       2: invokestatic  #3                  // Method io/reactivex/rxjava3/internal/disposables/DisposableHelper.setOnce:(Ljava/util/concurrent/atomic/AtomicReference;Lio/reactivex/rxjava3/disposables/Disposable;)Z
       5: pop
       6: return

  public void onSuccess(R);
    Code:
       0: aload_0
       1: aload_1
       2: putfield      #4                  // Field item:Ljava/lang/Object;
       5: aload_0
       6: getfield      #2                  // Field parent:Lio/reactivex/rxjava3/internal/operators/mixed/ObservableSwitchMapMaybe$SwitchMapMaybeMainObserver;
       9: invokevirtual #5                  // Method io/reactivex/rxjava3/internal/operators/mixed/ObservableSwitchMapMaybe$SwitchMapMaybeMainObserver.drain:()V
      12: return

  public void onError(java.lang.Throwable);
    Code:
       0: aload_0
       1: getfield      #2                  // Field parent:Lio/reactivex/rxjava3/internal/operators/mixed/ObservableSwitchMapMaybe$SwitchMapMaybeMainObserver;
       4: aload_0
       5: aload_1
       6: invokevirtual #6                  // Method io/reactivex/rxjava3/internal/operators/mixed/ObservableSwitchMapMaybe$SwitchMapMaybeMainObserver.innerError:(Lio/reactivex/rxjava3/internal/operators/mixed/ObservableSwitchMapMaybe$SwitchMapMaybeMainObserver$SwitchMapMaybeObserver;Ljava/lang/Throwable;)V
       9: return

  public void onComplete();
    Code:
       0: aload_0
       1: getfield      #2                  // Field parent:Lio/reactivex/rxjava3/internal/operators/mixed/ObservableSwitchMapMaybe$SwitchMapMaybeMainObserver;
       4: aload_0
       5: invokevirtual #7                  // Method io/reactivex/rxjava3/internal/operators/mixed/ObservableSwitchMapMaybe$SwitchMapMaybeMainObserver.innerComplete:(Lio/reactivex/rxjava3/internal/operators/mixed/ObservableSwitchMapMaybe$SwitchMapMaybeMainObserver$SwitchMapMaybeObserver;)V
       8: return

  void dispose();
    Code:
       0: aload_0
       1: invokestatic  #8                  // Method io/reactivex/rxjava3/internal/disposables/DisposableHelper.dispose:(Ljava/util/concurrent/atomic/AtomicReference;)Z
       4: pop
       5: return
}
