Compiled from "ObservableConcatMapSingle.java"
public final class io.reactivex.rxjava3.internal.operators.mixed.ObservableConcatMapSingle<T, R> extends io.reactivex.rxjava3.core.Observable<R> {
  final io.reactivex.rxjava3.core.ObservableSource<T> source;

  final io.reactivex.rxjava3.functions.Function<? super T, ? extends io.reactivex.rxjava3.core.SingleSource<? extends R>> mapper;

  final io.reactivex.rxjava3.internal.util.ErrorMode errorMode;

  final int prefetch;

  public io.reactivex.rxjava3.internal.operators.mixed.ObservableConcatMapSingle(io.reactivex.rxjava3.core.ObservableSource<T>, io.reactivex.rxjava3.functions.Function<? super T, ? extends io.reactivex.rxjava3.core.SingleSource<? extends R>>, io.reactivex.rxjava3.internal.util.ErrorMode, int);
    Code:
       0: aload_0
       1: invokespecial #1                  // Method io/reactivex/rxjava3/core/Observable."<init>":()V
       4: aload_0
       5: aload_1
       6: putfield      #2                  // Field source:Lio/reactivex/rxjava3/core/ObservableSource;
       9: aload_0
      10: aload_2
      11: putfield      #3                  // Field mapper:Lio/reactivex/rxjava3/functions/Function;
      14: aload_0
      15: aload_3
      16: putfield      #4                  // Field errorMode:Lio/reactivex/rxjava3/internal/util/ErrorMode;
      19: aload_0
      20: iload         4
      22: putfield      #5                  // Field prefetch:I
      25: return

  protected void subscribeActual(io.reactivex.rxjava3.core.Observer<? super R>);
    Code:
       0: aload_0
       1: getfield      #2                  // Field source:Lio/reactivex/rxjava3/core/ObservableSource;
       4: aload_0
       5: getfield      #3                  // Field mapper:Lio/reactivex/rxjava3/functions/Function;
       8: aload_1
       9: invokestatic  #6                  // Method io/reactivex/rxjava3/internal/operators/mixed/ScalarXMapZHelper.tryAsSingle:(Ljava/lang/Object;Lio/reactivex/rxjava3/functions/Function;Lio/reactivex/rxjava3/core/Observer;)Z
      12: ifne          44
      15: aload_0
      16: getfield      #2                  // Field source:Lio/reactivex/rxjava3/core/ObservableSource;
      19: new           #7                  // class io/reactivex/rxjava3/internal/operators/mixed/ObservableConcatMapSingle$ConcatMapSingleMainObserver
      22: dup
      23: aload_1
      24: aload_0
      25: getfield      #3                  // Field mapper:Lio/reactivex/rxjava3/functions/Function;
      28: aload_0
      29: getfield      #5                  // Field prefetch:I
      32: aload_0
      33: getfield      #4                  // Field errorMode:Lio/reactivex/rxjava3/internal/util/ErrorMode;
      36: invokespecial #8                  // Method io/reactivex/rxjava3/internal/operators/mixed/ObservableConcatMapSingle$ConcatMapSingleMainObserver."<init>":(Lio/reactivex/rxjava3/core/Observer;Lio/reactivex/rxjava3/functions/Function;ILio/reactivex/rxjava3/internal/util/ErrorMode;)V
      39: invokeinterface #9,  2            // InterfaceMethod io/reactivex/rxjava3/core/ObservableSource.subscribe:(Lio/reactivex/rxjava3/core/Observer;)V
      44: return
}
