Compiled from "ObservableConcatMapSingle.java"
final class io.reactivex.rxjava3.internal.operators.mixed.ObservableConcatMapSingle$ConcatMapSingleMainObserver<T, R> extends io.reactivex.rxjava3.internal.operators.mixed.ConcatMapXMainObserver<T> {
  private static final long serialVersionUID;

  final io.reactivex.rxjava3.core.Observer<? super R> downstream;

  final io.reactivex.rxjava3.functions.Function<? super T, ? extends io.reactivex.rxjava3.core.SingleSource<? extends R>> mapper;

  final io.reactivex.rxjava3.internal.operators.mixed.ObservableConcatMapSingle$ConcatMapSingleMainObserver$ConcatMapSingleObserver<R> inner;

  R item;

  volatile int state;

  static final int STATE_INACTIVE;

  static final int STATE_ACTIVE;

  static final int STATE_RESULT_VALUE;

  io.reactivex.rxjava3.internal.operators.mixed.ObservableConcatMapSingle$ConcatMapSingleMainObserver(io.reactivex.rxjava3.core.Observer<? super R>, io.reactivex.rxjava3.functions.Function<? super T, ? extends io.reactivex.rxjava3.core.SingleSource<? extends R>>, int, io.reactivex.rxjava3.internal.util.ErrorMode);
    Code:
       0: aload_0
       1: iload_3
       2: aload         4
       4: invokespecial #1                  // Method io/reactivex/rxjava3/internal/operators/mixed/ConcatMapXMainObserver."<init>":(ILio/reactivex/rxjava3/internal/util/ErrorMode;)V
       7: aload_0
       8: aload_1
       9: putfield      #2                  // Field downstream:Lio/reactivex/rxjava3/core/Observer;
      12: aload_0
      13: aload_2
      14: putfield      #3                  // Field mapper:Lio/reactivex/rxjava3/functions/Function;
      17: aload_0
      18: new           #4                  // class io/reactivex/rxjava3/internal/operators/mixed/ObservableConcatMapSingle$ConcatMapSingleMainObserver$ConcatMapSingleObserver
      21: dup
      22: aload_0
      23: invokespecial #5                  // Method io/reactivex/rxjava3/internal/operators/mixed/ObservableConcatMapSingle$ConcatMapSingleMainObserver$ConcatMapSingleObserver."<init>":(Lio/reactivex/rxjava3/internal/operators/mixed/ObservableConcatMapSingle$ConcatMapSingleMainObserver;)V
      26: putfield      #6                  // Field inner:Lio/reactivex/rxjava3/internal/operators/mixed/ObservableConcatMapSingle$ConcatMapSingleMainObserver$ConcatMapSingleObserver;
      29: return

  void innerSuccess(R);
    Code:
       0: aload_0
       1: aload_1
       2: putfield      #7                  // Field item:Ljava/lang/Object;
       5: aload_0
       6: iconst_2
       7: putfield      #9                  // Field state:I
      10: aload_0
      11: invokevirtual #10                 // Method drain:()V
      14: return

  void innerError(java.lang.Throwable);
    Code:
       0: aload_0
       1: getfield      #11                 // Field errors:Lio/reactivex/rxjava3/internal/util/AtomicThrowable;
       4: aload_1
       5: invokevirtual #12                 // Method io/reactivex/rxjava3/internal/util/AtomicThrowable.tryAddThrowableOrReport:(Ljava/lang/Throwable;)Z
       8: ifeq          39
      11: aload_0
      12: getfield      #13                 // Field errorMode:Lio/reactivex/rxjava3/internal/util/ErrorMode;
      15: getstatic     #14                 // Field io/reactivex/rxjava3/internal/util/ErrorMode.END:Lio/reactivex/rxjava3/internal/util/ErrorMode;
      18: if_acmpeq     30
      21: aload_0
      22: getfield      #15                 // Field upstream:Lio/reactivex/rxjava3/disposables/Disposable;
      25: invokeinterface #16,  1           // InterfaceMethod io/reactivex/rxjava3/disposables/Disposable.dispose:()V
      30: aload_0
      31: iconst_0
      32: putfield      #9                  // Field state:I
      35: aload_0
      36: invokevirtual #10                 // Method drain:()V
      39: return

  void disposeInner();
    Code:
       0: aload_0
       1: getfield      #6                  // Field inner:Lio/reactivex/rxjava3/internal/operators/mixed/ObservableConcatMapSingle$ConcatMapSingleMainObserver$ConcatMapSingleObserver;
       4: invokevirtual #17                 // Method io/reactivex/rxjava3/internal/operators/mixed/ObservableConcatMapSingle$ConcatMapSingleMainObserver$ConcatMapSingleObserver.dispose:()V
       7: return

  void onSubscribeDownstream();
    Code:
       0: aload_0
       1: getfield      #2                  // Field downstream:Lio/reactivex/rxjava3/core/Observer;
       4: aload_0
       5: invokeinterface #18,  2           // InterfaceMethod io/reactivex/rxjava3/core/Observer.onSubscribe:(Lio/reactivex/rxjava3/disposables/Disposable;)V
      10: return

  void clearValue();
    Code:
       0: aload_0
       1: aconst_null
       2: putfield      #7                  // Field item:Ljava/lang/Object;
       5: return

  void drain();
    Code:
       0: aload_0
       1: invokevirtual #19                 // Method getAndIncrement:()I
       4: ifeq          8
       7: return
       8: iconst_1
       9: istore_1
      10: aload_0
      11: getfield      #2                  // Field downstream:Lio/reactivex/rxjava3/core/Observer;
      14: astore_2
      15: aload_0
      16: getfield      #13                 // Field errorMode:Lio/reactivex/rxjava3/internal/util/ErrorMode;
      19: astore_3
      20: aload_0
      21: getfield      #20                 // Field queue:Lio/reactivex/rxjava3/operators/SimpleQueue;
      24: astore        4
      26: aload_0
      27: getfield      #11                 // Field errors:Lio/reactivex/rxjava3/internal/util/AtomicThrowable;
      30: astore        5
      32: aload_0
      33: getfield      #21                 // Field disposed:Z
      36: ifeq          54
      39: aload         4
      41: invokeinterface #22,  1           // InterfaceMethod io/reactivex/rxjava3/operators/SimpleQueue.clear:()V
      46: aload_0
      47: aconst_null
      48: putfield      #7                  // Field item:Ljava/lang/Object;
      51: goto          316
      54: aload_0
      55: getfield      #9                  // Field state:I
      58: istore        6
      60: aload         5
      62: invokevirtual #23                 // Method io/reactivex/rxjava3/internal/util/AtomicThrowable.get:()Ljava/lang/Object;
      65: ifnull        106
      68: aload_3
      69: getstatic     #24                 // Field io/reactivex/rxjava3/internal/util/ErrorMode.IMMEDIATE:Lio/reactivex/rxjava3/internal/util/ErrorMode;
      72: if_acmpeq     87
      75: aload_3
      76: getstatic     #25                 // Field io/reactivex/rxjava3/internal/util/ErrorMode.BOUNDARY:Lio/reactivex/rxjava3/internal/util/ErrorMode;
      79: if_acmpne     106
      82: iload         6
      84: ifne          106
      87: aload         4
      89: invokeinterface #22,  1           // InterfaceMethod io/reactivex/rxjava3/operators/SimpleQueue.clear:()V
      94: aload_0
      95: aconst_null
      96: putfield      #7                  // Field item:Ljava/lang/Object;
      99: aload         5
     101: aload_2
     102: invokevirtual #26                 // Method io/reactivex/rxjava3/internal/util/AtomicThrowable.tryTerminateConsumer:(Lio/reactivex/rxjava3/core/Observer;)V
     105: return
     106: iload         6
     108: ifne          283
     111: aload_0
     112: getfield      #27                 // Field done:Z
     115: istore        7
     117: aload         4
     119: invokeinterface #28,  1           // InterfaceMethod io/reactivex/rxjava3/operators/SimpleQueue.poll:()Ljava/lang/Object;
     124: astore        8
     126: goto          165
     129: astore        9
     131: aload         9
     133: invokestatic  #30                 // Method io/reactivex/rxjava3/exceptions/Exceptions.throwIfFatal:(Ljava/lang/Throwable;)V
     136: aload_0
     137: iconst_1
     138: putfield      #21                 // Field disposed:Z
     141: aload_0
     142: getfield      #15                 // Field upstream:Lio/reactivex/rxjava3/disposables/Disposable;
     145: invokeinterface #16,  1           // InterfaceMethod io/reactivex/rxjava3/disposables/Disposable.dispose:()V
     150: aload         5
     152: aload         9
     154: invokevirtual #12                 // Method io/reactivex/rxjava3/internal/util/AtomicThrowable.tryAddThrowableOrReport:(Ljava/lang/Throwable;)Z
     157: pop
     158: aload         5
     160: aload_2
     161: invokevirtual #26                 // Method io/reactivex/rxjava3/internal/util/AtomicThrowable.tryTerminateConsumer:(Lio/reactivex/rxjava3/core/Observer;)V
     164: return
     165: aload         8
     167: ifnonnull     174
     170: iconst_1
     171: goto          175
     174: iconst_0
     175: istore        9
     177: iload         7
     179: ifeq          194
     182: iload         9
     184: ifeq          194
     187: aload         5
     189: aload_2
     190: invokevirtual #26                 // Method io/reactivex/rxjava3/internal/util/AtomicThrowable.tryTerminateConsumer:(Lio/reactivex/rxjava3/core/Observer;)V
     193: return
     194: iload         9
     196: ifeq          202
     199: goto          316
     202: aload_0
     203: getfield      #3                  // Field mapper:Lio/reactivex/rxjava3/functions/Function;
     206: aload         8
     208: invokeinterface #31,  2           // InterfaceMethod io/reactivex/rxjava3/functions/Function.apply:(Ljava/lang/Object;)Ljava/lang/Object;
     213: ldc           #32                 // String The mapper returned a null SingleSource
     215: invokestatic  #33                 // Method java/util/Objects.requireNonNull:(Ljava/lang/Object;Ljava/lang/String;)Ljava/lang/Object;
     218: checkcast     #34                 // class io/reactivex/rxjava3/core/SingleSource
     221: astore        10
     223: goto          264
     226: astore        11
     228: aload         11
     230: invokestatic  #30                 // Method io/reactivex/rxjava3/exceptions/Exceptions.throwIfFatal:(Ljava/lang/Throwable;)V
     233: aload_0
     234: getfield      #15                 // Field upstream:Lio/reactivex/rxjava3/disposables/Disposable;
     237: invokeinterface #16,  1           // InterfaceMethod io/reactivex/rxjava3/disposables/Disposable.dispose:()V
     242: aload         4
     244: invokeinterface #22,  1           // InterfaceMethod io/reactivex/rxjava3/operators/SimpleQueue.clear:()V
     249: aload         5
     251: aload         11
     253: invokevirtual #12                 // Method io/reactivex/rxjava3/internal/util/AtomicThrowable.tryAddThrowableOrReport:(Ljava/lang/Throwable;)Z
     256: pop
     257: aload         5
     259: aload_2
     260: invokevirtual #26                 // Method io/reactivex/rxjava3/internal/util/AtomicThrowable.tryTerminateConsumer:(Lio/reactivex/rxjava3/core/Observer;)V
     263: return
     264: aload_0
     265: iconst_1
     266: putfield      #9                  // Field state:I
     269: aload         10
     271: aload_0
     272: getfield      #6                  // Field inner:Lio/reactivex/rxjava3/internal/operators/mixed/ObservableConcatMapSingle$ConcatMapSingleMainObserver$ConcatMapSingleObserver;
     275: invokeinterface #35,  2           // InterfaceMethod io/reactivex/rxjava3/core/SingleSource.subscribe:(Lio/reactivex/rxjava3/core/SingleObserver;)V
     280: goto          316
     283: iload         6
     285: iconst_2
     286: if_icmpne     316
     289: aload_0
     290: getfield      #7                  // Field item:Ljava/lang/Object;
     293: astore        7
     295: aload_0
     296: aconst_null
     297: putfield      #7                  // Field item:Ljava/lang/Object;
     300: aload_2
     301: aload         7
     303: invokeinterface #36,  2           // InterfaceMethod io/reactivex/rxjava3/core/Observer.onNext:(Ljava/lang/Object;)V
     308: aload_0
     309: iconst_0
     310: putfield      #9                  // Field state:I
     313: goto          32
     316: aload_0
     317: iload_1
     318: ineg
     319: invokevirtual #37                 // Method addAndGet:(I)I
     322: istore_1
     323: iload_1
     324: ifne          32
     327: goto          330
     330: return
    Exception table:
       from    to  target type
         117   126   129   Class java/lang/Throwable
         202   223   226   Class java/lang/Throwable
}
