Compiled from "ScalarXMapZHelper.java"
final class io.reactivex.rxjava3.internal.operators.mixed.ScalarXMapZHelper {
  private io.reactivex.rxjava3.internal.operators.mixed.ScalarXMapZHelper();
    Code:
       0: aload_0
       1: invokespecial #1                  // Method java/lang/Object."<init>":()V
       4: new           #2                  // class java/lang/IllegalStateException
       7: dup
       8: ldc           #3                  // String No instances!
      10: invokespecial #4                  // Method java/lang/IllegalStateException."<init>":(Ljava/lang/String;)V
      13: athrow

  static <T> boolean tryAsCompletable(java.lang.Object, io.reactivex.rxjava3.functions.Function<? super T, ? extends io.reactivex.rxjava3.core.CompletableSource>, io.reactivex.rxjava3.core.CompletableObserver);
    Code:
       0: aload_0
       1: instanceof    #5                  // class io/reactivex/rxjava3/functions/Supplier
       4: ifeq          86
       7: aload_0
       8: checkcast     #5                  // class io/reactivex/rxjava3/functions/Supplier
      11: astore_3
      12: aconst_null
      13: astore        4
      15: aload_3
      16: invokeinterface #6,  1            // InterfaceMethod io/reactivex/rxjava3/functions/Supplier.get:()Ljava/lang/Object;
      21: astore        5
      23: aload         5
      25: ifnull        46
      28: aload_1
      29: aload         5
      31: invokeinterface #7,  2            // InterfaceMethod io/reactivex/rxjava3/functions/Function.apply:(Ljava/lang/Object;)Ljava/lang/Object;
      36: ldc           #8                  // String The mapper returned a null CompletableSource
      38: invokestatic  #9                  // Method java/util/Objects.requireNonNull:(Ljava/lang/Object;Ljava/lang/String;)Ljava/lang/Object;
      41: checkcast     #10                 // class io/reactivex/rxjava3/core/CompletableSource
      44: astore        4
      46: goto          64
      49: astore        5
      51: aload         5
      53: invokestatic  #12                 // Method io/reactivex/rxjava3/exceptions/Exceptions.throwIfFatal:(Ljava/lang/Throwable;)V
      56: aload         5
      58: aload_2
      59: invokestatic  #13                 // Method io/reactivex/rxjava3/internal/disposables/EmptyDisposable.error:(Ljava/lang/Throwable;Lio/reactivex/rxjava3/core/CompletableObserver;)V
      62: iconst_1
      63: ireturn
      64: aload         4
      66: ifnonnull     76
      69: aload_2
      70: invokestatic  #14                 // Method io/reactivex/rxjava3/internal/disposables/EmptyDisposable.complete:(Lio/reactivex/rxjava3/core/CompletableObserver;)V
      73: goto          84
      76: aload         4
      78: aload_2
      79: invokeinterface #15,  2           // InterfaceMethod io/reactivex/rxjava3/core/CompletableSource.subscribe:(Lio/reactivex/rxjava3/core/CompletableObserver;)V
      84: iconst_1
      85: ireturn
      86: iconst_0
      87: ireturn
    Exception table:
       from    to  target type
          15    46    49   Class java/lang/Throwable

  static <T, R> boolean tryAsMaybe(java.lang.Object, io.reactivex.rxjava3.functions.Function<? super T, ? extends io.reactivex.rxjava3.core.MaybeSource<? extends R>>, io.reactivex.rxjava3.core.Observer<? super R>);
    Code:
       0: aload_0
       1: instanceof    #5                  // class io/reactivex/rxjava3/functions/Supplier
       4: ifeq          89
       7: aload_0
       8: checkcast     #5                  // class io/reactivex/rxjava3/functions/Supplier
      11: astore_3
      12: aconst_null
      13: astore        4
      15: aload_3
      16: invokeinterface #6,  1            // InterfaceMethod io/reactivex/rxjava3/functions/Supplier.get:()Ljava/lang/Object;
      21: astore        5
      23: aload         5
      25: ifnull        46
      28: aload_1
      29: aload         5
      31: invokeinterface #7,  2            // InterfaceMethod io/reactivex/rxjava3/functions/Function.apply:(Ljava/lang/Object;)Ljava/lang/Object;
      36: ldc           #16                 // String The mapper returned a null MaybeSource
      38: invokestatic  #9                  // Method java/util/Objects.requireNonNull:(Ljava/lang/Object;Ljava/lang/String;)Ljava/lang/Object;
      41: checkcast     #17                 // class io/reactivex/rxjava3/core/MaybeSource
      44: astore        4
      46: goto          64
      49: astore        5
      51: aload         5
      53: invokestatic  #12                 // Method io/reactivex/rxjava3/exceptions/Exceptions.throwIfFatal:(Ljava/lang/Throwable;)V
      56: aload         5
      58: aload_2
      59: invokestatic  #18                 // Method io/reactivex/rxjava3/internal/disposables/EmptyDisposable.error:(Ljava/lang/Throwable;Lio/reactivex/rxjava3/core/Observer;)V
      62: iconst_1
      63: ireturn
      64: aload         4
      66: ifnonnull     76
      69: aload_2
      70: invokestatic  #19                 // Method io/reactivex/rxjava3/internal/disposables/EmptyDisposable.complete:(Lio/reactivex/rxjava3/core/Observer;)V
      73: goto          87
      76: aload         4
      78: aload_2
      79: invokestatic  #20                 // Method io/reactivex/rxjava3/internal/operators/maybe/MaybeToObservable.create:(Lio/reactivex/rxjava3/core/Observer;)Lio/reactivex/rxjava3/core/MaybeObserver;
      82: invokeinterface #21,  2           // InterfaceMethod io/reactivex/rxjava3/core/MaybeSource.subscribe:(Lio/reactivex/rxjava3/core/MaybeObserver;)V
      87: iconst_1
      88: ireturn
      89: iconst_0
      90: ireturn
    Exception table:
       from    to  target type
          15    46    49   Class java/lang/Throwable

  static <T, R> boolean tryAsSingle(java.lang.Object, io.reactivex.rxjava3.functions.Function<? super T, ? extends io.reactivex.rxjava3.core.SingleSource<? extends R>>, io.reactivex.rxjava3.core.Observer<? super R>);
    Code:
       0: aload_0
       1: instanceof    #5                  // class io/reactivex/rxjava3/functions/Supplier
       4: ifeq          89
       7: aload_0
       8: checkcast     #5                  // class io/reactivex/rxjava3/functions/Supplier
      11: astore_3
      12: aconst_null
      13: astore        4
      15: aload_3
      16: invokeinterface #6,  1            // InterfaceMethod io/reactivex/rxjava3/functions/Supplier.get:()Ljava/lang/Object;
      21: astore        5
      23: aload         5
      25: ifnull        46
      28: aload_1
      29: aload         5
      31: invokeinterface #7,  2            // InterfaceMethod io/reactivex/rxjava3/functions/Function.apply:(Ljava/lang/Object;)Ljava/lang/Object;
      36: ldc           #22                 // String The mapper returned a null SingleSource
      38: invokestatic  #9                  // Method java/util/Objects.requireNonNull:(Ljava/lang/Object;Ljava/lang/String;)Ljava/lang/Object;
      41: checkcast     #23                 // class io/reactivex/rxjava3/core/SingleSource
      44: astore        4
      46: goto          64
      49: astore        5
      51: aload         5
      53: invokestatic  #12                 // Method io/reactivex/rxjava3/exceptions/Exceptions.throwIfFatal:(Ljava/lang/Throwable;)V
      56: aload         5
      58: aload_2
      59: invokestatic  #18                 // Method io/reactivex/rxjava3/internal/disposables/EmptyDisposable.error:(Ljava/lang/Throwable;Lio/reactivex/rxjava3/core/Observer;)V
      62: iconst_1
      63: ireturn
      64: aload         4
      66: ifnonnull     76
      69: aload_2
      70: invokestatic  #19                 // Method io/reactivex/rxjava3/internal/disposables/EmptyDisposable.complete:(Lio/reactivex/rxjava3/core/Observer;)V
      73: goto          87
      76: aload         4
      78: aload_2
      79: invokestatic  #24                 // Method io/reactivex/rxjava3/internal/operators/single/SingleToObservable.create:(Lio/reactivex/rxjava3/core/Observer;)Lio/reactivex/rxjava3/core/SingleObserver;
      82: invokeinterface #25,  2           // InterfaceMethod io/reactivex/rxjava3/core/SingleSource.subscribe:(Lio/reactivex/rxjava3/core/SingleObserver;)V
      87: iconst_1
      88: ireturn
      89: iconst_0
      90: ireturn
    Exception table:
       from    to  target type
          15    46    49   Class java/lang/Throwable
}
