Compiled from "BaseRule.java"
public class org.apache.dubbo.rpc.cluster.router.mesh.rule.BaseRule {
  private java.lang.String apiVersion;

  private java.lang.String kind;

  private java.util.Map<java.lang.String, java.lang.String> metadata;

  public org.apache.dubbo.rpc.cluster.router.mesh.rule.BaseRule();
    Code:
       0: aload_0
       1: invokespecial #1                  // Method java/lang/Object."<init>":()V
       4: return

  public java.lang.String getApiVersion();
    Code:
       0: aload_0
       1: getfield      #2                  // Field apiVersion:Ljava/lang/String;
       4: areturn

  public void setApiVersion(java.lang.String);
    Code:
       0: aload_0
       1: aload_1
       2: putfield      #2                  // Field apiVersion:Ljava/lang/String;
       5: return

  public java.lang.String getKind();
    Code:
       0: aload_0
       1: getfield      #3                  // Field kind:Ljava/lang/String;
       4: areturn

  public void setKind(java.lang.String);
    Code:
       0: aload_0
       1: aload_1
       2: putfield      #3                  // Field kind:Ljava/lang/String;
       5: return

  public java.util.Map<java.lang.String, java.lang.String> getMetadata();
    Code:
       0: aload_0
       1: getfield      #4                  // Field metadata:Ljava/util/Map;
       4: areturn

  public void setMetadata(java.util.Map<java.lang.String, java.lang.String>);
    Code:
       0: aload_0
       1: aload_1
       2: putfield      #4                  // Field metadata:Ljava/util/Map;
       5: return

  public java.lang.String toString();
    Code:
       0: new           #5                  // class java/lang/StringBuilder
       3: dup
       4: invokespecial #6                  // Method java/lang/StringBuilder."<init>":()V
       7: ldc           #7                  // String BaseRule{apiVersion=\'
       9: invokevirtual #8                  // Method java/lang/StringBuilder.append:(Ljava/lang/String;)Ljava/lang/StringBuilder;
      12: aload_0
      13: getfield      #2                  // Field apiVersion:Ljava/lang/String;
      16: invokevirtual #8                  // Method java/lang/StringBuilder.append:(Ljava/lang/String;)Ljava/lang/StringBuilder;
      19: bipush        39
      21: invokevirtual #9                  // Method java/lang/StringBuilder.append:(C)Ljava/lang/StringBuilder;
      24: ldc           #10                 // String , kind=\'
      26: invokevirtual #8                  // Method java/lang/StringBuilder.append:(Ljava/lang/String;)Ljava/lang/StringBuilder;
      29: aload_0
      30: getfield      #3                  // Field kind:Ljava/lang/String;
      33: invokevirtual #8                  // Method java/lang/StringBuilder.append:(Ljava/lang/String;)Ljava/lang/StringBuilder;
      36: bipush        39
      38: invokevirtual #9                  // Method java/lang/StringBuilder.append:(C)Ljava/lang/StringBuilder;
      41: ldc           #11                 // String , metadata=
      43: invokevirtual #8                  // Method java/lang/StringBuilder.append:(Ljava/lang/String;)Ljava/lang/StringBuilder;
      46: aload_0
      47: getfield      #4                  // Field metadata:Ljava/util/Map;
      50: invokevirtual #12                 // Method java/lang/StringBuilder.append:(Ljava/lang/Object;)Ljava/lang/StringBuilder;
      53: bipush        125
      55: invokevirtual #9                  // Method java/lang/StringBuilder.append:(C)Ljava/lang/StringBuilder;
      58: invokevirtual #13                 // Method java/lang/StringBuilder.toString:()Ljava/lang/String;
      61: areturn
}
