Compiled from "VsDestinationGroup.java"
public class org.apache.dubbo.rpc.cluster.router.mesh.rule.VsDestinationGroup {
  private java.lang.String appName;

  private java.util.List<org.apache.dubbo.rpc.cluster.router.mesh.rule.virtualservice.VirtualServiceRule> virtualServiceRuleList;

  private java.util.List<org.apache.dubbo.rpc.cluster.router.mesh.rule.destination.DestinationRule> destinationRuleList;

  public org.apache.dubbo.rpc.cluster.router.mesh.rule.VsDestinationGroup();
    Code:
       0: aload_0
       1: invokespecial #1                  // Method java/lang/Object."<init>":()V
       4: aload_0
       5: new           #2                  // class java/util/LinkedList
       8: dup
       9: invokespecial #3                  // Method java/util/LinkedList."<init>":()V
      12: putfield      #4                  // Field virtualServiceRuleList:Ljava/util/List;
      15: aload_0
      16: new           #2                  // class java/util/LinkedList
      19: dup
      20: invokespecial #3                  // Method java/util/LinkedList."<init>":()V
      23: putfield      #5                  // Field destinationRuleList:Ljava/util/List;
      26: return

  public java.lang.String getAppName();
    Code:
       0: aload_0
       1: getfield      #6                  // Field appName:Ljava/lang/String;
       4: areturn

  public void setAppName(java.lang.String);
    Code:
       0: aload_0
       1: aload_1
       2: putfield      #6                  // Field appName:Ljava/lang/String;
       5: return

  public java.util.List<org.apache.dubbo.rpc.cluster.router.mesh.rule.virtualservice.VirtualServiceRule> getVirtualServiceRuleList();
    Code:
       0: aload_0
       1: getfield      #4                  // Field virtualServiceRuleList:Ljava/util/List;
       4: areturn

  public void setVirtualServiceRuleList(java.util.List<org.apache.dubbo.rpc.cluster.router.mesh.rule.virtualservice.VirtualServiceRule>);
    Code:
       0: aload_0
       1: aload_1
       2: putfield      #4                  // Field virtualServiceRuleList:Ljava/util/List;
       5: return

  public java.util.List<org.apache.dubbo.rpc.cluster.router.mesh.rule.destination.DestinationRule> getDestinationRuleList();
    Code:
       0: aload_0
       1: getfield      #5                  // Field destinationRuleList:Ljava/util/List;
       4: areturn

  public void setDestinationRuleList(java.util.List<org.apache.dubbo.rpc.cluster.router.mesh.rule.destination.DestinationRule>);
    Code:
       0: aload_0
       1: aload_1
       2: putfield      #5                  // Field destinationRuleList:Ljava/util/List;
       5: return

  public boolean isValid();
    Code:
       0: aload_0
       1: getfield      #4                  // Field virtualServiceRuleList:Ljava/util/List;
       4: invokeinterface #7,  1            // InterfaceMethod java/util/List.size:()I
       9: ifle          28
      12: aload_0
      13: getfield      #5                  // Field destinationRuleList:Ljava/util/List;
      16: invokeinterface #7,  1            // InterfaceMethod java/util/List.size:()I
      21: ifle          28
      24: iconst_1
      25: goto          29
      28: iconst_0
      29: ireturn
}
