Compiled from "JsonCodec.java"
public class org.apache.dubbo.rpc.protocol.rest.message.codec.JsonCodec implements org.apache.dubbo.rpc.protocol.rest.message.HttpMessageCodec<byte[], java.io.OutputStream> {
  private static final java.util.Set<java.lang.Class> unSupportClasses;

  public org.apache.dubbo.rpc.protocol.rest.message.codec.JsonCodec();
    Code:
       0: aload_0
       1: invokespecial #1                  // Method java/lang/Object."<init>":()V
       4: return

  public java.lang.Object decode(byte[], java.lang.Class<?>) throws java.lang.Exception;
    Code:
       0: aload_2
       1: aload_1
       2: invokestatic  #2                  // Method org/apache/dubbo/rpc/protocol/rest/util/DataParseUtils.jsonConvert:(Ljava/lang/Class;[B)Ljava/lang/Object;
       5: areturn

  public boolean contentTypeSupport(org.apache.dubbo.metadata.rest.media.MediaType, java.lang.Class<?>);
    Code:
       0: getstatic     #3                  // Field org/apache/dubbo/rpc/protocol/rest/message/MediaTypeMatcher.APPLICATION_JSON:Lorg/apache/dubbo/rpc/protocol/rest/message/MediaTypeMatcher;
       3: aload_1
       4: invokevirtual #4                  // Method org/apache/dubbo/rpc/protocol/rest/message/MediaTypeMatcher.mediaSupport:(Lorg/apache/dubbo/metadata/rest/media/MediaType;)Z
       7: ifeq          26
      10: getstatic     #5                  // Field unSupportClasses:Ljava/util/Set;
      13: aload_2
      14: invokeinterface #6,  2            // InterfaceMethod java/util/Set.contains:(Ljava/lang/Object;)Z
      19: ifne          26
      22: iconst_1
      23: goto          27
      26: iconst_0
      27: ireturn

  public boolean typeSupport(java.lang.Class<?>);
    Code:
       0: getstatic     #5                  // Field unSupportClasses:Ljava/util/Set;
       3: aload_1
       4: invokeinterface #6,  2            // InterfaceMethod java/util/Set.contains:(Ljava/lang/Object;)Z
       9: ifne          23
      12: aload_1
      13: invokestatic  #7                  // Method org/apache/dubbo/rpc/protocol/rest/util/DataParseUtils.isTextType:(Ljava/lang/Class;)Z
      16: ifne          23
      19: iconst_1
      20: goto          24
      23: iconst_0
      24: ireturn

  public org.apache.dubbo.metadata.rest.media.MediaType contentType();
    Code:
       0: getstatic     #8                  // Field org/apache/dubbo/metadata/rest/media/MediaType.APPLICATION_JSON_VALUE:Lorg/apache/dubbo/metadata/rest/media/MediaType;
       3: areturn

  public void encode(java.io.OutputStream, java.lang.Object, org.apache.dubbo.common.URL) throws java.lang.Exception;
    Code:
       0: aload_1
       1: aload_2
       2: invokestatic  #9                  // Method org/apache/dubbo/common/utils/JsonUtils.toJson:(Ljava/lang/Object;)Ljava/lang/String;
       5: getstatic     #10                 // Field java/nio/charset/StandardCharsets.UTF_8:Ljava/nio/charset/Charset;
       8: invokevirtual #11                 // Method java/lang/String.getBytes:(Ljava/nio/charset/Charset;)[B
      11: invokevirtual #12                 // Method java/io/OutputStream.write:([B)V
      14: return

  public java.lang.Object decode(java.lang.Object, java.lang.Class) throws java.lang.Exception;
    Code:
       0: aload_0
       1: aload_1
       2: checkcast     #13                 // class "[B"
       5: aload_2
       6: invokevirtual #14                 // Method decode:([BLjava/lang/Class;)Ljava/lang/Object;
       9: areturn

  public void encode(java.lang.Object, java.lang.Object, org.apache.dubbo.common.URL) throws java.lang.Exception;
    Code:
       0: aload_0
       1: aload_1
       2: checkcast     #15                 // class java/io/OutputStream
       5: aload_2
       6: aload_3
       7: invokevirtual #16                 // Method encode:(Ljava/io/OutputStream;Ljava/lang/Object;Lorg/apache/dubbo/common/URL;)V
      10: return

  static {};
    Code:
       0: new           #17                 // class java/util/HashSet
       3: dup
       4: invokespecial #18                 // Method java/util/HashSet."<init>":()V
       7: putstatic     #5                  // Field unSupportClasses:Ljava/util/Set;
      10: getstatic     #5                  // Field unSupportClasses:Ljava/util/Set;
      13: ldc           #13                 // class "[B"
      15: invokeinterface #19,  2           // InterfaceMethod java/util/Set.add:(Ljava/lang/Object;)Z
      20: pop
      21: getstatic     #5                  // Field unSupportClasses:Ljava/util/Set;
      24: ldc           #20                 // class java/lang/String
      26: invokeinterface #19,  2           // InterfaceMethod java/util/Set.add:(Ljava/lang/Object;)Z
      31: pop
      32: getstatic     #5                  // Field unSupportClasses:Ljava/util/Set;
      35: ldc           #21                 // class javax/ws/rs/core/Response
      37: invokeinterface #19,  2           // InterfaceMethod java/util/Set.add:(Ljava/lang/Object;)Z
      42: pop
      43: return
}
