Compiled from "MultiValueCodec.java"
public class org.apache.dubbo.rpc.protocol.rest.message.codec.MultiValueCodec implements org.apache.dubbo.rpc.protocol.rest.message.HttpMessageCodec<byte[], java.io.OutputStream> {
  public org.apache.dubbo.rpc.protocol.rest.message.codec.MultiValueCodec();
    Code:
       0: aload_0
       1: invokespecial #1                  // Method java/lang/Object."<init>":()V
       4: return

  public java.lang.Object decode(byte[], java.lang.Class<?>) throws java.lang.Exception;
    Code:
       0: aload_1
       1: aload_2
       2: invokestatic  #2                  // Method org/apache/dubbo/rpc/protocol/rest/util/DataParseUtils.multipartFormConvert:([BLjava/lang/Class;)Ljava/lang/Object;
       5: astore_3
       6: aload_3
       7: checkcast     #3                  // class java/util/Map
      10: astore        4
      12: ldc           #3                  // class java/util/Map
      14: aload_2
      15: invokevirtual #4                  // Method java/lang/Class.isAssignableFrom:(Ljava/lang/Class;)Z
      18: ifeq          23
      21: aload_3
      22: areturn
      23: aload_2
      24: invokestatic  #5                  // Method org/apache/dubbo/rpc/protocol/rest/util/DataParseUtils.isTextType:(Ljava/lang/Class;)Z
      27: ifeq          95
      30: aload         4
      32: invokeinterface #6,  1            // InterfaceMethod java/util/Map.keySet:()Ljava/util/Set;
      37: astore        5
      39: new           #7                  // class java/util/ArrayList
      42: dup
      43: aload         5
      45: invokespecial #8                  // Method java/util/ArrayList."<init>":(Ljava/util/Collection;)V
      48: astore        6
      50: aload         6
      52: iconst_0
      53: invokevirtual #9                  // Method java/util/ArrayList.get:(I)Ljava/lang/Object;
      56: astore        7
      58: aload         4
      60: aload         7
      62: invokeinterface #10,  2           // InterfaceMethod java/util/Map.get:(Ljava/lang/Object;)Ljava/lang/Object;
      67: astore        8
      69: aload         8
      71: ifnonnull     76
      74: aconst_null
      75: areturn
      76: aload_2
      77: aload         8
      79: checkcast     #11                 // class java/util/List
      82: iconst_0
      83: invokeinterface #12,  2           // InterfaceMethod java/util/List.get:(I)Ljava/lang/Object;
      88: invokestatic  #13                 // Method java/lang/String.valueOf:(Ljava/lang/Object;)Ljava/lang/String;
      91: invokestatic  #14                 // Method org/apache/dubbo/rpc/protocol/rest/util/DataParseUtils.stringTypeConvert:(Ljava/lang/Class;Ljava/lang/String;)Ljava/lang/Object;
      94: areturn
      95: aload_2
      96: invokestatic  #15                 // Method org/apache/dubbo/common/utils/ReflectUtils.getBeanPropertyFields:(Ljava/lang/Class;)Ljava/util/Map;
      99: astore        5
     101: aload_2
     102: invokestatic  #16                 // Method org/apache/dubbo/common/utils/ReflectUtils.getEmptyObject:(Ljava/lang/Class;)Ljava/lang/Object;
     105: astore        6
     107: aload         5
     109: invokeinterface #17,  1           // InterfaceMethod java/util/Map.entrySet:()Ljava/util/Set;
     114: invokeinterface #18,  1           // InterfaceMethod java/util/Set.stream:()Ljava/util/stream/Stream;
     119: aload         4
     121: aload         6
     123: invokedynamic #19,  0             // InvokeDynamic #0:accept:(Ljava/util/Map;Ljava/lang/Object;)Ljava/util/function/Consumer;
     128: invokeinterface #20,  2           // InterfaceMethod java/util/stream/Stream.forEach:(Ljava/util/function/Consumer;)V
     133: aload         6
     135: areturn

  public boolean contentTypeSupport(org.apache.dubbo.metadata.rest.media.MediaType, java.lang.Class<?>);
    Code:
       0: getstatic     #21                 // Field org/apache/dubbo/rpc/protocol/rest/message/MediaTypeMatcher.MULTI_VALUE:Lorg/apache/dubbo/rpc/protocol/rest/message/MediaTypeMatcher;
       3: aload_1
       4: invokevirtual #22                 // Method org/apache/dubbo/rpc/protocol/rest/message/MediaTypeMatcher.mediaSupport:(Lorg/apache/dubbo/metadata/rest/media/MediaType;)Z
       7: ireturn

  public boolean typeSupport(java.lang.Class<?>);
    Code:
       0: iconst_0
       1: ireturn

  public org.apache.dubbo.metadata.rest.media.MediaType contentType();
    Code:
       0: getstatic     #23                 // Field org/apache/dubbo/metadata/rest/media/MediaType.APPLICATION_FORM_URLENCODED_VALUE:Lorg/apache/dubbo/metadata/rest/media/MediaType;
       3: areturn

  public void encode(java.io.OutputStream, java.lang.Object, org.apache.dubbo.common.URL) throws java.lang.Exception;
    Code:
       0: aload_2
       1: checkcast     #3                  // class java/util/Map
       4: aload_1
       5: invokestatic  #24                 // Method org/apache/dubbo/rpc/protocol/rest/util/DataParseUtils.writeFormContent:(Ljava/util/Map;Ljava/io/OutputStream;)V
       8: return

  public java.lang.Object decode(java.lang.Object, java.lang.Class) throws java.lang.Exception;
    Code:
       0: aload_0
       1: aload_1
       2: checkcast     #25                 // class "[B"
       5: aload_2
       6: invokevirtual #26                 // Method decode:([BLjava/lang/Class;)Ljava/lang/Object;
       9: areturn

  public void encode(java.lang.Object, java.lang.Object, org.apache.dubbo.common.URL) throws java.lang.Exception;
    Code:
       0: aload_0
       1: aload_1
       2: checkcast     #27                 // class java/io/OutputStream
       5: aload_2
       6: aload_3
       7: invokevirtual #28                 // Method encode:(Ljava/io/OutputStream;Ljava/lang/Object;Lorg/apache/dubbo/common/URL;)V
      10: return

  private static void lambda$decode$0(java.util.Map, java.lang.Object, java.util.Map$Entry);
    Code:
       0: aload_0
       1: aload_2
       2: invokeinterface #29,  1           // InterfaceMethod java/util/Map$Entry.getKey:()Ljava/lang/Object;
       7: invokeinterface #10,  2           // InterfaceMethod java/util/Map.get:(Ljava/lang/Object;)Ljava/lang/Object;
      12: checkcast     #11                 // class java/util/List
      15: astore_3
      16: aload_3
      17: ifnonnull     24
      20: aconst_null
      21: goto          34
      24: aload_3
      25: iconst_0
      26: invokeinterface #12,  2           // InterfaceMethod java/util/List.get:(I)Ljava/lang/Object;
      31: invokestatic  #13                 // Method java/lang/String.valueOf:(Ljava/lang/Object;)Ljava/lang/String;
      34: astore        4
      36: aload_2
      37: invokeinterface #30,  1           // InterfaceMethod java/util/Map$Entry.getValue:()Ljava/lang/Object;
      42: checkcast     #31                 // class java/lang/reflect/Field
      45: aload_1
      46: aload_2
      47: invokeinterface #30,  1           // InterfaceMethod java/util/Map$Entry.getValue:()Ljava/lang/Object;
      52: checkcast     #31                 // class java/lang/reflect/Field
      55: invokevirtual #32                 // Method java/lang/reflect/Field.getType:()Ljava/lang/Class;
      58: aload         4
      60: invokestatic  #14                 // Method org/apache/dubbo/rpc/protocol/rest/util/DataParseUtils.stringTypeConvert:(Ljava/lang/Class;Ljava/lang/String;)Ljava/lang/Object;
      63: invokevirtual #33                 // Method java/lang/reflect/Field.set:(Ljava/lang/Object;Ljava/lang/Object;)V
      66: goto          70
      69: astore_3
      70: return
    Exception table:
       from    to  target type
           0    66    69   Class java/lang/IllegalAccessException
}
