Compiled from "ResteasyResponseCodec.java"
public class org.apache.dubbo.rpc.protocol.rest.message.codec.ResteasyResponseCodec implements org.apache.dubbo.rpc.protocol.rest.message.HttpMessageCodec<byte[], java.io.OutputStream> {
  private java.lang.Class<?> responseClass;

  public org.apache.dubbo.rpc.protocol.rest.message.codec.ResteasyResponseCodec();
    Code:
       0: aload_0
       1: invokespecial #1                  // Method java/lang/Object."<init>":()V
       4: aload_0
       5: ldc           #2                  // String javax.ws.rs.core.Response
       7: invokestatic  #3                  // Method org/apache/dubbo/common/utils/ClassUtils.forName:(Ljava/lang/String;)Ljava/lang/Class;
      10: putfield      #4                  // Field responseClass:Ljava/lang/Class;
      13: goto          22
      16: astore_1
      17: aload_0
      18: aconst_null
      19: putfield      #4                  // Field responseClass:Ljava/lang/Class;
      22: return
    Exception table:
       from    to  target type
           4    13    16   Class java/lang/Exception

  public boolean contentTypeSupport(org.apache.dubbo.metadata.rest.media.MediaType, java.lang.Class<?>);
    Code:
       0: aload_0
       1: aload_2
       2: invokespecial #6                  // Method isMatch:(Ljava/lang/Class;)Z
       5: ireturn

  public boolean typeSupport(java.lang.Class<?>);
    Code:
       0: aload_0
       1: aload_1
       2: invokespecial #6                  // Method isMatch:(Ljava/lang/Class;)Z
       5: ireturn

  public org.apache.dubbo.metadata.rest.media.MediaType contentType();
    Code:
       0: getstatic     #7                  // Field org/apache/dubbo/metadata/rest/media/MediaType.APPLICATION_JSON_VALUE:Lorg/apache/dubbo/metadata/rest/media/MediaType;
       3: areturn

  public java.lang.Object decode(byte[], java.lang.Class<?>) throws java.lang.Exception;
    Code:
       0: aconst_null
       1: aload_1
       2: if_acmpeq     10
       5: aload_1
       6: arraylength
       7: ifne          12
      10: aconst_null
      11: areturn
      12: ldc           #8                  // String org.jboss.resteasy.specimpl.BuiltResponse
      14: invokestatic  #3                  // Method org/apache/dubbo/common/utils/ClassUtils.forName:(Ljava/lang/String;)Ljava/lang/Class;
      17: astore_3
      18: aload_3
      19: invokevirtual #9                  // Method java/lang/Class.newInstance:()Ljava/lang/Object;
      22: astore        4
      24: aload_3
      25: ldc           #10                 // String setEntity
      27: iconst_1
      28: anewarray     #11                 // class java/lang/Class
      31: dup
      32: iconst_0
      33: ldc           #12                 // class java/lang/Object
      35: aastore
      36: invokevirtual #13                 // Method java/lang/Class.getMethod:(Ljava/lang/String;[Ljava/lang/Class;)Ljava/lang/reflect/Method;
      39: astore        5
      41: aload         5
      43: aload         4
      45: iconst_1
      46: anewarray     #12                 // class java/lang/Object
      49: dup
      50: iconst_0
      51: new           #14                 // class java/lang/String
      54: dup
      55: aload_1
      56: getstatic     #15                 // Field java/nio/charset/StandardCharsets.UTF_8:Ljava/nio/charset/Charset;
      59: invokespecial #16                 // Method java/lang/String."<init>":([BLjava/nio/charset/Charset;)V
      62: aastore
      63: invokevirtual #17                 // Method java/lang/reflect/Method.invoke:(Ljava/lang/Object;[Ljava/lang/Object;)Ljava/lang/Object;
      66: pop
      67: aload         4
      69: areturn

  public void encode(java.io.OutputStream, java.lang.Object, org.apache.dubbo.common.URL) throws java.lang.Exception;
    Code:
       0: aload_2
       1: ifnull        52
       4: aload_2
       5: invokevirtual #18                 // Method java/lang/Object.getClass:()Ljava/lang/Class;
       8: ldc           #19                 // String getEntity
      10: iconst_0
      11: anewarray     #11                 // class java/lang/Class
      14: invokevirtual #13                 // Method java/lang/Class.getMethod:(Ljava/lang/String;[Ljava/lang/Class;)Ljava/lang/reflect/Method;
      17: astore        4
      19: aload         4
      21: iconst_1
      22: invokevirtual #20                 // Method java/lang/reflect/Method.setAccessible:(Z)V
      25: aload         4
      27: aload_2
      28: iconst_0
      29: anewarray     #12                 // class java/lang/Object
      32: invokevirtual #17                 // Method java/lang/reflect/Method.invoke:(Ljava/lang/Object;[Ljava/lang/Object;)Ljava/lang/Object;
      35: astore        5
      37: aload_1
      38: aload         5
      40: invokestatic  #21                 // Method org/apache/dubbo/common/utils/JsonUtils.toJson:(Ljava/lang/Object;)Ljava/lang/String;
      43: getstatic     #15                 // Field java/nio/charset/StandardCharsets.UTF_8:Ljava/nio/charset/Charset;
      46: invokevirtual #22                 // Method java/lang/String.getBytes:(Ljava/nio/charset/Charset;)[B
      49: invokevirtual #23                 // Method java/io/OutputStream.write:([B)V
      52: return

  private boolean isMatch(java.lang.Class<?>);
    Code:
       0: aload_0
       1: getfield      #4                  // Field responseClass:Ljava/lang/Class;
       4: ifnull        27
       7: aconst_null
       8: aload_1
       9: if_acmpeq     27
      12: aload_0
      13: getfield      #4                  // Field responseClass:Ljava/lang/Class;
      16: aload_1
      17: invokevirtual #24                 // Method java/lang/Class.isAssignableFrom:(Ljava/lang/Class;)Z
      20: ifeq          27
      23: iconst_1
      24: goto          28
      27: iconst_0
      28: ireturn

  public java.lang.Object decode(java.lang.Object, java.lang.Class) throws java.lang.Exception;
    Code:
       0: aload_0
       1: aload_1
       2: checkcast     #25                 // class "[B"
       5: aload_2
       6: invokevirtual #26                 // Method decode:([BLjava/lang/Class;)Ljava/lang/Object;
       9: areturn

  public void encode(java.lang.Object, java.lang.Object, org.apache.dubbo.common.URL) throws java.lang.Exception;
    Code:
       0: aload_0
       1: aload_1
       2: checkcast     #27                 // class java/io/OutputStream
       5: aload_2
       6: aload_3
       7: invokevirtual #28                 // Method encode:(Ljava/io/OutputStream;Ljava/lang/Object;Lorg/apache/dubbo/common/URL;)V
      10: return
}
