Compiled from "TextCodec.java"
public class org.apache.dubbo.rpc.protocol.rest.message.codec.TextCodec implements org.apache.dubbo.rpc.protocol.rest.message.HttpMessageCodec<byte[], java.io.OutputStream> {
  public org.apache.dubbo.rpc.protocol.rest.message.codec.TextCodec();
    Code:
       0: aload_0
       1: invokespecial #1                  // Method java/lang/Object."<init>":()V
       4: return

  public java.lang.Object decode(byte[], java.lang.Class<?>) throws java.lang.Exception;
    Code:
       0: aload_2
       1: new           #2                  // class java/lang/String
       4: dup
       5: aload_1
       6: getstatic     #3                  // Field java/nio/charset/StandardCharsets.UTF_8:Ljava/nio/charset/Charset;
       9: invokespecial #4                  // Method java/lang/String."<init>":([BLjava/nio/charset/Charset;)V
      12: invokestatic  #5                  // Method org/apache/dubbo/rpc/protocol/rest/util/DataParseUtils.stringTypeConvert:(Ljava/lang/Class;Ljava/lang/String;)Ljava/lang/Object;
      15: areturn

  public boolean contentTypeSupport(org.apache.dubbo.metadata.rest.media.MediaType, java.lang.Class<?>);
    Code:
       0: getstatic     #6                  // Field org/apache/dubbo/rpc/protocol/rest/message/MediaTypeMatcher.TEXT_PLAIN:Lorg/apache/dubbo/rpc/protocol/rest/message/MediaTypeMatcher;
       3: aload_1
       4: invokevirtual #7                  // Method org/apache/dubbo/rpc/protocol/rest/message/MediaTypeMatcher.mediaSupport:(Lorg/apache/dubbo/metadata/rest/media/MediaType;)Z
       7: ireturn

  public boolean typeSupport(java.lang.Class<?>);
    Code:
       0: aload_1
       1: invokestatic  #8                  // Method org/apache/dubbo/rpc/protocol/rest/util/DataParseUtils.isTextType:(Ljava/lang/Class;)Z
       4: ireturn

  public org.apache.dubbo.metadata.rest.media.MediaType contentType();
    Code:
       0: getstatic     #9                  // Field org/apache/dubbo/metadata/rest/media/MediaType.TEXT_PLAIN:Lorg/apache/dubbo/metadata/rest/media/MediaType;
       3: areturn

  public void encode(java.io.OutputStream, java.lang.Object, org.apache.dubbo.common.URL) throws java.lang.Exception;
    Code:
       0: aload_2
       1: aload_1
       2: invokestatic  #10                 // Method org/apache/dubbo/rpc/protocol/rest/util/DataParseUtils.writeTextContent:(Ljava/lang/Object;Ljava/io/OutputStream;)V
       5: return

  public java.lang.Object decode(java.lang.Object, java.lang.Class) throws java.lang.Exception;
    Code:
       0: aload_0
       1: aload_1
       2: checkcast     #11                 // class "[B"
       5: aload_2
       6: invokevirtual #12                 // Method decode:([BLjava/lang/Class;)Ljava/lang/Object;
       9: areturn

  public void encode(java.lang.Object, java.lang.Object, org.apache.dubbo.common.URL) throws java.lang.Exception;
    Code:
       0: aload_0
       1: aload_1
       2: checkcast     #13                 // class java/io/OutputStream
       5: aload_2
       6: aload_3
       7: invokevirtual #14                 // Method encode:(Ljava/io/OutputStream;Ljava/lang/Object;Lorg/apache/dubbo/common/URL;)V
      10: return
}
