Compiled from "XMLCodec.java"
public class org.apache.dubbo.rpc.protocol.rest.message.codec.XMLCodec implements org.apache.dubbo.rpc.protocol.rest.message.HttpMessageCodec<byte[], java.io.OutputStream> {
  public org.apache.dubbo.rpc.protocol.rest.message.codec.XMLCodec();
    Code:
       0: aload_0
       1: invokespecial #1                  // Method java/lang/Object."<init>":()V
       4: return

  public java.lang.Object decode(byte[], java.lang.Class<?>) throws java.lang.Exception;
    Code:
       0: invokestatic  #2                  // Method javax/xml/parsers/SAXParserFactory.newInstance:()Ljavax/xml/parsers/SAXParserFactory;
       3: astore_3
       4: aload_3
       5: ldc           #3                  // String http://xml.org/sax/features/external-general-entities
       7: iconst_0
       8: invokevirtual #4                  // Method javax/xml/parsers/SAXParserFactory.setFeature:(Ljava/lang/String;Z)V
      11: aload_3
      12: ldc           #5                  // String http://xml.org/sax/features/external-parameter-entities
      14: iconst_0
      15: invokevirtual #4                  // Method javax/xml/parsers/SAXParserFactory.setFeature:(Ljava/lang/String;Z)V
      18: aload_3
      19: ldc           #6                  // String http://apache.org/xml/features/nonvalidating/load-external-dtd
      21: iconst_0
      22: invokevirtual #4                  // Method javax/xml/parsers/SAXParserFactory.setFeature:(Ljava/lang/String;Z)V
      25: new           #7                  // class javax/xml/transform/sax/SAXSource
      28: dup
      29: aload_3
      30: invokevirtual #8                  // Method javax/xml/parsers/SAXParserFactory.newSAXParser:()Ljavax/xml/parsers/SAXParser;
      33: invokevirtual #9                  // Method javax/xml/parsers/SAXParser.getXMLReader:()Lorg/xml/sax/XMLReader;
      36: new           #10                 // class org/xml/sax/InputSource
      39: dup
      40: new           #11                 // class java/io/StringReader
      43: dup
      44: new           #12                 // class java/lang/String
      47: dup
      48: aload_1
      49: invokespecial #13                 // Method java/lang/String."<init>":([B)V
      52: invokespecial #14                 // Method java/io/StringReader."<init>":(Ljava/lang/String;)V
      55: invokespecial #15                 // Method org/xml/sax/InputSource."<init>":(Ljava/io/Reader;)V
      58: invokespecial #16                 // Method javax/xml/transform/sax/SAXSource."<init>":(Lorg/xml/sax/XMLReader;Lorg/xml/sax/InputSource;)V
      61: astore        4
      63: iconst_1
      64: anewarray     #17                 // class java/lang/Class
      67: dup
      68: iconst_0
      69: aload_2
      70: aastore
      71: invokestatic  #18                 // Method javax/xml/bind/JAXBContext.newInstance:([Ljava/lang/Class;)Ljavax/xml/bind/JAXBContext;
      74: astore        5
      76: aload         5
      78: invokevirtual #19                 // Method javax/xml/bind/JAXBContext.createUnmarshaller:()Ljavax/xml/bind/Unmarshaller;
      81: astore        6
      83: aload         6
      85: aload         4
      87: invokeinterface #20,  2           // InterfaceMethod javax/xml/bind/Unmarshaller.unmarshal:(Ljavax/xml/transform/Source;)Ljava/lang/Object;
      92: areturn

  public boolean contentTypeSupport(org.apache.dubbo.metadata.rest.media.MediaType, java.lang.Class<?>);
    Code:
       0: getstatic     #21                 // Field org/apache/dubbo/rpc/protocol/rest/message/MediaTypeMatcher.TEXT_XML:Lorg/apache/dubbo/rpc/protocol/rest/message/MediaTypeMatcher;
       3: aload_1
       4: invokevirtual #22                 // Method org/apache/dubbo/rpc/protocol/rest/message/MediaTypeMatcher.mediaSupport:(Lorg/apache/dubbo/metadata/rest/media/MediaType;)Z
       7: ireturn

  public boolean typeSupport(java.lang.Class<?>);
    Code:
       0: iconst_0
       1: ireturn

  public org.apache.dubbo.metadata.rest.media.MediaType contentType();
    Code:
       0: getstatic     #23                 // Field org/apache/dubbo/metadata/rest/media/MediaType.TEXT_XML:Lorg/apache/dubbo/metadata/rest/media/MediaType;
       3: areturn

  public void encode(java.io.OutputStream, java.lang.Object, org.apache.dubbo.common.URL) throws java.lang.Exception;
    Code:
       0: iconst_1
       1: anewarray     #17                 // class java/lang/Class
       4: dup
       5: iconst_0
       6: aload_2
       7: invokevirtual #24                 // Method java/lang/Object.getClass:()Ljava/lang/Class;
      10: aastore
      11: invokestatic  #18                 // Method javax/xml/bind/JAXBContext.newInstance:([Ljava/lang/Class;)Ljavax/xml/bind/JAXBContext;
      14: invokevirtual #25                 // Method javax/xml/bind/JAXBContext.createMarshaller:()Ljavax/xml/bind/Marshaller;
      17: astore        4
      19: aload         4
      21: aload_2
      22: aload_1
      23: invokeinterface #26,  3           // InterfaceMethod javax/xml/bind/Marshaller.marshal:(Ljava/lang/Object;Ljava/io/OutputStream;)V
      28: return

  public java.lang.Object decode(java.lang.Object, java.lang.Class) throws java.lang.Exception;
    Code:
       0: aload_0
       1: aload_1
       2: checkcast     #27                 // class "[B"
       5: aload_2
       6: invokevirtual #28                 // Method decode:([BLjava/lang/Class;)Ljava/lang/Object;
       9: areturn

  public void encode(java.lang.Object, java.lang.Object, org.apache.dubbo.common.URL) throws java.lang.Exception;
    Code:
       0: aload_0
       1: aload_1
       2: checkcast     #29                 // class java/io/OutputStream
       5: aload_2
       6: aload_3
       7: invokevirtual #30                 // Method encode:(Ljava/io/OutputStream;Ljava/lang/Object;Lorg/apache/dubbo/common/URL;)V
      10: return
}
