Compiled from "FutureFilter.java"
public class org.apache.dubbo.rpc.protocol.dubbo.filter.FutureFilter implements org.apache.dubbo.rpc.cluster.filter.ClusterFilter,org.apache.dubbo.rpc.BaseFilter$Listener {
  protected static final org.apache.dubbo.common.logger.ErrorTypeAwareLogger logger;

  public org.apache.dubbo.rpc.protocol.dubbo.filter.FutureFilter();
    Code:
       0: aload_0
       1: invokespecial #4                  // Method java/lang/Object."<init>":()V
       4: return

  public org.apache.dubbo.rpc.Result invoke(org.apache.dubbo.rpc.Invoker<?>, org.apache.dubbo.rpc.Invocation) throws org.apache.dubbo.rpc.RpcException;
    Code:
       0: aload_0
       1: aload_1
       2: aload_2
       3: invokespecial #5                  // Method fireInvokeCallback:(Lorg/apache/dubbo/rpc/Invoker;Lorg/apache/dubbo/rpc/Invocation;)V
       6: aload_1
       7: aload_2
       8: invokeinterface #6,  2            // InterfaceMethod org/apache/dubbo/rpc/Invoker.invoke:(Lorg/apache/dubbo/rpc/Invocation;)Lorg/apache/dubbo/rpc/Result;
      13: areturn

  public void onResponse(org.apache.dubbo.rpc.Result, org.apache.dubbo.rpc.Invoker<?>, org.apache.dubbo.rpc.Invocation);
    Code:
       0: aload_1
       1: invokeinterface #7,  1            // InterfaceMethod org/apache/dubbo/rpc/Result.hasException:()Z
       6: ifeq          24
       9: aload_0
      10: aload_2
      11: aload_3
      12: aload_1
      13: invokeinterface #8,  1            // InterfaceMethod org/apache/dubbo/rpc/Result.getException:()Ljava/lang/Throwable;
      18: invokespecial #9                  // Method fireThrowCallback:(Lorg/apache/dubbo/rpc/Invoker;Lorg/apache/dubbo/rpc/Invocation;Ljava/lang/Throwable;)V
      21: goto          36
      24: aload_0
      25: aload_2
      26: aload_3
      27: aload_1
      28: invokeinterface #10,  1           // InterfaceMethod org/apache/dubbo/rpc/Result.getValue:()Ljava/lang/Object;
      33: invokespecial #11                 // Method fireReturnCallback:(Lorg/apache/dubbo/rpc/Invoker;Lorg/apache/dubbo/rpc/Invocation;Ljava/lang/Object;)V
      36: return

  public void onError(java.lang.Throwable, org.apache.dubbo.rpc.Invoker<?>, org.apache.dubbo.rpc.Invocation);
    Code:
       0: aload_0
       1: aload_2
       2: aload_3
       3: aload_1
       4: invokespecial #9                  // Method fireThrowCallback:(Lorg/apache/dubbo/rpc/Invoker;Lorg/apache/dubbo/rpc/Invocation;Ljava/lang/Throwable;)V
       7: return

  private void fireInvokeCallback(org.apache.dubbo.rpc.Invoker<?>, org.apache.dubbo.rpc.Invocation);
    Code:
       0: aload_0
       1: aload_1
       2: aload_2
       3: invokespecial #12                 // Method getAsyncMethodInfo:(Lorg/apache/dubbo/rpc/Invoker;Lorg/apache/dubbo/rpc/Invocation;)Lorg/apache/dubbo/rpc/model/AsyncMethodInfo;
       6: astore_3
       7: aload_3
       8: ifnonnull     12
      11: return
      12: aload_3
      13: invokevirtual #13                 // Method org/apache/dubbo/rpc/model/AsyncMethodInfo.getOninvokeMethod:()Ljava/lang/reflect/Method;
      16: astore        4
      18: aload_3
      19: invokevirtual #14                 // Method org/apache/dubbo/rpc/model/AsyncMethodInfo.getOninvokeInstance:()Ljava/lang/Object;
      22: astore        5
      24: aload         4
      26: ifnonnull     35
      29: aload         5
      31: ifnonnull     35
      34: return
      35: aload         4
      37: ifnull        45
      40: aload         5
      42: ifnonnull     114
      45: new           #15                 // class java/lang/IllegalStateException
      48: dup
      49: new           #16                 // class java/lang/StringBuilder
      52: dup
      53: invokespecial #17                 // Method java/lang/StringBuilder."<init>":()V
      56: ldc           #18                 // String service:
      58: invokevirtual #19                 // Method java/lang/StringBuilder.append:(Ljava/lang/String;)Ljava/lang/StringBuilder;
      61: aload_1
      62: invokeinterface #20,  1           // InterfaceMethod org/apache/dubbo/rpc/Invoker.getUrl:()Lorg/apache/dubbo/common/URL;
      67: invokevirtual #21                 // Method org/apache/dubbo/common/URL.getServiceKey:()Ljava/lang/String;
      70: invokevirtual #19                 // Method java/lang/StringBuilder.append:(Ljava/lang/String;)Ljava/lang/StringBuilder;
      73: ldc           #22                 // String  has a oninvoke callback config , but no such
      75: invokevirtual #19                 // Method java/lang/StringBuilder.append:(Ljava/lang/String;)Ljava/lang/StringBuilder;
      78: aload         4
      80: ifnonnull     88
      83: ldc           #23                 // String method
      85: goto          90
      88: ldc           #24                 // String instance
      90: invokevirtual #19                 // Method java/lang/StringBuilder.append:(Ljava/lang/String;)Ljava/lang/StringBuilder;
      93: ldc           #25                 // String  found. url:
      95: invokevirtual #19                 // Method java/lang/StringBuilder.append:(Ljava/lang/String;)Ljava/lang/StringBuilder;
      98: aload_1
      99: invokeinterface #20,  1           // InterfaceMethod org/apache/dubbo/rpc/Invoker.getUrl:()Lorg/apache/dubbo/common/URL;
     104: invokevirtual #26                 // Method java/lang/StringBuilder.append:(Ljava/lang/Object;)Ljava/lang/StringBuilder;
     107: invokevirtual #27                 // Method java/lang/StringBuilder.toString:()Ljava/lang/String;
     110: invokespecial #28                 // Method java/lang/IllegalStateException."<init>":(Ljava/lang/String;)V
     113: athrow
     114: aload         4
     116: invokevirtual #29                 // Method java/lang/reflect/Method.isAccessible:()Z
     119: ifne          128
     122: aload         4
     124: iconst_1
     125: invokevirtual #30                 // Method java/lang/reflect/Method.setAccessible:(Z)V
     128: aload_2
     129: invokeinterface #31,  1           // InterfaceMethod org/apache/dubbo/rpc/Invocation.getArguments:()[Ljava/lang/Object;
     134: astore        6
     136: aload         4
     138: aload         5
     140: aload         6
     142: invokevirtual #32                 // Method java/lang/reflect/Method.invoke:(Ljava/lang/Object;[Ljava/lang/Object;)Ljava/lang/Object;
     145: pop
     146: goto          175
     149: astore        7
     151: aload_0
     152: aload_1
     153: aload_2
     154: aload         7
     156: invokevirtual #34                 // Method java/lang/reflect/InvocationTargetException.getTargetException:()Ljava/lang/Throwable;
     159: invokespecial #9                  // Method fireThrowCallback:(Lorg/apache/dubbo/rpc/Invoker;Lorg/apache/dubbo/rpc/Invocation;Ljava/lang/Throwable;)V
     162: goto          175
     165: astore        7
     167: aload_0
     168: aload_1
     169: aload_2
     170: aload         7
     172: invokespecial #9                  // Method fireThrowCallback:(Lorg/apache/dubbo/rpc/Invoker;Lorg/apache/dubbo/rpc/Invocation;Ljava/lang/Throwable;)V
     175: return
    Exception table:
       from    to  target type
         136   146   149   Class java/lang/reflect/InvocationTargetException
         136   146   165   Class java/lang/Throwable

  private void fireReturnCallback(org.apache.dubbo.rpc.Invoker<?>, org.apache.dubbo.rpc.Invocation, java.lang.Object);
    Code:
       0: aload_0
       1: aload_1
       2: aload_2
       3: invokespecial #12                 // Method getAsyncMethodInfo:(Lorg/apache/dubbo/rpc/Invoker;Lorg/apache/dubbo/rpc/Invocation;)Lorg/apache/dubbo/rpc/model/AsyncMethodInfo;
       6: astore        4
       8: aload         4
      10: ifnonnull     14
      13: return
      14: aload         4
      16: invokevirtual #36                 // Method org/apache/dubbo/rpc/model/AsyncMethodInfo.getOnreturnMethod:()Ljava/lang/reflect/Method;
      19: astore        5
      21: aload         4
      23: invokevirtual #37                 // Method org/apache/dubbo/rpc/model/AsyncMethodInfo.getOnreturnInstance:()Ljava/lang/Object;
      26: astore        6
      28: aload         5
      30: ifnonnull     39
      33: aload         6
      35: ifnonnull     39
      38: return
      39: aload         5
      41: ifnull        49
      44: aload         6
      46: ifnonnull     118
      49: new           #15                 // class java/lang/IllegalStateException
      52: dup
      53: new           #16                 // class java/lang/StringBuilder
      56: dup
      57: invokespecial #17                 // Method java/lang/StringBuilder."<init>":()V
      60: ldc           #18                 // String service:
      62: invokevirtual #19                 // Method java/lang/StringBuilder.append:(Ljava/lang/String;)Ljava/lang/StringBuilder;
      65: aload_1
      66: invokeinterface #20,  1           // InterfaceMethod org/apache/dubbo/rpc/Invoker.getUrl:()Lorg/apache/dubbo/common/URL;
      71: invokevirtual #21                 // Method org/apache/dubbo/common/URL.getServiceKey:()Ljava/lang/String;
      74: invokevirtual #19                 // Method java/lang/StringBuilder.append:(Ljava/lang/String;)Ljava/lang/StringBuilder;
      77: ldc           #38                 // String  has a onreturn callback config , but no such
      79: invokevirtual #19                 // Method java/lang/StringBuilder.append:(Ljava/lang/String;)Ljava/lang/StringBuilder;
      82: aload         5
      84: ifnonnull     92
      87: ldc           #23                 // String method
      89: goto          94
      92: ldc           #24                 // String instance
      94: invokevirtual #19                 // Method java/lang/StringBuilder.append:(Ljava/lang/String;)Ljava/lang/StringBuilder;
      97: ldc           #25                 // String  found. url:
      99: invokevirtual #19                 // Method java/lang/StringBuilder.append:(Ljava/lang/String;)Ljava/lang/StringBuilder;
     102: aload_1
     103: invokeinterface #20,  1           // InterfaceMethod org/apache/dubbo/rpc/Invoker.getUrl:()Lorg/apache/dubbo/common/URL;
     108: invokevirtual #26                 // Method java/lang/StringBuilder.append:(Ljava/lang/Object;)Ljava/lang/StringBuilder;
     111: invokevirtual #27                 // Method java/lang/StringBuilder.toString:()Ljava/lang/String;
     114: invokespecial #28                 // Method java/lang/IllegalStateException."<init>":(Ljava/lang/String;)V
     117: athrow
     118: aload         5
     120: invokevirtual #29                 // Method java/lang/reflect/Method.isAccessible:()Z
     123: ifne          132
     126: aload         5
     128: iconst_1
     129: invokevirtual #30                 // Method java/lang/reflect/Method.setAccessible:(Z)V
     132: aload_2
     133: invokeinterface #31,  1           // InterfaceMethod org/apache/dubbo/rpc/Invocation.getArguments:()[Ljava/lang/Object;
     138: astore        7
     140: aload         5
     142: invokevirtual #39                 // Method java/lang/reflect/Method.getParameterTypes:()[Ljava/lang/Class;
     145: astore        9
     147: aload         9
     149: arraylength
     150: iconst_1
     151: if_icmple     223
     154: aload         9
     156: arraylength
     157: iconst_2
     158: if_icmpne     193
     161: aload         9
     163: iconst_1
     164: aaload
     165: ldc           #40                 // class "[Ljava/lang/Object;"
     167: invokevirtual #41                 // Method java/lang/Class.isAssignableFrom:(Ljava/lang/Class;)Z
     170: ifeq          193
     173: iconst_2
     174: anewarray     #42                 // class java/lang/Object
     177: astore        8
     179: aload         8
     181: iconst_0
     182: aload_3
     183: aastore
     184: aload         8
     186: iconst_1
     187: aload         7
     189: aastore
     190: goto          233
     193: aload         7
     195: arraylength
     196: iconst_1
     197: iadd
     198: anewarray     #42                 // class java/lang/Object
     201: astore        8
     203: aload         8
     205: iconst_0
     206: aload_3
     207: aastore
     208: aload         7
     210: iconst_0
     211: aload         8
     213: iconst_1
     214: aload         7
     216: arraylength
     217: invokestatic  #43                 // Method java/lang/System.arraycopy:(Ljava/lang/Object;ILjava/lang/Object;II)V
     220: goto          233
     223: iconst_1
     224: anewarray     #42                 // class java/lang/Object
     227: dup
     228: iconst_0
     229: aload_3
     230: aastore
     231: astore        8
     233: aload         5
     235: aload         6
     237: aload         8
     239: invokevirtual #32                 // Method java/lang/reflect/Method.invoke:(Ljava/lang/Object;[Ljava/lang/Object;)Ljava/lang/Object;
     242: pop
     243: goto          272
     246: astore        10
     248: aload_0
     249: aload_1
     250: aload_2
     251: aload         10
     253: invokevirtual #34                 // Method java/lang/reflect/InvocationTargetException.getTargetException:()Ljava/lang/Throwable;
     256: invokespecial #9                  // Method fireThrowCallback:(Lorg/apache/dubbo/rpc/Invoker;Lorg/apache/dubbo/rpc/Invocation;Ljava/lang/Throwable;)V
     259: goto          272
     262: astore        10
     264: aload_0
     265: aload_1
     266: aload_2
     267: aload         10
     269: invokespecial #9                  // Method fireThrowCallback:(Lorg/apache/dubbo/rpc/Invoker;Lorg/apache/dubbo/rpc/Invocation;Ljava/lang/Throwable;)V
     272: return
    Exception table:
       from    to  target type
         233   243   246   Class java/lang/reflect/InvocationTargetException
         233   243   262   Class java/lang/Throwable

  private void fireThrowCallback(org.apache.dubbo.rpc.Invoker<?>, org.apache.dubbo.rpc.Invocation, java.lang.Throwable);
    Code:
       0: aload_0
       1: aload_1
       2: aload_2
       3: invokespecial #12                 // Method getAsyncMethodInfo:(Lorg/apache/dubbo/rpc/Invoker;Lorg/apache/dubbo/rpc/Invocation;)Lorg/apache/dubbo/rpc/model/AsyncMethodInfo;
       6: astore        4
       8: aload         4
      10: ifnonnull     14
      13: return
      14: aload         4
      16: invokevirtual #44                 // Method org/apache/dubbo/rpc/model/AsyncMethodInfo.getOnthrowMethod:()Ljava/lang/reflect/Method;
      19: astore        5
      21: aload         4
      23: invokevirtual #45                 // Method org/apache/dubbo/rpc/model/AsyncMethodInfo.getOnthrowInstance:()Ljava/lang/Object;
      26: astore        6
      28: aload         5
      30: ifnonnull     39
      33: aload         6
      35: ifnonnull     39
      38: return
      39: aload         5
      41: ifnull        49
      44: aload         6
      46: ifnonnull     118
      49: new           #15                 // class java/lang/IllegalStateException
      52: dup
      53: new           #16                 // class java/lang/StringBuilder
      56: dup
      57: invokespecial #17                 // Method java/lang/StringBuilder."<init>":()V
      60: ldc           #18                 // String service:
      62: invokevirtual #19                 // Method java/lang/StringBuilder.append:(Ljava/lang/String;)Ljava/lang/StringBuilder;
      65: aload_1
      66: invokeinterface #20,  1           // InterfaceMethod org/apache/dubbo/rpc/Invoker.getUrl:()Lorg/apache/dubbo/common/URL;
      71: invokevirtual #21                 // Method org/apache/dubbo/common/URL.getServiceKey:()Ljava/lang/String;
      74: invokevirtual #19                 // Method java/lang/StringBuilder.append:(Ljava/lang/String;)Ljava/lang/StringBuilder;
      77: ldc           #46                 // String  has a onthrow callback config , but no such
      79: invokevirtual #19                 // Method java/lang/StringBuilder.append:(Ljava/lang/String;)Ljava/lang/StringBuilder;
      82: aload         5
      84: ifnonnull     92
      87: ldc           #23                 // String method
      89: goto          94
      92: ldc           #24                 // String instance
      94: invokevirtual #19                 // Method java/lang/StringBuilder.append:(Ljava/lang/String;)Ljava/lang/StringBuilder;
      97: ldc           #25                 // String  found. url:
      99: invokevirtual #19                 // Method java/lang/StringBuilder.append:(Ljava/lang/String;)Ljava/lang/StringBuilder;
     102: aload_1
     103: invokeinterface #20,  1           // InterfaceMethod org/apache/dubbo/rpc/Invoker.getUrl:()Lorg/apache/dubbo/common/URL;
     108: invokevirtual #26                 // Method java/lang/StringBuilder.append:(Ljava/lang/Object;)Ljava/lang/StringBuilder;
     111: invokevirtual #27                 // Method java/lang/StringBuilder.toString:()Ljava/lang/String;
     114: invokespecial #28                 // Method java/lang/IllegalStateException."<init>":(Ljava/lang/String;)V
     117: athrow
     118: aload         5
     120: invokevirtual #29                 // Method java/lang/reflect/Method.isAccessible:()Z
     123: ifne          132
     126: aload         5
     128: iconst_1
     129: invokevirtual #30                 // Method java/lang/reflect/Method.setAccessible:(Z)V
     132: aload         5
     134: invokevirtual #39                 // Method java/lang/reflect/Method.getParameterTypes:()[Ljava/lang/Class;
     137: astore        7
     139: aload         7
     141: iconst_0
     142: aaload
     143: aload_3
     144: invokevirtual #47                 // Method java/lang/Object.getClass:()Ljava/lang/Class;
     147: invokevirtual #41                 // Method java/lang/Class.isAssignableFrom:(Ljava/lang/Class;)Z
     150: ifeq          324
     153: aload_2
     154: invokeinterface #31,  1           // InterfaceMethod org/apache/dubbo/rpc/Invocation.getArguments:()[Ljava/lang/Object;
     159: astore        8
     161: aload         7
     163: arraylength
     164: iconst_1
     165: if_icmple     237
     168: aload         7
     170: arraylength
     171: iconst_2
     172: if_icmpne     207
     175: aload         7
     177: iconst_1
     178: aaload
     179: ldc           #40                 // class "[Ljava/lang/Object;"
     181: invokevirtual #41                 // Method java/lang/Class.isAssignableFrom:(Ljava/lang/Class;)Z
     184: ifeq          207
     187: iconst_2
     188: anewarray     #42                 // class java/lang/Object
     191: astore        9
     193: aload         9
     195: iconst_0
     196: aload_3
     197: aastore
     198: aload         9
     200: iconst_1
     201: aload         8
     203: aastore
     204: goto          247
     207: aload         8
     209: arraylength
     210: iconst_1
     211: iadd
     212: anewarray     #42                 // class java/lang/Object
     215: astore        9
     217: aload         9
     219: iconst_0
     220: aload_3
     221: aastore
     222: aload         8
     224: iconst_0
     225: aload         9
     227: iconst_1
     228: aload         8
     230: arraylength
     231: invokestatic  #43                 // Method java/lang/System.arraycopy:(Ljava/lang/Object;ILjava/lang/Object;II)V
     234: goto          247
     237: iconst_1
     238: anewarray     #42                 // class java/lang/Object
     241: dup
     242: iconst_0
     243: aload_3
     244: aastore
     245: astore        9
     247: aload         5
     249: aload         6
     251: aload         9
     253: invokevirtual #32                 // Method java/lang/reflect/Method.invoke:(Ljava/lang/Object;[Ljava/lang/Object;)Ljava/lang/Object;
     256: pop
     257: goto          382
     260: astore        8
     262: getstatic     #48                 // Field logger:Lorg/apache/dubbo/common/logger/ErrorTypeAwareLogger;
     265: ldc           #49                 // String 4-11
     267: ldc           #50                 // String
     269: ldc           #50                 // String
     271: new           #16                 // class java/lang/StringBuilder
     274: dup
     275: invokespecial #17                 // Method java/lang/StringBuilder."<init>":()V
     278: aload_2
     279: invokeinterface #51,  1           // InterfaceMethod org/apache/dubbo/rpc/Invocation.getMethodName:()Ljava/lang/String;
     284: invokevirtual #19                 // Method java/lang/StringBuilder.append:(Ljava/lang/String;)Ljava/lang/StringBuilder;
     287: ldc           #52                 // String .call back method invoke error . callback method :
     289: invokevirtual #19                 // Method java/lang/StringBuilder.append:(Ljava/lang/String;)Ljava/lang/StringBuilder;
     292: aload         5
     294: invokevirtual #26                 // Method java/lang/StringBuilder.append:(Ljava/lang/Object;)Ljava/lang/StringBuilder;
     297: ldc           #53                 // String , url:
     299: invokevirtual #19                 // Method java/lang/StringBuilder.append:(Ljava/lang/String;)Ljava/lang/StringBuilder;
     302: aload_1
     303: invokeinterface #20,  1           // InterfaceMethod org/apache/dubbo/rpc/Invoker.getUrl:()Lorg/apache/dubbo/common/URL;
     308: invokevirtual #26                 // Method java/lang/StringBuilder.append:(Ljava/lang/Object;)Ljava/lang/StringBuilder;
     311: invokevirtual #27                 // Method java/lang/StringBuilder.toString:()Ljava/lang/String;
     314: aload         8
     316: invokeinterface #54,  6           // InterfaceMethod org/apache/dubbo/common/logger/ErrorTypeAwareLogger.error:(Ljava/lang/String;Ljava/lang/String;Ljava/lang/String;Ljava/lang/String;Ljava/lang/Throwable;)V
     321: goto          382
     324: getstatic     #48                 // Field logger:Lorg/apache/dubbo/common/logger/ErrorTypeAwareLogger;
     327: ldc           #49                 // String 4-11
     329: ldc           #50                 // String
     331: ldc           #50                 // String
     333: new           #16                 // class java/lang/StringBuilder
     336: dup
     337: invokespecial #17                 // Method java/lang/StringBuilder."<init>":()V
     340: aload_2
     341: invokeinterface #51,  1           // InterfaceMethod org/apache/dubbo/rpc/Invocation.getMethodName:()Ljava/lang/String;
     346: invokevirtual #19                 // Method java/lang/StringBuilder.append:(Ljava/lang/String;)Ljava/lang/StringBuilder;
     349: ldc           #52                 // String .call back method invoke error . callback method :
     351: invokevirtual #19                 // Method java/lang/StringBuilder.append:(Ljava/lang/String;)Ljava/lang/StringBuilder;
     354: aload         5
     356: invokevirtual #26                 // Method java/lang/StringBuilder.append:(Ljava/lang/Object;)Ljava/lang/StringBuilder;
     359: ldc           #53                 // String , url:
     361: invokevirtual #19                 // Method java/lang/StringBuilder.append:(Ljava/lang/String;)Ljava/lang/StringBuilder;
     364: aload_1
     365: invokeinterface #20,  1           // InterfaceMethod org/apache/dubbo/rpc/Invoker.getUrl:()Lorg/apache/dubbo/common/URL;
     370: invokevirtual #26                 // Method java/lang/StringBuilder.append:(Ljava/lang/Object;)Ljava/lang/StringBuilder;
     373: invokevirtual #27                 // Method java/lang/StringBuilder.toString:()Ljava/lang/String;
     376: aload_3
     377: invokeinterface #54,  6           // InterfaceMethod org/apache/dubbo/common/logger/ErrorTypeAwareLogger.error:(Ljava/lang/String;Ljava/lang/String;Ljava/lang/String;Ljava/lang/String;Ljava/lang/Throwable;)V
     382: return
    Exception table:
       from    to  target type
         153   257   260   Class java/lang/Throwable

  private org.apache.dubbo.rpc.model.AsyncMethodInfo getAsyncMethodInfo(org.apache.dubbo.rpc.Invoker<?>, org.apache.dubbo.rpc.Invocation);
    Code:
       0: aload_2
       1: ldc           #55                 // String async-method-info
       3: invokeinterface #56,  2           // InterfaceMethod org/apache/dubbo/rpc/Invocation.get:(Ljava/lang/Object;)Ljava/lang/Object;
       8: checkcast     #57                 // class org/apache/dubbo/rpc/model/AsyncMethodInfo
      11: astore_3
      12: aload_3
      13: ifnull        18
      16: aload_3
      17: areturn
      18: aload_2
      19: invokeinterface #58,  1           // InterfaceMethod org/apache/dubbo/rpc/Invocation.getServiceModel:()Lorg/apache/dubbo/rpc/model/ServiceModel;
      24: astore        4
      26: aload         4
      28: instanceof    #59                 // class org/apache/dubbo/rpc/model/ConsumerModel
      31: ifne          36
      34: aconst_null
      35: areturn
      36: aload_2
      37: invokeinterface #51,  1           // InterfaceMethod org/apache/dubbo/rpc/Invocation.getMethodName:()Ljava/lang/String;
      42: astore        5
      44: aload         5
      46: ldc           #60                 // String $invoke
      48: invokevirtual #61                 // Method java/lang/String.equals:(Ljava/lang/Object;)Z
      51: ifeq          67
      54: aload_2
      55: invokeinterface #31,  1           // InterfaceMethod org/apache/dubbo/rpc/Invocation.getArguments:()[Ljava/lang/Object;
      60: iconst_0
      61: aaload
      62: checkcast     #62                 // class java/lang/String
      65: astore        5
      67: aload         4
      69: checkcast     #59                 // class org/apache/dubbo/rpc/model/ConsumerModel
      72: aload         5
      74: invokevirtual #63                 // Method org/apache/dubbo/rpc/model/ConsumerModel.getAsyncInfo:(Ljava/lang/String;)Lorg/apache/dubbo/rpc/model/AsyncMethodInfo;
      77: areturn

  static {};
    Code:
       0: ldc           #64                 // class org/apache/dubbo/rpc/protocol/dubbo/filter/FutureFilter
       2: invokestatic  #65                 // Method org/apache/dubbo/common/logger/LoggerFactory.getErrorTypeAwareLogger:(Ljava/lang/Class;)Lorg/apache/dubbo/common/logger/ErrorTypeAwareLogger;
       5: putstatic     #48                 // Field logger:Lorg/apache/dubbo/common/logger/ErrorTypeAwareLogger;
       8: return
}
