Compiled from "ConnectableFlowable.java"
public abstract class io.reactivex.rxjava3.flowables.ConnectableFlowable<T> extends io.reactivex.rxjava3.core.Flowable<T> {
  public io.reactivex.rxjava3.flowables.ConnectableFlowable();
    Code:
       0: aload_0
       1: invokespecial #1                  // Method io/reactivex/rxjava3/core/Flowable."<init>":()V
       4: return

  public abstract void connect(io.reactivex.rxjava3.functions.Consumer<? super io.reactivex.rxjava3.disposables.Disposable>);

  public abstract void reset();

  public final io.reactivex.rxjava3.disposables.Disposable connect();
    Code:
       0: new           #2                  // class io/reactivex/rxjava3/internal/util/ConnectConsumer
       3: dup
       4: invokespecial #3                  // Method io/reactivex/rxjava3/internal/util/ConnectConsumer."<init>":()V
       7: astore_1
       8: aload_0
       9: aload_1
      10: invokevirtual #4                  // Method connect:(Lio/reactivex/rxjava3/functions/Consumer;)V
      13: aload_1
      14: getfield      #5                  // Field io/reactivex/rxjava3/internal/util/ConnectConsumer.disposable:Lio/reactivex/rxjava3/disposables/Disposable;
      17: areturn

  public io.reactivex.rxjava3.core.Flowable<T> refCount();
    Code:
       0: new           #6                  // class io/reactivex/rxjava3/internal/operators/flowable/FlowableRefCount
       3: dup
       4: aload_0
       5: invokespecial #7                  // Method io/reactivex/rxjava3/internal/operators/flowable/FlowableRefCount."<init>":(Lio/reactivex/rxjava3/flowables/ConnectableFlowable;)V
       8: invokestatic  #8                  // Method io/reactivex/rxjava3/plugins/RxJavaPlugins.onAssembly:(Lio/reactivex/rxjava3/core/Flowable;)Lio/reactivex/rxjava3/core/Flowable;
      11: areturn

  public final io.reactivex.rxjava3.core.Flowable<T> refCount(int);
    Code:
       0: aload_0
       1: iload_1
       2: lconst_0
       3: getstatic     #9                  // Field java/util/concurrent/TimeUnit.NANOSECONDS:Ljava/util/concurrent/TimeUnit;
       6: invokestatic  #10                 // Method io/reactivex/rxjava3/schedulers/Schedulers.trampoline:()Lio/reactivex/rxjava3/core/Scheduler;
       9: invokevirtual #11                 // Method refCount:(IJLjava/util/concurrent/TimeUnit;Lio/reactivex/rxjava3/core/Scheduler;)Lio/reactivex/rxjava3/core/Flowable;
      12: areturn

  public final io.reactivex.rxjava3.core.Flowable<T> refCount(long, java.util.concurrent.TimeUnit);
    Code:
       0: aload_0
       1: iconst_1
       2: lload_1
       3: aload_3
       4: invokestatic  #12                 // Method io/reactivex/rxjava3/schedulers/Schedulers.computation:()Lio/reactivex/rxjava3/core/Scheduler;
       7: invokevirtual #11                 // Method refCount:(IJLjava/util/concurrent/TimeUnit;Lio/reactivex/rxjava3/core/Scheduler;)Lio/reactivex/rxjava3/core/Flowable;
      10: areturn

  public final io.reactivex.rxjava3.core.Flowable<T> refCount(long, java.util.concurrent.TimeUnit, io.reactivex.rxjava3.core.Scheduler);
    Code:
       0: aload_0
       1: iconst_1
       2: lload_1
       3: aload_3
       4: aload         4
       6: invokevirtual #11                 // Method refCount:(IJLjava/util/concurrent/TimeUnit;Lio/reactivex/rxjava3/core/Scheduler;)Lio/reactivex/rxjava3/core/Flowable;
       9: areturn

  public final io.reactivex.rxjava3.core.Flowable<T> refCount(int, long, java.util.concurrent.TimeUnit);
    Code:
       0: aload_0
       1: iload_1
       2: lload_2
       3: aload         4
       5: invokestatic  #12                 // Method io/reactivex/rxjava3/schedulers/Schedulers.computation:()Lio/reactivex/rxjava3/core/Scheduler;
       8: invokevirtual #11                 // Method refCount:(IJLjava/util/concurrent/TimeUnit;Lio/reactivex/rxjava3/core/Scheduler;)Lio/reactivex/rxjava3/core/Flowable;
      11: areturn

  public final io.reactivex.rxjava3.core.Flowable<T> refCount(int, long, java.util.concurrent.TimeUnit, io.reactivex.rxjava3.core.Scheduler);
    Code:
       0: iload_1
       1: ldc           #13                 // String subscriberCount
       3: invokestatic  #14                 // Method io/reactivex/rxjava3/internal/functions/ObjectHelper.verifyPositive:(ILjava/lang/String;)I
       6: pop
       7: aload         4
       9: ldc           #15                 // String unit is null
      11: invokestatic  #16                 // Method java/util/Objects.requireNonNull:(Ljava/lang/Object;Ljava/lang/String;)Ljava/lang/Object;
      14: pop
      15: aload         5
      17: ldc           #17                 // String scheduler is null
      19: invokestatic  #16                 // Method java/util/Objects.requireNonNull:(Ljava/lang/Object;Ljava/lang/String;)Ljava/lang/Object;
      22: pop
      23: new           #6                  // class io/reactivex/rxjava3/internal/operators/flowable/FlowableRefCount
      26: dup
      27: aload_0
      28: iload_1
      29: lload_2
      30: aload         4
      32: aload         5
      34: invokespecial #18                 // Method io/reactivex/rxjava3/internal/operators/flowable/FlowableRefCount."<init>":(Lio/reactivex/rxjava3/flowables/ConnectableFlowable;IJLjava/util/concurrent/TimeUnit;Lio/reactivex/rxjava3/core/Scheduler;)V
      37: invokestatic  #19                 // Method io/reactivex/rxjava3/plugins/RxJavaPlugins.onAssembly:(Lio/reactivex/rxjava3/core/Flowable;)Lio/reactivex/rxjava3/core/Flowable;
      40: areturn

  public io.reactivex.rxjava3.core.Flowable<T> autoConnect();
    Code:
       0: aload_0
       1: iconst_1
       2: invokevirtual #20                 // Method autoConnect:(I)Lio/reactivex/rxjava3/core/Flowable;
       5: areturn

  public io.reactivex.rxjava3.core.Flowable<T> autoConnect(int);
    Code:
       0: aload_0
       1: iload_1
       2: invokestatic  #21                 // Method io/reactivex/rxjava3/internal/functions/Functions.emptyConsumer:()Lio/reactivex/rxjava3/functions/Consumer;
       5: invokevirtual #22                 // Method autoConnect:(ILio/reactivex/rxjava3/functions/Consumer;)Lio/reactivex/rxjava3/core/Flowable;
       8: areturn

  public io.reactivex.rxjava3.core.Flowable<T> autoConnect(int, io.reactivex.rxjava3.functions.Consumer<? super io.reactivex.rxjava3.disposables.Disposable>);
    Code:
       0: aload_2
       1: ldc           #23                 // String connection is null
       3: invokestatic  #16                 // Method java/util/Objects.requireNonNull:(Ljava/lang/Object;Ljava/lang/String;)Ljava/lang/Object;
       6: pop
       7: iload_1
       8: ifgt          21
      11: aload_0
      12: aload_2
      13: invokevirtual #4                  // Method connect:(Lio/reactivex/rxjava3/functions/Consumer;)V
      16: aload_0
      17: invokestatic  #24                 // Method io/reactivex/rxjava3/plugins/RxJavaPlugins.onAssembly:(Lio/reactivex/rxjava3/flowables/ConnectableFlowable;)Lio/reactivex/rxjava3/flowables/ConnectableFlowable;
      20: areturn
      21: new           #25                 // class io/reactivex/rxjava3/internal/operators/flowable/FlowableAutoConnect
      24: dup
      25: aload_0
      26: iload_1
      27: aload_2
      28: invokespecial #26                 // Method io/reactivex/rxjava3/internal/operators/flowable/FlowableAutoConnect."<init>":(Lio/reactivex/rxjava3/flowables/ConnectableFlowable;ILio/reactivex/rxjava3/functions/Consumer;)V
      31: invokestatic  #27                 // Method io/reactivex/rxjava3/plugins/RxJavaPlugins.onAssembly:(Lio/reactivex/rxjava3/core/Flowable;)Lio/reactivex/rxjava3/core/Flowable;
      34: areturn
}
