Compiled from "GroupedFlowable.java"
public abstract class io.reactivex.rxjava3.flowables.GroupedFlowable<K, T> extends io.reactivex.rxjava3.core.Flowable<T> {
  final K key;

  protected io.reactivex.rxjava3.flowables.GroupedFlowable(K);
    Code:
       0: aload_0
       1: invokespecial #1                  // Method io/reactivex/rxjava3/core/Flowable."<init>":()V
       4: aload_0
       5: aload_1
       6: putfield      #2                  // Field key:Ljava/lang/Object;
       9: return

  public K getKey();
    Code:
       0: aload_0
       1: getfield      #2                  // Field key:Ljava/lang/Object;
       4: areturn
}
