Compiled from "Functions.java"
final class io.reactivex.rxjava3.internal.functions.Functions$NaturalComparator extends java.lang.Enum<io.reactivex.rxjava3.internal.functions.Functions$NaturalComparator> implements java.util.Comparator<java.lang.Object> {
  public static final io.reactivex.rxjava3.internal.functions.Functions$NaturalComparator INSTANCE;

  private static final io.reactivex.rxjava3.internal.functions.Functions$NaturalComparator[] $VALUES;

  public static io.reactivex.rxjava3.internal.functions.Functions$NaturalComparator[] values();
    Code:
       0: getstatic     #1                  // Field $VALUES:[Lio/reactivex/rxjava3/internal/functions/Functions$NaturalComparator;
       3: invokevirtual #2                  // Method "[Lio/reactivex/rxjava3/internal/functions/Functions$NaturalComparator;".clone:()Ljava/lang/Object;
       6: checkcast     #3                  // class "[Lio/reactivex/rxjava3/internal/functions/Functions$NaturalComparator;"
       9: areturn

  public static io.reactivex.rxjava3.internal.functions.Functions$NaturalComparator valueOf(java.lang.String);
    Code:
       0: ldc           #4                  // class io/reactivex/rxjava3/internal/functions/Functions$NaturalComparator
       2: aload_0
       3: invokestatic  #5                  // Method java/lang/Enum.valueOf:(Ljava/lang/Class;Ljava/lang/String;)Ljava/lang/Enum;
       6: checkcast     #4                  // class io/reactivex/rxjava3/internal/functions/Functions$NaturalComparator
       9: areturn

  private io.reactivex.rxjava3.internal.functions.Functions$NaturalComparator();
    Code:
       0: aload_0
       1: aload_1
       2: iload_2
       3: invokespecial #6                  // Method java/lang/Enum."<init>":(Ljava/lang/String;I)V
       6: return

  public int compare(java.lang.Object, java.lang.Object);
    Code:
       0: aload_1
       1: checkcast     #7                  // class java/lang/Comparable
       4: aload_2
       5: invokeinterface #8,  2            // InterfaceMethod java/lang/Comparable.compareTo:(Ljava/lang/Object;)I
      10: ireturn

  static {};
    Code:
       0: new           #4                  // class io/reactivex/rxjava3/internal/functions/Functions$NaturalComparator
       3: dup
       4: ldc           #9                  // String INSTANCE
       6: iconst_0
       7: invokespecial #10                 // Method "<init>":(Ljava/lang/String;I)V
      10: putstatic     #11                 // Field INSTANCE:Lio/reactivex/rxjava3/internal/functions/Functions$NaturalComparator;
      13: iconst_1
      14: anewarray     #4                  // class io/reactivex/rxjava3/internal/functions/Functions$NaturalComparator
      17: dup
      18: iconst_0
      19: getstatic     #11                 // Field INSTANCE:Lio/reactivex/rxjava3/internal/functions/Functions$NaturalComparator;
      22: aastore
      23: putstatic     #1                  // Field $VALUES:[Lio/reactivex/rxjava3/internal/functions/Functions$NaturalComparator;
      26: return
}
