Compiled from "Functions.java"
final class io.reactivex.rxjava3.internal.functions.Functions$ListSorter<T> implements io.reactivex.rxjava3.functions.Function<java.util.List<T>, java.util.List<T>> {
  final java.util.Comparator<? super T> comparator;

  io.reactivex.rxjava3.internal.functions.Functions$ListSorter(java.util.Comparator<? super T>);
    Code:
       0: aload_0
       1: invokespecial #1                  // Method java/lang/Object."<init>":()V
       4: aload_0
       5: aload_1
       6: putfield      #2                  // Field comparator:Ljava/util/Comparator;
       9: return

  public java.util.List<T> apply(java.util.List<T>);
    Code:
       0: aload_1
       1: aload_0
       2: getfield      #2                  // Field comparator:Ljava/util/Comparator;
       5: invokestatic  #3                  // Method java/util/Collections.sort:(Ljava/util/List;Ljava/util/Comparator;)V
       8: aload_1
       9: areturn

  public java.lang.Object apply(java.lang.Object) throws java.lang.Throwable;
    Code:
       0: aload_0
       1: aload_1
       2: checkcast     #4                  // class java/util/List
       5: invokevirtual #5                  // Method apply:(Ljava/util/List;)Ljava/util/List;
       8: areturn
}
