Compiled from "Functions.java"
final class io.reactivex.rxjava3.internal.functions.Functions$BooleanSupplierPredicateReverse<T> implements io.reactivex.rxjava3.functions.Predicate<T> {
  final io.reactivex.rxjava3.functions.BooleanSupplier supplier;

  io.reactivex.rxjava3.internal.functions.Functions$BooleanSupplierPredicateReverse(io.reactivex.rxjava3.functions.BooleanSupplier);
    Code:
       0: aload_0
       1: invokespecial #1                  // Method java/lang/Object."<init>":()V
       4: aload_0
       5: aload_1
       6: putfield      #2                  // Field supplier:Lio/reactivex/rxjava3/functions/BooleanSupplier;
       9: return

  public boolean test(T) throws java.lang.Throwable;
    Code:
       0: aload_0
       1: getfield      #2                  // Field supplier:Lio/reactivex/rxjava3/functions/BooleanSupplier;
       4: invokeinterface #3,  1            // InterfaceMethod io/reactivex/rxjava3/functions/BooleanSupplier.getAsBoolean:()Z
       9: ifne          16
      12: iconst_1
      13: goto          17
      16: iconst_0
      17: ireturn
}
