Compiled from "Functions.java"
final class io.reactivex.rxjava3.internal.functions.Functions$TimestampFunction<T> implements io.reactivex.rxjava3.functions.Function<T, io.reactivex.rxjava3.schedulers.Timed<T>> {
  final java.util.concurrent.TimeUnit unit;

  final io.reactivex.rxjava3.core.Scheduler scheduler;

  io.reactivex.rxjava3.internal.functions.Functions$TimestampFunction(java.util.concurrent.TimeUnit, io.reactivex.rxjava3.core.Scheduler);
    Code:
       0: aload_0
       1: invokespecial #1                  // Method java/lang/Object."<init>":()V
       4: aload_0
       5: aload_1
       6: putfield      #2                  // Field unit:Ljava/util/concurrent/TimeUnit;
       9: aload_0
      10: aload_2
      11: putfield      #3                  // Field scheduler:Lio/reactivex/rxjava3/core/Scheduler;
      14: return

  public io.reactivex.rxjava3.schedulers.Timed<T> apply(T);
    Code:
       0: new           #4                  // class io/reactivex/rxjava3/schedulers/Timed
       3: dup
       4: aload_1
       5: aload_0
       6: getfield      #3                  // Field scheduler:Lio/reactivex/rxjava3/core/Scheduler;
       9: aload_0
      10: getfield      #2                  // Field unit:Ljava/util/concurrent/TimeUnit;
      13: invokevirtual #5                  // Method io/reactivex/rxjava3/core/Scheduler.now:(Ljava/util/concurrent/TimeUnit;)J
      16: aload_0
      17: getfield      #2                  // Field unit:Ljava/util/concurrent/TimeUnit;
      20: invokespecial #6                  // Method io/reactivex/rxjava3/schedulers/Timed."<init>":(Ljava/lang/Object;JLjava/util/concurrent/TimeUnit;)V
      23: areturn

  public java.lang.Object apply(java.lang.Object) throws java.lang.Throwable;
    Code:
       0: aload_0
       1: aload_1
       2: invokevirtual #7                  // Method apply:(Ljava/lang/Object;)Lio/reactivex/rxjava3/schedulers/Timed;
       5: areturn
}
