Compiled from "Functions.java"
final class io.reactivex.rxjava3.internal.functions.Functions$EqualsPredicate<T> implements io.reactivex.rxjava3.functions.Predicate<T> {
  final T value;

  io.reactivex.rxjava3.internal.functions.Functions$EqualsPredicate(T);
    Code:
       0: aload_0
       1: invokespecial #1                  // Method java/lang/Object."<init>":()V
       4: aload_0
       5: aload_1
       6: putfield      #2                  // Field value:Ljava/lang/Object;
       9: return

  public boolean test(T);
    Code:
       0: aload_1
       1: aload_0
       2: getfield      #2                  // Field value:Ljava/lang/Object;
       5: invokestatic  #3                  // Method java/util/Objects.equals:(Ljava/lang/Object;Ljava/lang/Object;)Z
       8: ireturn
}
