Compiled from "Functions.java"
final class io.reactivex.rxjava3.internal.functions.Functions$MaxRequestSubscription implements io.reactivex.rxjava3.functions.Consumer<org.reactivestreams.Subscription> {
  io.reactivex.rxjava3.internal.functions.Functions$MaxRequestSubscription();
    Code:
       0: aload_0
       1: invokespecial #1                  // Method java/lang/Object."<init>":()V
       4: return

  public void accept(org.reactivestreams.Subscription);
    Code:
       0: aload_1
       1: ldc2_w        #3                  // long 9223372036854775807l
       4: invokeinterface #5,  3            // InterfaceMethod org/reactivestreams/Subscription.request:(J)V
       9: return

  public void accept(java.lang.Object) throws java.lang.Throwable;
    Code:
       0: aload_0
       1: aload_1
       2: checkcast     #6                  // class org/reactivestreams/Subscription
       5: invokevirtual #7                  // Method accept:(Lorg/reactivestreams/Subscription;)V
       8: return
}
