Compiled from "Functions.java"
final class io.reactivex.rxjava3.internal.functions.Functions$JustValue<T, U> implements java.util.concurrent.Callable<U>, io.reactivex.rxjava3.functions.Supplier<U>, io.reactivex.rxjava3.functions.Function<T, U> {
  final U value;

  io.reactivex.rxjava3.internal.functions.Functions$JustValue(U);
    Code:
       0: aload_0
       1: invokespecial #1                  // Method java/lang/Object."<init>":()V
       4: aload_0
       5: aload_1
       6: putfield      #2                  // Field value:Ljava/lang/Object;
       9: return

  public U call();
    Code:
       0: aload_0
       1: getfield      #2                  // Field value:Ljava/lang/Object;
       4: areturn

  public U apply(T);
    Code:
       0: aload_0
       1: getfield      #2                  // Field value:Ljava/lang/Object;
       4: areturn

  public U get();
    Code:
       0: aload_0
       1: getfield      #2                  // Field value:Ljava/lang/Object;
       4: areturn
}
