Compiled from "Functions.java"
final class io.reactivex.rxjava3.internal.functions.Functions$ToMapKeyValueSelector<K, V, T> implements io.reactivex.rxjava3.functions.BiConsumer<java.util.Map<K, V>, T> {
  private final io.reactivex.rxjava3.functions.Function<? super T, ? extends V> valueSelector;

  private final io.reactivex.rxjava3.functions.Function<? super T, ? extends K> keySelector;

  io.reactivex.rxjava3.internal.functions.Functions$ToMapKeyValueSelector(io.reactivex.rxjava3.functions.Function<? super T, ? extends V>, io.reactivex.rxjava3.functions.Function<? super T, ? extends K>);
    Code:
       0: aload_0
       1: invokespecial #1                  // Method java/lang/Object."<init>":()V
       4: aload_0
       5: aload_1
       6: putfield      #2                  // Field valueSelector:Lio/reactivex/rxjava3/functions/Function;
       9: aload_0
      10: aload_2
      11: putfield      #3                  // Field keySelector:Lio/reactivex/rxjava3/functions/Function;
      14: return

  public void accept(java.util.Map<K, V>, T) throws java.lang.Throwable;
    Code:
       0: aload_0
       1: getfield      #3                  // Field keySelector:Lio/reactivex/rxjava3/functions/Function;
       4: aload_2
       5: invokeinterface #4,  2            // InterfaceMethod io/reactivex/rxjava3/functions/Function.apply:(Ljava/lang/Object;)Ljava/lang/Object;
      10: astore_3
      11: aload_0
      12: getfield      #2                  // Field valueSelector:Lio/reactivex/rxjava3/functions/Function;
      15: aload_2
      16: invokeinterface #4,  2            // InterfaceMethod io/reactivex/rxjava3/functions/Function.apply:(Ljava/lang/Object;)Ljava/lang/Object;
      21: astore        4
      23: aload_1
      24: aload_3
      25: aload         4
      27: invokeinterface #5,  3            // InterfaceMethod java/util/Map.put:(Ljava/lang/Object;Ljava/lang/Object;)Ljava/lang/Object;
      32: pop
      33: return

  public void accept(java.lang.Object, java.lang.Object) throws java.lang.Throwable;
    Code:
       0: aload_0
       1: aload_1
       2: checkcast     #6                  // class java/util/Map
       5: aload_2
       6: invokevirtual #7                  // Method accept:(Ljava/util/Map;Ljava/lang/Object;)V
       9: return
}
