Compiled from "Functions.java"
final class io.reactivex.rxjava3.internal.functions.Functions$NotificationOnNext<T> implements io.reactivex.rxjava3.functions.Consumer<T> {
  final io.reactivex.rxjava3.functions.Consumer<? super io.reactivex.rxjava3.core.Notification<T>> onNotification;

  io.reactivex.rxjava3.internal.functions.Functions$NotificationOnNext(io.reactivex.rxjava3.functions.Consumer<? super io.reactivex.rxjava3.core.Notification<T>>);
    Code:
       0: aload_0
       1: invokespecial #1                  // Method java/lang/Object."<init>":()V
       4: aload_0
       5: aload_1
       6: putfield      #2                  // Field onNotification:Lio/reactivex/rxjava3/functions/Consumer;
       9: return

  public void accept(T) throws java.lang.Throwable;
    Code:
       0: aload_0
       1: getfield      #2                  // Field onNotification:Lio/reactivex/rxjava3/functions/Consumer;
       4: aload_1
       5: invokestatic  #3                  // Method io/reactivex/rxjava3/core/Notification.createOnNext:(Ljava/lang/Object;)Lio/reactivex/rxjava3/core/Notification;
       8: invokeinterface #4,  2            // InterfaceMethod io/reactivex/rxjava3/functions/Consumer.accept:(Ljava/lang/Object;)V
      13: return
}
