Compiled from "Functions.java"
public class io.reactivex.rxjava3.internal.functions.Functions$BoundedConsumer implements io.reactivex.rxjava3.functions.Consumer<org.reactivestreams.Subscription> {
  final int bufferSize;

  io.reactivex.rxjava3.internal.functions.Functions$BoundedConsumer(int);
    Code:
       0: aload_0
       1: invokespecial #1                  // Method java/lang/Object."<init>":()V
       4: aload_0
       5: iload_1
       6: putfield      #2                  // Field bufferSize:I
       9: return

  public void accept(org.reactivestreams.Subscription);
    Code:
       0: aload_1
       1: aload_0
       2: getfield      #2                  // Field bufferSize:I
       5: i2l
       6: invokeinterface #3,  3            // InterfaceMethod org/reactivestreams/Subscription.request:(J)V
      11: return

  public void accept(java.lang.Object) throws java.lang.Throwable;
    Code:
       0: aload_0
       1: aload_1
       2: checkcast     #4                  // class org/reactivestreams/Subscription
       5: invokevirtual #5                  // Method accept:(Lorg/reactivestreams/Subscription;)V
       8: return
}
