Compiled from "Functions.java"
final class io.reactivex.rxjava3.internal.functions.Functions$ArrayListCapacityCallable<T> implements io.reactivex.rxjava3.functions.Supplier<java.util.List<T>> {
  final int capacity;

  io.reactivex.rxjava3.internal.functions.Functions$ArrayListCapacityCallable(int);
    Code:
       0: aload_0
       1: invokespecial #1                  // Method java/lang/Object."<init>":()V
       4: aload_0
       5: iload_1
       6: putfield      #2                  // Field capacity:I
       9: return

  public java.util.List<T> get();
    Code:
       0: new           #3                  // class java/util/ArrayList
       3: dup
       4: aload_0
       5: getfield      #2                  // Field capacity:I
       8: invokespecial #4                  // Method java/util/ArrayList."<init>":(I)V
      11: areturn

  public java.lang.Object get() throws java.lang.Throwable;
    Code:
       0: aload_0
       1: invokevirtual #5                  // Method get:()Ljava/util/List;
       4: areturn
}
