Compiled from "Functions.java"
final class io.reactivex.rxjava3.internal.functions.Functions$CastToClass<T, U> implements io.reactivex.rxjava3.functions.Function<T, U> {
  final java.lang.Class<U> clazz;

  io.reactivex.rxjava3.internal.functions.Functions$CastToClass(java.lang.Class<U>);
    Code:
       0: aload_0
       1: invokespecial #1                  // Method java/lang/Object."<init>":()V
       4: aload_0
       5: aload_1
       6: putfield      #2                  // Field clazz:Ljava/lang/Class;
       9: return

  public U apply(T);
    Code:
       0: aload_0
       1: getfield      #2                  // Field clazz:Ljava/lang/Class;
       4: aload_1
       5: invokevirtual #3                  // Method java/lang/Class.cast:(Ljava/lang/Object;)Ljava/lang/Object;
       8: areturn
}
