Compiled from "Functions.java"
final class io.reactivex.rxjava3.internal.functions.Functions$ToMultimapKeyValueSelector<K, V, T> implements io.reactivex.rxjava3.functions.BiConsumer<java.util.Map<K, java.util.Collection<V>>, T> {
  private final io.reactivex.rxjava3.functions.Function<? super K, ? extends java.util.Collection<? super V>> collectionFactory;

  private final io.reactivex.rxjava3.functions.Function<? super T, ? extends V> valueSelector;

  private final io.reactivex.rxjava3.functions.Function<? super T, ? extends K> keySelector;

  io.reactivex.rxjava3.internal.functions.Functions$ToMultimapKeyValueSelector(io.reactivex.rxjava3.functions.Function<? super K, ? extends java.util.Collection<? super V>>, io.reactivex.rxjava3.functions.Function<? super T, ? extends V>, io.reactivex.rxjava3.functions.Function<? super T, ? extends K>);
    Code:
       0: aload_0
       1: invokespecial #1                  // Method java/lang/Object."<init>":()V
       4: aload_0
       5: aload_1
       6: putfield      #2                  // Field collectionFactory:Lio/reactivex/rxjava3/functions/Function;
       9: aload_0
      10: aload_2
      11: putfield      #3                  // Field valueSelector:Lio/reactivex/rxjava3/functions/Function;
      14: aload_0
      15: aload_3
      16: putfield      #4                  // Field keySelector:Lio/reactivex/rxjava3/functions/Function;
      19: return

  public void accept(java.util.Map<K, java.util.Collection<V>>, T) throws java.lang.Throwable;
    Code:
       0: aload_0
       1: getfield      #4                  // Field keySelector:Lio/reactivex/rxjava3/functions/Function;
       4: aload_2
       5: invokeinterface #5,  2            // InterfaceMethod io/reactivex/rxjava3/functions/Function.apply:(Ljava/lang/Object;)Ljava/lang/Object;
      10: astore_3
      11: aload_1
      12: aload_3
      13: invokeinterface #6,  2            // InterfaceMethod java/util/Map.get:(Ljava/lang/Object;)Ljava/lang/Object;
      18: checkcast     #7                  // class java/util/Collection
      21: astore        4
      23: aload         4
      25: ifnonnull     53
      28: aload_0
      29: getfield      #2                  // Field collectionFactory:Lio/reactivex/rxjava3/functions/Function;
      32: aload_3
      33: invokeinterface #5,  2            // InterfaceMethod io/reactivex/rxjava3/functions/Function.apply:(Ljava/lang/Object;)Ljava/lang/Object;
      38: checkcast     #7                  // class java/util/Collection
      41: astore        4
      43: aload_1
      44: aload_3
      45: aload         4
      47: invokeinterface #8,  3            // InterfaceMethod java/util/Map.put:(Ljava/lang/Object;Ljava/lang/Object;)Ljava/lang/Object;
      52: pop
      53: aload_0
      54: getfield      #3                  // Field valueSelector:Lio/reactivex/rxjava3/functions/Function;
      57: aload_2
      58: invokeinterface #5,  2            // InterfaceMethod io/reactivex/rxjava3/functions/Function.apply:(Ljava/lang/Object;)Ljava/lang/Object;
      63: astore        5
      65: aload         4
      67: aload         5
      69: invokeinterface #9,  2            // InterfaceMethod java/util/Collection.add:(Ljava/lang/Object;)Z
      74: pop
      75: return

  public void accept(java.lang.Object, java.lang.Object) throws java.lang.Throwable;
    Code:
       0: aload_0
       1: aload_1
       2: checkcast     #10                 // class java/util/Map
       5: aload_2
       6: invokevirtual #11                 // Method accept:(Ljava/util/Map;Ljava/lang/Object;)V
       9: return
}
