Compiled from "Functions.java"
final class io.reactivex.rxjava3.internal.functions.Functions$ActionConsumer<T> implements io.reactivex.rxjava3.functions.Consumer<T> {
  final io.reactivex.rxjava3.functions.Action action;

  io.reactivex.rxjava3.internal.functions.Functions$ActionConsumer(io.reactivex.rxjava3.functions.Action);
    Code:
       0: aload_0
       1: invokespecial #1                  // Method java/lang/Object."<init>":()V
       4: aload_0
       5: aload_1
       6: putfield      #2                  // Field action:Lio/reactivex/rxjava3/functions/Action;
       9: return

  public void accept(T) throws java.lang.Throwable;
    Code:
       0: aload_0
       1: getfield      #2                  // Field action:Lio/reactivex/rxjava3/functions/Action;
       4: invokeinterface #3,  1            // InterfaceMethod io/reactivex/rxjava3/functions/Action.run:()V
       9: return
}
