Compiled from "Functions.java"
final class io.reactivex.rxjava3.internal.functions.Functions$OnErrorMissingConsumer implements io.reactivex.rxjava3.functions.Consumer<java.lang.Throwable> {
  io.reactivex.rxjava3.internal.functions.Functions$OnErrorMissingConsumer();
    Code:
       0: aload_0
       1: invokespecial #1                  // Method java/lang/Object."<init>":()V
       4: return

  public void accept(java.lang.Throwable);
    Code:
       0: new           #2                  // class io/reactivex/rxjava3/exceptions/OnErrorNotImplementedException
       3: dup
       4: aload_1
       5: invokespecial #3                  // Method io/reactivex/rxjava3/exceptions/OnErrorNotImplementedException."<init>":(Ljava/lang/Throwable;)V
       8: invokestatic  #4                  // Method io/reactivex/rxjava3/plugins/RxJavaPlugins.onError:(Ljava/lang/Throwable;)V
      11: return

  public void accept(java.lang.Object) throws java.lang.Throwable;
    Code:
       0: aload_0
       1: aload_1
       2: checkcast     #5                  // class java/lang/Throwable
       5: invokevirtual #6                  // Method accept:(Ljava/lang/Throwable;)V
       8: return
}
