Compiled from "Functions.java"
final class io.reactivex.rxjava3.internal.functions.Functions$FutureAction implements io.reactivex.rxjava3.functions.Action {
  final java.util.concurrent.Future<?> future;

  io.reactivex.rxjava3.internal.functions.Functions$FutureAction(java.util.concurrent.Future<?>);
    Code:
       0: aload_0
       1: invokespecial #1                  // Method java/lang/Object."<init>":()V
       4: aload_0
       5: aload_1
       6: putfield      #2                  // Field future:Ljava/util/concurrent/Future;
       9: return

  public void run() throws java.lang.Exception;
    Code:
       0: aload_0
       1: getfield      #2                  // Field future:Ljava/util/concurrent/Future;
       4: invokeinterface #3,  1            // InterfaceMethod java/util/concurrent/Future.get:()Ljava/lang/Object;
       9: pop
      10: return
}
