Compiled from "Functions.java"
public final class io.reactivex.rxjava3.internal.functions.Functions {
  static final io.reactivex.rxjava3.functions.Function<java.lang.Object, java.lang.Object> IDENTITY;

  public static final java.lang.Runnable EMPTY_RUNNABLE;

  public static final io.reactivex.rxjava3.functions.Action EMPTY_ACTION;

  static final io.reactivex.rxjava3.functions.Consumer<java.lang.Object> EMPTY_CONSUMER;

  public static final io.reactivex.rxjava3.functions.Consumer<java.lang.Throwable> ERROR_CONSUMER;

  public static final io.reactivex.rxjava3.functions.Consumer<java.lang.Throwable> ON_ERROR_MISSING;

  public static final io.reactivex.rxjava3.functions.LongConsumer EMPTY_LONG_CONSUMER;

  static final io.reactivex.rxjava3.functions.Predicate<java.lang.Object> ALWAYS_TRUE;

  static final io.reactivex.rxjava3.functions.Predicate<java.lang.Object> ALWAYS_FALSE;

  static final io.reactivex.rxjava3.functions.Supplier<java.lang.Object> NULL_SUPPLIER;

  public static final io.reactivex.rxjava3.functions.Consumer<org.reactivestreams.Subscription> REQUEST_MAX;

  private io.reactivex.rxjava3.internal.functions.Functions();
    Code:
       0: aload_0
       1: invokespecial #1                  // Method java/lang/Object."<init>":()V
       4: new           #2                  // class java/lang/IllegalStateException
       7: dup
       8: ldc           #3                  // String No instances!
      10: invokespecial #4                  // Method java/lang/IllegalStateException."<init>":(Ljava/lang/String;)V
      13: athrow

  public static <T1, T2, R> io.reactivex.rxjava3.functions.Function<java.lang.Object[], R> toFunction(io.reactivex.rxjava3.functions.BiFunction<? super T1, ? super T2, ? extends R>);
    Code:
       0: new           #5                  // class io/reactivex/rxjava3/internal/functions/Functions$Array2Func
       3: dup
       4: aload_0
       5: invokespecial #6                  // Method io/reactivex/rxjava3/internal/functions/Functions$Array2Func."<init>":(Lio/reactivex/rxjava3/functions/BiFunction;)V
       8: areturn

  public static <T1, T2, T3, R> io.reactivex.rxjava3.functions.Function<java.lang.Object[], R> toFunction(io.reactivex.rxjava3.functions.Function3<T1, T2, T3, R>);
    Code:
       0: new           #7                  // class io/reactivex/rxjava3/internal/functions/Functions$Array3Func
       3: dup
       4: aload_0
       5: invokespecial #8                  // Method io/reactivex/rxjava3/internal/functions/Functions$Array3Func."<init>":(Lio/reactivex/rxjava3/functions/Function3;)V
       8: areturn

  public static <T1, T2, T3, T4, R> io.reactivex.rxjava3.functions.Function<java.lang.Object[], R> toFunction(io.reactivex.rxjava3.functions.Function4<T1, T2, T3, T4, R>);
    Code:
       0: new           #9                  // class io/reactivex/rxjava3/internal/functions/Functions$Array4Func
       3: dup
       4: aload_0
       5: invokespecial #10                 // Method io/reactivex/rxjava3/internal/functions/Functions$Array4Func."<init>":(Lio/reactivex/rxjava3/functions/Function4;)V
       8: areturn

  public static <T1, T2, T3, T4, T5, R> io.reactivex.rxjava3.functions.Function<java.lang.Object[], R> toFunction(io.reactivex.rxjava3.functions.Function5<T1, T2, T3, T4, T5, R>);
    Code:
       0: new           #11                 // class io/reactivex/rxjava3/internal/functions/Functions$Array5Func
       3: dup
       4: aload_0
       5: invokespecial #12                 // Method io/reactivex/rxjava3/internal/functions/Functions$Array5Func."<init>":(Lio/reactivex/rxjava3/functions/Function5;)V
       8: areturn

  public static <T1, T2, T3, T4, T5, T6, R> io.reactivex.rxjava3.functions.Function<java.lang.Object[], R> toFunction(io.reactivex.rxjava3.functions.Function6<T1, T2, T3, T4, T5, T6, R>);
    Code:
       0: new           #13                 // class io/reactivex/rxjava3/internal/functions/Functions$Array6Func
       3: dup
       4: aload_0
       5: invokespecial #14                 // Method io/reactivex/rxjava3/internal/functions/Functions$Array6Func."<init>":(Lio/reactivex/rxjava3/functions/Function6;)V
       8: areturn

  public static <T1, T2, T3, T4, T5, T6, T7, R> io.reactivex.rxjava3.functions.Function<java.lang.Object[], R> toFunction(io.reactivex.rxjava3.functions.Function7<T1, T2, T3, T4, T5, T6, T7, R>);
    Code:
       0: new           #15                 // class io/reactivex/rxjava3/internal/functions/Functions$Array7Func
       3: dup
       4: aload_0
       5: invokespecial #16                 // Method io/reactivex/rxjava3/internal/functions/Functions$Array7Func."<init>":(Lio/reactivex/rxjava3/functions/Function7;)V
       8: areturn

  public static <T1, T2, T3, T4, T5, T6, T7, T8, R> io.reactivex.rxjava3.functions.Function<java.lang.Object[], R> toFunction(io.reactivex.rxjava3.functions.Function8<T1, T2, T3, T4, T5, T6, T7, T8, R>);
    Code:
       0: new           #17                 // class io/reactivex/rxjava3/internal/functions/Functions$Array8Func
       3: dup
       4: aload_0
       5: invokespecial #18                 // Method io/reactivex/rxjava3/internal/functions/Functions$Array8Func."<init>":(Lio/reactivex/rxjava3/functions/Function8;)V
       8: areturn

  public static <T1, T2, T3, T4, T5, T6, T7, T8, T9, R> io.reactivex.rxjava3.functions.Function<java.lang.Object[], R> toFunction(io.reactivex.rxjava3.functions.Function9<T1, T2, T3, T4, T5, T6, T7, T8, T9, R>);
    Code:
       0: new           #19                 // class io/reactivex/rxjava3/internal/functions/Functions$Array9Func
       3: dup
       4: aload_0
       5: invokespecial #20                 // Method io/reactivex/rxjava3/internal/functions/Functions$Array9Func."<init>":(Lio/reactivex/rxjava3/functions/Function9;)V
       8: areturn

  public static <T> io.reactivex.rxjava3.functions.Function<T, T> identity();
    Code:
       0: getstatic     #21                 // Field IDENTITY:Lio/reactivex/rxjava3/functions/Function;
       3: areturn

  public static <T> io.reactivex.rxjava3.functions.Consumer<T> emptyConsumer();
    Code:
       0: getstatic     #22                 // Field EMPTY_CONSUMER:Lio/reactivex/rxjava3/functions/Consumer;
       3: areturn

  public static <T> io.reactivex.rxjava3.functions.Predicate<T> alwaysTrue();
    Code:
       0: getstatic     #23                 // Field ALWAYS_TRUE:Lio/reactivex/rxjava3/functions/Predicate;
       3: areturn

  public static <T> io.reactivex.rxjava3.functions.Predicate<T> alwaysFalse();
    Code:
       0: getstatic     #24                 // Field ALWAYS_FALSE:Lio/reactivex/rxjava3/functions/Predicate;
       3: areturn

  public static <T> io.reactivex.rxjava3.functions.Supplier<T> nullSupplier();
    Code:
       0: getstatic     #25                 // Field NULL_SUPPLIER:Lio/reactivex/rxjava3/functions/Supplier;
       3: areturn

  public static io.reactivex.rxjava3.functions.Action futureAction(java.util.concurrent.Future<?>);
    Code:
       0: new           #26                 // class io/reactivex/rxjava3/internal/functions/Functions$FutureAction
       3: dup
       4: aload_0
       5: invokespecial #27                 // Method io/reactivex/rxjava3/internal/functions/Functions$FutureAction."<init>":(Ljava/util/concurrent/Future;)V
       8: areturn

  public static <T> java.util.concurrent.Callable<T> justCallable(T);
    Code:
       0: new           #28                 // class io/reactivex/rxjava3/internal/functions/Functions$JustValue
       3: dup
       4: aload_0
       5: invokespecial #29                 // Method io/reactivex/rxjava3/internal/functions/Functions$JustValue."<init>":(Ljava/lang/Object;)V
       8: areturn

  public static <T> io.reactivex.rxjava3.functions.Supplier<T> justSupplier(T);
    Code:
       0: new           #28                 // class io/reactivex/rxjava3/internal/functions/Functions$JustValue
       3: dup
       4: aload_0
       5: invokespecial #29                 // Method io/reactivex/rxjava3/internal/functions/Functions$JustValue."<init>":(Ljava/lang/Object;)V
       8: areturn

  public static <T, U> io.reactivex.rxjava3.functions.Function<T, U> justFunction(U);
    Code:
       0: new           #28                 // class io/reactivex/rxjava3/internal/functions/Functions$JustValue
       3: dup
       4: aload_0
       5: invokespecial #29                 // Method io/reactivex/rxjava3/internal/functions/Functions$JustValue."<init>":(Ljava/lang/Object;)V
       8: areturn

  public static <T, U> io.reactivex.rxjava3.functions.Function<T, U> castFunction(java.lang.Class<U>);
    Code:
       0: new           #30                 // class io/reactivex/rxjava3/internal/functions/Functions$CastToClass
       3: dup
       4: aload_0
       5: invokespecial #31                 // Method io/reactivex/rxjava3/internal/functions/Functions$CastToClass."<init>":(Ljava/lang/Class;)V
       8: areturn

  public static <T> io.reactivex.rxjava3.functions.Supplier<java.util.List<T>> createArrayList(int);
    Code:
       0: new           #32                 // class io/reactivex/rxjava3/internal/functions/Functions$ArrayListCapacityCallable
       3: dup
       4: iload_0
       5: invokespecial #33                 // Method io/reactivex/rxjava3/internal/functions/Functions$ArrayListCapacityCallable."<init>":(I)V
       8: areturn

  public static <T> io.reactivex.rxjava3.functions.Predicate<T> equalsWith(T);
    Code:
       0: new           #34                 // class io/reactivex/rxjava3/internal/functions/Functions$EqualsPredicate
       3: dup
       4: aload_0
       5: invokespecial #35                 // Method io/reactivex/rxjava3/internal/functions/Functions$EqualsPredicate."<init>":(Ljava/lang/Object;)V
       8: areturn

  public static <T> io.reactivex.rxjava3.functions.Supplier<java.util.Set<T>> createHashSet();
    Code:
       0: getstatic     #36                 // Field io/reactivex/rxjava3/internal/functions/Functions$HashSetSupplier.INSTANCE:Lio/reactivex/rxjava3/internal/functions/Functions$HashSetSupplier;
       3: areturn

  public static <T> io.reactivex.rxjava3.functions.Consumer<T> notificationOnNext(io.reactivex.rxjava3.functions.Consumer<? super io.reactivex.rxjava3.core.Notification<T>>);
    Code:
       0: new           #37                 // class io/reactivex/rxjava3/internal/functions/Functions$NotificationOnNext
       3: dup
       4: aload_0
       5: invokespecial #38                 // Method io/reactivex/rxjava3/internal/functions/Functions$NotificationOnNext."<init>":(Lio/reactivex/rxjava3/functions/Consumer;)V
       8: areturn

  public static <T> io.reactivex.rxjava3.functions.Consumer<java.lang.Throwable> notificationOnError(io.reactivex.rxjava3.functions.Consumer<? super io.reactivex.rxjava3.core.Notification<T>>);
    Code:
       0: new           #39                 // class io/reactivex/rxjava3/internal/functions/Functions$NotificationOnError
       3: dup
       4: aload_0
       5: invokespecial #40                 // Method io/reactivex/rxjava3/internal/functions/Functions$NotificationOnError."<init>":(Lio/reactivex/rxjava3/functions/Consumer;)V
       8: areturn

  public static <T> io.reactivex.rxjava3.functions.Action notificationOnComplete(io.reactivex.rxjava3.functions.Consumer<? super io.reactivex.rxjava3.core.Notification<T>>);
    Code:
       0: new           #41                 // class io/reactivex/rxjava3/internal/functions/Functions$NotificationOnComplete
       3: dup
       4: aload_0
       5: invokespecial #42                 // Method io/reactivex/rxjava3/internal/functions/Functions$NotificationOnComplete."<init>":(Lio/reactivex/rxjava3/functions/Consumer;)V
       8: areturn

  public static <T> io.reactivex.rxjava3.functions.Consumer<T> actionConsumer(io.reactivex.rxjava3.functions.Action);
    Code:
       0: new           #43                 // class io/reactivex/rxjava3/internal/functions/Functions$ActionConsumer
       3: dup
       4: aload_0
       5: invokespecial #44                 // Method io/reactivex/rxjava3/internal/functions/Functions$ActionConsumer."<init>":(Lio/reactivex/rxjava3/functions/Action;)V
       8: areturn

  public static <T, U> io.reactivex.rxjava3.functions.Predicate<T> isInstanceOf(java.lang.Class<U>);
    Code:
       0: new           #45                 // class io/reactivex/rxjava3/internal/functions/Functions$ClassFilter
       3: dup
       4: aload_0
       5: invokespecial #46                 // Method io/reactivex/rxjava3/internal/functions/Functions$ClassFilter."<init>":(Ljava/lang/Class;)V
       8: areturn

  public static <T> io.reactivex.rxjava3.functions.Predicate<T> predicateReverseFor(io.reactivex.rxjava3.functions.BooleanSupplier);
    Code:
       0: new           #47                 // class io/reactivex/rxjava3/internal/functions/Functions$BooleanSupplierPredicateReverse
       3: dup
       4: aload_0
       5: invokespecial #48                 // Method io/reactivex/rxjava3/internal/functions/Functions$BooleanSupplierPredicateReverse."<init>":(Lio/reactivex/rxjava3/functions/BooleanSupplier;)V
       8: areturn

  public static <T> io.reactivex.rxjava3.functions.Function<T, io.reactivex.rxjava3.schedulers.Timed<T>> timestampWith(java.util.concurrent.TimeUnit, io.reactivex.rxjava3.core.Scheduler);
    Code:
       0: new           #49                 // class io/reactivex/rxjava3/internal/functions/Functions$TimestampFunction
       3: dup
       4: aload_0
       5: aload_1
       6: invokespecial #50                 // Method io/reactivex/rxjava3/internal/functions/Functions$TimestampFunction."<init>":(Ljava/util/concurrent/TimeUnit;Lio/reactivex/rxjava3/core/Scheduler;)V
       9: areturn

  public static <T, K> io.reactivex.rxjava3.functions.BiConsumer<java.util.Map<K, T>, T> toMapKeySelector(io.reactivex.rxjava3.functions.Function<? super T, ? extends K>);
    Code:
       0: new           #51                 // class io/reactivex/rxjava3/internal/functions/Functions$ToMapKeySelector
       3: dup
       4: aload_0
       5: invokespecial #52                 // Method io/reactivex/rxjava3/internal/functions/Functions$ToMapKeySelector."<init>":(Lio/reactivex/rxjava3/functions/Function;)V
       8: areturn

  public static <T, K, V> io.reactivex.rxjava3.functions.BiConsumer<java.util.Map<K, V>, T> toMapKeyValueSelector(io.reactivex.rxjava3.functions.Function<? super T, ? extends K>, io.reactivex.rxjava3.functions.Function<? super T, ? extends V>);
    Code:
       0: new           #53                 // class io/reactivex/rxjava3/internal/functions/Functions$ToMapKeyValueSelector
       3: dup
       4: aload_1
       5: aload_0
       6: invokespecial #54                 // Method io/reactivex/rxjava3/internal/functions/Functions$ToMapKeyValueSelector."<init>":(Lio/reactivex/rxjava3/functions/Function;Lio/reactivex/rxjava3/functions/Function;)V
       9: areturn

  public static <T, K, V> io.reactivex.rxjava3.functions.BiConsumer<java.util.Map<K, java.util.Collection<V>>, T> toMultimapKeyValueSelector(io.reactivex.rxjava3.functions.Function<? super T, ? extends K>, io.reactivex.rxjava3.functions.Function<? super T, ? extends V>, io.reactivex.rxjava3.functions.Function<? super K, ? extends java.util.Collection<? super V>>);
    Code:
       0: new           #55                 // class io/reactivex/rxjava3/internal/functions/Functions$ToMultimapKeyValueSelector
       3: dup
       4: aload_2
       5: aload_1
       6: aload_0
       7: invokespecial #56                 // Method io/reactivex/rxjava3/internal/functions/Functions$ToMultimapKeyValueSelector."<init>":(Lio/reactivex/rxjava3/functions/Function;Lio/reactivex/rxjava3/functions/Function;Lio/reactivex/rxjava3/functions/Function;)V
      10: areturn

  public static <T> java.util.Comparator<T> naturalComparator();
    Code:
       0: getstatic     #57                 // Field io/reactivex/rxjava3/internal/functions/Functions$NaturalComparator.INSTANCE:Lio/reactivex/rxjava3/internal/functions/Functions$NaturalComparator;
       3: areturn

  public static <T> io.reactivex.rxjava3.functions.Function<java.util.List<T>, java.util.List<T>> listSorter(java.util.Comparator<? super T>);
    Code:
       0: new           #58                 // class io/reactivex/rxjava3/internal/functions/Functions$ListSorter
       3: dup
       4: aload_0
       5: invokespecial #59                 // Method io/reactivex/rxjava3/internal/functions/Functions$ListSorter."<init>":(Ljava/util/Comparator;)V
       8: areturn

  public static <T> io.reactivex.rxjava3.functions.Consumer<T> boundedConsumer(int);
    Code:
       0: new           #60                 // class io/reactivex/rxjava3/internal/functions/Functions$BoundedConsumer
       3: dup
       4: iload_0
       5: invokespecial #61                 // Method io/reactivex/rxjava3/internal/functions/Functions$BoundedConsumer."<init>":(I)V
       8: areturn

  static {};
    Code:
       0: new           #62                 // class io/reactivex/rxjava3/internal/functions/Functions$Identity
       3: dup
       4: invokespecial #63                 // Method io/reactivex/rxjava3/internal/functions/Functions$Identity."<init>":()V
       7: putstatic     #21                 // Field IDENTITY:Lio/reactivex/rxjava3/functions/Function;
      10: new           #64                 // class io/reactivex/rxjava3/internal/functions/Functions$EmptyRunnable
      13: dup
      14: invokespecial #65                 // Method io/reactivex/rxjava3/internal/functions/Functions$EmptyRunnable."<init>":()V
      17: putstatic     #66                 // Field EMPTY_RUNNABLE:Ljava/lang/Runnable;
      20: new           #67                 // class io/reactivex/rxjava3/internal/functions/Functions$EmptyAction
      23: dup
      24: invokespecial #68                 // Method io/reactivex/rxjava3/internal/functions/Functions$EmptyAction."<init>":()V
      27: putstatic     #69                 // Field EMPTY_ACTION:Lio/reactivex/rxjava3/functions/Action;
      30: new           #70                 // class io/reactivex/rxjava3/internal/functions/Functions$EmptyConsumer
      33: dup
      34: invokespecial #71                 // Method io/reactivex/rxjava3/internal/functions/Functions$EmptyConsumer."<init>":()V
      37: putstatic     #22                 // Field EMPTY_CONSUMER:Lio/reactivex/rxjava3/functions/Consumer;
      40: new           #72                 // class io/reactivex/rxjava3/internal/functions/Functions$ErrorConsumer
      43: dup
      44: invokespecial #73                 // Method io/reactivex/rxjava3/internal/functions/Functions$ErrorConsumer."<init>":()V
      47: putstatic     #74                 // Field ERROR_CONSUMER:Lio/reactivex/rxjava3/functions/Consumer;
      50: new           #75                 // class io/reactivex/rxjava3/internal/functions/Functions$OnErrorMissingConsumer
      53: dup
      54: invokespecial #76                 // Method io/reactivex/rxjava3/internal/functions/Functions$OnErrorMissingConsumer."<init>":()V
      57: putstatic     #77                 // Field ON_ERROR_MISSING:Lio/reactivex/rxjava3/functions/Consumer;
      60: new           #78                 // class io/reactivex/rxjava3/internal/functions/Functions$EmptyLongConsumer
      63: dup
      64: invokespecial #79                 // Method io/reactivex/rxjava3/internal/functions/Functions$EmptyLongConsumer."<init>":()V
      67: putstatic     #80                 // Field EMPTY_LONG_CONSUMER:Lio/reactivex/rxjava3/functions/LongConsumer;
      70: new           #81                 // class io/reactivex/rxjava3/internal/functions/Functions$TruePredicate
      73: dup
      74: invokespecial #82                 // Method io/reactivex/rxjava3/internal/functions/Functions$TruePredicate."<init>":()V
      77: putstatic     #23                 // Field ALWAYS_TRUE:Lio/reactivex/rxjava3/functions/Predicate;
      80: new           #83                 // class io/reactivex/rxjava3/internal/functions/Functions$FalsePredicate
      83: dup
      84: invokespecial #84                 // Method io/reactivex/rxjava3/internal/functions/Functions$FalsePredicate."<init>":()V
      87: putstatic     #24                 // Field ALWAYS_FALSE:Lio/reactivex/rxjava3/functions/Predicate;
      90: new           #85                 // class io/reactivex/rxjava3/internal/functions/Functions$NullProvider
      93: dup
      94: invokespecial #86                 // Method io/reactivex/rxjava3/internal/functions/Functions$NullProvider."<init>":()V
      97: putstatic     #25                 // Field NULL_SUPPLIER:Lio/reactivex/rxjava3/functions/Supplier;
     100: new           #87                 // class io/reactivex/rxjava3/internal/functions/Functions$MaxRequestSubscription
     103: dup
     104: invokespecial #88                 // Method io/reactivex/rxjava3/internal/functions/Functions$MaxRequestSubscription."<init>":()V
     107: putstatic     #89                 // Field REQUEST_MAX:Lio/reactivex/rxjava3/functions/Consumer;
     110: return
}
