Compiled from "ObjectHelper.java"
public final class io.reactivex.rxjava3.internal.functions.ObjectHelper {
  static final io.reactivex.rxjava3.functions.BiPredicate<java.lang.Object, java.lang.Object> EQUALS;

  private io.reactivex.rxjava3.internal.functions.ObjectHelper();
    Code:
       0: aload_0
       1: invokespecial #1                  // Method java/lang/Object."<init>":()V
       4: new           #2                  // class java/lang/IllegalStateException
       7: dup
       8: ldc           #3                  // String No instances!
      10: invokespecial #4                  // Method java/lang/IllegalStateException."<init>":(Ljava/lang/String;)V
      13: athrow

  public static <T> io.reactivex.rxjava3.functions.BiPredicate<T, T> equalsPredicate();
    Code:
       0: getstatic     #5                  // Field EQUALS:Lio/reactivex/rxjava3/functions/BiPredicate;
       3: areturn

  public static int verifyPositive(int, java.lang.String);
    Code:
       0: iload_0
       1: ifgt          35
       4: new           #6                  // class java/lang/IllegalArgumentException
       7: dup
       8: new           #7                  // class java/lang/StringBuilder
      11: dup
      12: invokespecial #8                  // Method java/lang/StringBuilder."<init>":()V
      15: aload_1
      16: invokevirtual #9                  // Method java/lang/StringBuilder.append:(Ljava/lang/String;)Ljava/lang/StringBuilder;
      19: ldc           #10                 // String  > 0 required but it was
      21: invokevirtual #9                  // Method java/lang/StringBuilder.append:(Ljava/lang/String;)Ljava/lang/StringBuilder;
      24: iload_0
      25: invokevirtual #11                 // Method java/lang/StringBuilder.append:(I)Ljava/lang/StringBuilder;
      28: invokevirtual #12                 // Method java/lang/StringBuilder.toString:()Ljava/lang/String;
      31: invokespecial #13                 // Method java/lang/IllegalArgumentException."<init>":(Ljava/lang/String;)V
      34: athrow
      35: iload_0
      36: ireturn

  public static long verifyPositive(long, java.lang.String);
    Code:
       0: lload_0
       1: lconst_0
       2: lcmp
       3: ifgt          37
       6: new           #6                  // class java/lang/IllegalArgumentException
       9: dup
      10: new           #7                  // class java/lang/StringBuilder
      13: dup
      14: invokespecial #8                  // Method java/lang/StringBuilder."<init>":()V
      17: aload_2
      18: invokevirtual #9                  // Method java/lang/StringBuilder.append:(Ljava/lang/String;)Ljava/lang/StringBuilder;
      21: ldc           #10                 // String  > 0 required but it was
      23: invokevirtual #9                  // Method java/lang/StringBuilder.append:(Ljava/lang/String;)Ljava/lang/StringBuilder;
      26: lload_0
      27: invokevirtual #14                 // Method java/lang/StringBuilder.append:(J)Ljava/lang/StringBuilder;
      30: invokevirtual #12                 // Method java/lang/StringBuilder.toString:()Ljava/lang/String;
      33: invokespecial #13                 // Method java/lang/IllegalArgumentException."<init>":(Ljava/lang/String;)V
      36: athrow
      37: lload_0
      38: lreturn

  static {};
    Code:
       0: new           #15                 // class io/reactivex/rxjava3/internal/functions/ObjectHelper$BiObjectPredicate
       3: dup
       4: invokespecial #16                 // Method io/reactivex/rxjava3/internal/functions/ObjectHelper$BiObjectPredicate."<init>":()V
       7: putstatic     #5                  // Field EQUALS:Lio/reactivex/rxjava3/functions/BiPredicate;
      10: return
}
